Workbook
Name LIST_YES_NO: 'Reference lists'!$C$5:$C$6
Name LIST_BU_REVIEW: 'Reference lists'!$C$7:$C$9
Name LIST_R03_RECORD_TYPE: 'Reference lists'!$C$10:$C$13
Name LIST_R06_QUALIFIER: 'Reference lists'!$C$14:$C$16
Name LIST_R06_ACTION: 'Reference lists'!$C$17:$C$18
Name LIST_R08_ACCOUNT_TYPE: 'Reference lists'!$C$19:$C$23
Name LIST_R08_NORMAL_BALANCE: 'Reference lists'!$C$24:$C$25
Name LIST_R08_LEGACY_CONTROL_TYPE: 'Reference lists'!$C$26:$C$33
Name LIST_R09_DEFAULT_MODE: 'Reference lists'!$C$34:$C$40
Name LIST_R11_KIND: 'Reference lists'!$C$41:$C$42
Name LIST_C01_CLIENT_TYPE: 'Reference lists'!$C$43:$C$44
Name LIST_C02_RECORD_TYPE: 'Reference lists'!$C$45:$C$46
Name LIST_C02_ADDRESS_TYPE: 'Reference lists'!$C$47:$C$50
Name LIST_C03_MODE: 'Reference lists'!$C$51:$C$52
Name LIST_P01_BUSINESS_TYPE: 'Reference lists'!$C$53:$C$54
Name LIST_P01_PAYMENT_ARRANGEMENT: 'Reference lists'!$C$55:$C$56
Name LIST_P03_RA_CHANNEL: 'Reference lists'!$C$57:$C$60
Name LIST_F01_INVOICE_KIND: 'Reference lists'!$C$61:$C$64
Name LIST_F01C_COMPONENT: 'Reference lists'!$C$65:$C$75
Name LIST_F02_CHANNEL: 'Reference lists'!$C$76:$C$82
Name LIST_F02_DISPOSITION_STATUS: 'Reference lists'!$C$83:$C$85
Name LIST_F03_RECORD_TYPE: 'Reference lists'!$C$86:$C$89
Name LIST_F04_RECORD_TYPE: 'Reference lists'!$C$90:$C$92
Name LIST_F06_RECORD_TYPE: 'Reference lists'!$C$93:$C$95
Name LIST_G01_TB_VERSION: 'Reference lists'!$C$96:$C$100
Name LIST_G03_TRUEUP_NO: 'Reference lists'!$C$101:$C$104
Name LIST_G03_ADJUSTMENT_KIND: 'Reference lists'!$C$105:$C$106
Name LIST_G03D_TRUEUP_NO: 'Reference lists'!$C$107:$C$110
Name LIST_G03D_ITEM_KIND: 'Reference lists'!$C$111:$C$112
Name LIST_G03D_COMPONENT: 'Reference lists'!$C$113:$C$126
Name LIST_G03D_MOVEMENT: 'Reference lists'!$C$127:$C$128
Name LIST_H01_RECORD_TYPE: 'Reference lists'!$C$129:$C$139
Name LIST_STATUS: 'Reference lists'!$C$140:$C$143

Sheet Cover
B6: MIGRATION WORKBOOK
B7: Migration Workbook BRD-13 Data Migration
B8: BRD-13 Data Migration – objects and decisions, load templates, code maps, validation rules, data owners, cut-over plan, reconciliation sign-off and the screens, for BU review
B9: BIBS – BDOI Broker System
B11: Client | C11: BDO Insurance and Reinsurance Brokers, Inc.
B12: BRD | C12: BRD-13
B13: Version | C13: 2.1
B14: Date | C14: 8 October 2026
B15: Classification | C15: Confidential
B16: Prepared by | C16: iorta TechNXT
B18: Sheets
B19: Sheet | C19: Content | D19: Rows
B20: README | C20: What each column of each sheet means, with the allowed values
B21: How to review | C21: How the business unit reviews this workbook | D21: 7
B22: Object catalogue | C22: One row per legacy data object with the proposed decision and the four criteria of the BRD (BRID_MIG 1.1) | D22: 32
B23: Data owners | C23: Business owner and data steward of every object; BDOI names the people (DMQ01) | D23: 30
B24: Extract planning | C24: What BDOI extracts per object, how much, how far back and by when | D24: 26
B25: Milestones | C25: Milestones used in the Due and Needed-by columns | D25: 7
B26: File rules | C26: Rules of every extract and control file: the delivery rules of the console workbook, then the rules of the migration | D26: 11
B27: Load templates | C27: Who provides what, the steps and the templates in the order they are filled in | D27: 29
B28: R01 Lists of values and MIS val | C28: R01 Lists of values and MIS values: One row per record of Lists of values and MIS values as extracted from QPS, EBIX. Key list_type, code. Sent as the file R01_template.csv (CSV, header row as below) with its control file (row count, count of … | D28: 1
B29: R02 Branches and invoicing bran | C29: R02 Branches and invoicing branches: One row per record of Branches and invoicing branches as extracted from EBIX. Key branch_code. Sent as the file R02_template.csv (CSV, header row as below) with its control file (row count, count of distinct … | D29: 1
B30: R03 Sales organisation (units a | C30: R03 Sales organisation (units and account officers): One row per record of Sales organisation (regions, departments, teams, unit heads, account officers) as extracted from QPS, EBIX. Key record_type, unit_code, ao_user_id. Sent as the file … | D30: 1
B31: R04 Insurers | C31: R04 Insurers: One row per record of Insurers and insurer branches as extracted from QPS, EBIX. Key insurer_code. Sent as the file R04_template.csv (CSV, header row as below) with its control file (row count, count of distinct keys). | D31: 1
B32: R04B Insurer branches | C32: R04B Insurer branches: One row per record of Insurers and insurer branches as extracted from QPS, EBIX. Key insurer_code, branch_code. Sent as the file R04B_template.csv (CSV, header row as below) with its control file (row count, count of distinct … | D32: 1
... B89: Sign-off certificate | C89: By signing, the signatories confirm the BRD-13 Data Migration – Business Sign-off Pack v2.1: its content, screens and navigation are frozen; the screenshots use fictitious seed data; later changes go through the Change Management Register | D89: 17
B91: Legend
B92: Accept | C92: The row is correct as specified
B93: Change requested | C93: The row must change: describe the change in BU comment
B94: Comment | C94: A remark that does not change the row
B96: Issued on 08-Oct-2026 with the Data Migration Handbook v2.1, re-based on the Data Migration BRD V0.03. The load template sheets are the layouts of the Migration Console column for column, each with its guide above the header row; the sheet Load templates lists them in load order. The console exports the same templates (Layouts and Rules).
B97: Fill in the BU review columns (on a load template sheet, the BU review rows above each column) and, on the Proposed rules sheet, the BDOI decision. After sign-off the objects, decisions, layouts, screens and rules are frozen; later changes go through the Change Management Register.
B99: Prepared by iorta TechNXT for BDOI. Confidential – BDOI.

Sheet README
A1: README – columns of each sheet
A2: Migration Workbook BRD-13 Data Migration, version 2.1. Drop-down columns accept only the listed values.
A4: Sheet | B4: Column | C4: Meaning | D4: Allowed values
A5: How to review | B5: Step | C5: Step number
A6: How to review | B6: How to review | C6: Instruction
A7: Object catalogue | B7: Object | C7: Data object code
A8: Object catalogue | B8: Data object | C8: What the object holds
A9: Object catalogue | B9: Category | C9: Reference, Client, Policy, Open item, GL, History
A10: Object catalogue | B10: Decision (proposed) | C10: Migrate, Carry forward, Conditional, Archive or Excluded; the business owner confirms at gate G1 | D10: Migrate, Carry forward, Conditional, Archive, Excluded
A11: Object catalogue | B11: Rationale | C11: Why this decision
A12: Object catalogue | B12: Day-1 need | C12: Needed in BIBS on the first business day
A13: Object catalogue | B13: Compliance need | C13: Must be kept for compliance or audit
A14: Object catalogue | B14: Archive option | C14: Read-only legacy or the BIBS archive is enough
A15: Object catalogue | B15: Data trust | C15: High, Medium or Low, before cleansing
A16: Object catalogue | B16: Condition | C16: Condition of a conditional object
A17: Object catalogue | B17: Source system | C17: Legacy system(s) that hold the object
A18: Object catalogue | B18: Templates | C18: Load templates of the object (sheets of this workbook)
A19: Object catalogue | B19: Where it lands in BIBS | C19: The BIBS records the object becomes
A20: Object catalogue | B20: Load order | C20: Lower loads first
A21: Object catalogue | B21: Loads after | C21: Objects that must be accepted first
A22: Object catalogue | B22: BRD | C22: BRD requirement
A23: Object catalogue | B23: Open decisions | C23: Decisions that affect the object
A24: Object catalogue | B24: BU review | C24: Business unit decision on the row | D24: Accept, Change requested, Comment
A25: Object catalogue | B25: BU comment | C25: What should change, or the comment
A26: Object catalogue | B26: Reviewer | C26: Name of the BU reviewer
A27: Object catalogue | B27: Review date | C27: Date of the review (dd-mmm-yyyy)
A28: Data owners | B28: Object | C28: Data object code
A29: Data owners | B29: Data object | C29: What the object holds
A30: Data owners | B30: Business owner (proposed) | C30: Signs the decision (G1), the code maps (G2) and the acceptance (G6)
A31: Data owners | B31: Data steward (proposed) | C31: Prepares the code maps, resolves data-quality issues, fixes records at source
A32: Data owners | B32: Named business owner | C32: Name given by BDOI
A33: Data owners | B33: Named data steward | C33: Name given by BDOI
A34: Data owners | B34: BU review | C34: Business unit decision on the row | D34: Accept, Change requested, Comment
A35: Data owners | B35: BU comment | C35: What should change, or the comment
A36: Data owners | B36: Reviewer | C36: Name of the BU reviewer
A37: Data owners | B37: Review date | C37: Date of the review (dd-mmm-yyyy)
A38: Extract planning | B38: Object | C38: Data object code
A39: Extract planning | B39: Data object | C39: What the object holds
A40: Extract planning | B40: Volume (BDOI to fill) | C40: Row count per source system at the last extract
A41: Extract planning | B41: Planning bound | C41: Known bound from the BRDs
A42: Extract planning | B42: History depth | C42: Which records and how far back
A43: Extract planning | B43: Delta frequency | C43: Extracts after the first full one
A44: Extract planning | B44: Format | C44: CSV or XLSX, with a control file
A45: Extract planning | B45: Control totals | C45: Measures of the control file
A46: Extract planning | B46: Due | C46: Milestone of the first full extract and of the final one
A47: Extract planning | B47: BU review | C47: Business unit decision on the row | D47: Accept, Change requested, Comment
A48: Extract planning | B48: BU comment | C48: What should change, or the comment
A49: Extract planning | B49: Reviewer | C49: Name of the BU reviewer
A50: Extract planning | B50: Review date | C50: Date of the review (dd-mmm-yyyy)
A51: Milestones | B51: Milestone | C51: Milestone ID
A52: Milestones | B52: What is due | C52: Content of the milestone
A53: Milestones | B53: When | C53: Date
A54: File rules | B54: Topic | C54: Topic of the rule
A55: File rules | B55: Rule | C55: What every extract file follows
A56: File rules | B56: BU review | C56: Business unit decision on the row | D56: Accept, Change requested, Comment
A57: File rules | B57: BU comment | C57: What should change, or the comment
A58: File rules | B58: Reviewer | C58: Name of the BU reviewer
A59: File rules | B59: Review date | C59: Date of the review (dd-mmm-yyyy)
A60: Control file | B60: No. | C60: Column position
A61: Control file | B61: Column | C61: Column name of the control-file template
A62: Control file | B62: What it holds | C62: Content
A63: Control file | B63: Mandatory | C63: Y, N or C (conditional)
A64: Control file | B64: Format | C64: How the value is written
A65: Control file | B65: Example | C65: A made-up example
A66: Control example | B66: object | C66: Object code of the data file
A67: Control example | B67: layout | C67: Layout (template) code
A68: Control example | B68: source_system | C68: Source system: EBIX, QPS, ISYS, CMS or EXCEL
... A79: Control totals | B79: Object | C79: Data object
A80: Control totals | B80: Measure | C80: Control measure | D80: ROW_COUNT, HASH_TOTAL, AMOUNT_TOTAL, SHA256
A81: Control totals | B81: Column | C81: Column the measure applies to
A82: Control totals | B82: Currency | C82: Per currency or not
A83: Control totals | B83: How it is computed | C83: Computation
A84: Control totals | B84: Value from BDOI | C84: From the control file
A85: Control totals | B85: Value in BIBS | C85: Received, staged or loaded value (Reconciliation Summary)
A86: Control totals | B86: Difference | C86: BDOI value minus BIBS value
A87: Control totals | B87: Status | C87: Matched, Break or Explained | D87: MATCHED, BREAK, EXPLAINED
A88: Code maps | B88: Code map | C88: Code map set
A89: Code maps | B89: What is mapped | C89: Legacy codes mapped
A90: Code maps | B90: BIBS values | C90: The BIBS values the codes map to
A91: Code maps | B91: Used by layouts | C91: Layouts whose columns use the set
A92: Code maps | B92: Approves (G2) | C92: Business owner who approves each version
A93: Code maps | B93: Prepares | C93: Data steward who prepares the entries
A94: Code maps | B94: First approved version due | C94: Milestone
A95: Code maps | B95: BU review | C95: Business unit decision on the row | D95: Accept, Change requested, Comment
A96: Code maps | B96: BU comment | C96: What should change, or the comment
A97: Code maps | B97: Reviewer | C97: Name of the BU reviewer
A98: Code maps | B98: Review date | C98: Date of the review (dd-mmm-yyyy)
A99: Code map template | B99: Code map | C99: Code map set; the console exports one sheet per set, named after it
A100: Code map template | B100: source_system | C100: Legacy system of the code | D100: EBIX, QPS, ISYS, CMS, EXCEL
A101: Code map template | B101: legacy_code | C101: Code as stored in legacy
A102: Code map template | B102: legacy_description | C102: Description in legacy
A103: Code map template | B103: qualifier | C103: Attribute that splits one legacy code into several BIBS values (package code map: RISK_CODE, INSURER or SI_BAND); empty otherwise
A104: Code map template | B104: qualifier_value | C104: Value of the qualifier (a code, or a from-to amount band)
A105: Code map template | B105: action | C105: MAP to a BIBS value, DEFAULT to the default of the set, REJECT the rows, CREATE a new BIBS value | D105: MAP, DEFAULT, REJECT, CREATE
A106: Code map template | B106: target_code | C106: BIBS value; mandatory for MAP and CREATE
A107: Code map template | B107: remarks | C107: Reason for DEFAULT, REJECT or CREATE; condition of a conditional entry
A108: Code map template | B108: Rows using it | C108: From the profiling of the extracts (not part of the file)
A109: Validation rules | B109: Rule | C109: Rule ID shown with each issue
A110: Validation rules | B110: Layouts | C110: Layouts checked
A111: Validation rules | B111: Columns | C111: Columns checked
...

Sheet How to review
A1: How to review
A2: How the business unit reviews this workbook
A4: Step | B4: How to review
A5: 1 | B5: Read the Handbook part of your role with the screenshots, or walk through the Migration Console on the SIT environment during the sessions of the Start Here guide.
A6: 2 | B6: On the sheets of your objects (Object catalogue, Data owners, Extract planning, Code maps, Validation rules, Reconciliation sign-off) and on the screen sheets, set BU review to Accept, Change requested or Comment for each row you review, and write the change in BU comment. On a load template sheet the BU review and BU comment rows sit above each column.
A7: 3 | B7: On the Proposed rules sheet, record the BDOI decision (Agree, Agree with change, Disagree, Need more information), the change asked for, who decided and the date.
A8: 4 | B8: Put your name in Reviewer and the date in Review date. Leave the other columns unchanged.
A9: 5 | B9: The sheet Load templates lists the load templates in load order with a link to each. A load template sheet is the layout of the Migration Console column for column, with the guide of each column (Mandatory, Format, Allowed values, What to enter, the check when loaded) directly above the header row; the console exports the same templates (Layouts and Rules, Load Templates Workbook).
A10: 6 | B10: Return the workbook to the iorta TechNXT project team by the date of the Start Here guide. Every Change requested row is answered in the Comments log before sign-off.
A11: 7 | B11: Questions and change requests go to the Comments log, with the load template and the column when they concern one; the project team answers each one there. On the Sign-off certificate sheet, each signatory records the decision and the date. The screenshots use fictitious seed data.

Sheet Object catalogue
A1: Object catalogue
A2: One row per legacy data object with the proposed decision and the four criteria of the BRD (BRID_MIG 1.1)
A4: Object | B4: Data object | C4: Category | D4: Decision (proposed) | E4: Rationale | F4: Day-1 need | G4: Compliance need | H4: Archive option | I4: Data trust | J4: Condition | K4: Source system | L4: Templates | M4: Where it lands in BIBS | N4: Load order | O4: Loads after | P4: BRD | Q4: Open decisions | R4: BU review | S4: BU comment | T4: Reviewer | U4: Review date
A5: R01 | B5: Lists of values and MIS values | C5: Reference | D5: Migrate | E5: Every coded field of clients, policies and open items needs its BIBS value on Day 1 (BRID_MIG 3.1). Legacy values are mapped to BIBS values; missing values are created through the LOV master with maker-checker. | F5: Yes | G5: No | H5: No | I5: Medium | K5: QPS, EBIX | L5: R01 | M5: Lists of Values (maker-checker); MIS field catalogue | N5: 1 | O5: - | P5: BRID_MIG 3.1 | Q5: DMQ08
A6: R02 | B6: Branches and invoicing branches | C6: Reference | D6: Migrate | E6: Branch codes are mapped only; BIBS branches are configured by Comptrollership before the load. | F6: Yes | G6: No | H6: No | I6: Medium | K6: EBIX | L6: R02 | M6: Branches (check only, code map BRANCH) | N6: 1 | O6: - | P6: BRID_MIG 3.1 | Q6: DMQ08
A7: R03 | B7: Sales organisation (regions, departments, teams, unit heads, account officers) | C7: Reference | D7: Migrate | E7: Clients, policies and open items carry the AO and unit; MIS reporting and Collections assignment need them on Day 1. | F7: Yes | G7: No | H7: No | I7: Medium | K7: QPS, EBIX | L7: R03 | M7: Sales organisation: sales units and account officers | N7: 2 | O7: R02 | P7: BRID_MIG 3.1 | Q7: DMQ08
A8: R04 | B8: Insurers and insurer branches | C8: Reference | D8: Migrate | E8: Every open invoice, header and remittance position is owed to or by an insurer. | F8: Yes | G8: No | H8: No | I8: Medium | K8: QPS, EBIX | L8: R04, R04B | M8: Insurers and insurer branches (insurer and party records) | N8: 2 | O8: - | P8: BRID_MIG 3.1 | Q8: DMQ08
A9: R05 | B9: Product lines, cover types, products and risk codes | C9: Reference | D9: Migrate | E9: The risk code decides the premium components, taxes and commission of every open invoice and header. | F9: Yes | G9: No | H9: No | I9: Medium | K9: QPS, EBIX | L9: R05 | M9: Product catalogue: product lines, cover types and products | N9: 3 | O9: - | P9: BRID_MIG 3.1 | Q9: DMQ08
A10: R06 | B10: Package code map (legacy package and version to BIBS package version) | C10: Reference | D10: Migrate | E10: Packages are remapped at sanitation in Renewal, not at migration intake (DMQ36, answered 26-Sep-2026). The migration loads the package code map as reference data only; the Renewal package check uses it and sends unmapped packages to the Exception bucket, worked by the Renewal processing team. The BIBS packages themselves are maintained by TSU in Product Maintenance (BRD-3) and are not migrated. | F10: Yes | G10: No | H10: No | I10: Medium | K10: QPS (legacy packages); TSU (BIBS package versions) | L10: R06 | M10: Renewal package map, used by the package check of the Renewal sanitation | N10: 3 | O10: - | P10: BRID_MIG 3.1, 12.1 | Q10: DMQ08, DMQ36
A11: R07 | B11: Commission rates by insurer and product | C11: Reference | D11: Migrate | E11: Endorsements and renewals of legacy policies compute commission from the rate table. | F11: Yes | G11: No | H11: No | I11: Medium | K11: QPS, EBIX | L11: R07 | M11: Commission rates of the product catalogue | N11: 3 | O11: R04 | P11: BRID_MIG 3.1 | Q11: DMQ30
A12: R08 | B12: Chart of accounts mapping (legacy GL account to BIBS account) | C12: Reference | D12: Migrate | E12: The GL opening trial balance (G01) is loaded through this map; legacy control accounts are mapped to Migration Clearing. | F12: Yes | G12: No | H12: No | I12: Medium | K12: EBIX, ISYS GL | L12: R08 | M12: GL account code map to the BIBS chart of accounts (chart configured by Comptrollership) | N12: 3 | O12: - | P12: BRID_MIG 5.1-8.1; AQ01 | Q12: DMQ18
A13: R09 | B13: Payees | C13: Reference | D13: Conditional | E13: Payees are loaded through the payee migration upload of Disbursement; in scope if BDOI confirms (AQ11, DMQ30). | F13: Yes | G13: No | H13: No | I13: Medium | J13: Loaded through the payee registration of Disbursement if BDOI confirms (DMQ30). | K13: EBIX, Disbursement files | L13: R09 | M13: Payees (party and payee records, loaded by the payee migration) | N13: 4 | O13: - | P13: BRID_MIG 3.1; AQ11 | Q13: DMQ30, CLR-DM-06
A14: R10 | B14: Users and roles | C14: Reference | D14: Excluded | E14: Users are created through User Access requests and approvals (BRD-11); legacy user IDs are only mapped (user code map) so that the AO, handler and collector fields resolve. | F14: No | G14: No | H14: Yes | I14: Medium | K14: QPS, EBIX | L14: - | M14: None (code map USER only) | N14: - | O14: - | P14: BRD-11 | Q14: DMQ30
A15: R11 | B15: Receipt series in use (AR and OR, ATP and next number) | C15: Reference | D15: Carry forward | E15: Receipts issued in BIBS after go-live must continue the BIR-authorised series without gap or overlap. | F15: Yes | G15: No | H15: No | I15: Medium | K15: EBIX | L15: R11 | M15: Receipt series of Cashiering | N15: 4 | O15: R02 | P15: BRID_MIG 6.1 | Q15: DMQ14
A16: C01 | B16: Client master (individual and corporate) | C16: Client | D16: Migrate | E16: Marketing, Operations and Renewal must find and use clients on Day 1 without re-encoding (BRID_MIG 2.1); clients are deduplicated before load. Umbrella BRD p.43 asks for clients "2020 to present" and daily client batches (DCR-173). | F16: Yes | G16: No | H16: No | I16: Medium | K16: QPS, EBIX, CMS | L16: C01, C02 | M16: Client master, registered as migrated clients | N16: 5 | O16: R01,R02,R03 | P16: BRID_MIG 1.3, 2.1 | Q16: DMQ04, DMQ05, DMQ06, DCR-173, CLR-DM-10, CLR-DM-11
A17: C03 | B17: Client payout accounts (for refunds) | C17: Client | D17: Migrate | E17: Refunds of legacy UPP (BRID_MIG 5.4) need the client's payout account. | F17: Yes | G17: No | H17: No | I17: Medium | K17: EBIX | L17: C03 | M17: Client payout accounts | N17: 6 | O17: C01 | P17: BRID_MIG 5.4 | Q17: DMQ17
A18: C04 | B18: KYC documents and IDs | C18: Client | D18: Archive | E18: Documents stay retrievable for audit; BIBS keeps the KYC status and review date on the client (DMQ07 may change this to MIGRATE). | F18: No | G18: Yes | H18: Yes | I18: Medium | K18: QPS, file shares | L18: H02 | M18: BIBS archive (legacy document attachments) | N18: 16 | O18: - | P18: BRID_MIG 11.1 | Q18: DMQ07, DMQ24
A19: C05 | B19: Screening results and risk ratings | C19: Client | D19: Excluded | E19: One full screening run after the client load gives current results (BRD-10); legacy results are archived with the client history. | F19: No | G19: No | H19: Yes | I19: Medium | K19: Excel, Compliance | L19: - | M19: None (a full periodic screening run after C01) | N19: - | O19: - | P19: BRID_MIG 2.1 | Q19: DMQ06
A20: P01 | B20: In-force policy headers | C20: Policy | D20: Conditional | E20: Needed to locate active coverage, to endorse legacy invoices (BRID_MIG 9) and to renew in BIBS (BRID_MIG 12.1); the scope condition is decided by BDOI (DMQ09). Whatever it is, every policy expiring from T to 31-May-2028 and every renewal term booked in legacy that starts on or after T are in scope, because the go-live renewal extraction works only from the headers (DMQ37). The legacy package is kept as given; it is remapped at Renewal sanitation (DMQ36). | F20: Yes | G20: No | H20: No | I20: Medium | J20: Needed to locate active coverage, to endorse legacy invoices and to renew in BIBS; the scope condition is decided by BDOI. Whatever it is, every policy expiring from T to 31-May-2028 and every renewal term booked in legacy that starts on or after T are in scope, because the go-live renewal extraction works only from the headers. The legacy package is kept as given; it is remapped at Renewal sanitation. | K20: QPS, EBIX | L20: P01, P01S | M20: Accounts, imported as legacy policy headers | N20: 7 | O20: C01,R04,R05 | P20: BRID_MIG 1.3, 4.1 | Q20: DMQ09, DMQ22, DMQ36, DMQ37
A21: P02 | B21: Expired policies and policy history | C21: Policy | D21: Archive | E21: History is not converted (BRD p.3); kept for inquiry. | F21: No | G21: Yes | H21: Yes | I21: Medium | K21: QPS, EBIX | L21: H01 | M21: BIBS archive, record type POLICY | N21: 16 | O21: - | P21: BRID_MIG 11.1 | Q21: DMQ24
A22: P03 | B22: Renewal advices already sent before go-live (RA-sent file) | C22: Policy | D22: Migrate | E22: The January-May 2028 expiries are processed in BIBS after go-live from a go-live extraction of the migrated headers (DMQ37, answered 26-Sep-2026); no renewal candidate is carried. The RAs already sent by hand before go-live, kept in the Excel trackers of the Renewal processing team (DMQ38), are loaded as a small reference file so that BIBS does not send them again. | F22: Yes | G22: No | H22: No | I22: Medium | K22: Excel RA trackers of the Renewal processing team | L22: P03 | M22: Renewal Advices already sent, given to Renewal with the policy header in the go-live extraction | N22: 13 | O22: P01 | P22: BRID_MIG 12.1, 12.2 | Q22: DMQ26, DMQ37, DMQ38, CLR-DM-07
A23: P04 | B23: Submitted-policy masterlists | C23: Policy | D23: Conditional | E23: Loaded through the masterlist upload of Submitted Policies if BDOI confirms (SP SQ16, DMQ30); the layout is issued with that module. | F23: Yes | G23: No | H23: No | I23: Medium | J23: Loaded through the policy registration of Submitted Policies if BDOI confirms (DMQ30); the layout is issued with the Submitted Policies set. | K23: Excel | L23: - | M23: Submitted Policies masterlist (migration upload) | N23: 14 | O23: - | P23: BRID_MIG 1.3; BRIDSP-33 | Q23: DMQ30, CLR-DM-05
A24: P05 | B24: Employee Benefits programmes | C24: Policy | D24: Conditional | E24: Loaded through the programme upload of Employee Benefits if BDOI confirms (DMQ30); the layout is issued with that module. | F24: Yes | G24: No | H24: No | I24: Medium | J24: Loaded through the programme set-up of Employee Benefits if BDOI confirms (DMQ30); the layout is issued with the Employee Benefits set. | K24: EBIX | L24: - | M24: Employee Benefits programmes (programme load) | N24: 14 | O24: - | P24: BRD-8 | Q24: DMQ30
A25: F01 | B25: Open legacy invoices (premium receivable, paid not remitted, commission receivable, PR2307), with components and insurer shares | C25: Open item | D25: Carry forward | E25: Receivables and payables open at cutover must be collected, remitted, reversed and endorsed in BIBS (BRID_MIG 5.1-10.1). | F25: Yes | G25: No | H25: No | I25: Medium | K25: EBIX, QPS | L25: F01, F01S, F01C | M25: Operations invoice ledger (invoices, insurer shares, components) with an opening accounting entry on the legacy sub-ledgers | N25: 8 | O25: C01,R04,R05,P01 | P25: BRID_MIG 5.2, 6.1-6.4, 7.1, 7.2, 8.1, 9.1-9.3, 10.1, 13.1 | Q25: DMQ10, DMQ11, DMQ12, DMQ13, DMQ35, CLR-DM-14, CLR-DM-18
A26: F02 | B26: Unapplied premium payments (UPP) with disposition in progress | C26: Open item | D26: Carry forward | E26: Unapplied cash must not be lost after cutover (BRID_MIG 5.1); it is applied, refunded or reclassified in BIBS. | F26: Yes | G26: No | H26: No | I26: Medium | K26: EBIX, CMS | L26: F02 | M26: Cashiering unapplied payments, as migrated items, with an opening accounting entry | N26: 9 | O26: C01 | P26: BRID_MIG 5.1-5.5, 6.3, 6.4, 13.1 | Q26: DMQ14, DMQ15, DMQ16
A27: F03 | B27: Open collection state (dispositions, promises to pay, installment plans, collector assignments) | C27: Open item | D27: Carry forward | E27: Collectors continue their follow-up without re-keying (CQ07); only the open state is carried, history is archived (DMQ34). | F27: Yes | G27: No | H27: No | I27: Medium | K27: CMS | L27: F03 | M27: Legacy follow-up of the Collections worklist items | N27: 10 | O27: F01 | P27: CQ07 | Q27: DMQ34
A28: F04 | B28: Remittance in flight (batches not yet paid, holds, special remittances) | C28: Open item | D28: Conditional | E28: Proposal - complete legacy batches before the freeze; carry only holds and special remittances that cannot complete (DMQ21). | F28: Yes | G28: No | H28: No | I28: Medium | J28: Proposal - complete legacy batches before the freeze; carry only holds and special remittances that cannot complete. | K28: EBIX | L28: F04 | M28: Remittance holds and special remittances | N28: 11 | O28: F01 | P28: BRID_MIG 8.1 | Q28: DMQ21
A29: F05 | B29: DP billing in process and DP commission receivable | C29: Open item | D29: Carry forward | E29: Carried inside F01 (dp_flag and the COMMISSION components of direct-payment invoices); no separate file. | F29: Yes | G29: No | H29: No | I29: Medium | K29: EBIX, Operations files | L29: - | M29: Part of F01; Commission DP list | N29: 8 | O29: - | P29: BRID_MIG 7.1 | Q29: DMQ19, CLR-DM-15
A30: F06 | B30: PDCs in the warehouse, check pick-ups and refunds in process | C30: Open item | D30: Conditional | E30: Proposal - carry PDCs in the warehouse; complete pick-ups and refunds in legacy before the freeze where possible (DMQ33). | F30: Yes | G30: No | H30: No | I30: Medium | J30: Proposal - carry PDCs in the warehouse; complete pick-ups and refunds in legacy before the freeze where possible. | K30: EBIX | L30: F06 | M30: Cashiering PDC warehouse and check pick-up | N30: 11 | O30: C01 | P30: BRID_MIG 5.1 | Q30: DMQ33
A31: F07 | B31: Open claims | C31: Open item | D31: Conditional | E31: Loaded through the Claims migration if BDOI decides (CLQ14, DMQ30); closed claims are archived. | F31: Yes | G31: No | H31: No | I31: Medium | J31: Loaded through the claim registration of Claims if BDOI decides (DMQ30); closed claims are archived. | K31: EBIX, ISYS | L31: - | M31: Claims, through the claims migration | N31: 14 | O31: - | P31: BRID_MIG 1.3, 14.1; CLQ14 | Q31: DMQ30, CLR-DM-08
A32: G01 | B32: GL trial balance per account, branch and currency (provisional opening; legacy TB at each true-up) | C32: GL | D32: Migrate | E32: At the year-end go-live (DMQ39, option A recommended) the BIBS GL opens from the preliminary December 2027 TB - balance-sheet accounts only, the FY2027 net result to retained earnings, legacy control-account lines to Migration Clearing, which the F01 and F02 opening entries clear to 0.00. The opening is provisional; at each true-up the legacy TB after the adjustments is sent again as reconciliation input (G03). | F32: Yes | G32: No | H32: No | I32: Medium | K32: EBIX GL, ISYS GL | L32: G01 | M32: General ledger journals of type OPENING (value date 1-Jan-2028); at a true-up, reconciliation input only | N32: 12 | O32: R08,F01,F02 | P32: BRID_MIG 1.2, 5.1-8.1, 13.1 | Q32: DMQ18, DMQ25, DMQ35, DMQ39
A33: G02 | B33: GL history (journals and balances before cutover) | C33: History | D33: Archive | E33: Kept for audit; BIBS starts from the opening trial balance. | F33: No | G33: Yes | H33: Yes | I33: Medium | K33: EBIX GL, ISYS GL | L33: H01 | M33: BIBS archive, record type GL journal | N33: 16 | O33: - | P33: BRID_MIG 11.1 | Q33: DMQ24
A34: G03 | B34: FY2027 opening-balance true-ups (legacy adjustment journals after the freeze and their open-item detail) | C34: GL | D34: Migrate | E34: The legacy GL stays open after the freeze only for the FY2027 closing and audit adjustments of Comptrollership (DMQ39). Each adjustment reaches BIBS as a controlled opening-balance adjustment journal in the opening period - after the legacy year-end close and after the audited FS - with approvals, cut-off controls and a reconciliation to the legacy TB. | F34: Yes | G34: No | H34: No | I34: Medium | K34: EBIX GL, ISYS GL; FY2027 adjustment register of Comptrollership | L34: G03, G03D | M34: General ledger journals of type OPENING (reference MIG-TU-<n>); opening adjustments of the legacy open items and unapplied payments | N34: 17 | O34: G01 | P34: BRID_MIG 1.2, 5.1-8.1, 13.1 | Q34: DMQ18, DMQ39
A35: H01 | B35: Closed transactions (paid and remitted invoices, receipts, remittances, endorsements, claims, renewal advices, letters) | C35: History | D35: Archive | E35: History stays in read-only legacy or the BIBS archive with logged access (BRID_MIG 11.1). | F35: No | G35: Yes | H35: Yes | I35: Medium | K35: EBIX, QPS, ISYS | L35: H01 | M35: BIBS archive (Legacy Inquiry) | N35: 16 | O35: - | P35: BRID_MIG 11.1 | Q35: DMQ24, DMQ27
A36: H02 | B36: Legacy documents (policies, SOAs, ORs, certificates, letters) | C36: History | D36: Archive | E36: Documents are kept with their archive record and a checksum. | F36: No | G36: Yes | H36: Yes | I36: Medium | K36: File shares, EBIX | L36: H02 | M36: Legacy documents attached to the archive records | N36: 16 | O36: - | P36: BRID_MIG 11.1 | Q36: DMQ24

Sheet Data owners
A1: Data owners
A2: Business owner and data steward of every object; BDOI names the people (DMQ01)
A4: Object | B4: Data object | C4: Business owner (proposed) | D4: Data steward (proposed) | E4: Named business owner | F4: Named data steward | G4: BU review | H4: BU comment | I4: Reviewer | J4: Review date
A5: R01 | B5: Lists of values and MIS values | C5: Product Owner, Marketing Business System (MBS) | D5: MBS data steward (to name)
A6: R02 | B6: Branches and invoicing branches | C6: Head, Comptrollership | D6: Comptrollership data steward (to name)
A7: R03 | B7: Sales organisation (regions, departments, teams, unit heads, account officers) | C7: Heads, Retail and Corporate Marketing | D7: Marketing data steward (to name)
A8: R04 | B8: Insurers and insurer branches | C8: Head, Operations | D8: Operations data steward (to name)
A9: R05 | B9: Product lines, cover types, products and risk codes | C9: Product Owner, MBS | D9: MBS data steward (to name)
A10: R06 | B10: Package code map (legacy package and version to BIBS package version) | C10: Product Owner, MBS (approves); TSU (prepares) | D10: TSU (to name)
A11: R07 | B11: Commission rates by insurer and product | C11: Head, Operations | D11: Operations data steward (to name)
A12: R08 | B12: Chart of accounts mapping (legacy GL account to BIBS account) | C12: Head, Comptrollership; Product Owner FRBS and ACSL | D12: Comptrollership data steward (to name)
A13: R09 | B13: Payees | C13: Product Owner, Comptrollership - Disbursement | D13: Disbursement data steward (to name)
A14: R11 | B14: Receipt series in use (AR and OR, ATP and next number) | C14: Operations - Financial Transactions | D14: Cashiering data steward (to name)
A15: C01 | B15: Client master (individual and corporate) | C15: Product Owner, MBS; Heads, Retail and Corporate Marketing | D15: Marketing data steward (to name)
A16: C03 | B16: Client payout accounts (for refunds) | C16: Product Owner, Comptrollership - Disbursement | D16: Disbursement data steward (to name)
... A34: H02 | B34: Legacy documents (policies, SOAs, ORs, certificates, letters) | C34: Audit / Compliance | D34: Compliance data steward (to name)

Sheet Extract planning
A1: Extract planning
A2: What BDOI extracts per object, how much, how far back and by when
A4: Object | B4: Data object | C4: Volume (BDOI to fill) | D4: Planning bound | E4: History depth | F4: Delta frequency | G4: Format | H4: Control totals | I4: Due | J4: BU review | K4: BU comment | L4: Reviewer | M4: Review date
A5: R01 | B5: Lists of values and MIS values | D5: A few thousand values | E5: Current values and values used by any migrated record | F5: None after the map freeze (T-7 days); changes by change request and a new map version | G5: CSV | H5: Row count; count of distinct (list_type, code) | I5: M3 (29 Jan 2027)
A6: R02 | B6: Branches and invoicing branches | D6: Under 100 | E6: Current | F6: None | G6: CSV | H6: Row count | I6: M3 (29 Jan 2027)
A7: R03 | B7: Sales organisation (regions, departments, teams, unit heads, account officers) | D7: About 600 AOs (485 Marketing users, BRD-3) | E7: Current, plus inactive AOs referenced by open items | F7: Weekly until the freeze | G7: CSV | H7: Row count per record type | I7: M3 (29 Jan 2027)
A8: R04 | B8: Insurers and insurer branches | D8: Under 100 insurers | E8: Active insurers, and inactive insurers with open items | F8: None | G8: CSV | H8: Row count per file | I8: M3 (29 Jan 2027)
A9: R05 | B9: Product lines, cover types, products and risk codes | D9: A few hundred codes | E9: Current, plus codes used by in-force policies and open items | F9: None | G9: CSV | H9: Row count | I9: M3 (29 Jan 2027)
A10: R06 | B10: Package code map (legacy package and version to BIBS package version) | D10: Under 200 legacy packages | E10: Legacy packages of in-force policies | F10: New map versions until the map freeze (T-7 days) | G10: XLSX or CSV | H10: Row count; count of distinct (legacy_package_code, legacy_package_version) | I10: M5 (18 Jun 2027); final at T-7
A11: R07 | B11: Commission rates by insurer and product | D11: Insurers x products | E11: Rates effective at cutover and later | F11: None | G11: CSV | H11: Row count | I11: M3 (29 Jan 2027)
A12: R08 | B12: Chart of accounts mapping (legacy GL account to BIBS account) | D12: A few thousand accounts | E12: Current chart | F12: None | G12: XLSX or CSV | H12: Row count | I12: M3 (29 Jan 2027)
A13: R09 | B13: Payees | D13: To supply | E13: Active payees | F13: None | G13: CSV | H13: Row count | I13: M3 (29 Jan 2027)
A14: R11 | B14: Receipt series in use (AR and OR, ATP and next number) | D14: One per branch and kind | E14: Series in use at the freeze | F14: Final values at the freeze (T-3) | G14: CSV | H14: Row count | I14: M3 (29 Jan 2027); final at T-3
A15: C01 | B15: Client master (individual and corporate) | D15: Loaders sized for 1,000,000 rows | E15: Clients from 2020 to present (umbrella p.43); filter per DMQ05 | F15: Daily new and changed clients from T-14 days until the freeze | G15: CSV | H15: Row count; count of distinct legacy_client_no | I15: M3 (29 Jan 2027); deltas daily from T-14 days
A16: C03 | B16: Client payout accounts (for refunds) | D16: To supply | E16: Active accounts | F16: None | G16: CSV | H16: Row count | I16: M3 (29 Jan 2027)
... A30: H02 | B30: Legacy documents (policies, SOAs, ORs, certificates, letters) | D30: To supply | E30: Per retention | F30: None | G30: CSV index plus files | H30: Row count; SHA-256 per file | I30: Before decommissioning

Sheet Milestones
A1: Milestones
A2: Milestones used in the Due and Needed-by columns
A4: Milestone | B4: What is due | C4: When
A5: M0 | B5: Business sign-off set issued to BDOI (release set v2.0, with the BDOI answers to DMQ36-DMQ39) | C5: 5 Oct 2026
A6: M1 | B6: Scope-shaping decisions (answers that change the migration functions) | C6: 16 Oct 2026
A7: M2 | B7: Owners, stewards, keys and remaining business rules; object decisions signed (gate G1); layouts frozen, version 1 (G2 part 1) - end of requirements and mapping | C7: 30 Oct 2026
A8: M3 | B8: First full extracts in the templates, with control files and volumes (profiling, performance sizing) | C8: 29 Jan 2027
A9: M4 | B9: Extracts for Trial migration 1 (SIT migration starts); reference data and clients first | C9: 9 Apr 2027
A10: M5 | B10: Code maps approved for Trial migration 2 (G2), including the package code map | C10: 18 Jun 2027
A11: M6 | B11: Cut-over date and window, fallback and decommissioning criteria agreed; Comptrollership confirms the year-end option A (DMQ39) | C11: 1 Oct 2027

Sheet File rules
A1: File rules
A2: Rules of every extract and control file: the delivery rules of the console workbook, then the rules of the migration
A4: Topic | B4: Rule | C4: BU review | D4: BU comment | E4: Reviewer | F4: Review date
A5: File name | B5: <LAYOUT>_<SOURCE>_<yyyyMMdd>_<nn>.xlsx or .csv, for example F01C_EBIX_20271231_01.xlsx: the layout code, the source system, the as-of date and the sequence of the day
A6: One file per | B6: Layout, source system and extract; an object with several layouts sends one file per layout with the same as-of date
A7: Excel | B7: The load template of the console, uploaded as it is: its guide rows and example row are skipped and the sheet of the layout is read; a workbook of several layouts is uploaded once per layout, named after that layout. A plain workbook has the header in row 1 of its first sheet, no merged cells, no formulas
A8: CSV | B8: For large extracts: UTF-8 without byte order mark, comma separator, double quotes around values that hold a comma, a quote or a line break, one header row with the column names exactly as in the template
A9: Values | B9: Dates as Excel dates or yyyy-MM-dd; timestamps yyyy-MM-dd HH:mm:ss (Philippine time); amounts with a dot decimal, 2 decimals, no thousands separator, minus sign for negatives; currency ISO 4217; codes exactly as stored in the legacy system; blank means no value
A10: Control file | B10: <data file name>.ctl.xlsx or .ctl.csv in the control layout: the row count, the hash total of the key column, the total of each amount column per currency and the SHA-256 of the data file, one row per measure
A11: Delivery | B11: Upload the data file and its control file together on the Extracts screen of the Migration Console; never by e-mail
A12: Checks | B12: A file whose checksum, header, row count, amount totals or hash total does not agree with its control file is rejected with the reason; nothing of it is loaded
A13: Personal data | B13: Production extracts are loaded only in production. Every other environment receives masked data: names, addresses, TIN, ID, account and phone numbers, e-mail addresses and birth dates are masked when the file is received. Staged rows and files are deleted within 5 days of the batch sign-off
A14: Layout changes | B14: A layout is frozen at gate G2. A file whose header does not match the layout in force is rejected. A change of layout is a new layout version agreed with the Data Migration Lead
A15: Load template workbook of P03 | B15: The Renewal processing team may send the RA-sent file in the load template workbook of layout P03 exported by the Migration Console (the template sheet with the guide rows Mandatory, Format, Allowed values and What to enter directly above the header row, and the Lists sheet with the allowed values); the CSV template is also accepted

Sheet Load templates
A3: Load templates – start here
A4: The extract layouts in force, in load order, each with its sheet
A6: Client | C6: BDO Insurance and Reinsurance Brokers, Inc.
A7: Release set | C7: BRD-13 Data Migration (Drop 0, Setup and Data Migration)
A8: Version and date | C8: Version 2.1, 8 October 2026
A9: Owner | C9: Program Manager, Business Project Services (Data Migration)
A10: Due | C10: Per object: the Due of the index (milestones on the sheet Milestones)
A12: How to fill in this workbook
A13: 1 | B13: The index below lists the load templates in load order: reference data first, then clients, policies, open items, the general ledger and the archive. Each template has a sheet of its own, named as in the workbook the Migration Console exports (Layouts and Rules); the extracts are sent as CSV files with their control file (sheets File rules and Control file).
A14: 2 | B14: On a template sheet, the header block says what one row holds, who provides it, when it is due and how it is loaded; above each column the guide gives Mandatory, Format (type and length), Allowed values or the code map, What to enter and the check applied when the file is loaded. The header row is the header row of the file; * marks a mandatory column.
A15: 3 | B15: Review each column: set BU review (Accept, Change requested or Comment) and write the change in BU comment, in the two rows above the guide; record your name and the date in Reviewed by and Review date.
A16: 4 | B16: The grey example row is made up. Test rows may be entered under it for the review: the drop-downs offer the allowed values (sheet Reference lists) and a mandatory cell left empty turns red.
A17: 5 | B17: Set the Status of each template in the index. Questions go to the Comments log with the template and the column.
A19: Load templates in load order
A20: Step | B20: Layout | C20: Object | D20: Content | E20: Provided by | F20: Due | G20: Decision | H20: Loads after | I20: Columns | J20: Mandatory | K20: Key | L20: File | M20: Rows entered | N20: Mandatory cells missing | O20: Status | P20: Open
A21: 1 | B21: R01 | C21: R01 | D21: Lists of values and MIS values | E21: MBS data steward (to name); approved by Product Owner, Marketing Business System (MBS); extracted by BDOI IT | F21: M3 (29 Jan 2027) | G21: Migrate | H21: - | I21: 8 | J21: 4 | K21: list_type, code | L21: R01_template.csv | M21: ='R01 Lists of values and MIS val'!$C$9 | N21: ='R01 Lists of values and MIS val'!$E$9 | O21: Not started | P21: Open →
A22: 2 | B22: R02 | C22: R02 | D22: Branches and invoicing branches | E22: Comptrollership data steward (to name); approved by Head, Comptrollership; extracted by BDOI IT | F22: M3 (29 Jan 2027) | G22: Migrate | H22: - | I22: 5 | J22: 4 | K22: branch_code | L22: R02_template.csv | M22: ='R02 Branches and invoicing bran'!$C$9 | N22: ='R02 Branches and invoicing bran'!$E$9 | O22: Not started | P22: Open →
A23: 3 | B23: R03 | C23: R03 | D23: Sales organisation (units and account officers) | E23: Marketing data steward (to name); approved by Heads, Retail and Corporate Marketing; extracted by BDOI IT | F23: M3 (29 Jan 2027) | G23: Migrate | H23: R02 | I23: 11 | J23: 3 | K23: record_type, unit_code, ao_user_id | L23: R03_template.csv | M23: ='R03 Sales organisation (units a'!$C$9 | N23: ='R03 Sales organisation (units a'!$E$9 | O23: Not started | P23: Open →
A24: 4 | B24: R04 | C24: R04 | D24: Insurers | E24: Operations data steward (to name); approved by Head, Operations; extracted by BDOI IT | F24: M3 (29 Jan 2027) | G24: Migrate | H24: - | I24: 10 | J24: 3 | K24: insurer_code | L24: R04_template.csv | M24: ='R04 Insurers'!$C$9 | N24: ='R04 Insurers'!$E$9 | O24: Not started | P24: Open →
A25: 5 | B25: R04B | C25: R04 | D25: Insurer branches | E25: Operations data steward (to name); approved by Head, Operations; extracted by BDOI IT | F25: M3 (29 Jan 2027) | G25: Migrate | H25: R04 | I25: 7 | J25: 4 | K25: insurer_code, branch_code | L25: R04B_template.csv | M25: ='R04B Insurer branches'!$C$9 | N25: ='R04B Insurer branches'!$E$9 | O25: Not started | P25: Open →
A26: 6 | B26: R05 | C26: R05 | D26: Product lines, cover types, products and risk codes | E26: MBS data steward (to name); approved by Product Owner, MBS; extracted by BDOI IT | F26: M3 (29 Jan 2027) | G26: Migrate | H26: - | I26: 9 | J26: 4 | K26: risk_code | L26: R05_template.csv | M26: ='R05 Product lines, cover types,'!$C$9 | N26: ='R05 Product lines, cover types,'!$E$9 | O26: Not started | P26: Open →
A27: 7 | B27: R06 | C27: R06 | D27: Package code map (legacy package to BIBS package version) | E27: TSU (to name); approved by Product Owner, MBS (approves); TSU (prepares); extracted by BDOI IT | F27: M5 (18 Jun 2027); final at T-7 | G27: Migrate | H27: - | I27: 8 | J27: 4 | K27: legacy_package_code, legacy_package_version, qualifier, qualifier_value | L27: R06_template.csv | M27: ='R06 Package code map (legacy pa'!$C$9 | N27: ='R06 Package code map (legacy pa'!$E$9 | O27: Not started | P27: Open →
A28: 8 | B28: R07 | C28: R07 | D28: Commission rates by insurer and product | E28: Operations data steward (to name); approved by Head, Operations; extracted by BDOI IT | F28: M3 (29 Jan 2027) | G28: Migrate | H28: R04, R04B | I28: 5 | J28: 4 | K28: insurer_code, risk_code, effective_from | L28: R07_template.csv | M28: ='R07 Commission rates by insurer'!$C$9 | N28: ='R07 Commission rates by insurer'!$E$9 | O28: Not started | P28: Open →
A29: 9 | B29: R08 | C29: R08 | D29: Chart of accounts mapping | E29: Comptrollership data steward (to name); approved by Head, Comptrollership; Product Owner FRBS and ACSL; extracted by BDOI IT | F29: M3 (29 Jan 2027) | G29: Migrate | H29: - | I29: 8 | J29: 4 | K29: legacy_account_code | L29: R08_template.csv | M29: ='R08 Chart of accounts mapping'!$C$9 | N29: ='R08 Chart of accounts mapping'!$E$9 | O29: Not started | P29: Open →
A30: 10 | B30: R09 | C30: R09 | D30: Payees | E30: Disbursement data steward (to name); approved by Product Owner, Comptrollership - Disbursement; extracted by BDOI IT | F30: M3 (29 Jan 2027) | G30: Conditional | H30: - | I30: 11 | J30: 6 | K30: payee_code | L30: R09_template.csv | M30: ='R09 Payees'!$C$9 | N30: ='R09 Payees'!$E$9 | O30: Not started | P30: Open →
A31: 11 | B31: R11 | C31: R11 | D31: Receipt series in use | E31: Cashiering data steward (to name); approved by Operations - Financial Transactions; extracted by BDOI IT | F31: M3 (29 Jan 2027); final at T-3 | G31: Carry forward | H31: R02 | I31: 8 | J31: 7 | K31: branch_code, kind, prefix | L31: R11_template.csv | M31: ='R11 Receipt series in use'!$C$9 | N31: ='R11 Receipt series in use'!$E$9 | O31: Not started | P31: Open →
A32: 12 | B32: C01 | C32: C01 | D32: Client master | E32: Marketing data steward (to name); approved by Product Owner, MBS; Heads, Retail and Corporate Marketing; extracted by BDOI IT | F32: M3 (29 Jan 2027); deltas daily from T-14 days | G32: Migrate | H32: R01, R02, R03 | I32: 36 | J32: 6 | K32: legacy_client_no | L32: C01_template.csv | M32: ='C01 Client master'!$C$9 | N32: ='C01 Client master'!$E$9 | O32: Not started | P32: Open →
A33: 13 | B33: C02 | C33: C01 | D33: Client addresses and contacts | E33: Marketing data steward (to name); approved by Product Owner, MBS; Heads, Retail and Corporate Marketing; extracted by BDOI IT | F33: M3 (29 Jan 2027); deltas daily from T-14 days | G33: Migrate | H33: C01, R01, R02, R03 | I33: 13 | J33: 4 | K33: legacy_client_no, record_type, seq_no | L33: C02_template.csv | M33: ='C02 Client addresses and contac'!$C$9 | N33: ='C02 Client addresses and contac'!$E$9 | O33: Not started | P33: Open →
A34: 14 | B34: C03 | C34: C03 | D34: Client payout accounts | E34: Disbursement data steward (to name); approved by Product Owner, Comptrollership - Disbursement; extracted by BDOI IT | F34: M3 (29 Jan 2027) | G34: Migrate | H34: C01, C02 | I34: 6 | J34: 4 | K34: legacy_client_no, account_no | L34: C03_template.csv | M34: ='C03 Client payout accounts'!$C$9 | N34: ='C03 Client payout accounts'!$E$9 | O34: Not started | P34: Open →
A35: 15 | B35: P01 | C35: P01 | D35: In-force policy headers | E35: Operations data steward (to name); approved by Head, Operations; extracted by BDOI IT | F35: M3 (29 Jan 2027); final at T-2 | G35: Conditional | H35: C01, C02, R04, R04B, R05 | I35: 31 | J35: 20 | K35: legacy_policy_ref | L35: P01_template.csv | M35: ='P01 In-force policy headers'!$C$9 | N35: ='P01 In-force policy headers'!$E$9 | O35: Not started | P35: Open →
A36: 16 | B36: P01S | C36: P01 | D36: Policy insurer shares | E36: Operations data steward (to name); approved by Head, Operations; extracted by BDOI IT | F36: M3 (29 Jan 2027); final at T-2 | G36: Conditional | H36: P01, C01, C02, R04, R04B, R05 | I36: 6 | J36: 5 | K36: legacy_policy_ref, share_seq | L36: P01S_template.csv | M36: ='P01S Policy insurer shares'!$C$9 | N36: ='P01S Policy insurer shares'!$E$9 | O36: Not started | P36: Open →
A37: 17 | B37: F01 | C37: F01 | D37: Open legacy invoices - header | E37: Operations data steward (to name); approved by Operations - Financial Transactions; Head, Comptrollership; extracted by BDOI IT | F37: M3 (29 Jan 2027); final at T-2 | G37: Carry forward | H37: C01, C02, R04, R04B, R05, P01, P01S | I37: 38 | J37: 24 | K37: legacy_invoice_no | L37: F01_template.csv | M37: ='F01 Open legacy invoices - head'!$C$9 | N37: ='F01 Open legacy invoices - head'!$E$9 | O37: Not started | P37: Open →
A38: 18 | B38: F01C | C38: F01 | D38: Open legacy invoices - components and positions | E38: Operations data steward (to name); approved by Operations - Financial Transactions; Head, Comptrollership; extracted by BDOI IT | F38: M3 (29 Jan 2027); final at T-2 | G38: Carry forward | H38: F01, C01, C02, R04, R04B, R05, P01, P01S | I38: 8 | J38: 8 | K38: legacy_invoice_no, component | L38: F01C_template.csv | M38: ='F01C Open legacy invoices - com'!$C$9 | N38: ='F01C Open legacy invoices - com'!$E$9 | O38: Not started | P38: Open →
A39: 19 | B39: F01S | C39: F01 | D39: Open legacy invoices - insurer shares | E39: Operations data steward (to name); approved by Operations - Financial Transactions; Head, Comptrollership; extracted by BDOI IT | F39: M3 (29 Jan 2027); final at T-2 | G39: Carry forward | H39: F01, C01, C02, R04, R04B, R05, P01, P01S | I39: 5 | J39: 5 | K39: legacy_invoice_no, share_seq | L39: F01S_template.csv | M39: ='F01S Open legacy invoices - ins'!$C$9 | N39: ='F01S Open legacy invoices - ins'!$E$9 | O39: Not started | P39: Open →
A40: 20 | B40: F02 | C40: F02 | D40: Unapplied premium payments (UPP) | E40: Cashiering data steward (to name); approved by Operations - Financial Transactions; extracted by BDOI IT | F40: M3 (29 Jan 2027); final at T-2 | G40: Carry forward | H40: C01, C02 | I40: 21 | J40: 11 | K40: legacy_upp_ref | L40: F02_template.csv | M40: ='F02 Unapplied premium payments'!$C$9 | N40: ='F02 Unapplied premium payments'!$E$9 | O40: Not started | P40: Open →
A41: 21 | B41: F03 | C41: F03 | D41: Open collection state | E41: Collections data steward (to name); approved by Head, Operations (Collections); extracted by BDOI IT | F41: M3 (29 Jan 2027); final at T-2 | G41: Carry forward | H41: F01, F01S, F01C | I41: 12 | J41: 3 | K41: legacy_invoice_no, record_type, seq_no | L41: F03_template.csv | M41: ='F03 Open collection state'!$C$9 | N41: ='F03 Open collection state'!$E$9 | O41: Not started | P41: Open →
A42: 22 | B42: F04 | C42: F04 | D42: Remittance in flight | E42: Remittance data steward (to name); approved by Operations - Remittance; extracted by BDOI IT | F42: M3 (29 Jan 2027); final at T-2 | G42: Conditional | H42: F01, F01S, F01C | I42: 10 | J42: 6 | K42: legacy_batch_no, legacy_invoice_no | L42: F04_template.csv | M42: ='F04 Remittance in flight'!$C$9 | N42: ='F04 Remittance in flight'!$E$9 | O42: Not started | P42: Open →
A43: 23 | B43: F06 | C43: F06 | D43: PDCs, check pick-ups and refunds in process | E43: Cashiering data steward (to name); approved by Operations - Cashiering; extracted by BDOI IT | F43: M3 (29 Jan 2027); final at T-2 | G43: Conditional | H43: C01, C02 | I43: 14 | J43: 6 | K43: record_type, reference | L43: F06_template.csv | M43: ='F06 PDCs, check pick-ups and re'!$C$9 | N43: ='F06 PDCs, check pick-ups and re'!$E$9 | O43: Not started | P43: Open →
A44: 24 | B44: G01 | C44: G01 | D44: GL opening trial balance | E44: Comptrollership data steward (to name); approved by Head, Comptrollership; extracted by BDOI IT | F44: M3 (29 Jan 2027); final at T-2; at each true-up | G44: Migrate | H44: R08, F01, F01S, F01C, F02 | I44: 11 | J44: 9 | K44: tb_version, branch_code, currency, legacy_account_code, cost_center | L44: G01_template.csv | M44: ='G01 GL opening trial balance'!$C$9 | N44: ='G01 GL opening trial balance'!$E$9 | O44: Not started | P44: Open →
A45: 25 | B45: P03 | C45: P03 | D45: Renewal advices already sent before go-live (RA-sent file) | E45: Renewal processing team - makers (corrections) and checkers (resubmission approval); approved by Head of the Renewal processing team; extracted by BDOI IT | F45: M4 (9 Apr 2027) (Trial migration 1); final at T-5 | G45: Migrate | H45: P01, P01S | I45: 13 | J45: 6 | K45: legacy_policy_ref | L45: P03_template.csv | M45: ='P03 Renewal advices already sen'!$C$9 | N45: ='P03 Renewal advices already sen'!$E$9 | O45: Not started | P45: Open →
A46: 26 | B46: H01 | C46: H01 | D46: Archive records (closed transactions and history) | E46: Compliance data steward (to name); approved by Audit / Compliance; legacy system owners; extracted by BDOI IT | F46: Before decommissioning | G46: Archive | H46: - | I46: 15 | J46: 3 | K46: record_type, legacy_key | L46: H01_template.csv | M46: ='H01 Archive records (closed tra'!$C$9 | N46: ='H01 Archive records (closed tra'!$E$9 | O46: Not started | P46: Open →
A47: 27 | B47: H02 | C47: H02 | D47: Archive documents index | E47: Compliance data steward (to name); approved by Audit / Compliance; extracted by BDOI IT | F47: Before decommissioning | G47: Archive | H47: - | I47: 8 | J47: 6 | K47: record_type, legacy_key, file_name | L47: H02_template.csv | M47: ='H02 Archive documents index'!$C$9 | N47: ='H02 Archive documents index'!$E$9 | O47: Not started | P47: Open →
A48: 28 | B48: G03 | C48: G03 | D48: FY2027 true-up - legacy adjustment journal lines after the freeze | E48: Comptrollership GL lead (prepares each true-up); approved by Head, Comptrollership; extracted by BDOI IT | F48: T+16 (true-up 1); T+92 (final) | G48: Migrate | H48: G01 | I48: 19 | J48: 17 | K48: legacy_journal_no, line_no | L48: G03_template.csv | M48: ='G03 FY2027 true-up - legacy adj'!$C$9 | N48: ='G03 FY2027 true-up - legacy adj'!$E$9 | O48: Not started | P48: Open →
A49: 29 | B49: G03D | C49: G03 | D49: FY2027 true-up - open-item detail of the lines on legacy control accounts | E49: Comptrollership GL lead (prepares each true-up); approved by Head, Comptrollership; extracted by BDOI IT | F49: T+16 (true-up 1); T+92 (final) | G49: Migrate | H49: G03, G01 | I49: 10 | J49: 10 | K49: legacy_journal_no, line_no, item_ref, component | L49: G03D_template.csv | M49: ='G03D FY2027 true-up - open-item'!$C$9 | N49: ='G03D FY2027 true-up - open-item'!$E$9 | O49: Not started | P49: Open →
A51: Prepared by iorta TechNXT for BDOI. Confidential – BDOI.

Sheet R01 Lists of values and MIS val
A1: R01 Lists of values and MIS values | I1: Step 1 of 29
A2: ← Back to Load templates | B2: Step 1 of 29. Fill in one row per record below the column headers; the guide above each column says what to enter. | I2: Ask a question →
A3: Purpose | B3: One row per record of Lists of values and MIS values as extracted from QPS, EBIX. Key list_type, code. Sent as the file R01_template.csv (CSV, header row as below) with its control file (row count, count of distinct keys).
A4: Provided by | B4: MBS data steward (to name); approved by Product Owner, Marketing Business System (MBS); extracted by BDOI IT
A5: Due | B5: M3 (29 Jan 2027)
A6: How it is loaded | B6: Data migration object R01 (Migrate), layout R01 version 1, through the Migration Console; lands in: Lists of Values (maker-checker); MIS field catalogue
A7: Source | B7: QPS, EBIX
A8: Depends on | B8: Nothing: this template can be filled in first
A9: Progress | B9: Rows entered | C9: =SUMPRODUCT(((ROW($B$20:$B$220)>20)+($B$20<>"MARKET_SEGMENT")>0)*(LEN($B$20:$B$220&$C$20:$C$220&$D$20:$D$220&$E$20:$E$220&$F$20:$F$220&$G$20:$G$220&$H$20:$H$220&$I$20:$I$220)>0)) | D9: Mandatory cells missing | E9: =SUMPRODUCT(((ROW($B$20:$B$220)>20)+($B$20<>"MARKET_SEGMENT")>0)*(LEN($B$20:$B$220&$C$20:$C$220&$D$20:$D$220&$E$20:$E$220&$F$20:$F$220&$G$20:$G$220&$H$20:$H$220&$I$20:$I$220)>0)*(($B$20:$B$220="")+($C$20:$C$220="")+($D$20:$D$220="")+($F$20:$F$220="")))
A10: Reviewed by (BU reviewer) | D10: Review date
A12: BU review
A13: BU comment
A14: Check when loaded | B14: Known list name | C14: Unique per list_type | D14: Not blank | E14: Parent exists in the file | F14: Y or N | G14: Valid date | H14: Not before effective_from | I14: 0 or more
A15: Mandatory | B15: Yes | C15: Yes | D15: Yes | E15: No | F15: Yes | G15: No | H15: No | I15: No
A16: Format | B16: Code, up to 40; Upper case | C16: Code, up to 40; As stored in legacy | D16: Text, up to 200; Free text | E16: Code, up to 40 | F16: Flag, up to 1; Y or N | G16: Date, up to 10; yyyy-MM-dd | H16: Date, up to 10; yyyy-MM-dd | I16: Integer, up to 9; Digits
A17: Allowed values | B17: Legacy list names; one code map set LOV:<list> or MIS:<field> per list | C17: Free entry, up to 40 characters | D17: Free entry, up to 200 characters | E17: Codes of the same file | F17: Y or N | G17: Free entry | H17: Free entry | I17: A whole number
A18: What to enter | B18: Legacy name of the list (for example MARKET_SEGMENT, BUSINESS_ORIGIN, CUSTOMER_SEGMENT, REGION, AREA, DEPARTMENT, ACCOUNT_TYPE, ID_TYPE, NATIONALITY) | C18: Legacy value code | D18: Legacy value description | E18: Code of the parent value for hierarchical lists (area under region) | F18: Value in use in legacy | G18: First day the value is valid | H18: Last day the value is valid | I18: Number of legacy records that use the value (helps the mapping)
A19: Row | B19: list_type * | C19: code * | D19: description * | E19: parent_code | F19: active_flag * | G19: effective_from | H19: effective_to | I19: used_count
A20: Example – overwrite or delete | B20: MARKET_SEGMENT | C20: CBG | D20: Consumer Banking Group | E20: NCR | F20: Y | G20: 2020-01-01 | I20: 1520

Sheet R02 Branches and invoicing bran
A1: R02 Branches and invoicing branches | G1: Step 2 of 29
A2: ← Back to Load templates | B2: Step 2 of 29. Fill in one row per record below the column headers; the guide above each column says what to enter. | G2: Ask a question →
A3: Purpose | B3: One row per record of Branches and invoicing branches as extracted from EBIX. Key branch_code. Sent as the file R02_template.csv (CSV, header row as below) with its control file (row count, count of distinct keys).
A4: Provided by | B4: Comptrollership data steward (to name); approved by Head, Comptrollership; extracted by BDOI IT
A5: Due | B5: M3 (29 Jan 2027)
A6: How it is loaded | B6: Data migration object R02 (Migrate), layout R02 version 1, through the Migration Console; lands in: Branches (check only, code map BRANCH)
A7: Source | B7: EBIX
A8: Depends on | B8: Nothing: this template can be filled in first
A9: Progress | B9: Rows entered | C9: =SUMPRODUCT(((ROW($B$20:$B$220)>20)+($B$20<>"MKT01")>0)*(LEN($B$20:$B$220&$C$20:$C$220&$D$20:$D$220&$E$20:$E$220&$F$20:$F$220)>0)) | D9: Mandatory cells missing | E9: =SUMPRODUCT(((ROW($B$20:$B$220)>20)+($B$20<>"MKT01")>0)*(LEN($B$20:$B$220&$C$20:$C$220&$D$20:$D$220&$E$20:$E$220&$F$20:$F$220)>0)*(($B$20:$B$220="")+($C$20:$C$220="")+($D$20:$D$220="")+($F$20:$F$220="")))
A10: Reviewed by (BU reviewer) | D10: Review date
A12: BU review
A13: BU comment
A14: Check when loaded | B14: Unique | C14: Not blank | D14: Y or N | E14: - | F14: Y or N
A15: Mandatory | B15: Yes | C15: Yes | D15: Yes | E15: No | F15: Yes
A16: Format | B16: Code, up to 20; As stored in legacy | C16: Text, up to 120; Free text | D16: Flag, up to 1; Y or N | E16: Text, up to 80; Free text | F16: Flag, up to 1; Y or N
A17: Allowed values | B17: Free entry, up to 20 characters | C17: Free entry, up to 120 characters | D17: Y or N | E17: Free entry, up to 80 characters | F17: Y or N
A18: What to enter | B18: Legacy branch code | C18: Branch name | D18: Branch issues invoices and receipts | E18: City of the branch | F18: Branch active in legacy
A19: Row | B19: branch_code * | C19: branch_name * | D19: invoicing_branch_flag * | E19: city | F19: active_flag *
A20: Example – overwrite or delete | B20: MKT01 | C20: Makati Head Office | D20: Y | E20: Makati City | F20: Y

Sheet R03 Sales organisation (units a
A1: R03 Sales organisation (units and account officers) | L1: Step 3 of 29
A2: ← Back to Load templates | B2: Step 3 of 29. Fill in one row per record below the column headers; the guide above each column says what to enter. | L2: Ask a question →
A3: Purpose | B3: One row per record of Sales organisation (regions, departments, teams, unit heads, account officers) as extracted from QPS, EBIX. Key record_type, unit_code, ao_user_id. Sent as the file R03_template.csv (CSV, header row as below) with its control file (row count, row count).
A4: Provided by | B4: Marketing data steward (to name); approved by Heads, Retail and Corporate Marketing; extracted by BDOI IT
A5: Due | B5: M3 (29 Jan 2027)
A6: How it is loaded | B6: Data migration object R03 (Migrate), layout R03 version 1, through the Migration Console; lands in: Sales organisation: sales units and account officers
A7: Source | B7: QPS, EBIX
A8: Depends on | B8: R02 Branches and invoicing branches →
A9: Progress | B9: Rows entered | C9: =SUMPRODUCT(((ROW($B$20:$B$220)>20)+($B$20<>"TEAM")>0)*(LEN($B$20:$B$220&$C$20:$C$220&$D$20:$D$220&$E$20:$E$220&$F$20:$F$220&$G$20:$G$220&$H$20:$H$220&$I$20:$I$220&$J$20:$J$220&$K$20:$K$220&$L$20:$L$220)>0)) | D9: Mandatory cells missing | E9: =SUMPRODUCT(((ROW($B$20:$B$220)>20)+($B$20<>"TEAM")>0)*(LEN($B$20:$B$220&$C$20:$C$220&$D$20:$D$220&$E$20:$E$220&$F$20:$F$220&$G$20:$G$220&$H$20:$H$220&$I$20:$I$220&$J$20:$J$220&$K$20:$K$220&$L$20:$L$220)>0)*(($B$20:$B$220="")+($C$20:$C$220="")+($L$20:$L$220="")))
A10: Reviewed by (BU reviewer) | D10: Review date
A12: BU review
A13: BU comment
A14: Check when loaded | B14: In the list | C14: Exists as a TEAM row for AO rows | D14: Mandatory for REGION, DEPARTMENT, TEAM | E14: Mandatory for DEPARTMENT and TEAM; parent exists | F14: Mapped in USER | G14: Mapped | H14: Mandatory for AO rows; mapped in USER | I14: Unique | J14: Mandatory for AO rows | K14: Mapped | L14: Y or N
A15: Mandatory | B15: Yes | C15: Yes | D15: Conditional: Mandatory for REGION, DEPARTMENT, TEAM | E15: Conditional: Mandatory for DEPARTMENT and TEAM; parent exists | F15: No | G15: No | H15: Conditional: Mandatory for AO rows; mapped in USER | I15: No | J15: Conditional: Mandatory for AO rows | K15: No | L15: Yes
A16: Format | B16: Code, up to 12; Upper case | C16: Code, up to 20; As stored in legacy | D16: Text, up to 120; Free text | E16: Code, up to 20; As stored in legacy | F16: Code, up to 50; As stored in legacy | G16: Code, up to 20; As stored in legacy | H16: Code, up to 50; As stored in legacy | I16: Code, up to 20; As stored in legacy | J16: Text, up to 120; Free text | K16: Code, up to 20; As stored in legacy | L16: Flag, up to 1; Y or N
A17: Allowed values | B17: REGION, DEPARTMENT, TEAM, AO (list R03 record_type) | C17: Free entry, up to 20 characters | D17: Free entry, up to 120 characters | E17: unit_code values of the file | F17: The legacy code; mapped by the code map USER (sheet Code maps) | G17: The legacy code; mapped by the code map COST_CENTER (sheet Code maps) | H17: The legacy code; mapped by the code map USER (sheet Code maps) | I17: The legacy code; mapped by the code map AO (sheet Code maps) | J17: Free entry, up to 120 characters | K17: The legacy code; mapped by the code map BRANCH (sheet Code maps) | L17: Y or N
A18: What to enter | B18: Kind of row | C18: Legacy code of the unit (for an AO row, the team of the AO) | D18: Unit name | E18: Code of the parent unit (department of a team, region of a department) | F18: Legacy user ID of the unit head | G18: Cost centre of the unit | H18: Legacy user ID of the account officer | I18: Legacy AO code if different from the user ID | J18: AO full name | K18: Branch of the unit or AO | L18: Unit or AO active
A19: Row | B19: record_type * | C19: unit_code * | D19: unit_name | E19: parent_unit_code | F19: unit_head_user_id | G19: cost_center | H19: ao_user_id | I19: ao_code | J19: ao_name | K19: branch_code | L19: active_flag *
A20: Example – overwrite or delete | B20: TEAM | C20: T-RET-07 | D20: Retail Team 7 | E20: D-RET | F20: jdelacruz | G20: 4100 | H20: mreyes | I20: AO0457 | J20: Maria Reyes | K20: MKT01 | L20: Y

Sheet R04 Insurers
A1: R04 Insurers | K1: Step 4 of 29
A2: ← Back to Load templates | B2: Step 4 of 29. Fill in one row per record below the column headers; the guide above each column says what to enter. | K2: Ask a question →
A3: Purpose | B3: One row per record of Insurers and insurer branches as extracted from QPS, EBIX. Key insurer_code. Sent as the file R04_template.csv (CSV, header row as below) with its control file (row count, count of distinct keys).
A4: Provided by | B4: Operations data steward (to name); approved by Head, Operations; extracted by BDOI IT
A5: Due | B5: M3 (29 Jan 2027)
A6: How it is loaded | B6: Data migration object R04 (Migrate), layout R04 version 1, through the Migration Console; lands in: Insurers and insurer branches (insurer and party records)
A7: Source | B7: QPS, EBIX
A8: Depends on | B8: Nothing: this template can be filled in first
A9: Progress | B9: Rows entered | C9: =SUMPRODUCT(((ROW($B$20:$B$220)>20)+($B$20<>"MAL")>0)*(LEN($B$20:$B$220&$C$20:$C$220&$D$20:$D$220&$E$20:$E$220&$F$20:$F$220&$G$20:$G$220&$H$20:$H$220&$I$20:$I$220&$J$20:$J$220&$K$20:$K$220)>0)) | D9: Mandatory cells missing | E9: =SUMPRODUCT(((ROW($B$20:$B$220)>20)+($B$20<>"MAL")>0)*(LEN($B$20:$B$220&$C$20:$C$220&$D$20:$D$220&$E$20:$E$220&$F$20:$F$220&$G$20:$G$220&$H$20:$H$220&$I$20:$I$220&$J$20:$J$220&$K$20:$K$220)>0)*(($B$20:$B$220="")+($C$20:$C$220="")+($K$20:$K$220="")))
A10: Reviewed by (BU reviewer) | D10: Review date
A12: BU review
A13: BU comment
A14: Check when loaded | B14: Unique | C14: Not blank | D14: - | E14: 9 to 12 digits | F14: - | G14: - | H14: Valid date | I14: Valid e-mail addresses | J14: 0 to 365 | K14: Mapped
A15: Mandatory | B15: Yes | C15: Yes | D15: No | E15: No | F15: No | G15: No | H15: No | I15: No | J15: No | K15: Yes
A16: Format | B16: Code, up to 30; As stored in legacy | C16: Text, up to 200; Free text | D16: Text, up to 40; Free text | E16: Text, up to 20; 000-000-000-000 | F16: Text, up to 300; Free text | G16: Text, up to 40; Free text | H16: Date, up to 10; yyyy-MM-dd | I16: Text, up to 500; name@domain;name@domain | J16: Integer, up to 3; Digits | K16: Code, up to 20; As stored in legacy
A17: Allowed values | B17: Free entry, up to 30 characters | C17: Free entry, up to 200 characters | D17: Free entry, up to 40 characters | E17: Free entry, up to 20 characters | F17: Free entry, up to 300 characters | G17: Free entry, up to 40 characters | H17: Free entry | I17: Free entry, up to 500 characters | J17: A whole number | K17: The legacy code; mapped by the code map STATUS:INSURER (sheet Code maps)
A18: What to enter | B18: Legacy insurer code | C18: Registered name | D18: Short name | E18: Tax identification number | F18: Registered address | G18: Insurance Commission accreditation number | H18: End of accreditation | I18: E-mail address(es) for placement, separated by semicolons | J18: Credit term in days | K18: Insurer status in legacy
A19: Row | B19: insurer_code * | C19: insurer_name * | D19: short_name | E19: tin | F19: address | G19: accreditation_no | H19: accredited_until | I19: placement_email | J19: default_credit_days | K19: status *
A20: Example – overwrite or delete | B20: MAL | C20: Malayan Insurance Co., Inc. | D20: Malayan | E20: 000-123-456-000 | F20: 500 Quintin Paredes St., Manila | G20: IC-2025-0123 | H20: 2028-06-30 | I20: placement@insurer.example | J20: 60 | K20: ACTIVE

Sheet R04B Insurer branches
A1: R04B Insurer branches | H1: Step 5 of 29
A2: ← Back to Load templates | B2: Step 5 of 29. Fill in one row per record below the column headers; the guide above each column says what to enter. | H2: Ask a question →
A3: Purpose | B3: One row per record of Insurers and insurer branches as extracted from QPS, EBIX. Key insurer_code, branch_code. Sent as the file R04B_template.csv (CSV, header row as below) with its control file (row count, count of distinct keys).
A4: Provided by | B4: Operations data steward (to name); approved by Head, Operations; extracted by BDOI IT
A5: Due | B5: M3 (29 Jan 2027)
A6: How it is loaded | B6: Data migration object R04 (Migrate), layout R04B version 1, through the Migration Console; lands in: Insurers and insurer branches (insurer and party records)
A7: Source | B7: QPS, EBIX
A8: Depends on | B8: R04 Insurers →
A9: Progress | B9: Rows entered | C9: =SUMPRODUCT(((ROW($B$20:$B$220)>20)+($B$20<>"MAL")>0)*(LEN($B$20:$B$220&$C$20:$C$220&$D$20:$D$220&$E$20:$E$220&$F$20:$F$220&$G$20:$G$220&$H$20:$H$220)>0)) | D9: Mandatory cells missing | E9: =SUMPRODUCT(((ROW($B$20:$B$220)>20)+($B$20<>"MAL")>0)*(LEN($B$20:$B$220&$C$20:$C$220&$D$20:$D$220&$E$20:$E$220&$F$20:$F$220&$G$20:$G$220&$H$20:$H$220)>0)*(($B$20:$B$220="")+($C$20:$C$220="")+($D$20:$D$220="")+($H$20:$H$220="")))
A10: Reviewed by (BU reviewer) | D10: Review date
A12: BU review
A13: BU comment
A14: Check when loaded | B14: Exists in R04 | C14: Unique per insurer | D14: Not blank | E14: - | F14: 0 to 5 | G14: Valid e-mail | H14: Mapped
A15: Mandatory | B15: Yes | C15: Yes | D15: Yes | E15: No | F15: No | G15: No | H15: Yes
A16: Format | B16: Code, up to 30; As stored in legacy | C16: Code, up to 20; As stored in legacy | D16: Text, up to 120; Free text | E16: Text, up to 80; Free text | F16: Decimal, up to 9,4; Dot decimal | G16: Text, up to 120; name@domain | H16: Code, up to 20; As stored in legacy
A17: Allowed values | B17: The legacy code; mapped by the code map INSURER (sheet Code maps) | C17: Free entry, up to 20 characters | D17: Free entry, up to 120 characters | E17: Free entry, up to 80 characters | F17: A number | G17: Free entry, up to 120 characters | H17: The legacy code; mapped by the code map STATUS:INSURER (sheet Code maps)
A18: What to enter | B18: Legacy insurer code | C18: Legacy insurer branch code | D18: Branch name | E18: City | F18: Local government tax rate of the branch location, in percent | G18: Branch placement e-mail | H18: Branch status
A19: Row | B19: insurer_code * | C19: branch_code * | D19: branch_name * | E19: city | F19: lgt_rate | G19: placement_email | H19: status *
A20: Example – overwrite or delete | B20: MAL | C20: MAL-CEB | D20: Malayan Cebu | E20: Cebu City | F20: 0.75 | G20: cebu@insurer.example | H20: ACTIVE

Sheet R05 Product lines, cover types,
A1: R05 Product lines, cover types, products and risk codes | J1: Step 6 of 29
A2: ← Back to Load templates | B2: Step 6 of 29. Fill in one row per record below the column headers; the guide above each column says what to enter. | J2: Ask a question →
A3: Purpose | B3: One row per record of Product lines, cover types, products and risk codes as extracted from QPS, EBIX. Key risk_code. Sent as the file R05_template.csv (CSV, header row as below) with its control file (row count, count of distinct keys).
A4: Provided by | B4: MBS data steward (to name); approved by Product Owner, MBS; extracted by BDOI IT
A5: Due | B5: M3 (29 Jan 2027)
A6: How it is loaded | B6: Data migration object R05 (Migrate), layout R05 version 1, through the Migration Console; lands in: Product catalogue: product lines, cover types and products
A7: Source | B7: QPS, EBIX
A8: Depends on | B8: Nothing: this template can be filled in first
A9: Progress | B9: Rows entered | C9: =SUMPRODUCT(((ROW($B$20:$B$220)>20)+($B$20<>"MOTOR")>0)*(LEN($B$20:$B$220&$C$20:$C$220&$D$20:$D$220&$E$20:$E$220&$F$20:$F$220&$G$20:$G$220&$H$20:$H$220&$I$20:$I$220&$J$20:$J$220)>0)) | D9: Mandatory cells missing | E9: =SUMPRODUCT(((ROW($B$20:$B$220)>20)+($B$20<>"MOTOR")>0)*(LEN($B$20:$B$220&$C$20:$C$220&$D$20:$D$220&$E$20:$E$220&$F$20:$F$220&$G$20:$G$220&$H$20:$H$220&$I$20:$I$220&$J$20:$J$220)>0)*(($B$20:$B$220="")+($E$20:$E$220="")+($F$20:$F$220="")+($I$20:$I$220="")))
A10: Reviewed by (BU reviewer) | D10: Review date
A12: BU review
A13: BU comment
A14: Check when loaded | B14: Mapped | C14: - | D14: Mapped | E14: Unique | F14: Not blank | G14: Y or N | H14: Each mapped | I14: Mapped | J14: 0 or more
A15: Mandatory | B15: Yes | C15: No | D15: No | E15: Yes | F15: Yes | G15: No | H15: No | I15: Yes | J15: No
A16: Format | B16: Code, up to 30; As stored in legacy | C16: Text, up to 120; Free text | D16: Code, up to 30; As stored in legacy | E16: Code, up to 20; As stored in legacy | F16: Text, up to 200; Free text | G16: Flag, up to 1; Y or N | H16: Text, up to 300; CODE;CODE | I16: Code, up to 20; As stored in legacy | J16: Integer, up to 9; Digits
A17: Allowed values | B17: The legacy code; mapped by the code map LINE (sheet Code maps) | C17: Free entry, up to 120 characters | D17: The legacy code; mapped by the code map COVER_TYPE (sheet Code maps) | E17: Free entry, up to 20 characters | F17: Free entry, up to 200 characters | G17: Y or N | H17: The legacy code; mapped by the code map LOV:MARKET_SEGMENT (sheet Code maps) | I17: The legacy code; mapped by the code map STATUS:PRODUCT (sheet Code maps) | J17: A whole number
A18: What to enter | B18: Legacy line of business | C18: Line name | D18: Legacy cover type | E18: Legacy risk code / product code | F18: Product / risk name | G18: Sold as a package | H18: Segments that may use the product, separated by semicolons | I18: Status in legacy | J18: Open invoices and in-force policies using the code (helps the mapping)
A19: Row | B19: line_code * | C19: line_name | D19: cover_type_code | E19: risk_code * | F19: risk_name * | G19: packaged_flag | H19: market_segments | I19: status * | J19: open_item_count
A20: Example – overwrite or delete | B20: MOTOR | C20: Motor Car | D20: COMP | E20: MC-PC-COMP | F20: Private Car Own Damage and Theft | G20: N | H20: CBG;RETAIL | I20: ACTIVE | J20: 4211

Sheet R06 Package code map (legacy pa
A1: R06 Package code map (legacy package to BIBS package version) | I1: Step 7 of 29
A2: ← Back to Load templates | B2: Step 7 of 29. Fill in one row per record below the column headers; the guide above each column says what to enter. | I2: Ask a question →
A3: Purpose | B3: One row per record of Package code map (legacy package and version to BIBS package version) as extracted from QPS (legacy packages); TSU (BIBS package versions). Key legacy_package_code, legacy_package_version, qualifier, qualifier_value. Sent as the file R06_template.csv (CSV, header row as below) with its control file (row count, count of distinct keys).
A4: Provided by | B4: TSU (to name); approved by Product Owner, MBS (approves); TSU (prepares); extracted by BDOI IT
A5: Due | B5: M5 (18 Jun 2027); final at T-7
A6: How it is loaded | B6: Data migration object R06 (Migrate), layout R06 version 1, through the Migration Console; lands in: Renewal package map, used by the package check of the Renewal sanitation
A7: Source | B7: QPS (legacy packages); TSU (BIBS package versions)
A8: Depends on | B8: Nothing: this template can be filled in first
A9: Progress | B9: Rows entered | C9: =SUMPRODUCT(((ROW($B$20:$B$220)>20)+($B$20<>"PKG-MC-PRIV")>0)*(LEN($B$20:$B$220&$C$20:$C$220&$D$20:$D$220&$E$20:$E$220&$F$20:$F$220&$G$20:$G$220&$H$20:$H$220&$I$20:$I$220)>0)) | D9: Mandatory cells missing | E9: =SUMPRODUCT(((ROW($B$20:$B$220)>20)+($B$20<>"PKG-MC-PRIV")>0)*(LEN($B$20:$B$220&$C$20:$C$220&$D$20:$D$220&$E$20:$E$220&$F$20:$F$220&$G$20:$G$220&$H$20:$H$220&$I$20:$I$220)>0)*(($B$20:$B$220="")+($C$20:$C$220="")+($D$20:$D$220="")+($G$20:$G$220="")))
A10: Reviewed by (BU reviewer) | D10: Review date
A12: BU review
A13: BU comment
A14: Check when loaded | B14: Exists in the legacy package list | C14: 0 or more | D14: Not blank | E14: In the list; one qualifier per entry | F14: Mandatory with a qualifier; bands of one legacy package do not overlap | G14: In the list | H14: Mandatory for MAP; active in Product Maintenance | I14: -
A15: Mandatory | B15: Yes | C15: Yes | D15: Yes | E15: No | F15: Conditional: Mandatory with a qualifier; bands of one legacy package do not overlap | G15: Yes | H15: Conditional: Mandatory for MAP; active in Product Maintenance | I15: No
A16: Format | B16: Code, up to 20; As stored in legacy | C16: Integer, up to 4; Digits | D16: Text, up to 200; Free text | E16: Code, up to 20; Upper case | F16: Text, up to 60; Code, or from-to amounts with a dot decimal | G16: Code, up to 6; Upper case | H16: Code, up to 40; As in BIBS | I16: Text, up to 250; Free text
A17: Allowed values | B17: Free entry, up to 20 characters | C17: A whole number | D17: Free entry, up to 200 characters | E17: RISK_CODE, INSURER, SI_BAND (list R06 qualifier) | F17: Free entry, up to 60 characters | G17: MAP, REJECT (list R06 action) | H17: Active package versions in Product Maintenance | I17: Free entry, up to 250 characters
A18: What to enter | B18: Legacy package code | C18: Version of the legacy package | D18: Package name in legacy | E18: Attribute that splits one legacy package into several BIBS packages | F18: Value of the qualifier (risk code, insurer code, or sum-insured band as from-to) | G18: MAP to a BIBS package version, or REJECT (no BIBS package) | H18: BIBS package version maintained by TSU | I18: Why the entry maps as it does
A19: Row | B19: legacy_package_code * | C19: legacy_package_version * | D19: legacy_package_name * | E19: qualifier | F19: qualifier_value | G19: action * | H19: bibs_package_version | I19: remarks
A20: Example – overwrite or delete | B20: PKG-MC-PRIV | C20: 3 | D20: Private Car Package 2027 | E20: SI_BAND | F20: 0.00-2000000.00 | G20: MAP | H20: MC-PRIVATE-STD v1 | I20: Sum insured up to 2,000,000.00

Sheet R07 Commission rates by insurer
A1: R07 Commission rates by insurer and product | G1: Step 8 of 29
A2: ← Back to Load templates | B2: Step 8 of 29. Fill in one row per record below the column headers; the guide above each column says what to enter. | G2: Ask a question →
A3: Purpose | B3: One row per record of Commission rates by insurer and product as extracted from QPS, EBIX. Key insurer_code, risk_code, effective_from. Sent as the file R07_template.csv (CSV, header row as below) with its control file (row count, row count).
A4: Provided by | B4: Operations data steward (to name); approved by Head, Operations; extracted by BDOI IT
A5: Due | B5: M3 (29 Jan 2027)
A6: How it is loaded | B6: Data migration object R07 (Migrate), layout R07 version 1, through the Migration Console; lands in: Commission rates of the product catalogue
A7: Source | B7: QPS, EBIX
A8: Depends on | B8: R04 Insurers → | D8: R04B Insurer branches →
A9: Progress | B9: Rows entered | C9: =SUMPRODUCT(((ROW($B$20:$B$220)>20)+($B$20<>"MAL")>0)*(LEN($B$20:$B$220&$C$20:$C$220&$D$20:$D$220&$E$20:$E$220&$F$20:$F$220)>0)) | D9: Mandatory cells missing | E9: =SUMPRODUCT(((ROW($B$20:$B$220)>20)+($B$20<>"MAL")>0)*(LEN($B$20:$B$220&$C$20:$C$220&$D$20:$D$220&$E$20:$E$220&$F$20:$F$220)>0)*(($B$20:$B$220="")+($C$20:$C$220="")+($D$20:$D$220="")+($E$20:$E$220="")))
A10: Reviewed by (BU reviewer) | D10: Review date
A12: BU review
A13: BU comment
A14: Check when loaded | B14: Mapped | C14: Mapped | D14: 0 to 100 | E14: Valid date | F14: No overlap for the same insurer and product
A15: Mandatory | B15: Yes | C15: Yes | D15: Yes | E15: Yes | F15: No
A16: Format | B16: Code, up to 30; As stored in legacy | C16: Code, up to 20; As stored in legacy | D16: Decimal, up to 9,4; Dot decimal | E16: Date, up to 10; yyyy-MM-dd | F16: Date, up to 10; yyyy-MM-dd
A17: Allowed values | B17: The legacy code; mapped by the code map INSURER (sheet Code maps) | C17: The legacy code; mapped by the code map PRODUCT (sheet Code maps) | D17: A number | E17: Free entry | F17: Free entry
A18: What to enter | B18: Legacy insurer code | C18: Legacy product / risk code | D18: Commission rate in percent | E18: Rate valid from | F18: Rate valid to
A19: Row | B19: insurer_code * | C19: risk_code * | D19: rate_pct * | E19: effective_from * | F19: effective_to
A20: Example – overwrite or delete | B20: MAL | C20: MC-PC-COMP | D20: 20 | E20: 2026-01-01

Sheet R08 Chart of accounts mapping
A1: R08 Chart of accounts mapping | I1: Step 9 of 29
A2: ← Back to Load templates | B2: Step 9 of 29. Fill in one row per record below the column headers; the guide above each column says what to enter. | I2: Ask a question →
A3: Purpose | B3: One row per record of Chart of accounts mapping (legacy GL account to BIBS account) as extracted from EBIX, ISYS GL. Key legacy_account_code. Sent as the file R08_template.csv (CSV, header row as below) with its control file (row count, count of distinct keys).
A4: Provided by | B4: Comptrollership data steward (to name); approved by Head, Comptrollership; Product Owner FRBS and ACSL; extracted by BDOI IT
A5: Due | B5: M3 (29 Jan 2027)
A6: How it is loaded | B6: Data migration object R08 (Migrate), layout R08 version 1, through the Migration Console; lands in: GL account code map to the BIBS chart of accounts (chart configured by Comptrollership)
A7: Source | B7: EBIX, ISYS GL
A8: Depends on | B8: Nothing: this template can be filled in first
A9: Progress | B9: Rows entered | C9: =SUMPRODUCT(((ROW($B$20:$B$220)>20)+($B$20<>"1101-02")>0)*(LEN($B$20:$B$220&$C$20:$C$220&$D$20:$D$220&$E$20:$E$220&$F$20:$F$220&$G$20:$G$220&$H$20:$H$220&$I$20:$I$220)>0)) | D9: Mandatory cells missing | E9: =SUMPRODUCT(((ROW($B$20:$B$220)>20)+($B$20<>"1101-02")>0)*(LEN($B$20:$B$220&$C$20:$C$220&$D$20:$D$220&$E$20:$E$220&$F$20:$F$220&$G$20:$G$220&$H$20:$H$220&$I$20:$I$220)>0)*(($B$20:$B$220="")+($C$20:$C$220="")+($D$20:$D$220="")+($E$20:$E$220="")))
A10: Reviewed by (BU reviewer) | D10: Review date
A12: BU review
A13: BU comment
A14: Check when loaded | B14: Unique | C14: Not blank | D14: In the list | E14: In the list | F14: In the list | G14: Mandatory when legacy_control_type is NONE; exists and active in BIBS | H14: Y or N | I14: -
A15: Mandatory | B15: Yes | C15: Yes | D15: Yes | E15: Yes | F15: No | G15: Conditional: Mandatory when legacy_control_type is NONE; exists and active in BIBS | H15: No | I15: No
A16: Format | B16: Code, up to 30; As stored in legacy | C16: Text, up to 200; Free text | D16: Code, up to 12; Upper case | E16: Code, up to 2; Upper case | F16: Code, up to 20; Upper case | G16: Code, up to 30; As in the BIBS chart | H16: Flag, up to 1; Y or N | I16: Text, up to 300; Free text
A17: Allowed values | B17: Free entry, up to 30 characters | C17: Free entry, up to 200 characters | D17: ASSET, LIABILITY, EQUITY, INCOME, EXPENSE (list R08 account_type) | E17: DR, CR (list R08 normal_balance) | F17: List R08 legacy_control_type: 8 values, see Reference lists | G17: Account codes of the BIBS chart of accounts | H17: Y or N | I17: Free entry, up to 300 characters
A18: What to enter | B18: Legacy GL account code | C18: Legacy account name | D18: Account type | E18: Normal balance side | F18: Marks the legacy control accounts whose balance F01 or F02 carries in detail | G18: BIBS account the legacy account maps to (filled by Comptrollership) | H18: Balances are kept per branch | I18: Mapping remarks
A19: Row | B19: legacy_account_code * | C19: legacy_account_name * | D19: account_type * | E19: normal_balance * | F19: legacy_control_type | G19: bibs_account_code | H19: branch_specific_flag | I19: remarks
A20: Example – overwrite or delete | B20: 1101-02 | C20: Cash in Bank - BDO Makati | D20: ASSET | E20: DR | F20: NONE | G20: X102.03 (illustrative code, not in use) | H20: Y | I20: Merged with 1201-01

Sheet R09 Payees
A1: R09 Payees | L1: Step 10 of 29
A2: ← Back to Load templates | B2: Step 10 of 29. Fill in one row per record below the column headers; the guide above each column says what to enter. | L2: Ask a question →
A3: Purpose | B3: One row per record of Payees as extracted from EBIX, Disbursement files. Key payee_code. Sent as the file R09_template.csv (CSV, header row as below) with its control file (row count, count of distinct keys).
A4: Provided by | B4: Disbursement data steward (to name); approved by Product Owner, Comptrollership - Disbursement; extracted by BDOI IT
A5: Due | B5: M3 (29 Jan 2027)
A6: How it is loaded | B6: Data migration object R09 (Conditional), layout R09 version 1, through the Migration Console; lands in: Payees (party and payee records, loaded by the payee migration)
A7: Source | B7: EBIX, Disbursement files
A8: Depends on | B8: Nothing: this template can be filled in first
A9: Progress | B9: Rows entered | C9: =SUMPRODUCT(((ROW($B$20:$B$220)>20)+($B$20<>"SUP-0001")>0)*(LEN($B$20:$B$220&$C$20:$C$220&$D$20:$D$220&$E$20:$E$220&$F$20:$F$220&$G$20:$G$220&$H$20:$H$220&$I$20:$I$220&$J$20:$J$220&$K$20:$K$220&$L$20:$L$220)>0)) | D9: Mandatory cells missing | E9: =SUMPRODUCT(((ROW($B$20:$B$220)>20)+($B$20<>"SUP-0001")>0)*(LEN($B$20:$B$220&$C$20:$C$220&$D$20:$D$220&$E$20:$E$220&$F$20:$F$220&$G$20:$G$220&$H$20:$H$220&$I$20:$I$220&$J$20:$J$220&$K$20:$K$220&$L$20:$L$220)>0)*(($B$20:$B$220="")+($C$20:$C$220="")+($D$20:$D$220="")+($H$20:$H$220="")+($I$20:$I$220="")+($J$20:$J$220="")))
A10: Reviewed by (BU reviewer) | D10: Review date
A12: BU review
A13: BU comment
A14: Check when loaded | B14: Unique | C14: In the list | D14: Not blank | E14: - | F14: Valid e-mail | G14: 9 to 12 digits | H14: One of allowed_modes | I14: CTA | J14: Valid code | K14: Mapped | L14: Mandatory for CTA
A15: Mandatory | B15: Yes | C15: Yes | D15: Yes | E15: No | F15: No | G15: No | H15: Yes | I15: Yes | J15: Yes | K15: No | L15: Conditional: Mandatory for CTA
A16: Format | B16: Code, up to 30; As stored in legacy | C16: Code, up to 20; Upper case | D16: Text, up to 250; Free text | E16: Text, up to 300; Free text | F16: Text, up to 120; name@domain | G16: Text, up to 20; 000-000-000-000 | H16: Code, up to 20; Upper case | I16: Text, up to 100; MODE\ | J16: Code, up to 3; Upper case | K16: Text, up to 120; Free text | L16: Text, up to 40; Digits
A17: Allowed values | B17: Free entry, up to 30 characters | C17: LOV PAYEE_CLASS | D17: Free entry, up to 250 characters | E17: Free entry, up to 300 characters | F17: Free entry, up to 120 characters | G17: Free entry, up to 20 characters | H17: List R09 default_mode: 7 values, see Reference lists | I17: Same list as default_mode | J17: ISO 4217 | K17: The legacy code; mapped by the code map BANK (sheet Code maps) | L17: Free entry, up to 40 characters
A18: What to enter | B18: Legacy payee code | C18: Payee class | D18: Payee name | E18: Address | F18: E-mail for payment advices | G18: Tax identification number | H18: Default payment mode | I18: Allowed payment modes separated by a vertical bar | J18: Currency | K18: Bank of the payee account | L18: Payee account number
A19: Row | B19: payee_code * | C19: payee_class * | D19: name * | E19: address | F19: email | G19: tin | H19: default_mode * | I19: allowed_modes * | J19: currency * | K19: bank | L19: account_no
A20: Example – overwrite or delete | B20: SUP-0001 | C20: SUPPLIER | D20: Acme Office Supply | E20: Makati City | F20: ap@acme.example | G20: 123-456-789-000 | H20: CHECK | I20: MODE | J20: PHP | K20: BDO Unibank | L20: 001234567890

Sheet R11 Receipt series in use
A1: R11 Receipt series in use | I1: Step 11 of 29
A2: ← Back to Load templates | B2: Step 11 of 29. Fill in one row per record below the column headers; the guide above each column says what to enter. | I2: Ask a question →
A3: Purpose | B3: One row per record of Receipt series in use (AR and OR, ATP and next number) as extracted from EBIX. Key branch_code, kind, prefix. Sent as the file R11_template.csv (CSV, header row as below) with its control file (row count, row count).
A4: Provided by | B4: Cashiering data steward (to name); approved by Operations - Financial Transactions; extracted by BDOI IT
A5: Due | B5: M3 (29 Jan 2027); final at T-3
A6: How it is loaded | B6: Data migration object R11 (Carry forward), layout R11 version 1, through the Migration Console; lands in: Receipt series of Cashiering
A7: Source | B7: EBIX
A8: Depends on | B8: R02 Branches and invoicing branches →
A9: Progress | B9: Rows entered | C9: =SUMPRODUCT(((ROW($B$20:$B$220)>20)+($B$20<>"MKT01")>0)*(LEN($B$20:$B$220&$C$20:$C$220&$D$20:$D$220&$E$20:$E$220&$F$20:$F$220&$G$20:$G$220&$H$20:$H$220&$I$20:$I$220)>0)) | D9: Mandatory cells missing | E9: =SUMPRODUCT(((ROW($B$20:$B$220)>20)+($B$20<>"MKT01")>0)*(LEN($B$20:$B$220&$C$20:$C$220&$D$20:$D$220&$E$20:$E$220&$F$20:$F$220&$G$20:$G$220&$H$20:$H$220&$I$20:$I$220)>0)*(($B$20:$B$220="")+($C$20:$C$220="")+($D$20:$D$220="")+($F$20:$F$220="")+($G$20:$G$220="")+($H$20:$H$220="")+($I$20:$I$220="")))
A10: Reviewed by (BU reviewer) | D10: Review date
A12: BU review
A13: BU comment
A14: Check when loaded | B14: Mapped | C14: In the list | D14: Not blank | E14: Unique per branch and kind | F14: Less than to_no | G14: More than from_no | H14: Between from_no and to_no | I14: =last_used_no + 1
A15: Mandatory | B15: Yes | C15: Yes | D15: Yes | E15: No | F15: Yes | G15: Yes | H15: Yes | I15: Yes
A16: Format | B16: Code, up to 20; As stored in legacy | C16: Code, up to 2; Upper case | D16: Text, up to 40; As printed | E16: Text, up to 20; As printed | F16: Integer, up to 12; Digits | G16: Integer, up to 12; Digits | H16: Integer, up to 12; Digits | I16: Integer, up to 12; Digits
A17: Allowed values | B17: The legacy code; mapped by the code map BRANCH (sheet Code maps) | C17: AR, OR (list R11 kind) | D17: Free entry, up to 40 characters | E17: Free entry, up to 20 characters | F17: A whole number | G17: A whole number | H17: A whole number | I17: A whole number
A18: What to enter | B18: Issuing branch | C18: Receipt kind | D18: BIR Authority to Print number | E18: Series prefix | F18: First number of the series | G18: Last number of the series | H18: Last number issued in legacy at the freeze | I18: Next number BIBS issues
A19: Row | B19: branch_code * | C19: kind * | D19: atp_no * | E19: prefix | F19: from_no * | G19: to_no * | H19: last_used_no * | I19: next_no *
A20: Example – overwrite or delete | B20: MKT01 | C20: AR | D20: ATP-OCN-2025-000123 | E20: AR-MKT | F20: 100001 | G20: 150000 | H20: 131245 | I20: 131246

Sheet C01 Client master
A1: C01 Client master | AK1: Step 12 of 29
A2: ← Back to Load templates | B2: Step 12 of 29. Fill in one row per record below the column headers; the guide above each column says what to enter. | AK2: Ask a question →
A3: Purpose | B3: One row per record of Client master (individual and corporate) as extracted from QPS, EBIX, CMS. Key legacy_client_no. Sent as the file C01_template.csv (CSV, header row as below) with its control file (row count, count of distinct keys).
A4: Provided by | B4: Marketing data steward (to name); approved by Product Owner, MBS; Heads, Retail and Corporate Marketing; extracted by BDOI IT
A5: Due | B5: M3 (29 Jan 2027); deltas daily from T-14 days
A6: How it is loaded | B6: Data migration object C01 (Migrate), layout C01 version 1, through the Migration Console; lands in: Client master, registered as migrated clients
A7: Source | B7: QPS, EBIX, CMS
A8: Depends on | B8: R01 Lists of values and MIS values → | D8: R02 Branches and invoicing branches → | F8: R03 Sales organisation (units and account officers) →
A9: Progress | B9: Rows entered | C9: =SUMPRODUCT(((ROW($B$20:$B$220)>20)+($B$20<>"Q-0012345")>0)*(LEN($B$20:$B$220&$C$20:$C$220&$D$20:$D$220&$E$20:$E$220&$F$20:$F$220&$G$20:$G$220&$H$20:$H$220&$I$20:$I$220&$J$20:$J$220&$K$20:$K$220&$L$20:$L$220&$M$20:$M$220&$N$20:$N$220&$O$20:$O$220&$P$20:$P$220&$Q$20:$Q$220&$R$20:$R$220&$S$20:$S$220&$T$20:$T$220&$U$20:$U$220&$V$20:$V$220&$W$20:$W$220&$X$20:$X$220&$Y$20:$Y$220&$Z$20:$Z$220&$AA$20:$AA$220&$AB$20:$AB$220&$AC$20:$AC$220&$AD$20:$AD$220&$AE$20:$AE$220&$AF$20:$AF$220&$AG$20:$AG$220&$AH$20:$AH$220&$AI$20:$AI$220&$AJ$20:$AJ$220&$AK$20:$AK$220)>0)) | D9: Mandatory cells missing | E9: =SUMPRODUCT(((ROW($B$20:$B$220)>20)+($B$20<>"Q-0012345")>0)*(LEN($B$20:$B$220&$C$20:$C$220&$D$20:$D$220&$E$20:$E$220&$F$20:$F$220&$G$20:$G$220&$H$20:$H$220&$I$20:$I$220&$J$20:$J$220&$K$20:$K$220&$L$20:$L$220&$M$20:$M$220&$N$20:$N$220&$O$20:$O$220&$P$20:$P$220&$Q$20:$Q$220&$R$20:$R$220&$S$20:$S$220&$T$20:$T$220&$U$20:$U$220&$V$20:$V$220&$W$20:$W$220&$X$20:$X$220&$Y$20:$Y$220&$Z$20:$Z$220&$AA$20:$AA$220&$AB$20:$AB$220&$AC$20:$AC$220&$AD$20:$AD$220&$AE$20:$AE$220&$AF$20:$AF$220&$AG$20:$AG$220&$AH$20:$AH$220&$AI$20:$AI$220&$AJ$20:$AJ$220&$AK$20:$AK$220)>0)*(($B$20:$B$220="")+($C$20:$C$220="")+($R$20:$R$220="")+($AI$20:$AI$220="")+($AJ$20:$AJ$220="")+($AK$20:$AK$220="")))
A10: Reviewed by (BU reviewer) | D10: Review date
A12: BU review
A13: BU comment
A14: Check when loaded | B14: Unique in the file | C14: In the list | D14: Mandatory for I | E14: Mandatory for I | F14: - | G14: - | H14: Mandatory for C | I14: - | J14: Mandatory for I; not in the future; age 0 to 120 | K14: 9 to 12 digits; duplicate key K1 | L14: Mapped | M14: Mandatory when id_type is given; duplicate key K2 | N14: Y or N | O14: Duplicate key K5 if agreed | P14: Mapped | Q14: Mapped | R14: Mapped | S14: Mapped | T14: Mapped | U14: Mapped in USER | V14: Mapped | W14: Mapped | X14: Valid e-mail; soft key K6 | Y14: PH mobile format; soft key K6 | Z14: - | AA14: - | AB14: - | AC14: - | AD14: 4 digits | AE14: Mapped | AF14: Not in the future | AG14: Valid date | AH14: Mapped | AI14: Mapped | AJ14: Valid date | AK14: Valid timestamp
A15: Mandatory | B15: Yes | C15: Yes | D15: Conditional: Mandatory for I | E15: Conditional: Mandatory for I | F15: No | G15: No | H15: Conditional: Mandatory for C | I15: No | J15: Conditional: Mandatory for I; not in the future; age 0 to 120 | K15: No | L15: No | M15: Conditional: Mandatory when id_type is given; duplicate key K2 | N15: No | O15: No | P15: No | Q15: No | R15: Yes | S15: No | T15: No | U15: No | V15: No | W15: No | X15: No | Y15: No | Z15: No | AA15: No | AB15: No | AC15: No | AD15: No | AE15: No | AF15: No | AG15: No | AH15: No | AI15: Yes | AJ15: Yes | AK15: Yes
A16: Format | B16: Code, up to 30; As stored in legacy | C16: Code, up to 1; Upper case | D16: Text, up to 100; Free text | E16: Text, up to 100; Free text | F16: Text, up to 100; Free text | G16: Text, up to 20; Free text | H16: Text, up to 200; Free text | I16: Text, up to 60; As registered | J16: Date, up to 10; yyyy-MM-dd | K16: Text, up to 20; 000-000-000-000 | L16: Code, up to 40; As stored in legacy | M16: Text, up to 60; As printed | N16: Flag, up to 1; Y or N | O16: Text, up to 40; Digits | P16: Code, up to 40; As stored in legacy | Q16: Code, up to 40; As stored in legacy | R16: Code, up to 40; As stored in legacy | S16: Code, up to 40; As stored in legacy | T16: Code, up to 40; As stored in legacy | U16: Code, up to 50; As stored in legacy | V16: Code, up to 20; As stored in legacy | W16: Code, up to 20; As stored in legacy | X16: Text, up to 120; name@domain | Y16: Text, up to 30; 09xxxxxxxxx or +639xxxxxxxxx | Z16: Text, up to 30; Free text | AA16: Text, up to 300; Free text | AB16: Text, up to 80; Free text | AC16: Text, up to 80; Free text | AD16: Text, up to 10; 4 digits | AE16: Code, up to 20; As stored in legacy | AF16: Date, up to 10; yyyy-MM-dd | AG16: Date, up to 10; yyyy-MM-dd | AH16: Code, up to 20; As stored in legacy | AI16: Code, up to 20; As stored in legacy | AJ16: Date, up to 10; yyyy-MM-dd | AK16: Timestamp, up to 19; yyyy-MM-dd HH:mm:ss
A17: Allowed values | B17: Free entry, up to 30 characters | C17: I, C (list C01 client_type) | D17: Free entry, up to 100 characters | E17: Free entry, up to 100 characters | F17: Free entry, up to 100 characters | G17: Free entry, up to 20 characters | H17: Free entry, up to 200 characters | I17: Free entry, up to 60 characters | J17: Free entry | K17: Free entry, up to 20 characters | L17: The legacy code; mapped by the code map LOV:ID_TYPE (sheet Code maps) | M17: Free entry, up to 60 characters | N17: Y or N | O17: Free entry, up to 40 characters | P17: The legacy code; mapped by the code map LOV:NATIONALITY (sheet Code maps) | Q17: The legacy code; mapped by the code map LOV:SOURCE_OF_FUNDS (sheet Code maps) | R17: The legacy code; mapped by the code map LOV:MARKET_SEGMENT (sheet Code maps) | S17: The legacy code; mapped by the code map MIS:CUSTOMER_SEGMENT (sheet Code maps) | T17: The legacy code; mapped by the code map MIS:BUSINESS_ORIGIN (sheet Code maps) | U17: The legacy code; mapped by the code map USER (sheet Code maps) | V17: The legacy code; mapped by the code map SALES_UNIT (sheet Code maps) | W17: The legacy code; mapped by the code map BRANCH (sheet Code maps) | X17: Free entry, up to 120 characters | Y17: Free entry, up to 30 characters | Z17: Free entry, up to 30 characters | AA17: Free entry, up to 300 characters | AB17: Free entry, up to 80 characters | AC17: Free entry, up to 80 characters | AD17: Free entry, up to 10 characters | AE17: The legacy code; mapped by the code map STATUS:KYC (sheet Code maps) | AF17: Free entry | AG17: Free entry | AH17: The legacy code; mapped by the code map LOV:KYC_RISK_RATING (sheet Code maps) | AI17: The legacy code; mapped by the code map STATUS:CLIENT (sheet Code maps) | AJ17: Free entry | AK17: Free entry
A18: What to enter | B18: Client number in the source system | C18: Individual or corporate | D18: Last name (individual) | E18: First name (individual) | F18: Middle name | G18: Name suffix | H18: Registered name (corporate) | I18: SEC or DTI registration number (corporate) | J18: Birth date (individual) | K18: Tax identification number | L18: Government ID type | M18: Government ID number | N18: BDO bank client | O18: BDO customer information file number | P18: Nationality | Q18: Source of funds | R18: Market segment | S18: Customer segment (MIS) | T18: Business origin (MIS) | U18: Account officer | V18: Sales unit of the client | W18: Servicing branch | X18: Primary e-mail | Y18: Primary mobile number | Z18: Landline | AA18: Primary street address | AB18: City / municipality | AC18: Province | AD18: Postal code | AE18: KYC status in legacy | AF18: Date KYC was verified | AG18: Next KYC review date | AH18: KYC risk rating | AI18: Client status in legacy | AJ18: Date the client was created in legacy | AK18: Last change in legacy (survivorship and deltas)
A19: Row | B19: legacy_client_no * | C19: client_type * | D19: last_name | E19: first_name | F19: middle_name | G19: suffix | H19: corporate_name | I19: registration_no | J19: birth_date | K19: tin | L19: id_type | M19: id_number | N19: bank_client_flag | O19: bank_cif | P19: nationality | Q19: source_of_funds | R19: market_segment * | S19: customer_segment | T19: business_origin | U19: ao_user_id | V19: sales_unit_code | W19: branch_code | X19: email | Y19: mobile | Z19: phone | AA19: address_line | AB19: city | AC19: province | AD19: postal_code | AE19: kyc_status | AF19: kyc_verified_date | AG19: kyc_review_due | AH19: risk_rating | AI19: client_status * | AJ19: created_date * | AK19: last_updated *
A20: Example – overwrite or delete | B20: Q-0012345 | C20: I | D20: Reyes | E20: Ana | F20: Cruz | G20: Jr. | H20: Acme Trading Corp. | I20: CS201912345 | J20: 1990-04-15 | K20: 123-456-789-000 | L20: PASSPORT | M20: P1234567A | N20: Y | O20: 1234567890 | P20: FILIPINO | Q20: SALARY | R20: CBG | S20: AFFLUENT | T20: BANK_REFERRAL | U20: mreyes | V20: T-RET-07 | W20: MKT01 | X20: ana.reyes@example.ph | Y20: 09171234567 | Z20: (02) 8123 4567 | AA20: 12 Rizal St., Brgy. San Antonio | AB20: Pasig | AC20: Metro Manila | AD20: 1600 | AE20: COMPLETE | AF20: 2024-03-11 | AG20: 2028-03-11 | AH20: STANDARD | AI20: ACTIVE | AJ20: 2021-07-02 | AK20: 2026-08-30 14:22:05

Sheet C02 Client addresses and contac
A1: C02 Client addresses and contacts | N1: Step 13 of 29
A2: ← Back to Load templates | B2: Step 13 of 29. Fill in one row per record below the column headers; the guide above each column says what to enter. | N2: Ask a question →
A3: Purpose | B3: One row per record of Client master (individual and corporate) as extracted from QPS, EBIX, CMS. Key legacy_client_no, record_type, seq_no. Sent as the file C02_template.csv (CSV, header row as below) with its control file (row count, row count).
A4: Provided by | B4: Marketing data steward (to name); approved by Product Owner, MBS; Heads, Retail and Corporate Marketing; extracted by BDOI IT
A5: Due | B5: M3 (29 Jan 2027); deltas daily from T-14 days
A6: How it is loaded | B6: Data migration object C01 (Migrate), layout C02 version 1, through the Migration Console; lands in: Client master, registered as migrated clients
A7: Source | B7: QPS, EBIX, CMS
A8: Depends on | B8: C01 Client master → | D8: R01 Lists of values and MIS values → | F8: R02 Branches and invoicing branches → | G8: R03 Sales organisation (units and account officers) →
A9: Progress | B9: Rows entered | C9: =SUMPRODUCT(((ROW($B$20:$B$220)>20)+($B$20<>"Q-0012345")>0)*(LEN($B$20:$B$220&$C$20:$C$220&$D$20:$D$220&$E$20:$E$220&$F$20:$F$220&$G$20:$G$220&$H$20:$H$220&$I$20:$I$220&$J$20:$J$220&$K$20:$K$220&$L$20:$L$220&$M$20:$M$220&$N$20:$N$220)>0)) | D9: Mandatory cells missing | E9: =SUMPRODUCT(((ROW($B$20:$B$220)>20)+($B$20<>"Q-0012345")>0)*(LEN($B$20:$B$220&$C$20:$C$220&$D$20:$D$220&$E$20:$E$220&$F$20:$F$220&$G$20:$G$220&$H$20:$H$220&$I$20:$I$220&$J$20:$J$220&$K$20:$K$220&$L$20:$L$220&$M$20:$M$220&$N$20:$N$220)>0)*(($B$20:$B$220="")+($C$20:$C$220="")+($D$20:$D$220="")+($N$20:$N$220="")))
A10: Reviewed by (BU reviewer) | D10: Review date
A12: BU review
A13: BU comment
A14: Check when loaded | B14: Exists in C01 of the same source | C14: In the list | D14: Unique per client and record type | E14: Mandatory for ADDRESS | F14: Mandatory for ADDRESS | G14: - | H14: - | I14: 4 digits | J14: Mandatory for CONTACT | K14: - | L14: Valid e-mail | M14: PH mobile format | N14: One primary ADDRESS per client
A15: Mandatory | B15: Yes | C15: Yes | D15: Yes | E15: Conditional: Mandatory for ADDRESS | F15: Conditional: Mandatory for ADDRESS | G15: No | H15: No | I15: No | J15: Conditional: Mandatory for CONTACT | K15: No | L15: No | M15: No | N15: Yes
A16: Format | B16: Code, up to 30; As stored in legacy | C16: Code, up to 10; Upper case | D16: Integer, up to 3; Digits | E16: Code, up to 12; Upper case | F16: Text, up to 300; Free text | G16: Text, up to 80; Free text | H16: Text, up to 80; Free text | I16: Text, up to 10; 4 digits | J16: Text, up to 200; Free text | K16: Text, up to 60; Free text | L16: Text, up to 120; name@domain | M16: Text, up to 30; 09xxxxxxxxx | N16: Flag, up to 1; Y or N
A17: Allowed values | B17: legacy_client_no of C01 | C17: ADDRESS, CONTACT (list C02 record_type) | D17: A whole number | E17: HOME, BUSINESS, MAILING, BILLING (list C02 address_type) | F17: Free entry, up to 300 characters | G17: Free entry, up to 80 characters | H17: Free entry, up to 80 characters | I17: Free entry, up to 10 characters | J17: Free entry, up to 200 characters | K17: Free entry, up to 60 characters | L17: Free entry, up to 120 characters | M17: Free entry, up to 30 characters | N17: Y or N
A18: What to enter | B18: Client number in the source system | C18: Address or contact person | D18: Sequence within the client and record type | E18: Kind of address | F18: Street address | G18: City / municipality | H18: Province | I18: Postal code | J18: Contact person (corporate clients) | K18: Role of the contact | L18: E-mail | M18: Mobile number | N18: Primary address or contact
A19: Row | B19: legacy_client_no * | C19: record_type * | D19: seq_no * | E19: address_type | F19: address_line | G19: city | H19: province | I19: postal_code | J19: contact_name | K19: contact_role | L19: email | M19: mobile | N19: primary_flag *
A20: Example – overwrite or delete | B20: Q-0012345 | C20: ADDRESS | D20: 1 | E20: MAILING | F20: 12 Rizal St., Brgy. San Antonio | G20: Pasig | H20: Metro Manila | I20: 1600 | J20: Jose Santos | K20: HR Manager | L20: jose.santos@acme.example | M20: 09181234567 | N20: Y

Sheet C03 Client payout accounts
A1: C03 Client payout accounts | G1: Step 14 of 29
A2: ← Back to Load templates | B2: Step 14 of 29. Fill in one row per record below the column headers; the guide above each column says what to enter. | G2: Ask a question →
A3: Purpose | B3: One row per record of Client payout accounts (for refunds) as extracted from EBIX. Key legacy_client_no, account_no. Sent as the file C03_template.csv (CSV, header row as below) with its control file (row count, row count).
A4: Provided by | B4: Disbursement data steward (to name); approved by Product Owner, Comptrollership - Disbursement; extracted by BDOI IT
A5: Due | B5: M3 (29 Jan 2027)
A6: How it is loaded | B6: Data migration object C03 (Migrate), layout C03 version 1, through the Migration Console; lands in: Client payout accounts
A7: Source | B7: EBIX
A8: Depends on | B8: C01 Client master → | D8: C02 Client addresses and contacts →
A9: Progress | B9: Rows entered | C9: =SUMPRODUCT(((ROW($B$20:$B$220)>20)+($B$20<>"E-0098765")>0)*(LEN($B$20:$B$220&$C$20:$C$220&$D$20:$D$220&$E$20:$E$220&$F$20:$F$220&$G$20:$G$220)>0)) | D9: Mandatory cells missing | E9: =SUMPRODUCT(((ROW($B$20:$B$220)>20)+($B$20<>"E-0098765")>0)*(LEN($B$20:$B$220&$C$20:$C$220&$D$20:$D$220&$E$20:$E$220&$F$20:$F$220&$G$20:$G$220)>0)*(($B$20:$B$220="")+($C$20:$C$220="")+($D$20:$D$220="")+($G$20:$G$220="")))
A10: Reviewed by (BU reviewer) | D10: Review date
A12: BU review
A13: BU comment
A14: Check when loaded | B14: Client loaded | C14: In the list | D14: Not blank | E14: Mandatory for CTA; mapped | F14: Mandatory for CTA | G14: Y or N
A15: Mandatory | B15: Yes | C15: Yes | D15: Yes | E15: Conditional: Mandatory for CTA; mapped | F15: Conditional: Mandatory for CTA | G15: Yes
A16: Format | B16: Code, up to 30; As stored in legacy | C16: Code, up to 10; Upper case | D16: Text, up to 250; Free text | E16: Code, up to 30; As stored in legacy | F16: Text, up to 40; Digits | G16: Flag, up to 1; Y or N
A17: Allowed values | B17: legacy_client_no of C01 | C17: CTA, CHECK (list C03 mode) | D17: Free entry, up to 250 characters | E17: The legacy code; mapped by the code map BANK (sheet Code maps) | F17: Free entry, up to 40 characters | G17: Y or N
A18: What to enter | B18: Client number in the source system | C18: Payout mode | D18: Name on the account or check | E18: Bank of the account | F18: Account number | G18: Account in use
A19: Row | B19: legacy_client_no * | C19: mode * | D19: payee_name * | E19: bank_code | F19: account_no | G19: active_flag *
A20: Example – overwrite or delete | B20: E-0098765 | C20: CTA | D20: Ana C. Reyes | E20: BDO | F20: 001234567890 | G20: Y

Sheet P01 In-force policy headers
A1: P01 In-force policy headers | AF1: Step 15 of 29
A2: ← Back to Load templates | B2: Step 15 of 29. Fill in one row per record below the column headers; the guide above each column says what to enter. | AF2: Ask a question →
A3: Purpose | B3: One row per record of In-force policy headers as extracted from QPS, EBIX. Key legacy_policy_ref. Sent as the file P01_template.csv (CSV, header row as below) with its control file (row count, count of distinct keys; amount totals per currency: sum_insured, gross_premium, net_premium).
A4: Provided by | B4: Operations data steward (to name); approved by Head, Operations; extracted by BDOI IT
A5: Due | B5: M3 (29 Jan 2027); final at T-2
A6: How it is loaded | B6: Data migration object P01 (Conditional), layout P01 version 1, through the Migration Console; lands in: Accounts, imported as legacy policy headers
A7: Source | B7: QPS, EBIX
A8: Depends on | B8: C01 Client master → | D8: C02 Client addresses and contacts → | F8: R04 Insurers → | H8: R04B Insurer branches → | J8: R05 Product lines, cover types, products and risk codes →
A9: Progress | B9: Rows entered | C9: =SUMPRODUCT(((ROW($B$20:$B$220)>20)+($B$20<>"C-2026-004512-01")>0)*(LEN($B$20:$B$220&$C$20:$C$220&$D$20:$D$220&$E$20:$E$220&$F$20:$F$220&$G$20:$G$220&$H$20:$H$220&$I$20:$I$220&$J$20:$J$220&$K$20:$K$220&$L$20:$L$220&$M$20:$M$220&$N$20:$N$220&$O$20:$O$220&$P$20:$P$220&$Q$20:$Q$220&$R$20:$R$220&$S$20:$S$220&$T$20:$T$220&$U$20:$U$220&$V$20:$V$220&$W$20:$W$220&$X$20:$X$220&$Y$20:$Y$220&$Z$20:$Z$220&$AA$20:$AA$220&$AB$20:$AB$220&$AC$20:$AC$220&$AD$20:$AD$220&$AE$20:$AE$220&$AF$20:$AF$220)>0)) | D9: Mandatory cells missing | E9: =SUMPRODUCT(((ROW($B$20:$B$220)>20)+($B$20<>"C-2026-004512-01")>0)*(LEN($B$20:$B$220&$C$20:$C$220&$D$20:$D$220&$E$20:$E$220&$F$20:$F$220&$G$20:$G$220&$H$20:$H$220&$I$20:$I$220&$J$20:$J$220&$K$20:$K$220&$L$20:$L$220&$M$20:$M$220&$N$20:$N$220&$O$20:$O$220&$P$20:$P$220&$Q$20:$Q$220&$R$20:$R$220&$S$20:$S$220&$T$20:$T$220&$U$20:$U$220&$V$20:$V$220&$W$20:$W$220&$X$20:$X$220&$Y$20:$Y$220&$Z$20:$Z$220&$AA$20:$AA$220&$AB$20:$AB$220&$AC$20:$AC$220&$AD$20:$AD$220&$AE$20:$AE$220&$AF$20:$AF$220)>0)*(($B$20:$B$220="")+($C$20:$C$220="")+($E$20:$E$220="")+($F$20:$F$220="")+($G$20:$G$220="")+($H$20:$H$220="")+($K$20:$K$220="")+($M$20:$M$220="")+($N$20:$N$220="")+($O$20:$O$220="")+($P$20:$P$220="")+($Q$20:$Q$220="")+($R$20:$R$220="")+($S$20:$S$220="")+($T$20:$T$220="")+($V$20:$V$220="")+($AA$20:$AA$220="")+($AB$20:$AB$220="")+($AC$20:$AC$220="")+($AD$20:$AD$220="")))
A10: Reviewed by (BU reviewer) | D10: Review date
A12: BU review
A13: BU comment
A14: Check when loaded | B14: Unique in the file | C14: Not blank | D14: 0 or more | E14: Not blank | F14: Client loaded | G14: Not blank | H14: Mapped | I14: Mandatory for packaged policies; not mapped at load | J14: Mandatory with package_code | K14: Mapped; consistent with risk_code | L14: Mapped | M14: In the list | N14: Mapped to an in-force status | O14: Valid date | P14: After inception_date; on or after the cutover date; every expiry to 31-May-2028 present (go-live renewal extraction) | Q14: Valid code | R14: 0 or more | S14: 0 or more | T14: Not below net_premium | U14: 0 to 100 | V14: In the list | W14: - | X14: - | Y14: Mapped | Z14: Y or N | AA14: Mapped in USER | AB14: Mapped | AC14: Mapped | AD14: Mapped | AE14: Mapped | AF14: -
A15: Mandatory | B15: Yes | C15: Yes | D15: No | E15: Yes | F15: Yes | G15: Yes | H15: Yes | I15: Conditional: Mandatory for packaged policies; not mapped at load | J15: Conditional: Mandatory with package_code | K15: Yes | L15: No | M15: Yes | N15: Yes | O15: Yes | P15: Yes | Q15: Yes | R15: Yes | S15: Yes | T15: Yes | U15: No | V15: Yes | W15: No | X15: No | Y15: No | Z15: No | AA15: Yes | AB15: Yes | AC15: Yes | AD15: Yes | AE15: No | AF15: No
A16: Format | B16: Code, up to 60; <cover no.>-<version> | C16: Text, up to 40; As stored in legacy | D16: Integer, up to 4; Digits | E16: Text, up to 60; As issued | F16: Code, up to 30; As stored in legacy | G16: Text, up to 250; Free text | H16: Code, up to 20; As stored in legacy | I16: Code, up to 20; As stored in legacy | J16: Integer, up to 4; Digits | K16: Code, up to 30; As stored in legacy | L16: Code, up to 30; As stored in legacy | M16: Code, up to 2; Upper case | N16: Code, up to 20; As stored in legacy | O16: Date, up to 10; yyyy-MM-dd | P16: Date, up to 10; yyyy-MM-dd | Q16: Code, up to 3; Upper case | R16: Amount, up to 19,2; Dot decimal, 2 decimals | S16: Amount, up to 19,2; Dot decimal, 2 decimals | T16: Amount, up to 19,2; Dot decimal, 2 decimals | U16: Decimal, up to 9,4; Dot decimal | V16: Code, up to 20; Upper case | W16: Text, up to 500; PN;PN | X16: Text, up to 40; As stored in legacy | Y16: Code, up to 40; As stored in legacy | Z16: Flag, up to 1; Y or N | AA16: Code, up to 50; As stored in legacy | AB16: Code, up to 20; As stored in legacy | AC16: Code, up to 20; As stored in legacy | AD16: Code, up to 40; As stored in legacy | AE16: Code, up to 40; As stored in legacy | AF16: Text, up to 300; Free text
A17: Allowed values | B17: Free entry, up to 60 characters | C17: Free entry, up to 40 characters | D17: A whole number | E17: Free entry, up to 60 characters | F17: legacy_client_no of C01 | G17: Free entry, up to 250 characters | H17: The legacy code; mapped by the code map PRODUCT (sheet Code maps) | I17: Free entry, up to 20 characters | J17: A whole number | K17: The legacy code; mapped by the code map LINE (sheet Code maps) | L17: The legacy code; mapped by the code map COVER_TYPE (sheet Code maps) | M17: NB, RB (list P01 business_type) | N17: The legacy code; mapped by the code map STATUS:POLICY (sheet Code maps) | O17: Free entry | P17: Free entry | Q17: ISO 4217 | R17: A number | S17: A number | T17: A number | U17: A number | V17: VIA_BDOI, DIRECT (list P01 payment_arrangement) | W17: Free entry, up to 500 characters | X17: Free entry, up to 40 characters | Y17: The legacy code; mapped by the code map BANK (sheet Code maps) | Z17: Y or N | AA17: The legacy code; mapped by the code map USER (sheet Code maps) | AB17: The legacy code; mapped by the code map SALES_UNIT (sheet Code maps) | AC17: The legacy code; mapped by the code map BRANCH (sheet Code maps) | AD17: The legacy code; mapped by the code map LOV:MARKET_SEGMENT (sheet Code maps) | AE17: The legacy code; mapped by the code map MIS:BUSINESS_ORIGIN (sheet Code maps) | AF17: Free entry, up to 300 characters
A18: What to enter | B18: Unique legacy reference of the policy term (cover no. and version, or policy reference) | C18: Legacy cover number | D18: Legacy cover version | E18: Insurer policy number | F18: Client number of the assured | G18: Assured name as on the policy | H18: Product / risk code | I18: Legacy package of a packaged policy | J18: Version of the legacy package | K18: Line of business | L18: Cover type | M18: New business or renewal | N18: Status of the term in legacy | O18: Period from | P18: Period to | Q18: Policy currency | R18: Total sum insured | S18: Basic premium | T18: Gross premium including taxes and charges | U18: Commission rate in percent | V18: Premium paid through BDOI or directly to the insurer | W18: Loan promissory note numbers, separated by semicolons | X18: Loan application number | Y18: Mortgagee | Z18: Free first year | AA18: Account officer | AB18: Sales team | AC18: Branch | AD18: Market segment | AE18: Business origin / channel | AF18: Short risk description (vehicle, location)
A19: Row | B19: legacy_policy_ref * | C19: cover_no * | D19: cover_version | E19: policy_no * | F19: legacy_client_no * | G19: assured_name * | H19: risk_code * | I19: package_code | J19: package_version | K19: line_code * | L19: cover_type_code | M19: business_type * | N19: policy_status * | O19: inception_date * | P19: expiry_date * | Q19: currency * | R19: sum_insured * | S19: net_premium * | T19: gross_premium * | U19: commission_rate_pct | V19: payment_arrangement * | W19: pn_nos | X19: loan_application_no | Y19: mortgagee_bank | Z19: ffy_flag | AA19: ao_user_id * | AB19: sales_unit_code * | AC19: branch_code * | AD19: market_segment * | AE19: source_channel | AF19: risk_description
A20: Example – overwrite or delete | B20: C-2026-004512-01 | C20: C-2026-004512 | D20: 1 | E20: MC-PC-26-0012345 | F20: Q-0012345 | G20: Ana C. Reyes | H20: MC-PC-COMP | I20: PKG-MC-PRIV | J20: 3 | K20: MOTOR | L20: COMP | M20: RB | N20: ISSUED | O20: 2027-03-15 | P20: 2028-03-15 | Q20: PHP | R20: 950000 | S20: 21375 | T20: 25946.25 | U20: 20 | V20: VIA_BDOI | W20: PN-2019-000123 | X20: LA-2019-5566 | Y20: BDO | Z20: N | AA20: mreyes | AB20: T-RET-07 | AC20: MKT01 | AD20: CBG | AE20: BANK_REFERRAL | AF20: 2022 Toyota Vios ABC 1234

Sheet P01S Policy insurer shares
A1: P01S Policy insurer shares | G1: Step 16 of 29
A2: ← Back to Load templates | B2: Step 16 of 29. Fill in one row per record below the column headers; the guide above each column says what to enter. | G2: Ask a question →
A3: Purpose | B3: One row per record of In-force policy headers as extracted from QPS, EBIX. Key legacy_policy_ref, share_seq. Sent as the file P01S_template.csv (CSV, header row as below) with its control file (row count, row count).
A4: Provided by | B4: Operations data steward (to name); approved by Head, Operations; extracted by BDOI IT
A5: Due | B5: M3 (29 Jan 2027); final at T-2
A6: How it is loaded | B6: Data migration object P01 (Conditional), layout P01S version 1, through the Migration Console; lands in: Accounts, imported as legacy policy headers
A7: Source | B7: QPS, EBIX
A8: Depends on | B8: P01 In-force policy headers → | D8: C01 Client master → | F8: C02 Client addresses and contacts →
A9: Progress | B9: Rows entered | C9: =SUMPRODUCT(((ROW($B$20:$B$220)>20)+($B$20<>"C-2026-004512-01")>0)*(LEN($B$20:$B$220&$C$20:$C$220&$D$20:$D$220&$E$20:$E$220&$F$20:$F$220&$G$20:$G$220)>0)) | D9: Mandatory cells missing | E9: =SUMPRODUCT(((ROW($B$20:$B$220)>20)+($B$20<>"C-2026-004512-01")>0)*(LEN($B$20:$B$220&$C$20:$C$220&$D$20:$D$220&$E$20:$E$220&$F$20:$F$220&$G$20:$G$220)>0)*(($B$20:$B$220="")+($C$20:$C$220="")+($D$20:$D$220="")+($F$20:$F$220="")+($G$20:$G$220="")))
A10: Reviewed by (BU reviewer) | D10: Review date
A12: BU review
A13: BU comment
A14: Check when loaded | B14: Exists in P01 | C14: Unique per policy | D14: Mapped | E14: Mapped | F14: Above 0; shares of a policy add to 100 | G14: One lead per policy
A15: Mandatory | B15: Yes | C15: Yes | D15: Yes | E15: No | F15: Yes | G15: Yes
A16: Format | B16: Code, up to 60; As in P01 | C16: Integer, up to 2; Digits | D16: Code, up to 30; As stored in legacy | E16: Code, up to 20; As stored in legacy | F16: Decimal, up to 9,4; Dot decimal | G16: Flag, up to 1; Y or N
A17: Allowed values | B17: legacy_policy_ref of P01 | C17: A whole number | D17: The legacy code; mapped by the code map INSURER (sheet Code maps) | E17: The legacy code; mapped by the code map INSURER_BRANCH (sheet Code maps) | F17: A number | G17: Y or N
A18: What to enter | B18: Legacy reference of the policy term | C18: Sequence of the insurer | D18: Insurer | E18: Insurer branch | F18: Share in percent | G18: Lead insurer
A19: Row | B19: legacy_policy_ref * | C19: share_seq * | D19: insurer_code * | E19: insurer_branch_code | F19: share_pct * | G19: lead_flag *
A20: Example – overwrite or delete | B20: C-2026-004512-01 | C20: 1 | D20: MAL | E20: MAL-CEB | F20: 100 | G20: Y

Sheet F01 Open legacy invoices - head
A1: F01 Open legacy invoices - header | AM1: Step 17 of 29
A2: ← Back to Load templates | B2: Step 17 of 29. Fill in one row per record below the column headers; the guide above each column says what to enter. | AM2: Ask a question →
A3: Purpose | B3: One row per record of Open legacy invoices (premium receivable, paid not remitted, commission receivable, PR2307), with components and insurer shares as extracted from EBIX, QPS. Key legacy_invoice_no. Sent as the file F01_template.csv (CSV, header row as below) with its control file (row count, count of distinct keys; amount totals per currency: gross_premium, commission, vat_on_commission).
A4: Provided by | B4: Operations data steward (to name); approved by Operations - Financial Transactions; Head, Comptrollership; extracted by BDOI IT
A5: Due | B5: M3 (29 Jan 2027); final at T-2
A6: How it is loaded | B6: Data migration object F01 (Carry forward), layout F01 version 1, through the Migration Console; lands in: Operations invoice ledger (invoices, insurer shares, components) with an opening accounting entry on the legacy sub-ledgers
A7: Source | B7: EBIX, QPS
A8: Depends on | B8: C01 Client master → | D8: C02 Client addresses and contacts → | F8: R04 Insurers → | H8: R04B Insurer branches → | J8: R05 Product lines, cover types, products and risk codes → | L8: P01 In-force policy headers → | N8: P01S Policy insurer shares →
A9: Progress | B9: Rows entered | C9: =SUMPRODUCT(((ROW($B$20:$B$220)>20)+($B$20<>"I00123456")>0)*(LEN($B$20:$B$220&$C$20:$C$220&$D$20:$D$220&$E$20:$E$220&$F$20:$F$220&$G$20:$G$220&$H$20:$H$220&$I$20:$I$220&$J$20:$J$220&$K$20:$K$220&$L$20:$L$220&$M$20:$M$220&$N$20:$N$220&$O$20:$O$220&$P$20:$P$220&$Q$20:$Q$220&$R$20:$R$220&$S$20:$S$220&$T$20:$T$220&$U$20:$U$220&$V$20:$V$220&$W$20:$W$220&$X$20:$X$220&$Y$20:$Y$220&$Z$20:$Z$220&$AA$20:$AA$220&$AB$20:$AB$220&$AC$20:$AC$220&$AD$20:$AD$220&$AE$20:$AE$220&$AF$20:$AF$220&$AG$20:$AG$220&$AH$20:$AH$220&$AI$20:$AI$220&$AJ$20:$AJ$220&$AK$20:$AK$220&$AL$20:$AL$220&$AM$20:$AM$220)>0)) | D9: Mandatory cells missing | E9: =SUMPRODUCT(((ROW($B$20:$B$220)>20)+($B$20<>"I00123456")>0)*(LEN($B$20:$B$220&$C$20:$C$220&$D$20:$D$220&$E$20:$E$220&$F$20:$F$220&$G$20:$G$220&$H$20:$H$220&$I$20:$I$220&$J$20:$J$220&$K$20:$K$220&$L$20:$L$220&$M$20:$M$220&$N$20:$N$220&$O$20:$O$220&$P$20:$P$220&$Q$20:$Q$220&$R$20:$R$220&$S$20:$S$220&$T$20:$T$220&$U$20:$U$220&$V$20:$V$220&$W$20:$W$220&$X$20:$X$220&$Y$20:$Y$220&$Z$20:$Z$220&$AA$20:$AA$220&$AB$20:$AB$220&$AC$20:$AC$220&$AD$20:$AD$220&$AE$20:$AE$220&$AF$20:$AF$220&$AG$20:$AG$220&$AH$20:$AH$220&$AI$20:$AI$220&$AJ$20:$AJ$220&$AK$20:$AK$220&$AL$20:$AL$220&$AM$20:$AM$220)>0)*(($B$20:$B$220="")+($C$20:$C$220="")+($G$20:$G$220="")+($I$20:$I$220="")+($J$20:$J$220="")+($L$20:$L$220="")+($N$20:$N$220="")+($O$20:$O$220="")+($P$20:$P$220="")+($Q$20:$Q$220="")+($R$20:$R$220="")+($S$20:$S$220="")+($T$20:$T$220="")+($U$20:$U$220="")+($V$20:$V$220="")+($W$20:$W$220="")+($X$20:$X$220="")+($AA$20:$AA$220="")+($AB$20:$AB$220="")+($AC$20:$AC$220="")+($AD$20:$AD$220="")+($AE$20:$AE$220="")+($AG$20:$AG$220="")+($AH$20:$AH$220="")))
A10: Reviewed by (BU reviewer) | D10: Review date
A12: BU review
A13: BU comment
A14: Check when loaded | B14: Unique across EBIX and QPS | C14: In the list | D14: Mandatory for ENDORSEMENT_PLUS, ENDORSEMENT_MINUS and CANCELLATION; parent in the file or loaded | E14: - | F14: Mandatory when P01 is in scope; exists in P01 | G14: Not blank | H14: 1 or more | I14: Client loaded | J14: Not blank | K14: - | L14: Valid code | M14: Mandatory when currency is not PHP | N14: Before the cutover date | O14: Before the cutover date | P14: Valid date | Q14: Valid date | R14: On or after inception_date | S14: Mapped | T14: Mapped | U14: Mapped | V14: Mapped in USER | W14: Mapped | X14: Mapped | Y14: Mapped | Z14: - | AA14: =sum of F01C booked for BASIC, DST, PREMIUM_TAX_VAT, LGT, FST, OTHER | AB14: =F01C booked COMMISSION | AC14: =F01C booked COMMISSION_VAT | AD14: 0 to 100 | AE14: 0 to commission | AF14: 0 to vat_on_commission | AG14: Y or N | AH14: Y or N | AI14: Y or N | AJ14: Y or N | AK14: - | AL14: Not after the freeze | AM14: -
A15: Mandatory | B15: Yes | C15: Yes | D15: Conditional: Mandatory for ENDORSEMENT_PLUS, ENDORSEMENT_MINUS and CANCELLATION; parent in the file or loaded | E15: No | F15: Conditional: Mandatory when P01 is in scope; exists in P01 | G15: Yes | H15: No | I15: Yes | J15: Yes | K15: No | L15: Yes | M15: Conditional: Mandatory when currency is not PHP | N15: Yes | O15: Yes | P15: Yes | Q15: Yes | R15: Yes | S15: Yes | T15: Yes | U15: Yes | V15: Yes | W15: Yes | X15: Yes | Y15: No | Z15: No | AA15: Yes | AB15: Yes | AC15: Yes | AD15: Yes | AE15: Yes | AF15: No | AG15: Yes | AH15: Yes | AI15: No | AJ15: No | AK15: No | AL15: No | AM15: No
A16: Format | B16: Code, up to 40; EBIX I######## | C16: Code, up to 20; Upper case | D16: Code, up to 40; As stored in legacy | E16: Text, up to 40; As stored in legacy | F16: Code, up to 60; As in P01 | G16: Text, up to 60; As issued | H16: Integer, up to 2; Digits | I16: Code, up to 30; As stored in legacy | J16: Text, up to 250; Free text | K16: Text, up to 250; Free text | L16: Code, up to 3; Upper case | M16: Decimal, up to 12,6; Dot decimal | N16: Date, up to 10; yyyy-MM-dd | O16: Date, up to 10; yyyy-MM-dd | P16: Date, up to 10; yyyy-MM-dd | Q16: Date, up to 10; yyyy-MM-dd | R16: Date, up to 10; yyyy-MM-dd | S16: Code, up to 20; As stored in legacy | T16: Code, up to 30; As stored in legacy | U16: Code, up to 40; As stored in legacy | V16: Code, up to 50; As stored in legacy | W16: Code, up to 20; As stored in legacy | X16: Code, up to 20; As stored in legacy | Y16: Code, up to 20; As stored in legacy | Z16: Text, up to 500; PN;PN | AA16: Amount, up to 19,2; Dot decimal, 2 decimals; minus for return invoices | AB16: Amount, up to 19,2; Dot decimal, 2 decimals | AC16: Amount, up to 19,2; Dot decimal, 2 decimals | AD16: Decimal, up to 9,4; Dot decimal | AE16: Amount, up to 19,2; Dot decimal, 2 decimals | AF16: Amount, up to 19,2; Dot decimal, 2 decimals | AG16: Flag, up to 1; Y or N | AH16: Flag, up to 1; Y or N | AI16: Flag, up to 1; Y or N | AJ16: Flag, up to 1; Y or N | AK16: Text, up to 40; As printed | AL16: Date, up to 10; yyyy-MM-dd | AM16: Text, up to 500; Free text
A17: Allowed values | B17: Free entry, up to 40 characters | C17: BOOKING, ENDORSEMENT_PLUS, ENDORSEMENT_MINUS, CANCELLATION (list F01 invoice_kind) | D17: legacy_invoice_no values | E17: Free entry, up to 40 characters | F17: legacy_policy_ref of P01 | G17: Free entry, up to 60 characters | H17: A whole number | I17: legacy_client_no of C01 | J17: Free entry, up to 250 characters | K17: Free entry, up to 250 characters | L17: ISO 4217 | M17: A number | N17: Free entry | O17: Free entry | P17: Free entry | Q17: Free entry | R17: Free entry | S17: The legacy code; mapped by the code map PRODUCT (sheet Code maps) | T17: The legacy code; mapped by the code map LINE (sheet Code maps) | U17: The legacy code; mapped by the code map LOV:MARKET_SEGMENT (sheet Code maps) | V17: The legacy code; mapped by the code map USER (sheet Code maps) | W17: The legacy code; mapped by the code map SALES_UNIT (sheet Code maps) | X17: The legacy code; mapped by the code map BRANCH (sheet Code maps) | Y17: The legacy code; mapped by the code map COST_CENTER (sheet Code maps) | Z17: Free entry, up to 500 characters | AA17: A number | AB17: A number | AC17: A number | AD17: A number | AE17: A number | AF17: A number | AG17: Y or N | AH17: Y or N | AI17: Y or N | AJ17: Y or N | AK17: Free entry, up to 40 characters | AL17: Free entry | AM17: Free entry, up to 500 characters
A18: What to enter | B18: Invoice number in the source system | C18: Kind of invoice | D18: Original invoice of an endorsement or cancellation invoice | E18: Legacy endorsement number | F18: Legacy reference of the policy term | G18: Insurer policy number | H18: Year of a multi-year policy | I18: Client number of the assured | J18: Assured name on the invoice | K18: Payor if not the assured | L18: Invoice currency | M18: Exchange rate used at booking (foreign currency) | N18: Legacy booking date | O18: Invoice date | P18: Due date | Q18: Period from | R18: Period to | S18: Product / risk code | T18: Line of business | U18: Market segment | V18: Account officer | W18: Sales team | X18: Invoicing branch | Y18: Cost centre | Z18: Loan PN numbers, separated by semicolons | AA18: Gross premium of the invoice (sum of the six premium components) | AB18: Commission of the invoice | AC18: VAT on commission | AD18: Withholding tax rate on commission, in percent | AE18: Commission already realised (recognised as income) in legacy | AF18: Output VAT on commission still deferred | AG18: Direct-payment invoice (premium paid to the insurer) | AH18: Client withholds 2% (BIR 2307) | AI18: Counts for incentive programmes | AJ18: Remittance on hold in legacy | AK18: Legacy service invoice issued for the commission | AL18: Date of the last payment applied in legacy | AM18: Legacy remarks
A19: Row | B19: legacy_invoice_no * | C19: invoice_kind * | D19: parent_invoice_no | E19: endorsement_no | F19: legacy_policy_ref | G19: policy_no * | H19: policy_year | I19: legacy_client_no * | J19: assured_name * | K19: payor_name | L19: currency * | M19: booking_fx_rate | N19: booking_date * | O19: invoice_date * | P19: due_date * | Q19: inception_date * | R19: expiry_date * | S19: risk_code * | T19: line_code * | U19: market_segment * | V19: ao_user_id * | W19: sales_unit_code * | X19: branch_code * | Y19: cost_center | Z19: pn_nos | AA19: gross_premium * | AB19: commission * | AC19: vat_on_commission * | AD19: wtax_rate_pct * | AE19: commission_realised * | AF19: deferred_vat_open | AG19: dp_flag * | AH19: cwt_flag * | AI19: incentive_eligible_flag | AJ19: hold_flag | AK19: legacy_service_invoice_no | AL19: last_payment_date | AM19: remarks
A20: Example – overwrite or delete | B20: I00123456 | C20: BOOKING | D20: I00119876 | E20: END-2026-0456 | F20: C-2026-004512-01 | G20: MC-PC-26-0012345 | H20: 1 | I20: Q-0012345 | J20: Ana C. Reyes | K20: BDO Unibank - Auto Loans | L20: PHP | M20: 56.125 | N20: 2027-03-10 | O20: 2027-03-10 | P20: 2027-04-09 | Q20: 2027-03-15 | R20: 2028-03-15 | S20: MC-PC-COMP | T20: MOTOR | U20: CBG | V20: mreyes | W20: T-RET-07 | X20: MKT01 | Y20: 4100 | Z20: PN-2019-000123 | AA20: 25946.25 | AB20: 4275 | AC20: 513 | AD20: 10 | AE20: 1710 | AF20: 307.8 | AG20: N | AH20: N | AI20: N | AJ20: N | AK20: SI-000456789 | AL20: 2027-05-02 | AM20: Balance under dispute

Sheet F01C Open legacy invoices - com
A1: F01C Open legacy invoices - components and positions | I1: Step 18 of 29
A2: ← Back to Load templates | B2: Step 18 of 29. Fill in one row per record below the column headers; the guide above each column says what to enter. | I2: Ask a question →
A3: Purpose | B3: One row per record of Open legacy invoices (premium receivable, paid not remitted, commission receivable, PR2307), with components and insurer shares as extracted from EBIX, QPS. Key legacy_invoice_no, component. Sent as the file F01C_template.csv (CSV, header row as below) with its control file (row count, row count; amount totals per currency: booked, adjusted, paid, remitted, written_off, open_balance).
A4: Provided by | B4: Operations data steward (to name); approved by Operations - Financial Transactions; Head, Comptrollership; extracted by BDOI IT
A5: Due | B5: M3 (29 Jan 2027); final at T-2
A6: How it is loaded | B6: Data migration object F01 (Carry forward), layout F01C version 1, through the Migration Console; lands in: Operations invoice ledger (invoices, insurer shares, components) with an opening accounting entry on the legacy sub-ledgers
A7: Source | B7: EBIX, QPS
A8: Depends on | B8: F01 Open legacy invoices - header → | D8: C01 Client master → | E8: C02 Client addresses and contacts → | G8: R04 Insurers → | I8: R04B Insurer branches →
A9: Progress | B9: Rows entered | C9: =SUMPRODUCT(((ROW($B$20:$B$220)>20)+($B$20<>"I00123456")>0)*(LEN($B$20:$B$220&$C$20:$C$220&$D$20:$D$220&$E$20:$E$220&$F$20:$F$220&$G$20:$G$220&$H$20:$H$220&$I$20:$I$220)>0)) | D9: Mandatory cells missing | E9: =SUMPRODUCT(((ROW($B$20:$B$220)>20)+($B$20<>"I00123456")>0)*(LEN($B$20:$B$220&$C$20:$C$220&$D$20:$D$220&$E$20:$E$220&$F$20:$F$220&$G$20:$G$220&$H$20:$H$220&$I$20:$I$220)>0)*(($B$20:$B$220="")+($C$20:$C$220="")+($D$20:$D$220="")+($E$20:$E$220="")+($F$20:$F$220="")+($G$20:$G$220="")+($H$20:$H$220="")+($I$20:$I$220="")))
A10: Reviewed by (BU reviewer) | D10: Review date
A12: BU review
A13: BU comment
A14: Check when loaded | B14: Exists in F01 | C14: In the list; one row per component and invoice | D14: Same sign as the invoice | E14: - | F14: 0 for DTIP, COMMISSION, COMMISSION_VAT, WTAX | G14: 0 for premium components | H14: - | I14: Premium components and PR2307 = booked + adjusted - paid - written_off; DTIP, COMMISSION, COMMISSION_VAT, WTAX = booked + adjusted - remitted - written_off; within 0 and booked + adjusted
A15: Mandatory | B15: Yes | C15: Yes | D15: Yes | E15: Yes | F15: Yes | G15: Yes | H15: Yes | I15: Yes
A16: Format | B16: Code, up to 40; As in F01 | C16: Code, up to 20; Upper case | D16: Amount, up to 19,2; Dot decimal, 2 decimals; minus for return invoices | E16: Amount, up to 19,2; Dot decimal, 2 decimals | F16: Amount, up to 19,2; Dot decimal, 2 decimals | G16: Amount, up to 19,2; Dot decimal, 2 decimals | H16: Amount, up to 19,2; Dot decimal, 2 decimals | I16: Amount, up to 19,2; Dot decimal, 2 decimals
A17: Allowed values | B17: legacy_invoice_no of F01 | C17: List F01C component: 11 values, see Reference lists | D17: A number | E17: A number | F17: A number | G17: A number | H17: A number | I17: A number
A18: What to enter | B18: Invoice number in the source system | C18: Premium or settlement component | D18: Amount booked in legacy | E18: Net legacy adjustments kept on the same invoice | F18: Paid by the client before cutover (premium components and PR2307) | G18: Settled with the insurer before cutover (DTIP, commission, VAT on commission, WTAX) | H18: Written off or DP-reversed before cutover | I18: Open balance at the freeze
A19: Row | B19: legacy_invoice_no * | C19: component * | D19: booked * | E19: adjusted * | F19: paid * | G19: remitted * | H19: written_off * | I19: open_balance *
A20: Example – overwrite or delete | B20: I00123456 | C20: BASIC | D20: 21375 | E20: 0 | F20: 8550 | G20: 0 | H20: 0 | I20: 12825

Sheet F01S Open legacy invoices - ins
A1: F01S Open legacy invoices - insurer shares | G1: Step 19 of 29
A2: ← Back to Load templates | B2: Step 19 of 29. Fill in one row per record below the column headers; the guide above each column says what to enter. | G2: Ask a question →
A3: Purpose | B3: One row per record of Open legacy invoices (premium receivable, paid not remitted, commission receivable, PR2307), with components and insurer shares as extracted from EBIX, QPS. Key legacy_invoice_no, share_seq. Sent as the file F01S_template.csv (CSV, header row as below) with its control file (row count, row count).
A4: Provided by | B4: Operations data steward (to name); approved by Operations - Financial Transactions; Head, Comptrollership; extracted by BDOI IT
A5: Due | B5: M3 (29 Jan 2027); final at T-2
A6: How it is loaded | B6: Data migration object F01 (Carry forward), layout F01S version 1, through the Migration Console; lands in: Operations invoice ledger (invoices, insurer shares, components) with an opening accounting entry on the legacy sub-ledgers
A7: Source | B7: EBIX, QPS
A8: Depends on | B8: F01 Open legacy invoices - header → | D8: C01 Client master → | F8: C02 Client addresses and contacts →
A9: Progress | B9: Rows entered | C9: =SUMPRODUCT(((ROW($B$20:$B$220)>20)+($B$20<>"I00123456")>0)*(LEN($B$20:$B$220&$C$20:$C$220&$D$20:$D$220&$E$20:$E$220&$F$20:$F$220)>0)) | D9: Mandatory cells missing | E9: =SUMPRODUCT(((ROW($B$20:$B$220)>20)+($B$20<>"I00123456")>0)*(LEN($B$20:$B$220&$C$20:$C$220&$D$20:$D$220&$E$20:$E$220&$F$20:$F$220)>0)*(($B$20:$B$220="")+($C$20:$C$220="")+($D$20:$D$220="")+($E$20:$E$220="")+($F$20:$F$220="")))
A10: Reviewed by (BU reviewer) | D10: Review date
A12: BU review
A13: BU comment
A14: Check when loaded | B14: Exists in F01 | C14: Unique per invoice | D14: Mapped | E14: Above 0 and at most 100; shares of an invoice add to 100 | F14: One lead per invoice
A15: Mandatory | B15: Yes | C15: Yes | D15: Yes | E15: Yes | F15: Yes
A16: Format | B16: Code, up to 40; As in F01 | C16: Integer, up to 2; Digits | D16: Code, up to 30; As stored in legacy | E16: Decimal, up to 9,4; Dot decimal | F16: Flag, up to 1; Y or N
A17: Allowed values | B17: legacy_invoice_no of F01 | C17: A whole number | D17: The legacy code; mapped by the code map INSURER (sheet Code maps) | E17: A number | F17: Y or N
A18: What to enter | B18: Invoice number in the source system | C18: Sequence of the insurer | D18: Insurer | E18: Share in percent | F18: Lead insurer
A19: Row | B19: legacy_invoice_no * | C19: share_seq * | D19: insurer_code * | E19: share_pct * | F19: lead_flag *
A20: Example – overwrite or delete | B20: I00123456 | C20: 1 | D20: MAL | E20: 100 | F20: Y

Sheet F02 Unapplied premium payments
A1: F02 Unapplied premium payments (UPP) | V1: Step 20 of 29
A2: ← Back to Load templates | B2: Step 20 of 29. Fill in one row per record below the column headers; the guide above each column says what to enter. | V2: Ask a question →
A3: Purpose | B3: One row per record of Unapplied premium payments (UPP) with disposition in progress as extracted from EBIX, CMS. Key legacy_upp_ref. Sent as the file F02_template.csv (CSV, header row as below) with its control file (row count, count of distinct keys; amount totals per currency: amount, balance).
A4: Provided by | B4: Cashiering data steward (to name); approved by Operations - Financial Transactions; extracted by BDOI IT
A5: Due | B5: M3 (29 Jan 2027); final at T-2
A6: How it is loaded | B6: Data migration object F02 (Carry forward), layout F02 version 1, through the Migration Console; lands in: Cashiering unapplied payments, as migrated items, with an opening accounting entry
A7: Source | B7: EBIX, CMS
A8: Depends on | B8: C01 Client master → | D8: C02 Client addresses and contacts →
A9: Progress | B9: Rows entered | C9: =SUMPRODUCT(((ROW($B$20:$B$220)>20)+($B$20<>"UPP-2026-004321")>0)*(LEN($B$20:$B$220&$C$20:$C$220&$D$20:$D$220&$E$20:$E$220&$F$20:$F$220&$G$20:$G$220&$H$20:$H$220&$I$20:$I$220&$J$20:$J$220&$K$20:$K$220&$L$20:$L$220&$M$20:$M$220&$N$20:$N$220&$O$20:$O$220&$P$20:$P$220&$Q$20:$Q$220&$R$20:$R$220&$S$20:$S$220&$T$20:$T$220&$U$20:$U$220&$V$20:$V$220)>0)) | D9: Mandatory cells missing | E9: =SUMPRODUCT(((ROW($B$20:$B$220)>20)+($B$20<>"UPP-2026-004321")>0)*(LEN($B$20:$B$220&$C$20:$C$220&$D$20:$D$220&$E$20:$E$220&$F$20:$F$220&$G$20:$G$220&$H$20:$H$220&$I$20:$I$220&$J$20:$J$220&$K$20:$K$220&$L$20:$L$220&$M$20:$M$220&$N$20:$N$220&$O$20:$O$220&$P$20:$P$220&$Q$20:$Q$220&$R$20:$R$220&$S$20:$S$220&$T$20:$T$220&$U$20:$U$220&$V$20:$V$220)>0)*(($B$20:$B$220="")+($C$20:$C$220="")+($D$20:$D$220="")+($E$20:$E$220="")+($F$20:$F$220="")+($G$20:$G$220="")+($I$20:$I$220="")+($J$20:$J$220="")+($K$20:$K$220="")+($M$20:$M$220="")+($R$20:$R$220="")))
A10: Reviewed by (BU reviewer) | D10: Review date
A12: BU review
A13: BU comment
A14: Check when loaded | B14: Unique | C14: Not blank | D14: Before the cutover date | E14: Before the cutover date | F14: In the list | G14: Not blank | H14: Client loaded when given | I14: Valid code | J14: Above 0 | K14: Above 0 and at most amount | L14: Mapped | M14: Mapped | N14: At least one ref_ field is recommended | O14: - | P14: - | Q14: - | R14: Mapped | S14: Mapped | T14: Mandatory when disposition_type is given | U14: - | V14: -
A15: Mandatory | B15: Yes | C15: Yes | D15: Yes | E15: Yes | F15: Yes | G15: Yes | H15: No | I15: Yes | J15: Yes | K15: Yes | L15: No | M15: Yes | N15: No | O15: No | P15: No | Q15: No | R15: Yes | S15: No | T15: Conditional: Mandatory when disposition_type is given | U15: No | V15: No
A16: Format | B16: Code, up to 40; As stored in legacy | C16: Text, up to 40; As printed | D16: Date, up to 10; yyyy-MM-dd | E16: Date, up to 10; yyyy-MM-dd | F16: Code, up to 20; Upper case | G16: Text, up to 250; Free text | H16: Code, up to 30; As stored in legacy | I16: Code, up to 3; Upper case | J16: Amount, up to 19,2; Dot decimal, 2 decimals | K16: Amount, up to 19,2; Dot decimal, 2 decimals | L16: Code, up to 20; As stored in legacy | M16: Code, up to 20; As stored in legacy | N16: Text, up to 400; NO;NO | O16: Text, up to 400; NO;NO | P16: Text, up to 400; PN;PN | Q16: Text, up to 80; As in the payment file | R16: Code, up to 30; As stored in legacy | S16: Code, up to 40; As stored in legacy | T16: Code, up to 20; Upper case | U16: Text, up to 500; Free text | V16: Text, up to 250; Free text
A17: Allowed values | B17: Free entry, up to 40 characters | C17: Free entry, up to 40 characters | D17: Free entry | E17: Free entry | F17: List F02 channel: 7 values, see Reference lists | G17: Free entry, up to 250 characters | H17: legacy_client_no of C01 | I17: ISO 4217 | J17: A number | K17: A number | L17: The legacy code; mapped by the code map SALES_UNIT (sheet Code maps) | M17: The legacy code; mapped by the code map BRANCH (sheet Code maps) | N17: Free entry, up to 400 characters | O17: Free entry, up to 400 characters | P17: Free entry, up to 400 characters | Q17: Free entry, up to 80 characters | R17: The legacy code; mapped by the code map STATUS:UPP (sheet Code maps) | S17: The legacy code; mapped by the code map DISPOSITION_TYPE (sheet Code maps) | T17: MONITORING, FOR_APPROVAL, IN_PROCESS (list F02 disposition_status) | U17: Free entry, up to 500 characters | V17: Free entry, up to 250 characters
A18: What to enter | B18: UPP reference in the source system | C18: Acknowledgment receipt issued in legacy | D18: AR date | E18: Value date of the cash | F18: Channel of the payment | G18: Payor | H18: Client if identified | I18: Currency | J18: Amount received | K18: Unapplied balance at the freeze | L18: Sales unit | M18: Branch that received the cash | N18: Invoice numbers the payor quoted, separated by semicolons | O18: Cover or policy numbers quoted | P18: PN numbers quoted | Q18: Bank or payment file reference | R18: UPP status in legacy | S18: Disposition in progress in legacy | T18: Status of the disposition | U18: Details (target invoice, refund payee, amount) | V18: Legacy remarks
A19: Row | B19: legacy_upp_ref * | C19: legacy_ar_no * | D19: legacy_ar_date * | E19: value_date * | F19: channel * | G19: payor_name * | H19: legacy_client_no | I19: currency * | J19: amount * | K19: balance * | L19: sales_unit_code | M19: branch_code * | N19: ref_invoice_nos | O19: ref_cover_nos | P19: ref_pn_nos | Q19: ref_bank_reference | R19: legacy_status * | S19: disposition_type | T19: disposition_status | U19: disposition_details | V19: remarks
A20: Example – overwrite or delete | B20: UPP-2026-004321 | C20: AR-MKT-131002 | D20: 2026-07-14 | E20: 2026-07-14 | F20: DIRECT_CREDIT | G20: Ana C. Reyes | H20: Q-0012345 | I20: PHP | J20: 5000 | K20: 5000 | L20: T-RET-07 | M20: MKT01 | N20: I00123456 | O20: C-2026-004512 | P20: PN-2019-000123 | Q20: DC20260714-000981 | R20: FOR_MONITORING | S20: REFUND | T20: FOR_APPROVAL | U20: Refund to CTA 001234567890 | V20: Client to confirm invoice

Sheet F03 Open collection state
A1: F03 Open collection state | M1: Step 21 of 29
A2: ← Back to Load templates | B2: Step 21 of 29. Fill in one row per record below the column headers; the guide above each column says what to enter. | M2: Ask a question →
A3: Purpose | B3: One row per record of Open collection state (dispositions, promises to pay, installment plans, collector assignments) as extracted from CMS. Key legacy_invoice_no, record_type, seq_no. Sent as the file F03_template.csv (CSV, header row as below) with its control file (row count, row count; amount totals per currency: promise_amount, installment_amount).
A4: Provided by | B4: Collections data steward (to name); approved by Head, Operations (Collections); extracted by BDOI IT
A5: Due | B5: M3 (29 Jan 2027); final at T-2
A6: How it is loaded | B6: Data migration object F03 (Carry forward), layout F03 version 1, through the Migration Console; lands in: Legacy follow-up of the Collections worklist items
A7: Source | B7: CMS
A8: Depends on | B8: F01 Open legacy invoices - header → | D8: F01S Open legacy invoices - insurer shares → | F8: F01C Open legacy invoices - components and positions →
A9: Progress | B9: Rows entered | C9: =SUMPRODUCT(((ROW($B$20:$B$220)>20)+($B$20<>"I00123456")>0)*(LEN($B$20:$B$220&$C$20:$C$220&$D$20:$D$220&$E$20:$E$220&$F$20:$F$220&$G$20:$G$220&$H$20:$H$220&$I$20:$I$220&$J$20:$J$220&$K$20:$K$220&$L$20:$L$220&$M$20:$M$220)>0)) | D9: Mandatory cells missing | E9: =SUMPRODUCT(((ROW($B$20:$B$220)>20)+($B$20<>"I00123456")>0)*(LEN($B$20:$B$220&$C$20:$C$220&$D$20:$D$220&$E$20:$E$220&$F$20:$F$220&$G$20:$G$220&$H$20:$H$220&$I$20:$I$220&$J$20:$J$220&$K$20:$K$220&$L$20:$L$220&$M$20:$M$220)>0)*(($B$20:$B$220="")+($C$20:$C$220="")+($D$20:$D$220="")))
A10: Reviewed by (BU reviewer) | D10: Review date
A12: BU review
A13: BU comment
A14: Check when loaded | B14: Exists in F01 | C14: In the list | D14: Unique per invoice and record type | E14: Mandatory for DISPOSITION; mapped | F14: Mandatory for DISPOSITION | G14: Mandatory for PROMISE | H14: Mandatory for PROMISE; at most the open PR | I14: Mandatory for INSTALLMENT | J14: Mandatory for INSTALLMENT | K14: Mandatory for INSTALLMENT | L14: Mandatory for ASSIGNMENT; mapped | M14: -
A15: Mandatory | B15: Yes | C15: Yes | D15: Yes | E15: Conditional: Mandatory for DISPOSITION; mapped | F15: Conditional: Mandatory for DISPOSITION | G15: Conditional: Mandatory for PROMISE | H15: Conditional: Mandatory for PROMISE; at most the open PR | I15: Conditional: Mandatory for INSTALLMENT | J15: Conditional: Mandatory for INSTALLMENT | K15: Conditional: Mandatory for INSTALLMENT | L15: Conditional: Mandatory for ASSIGNMENT; mapped | M15: No
A16: Format | B16: Code, up to 40; As in F01 | C16: Code, up to 12; Upper case | D16: Integer, up to 3; Digits | E16: Code, up to 40; As stored in legacy | F16: Date, up to 10; yyyy-MM-dd | G16: Date, up to 10; yyyy-MM-dd | H16: Amount, up to 19,2; Dot decimal, 2 decimals | I16: Integer, up to 3; Digits | J16: Date, up to 10; yyyy-MM-dd | K16: Amount, up to 19,2; Dot decimal, 2 decimals | L16: Code, up to 50; As stored in legacy | M16: Text, up to 500; Free text
A17: Allowed values | B17: legacy_invoice_no of F01 | C17: DISPOSITION, PROMISE, INSTALLMENT, ASSIGNMENT (list F03 record_type) | D17: A whole number | E17: The legacy code; mapped by the code map DISPOSITION_CLX (sheet Code maps) | F17: Free entry | G17: Free entry | H17: A number | I17: A whole number | J17: Free entry | K17: A number | L17: The legacy code; mapped by the code map USER (sheet Code maps) | M17: Free entry, up to 500 characters
A18: What to enter | B18: Invoice the follow-up belongs to | C18: Kind of row | D18: Sequence within the invoice and record type | E18: Latest disposition | F18: Date of the disposition | G18: Promised payment date | H18: Promised amount | I18: Installment number | J18: Installment due date | K18: Installment amount | L18: Assigned collector | M18: Collector remarks
A19: Row | B19: legacy_invoice_no * | C19: record_type * | D19: seq_no * | E19: disposition_code | F19: disposition_date | G19: promise_date | H19: promise_amount | I19: installment_no | J19: installment_due | K19: installment_amount | L19: collector_user_id | M19: remarks
A20: Example – overwrite or delete | B20: I00123456 | C20: PROMISE | D20: 1 | E20: PTP | F20: 2027-12-20 | G20: 2028-01-14 | H20: 6000 | I20: 2 | J20: 2028-01-15 | K20: 3000 | L20: jgarcia | M20: Client will pay after salary

Sheet F04 Remittance in flight
A1: F04 Remittance in flight | K1: Step 22 of 29
A2: ← Back to Load templates | B2: Step 22 of 29. Fill in one row per record below the column headers; the guide above each column says what to enter. | K2: Ask a question →
A3: Purpose | B3: One row per record of Remittance in flight (batches not yet paid, holds, special remittances) as extracted from EBIX. Key legacy_batch_no, legacy_invoice_no. Sent as the file F04_template.csv (CSV, header row as below) with its control file (row count, row count; amount totals per currency: amount).
A4: Provided by | B4: Remittance data steward (to name); approved by Operations - Remittance; extracted by BDOI IT
A5: Due | B5: M3 (29 Jan 2027); final at T-2
A6: How it is loaded | B6: Data migration object F04 (Conditional), layout F04 version 1, through the Migration Console; lands in: Remittance holds and special remittances
A7: Source | B7: EBIX
A8: Depends on | B8: F01 Open legacy invoices - header → | D8: F01S Open legacy invoices - insurer shares → | F8: F01C Open legacy invoices - components and positions →
A9: Progress | B9: Rows entered | C9: =SUMPRODUCT(((ROW($B$20:$B$220)>20)+($B$20<>"HOLD")>0)*(LEN($B$20:$B$220&$C$20:$C$220&$D$20:$D$220&$E$20:$E$220&$F$20:$F$220&$G$20:$G$220&$H$20:$H$220&$I$20:$I$220&$J$20:$J$220&$K$20:$K$220)>0)) | D9: Mandatory cells missing | E9: =SUMPRODUCT(((ROW($B$20:$B$220)>20)+($B$20<>"HOLD")>0)*(LEN($B$20:$B$220&$C$20:$C$220&$D$20:$D$220&$E$20:$E$220&$F$20:$F$220&$G$20:$G$220&$H$20:$H$220&$I$20:$I$220&$J$20:$J$220&$K$20:$K$220)>0)*(($B$20:$B$220="")+($D$20:$D$220="")+($E$20:$E$220="")+($F$20:$F$220="")+($G$20:$G$220="")+($H$20:$H$220="")))
A10: Reviewed by (BU reviewer) | D10: Review date
A12: BU review
A13: BU comment
A14: Check when loaded | B14: In the list | C14: Mandatory for BATCH and SPECIAL | D14: Mapped | E14: Exists in F01 | F14: Valid code | G14: At most the open DTIP | H14: Mapped | I14: Mandatory for HOLD | J14: Valid date | K14: Mapped
A15: Mandatory | B15: Yes | C15: Conditional: Mandatory for BATCH and SPECIAL | D15: Yes | E15: Yes | F15: Yes | G15: Yes | H15: Yes | I15: Conditional: Mandatory for HOLD | J15: No | K15: No
A16: Format | B16: Code, up to 10; Upper case | C16: Text, up to 40; As stored in legacy | D16: Code, up to 30; As stored in legacy | E16: Code, up to 40; As in F01 | F16: Code, up to 3; Upper case | G16: Amount, up to 19,2; Dot decimal, 2 decimals | H16: Code, up to 30; As stored in legacy | I16: Text, up to 250; Free text | J16: Date, up to 10; yyyy-MM-dd | K16: Code, up to 50; As stored in legacy
A17: Allowed values | B17: HOLD, SPECIAL, BATCH (list F04 record_type) | C17: Free entry, up to 40 characters | D17: The legacy code; mapped by the code map INSURER (sheet Code maps) | E17: legacy_invoice_no of F01 | F17: ISO 4217 | G17: A number | H17: The legacy code; mapped by the code map STATUS:REMITTANCE (sheet Code maps) | I17: Free entry, up to 250 characters | J17: Free entry | K17: The legacy code; mapped by the code map USER (sheet Code maps)
A18: What to enter | B18: Kind of row | C18: Legacy remittance batch number (BATCH, SPECIAL) | D18: Insurer | E18: Invoice of the line | F18: Currency | G18: Amount held or to remit | H18: Status in legacy | I18: Reason of the hold | J18: End of the hold | K18: Requester
A19: Row | B19: record_type * | C19: legacy_batch_no | D19: insurer_code * | E19: legacy_invoice_no * | F19: currency * | G19: amount * | H19: status * | I19: hold_reason | J19: hold_until | K19: requested_by_user_id
A20: Example – overwrite or delete | B20: HOLD | C20: RB-2026-0877 | D20: MAL | E20: I00123456 | F20: PHP | G20: 21671.25 | H20: ON_HOLD | I20: Pending negative endorsement | J20: 2028-01-31 | K20: rtan

Sheet F06 PDCs, check pick-ups and re
A1: F06 PDCs, check pick-ups and refunds in process | O1: Step 23 of 29
A2: ← Back to Load templates | B2: Step 23 of 29. Fill in one row per record below the column headers; the guide above each column says what to enter. | O2: Ask a question →
A3: Purpose | B3: One row per record of PDCs in the warehouse, check pick-ups and refunds in process as extracted from EBIX. Key record_type, reference. Sent as the file F06_template.csv (CSV, header row as below) with its control file (row count, row count; amount totals per currency: amount).
A4: Provided by | B4: Cashiering data steward (to name); approved by Operations - Cashiering; extracted by BDOI IT
A5: Due | B5: M3 (29 Jan 2027); final at T-2
A6: How it is loaded | B6: Data migration object F06 (Conditional), layout F06 version 1, through the Migration Console; lands in: Cashiering PDC warehouse and check pick-up
A7: Source | B7: EBIX
A8: Depends on | B8: C01 Client master → | D8: C02 Client addresses and contacts →
A9: Progress | B9: Rows entered | C9: =SUMPRODUCT(((ROW($B$20:$B$220)>20)+($B$20<>"PDC")>0)*(LEN($B$20:$B$220&$C$20:$C$220&$D$20:$D$220&$E$20:$E$220&$F$20:$F$220&$G$20:$G$220&$H$20:$H$220&$I$20:$I$220&$J$20:$J$220&$K$20:$K$220&$L$20:$L$220&$M$20:$M$220&$N$20:$N$220&$O$20:$O$220)>0)) | D9: Mandatory cells missing | E9: =SUMPRODUCT(((ROW($B$20:$B$220)>20)+($B$20<>"PDC")>0)*(LEN($B$20:$B$220&$C$20:$C$220&$D$20:$D$220&$E$20:$E$220&$F$20:$F$220&$G$20:$G$220&$H$20:$H$220&$I$20:$I$220&$J$20:$J$220&$K$20:$K$220&$L$20:$L$220&$M$20:$M$220&$N$20:$N$220&$O$20:$O$220)>0)*(($B$20:$B$220="")+($C$20:$C$220="")+($I$20:$I$220="")+($J$20:$J$220="")+($L$20:$L$220="")+($N$20:$N$220="")))
A10: Reviewed by (BU reviewer) | D10: Review date
A12: BU review
A13: BU comment
A14: Check when loaded | B14: In the list | C14: Unique per record type | D14: Mandatory for PDC | E14: Mandatory for PDC and PICKUP | F14: Mandatory for PDC; mapped | G14: - | H14: Mandatory for PDC | I14: Valid code | J14: Above 0 | K14: Client loaded when given | L14: Not blank | M14: Exists in F01 when given | N14: Mapped | O14: -
A15: Mandatory | B15: Yes | C15: Yes | D15: Conditional: Mandatory for PDC | E15: Conditional: Mandatory for PDC and PICKUP | F15: Conditional: Mandatory for PDC; mapped | G15: No | H15: Conditional: Mandatory for PDC | I15: Yes | J15: Yes | K15: No | L15: Yes | M15: No | N15: Yes | O15: No
A16: Format | B16: Code, up to 10; Upper case | C16: Text, up to 80; As stored in legacy | D16: Text, up to 30; As stored in legacy | E16: Text, up to 40; Digits | F16: Code, up to 30; As stored in legacy | G16: Text, up to 60; Free text | H16: Date, up to 10; yyyy-MM-dd | I16: Code, up to 3; Upper case | J16: Amount, up to 19,2; Dot decimal, 2 decimals | K16: Code, up to 30; As stored in legacy | L16: Text, up to 250; Free text | M16: Code, up to 40; As in F01 | N16: Code, up to 20; As stored in legacy | O16: Text, up to 250; Free text
A17: Allowed values | B17: PDC, PICKUP, REFUND (list F06 record_type) | C17: Free entry, up to 80 characters | D17: Free entry, up to 30 characters | E17: Free entry, up to 40 characters | F17: The legacy code; mapped by the code map BANK (sheet Code maps) | G17: Free entry, up to 60 characters | H17: Free entry | I17: ISO 4217 | J17: A number | K17: legacy_client_no of C01 | L17: Free entry, up to 250 characters | M17: legacy_invoice_no of F01 | N17: The legacy code; mapped by the code map STATUS:PDC (sheet Code maps) | O17: Free entry, up to 250 characters
A18: What to enter | B18: Kind of item | C18: Legacy reference of the item | D18: PDC warehouse number | E18: Check number | F18: Drawee bank | G18: Drawee branch | H18: Check date or maturity date | I18: Currency | J18: Amount | K18: Client | L18: Payor | M18: Invoice the item pays or refunds | N18: Status in legacy | O18: Remarks
A19: Row | B19: record_type * | C19: reference * | D19: warehouse_no | E19: check_no | F19: bank_code | G19: check_branch | H19: check_date | I19: currency * | J19: amount * | K19: legacy_client_no | L19: payor_name * | M19: legacy_invoice_no | N19: status * | O19: remarks
A20: Example – overwrite or delete | B20: PDC | C20: PDC-2026-000345 | D20: WH-02 | E20: 0004567 | F20: BPI | G20: BPI Ortigas | H20: 2028-01-15 | I20: PHP | J20: 6000 | K20: Q-0012345 | L20: Ana C. Reyes | M20: I00123456 | N20: WAREHOUSED | O20: Replacement check expected

Sheet G01 GL opening trial balance
A1: G01 GL opening trial balance | L1: Step 24 of 29
A2: ← Back to Load templates | B2: Step 24 of 29. Fill in one row per record below the column headers; the guide above each column says what to enter. | L2: Ask a question →
A3: Purpose | B3: One row per record of GL trial balance per account, branch and currency (provisional opening; legacy TB at each true-up) as extracted from EBIX GL, ISYS GL. Key tb_version, branch_code, currency, legacy_account_code, cost_center. Sent as the file G01_template.csv (CSV, header row as below) with its control file (row count, row count; amount totals per currency: debit_fc, credit_fc, debit_php, credit_php).
A4: Provided by | B4: Comptrollership data steward (to name); approved by Head, Comptrollership; extracted by BDOI IT
A5: Due | B5: M3 (29 Jan 2027); final at T-2; at each true-up
A6: How it is loaded | B6: Data migration object G01 (Migrate), layout G01 version 1, through the Migration Console; lands in: General ledger journals of type OPENING (value date 1-Jan-2028); at a true-up, reconciliation input only
A7: Source | B7: EBIX GL, ISYS GL
A8: Depends on | B8: R08 Chart of accounts mapping → | D8: F01 Open legacy invoices - header → | F8: F01S Open legacy invoices - insurer shares → | G8: F01C Open legacy invoices - components and positions → | I8: F02 Unapplied premium payments (UPP) →
A9: Progress | B9: Rows entered | C9: =SUMPRODUCT(((ROW($B$20:$B$220)>20)+($B$20<>"PROVISIONAL")>0)*(LEN($B$20:$B$220&$C$20:$C$220&$D$20:$D$220&$E$20:$E$220&$F$20:$F$220&$G$20:$G$220&$H$20:$H$220&$I$20:$I$220&$J$20:$J$220&$K$20:$K$220&$L$20:$L$220)>0)) | D9: Mandatory cells missing | E9: =SUMPRODUCT(((ROW($B$20:$B$220)>20)+($B$20<>"PROVISIONAL")>0)*(LEN($B$20:$B$220&$C$20:$C$220&$D$20:$D$220&$E$20:$E$220&$F$20:$F$220&$G$20:$G$220&$H$20:$H$220&$I$20:$I$220&$J$20:$J$220&$K$20:$K$220&$L$20:$L$220)>0)*(($B$20:$B$220="")+($C$20:$C$220="")+($D$20:$D$220="")+($E$20:$E$220="")+($F$20:$F$220="")+($H$20:$H$220="")+($I$20:$I$220="")+($J$20:$J$220="")+($K$20:$K$220="")))
A10: Reviewed by (BU reviewer) | D10: Review date
A12: BU review
A13: BU comment
A14: Check when loaded | B14: In the list; one version per file | C14: One date in the file | D14: Mapped | E14: Valid code | F14: Mapped | G14: Mapped | H14: 0 or more; debit or credit, not both | I14: 0 or more | J14: 0 or more | K14: 0 or more | L14: Mandatory when currency is not PHP
A15: Mandatory | B15: Yes | C15: Yes | D15: Yes | E15: Yes | F15: Yes | G15: No | H15: Yes | I15: Yes | J15: Yes | K15: Yes | L15: Conditional: Mandatory when currency is not PHP
A16: Format | B16: Code, up to 12; Upper case | C16: Date, up to 10; yyyy-MM-dd | D16: Code, up to 20; As stored in legacy | E16: Code, up to 3; Upper case | F16: Code, up to 30; As stored in legacy | G16: Code, up to 20; As stored in legacy | H16: Amount, up to 19,2; Dot decimal, 2 decimals | I16: Amount, up to 19,2; Dot decimal, 2 decimals | J16: Amount, up to 19,2; Dot decimal, 2 decimals | K16: Amount, up to 19,2; Dot decimal, 2 decimals | L16: Decimal, up to 12,6; Dot decimal
A17: Allowed values | B17: PROVISIONAL, TU1, TU2, TU3, FINAL (list G01 tb_version) | C17: Free entry | D17: The legacy code; mapped by the code map BRANCH (sheet Code maps) | E17: ISO 4217 | F17: The legacy code; mapped by the code map GL_ACCOUNT (sheet Code maps) | G17: The legacy code; mapped by the code map COST_CENTER (sheet Code maps) | H17: A number | I17: A number | J17: A number | K17: A number | L17: A number
A18: What to enter | B18: Version of the trial balance - PROVISIONAL at cut-over (preliminary December TB), then TU1, TU2... and FINAL (audited) at the true-ups | C18: Trial balance date - 31-Dec-2027 for every version; the version says which adjustments it includes | D18: Branch | E18: Account currency | F18: Legacy account | G18: Cost centre | H18: Debit balance in the account currency | I18: Credit balance in the account currency | J18: Debit balance in PHP | K18: Credit balance in PHP | L18: Rate used for the PHP amount
A19: Row | B19: tb_version * | C19: as_of_date * | D19: branch_code * | E19: currency * | F19: legacy_account_code * | G19: cost_center | H19: debit_fc * | I19: credit_fc * | J19: debit_php * | K19: credit_php * | L19: fx_rate
A20: Example – overwrite or delete | B20: PROVISIONAL | C20: 2027-12-31 | D20: MKT01 | E20: USD | F20: 1101-02 | G20: 4100 | H20: 12500 | I20: 0 | J20: 701562.5 | K20: 0 | L20: 56.125

Sheet P03 Renewal advices already sen
A1: P03 Renewal advices already sent before go-live (RA-sent file) | N1: Step 25 of 29
A2: ← Back to Load templates | B2: Step 25 of 29. Fill in one row per record below the column headers; the guide above each column says what to enter. | N2: Ask a question →
A3: Purpose | B3: One row per record of Renewal advices already sent before go-live (RA-sent file) as extracted from Excel RA trackers of the Renewal processing team. Key legacy_policy_ref. Sent as the file P03_template.csv (CSV, header row as below) with its control file (row count, count of distinct keys; amount totals per currency: proposed_premium).
A4: Provided by | B4: Renewal processing team - makers (corrections) and checkers (resubmission approval); approved by Head of the Renewal processing team; extracted by BDOI IT
A5: Due | B5: M4 (9 Apr 2027) (Trial migration 1); final at T-5
A6: How it is loaded | B6: Data migration object P03 (Migrate), layout P03 version 1, through the Migration Console; lands in: Renewal Advices already sent, given to Renewal with the policy header in the go-live extraction
A7: Source | B7: Excel RA trackers of the Renewal processing team
A8: Depends on | B8: P01 In-force policy headers → | D8: P01S Policy insurer shares →
A9: Progress | B9: Rows entered | C9: =SUMPRODUCT(((ROW($B$20:$B$220)>20)+($B$20<>"C-2027-004512-01")>0)*(LEN($B$20:$B$220&$C$20:$C$220&$D$20:$D$220&$E$20:$E$220&$F$20:$F$220&$G$20:$G$220&$H$20:$H$220&$I$20:$I$220&$J$20:$J$220&$K$20:$K$220&$L$20:$L$220&$M$20:$M$220&$N$20:$N$220)>0)) | D9: Mandatory cells missing | E9: =SUMPRODUCT(((ROW($B$20:$B$220)>20)+($B$20<>"C-2027-004512-01")>0)*(LEN($B$20:$B$220&$C$20:$C$220&$D$20:$D$220&$E$20:$E$220&$F$20:$F$220&$G$20:$G$220&$H$20:$H$220&$I$20:$I$220&$J$20:$J$220&$K$20:$K$220&$L$20:$L$220&$M$20:$M$220&$N$20:$N$220)>0)*(($B$20:$B$220="")+($C$20:$C$220="")+($D$20:$D$220="")+($E$20:$E$220="")+($G$20:$G$220="")+($M$20:$M$220="")))
A10: Reviewed by (BU reviewer) | D10: Review date
A12: BU review
A13: BU comment
A14: Check when loaded | B14: Exists in P01 of the same load | C14: Equals the cover of the P01 header | D14: Equals the P01 expiry; from T to 31-May-2028 | E14: Not after the last legacy business day; warning when more than 140 days before expiry | F14: - | G14: In the list | H14: Masked outside production | I14: Mapped | J14: Mandatory with proposed_premium | K14: 0 or more | L14: Mapped in USER | M14: Not blank | N14: -
A15: Mandatory | B15: Yes | C15: Yes | D15: Yes | E15: Yes | F15: No | G15: Yes | H15: No | I15: No | J15: Conditional: Mandatory with proposed_premium | K15: No | L15: No | M15: Yes | N15: No
A16: Format | B16: Code, up to 60; As in P01 | C16: Text, up to 40; As stored in legacy | D16: Date, up to 10; yyyy-MM-dd | E16: Date, up to 10; yyyy-MM-dd | F16: Text, up to 30; As in the tracker | G16: Code, up to 10; Upper case | H16: Text, up to 250; Free text | I16: Code, up to 30; As stored in legacy | J16: Code, up to 3; Upper case | K16: Amount, up to 19,2; Dot decimal, 2 decimals | L16: Code, up to 50; As stored in legacy | M16: Text, up to 120; File / sheet | N16: Text, up to 500; Free text
A17: Allowed values | B17: legacy_policy_ref of P01 | C17: Free entry, up to 40 characters | D17: Free entry | E17: Free entry | F17: Free entry, up to 30 characters | G17: EMAIL, COURIER, HAND, OTHER (list P03 ra_channel) | H17: Free entry, up to 250 characters | I17: The legacy code; mapped by the code map INSURER (sheet Code maps) | J17: ISO 4217 | K17: A number | L17: The legacy code; mapped by the code map USER (sheet Code maps) | M17: Free entry, up to 120 characters | N17: Free entry, up to 500 characters
A18: What to enter | B18: Legacy reference of the expiring policy term | C18: Legacy cover number of the expiring term | D18: Expiry of the expiring term | E18: Date the RA was sent | F18: RA reference, if the tracker gives one | G18: How the RA was sent | H18: Recipient (client name or e-mail address) | I18: Insurer quoted on the RA | J18: Currency of the quoted premium | K18: Gross premium quoted on the RA | L18: Renewal processor who sent the RA | M18: Tracker file and sheet the row comes from | N18: Remarks of the processor
A19: Row | B19: legacy_policy_ref * | C19: cover_no * | D19: expiry_date * | E19: ra_sent_date * | F19: ra_ref | G19: ra_channel * | H19: sent_to | I19: proposed_insurer_code | J19: currency | K19: proposed_premium | L19: sent_by_user_id | M19: tracker_name * | N19: remarks
A20: Example – overwrite or delete | B20: C-2027-004512-01 | C20: C-2027-004512 | D20: 2028-01-15 | E20: 2027-11-16 | F20: RA-2027-018833 | G20: EMAIL | H20: ana.reyes@example.com | I20: MAL | J20: PHP | K20: 24650 | L20: mreyes | M20: Retail RA tracker Jan-2028 / MKT01 | N20: Client asked for a quote with higher SI

Sheet H01 Archive records (closed tra
A1: H01 Archive records (closed transactions and history) | P1: Step 26 of 29
A2: ← Back to Load templates | B2: Step 26 of 29. Fill in one row per record below the column headers; the guide above each column says what to enter. | P2: Ask a question →
A3: Purpose | B3: One row per record of Closed transactions (paid and remitted invoices, receipts, remittances, endorsements, claims, renewal advices, letters) as extracted from EBIX, QPS, ISYS. Key record_type, legacy_key. Sent as the file H01_template.csv (CSV, header row as below) with its control file (row count, count of distinct keys; amount totals per currency: amount).
A4: Provided by | B4: Compliance data steward (to name); approved by Audit / Compliance; legacy system owners; extracted by BDOI IT
A5: Due | B5: Before decommissioning
A6: How it is loaded | B6: Data migration object H01 (Archive), layout H01 version 1, through the Migration Console; lands in: BIBS archive (Legacy Inquiry)
A7: Source | B7: EBIX, QPS, ISYS
A8: Depends on | B8: Nothing: this template can be filled in first
A9: Progress | B9: Rows entered | C9: =SUMPRODUCT(((ROW($B$20:$B$220)>20)+($B$20<>"INVOICE")>0)*(LEN($B$20:$B$220&$C$20:$C$220&$D$20:$D$220&$E$20:$E$220&$F$20:$F$220&$G$20:$G$220&$H$20:$H$220&$I$20:$I$220&$J$20:$J$220&$K$20:$K$220&$L$20:$L$220&$M$20:$M$220&$N$20:$N$220&$O$20:$O$220&$P$20:$P$220)>0)) | D9: Mandatory cells missing | E9: =SUMPRODUCT(((ROW($B$20:$B$220)>20)+($B$20<>"INVOICE")>0)*(LEN($B$20:$B$220&$C$20:$C$220&$D$20:$D$220&$E$20:$E$220&$F$20:$F$220&$G$20:$G$220&$H$20:$H$220&$I$20:$I$220&$J$20:$J$220&$K$20:$K$220&$L$20:$L$220&$M$20:$M$220&$N$20:$N$220&$O$20:$O$220&$P$20:$P$220)>0)*(($B$20:$B$220="")+($C$20:$C$220="")+($J$20:$J$220="")))
A10: Reviewed by (BU reviewer) | D10: Review date
A12: BU review
A13: BU comment
A14: Check when loaded | B14: In the list | C14: Unique per record type | D14: - | E14: - | F14: - | G14: - | H14: - | I14: - | J14: Valid date | K14: Valid date | L14: Not before period_from | M14: Valid code | N14: - | O14: - | P14: Every pair has a label and a value
A15: Mandatory | B15: Yes | C15: Yes | D15: No | E15: No | F15: No | G15: No | H15: No | I15: No | J15: Yes | K15: No | L15: No | M15: No | N15: No | O15: No | P15: No
A16: Format | B16: Code, up to 20; Upper case | C16: Code, up to 80; As stored in legacy | D16: Code, up to 30; As stored in legacy | E16: Text, up to 250; Free text | F16: Text, up to 60; As stored in legacy | G16: Text, up to 40; As stored in legacy | H16: Text, up to 40; As printed | I16: Text, up to 40; As stored in legacy | J16: Date, up to 10; yyyy-MM-dd | K16: Date, up to 10; yyyy-MM-dd | L16: Date, up to 10; yyyy-MM-dd | M16: Code, up to 3; Upper case | N16: Amount, up to 19,2; Dot decimal, 2 decimals | O16: Text, up to 40; As stored in legacy | P16: Text, up to 20000; Label: value pairs separated by ;
A17: Allowed values | B17: List H01 record_type: 11 values, see Reference lists | C17: Free entry, up to 80 characters | D17: Free entry, up to 30 characters | E17: Free entry, up to 250 characters | F17: Free entry, up to 60 characters | G17: Free entry, up to 40 characters | H17: Free entry, up to 40 characters | I17: Free entry, up to 40 characters | J17: Free entry | K17: Free entry | L17: Free entry | M17: ISO 4217 | N17: A number | O17: Free entry, up to 40 characters | P17: Free entry, up to 20000 characters
A18: What to enter | B18: Kind of record | C18: Unique key of the record in the source | D18: Client number | E18: Client name | F18: Policy or cover number | G18: Invoice number | H18: AR or OR number | I18: Claim number | J18: Date of the record | K18: Period from | L18: Period to | M18: Currency | N18: Main amount of the record | O18: Status in legacy | P18: Other legacy fields of the record, each as a label and its value
A19: Row | B19: record_type * | C19: legacy_key * | D19: legacy_client_no | E19: client_name | F19: policy_no | G19: invoice_no | H19: receipt_no | I19: claim_no | J19: document_date * | K19: period_from | L19: period_to | M19: currency | N19: amount | O19: status | P19: detail_json
A20: Example – overwrite or delete | B20: INVOICE | C20: I00098765 | D20: Q-0012345 | E20: Ana C. Reyes | F20: MC-PC-22-0004567 | G20: I00098765 | H20: AR-MKT-098001 | I20: CL-2023-000456 | J20: 2022-05-10 | K20: 2022-05-15 | L20: 2023-05-15 | M20: PHP | N20: 18450 | O20: PAID_REMITTED | P20: Insurer: MAL; Remitted on: 01-Jul-2022

Sheet H02 Archive documents index
A1: H02 Archive documents index | I1: Step 27 of 29
A2: ← Back to Load templates | B2: Step 27 of 29. Fill in one row per record below the column headers; the guide above each column says what to enter. | I2: Ask a question →
A3: Purpose | B3: One row per record of Legacy documents (policies, SOAs, ORs, certificates, letters) as extracted from File shares, EBIX. Key record_type, legacy_key, file_name. Sent as the file H02_template.csv (CSV, header row as below) with its control file (row count, row count).
A4: Provided by | B4: Compliance data steward (to name); approved by Audit / Compliance; extracted by BDOI IT
A5: Due | B5: Before decommissioning
A6: How it is loaded | B6: Data migration object H02 (Archive), layout H02 version 1, through the Migration Console; lands in: Legacy documents attached to the archive records
A7: Source | B7: File shares, EBIX
A8: Depends on | B8: Nothing: this template can be filled in first
A9: Progress | B9: Rows entered | C9: =SUMPRODUCT(((ROW($B$20:$B$220)>20)+($B$20<>"CLIENT")>0)*(LEN($B$20:$B$220&$C$20:$C$220&$D$20:$D$220&$E$20:$E$220&$F$20:$F$220&$G$20:$G$220&$H$20:$H$220&$I$20:$I$220)>0)) | D9: Mandatory cells missing | E9: =SUMPRODUCT(((ROW($B$20:$B$220)>20)+($B$20<>"CLIENT")>0)*(LEN($B$20:$B$220&$C$20:$C$220&$D$20:$D$220&$E$20:$E$220&$F$20:$F$220&$G$20:$G$220&$H$20:$H$220&$I$20:$I$220)>0)*(($B$20:$B$220="")+($C$20:$C$220="")+($D$20:$D$220="")+($G$20:$G$220="")+($H$20:$H$220="")+($I$20:$I$220="")))
A10: Reviewed by (BU reviewer) | D10: Review date
A12: BU review
A13: BU comment
A14: Check when loaded | B14: In the list | C14: Record exists in H01 or C01 | D14: Mapped | E14: - | F14: Valid date | G14: File present in the transfer | H14: =size of the received file | I14: =checksum computed at intake
A15: Mandatory | B15: Yes | C15: Yes | D15: Yes | E15: No | F15: No | G15: Yes | H15: Yes | I15: Yes
A16: Format | B16: Code, up to 20; Upper case | C16: Code, up to 80; As in H01 | D16: Code, up to 40; As stored in legacy | E16: Text, up to 60; As printed | F16: Date, up to 10; yyyy-MM-dd | G16: Text, up to 255; name.ext | H16: Integer, up to 12; Digits | I16: Text, up to 64; Lower-case hex
A17: Allowed values | B17: Same list as H01 record_type | C17: legacy_key of H01 | D17: The legacy code; mapped by the code map DOCUMENT_TYPE (sheet Code maps) | E17: Free entry, up to 60 characters | F17: Free entry | G17: Free entry, up to 255 characters | H17: A whole number | I17: Free entry, up to 64 characters
A18: What to enter | B18: Kind of the archive record the document belongs to | C18: Key of the archive record (or legacy_client_no for KYC documents) | D18: Kind of document | E18: Document number (ID number, policy number) | F18: Date of the document | G18: File name in the transfer folder | H18: File size | I18: SHA-256 of the file, 64 hexadecimal characters
A19: Row | B19: record_type * | C19: legacy_key * | D19: document_type * | E19: document_no | F19: document_date | G19: file_name * | H19: file_size_bytes * | I19: sha256 *
A20: Example – overwrite or delete | B20: CLIENT | C20: Q-0012345 | D20: KYC_ID | E20: P1234567A | F20: 2021-07-02 | G20: Q-0012345_KYC_ID_1.pdf | H20: 245760 | I20: 9f86d081884c7d659a2feaa0c55ad015a3bf4f1b2b0b822cd15d6c15b0f00a08

Sheet G03 FY2027 true-up - legacy adj
A1: G03 FY2027 true-up - legacy adjustment journal lines after the freeze | T1: Step 28 of 29
A2: ← Back to Load templates | B2: Step 28 of 29. Fill in one row per record below the column headers; the guide above each column says what to enter. | T2: Ask a question →
A3: Purpose | B3: One row per record of FY2027 opening-balance true-ups (legacy adjustment journals after the freeze and their open-item detail) as extracted from EBIX GL, ISYS GL; FY2027 adjustment register of Comptrollership. Key legacy_journal_no, line_no. Sent as the file G03_template.csv (CSV, header row as below) with its control file (row count, count of distinct keys; amount totals per currency: debit_fc, credit_fc, debit_php, credit_php).
A4: Provided by | B4: Comptrollership GL lead (prepares each true-up); approved by Head, Comptrollership; extracted by BDOI IT
A5: Due | B5: T+16 (true-up 1); T+92 (final)
A6: How it is loaded | B6: Data migration object G03 (Migrate), layout G03 version 1, through the Migration Console; lands in: General ledger journals of type OPENING (reference MIG-TU-<n>); opening adjustments of the legacy open items and unapplied payments
A7: Source | B7: EBIX GL, ISYS GL; FY2027 adjustment register of Comptrollership
A8: Depends on | B8: G01 GL opening trial balance →
A9: Progress | B9: Rows entered | C9: =SUMPRODUCT(((ROW($B$20:$B$220)>20)+($B$20<>"1")>0)*(LEN($B$20:$B$220&$C$20:$C$220&$D$20:$D$220&$E$20:$E$220&$F$20:$F$220&$G$20:$G$220&$H$20:$H$220&$I$20:$I$220&$J$20:$J$220&$K$20:$K$220&$L$20:$L$220&$M$20:$M$220&$N$20:$N$220&$O$20:$O$220&$P$20:$P$220&$Q$20:$Q$220&$R$20:$R$220&$S$20:$S$220&$T$20:$T$220)>0)) | D9: Mandatory cells missing | E9: =SUMPRODUCT(((ROW($B$20:$B$220)>20)+($B$20<>"1")>0)*(LEN($B$20:$B$220&$C$20:$C$220&$D$20:$D$220&$E$20:$E$220&$F$20:$F$220&$G$20:$G$220&$H$20:$H$220&$I$20:$I$220&$J$20:$J$220&$K$20:$K$220&$L$20:$L$220&$M$20:$M$220&$N$20:$N$220&$O$20:$O$220&$P$20:$P$220&$Q$20:$Q$220&$R$20:$R$220&$S$20:$S$220&$T$20:$T$220)>0)*(($B$20:$B$220="")+($C$20:$C$220="")+($D$20:$D$220="")+($E$20:$E$220="")+($F$20:$F$220="")+($G$20:$G$220="")+($H$20:$H$220="")+($I$20:$I$220="")+($J$20:$J$220="")+($K$20:$K$220="")+($M$20:$M$220="")+($N$20:$N$220="")+($O$20:$O$220="")+($P$20:$P$220="")+($R$20:$R$220="")+($S$20:$S$220="")+($T$20:$T$220="")))
A10: Reviewed by (BU reviewer) | D10: Review date
A12: BU review
A13: BU comment
A14: Check when loaded | B14: In the list; one true-up per file | C14: In the FY2027 adjustment register | D14: Unique per journal | E14: From 1-Jan-2027 to 31-Dec-2027 | F14: After the freeze (T-3 22:00) | G14: In the list | H14: Exists in the register | I14: Mapped | J14: Valid code | K14: Mapped; a legacy control account needs G03D detail | L14: Mapped | M14: 0 or more; debit or credit, not both | N14: 0 or more | O14: 0 or more; each journal balances per branch and currency | P14: 0 or more | Q14: Mandatory when currency is not PHP | R14: Not blank | S14: On the Comptrollership access list | T14: On the access list; not the preparer
A15: Mandatory | B15: Yes | C15: Yes | D15: Yes | E15: Yes | F15: Yes | G15: Yes | H15: Yes | I15: Yes | J15: Yes | K15: Yes | L15: No | M15: Yes | N15: Yes | O15: Yes | P15: Yes | Q15: Conditional: Mandatory when currency is not PHP | R15: Yes | S15: Yes | T15: Yes
A16: Format | B16: Code, up to 2; As listed | C16: Code, up to 30; As stored in legacy | D16: Integer, up to 4; Digits | E16: Date, up to 10; yyyy-MM-dd | F16: Timestamp, up to 19; yyyy-MM-dd HH:mm:ss | G16: Code, up to 8; Upper case | H16: Text, up to 20; As in the register | I16: Code, up to 20; As stored in legacy | J16: Code, up to 3; Upper case | K16: Code, up to 30; As stored in legacy | L16: Code, up to 20; As stored in legacy | M16: Amount, up to 19,2; Dot decimal, 2 decimals | N16: Amount, up to 19,2; Dot decimal, 2 decimals | O16: Amount, up to 19,2; Dot decimal, 2 decimals | P16: Amount, up to 19,2; Dot decimal, 2 decimals | Q16: Decimal, up to 12,6; Dot decimal | R16: Text, up to 250; Free text | S16: Text, up to 50; As in legacy | T16: Text, up to 50; As in legacy
A17: Allowed values | B17: 1, 2, 3, F (list G03 trueup_no) | C17: Free entry, up to 30 characters | D17: A whole number | E17: Free entry | F17: Free entry | G17: CLOSING, AUDIT (list G03 adjustment_kind) | H17: Free entry, up to 20 characters | I17: The legacy code; mapped by the code map BRANCH (sheet Code maps) | J17: ISO 4217 | K17: The legacy code; mapped by the code map GL_ACCOUNT (sheet Code maps) | L17: The legacy code; mapped by the code map COST_CENTER (sheet Code maps) | M17: A number | N17: A number | O17: A number | P17: A number | Q17: A number | R17: Free entry, up to 250 characters | S17: Free entry, up to 50 characters | T17: Free entry, up to 50 characters
A18: What to enter | B18: True-up number - 1 after the legacy year-end close, 2 and 3 for interim true-ups, F for the final one after the audited FS | C18: Legacy journal voucher number | D18: Line of the legacy journal | E18: Value date of the legacy journal | F18: When the journal was posted in legacy | G18: Year-end closing or audit adjustment | H18: Reference of the journal in the FY2027 adjustment register | I18: Branch | J18: Account currency | K18: Legacy account | L18: Cost centre | M18: Debit in the account currency | N18: Credit in the account currency | O18: Debit in PHP | P18: Credit in PHP | Q18: Rate used for the PHP amount | R18: Journal line description | S18: Legacy user who prepared the journal | T18: Legacy user who approved the journal
A19: Row | B19: trueup_no * | C19: legacy_journal_no * | D19: line_no * | E19: legacy_journal_date * | F19: posted_at * | G19: adjustment_kind * | H19: register_ref * | I19: branch_code * | J19: currency * | K19: legacy_account_code * | L19: cost_center | M19: debit_fc * | N19: credit_fc * | O19: debit_php * | P19: credit_php * | Q19: fx_rate | R19: description * | S19: prepared_by * | T19: approved_by *
A20: Example – overwrite or delete | B20: 1 | C20: JV-2027-12-0457 | D20: 1 | E20: 2027-12-31 | F20: 2028-01-14 10:22:05 | G20: CLOSING | H20: ADJ-2027-014 | I20: MKT01 | J20: PHP | K20: 5120-01 | L20: 4100 | M20: 80000 | N20: 0 | O20: 80000 | P20: 0 | Q20: 56.125 | R20: Accrual of December 2027 professional fees | S20: cmp.jdelacruz | T20: cmp.head

Sheet G03D FY2027 true-up - open-item
A1: G03D FY2027 true-up - open-item detail of the lines on legacy control accounts | K1: Step 29 of 29
A2: ← Back to Load templates | B2: Step 29 of 29. Fill in one row per record below the column headers; the guide above each column says what to enter. | K2: Ask a question →
A3: Purpose | B3: One row per record of FY2027 opening-balance true-ups (legacy adjustment journals after the freeze and their open-item detail) as extracted from EBIX GL, ISYS GL; FY2027 adjustment register of Comptrollership. Key legacy_journal_no, line_no, item_ref, component. Sent as the file G03D_template.csv (CSV, header row as below) with its control file (row count, row count; amount totals per currency: amount).
A4: Provided by | B4: Comptrollership GL lead (prepares each true-up); approved by Head, Comptrollership; extracted by BDOI IT
A5: Due | B5: T+16 (true-up 1); T+92 (final)
A6: How it is loaded | B6: Data migration object G03 (Migrate), layout G03D version 1, through the Migration Console; lands in: General ledger journals of type OPENING (reference MIG-TU-<n>); opening adjustments of the legacy open items and unapplied payments
A7: Source | B7: EBIX GL, ISYS GL; FY2027 adjustment register of Comptrollership
A8: Depends on | B8: G03 FY2027 true-up - legacy adjustment journal lines after the freeze → | D8: G01 GL opening trial balance →
A9: Progress | B9: Rows entered | C9: =SUMPRODUCT(((ROW($B$20:$B$220)>20)+($B$20<>"1")>0)*(LEN($B$20:$B$220&$C$20:$C$220&$D$20:$D$220&$E$20:$E$220&$F$20:$F$220&$G$20:$G$220&$H$20:$H$220&$I$20:$I$220&$J$20:$J$220&$K$20:$K$220)>0)) | D9: Mandatory cells missing | E9: =SUMPRODUCT(((ROW($B$20:$B$220)>20)+($B$20<>"1")>0)*(LEN($B$20:$B$220&$C$20:$C$220&$D$20:$D$220&$E$20:$E$220&$F$20:$F$220&$G$20:$G$220&$H$20:$H$220&$I$20:$I$220&$J$20:$J$220&$K$20:$K$220)>0)*(($B$20:$B$220="")+($C$20:$C$220="")+($D$20:$D$220="")+($E$20:$E$220="")+($F$20:$F$220="")+($G$20:$G$220="")+($H$20:$H$220="")+($I$20:$I$220="")+($J$20:$J$220="")+($K$20:$K$220="")))
A10: Reviewed by (BU reviewer) | D10: Review date
A12: BU review
A13: BU comment
A14: Check when loaded | B14: Equals the G03 file | C14: Exists in G03 | D14: Exists in G03; the line is on a legacy control account | E14: In the list | F14: Item loaded | G14: In the list | H14: In the list | I14: Equals the item currency | J14: Open balance stays within 0 and booked + adjusted; detail per account equals the G03 line | K14: Not blank
A15: Mandatory | B15: Yes | C15: Yes | D15: Yes | E15: Yes | F15: Yes | G15: Yes | H15: Yes | I15: Yes | J15: Yes | K15: Yes
A16: Format | B16: Code, up to 2; As listed | C16: Code, up to 30; As in G03 | D16: Integer, up to 4; Digits | E16: Code, up to 8; Upper case | F16: Code, up to 40; As in F01 or F02 | G16: Code, up to 20; Upper case | H16: Code, up to 12; Upper case | I16: Code, up to 3; Upper case | J16: Amount, up to 19,2; Dot decimal, 2 decimals | K16: Text, up to 250; Free text
A17: Allowed values | B17: 1, 2, 3, F (list G03D trueup_no) | C17: legacy_journal_no of G03 | D17: line_no of G03 | E17: INVOICE, UPP (list G03D item_kind) | F17: legacy_invoice_no of F01 or legacy_upp_ref of F02 | G17: List G03D component: 14 values, see Reference lists | H17: ADJUSTED, WRITTEN_OFF (list G03D movement) | I17: ISO 4217 | J17: A number | K17: Free entry, up to 250 characters
A18: What to enter | B18: True-up number, as in G03 | C18: Legacy journal of the line | D18: Line of the legacy journal on the legacy control account | E18: Legacy invoice or legacy UPP | F18: Legacy invoice number (F01) or UPP reference (F02) | G18: Component adjusted (UPP for an unapplied item) | H18: Effect on the open item | I18: Currency of the item | J18: Change of the open balance - positive raises it, negative lowers it | K18: Reason or audit finding
A19: Row | B19: trueup_no * | C19: legacy_journal_no * | D19: line_no * | E19: item_kind * | F19: item_ref * | G19: component * | H19: movement * | I19: currency * | J19: amount * | K19: reason *
A20: Example – overwrite or delete | B20: 1 | C20: JV-2028-AUD-0003 | D20: 2 | E20: INVOICE | F20: I00300002 | G20: BASIC | H20: WRITTEN_OFF | I20: PHP | J20: -3000 | K20: Audit finding 7 - uncollectible premium written off

Sheet Reference lists
A1: Reference lists
A2: ← Back to Load templates | B2: Every list of allowed values used by the drop-downs, with its code and label. A drop-down accepts the codes of its list.
A4: List | B4: Used in | C4: Code | D4: Label | E4: Note
A5: Yes or no (YES_NO) | B5: R01 Lists of values and MIS val: active_flag R02 Branches and invoicing bran: invoicing_branch_flag R02 Branches and invoicing bran: active_flag R03 Sales organisation (units a: active_flag R05 Product lines, cover types,: packaged_flag R08 Chart of accounts mapping: branch_specific_flag C01 Client master: bank_client_flag C02 Client addresses and contac: primary_flag C03 Client payout accounts: active_flag P01 In-force policy headers: ffy_flag P01S Policy insurer shares: lead_flag F01 Open legacy invoices - head: dp_flag F01 Open legacy invoices - head: cwt_flag F01 Open legacy invoices - head: incentive_eligible_flag F01 Open legacy invoices - head: hold_flag F01S Open legacy invoices - ins: lead_flag | C5: Y | D5: Yes
C6: N | D6: No
A7: BU review (BU_REVIEW) | B7: R01 Lists of values and MIS val: BU review R02 Branches and invoicing bran: BU review R03 Sales organisation (units a: BU review R04 Insurers: BU review R04B Insurer branches: BU review R05 Product lines, cover types,: BU review R06 Package code map (legacy pa: BU review R07 Commission rates by insurer: BU review R08 Chart of accounts mapping: BU review R09 Payees: BU review R11 Receipt series in use: BU review C01 Client master: BU review C02 Client addresses and contac: BU review C03 Client payout accounts: BU review P01 In-force policy headers: BU review P01S Policy insurer shares: BU review F01 Open legacy invoices - head: BU review F01C Open legacy invoices - com: BU review F01S Open legacy invoices - ins: BU review F02 Unapplied premium payments: BU review F03 Open collection state: BU review F04 Remittance in flight: BU review F06 PDCs, check pick-ups and re: BU review G01 GL opening trial balance: BU review P03 Renewal advices already sen: BU review H01 Archive records (closed tra: BU review H02 Archive documents index: BU review G03 FY2027 true-up - legacy adj: BU review G03D FY2027 true-up - open-item: BU review | C7: Accept
C8: Change requested
C9: Comment
A10: R03 record_type (R03_RECORD_TYPE) | B10: R03 Sales organisation (units a: record_type | C10: REGION
C11: DEPARTMENT
C12: TEAM
C13: AO
A14: R06 qualifier (R06_QUALIFIER) | B14: R06 Package code map (legacy pa: qualifier | C14: RISK_CODE
C15: INSURER
C16: SI_BAND
A17: R06 action (R06_ACTION) | B17: R06 Package code map (legacy pa: action | C17: MAP
C18: REJECT
A19: R08 account_type (R08_ACCOUNT_TYPE) | B19: R08 Chart of accounts mapping: account_type | C19: ASSET
C20: LIABILITY
C21: EQUITY
C22: INCOME
C23: EXPENSE
A24: R08 normal_balance (R08_NORMAL_BALANCE) | B24: R08 Chart of accounts mapping: normal_balance | C24: DR
C25: CR
A26: R08 legacy_control_type (R08_LEGACY_CONTROL_TYPE) | B26: R08 Chart of accounts mapping: legacy_control_type | C26: PR
C27: PR2307
C28: DTIP
C29: COMMISSION_REC
C30: UNREALIZED_COMM
C31: DEFERRED_VAT
C32: UPP
C33: NONE
A34: R09 default_mode (R09_DEFAULT_MODE) | B34: R09 Payees: default_mode | C34: CTA
C35: ATD
C36: MC_DD
C37: CREDIT_TICKET
C38: TT
C39: ONLINE_BANKING
C40: CHECK
A41: R11 kind (R11_KIND) | B41: R11 Receipt series in use: kind | C41: AR
C42: OR
A43: C01 client_type (C01_CLIENT_TYPE) | B43: C01 Client master: client_type | C43: I
C44: C
A45: C02 record_type (C02_RECORD_TYPE) | B45: C02 Client addresses and contac: record_type | C45: ADDRESS
C46: CONTACT
A47: C02 address_type (C02_ADDRESS_TYPE) | B47: C02 Client addresses and contac: address_type | C47: HOME
C48: BUSINESS
C49: MAILING
C50: BILLING
A51: C03 mode (C03_MODE) | B51: C03 Client payout accounts: mode | C51: CTA
C52: CHECK
A53: P01 business_type (P01_BUSINESS_TYPE) | B53: P01 In-force policy headers: business_type | C53: NB
C54: RB
A55: P01 payment_arrangement (P01_PAYMENT_ARRANGEMENT) | B55: P01 In-force policy headers: payment_arrangement | C55: VIA_BDOI
C56: DIRECT
A57: P03 ra_channel (P03_RA_CHANNEL) | B57: P03 Renewal advices already sen: ra_channel | C57: EMAIL
C58: COURIER
C59: HAND
C60: OTHER
A61: F01 invoice_kind (F01_INVOICE_KIND) | B61: F01 Open legacy invoices - head: invoice_kind | C61: BOOKING
C62: ENDORSEMENT_PLUS
C63: ENDORSEMENT_MINUS
C64: CANCELLATION
A65: F01C component (F01C_COMPONENT) | B65: F01C Open legacy invoices - com: component | C65: BASIC
C66: DST
C67: PREMIUM_TAX_VAT
C68: LGT
C69: FST
C70: OTHER
C71: DTIP
C72: COMMISSION
C73: COMMISSION_VAT
C74: WTAX
C75: PR2307
A76: F02 channel (F02_CHANNEL) | B76: F02 Unapplied premium payments: channel | C76: OTC
C77: BILLS_PAYMENT
C78: TRADE
C79: CLPC
C80: DIRECT_CREDIT
C81: CHECK
C82: OTHER
A83: F02 disposition_status (F02_DISPOSITION_STATUS) | B83: F02 Unapplied premium payments: disposition_status | C83: MONITORING
C84: FOR_APPROVAL
C85: IN_PROCESS
A86: F03 record_type (F03_RECORD_TYPE) | B86: F03 Open collection state: record_type | C86: DISPOSITION
C87: PROMISE
C88: INSTALLMENT
C89: ASSIGNMENT
A90: F04 record_type (F04_RECORD_TYPE) | B90: F04 Remittance in flight: record_type | C90: HOLD
C91: SPECIAL
C92: BATCH
A93: F06 record_type (F06_RECORD_TYPE) | B93: F06 PDCs, check pick-ups and re: record_type | C93: PDC
C94: PICKUP
C95: REFUND
A96: G01 tb_version (G01_TB_VERSION) | B96: G01 GL opening trial balance: tb_version | C96: PROVISIONAL
C97: TU1
C98: TU2
C99: TU3
C100: FINAL
A101: G03 trueup_no (G03_TRUEUP_NO) | B101: G03 FY2027 true-up - legacy adj: trueup_no | C101: 1
...

Sheet Control file
A1: Control file
A2: The control file sent with every data file (<data file name>.ctl.csv): one row per measure
A4: No. | B4: Column | C4: What it holds | D4: Mandatory | E4: Format | F4: Example
A5: 1 | B5: object | C5: Object code of the data file | D5: Y | E5: Upper case; matches the file name | F5: F01
A6: 2 | B6: layout | C6: Layout (template) code | D6: Y | E6: Upper case; matches the header row | F6: F01C
A7: 3 | B7: source_system | C7: Source system: EBIX, QPS, ISYS, CMS or EXCEL | D7: Y | E7: Upper case; matches the file name | F7: EBIX
A8: 4 | B8: data_file | C8: Name of the data file the control file belongs to | D8: Y | E8: <LAYOUT>_<SOURCE>_<yyyyMMdd>_<nn>.csv or .xlsx | F8: F01C_EBIX_20271231_01.csv
A9: 5 | B9: as_of | C9: Date and time the data represents | D9: Y | E9: yyyy-MM-dd HH:mm:ss; not earlier than the previous extract of the layout | F9: 2027-12-31 22:00:00
A10: 6 | B10: extracted_at | C10: When the extract ran | D10: Y | E10: yyyy-MM-dd HH:mm:ss; after as_of | F10: 2028-01-01 00:40:12
A11: 7 | B11: extracted_by | C11: BDOI IT user who ran the extract | D11: Y | E11: Free text | F11: bdoi.it.jramos
A12: 8 | B12: measure | C12: Kind of control: ROW_COUNT, HASH_TOTAL, AMOUNT_TOTAL or SHA256 | D12: Y | E12: Upper case | F12: AMOUNT_TOTAL
A13: 9 | B13: column_name | C13: Column the measure applies to | D13: C | E13: As in the header; mandatory for HASH_TOTAL and AMOUNT_TOTAL | F13: open_balance
A14: 10 | B14: currency | C14: Currency of an AMOUNT_TOTAL | D14: C | E14: ISO 4217; mandatory for AMOUNT_TOTAL | F14: PHP
A15: 11 | B15: filter | C15: Optional filter of the measure | D15: N | E15: column=value | F15: component=BASIC
A16: 12 | B16: value | C16: Value of the measure | D16: Y | E16: Digits with a dot decimal for amounts; 64 hexadecimal characters for SHA256 | F16: 98450221.40

Sheet Control example
A1: Control example
A2: Example control file of F01C (made-up values)
A4: object | B4: layout | C4: source_system | D4: data_file | E4: as_of | F4: extracted_at | G4: extracted_by | H4: measure | I4: column_name | J4: currency | K4: filter | L4: value
A5: F01C | B5: F01C | C5: EBIX | D5: F01C_EBIX_20271231_01.csv | E5: 2027-12-31 22:00:00 | F5: 2028-01-01 00:40:12 | G5: bdoi.it.jramos | H5: ROW_COUNT | L5: 184220
A6: F01C | B6: F01C | C6: EBIX | D6: F01C_EBIX_20271231_01.csv | E6: 2027-12-31 22:00:00 | F6: 2028-01-01 00:40:12 | G6: bdoi.it.jramos | H6: HASH_TOTAL | I6: legacy_invoice_no | L6: 31207
A7: F01C | B7: F01C | C7: EBIX | D7: F01C_EBIX_20271231_01.csv | E7: 2027-12-31 22:00:00 | F7: 2028-01-01 00:40:12 | G7: bdoi.it.jramos | H7: AMOUNT_TOTAL | I7: open_balance | J7: PHP | K7: component=BASIC | L7: 98450221.40
A8: F01C | B8: F01C | C8: EBIX | D8: F01C_EBIX_20271231_01.csv | E8: 2027-12-31 22:00:00 | F8: 2028-01-01 00:40:12 | G8: bdoi.it.jramos | H8: AMOUNT_TOTAL | I8: open_balance | J8: PHP | K8: component=DTIP | L8: -84120775.15
A9: F01C | B9: F01C | C9: EBIX | D9: F01C_EBIX_20271231_01.csv | E9: 2027-12-31 22:00:00 | F9: 2028-01-01 00:40:12 | G9: bdoi.it.jramos | H9: AMOUNT_TOTAL | I9: open_balance | J9: USD | K9: component=BASIC | L9: 412330.00
A10: F01C | B10: F01C | C10: EBIX | D10: F01C_EBIX_20271231_01.csv | E10: 2027-12-31 22:00:00 | F10: 2028-01-01 00:40:12 | G10: bdoi.it.jramos | H10: AMOUNT_TOTAL | I10: booked | J10: PHP | L10: 1284533.75
A11: F01C | B11: F01C | C11: EBIX | D11: F01C_EBIX_20271231_01.csv | E11: 2027-12-31 22:00:00 | F11: 2028-01-01 00:40:12 | G11: bdoi.it.jramos | H11: SHA256 | L11: 3a7bd3e2360a3d29eea436fcfb7e44c735d117c42d1c1835420b6b9942dd4f1b

Sheet Control totals
A1: Control totals
A2: Control totals per layout; the tie-out sheet of reconciliation levels L1 to L3 in each run
A4: Layout | B4: Object | C4: Measure | D4: Column | E4: Currency | F4: How it is computed | G4: Value from BDOI | H4: Value in BIBS | I4: Difference | J4: Status
A5: R01 | B5: R01 | C5: ROW_COUNT | D5: - | E5: - | F5: Rows of the data file, header excluded
A6: R01 | B6: R01 | C6: HASH_TOTAL | D6: list_type, code | E6: - | F6: Count of distinct keys
A7: R01 | B7: R01 | C7: SHA256 | D7: - | E7: - | F7: SHA-256 of the data file as sent
A8: R02 | B8: R02 | C8: ROW_COUNT | D8: - | E8: - | F8: Rows of the data file, header excluded
A9: R02 | B9: R02 | C9: HASH_TOTAL | D9: branch_code | E9: - | F9: Count of distinct keys
A10: R02 | B10: R02 | C10: SHA256 | D10: - | E10: - | F10: SHA-256 of the data file as sent
A11: R03 | B11: R03 | C11: ROW_COUNT | D11: - | E11: - | F11: Rows of the data file, header excluded
A12: R03 | B12: R03 | C12: HASH_TOTAL | D12: record_type, unit_code, ao_user_id | E12: - | F12: Row count
A13: R03 | B13: R03 | C13: SHA256 | D13: - | E13: - | F13: SHA-256 of the data file as sent
A14: R04 | B14: R04 | C14: ROW_COUNT | D14: - | E14: - | F14: Rows of the data file, header excluded
A15: R04 | B15: R04 | C15: HASH_TOTAL | D15: insurer_code | E15: - | F15: Count of distinct keys
A16: R04 | B16: R04 | C16: SHA256 | D16: - | E16: - | F16: SHA-256 of the data file as sent
... A120: H02 | B120: H02 | C120: SHA256 | D120: - | E120: - | F120: SHA-256 of the data file as sent

Sheet Code maps
A1: Code maps
A2: Code map sets of the Migration Console (BRID_MIG 3.1): one per domain, versioned and approved by the business owner
A4: Code map | B4: What is mapped | C4: BIBS values | D4: Used by layouts | E4: Approves (G2) | F4: Prepares | G4: First approved version due | H4: BU review | I4: BU comment | J4: Reviewer | K4: Review date
A5: INSURER | B5: Legacy insurer code to BIBS insurer | C5: Insurers | D5: R04, R06, R07, P01S, P03, F01S, F04 | E5: Head, Operations | F5: Operations data steward | G5: M5 (18 Jun 2027)
A6: INSURER_BRANCH | B6: Legacy insurer branch to BIBS insurer branch | C6: Insurer branches | D6: R04B, P01S | E6: Head, Operations | F6: Operations data steward | G6: M5 (18 Jun 2027)
A7: LINE | B7: Legacy line of business to BIBS product line | C7: Product lines | D7: R05, P01, F01 | E7: Product Owner, MBS | F7: MBS data steward | G7: M5 (18 Jun 2027)
A8: COVER_TYPE | B8: Legacy cover type to BIBS cover type | C8: Cover types | D8: R05, P01 | E8: Product Owner, MBS | F8: MBS data steward | G8: M5 (18 Jun 2027)
A9: PRODUCT | B9: Legacy product / risk code to BIBS product code | C9: Products and risk codes | D9: R05, R06, R07, P01, F01 | E9: Product Owner, MBS | F9: MBS data steward | G9: M5 (18 Jun 2027)
A10: PACKAGE | B10: Legacy package and version to the BIBS package version maintained by TSU; conditional entries (risk code, insurer, sum-insured band) where one legacy package splits. Loaded as reference data (R06) for | C10: Package versions (Renewal package map) | D10: R06 | E10: Product Owner, MBS (approves) | F10: TSU (prepares) | G10: M5 (18 Jun 2027)
A11: BRANCH | B11: Legacy branch to BIBS branch | C11: Branches | D11: R02, R03, R11, C01, P01, F01, F02, G01, G03 | E11: Head, Comptrollership | F11: Comptrollership data steward | G11: M5 (18 Jun 2027)
A12: SALES_UNIT | B12: Legacy region, department and team to BIBS sales unit | C12: Sales units | D12: R03, C01, P01, F01, F02 | E12: Heads, Retail and Corporate Marketing | F12: Marketing data steward | G12: M5 (18 Jun 2027)
A13: AO | B13: Legacy AO code to BIBS account officer | C13: Account officers | D13: R03 | E13: Heads, Retail and Corporate Marketing | F13: Marketing data steward | G13: M5 (18 Jun 2027)
A14: USER | B14: Legacy user ID to BIBS username (AO, handler, collector, requester) | C14: BIBS users (User Access) | D14: R03, C01, P01, P03, F01, F03, F04 | E14: Unit Head, Analytics and Risk Management | F14: IT security administrator | G14: M5 (18 Jun 2027)
A15: COST_CENTER | B15: Legacy cost centre to BIBS cost centre | C15: Cost centres | D15: R03, F01, G01, G03 | E15: Head, Comptrollership | F15: Comptrollership data steward | G15: M5 (18 Jun 2027)
A16: GL_ACCOUNT | B16: Legacy GL account to BIBS account (legacy control accounts to Migration Clearing; lines on P&L accounts post to retained earnings in the opening and the true-ups) | C16: Chart of accounts | D16: R08, G01, G03 | E16: Head, Comptrollership | F16: Comptrollership data steward | G16: M5 (18 Jun 2027)
... A38: STATUS:UPP | B38: Legacy statuses of upp | C38: Status of the BIBS record | D38: C01, R04, R05, P01, F02, F04, F06 | E38: Owner of the object | F38: Steward of the object | G38: M5 (18 Jun 2027)

Sheet Code map template
A1: Code map template
A2: Columns of a code map version as exported and imported in Excel on the Code Maps screen (the columns source_system to remarks; illustrative rows)
A4: Code map | B4: source_system | C4: legacy_code | D4: legacy_description | E4: qualifier | F4: qualifier_value | G4: action | H4: target_code | I4: remarks | J4: Rows using it
A5: INSURER | B5: EBIX | C5: MAL | D5: Malayan Insurance Co., Inc. | G5: MAP | H5: INS-MAL | J5: 1,240
A6: INSURER | B6: QPS | C6: 0012 | D6: Malayan Insurance | G6: MAP | H6: INS-MAL | I6: QPS numeric code of the same insurer | J6: 310
A7: LOV:MARKET_SEGMENT | B7: QPS | C7: CBG | D7: Consumer Banking Group | G7: MAP | H7: CBG | J7: 88,410
A8: LOV:MARKET_SEGMENT | B8: QPS | C8: OLD-RET | D8: Retail (discontinued 2019) | G8: DEFAULT | I8: Segment discontinued; the default of the set applies | J8: 12
A9: PRODUCT | B9: EBIX | C9: MC-PC-COMP | D9: Private Car Own Damage and Theft | G9: MAP | H9: MCPC01 | J9: 41,002
A10: STATUS:UPP | B10: EBIX | C10: FOR_MONITORING | D10: For monitoring | G10: MAP | H10: MONITORING | I10: Monitoring tab of the Unapplied workbench | J10: 815
A11: USER | B11: QPS | C11: mreyes | D11: Maria Reyes | G11: MAP | H11: maria.reyes | I11: BIBS user created through User Access | J11: 3,112
A12: MIS:BUSINESS_ORIGIN | B12: QPS | C12: WALKIN | D12: Walk-in | G12: CREATE | H12: WALK_IN | I12: New MIS value; authorised in the LOV master | J12: 57
