Workbook

Sheet Cover
B6: REGISTER
B7: BRD Discrepancy and Clarification Register
B8: Discrepancies, conflicts, gaps and points for clarification in the BRDs (BRD-00 to BRD-13) and the Report List
B9: BIBS – BDOI Broker System
B11: Client | C11: BDO Insurance and Reinsurance Brokers, Inc.
B12: BRD | C12: BRD-00
B13: Version | C13: 1.2
B14: Date | C14: 26 September 2026
B15: Classification | C15: Confidential
B16: Prepared by | C16: iorta TechNXT
B18: Sheets
B19: Sheet | C19: Content | D19: Rows
B20: README | C20: What each column of each sheet means, with the allowed values
B21: Summary | C21: Counts by BRD, type and severity; status pivot; items to resolve first
B22: Register | C22: One row per discrepancy, conflict, gap or clarification. Filter on BRD, drop, type, severity or status. | D22: 239
B23: Open questions | C23: Every open question of the specs, with its status, the consolidated question and the register items. | D23: 453
B24: NFR comparison | C24: Every NFR theme against each BRD's value. Conflicting rows are highlighted; grey cells: not stated or 'follow QPS'. | D24: 18
B26: Legend
B27: Open | C27: Waiting for a BDOI answer
B28: Answered | C28: A signed BDOI document answers the item; BDOI confirms to close
B29: Closed | C29: BDOI confirmed the resolution
B31: Severity rule, types and status values: see the README sheet.
B32: Page numbers are PDF pages of the source files in docs/source-documents.
B33: The CSF pack holds meeting credentials in an attached e-mail (DCR-098); they are not copied here.
B35: Prepared by iorta TechNXT for BDOI. Confidential – BDOI.

Sheet README
A1: README – columns of each sheet
A2: BRD Discrepancy and Clarification Register, version 1.2. Drop-down columns accept only the listed values.
A4: Sheet | B4: Column | C4: Meaning | D4: Allowed values
A5: Register | B5: Ref | C5: Register reference DCR-nnn. Stable: a new item gets the next number.
A6: Register | B6: BRD(s) involved | C6: BRDs the item involves (BRD-n and short name; Report List where relevant). Several BRDs are separated by semicolons.
A7: Register | B7: Drop | C7: BDOI drop in which the item is resolved: Drop 0 (setup and data migration), Drop 1 (transactional), Drop 2 (independent), Programme (platform-wide) or Phase 2 (outside the January 2028 scope). Default: the earliest drop of the BRDs involved. | D7: Drop 0, Drop 1, Drop 2, Programme, Phase 2
A8: Register | B8: BRD ID / section / page | C8: Requirement ID, section and PDF page of the source file in docs/source-documents, for each BRD involved.
A9: Register | B9: Type | C9: Kind of issue (definitions below). | D9: Contradiction within BRD, Conflict between BRDs, Gap / missing detail, Ambiguity, BRD vs platform, NFR inconsistency, Data / numbering issue, Document quality
A10: Register | B10: Description | C10: What the BRD says, with the conflicting statements quoted briefly.
A11: Register | B11: Impact (business / build / test) | C11: Effect on the business process, on what is built, and on testing.
A12: Register | B12: Severity | C12: High, Medium or Low (rule below). | D12: High, Medium, Low
A13: Register | B13: Affected modules | C13: BIBS modules affected.
A14: Register | B14: Proposed resolution / recommendation | C14: What the project proposes, and builds as the default until BDOI answers.
A15: Register | B15: Clarification question to BDOI | C15: The question BDOI is asked to answer.
A16: Register | B16: Owner (BDOI) | C16: BDOI business unit that owns the answer, from the BRD approval sheets. Items involving several BRDs go to the BIBS Product Owner with the owners involved.
A17: Register | B17: Raised on | C17: Date the item was raised.
A18: Register | B18: Status | C18: Open, Answered or Closed (rule below). | D18: Open, Answered, Closed
A19: Register | B19: BDOI response | C19: BDOI's answer, or the signed BDOI document that answers the item.
A20: Register | B20: Resolution date | C20: Date the item was Closed.
A21: Register | B21: Related question IDs | C21: Open-question IDs of the specs (CRQ, Q, OQ, PQ, CQ, AQ, RQ, CLQ, EBQ, CSQ, SP-SQ, SANC-SQ, UQ, DMQ, IQ, DSQ, XQ; see the Open questions sheet) and related register items (DCR).
A22: Open questions | B22: Question ID | C22: Original ID of the question. SQ is used by two specs, so it is written SP-SQnn (Submitted Policies) and SANC-SQnn (Sanction Screening).
A23: Open questions | B23: BRD | C23: Spec that raised the question (Cross-BRD: BDOI_CROSS_BRD_DECISIONS.md).
A24: Open questions | B24: Topic | C24: Topic of the question.
A25: Open questions | B25: Question | C25: Question as asked in the spec.
A26: Open questions | B26: Source reference | C26: Requirement IDs and earlier questions the question refers to.
A27: Open questions | B27: Status | C27: Open, Partially answered (a later BRD answers part of it) or Answered. | D27: Open, Partially answered, Answered
A28: Open questions | B28: Answer so far (source) | C28: Short answer from a later BRD, with the answering document and ID.
A29: Open questions | B29: Consolidated under | C29: Primary question of the topic when several specs ask the same thing. Answer the primary question; the others follow.
A30: Open questions | B30: Same topic as | C30: For a primary question: the questions consolidated under it.
A31: Open questions | B31: Register items | C31: Register items (DCR) that cite the question.
A32: NFR comparison | B32: NFR theme | C32: Non-functional theme compared across the BRDs.
A33: NFR comparison | B33: BRD-0 CORE | C33: Value in BRD-0 CORE BDOI Core Replacement (umbrella), with the page.
A34: NFR comparison | B34: BRD-1 NB | C34: Value in BRD-1 NB New Business (NB), with the page.
A35: NFR comparison | B35: BRD-2 OPS | C35: Value in BRD-2 OPS Operations, with the page.
A36: NFR comparison | B36: BRD-3 PM | C36: Value in BRD-3 PM Product Maintenance, with the page.
A37: NFR comparison | B37: BRD-4 CLXN | C37: Value in BRD-4 CLXN Collections (CLXN), with the page.
A38: NFR comparison | B38: BRD-5 ACCT | C38: Value in BRD-5 ACCT Accounting, Disbursement and ACSL, with the page.
A39: NFR comparison | B39: BRD-6 RN | C39: Value in BRD-6 RN Renewal (RN), with the page.
... A49: NFR comparison | B49: Register items | C49: Register items on the theme.
A51: Severity rule
A52: High | B52: The item changes what is built or how data is structured, affects money (premium, commission, GL, remittance), regulatory compliance, security or access, or leaves a requirement without a testable result. Resolve before the FRS of the area is signed off.
A53: Medium | B53: The item changes a rule, value, screen, report or test case, but a documented default can be built now and changed later by configuration or a small change.
A54: Low | B54: Document quality only (typing, numbering, headings, working notes, names). No effect on the build; correct it in the next BRD revision.
A56: Types
A57: Contradiction within BRD | B57: Two statements in the same BRD pack cannot both be met.
A58: Conflict between BRDs | B58: Two BRDs give different owners, values, roles or rules for the same thing.
A59: Gap / missing detail | B59: A value, list, layout or rule needed to build or test is missing or marked TBD.
A60: Ambiguity | B60: The text can be read in more than one way.
A61: BRD vs platform | B61: The BRD differs from BIBS as built or designed, or assumes a legacy system (EBIX, QPS, ISYS) that BIBS replaces.
A62: NFR inconsistency | B62: Non-functional values (hours, availability, RPO / RTO, backup, retention, response time, session, password) differ within or between BRDs.
A63: Data / numbering issue | B63: Duplicate, missing or misnumbered requirement IDs, or data values that do not add up.
A64: Document quality | B64: Headings, names, dates, working notes, approvals or confidential content in the pack.
A66: Status
A67: Open | B67: Waiting for a BDOI answer.
A68: Answered | B68: A signed BDOI document answers the item (quoted in BDOI response). The project applies the answer; BDOI confirms to close.
A69: Closed | B69: BDOI confirmed the resolution. Resolution date is filled in.
A71: Sources
A72: BRD-0 CORE | B72: BDOI Core Replacement (umbrella): docs/source-documents/00 - BRD BDOI Core Replacement v01.pdf; baseline docs/requirements/BDOI_CORE_BRD_SPEC.md
A73: BRD-1 NB | B73: New Business (NB): docs/source-documents/New Business (NB) BRD.pdf; baseline docs/requirements/BDOI_NB_BRD_SPEC.md
A74: BRD-2 OPS | B74: Operations: docs/source-documents/Operations.pdf; baseline docs/requirements/BDOI_OPS_BRD_SPEC.md
A75: BRD-3 PM | B75: Product Maintenance: docs/source-documents/Product Maintenance.pdf; baseline docs/requirements/BDOI_PM_BRD_SPEC.md
A76: BRD-4 CLXN | B76: Collections (CLXN): docs/source-documents/Collections (CLXN) BRD.pdf; baseline docs/requirements/BDOI_CLXN_BRD_SPEC.md
A77: BRD-5 ACCT | B77: Accounting, Disbursement and ACSL: docs/source-documents/Accounting, Disbursement, and Accounting Controls and Subsidiary Ledger BRD.zip; baseline docs/requirements/BDOI_ACCT_BRD_SPEC.md
A78: BRD-6 RN | B78: Renewal (RN): docs/source-documents/Renewal (RN) BRD.pdf; baseline docs/requirements/BDOI_RN_BRD_SPEC.md
A79: BRD-7 CLM | B79: Claims (CLM): docs/source-documents/Claims (CLM).PDF; baseline docs/requirements/BDOI_CLM_BRD_SPEC.md
A80: BRD-8 EB | B80: Employee Benefits (EB): docs/source-documents/Employee Benefits.pdf; baseline docs/requirements/BDOI_EB_BRD_SPEC.md
A81: BRD-9 CSF | B81: Customer Servicing Facility (CSF): docs/source-documents/Customer Servicing Facility.PDF; baseline docs/requirements/BDOI_CSF_BRD_SPEC.md
A82: BRD-10 SANC | B82: Sanction Screening and Risk Profiling: docs/source-documents/Sanction Screening and Risk Profiling BRD.pdf; baseline docs/requirements/BDOI_SANC_BRD_SPEC.md
A83: BRD-11 UAM | B83: User Access Maintenance (UAM): docs/source-documents/User Access Maintenance.pdf; baseline docs/requirements/BDOI_UAM_BRD_SPEC.md
... A92: Refresh | B92: Edit docs/deliverables/src/registers/discrepancy_register.yaml and run python docs/deliverables/src/registers/build_discrepancy_register.py. Open questions are re-read from the specs at every build.

Sheet Summary
B1: Summary
B2: BRD Discrepancy and Clarification Register, version 1.2, 26 September 2026. 239 register items; 453 open questions from the BRD specs, the programme alignment, the document storage decision and the cross-BRD decisions.
B5: Items by severity and status
B6: Status pivot. Counts follow the Status column of the Register.
B7: Severity | C7: Open | D7: Answered | E7: Closed | F7: Total
B8: High | C8: =COUNTIFS('Register'!$H$5:$H$743,"High",'Register'!$N$5:$N$743,"Open") | D8: =COUNTIFS('Register'!$H$5:$H$743,"High",'Register'!$N$5:$N$743,"Answered") | E8: =COUNTIFS('Register'!$H$5:$H$743,"High",'Register'!$N$5:$N$743,"Closed") | F8: =SUM(C8:E8)
B9: Medium | C9: =COUNTIFS('Register'!$H$5:$H$743,"Medium",'Register'!$N$5:$N$743,"Open") | D9: =COUNTIFS('Register'!$H$5:$H$743,"Medium",'Register'!$N$5:$N$743,"Answered") | E9: =COUNTIFS('Register'!$H$5:$H$743,"Medium",'Register'!$N$5:$N$743,"Closed") | F9: =SUM(C9:E9)
B10: Low | C10: =COUNTIFS('Register'!$H$5:$H$743,"Low",'Register'!$N$5:$N$743,"Open") | D10: =COUNTIFS('Register'!$H$5:$H$743,"Low",'Register'!$N$5:$N$743,"Answered") | E10: =COUNTIFS('Register'!$H$5:$H$743,"Low",'Register'!$N$5:$N$743,"Closed") | F10: =SUM(C10:E10)
B11: Total | C11: =SUM(C8:C10) | D11: =SUM(D8:D10) | E11: =SUM(E8:E10) | F11: =SUM(F8:F10)
B13: Items by BRD
B14: An item that involves several BRDs is counted once for each BRD involved.
B15: BRD | C15: High | D15: Medium | E15: Low | F15: Total | G15: Open
B16: BRD-0 CORE - BDOI Core Replacement (umbrella) | C16: =COUNTIFS('Register'!$B$5:$B$743,"*BRD-0 CORE*",'Register'!$H$5:$H$743,"High") | D16: =COUNTIFS('Register'!$B$5:$B$743,"*BRD-0 CORE*",'Register'!$H$5:$H$743,"Medium") | E16: =COUNTIFS('Register'!$B$5:$B$743,"*BRD-0 CORE*",'Register'!$H$5:$H$743,"Low") | F16: =SUM(C16:E16) | G16: =COUNTIFS('Register'!$B$5:$B$743,"*BRD-0 CORE*",'Register'!$N$5:$N$743,"Open")
B17: BRD-1 NB - New Business (NB) | C17: =COUNTIFS('Register'!$B$5:$B$743,"*BRD-1 NB*",'Register'!$H$5:$H$743,"High") | D17: =COUNTIFS('Register'!$B$5:$B$743,"*BRD-1 NB*",'Register'!$H$5:$H$743,"Medium") | E17: =COUNTIFS('Register'!$B$5:$B$743,"*BRD-1 NB*",'Register'!$H$5:$H$743,"Low") | F17: =SUM(C17:E17) | G17: =COUNTIFS('Register'!$B$5:$B$743,"*BRD-1 NB*",'Register'!$N$5:$N$743,"Open")
B18: BRD-2 OPS - Operations | C18: =COUNTIFS('Register'!$B$5:$B$743,"*BRD-2 OPS*",'Register'!$H$5:$H$743,"High") | D18: =COUNTIFS('Register'!$B$5:$B$743,"*BRD-2 OPS*",'Register'!$H$5:$H$743,"Medium") | E18: =COUNTIFS('Register'!$B$5:$B$743,"*BRD-2 OPS*",'Register'!$H$5:$H$743,"Low") | F18: =SUM(C18:E18) | G18: =COUNTIFS('Register'!$B$5:$B$743,"*BRD-2 OPS*",'Register'!$N$5:$N$743,"Open")
B19: BRD-3 PM - Product Maintenance | C19: =COUNTIFS('Register'!$B$5:$B$743,"*BRD-3 PM*",'Register'!$H$5:$H$743,"High") | D19: =COUNTIFS('Register'!$B$5:$B$743,"*BRD-3 PM*",'Register'!$H$5:$H$743,"Medium") | E19: =COUNTIFS('Register'!$B$5:$B$743,"*BRD-3 PM*",'Register'!$H$5:$H$743,"Low") | F19: =SUM(C19:E19) | G19: =COUNTIFS('Register'!$B$5:$B$743,"*BRD-3 PM*",'Register'!$N$5:$N$743,"Open")
B20: BRD-4 CLXN - Collections (CLXN) | C20: =COUNTIFS('Register'!$B$5:$B$743,"*BRD-4 CLXN*",'Register'!$H$5:$H$743,"High") | D20: =COUNTIFS('Register'!$B$5:$B$743,"*BRD-4 CLXN*",'Register'!$H$5:$H$743,"Medium") | E20: =COUNTIFS('Register'!$B$5:$B$743,"*BRD-4 CLXN*",'Register'!$H$5:$H$743,"Low") | F20: =SUM(C20:E20) | G20: =COUNTIFS('Register'!$B$5:$B$743,"*BRD-4 CLXN*",'Register'!$N$5:$N$743,"Open")
B21: BRD-5 ACCT - Accounting, Disbursement and ACSL | C21: =COUNTIFS('Register'!$B$5:$B$743,"*BRD-5 ACCT*",'Register'!$H$5:$H$743,"High") | D21: =COUNTIFS('Register'!$B$5:$B$743,"*BRD-5 ACCT*",'Register'!$H$5:$H$743,"Medium") | E21: =COUNTIFS('Register'!$B$5:$B$743,"*BRD-5 ACCT*",'Register'!$H$5:$H$743,"Low") | F21: =SUM(C21:E21) | G21: =COUNTIFS('Register'!$B$5:$B$743,"*BRD-5 ACCT*",'Register'!$N$5:$N$743,"Open")
B22: BRD-6 RN - Renewal (RN) | C22: =COUNTIFS('Register'!$B$5:$B$743,"*BRD-6 RN*",'Register'!$H$5:$H$743,"High") | D22: =COUNTIFS('Register'!$B$5:$B$743,"*BRD-6 RN*",'Register'!$H$5:$H$743,"Medium") | E22: =COUNTIFS('Register'!$B$5:$B$743,"*BRD-6 RN*",'Register'!$H$5:$H$743,"Low") | F22: =SUM(C22:E22) | G22: =COUNTIFS('Register'!$B$5:$B$743,"*BRD-6 RN*",'Register'!$N$5:$N$743,"Open")
B23: BRD-7 CLM - Claims (CLM) | C23: =COUNTIFS('Register'!$B$5:$B$743,"*BRD-7 CLM*",'Register'!$H$5:$H$743,"High") | D23: =COUNTIFS('Register'!$B$5:$B$743,"*BRD-7 CLM*",'Register'!$H$5:$H$743,"Medium") | E23: =COUNTIFS('Register'!$B$5:$B$743,"*BRD-7 CLM*",'Register'!$H$5:$H$743,"Low") | F23: =SUM(C23:E23) | G23: =COUNTIFS('Register'!$B$5:$B$743,"*BRD-7 CLM*",'Register'!$N$5:$N$743,"Open")
B24: BRD-8 EB - Employee Benefits (EB) | C24: =COUNTIFS('Register'!$B$5:$B$743,"*BRD-8 EB*",'Register'!$H$5:$H$743,"High") | D24: =COUNTIFS('Register'!$B$5:$B$743,"*BRD-8 EB*",'Register'!$H$5:$H$743,"Medium") | E24: =COUNTIFS('Register'!$B$5:$B$743,"*BRD-8 EB*",'Register'!$H$5:$H$743,"Low") | F24: =SUM(C24:E24) | G24: =COUNTIFS('Register'!$B$5:$B$743,"*BRD-8 EB*",'Register'!$N$5:$N$743,"Open")
B25: BRD-9 CSF - Customer Servicing Facility (CSF) | C25: =COUNTIFS('Register'!$B$5:$B$743,"*BRD-9 CSF*",'Register'!$H$5:$H$743,"High") | D25: =COUNTIFS('Register'!$B$5:$B$743,"*BRD-9 CSF*",'Register'!$H$5:$H$743,"Medium") | E25: =COUNTIFS('Register'!$B$5:$B$743,"*BRD-9 CSF*",'Register'!$H$5:$H$743,"Low") | F25: =SUM(C25:E25) | G25: =COUNTIFS('Register'!$B$5:$B$743,"*BRD-9 CSF*",'Register'!$N$5:$N$743,"Open")
B26: BRD-10 SANC - Sanction Screening and Risk Profiling | C26: =COUNTIFS('Register'!$B$5:$B$743,"*BRD-10 SANC*",'Register'!$H$5:$H$743,"High") | D26: =COUNTIFS('Register'!$B$5:$B$743,"*BRD-10 SANC*",'Register'!$H$5:$H$743,"Medium") | E26: =COUNTIFS('Register'!$B$5:$B$743,"*BRD-10 SANC*",'Register'!$H$5:$H$743,"Low") | F26: =SUM(C26:E26) | G26: =COUNTIFS('Register'!$B$5:$B$743,"*BRD-10 SANC*",'Register'!$N$5:$N$743,"Open")
B27: BRD-11 UAM - User Access Maintenance (UAM) | C27: =COUNTIFS('Register'!$B$5:$B$743,"*BRD-11 UAM*",'Register'!$H$5:$H$743,"High") | D27: =COUNTIFS('Register'!$B$5:$B$743,"*BRD-11 UAM*",'Register'!$H$5:$H$743,"Medium") | E27: =COUNTIFS('Register'!$B$5:$B$743,"*BRD-11 UAM*",'Register'!$H$5:$H$743,"Low") | F27: =SUM(C27:E27) | G27: =COUNTIFS('Register'!$B$5:$B$743,"*BRD-11 UAM*",'Register'!$N$5:$N$743,"Open")
B28: BRD-12 SP - Submitted Policies (SP) | C28: =COUNTIFS('Register'!$B$5:$B$743,"*BRD-12 SP*",'Register'!$H$5:$H$743,"High") | D28: =COUNTIFS('Register'!$B$5:$B$743,"*BRD-12 SP*",'Register'!$H$5:$H$743,"Medium") | E28: =COUNTIFS('Register'!$B$5:$B$743,"*BRD-12 SP*",'Register'!$H$5:$H$743,"Low") | F28: =SUM(C28:E28) | G28: =COUNTIFS('Register'!$B$5:$B$743,"*BRD-12 SP*",'Register'!$N$5:$N$743,"Open")
B29: BRD-13 DM - Data Migration (draft v0.01) | C29: =COUNTIFS('Register'!$B$5:$B$743,"*BRD-13 DM*",'Register'!$H$5:$H$743,"High") | D29: =COUNTIFS('Register'!$B$5:$B$743,"*BRD-13 DM*",'Register'!$H$5:$H$743,"Medium") | E29: =COUNTIFS('Register'!$B$5:$B$743,"*BRD-13 DM*",'Register'!$H$5:$H$743,"Low") | F29: =SUM(C29:E29) | G29: =COUNTIFS('Register'!$B$5:$B$743,"*BRD-13 DM*",'Register'!$N$5:$N$743,"Open")
B30: Report List as of 27-Apr-2026 | C30: =COUNTIFS('Register'!$B$5:$B$743,"*Report List*",'Register'!$H$5:$H$743,"High") | D30: =COUNTIFS('Register'!$B$5:$B$743,"*Report List*",'Register'!$H$5:$H$743,"Medium") | E30: =COUNTIFS('Register'!$B$5:$B$743,"*Report List*",'Register'!$H$5:$H$743,"Low") | F30: =SUM(C30:E30) | G30: =COUNTIFS('Register'!$B$5:$B$743,"*Report List*",'Register'!$N$5:$N$743,"Open")
B31: Items involving two or more BRDs | C31: =COUNTIFS('Register'!$B$5:$B$743,"*;*",'Register'!$H$5:$H$743,"High") | D31: =COUNTIFS('Register'!$B$5:$B$743,"*;*",'Register'!$H$5:$H$743,"Medium") | E31: =COUNTIFS('Register'!$B$5:$B$743,"*;*",'Register'!$H$5:$H$743,"Low") | F31: =SUM(C31:E31) | G31: =COUNTIFS('Register'!$B$5:$B$743,"*;*",'Register'!$N$5:$N$743,"Open")
B33: Items by drop
B34: Drop in which the item is resolved (column Drop of the Register).
B35: Drop | C35: High | D35: Medium | E35: Low | F35: Total | G35: Open
B36: Drop 0 - Setup and Data Migration | C36: =COUNTIFS('Register'!$C$5:$C$743,"Drop 0",'Register'!$H$5:$H$743,"High") | D36: =COUNTIFS('Register'!$C$5:$C$743,"Drop 0",'Register'!$H$5:$H$743,"Medium") | E36: =COUNTIFS('Register'!$C$5:$C$743,"Drop 0",'Register'!$H$5:$H$743,"Low") | F36: =SUM(C36:E36) | G36: =COUNTIFS('Register'!$C$5:$C$743,"Drop 0",'Register'!$N$5:$N$743,"Open")
B37: Drop 1 - Transactional (upstream and downstream) | C37: =COUNTIFS('Register'!$C$5:$C$743,"Drop 1",'Register'!$H$5:$H$743,"High") | D37: =COUNTIFS('Register'!$C$5:$C$743,"Drop 1",'Register'!$H$5:$H$743,"Medium") | E37: =COUNTIFS('Register'!$C$5:$C$743,"Drop 1",'Register'!$H$5:$H$743,"Low") | F37: =SUM(C37:E37) | G37: =COUNTIFS('Register'!$C$5:$C$743,"Drop 1",'Register'!$N$5:$N$743,"Open")
B38: Drop 2 - Independent | C38: =COUNTIFS('Register'!$C$5:$C$743,"Drop 2",'Register'!$H$5:$H$743,"High") | D38: =COUNTIFS('Register'!$C$5:$C$743,"Drop 2",'Register'!$H$5:$H$743,"Medium") | E38: =COUNTIFS('Register'!$C$5:$C$743,"Drop 2",'Register'!$H$5:$H$743,"Low") | F38: =SUM(C38:E38) | G38: =COUNTIFS('Register'!$C$5:$C$743,"Drop 2",'Register'!$N$5:$N$743,"Open")
B39: Programme (cross-drop) | C39: =COUNTIFS('Register'!$C$5:$C$743,"Programme",'Register'!$H$5:$H$743,"High") | D39: =COUNTIFS('Register'!$C$5:$C$743,"Programme",'Register'!$H$5:$H$743,"Medium") | E39: =COUNTIFS('Register'!$C$5:$C$743,"Programme",'Register'!$H$5:$H$743,"Low") | F39: =SUM(C39:E39) | G39: =COUNTIFS('Register'!$C$5:$C$743,"Programme",'Register'!$N$5:$N$743,"Open")
B40: Phase 2 (outside the January 2028 scope) | C40: =COUNTIFS('Register'!$C$5:$C$743,"Phase 2",'Register'!$H$5:$H$743,"High") | D40: =COUNTIFS('Register'!$C$5:$C$743,"Phase 2",'Register'!$H$5:$H$743,"Medium") | E40: =COUNTIFS('Register'!$C$5:$C$743,"Phase 2",'Register'!$H$5:$H$743,"Low") | F40: =SUM(C40:E40) | G40: =COUNTIFS('Register'!$C$5:$C$743,"Phase 2",'Register'!$N$5:$N$743,"Open")
B42: Items by type
B43: Type | C43: High | D43: Medium | E43: Low | F43: Total | G43: Open
B44: Contradiction within BRD | C44: =COUNTIFS('Register'!$E$5:$E$743,"Contradiction within BRD",'Register'!$H$5:$H$743,"High") | D44: =COUNTIFS('Register'!$E$5:$E$743,"Contradiction within BRD",'Register'!$H$5:$H$743,"Medium") | E44: =COUNTIFS('Register'!$E$5:$E$743,"Contradiction within BRD",'Register'!$H$5:$H$743,"Low") | F44: =SUM(C44:E44) | G44: =COUNTIFS('Register'!$E$5:$E$743,"Contradiction within BRD",'Register'!$N$5:$N$743,"Open")
B45: Conflict between BRDs | C45: =COUNTIFS('Register'!$E$5:$E$743,"Conflict between BRDs",'Register'!$H$5:$H$743,"High") | D45: =COUNTIFS('Register'!$E$5:$E$743,"Conflict between BRDs",'Register'!$H$5:$H$743,"Medium") | E45: =COUNTIFS('Register'!$E$5:$E$743,"Conflict between BRDs",'Register'!$H$5:$H$743,"Low") | F45: =SUM(C45:E45) | G45: =COUNTIFS('Register'!$E$5:$E$743,"Conflict between BRDs",'Register'!$N$5:$N$743,"Open")
B46: Gap / missing detail | C46: =COUNTIFS('Register'!$E$5:$E$743,"Gap / missing detail",'Register'!$H$5:$H$743,"High") | D46: =COUNTIFS('Register'!$E$5:$E$743,"Gap / missing detail",'Register'!$H$5:$H$743,"Medium") | E46: =COUNTIFS('Register'!$E$5:$E$743,"Gap / missing detail",'Register'!$H$5:$H$743,"Low") | F46: =SUM(C46:E46) | G46: =COUNTIFS('Register'!$E$5:$E$743,"Gap / missing detail",'Register'!$N$5:$N$743,"Open")
B47: Ambiguity | C47: =COUNTIFS('Register'!$E$5:$E$743,"Ambiguity",'Register'!$H$5:$H$743,"High") | D47: =COUNTIFS('Register'!$E$5:$E$743,"Ambiguity",'Register'!$H$5:$H$743,"Medium") | E47: =COUNTIFS('Register'!$E$5:$E$743,"Ambiguity",'Register'!$H$5:$H$743,"Low") | F47: =SUM(C47:E47) | G47: =COUNTIFS('Register'!$E$5:$E$743,"Ambiguity",'Register'!$N$5:$N$743,"Open")
B48: BRD vs platform | C48: =COUNTIFS('Register'!$E$5:$E$743,"BRD vs platform",'Register'!$H$5:$H$743,"High") | D48: =COUNTIFS('Register'!$E$5:$E$743,"BRD vs platform",'Register'!$H$5:$H$743,"Medium") | E48: =COUNTIFS('Register'!$E$5:$E$743,"BRD vs platform",'Register'!$H$5:$H$743,"Low") | F48: =SUM(C48:E48) | G48: =COUNTIFS('Register'!$E$5:$E$743,"BRD vs platform",'Register'!$N$5:$N$743,"Open")
B49: NFR inconsistency | C49: =COUNTIFS('Register'!$E$5:$E$743,"NFR inconsistency",'Register'!$H$5:$H$743,"High") | D49: =COUNTIFS('Register'!$E$5:$E$743,"NFR inconsistency",'Register'!$H$5:$H$743,"Medium") | E49: =COUNTIFS('Register'!$E$5:$E$743,"NFR inconsistency",'Register'!$H$5:$H$743,"Low") | F49: =SUM(C49:E49) | G49: =COUNTIFS('Register'!$E$5:$E$743,"NFR inconsistency",'Register'!$N$5:$N$743,"Open")
B50: Data / numbering issue | C50: =COUNTIFS('Register'!$E$5:$E$743,"Data / numbering issue",'Register'!$H$5:$H$743,"High") | D50: =COUNTIFS('Register'!$E$5:$E$743,"Data / numbering issue",'Register'!$H$5:$H$743,"Medium") | E50: =COUNTIFS('Register'!$E$5:$E$743,"Data / numbering issue",'Register'!$H$5:$H$743,"Low") | F50: =SUM(C50:E50) | G50: =COUNTIFS('Register'!$E$5:$E$743,"Data / numbering issue",'Register'!$N$5:$N$743,"Open")
B51: Document quality | C51: =COUNTIFS('Register'!$E$5:$E$743,"Document quality",'Register'!$H$5:$H$743,"High") | D51: =COUNTIFS('Register'!$E$5:$E$743,"Document quality",'Register'!$H$5:$H$743,"Medium") | E51: =COUNTIFS('Register'!$E$5:$E$743,"Document quality",'Register'!$H$5:$H$743,"Low") | F51: =SUM(C51:E51) | G51: =COUNTIFS('Register'!$E$5:$E$743,"Document quality",'Register'!$N$5:$N$743,"Open")
B52: Total | C52: =SUM(C44:C51) | D52: =SUM(D44:D51) | E52: =SUM(E44:E51) | F52: =SUM(F44:F51) | G52: =SUM(G44:G51)
B54: Open questions
B55: From the Open questions sheet (status as recorded in the data file).
B56: Status | C56: Questions
B57: Open | C57: 370
B58: Partially answered | C58: 70
B59: Answered | C59: 13
B60: Consolidated under another question | C60: 99
B61: Total | C61: 453
B63: Resolve first
B64: The 15 items that most affect the build, money or compliance, in the order proposed for resolution.
B65: Item | C65: Ref | D65: Severity | E65: Status | F65: BRD(s) | H65: Why first
B66: 1. Directory sign-in (EIAM, Entra ID) for all users | C66: DCR-143 | D66: High | E66: Open | F66: Cross-BRD | H66: Identity source for every BIBS user; EIAM is a Drop 0 integration (DCR-230).
B67: 2. BIBS-wide user access matrix | C67: DCR-121 | D67: High | E67: Open | F67: BRD-11 UAM | H67: Every module's roles and persona tests depend on it.
B68: 3. IGA (UIDM-ISC) against BRD-11 requests | C68: DCR-229 | D68: High | E68: Open | F68: BRD-11 UAM, BRD-0 CORE | H68: Decides whether access requests stay in BIBS.
B69: 4. Go-live date and migration calendar | C69: DCR-217 | D69: High | E69: Open | F69: BRD-0 CORE, BRD-13 DM | H69: Fixes T, the freeze weekend and the mock dates.
B70: 5. Architecture in the IER | C70: DCR-222 | D70: High | E70: Open | F70: BRD-0 CORE | H70: The IER sizes and costs ten microservices, Aurora / Mongo and a portal tenant that BIBS does not have.
B71: 6. Documents in S3 only | C71: DCR-227 | D71: High | E71: Answered | F71: BRD-0 CORE, BRD-13 DM | H71: Build item ST0 / ST1 across every module that stores files.
B72: 7. Renewal of submitted policies: boundary | C72: DCR-129 | D72: High | E72: Open | F72: BRD-12 SP, BRD-6 RN | H72: Two BRDs specify the same renewal letters, hold cover and booking.
B73: 8. One LAMD intake or two | C73: DCR-146 | D73: High | E73: Open | F73: BRD-6 RN, BRD-12 SP | H73: Loan status drives both renewal eligibility and submitted-policy buckets.
B74: 9. Online vs offline renewal disposition | C74: DCR-062 | D74: High | E74: Open | F74: BRD-6 RN | H74: Decides the AO disposition screens and the upload path.
B75: 10. Manual initiation vs straight-through renewal | C75: DCR-063 | D75: High | E75: Open | F75: BRD-6 RN | H75: Decides the renewal workflow triggers.
B76: 11. Incentive programmes across four BRDs | C76: DCR-037 | D76: High | E76: Open | F76: Cross-BRD | H76: Incentive income; one model for Product Maintenance, Remittance and Commission.
... B80: 15. Go-live data migration scope | C80: DCR-157 | D80: High | E80: Open | F80: Cross-BRD | H80: Open items and history from EBIX, ISYS, QPS and Excel at cut-over.

Sheet Register
A1: Register
A2: One row per discrepancy, conflict, gap or clarification. Filter on BRD, drop, type, severity or status.
A4: Ref | B4: BRD(s) involved | C4: Drop | D4: BRD ID / section / page | E4: Type | F4: Description | G4: Impact (business / build / test) | H4: Severity | I4: Affected modules | J4: Proposed resolution / recommendation | K4: Clarification question to BDOI | L4: Owner (BDOI) | M4: Raised on | N4: Status | O4: BDOI response | P4: Resolution date | Q4: Related question IDs
A5: DCR-001 | B5: BRD-1 NB | C5: Drop 1 | D5: BRNB.029 / BRD 1.3.1.1.3 (p.68); BRNB.063 / BRD 1.3.1 (p.109-110, p.153) | E5: Contradiction within BRD | F5: BRNB.029: "Quotation/Proposal creation must require a client code." BRNB.063: "Generate a quotation/proposal reference number creation without client code." | G5: Business: walk-in and bank-referred prospects may not be quotable. Build: decides whether a prospect client code is created at quotation. Test: one of the two rows fails whichever rule is built. | H5: High | I5: Quotation; Client (CRM) | J5: Allow a quotation without a confirmed client, and create a prospect client code automatically at quotation (BRNB.029 then holds for the prospect code). | K5: Can a quotation be created before the client exists? If yes, may BIBS create a prospect client code automatically at that point? | L5: Marketing and Processing - New Business (Product Owner) | M5: 46290 | N5: Open | Q5: Q13, Q20
A6: DCR-002 | B6: BRD-1 NB | C6: Drop 1 | D6: Role matrix item 35 / 42 (p.124, p.127); BRD 2.1.16 (p.180) | E6: Data / numbering issue | F6: "Reactivate cancelled placed accounts" is in the role matrix and in legacy BRD 2.1.16, but no BRNB ID carries it, so it is missing from the BRNB consolidation. | G6: Build: the function is not traced to a governing requirement. Test: no acceptance criteria in the BRNB set. | H6: Medium | I6: Placement | J6: Add a BRNB ID for reactivation of cancelled placements, or confirm it is dropped. | K6: Is reactivation of a cancelled placement in scope? If yes, please confirm the BRNB ID and who may reactivate. | L6: Marketing and Processing - New Business (Product Owner) | M6: 46290 | N6: Open | Q6: Q25
A7: DCR-003 | B7: BRD-1 NB | C7: Drop 1 | D7: Workshop addendum (p.1-44): row "send generated service invoice" without ID | E7: Data / numbering issue | F7: The workshop addendum has an unnumbered row "send generated service invoice". It is traced as BRNB.100b in the baseline. | G7: Test: acceptance cannot cite an official ID. | H7: Low | I7: Booking | J7: Assign an ID in the next addendum revision; BRNB.100b is used until then. | K7: Please confirm the ID for "send generated service invoice" (proposed BRNB.100b). | L7: Marketing and Processing - New Business (Product Owner) | M7: 46290 | N7: Open | Q7: Q32
A8: DCR-004 | B8: BRD-1 NB | C8: Drop 1 | D8: BRNB.089 / BRD 3.4.3.1 (p.127) | E8: Document quality | F8: Under "a. Generate audit log report", criterion 1 reads "User should be able to assign cancel placement function", copied from the row above. | G8: Test: the criterion does not describe the audit log report. | H8: Low | I8: User Access; Reports | J8: Read criterion 1 as "generate the audit log report". | K8: Please confirm criterion 1 of BRNB.089 is "generate the audit log report". | L8: Marketing and Processing - New Business (Product Owner) | M8: 46290 | N8: Open
A9: DCR-005 | B9: BRD-1 NB | C9: Drop 1 | D9: Appendix A, Fire computation (p.216) | E9: Ambiguity | F9: Appendix A gives "PTX (Premium Tax) 12% of the Net Premium" for Fire, next to FST 2% and LGT. 12% is the VAT rate; the premium tax rate and base are not stated elsewhere. | G9: Business: gross premium on quotations and invoices is wrong if the rate is wrong. Build: premium calculator and tax table. Test: expected premiums in test cases. | H9: High | I9: Quotation; Product Maintenance (rates and taxes); Booking | J9: Keep tax rates and bases in the Rates and Taxes master; seed them only after Comptrollership confirms. | K9: For Fire, which taxes apply (VAT or premium tax, DST, FST, LGT), at what rate and on which base? Does BDOI compute them or copy the insurer's figures? | L9: Marketing and Processing - New Business (Product Owner) | M9: 46290 | N9: Open | Q9: Q43, PQ10
A10: DCR-006 | B10: BRD-1 NB | C10: Drop 1 | D10: Appendix A, Motor computation (p.216) | E10: Ambiguity | F10: OD / Theft cover formula gives two bases on one line: "81% of TSI" and "90% of TSI", without saying which applies when (new vs used vehicle, year of cover, multi-year). | G10: Business: Motor premium differs by 9 points of TSI. Build: motor rating rule. Test: expected premiums. | H10: High | I10: Quotation; Product Maintenance | J10: Model the OD / Theft base as a parameter per product and policy year until confirmed. | K10: When does the OD / Theft base use 81% of TSI and when 90%? Is it tied to multi-year policies (year 2 onwards)? | L10: Marketing and Processing - New Business (Product Owner) | M10: 46290 | N10: Open | Q10: Q35
A11: DCR-007 | B11: BRD-1 NB | C11: Drop 1 | D11: Addendum data retention (p.82); main BRD usage requirements (p.212) | E11: NFR inconsistency | F11: The addendum sets 5 years online, 15 years offline, backup every 4 hours, backup retention 5 years (p.82). The main BRD says "Follow existing QPS set up" (p.212). | G11: Build: retention and archive rules. The baseline applies the addendum (later document). | H11: Medium | I11: Platform (retention and archive) | J11: Apply the addendum values (5 / 15 years, 4-hour backup, 5-year backup retention). | K11: Please confirm that the addendum retention values replace "Follow existing QPS set up" for New Business. | L11: Marketing and Processing - New Business (Product Owner) | M11: 46290 | N11: Open | Q11: Q39, XQ08
A12: DCR-008 | B12: BRD-1 NB; BRD-11 UAM | C12: Drop 0 | D12: BRD-1 BRD 1.4.1.1 (p.93), 1.1.1.2-1.1.1.3 (p.137); BRD-11 BRD 1.001.1.2-1.001.1.3 (p.8), NFR 5 (p.17) | E12: Ambiguity | F12: BRD-1: "Receive warning 30 minutes prior to system triggered log out" after an inactivity warning at 15 minutes; it is unclear whether 30 minutes is an absolute session length. BRD-11 states "inactivity warning (15 minutes)" and "warning prior to system triggered log out (30 minutes)". | G12: Build: session timer. Test: logout timing cases. | H12: Medium | I12: Security (sessions) | J12: Inactivity log-out at 30 minutes with a warning at 15 minutes (SESSION_TIMEOUT_MINUTES = 30, SESSION_IDLE_WARNING_MINUTES = 15). | K12: Confirm that the 30 minutes is inactivity, not a maximum session length. | L12: UAM process owner (Product Owner) with ITIO | M12: 46290 | N12: Answered | O12: BRD-11 p.17 NFR 5: inactivity warning after 15 minutes, warning prior to system-triggered log out after 30 minutes. | Q12: Q42
A13: DCR-009 | B13: BRD-1 NB; BRD-6 RN; BRD-12 SP; Report List | C13: Drop 1 | D13: BRD-1 BRNB.018 (p.57); Report List #182 (p.57); BRD-6 reports 1.009.2-1.009.3 | E13: Conflict between BRDs | F13: BRNB.018 asks for a "Late Renewal Requests Report" in New Business. The Renewal BRD has no such report, and Report List #182 "Late Renewal" is a TSU package report ("This should be under a separate TSU module"). | G13: Build: no owner for the report. Test: BRNB.018 cannot be accepted. | H13: Medium | I13: Renewal; Reports | J13: Build it in Renewal as a variant of the renewal listing (renewals booked after expiry). | K13: Is the Late Renewal Requests Report still needed? If yes, is it the renewal listing filtered on late requests, and who uses it? | L13: Marketing and Processing - Renewal (RMEL) | M13: 46290 | N13: Open | Q13: Q09, RQ29, XQ09
A14: DCR-010 | B14: BRD-1 NB; BRD-6 RN; BRD-8 EB; BRD-12 SP | C14: Drop 1 | D14: BRNB.097 (BRD-1); BRRN.033 (BRD-6, p.4-15); BRID-022.01 (BRD-8 Add. p.10); BRIDSP-26 / 27 (BRD-12 p.11) | E14: BRD vs platform | F14: Four BRDs require New Business / Renewal classification from creation to the invoice and as a report filter. BIBS booking sets every invoice to NEW_BUSINESS (booking InvoiceBuilder, line 129). | G14: Business: renewal production cannot be reported apart from new business. Build: shared change BT0 (account business type, invoice, report filters). Test: every booking and production report test. | H14: High | I14: Account; Booking; Reports; Renewal; Employee Benefits; Submitted Policies | J14: Build work item BT0 once for all three BRDs: business type on the account, carried to the invoice and used as a report filter. | K14: Confirm the two values (New Business, Renewal) and that a renewal with changed terms stays a Renewal (BRRN.033). | L14: BIBS Product Owner, with the owners of the BRDs involved | M14: 46290 | N14: Answered | O14: BRRN.033 (BRD-6), BRID-022.01 (BRD-8) and BRIDSP-26 / 27 (BRD-12) require the classification at creation and as a report filter.
A15: DCR-011 | B15: BRD-2 OPS | C15: Drop 1 | D15: RMTID.002: main BRD (p.50) and Addendum 1 (p.3-4) | E15: Contradiction within BRD | F15: Main BRD: "Facility to allow User to edit the extracted file" and push it "with or without edit". Addendum 1: users "mark specific record or row for exclusion"; only non-excluded data is pushed; no editing of financial data. | G15: Build: remittance extraction screen. The addendum governs. | H15: Medium | I15: Remittance | J15: Build exclusion only (no edit of financial fields), per Addendum 1. | K15: None; recorded for traceability. BDOI to confirm the main-BRD wording is superseded. | L15: Operations - Financial Transactions and Processing | M15: 46290 | N15: Answered | O15: Operations Addendum 1 (p.3-4): exclusion instead of edit; "When the file is pushed to Disbursement, only non-excluded data" is sent.
A16: DCR-012 | B16: BRD-2 OPS | C16: Drop 1 | D16: ADJID.015 (p.96); MKTID.008 (Adjustment section) | E16: Data / numbering issue | F16: ADJID.015 (persona "User", "Note: This is a Marketing activity") and MKTID.008 describe the same Endorsement Slip. | G16: Build: one function, two IDs. Test: two rows cite one screen. | H16: Medium | I16: Adjustment | J16: Build the Endorsement Slip once, available to Marketing and Adjustment users. | K16: Who prepares the Endorsement Slip: Marketing, the Adjustment unit, or both? | L16: Operations - Financial Transactions and Processing | M16: 46290 | N16: Open | Q16: OQ32
A17: DCR-013 | B17: BRD-2 OPS | C17: Drop 1 | D17: RMTID.023 (p.62); PRCID.028 (p.85) | E17: Contradiction within BRD | F17: RMTID.023 (Remittance) and PRCID.028 (Production Reconciliation) both automate the early-remittance incentive. PRCID.028 limits it to CLG / CBG motor and fire; RMTID.023 does not. | G17: Business: incentive income may be computed twice or on the wrong lines. Build: one computation owner. Test: incentive amounts. | H17: High | I17: Remittance; Production Reconciliation; Commission | J17: One computation in Remittance, with eligible lines as data (CLG / CBG motor and fire at go-live). | K17: Is the early-remittance incentive one programme? Which lines and rates apply, and does the window start at inception or booking? | L17: Operations - Financial Transactions and Processing | M17: 46290 | N17: Open | Q17: OQ23, CQ24, AQ25
A18: DCR-014 | B18: BRD-2 OPS | C18: Drop 1 | D18: Summary 5.f (p.22); CSHID.016 (p.37-38); ADJID.026 (p.101) | E18: Contradiction within BRD | F18: Three minimal-balance rules: summary 5.f "Auto-reverse records with minimal balances (Php 10.00 and below) to AP overages"; CSHID.016 balances "<= Php 10.00" compared with PR2307; ADJID.026 "balances between 10.00 and 100.00 ... may be written off or credited". 10.00 is in both ranges. | G18: Business: small balances post to different GL accounts. Build: cashiering and adjustment rules. Test: boundary cases at 10.00. | H18: High | I18: Cashiering; Adjustment; FRBS / GL | J18: Up to 9.99 auto-reversed to AP overages; 10.00-100.00 write-off or credit through an adjustment. Thresholds as parameters. | K18: Please give one rule for small balances: the boundary at exactly 10.00, GL accounts, and who approves a write-off. | L18: Operations - Financial Transactions and Processing | M18: 46290 | N18: Open | Q18: OQ11, CQ03, OQ26
A19: DCR-015 | B19: BRD-2 OPS | C19: Drop 1 | D19: RMTID.014 (p.56-57) | E19: Contradiction within BRD | F19: RMTID.014 "Validate that paid AR is not more than" the DTIP balance: the expected result remits only the DTIP balance, while the acceptance criteria flag and exclude the account. | G19: Business: remittance to insurers is capped or withheld. Build: remittance validation. Test: expected result differs. | H19: High | I19: Remittance | J19: Flag and exclude the account from the batch until resolved (acceptance criteria). | K19: When paid AR is more than the DTIP balance, should BIBS remit the DTIP balance or exclude the account? | L19: Operations - Financial Transactions and Processing | M19: 46290 | N19: Open | Q19: OQ19
A20: DCR-016 | B20: BRD-2 OPS | C20: Drop 1 | D20: RMTID.019 (p.59) | E20: Ambiguity | F20: RMTID.019 "Validate remittance status upon submission" lists payment states (Unapplied Payment, With Outstanding Balance) together with remittance states. | G20: Build: remittance status model. Test: status transitions. | H20: Medium | I20: Remittance | J20: Keep payment state and remittance state as two separate fields. | K20: Please confirm the remittance status list and who approves a remittance batch (TL / TH). | L20: Operations - Financial Transactions and Processing | M20: 46290 | N20: Open | Q20: OQ21
A21: DCR-017 | B21: BRD-2 OPS | C21: Drop 1 | D21: Key capability f (p.21); CSHID.007 (p.29) | E21: Contradiction within BRD | F21: CSHID.007: "One OR per Remittance Batch number" and "OR is issued per individual payment unless consolidation" criteria are met. Key capability f: "one OR per settlement batch per Insurer". | G21: Business: number of ORs issued for commission. Build: OR generation. Test: OR count. | H21: Medium | I21: Cashiering; Commission | J21: One OR per remittance batch per insurer by default; individual OR as an option. | K21: For commission received from insurers, which prevails: one OR per remittance batch, or one per payment? | L21: Operations - Financial Transactions and Processing | M21: 46290 | N21: Open | Q21: OQ49
A22: DCR-018 | B22: BRD-2 OPS | C22: Drop 1 | D22: ADJID.002e (p.90), ADJID.010 (p.94); ADJID.004 item 4 (p.91) | E22: Contradiction within BRD | F22: "Extension of Cover" is a financial endorsement with additional premium and approval (ADJID.002e, ADJID.010) and a non-financial endorsement (ADJID.004: "extensions of cover/clauses/warranties/deductibles are added"). | G22: Business: approval and premium may be skipped. Build: endorsement type list. Test: endorsement cases. | H22: Medium | I22: Adjustment | J22: Two types: "Extension of cover (period, with premium)" and "Additional clause / warranty (no premium)". | K22: Please confirm the endorsement type list and who approves additional premium. | L22: Operations - Financial Transactions and Processing | M22: 46290 | N22: Open | Q22: OQ35
A23: DCR-019 | B23: BRD-2 OPS | C23: Drop 1 | D23: RMTID.001 (p.49); PRCID.004 (p.79); PRCID.016 (p.82); PRCID.024 / 025; ADJID.025 (p.100) | E23: Gap / missing detail | F23: Values left open in the signed BRD: "Batch Run: TDB" (RMTID.001); "Standard naming convention: TBD" (PRCID.004); company-concerned list "to be provided" (PRCID.016); automatch frequency blank (PRCID.024 / 025); supporting document list blank (ADJID.025). | G23: Build: defaults must be assumed. Test: no expected values. | H23: Medium | I23: Remittance; Production Reconciliation; Adjustment | J23: Build each as a parameter or list with a documented default. | K23: Please give the remittance extraction schedule, the production register naming, the company-concerned list, the automatch frequency and the endorsement document list. | L23: Operations - Financial Transactions and Processing | M23: 46290 | N23: Open | Q23: OQ17, OQ29, OQ30, OQ31, OQ32
A24: DCR-020 | B24: BRD-2 OPS | C24: Drop 1 | D24: CSHID.008 (p.30-31) | E24: Ambiguity | F24: Trade, Direct Credit and CLPC files are "manually prepared by BU, send to IT, IT to run batch process - FS04", while Operations users upload payment files. The PDC list is an Excel upload and also "PDC from PMS". | G24: Build: upload screen vs batch intake. Test: file intake cases. | H24: Medium | I24: Cashiering | J24: Operations users upload all files in BIBS; a scheduled pick-up from FS04 can be added later. | K24: Who loads each payment file (Operations or IT batch)? What is PMS? Please share sample files and layouts. | L24: Operations - Financial Transactions and Processing | M24: 46290 | N24: Open | Q24: OQ03, OQ04
A25: DCR-021 | B25: BRD-2 OPS | C25: Drop 1 | D25: CSHID.026 / 027, RMTID.038 / 040, ADJID.026-028, CMRID.015, MKTID.010-013 | E25: Data / numbering issue | F25: Several IDs have no key-capability number. MKTID numbering does not follow document order (MKTID.013 is in Cashiering, MKTID.008 comes last, in Adjustment). | G25: Traceability only. | H25: Low | I25: Operations (all) | J25: Trace by ID; key capability inferred from the section. | K25: None; correct in the next revision. | L25: Operations - Financial Transactions and Processing | M25: 46290 | N25: Open
A26: DCR-022 | B26: BRD-2 OPS; BRD-4 CLXN; BRD-5 ACCT; BRD-7 CLM | C26: Drop 1 | D26: BRD-2 BRQID.004-005 (p.16-20); BRD-4 p.37-39; BRD-5 DIS 3.25.0, FRBS 2.5.0; BRD-7 p.23 | E26: Conflict between BRDs | F26: BRD-2 treats Collection, Accounting, Disbursement, Marketing and Claims as other systems that Operations integrates with. BRD-4, BRD-5 and BRD-7 describe Collections, Accounting, Disbursement and Claims as functions inside the target system. | G26: Build: in-app interfaces instead of external integrations. | H26: Medium | I26: Cashiering; Remittance; Collections; Disbursement; FRBS / GL; Claims | J26: Collections, Disbursement, FRBS and Claims are BIBS modules; Operations uses in-app ports. | K26: Confirm that the Marketing (ISYS) link is the only external system left in BRQID.004. | L26: BIBS Product Owner, with the owners of the BRDs involved | M26: 46290 | N26: Answered | O26: BRD-4 p.37-39 (Collection Management System); BRD-5 DIS 3.25.0 and FRBS 2.5.0 (Disbursement and GL in the target system); BRD-7 p.23 (claims module). | Q26: OQ01, OQ02, OQ46
A27: DCR-023 | B27: BRD-2 OPS; BRD-4 CLXN | C27: Drop 1 | D27: BRD-2 MKTID.001-013; BRD-4 BRCLXN.016, p.41 | E27: Ambiguity | F27: MKTID (Marketing) and DBMID (Disbursement) rows are requirements on other units. BRD-4 covers only the 2307 and DP tagging dispositions; holds, special remittance, send-schedule and DP tagging at quotation (MKTID.001-009, 011) have no other BRD. | G27: Build: the Marketing screens stay in the Operations build. | H27: Medium | I27: Remittance; Collections; Adjustment | J27: MKTID.001-009 and 011 stay in Operations; MKTID.010 / 013 tagging moves to Collections dispositions. | K27: Confirm that Marketing performs holds, special remittance requests and the schedule request inside BIBS. | L27: Operations - Financial Transactions and Processing | M27: 46290 | N27: Open | Q27: OQ45
A28: DCR-024 | B28: BRD-2 OPS | C28: Drop 1 | D28: Annex I acronyms (p.124) | E28: Document quality | F28: The acronym table gives "DTIP - Due To Insurer Provider" and "BDOI - BDO Insurance Brokers, Inc." | G28: Glossary only. | H28: Low | I28: - | J28: Glossary uses "Due to Insurance Provider" and the registered company name. | K28: Please confirm the expansion of DTIP. | L28: Operations - Financial Transactions and Processing | M28: 46290 | N28: Open
A29: DCR-025 | B29: BRD-2 OPS | C29: Drop 1 | D29: Usage requirements, Commission Receivables (p.118-119) | E29: Gap / missing detail | F29: The Commission Receivables volume table is headed "Volume and Performance - Adjustment / Endorsement" (copy error). Transaction volumes and growth rates are blank for every area. | G29: Build: sizing assumed from BRD-1. Test: no volume targets for performance tests. | H29: Medium | I29: Platform (sizing) | J29: Size with the BRD-1 volumes plus Operations users. | K29: Please give monthly transaction volumes and growth per Operations area. | L29: Operations - Financial Transactions and Processing | M29: 46290 | N29: Open | Q29: OQ44
A30: DCR-026 | B30: BRD-2 OPS | C30: Drop 1 | D30: Addendum 1 approval (p.6) | E30: Document quality | F30: A reviewer date on the addendum approval page is written "1/6/2025"; the addendum is dated 18-Dec-2025, so it is probably 1/6/2026. | G30: Approval record only. | H30: Low | I30: - | J30: None. | K30: Please confirm the date. | L30: Operations - Financial Transactions and Processing | M30: 46290 | N30: Open
A31: DCR-027 | B31: BRD-1 NB; BRD-2 OPS | C31: Drop 1 | D31: BRD-1 BRNB.067 (p.114), BRNB.076 (p.118), BRNB.114; BRD-2 CSHID.008 (p.30), ADJID.001 / 003 / 011, MKTID.011 | E31: Conflict between BRDs | F31: The same functions are specified twice: CLPC payment matching before placement (BRNB.067 / 068) and CLPC payment upload (CSHID.008); endorsements and cancellation in booking (BRNB.076 / 081 / 094) and in Adjustment (ADJID.001 / 003 / 011); DP tagging (BRNB.114, MKTID.011). | G31: Business: two owners for one process. Build: risk of two payment intakes and two endorsement paths. Test: duplicated cases. | H31: High | I31: Placement; Booking; Cashiering; Adjustment | J31: Cashiering is the single payment intake and placement reads its result; Adjustment owns endorsements and cancellations after booking; Marketing raises the request. | K31: Confirm Cashiering as the single payment intake, and who raises (Marketing) and processes (Adjustment) endorsements. | L31: BIBS Product Owner, with the owners of the BRDs involved | M31: 46290 | N31: Open | Q31: OQ12, OQ32, OQ38
A32: DCR-028 | B32: BRD-2 OPS | C32: Drop 1 | D32: CSHID.026 (p.44); CSHID.027 / DBMID.001 | E32: Gap / missing detail | F32: For 2307 cash payments CSHID.026 says only "Premium is reversed" and the remittance is processed, with no accounting entries. CSHID.027 / DBMID.001 give Dr PR2307 / Cr PR and Dr DTIP / Cr PR2307. | G32: Business: GL entries for CWT unclear. Build: posting rules. Test: GL expected entries. | H32: High | I32: Cashiering; Remittance; FRBS / GL | J32: Post Dr PR2307 / Cr PR on application and Dr DTIP / Cr PR2307 when the 2307 batch is released with the remittance. | K32: Please give the entries for CSHID.026 and the moment Dr DTIP / Cr PR2307 is posted. | L32: Operations - Financial Transactions and Processing | M32: 46290 | N32: Open | Q32: OQ10, OQ16, AQ16
A33: DCR-029 | B33: BRD-3 PM | C33: Drop 0 | D33: BRPM.022 / BRPM.024 (p.31); earlier version BRQID.022 / 024 (p.36-61) | E33: Data / numbering issue | F33: BRPM.023 does not exist: BRPM.022 is followed by BRPM.024. The earlier signed version also skips BRQID.023. | G33: Traceability: a requirement may be missing. | H33: Low | I33: Product Maintenance | J33: Treat the gap as numbering only. | K33: Confirm that no requirement is missing at BRPM.023. | L33: Marketing Business Services (MBS) and TSU | M33: 46290 | N33: Open | Q33: PQ20
A34: DCR-030 | B34: BRD-3 PM | C34: Drop 0 | D34: Earlier signed version BRQID.008 (p.36-61); final BRPM.007 (p.17) | E34: Gap / missing detail | F34: The pack holds an earlier signed version (pp.36-61). Its BRQID.008 required documented client negotiation before a new rate scheme applies to a renewal already advised. The final version drops it without a revision-log entry and keeps only "old packages locked for new business but accessible for renewals". | G34: Business: a renewal could be repriced after the RA without client evidence. Build: renewal acceptance evidence. | H34: Medium | I34: Product Maintenance; Renewal | J34: BRRN.038 AC 3 (acceptance evidence when a renewal has a financial impact) covers the dropped rule; no separate Product Maintenance control. | K34: Confirm that BRQID.008 was dropped on purpose and that BRRN.038 now governs. | L34: Marketing Business Services (MBS) and TSU | M34: 46290 | N34: Open | Q34: PQ10
A35: DCR-031 | B35: BRD-3 PM | C35: Drop 0 | D35: Addendum p.2, p.3, p.4, p.8; main BRD approval p.34, p.59 | E35: Document quality | F35: Copied headings: the addendum is titled "Business Requirements for New Business" (p.3) and "Table of New Business Requirements" (p.4); its approval says "New Business Fire and Motor" (p.8); the main BRD approval says "for the OPERATIONS request" (p.34, p.59). Revision log: "Added BRID PMADD07 and PMADD07" (p.2); preparer date "11/06/205" (p.34). | G35: Approval record: the signatures refer to another BRD title. | H35: Low | I35: - | J35: None for the build. | K35: Please confirm the approvals apply to Product Maintenance, and correct the headings in the next revision. | L35: Marketing Business Services (MBS) and TSU | M35: 46290 | N35: Open
A36: DCR-032 | B36: BRD-3 PM | C36: Drop 0 | D36: Addendum table, column "Source BRD ID" (p.4-7) | E36: Gap / missing detail | F36: The "Source BRD ID" column is empty for every PMADD row, so the addendum does not say which main-BRD rows it refines. Read against the main BRD: PMADD06 details BRPM.015, PMADD04 details BRPM.010 / 013, PMADD03 details BRPM.014, PMADD05 details BRPM.002. | G36: Test: acceptance may be run against the superseded wording. | H36: Medium | I36: Product Maintenance | J36: Use the mapping above. | K36: Please confirm the PMADD to BRPM mapping. | L36: Marketing Business Services (MBS) and TSU | M36: 46290 | N36: Open
A37: DCR-033 | B37: BRD-3 PM | C37: Drop 0 | D37: BRPM.003 (p.16); BRPM.013 (p.23) | E37: Data / numbering issue | F37: BRPM.003 has no priority level. BRPM.013 names the keying of insurer terms, but its acceptance criteria describe comparative tables and a monitoring sheet. | G37: Test: BRPM.013 criteria do not test the requirement. | H37: Low | I37: Product Maintenance | J37: Treat BRPM.003 as Must have; test BRPM.013 on the capture of insurer terms. | K37: Confirm the priority of BRPM.003 and the acceptance criteria of BRPM.013. | L37: Marketing Business Services (MBS) and TSU | M37: 46290 | N37: Open | Q37: PQ06
A38: DCR-034 | B38: BRD-3 PM; BRD-1 NB | C38: Drop 0 | D38: BRD-3 BRPM.018 (p.28); BRD-1 BRNB.011 | E38: Contradiction within BRD | F38: BRPM.018 is titled "Placement Update Reports" but its result speaks of "Package Status Update Reports" of package creation. BRD-1 already has a Placement Update Report (BRNB.011). | G38: Build: two reports with one name. Test: wrong report tested. | H38: Medium | I38: Product Maintenance; Reports | J38: Name it "Package Status Update Report", separate from the BRD-1 Placement Update Report. | K38: Confirm BRPM.018 is a package status report and give its columns. | L38: Marketing Business Services (MBS) and TSU | M38: 46290 | N38: Open | Q38: PQ15
A39: DCR-035 | B39: BRD-3 PM | C39: Drop 0 | D39: Addendum footnote 2 (p.4); approval p.8; earlier version p.49 | E39: Ambiguity | F39: Persona "User": "User could be but not limited to Marketing AO, TSU, Processing. User roles and authorization will be further defined in succeeding documentations." MBS and ManCom are not defined in the final version. | G39: Build: role-to-action matrix (PMADD05) has no agreed content. Test: access tests. | H39: Medium | I39: Product Maintenance; User Access | J39: Seed roles from the design persona list; BDOI confirms the matrix. | K39: Please provide the Product Maintenance role-to-action matrix and the ManCom membership and decision rule. | L39: Marketing Business Services (MBS) and TSU | M39: 46290 | N39: Open | Q39: PQ07, PQ17, OQ48
A40: DCR-036 | B40: BRD-3 PM | C40: Drop 0 | D40: Revision log (p.11); PMADD01 (p.4) | E40: Gap / missing detail | F40: The revision log of 27-Oct-2025 says "Exclude Non-Package and include this as part of an addendum". The April 2026 addendum does not add it; PMADD01 mentions "non-package items if/when added". | G40: Build: scope of product maintenance for non-package products is undefined. | H40: Medium | I40: Product Maintenance | J40: Non-package product maintenance out of this phase; non-package placement stays in New Business. | K40: Confirm that maintenance of non-package products is out of scope for this phase. | L40: Marketing Business Services (MBS) and TSU | M40: 46290 | N40: Open | Q40: PQ19
A41: DCR-037 | B41: BRD-3 PM; BRD-5 ACCT; BRD-2 OPS; BRD-4 CLXN | C41: Drop 0 | D41: BRD-3 PMADD07 / 08 (p.6-7); BRD-5 DIS 3.29.0-3.29.2 (Workshop addendum p.1-15); BRD-2 CMRID.003-006; BRD-4 BRCLXN.061-062 (draft) | E41: Conflict between BRDs | F41: Incentives are specified in four BRDs: criteria on the products matrix "(i.e. CPC2)" (BRD-3, no definition); CPC2 as package Fire / Motor incentive computed per remittance, and early incentive with service invoice and 2% withholding (BRD-5); No Touch, Top Up and Motor Mania schemes (BRD-2); incentive campaigns (BRD-4 draft rows). No BRD gives rates, tiers or targets. | G41: Business: incentive income and pass-on to branches. Build: one incentive model across modules. Test: no expected values. | H41: High | I41: Product Maintenance; Remittance; Commission; Collections; FRBS / GL | J41: Criteria kept once in Product Maintenance; CPC2 and early incentive computed in Remittance; schemes in Commission reference the criteria. | K41: Please list the incentive programmes (CPC2, early remittance, No Touch, Top Up, Motor Mania, campaigns) with rates, base, period, payer and whether each is billed by service invoice. | L41: BIBS Product Owner, with the owners of the BRDs involved | M41: 46290 | N41: Open | Q41: PQ04, OQ39, Q33, AQ24, CQ24, SP-SQ14
A42: DCR-038 | B42: BRD-3 PM; BRD-6 RN | C42: Drop 0 | D42: BRD-3 BRPM.017, key capabilities 11-13 (p.14); BRD-6 renewal scope | E42: Ambiguity | F42: BRPM.017 "package renewal" is the renewal of the package (insurer agreement); BRD-6 is the renewal of client policies. Both use "renewal". | G42: Test: scenarios may be mixed. | H42: Low | I42: Product Maintenance; Renewal | J42: Keep them apart: "package renewal" in Product Maintenance, "policy renewal" in Renewal. | K42: Confirm the reading. | L42: BIBS Product Owner, with the owners of the BRDs involved | M42: 46290 | N42: Open | Q42: PQ11
A43: DCR-039 | B43: BRD-4 CLXN | C43: Drop 1 | D43: Draft addendum (p.1-12, "x of 14"); signed addendum (p.13-22) | E43: Document quality | F43: The pack holds two versions of the workshop addendum. The draft ("x of 14", pages 13-14 not in the pack) has BRCLXN.049-064. The signed version stops at BRCLXN.060. BRCLXN.061-064 (commission, incentive campaigns, mixed payments) are therefore not approved. | G43: Business: scope of four requirements unclear. Build: rows designed as Draft. Test: no approved criteria. | H43: High | I43: Collections; Commission | J43: Build BRCLXN.061-064 only after BDOI confirms them. | K43: Are BRCLXN.061-064 in scope, and who owns them (Collections or Commission)? Please provide the signed version if it exists. | L43: Operations - Collections (Head of BDOI Operations) | M43: 46290 | N43: Open | Q43: CQ01, CQ19, CQ24
A44: DCR-040 | B44: BRD-4 CLXN | C44: Drop 2 | D44: Renumbering addendum (p.24-25) | E44: Document quality | F44: The Collections renumbering addendum has the page header "CLAIMS" and the heading "Addendum1: Claims". | G44: Approval record only. | H44: Low | I44: - | J44: None. | K44: None; correct in the next revision. | L44: Operations - Collections (Head of BDOI Operations) | M44: 46290 | N44: Open
A45: DCR-041 | B45: BRD-4 CLXN | C45: Drop 2 | D45: BRCLXN.001 (p.26); FRID-001 / RQID-001 (p.47) | E45: Contradiction within BRD | F45: FRID-001: outstanding premium receivable "at the Cover Number level". BRCLXN.001 (renumbering): "at the Invoice Number level". The change has no explanation. | G45: Build: grain of the collection list and the threshold rule (BRCLXN.003). Test: list totals. | H45: High | I45: Collections | J45: Invoice level (the governing BRCLXN wording), with totals per account and client. | K45: Confirm the invoice level, and whether the threshold applies per invoice, per account (ARN) or per client. | L45: Operations - Collections (Head of BDOI Operations) | M45: 46290 | N45: Open | Q45: CQ02, CQ03
A46: DCR-042 | B46: BRD-4 CLXN | C46: Drop 2 | D46: BRCLXN.036 (p.31); FRID-036 (p.49); FRID-039 / 040 (p.49) | E46: Data / numbering issue | F46: BRCLXN.036 adds a field "BOOKER - Should be name of the booker" that FRID-036 does not have. FRID-045-048 have no RQ ID, and RQ IDs jump from RQID-031 to RQID-033. | G46: Traceability only; the BOOKER field is built. | H46: Low | I46: Collections | J46: Follow the BRCLXN wording. | K46: None; confirm BOOKER is the user who booked the invoice. | L46: Operations - Collections (Head of BDOI Operations) | M46: 46290 | N46: Open | Q46: CQ11
A47: DCR-043 | B47: BRD-4 CLXN | C47: Drop 2 | D47: Stakeholder functions (p.43-46); handwritten caveat on the CMS approval (p.93); handwritten edit of FRID-015 (p.78) | E47: Contradiction within BRD | F47: Stakeholder functions include "Export the disposition list" and "View and export unapplied payment lists". The Head of BDOI Operations wrote on the approval sheet that export and download from the UI "may lead to slowdown & performance issues" and "were not part of the original requirement". | G47: Build: exports allowed or not. Test: export cases. | H47: Medium | I47: Collections; Reports | J47: Exports run as asynchronous jobs with row limits and a separate export permission. | K47: May Collections users export lists? If yes, which roles? | L47: Operations - Collections (Head of BDOI Operations) | M47: 46290 | N47: Open | Q47: CQ06
A48: DCR-044 | B48: BRD-4 CLXN | C48: Drop 1 | D48: NFR 3.04 (p.52), NFR 9.02 and 10.07 (p.53) | E48: Contradiction within BRD | F48: NFR 9.02: "For internal systems, concurrent open sessions should be allowed". NFR 10.07: "limit the number of concurrent sessions to a single device. An opened session to a different device will prompt a logoff on the previous device session." | G48: Security: session policy. Build: session registry. Test: multi-device login cases. | H48: High | I48: Security (sessions) | J48: Session log built; the single-device rule is enforced only after BDOI confirms it (parameter, off by default). | K48: Is one active session per user (a new device logs off the old one) required, and for all BIBS users or Collections only? | L48: Operations - Collections (Head of BDOI Operations) | M48: 46290 | N48: Open | Q48: CQ23, UQ09, XQ11
A49: DCR-045 | B49: BRD-4 CLXN; BRD-11 UAM | C49: Drop 0 | D49: BRD-4 NFR 3.04 (p.52); BRD-11 NFR 1.c-d (p.13) | E49: Conflict between BRDs | F49: BRD-4: "The system should not allow users to have multiple roles." BRD-11: "More than one user can be assigned to a role"; "User can have more than one role". | G49: Security: segregation of duties. Build: role assignment rule. | H49: High | I49: User Access; Security | J49: Several roles per user allowed (BRD-11 governs access BIBS-wide); incompatible role pairs can be blocked as a segregation rule. | K49: Confirm that the single-role rule is dropped, or name the role pairs that one user must not hold together. | L49: UAM process owner (Product Owner) with ITIO | M49: 46290 | N49: Answered | O49: BRD-11 p.13, NFR 1.d: "User can have more than one role." | Q49: CQ23, UQ09
A50: DCR-046 | B50: BRD-4 CLXN | C50: Drop 2 | D50: BRCLXN.036 / FRID-036 (p.31, p.49); FRID-041 / 042 (p.32, p.49); report fields (p.59-61) | E50: BRD vs platform | F50: The BRD is written for EBIX, QPS and the Automated Payment System: "EBIX INVOICE NUMBER - Should be in this format - I00622656", cover number, QPS reference, BDOI SYS REF, and a daily "For Application To Invoice" file loaded to FS04 "before 6:00 AM". In BIBS, invoices have BIBS numbers and payments are applied in the application. | G50: Build: validation of invoice numbers during migration. Test: field mapping. | H50: Medium | I50: Collections; Cashiering | J50: Accept BIBS invoice numbers, and legacy EBIX numbers only for migrated items; keep the FS04 file only if a downstream system still reads it. | K50: After go-live, is the daily application file to FS04 still needed? How should legacy fields (cover no., QPS ref., BDOI SYS REF) map to BIBS? | L50: Operations - Collections (Head of BDOI Operations) | M50: 46290 | N50: Open | Q50: CQ12, CQ13, CQ22
A51: DCR-047 | B51: BRD-4 CLXN | C51: Drop 1 | D51: Performance table (p.56-57); table numbers (p.58) | E51: Document quality | F51: Typing errors in the NFR tables: "6,0000" weekly volume, "3 minuntes". Tables carry template numbers "15a" and "23b". | G51: Weekly volume target unclear (6,000 or 60,000). | H51: Low | I51: Platform (sizing) | J51: Read as 6,000 per week. | K51: Please confirm the weekly report volume. | L51: Operations - Collections (Head of BDOI Operations) | M51: 46290 | N51: Open
A52: DCR-048 | B52: BRD-4 CLXN | C52: Drop 2 | D52: Signed addendum approval (p.22); CMS BRD sign-off (p.62-65) | E52: Document quality | F52: Signed addendum: one Product Owner "for regularization - on leave", Head of Comptrollership "not required", two approvers "with signing". The CMS BRD sign-off approver block is unsigned; approval is by e-mail (p.64-65). | G52: Governance: approval evidence incomplete for one Product Owner. | H52: Medium | I52: - | J52: None for the build. | K52: Please complete the regularization signature. | L52: Operations - Collections (Head of BDOI Operations) | M52: 46290 | N52: Open
A53: DCR-049 | B53: BRD-5 ACCT | C53: Drop 1 | D53: Workshop addendum (p.1-15, scanned); Addendum 1 approval text (p.38) | E53: Document quality | F53: The workshop addendum is titled "Financial Reporting, Disbursement and ACSL" and its purpose says "Business Requirements for New Business"; Addendum 1 approval text refers to "New Business Fire and Motor" (p.38). Page 13 of the scan is upside down. | G53: Approval record refers to another BRD. | H53: Low | I53: - | J53: None. | K53: Confirm the approvals apply to the Accounting, Disbursement and ACSL BRD. | L53: Comptrollership - FRBS, Disbursement and ACSL | M53: 46290 | N53: Open
A54: DCR-050 | B54: BRD-5 ACCT | C54: Drop 1 | D54: FRBS 3.6.0 (p.65-66); DIS 2.17.3 (p.90); DIS 2.24.1 (p.93-94); ACSL 2.5.4 (p.117-118); DIS 3.30.1 (workshop addendum); Addendum 1 (p.33-34) | E54: Data / numbering issue | F54: Duplicate IDs: FRBS 3.6.0 (items p and q), DIS 2.17.3 (verify / approve), DIS 2.24.1 (add / tag status), ACSL 2.5.4 (receive request / provide result), DIS 3.30.1 (cost centre / headcount report). Addendum 1 renames some (2.17.4, 2.24.2, 2.5.5); FRBS 3.6.0 and DIS 3.30.1 remain duplicated. Access rows in the Accounting and Disbursement tables are all "BRD 1.1.0-1.1.3". | G54: Traceability and test references are ambiguous. | H54: Medium | I54: FRBS / GL; Disbursement; ACSL | J54: Baseline uses FRBS 1.1.x / DIS 1.1.x for access rows and DIS 3.30.2 for the second DIS 3.30.1. | K54: Please confirm the renumbering of the remaining duplicates. | L54: Comptrollership - FRBS, Disbursement and ACSL | M54: 46290 | N54: Open
A55: DCR-051 | B55: BRD-5 ACCT | C55: Drop 1 | D55: MKT 1.20.0 (p.111); MKT 2.22.0 (p.111) | E55: Data / numbering issue | F55: Marketing request IDs jump from MKT 1.20.0 to MKT 2.22.0; there is no 2.21.0. | G55: Traceability only. | H55: Low | I55: Marketing Requests | J55: None. | K55: Confirm no requirement is missing. | L55: Comptrollership - FRBS, Disbursement and ACSL | M55: 46290 | N55: Open
A56: DCR-052 | B56: BRD-5 ACCT | C56: Drop 1 | D56: MKT 1.10.0 (p.107); Appendix D (p.152-153) | E56: Gap / missing detail | F56: MKT 1.10.0: "Refund Request Form (for refund requests) - populate the below details:" and no list follows. The fields exist only on the Appendix D form images. | G56: Build: mandatory fields of the RRF / RFP. Test: field validations. | H56: Medium | I56: Marketing Requests; Disbursement | J56: Use the Appendix D form fields as the field list. | K56: Please confirm the mandatory RRF and RFP fields. | L56: Comptrollership - FRBS, Disbursement and ACSL | M56: 46290 | N56: Open | Q56: AQ18
A57: DCR-053 | B57: BRD-5 ACCT | C57: Drop 1 | D57: DIS 2.7.8 (p.81); DIS 2.7.9 (p.82) | E57: Contradiction within BRD | F57: DIS 2.7.9 "Process Credit Ticket / TT": the expected result says "User should be able to process Demand" Draft, copied from DIS 2.7.8, while the steps describe the Credit Ticket / Telegraphic Transfer form. | G57: Test: expected result does not match the function. | H57: Medium | I57: Disbursement | J57: Read DIS 2.7.9 as Credit Ticket / TT processing. | K57: Confirm the expected result of DIS 2.7.9. | L57: Comptrollership - FRBS, Disbursement and ACSL | M57: 46290 | N57: Open | Q57: AQ14
A58: DCR-054 | B58: BRD-5 ACCT | C58: Drop 1 | D58: FRBS 2.6.0 and 2.6.1 (p.58); Addendum 1 FRBS 2.6.0 (p.35-36) | E58: Contradiction within BRD | F58: Main BRD FRBS 2.6.0: close previous-month GL books "every 2nd banking day of the current month". Addendum 1: close "on a preferred date and time in the current month". FRBS 2.6.1 still refers to the closing date of the previous month. | G58: Business: month-end close. Build: closing validation. Test: closing-date cases. | H58: Medium | I58: FRBS / GL | J58: Manual close on a date chosen in the current month (Addendum 1); FRBS 2.6.1 validates against that date. | K58: Confirm the closing rule and whether a closed month may be reopened. | L58: Comptrollership - FRBS, Disbursement and ACSL | M58: 46290 | N58: Open | Q58: AQ04
A59: DCR-055 | B59: BRD-5 ACCT | C59: Drop 1 | D59: Appendix A (p.143-144) | E59: Ambiguity | F59: Appendix A lists BIR Form 2550-M (monthly VAT) and payroll reports (SSS, 1601-C and others), although BIBS has no payroll. The last group ends with an unlabelled line "Referrers share in commission earned by BDOI. Computed at 2.5%/1% of fully paid commission", read as the service-fee definition. | G59: Build: reports with no data source in BIBS. Test: report scope. | H59: Medium | I59: FRBS / GL; Reports | J59: Payroll reports out of scope; 2550-M kept only if BDOI still files it. | K59: Is 2550-M still filed? Are payroll reports imported or out of scope? Confirm the service-fee definition. | L59: Comptrollership - FRBS, Disbursement and ACSL | M59: 46290 | N59: Open | Q59: AQ06, AQ07, AQ20
A60: DCR-056 | B60: BRD-5 ACCT | C60: Drop 1 | D60: DIS 2.17.x (p.33, p.68, p.90) | E60: Ambiguity | F60: Account funding requirements refer to the "Main BDOIR China bank account", funded "via Business Online banking (BOB)". | G60: Build: bank account master and funding flow. Test: funding cases. | H60: Medium | I60: Disbursement | J60: Bank accounts as master data; no bank name in code. | K60: Which bank holds the main disbursement account, which accounts fund it, and are both approvers required in order? | L60: Comptrollership - FRBS, Disbursement and ACSL | M60: 46290 | N60: Open | Q60: AQ10
A61: DCR-057 | B61: BRD-5 ACCT | C61: Drop 1 | D61: Main BRD availability (p.138); Addendum 1 availability (p.37) | E61: NFR inconsistency | F61: Main BRD: availability, downtime, maintenance and BCP "Follow existing QPS/EBIX Setup". Addendum 1: availability 100%, maintenance 7PM to 7AM, BCP threshold less than 3 days. 100% is not a measurable service level. | G61: Build: HA design. Test: availability cannot be verified at 100%. | H61: Medium | I61: Platform (availability) | J61: Apply Addendum 1 with a measurable target (for example 99.9% in service hours). | K61: Please give a measurable availability target for Accounting, Disbursement and ACSL. | L61: Comptrollership - FRBS, Disbursement and ACSL | M61: 46290 | N61: Open | Q61: AQ27, XQ08
A62: DCR-058 | B62: BRD-5 ACCT | C62: Drop 1 | D62: Current process (p.45); ACSL 2.16.0 (Addendum 1 p.34); DIS 3.27.2 | E62: BRD vs platform | F62: Current process: "A different invoice number is generated for transaction cancellations". ACSL 2.16.0 requires related transactions (booking, adjustment, cancellation) to be linked to a single invoice number. BIBS issues a new number per transaction. | G62: Business: BIR invoice uniqueness vs one reference per policy. Build: invoice numbering and sub-ledger. Test: ACSL reconciliation. | H62: High | I62: Booking; Adjustment; ACSL | J62: Keep a new BIR-compliant number per document, linked to a root invoice number shown on every related transaction. | K62: Is a root invoice number that links related transactions acceptable, or must the same invoice number be reused? | L62: Comptrollership - FRBS, Disbursement and ACSL | M62: 46290 | N62: Open | Q62: AQ29, Q32
A63: DCR-059 | B63: BRD-5 ACCT | C63: Drop 1 | D63: Role matrices (p.66-67, 102-103, 113, 126); scanned copies (p.181, 216-217, 227, 240) | E63: Document quality | F63: The role matrices lost their tick marks in the digital pages and were read from the scanned copies; a few ticks are ambiguous. | G63: Build: role grants. Test: access tests. | H63: Medium | I63: FRBS / GL; Disbursement; Marketing Requests; ACSL; User Access | J63: Roles built from the scans; BDOI confirms. | K63: Please confirm the role matrices, and that the verifier must differ from the maker. | L63: Comptrollership - FRBS, Disbursement and ACSL | M63: 46290 | N63: Open | Q63: AQ28, OQ48
A64: DCR-060 | B64: BRD-5 ACCT | C64: Drop 1 | D64: Business / System Admin table heading (p.127); DIS 2.23.x "Edit beginning check series" (p.93) | E64: Document quality | F64: The Business and System Administration table is headed "Accounting Controls and Subsidiary Ledger (ACSL) Unit Business Requirements". "Edit beginning check series" reads "User should be able to add edit series". | G64: None on the build. | H64: Low | I64: - | J64: None. | K64: None; correct in the next revision. | L64: Comptrollership - FRBS, Disbursement and ACSL | M64: 46290 | N64: Open
A65: DCR-061 | B65: BRD-6 RN | C65: Drop 1 | D65: BRD 1.009.1 (p.58), BRD 1.010.1 (p.76), BRD 1.011.1 (p.78), BRD 2.005.1 (p.84) | E65: Document quality | F65: Working notes are left in the signed main BRD: "Discussed - 11/20/2025" (p.58), "Start here - next meeting" (p.76), "Type text here" (p.78), "Resume here" (p.84). | G65: None on the build; shows the text was edited after the May 2025 signature. | H65: Low | I65: - | J65: None. | K65: Please confirm that the signed text is final and remove the notes in the next revision. | L65: Marketing and Processing - Renewal (RMEL) | M65: 46290 | N65: Open
A66: DCR-062 | B66: BRD-6 RN | C66: Drop 1 | D66: BRRN.018 / BRD 3.004.1 (p.31); main BRD section 2.004 (Online Dispositioning) | E66: Contradiction within BRD | F66: BRRN.018: "Dispositioning is performed outside the system, and the system's role is to accept a batch upload". The main BRD is "RMEL Phase 2 - Online Dispositioning" with AO disposition screens (2.004). | G66: Business: where AOs record dispositions. Build: disposition screens and upload. Test: both paths. | H66: High | I66: Renewal | J66: Build both: online disposition for AOs and batch upload for bulk segments (CLG, insurer files). | K66: Which segments disposition online and which by uploaded file? Who prepares the file and in which layout? | L66: Marketing and Processing - Renewal (RMEL) | M66: 46290 | N66: Open | Q66: RQ14, RQ15
A67: DCR-063 | B67: BRD-6 RN | C67: Drop 1 | D67: BRRN.021 (p.4); BRRN.031, 035, 039, 040 (p.9-15) | E67: Contradiction within BRD | F67: BRRN.021: "Extraction does not automatically trigger renewal"; accounts do not progress "without explicit user initiation". BRRN.035: an "Approve / Renew As Is" insurer response advances the renewal "without manual user action"; BRRN.031 / 039 / 040 require straight-through processing. | G67: Business: control over renewal start. Build: workflow triggers. Test: STP scenarios. | H67: High | I67: Renewal | J67: Explicit initiation step after extraction (CLG in bulk, Non-Mortgage individually); straight-through processing only after initiation. | K67: Confirm: initiation is always manual, and every step after initiation may run without user action. Is CBG STP initiated automatically? | L67: Marketing and Processing - Renewal (RMEL) | M67: 46290 | N67: Open | Q67: RQ02
A68: DCR-064 | B68: BRD-6 RN | C68: Drop 1 | D68: BRRN.025 (p.6) | E68: Ambiguity | F68: BRRN.025 sets the NRNS reminder "at the defined follow-up checkpoint (e.g., +90 days)" and "at the defined checkpoint (e.g., +90 days before expiry)". | G68: Build: reminder schedule. Test: reminder dates. | H68: Medium | I68: Renewal; Notifications | J68: Checkpoint as a parameter in days before expiry, default 90. | K68: Is the NRNS checkpoint 90 days before expiry, and what does "not yet submitted" mean? | L68: Marketing and Processing - Renewal (RMEL) | M68: 46290 | N68: Open | Q68: RQ18
A69: DCR-065 | B69: BRD-6 RN | C69: Drop 1 | D69: 1.003.4.1.1.21-24 (p.49-50); 3.003.4.1.8-21 (p.112-114); RA IDs 4.09.x (p.177-178); sections VIII / XI (p.145, p.177) | E69: Data / numbering issue | F69: Requirement IDs 1.003.4.1.1.21-24 are all labelled "1.21"; labels of 3.003.4.1.8-21 restart at 1.2; RA IDs use "4.09.x" instead of "4.009.x"; section "XI. Generate Renewal Advice" follows "VIII. Generate Report" (IX and X missing). | G69: Traceability of the expiring-list columns and RA rows. | H69: Low | I69: Renewal | J69: Baseline numbers the rows in page order. | K69: None; correct in the next revision. | L69: Marketing and Processing - Renewal (RMEL) | M69: 46290 | N69: Open
A70: DCR-066 | B70: BRD-6 RN | C70: Drop 1 | D70: BRD 4.001.1.1 (p.148); 4.09.x (p.177-178); BRRN.010 | E70: Contradiction within BRD | F70: In the Processing Officer section the requirement reads "Log in with a Operations Team Leader user profile" and the result "Processing Team Leader user profile". The RA encryption item (x.010.7.1) exists for the other personas but not for the Processing Officer, although BRRN.010 applies to all. | G70: Build: role of the Processing Officer; RA protection. Test: access and encryption cases. | H70: Medium | I70: Renewal; User Access | J70: Processing Officer logs in with its own profile; RA encryption applies to every persona (BRRN.010). | K70: Confirm the Processing Officer profile and that RA encryption applies to Processing Officers. | L70: Marketing and Processing - Renewal (RMEL) | M70: 46290 | N70: Open
A71: DCR-067 | B71: BRD-6 RN | C71: Drop 1 | D71: BRD 2.004.9 (p.84) | E71: Contradiction within BRD | F71: Requirement 2.004.9 locks accounts after RA generation ("account should be locked on the marketing side"); its result reads "User should be able to provide disposition and edit locked accounts". | G71: Build: edit lock. Test: expected result inverted. | H71: Medium | I71: Renewal | J71: Locked accounts cannot be edited by Marketing; the negative scenario is the test. | K71: What unlocks an account after RA generation, and may Processing still edit it? | L71: Marketing and Processing - Renewal (RMEL) | M71: 46290 | N71: Open | Q71: RQ12
A72: DCR-068 | B72: BRD-6 RN | C72: Drop 1 | D72: BRD 1.006 (p.54); 3.005.1 (p.117); 3.008.2.5; Addendum 1 BRRN.002 sources (p.22) | E72: Document quality | F72: Wording slips: "Transfer to account to other units" (1.006); "processing office (PO)" (3.005.1); 3.008.2.5 title "Return to the assigned Marketing TL" but result "Marketing AO or Marketing TL"; BRRN.002 cites source "BRD 3.003.4.1.1", an EBIX column that Addendum 1 puts out of scope. | G72: Minor; 3.008.2.5 recipient needs confirming. | H72: Low | I72: Renewal | J72: Return to the AO or TL who last handled the account. | K72: Confirm the recipient of a returned account (3.008.2.5). | L72: Marketing and Processing - Renewal (RMEL) | M72: 46290 | N72: Open
A73: DCR-069 | B73: BRD-6 RN | C73: Drop 1 | D73: Main BRD approval (p.188) | E73: Document quality | F73: The Unit Head Combank / Corbank approved the main BRD "with email approval (see attached)"; the e-mail is not in the pack. The Head of Comptrollership line is blank (p.189). | G73: Governance: approval evidence incomplete. | H73: Medium | I73: - | J73: None for the build. | K73: Please add the approval e-mail to the pack. | L73: Marketing and Processing - Renewal (RMEL) | M73: 46290 | N73: Open
A74: DCR-070 | B74: BRD-6 RN | C74: Drop 1 | D74: Summary counters 1.009.3.2 (p.70-74) | E74: Gap / missing detail | F74: The summary counters include "For ARF", "Renew to TSU", "Disapproved Accounts" and "unrenewed ... to other bank", which no disposition, reason or step in the BRD produces. ARF is not defined. | G74: Build: counters cannot be computed. Test: counter values. | H74: Medium | I74: Renewal; Reports | J74: Counters mapped to renewal stages; unmapped counters show zero until defined. | K74: Please define each of the 34 counters, including For ARF, Renew to TSU, Disapproved and to Other Bank. | L74: Marketing and Processing - Renewal (RMEL) | M74: 46290 | N74: Open | Q74: RQ10, Q10
A75: DCR-071 | B75: BRD-6 RN | C75: Drop 1 | D75: Usage requirements (p.186-188); Addendum 1 out of scope (p.21, p.34) | E75: Contradiction within BRD | F75: Availability, downtime, maintenance, DR, retention and anonymisation are "Follow existing QPS set up", while Addendum 1 states "Requirements referencing BDOIsys, EBIX, or QPS ... are excluded". | G75: Build: no NFR values for Renewal. Test: no targets. | H75: Medium | I75: Platform | J75: Apply the BIBS-wide NFR set once agreed (DCR-133 to DCR-139). | K75: Please give the Renewal NFR values (availability, maintenance, DR, retention). | L75: Marketing and Processing - Renewal (RMEL) | M75: 46290 | N75: Open | Q75: RQ28, XQ08
A76: DCR-072 | B76: BRD-6 RN | C76: Drop 1 | D76: BRRN.010 negative scenario (p.28) | E76: Ambiguity | F76: BRRN.010 treats sending the RA "outside BDOI's approved domains or without TLS" as a data-privacy violation, but clients use any e-mail domain. | G76: Build: recipient policy for RA e-mails. Test: sending rules. | H76: Medium | I76: Renewal; Notifications | J76: Send to the registered client e-mail over TLS; restrict only internal copies to BDO domains. | K76: What are the "approved domains"? Is the RA sent to the client, the AO or the bank unit? | L76: Marketing and Processing - Renewal (RMEL) | M76: 46290 | N76: Open | Q76: RQ16, Q07
A77: DCR-073 | B77: BRD-6 RN | C77: Drop 1 | D77: Reason 2.004.4.9 (p.83); BRRN.009; 3.004.4; counter 1.009.3.2.32 (p.74) | E77: Ambiguity | F77: "Non-renewable Accounts" is both a reason the AO selects (2.004.4.9) and a system tag (BRRN.009, 3.004.4) that triggers the NFR letter. | G77: Build: reason list vs tag. Test: NFR letter trigger. | H77: Medium | I77: Renewal | J77: System tag from the non-renewable risk codes; AO reason kept for manual cases. | K77: Is the NFR sent automatically on the system tag without review? Is NFR the same letter as NRL? | L77: Marketing and Processing - Renewal (RMEL) | M77: 46290 | N77: Open | Q77: RQ07
A78: DCR-074 | B78: BRD-6 RN | C78: Drop 1 | D78: BRRN.004 / BRRN.011 (p.23) | E78: BRD vs platform | F78: BRRN.004 / 011 require one scrollable view with no pagination. The BDO UX guidelines use a pager ("Showing 1 to n of N"). | G78: Build: grid pattern. Test: large list performance. | H78: Low | I78: Renewal | J78: Virtualised grid with a row count, no pager. | K78: Is a virtualised scrollable grid with a total row count acceptable? | L78: Marketing and Processing - Renewal (RMEL) | M78: 46290 | N78: Open | Q78: RQ05
A79: DCR-075 | B79: BRD-6 RN; BRD-3 PM | C79: Drop 0 | D79: BRD-6 Addendum 1 out of scope (p.34), BRRN.005; BRD-3 BRPM.007 | E79: Gap / missing detail | F79: Addendum 1 excludes requirements that reference BDOIsys, EBIX or QPS, but policies booked in EBIX / QPS that expire after go-live are not in BIBS. No requirement covers loading them for renewal. | G79: Business: first-year renewals of legacy policies could be missed. Build: one-time load of expiring policies. Test: renewal list completeness. | H79: High | I79: Renewal; Data migration | J79: One-time load of policies expiring in the first 12 months after go-live, keyed by the EBIX invoice number. | K79: Is a load of expiring legacy policies required? From which system, and for how many months of expiry? | L79: Marketing and Processing - Renewal (RMEL) | M79: 46290 | N79: Open | Q79: RQ27, RQ06, CQ07
A80: DCR-076 | B80: BRD-6 RN | C80: Drop 1 | D80: Workshop addendum heading (p.4); Addendum 1 page header vs approval text (p.19-38) | E80: Document quality | F80: The Renewal workshop addendum table is titled "Table of New Business Requirements" (p.4). Addendum 1 pages are headed "Renewal Addendum" while the approval text says "RMEL Phase 2 - Online Dispositioning request". | G80: None on the build. | H80: Low | I80: - | J80: None. | K80: None; correct in the next revision. | L80: Marketing and Processing - Renewal (RMEL) | M80: 46290 | N80: Open
A81: DCR-077 | B81: BRD-6 RN | C81: Drop 1 | D81: Main BRD rows, column "Process Step" (p.44-185); workshop addendum "Source BRD ID" column (p.4-15) | E81: Gap / missing detail | F81: Main BRD rows carry a "Process Step" (1-6) but the process flow they refer to is not in the pack. The workshop addendum leaves "Source BRD ID" empty for BRRN.020-040. | G81: Traceability of BRRN.020-040 to the persona steps is inferred. | H81: Low | I81: Renewal | J81: Mapping in the Renewal spec, section 4. | K81: Please provide the process flow and the source IDs of BRRN.020-040. | L81: Marketing and Processing - Renewal (RMEL) | M81: 46290 | N81: Open
A82: DCR-078 | B82: BRD-7 CLM | C82: Drop 2 | D82: BRCLM.014 (p.14); overview (p.23); target process (p.27); stakeholder matrix (p.28) | E82: Ambiguity | F82: The "Requested Type of Settlement" values are outcomes (e.g. "Closed - Denied", "Settled - LOA Issued"). The overview lists "Settlement Types" and "Settlement Status" separately, and p.27 / p.28 ask to "Maintain Settlement Type Status values" with no ID and no values. | G82: Business: claim closure and reporting. Build: status and settlement model. Test: closure cases. | H82: High | I82: Claims | J82: One settlement-type list with a "closes claim" flag, maintained as a list of values. | K82: Are settlement type and settlement status one list or two? Which values close the claim? | L82: Claims and Risk Management | M82: 46290 | N82: Open | Q82: CLQ05, CLQ28
A83: DCR-079 | B83: BRD-7 CLM | C83: Drop 2 | D83: BRCLM.005 (p.13); BRCLM.035 (p.16); stakeholder matrix (p.28) | E83: Contradiction within BRD | F83: Claims Officers "Tag closures as temporary or permanent" (p.28, BRCLM.035), while closing a claim is a Team Head / Team Lead permission (BRCLM.005). | G83: Build: closure permissions. Test: access cases. | H83: Medium | I83: Claims | J83: Officers set temporary closure; TL / TH close permanently and reopen. | K83: Who may close a claim permanently, and who may reopen it? | L83: Claims and Risk Management | M83: 46290 | N83: Open | Q83: CLQ06
A84: DCR-080 | B84: BRD-7 CLM | C84: Drop 2 | D84: Retention table NFR 25.18-25.25 (p.41) | E84: Contradiction within BRD | F84: Audit logs are archived "16 years" while every record type is purged "after 15 years". The table header says "Values on the table are sample requirements you can use" (also the capacity table, p.39). | G84: Build: retention rules; whether the values are binding. Test: purge cases. | H84: Medium | I84: Claims; Platform (retention) | J84: Treat the values as requirements; audit logs purged after 16 years. | K84: Are the capacity and retention values requirements or samples? Is the audit-log archive 15 or 16 years? | L84: Claims and Risk Management | M84: 46290 | N84: Open | Q84: CLQ24, Q39
A85: DCR-081 | B85: BRD-7 CLM | C85: Drop 2 | D85: Overview and assumptions (p.23) | E85: BRD vs platform | F85: The BRD asks for "a facility in eBIX" and assumes "the existing claims module is functional and can be enhanced"; assumption 3: "Data migration and integration with existing systems will be seamless". In BIBS the broker claims module is a new build; the platform's insurer-side claims module does not fit a broker. | G85: Build: new module; claims history must be migrated. Test: migration. | H85: Medium | I85: Claims; Data migration | J85: New broker claims module; open and historical claims migrated from EBIX / ISYS. | K85: Which open and historical claims (years, format) must be migrated? | L85: Claims and Risk Management | M85: 46290 | N85: Open | Q85: CLQ14
A86: DCR-082 | B86: BRD-7 CLM | C86: Drop 2 | D86: p.13 ("1BRCLM.004"); BRCLM.027, 029, 030; glossary (p.22); approval (p.9) | E86: Document quality | F86: ID printed "1BRCLM.004"; BRCLM.027, 029 and 030 have no process component; the glossary and references page is empty (CNR, CASA, LOA, PLA, CRF undefined); a reviewer name is printed "Dan Ace Cəuton". | G86: None on the build; acronyms need a glossary. | H86: Low | I86: Claims | J86: None. | K86: Please expand CNR and CASA. | L86: Claims and Risk Management | M86: 46290 | N86: Open | Q86: CLQ12
A87: DCR-083 | B87: BRD-7 CLM | C87: Drop 2 | D87: Workshop addendum purpose (p.4); BRCLM.037-043 (p.5-7) | E87: Ambiguity | F87: The workshop addendum "does not introduce a change in project scope", yet it adds seven must-have requirements (multi-location, claims-prone locations, insurer updates, location references, several insurer claim numbers). | G87: Business: scope baseline. Build: BRCLM.037-043 are baselined in scope. | H87: Medium | I87: Claims | J87: Treat BRCLM.037-043 as in scope. | K87: Confirm BRCLM.037-043 are in scope for the first release. | L87: Claims and Risk Management | M87: 46290 | N87: Open | Q87: CLQ16, CLQ17, CLQ18, CLQ19
A88: DCR-084 | B88: BRD-7 CLM; Report List | C88: Drop 2 | D88: BRD-7 report list (p.42-44); Report List claims reports (p.39-42) | E88: Conflict between BRDs | F88: The Report List names ISYS as source of the claims reports and adds fields (adjuster appointed, loss reserve, paid to date, last action date) and age brackets 0-30 / 31-60 / 61-90 / 91-180 / 181+ that the Claims BRD does not list. The BRD sends report files to a "Shared Drive" (p.39-40). | G88: Build: report layouts and delivery. Test: report columns. | H88: Medium | I88: Claims; Reports | J88: BIBS replaces ISYS for claims reports; columns from both documents; files kept in BIBS. | K88: Does BIBS replace ISYS for claims reporting? Confirm the columns and aging brackets and whether files must be placed on a shared drive. | L88: Claims and Risk Management | M88: 46290 | N88: Open | Q88: CLQ21, OQ43, OQ17
A89: DCR-085 | B89: BRD-7 CLM | C89: Drop 2 | D89: BRCLM.001; NFR 15.05 (p.39-40) | E89: Gap / missing detail | F89: BRCLM.001 blocks a claim on unpaid premium by disabling the "Claims Authorization Code", which is not defined (EBIX function, code to the insurer, or internal approval), nor is "unpaid" (any invoice of the policy year, the invoice covering the loss date, instalments, direct payment). | G89: Business: valid claims could be blocked. Build: premium validation rule. Test: claim intake cases. | H89: High | I89: Claims; Collections | J89: Block when the invoice covering the loss date has an outstanding balance, with TL / TH override and reason. | K89: What is the Claims Authorization Code, which unpaid invoices block a claim, and may a TL / TH override? | L89: Claims and Risk Management | M89: 46290 | N89: Open | Q89: CLQ01
A90: DCR-086 | B90: BRD-7 CLM; BRD-2 OPS | C90: Drop 1 | D90: BRD-7 BRCLM.010 statuses (p.13-14), current process (p.24-26); BRD-2 MKTID.009 | E90: Gap / missing detail | F90: Claims statuses include "With BDOI - For Transmittal of Settlement Check", but no BRD says whether claim money ever passes through BDOI (cheque payable to BDOI, fund transfer) or what is recorded for the transmittal. | G90: Business: cash handling. Build: Cashiering and Disbursement flows only if money passes through BDOI. Test: settlement cases. | H90: High | I90: Claims; Cashiering; Disbursement | J90: No claim money through BDOI; record cheque number, bank, amount and received / released dates only. | K90: Does BDOI ever receive or pay claim money? What must be recorded when transmitting a settlement cheque? | L90: Claims and Risk Management | M90: 46290 | N90: Open | Q90: CLQ10, OQ46
A91: DCR-087 | B91: BRD-8 EB | C91: Drop 2 | D91: BRID-001 (p.24); Turn-around-time annex (p.59) | E91: Contradiction within BRD | F91: BRID-001 sends the renewal advice "at a defined period (e.g., 180 days)" before expiry; the TAT annex says "Send renewal notice to client: 135 days prior to inception date". | G91: Build: RA schedule. Test: RA dates. | H91: Medium | I91: Employee Benefits; Notifications | J91: Lead time as a parameter, default 135 days (the specific value). | K91: Is the EB renewal advice sent 180 or 135 days before expiry? How many reminders? | L91: Employee Benefits - Marketing, Processing and Collection | M91: 46290 | N91: Open | Q91: EBQ02
A92: DCR-088 | B92: BRD-8 EB | C92: Drop 2 | D92: BRID-008 (p.30-31); addendum flow (Add. p.4); main flow (p.22) | E92: Contradiction within BRD | F92: The BRID-008 negative scenario treats a BOR uploaded for a renewal transaction as invalid, while both flow charts request the BOR in the renewal lane. | G92: Build: BOR validation. Test: renewal with BOR. | H92: Medium | I92: Employee Benefits; Documents | J92: BOR required for new business and for renewals being remarketed to other insurers. | K92: When is a Broker on Record needed for a renewal: never, when remarketing, or always? | L92: Employee Benefits - Marketing, Processing and Collection | M92: 46290 | N92: Open | Q92: EBQ05, EBQ06
A93: DCR-089 | B93: BRD-8 EB | C93: Drop 2 | D93: Addendum out of scope (Add. p.13); main BRD BRID-028; current role matrix (p.58) | E93: Contradiction within BRD | F93: The addendum states "BRID-0028 as high risks account is not applicable to Employee Benefits", but BRID-028 remains in the main BRD and in the current role matrix. | G93: Build: none (OUT). | H93: Low | I93: Employee Benefits | J93: BRID-028 out of scope. | K93: Confirm that no high-risk handling applies to EB. | L93: Employee Benefits - Marketing, Processing and Collection | M93: 46290 | N93: Answered | O93: EB Addendum p.13: "BRID-0028 as high risks account is not applicable to Employee Benefits." | Q93: EBQ26
A94: DCR-090 | B94: BRD-8 EB | C94: Drop 2 | D94: Addendum flow (Add. p.4); main flow (p.22) | E94: Gap / missing detail | F94: The addendum flow adds steps not in the main flow and without requirement rows: franchise approval before TOR release, and an ISACOM approval "if the policy will be awarded to a non-accredited provider". ISACOM and franchise are not defined. | G94: Build: approval steps. Test: no criteria. | H94: Medium | I94: Employee Benefits | J94: Franchise approval and ISACOM approval as optional workflow steps, off until defined. | K94: What is ISACOM and when is its approval needed? What is a franchise, and is it needed for the incumbent? | L94: Employee Benefits - Marketing, Processing and Collection | M94: 46290 | N94: Open | Q94: EBQ07, EBQ24
A95: DCR-091 | B95: BRD-8 EB | C95: Drop 2 | D95: Volumes per team (Add. p.14) | E95: Data / numbering issue | F95: Growth percentages do not match the figures: Voluntary 550 to 560 is shown as 3% (1.8%); BDO 400 to 550 as 38% (37.5%); Solicited 700 to 900 as 29% (28.6%). | G95: Sizing only. | H95: Low | I95: Platform (sizing) | J95: Use the absolute figures. | K95: None. | L95: Employee Benefits - Marketing, Processing and Collection | M95: 46290 | N95: Open
A96: DCR-092 | B96: BRD-8 EB | C96: Drop 2 | D96: Usage requirements (p.53-54) | E96: Gap / missing detail | F96: The EB usage table gives users only (Marketing 13, Processing 4, Collection 3); transaction volume, growth and expected response time are blank. Peak hours are written "08:30 - 07:00pm". Insurer and client portal users are not sized. | G96: Build: portal sizing. Test: no response-time target. | H96: Medium | I96: Employee Benefits; Insurer / Client Portal | J96: Apply the BIBS response-time target; size the portal after EBQ13. | K96: Please give response times, and the number of insurer and client portal users. | L96: Employee Benefits - Marketing, Processing and Collection | M96: 46290 | N96: Open | Q96: EBQ25, EBQ13
A97: DCR-093 | B97: BRD-8 EB | C97: Drop 2 | D97: Executive summary (p.20) | E97: Gap / missing detail | F97: The executive summary cites internal guidelines "MIS Credit / no payment no booking on adjustment"; no requirement row defines them. | G97: Business: booking of member movements. Build: adjustment booking rule. | H97: Medium | I97: Employee Benefits; Adjustment; Booking | J97: Book a member-movement adjustment only after payment, when the guideline applies. | K97: What is "MIS Credit", and does "no payment no booking" apply to every EB adjustment? | L97: Employee Benefits - Marketing, Processing and Collection | M97: 46290 | N97: Open | Q97: EBQ16
A98: DCR-094 | B98: BRD-8 EB | C98: Drop 2 | D98: BRID-007 (p.29); BRID-013, 014, 030 | E98: Gap / missing detail | F98: EB handles employee master lists and utilization reports (health-related data). The BRD has no data-privacy requirement (access, masking, retention) beyond password protection of outbound files. | G98: Business: Data Privacy Act exposure. Build: access classes and masking. Test: privacy tests. | H98: High | I98: Employee Benefits; Documents; Insurer / Client Portal | J98: Treat master lists and utilization as sensitive personal information: need-to-know access classes, download logging, encryption. | K98: Please confirm the access, masking and retention rules for member data and utilization reports. | L98: Employee Benefits - Marketing, Processing and Collection | M98: 46290 | N98: Open | Q98: EBQ15, XQ04
A99: DCR-095 | B99: BRD-8 EB | C99: Drop 2 | D99: Addendum revision log (Add. p.2); approval (p.55); TAT annex (p.59) | E99: Document quality | F99: Revision log starts "February 04,2025" (other entries 2026); an input date reads "11/124/2025"; the TAT annex still says "Booking in EBIX". | G99: None on the build. | H99: Low | I99: - | J99: None. | K99: None; correct in the next revision. | L99: Employee Benefits - Marketing, Processing and Collection | M99: 46290 | N99: Open
A100: DCR-096 | B100: BRD-8 EB; BRD-11 UAM | C100: Drop 0 | D100: BRD-8 BRID-005, 005.01-005.03, 014 (Add. p.7-13), envisioned process item 3 (Add. p.4); BRD-11 section 3 (p.6) | E100: Gap / missing detail | F100: EB gives insurers and clients "secure access to the system". These are the first external users of BIBS. No BRD defines their hosting, authentication (MFA), who creates and approves them, or several users per insurer / client. BRD-11 covers internal users only. | G100: Security: internet-facing access. Build: portal realm and user provisioning. Test: security tests. | H100: High | I100: Insurer / Client Portal; User Access; Security | J100: Portal users provisioned through User Access requests as external users (decision D7); hosting and MFA per BDO Information Security. | K100: Who creates and approves portal users? Hosting (DMZ), MFA and password policy for external users? | L100: BIBS Product Owner, with the owners of the BRDs involved | M100: 46290 | N100: Open | Q100: EBQ13, EBQ14, Q06
A101: DCR-097 | B101: BRD-8 EB; BRD-1 NB | C101: Drop 1 | D101: BRD-8 BRID-013; BRD-1 catalog of insurers | E101: BRD vs platform | F101: EB benefit lines include HMO, whose providers are not insurance companies. BIBS holds placement counterparties as insurers in the catalog. | G101: Build: catalog party type and commission rates for HMO providers. | H101: Medium | I101: Product Maintenance; Employee Benefits | J101: Hold HMO providers in the insurer master with a provider type. | K101: Please list the EB benefit lines and confirm HMO providers are held with the insurers. | L101: Employee Benefits - Marketing, Processing and Collection | M101: 46290 | N101: Open | Q101: EBQ01
...

Sheet Open questions
A1: Open questions
A2: Every open question of the specs, with its status, the consolidated question and the register items.
A4: Question ID | B4: BRD | C4: Topic | D4: Question | E4: Source reference | F4: Status | G4: Answer so far (source) | H4: Consolidated under | I4: Same topic as | J4: Register items
A5: CRQ01 | B5: BRD-0 CORE | C5: BRD set and ownership | D5: The umbrella lists ten BRDs (p.3) and cites a "User & Data Management" BRD (pp.38-41). Is it the umbrella over all twelve BRDs, the Data Migration BRD and the ReInsurance BRD? Who owns Data Management (capability 17)? | E5: CF-07, CORE-17 | F5: Open | J5: DCR-169, DCR-201
A6: CRQ02 | B6: BRD-0 CORE | C6: Non-Package Management | D6: Capability 4 (added 20-Nov-2025) has no BR ID and no traceability row. Please confirm it is the non-package placement of New Business (PRF, quotation slip, comparative table, proposal slip) and not the maintenance of non-package products (PQ19). | E6: CORE-04 | F6: Open | H6: PQ19 | J6: DCR-181
A7: CRQ03 | B7: BRD-0 CORE | C7: Claims cheques | D7: BR-146 to BR-148 ask for safekeeping of unclaimed cheques and hand-over to / retrieval from Cashiering. BRD-7 has no claim money through BDOI (CLQ10). Does BDOI hold settlement cheques? If yes, which unit keeps them, and what is recorded at hand-over and release? | E7: CORE-14.08-14.10 | F7: Open | H7: XQ13 | J7: DCR-164
A8: CRQ04 | B8: BRD-0 CORE | C8: CSF case management | D8: BR-165 asks for case resolution; BRD-9 e-mail item 10 keeps case logging in SharePoint. Which applies in phase 1? | E8: CORE-16.06 | F8: Open | H8: XQ12 | J8: DCR-163
A9: CRQ05 | B9: BRD-0 CORE | C9: Delete of prospect | D9: Is deactivation with a reason, followed by the retention purge, acceptable for "delete of prospect / record" (BR-008), or must a prospect be erased on request (for example under the Data Privacy Act)? | E9: CORE-01.04 | F9: Open | J9: DCR-182
A10: CRQ06 | B10: BRD-0 CORE | C10: Role dashboards | D10: Which figures does each role see on its home page (BR-125, 152, 160 say "to be defined")? Is one landing page per role expected, or the existing section homes? | E10: XC-02 | F10: Open | J10: DCR-178
A11: CRQ07 | B11: BRD-0 CORE | C11: Master data change log | D11: Which master data is in scope (users, products, insurers, LOVs, others)? Must the log show old and new values per field and the approver? Who views it? | E11: CORE-17.01 | F11: Open | J11: DCR-174
A12: CRQ08 | B12: BRD-0 CORE | C12: Insurer management | D12: What are "risk participation", "payment terms" and "remittance schedules" on the insurer record (BR-171)? Which unit maintains insurer records, and do changes need approval? | E12: CORE-17.02 | F12: Open | J12: DCR-176
A13: CRQ09 | B13: BRD-0 CORE | C13: MIS field definition | D13: Is BR-173 a fixed list of MIS fields per entity (as in its example) or a facility for users to add fields? Who maintains it? | E13: CORE-17.04 | F13: Open | J13: DCR-175, DCR-214
A14: CRQ10 | B14: BRD-0 CORE | C14: Emerging capabilities | D14: Capability 18 and BR-176 ("any other / additional system capabilities") cannot be tested. Please list the capabilities or withdraw the row. | E14: CORE-18.01 | F14: Open | J14: DCR-180
A15: CRQ11 | B15: BRD-0 CORE | C15: Report customisation and scheduling | D15: Which reports need user-chosen fields, charts and summaries? Who may schedule a report, how often, in which formats, and how is it delivered (e-mail, folder)? Is Word needed for all reports (EBQ21)? | E15: CORE-21.04, 21.05 | F15: Open | H15: Q40 | J15: DCR-177
A16: CRQ12 | B16: BRD-0 CORE | C16: SOA at booking | D16: Which SOA is generated with the placement report and Insurance Advice (BR-039) and with the insurer's service invoice at booking (BR-043): the client billing SOA or an insurer SOA? | E16: XC-10 | F16: Open | J16: DCR-171
A17: CRQ13 | B17: BRD-0 CORE | C17: Invoice Master List | D17: Is the Invoice Master List (BR-175) the Operations invoice ledger? Please confirm the columns (cover number, version number, assignees, placement status, approval dates) and the owner. | E17: XC-13 | F17: Open | J17: DCR-179
A18: CRQ14 | B18: BRD-0 CORE | C18: Letter names | D18: The umbrella writes "Non-Renewal Letter (NRL)", BRD-6 "Not for Renewal Letter (NFR)". Which name is printed on the letter? | E18: CORE-06.07 | F18: Open | J18: DCR-168
A19: CRQ15 | B19: BRD-0 CORE | C19: Bank account operations | D19: What does "Bank Account Operations" (p.9) cover beyond the account funding and bank instruments of BRD-5? | E19: CORE-08.21 | F19: Open
A20: CRQ16 | B20: BRD-0 CORE | C20: CSF resend | D20: Must CSF agents also resend e-policies (BR-164), or only RAs (BRCSF-006)? | E20: CORE-16.04 | F20: Open | J20: DCR-172
A21: CRQ17 | B21: BRD-0 CORE | C21: BDO design assets | D21: Please supply the BDO icon and illustration set and the design system or Figma files (BR-179, 180, 183). | E21: XC-14 | F21: Open | J21: DCR-187
A22: CRQ18 | B22: BRD-0 CORE | C22: Insurer invoice delivery | D22: For "Invoice Batch Printing" (p.43): what is the batch file (one PDF per insurer, a ZIP, a manifest), the SFTP endpoint per insurer, and does it replace the e-mail of each service invoice? | E22: XC-19 | F22: Open | J22: DCR-184
A23: CRQ19 | B23: BRD-0 CORE | C23: Client migration and feeds | D23: "One-time migration from Broker and source, 2020 to present" and the daily midday and EOD client batches (p.43): which source system, and for how long do the daily batches run? How does this fit the selective migration of the Data Migration BRD? | E23: XC-20, CF-11 | F23: Open | H23: DMQ05 | J23: DCR-173
A24: CRQ20 | B24: BRD-0 CORE | C24: ALeA | D24: What is ALeA, and what is "e-mail address encoding" (p.43)? | E24: XC-21 | F24: Open | J24: DCR-185
A25: CRQ21 | B25: BRD-0 CORE | C25: Response time and sizing | D25: Response under 5 seconds for every role (p.42) differs from nine BRDs; 429 concurrent users is the sum of the BRD rows. Which values govern the performance tests? | E25: CF-03, CF-04 | F25: Open | H25: XQ08 | J25: DCR-165, DCR-166
A26: CRQ22 | B26: BRD-0 CORE | C26: Retention and backup | D26: Do the umbrella values (5 / 15 years, backup every 4 hours kept 5 years) replace the BRD-specific ones (BRD-7 10 years online; BRD-5, 10, 12 five years archive; BRD-9 backup every 15 minutes; BRD-2 and BRD-8 backup kept 7 years)? | E26: CF-05 | F26: Open | H26: XQ08 | J26: DCR-167, DCR-209
A27: CRQ23 | B27: BRD-0 CORE | C27: Traceability workbook | D27: Please send "E2E BDOI Mapping.xlsx" (p.30) and confirm that the final IDs of each BRD (BRPM, BRRN, BRCLXN, BRCLM, BRCSF) govern where the umbrella cites earlier ones. | E27: CF-08, §10 | F27: Open | J27: DCR-170
A28: CRQ24 | B28: BRD-0 CORE | C28: User counts | D28: Employee Benefits 13 / 13 (umbrella) or 20 internal users (BRD-8)? Claims 67 / 26 or 47 / 25 (BRD-7)? Product Maintenance 13 / 13 or TSU 13 plus MBS 5? | E28: CF-04 | F28: Open | H28: XQ08 | J28: DCR-166
A29: CRQ25 | B29: BRD-0 CORE | C29: Approval of the umbrella | D29: The Product Owner for FRBS and ACSL is marked "On Mandatory Leave" without a signature; the Analytics and Risk Management head marks "sign-off not applicable"; four approvals are by e-mail only (pp.46-48). Is the document approved? | E29: §14 | F29: Open | J29: DCR-186
A30: Q01 | B30: BRD-1 NB | C30: Product master | D30: Please share the product matrix files (MTR08..MTR38, PAR01..PAR25, other risk codes) referenced in Appendix B; the SharePoint link is internal to BDO. | E30: BRNB.001-003, 093 | F30: Partially answered | G30: The products matrix is maintained in BIBS by MBS / TSU with the hierarchy LOB, subline / type / subtype, coverage / peril. The MTR / PAR matrix files are still not provided. (BRD-3 p.12, PMADD01-02)
A31: Q02 | B31: BRD-1 NB | C31: Product master | D31: Minimum mandatory fields per product line / cover type (Annex II: Property, Motor, Engineering, Liability, Crime, Floater, Marine, Hull, Aviation, PA, EEI, Misc.). | E31: BRNB.002, 003, 093 | F31: Open
A32: Q03 | B32: BRD-1 NB | C32: Templates | D32: Sample layouts for IDF, FFYMI quotation, Quotation Slip, Proposal Slip, Comparative Table, Placement Slip, Hold Cover request, Insurance Advice, Service Invoice. | E32: BRNB.004, 008, 017, 069, 070, 100 | F32: Open | I32: RQ26, EBQ08
A33: Q04 | B33: BRD-1 NB | C33: TSU routing | D33: Exact TSU involvement criteria: package vs non-package list, fleet threshold (no. of units), multi-location threshold, TSI threshold, endorsement types. | E33: BRNB.098 | F33: Open | J33: DCR-131
A34: Q05 | B34: BRD-1 NB | C34: Approvals | D34: Approval chain and limits for PRF (Marketing TL / TH / UH) and QS (TSU) - by amount, product or segment? | E34: BRNB.005, 014 | F34: Partially answered | G34: Package requests: approved by the Marketing TL, TH or UH; TSU TL recommends, TH approves; ManCom sign-off. No amount limits. (BRD-3 BRPM.008 / 009 / 012 / 015, PMADD06) | I34: PQ08
A35: Q06 | B35: BRD-1 NB | C35: Insurer channel | D35: How are insurers reached per insurer: e-mail only, SFTP, or insurer API? List of panel insurers and branch codes (LGT depends on insurer branch). | E35: BRNB.008, 071 | F35: Partially answered | G35: For EB, insurers use a secure portal or API. Other lines: still e-mail. (BRD-8 BRID-005, 005.01-005.02, 009) | I35: OQ29, Q31 | J35: DCR-096, DCR-211
A36: Q07 | B36: BRD-1 NB | C36: Encryption | D36: Password convention for outbound documents (standard vs generated syntax, e.g. surname + birth date); which documents to clients vs insurers. | E36: BRNB.013, 035, 077 | F36: Partially answered | G36: Standard assigned password or system-generated with a defined syntax, sent separately. The convention itself is still missing. (BRD-8 BRID-007) | I36: EBQ09, PQ21, CSQ06, RQ16 | J36: DCR-072, DCR-153
A37: Q08 | B37: BRD-1 NB | C37: Integration | D37: Which 'BDOI systems' must receive NB data (core/accounting, CRM, GRF/ARF, data warehouse) and preferred interface (file vs API). | E37: BRNB.015, 096 | F37: Partially answered | G37: QPS and EBIX receive client contact updates during coexistence (BRD-9); BRD-13 makes legacy read-only after cutover with no feed required (conflict DCR-202). Accounting is internal to BIBS. Other targets open. (BRD-9 p.3 footnote 3; BRD-5 FRBS 2.5.0; BRD-13 p.5) | I37: PQ16 | J37: DCR-104, DCR-202
A38: Q09 | B38: BRD-1 NB | C38: Renewals | D38: Late Renewal Requests Report is renewal-related - confirm it stays in NB scope or moves to the Renewal BRD. | E38: BRNB.018 | F38: Open | H38: XQ09 | J38: DCR-009
A39: Q10 | B39: BRD-1 NB | C39: Workflow | D39: Confirm the master list of stages and statuses and allowed transitions per transaction type (NB individual, NB bulk, non-package, direct booking, endorsement). | E39: BRNB.022, 115 | F39: Partially answered | G39: Renewal stages and statuses, and package negotiation outcomes. Counter mapping still to confirm. (BRD-6 personas, tabs, counters, BRRN.040; BRD-3 PMADD04) | I39: RQ10 | J39: DCR-070
A40: Q11 | B40: BRD-1 NB | C40: HLS | D40: HLS interface specification (format, fields, frequency, transport, source authentication) and other source systems for bulk (e.g. auto loans for FFYMI). | E40: BRNB.023, 028 | F40: Partially answered | G40: Sources named (LFS, HLS, CIU, SPI, LAMD, Loan Booking Report, IA masterlist), all Excel. Layouts and transport open. (BRD-12 p.4-5; Report List #138, #151) | I40: SP-SQ01 | J40: DCR-216
A41: Q12 | B41: BRD-1 NB | C41: E-mail intake | D41: Should the system read a shared mailbox for quotation requests automatically, or is manual capture with the e-mail attached sufficient? | E41: BRNB.041 | F41: Open
A42: Q13 | B42: BRD-1 NB | C42: Client code | D42: BRNB.029 requires a client code for every quotation; BRNB.063 allows quotation without client code. Confirm: auto-create prospect code at quotation? | E42: BRNB.029, 063 | F42: Open | J42: DCR-001
A43: Q14 | B43: BRD-1 NB | C43: Sanitation | D43: Defined sanitisation criteria for bulk lists. | E43: BRNB.064 | F43: Partially answered | G43: Renewal sanitation is rule-based (criteria not listed); submitted-policy criteria listed. (BRD-6 BRRN.020; BRD-12, Report List #151) | I43: RQ01
A44: Q15 | B44: BRD-1 NB | C44: Reference no. | D44: Format of the single Account Reference Number (prefix, segment, year, sequence) and whether PRF marketing reference is the same number. | E44: BRNB.006, 102 | F44: Partially answered | G44: A mandatory unique renewal reference is the matching key; no format given. (BRD-6 BRRN.022) | I44: RQ03, SP-SQ20 | J44: DCR-156
A45: Q16 | B45: BRD-1 NB | C45: Client / KYC | D45: BDO 'bank standard' client data and KYC fields; is there a BDO CIF to integrate with (source of truth for bank clients)? | E45: BRNB.030, 065, 090, 092 | F45: Open | I45: RQ22
A46: Q17 | B46: BRD-1 NB | C46: Dedupe | D46: Duplicate-client keys and match precedence (name + DOB, ID number, e-mail, mobile, TIN). | E46: BRNB.032 | F46: Open
A47: Q18 | B47: BRD-1 NB | C47: Tags | D47: List of client/account tags and special-instruction types, and which processes must enforce them (block vs warn). | E47: BRNB.091 | F47: Partially answered | G47: PEP and high-risk tags are set by rules and trigger reviews. Block vs warn still open (SANC-SQ07). (BRD-10 SNSRP-302 / 303) | I47: SANC-SQ07 | J47: DCR-112
A48: Q19 | B48: BRD-1 NB | C48: CRM | D48: Lead management scope: do leads come from bank channels (referrals) and is lead-to-prospect conversion required in NB phase? | E48: BRNB.099 | F48: Open
A49: Q20 | B49: BRD-1 NB | C49: Prospect | D49: Prospect vs confirmed client: which event confirms (KYC complete, first booking)? | E49: BRNB.101 | F49: Open | J49: DCR-001
A50: Q21 | B50: BRD-1 NB | C50: KYC review | D50: KYC review frequency by risk rating for non-bank clients; 'shared path' - is an in-system report acceptable? | E50: BRNB.110 | F50: Partially answered | G50: KYC due is visibility only in renewal; high-risk / PEP clients with an active policy get a review case. Frequency per rating not given. (BRD-6 BRRN.028; BRD-10 SNSRP-102 / 303) | I50: SANC-SQ03 | J50: DCR-112
A51: Q22 | B51: BRD-1 NB | C51: Duplicates | D51: Fire duplicate rule 'same client ID + location + items' - exact or normalised address match? Motor: CTPL vs MTR exception confirmed. | E51: BRNB.051, 066 | F51: Open
A52: Q23 | B52: BRD-1 NB | C52: Files | D52: Maximum file size and full list of allowed file types; file-naming syntax. | E52: BRNB.026 | F52: Partially answered | G52: File types listed for EB and CSF; naming syntax for screening documents only. Maximum size open. (BRD-8 BRID-002, 005.01, 014; BRD-9 BRCSF-007; BRD-10 SNSRP-601) | I52: CSQ08 | J52: DCR-154
A53: Q24 | B53: BRD-1 NB | C53: Extraction | D53: Which documents need auto-extraction (e-policy per insurer?) and which fields; are insurer e-policy layouts stable? | E53: BRNB.074, 104, 105 | F53: Partially answered | G53: Submitted policy documents are extracted and confirmed by a user; scanned input implies OCR. (BRD-12 BRIDSP-02) | I53: SP-SQ03
A54: Q25 | B54: BRD-1 NB | C54: Reactivation | D54: Reactivate cancelled placement (BRD 2.1.16) has no BRNB ID - confirm in scope. | E54: BRD 2.1.16 | F54: Open | J54: DCR-002
A55: Q26 | B55: BRD-1 NB | C55: Placement | D55: Prerequisites before placement per segment (payment received, client confirmation, docs complete, TSU clearance). | E55: BRNB.069 | F55: Open
A56: Q27 | B56: BRD-1 NB | C56: Hold cover | D56: Which accounts need an automatic 30-day hold cover request, and what happens at expiry without confirmation? | E56: BRNB.072, 103 | F56: Partially answered | G56: Hold covers apply to renewals; 30-day hold cover for submitted renewals, accepted within 3-5 days. Expiry handling open. (BRD-6 1.009.3.1.33-34; BRD-12 p.5, BRIDSP-24 / 32) | I56: SP-SQ12 | J56: DCR-155
A57: Q28 | B57: BRD-1 NB | C57: CLPC | D57: CLPC billing file and payment report layouts, transport and schedule; payment report for other segments (bank debit, OTC, online). | E57: BRNB.067, 068 | F57: Partially answered | G57: Three CLPC billing variants with sample files. Transport and schedule open. (Report List #65-67)
A58: Q29 | B58: BRD-1 NB | C58: Direct payment | D58: Direct-payment criteria and accounting: does BDOI book only commission receivable from insurer for these? | E58: BRNB.114 | F58: Open | H58: OQ38
A59: Q30 | B59: BRD-1 NB | C59: Insurance Advice | D59: IA trigger point and recipient (mortgagee bank unit) for mortgaged accounts. | E59: BRNB.070, 095 | F59: Open
A60: Q31 | B60: BRD-1 NB | C60: E-policy receipt | D60: How are e-policies received (insurer e-mail to shared mailbox, SFTP, portal download)? | E60: BRNB.073 | F60: Partially answered | G60: EB insurers upload policy forms and billing through the portal. Other lines open. (BRD-8 BRID-005.01) | H60: Q06 | J60: DCR-211
A61: Q32 | B61: BRD-1 NB | C61: Accounting | D61: Booking accounting entries (premium receivable/payable to insurer, commission income, VAT, EWT) and service invoice rules - is commission invoiced per booking or monthly per insurer? | E61: BRNB.027, 100 | F61: Partially answered | G61: Related transactions must link to a single invoice number. No entries given. (BRD-5 ACSL 2.16.0, DIS 3.27.2) | J61: DCR-003, DCR-058
A62: Q33 | B62: BRD-1 NB | C62: Incentives | D62: Incentive qualification rules and whether incentive computation/payout is in scope. | E62: BRNB.107 | F62: Partially answered | G62: Incentive criteria kept on the products matrix; CPC2 = package Fire / Motor incentive computed per remittance. Rates not given. (BRD-3 PMADD07 / 08; BRD-5 DIS 3.29.2) | H62: OQ39 | J62: DCR-037
A63: Q34 | B63: BRD-1 NB | C63: Cost center | D63: Cost center master data source and default rule (by AO, branch, segment). | E63: BRNB.108 | F63: Open
A64: Q35 | B64: BRD-1 NB | C64: Multi-year | D64: Multi-year: premium paid upfront or yearly? Commission recognition per year or upfront? 81% vs 90% OD/Theft basis. | E64: BRNB.112 | F64: Partially answered | G64: Multi-year policies are billed per billing cycle. Accounting per cycle open. (BRD-4 BRCLXN.058) | I64: CQ15 | J64: DCR-006
A65: Q36 | B65: BRD-1 NB | C65: FFY | D65: Free First-Year: who pays the first-year premium (dealer / bank), FFY period length and renewal hand-off. | E65: BRNB.113 | F65: Partially answered | G65: FFY accounts get an FFY RA template; FFY is both a renewal and a non-renewal bucket. Payer not stated. (BRD-12 BRIDSP-13 / 14) | J65: DCR-124
A66: Q37 | B66: BRD-1 NB | C66: Data ownership | D66: Authoritative system per data element (client, vehicle, property, address, policy, invoice). | E66: BRNB.092 | F66: Partially answered | G66: Policy number flows from the policy system to Claims; QPS / EBIX are systems of record for contacts during coexistence; from cutover the new Core holds the trusted client master and reference data (BRD-13 draft). (BRD-7 BRCLM.007 / 039; BRD-9 p.3, BRCSF-002; BRD-13 p.5) | I66: CSQ01 | J66: DCR-104
A67: Q38 | B67: BRD-1 NB | C67: GRF/ARF | D67: Describe the existing GRF and ARF request forms to replicate their behaviour. | E67: BRNB.096 | F67: Open
A68: Q39 | B68: BRD-1 NB | C68: Retention | D68: Retention periods per record type and status (not proceeded, abandoned, voided) and purge vs archive. | E68: BRNB.106 | F68: Partially answered | G68: Umbrella: 5 years online / 15 years offline for application, database, audit logs and historical data. Claims 10 / 15; EB 5 / 15; CSF 5 / 15; screening 5 / 5. Exceptions per record type and purge vs archive open (CRQ22). (BRD-7 p.41; BRD-8 p.54; BRD-9 p.14; BRD-10 p.25; BRD-00 p.45) | H68: XQ08 | J68: DCR-007, DCR-080, DCR-136, DCR-167
A69: Q40 | B69: BRD-1 NB | C69: Dynamic reports | D69: Expected scope of 'dynamic reports' (ad-hoc column/filter builder vs saved report variants). | E69: BRNB.057 | F69: Partially answered | G69: User-defined filters and exports; the umbrella adds customised reports with fields, charts and summaries, scheduled or on demand (CRQ11). (BRD-8 BRID-022 AC9; Report List #74; BRD-00 BR-053, BR-054) | I69: CRQ11 | J69: DCR-177
A70: Q41 | B70: BRD-1 NB | C70: Production stats | D70: Region / department / team hierarchy and target values per stage for production statistics. | E70: BRNB.075 | F70: Open
A71: Q42 | B71: BRD-1 NB | C71: Login | D71: Authentication: BDO Active Directory / SSO? Clarify '30-min warning prior to system-triggered logout' (absolute session length?). | E71: BRNB.040 | F71: Answered | G71: Directory sign-in (Windows ID through EUA, LDAP / AD or SSO) is required; inactivity log-out at 30 minutes with a warning at 15 minutes. The EUA interface remains open (UQ04). (BRD-11 p.13-14, p.17) | I71: UQ04 | J71: DCR-008, DCR-140, DCR-143, DCR-230
A72: Q43 | B72: BRD-1 NB | C72: Taxes | D72: Appendix A shows PTX 12% of net premium for Fire; please confirm premium tax / VAT basis per line and whether BDOI computes taxes or copies insurer figures. | E72: Appendix A | F72: Open | J72: DCR-005
A73: Q44 | B73: BRD-1 NB | C73: Scope boundary | D73: Broker model: confirm insurer-only platform functions (reinsurance, technical reserves, IBNR, claims reserving) are not required for BDOI. | E73: Platform | F73: Answered | G73: Claims: insurer reserve and settlement are information only. Reinsurance is a BDOI business line whose BRD is phase 2; in phase 1 the insurer-side modules stay hidden. (BRD-7 BRCLM.023 / 024; BRD-00 goal 1, capability 15)
A74: OQ01 | B74: BRD-2 OPS | C74: Integration | D74: For each system in BRQID.004 (Collection, Accounting, Disbursement, Marketing, Claims): is it an existing BDO/BDOI system or a BrokerVerse module of a later BRD? Direction, data, interface (API / file / DB), frequency, and who owns the specification. | E74: BRQID.004-005, CSHID.009/026, RMTID.030, CMRID.001/009 | F74: Partially answered | G74: Collection, Accounting, Disbursement and Claims are BIBS modules. Marketing (ISYS) open. (BRD-4 p.37-39; BRD-5 FRBS 2.5.0, DIS 3.25.0; BRD-7 p.23; BRD-8 BRID-021) | J74: DCR-022, DCR-212
A75: OQ02 | B75: BRD-2 OPS | C75: Disbursement | D75: What is 'Disbursement' (system or unit)? Payload of 'push to Disbursement' (remittance batch, payment request, 2307 report), and how DV numbers / payment status return (needed for Fully / Partially Remitted). May the BrokerVerse payables module (payment vouchers) act as Disbursement? | E75: RMTID.002/011/019/034, CSHID.026/027, DBMID.001 | F75: Answered | G75: Disbursement is a Comptrollership unit working in BIBS; it creates DVs from system-triggered requests and returns instrument statuses. (BRD-5 DIS 2.7.5-2.7.12, 2.20.0, 3.25.0) | J75: DCR-022
A76: OQ03 | B76: BRD-2 OPS | C76: Payment files | D76: Sample files and record layouts (encoding, header / trailer, control totals) for Bills Payment FS01 (IT-DCO), Trade (CIB), CLPC Excel, PDC Excel ('PDC from PMS' - what is PMS?), Direct Credit FS01/04. Who uploads: Operations users, or IT batch (FS04) as stated for Trade / Direct Credit / CLPC? | E76: CSHID.008 | F76: Open | J76: DCR-020, DCR-234
A77: OQ04 | B77: BRD-2 OPS | C77: File integrity | D77: 'Files are encrypted and cannot be edited': are source files PGP-encrypted by the sender, or is the requirement that BrokerVerse stores them read-only with a checksum? | E77: CSHID.008 | F77: Open | J77: DCR-020
A78: OQ05 | B78: BRD-2 OPS | C78: Receipt series | D78: AR / OR numbering: BIR ATP series per branch? Format and length; pre-printed vs system-generated receipts (CAS registration); low-series warning threshold; are AR numbers BIR-controlled like ORs? | E78: CSHID.001/002/006/015/019 | F78: Open
A79: OQ06 | B79: BRD-2 OPS | C79: Cancel / reinstate | D79: Do AR / OR cancellation and reinstatement need checker approval (TL / TH)? Definition of full vs partial reinstatement; accounting per reason. | E79: CSHID.001-005 | F79: Open
A80: OQ07 | B80: BRD-2 OPS | C80: Chart of accounts and entries | D80: Comptrollership default entries and GL accounts for: AR premium (trust cash), payment application by PR component, unapplied / AP unapplied payments, AP overages, PR2307, DTIP, commission (realized on collection?), VAT on commission, WTAX, AR Insurance / AR Insurer, incentives, write-off, cancellation (flat / retain DST / partial), DP PR reversal. | E80: CSHID.012-016, ADJID.011-013, MKTID.012 | F80: Partially answered | G80: Account names given through the reports; no chart and no entries. (BRD-5 FRBS 2.3.x, reports; BRD-4 draft 061 / 063) | I80: AQ01, AQ02, DMQ18
A81: OQ08 | B81: BRD-2 OPS | C81: Exchange rate | D81: 'Comptrollership exchange rate table' with 2 decimals: which rate (buying / selling / booking), daily or monthly, and which date (receipt vs booking)? Treatment of FX difference between booking and collection of dollar accounts. | E81: CSHID.012-014 | F81: Partially answered | G81: A monthly revaluation rate is entered in BIBS. Its use for receipts is not stated. (BRD-5 FRBS 2.2.0, 3.5.0, 3.6.0) | I81: AQ03, DMQ35
A82: OQ09 | B82: BRD-2 OPS | C82: Application hierarchy | D82: Component hierarchy DST -> VAT -> LGT -> Other -> Basic confirmed; meaning of mode-of-payment hierarchy 'Check, Cash'; order across several invoices of one payer (oldest first?); hierarchy for commission receipts. | E82: CSHID.022, CSHID.020 | F82: Open
A83: OQ10 | B83: BRD-2 OPS | C83: 2% CWT | D83: Which clients / invoices are 2% CWT (flag source)? Apply 98% and keep 2% as PR2307 until certificate - confirm. CSHID.026 cash path says 'premium is reversed, remittance processed': which entries? | E83: CSHID.020/026/016, MKTID.010 | F83: Partially answered | G83: Net-of-CWT payments keep the tag with Marketing until the BIR 2307 is collected. (BRD-4 p.41, p.59) | J83: DCR-028
A84: OQ11 | B84: BRD-2 OPS | C84: Minimal balances | D84: Reconcile the three rules: CSHID.016 (PR <= 10.00 reversed unless equal to 2% CWT / DST / entire premium, compared to PR2307), summary 5.f (<= 10.00 to AP overages) and ADJID.026 (10.00-100.00 write-off or credit). Boundary at exactly 10.00, GL targets, content of the minimal balance table, approval. | E84: CSHID.016, ADJID.026 | F84: Open | I84: CQ03 | J84: DCR-014
A85: OQ12 | B85: BRD-2 OPS | C85: Pre-booked matching | D85: Key used to match a payment to a pre-booked account (ARN, invoice no., PN no.?), re-run schedule, retention in the pre-booked table. BRD-1 placement also matches CLPC payments before placement (BRNB.067/068): confirm Cashiering is the single payment intake and the placement gate consumes its result. | E85: CSHID.020, CSHID.008 | F85: Partially answered | G85: Handling fee: PN for CLPC, Location Reference for OTC; PN is the LAMD matching key. General pre-booked key open. (BRD-12 BRIDSP-31; BRD-6 BRRN.029 / 039) | J85: DCR-027
A86: OQ13 | B86: BRD-2 OPS | C86: Check pick-up | D86: How does the Collection 'for check pick' status reach Operations? Is the AR printed and handed over at pick-up? | E86: CSHID.009 | F86: Partially answered | G86: Check pick-up is a Collection Handler task in BIBS. Printing of the AR at pick-up open. (BRD-4 p.40)
A87: OQ14 | B87: BRD-2 OPS | C87: AR Insurance | D87: Definition and identification of non-premium insurer payments (refunds of remitted premium, others) and the AR Insurance accounting. | E87: CSHID.021, ADJID.012 | F87: Partially answered | G87: AR insurer's refund and A/P refund from insurer are separate schedules. (BRD-5 Appendix C)
A88: OQ15 | B88: BRD-2 OPS | C88: Dispositions | D88: Full disposition type list, which require approval and by whom, and the refund hand-off to Collection / Disbursement. | E88: CSHID.024/025, ADJID.013 | F88: Partially answered | G88: Seven unapplied dispositions plus Handling Fee; refund path through the RRF. Approvals open. (Report List #105; BRD-12 BRIDSP-31; BRD-5 MKT 1.11.0, 2.23.0-2.24.0) | I88: CQ08, CQ10 | J88: DCR-126, DCR-162, DCR-205
A89: OQ16 | B89: BRD-2 OPS | C89: BIR 2307 flow | D89: Certificate statuses, sorting per insurer, when Dr DTIP / Cr PR2307 is posted (on validation or on release to insurer), and whether Marketing tagging stays in BrokerVerse or comes from the Collection system. | E89: CSHID.026/027, MKTID.010/013, DBMID.001 | F89: Partially answered | G89: 2307 tagging stays in BIBS; client 2307s are remitted to insurers in batches. Posting moment open. (BRD-4 p.41, p.59; BRD-5 Appendix C, DIS 2.11) | I89: AQ16 | J89: DCR-028
A90: OQ17 | B90: BRD-2 OPS | C90: Remittance types / schedule | D90: How an invoice is classified With Incentives / Normal-Dollar / Normal-Peso; extraction schedule ('Batch Run: TDB'); file naming; shared-drive path, or is an in-system repository acceptable? | E90: RMTID.001/003/007 | F90: Partially answered | G90: Target is a single master database; Claims still names a shared drive, Collections FS04. (BRD-12 p.6; BRD-7 p.39-40; BRD-4 FRID-041 / 042) | I90: SANC-SQ16 | J90: DCR-019, DCR-084, DCR-152
A91: OQ18 | B91: BRD-2 OPS | C91: EOD trigger | D91: Meaning of 'trigger extraction at end of day if payment application is searched' (RMTID.005, summary 1.e). | E91: RMTID.005 | F91: Open
A92: OQ19 | B92: BRD-2 OPS | C92: Paid AR > DTIP | D92: Expected result says remit only the DTIP balance; acceptance criteria say flag and exclude. Which one? | E92: RMTID.014/015 | F92: Open | J92: DCR-015
A93: OQ20 | B93: BRD-2 OPS | C93: Check clearing | D93: Holding period: 3 banking days from AR date or deposit date? Source of 'cleared' status (bank reconciliation, bank file, manual)? | E93: RMTID.017/018/028 | F93: Open
A94: OQ21 | B94: BRD-2 OPS | C94: Remittance approval | D94: Who approves a remittance batch (TL / TH) and the full status model; RMTID.019 mixes payment statuses (Unapplied, Outstanding Balance) with remittance statuses. | E94: RMTID.010/019/029 | F94: Open | J94: DCR-016
A95: OQ22 | B95: BRD-2 OPS | C95: Insurer OR upload | D95: Layout of the insurer-populated remittance schedule; OR amount vs paid PR comparison level (invoice / batch) and tolerance; why is MKTID.001 (send schedule to insurer) a Marketing request? | E95: RMTID.012/013/016, MKTID.001 | F95: Open
A96: OQ23 | B96: BRD-2 OPS | C96: Early remittance incentive | D96: Rates per insurer / product (2% for CLG / CBG motor and fire?), window start (inception vs booking), deduction from the remittance vs separate OR, and the difference between RMTID.023 and PRCID.028. | E96: RMTID.023, PRCID.028 | F96: Partially answered | G96: Early incentive: service invoice with 2% withholding; Other Income. Rates not given. (BRD-5 DIS 3.29.1, FRBS 3.1.2; BRD-4 draft 062) | I96: AQ25 | J96: DCR-013
A97: OQ24 | B97: BRD-2 OPS | C97: Hold remittance | D97: Who requests and approves holds (Marketing AO / TL / UH), maximum hold and extension rules, whether hold data will flow in from a Marketing system. | E97: MKTID.002-006, RMTID.021 | F97: Open
A98: OQ25 | B98: BRD-2 OPS | C98: Special remittance | D98: Approvers and SLA; exact eligibility for claims / renewal / installment / immediate OR. | E98: MKTID.009, RMTID.030 | F98: Partially answered | G98: Claims condition: invoice of the cover of an open claim in status "With BDOI - For Premium Remittance". Approvers and SLA open. (BRD-7 BRCLM.010)
A99: OQ26 | B99: BRD-2 OPS | C99: Write-off | D99: Who writes off accounts and through which transaction (adjustment request type 'Write-off', minimal balance file)? | E99: RMTID.022, ADJID.026 | F99: Open | J99: DCR-014
A100: OQ27 | B100: BRD-2 OPS | C100: Estimated items | D100: Definition of 'estimated items' in production reports. | E100: RMTID.037, CMRID.014 | F100: Open
A101: OQ28 | B101: BRD-2 OPS | C101: Invoice locking | D101: Which Comptrollership activity holds an invoice ('still with comptrollership')? List of lock reasons. | E101: RMTID.040 | F101: Open
...

Sheet NFR comparison
A1: NFR comparison
A2: Every NFR theme against each BRD's value. Conflicting rows are highlighted; grey cells: not stated or 'follow QPS'.
A4: NFR theme | B4: BRD-0 CORE | C4: BRD-1 NB | D4: BRD-2 OPS | E4: BRD-3 PM | F4: BRD-4 CLXN | G4: BRD-5 ACCT | H4: BRD-6 RN | I4: BRD-7 CLM | J4: BRD-8 EB | K4: BRD-9 CSF | L4: BRD-10 SANC | M4: BRD-11 UAM | N4: BRD-12 SP | O4: BRD-13 DM | P4: Aligned? | Q4: Proposed BIBS-wide value | R4: Register items
A5: Availability target | B5: Refer to BRD (p.44) | C5: Follow existing QPS set up (p.212) | D5: 99.9% (p.115) | E5: 99.9% (p.33) | F5: Not stated; no downtime when scaling (p.54-55) | G5: Main BRD: follow QPS / EBIX (p.138). Addendum 1: 100% (p.37) | H5: Follow existing QPS set up (p.187) | I5: Not stated | J5: 99.99% (p.53) | K5: 99.9% (p.13) | L5: 99.9% (p.24) | M5: Follow existing QPS set up (p.11) | N5: 99.9% uptime (p.14) | O5: Not stated; refers to the consolidated NFR, not in the pack (p.13-14) | P5: CONFLICT | Q5: 99.9% within service hours | R5: DCR-134, DCR-057
A6: Service hours | B6: Refer to BRD (p.44) | C6: 07:00-22:00 Mon-Sat (p.212) | D6: 07:00-18:30; Adjustment and Commission 07:30-18:00 (p.115-119) | E6: 07:00-18:30 (p.33) | F6: 06:00-22:00 Mon-Fri, and month-end weekends (p.54) | G6: 07:00-18:00 Mon-Sat (p.37, p.138) | H6: 07:00-22:00 Mon-Sat (p.187) | I6: 06:00-20:00 Mon-Fri (p.37) | J6: 08:30-19:00 (p.53) | K6: 06:00-22:00 (p.13) | L6: 08:00-18:00 Mon-Fri (p.25) | M6: Follow existing QPS set up (p.11) | N6: Business hours (p.14) | O6: Not stated; refers to the consolidated NFR, not in the pack (p.13-14) | P6: CONFLICT | Q6: 06:00-22:00 Mon-Sat, plus month-end weekends | R6: DCR-133
A7: Maintenance window | B7: Refer to BRD (p.44) | C7: Follow existing QPS set up (p.212) | D7: As per bank standard (p.116) | E7: As per bank standard (p.33) | F7: Follow standard window time (p.55) | G7: 19:00-07:00 (p.37) | H7: Follow existing QPS set up (p.187) | I7: Standard maintenance window (p.37) | J7: As per bank standard (p.53) | K7: 21:00-05:00 weekdays and Saturdays (p.13) | L7: 00:00-04:00 (p.25) | M7: Follow existing QPS set up (p.11) | N7: 00:00-04:00 (p.14) | O7: Not stated; refers to the consolidated NFR, not in the pack (p.13-14) | P7: CONFLICT | Q7: 00:00-04:00 | R7: DCR-138, DCR-103
A8: Allowed downtime / BCP threshold | B8: Refer to BRD (p.44) | C8: Follow existing QPS set up (p.212) | D8: Not stated | E8: Not stated | F8: Database scaling up to 120 minutes, manual (p.54-55) | G8: Less than 24 hours a month / year; BCP less than 3 days (p.37) | H8: Follow existing QPS set up (p.187) | I8: Database scaling up to 120 minutes (p.37) | J8: Not stated | K8: Not stated | L8: At most 45 minutes a month, planned only; BCP less than 3 days (p.25) | M8: Follow existing QPS set up (p.11) | N8: At most 45 minutes a month, planned only (p.14) | O8: Not stated; refers to the consolidated NFR, not in the pack (p.13-14) | P8: CONFLICT | Q8: At most 45 minutes a month of planned downtime, inside the maintenance window | R8: DCR-134
A9: RTO | B9: Not stated | C9: Follow existing QPS set up (p.212) | D9: 4 hours (p.115-118) | E9: 4 hours (p.33) | F9: 4 hours (p.55) | G9: Not stated | H9: Follow existing QPS set up (p.187) | I9: 4 hours (p.37) | J9: 4 hours (p.53) | K9: 4 hours (p.13) | L9: Not stated | M9: Follow existing QPS set up (p.11) | N9: 4 hours for critical services; full recovery 24 hours (p.14) | O9: Not stated; refers to the consolidated NFR, not in the pack (p.13-14) | P9: ALIGNED | Q9: 4 hours | R9: DCR-135
A10: RPO | B10: Not stated | C10: Follow existing QPS set up (p.212) | D10: 24 hours (p.115-118) | E10: 24 hours (p.33) | F10: 4 hours (p.55) | G10: Not stated | H10: Follow existing QPS set up (p.187) | I10: 4 hours (p.38) | J10: 24 hours (p.53) | K10: 4 hours (p.13) | L10: Not stated | M10: Follow existing QPS set up (p.11) | N10: Not stated | O10: Not stated; refers to the consolidated NFR, not in the pack (p.13-14) | P10: CONFLICT | Q10: 15 minutes (continuous log archiving) | R10: DCR-135, DCR-102
A11: Backup frequency | B11: Every 4 hours (p.45) | C11: Every 4 hours (p.82) | D11: Every 4 hours (p.120) | E11: Not stated | F11: Every 4 hours (p.58) | G11: Daily (Addendum 1) | H11: Follow existing QPS set up (p.188) | I11: Every 4 hours; configuration weekly; documents monthly (p.41) | J11: Every 4 hours (p.54) | K11: Every 15 minutes (p.11) and every 4 hours (p.14) | L11: Daily (p.25) | M11: Follow existing QPS set up (p.11) | N11: Daily (p.14) | O11: Not stated; refers to the consolidated NFR, not in the pack (p.13-14) | P11: CONFLICT | Q11: Continuous log archiving plus a base backup every 4 hours | R11: DCR-102, DCR-135
A12: Backup retention | B12: 5 years (p.45) | C12: 5 years (p.82) | D12: 7 years (p.120) | E12: Not stated | F12: 5 years (p.58) | G12: 5 years (Addendum 1) | H12: Follow existing QPS set up (p.188) | I12: 5 years (p.41) | J12: 7 years (p.54) | K12: 5 years (p.14) | L12: 5 years (p.25) | M12: Follow existing QPS set up (p.11) | N12: 5 years (p.14) | O12: Not stated; refers to the consolidated NFR, not in the pack (p.13-14) | P12: CONFLICT | Q12: 7 years | R12: DCR-136
A13: Data retention (online / archive) | B13: 5 years online, 15 years offline for application, database and audit logs and historical data (p.45); no anonymisation (p.46) | C13: 5 years online, 15 years archive (p.82); main BRD: follow QPS (p.212) | D13: 5 years online, 15 years archive (p.120) | E13: Not stated | F13: 5 / 15 years, purge after 15; hard copy 5 / 10 (p.58) | G13: 5 years online, 5 years archive (Addendum 1) | H13: Follow existing QPS set up (p.188) | I13: 10 years online, 15 archive, purge after 15; audit logs archive 16 years (p.41) | J13: 5 years online, 15 years archive (p.54) | K13: 5 years online, 15 years archive (p.14) | L13: 5 years online, 5 years archive (p.25) | M13: Follow QPS retention policy (p.11) | N13: 5 years online, 5 years archive (p.14) | O13: Not stated; refers to the consolidated NFR, not in the pack (p.13-14) | P13: CONFLICT | Q13: Per record type; default 5 years online, 15 years archive | R13: DCR-136, DCR-007, DCR-080, DCR-167
A14: Response time - screens | B14: Under 5 seconds for every role (p.42) | C14: 10 seconds (p.210) | D14: Under 5 seconds (p.115) | E14: Under 5 seconds (p.33) | F14: 5 seconds (p.56) | G14: Load 5-10 seconds; save 2-5 seconds (p.133-137) | H14: 10 seconds (p.186) | I14: 5 seconds; status updates 1 minute (p.39-40) | J14: Blank (p.53) | K14: Under 3 seconds (p.13) | L14: 3-5 seconds per screen (p.22-24) | M14: 10 seconds (p.11) | N14: 2 seconds (p.13) | O14: Not stated; refers to the consolidated NFR, not in the pack (p.13-14) | P14: CONFLICT | Q14: p95 under 2 seconds for screens and single-record actions | R14: DCR-137, DCR-165
A15: Response time - reports and batch | B15: Under 5 seconds for every role (p.42) | C15: 10 seconds (p.210) | D15: Batch print of 50 documents under 10 seconds (p.115) | E15: Not stated | F15: Daily report 3 minutes, weekly 10 minutes, monthly 15 minutes (p.56-57) | G15: 10-20 seconds first load (p.133-137) | H15: 20 seconds for reports and RA generation (p.186) | I15: 5 minutes (p.39-40) | J15: Blank (p.53) | K15: 5 seconds (p.13) | L15: 3-5 seconds per screen (p.24) | M15: 20 seconds (p.11) | N15: 2 seconds (p.13) | O15: Not stated; refers to the consolidated NFR, not in the pack (p.13-14) | P15: CONFLICT | Q15: Asynchronous jobs with progress; interactive reports under 20 seconds | R15: DCR-137, DCR-165
... A22: Audit logging | B22: Not stated | C22: Audit log report (BRNB.089, p.127) | D22: Audit trail per transaction; search logs (CSHID.010) | E22: Audit trail for all actions (BRPM.024, p.31) | F22: Log-in / log-out, privileged use, admin actions, record access, source IP; exportable (p.52) | G22: Audit trail per transaction | H22: Every action with user, time and data source (BRRN rows) | I22: As BRD-4, including source IP (p.33-34) | J22: Upload and approval activity logged (BRID-005.01, 025) | K22: Audit trail report of changes (BRCSF-010 / 011, p.11-12) | L22: Audit logs and case history (SNSRP-902) | M22: Role and permission changes, log-in / log-out, audit log report (p.17-18) | N22: Not stated | O22: Not stated; refers to the consolidated NFR, not in the pack (p.13-14) | P22: ALIGNED | Q22: One audit trail with user, time, source IP and resource; log-out recorded | R22: DCR-145, DCR-119

Sheet _lists
A1: Drop 0 | B1: Contradiction within BRD | C1: High | D1: Open | E1: Open
A2: Drop 1 | B2: Conflict between BRDs | C2: Medium | D2: Answered | E2: Partially answered
A3: Drop 2 | B3: Gap / missing detail | C3: Low | D3: Closed | E3: Answered
A4: Programme | B4: Ambiguity
A5: Phase 2 | B5: BRD vs platform
B6: NFR inconsistency
B7: Data / numbering issue
B8: Document quality
