Workbook
Name CODES_D0_02_BRANCH_CODE: 'D0-02 Branches'!$B$18:$B$518
Name CODES_D0_04_CODE: 'D0-04 Dimensions'!$C$17:$C$517
Name CODES_D0_06_ACCOUNT_CODE: 'D0-06 Chart of accounts'!$C$17:$C$517
Name CODES_D0_07_CATEGORY_CODE: 'D0-07 Categories and numbering'!$C$17:$C$517
Name CODES_MD_02_CURRENCY_CODE: 'MD-02 Currencies'!$B$17:$B$317
Name CODES_PM_01_COVER_TYPE_CODE: 'PM-01 Product catalogue'!$E$17:$E$517
Name CODES_UA_01_USER_ID: 'UA-01 Users and roles'!$C$17:$C$517
Name CODES_PM_01_LINE_CODE: 'PM-01 Product catalogue'!$B$17:$B$517
Name CODES_D0_11_BANK_ACCOUNT_CODE: 'D0-11 Bank accounts'!$B$18:$B$518
Name CODES_D0_05_EMPLOYEE_NUMBER: 'D0-05 Employees'!$B$17:$B$517
Name CODES_PM_01_RISK_CODE: 'PM-01 Product catalogue'!$H$17:$H$517
Name LIST_YES_NO: 'Reference lists'!$C$5:$C$6
Name LIST_MARKET_SEGMENT: 'Reference lists'!$C$7:$C$11
Name LIST_PLACEMENT_GATE: 'Reference lists'!$C$12:$C$13
Name LIST_TSU_REVIEW: 'Reference lists'!$C$14:$C$16
Name LIST_CI02_RECORD: 'Reference lists'!$C$17:$C$19
Name LIST_DOCUMENT_TYPE: 'Reference lists'!$C$20:$C$80
Name LIST_CLAUSE_KIND: 'Reference lists'!$C$81:$C$84
Name LIST_RATE_TABLE: 'Reference lists'!$C$85:$C$87
Name LIST_MAP_ACTION: 'Reference lists'!$C$88:$C$89
Name LIST_PKG_DOCUMENT: 'Reference lists'!$C$90:$C$95
Name LIST_PM_LIST_OR_PARAMETER: 'Reference lists'!$C$96:$C$119
Name LIST_INCENTIVE_TYPE: 'Reference lists'!$C$120:$C$121
Name LIST_UA_ACTION: 'Reference lists'!$C$122:$C$125
Name LIST_PRIVILEGE_LEVEL: 'Reference lists'!$C$126:$C$129
Name LIST_KEEP_ADD_REMOVE: 'Reference lists'!$C$130:$C$132
Name LIST_UA_ROLE: 'Reference lists'!$C$133:$C$137
Name LIST_SOD_STATUS: 'Reference lists'!$C$138:$C$140
Name LIST_SOD_CONTROL: 'Reference lists'!$C$141:$C$143
Name LIST_REVIEW_FREQUENCY: 'Reference lists'!$C$144:$C$145
Name LIST_UA_PARAMETER: 'Reference lists'!$C$146:$C$162
Name LIST_UA_LIST: 'Reference lists'!$C$163:$C$165
Name LIST_DIMENSION: 'Reference lists'!$C$166:$C$167
Name LIST_ACCOUNT_CLASS: 'Reference lists'!$C$168:$C$172
Name LIST_ACCOUNT_CLASS_CHART: 'Reference lists'!$C$173:$C$178
Name LIST_ACCOUNT_LEVEL: 'Reference lists'!$C$179:$C$182
Name LIST_NEGATIVE_BALANCE: 'Reference lists'!$C$183:$C$185
Name LIST_CATEGORY_ROW: 'Reference lists'!$C$186:$C$187
Name LIST_ACCOUNTING_EVENT: 'Reference lists'!$C$188:$C$252
Name LIST_DEBIT_CREDIT: 'Reference lists'!$C$253:$C$254
Name LIST_LEGACY_ACCOUNT: 'Reference lists'!$C$255:$C$262
Name LIST_TAX_TYPE: 'Reference lists'!$C$263:$C$266
Name LIST_PAYEE_CLASS: 'Reference lists'!$C$267:$C$272
Name LIST_APPROVAL_MODULE: 'Reference lists'!$C$273:$C$276
Name LIST_D0_04_DIMENSION: 'Reference lists'!$C$277:$C$279
Name LIST_R03_RECORD_TYPE: 'Reference lists'!$C$280:$C$283
Name LIST_UA_06_LIST: 'Reference lists'!$C$284:$C$286
Name LIST_UA_02_PRIVILEGE_LEVEL: 'Reference lists'!$C$287:$C$290
Name LIST_UA_02_KEEP_ADD_REMOVE: 'Reference lists'!$C$291:$C$293
Name LIST_UA_03_ROLE_IN_USER_ACCESS: 'Reference lists'!$C$294:$C$298
Name LIST_UA_04_STATUS: 'Reference lists'!$C$299:$C$301
Name LIST_UA_04_CONTROL: 'Reference lists'!$C$302:$C$304
Name LIST_UA_04_REVIEW_FREQUENCY: 'Reference lists'!$C$305:$C$306
Name LIST_UA_05_PARAMETER: 'Reference lists'!$C$307:$C$323
Name LIST_D0_15_MODULE: 'Reference lists'!$C$324:$C$327
Name LIST_D0_07_ROW: 'Reference lists'!$C$328:$C$329
Name LIST_D0_07_ACCOUNT_CLASS: 'Reference lists'!$C$330:$C$335
Name LIST_D0_07_SEPARATOR: 'Reference lists'!$C$336:$C$337
Name LIST_R08_ACCOUNT_TYPE: 'Reference lists'!$C$338:$C$342
Name LIST_R08_NORMAL_BALANCE: 'Reference lists'!$C$343:$C$344

Sheet Start here
A3: Master Data and Configuration Upload Templates
A4: Every master, reference and configuration dataset BIBS needs before go-live, with the templates in the order the data is loaded
A6: Client | C6: BDO Insurance and Reinsurance Brokers, Inc.
A7: Scope | C7: Every master, reference and configuration dataset BIBS needs before go-live, all BRDs
A8: Version and date | C8: Version 1.2, 9 October 2026
A9: Go-live | C9: Go-live is proposed for Monday 3 January 2028 (T), at the year-end boundary (option A of the Data Migration set, for Comptrollership to confirm).
A10: Owner | C10: Program Manager, Business Project Services, with the BDOI owner of each dataset
A11: Prepared by | C11: iorta TechNXT
A12: Classification | C12: Confidential
A14: How to fill in this workbook
A15: 1 | B15: The index below lists every master, reference and configuration dataset BIBS needs before go-live, one template sheet each, in the order the data is loaded: a dataset whose codes others use comes first (Loads after names the templates it depends on). Each template has the column layout BIBS loads.
A16: 2 | B16: Load route: Configuration screen upload (28 templates) - the filled-in sheet is uploaded with Upload on the named configuration screen, in exactly this layout; every row is checked first and the rows are applied when a second user approves the upload; Screen upload (5) - the filled-in sheet is uploaded on the named screen, which checks every row; Migration Console (15) - the data is extracted from the legacy systems by BDOI IT in this layout and loaded by the Data Migration Console; Configuration screen (0) - no upload: the rows are keyed on the screen from the filled-in template (sheet Gaps). Every record is authorised by a second user.
A17: 3 | B17: On a template sheet, read the header block (purpose, who fills it in, how it is loaded, due, depends on) and the guide above each column (Mandatory, Format, Allowed values, What to enter; * marks a mandatory column). Overwrite or delete the grey example row and enter one row per record. Drop-downs offer the allowed values (sheet Reference lists) and the codes of the templates filled in before; a mandatory cell left empty turns red. For a large legacy dataset (clients, opening balances) BDOI IT sends the extract file in the layout instead of typing it.
A18: 4 | B18: The review sheets (lists of values, system parameters, SLA and turnaround, numbering prefixes, notification events, document templates, accounting events) list what the platform delivers; write the value wanted or the decision on each row you own. The sheet Configured on screens lists the set-up decided in working sessions and entered directly on the screens.
A19: 5 | B19: Set the Status of each template, follow Rows entered and Mandatory cells missing, raise questions on the sheet Questions and comments, and return the workbook to the iorta TechNXT project team by each due date. The owner confirms each template (Confirmed by and Date on the sheet) before it is loaded; the guide (BIBS_Templates_BRD-00_Master_Data_Upload_Guide_v1.2) explains the validation and the sign-off of the master data.
A21: Index of the datasets in load order (dependencies first)
A22: Step | B22: ID | C22: Dataset | D22: Group | E22: BRD | F22: Drop | G22: Provided by | H22: Load route | I22: Entered or loaded on | J22: Loads after | K22: Due | L22: Rows entered | M22: Mandatory cells missing | N22: Status | O22: Open
A23: 1 | B23: D0-02 | C23: Branches | D23: Organisation | E23: BRD-05 | F23: Drop 1 | G23: Head, Comptrollership | H23: Configuration screen upload | I23: Setup & Administration › Setup › Branches | J23: - | K23: 4-Jan-2027 – Platform set-up for Drop 1 SIT | L23: ='D0-02 Branches'!$C$10 | M23: ='D0-02 Branches'!$E$10 | N23: Not started | O23: D0-02 →
A24: 2 | B24: D0-04 | C24: Cost centres and business lines | D24: Organisation | E24: BRD-05 | F24: Drop 1 | G24: Head, Comptrollership | H24: Configuration screen upload | I24: Setup & Administration › Setup › Dimensions | J24: - | K24: 4-Jan-2027 – Platform set-up for Drop 1 SIT | L24: ='D0-04 Dimensions'!$C$9 | M24: ='D0-04 Dimensions'!$E$9 | N24: Not started | O24: D0-04 →
A25: 3 | B25: D0-07 | C25: Account categories and numbering | D25: Chart of accounts, tax and accounting | E25: BRD-05 | F25: Drop 1 | G25: Head, Comptrollership | H25: Configuration screen upload | I25: Finance › General Ledger › Chart Upload | J25: - | K25: 4-Jan-2027 – Platform set-up for Drop 1 SIT | L25: ='D0-07 Categories and numbering'!$C$9 | M25: ='D0-07 Categories and numbering'!$E$9 | N25: Not started | O25: D0-07 →
A26: 4 | B26: MD-02 | C26: Currencies | D26: Chart of accounts, tax and accounting | E26: BRD-05 | F26: Drop 1 | G26: Head, Comptrollership (Treasury) | H26: Configuration screen – no upload: BDOI fills in this template and the rows are keyed on the screen, each record authorised by a second user | I26: Setup & Administration › Setup › Currencies & Rates | J26: - | K26: 4-Jan-2027 – Platform set-up for Drop 1 SIT | L26: ='MD-02 Currencies'!$C$9 | M26: ='MD-02 Currencies'!$E$9 | N26: Not started | O26: MD-02 →
A27: 5 | B27: PM-09 | C27: Lists of values and parameters | D27: Products, packages and rates | E27: BRD-03 | F27: Drop 0 | G27: Product Owner, MBS; System Administrator (entry) | H27: Configuration screen upload | I27: Setup & Administration › Broking Setup › Lists of Values or Setup & Administration › Administration › System Parameters | J27: - | K27: 16-Jul-2027 – Values for UAT | L27: ='PM-09 Lists and parameters'!$C$9 | M27: ='PM-09 Lists and parameters'!$E$9 | N27: Not started | O27: PM-09 →
A28: 6 | B28: R01 | C28: Lists of values and MIS values | D28: Clients and KYC | E28: BRD-13 | F28: Drop 0 | G28: MBS data steward (to name); approved by Product Owner, Marketing Business System (MBS); extracted by BDOI IT | H28: Migration Console | I28: Data Migration › Data Migration › Extracts and Batches | J28: - | K28: M3 (29 Jan 2027) | L28: ='R01 Lists of values and MIS val'!$C$9 | M28: ='R01 Lists of values and MIS val'!$E$9 | N28: Not started | O28: R01 →
A29: 7 | B29: R04 | C29: Insurers | D29: Insurers, partners, intermediaries and payees | E29: BRD-03 | F29: Drop 0 | G29: Operations data steward (to name); approved by Head, Operations; extracted by BDOI IT | H29: Migration Console | I29: Data Migration › Data Migration › Extracts and Batches | J29: - | K29: M3 (29 Jan 2027) | L29: ='R04 Insurers'!$C$11 | M29: ='R04 Insurers'!$E$11 | N29: Not started | O29: R04 →
A30: 8 | B30: UA-02 | C30: Role-to-permission matrix | D30: Users, access and approvals | E30: BRD-11 | F30: Drop 0 | G30: Business Administration with the unit heads; reviewed and signed by BDOI Information Security | H30: Configuration screen upload | I30: Setup & Administration › Administration › Roles & Permissions | J30: - | K30: 9-Apr-2027 – Reference data for Trial migration 1 (M4) | L30: ='UA-02 Role matrix'!$C$9 | M30: ='UA-02 Role matrix'!$E$9 | N30: Not started | O30: UA-02 →
A31: 9 | B31: UA-06 | C31: Lists of values | D31: Users, access and approvals | E31: BRD-11 | F31: Drop 0 | G31: Business Administration | H31: Configuration screen upload | I31: Setup & Administration › Broking Setup › Lists of Values | J31: - | K31: 1-Nov-2027 – before the templates that use its codes | L31: ='UA-06 Lists of values'!$C$9 | M31: ='UA-06 Lists of values'!$E$9 | N31: Not started | O31: UA-06 →
A32: 10 | B32: D0-05 | C32: Employees | D32: Organisation | E32: BRD-05 | F32: Drop 1 | G32: Human Resources; Head, Comptrollership | H32: Configuration screen upload | I32: Setup & Administration › Setup › Employees | J32: D0-02, D0-04 | K32: 16-Jul-2027 – Values for UAT | L32: ='D0-05 Employees'!$C$9 | M32: ='D0-05 Employees'!$E$9 | N32: Not started | O32: D0-05 →
A33: 11 | B33: D0-06 | C33: Chart of accounts | D33: Chart of accounts, tax and accounting | E33: BRD-05 | F33: Drop 1 | G33: Head, Comptrollership | H33: Screen upload | I33: Finance › General Ledger › Chart Upload | J33: D0-07 | K33: 4-Jan-2027 – Platform set-up for Drop 1 SIT | L33: ='D0-06 Chart of accounts'!$C$9 | M33: ='D0-06 Chart of accounts'!$E$9 | N33: Not started | O33: D0-06 →
A34: 12 | B34: MD-01 | C34: Business partners (reinsurers, intermediaries, suppliers) | D34: Insurers, partners, intermediaries and payees | E34: BRD-05 | F34: Drop 1 | G34: Head, Comptrollership; Head, Operations for the reinsurers and intermediaries | H34: Configuration screen upload | I34: Setup & Administration › Setup › Business Partners | J34: D0-02 | K34: 9-Apr-2027 – Reference data for Trial migration 1 (M4) | L34: ='MD-01 Business partners'!$C$9 | M34: ='MD-01 Business partners'!$E$9 | N34: Not started | O34: MD-01 →
A35: 13 | B35: R03 | C35: Sales organisation (units and account officers) | D35: Organisation | E35: BRD-01 | F35: Drop 1 | G35: Marketing data steward (to name); approved by Heads, Retail and Corporate Marketing; extracted by BDOI IT | H35: Migration Console | I35: Data Migration › Data Migration › Extracts and Batches | J35: D0-02, D0-04 | K35: M3 (29 Jan 2027) | L35: ='R03 Sales organisation (units a'!$C$9 | M35: ='R03 Sales organisation (units a'!$E$9 | N35: Not started | O35: R03 →
A36: 14 | B36: R05 | C36: Product lines, cover types, products and risk codes | D36: Products, packages and rates | E36: BRD-03 | F36: Drop 0 | G36: MBS data steward (to name); approved by Product Owner, MBS; extracted by BDOI IT | H36: Migration Console | I36: Data Migration › Data Migration › Extracts and Batches | J36: PM-09 | K36: M3 (29 Jan 2027) | L36: ='R05 Product lines, cover types,'!$C$9 | M36: ='R05 Product lines, cover types,'!$E$9 | N36: Not started | O36: R05 →
A37: 15 | B37: UA-01 | C37: Users and roles load | D37: Users, access and approvals | E37: BRD-11 | F37: Drop 0 | G37: Business Administration, with the unit heads who name their users | H37: Screen upload | I37: Setup & Administration › User Access › Bulk Request | J37: UA-06, UA-02 | K37: 1-Nov-2027 – Production values before the dress rehearsal | L37: ='UA-01 Users and roles'!$C$9 | M37: ='UA-01 Users and roles'!$E$9 | N37: Not started | O37: UA-01 →
A38: 16 | B38: D0-03 | C38: Holiday calendar | D38: Organisation | E38: BRD-05 | F38: Drop 1 | G38: Head, Comptrollership; Human Resources | H38: Configuration screen upload | I38: Setup & Administration › Setup › Holiday Calendar | J38: D0-02 | K38: 4-Jan-2027 – Platform set-up for Drop 1 SIT | L38: ='D0-03 Holiday calendar'!$C$9 | M38: ='D0-03 Holiday calendar'!$E$9 | N38: Not started | O38: D0-03 →
A39: 17 | B39: MD-03 | C39: Exchange rates and their source | D39: Chart of accounts, tax and accounting | E39: BRD-05 | F39: Drop 1 | G39: Head, Comptrollership (Treasury) | H39: Configuration screen – no upload: BDOI fills in this template and the rows are keyed on the screen, each record authorised by a second user | I39: Setup & Administration › Setup › Currencies & Rates | J39: MD-02 | K39: 16-Jul-2027 – Values for UAT | L39: ='MD-03 Exchange rates'!$C$9 | M39: ='MD-03 Exchange rates'!$E$9 | N39: Not started | O39: MD-03 →
A40: 18 | B40: R02 | C40: Branches and invoicing branches | D40: Organisation | E40: BRD-05 | F40: Drop 1 | G40: Comptrollership data steward (to name); approved by Head, Comptrollership; extracted by BDOI IT | H40: Migration Console | I40: Data Migration › Data Migration › Extracts and Batches | J40: D0-02 | K40: M3 (29 Jan 2027) | L40: ='R02 Branches and invoicing bran'!$C$9 | M40: ='R02 Branches and invoicing bran'!$E$9 | N40: Not started | O40: R02 →
A41: 19 | B41: R04B | C41: Insurer branches | D41: Insurers, partners, intermediaries and payees | E41: BRD-03 | F41: Drop 0 | G41: Operations data steward (to name); approved by Head, Operations; extracted by BDOI IT | H41: Migration Console | I41: Data Migration › Data Migration › Extracts and Batches | J41: R04 | K41: M3 (29 Jan 2027) | L41: ='R04B Insurer branches'!$C$9 | M41: ='R04B Insurer branches'!$E$9 | N41: Not started | O41: R04B →
A42: 20 | B42: R11 | C42: Receipt series in use | D42: Banks, bank accounts and cheque books | E42: BRD-02 | F42: Drop 1 | G42: Cashiering data steward (to name); approved by Operations - Financial Transactions; extracted by BDOI IT | H42: Migration Console | I42: Data Migration › Data Migration › Extracts and Batches | J42: D0-02 | K42: M3 (29 Jan 2027); final at T-3 | L42: ='R11 Receipt series in use'!$C$9 | M42: ='R11 Receipt series in use'!$E$9 | N42: Not started | O42: R11 →
A43: 21 | B43: UA-04 | C43: Separation-of-duties rules | D43: Users, access and approvals | E43: BRD-11 | F43: Drop 0 | G43: BDOI Information Security | H43: Configuration screen upload | I43: Setup & Administration › User Access › Separation of Duties | J43: UA-02 | K43: 16-Jul-2027 – Values for UAT | L43: ='UA-04 SoD rules'!$C$10 | M43: ='UA-04 SoD rules'!$E$10 | N43: Not started | O43: UA-04 →
A44: 22 | B44: UP-01 | C44: Clients not held in the legacy systems | D44: Clients and KYC | E44: BRD-01 | F44: Drop 1 | G44: Heads, Retail and Corporate Marketing; Product Owner, MBS | H44: Screen upload | I44: Client & Policy › Clients › Clients | J44: R01 | K44: 16-Jul-2027 – Values for UAT | L44: ='UP-01 Clients (upload)'!$C$9 | M44: ='UP-01 Clients (upload)'!$E$9 | N44: Not started | O44: UP-01 →
A45: 23 | B45: C01 | C45: Client master | D45: Clients and KYC | E45: BRD-01 | F45: Drop 1 | G45: Marketing data steward (to name); approved by Product Owner, MBS; Heads, Retail and Corporate Marketing; extracted by BDOI IT | H45: Migration Console | I45: Data Migration › Data Migration › Extracts and Batches | J45: R01, R03, D0-02 | K45: M3 (29 Jan 2027); deltas daily from T-14 days | L45: ='C01 Client master'!$C$10 | M45: ='C01 Client master'!$E$10 | N45: Not started | O45: C01 →
A46: 24 | B46: D0-10 | C46: Tax codes | D46: Chart of accounts, tax and accounting | E46: BRD-05 | F46: Drop 1 | G46: Head, Comptrollership (Tax) | H46: Configuration screen upload | I46: Finance › Tax & Statutory › Tax Codes & Forms | J46: D0-06 | K46: 16-Jul-2027 – Values for UAT | L46: ='D0-10 Tax codes'!$C$11 | M46: ='D0-10 Tax codes'!$E$11 | N46: Not started | O46: D0-10 →
A47: 25 | B47: D0-11 | C47: Company bank accounts | D47: Banks, bank accounts and cheque books | E47: BRD-05 | F47: Drop 1 | G47: Head, Comptrollership; Treasury | H47: Configuration screen upload | I47: Finance › Disbursement › Bank Accounts and Checks | J47: D0-06, D0-02 | K47: 4-Jan-2027 – Platform set-up for Drop 1 SIT | L47: ='D0-11 Bank accounts'!$C$10 | M47: ='D0-11 Bank accounts'!$E$10 | N47: Not started | O47: D0-11 →
A48: 26 | B48: PM-01 | C48: Product catalogue | D48: Products, packages and rates | E48: BRD-03 | F48: Drop 0 | G48: Product Owner, Marketing Business System (MBS) | H48: Migration Console | I48: Client & Policy › Product Maintenance › Products | J48: PM-09, R05 | K48: 9-Apr-2027 – Reference data for Trial migration 1 (M4) | L48: ='PM-01 Product catalogue'!$C$9 | M48: ='PM-01 Product catalogue'!$E$9 | N48: Not started | O48: PM-01 →
A49: 27 | B49: R08 | C49: Chart of accounts mapping | D49: Chart of accounts, tax and accounting | E49: BRD-05 | F49: Drop 1 | G49: Comptrollership data steward (to name); approved by Head, Comptrollership; Product Owner FRBS and ACSL; extracted by BDOI IT | H49: Migration Console | I49: Data Migration › Data Migration › Extracts and Batches | J49: D0-06 | K49: M3 (29 Jan 2027) | L49: ='R08 Chart of accounts mapping'!$C$9 | M49: ='R08 Chart of accounts mapping'!$E$9 | N49: Not started | O49: R08 →
A50: 28 | B50: UP-02 | C50: Payees | D50: Insurers, partners, intermediaries and payees | E50: BRD-05 | F50: Drop 1 | G50: Product Owner, Comptrollership - Disbursement | H50: Screen upload | I50: Finance › Disbursement › Disbursement Uploads | J50: MD-01 | K50: 9-Apr-2027 – Reference data for Trial migration 1 (M4) | L50: ='UP-02 Payees (upload)'!$C$9 | M50: ='UP-02 Payees (upload)'!$E$9 | N50: Not started | O50: UP-02 →
A51: 29 | B51: D0-01 | C51: Company | D51: Organisation | E51: BRD-05 | F51: Drop 1 | G51: Head, Comptrollership | H51: Configuration screen upload | I51: Setup & Administration › Setup › Companies | J51: D0-06 | K51: 4-Jan-2027 – Platform set-up for Drop 1 SIT | L51: ='D0-01 Company'!$C$10 | M51: ='D0-01 Company'!$E$10 | N51: Not started | O51: D0-01 →
A52: 30 | B52: D0-08 | C52: Accounting rules | D52: Chart of accounts, tax and accounting | E52: BRD-05 | F52: Drop 1 | G52: Head, Comptrollership | H52: Configuration screen upload | I52: Finance › Accounting Engine › Accounting Rules | J52: D0-04, D0-06 | K52: 4-Jan-2027 – Platform set-up for Drop 1 SIT | L52: ='D0-08 Accounting rules'!$C$9 | M52: ='D0-08 Accounting rules'!$E$9 | N52: Not started | O52: D0-08 →
A53: 31 | B53: D0-09 | C53: Legacy control accounts | D53: Chart of accounts, tax and accounting | E53: BRD-05 | F53: Drop 1 | G53: Head, Comptrollership | H53: Configuration screen upload | I53: Finance › General Ledger › Chart of Accounts | J53: D0-06 | K53: 1-Dec-2026 – Drafts with the Drop 0 sign-off | L53: ='D0-09 Legacy accounts'!$C$9 | M53: ='D0-09 Legacy accounts'!$E$9 | N53: Not started | O53: D0-09 →
A54: 32 | B54: D0-15 | C54: Approval limits and matrices | D54: Users, access and approvals | E54: BRD-00 | F54: Programme | G54: Owners of the modules; Head, Comptrollership for the amounts | H54: Configuration screen upload | I54: Client & Policy › Submitted Policies › Submitted Policies Setup or Client & Policy › Employee Benefits › EB Setup | J54: UA-02, UA-01 | K54: 16-Jul-2027 – Values for UAT | L54: ='D0-15 Approval limits'!$C$11 | M54: ='D0-15 Approval limits'!$E$11 | N54: Not started | O54: D0-15 →
A55: 33 | B55: R07 | C55: Commission rates by insurer and product | D55: Insurers, partners, intermediaries and payees | E55: BRD-03 | F55: Drop 0 | G55: Operations data steward (to name); approved by Head, Operations; extracted by BDOI IT | H55: Migration Console | I55: Data Migration › Data Migration › Extracts and Batches | J55: R04, R05 | K55: M3 (29 Jan 2027) | L55: ='R07 Commission rates by insurer'!$C$9 | M55: ='R07 Commission rates by insurer'!$E$9 | N55: Not started | O55: R07 →
A56: 34 | B56: TX-02 | C56: Tax forms and filing calendar | D56: Chart of accounts, tax and accounting | E56: BRD-05 | F56: Drop 1 | G56: Head, Comptrollership (Tax) | H56: Configuration screen – no upload: BDOI fills in this template and the rows are keyed on the screen, each record authorised by a second user | I56: Finance › Tax & Statutory › Tax Codes & Forms | J56: D0-06 | K56: 16-Jul-2027 – Values for UAT | L56: ='TX-02 Tax forms'!$C$9 | M56: ='TX-02 Tax forms'!$E$9 | N56: Not started | O56: TX-02 →
A57: 35 | B57: UA-03 | C57: Approvers, approval rules and limits | D57: Users, access and approvals | E57: BRD-11 | F57: Drop 0 | G57: Business Administration; BDOI Information Security for the second approval; Comptrollership for the authorisation limits | H57: Configuration screen upload | I57: Setup & Administration › Administration › Users | J57: UA-01 | K57: 16-Jul-2027 – Values for UAT | L57: ='UA-03 Approval rules'!$C$9 | M57: ='UA-03 Approval rules'!$E$9 | N57: Not started | O57: UA-03 →
A58: 36 | B58: PM-02 | C58: Coverages, perils and field rules | D58: Products, packages and rates | E58: BRD-03 | F58: Drop 0 | G58: MBS | H58: Configuration screen upload | I58: Client & Policy › Product Maintenance › Coverages & Clauses or Client & Policy › Product Maintenance › Products | J58: PM-09, PM-01 | K58: 16-Jul-2027 – Values for UAT | L58: ='PM-02 Coverages and rules'!$C$9 | M58: ='PM-02 Coverages and rules'!$E$9 | N58: Not started | O58: PM-02 →
A59: 37 | B59: PM-03 | C59: Clause library | D59: Products, packages and rates | E59: BRD-03 | F59: Drop 0 | G59: TSU (wordings); MBS (maintenance) | H59: Configuration screen upload | I59: Client & Policy › Product Maintenance › Coverages & Clauses | J59: PM-09, PM-01 | K59: 16-Jul-2027 – Values for UAT | L59: ='PM-03 Clause library'!$C$9 | M59: ='PM-03 Clause library'!$E$9 | N59: Not started | O59: PM-03 →
A60: 38 | B60: C02 | C60: Client addresses and contacts | D60: Clients and KYC | E60: BRD-01 | F60: Drop 1 | G60: Marketing data steward (to name); approved by Product Owner, MBS; Heads, Retail and Corporate Marketing; extracted by BDOI IT | H60: Migration Console | I60: Data Migration › Data Migration › Extracts and Batches | J60: C01 | K60: M3 (29 Jan 2027); deltas daily from T-14 days | L60: ='C02 Client addresses and contac'!$C$9 | M60: ='C02 Client addresses and contac'!$E$9 | N60: Not started | O60: C02 →
A61: 39 | B61: C03 | C61: Client payout accounts | D61: Clients and KYC | E61: BRD-05 | F61: Drop 1 | G61: Disbursement data steward (to name); approved by Product Owner, Comptrollership - Disbursement; extracted by BDOI IT | H61: Migration Console | I61: Data Migration › Data Migration › Extracts and Batches | J61: C01 | K61: M3 (29 Jan 2027) | L61: ='C03 Client payout accounts'!$C$9 | M61: ='C03 Client payout accounts'!$E$9 | N61: Not started | O61: C03 →
A62: 40 | B62: D0-12 | C62: Check books | D62: Banks, bank accounts and cheque books | E62: BRD-05 | F62: Drop 1 | G62: Treasury; Product Owner, Comptrollership - Disbursement | H62: Configuration screen upload | I62: Finance › Disbursement › Bank Accounts and Checks | J62: D0-11 | K62: 1-Nov-2027 – Production values before the dress rehearsal | L62: ='D0-12 Check books'!$C$9 | M62: ='D0-12 Check books'!$E$9 | N62: Not started | O62: D0-12 →
A63: 41 | B63: D0-13 | C63: Petty cash funds | D63: Banks, bank accounts and cheque books | E63: BRD-05 | F63: Drop 1 | G63: Head, Comptrollership | H63: Configuration screen upload | I63: Finance › Payables & Cash › Petty Cash | J63: D0-02, D0-05, D0-06, D0-11 | K63: 1-Nov-2027 – Production values before the dress rehearsal | L63: ='D0-13 Petty cash funds'!$C$9 | M63: ='D0-13 Petty cash funds'!$E$9 | N63: Not started | O63: D0-13 →
A64: 42 | B64: D0-14 | C64: Bank statement layouts | D64: Banks, bank accounts and cheque books | E64: BRD-05 | F64: Drop 1 | G64: Head, Comptrollership; Treasury | H64: Configuration screen upload | I64: Setup & Administration › Setup › Bank Statement Layouts | J64: D0-11 | K64: 16-Jul-2027 – Values for UAT | L64: ='D0-14 Statement layouts'!$C$9 | M64: ='D0-14 Statement layouts'!$E$9 | N64: Not started | O64: D0-14 →
A65: 43 | B65: G01 | C65: GL opening trial balance | D65: Chart of accounts, tax and accounting | E65: BRD-05 | F65: Drop 1 | G65: Comptrollership data steward (to name); approved by Head, Comptrollership; extracted by BDOI IT | H65: Migration Console | I65: Data Migration › Data Migration › Extracts and Batches | J65: R08, D0-02 | K65: M3 (29 Jan 2027); final at T-2; at each true-up | L65: ='G01 GL opening trial balance'!$C$9 | M65: ='G01 GL opening trial balance'!$E$9 | N65: Not started | O65: G01 →
A66: 44 | B66: PM-04 | C66: Rate tables | D66: Products, packages and rates | E66: BRD-03 | F66: Drop 0 | G66: Product Owner, MBS; Comptrollership (taxes) | H66: Configuration screen upload | I66: Client & Policy › Product Maintenance › Rates & Taxes | J66: PM-01 | K66: 16-Jul-2027 – Values for UAT | L66: ='PM-04 Rate tables'!$C$12 | M66: ='PM-04 Rate tables'!$E$12 | N66: Not started | O66: PM-04 →
A67: 45 | B67: PM-04C | C67: Other charges billed with the premium | D67: Products, packages and rates | E67: BRD-03 | F67: Drop 0 | G67: Product Owner, MBS; Head, Comptrollership (charges and accounts) | H67: Configuration screen upload | I67: Client & Policy › Product Maintenance › Rates & Taxes | J67: PM-01, D0-06 | K67: 16-Jul-2027 – Values for UAT | L67: ='PM-04C Other charges'!$C$10 | M67: ='PM-04C Other charges'!$E$10 | N67: Not started | O67: PM-04C →
A68: 46 | B68: PM-10 | C68: Incentive criteria | D68: Products, packages and rates | E68: BRD-03 | F68: Drop 0 | G68: Incentive Maintenance user (MBS); Comptrollership (CPC2 definition, PQ04) | H68: Configuration screen upload | I68: Client & Policy › Product Maintenance › Incentive Criteria | J68: PM-09, PM-01 | K68: 16-Jul-2027 – Values for UAT | L68: ='PM-10 Incentive criteria'!$C$9 | M68: ='PM-10 Incentive criteria'!$E$9 | N68: Not started | O68: PM-10 →
A69: 47 | B69: TX-01 | C69: Party tax profiles (clients, insurers, payees) | D69: Chart of accounts, tax and accounting | E69: BRD-05 | F69: Drop 1 | G69: Head, Comptrollership (Tax) | H69: Configuration screen – no upload: BDOI fills in this template and the rows are keyed on the screen, each record authorised by a second user | I69: Finance › Tax & Statutory › Party Tax Profiles | J69: D0-10, R04, C01, MD-01, UP-02 | K69: 16-Jul-2027 – Values for UAT | L69: ='TX-01 Party tax profiles'!$C$10 | M69: ='TX-01 Party tax profiles'!$E$10 | N69: Not started | O69: TX-01 →
A70: 48 | B70: PM-06 | C70: Packages in force at go-live | D70: Products, packages and rates | E70: BRD-03 | F70: Drop 0 | G70: TSU (prepares); Product Owner, MBS (approves) | H70: Configuration screen upload | I70: Client & Policy › Product Maintenance › Products | J70: PM-01, PM-02, R04, PM-03 | K70: 1-Nov-2027 – Production values before the dress rehearsal | L70: ='PM-06 Packages'!$C$9 | M70: ='PM-06 Packages'!$E$9 | N70: Not started | O70: PM-06 →
A71: 49 | B71: R06 | C71: Package code map (legacy package to BIBS package version) | D71: Products, packages and rates | E71: BRD-03 | F71: Drop 0 | G71: TSU (to name); approved by Product Owner, MBS (approves); TSU (prepares); extracted by BDOI IT | H71: Migration Console | I71: Data Migration › Data Migration › Extracts and Batches | J71: R05, PM-06 | K71: M5 (18 Jun 2027); final at T-7 | L71: ='R06 Package code map (legacy pa'!$C$9 | M71: ='R06 Package code map (legacy pa'!$E$9 | N71: Not started | O71: R06 →
A72: 50 | B72: PM-08 | C72: Document templates | D72: Products, packages and rates | E72: BRD-03 | F72: Drop 0 | G72: TSU and MBS (texts); Business Administrator (maintenance) | H72: Configuration screen upload | I72: Setup & Administration › Broking Setup › Document Templates | J72: - | K72: 16-Jul-2027 – Values for UAT | L72: ='PM-08 Document templates'!$C$9 | M72: ='PM-08 Document templates'!$E$9 | N72: Not started | O72: PM-08 →
A73: 51 | B73: UA-05 | C73: Password, session and sign-in parameters | D73: Users, access and approvals | E73: BRD-11 | F73: Drop 0 | G73: BDOI Information Security; BDOI IT for the sign-in mode | H73: Configuration screen upload | I73: Setup & Administration › Administration › System Parameters | J73: - | K73: 16-Jul-2027 – Values for UAT | L73: ='UA-05 Parameters'!$C$9 | M73: ='UA-05 Parameters'!$E$9 | N73: Not started | O73: UA-05 →
A74: 52 | B74: UP-03 | C74: Watchlist entries (sanctions, PEP and internal lists) | D74: Compliance | E74: BRD-10 | F74: Drop 1 | G74: Compliance (Chief Compliance Officer) | H74: Screen upload | I74: Setup & Administration › Compliance Setup › List Sources and Runs | J74: - | K74: 16-Jul-2027 – Values for UAT | L74: ='UP-03 Watchlist entries (upload'!$C$9 | M74: ='UP-03 Watchlist entries (upload'!$E$9 | N74: Not started | O74: UP-03 →
A76: Groups of datasets
A77: Group | D77: Templates | J77: Configuration screen upload | L77: Screen upload | N77: Migration Console | O77: Keyed on screen
A78: Organisation | D78: D0-01, D0-02, R02, D0-03, D0-04, D0-05, R03 | J78: 5 | L78: 0 | N78: 2 | O78: 0
A79: Users, access and approvals | D79: UA-06, UA-02, UA-01, UA-03, UA-04, UA-05, D0-15 | J79: 6 | L79: 1 | N79: 0 | O79: 0
A80: Chart of accounts, tax and accounting | D80: D0-07, D0-06, R08, D0-09, D0-08, D0-10, TX-02, TX-01, MD-02, MD-03, G01 | J80: 4 | L80: 1 | N80: 2 | O80: 4
A81: Banks, bank accounts and cheque books | D81: D0-11, D0-12, D0-13, D0-14, R11 | J81: 4 | L81: 0 | N81: 1 | O81: 0
A82: Products, packages and rates | D82: PM-09, R05, PM-01, PM-02, PM-03, PM-04, PM-04C, PM-06, R06, PM-10, PM-08 | J82: 8 | L82: 0 | N82: 3 | O82: 0
A83: Insurers, partners, intermediaries and payees | D83: R04, R04B, R07, MD-01, UP-02 | J83: 1 | L83: 1 | N83: 3 | O83: 0
A84: Clients and KYC | D84: R01, C01, C02, C03, UP-01 | J84: 0 | L84: 1 | N84: 4 | O84: 0
A85: Compliance | D85: UP-03 | J85: 0 | L85: 1 | N85: 0 | O85: 0
A87: Due milestones
A88: Due | B88: Milestone | F88: Due date | H88: Before go-live | J88: Why this date
A89: D1 | B89: Drafts with the Drop 0 sign-off | F89: 1-Dec-2026 | H89: T-56 weeks | J89: Sign-off of BRD-11 on 1-Dec-2026, the last of the three Drop 0 sets
A90: D2 | B90: Platform set-up for Drop 1 SIT | F90: 4-Jan-2027 | H90: T-52 weeks | J90: Drop 1 SIT runs Jan - Jul 2027 on the BDOI organisation, chart of accounts and banks
A91: D3 | B91: Reference data for Trial migration 1 (M4) | F91: 9-Apr-2027 | H91: T-38 weeks | J91: Extracts for Trial migration 1; reference data and clients first
A92: D4 | B92: Code maps approved (M5) | F92: 18-Jun-2027 | H92: T-28 weeks | J92: Code maps approved for Trial migration 2, including the package code map
A93: D5 | B93: Values for UAT | F93: 16-Jul-2027 | H93: T-24 weeks | J93: UAT plans and sign-off forms due 16-Jul-2027; UAT Aug - Dec 2027 runs on the production values
A94: D6 | B94: Production values before the dress rehearsal | F94: 1-Nov-2027 | H94: T-9 weeks | J94: Dress rehearsal in November 2027; the values loaded for it are the go-live values
A95: D7 | B95: Map freeze (T-7) | F95: 27-Dec-2027 | H95: T-1 weeks | J95: No change of a code map or reference value after the freeze except by change request
A97: Other sheets
A98: Sheet | D98: What it holds
A99: Lists of values | D99: Every list of values of BIBS with its owner and its route: legacy values mapped through the Migration Console (R01), the others entered on Lists of Values
A100: System parameters | D100: Every system parameter of BIBS (other than the SLA and turnaround parameters and the numbering prefixes) with the value proposed and the value BDOI wants
A101: SLA and turnaround | D101: The SLA, turnaround, reminder, escalation and ageing parameters: days and hours of the work queues, insurer replies, reminders and alerts
A102: Numbering prefixes | D102: Prefixes of the numbered documents; receipt series come from R11, check numbers from D0-12
A103: Notification events | D103: Every notification event with its default channels and the unit mailbox that also receives it; users choose their own channels in Notification Settings
A104: Document templates | D104: Every generated document and letter with the unit that gives its BDOI wording and layout; the layout is uploaded as a Word file on Document Templates
A105: Accounting events | D105: The accounting events that need a rule of template D0-08 (accounting rules mapping); owner Head, Comptrollership
A106: PM-04 Charges checklist | D106: Premium charges billed to clients: one row per charge with the rule BIBS applies
A107: D0-10 Tax checklist | D107: BDOI's own taxes: one row per kind of tax, what BIBS does and what BDOI provides
A108: Configured on screens | D108: Set-up decided in working sessions and entered on the screens (no template)
...

Sheet D0-02 Branches
A1: D0-02 Branches | O1: Step 1 of 52
A2: ← Back to Start here | B2: Step 1 of 52. Fill in one row per record below the column headers; the guide above each column says what to enter. | O2: Ask a question →
A3: Purpose | B3: Every BDOI branch and invoicing branch
A4: Provided by | B4: Head, Comptrollership
A5: Due | B5: 4-Jan-2027 – Platform set-up for Drop 1 SIT
A6: How it is loaded | B6: Upload on the configuration screen Setup & Administration › Setup › Branches, approved by a second user
A7: Source | B7: Upload template of the configuration screen (the same columns, headers, mandatory flags and allowed values)
A8: Depends on | B8: Nothing: this template can be filled in first
A9: Tax registration | B9: The BIR branch code and the RDO code of each branch registered with the BIR (blank for a branch that is not a separate registration)
A10: Progress | B10: Rows entered | C10: =SUMPRODUCT(((ROW($B$18:$B$518)>18)+($B$18<>"HO")>0)*(LEN($B$18:$B$518&$C$18:$C$518&$D$18:$D$518&$E$18:$E$518&$F$18:$F$518&$G$18:$G$518&$H$18:$H$518&$I$18:$I$518&$J$18:$J$518&$K$18:$K$518&$L$18:$L$518&$M$18:$M$518&$N$18:$N$518&$O$18:$O$518)>0)) | D10: Mandatory cells missing | E10: =SUMPRODUCT(((ROW($B$18:$B$518)>18)+($B$18<>"HO")>0)*(LEN($B$18:$B$518&$C$18:$C$518&$D$18:$D$518&$E$18:$E$518&$F$18:$F$518&$G$18:$G$518&$H$18:$H$518&$I$18:$I$518&$J$18:$J$518&$K$18:$K$518&$L$18:$L$518&$M$18:$M$518&$N$18:$N$518&$O$18:$O$518)>0)*(($B$18:$B$518="")+($C$18:$C$518="")+($F$18:$F$518="")+($G$18:$G$518="")+($H$18:$H$518="")))
A11: Confirmed by (BDOI owner) | D11: Date
A13: Mandatory | B13: Yes | C13: Yes | D13: No | E13: No | F13: Yes | G13: Yes | H13: Yes | I13: No | J13: No | K13: No | L13: No | M13: No | N13: No | O13: No
A14: Format | B14: Up to 10 capitals | C14: Text | D14: Text | E14: Text | F14: Date dd-MMM-yyyy, e.g. 15-Jan-2026 | G14: Y or N | H14: Y or N | I14: Text | J14: Text | K14: Text | L14: SAT, SUN | M14: Codes separated by commas | N14: 3 to 5 digits | O14: Three digits, optionally a letter
A15: Allowed values | B15: Free entry | C15: Free entry | D15: Free entry | E15: Free entry | F15: A date, for example 15-Jan-2028 | G15: Y or N | H15: Y or N | I15: Free entry | J15: Free entry | K15: Free entry | L15: Free entry | M15: Free entry | N15: Free entry | O15: Free entry
A16: What to enter | B16: Code of the branch; unique | C16: Name shown on screens and documents | D16: Region of the branch | E16: Address printed on documents | F16: Date the branch opened | G16: Y for one branch only | H16: May receive and pay in foreign currency | I16: Branch telephone | J16: Branch mailbox | K16: Head of the branch | L16: Days the branch is closed each week | M16: Legacy branch codes for the code map BRANCH | N16: Branch code of the BIR registration | O16: Revenue District Office of the branch
A17: Row | B17: Branch code * | C17: Branch name * | D17: Region | E17: Address | F17: Opening date * | G17: Head office * | H17: Foreign currency authorised * | I17: Contact phone | J17: Contact e-mail | K17: Branch manager | L17: Weekly rest days | M17: Legacy branch codes | N17: BIR branch code | O17: RDO code
A18: Example – overwrite or delete | B18: HO | C18: Head Office | D18: NCR | E18: Makati City | F18: 40179 | G18: Y | H18: Y | I18: (02) 8888-0000 | J18: ho@company.example.ph | L18: SAT,SUN | M18: 001 | N18: 00000 | O18: 050

Sheet D0-04 Dimensions
A1: D0-04 Cost centres and business lines | G1: Step 2 of 52
A2: ← Back to Start here | B2: Step 2 of 52. Fill in one row per record below the column headers; the guide above each column says what to enter. | G2: Ask a question →
A3: Purpose | B3: The values of the dimensions of journal lines
A4: Provided by | B4: Head, Comptrollership
A5: Due | B5: 4-Jan-2027 – Platform set-up for Drop 1 SIT
A6: How it is loaded | B6: Upload on the configuration screen Setup & Administration › Setup › Dimensions, approved by a second user
A7: Source | B7: Upload template of the configuration screen (the same columns, headers, mandatory flags and allowed values)
A8: Depends on | B8: Nothing: this template can be filled in first
A9: Progress | B9: Rows entered | C9: =SUMPRODUCT(((ROW($B$17:$B$517)>17)+($B$17<>"COST_CENTER")>0)*(LEN($B$17:$B$517&$C$17:$C$517&$D$17:$D$517&$E$17:$E$517)>0)) | D9: Mandatory cells missing | E9: =SUMPRODUCT(((ROW($B$17:$B$517)>17)+($B$17<>"COST_CENTER")>0)*(LEN($B$17:$B$517&$C$17:$C$517&$D$17:$D$517&$E$17:$E$517)>0)*(($B$17:$B$517="")+($C$17:$C$517="")+($D$17:$D$517="")+($E$17:$E$517="")))
A10: Confirmed by (BDOI owner) | D10: Date
A12: Mandatory | B12: Yes | C12: Yes | D12: Yes | E12: Yes
A13: Format | B13: Code from the drop-down | C13: Up to 20 capitals or digits | D13: Text | E13: Y or N
A14: Allowed values | B14: COST_CENTER, BUSINESS_LINE, DEPARTMENT (list Dimension (D0-04)) | C14: Free entry | D14: Free entry | E14: Y or N
A15: What to enter | B15: Dimension of the value | C15: Code of the value | D15: Name shown on screens and reports | E15: N keeps the value for history only
A16: Row | B16: Dimension * | C16: Code * | D16: Name * | E16: Active *
A17: Example – overwrite or delete | B17: COST_CENTER | C17: FIN | D17: Finance and Accounting | E17: Y

Sheet D0-07 Categories and numbering
A1: D0-07 Account categories and numbering | I1: Step 3 of 52
A2: ← Back to Start here | B2: Step 3 of 52. Fill in one row per record below the column headers; the guide above each column says what to enter. | I2: Ask a question →
A3: Purpose | B3: The GL categories and the numbering scheme under each parent account
A4: Provided by | B4: Head, Comptrollership
A5: Due | B5: 4-Jan-2027 – Platform set-up for Drop 1 SIT
A6: How it is loaded | B6: Upload on the configuration screen Finance › General Ledger › Chart Upload, approved by a second user
A7: Source | B7: Upload template of the configuration screen (the same columns, headers, mandatory flags and allowed values)
A8: Depends on | B8: Nothing: this template can be filled in first
A9: Progress | B9: Rows entered | C9: =SUMPRODUCT(((ROW($B$17:$B$517)>17)+($B$17<>"CATEGORY")>0)*(LEN($B$17:$B$517&$C$17:$C$517&$D$17:$D$517&$E$17:$E$517&$F$17:$F$517&$G$17:$G$517&$H$17:$H$517&$I$17:$I$517)>0)) | D9: Mandatory cells missing | E9: =SUMPRODUCT(((ROW($B$17:$B$517)>17)+($B$17<>"CATEGORY")>0)*(LEN($B$17:$B$517&$C$17:$C$517&$D$17:$D$517&$E$17:$E$517&$F$17:$F$517&$G$17:$G$517&$H$17:$H$517&$I$17:$I$517)>0)*(($B$17:$B$517="")))
A10: Confirmed by (BDOI owner) | D10: Date
A12: Mandatory | B12: Yes | C12: Conditional: CATEGORY | D12: Conditional: CATEGORY | E12: Conditional: CATEGORY | F12: Conditional: CATEGORY | G12: Conditional: NUMBERING | H12: Conditional: NUMBERING | I12: Conditional: NUMBERING
A13: Format | B13: Code from the drop-down | C13: Text | D13: Text | E13: Code from the drop-down | F13: Y or N | G13: Text | H13: Code from the drop-down | I13: Number without thousands separators, e.g. 1500000.50
A14: Allowed values | B14: CATEGORY, NUMBERING (list Row (D0-07)) | C14: Free entry | D14: Free entry | E14: ASSET, LIABILITY, EQUITY, INCOME, EXPENSE, MEMORANDUM (list Account class (D0-07)) | F14: Y or N | G14: Code of an existing account of the chart of accounts | H14: ., - (list Separator (D0-07)) | I14: A whole number from 1 to 6
A15: What to enter | B15: What the row defines | C15: GL category | D15: Name of the category | E15: Class of the accounts of the category | F15: Y for the accounts of bank accounts | G15: Parent whose children are numbered | H15: Between the parent code and the running number | I15: Digits of the running number
A16: Row | B16: Row * | C16: Category code | D16: Category name | E16: Account class | F16: Bank category | G16: Parent account | H16: Separator | I16: Width
A17: Example – overwrite or delete | B17: CATEGORY | C17: CASH_IN_BANK | D17: Cash in bank | E17: ASSET | F17: Y | G17: 1110 | H17: . | I17: 2

Sheet MD-02 Currencies
A1: MD-02 Currencies | G1: Step 4 of 52
A2: ← Back to Start here | B2: Step 4 of 52. Fill in one row per record below the column headers; the guide above each column says what to enter. | G2: Ask a question →
A3: Purpose | B3: One row per currency BIBS accepts on transactions and bank accounts: the base currency PHP and each foreign currency BDOI deals in.
A4: Provided by | B4: Head, Comptrollership (Treasury)
A5: Due | B5: 4-Jan-2027 – Platform set-up for Drop 1 SIT
A6: How it is loaded | B6: Configuration screen: Setup & Administration › Setup › Currencies & Rates, authorised by a second user
A7: Source | B7: BDOI currency list
A8: Depends on | B8: Nothing: this template can be filled in first
A9: Progress | B9: Rows entered | C9: =SUMPRODUCT(((ROW($B$17:$B$317)>17)+($B$17<>"USD")>0)*(LEN($B$17:$B$317&$C$17:$C$317&$D$17:$D$317&$E$17:$E$317&$F$17:$F$317)>0)) | D9: Mandatory cells missing | E9: =SUMPRODUCT(((ROW($B$17:$B$317)>17)+($B$17<>"USD")>0)*(LEN($B$17:$B$317&$C$17:$C$317&$D$17:$D$317&$E$17:$E$317&$F$17:$F$317)>0)*(($B$17:$B$317="")+($C$17:$C$317="")+($E$17:$E$317="")+($F$17:$F$317="")))
A10: Confirmed by (BDOI owner) | D10: Date
A12: Mandatory | B12: Yes | C12: Yes | D12: No | E12: Yes | F12: Yes
A13: Format | B13: ISO 4217, 3 capitals | C13: Text, up to 60 | D13: Up to 5 characters | E13: Whole number 0 to 4 | F13: Y or N
A14: Allowed values | B14: Free entry, up to 3 characters | C14: Free entry, up to 60 characters | D14: Free entry, up to 5 characters | E14: A whole number from 0 to 4 | F14: Y or N
A15: What to enter | B15: Code of the currency | C15: Name of the currency | D15: Symbol printed on documents | E15: Decimals of the amounts in the currency | F15: Y when the currency may be used
A16: Row | B16: Currency code * | C16: Name * | D16: Symbol | E16: Decimal places * | F16: Active *
A17: Example – overwrite or delete | B17: USD | C17: US dollar | D17: $ | E17: 2 | F17: Y

Sheet PM-09 Lists and parameters
A1: PM-09 Lists of values and parameters | G1: Step 5 of 52
A2: ← Back to Start here | B2: Step 5 of 52. Fill in one row per record below the column headers; the guide above each column says what to enter. | G2: Ask a question →
A3: Purpose | B3: The values of the Product Maintenance lists (request reasons, response outcomes, advisory groups, not-proceeded reasons, incentive types, coverage kinds, clause kinds, document types, market segments) and the parameters (numbering, reply days, expiry notice, advisory groups, service levels)
A4: Provided by | B4: Product Owner, MBS; System Administrator (entry)
A5: Due | B5: 16-Jul-2027 – Values for UAT
A6: How it is loaded | B6: Upload on the configuration screen Setup & Administration › Broking Setup › Lists of Values or Setup & Administration › Administration › System Parameters, approved by a second user
A7: Source | B7: Upload template of the configuration screen (the same columns, headers, mandatory flags and allowed values)
A8: Depends on | B8: Nothing: this template can be filled in first
A9: Progress | B9: Rows entered | C9: =SUMPRODUCT(((ROW($B$17:$B$517)>17)+($B$17<>"PKG_REQUEST_REASON")>0)*(LEN($B$17:$B$517&$C$17:$C$517&$D$17:$D$517&$E$17:$E$517&$F$17:$F$517)>0)) | D9: Mandatory cells missing | E9: =SUMPRODUCT(((ROW($B$17:$B$517)>17)+($B$17<>"PKG_REQUEST_REASON")>0)*(LEN($B$17:$B$517&$C$17:$C$517&$D$17:$D$517&$E$17:$E$517&$F$17:$F$517)>0)*(($B$17:$B$517="")+($D$17:$D$517="")))
A10: Confirmed by (BDOI owner) | D10: Date
A12: Mandatory | B12: Yes | C12: Conditional: list | D12: Yes | E12: Conditional: list | F12: Conditional: list
A13: Format | B13: Code from the drop-down | C13: Up to 40 capitals | D13: Text | E13: Text | F13: dd-MMM-yyyy
A14: Allowed values | B14: List List or parameter (PM-09): 23 values, see Reference lists | C14: Free entry | D14: Free entry | E14: Free entry | F14: Free entry
A15: What to enter | B15: List or parameter | C15: Code of the value of a list | D15: Label of the value, or value of the parameter | E15: Order; active Y or N | F15: First day of use of the value
A16: Row | B16: List or parameter * | C16: Value code | D16: Label or value * | E16: Order / Active | F16: Effective from
A17: Example – overwrite or delete | B17: PKG_REQUEST_REASON | C17: LOSS_EXPERIENCE | D17: Loss experience | E17: 50; Y

Sheet R01 Lists of values and MIS val
A1: R01 Lists of values and MIS values | I1: Step 6 of 52
A2: ← Back to Start here | B2: Step 6 of 52. Fill in one row per record below the column headers; the guide above each column says what to enter. | I2: Ask a question →
A3: Purpose | B3: One row per record of Lists of values and MIS values as extracted from QPS, EBIX. Key list_type, code. Sent as the file R01_template.csv (CSV, header row as below) with its control file (row count, count of distinct keys).
A4: Provided by | B4: MBS data steward (to name); approved by Product Owner, Marketing Business System (MBS); extracted by BDOI IT
A5: Due | B5: M3 (29 Jan 2027)
A6: How it is loaded | B6: Migration Console: the file R01_template.csv (the header row as below) and its control file are received on Data Migration › Data Migration › Extracts and loaded by a batch of object R01; lands in: Lists of Values (maker-checker); MIS field catalogue
A7: Source | B7: QPS, EBIX
A8: Depends on | B8: Nothing: this template can be filled in first
A9: Progress | B9: Rows entered | C9: =SUMPRODUCT(((ROW($B$18:$B$218)>18)+($B$18<>"MARKET_SEGMENT")>0)*(LEN($B$18:$B$218&$C$18:$C$218&$D$18:$D$218&$E$18:$E$218&$F$18:$F$218&$G$18:$G$218&$H$18:$H$218&$I$18:$I$218)>0)) | D9: Mandatory cells missing | E9: =SUMPRODUCT(((ROW($B$18:$B$218)>18)+($B$18<>"MARKET_SEGMENT")>0)*(LEN($B$18:$B$218&$C$18:$C$218&$D$18:$D$218&$E$18:$E$218&$F$18:$F$218&$G$18:$G$218&$H$18:$H$218&$I$18:$I$218)>0)*(($B$18:$B$218="")+($C$18:$C$218="")+($D$18:$D$218="")+($F$18:$F$218="")))
A10: Confirmed by (BDOI owner) | D10: Date
A12: Check when loaded | B12: Known list name | C12: Unique per list_type | D12: Not blank | E12: Parent exists in the file | F12: Y or N | G12: Valid date | H12: Not before effective_from | I12: 0 or more
A13: Mandatory | B13: Yes | C13: Yes | D13: Yes | E13: No | F13: Yes | G13: No | H13: No | I13: No
A14: Format | B14: Code, up to 40; Upper case | C14: Code, up to 40; As stored in legacy | D14: Text, up to 200; Free text | E14: Code, up to 40 | F14: Flag, up to 1; Y or N | G14: Date, up to 10; yyyy-MM-dd | H14: Date, up to 10; yyyy-MM-dd | I14: Integer, up to 9; Digits
A15: Allowed values | B15: Legacy list names; one code map set LOV:<list> or MIS:<field> per list | C15: Free entry, up to 40 characters | D15: Free entry, up to 200 characters | E15: Codes of the same file | F15: Y or N | G15: Free entry | H15: Free entry | I15: A whole number
A16: What to enter | B16: Legacy name of the list (for example MARKET_SEGMENT, BUSINESS_ORIGIN, CUSTOMER_SEGMENT, REGION, AREA, DEPARTMENT, ACCOUNT_TYPE, ID_TYPE, NATIONALITY) | C16: Legacy value code | D16: Legacy value description | E16: Code of the parent value for hierarchical lists (area under region) | F16: Value in use in legacy | G16: First day the value is valid | H16: Last day the value is valid | I16: Number of legacy records that use the value (helps the mapping)
A17: Row | B17: list_type * | C17: code * | D17: description * | E17: parent_code | F17: active_flag * | G17: effective_from | H17: effective_to | I17: used_count
A18: Example – overwrite or delete | B18: MARKET_SEGMENT | C18: CBG | D18: Consumer Banking Group | E18: NCR | F18: Y | G18: 2020-01-01 | I18: 1520

Sheet R04 Insurers
A1: R04 Insurers | K1: Step 7 of 52
A2: ← Back to Start here | B2: Step 7 of 52. Fill in one row per record below the column headers; the guide above each column says what to enter. | K2: Ask a question →
A3: Purpose | B3: One row per record of Insurers and insurer branches as extracted from QPS, EBIX. Key insurer_code. Sent as the file R04_template.csv (CSV, header row as below) with its control file (row count, count of distinct keys).
A4: Provided by | B4: Operations data steward (to name); approved by Head, Operations; extracted by BDOI IT
A5: Due | B5: M3 (29 Jan 2027)
A6: How it is loaded | B6: Migration Console: the file R04_template.csv (the header row as below) and its control file are received on Data Migration › Data Migration › Extracts and loaded by a batch of object R04; lands in: Insurers and insurer branches (insurer and party records)
A7: Source | B7: QPS, EBIX
A8: Depends on | B8: Nothing: this template can be filled in first
A9: Tax profile | B9: The insurer's registered TIN, VAT treatment and the ATC it withholds on BDOI's commission are kept in the party tax profile (template TX-01)
A10: Tax status | B10: VAT-registered (VAT on premium) or not VAT-registered (premium tax) is not a column of this layout: it is entered on the insurer screen (Client & Policy › Product Maintenance › Insurers, field Tax status); blank keeps the tax of the product line
A11: Progress | B11: Rows entered | C11: =SUMPRODUCT(((ROW($B$20:$B$220)>20)+($B$20<>"MAL")>0)*(LEN($B$20:$B$220&$C$20:$C$220&$D$20:$D$220&$E$20:$E$220&$F$20:$F$220&$G$20:$G$220&$H$20:$H$220&$I$20:$I$220&$J$20:$J$220&$K$20:$K$220)>0)) | D11: Mandatory cells missing | E11: =SUMPRODUCT(((ROW($B$20:$B$220)>20)+($B$20<>"MAL")>0)*(LEN($B$20:$B$220&$C$20:$C$220&$D$20:$D$220&$E$20:$E$220&$F$20:$F$220&$G$20:$G$220&$H$20:$H$220&$I$20:$I$220&$J$20:$J$220&$K$20:$K$220)>0)*(($B$20:$B$220="")+($C$20:$C$220="")+($K$20:$K$220="")))
A12: Confirmed by (BDOI owner) | D12: Date
A14: Check when loaded | B14: Unique | C14: Not blank | D14: - | E14: 9 to 12 digits | F14: - | G14: - | H14: Valid date | I14: Valid e-mail addresses | J14: 0 to 365 | K14: Mapped
A15: Mandatory | B15: Yes | C15: Yes | D15: No | E15: No | F15: No | G15: No | H15: No | I15: No | J15: No | K15: Yes
A16: Format | B16: Code, up to 30; As stored in legacy | C16: Text, up to 200; Free text | D16: Text, up to 40; Free text | E16: Text, up to 20; 000-000-000-000 | F16: Text, up to 300; Free text | G16: Text, up to 40; Free text | H16: Date, up to 10; yyyy-MM-dd | I16: Text, up to 500; name@domain;name@domain | J16: Integer, up to 3; Digits | K16: Code, up to 20; As stored in legacy
A17: Allowed values | B17: Free entry, up to 30 characters | C17: Free entry, up to 200 characters | D17: Free entry, up to 40 characters | E17: Free entry, up to 20 characters | F17: Free entry, up to 300 characters | G17: Free entry, up to 40 characters | H17: Free entry | I17: Free entry, up to 500 characters | J17: A whole number | K17: The legacy code; mapped by the code map STATUS:INSURER (Code Maps screen of the Data Migration Console; maps prepared in the Migration Workbook of BRD-13)
A18: What to enter | B18: Legacy insurer code | C18: Registered name | D18: Short name | E18: Tax identification number | F18: Registered address | G18: Insurance Commission accreditation number | H18: End of accreditation | I18: E-mail address(es) for placement, separated by semicolons | J18: Credit term in days | K18: Insurer status in legacy
A19: Row | B19: insurer_code * | C19: insurer_name * | D19: short_name | E19: tin | F19: address | G19: accreditation_no | H19: accredited_until | I19: placement_email | J19: default_credit_days | K19: status *
A20: Example – overwrite or delete | B20: MAL | C20: Malayan Insurance Co., Inc. | D20: Malayan | E20: 000-123-456-000 | F20: 500 Quintin Paredes St., Manila | G20: IC-2025-0123 | H20: 2028-06-30 | I20: placement@insurer.example | J20: 60 | K20: ACTIVE

Sheet UA-02 Role matrix
A1: UA-02 Role-to-permission matrix | I1: Step 8 of 52
A2: ← Back to Start here | B2: Step 8 of 52. Fill in one row per record below the column headers; the guide above each column says what to enter. | I2: Ask a question →
A3: Purpose | B3: The group profiles BDOI keeps, their privilege level and the permissions of each, starting from the User Access Matrix as delivered
A4: Provided by | B4: Business Administration with the unit heads; reviewed and signed by BDOI Information Security
A5: Due | B5: 9-Apr-2027 – Reference data for Trial migration 1 (M4)
A6: How it is loaded | B6: Upload on the configuration screen Setup & Administration › Administration › Roles & Permissions, approved by a second user
A7: Source | B7: Upload template of the configuration screen (the same columns, headers, mandatory flags and allowed values)
A8: Depends on | B8: Nothing: this template can be filled in first
A9: Progress | B9: Rows entered | C9: =SUMPRODUCT(((ROW($B$17:$B$517)>17)+($B$17<>"MKT_AO")>0)*(LEN($B$17:$B$517&$C$17:$C$517&$D$17:$D$517&$E$17:$E$517&$F$17:$F$517&$G$17:$G$517&$H$17:$H$517&$I$17:$I$517)>0)) | D9: Mandatory cells missing | E9: =SUMPRODUCT(((ROW($B$17:$B$517)>17)+($B$17<>"MKT_AO")>0)*(LEN($B$17:$B$517&$C$17:$C$517&$D$17:$D$517&$E$17:$E$517&$F$17:$F$517&$G$17:$G$517&$H$17:$H$517&$I$17:$I$517)>0)*(($B$17:$B$517="")+($C$17:$C$517="")+($E$17:$E$517="")+($F$17:$F$517="")+($H$17:$H$517="")+($I$17:$I$517="")))
A10: Confirmed by (BDOI owner) | D10: Date
A12: Mandatory | B12: Yes | C12: Yes | D12: No | E12: Yes | F12: Yes | G12: No | H12: Yes | I12: Yes
A13: Format | B13: Up to 40 capital letters, digits or _ | C13: Text | D13: Text | E13: Code from the drop-down | F13: Text | G13: Text | H13: Code from the drop-down | I13: Text
A14: Allowed values | B14: Free entry | C14: Free entry | D14: Free entry | E14: Low, Standard, High, Admin (list Privilege level (UA-02)) | F14: Permission code of the User Access Matrix | G14: Free entry | H14: KEEP, ADD, REMOVE (list Keep / Add / Remove (UA-02)) | I14: Free entry
A15: What to enter | B15: Code of the profile; an existing code changes the profile | C15: Name shown on screens | D15: What the profile is for | E15: Low, Standard, High or Admin | F15: One row per permission of the profile | G15: As shown by the matrix, for the review | H15: Change against the matrix as delivered | I15: Unit head who confirms the row
A16: Row | B16: Group profile code * | C16: Name * | D16: Description | E16: Privilege level * | F16: Permission * | G16: Action class | H16: Keep / Add / Remove * | I16: Approved by unit head *
A17: Example – overwrite or delete | B17: MKT_AO | C17: Marketing Account Officer | D17: Marketing account officers | E17: Standard | F17: QUOTE_MAINTAIN | G17: Create, Amend | H17: KEEP | I17: Carla Reyes

Sheet UA-06 Lists of values
A1: UA-06 Lists of values | G1: Step 9 of 52
A2: ← Back to Start here | B2: Step 9 of 52. Fill in one row per record below the column headers; the guide above each column says what to enter. | G2: Ask a question →
A3: Purpose | B3: The values of the lists of user access (business unit groups and user levels, empty as delivered; deactivation reasons, to confirm with BDOI; the reason No sign-in for the dormancy period is used by the dormant-user job and stays)
A4: Provided by | B4: Business Administration
A5: Due | B5: 1-Nov-2027 – before the templates that use its codes
A6: How it is loaded | B6: Upload on the configuration screen Setup & Administration › Broking Setup › Lists of Values, approved by a second user
A7: Source | B7: Upload template of the configuration screen (the same columns, headers, mandatory flags and allowed values)
A8: Depends on | B8: Nothing: this template can be filled in first
A9: Progress | B9: Rows entered | C9: =SUMPRODUCT(((ROW($B$17:$B$517)>17)+($B$17<>"UAM_BUSINESS_UNIT")>0)*(LEN($B$17:$B$517&$C$17:$C$517&$D$17:$D$517&$E$17:$E$517&$F$17:$F$517)>0)) | D9: Mandatory cells missing | E9: =SUMPRODUCT(((ROW($B$17:$B$517)>17)+($B$17<>"UAM_BUSINESS_UNIT")>0)*(LEN($B$17:$B$517&$C$17:$C$517&$D$17:$D$517&$E$17:$E$517&$F$17:$F$517)>0)*(($B$17:$B$517="")+($C$17:$C$517="")+($D$17:$D$517="")+($F$17:$F$517="")))
A10: Confirmed by (BDOI owner) | D10: Date
A12: Mandatory | B12: Yes | C12: Yes | D12: Yes | E12: No | F12: Yes
A13: Format | B13: Code from the drop-down | C13: Up to 30 capitals, digits or _ | D13: Up to 120 characters | E13: Number without thousands separators, e.g. 1500000.50 | F13: Date dd-MMM-yyyy, e.g. 15-Jan-2026
A14: Allowed values | B14: UAM_BUSINESS_UNIT, UAM_USER_LEVEL, UAM_DEACTIVATION_REASON (list List (UA-06)) | C14: Free entry | D14: Free entry | E14: A number | F14: A date, for example 15-Jan-2028
A15: What to enter | B15: The list | C15: Code of the value | D15: Label shown on screens | E15: Order in the drop-down | F15: Date the value may be used
A16: Row | B16: List * | C16: Code * | D16: Label * | E16: Sort order | F16: Effective from *
A17: Example – overwrite or delete | B17: UAM_BUSINESS_UNIT | C17: COMBANK_MKT | D17: Combank Marketing | E17: 10 | F17: 46391

Sheet D0-05 Employees
A1: D0-05 Employees | H1: Step 10 of 52
A2: ← Back to Start here | B2: Step 10 of 52. Fill in one row per record below the column headers; the guide above each column says what to enter. | H2: Ask a question →
A3: Purpose | B3: Employees used by the cost-centre rules, petty cash and staff advances
A4: Provided by | B4: Human Resources; Head, Comptrollership
A5: Due | B5: 16-Jul-2027 – Values for UAT
A6: How it is loaded | B6: Upload on the configuration screen Setup & Administration › Setup › Employees, approved by a second user
A7: Source | B7: Upload template of the configuration screen (the same columns, headers, mandatory flags and allowed values)
A8: Depends on | B8: D0-02 Branches → | D8: D0-04 Cost centres and business lines →
A9: Progress | B9: Rows entered | C9: =SUMPRODUCT(((ROW($B$17:$B$517)>17)+($B$17<>"1203344")>0)*(LEN($B$17:$B$517&$C$17:$C$517&$D$17:$D$517&$E$17:$E$517&$F$17:$F$517&$G$17:$G$517&$H$17:$H$517)>0)) | D9: Mandatory cells missing | E9: =SUMPRODUCT(((ROW($B$17:$B$517)>17)+($B$17<>"1203344")>0)*(LEN($B$17:$B$517&$C$17:$C$517&$D$17:$D$517&$E$17:$E$517&$F$17:$F$517&$G$17:$G$517&$H$17:$H$517)>0)*(($B$17:$B$517="")+($C$17:$C$517="")+($D$17:$D$517="")+($E$17:$E$517="")))
A10: Confirmed by (BDOI owner) | D10: Date
A12: Mandatory | B12: Yes | C12: Yes | D12: Yes | E12: Yes | F12: No | G12: No | H12: No
A13: Format | B13: HR number | C13: Text | D13: Text | E13: Text | F13: Text | G13: Text | H13: Date dd-MMM-yyyy, e.g. 15-Jan-2026
A14: Allowed values | B14: Free entry | C14: Free entry | D14: Code of an existing branch | E14: Code of an existing cost centre | F14: Free entry | G14: Free entry | H14: A date, for example 15-Jan-2028
A15: What to enter | B15: Employee number; unique | C15: Name of the employee | D15: Home branch | E15: Cost centre of the employee | F15: Position title | G15: For advices and statements | H15: Date of hire
A16: Row | B16: Employee number * | C16: Full name * | D16: Branch code * | E16: Cost centre * | F16: Position | G16: E-mail | H16: Hired on
A17: Example – overwrite or delete | B17: 1203344 | C17: Andrea Mercado | D17: HO | E17: FIN | F17: Accounting Officer | G17: andrea.mercado@company.example.ph | H17: 43527

Sheet D0-06 Chart of accounts
A1: D0-06 Chart of accounts | Q1: Step 11 of 52
A2: ← Back to Start here | B2: Step 11 of 52. Fill in one row per record below the column headers; the guide above each column says what to enter. | Q2: Ask a question →
A3: Purpose | B3: The production chart of accounts, in the columns of the chart upload. List every parent before its children. Accounts are created pending authorization.
A4: Provided by | B4: Head, Comptrollership
A5: Due | B5: 4-Jan-2027 – Platform set-up for Drop 1 SIT
A6: How it is loaded | B6: Chart Upload (General Ledger): the file is checked row by row and every account is created pending authorisation by Comptrollership
A7: Source | B7: The BDOI chart of accounts in use, completed with the legacy control accounts (D0-09)
A8: Depends on | B8: D0-07 Account categories and numbering →
A9: Progress | B9: Rows entered | C9: =SUMPRODUCT(((ROW($C$17:$C$517)>17)+($C$17<>"1210.07")>0)*(LEN($B$17:$B$517&$C$17:$C$517&$D$17:$D$517&$E$17:$E$517&$F$17:$F$517&$G$17:$G$517&$H$17:$H$517&$I$17:$I$517&$J$17:$J$517&$K$17:$K$517&$L$17:$L$517&$M$17:$M$517&$N$17:$N$517&$O$17:$O$517&$P$17:$P$517&$Q$17:$Q$517)>0)) | D9: Mandatory cells missing | E9: =SUMPRODUCT(((ROW($C$17:$C$517)>17)+($C$17<>"1210.07")>0)*(LEN($B$17:$B$517&$C$17:$C$517&$D$17:$D$517&$E$17:$E$517&$F$17:$F$517&$G$17:$G$517&$H$17:$H$517&$I$17:$I$517&$J$17:$J$517&$K$17:$K$517&$L$17:$L$517&$M$17:$M$517&$N$17:$N$517&$O$17:$O$517&$P$17:$P$517&$Q$17:$Q$517)>0)*(($D$17:$D$517="")+($F$17:$F$517="")+($G$17:$G$517="")))
A10: Confirmed by (BDOI owner) | D10: Date
A12: Mandatory | B12: No | C12: No | D12: Yes | E12: No | F12: Yes | G12: Yes | H12: No | I12: No | J12: No | K12: No | L12: No | M12: No | N12: No | O12: No | P12: No | Q12: No
A13: Format | B13: Text | C13: Text | D13: Text | E13: Text | F13: Text | G13: Text | H13: Text | I13: Y or N | J13: Text | K13: Text | L13: Y or N | M13: Y or N | N13: Y or N | O13: Text | P13: yyyy-MM-dd | Q13: Text
A14: Allowed values | B14: A code of D0-06 Chart of accounts, column Account Code | C14: Free entry | D14: Free entry | E14: Free entry | F14: ASSET, LIABILITY, EQUITY, INCOME, EXPENSE, MEMORANDUM (list Account class of the chart) | G14: GROUP, MAIN, SUB, MICRO (list Account level) | H14: A code of D0-07 Account categories and numbering, column Category code | I14: Y or N | J14: Free entry | K14: Free entry | L14: Y or N | M14: Y or N | N14: Y or N | O14: Free entry | P14: Free entry | Q14: ALLOW, WARN, BLOCK (list Negative balance)
A15: What to enter | B15: Code of the parent account; blank for a top-level group | C15: Account code; blank for the next number of the parent's scheme | D15: Account name | E15: Unique short code used on journal lines | F15: Class of the account | G15: Level of the account, one tier below the parent | H15: GL category | I15: Control account | J15: Sub-ledger the account controls; blank for none | K15: Currencies allowed on the account; blank for all | L15: Manual journals allowed; blank for Y | M15: Cost centre mandatory on journal lines | N15: Revalued at month end | O15: Financial statement line | P15: Opening date; blank for today | Q15: What a negative balance does; blank for ALLOW
A16: Row | B16: Parent Code | C16: Account Code | D16: Account Name * | E16: Short Code | F16: Class * | G16: Level * | H16: Category | I16: Control Account | J16: Sub-ledger Type | K16: Currencies | L16: Manual Posting | M16: Cost Centre Required | N16: Revaluation Required | O16: Report Group | P16: Opened On | Q16: Negative Balance
A17: Example – overwrite or delete | C17: 1210.07 | D17: Premium Receivable - Motor | E17: PRMOTOR | F17: ASSET | G17: SUB | I17: N | J17: POLICYHOLDER | K17: PHP | L17: Y | M17: N | N17: N | O17: Premium Receivable | P17: 2026-01-01 | Q17: WARN

Sheet MD-01 Business partners
A1: MD-01 Business partners (reinsurers, intermediaries, suppliers) | O1: Step 12 of 52
A2: ← Back to Start here | B2: Step 12 of 52. Fill in one row per record below the column headers; the guide above each column says what to enter. | O2: Ask a question →
A3: Purpose | B3: One row per business partner other than an insurer or a client: agents and brokers (intermediaries), reinsurers and reinsurance brokers, co-insurers, suppliers, garages, surveyors and banks. Insurers come from R04; clients from C01 and the client upload.
A4: Provided by | B4: Head, Comptrollership; Head, Operations for the reinsurers and intermediaries
A5: Due | B5: 9-Apr-2027 – Reference data for Trial migration 1 (M4)
A6: How it is loaded | B6: Upload on the configuration screen Setup & Administration › Setup › Business Partners, approved by a second user
A7: Source | B7: Upload template of the configuration screen (the same columns, headers, mandatory flags and allowed values)
A8: Depends on | B8: D0-02 Branches →
A9: Progress | B9: Rows entered | C9: =SUMPRODUCT(((ROW($B$17:$B$317)>17)+($B$17<>"RI-0001")>0)*(LEN($B$17:$B$317&$C$17:$C$317&$D$17:$D$317&$E$17:$E$317&$F$17:$F$317&$G$17:$G$317&$H$17:$H$317&$I$17:$I$317&$J$17:$J$317&$K$17:$K$317&$L$17:$L$317&$M$17:$M$317&$N$17:$N$317&$O$17:$O$317)>0)) | D9: Mandatory cells missing | E9: =SUMPRODUCT(((ROW($B$17:$B$317)>17)+($B$17<>"RI-0001")>0)*(LEN($B$17:$B$317&$C$17:$C$317&$D$17:$D$317&$E$17:$E$317&$F$17:$F$317&$G$17:$G$317&$H$17:$H$317&$I$17:$I$317&$J$17:$J$317&$K$17:$K$317&$L$17:$L$317&$M$17:$M$317&$N$17:$N$317&$O$17:$O$317)>0)*(($B$17:$B$317="")+($C$17:$C$317="")+($D$17:$D$317="")+($I$17:$I$317="")))
A10: Confirmed by (BDOI owner) | D10: Date
A12: Mandatory | B12: Yes | C12: Yes | D12: Yes | E12: No | F12: No | G12: No | H12: No | I12: Yes | J12: No | K12: No | L12: Conditional: agent, broker, reinsurance broker | M12: No | N12: No | O12: No
A13: Format | B13: Up to 30; capitals, digits, - and . | C13: Code from the drop-down | D13: Text | E13: 000-000-000-000 | F13: Text | G13: Text | H13: Text | I13: Text | J13: Text | K13: Text | L13: Text | M13: Number without thousands separators, e.g. 1500000.50 | N13: Number without thousands separators, e.g. 1500000.50 | O13: Number without thousands separators, e.g. 1500000.50
A14: Allowed values | B14: Free entry | C14: List Party type (MD-01): 12 values, see Reference lists | D14: Free entry | E14: Free entry | F14: Free entry | G14: Free entry | H14: Free entry | I14: Free entry | J14: Free entry | K14: Free entry | L14: Free entry | M14: A number | N14: A number | O14: A number
A15: What to enter | B15: Code of the partner, unique | C15: Kind of partner | D15: Registered name | E15: Tax identification number | F15: Registered address | G15: E-mail for advices and statements | H15: Phone number | I15: Currency of the partner's transactions | J15: Bank of the partner's account | K15: Account number for payments | L15: Insurance Commission licence number | M15: Credit days of the partner's items | N15: Commission rate of an intermediary | O15: Withholding tax rate applied to the partner
A16: Row | B16: Party code * | C16: Party type * | D16: Name * | E16: TIN / tax id | F16: Address | G16: E-mail | H16: Phone | I16: Default currency * | J16: Bank name | K16: Bank account no. | L16: Licence no. | M16: Credit days | N16: Commission rate % | O16: Withholding tax rate %
A17: Example – overwrite or delete | B17: RI-0001 | C17: REINSURER | D17: Asia Pacific Reinsurance Corp. | E17: 123-456-789-000 | F17: Makati City | G17: treaty@apre.example.ph | H17: +63 2 8888 0000 | I17: PHP | J17: Metropolitan Commercial Bank | K17: 001234567890 | L17: IC-RB-2026-015 | M17: 30 | O17: 2

Sheet R03 Sales organisation (units a
A1: R03 Sales organisation (units and account officers) | L1: Step 13 of 52
A2: ← Back to Start here | B2: Step 13 of 52. Fill in one row per record below the column headers; the guide above each column says what to enter. | L2: Ask a question →
A3: Purpose | B3: One row per record of Sales organisation (regions, departments, teams, unit heads, account officers) as extracted from QPS, EBIX. Key record_type, unit_code, ao_user_id. Sent as the file R03_template.csv (CSV, header row as below) with its control file (row count, row count).
A4: Provided by | B4: Marketing data steward (to name); approved by Heads, Retail and Corporate Marketing; extracted by BDOI IT
A5: Due | B5: M3 (29 Jan 2027)
A6: How it is loaded | B6: Migration Console: the file R03_template.csv (the header row as below) and its control file are received on Data Migration › Data Migration › Extracts and loaded by a batch of object R03; lands in: Sales organisation: sales units and account officers
A7: Source | B7: QPS, EBIX
A8: Depends on | B8: D0-02 Branches → | D8: D0-04 Cost centres and business lines →
A9: Progress | B9: Rows entered | C9: =SUMPRODUCT(((ROW($B$18:$B$218)>18)+($B$18<>"TEAM")>0)*(LEN($B$18:$B$218&$C$18:$C$218&$D$18:$D$218&$E$18:$E$218&$F$18:$F$218&$G$18:$G$218&$H$18:$H$218&$I$18:$I$218&$J$18:$J$218&$K$18:$K$218&$L$18:$L$218)>0)) | D9: Mandatory cells missing | E9: =SUMPRODUCT(((ROW($B$18:$B$218)>18)+($B$18<>"TEAM")>0)*(LEN($B$18:$B$218&$C$18:$C$218&$D$18:$D$218&$E$18:$E$218&$F$18:$F$218&$G$18:$G$218&$H$18:$H$218&$I$18:$I$218&$J$18:$J$218&$K$18:$K$218&$L$18:$L$218)>0)*(($B$18:$B$218="")+($C$18:$C$218="")+($L$18:$L$218="")))
A10: Confirmed by (BDOI owner) | D10: Date
A12: Check when loaded | B12: In the list | C12: Exists as a TEAM row for AO rows | D12: Mandatory for REGION, DEPARTMENT, TEAM | E12: Mandatory for DEPARTMENT and TEAM; parent exists | F12: Mapped in USER | G12: Mapped | H12: Mandatory for AO rows; mapped in USER | I12: Unique | J12: Mandatory for AO rows | K12: Mapped | L12: Y or N
A13: Mandatory | B13: Yes | C13: Yes | D13: Conditional: Mandatory for REGION, DEPARTMENT, TEAM | E13: Conditional: Mandatory for DEPARTMENT and TEAM; parent exists | F13: No | G13: No | H13: Conditional: Mandatory for AO rows; mapped in USER | I13: No | J13: Conditional: Mandatory for AO rows | K13: No | L13: Yes
A14: Format | B14: Code, up to 12; Upper case | C14: Code, up to 20; As stored in legacy | D14: Text, up to 120; Free text | E14: Code, up to 20; As stored in legacy | F14: Code, up to 50; As stored in legacy | G14: Code, up to 20; As stored in legacy | H14: Code, up to 50; As stored in legacy | I14: Code, up to 20; As stored in legacy | J14: Text, up to 120; Free text | K14: Code, up to 20; As stored in legacy | L14: Flag, up to 1; Y or N
A15: Allowed values | B15: REGION, DEPARTMENT, TEAM, AO (list R03 record_type) | C15: Free entry, up to 20 characters | D15: Free entry, up to 120 characters | E15: unit_code values of the file | F15: The legacy code; mapped by the code map USER (Code Maps screen of the Data Migration Console; maps prepared in the Migration Workbook of BRD-13) | G15: The legacy code; mapped by the code map COST_CENTER (Code Maps screen of the Data Migration Console; maps prepared in the Migration Workbook of BRD-13) | H15: The legacy code; mapped by the code map USER (Code Maps screen of the Data Migration Console; maps prepared in the Migration Workbook of BRD-13) | I15: The legacy code; mapped by the code map AO (Code Maps screen of the Data Migration Console; maps prepared in the Migration Workbook of BRD-13) | J15: Free entry, up to 120 characters | K15: The legacy code; mapped by the code map BRANCH (Code Maps screen of the Data Migration Console; maps prepared in the Migration Workbook of BRD-13) | L15: Y or N
A16: What to enter | B16: Kind of row | C16: Legacy code of the unit (for an AO row, the team of the AO) | D16: Unit name | E16: Code of the parent unit (department of a team, region of a department) | F16: Legacy user ID of the unit head | G16: Cost centre of the unit | H16: Legacy user ID of the account officer | I16: Legacy AO code if different from the user ID | J16: AO full name | K16: Branch of the unit or AO | L16: Unit or AO active
A17: Row | B17: record_type * | C17: unit_code * | D17: unit_name | E17: parent_unit_code | F17: unit_head_user_id | G17: cost_center | H17: ao_user_id | I17: ao_code | J17: ao_name | K17: branch_code | L17: active_flag *
A18: Example – overwrite or delete | B18: TEAM | C18: T-RET-07 | D18: Retail Team 7 | E18: D-RET | F18: jdelacruz | G18: 4100 | H18: mreyes | I18: AO0457 | J18: Maria Reyes | K18: MKT01 | L18: Y

Sheet R05 Product lines, cover types,
A1: R05 Product lines, cover types, products and risk codes | J1: Step 14 of 52
A2: ← Back to Start here | B2: Step 14 of 52. Fill in one row per record below the column headers; the guide above each column says what to enter. | J2: Ask a question →
A3: Purpose | B3: One row per record of Product lines, cover types, products and risk codes as extracted from QPS, EBIX. Key risk_code. Sent as the file R05_template.csv (CSV, header row as below) with its control file (row count, count of distinct keys).
A4: Provided by | B4: MBS data steward (to name); approved by Product Owner, MBS; extracted by BDOI IT
A5: Due | B5: M3 (29 Jan 2027)
A6: How it is loaded | B6: Migration Console: the file R05_template.csv (the header row as below) and its control file are received on Data Migration › Data Migration › Extracts and loaded by a batch of object R05; lands in: Product catalogue: product lines, cover types and products
A7: Source | B7: QPS, EBIX
A8: Depends on | B8: PM-09 Lists of values and parameters →
A9: Progress | B9: Rows entered | C9: =SUMPRODUCT(((ROW($B$18:$B$218)>18)+($B$18<>"MOTOR")>0)*(LEN($B$18:$B$218&$C$18:$C$218&$D$18:$D$218&$E$18:$E$218&$F$18:$F$218&$G$18:$G$218&$H$18:$H$218&$I$18:$I$218&$J$18:$J$218)>0)) | D9: Mandatory cells missing | E9: =SUMPRODUCT(((ROW($B$18:$B$218)>18)+($B$18<>"MOTOR")>0)*(LEN($B$18:$B$218&$C$18:$C$218&$D$18:$D$218&$E$18:$E$218&$F$18:$F$218&$G$18:$G$218&$H$18:$H$218&$I$18:$I$218&$J$18:$J$218)>0)*(($B$18:$B$218="")+($E$18:$E$218="")+($F$18:$F$218="")+($I$18:$I$218="")))
A10: Confirmed by (BDOI owner) | D10: Date
A12: Check when loaded | B12: Mapped | C12: - | D12: Mapped | E12: Unique | F12: Not blank | G12: Y or N | H12: Each mapped | I12: Mapped | J12: 0 or more
A13: Mandatory | B13: Yes | C13: No | D13: No | E13: Yes | F13: Yes | G13: No | H13: No | I13: Yes | J13: No
A14: Format | B14: Code, up to 30; As stored in legacy | C14: Text, up to 120; Free text | D14: Code, up to 30; As stored in legacy | E14: Code, up to 20; As stored in legacy | F14: Text, up to 200; Free text | G14: Flag, up to 1; Y or N | H14: Text, up to 300; CODE;CODE | I14: Code, up to 20; As stored in legacy | J14: Integer, up to 9; Digits
A15: Allowed values | B15: The legacy code; mapped by the code map LINE (Code Maps screen of the Data Migration Console; maps prepared in the Migration Workbook of BRD-13) | C15: Free entry, up to 120 characters | D15: The legacy code; mapped by the code map COVER_TYPE (Code Maps screen of the Data Migration Console; maps prepared in the Migration Workbook of BRD-13) | E15: Free entry, up to 20 characters | F15: Free entry, up to 200 characters | G15: Y or N | H15: The legacy code; mapped by the code map LOV:MARKET_SEGMENT (Code Maps screen of the Data Migration Console; maps prepared in the Migration Workbook of BRD-13) | I15: The legacy code; mapped by the code map STATUS:PRODUCT (Code Maps screen of the Data Migration Console; maps prepared in the Migration Workbook of BRD-13) | J15: A whole number
A16: What to enter | B16: Legacy line of business | C16: Line name | D16: Legacy cover type | E16: Legacy risk code / product code | F16: Product / risk name | G16: Sold as a package | H16: Segments that may use the product, separated by semicolons | I16: Status in legacy | J16: Open invoices and in-force policies using the code (helps the mapping)
A17: Row | B17: line_code * | C17: line_name | D17: cover_type_code | E17: risk_code * | F17: risk_name * | G17: packaged_flag | H17: market_segments | I17: status * | J17: open_item_count
A18: Example – overwrite or delete | B18: MOTOR | C18: Motor Car | D18: COMP | E18: MC-PC-COMP | F18: Private Car Own Damage and Theft | G18: N | H18: CBG;RETAIL | I18: ACTIVE | J18: 4211

Sheet UA-01 Users and roles
A1: UA-01 Users and roles load | L1: Step 15 of 52
A2: ← Back to Start here | B2: Step 15 of 52. Fill in one row per record below the column headers; the guide above each column says what to enter. | L2: Ask a question →
A3: Purpose | B3: Every BIBS user at go-live with the user data and the group profiles, in the columns of the Bulk Request template
A4: Provided by | B4: Business Administration, with the unit heads who name their users
A5: Due | B5: 1-Nov-2027 – Production values before the dress rehearsal
A6: How it is loaded | B6: Bulk Request (SCR-UA-09): the file of this template is uploaded as a bulk batch, checked row by row and approved by an approver like single requests; users are out of the data migration scope (DMQ30)
A7: Source | B7: The users of the legacy systems and the unit rosters; the HR list of employees for the full names and e-mails
A8: Depends on | B8: UA-06 Lists of values → | D8: UA-02 Role-to-permission matrix →
A9: Progress | B9: Rows entered | C9: =SUMPRODUCT(((ROW($B$17:$B$517)>17)+($B$17<>"ENROL")>0)*(LEN($B$17:$B$517&$C$17:$C$517&$D$17:$D$517&$E$17:$E$517&$F$17:$F$517&$G$17:$G$517&$H$17:$H$517&$I$17:$I$517&$J$17:$J$517&$K$17:$K$517&$L$17:$L$517)>0)) | D9: Mandatory cells missing | E9: =SUMPRODUCT(((ROW($B$17:$B$517)>17)+($B$17<>"ENROL")>0)*(LEN($B$17:$B$517&$C$17:$C$517&$D$17:$D$517&$E$17:$E$517&$F$17:$F$517&$G$17:$G$517&$H$17:$H$517&$I$17:$I$517&$J$17:$J$517&$K$17:$K$517&$L$17:$L$517)>0)*(($B$17:$B$517="")+($C$17:$C$517="")+($L$17:$L$517="")))
A10: Confirmed by (BDOI owner) | D10: Date
A12: Mandatory | B12: Yes | C12: Yes | D12: Conditional: ENROL | E12: No | F12: No | G12: No | H12: No | I12: No | J12: Conditional: ENROL | K12: No | L12: Yes
A13: Format | B13: ENROL, MODIFY, DEACTIVATE or REACTIVATE | C13: A letter and nine digits (BDOI format a999999999) | D13: Up to 120 characters | E13: Company e-mail address | F13: Windows log-on name; unique | G13: Branch code | H13: Code of the list Business unit group (CI-06) | I13: Code of the list User level (CI-06) | J13: Profile codes of CI-02 separated by ';' | K13: yyyy-MM-dd; blank = on approval | L13: Up to 1,000 characters
A14: Allowed values | B14: ENROL, MODIFY, DEACTIVATE, REACTIVATE (list Bulk request action) | C14: Free entry, up to 10 characters | D14: Free entry, up to 120 characters | E14: Free entry | F14: Free entry | G14: Free entry | H14: Codes of UA-06 Lists of values, column Code (one or more) | I14: Codes of UA-06 Lists of values, column Code (one or more) | J14: Codes of UA-02 Role-to-permission matrix, column Group profile code (one or more) | K14: Free entry | L14: Free entry, up to 1000 characters
A15: What to enter | B15: ENROL for the go-live load | C15: The BIBS user ID; unique | D15: Name shown on screens and reports | E15: Receives the access-changed notices and the reset links | F15: Used for the BDO directory sign-in when it is enabled | G15: Home branch of the user | H15: Business unit group | I15: User level | J15: The group profiles of the user | K15: Date the change applies | L15: Justification of the line
A16: Row | B16: Action * | C16: User ID * | D16: Full Name | E16: E-mail | F16: Windows ID | G16: Home Branch Code | H16: Business Unit | I16: User Level | J16: Group Profiles | K16: Effective Date | L16: Remarks *
A17: Example – overwrite or delete | B17: ENROL | C17: a013000201 | D17: Andrea Mercado | E17: andrea.mercado@brokerverse-seed.ph | F17: AMERCADO | G17: HO | J17: MKT_AO | L17: Joined Marketing

Sheet D0-03 Holiday calendar
A1: D0-03 Holiday calendar | G1: Step 16 of 52
A2: ← Back to Start here | B2: Step 16 of 52. Fill in one row per record below the column headers; the guide above each column says what to enter. | G2: Ask a question →
A3: Purpose | B3: Public and company holidays of 2027 and 2028
A4: Provided by | B4: Head, Comptrollership; Human Resources
A5: Due | B5: 4-Jan-2027 – Platform set-up for Drop 1 SIT
A6: How it is loaded | B6: Upload on the configuration screen Setup & Administration › Setup › Holiday Calendar, approved by a second user
A7: Source | B7: Upload template of the configuration screen (the same columns, headers, mandatory flags and allowed values)
A8: Depends on | B8: D0-02 Branches →
A9: Progress | B9: Rows entered | C9: =SUMPRODUCT(((ROW($D$17:$D$517)>17)+($D$17<>"New Year's Day")>0)*(LEN($B$17:$B$517&$C$17:$C$517&$D$17:$D$517)>0)) | D9: Mandatory cells missing | E9: =SUMPRODUCT(((ROW($D$17:$D$517)>17)+($D$17<>"New Year's Day")>0)*(LEN($B$17:$B$517&$C$17:$C$517&$D$17:$D$517)>0)*(($C$17:$C$517="")+($D$17:$D$517="")))
A10: Confirmed by (BDOI owner) | D10: Date
A12: Mandatory | B12: No | C12: Yes | D12: Yes
A13: Format | B13: Text | C13: Date dd-MMM-yyyy, e.g. 15-Jan-2026 | D13: Text
A14: Allowed values | B14: Code of an existing branch | C14: A date, for example 15-Jan-2028 | D14: Free entry
A15: What to enter | B15: Branch the holiday applies to; blank = every branch | C15: Date of the holiday | D15: Name of the holiday
A16: Row | B16: Branch code | C16: Date * | D16: Description *
A17: Example – overwrite or delete | C17: 46753 | D17: New Year's Day

Sheet MD-03 Exchange rates
A1: MD-03 Exchange rates and their source | G1: Step 17 of 52
A2: ← Back to Start here | B2: Step 17 of 52. Fill in one row per record below the column headers; the guide above each column says what to enter. | G2: Ask a question →
A3: Purpose | B3: The opening exchange rates of each foreign currency per rate type at go-live. BIBS keeps four rate types: SPOT (daily rate of postings), CLOSING (month-end revaluation), AVERAGE (period average) and BUDGET. The source of the daily rates (for example the BDO Treasury board rate or the BSP reference rate) and who enters them are asked in the BDOI requirements workbook.
A4: Provided by | B4: Head, Comptrollership (Treasury)
A5: Due | B5: 16-Jul-2027 – Values for UAT
A6: How it is loaded | B6: Configuration screen: Setup & Administration › Setup › Currencies & Rates, one rate per currency, type and date
A7: Source | B7: BDO Treasury or BSP reference rates
A8: Depends on | B8: MD-02 Currencies →
A9: Progress | B9: Rows entered | C9: =SUMPRODUCT(((ROW($B$17:$B$317)>17)+($B$17<>"USD")>0)*(LEN($B$17:$B$317&$C$17:$C$317&$D$17:$D$317&$E$17:$E$317)>0)) | D9: Mandatory cells missing | E9: =SUMPRODUCT(((ROW($B$17:$B$317)>17)+($B$17<>"USD")>0)*(LEN($B$17:$B$317&$C$17:$C$317&$D$17:$D$317&$E$17:$E$317)>0)*(($B$17:$B$317="")+($C$17:$C$317="")+($D$17:$D$317="")+($E$17:$E$317="")))
A10: Confirmed by (BDOI owner) | D10: Date
A12: Mandatory | B12: Yes | C12: Yes | D12: Yes | E12: Yes
A13: Format | B13: Code of MD-02 | C13: Code of the list | D13: dd-mmm-yyyy | E13: Number, PHP per unit of the currency
A14: Allowed values | B14: A code of MD-02 Currencies, column Currency code | C14: SPOT, CLOSING, AVERAGE, BUDGET (list Exchange rate type) | D14: A date, for example 15-Jan-2028 | E14: A number from 0 to 1000000
A15: What to enter | B15: Currency of the rate (not PHP) | C15: Kind of rate | D15: Date from which the rate applies | E15: Pesos for one unit of the currency
A16: Row | B16: Currency code * | C16: Rate type * | D16: Effective date * | E16: Rate *
A17: Example – overwrite or delete | B17: USD | C17: SPOT | D17: 46755

Sheet R02 Branches and invoicing bran
A1: R02 Branches and invoicing branches | G1: Step 18 of 52
A2: ← Back to Start here | B2: Step 18 of 52. Fill in one row per record below the column headers; the guide above each column says what to enter. | G2: Ask a question →
A3: Purpose | B3: One row per record of Branches and invoicing branches as extracted from EBIX. Key branch_code. Sent as the file R02_template.csv (CSV, header row as below) with its control file (row count, count of distinct keys).
A4: Provided by | B4: Comptrollership data steward (to name); approved by Head, Comptrollership; extracted by BDOI IT
A5: Due | B5: M3 (29 Jan 2027)
A6: How it is loaded | B6: Migration Console: the file R02_template.csv (the header row as below) and its control file are received on Data Migration › Data Migration › Extracts and loaded by a batch of object R02; lands in: Branches (check only, code map BRANCH)
A7: Source | B7: EBIX
A8: Depends on | B8: D0-02 Branches →
A9: Progress | B9: Rows entered | C9: =SUMPRODUCT(((ROW($B$18:$B$218)>18)+($B$18<>"MKT01")>0)*(LEN($B$18:$B$218&$C$18:$C$218&$D$18:$D$218&$E$18:$E$218&$F$18:$F$218)>0)) | D9: Mandatory cells missing | E9: =SUMPRODUCT(((ROW($B$18:$B$218)>18)+($B$18<>"MKT01")>0)*(LEN($B$18:$B$218&$C$18:$C$218&$D$18:$D$218&$E$18:$E$218&$F$18:$F$218)>0)*(($B$18:$B$218="")+($C$18:$C$218="")+($D$18:$D$218="")+($F$18:$F$218="")))
A10: Confirmed by (BDOI owner) | D10: Date
A12: Check when loaded | B12: Unique | C12: Not blank | D12: Y or N | E12: - | F12: Y or N
A13: Mandatory | B13: Yes | C13: Yes | D13: Yes | E13: No | F13: Yes
A14: Format | B14: Code, up to 20; As stored in legacy | C14: Text, up to 120; Free text | D14: Flag, up to 1; Y or N | E14: Text, up to 80; Free text | F14: Flag, up to 1; Y or N
A15: Allowed values | B15: Free entry, up to 20 characters | C15: Free entry, up to 120 characters | D15: Y or N | E15: Free entry, up to 80 characters | F15: Y or N
A16: What to enter | B16: Legacy branch code | C16: Branch name | D16: Branch issues invoices and receipts | E16: City of the branch | F16: Branch active in legacy
A17: Row | B17: branch_code * | C17: branch_name * | D17: invoicing_branch_flag * | E17: city | F17: active_flag *
A18: Example – overwrite or delete | B18: MKT01 | C18: Makati Head Office | D18: Y | E18: Makati City | F18: Y

Sheet R04B Insurer branches
A1: R04B Insurer branches | H1: Step 19 of 52
A2: ← Back to Start here | B2: Step 19 of 52. Fill in one row per record below the column headers; the guide above each column says what to enter. | H2: Ask a question →
A3: Purpose | B3: One row per record of Insurers and insurer branches as extracted from QPS, EBIX. Key insurer_code, branch_code. Sent as the file R04B_template.csv (CSV, header row as below) with its control file (row count, count of distinct keys).
A4: Provided by | B4: Operations data steward (to name); approved by Head, Operations; extracted by BDOI IT
A5: Due | B5: M3 (29 Jan 2027)
A6: How it is loaded | B6: Migration Console: the file R04B_template.csv (the header row as below) and its control file are received on Data Migration › Data Migration › Extracts and loaded by a batch of object R04; lands in: Insurers and insurer branches (insurer and party records)
A7: Source | B7: QPS, EBIX
A8: Depends on | B8: R04 Insurers →
A9: Progress | B9: Rows entered | C9: =SUMPRODUCT(((ROW($B$18:$B$218)>18)+($B$18<>"MAL")>0)*(LEN($B$18:$B$218&$C$18:$C$218&$D$18:$D$218&$E$18:$E$218&$F$18:$F$218&$G$18:$G$218&$H$18:$H$218)>0)) | D9: Mandatory cells missing | E9: =SUMPRODUCT(((ROW($B$18:$B$218)>18)+($B$18<>"MAL")>0)*(LEN($B$18:$B$218&$C$18:$C$218&$D$18:$D$218&$E$18:$E$218&$F$18:$F$218&$G$18:$G$218&$H$18:$H$218)>0)*(($B$18:$B$218="")+($C$18:$C$218="")+($D$18:$D$218="")+($H$18:$H$218="")))
A10: Confirmed by (BDOI owner) | D10: Date
A12: Check when loaded | B12: Exists in R04 | C12: Unique per insurer | D12: Not blank | E12: - | F12: 0 to 5 | G12: Valid e-mail | H12: Mapped
A13: Mandatory | B13: Yes | C13: Yes | D13: Yes | E13: No | F13: No | G13: No | H13: Yes
A14: Format | B14: Code, up to 30; As stored in legacy | C14: Code, up to 20; As stored in legacy | D14: Text, up to 120; Free text | E14: Text, up to 80; Free text | F14: Decimal, up to 9,4; Dot decimal | G14: Text, up to 120; name@domain | H14: Code, up to 20; As stored in legacy
A15: Allowed values | B15: The legacy code; mapped by the code map INSURER (Code Maps screen of the Data Migration Console; maps prepared in the Migration Workbook of BRD-13) | C15: Free entry, up to 20 characters | D15: Free entry, up to 120 characters | E15: Free entry, up to 80 characters | F15: A number | G15: Free entry, up to 120 characters | H15: The legacy code; mapped by the code map STATUS:INSURER (Code Maps screen of the Data Migration Console; maps prepared in the Migration Workbook of BRD-13)
A16: What to enter | B16: Legacy insurer code | C16: Legacy insurer branch code | D16: Branch name | E16: City | F16: Local government tax rate of the branch location, in percent | G16: Branch placement e-mail | H16: Branch status
A17: Row | B17: insurer_code * | C17: branch_code * | D17: branch_name * | E17: city | F17: lgt_rate | G17: placement_email | H17: status *
A18: Example – overwrite or delete | B18: MAL | C18: MAL-CEB | D18: Malayan Cebu | E18: Cebu City | F18: 0.75 | G18: cebu@insurer.example | H18: ACTIVE

Sheet R11 Receipt series in use
A1: R11 Receipt series in use | I1: Step 20 of 52
A2: ← Back to Start here | B2: Step 20 of 52. Fill in one row per record below the column headers; the guide above each column says what to enter. | I2: Ask a question →
A3: Purpose | B3: One row per record of Receipt series in use (AR and OR, ATP and next number) as extracted from EBIX. Key branch_code, kind, prefix. Sent as the file R11_template.csv (CSV, header row as below) with its control file (row count, row count).
A4: Provided by | B4: Cashiering data steward (to name); approved by Operations - Financial Transactions; extracted by BDOI IT
A5: Due | B5: M3 (29 Jan 2027); final at T-3
A6: How it is loaded | B6: Migration Console: the file R11_template.csv (the header row as below) and its control file are received on Data Migration › Data Migration › Extracts and loaded by a batch of object R11; lands in: Receipt series of Cashiering
A7: Source | B7: EBIX
A8: Depends on | B8: D0-02 Branches →
A9: Progress | B9: Rows entered | C9: =SUMPRODUCT(((ROW($B$18:$B$218)>18)+($B$18<>"MKT01")>0)*(LEN($B$18:$B$218&$C$18:$C$218&$D$18:$D$218&$E$18:$E$218&$F$18:$F$218&$G$18:$G$218&$H$18:$H$218&$I$18:$I$218)>0)) | D9: Mandatory cells missing | E9: =SUMPRODUCT(((ROW($B$18:$B$218)>18)+($B$18<>"MKT01")>0)*(LEN($B$18:$B$218&$C$18:$C$218&$D$18:$D$218&$E$18:$E$218&$F$18:$F$218&$G$18:$G$218&$H$18:$H$218&$I$18:$I$218)>0)*(($B$18:$B$218="")+($C$18:$C$218="")+($D$18:$D$218="")+($F$18:$F$218="")+($G$18:$G$218="")+($H$18:$H$218="")+($I$18:$I$218="")))
A10: Confirmed by (BDOI owner) | D10: Date
A12: Check when loaded | B12: Mapped | C12: In the list | D12: Not blank | E12: Unique per branch and kind | F12: Less than to_no | G12: More than from_no | H12: Between from_no and to_no | I12: =last_used_no + 1
A13: Mandatory | B13: Yes | C13: Yes | D13: Yes | E13: No | F13: Yes | G13: Yes | H13: Yes | I13: Yes
A14: Format | B14: Code, up to 20; As stored in legacy | C14: Code, up to 2; Upper case | D14: Text, up to 40; As printed | E14: Text, up to 20; As printed | F14: Integer, up to 12; Digits | G14: Integer, up to 12; Digits | H14: Integer, up to 12; Digits | I14: Integer, up to 12; Digits
A15: Allowed values | B15: The legacy code; mapped by the code map BRANCH (Code Maps screen of the Data Migration Console; maps prepared in the Migration Workbook of BRD-13) | C15: AR, OR (list R11 kind) | D15: Free entry, up to 40 characters | E15: Free entry, up to 20 characters | F15: A whole number | G15: A whole number | H15: A whole number | I15: A whole number
A16: What to enter | B16: Issuing branch | C16: Receipt kind | D16: BIR Authority to Print number | E16: Series prefix | F16: First number of the series | G16: Last number of the series | H16: Last number issued in legacy at the freeze | I16: Next number BIBS issues
A17: Row | B17: branch_code * | C17: kind * | D17: atp_no * | E17: prefix | F17: from_no * | G17: to_no * | H17: last_used_no * | I17: next_no *
A18: Example – overwrite or delete | B18: MKT01 | C18: AR | D18: ATP-OCN-2025-000123 | E18: AR-MKT | F18: 100001 | G18: 150000 | H18: 131245 | I18: 131246

Sheet UA-04 SoD rules
A1: UA-04 Separation-of-duties rules | H1: Step 21 of 52
A2: ← Back to Start here | B2: Step 21 of 52. Fill in one row per record below the column headers; the guide above each column says what to enter. | H2: Ask a question →
A3: Purpose | B3: The rules BIBS enforces, for confirmation, and the combinations of profiles or permissions that BDOI Information Security does not allow one user to hold
A4: Provided by | B4: BDOI Information Security
A5: Due | B5: 16-Jul-2027 – Values for UAT
A6: How it is loaded | B6: Upload on the configuration screen Setup & Administration › User Access › Separation of Duties, approved by a second user
A7: Source | B7: Upload template of the configuration screen (the same columns, headers, mandatory flags and allowed values)
A8: Depends on | B8: UA-02 Role-to-permission matrix →
A9: Refused rows | B9: Only rules with the control Prevent between two group profiles are loaded; rules with the control Detect by review or Second approval are refused by the upload and are followed with the access reports. Keep them in this sheet for the review
A10: Progress | B10: Rows entered | C10: =SUMPRODUCT(((ROW($B$18:$B$518)>18)+($B$18<>"SOD-01")>0)*(LEN($B$18:$B$518&$C$18:$C$518&$D$18:$D$518&$E$18:$E$518&$F$18:$F$518&$G$18:$G$518&$H$18:$H$518)>0)) | D10: Mandatory cells missing | E10: =SUMPRODUCT(((ROW($B$18:$B$518)>18)+($B$18<>"SOD-01")>0)*(LEN($B$18:$B$518&$C$18:$C$518&$D$18:$D$518&$E$18:$E$518&$F$18:$F$518&$G$18:$G$518&$H$18:$H$518)>0)*(($B$18:$B$518="")+($C$18:$C$518="")+($D$18:$D$518="")+($G$18:$G$518="")))
A11: Confirmed by (BDOI owner) | D11: Date
A13: Mandatory | B13: Yes | C13: Yes | D13: Yes | E13: Conditional: combination rule | F13: Conditional: combination rule | G13: Yes | H13: No
A14: Format | B14: SOD-nn | C14: Text | D14: Code from the drop-down | E14: Group profile codes separated by commas | F14: Group profile codes separated by commas | G14: Code from the drop-down | H14: Code from the drop-down
A15: Allowed values | B15: Free entry | C15: Free entry | D15: Enforced, To confirm, New (list Status (UA-04)) | E15: Codes of UA-02 Role-to-permission matrix, column Group profile code (one or more) | F15: Codes of UA-02 Role-to-permission matrix, column Group profile code (one or more) | G15: Prevent, Detect by review, Second approval (list Control (UA-04)) | H15: Monthly, Quarterly (list Review frequency (UA-04))
A16: What to enter | B16: Identifier of the rule | C16: The rule | D16: Enforced = a fixed rule of BIBS | E16: First profile of the combination | F16: Profile that may not be held with A | G16: How the rule is controlled | H16: How often the reports are reviewed
A17: Row | B17: Rule ID * | C17: Rule * | D17: Status * | E17: Profile or permission A | F17: Profile or permission B | G17: Control * | H17: Review frequency
A18: Example – overwrite or delete | B18: SOD-01 | C18: The requester never decides his own request | D18: Enforced | E18: UAM_REQUESTOR | F18: UAM_APPROVER | G18: Prevent | H18: Quarterly

Sheet UP-01 Clients (upload)
A1: UP-01 Clients not held in the legacy systems | W1: Step 22 of 52
A2: ← Back to Start here | B2: Step 22 of 52. Fill in one row per record below the column headers; the guide above each column says what to enter. | W2: Ask a question →
A3: Purpose | B3: One row per individual or corporate client that is not in the legacy client master (for example a bank-referred prospect), with the KYC values BIBS keeps on the client: ID type and number, nationality, source of funds and risk rating. The legacy clients come through the Migration Console (C01 to C03); this upload also updates a client found by code, TIN, ID or name and birth date.
A4: Provided by | B4: Heads, Retail and Corporate Marketing; Product Owner, MBS
A5: Due | B5: 16-Jul-2027 – Values for UAT
A6: How it is loaded | B6: Screen upload: Client & Policy › Clients › Clients, button Bulk Upload (upload type Bulk client creation and update); every row is checked and the result is shown per row
A7: Source | B7: Platform upload definition (column layout as the screen loads it)
A8: Depends on | B8: R01 Lists of values and MIS values →
A9: Progress | B9: Rows entered | C9: =SUMPRODUCT(((ROW($C$17:$C$317)>17)+($C$17<>"INDIVIDUAL")>0)*(LEN($B$17:$B$317&$C$17:$C$317&$D$17:$D$317&$E$17:$E$317&$F$17:$F$317&$G$17:$G$317&$H$17:$H$317&$I$17:$I$317&$J$17:$J$317&$K$17:$K$317&$L$17:$L$317&$M$17:$M$317&$N$17:$N$317&$O$17:$O$317&$P$17:$P$317&$Q$17:$Q$317&$R$17:$R$317&$S$17:$S$317&$T$17:$T$317&$U$17:$U$317&$V$17:$V$317&$W$17:$W$317)>0)) | D9: Mandatory cells missing | E9: =SUMPRODUCT(((ROW($C$17:$C$317)>17)+($C$17<>"INDIVIDUAL")>0)*(LEN($B$17:$B$317&$C$17:$C$317&$D$17:$D$317&$E$17:$E$317&$F$17:$F$317&$G$17:$G$317&$H$17:$H$317&$I$17:$I$317&$J$17:$J$317&$K$17:$K$317&$L$17:$L$317&$M$17:$M$317&$N$17:$N$317&$O$17:$O$317&$P$17:$P$317&$Q$17:$Q$317&$R$17:$R$317&$S$17:$S$317&$T$17:$T$317&$U$17:$U$317&$V$17:$V$317&$W$17:$W$317)>0)*(($C$17:$C$317="")))
A10: Confirmed by (BDOI owner) | D10: Date
A12: Mandatory | B12: No | C12: Yes | D12: Conditional: Client Type is INDIVIDUAL | E12: Conditional: Client Type is INDIVIDUAL | F12: No | G12: Conditional: Client Type is CORPORATE | H12: No | I12: No | J12: No | K12: Conditional: ID Type is given | L12: No | M12: No | N12: No | O12: No | P12: No | Q12: No | R12: No | S12: No | T12: Conditional: Bank Client is Y | U12: No | V12: No | W12: No
A13: Format | B13: Text | C13: Text | D13: Text | E13: Text | F13: Text | G13: Text | H13: Date (dd-mmm-yyyy or yyyy-mm-dd) | I13: 000-000-000-000 | J13: Text | K13: Text | L13: Text | M13: 09xxxxxxxxx or +639xxxxxxxxx | N13: Text | O13: Text | P13: Text | Q13: Text | R13: Text | S13: Y or N | T13: Text | U13: Text | V13: Text | W13: Text
A14: Allowed values | B14: Free entry | C14: INDIVIDUAL, CORPORATE (list Client Type (UP-01)) | D14: Free entry | E14: Free entry | F14: Free entry | G14: Free entry | H14: A date, for example 15-Jan-2028 | I14: Free entry | J14: List Identification document: 10 values, see Reference lists | K14: Free entry | L14: Free entry | M14: Free entry | N14: Free entry | O14: Free entry | P14: Free entry | Q14: Free entry | R14: CBG, COMBANK, CORBANK, RETAIL, INSTITUTIONAL (list Market segment) | S14: Y or N | T14: Free entry | U14: FILIPINO, AMERICAN, CHINESE, JAPANESE, KOREAN, OTHERS (list Nationality) | V14: SALARY, BUSINESS, REMITTANCE, INVESTMENT, PENSION, OTHERS (list Source of funds) | W14: LOW, STANDARD, HIGH (list KYC risk rating)
A15: What to enter | B15: Prospect or client code to update; blank to create or match (a client or prospect known to BIBS) | C15: Individual or corporate client | D15: Last name of an individual | E15: First name of an individual | F15: Middle name | G15: Registered name of a corporate client | H15: Birth date of an individual | I15: Tax identification number | J15: Type of the identity document | K15: Number of the identity document | L15: E-mail address | M15: Mobile number | N15: Street address | O15: City / municipality | P15: Province | Q15: Postal code | R15: Market segment | S15: Client of the group's bank | T15: Customer information file number at the group's bank | U15: Nationality | V15: Source of funds | W15: Know-your-client risk rating
A16: Row | B16: Client Code | C16: Client Type * | D16: Last Name | E16: First Name | F16: Middle Name | G16: Corporate Name | H16: Birth Date | I16: TIN | J16: ID Type | K16: ID Number | L16: E-mail | M16: Mobile | N16: Address | O16: City | P16: Province | Q16: Postal Code | R16: Market Segment | S16: Bank Client | T16: Bank CIF | U16: Nationality | V16: Source of Funds | W16: Risk Rating
A17: Example – overwrite or delete | C17: INDIVIDUAL | D17: Reyes | E17: Ana | F17: Cruz | H17: 32978 | I17: 123-456-789-000 | J17: PASSPORT | K17: P1234567A | L17: ana.reyes@example.ph | M17: 09171234567 | N17: 12 Rizal St. | O17: Pasig | P17: Metro Manila | Q17: 1600 | R17: CBG | S17: Y | U17: FILIPINO | V17: SALARY | W17: STANDARD

Sheet C01 Client master
A1: C01 Client master | AK1: Step 23 of 52
A2: ← Back to Start here | B2: Step 23 of 52. Fill in one row per record below the column headers; the guide above each column says what to enter. | AK2: Ask a question →
A3: Purpose | B3: One row per record of Client master (individual and corporate) as extracted from QPS, EBIX, CMS. Key legacy_client_no. Sent as the file C01_template.csv (CSV, header row as below) with its control file (row count, count of distinct keys).
A4: Provided by | B4: Marketing data steward (to name); approved by Product Owner, MBS; Heads, Retail and Corporate Marketing; extracted by BDOI IT
A5: Due | B5: M3 (29 Jan 2027); deltas daily from T-14 days
A6: How it is loaded | B6: Migration Console: the file C01_template.csv (the header row as below) and its control file are received on Data Migration › Data Migration › Extracts and loaded by a batch of object C01; lands in: Client master, registered as migrated clients
A7: Source | B7: QPS, EBIX, CMS
A8: Depends on | B8: R01 Lists of values and MIS values → | D8: R03 Sales organisation (units and account officers) → | F8: D0-02 Branches →
A9: Tax profile | B9: The client's VAT treatment and default withholding code are kept in the party tax profile (template TX-01), not in the client master
A10: Progress | B10: Rows entered | C10: =SUMPRODUCT(((ROW($B$19:$B$219)>19)+($B$19<>"Q-0012345")>0)*(LEN($B$19:$B$219&$C$19:$C$219&$D$19:$D$219&$E$19:$E$219&$F$19:$F$219&$G$19:$G$219&$H$19:$H$219&$I$19:$I$219&$J$19:$J$219&$K$19:$K$219&$L$19:$L$219&$M$19:$M$219&$N$19:$N$219&$O$19:$O$219&$P$19:$P$219&$Q$19:$Q$219&$R$19:$R$219&$S$19:$S$219&$T$19:$T$219&$U$19:$U$219&$V$19:$V$219&$W$19:$W$219&$X$19:$X$219&$Y$19:$Y$219&$Z$19:$Z$219&$AA$19:$AA$219&$AB$19:$AB$219&$AC$19:$AC$219&$AD$19:$AD$219&$AE$19:$AE$219&$AF$19:$AF$219&$AG$19:$AG$219&$AH$19:$AH$219&$AI$19:$AI$219&$AJ$19:$AJ$219&$AK$19:$AK$219)>0)) | D10: Mandatory cells missing | E10: =SUMPRODUCT(((ROW($B$19:$B$219)>19)+($B$19<>"Q-0012345")>0)*(LEN($B$19:$B$219&$C$19:$C$219&$D$19:$D$219&$E$19:$E$219&$F$19:$F$219&$G$19:$G$219&$H$19:$H$219&$I$19:$I$219&$J$19:$J$219&$K$19:$K$219&$L$19:$L$219&$M$19:$M$219&$N$19:$N$219&$O$19:$O$219&$P$19:$P$219&$Q$19:$Q$219&$R$19:$R$219&$S$19:$S$219&$T$19:$T$219&$U$19:$U$219&$V$19:$V$219&$W$19:$W$219&$X$19:$X$219&$Y$19:$Y$219&$Z$19:$Z$219&$AA$19:$AA$219&$AB$19:$AB$219&$AC$19:$AC$219&$AD$19:$AD$219&$AE$19:$AE$219&$AF$19:$AF$219&$AG$19:$AG$219&$AH$19:$AH$219&$AI$19:$AI$219&$AJ$19:$AJ$219&$AK$19:$AK$219)>0)*(($B$19:$B$219="")+($C$19:$C$219="")+($R$19:$R$219="")+($AI$19:$AI$219="")+($AJ$19:$AJ$219="")+($AK$19:$AK$219="")))
A11: Confirmed by (BDOI owner) | D11: Date
A13: Check when loaded | B13: Unique in the file | C13: In the list | D13: Mandatory for I | E13: Mandatory for I | F13: - | G13: - | H13: Mandatory for C | I13: - | J13: Mandatory for I; not in the future; age 0 to 120 | K13: 9 to 12 digits; duplicate key K1 | L13: Mapped | M13: Mandatory when id_type is given; duplicate key K2 | N13: Y or N | O13: Duplicate key K5 if agreed | P13: Mapped | Q13: Mapped | R13: Mapped | S13: Mapped | T13: Mapped | U13: Mapped in USER | V13: Mapped | W13: Mapped | X13: Valid e-mail; soft key K6 | Y13: PH mobile format; soft key K6 | Z13: - | AA13: - | AB13: - | AC13: - | AD13: 4 digits | AE13: Mapped | AF13: Not in the future | AG13: Valid date | AH13: Mapped | AI13: Mapped | AJ13: Valid date | AK13: Valid timestamp
A14: Mandatory | B14: Yes | C14: Yes | D14: Conditional: Mandatory for I | E14: Conditional: Mandatory for I | F14: No | G14: No | H14: Conditional: Mandatory for C | I14: No | J14: Conditional: Mandatory for I; not in the future; age 0 to 120 | K14: No | L14: No | M14: Conditional: Mandatory when id_type is given; duplicate key K2 | N14: No | O14: No | P14: No | Q14: No | R14: Yes | S14: No | T14: No | U14: No | V14: No | W14: No | X14: No | Y14: No | Z14: No | AA14: No | AB14: No | AC14: No | AD14: No | AE14: No | AF14: No | AG14: No | AH14: No | AI14: Yes | AJ14: Yes | AK14: Yes
A15: Format | B15: Code, up to 30; As stored in legacy | C15: Code, up to 1; Upper case | D15: Text, up to 100; Free text | E15: Text, up to 100; Free text | F15: Text, up to 100; Free text | G15: Text, up to 20; Free text | H15: Text, up to 200; Free text | I15: Text, up to 60; As registered | J15: Date, up to 10; yyyy-MM-dd | K15: Text, up to 20; 000-000-000-000 | L15: Code, up to 40; As stored in legacy | M15: Text, up to 60; As printed | N15: Flag, up to 1; Y or N | O15: Text, up to 40; Digits | P15: Code, up to 40; As stored in legacy | Q15: Code, up to 40; As stored in legacy | R15: Code, up to 40; As stored in legacy | S15: Code, up to 40; As stored in legacy | T15: Code, up to 40; As stored in legacy | U15: Code, up to 50; As stored in legacy | V15: Code, up to 20; As stored in legacy | W15: Code, up to 20; As stored in legacy | X15: Text, up to 120; name@domain | Y15: Text, up to 30; 09xxxxxxxxx or +639xxxxxxxxx | Z15: Text, up to 30; Free text | AA15: Text, up to 300; Free text | AB15: Text, up to 80; Free text | AC15: Text, up to 80; Free text | AD15: Text, up to 10; 4 digits | AE15: Code, up to 20; As stored in legacy | AF15: Date, up to 10; yyyy-MM-dd | AG15: Date, up to 10; yyyy-MM-dd | AH15: Code, up to 20; As stored in legacy | AI15: Code, up to 20; As stored in legacy | AJ15: Date, up to 10; yyyy-MM-dd | AK15: Timestamp, up to 19; yyyy-MM-dd HH:mm:ss
A16: Allowed values | B16: Free entry, up to 30 characters | C16: I, C (list C01 client_type) | D16: Free entry, up to 100 characters | E16: Free entry, up to 100 characters | F16: Free entry, up to 100 characters | G16: Free entry, up to 20 characters | H16: Free entry, up to 200 characters | I16: Free entry, up to 60 characters | J16: Free entry | K16: Free entry, up to 20 characters | L16: The legacy code; mapped by the code map LOV:ID_TYPE (Code Maps screen of the Data Migration Console; maps prepared in the Migration Workbook of BRD-13) | M16: Free entry, up to 60 characters | N16: Y or N | O16: Free entry, up to 40 characters | P16: The legacy code; mapped by the code map LOV:NATIONALITY (Code Maps screen of the Data Migration Console; maps prepared in the Migration Workbook of BRD-13) | Q16: The legacy code; mapped by the code map LOV:SOURCE_OF_FUNDS (Code Maps screen of the Data Migration Console; maps prepared in the Migration Workbook of BRD-13) | R16: The legacy code; mapped by the code map LOV:MARKET_SEGMENT (Code Maps screen of the Data Migration Console; maps prepared in the Migration Workbook of BRD-13) | S16: The legacy code; mapped by the code map MIS:CUSTOMER_SEGMENT (Code Maps screen of the Data Migration Console; maps prepared in the Migration Workbook of BRD-13) | T16: The legacy code; mapped by the code map MIS:BUSINESS_ORIGIN (Code Maps screen of the Data Migration Console; maps prepared in the Migration Workbook of BRD-13) | U16: The legacy code; mapped by the code map USER (Code Maps screen of the Data Migration Console; maps prepared in the Migration Workbook of BRD-13) | V16: The legacy code; mapped by the code map SALES_UNIT (Code Maps screen of the Data Migration Console; maps prepared in the Migration Workbook of BRD-13) | W16: The legacy code; mapped by the code map BRANCH (Code Maps screen of the Data Migration Console; maps prepared in the Migration Workbook of BRD-13) | X16: Free entry, up to 120 characters | Y16: Free entry, up to 30 characters | Z16: Free entry, up to 30 characters | AA16: Free entry, up to 300 characters | AB16: Free entry, up to 80 characters | AC16: Free entry, up to 80 characters | AD16: Free entry, up to 10 characters | AE16: The legacy code; mapped by the code map STATUS:KYC (Code Maps screen of the Data Migration Console; maps prepared in the Migration Workbook of BRD-13) | AF16: Free entry | AG16: Free entry | AH16: The legacy code; mapped by the code map LOV:KYC_RISK_RATING (Code Maps screen of the Data Migration Console; maps prepared in the Migration Workbook of BRD-13) | AI16: The legacy code; mapped by the code map STATUS:CLIENT (Code Maps screen of the Data Migration Console; maps prepared in the Migration Workbook of BRD-13) | AJ16: Free entry | AK16: Free entry
A17: What to enter | B17: Client number in the source system | C17: Individual or corporate | D17: Last name (individual) | E17: First name (individual) | F17: Middle name | G17: Name suffix | H17: Registered name (corporate) | I17: SEC or DTI registration number (corporate) | J17: Birth date (individual) | K17: Tax identification number | L17: Government ID type | M17: Government ID number | N17: BDO bank client | O17: BDO customer information file number | P17: Nationality | Q17: Source of funds | R17: Market segment | S17: Customer segment (MIS) | T17: Business origin (MIS) | U17: Account officer | V17: Sales unit of the client | W17: Servicing branch | X17: Primary e-mail | Y17: Primary mobile number | Z17: Landline | AA17: Primary street address | AB17: City / municipality | AC17: Province | AD17: Postal code | AE17: KYC status in legacy | AF17: Date KYC was verified | AG17: Next KYC review date | AH17: KYC risk rating | AI17: Client status in legacy | AJ17: Date the client was created in legacy | AK17: Last change in legacy (survivorship and deltas)
A18: Row | B18: legacy_client_no * | C18: client_type * | D18: last_name | E18: first_name | F18: middle_name | G18: suffix | H18: corporate_name | I18: registration_no | J18: birth_date | K18: tin | L18: id_type | M18: id_number | N18: bank_client_flag | O18: bank_cif | P18: nationality | Q18: source_of_funds | R18: market_segment * | S18: customer_segment | T18: business_origin | U18: ao_user_id | V18: sales_unit_code | W18: branch_code | X18: email | Y18: mobile | Z18: phone | AA18: address_line | AB18: city | AC18: province | AD18: postal_code | AE18: kyc_status | AF18: kyc_verified_date | AG18: kyc_review_due | AH18: risk_rating | AI18: client_status * | AJ18: created_date * | AK18: last_updated *
A19: Example – overwrite or delete | B19: Q-0012345 | C19: I | D19: Reyes | E19: Ana | F19: Cruz | G19: Jr. | H19: Acme Trading Corp. | I19: CS201912345 | J19: 1990-04-15 | K19: 123-456-789-000 | L19: PASSPORT | M19: P1234567A | N19: Y | O19: 1234567890 | P19: FILIPINO | Q19: SALARY | R19: CBG | S19: AFFLUENT | T19: BANK_REFERRAL | U19: mreyes | V19: T-RET-07 | W19: MKT01 | X19: ana.reyes@example.ph | Y19: 09171234567 | Z19: (02) 8123 4567 | AA19: 12 Rizal St., Brgy. San Antonio | AB19: Pasig | AC19: Metro Manila | AD19: 1600 | AE19: COMPLETE | AF19: 2024-03-11 | AG19: 2028-03-11 | AH19: STANDARD | AI19: ACTIVE | AJ19: 2021-07-02 | AK19: 2026-08-30 14:22:05

Sheet D0-10 Tax codes
A1: D0-10 Tax codes | K1: Step 24 of 52
A2: ← Back to Start here | B2: Step 24 of 52. Fill in one row per record below the column headers; the guide above each column says what to enter. | K2: Ask a question →
A3: Purpose | B3: The tax codes with their ATC, rate and GL account
A4: Provided by | B4: Head, Comptrollership (Tax)
A5: Due | B5: 16-Jul-2027 – Values for UAT
A6: How it is loaded | B6: Upload on the configuration screen Finance › Tax & Statutory › Tax Codes & Forms, approved by a second user
A7: Source | B7: Upload template of the configuration screen (the same columns, headers, mandatory flags and allowed values)
A8: Depends on | B8: D0-06 Chart of accounts →
A9: Checklist | B9: One row per kind of tax is written below the header; give the code, the ATC, the rate, the GL account and the dates of each (rates and ATCs as BDOI's tax adviser confirms them), and add one row per ATC. The sheet D0-10 Tax checklist says what each covers
A10: Tax types | B10: Use only the twelve tax types of the list, as the upload accepts them; the ATC is mandatory for EWT and FWT (FWT, FINAL_VAT and PERCENTAGE_TAX are new in v1.2)
A11: Progress | B11: Rows entered | C11: =SUMPRODUCT(((ROW($B$19:$B$519)>19)+($B$19<>"EWT_WC158")>0)*(LEN($B$19:$B$519&$C$19:$C$519&$D$19:$D$519&$E$19:$E$519&$F$19:$F$519&$G$19:$G$519&$H$19:$H$519&$I$19:$I$519&$J$19:$J$519&$K$19:$K$519)>0)) | D11: Mandatory cells missing | E11: =SUMPRODUCT(((ROW($B$19:$B$519)>19)+($B$19<>"EWT_WC158")>0)*(LEN($B$19:$B$519&$C$19:$C$519&$D$19:$D$519&$E$19:$E$519&$F$19:$F$519&$G$19:$G$519&$H$19:$H$519&$I$19:$I$519&$J$19:$J$519&$K$19:$K$519)>0)*(($B$19:$B$519="")+($C$19:$C$519="")+($D$19:$D$519="")+($G$19:$G$519="")+($H$19:$H$519="")+($J$19:$J$519="")))
A12: Confirmed by (BDOI owner) | D12: Date
A14: Mandatory | B14: Yes | C14: Yes | D14: Yes | E14: Conditional: EWT, FWT | F14: No | G14: Yes | H14: Yes | I14: No | J14: Yes | K14: No
A15: Format | B15: Up to 20 capitals | C15: Text | D15: Code from the drop-down | E15: Text | F15: Code from the drop-down | G15: Number without thousands separators, e.g. 1500000.50 | H15: Text | I15: Text | J15: Date dd-MMM-yyyy, e.g. 15-Jan-2026 | K15: Date dd-MMM-yyyy, e.g. 15-Jan-2026
A16: Allowed values | B16: Free entry | C16: Free entry | D16: List Tax type (BIBS): 12 values, see Reference lists | E16: Free entry | F16: INDIVIDUAL, CORPORATE (list Payee class (BIR)) | G16: A number from 0 to 100 | H16: Code of an existing account of the chart of accounts | I16: Free entry | J16: A date, for example 15-Jan-2028 | K16: A date, for example 15-Jan-2028
A17: What to enter | B17: Code of the tax | C17: Name of the tax | D17: Kind of tax | E17: Alphanumeric tax code of the BIR | F17: Payee class of the withholding | G17: Rate in percent | H17: Account the tax posts to | I17: Nature of the income | J17: First day of the rate | K17: Last day of the rate; blank = open
A18: Row | B18: Tax code * | C18: Name * | D18: Tax type * | E18: ATC | F18: Payee class | G18: Rate % * | H18: GL account * | I18: Income nature | J18: Effective from * | K18: Effective to
A19: Example – overwrite or delete | B19: EWT_WC158 | C19: EWT 1% - goods | D19: EWT | E19: WC158 | F19: CORPORATE | G19: 1 | H19: 2150.02 | I19: Purchase of goods | J19: 46753
C20: Output VAT on commission and service fees | D20: VAT_OUTPUT
C21: Zero-rated sales (commission and fees on zero-rated clients) | D21: VAT_ZERO_RATED
C22: VAT-exempt sales | D22: VAT_EXEMPT
C23: Input VAT on purchases | D23: VAT_INPUT
C24: Creditable withholding tax withheld by insurers on BDOI's commission (2307 received) | D24: EWT
C25: Creditable withholding tax withheld by government and top withholding agent clients on service fees | D25: EWT
C26: EWT BDOI withholds on suppliers: one row per ATC (professional fees, rentals, contractors, goods, services, commissions) | D26: EWT
C27: Final VAT withheld by government payors on BDOI's commission and fees | D27: FINAL_VAT
C28: Final withholding tax: withheld by government payors, and the final tax on bank interest (one row per ATC) | D28: FWT
C29: Percentage tax on BDOI's own receipts not subject to VAT (only if BDOI confirms such income) | D29: PERCENTAGE_TAX

Sheet D0-10 Tax checklist
A1: D0-10 Tax checklist: BDOI's own taxes
A2: ← Back to Start here | B2: One row per kind of tax: what BIBS does, where it is set up (D0-10 tax codes, TX-01 party tax profiles, TX-02 tax forms, D0-01 and D0-02 tax registration) and what BDOI provides
A4: Tax | B4: What BIBS does | C4: Where it is set up | D4: What BDOI provides or confirms | E4: Held by BIBS | F4: Question | G4: Rule confirmed | H4: BDOI comments | I4: Status
A5: Output VAT on commission and service fees | B5: Tax type VAT_OUTPUT; the VAT worksheet prepares the quarterly VAT return (2550Q) from the sales. | C5: D0-10 (code, rate, GL account); TX-02 form 2550Q | D5: Code, rate and GL account of output VAT | E5: Yes | F5: TX-Q05 | I5: Not started
A6: Zero-rated and VAT-exempt sales | B6: Tax types VAT_ZERO_RATED and VAT_EXEMPT; a client's VAT treatment (TX-01) classifies a sale without VAT. | C6: D0-10; TX-01 VAT treatment | D6: The zero-rated and exempt cases and the clients concerned | E6: Yes | F6: TX-Q05 | I6: Not started
A7: Input VAT | B7: Tax type VAT_INPUT; credited against output VAT on the VAT return. | C7: D0-10; TX-02 credit account | D7: Code, rate and GL account of input VAT | E7: Yes | F7: TX-Q05 | I7: Not started
A8: Creditable withholding tax withheld by insurers on BDOI's commission | B8: The 2307 certificates received are recorded on Certificates Received (ATC, income, tax) and posted against the receivable. | C8: D0-10 EWT codes; TX-01 default ATC of each insurer | D8: The ATCs and rates the insurers withhold on commission | E8: Yes | F8: TX-Q05 | I8: Not started
A9: EWT BDOI withholds on suppliers | B9: Tax type EWT, one code per ATC; withheld on payments, 2307 issued, monthly 0619-E, quarterly 1601-EQ, QAP and alphalists. | C9: D0-10 (one row per ATC); TX-01 default ATC of each supplier; TX-02 forms | D9: The ATC list with rates, income nature and GL account | E9: Yes | F9: TX-Q05 | I9: Not started
A10: Government payors (final VAT and final tax withheld) | B10: Tax types FINAL_VAT (final VAT withheld) and FWT (final withholding tax, one code per ATC); the party tax profile marks the government payor, which is always a withholding agent. | C10: D0-10 (FINAL_VAT, FWT); TX-01 Government payor | D10: The codes, ATCs, rates and accounts, and the government payors among the clients | E10: Yes | F10: TX-Q06 | I10: Not started
A11: Top withholding agent clients | B11: Withholding by a client is recorded as a 2307 received; the party tax profile marks the withholding agents and the top withholding agents. | C11: TX-01 Withholding agent, Top withholding agent | D11: The clients that are withholding agents or top withholding agents | E11: Yes | F11: TX-Q09 | I11: Not started
A12: Final tax on bank interest | B12: Tax type FWT, one code per ATC. | C12: D0-10 (FWT) | D12: The ATC, rate and account of the final tax on bank interest | E12: Yes | F12: TX-Q06 | I12: Not started
A13: Percentage tax on BDOI's own receipts | B13: Tax type PERCENTAGE_TAX on BDOI's own receipts not subject to VAT (the premium tax of PM-04 stays a charge on premiums). | C13: D0-10 (PERCENTAGE_TAX) | D13: Whether any BDOI income is subject to percentage tax, with its rate and account | E13: Yes | F13: TX-Q06 | I13: Not started
A14: Tax returns and the filing calendar | B14: BIBS prepares the VAT return 2550Q and the withholding tax forms 0619-E and 1601-EQ from its worksheets and reminds of 1601-C (prepared in the payroll system). The premium-levy returns (DST, premium tax, local business tax, FST) are the insurers' returns and are not kept in BIBS. | C14: TX-02 | D14: The forms BDOI files, their due dates and accounts | E14: Yes | F14: TX-Q07 | I14: Not started
A15: Tax exemption certificates of clients | B15: The party tax profile keeps the certificate number and its validity; a zero-rated or exempt invoice dated outside the validity is flagged on the VAT worksheet for checking before the return is filed. | C15: TX-01 Tax exemption certificate no., Certificate valid from / to | D15: The certificates of the exempt parties | E15: Yes | F15: TX-Q09 | I15: Not started
A16: Company tax registration | B16: BIBS keeps the TIN with its branch code, the RDO, the VAT registration and the CAS and e-invoicing permits of the company, and the BIR branch code and RDO of each branch; the RDO is printed on the BIR exports. | C16: D0-01 RDO code, VAT registered, CAS and e-invoicing permits; D0-02 BIR branch code, RDO code | D16: The registration details of the company and of each registered branch | E16: Yes | F16: TX-Q08 | I16: Not started

Sheet D0-11 Bank accounts
A1: D0-11 Company bank accounts | J1: Step 25 of 52
A2: ← Back to Start here | B2: Step 25 of 52. Fill in one row per record below the column headers; the guide above each column says what to enter. | J2: Ask a question →
A3: Purpose | B3: The bank accounts of BDOI used for collections and disbursements
A4: Provided by | B4: Head, Comptrollership; Treasury
A5: Due | B5: 4-Jan-2027 – Platform set-up for Drop 1 SIT
A6: How it is loaded | B6: Upload on the configuration screen Finance › Disbursement › Bank Accounts and Checks, approved by a second user
A7: Source | B7: Upload template of the configuration screen (the same columns, headers, mandatory flags and allowed values)
A8: Depends on | B8: D0-06 Chart of accounts → | D8: D0-02 Branches →
A9: Payment notification format | B9: FIXED_WIDTH, CSV or DCTF, the formats the upload accepts; an e-mail advice is not a format of the bank account
A10: Progress | B10: Rows entered | C10: =SUMPRODUCT(((ROW($B$18:$B$518)>18)+($B$18<>"BNK-CA-001")>0)*(LEN($B$18:$B$518&$C$18:$C$518&$D$18:$D$518&$E$18:$E$518&$F$18:$F$518&$G$18:$G$518&$H$18:$H$518&$I$18:$I$518&$J$18:$J$518)>0)) | D10: Mandatory cells missing | E10: =SUMPRODUCT(((ROW($B$18:$B$518)>18)+($B$18<>"BNK-CA-001")>0)*(LEN($B$18:$B$518&$C$18:$C$518&$D$18:$D$518&$E$18:$E$518&$F$18:$F$518&$G$18:$G$518&$H$18:$H$518&$I$18:$I$518&$J$18:$J$518)>0)*(($B$18:$B$518="")+($C$18:$C$518="")+($D$18:$D$518="")+($E$18:$E$518="")+($F$18:$F$518="")+($G$18:$G$518="")+($J$18:$J$518="")))
A11: Confirmed by (BDOI owner) | D11: Date
A13: Mandatory | B13: Yes | C13: Yes | D13: Yes | E13: Yes | F13: Yes | G13: Yes | H13: No | I13: No | J13: Yes
A14: Format | B14: Up to 20 capitals | C14: Text | D14: Text | E14: Text | F14: Text | G14: Text | H14: Text | I14: Text | J14: Code from the drop-down
A15: Allowed values | B15: Free entry | C15: Free entry | D15: Free entry | E15: Free entry | F15: Free entry | G15: Code of an existing account of the chart of accounts | H15: Code of an existing account of the chart of accounts | I15: Code of an existing branch | J15: FIXED_WIDTH, CSV, DCTF (list Payment notification format (D0-11))
A16: What to enter | B16: Code of the bank account | C16: Name of the account | D16: Bank name | E16: As printed by the bank | F16: Currency of the account | G16: Account of the chart with a bank category | H16: Account of the post-dated checks | I16: Branch of the account | J16: Format of the bank advice
A17: Row | B17: Bank account code * | C17: Name * | D17: Bank * | E17: Account number * | F17: Currency * | G17: GL account * | H17: PDC clearing account | I17: Branch code | J17: Payment notification format *
A18: Example – overwrite or delete | B18: BNK-CA-001 | C18: Makati current account | D18: Metropolitan Commercial Bank | E18: 000123456789 | F18: PHP | G18: 1110.01 | H18: 2241 | I18: HO | J18: CSV

Sheet PM-01 Product catalogue
A1: PM-01 Product catalogue | W1: Step 26 of 52
A2: ← Back to Start here | B2: Step 26 of 52. Fill in one row per record below the column headers; the guide above each column says what to enter. | W2: Ask a question →
A3: Purpose | B3: Product lines, cover types and subtypes, and every product (risk code) with its features
A4: Provided by | B4: Product Owner, Marketing Business System (MBS)
A5: Due | B5: 9-Apr-2027 – Reference data for Trial migration 1 (M4)
A6: How it is loaded | B6: Data migration object R05 (product lines, cover types, products) through the catalogue services, pending authorisation; after go-live on Products (SCR-PM-11)
A7: Source | B7: Legacy QPS and EBIX product lists, completed by MBS
A8: Depends on | B8: PM-09 Lists of values and parameters → | D8: R05 Product lines, cover types, products and risk codes →
A9: Progress | B9: Rows entered | C9: =SUMPRODUCT(((ROW($B$17:$B$517)>17)+($B$17<>"MOTOR")>0)*(LEN($B$17:$B$517&$C$17:$C$517&$D$17:$D$517&$E$17:$E$517&$F$17:$F$517&$G$17:$G$517&$H$17:$H$517&$I$17:$I$517&$J$17:$J$517&$K$17:$K$517&$L$17:$L$517&$M$17:$M$517&$N$17:$N$517&$O$17:$O$517&$P$17:$P$517&$Q$17:$Q$517&$R$17:$R$517&$S$17:$S$517&$T$17:$T$517&$U$17:$U$517&$V$17:$V$517&$W$17:$W$517)>0)) | D9: Mandatory cells missing | E9: =SUMPRODUCT(((ROW($B$17:$B$517)>17)+($B$17<>"MOTOR")>0)*(LEN($B$17:$B$517&$C$17:$C$517&$D$17:$D$517&$E$17:$E$517&$F$17:$F$517&$G$17:$G$517&$H$17:$H$517&$I$17:$I$517&$J$17:$J$517&$K$17:$K$517&$L$17:$L$517&$M$17:$M$517&$N$17:$N$517&$O$17:$O$517&$P$17:$P$517&$Q$17:$Q$517&$R$17:$R$517&$S$17:$S$517&$T$17:$T$517&$U$17:$U$517&$V$17:$V$517&$W$17:$W$517)>0)*(($B$17:$B$517="")+($C$17:$C$517="")+($H$17:$H$517="")+($I$17:$I$517="")+($K$17:$K$517="")+($M$17:$M$517="")+($P$17:$P$517="")+($Q$17:$Q$517="")))
A10: Confirmed by (BDOI owner) | D10: Date
A12: Mandatory | B12: Yes | C12: Yes | D12: No | E12: Conditional: package products | F12: Conditional: with the code | G12: No | H12: Yes | I12: Yes | J12: No | K12: Yes | L12: No | M12: Yes | N12: No | O12: No | P12: Yes | Q12: Yes | R12: No | S12: No | T12: No | U12: No | V12: No | W12: No
A13: Format | B13: Up to 30 capitals | C13: Text | D13: Regular expression | E13: Up to 30 capitals | F13: Text | G13: Cover type code | H13: 1 to 20 capitals or digits | I13: Up to 200 characters | J13: Text | K13: Y or N | L13: Codes separated by commas; blank = all | M13: PAID or CLIENT_CONFIRMATION | N13: BY_RULES, ALWAYS or NEVER | O13: Up to four decimals | P13: Percentage | Q13: Amount in PHP | R13: Amount in PHP | S13: Y or N | T13: Y or N | U13: Y or N | V13: Y or N; 2 to 10 years | W13: Y or N
A14: Allowed values | B14: Free entry, up to 30 characters | C14: Free entry | D14: Free entry | E14: Free entry, up to 30 characters | F14: Free entry | G14: A code of PM-01 Product catalogue, column Cover type code | H14: Free entry, up to 20 characters | I14: Free entry, up to 200 characters | J14: Free entry | K14: Y or N | L14: One or more codes of the list Market segment (Reference lists), separated by commas | M14: PAID, CLIENT_CONFIRMATION (list Placement after) | N14: BY_RULES, ALWAYS, NEVER (list TSU review) | O14: A number from 0 to 100 | P14: A number from 0 to 100 | Q14: A number | R14: A number | S14: Y or N | T14: Y or N | U14: Y or N | V14: Free entry | W14: Y or N
A15: What to enter | B15: Product line (level 1), for example MOTOR, PROPERTY | C15: Name shown in the drop-downs | D15: Naming convention of the risk codes of the line, when BDOI states one | E15: Cover type (level 2) of the line | F15: Name of the cover type | G15: Only for a subtype (one level below a cover type) | H15: Product code (level 3); unique | I15: Name shown to users | J15: Code of the product in QPS or EBIX, for the migration map | K15: Y for a package product (terms change through versions) | L15: Segments the product is offered to (list MARKET_SEGMENT) | M15: Payment gate before placement | N15: When TSU reviews an account of the product | O15: Rate of a non-package product; for a package, of version 1 | P15: Commission when no insurer rate applies | Q15: Minimum premium of the product | R15: Above it the account goes to TSU | S15: Several vehicles on one account | T15: Mortgage or loan related | U15: Premium may be paid directly to the insurer | V15: Multi-year term and its maximum | W15: Free First Year eligible
A16: Row | B16: Line code * | C16: Line name * | D16: Risk-code pattern | E16: Cover type code | F16: Cover type name | G16: Parent cover type | H16: Risk code * | I16: Product name * | J16: Legacy code | K16: Package * | L16: Market segments | M16: Placement after * | N16: TSU review | O16: Default rate % | P16: Default commission % * | Q16: Minimum premium * | R16: Package TSI limit | S16: Fleet | T16: Mortgage related | U16: Direct payment allowed | V16: Multi-year / Maximum term | W16: Free First Year
A17: Example – overwrite or delete | B17: MOTOR | C17: Motor | D17: MTR[0-9]{2} | E17: COMPREHENSIVE | F17: Comprehensive | H17: MTR30 | I17: Motor Fleet Plus | J17: QPS-MFP | K17: Y | L17: COMBANK | M17: PAID | N17: BY_RULES | O17: 1.2 | P17: 15 | Q17: 5000 | R17: 5000000 | S17: Y | T17: N | U17: N | V17: N | W17: N

Sheet R08 Chart of accounts mapping
A1: R08 Chart of accounts mapping | I1: Step 27 of 52
A2: ← Back to Start here | B2: Step 27 of 52. Fill in one row per record below the column headers; the guide above each column says what to enter. | I2: Ask a question →
A3: Purpose | B3: One row per record of Chart of accounts mapping (legacy GL account to BIBS account) as extracted from EBIX, ISYS GL. Key legacy_account_code. Sent as the file R08_template.csv (CSV, header row as below) with its control file (row count, count of distinct keys).
A4: Provided by | B4: Comptrollership data steward (to name); approved by Head, Comptrollership; Product Owner FRBS and ACSL; extracted by BDOI IT
A5: Due | B5: M3 (29 Jan 2027)
A6: How it is loaded | B6: Migration Console: the file R08_template.csv (the header row as below) and its control file are received on Data Migration › Data Migration › Extracts and loaded by a batch of object R08; lands in: GL account code map to the BIBS chart of accounts (chart configured by Comptrollership)
A7: Source | B7: EBIX, ISYS GL
A8: Depends on | B8: D0-06 Chart of accounts →
A9: Progress | B9: Rows entered | C9: =SUMPRODUCT(((ROW($B$18:$B$218)>18)+($B$18<>"1101-02")>0)*(LEN($B$18:$B$218&$C$18:$C$218&$D$18:$D$218&$E$18:$E$218&$F$18:$F$218&$G$18:$G$218&$H$18:$H$218&$I$18:$I$218)>0)) | D9: Mandatory cells missing | E9: =SUMPRODUCT(((ROW($B$18:$B$218)>18)+($B$18<>"1101-02")>0)*(LEN($B$18:$B$218&$C$18:$C$218&$D$18:$D$218&$E$18:$E$218&$F$18:$F$218&$G$18:$G$218&$H$18:$H$218&$I$18:$I$218)>0)*(($B$18:$B$218="")+($C$18:$C$218="")+($D$18:$D$218="")+($E$18:$E$218="")))
A10: Confirmed by (BDOI owner) | D10: Date
A12: Check when loaded | B12: Unique | C12: Not blank | D12: In the list | E12: In the list | F12: In the list | G12: Mandatory when legacy_control_type is NONE; exists and active in BIBS | H12: Y or N | I12: -
A13: Mandatory | B13: Yes | C13: Yes | D13: Yes | E13: Yes | F13: No | G13: Conditional: Mandatory when legacy_control_type is NONE; exists and active in BIBS | H13: No | I13: No
A14: Format | B14: Code, up to 30; As stored in legacy | C14: Text, up to 200; Free text | D14: Code, up to 12; Upper case | E14: Code, up to 2; Upper case | F14: Code, up to 20; Upper case | G14: Code, up to 30; As in the BIBS chart | H14: Flag, up to 1; Y or N | I14: Text, up to 300; Free text
A15: Allowed values | B15: Free entry, up to 30 characters | C15: Free entry, up to 200 characters | D15: ASSET, LIABILITY, EQUITY, INCOME, EXPENSE (list R08 account_type) | E15: DR, CR (list R08 normal_balance) | F15: List R08 legacy_control_type: 8 values, see Reference lists | G15: Account codes of the BIBS chart of accounts | H15: Y or N | I15: Free entry, up to 300 characters
A16: What to enter | B16: Legacy GL account code | C16: Legacy account name | D16: Account type | E16: Normal balance side | F16: Marks the legacy control accounts whose balance F01 or F02 carries in detail | G16: BIBS account the legacy account maps to (filled by Comptrollership) | H16: Balances are kept per branch | I16: Mapping remarks
A17: Row | B17: legacy_account_code * | C17: legacy_account_name * | D17: account_type * | E17: normal_balance * | F17: legacy_control_type | G17: bibs_account_code | H17: branch_specific_flag | I17: remarks
A18: Example – overwrite or delete | B18: 1101-02 | C18: Cash in Bank - BDO Makati | D18: ASSET | E18: DR | F18: NONE | G18: X102.03 (illustrative code, not in use) | H18: Y | I18: Merged with 1201-01

Sheet UP-02 Payees (upload)
A1: UP-02 Payees | L1: Step 28 of 52
A2: ← Back to Start here | B2: Step 28 of 52. Fill in one row per record below the column headers; the guide above each column says what to enter. | L2: Ask a question →
A3: Purpose | B3: One row per payee of Disbursement (suppliers, service providers, employees, government agencies and other payees) with the payment modes, currency and bank account. This is also the layout of the payees of the legacy systems (migration object R09, in scope if BDOI confirms it).
A4: Provided by | B4: Product Owner, Comptrollership - Disbursement
A5: Due | B5: 9-Apr-2027 – Reference data for Trial migration 1 (M4)
A6: How it is loaded | B6: Screen upload: Finance › Disbursement › Disbursement Uploads, upload type Payee Migration; the payees and their bank accounts come in for authorisation
A7: Source | B7: Platform upload definition (column layout as the screen loads it)
A8: Depends on | B8: MD-01 Business partners (reinsurers, intermediaries, suppliers) →
A9: Progress | B9: Rows entered | C9: =SUMPRODUCT(((ROW($B$17:$B$317)>17)+($B$17<>"SUP-0001")>0)*(LEN($B$17:$B$317&$C$17:$C$317&$D$17:$D$317&$E$17:$E$317&$F$17:$F$317&$G$17:$G$317&$H$17:$H$317&$I$17:$I$317&$J$17:$J$317&$K$17:$K$317&$L$17:$L$317)>0)) | D9: Mandatory cells missing | E9: =SUMPRODUCT(((ROW($B$17:$B$317)>17)+($B$17<>"SUP-0001")>0)*(LEN($B$17:$B$317&$C$17:$C$317&$D$17:$D$317&$E$17:$E$317&$F$17:$F$317&$G$17:$G$317&$H$17:$H$317&$I$17:$I$317&$J$17:$J$317&$K$17:$K$317&$L$17:$L$317)>0)*(($B$17:$B$317="")+($C$17:$C$317="")+($D$17:$D$317="")+($H$17:$H$317="")+($I$17:$I$317="")+($J$17:$J$317="")))
A10: Confirmed by (BDOI owner) | D10: Date
A12: Mandatory | B12: Yes | C12: Yes | D12: Yes | E12: No | F12: No | G12: No | H12: Yes | I12: Yes | J12: Yes | K12: No | L12: Conditional: a mode crediting an account (CTA, TT, online banking) is allowed
A13: Format | B13: Text | C13: Text | D13: Text | E13: Text | F13: Text | G13: Text | H13: Text | I13: Mode codes separated by |, e.g. CHECK|CTA | J13: ISO currency code, 3 letters | K13: Text | L13: Text
A14: Allowed values | B14: Free entry | C14: SUPPLIER, INSURER, EMPLOYEE, CLIENT, GOVERNMENT, OTHER (list Payee class) | D14: Free entry | E14: Free entry | F14: Free entry | G14: Free entry | H14: List Default mode (UP-02): 7 values, see Reference lists | I14: Codes of the Default mode list | J14: Free entry | K14: Free entry | L14: Free entry
A15: What to enter | B15: Party code of the payee (a party known to BIBS) | C15: Class of the payee | D15: Payee name | E15: Address | F15: E-mail for payment advices | G15: Tax identification number | H15: Mode of payment used by default | I15: Modes of payment allowed for the payee | J15: Currency of payment (a currency known to BIBS) | K15: Bank of the payee account | L15: Account number of the payee at the bank
A16: Row | B16: Payee code * | C16: Payee class * | D16: Name * | E16: Address | F16: Email | G16: TIN | H16: Default mode * | I16: Allowed modes * | J16: Currency * | K16: Bank | L16: Account no
A17: Example – overwrite or delete | B17: SUP-0001 | C17: SUPPLIER | D17: Acme Office Supply | E17: Makati City | F17: ap@acme.example | G17: 123-456-789-000 | H17: CHECK | I17: CHECK|CTA | J17: PHP | K17: Philippine National Bank | L17: 001234567890

Sheet D0-01 Company
A1: D0-01 Company | P1: Step 29 of 52
A2: ← Back to Start here | B2: Step 29 of 52. Fill in one row per record below the column headers; the guide above each column says what to enter. | P2: Ask a question →
A3: Purpose | B3: The company record of BDOI
A4: Provided by | B4: Head, Comptrollership
A5: Due | B5: 4-Jan-2027 – Platform set-up for Drop 1 SIT
A6: How it is loaded | B6: Upload on the configuration screen Setup & Administration › Setup › Companies, approved by a second user
A7: Source | B7: Upload template of the configuration screen (the same columns, headers, mandatory flags and allowed values)
A8: Depends on | B8: D0-06 Chart of accounts →
A9: Tax registration | B9: Besides the TIN with its branch code, BIBS keeps the RDO code, the VAT registration and the CAS and e-invoicing permits (number and date); the RDO is printed on the BIR exports. The receipt series in use come from R11
A10: Progress | B10: Rows entered | C10: =SUMPRODUCT(((ROW($B$18:$B$518)>18)+($B$18<>"IBRK")>0)*(LEN($B$18:$B$518&$C$18:$C$518&$D$18:$D$518&$E$18:$E$518&$F$18:$F$518&$G$18:$G$518&$H$18:$H$518&$I$18:$I$518&$J$18:$J$518&$K$18:$K$518&$L$18:$L$518&$M$18:$M$518&$N$18:$N$518&$O$18:$O$518&$P$18:$P$518)>0)) | D10: Mandatory cells missing | E10: =SUMPRODUCT(((ROW($B$18:$B$518)>18)+($B$18<>"IBRK")>0)*(LEN($B$18:$B$518&$C$18:$C$518&$D$18:$D$518&$E$18:$E$518&$F$18:$F$518&$G$18:$G$518&$H$18:$H$518&$I$18:$I$518&$J$18:$J$518&$K$18:$K$518&$L$18:$L$518&$M$18:$M$518&$N$18:$N$518&$O$18:$O$518&$P$18:$P$518)>0)*(($B$18:$B$518="")+($C$18:$C$518="")+($D$18:$D$518="")+($E$18:$E$518="")+($F$18:$F$518="")+($G$18:$G$518="")+($H$18:$H$518="")+($I$18:$I$518="")+($J$18:$J$518="")))
A11: Confirmed by (BDOI owner) | D11: Date
A13: Mandatory | B13: Yes | C13: Yes | D13: Yes | E13: Yes | F13: Yes | G13: Yes | H13: Yes | I13: Yes | J13: Yes | K13: No | L13: No | M13: No | N13: No | O13: No | P13: No
A14: Format | B14: Up to 10 capitals | C14: Text | D14: 000-000-000-00000 | E14: Text | F14: ISO 4217 | G14: Number without thousands separators, e.g. 1500000.50 | H14: Number without thousands separators, e.g. 1500000.50 | I14: Number without thousands separators, e.g. 1500000.50 | J14: Text | K14: Three digits, optionally a letter | L14: Y or N | M14: Text | N14: Date dd-MMM-yyyy, e.g. 15-Jan-2026 | O14: Text | P14: Date dd-MMM-yyyy, e.g. 15-Jan-2026
A15: Allowed values | B15: Free entry | C15: Free entry | D15: Free entry | E15: Free entry | F15: Free entry | G15: A whole number from 1 to 12 | H15: A whole number from 0 to 365 | I15: A whole number from 0 to 365 | J15: Code of an existing account of the chart of accounts | K15: Free entry | L15: Y or N | M15: Free entry | N15: A date, for example 15-Jan-2028 | O15: Free entry | P15: A date, for example 15-Jan-2028
A16: What to enter | B16: Code of the company on every record | C16: Name as registered with the SEC | D16: Tax identification number with branch code | E16: Address printed on receipts and BIR forms | F16: Currency of the books | G16: First month of the financial year | H16: How many days before today a posting may be dated | I16: How many days after today a posting may be dated | J16: Account that receives the year-end result | K16: Revenue District Office of the registration | L16: Y when the company is VAT-registered | M16: Permit of the computerised accounting system | N16: Date of the CAS permit | O16: Permit of the electronic invoicing | P16: Date of the e-invoicing permit
A17: Row | B17: Company code * | C17: Registered name * | D17: TIN * | E17: Registered address * | F17: Base currency * | G17: Fiscal year start month * | H17: Back-value days * | I17: Forward-value days * | J17: Retained earnings account * | K17: RDO code | L17: VAT registered | M17: CAS permit no. | N17: CAS permit date | O17: E-invoicing permit no. | P17: E-invoicing permit date
A18: Example – overwrite or delete | B18: IBRK | C18: Insurance Brokers, Inc. | D18: 000-000-000-00000 | E18: Makati City | F18: PHP | G18: 1 | H18: 5 | I18: 0 | J18: 3200 | K18: 050 | L18: Y

Sheet D0-08 Accounting rules
A1: D0-08 Accounting rules | K1: Step 30 of 52
A2: ← Back to Start here | B2: Step 30 of 52. Fill in one row per record below the column headers; the guide above each column says what to enter. | K2: Ask a question →
A3: Purpose | B3: The debit and credit accounts of each accounting event of the platform
A4: Provided by | B4: Head, Comptrollership
A5: Due | B5: 4-Jan-2027 – Platform set-up for Drop 1 SIT
A6: How it is loaded | B6: Upload on the configuration screen Finance › Accounting Engine › Accounting Rules, approved by a second user
A7: Source | B7: Upload template of the configuration screen (the same columns, headers, mandatory flags and allowed values)
A8: Depends on | B8: D0-04 Cost centres and business lines → | D8: D0-06 Chart of accounts →
A9: Progress | B9: Rows entered | C9: =SUMPRODUCT(((ROW($B$17:$B$517)>17)+($B$17<>"PREMIUM_BOOKED")>0)*(LEN($B$17:$B$517&$C$17:$C$517&$D$17:$D$517&$E$17:$E$517&$F$17:$F$517&$G$17:$G$517&$H$17:$H$517&$I$17:$I$517&$J$17:$J$517&$K$17:$K$517)>0)) | D9: Mandatory cells missing | E9: =SUMPRODUCT(((ROW($B$17:$B$517)>17)+($B$17<>"PREMIUM_BOOKED")>0)*(LEN($B$17:$B$517&$C$17:$C$517&$D$17:$D$517&$E$17:$E$517&$F$17:$F$517&$G$17:$G$517&$H$17:$H$517&$I$17:$I$517&$J$17:$J$517&$K$17:$K$517)>0)*(($B$17:$B$517="")+($C$17:$C$517="")+($F$17:$F$517="")+($G$17:$G$517="")+($H$17:$H$517="")+($I$17:$I$517="")+($J$17:$J$517="")))
A10: Confirmed by (BDOI owner) | D10: Date
A12: Mandatory | B12: Yes | C12: Yes | D12: No | E12: No | F12: Yes | G12: Yes | H12: Yes | I12: Yes | J12: Yes | K12: No
A13: Format | B13: Text | C13: Text | D13: Text | E13: Text | F13: Date dd-MMM-yyyy, e.g. 15-Jan-2026 | G13: Number without thousands separators, e.g. 1500000.50 | H13: Code from the drop-down | I13: Text | J13: Text | K13: Text
A14: Allowed values | B14: Code of an existing accounting event | C14: Free entry | D14: Code of an existing business line | E14: Free entry | F14: A date, for example 15-Jan-2028 | G14: A whole number from 1 to 999 | H14: DEBIT, CREDIT (list Debit or credit (D0-08)) | I14: Code of an existing account of the chart of accounts | J14: A component of the event | K14: Free entry
A15: What to enter | B15: Event that the rule posts | C15: Name of the rule | D15: Line the rule applies to; blank = every line | E15: Currency the rule applies to; blank = every currency | F15: First posting date of the rule | G15: Order of the line in the entry | H15: Side of the line | I15: Account posted | J15: Amount the line posts | K15: Text of the journal line
A16: Row | B16: Event type * | C16: Rule name * | D16: Business line | E16: Currency | F16: Effective from * | G16: Line * | H16: Debit or credit * | I16: Account code * | J16: Amount component * | K16: Narration
A17: Example – overwrite or delete | B17: PREMIUM_BOOKED | C17: Premium booked - non-life | F17: 46753 | G17: 1 | H17: DEBIT | I17: 1210.07 | J17: GROSS_PREMIUM | K17: Premium receivable

Sheet D0-09 Legacy accounts
A1: D0-09 Legacy control accounts | G1: Step 31 of 52
A2: ← Back to Start here | B2: Step 31 of 52. Fill in one row per record below the column headers; the guide above each column says what to enter. | G2: Ask a question →
A3: Purpose | B3: The accounts that carry the migrated invoices and unapplied payments until they run off, and Migration Clearing
A4: Provided by | B4: Head, Comptrollership
A5: Due | B5: 1-Dec-2026 – Drafts with the Drop 0 sign-off
A6: How it is loaded | B6: Upload on the configuration screen Finance › General Ledger › Chart of Accounts, approved by a second user
A7: Source | B7: Upload template of the configuration screen (the same columns, headers, mandatory flags and allowed values)
A8: Depends on | B8: D0-06 Chart of accounts →
A9: Progress | B9: Rows entered | C9: =SUMPRODUCT(((ROW($B$17:$B$517)>17)+($B$17<>"Migration Clearing")>0)*(LEN($B$17:$B$517&$C$17:$C$517&$D$17:$D$517&$E$17:$E$517&$F$17:$F$517)>0)) | D9: Mandatory cells missing | E9: =SUMPRODUCT(((ROW($B$17:$B$517)>17)+($B$17<>"Migration Clearing")>0)*(LEN($B$17:$B$517&$C$17:$C$517&$D$17:$D$517&$E$17:$E$517&$F$17:$F$517)>0)*(($B$17:$B$517="")+($D$17:$D$517="")))
A10: Confirmed by (BDOI owner) | D10: Date
A12: Mandatory | B12: Yes | C12: Conditional: Premium Receivable - Legacy | D12: Yes | E12: No | F12: No
A13: Format | B13: Code from the drop-down | C13: Text | D13: Text | E13: Account codes separated by commas | F13: Text
A14: Allowed values | B14: List Legacy account (D0-09): 8 values, see Reference lists | C14: Free entry | D14: Code of an existing account of the chart of accounts | E14: Free entry | F14: Free entry
A15: What to enter | B15: One row per account | C15: Component the account holds | D15: Account in the production chart | E15: The legacy accounts it replaces (code map gl account) | F15: End state after the run-off
A16: Row | B16: Legacy account * | C16: Component | D16: BIBS account code * | E16: Legacy GL accounts | F16: Remarks
A17: Example – overwrite or delete | B17: Migration Clearing | C17: Basic premium | D17: 1990.01 | E17: 1210-01 | F17: Nets to 0.00 after the opening

Sheet D0-15 Approval limits
A1: D0-15 Approval limits and matrices | J1: Step 32 of 52
A2: ← Back to Start here | B2: Step 32 of 52. Fill in one row per record below the column headers; the guide above each column says what to enter. | J2: Ask a question →
A3: Purpose | B3: The approval levels by amount, sum insured or segment of the modules that approve by level
A4: Provided by | B4: Owners of the modules; Head, Comptrollership for the amounts
A5: Due | B5: 16-Jul-2027 – Values for UAT
A6: How it is loaded | B6: Upload on the configuration screen Client & Policy › Submitted Policies › Submitted Policies Setup or Client & Policy › Employee Benefits › EB Setup, approved by a second user
A7: Source | B7: Upload template of the configuration screen (the same columns, headers, mandatory flags and allowed values)
A8: Depends on | B8: UA-02 Role-to-permission matrix → | D8: UA-01 Users and roles load →
A9: Approver role | B9: Give the permission that the approvers of the level hold (a permission of the role matrix UA-02, for example SBM_PROCESS), not a group profile: the upload checks the permission
A10: Refused rows | B10: Rows of the modules Sanction Screening and Disbursement are refused by the upload: the approval routes of Sanction Screening are set in a draft configuration version on Compliance Setup, and disbursements follow the authorisation limit of the user (UA-03). Give those values in a BDOI comment; the configuration team sets them on those screens
A11: Progress | B11: Rows entered | C11: =SUMPRODUCT(((ROW($B$19:$B$519)>19)+($B$19<>"Submitted Policies")>0)*(LEN($B$19:$B$519&$C$19:$C$519&$D$19:$D$519&$E$19:$E$519&$F$19:$F$519&$G$19:$G$519&$H$19:$H$519&$I$19:$I$519&$J$19:$J$519)>0)) | D11: Mandatory cells missing | E11: =SUMPRODUCT(((ROW($B$19:$B$519)>19)+($B$19<>"Submitted Policies")>0)*(LEN($B$19:$B$519&$C$19:$C$519&$D$19:$D$519&$E$19:$E$519&$F$19:$F$519&$G$19:$G$519&$H$19:$H$519&$I$19:$I$519&$J$19:$J$519)>0)*(($B$19:$B$519="")+($C$19:$C$519="")+($G$19:$G$519="")+($H$19:$H$519="")))
A12: Confirmed by (BDOI owner) | D12: Date
A14: Mandatory | B14: Yes | C14: Yes | D14: No | E14: No | F14: No | G14: Yes | H14: Yes | I14: No | J14: No
A15: Format | B15: Code from the drop-down | C15: Text | D15: Text | E15: Number without thousands separators, e.g. 1500000.50 | F15: Number without thousands separators, e.g. 1500000.50 | G15: Number without thousands separators, e.g. 1500000.50 | H15: Text | I15: Text | J15: Text
A16: Allowed values | B16: Submitted Policies, Employee Benefits, Sanction Screening, Disbursement (list Module (D0-15)) | C16: IAAF or Terms of reference; for Employee Benefits: Sum insured or Annual premium | D16: Free entry | E16: A number | F16: A number | G16: A whole number from 1 to 9 | H16: A permission of the role matrix (UA-02) | I16: A code of UA-01 Users and roles load, column User ID | J16: Free entry
A17: What to enter | B17: Module of the approval | C17: What is approved | D17: Segment or benefit line of the row | E17: Lower bound (sum insured, premium or amount) | F17: Upper bound; blank = no limit | G17: Order of the approval | H17: Permission held by the approvers of the level | I17: User ID, only when one person approves | J17: Title printed on the document
A18: Row | B18: Module * | C18: Document or transaction * | D18: Segment or case type | E18: From amount | F18: To amount | G18: Approval level * | H18: Approver role * | I18: Named approver | J18: Signatory title
A19: Example – overwrite or delete | B19: Submitted Policies | C19: Terms of reference | D19: CBG | E19: 0 | F19: 10000000 | G19: 1 | H19: SBM_PROCESS | J19: Unit Head, Combank

Sheet R07 Commission rates by insurer
A1: R07 Commission rates by insurer and product | G1: Step 33 of 52
A2: ← Back to Start here | B2: Step 33 of 52. Fill in one row per record below the column headers; the guide above each column says what to enter. | G2: Ask a question →
A3: Purpose | B3: One row per record of Commission rates by insurer and product as extracted from QPS, EBIX. Key insurer_code, risk_code, effective_from. Sent as the file R07_template.csv (CSV, header row as below) with its control file (row count, row count).
A4: Provided by | B4: Operations data steward (to name); approved by Head, Operations; extracted by BDOI IT
A5: Due | B5: M3 (29 Jan 2027)
A6: How it is loaded | B6: Migration Console: the file R07_template.csv (the header row as below) and its control file are received on Data Migration › Data Migration › Extracts and loaded by a batch of object R07; lands in: Commission rates of the product catalogue
A7: Source | B7: QPS, EBIX
A8: Depends on | B8: R04 Insurers → | D8: R05 Product lines, cover types, products and risk codes →
A9: Progress | B9: Rows entered | C9: =SUMPRODUCT(((ROW($B$18:$B$218)>18)+($B$18<>"MAL")>0)*(LEN($B$18:$B$218&$C$18:$C$218&$D$18:$D$218&$E$18:$E$218&$F$18:$F$218)>0)) | D9: Mandatory cells missing | E9: =SUMPRODUCT(((ROW($B$18:$B$218)>18)+($B$18<>"MAL")>0)*(LEN($B$18:$B$218&$C$18:$C$218&$D$18:$D$218&$E$18:$E$218&$F$18:$F$218)>0)*(($B$18:$B$218="")+($C$18:$C$218="")+($D$18:$D$218="")+($E$18:$E$218="")))
A10: Confirmed by (BDOI owner) | D10: Date
A12: Check when loaded | B12: Mapped | C12: Mapped | D12: 0 to 100 | E12: Valid date | F12: No overlap for the same insurer and product
A13: Mandatory | B13: Yes | C13: Yes | D13: Yes | E13: Yes | F13: No
A14: Format | B14: Code, up to 30; As stored in legacy | C14: Code, up to 20; As stored in legacy | D14: Decimal, up to 9,4; Dot decimal | E14: Date, up to 10; yyyy-MM-dd | F14: Date, up to 10; yyyy-MM-dd
A15: Allowed values | B15: The legacy code; mapped by the code map INSURER (Code Maps screen of the Data Migration Console; maps prepared in the Migration Workbook of BRD-13) | C15: The legacy code; mapped by the code map PRODUCT (Code Maps screen of the Data Migration Console; maps prepared in the Migration Workbook of BRD-13) | D15: A number | E15: Free entry | F15: Free entry
A16: What to enter | B16: Legacy insurer code | C16: Legacy product / risk code | D16: Commission rate in percent | E16: Rate valid from | F16: Rate valid to
A17: Row | B17: insurer_code * | C17: risk_code * | D17: rate_pct * | E17: effective_from * | F17: effective_to
A18: Example – overwrite or delete | B18: MAL | C18: MC-PC-COMP | D18: 20 | E18: 2026-01-01

Sheet TX-02 Tax forms
A1: TX-02 Tax forms and filing calendar | K1: Step 34 of 52
A2: ← Back to Start here | B2: Step 34 of 52. Fill in one row per record below the column headers; the guide above each column says what to enter. | K2: Ask a question →
A3: Purpose | B3: One row per tax return or remittance form BDOI files, with its frequency and due date, so that the tax calendar warns before each deadline and the return worksheets post to the right accounts. The forms BIBS knows are listed on the sheet D0-10 Tax checklist; BDOI confirms which apply to it as a broker.
A4: Provided by | B4: Head, Comptrollership (Tax)
A5: Due | B5: 16-Jul-2027 – Values for UAT
A6: How it is loaded | B6: Configuration screen: Finance › Tax & Statutory › Tax Codes & Forms (Forms panel), authorised by a second user
A7: Source | B7: BDOI tax calendar
A8: Depends on | B8: D0-06 Chart of accounts →
A9: Progress | B9: Rows entered | C9: =SUMPRODUCT(((ROW($B$17:$B$317)>17)+($B$17<>"2550Q")>0)*(LEN($B$17:$B$317&$C$17:$C$317&$D$17:$D$317&$E$17:$E$317&$F$17:$F$317&$G$17:$G$317&$H$17:$H$317&$I$17:$I$317&$J$17:$J$317&$K$17:$K$317)>0)) | D9: Mandatory cells missing | E9: =SUMPRODUCT(((ROW($B$17:$B$317)>17)+($B$17<>"2550Q")>0)*(LEN($B$17:$B$317&$C$17:$C$317&$D$17:$D$317&$E$17:$E$317&$F$17:$F$317&$G$17:$G$317&$H$17:$H$317&$I$17:$I$317&$J$17:$J$317&$K$17:$K$317)>0)*(($B$17:$B$317="")+($C$17:$C$317="")+($D$17:$D$317="")+($E$17:$E$317="")+($F$17:$F$317="")+($G$17:$G$317="")+($H$17:$H$317="")+($K$17:$K$317="")))
A10: Confirmed by (BDOI owner) | D10: Date
A12: Mandatory | B12: Yes | C12: Yes | D12: Yes | E12: Yes | F12: Yes | G12: Yes | H12: Yes | I12: No | J12: No | K12: Yes
A13: Format | B13: Up to 20 characters | C13: Text, up to 150 | D13: Code of the list | E13: Code of the list | F13: Code of the list | G13: Whole number | H13: 1 to 31 (31 = month end) | I13: Account of D0-06 | J13: Account of D0-06 | K13: dd-mmm-yyyy
A14: Allowed values | B14: Free entry, up to 20 characters | C14: Free entry, up to 150 characters | D14: BIR, LGU, BFP (list Tax authority) | E14: MONTHLY, QUARTERLY, MONTHLY_EXCEPT_QUARTER_END, ANNUAL (list Filing frequency) | F14: VAT, EWT, NONE (list Tax worksheet) | G14: A whole number from 0 to 12 | H14: A whole number from 1 to 31 | I14: A code of D0-06 Chart of accounts, column Account Code | J14: A code of D0-06 Chart of accounts, column Account Code | K14: A date, for example 15-Jan-2028
A15: What to enter | B15: BIR or local form number | C15: Name of the return | D15: Who the form is filed with | E15: How often the form is filed | F15: Computation worksheet behind the form (NONE: prepared outside BIBS, reminder only) | G15: Months after the end of the period in which the form is due | H15: Day of the month the form is due | I15: Account the tax payable is posted to | J15: Input VAT account credited against the output VAT (VAT return only) | K15: First period the filing is tracked
A16: Row | B16: Form code * | C16: Name * | D16: Authority * | E16: Frequency * | F16: Worksheet * | G16: Months after period end * | H16: Due day * | I16: Tax payable account | J16: Credit account | K16: Tracked from *
A17: Example – overwrite or delete | B17: 2550Q | C17: Quarterly VAT return | D17: BIR | E17: QUARTERLY | F17: VAT | G17: 0 | H17: 25 | K17: 46753

Sheet UA-03 Approval rules
A1: UA-03 Approvers, approval rules and limits | G1: Step 35 of 52
A2: ← Back to Start here | B2: Step 35 of 52. Fill in one row per record below the column headers; the guide above each column says what to enter. | G2: Ask a question →
A3: Purpose | B3: Who requests and who approves user access, the order of the approvers of group-profile requests, the second approvers, the implementers, and the authorisation limits of the users whose work other modules approve by amount
A4: Provided by | B4: Business Administration; BDOI Information Security for the second approval; Comptrollership for the authorisation limits
A5: Due | B5: 16-Jul-2027 – Values for UAT
A6: How it is loaded | B6: Upload on the configuration screen Setup & Administration › Administration › Users, approved by a second user
A7: Source | B7: Upload template of the configuration screen (the same columns, headers, mandatory flags and allowed values)
A8: Depends on | B8: UA-01 Users and roles load →
A9: Progress | B9: Rows entered | C9: =SUMPRODUCT(((ROW($B$17:$B$517)>17)+($B$17<>"Approver")>0)*(LEN($B$17:$B$517&$C$17:$C$517&$D$17:$D$517&$E$17:$E$517&$F$17:$F$517&$G$17:$G$517)>0)) | D9: Mandatory cells missing | E9: =SUMPRODUCT(((ROW($B$17:$B$517)>17)+($B$17<>"Approver")>0)*(LEN($B$17:$B$517&$C$17:$C$517&$D$17:$D$517&$E$17:$E$517&$F$17:$F$517&$G$17:$G$517)>0)*(($B$17:$B$517="")+($C$17:$C$517="")+($D$17:$D$517="")))
A10: Confirmed by (BDOI owner) | D10: Date
A12: Mandatory | B12: Yes | C12: Yes | D12: Yes | E12: Conditional: Approver | F12: No | G12: No
A13: Format | B13: Code from the drop-down | C13: Text | D13: Text | E13: Number without thousands separators, e.g. 1500000.50 | F13: Y or N | G13: Number without thousands separators, e.g. 1500000.50
A14: Allowed values | B14: Requestor, Approver, Second Approver, Group-profile requester, Implementer (list Role in user access (UA-03)) | C14: Code of an existing user | D14: Code of the list Business unit group (Lists of Values) | E14: A number | F14: Y or N | G14: A number
A15: What to enter | B15: The user access role of the user | C15: The user who holds the role | D15: Unit the user requests or approves for | E15: Usual order of the approvers of a group-profile request | F15: Must match uam any approver (changed with UA-05) | G15: Limit of the approvals of the user; blank = unlimited
A16: Row | B16: Role in user access * | C16: User ID * | D16: Unit * | E16: Approver order for group profiles | F16: Any approver may decide | G16: Authorisation limit
A17: Example – overwrite or delete | B17: Approver | C17: a013000205 | D17: Combank Marketing | E17: 1 | F17: N | G17: 500000

Sheet PM-02 Coverages and rules
A1: PM-02 Coverages, perils and field rules | J1: Step 36 of 52
A2: ← Back to Start here | B2: Step 36 of 52. Fill in one row per record below the column headers; the guide above each column says what to enter. | J2: Ask a question →
A3: Purpose | B3: The coverage and peril level of each line, and the fields and documents each product needs on an account
A4: Provided by | B4: MBS
A5: Due | B5: 16-Jul-2027 – Values for UAT
A6: How it is loaded | B6: Upload on the configuration screen Client & Policy › Product Maintenance › Coverages & Clauses or Client & Policy › Product Maintenance › Products, approved by a second user
A7: Source | B7: Upload template of the configuration screen (the same columns, headers, mandatory flags and allowed values)
A8: Depends on | B8: PM-09 Lists of values and parameters → | D8: PM-01 Product catalogue →
A9: Progress | B9: Rows entered | C9: =SUMPRODUCT(((ROW($B$17:$B$517)>17)+($B$17<>"COVERAGE")>0)*(LEN($B$17:$B$517&$C$17:$C$517&$D$17:$D$517&$E$17:$E$517&$F$17:$F$517&$G$17:$G$517&$H$17:$H$517&$I$17:$I$517&$J$17:$J$517)>0)) | D9: Mandatory cells missing | E9: =SUMPRODUCT(((ROW($B$17:$B$517)>17)+($B$17<>"COVERAGE")>0)*(LEN($B$17:$B$517&$C$17:$C$517&$D$17:$D$517&$E$17:$E$517&$F$17:$F$517&$G$17:$G$517&$H$17:$H$517&$I$17:$I$517&$J$17:$J$517)>0)*(($B$17:$B$517="")+($C$17:$C$517="")+($D$17:$D$517="")+($E$17:$E$517="")+($F$17:$F$517="")+($J$17:$J$517="")))
A10: Confirmed by (BDOI owner) | D10: Date
A12: Mandatory | B12: Yes | C12: Yes | D12: Yes | E12: Yes | F12: Yes | G12: Conditional: COVERAGE | H12: Conditional: List, range or format rules | I12: Conditional: DOCUMENT_RULE | J12: Yes
A13: Format | B13: Code from the drop-down | C13: Line or risk codes separated by commas | D13: Text | E13: Text | F13: Text | G13: Y or N | H13: Text | I13: Code from the drop-down | J13: Y or N
A14: Allowed values | B14: COVERAGE, FIELD_RULE, DOCUMENT_RULE (list Record (PM-02)) | C14: Codes of PM-01 Product catalogue, column Risk code (one or more) | D14: Free entry | E14: Free entry | F14: Section, Coverage, Peril, Extension; Presence, List of values, Number range, Format | G14: Y or N | H14: Free entry | I14: List Document type: 61 values, see Reference lists | J14: Y or N
A15: What to enter | B15: Coverage, field rule or document rule | C15: Line or product the row applies to; * = every product | D15: Coverage code, or field key of the rule | E15: Name of the coverage or label of the field | F15: Coverage kind, or check of the field rule | G15: Y when the coverage is basic | H15: List code; minimum and maximum; pattern | I15: Document type of a document rule | J15: Y when the field or document is mandatory
A16: Row | B16: Record * | C16: Line code / Risk code * | D16: Code or field key * | E16: Name or label * | F16: Kind or check * | G16: Basic | H16: Parameters | I16: Document type | J16: Mandatory *
A17: Example – overwrite or delete | B17: COVERAGE | C17: MOTOR | D17: OD_THEFT | E17: Own damage and theft | F17: Coverage | G17: Y | J17: Y

Sheet PM-03 Clause library
A1: PM-03 Clause library | G1: Step 37 of 52
A2: ← Back to Start here | B2: Step 37 of 52. Fill in one row per record below the column headers; the guide above each column says what to enter. | G2: Ask a question →
A3: Purpose | B3: Warranties, clauses, exclusions and deductible wordings used in the insurer terms of package versions
A4: Provided by | B4: TSU (wordings); MBS (maintenance)
A5: Due | B5: 16-Jul-2027 – Values for UAT
A6: How it is loaded | B6: Upload on the configuration screen Client & Policy › Product Maintenance › Coverages & Clauses, approved by a second user
A7: Source | B7: Upload template of the configuration screen (the same columns, headers, mandatory flags and allowed values)
A8: Depends on | B8: PM-09 Lists of values and parameters → | D8: PM-01 Product catalogue →
A9: Progress | B9: Rows entered | C9: =SUMPRODUCT(((ROW($B$17:$B$517)>17)+($B$17<>"FLEET_REPAIR")>0)*(LEN($B$17:$B$517&$C$17:$C$517&$D$17:$D$517&$E$17:$E$517&$F$17:$F$517&$G$17:$G$517)>0)) | D9: Mandatory cells missing | E9: =SUMPRODUCT(((ROW($B$17:$B$517)>17)+($B$17<>"FLEET_REPAIR")>0)*(LEN($B$17:$B$517&$C$17:$C$517&$D$17:$D$517&$E$17:$E$517&$F$17:$F$517&$G$17:$G$517)>0)*(($B$17:$B$517="")+($C$17:$C$517="")+($E$17:$E$517="")+($F$17:$F$517="")+($G$17:$G$517="")))
A10: Confirmed by (BDOI owner) | D10: Date
A12: Mandatory | B12: Yes | C12: Yes | D12: No | E12: Yes | F12: Yes | G12: Yes
A13: Format | B13: A-Z, 0-9 and _ | C13: Code from the drop-down | D13: Text | E13: Text | F13: Text | G13: dd-MMM-yyyy; dd-MMM-yyyy
A14: Allowed values | B14: Free entry | C14: WARRANTY, CLAUSE, EXCLUSION, DEDUCTIBLE_WORDING (list Clause kind) | D14: Code of an existing line | E14: Free entry | F14: Free entry | G14: Free entry
A15: What to enter | B15: Code of the clause | C15: Kind of the clause | D15: Line of the clause; blank = every line | E15: Title of the clause | F15: Full text | G15: First day; last day after a semicolon, blank = open
A16: Row | B16: Clause code * | C16: Kind * | D16: Line code | E16: Title * | F16: Wording * | G16: Effective from / to *
A17: Example – overwrite or delete | B17: FLEET_REPAIR | C17: CLAUSE | D17: MOTOR | E17: Accredited repair shops for fleets | F17: Repairs are made at the accredited shops of the insurer. | G17: 01-Jan-2027

Sheet C02 Client addresses and contac
A1: C02 Client addresses and contacts | N1: Step 38 of 52
A2: ← Back to Start here | B2: Step 38 of 52. Fill in one row per record below the column headers; the guide above each column says what to enter. | N2: Ask a question →
A3: Purpose | B3: One row per record of Client master (individual and corporate) as extracted from QPS, EBIX, CMS. Key legacy_client_no, record_type, seq_no. Sent as the file C02_template.csv (CSV, header row as below) with its control file (row count, row count).
A4: Provided by | B4: Marketing data steward (to name); approved by Product Owner, MBS; Heads, Retail and Corporate Marketing; extracted by BDOI IT
A5: Due | B5: M3 (29 Jan 2027); deltas daily from T-14 days
A6: How it is loaded | B6: Migration Console: the file C02_template.csv (the header row as below) and its control file are received on Data Migration › Data Migration › Extracts and loaded by a batch of object C01; lands in: Client master, registered as migrated clients
A7: Source | B7: QPS, EBIX, CMS
A8: Depends on | B8: C01 Client master →
A9: Progress | B9: Rows entered | C9: =SUMPRODUCT(((ROW($B$18:$B$218)>18)+($B$18<>"Q-0012345")>0)*(LEN($B$18:$B$218&$C$18:$C$218&$D$18:$D$218&$E$18:$E$218&$F$18:$F$218&$G$18:$G$218&$H$18:$H$218&$I$18:$I$218&$J$18:$J$218&$K$18:$K$218&$L$18:$L$218&$M$18:$M$218&$N$18:$N$218)>0)) | D9: Mandatory cells missing | E9: =SUMPRODUCT(((ROW($B$18:$B$218)>18)+($B$18<>"Q-0012345")>0)*(LEN($B$18:$B$218&$C$18:$C$218&$D$18:$D$218&$E$18:$E$218&$F$18:$F$218&$G$18:$G$218&$H$18:$H$218&$I$18:$I$218&$J$18:$J$218&$K$18:$K$218&$L$18:$L$218&$M$18:$M$218&$N$18:$N$218)>0)*(($B$18:$B$218="")+($C$18:$C$218="")+($D$18:$D$218="")+($N$18:$N$218="")))
A10: Confirmed by (BDOI owner) | D10: Date
A12: Check when loaded | B12: Exists in C01 of the same source | C12: In the list | D12: Unique per client and record type | E12: Mandatory for ADDRESS | F12: Mandatory for ADDRESS | G12: - | H12: - | I12: 4 digits | J12: Mandatory for CONTACT | K12: - | L12: Valid e-mail | M12: PH mobile format | N12: One primary ADDRESS per client
A13: Mandatory | B13: Yes | C13: Yes | D13: Yes | E13: Conditional: Mandatory for ADDRESS | F13: Conditional: Mandatory for ADDRESS | G13: No | H13: No | I13: No | J13: Conditional: Mandatory for CONTACT | K13: No | L13: No | M13: No | N13: Yes
A14: Format | B14: Code, up to 30; As stored in legacy | C14: Code, up to 10; Upper case | D14: Integer, up to 3; Digits | E14: Code, up to 12; Upper case | F14: Text, up to 300; Free text | G14: Text, up to 80; Free text | H14: Text, up to 80; Free text | I14: Text, up to 10; 4 digits | J14: Text, up to 200; Free text | K14: Text, up to 60; Free text | L14: Text, up to 120; name@domain | M14: Text, up to 30; 09xxxxxxxxx | N14: Flag, up to 1; Y or N
A15: Allowed values | B15: legacy_client_no of C01 | C15: ADDRESS, CONTACT (list C02 record_type) | D15: A whole number | E15: HOME, BUSINESS, MAILING, BILLING (list C02 address_type) | F15: Free entry, up to 300 characters | G15: Free entry, up to 80 characters | H15: Free entry, up to 80 characters | I15: Free entry, up to 10 characters | J15: Free entry, up to 200 characters | K15: Free entry, up to 60 characters | L15: Free entry, up to 120 characters | M15: Free entry, up to 30 characters | N15: Y or N
A16: What to enter | B16: Client number in the source system | C16: Address or contact person | D16: Sequence within the client and record type | E16: Kind of address | F16: Street address | G16: City / municipality | H16: Province | I16: Postal code | J16: Contact person (corporate clients) | K16: Role of the contact | L16: E-mail | M16: Mobile number | N16: Primary address or contact
A17: Row | B17: legacy_client_no * | C17: record_type * | D17: seq_no * | E17: address_type | F17: address_line | G17: city | H17: province | I17: postal_code | J17: contact_name | K17: contact_role | L17: email | M17: mobile | N17: primary_flag *
A18: Example – overwrite or delete | B18: Q-0012345 | C18: ADDRESS | D18: 1 | E18: MAILING | F18: 12 Rizal St., Brgy. San Antonio | G18: Pasig | H18: Metro Manila | I18: 1600 | J18: Jose Santos | K18: HR Manager | L18: jose.santos@acme.example | M18: 09181234567 | N18: Y

Sheet C03 Client payout accounts
A1: C03 Client payout accounts | G1: Step 39 of 52
A2: ← Back to Start here | B2: Step 39 of 52. Fill in one row per record below the column headers; the guide above each column says what to enter. | G2: Ask a question →
A3: Purpose | B3: One row per record of Client payout accounts (for refunds) as extracted from EBIX. Key legacy_client_no, account_no. Sent as the file C03_template.csv (CSV, header row as below) with its control file (row count, row count).
A4: Provided by | B4: Disbursement data steward (to name); approved by Product Owner, Comptrollership - Disbursement; extracted by BDOI IT
A5: Due | B5: M3 (29 Jan 2027)
A6: How it is loaded | B6: Migration Console: the file C03_template.csv (the header row as below) and its control file are received on Data Migration › Data Migration › Extracts and loaded by a batch of object C03; lands in: Client payout accounts
A7: Source | B7: EBIX
A8: Depends on | B8: C01 Client master →
A9: Progress | B9: Rows entered | C9: =SUMPRODUCT(((ROW($B$18:$B$218)>18)+($B$18<>"E-0098765")>0)*(LEN($B$18:$B$218&$C$18:$C$218&$D$18:$D$218&$E$18:$E$218&$F$18:$F$218&$G$18:$G$218)>0)) | D9: Mandatory cells missing | E9: =SUMPRODUCT(((ROW($B$18:$B$218)>18)+($B$18<>"E-0098765")>0)*(LEN($B$18:$B$218&$C$18:$C$218&$D$18:$D$218&$E$18:$E$218&$F$18:$F$218&$G$18:$G$218)>0)*(($B$18:$B$218="")+($C$18:$C$218="")+($D$18:$D$218="")+($G$18:$G$218="")))
A10: Confirmed by (BDOI owner) | D10: Date
A12: Check when loaded | B12: Client loaded | C12: In the list | D12: Not blank | E12: Mandatory for CTA; mapped | F12: Mandatory for CTA | G12: Y or N
A13: Mandatory | B13: Yes | C13: Yes | D13: Yes | E13: Conditional: Mandatory for CTA; mapped | F13: Conditional: Mandatory for CTA | G13: Yes
A14: Format | B14: Code, up to 30; As stored in legacy | C14: Code, up to 10; Upper case | D14: Text, up to 250; Free text | E14: Code, up to 30; As stored in legacy | F14: Text, up to 40; Digits | G14: Flag, up to 1; Y or N
A15: Allowed values | B15: legacy_client_no of C01 | C15: CTA, CHECK (list C03 mode) | D15: Free entry, up to 250 characters | E15: The legacy code; mapped by the code map BANK (Code Maps screen of the Data Migration Console; maps prepared in the Migration Workbook of BRD-13) | F15: Free entry, up to 40 characters | G15: Y or N
A16: What to enter | B16: Client number in the source system | C16: Payout mode | D16: Name on the account or check | E16: Bank of the account | F16: Account number | G16: Account in use
A17: Row | B17: legacy_client_no * | C17: mode * | D17: payee_name * | E17: bank_code | F17: account_no | G17: active_flag *
A18: Example – overwrite or delete | B18: E-0098765 | C18: CTA | D18: Ana C. Reyes | E18: BDO | F18: 001234567890 | G18: Y

Sheet D0-12 Check books
A1: D0-12 Check books | G1: Step 40 of 52
A2: ← Back to Start here | B2: Step 40 of 52. Fill in one row per record below the column headers; the guide above each column says what to enter. | G2: Ask a question →
A3: Purpose | B3: The check books in stock per bank account at go-live
A4: Provided by | B4: Treasury; Product Owner, Comptrollership - Disbursement
A5: Due | B5: 1-Nov-2027 – Production values before the dress rehearsal
A6: How it is loaded | B6: Upload on the configuration screen Finance › Disbursement › Bank Accounts and Checks, approved by a second user
A7: Source | B7: Upload template of the configuration screen (the same columns, headers, mandatory flags and allowed values)
A8: Depends on | B8: D0-11 Company bank accounts →
A9: Progress | B9: Rows entered | C9: =SUMPRODUCT(((ROW($B$17:$B$517)>17)+($B$17<>"BNK-CA-001")>0)*(LEN($B$17:$B$517&$C$17:$C$517&$D$17:$D$517&$E$17:$E$517&$F$17:$F$517)>0)) | D9: Mandatory cells missing | E9: =SUMPRODUCT(((ROW($B$17:$B$517)>17)+($B$17<>"BNK-CA-001")>0)*(LEN($B$17:$B$517&$C$17:$C$517&$D$17:$D$517&$E$17:$E$517&$F$17:$F$517)>0)*(($B$17:$B$517="")+($C$17:$C$517="")+($D$17:$D$517="")+($E$17:$E$517="")+($F$17:$F$517="")))
A10: Confirmed by (BDOI owner) | D10: Date
A12: Mandatory | B12: Yes | C12: Yes | D12: Yes | E12: Yes | F12: Yes
A13: Format | B13: Text | C13: Digits | D13: Digits | E13: Digits | F13: Date dd-MMM-yyyy, e.g. 15-Jan-2026
A14: Allowed values | B14: Code of an existing bank account | C14: Free entry | D14: Free entry | E14: Free entry | F14: A date, for example 15-Jan-2028
A15: What to enter | B15: Bank account of the book | C15: First check number of the book | D15: Last check number of the book | E15: Next check number to issue | F15: Date the book was received
A16: Row | B16: Bank account code * | C16: First check number * | D16: Last check number * | E16: Next check number * | F16: Received on *
A17: Example – overwrite or delete | B17: BNK-CA-001 | C17: 0001001 | D17: 0001100 | E17: 0001001 | F17: 46722

Sheet D0-13 Petty cash funds
A1: D0-13 Petty cash funds | I1: Step 41 of 52
A2: ← Back to Start here | B2: Step 41 of 52. Fill in one row per record below the column headers; the guide above each column says what to enter. | I2: Ask a question →
A3: Purpose | B3: The petty cash funds of the branches
A4: Provided by | B4: Head, Comptrollership
A5: Due | B5: 1-Nov-2027 – Production values before the dress rehearsal
A6: How it is loaded | B6: Upload on the configuration screen Finance › Payables & Cash › Petty Cash, approved by a second user
A7: Source | B7: Upload template of the configuration screen (the same columns, headers, mandatory flags and allowed values)
A8: Depends on | B8: D0-02 Branches → | D8: D0-05 Employees → | E8: D0-06 Chart of accounts → | G8: D0-11 Company bank accounts →
A9: Progress | B9: Rows entered | C9: =SUMPRODUCT(((ROW($B$17:$B$517)>17)+($B$17<>"HO")>0)*(LEN($B$17:$B$517&$C$17:$C$517&$D$17:$D$517&$E$17:$E$517&$F$17:$F$517&$G$17:$G$517&$H$17:$H$517&$I$17:$I$517)>0)) | D9: Mandatory cells missing | E9: =SUMPRODUCT(((ROW($B$17:$B$517)>17)+($B$17<>"HO")>0)*(LEN($B$17:$B$517&$C$17:$C$517&$D$17:$D$517&$E$17:$E$517&$F$17:$F$517&$G$17:$G$517&$H$17:$H$517&$I$17:$I$517)>0)*(($B$17:$B$517="")+($C$17:$C$517="")+($D$17:$D$517="")+($E$17:$E$517="")+($F$17:$F$517="")+($G$17:$G$517="")+($H$17:$H$517="")+($I$17:$I$517="")))
A10: Confirmed by (BDOI owner) | D10: Date
A12: Mandatory | B12: Yes | C12: Yes | D12: Yes | E12: Yes | F12: Yes | G12: Yes | H12: Yes | I12: Yes
A13: Format | B13: Text | C13: Text | D13: Text | E13: Text | F13: Text | G13: Text | H13: Text | I13: Number without thousands separators, e.g. 1500000.50
A14: Allowed values | B14: Code of an existing branch | C14: Free entry | D14: Free entry | E14: Code of an existing employee | F14: Code of an existing account of the chart of accounts | G14: Code of an existing bank account | H14: Free entry | I14: A number
A15: What to enter | B15: Branch of the fund | C15: Code of the fund | D15: Name of the fund | E15: Employee number of the custodian | F15: Account of the fund | G15: Bank account that replenishes the fund | H15: Currency of the fund | I15: Amount of the fund
A16: Row | B16: Branch code * | C16: Fund code * | D16: Name * | E16: Custodian * | F16: GL account * | G16: Replenishment bank account * | H16: Currency * | I16: Imprest amount *
A17: Example – overwrite or delete | B17: HO | C17: PCF-HO | D17: Head Office petty cash | E17: 1203344 | F17: 1101.01 | G17: BNK-CA-001 | H17: PHP | I17: 20000

Sheet D0-14 Statement layouts
A1: D0-14 Bank statement layouts | K1: Step 42 of 52
A2: ← Back to Start here | B2: Step 42 of 52. Fill in one row per record below the column headers; the guide above each column says what to enter. | K2: Ask a question →
A3: Purpose | B3: The columns of the statement file of each bank account
A4: Provided by | B4: Head, Comptrollership; Treasury
A5: Due | B5: 16-Jul-2027 – Values for UAT
A6: How it is loaded | B6: Upload on the configuration screen Setup & Administration › Setup › Bank Statement Layouts, approved by a second user
A7: Source | B7: Upload template of the configuration screen (the same columns, headers, mandatory flags and allowed values)
A8: Depends on | B8: D0-11 Company bank accounts →
A9: Progress | B9: Rows entered | C9: =SUMPRODUCT(((ROW($B$17:$B$517)>17)+($B$17<>"BNK-CA-001")>0)*(LEN($B$17:$B$517&$C$17:$C$517&$D$17:$D$517&$E$17:$E$517&$F$17:$F$517&$G$17:$G$517&$H$17:$H$517&$I$17:$I$517&$J$17:$J$517&$K$17:$K$517)>0)) | D9: Mandatory cells missing | E9: =SUMPRODUCT(((ROW($B$17:$B$517)>17)+($B$17<>"BNK-CA-001")>0)*(LEN($B$17:$B$517&$C$17:$C$517&$D$17:$D$517&$E$17:$E$517&$F$17:$F$517&$G$17:$G$517&$H$17:$H$517&$I$17:$I$517&$J$17:$J$517&$K$17:$K$517)>0)*(($B$17:$B$517="")+($C$17:$C$517="")+($D$17:$D$517="")+($E$17:$E$517="")+($K$17:$K$517="")))
A10: Confirmed by (BDOI owner) | D10: Date
A12: Mandatory | B12: Yes | C12: Yes | D12: Yes | E12: Yes | F12: No | G12: No | H12: No | I12: No | J12: No | K12: Yes
A13: Format | B13: Text | C13: Text | D13: Column header or number | E13: Column header or number | F13: Column header or number | G13: Column header or number | H13: Column header or number | I13: Column header or number | J13: Column header or number | K13: For example dd/MM/yyyy
A14: Allowed values | B14: Code of an existing bank account | C14: Free entry | D14: Free entry | E14: Free entry | F14: Free entry | G14: Free entry | H14: Free entry | I14: Free entry | J14: Free entry | K14: Free entry
A15: What to enter | B15: Bank account of the statements | C15: Name of the layout | D15: Column of the posting date | E15: Column of the description | F15: Column of the reference | G15: Column of the debits | H15: Column of the credits | I15: Column of a signed amount, instead of debit and credit | J15: Column of the balance | K15: How the bank writes dates
A16: Row | B16: Bank account code * | C16: Layout name * | D16: Date column * | E16: Description column * | F16: Reference column | G16: Debit column | H16: Credit column | I16: Amount column | J16: Balance column | K16: Date format *
A17: Example – overwrite or delete | B17: BNK-CA-001 | C17: Bank CSV statement | D17: Posting Date | E17: Description | F17: Reference No. | G17: Debit | H17: Credit | J17: Balance | K17: MM/dd/yyyy

Sheet G01 GL opening trial balance
A1: G01 GL opening trial balance | L1: Step 43 of 52
A2: ← Back to Start here | B2: Step 43 of 52. Fill in one row per record below the column headers; the guide above each column says what to enter. | L2: Ask a question →
A3: Purpose | B3: One row per record of GL trial balance per account, branch and currency (provisional opening; legacy TB at each true-up) as extracted from EBIX GL, ISYS GL. Key tb_version, branch_code, currency, legacy_account_code, cost_center. Sent as the file G01_template.csv (CSV, header row as below) with its control file (row count, row count; amount totals per currency: debit_fc, credit_fc, debit_php, credit_php).
A4: Provided by | B4: Comptrollership data steward (to name); approved by Head, Comptrollership; extracted by BDOI IT
A5: Due | B5: M3 (29 Jan 2027); final at T-2; at each true-up
A6: How it is loaded | B6: Migration Console: the file G01_template.csv (the header row as below) and its control file are received on Data Migration › Data Migration › Extracts and loaded by a batch of object G01; lands in: General ledger journals of type OPENING (value date 1-Jan-2028); at a true-up, reconciliation input only
A7: Source | B7: EBIX GL, ISYS GL
A8: Depends on | B8: R08 Chart of accounts mapping → | D8: D0-02 Branches →
A9: Progress | B9: Rows entered | C9: =SUMPRODUCT(((ROW($B$18:$B$218)>18)+($B$18<>"PROVISIONAL")>0)*(LEN($B$18:$B$218&$C$18:$C$218&$D$18:$D$218&$E$18:$E$218&$F$18:$F$218&$G$18:$G$218&$H$18:$H$218&$I$18:$I$218&$J$18:$J$218&$K$18:$K$218&$L$18:$L$218)>0)) | D9: Mandatory cells missing | E9: =SUMPRODUCT(((ROW($B$18:$B$218)>18)+($B$18<>"PROVISIONAL")>0)*(LEN($B$18:$B$218&$C$18:$C$218&$D$18:$D$218&$E$18:$E$218&$F$18:$F$218&$G$18:$G$218&$H$18:$H$218&$I$18:$I$218&$J$18:$J$218&$K$18:$K$218&$L$18:$L$218)>0)*(($B$18:$B$218="")+($C$18:$C$218="")+($D$18:$D$218="")+($E$18:$E$218="")+($F$18:$F$218="")+($H$18:$H$218="")+($I$18:$I$218="")+($J$18:$J$218="")+($K$18:$K$218="")))
A10: Confirmed by (BDOI owner) | D10: Date
A12: Check when loaded | B12: In the list; one version per file | C12: One date in the file | D12: Mapped | E12: Valid code | F12: Mapped | G12: Mapped | H12: 0 or more; debit or credit, not both | I12: 0 or more | J12: 0 or more | K12: 0 or more | L12: Mandatory when currency is not PHP
A13: Mandatory | B13: Yes | C13: Yes | D13: Yes | E13: Yes | F13: Yes | G13: No | H13: Yes | I13: Yes | J13: Yes | K13: Yes | L13: Conditional: Mandatory when currency is not PHP
A14: Format | B14: Code, up to 12; Upper case | C14: Date, up to 10; yyyy-MM-dd | D14: Code, up to 20; As stored in legacy | E14: Code, up to 3; Upper case | F14: Code, up to 30; As stored in legacy | G14: Code, up to 20; As stored in legacy | H14: Amount, up to 19,2; Dot decimal, 2 decimals | I14: Amount, up to 19,2; Dot decimal, 2 decimals | J14: Amount, up to 19,2; Dot decimal, 2 decimals | K14: Amount, up to 19,2; Dot decimal, 2 decimals | L14: Decimal, up to 12,6; Dot decimal
A15: Allowed values | B15: PROVISIONAL, TU1, TU2, TU3, FINAL (list G01 tb_version) | C15: Free entry | D15: The legacy code; mapped by the code map BRANCH (Code Maps screen of the Data Migration Console; maps prepared in the Migration Workbook of BRD-13) | E15: ISO 4217 | F15: The legacy code; mapped by the code map GL_ACCOUNT (Code Maps screen of the Data Migration Console; maps prepared in the Migration Workbook of BRD-13) | G15: The legacy code; mapped by the code map COST_CENTER (Code Maps screen of the Data Migration Console; maps prepared in the Migration Workbook of BRD-13) | H15: A number | I15: A number | J15: A number | K15: A number | L15: A number
A16: What to enter | B16: Version of the trial balance - PROVISIONAL at cut-over (preliminary December TB), then TU1, TU2... and FINAL (audited) at the true-ups | C16: Trial balance date - 31-Dec-2027 for every version; the version says which adjustments it includes | D16: Branch | E16: Account currency | F16: Legacy account | G16: Cost centre | H16: Debit balance in the account currency | I16: Credit balance in the account currency | J16: Debit balance in PHP | K16: Credit balance in PHP | L16: Rate used for the PHP amount
A17: Row | B17: tb_version * | C17: as_of_date * | D17: branch_code * | E17: currency * | F17: legacy_account_code * | G17: cost_center | H17: debit_fc * | I17: credit_fc * | J17: debit_php * | K17: credit_php * | L17: fx_rate
A18: Example – overwrite or delete | B18: PROVISIONAL | C18: 2027-12-31 | D18: MKT01 | E18: USD | F18: 1101-02 | G18: 4100 | H18: 12500 | I18: 0 | J18: 701562.5 | K18: 0 | L18: 56.125

Sheet PM-04 Rate tables
A1: PM-04 Rate tables | H1: Step 44 of 52
A2: ← Back to Start here | B2: Step 44 of 52. Fill in one row per record below the column headers; the guide above each column says what to enter. | H2: Ask a question →
A3: Purpose | B3: Statutory charges and rating factors, the short-period table and the motor BI / PD limit premiums
A4: Provided by | B4: Product Owner, MBS; Comptrollership (taxes)
A5: Due | B5: 16-Jul-2027 – Values for UAT
A6: How it is loaded | B6: Upload on the configuration screen Client & Policy › Product Maintenance › Rates & Taxes, approved by a second user
A7: Source | B7: Upload template of the configuration screen (the same columns, headers, mandatory flags and allowed values)
A8: Depends on | B8: PM-01 Product catalogue →
A9: Checklist | B9: One row per premium charge is written below the header (DST, premium tax, VAT on premium, fire service tax, VAT on commission and the motor factors); complete the rate per line and the dates, and add a row per line where the rate differs. The rules BIBS applies are on the sheet PM-04 Charges checklist
A10: LGT | B10: The local government tax is not kept here: it is the rate of each insurer branch, column lgt_rate of template R04B
A11: Other charges | B11: The charges billed besides these taxes (authentication, notarial or documentation fees) are given in template PM-04C, uploaded on the same screen
A12: Progress | B12: Rows entered | C12: =SUMPRODUCT(((ROW($B$20:$B$520)>20)+($B$20<>"TAX")>0)*(LEN($B$20:$B$520&$C$20:$C$520&$D$20:$D$520&$E$20:$E$520&$F$20:$F$520&$G$20:$G$520&$H$20:$H$520)>0)) | D12: Mandatory cells missing | E12: =SUMPRODUCT(((ROW($B$20:$B$520)>20)+($B$20<>"TAX")>0)*(LEN($B$20:$B$520&$C$20:$C$520&$D$20:$D$520&$E$20:$E$520&$F$20:$F$520&$G$20:$G$520&$H$20:$H$520)>0)*(($B$20:$B$520="")+($H$20:$H$520="")))
A13: Confirmed by (BDOI owner) | D13: Date
A15: Mandatory | B15: Yes | C15: Conditional: TAX | D15: No | E15: Conditional: TAX, SHORT_PERIOD | F15: Conditional: SHORT_PERIOD | G15: Conditional: MOTOR_LIMIT | H15: Yes
A16: Format | B16: Code from the drop-down | C16: Code from the drop-down | D16: Text | E16: Text | F16: Text | G16: BI; 100000.00; 350.00 | H16: dd-MMM-yyyy; dd-MMM-yyyy
A17: Allowed values | B17: TAX, SHORT_PERIOD, MOTOR_LIMIT (list Table (PM-04)) | C17: List Premium charge or rating factor (BIBS): 7 values, see Reference lists | D17: Code of an existing line | E17: Free entry | F17: Free entry | G17: Free entry | H17: Free entry
A18: What to enter | B18: Rate table of the row | C18: Premium charge or rating factor | D18: Line of the rate; blank = every line | E18: Up to four decimals, 0 to 100 | F18: Months covered, 1 to 12 | G18: BI or PD; limit; premium | H18: First day; last day after a semicolon, blank = open
A19: Row | B19: Table * | C19: Rate | D19: Line code | E19: Rate % | F19: Months covered | G19: Coverage / Limit / Premium | H19: Effective from / to *
A20: Example – overwrite or delete | B20: TAX | C20: DST | E20: 12.5 | H20: 01-Jan-2028
B21: TAX | C21: DST
B22: TAX | C22: PREMIUM_TAX
B23: TAX | C23: VAT_PREMIUM
B24: TAX | C24: FIRE_SERVICE_TAX
B25: TAX | C25: VAT_COMMISSION
B26: TAX | C26: MOTOR_OD_ANNUAL
B27: TAX | C27: MOTOR_OD_MULTI_YEAR

Sheet PM-04 Charges checklist
A1: PM-04 Charges checklist: premium charges billed to clients
A2: ← Back to Start here | B2: One row per charge: how BIBS computes it, where its rate is given and what BDOI confirms (rates per line in PM-04, other charges in PM-04C, LGT per insurer branch in R04B)
A4: Charge | B4: What BIBS does | C4: Where it is set up | D4: What BDOI provides or confirms | E4: Held by BIBS | F4: Question | G4: Rule confirmed | H4: BDOI comments | I4: Status
A5: Documentary stamp tax (DST) | B5: Rate % of the net (basic) premium of the line. The tax is rounded to centavos and then up to the next half peso: .01 to .49 becomes .50, .51 to .99 the next peso, .00 and .50 stay; a refund is rounded the same way. | C5: PM-04, Rate DST (per line, or blank line = every line) | D5: The DST rate per line, confirmation of the net premium as the basis and of the half-peso rounding, and the lines or clients exempt from DST | E5: Yes | F5: TX-Q01 | I5: Not started
A6: Premium tax | B6: Rate % of the net premium of the line, rounded to centavos. BIBS applies it per product line; when the insurer's tax status is set, a VAT-registered insurer bills no premium tax and an insurer not VAT-registered bills premium tax instead of VAT. | C6: PM-04, Rate PREMIUM_TAX (per line); tax status of the insurer on the insurer screen | D6: The lines on which premium tax is billed instead of VAT, the rate, and the tax status of each insurer | E6: Yes | F6: TX-Q02 | I6: Not started
A7: VAT on premium | B7: Rate % of the net premium of the line, rounded to centavos. The charge follows the line, unless the insurer's tax status is set: a VAT-registered insurer bills VAT and no premium tax, an insurer not VAT-registered bills premium tax and no VAT. A zero-rated or exempt client is classified on the VAT worksheet by its VAT treatment (TX-01). | C7: PM-04, Rate VAT_PREMIUM (per line); tax status of the insurer on the insurer screen | D7: The VAT rate per line, the lines that are VAT-exempt or zero-rated, and the tax status of each insurer | E7: Yes | F7: TX-Q02 | I7: Not started
A8: Fire service tax (FST) | B8: Rate % of the net premium of the lines it is set for, rounded to centavos. | C8: PM-04, Rate FIRE_SERVICE_TAX (fire lines) | D8: The fire lines that carry FST, the rate and the basis | E8: Yes | F8: TX-Q01 | I8: Not started
A9: Local government tax (LGT) | B9: Rate % of the net premium at the rate of the insurer branch that places the policy, rounded to centavos. BIBS keeps no rate per local government unit. | C9: R04B, column lgt_rate of each insurer branch | D9: The LGT rate of each insurer branch and the ordinance basis of the LGU behind it | E9: Yes | F9: TX-Q03 | I9: Not started
A10: VAT on BDOI's commission | B10: Rate % of the commission (commission rate x net premium), rounded to centavos. | C10: PM-04, Rate VAT_COMMISSION | D10: The VAT rate on commission and the cases where it is zero-rated or exempt | E10: Yes | F10: TX-Q05 | I10: Not started
A11: Motor own damage / theft coverage factors | B11: Percent of the sum insured taken as the own damage / theft coverage: one factor for annual cover, one for multi-year cover. | C11: PM-04, Rates MOTOR_OD_ANNUAL and MOTOR_OD_MULTI_YEAR | D11: The two factors | E11: Yes | F11: TX-Q01 | I11: Not started
A12: Short-period table and motor BI / PD limit premiums | B12: Short period: percent of the annual premium by months covered; motor BI / PD: premium per limit. | C12: PM-04, Tables SHORT_PERIOD and MOTOR_LIMIT | D12: The short-period table and the limit premiums | E12: Yes | F12: TX-Q01 | I12: Not started
A13: Order | B13: basis | C13: minimum and rounding of the charges | D13: Every charge is computed on the net premium after the minimum premium, independently of the others (no charge on another charge); gross premium = net premium + all charges; no minimum amount per charge; every amount rounded to centavos half-up except DST (half peso). | E13: Fixed in BIBS (no column) | F13: Confirmation of the rules, or the basis, order, minimum or rounding BDOI applies | I13: Not started
A14: CTPL COCAF / LTO authentication fee | B14: Other charge of PM-04C: a fixed amount or a rate of the net premium per line or product, with its VAT treatment and GL account; billed only while the system parameter Other charges enabled is on. | C14: PM-04C (one row per charge and line or product) | D14: Whether BIBS bills it, its amount, VAT treatment and account | E14: Yes | F14: TX-Q04 | I14: Not started
A15: Notarial fee | B15: Other charge of PM-04C, as above. | C15: PM-04C | D15: Whether BIBS bills it, its amount, VAT treatment and account | E15: Yes | F15: TX-Q04 | I15: Not started
A16: Policy or documentation fee | B16: Other charge of PM-04C, as above. | C16: PM-04C | D16: Whether BIBS bills it, its amount, VAT treatment and account | E16: Yes | F16: TX-Q04 | I16: Not started
A17: Any other charge BDOI bills | B17: Other charge of PM-04C, as above. | C17: PM-04C | D17: The charge, its basis, amount, VAT treatment and account | E17: Yes | F17: TX-Q04 | I17: Not started

Sheet PM-04C Other charges
A1: PM-04C Other charges billed with the premium | J1: Step 45 of 52
A2: ← Back to Start here | B2: Step 45 of 52. Fill in one row per record below the column headers; the guide above each column says what to enter. | J2: Ask a question →
A3: Purpose | B3: One row per charge billed to clients with the premium besides the taxes of PM-04 (for example the CTPL COCAF / LTO authentication fee, a notarial fee, a policy or documentation fee), per line or product (blank = every product): a fixed amount or a rate of the net premium, its VAT treatment, the GL account it is credited to and its validity. BIBS bills these charges only while the system parameter Other charges enabled is on; it is delivered off until BDOI confirms which charges BIBS bills (question TX-Q04).
A4: Provided by | B4: Product Owner, MBS; Head, Comptrollership (charges and accounts)
A5: Due | B5: 16-Jul-2027 – Values for UAT
A6: How it is loaded | B6: Upload on the configuration screen Client & Policy › Product Maintenance › Rates & Taxes, approved by a second user
A7: Source | B7: Upload template of the configuration screen (the same columns, headers, mandatory flags and allowed values)
A8: Depends on | B8: PM-01 Product catalogue → | D8: D0-06 Chart of accounts →
A9: Switch | B9: The charges are billed only while the system parameter Other charges enabled is on (delivered off until BDOI confirms, question TX-Q04)
A10: Progress | B10: Rows entered | C10: =SUMPRODUCT(((ROW($B$18:$B$318)>18)+($B$18<>"NOTARIAL_FEE")>0)*(LEN($B$18:$B$318&$C$18:$C$318&$D$18:$D$318&$E$18:$E$318&$F$18:$F$318&$G$18:$G$318&$H$18:$H$318&$I$18:$I$318&$J$18:$J$318)>0)) | D10: Mandatory cells missing | E10: =SUMPRODUCT(((ROW($B$18:$B$318)>18)+($B$18<>"NOTARIAL_FEE")>0)*(LEN($B$18:$B$318&$C$18:$C$318&$D$18:$D$318&$E$18:$E$318&$F$18:$F$318&$G$18:$G$318&$H$18:$H$318&$I$18:$I$318&$J$18:$J$318)>0)*(($B$18:$B$318="")+($C$18:$C$318="")+($F$18:$F$318="")+($G$18:$G$318="")+($H$18:$H$318="")+($I$18:$I$318="")+($J$18:$J$318="")))
A11: Confirmed by (BDOI owner) | D11: Date
A13: Mandatory | B13: Yes | C13: Yes | D13: No | E13: No | F13: Yes | G13: Yes | H13: Yes | I13: Yes | J13: Yes
A14: Format | B14: Up to 30 capitals | C14: Text | D14: Text | E14: Text | F14: Code from the drop-down | G14: Number without thousands separators, e.g. 1500000.50 | H14: Code from the drop-down | I14: Text | J14: dd-MMM-yyyy; dd-MMM-yyyy
A15: Allowed values | B15: Free entry | C15: Free entry | D15: Code of an existing line | E15: Code of an existing product | F15: AMOUNT, RATE (list Basis (PM-04C)) | G15: A number | H15: VATABLE, EXEMPT, ZERO_RATED (list VAT treatment (PM-04C)) | I15: Code of an existing account of the chart of accounts | J15: Free entry
A16: What to enter | B16: Code of the charge | C16: Name on the invoice | D16: Line of the charge; blank = every line | E16: Product of the charge; blank = every product | F16: Fixed amount or rate of the net premium | G16: Amount, or rate from 0 to 100 | H16: VAT treatment of the charge | I16: Postable account the charge is credited to | J16: First day; last day after a semicolon, blank = open
A17: Row | B17: Charge code * | C17: Name * | D17: Line code | E17: Product code | F17: Basis * | G17: Amount or rate % * | H17: VAT treatment * | I17: GL account * | J17: Effective from / to *
A18: Example – overwrite or delete | B18: NOTARIAL_FEE | C18: Notarial fee | D18: MOTOR | F18: AMOUNT | G18: 150 | H18: VATABLE | I18: 4190 | J18: 01-Jan-2028

Sheet PM-10 Incentive criteria
A1: PM-10 Incentive criteria | G1: Step 46 of 52
A2: ← Back to Start here | B2: Step 46 of 52. Fill in one row per record below the column headers; the guide above each column says what to enter. | G2: Ask a question →
A3: Purpose | B3: The incentive criteria (for example CPC2) with their value, the products matrix and the effective dates
A4: Provided by | B4: Incentive Maintenance user (MBS); Comptrollership (CPC2 definition, PQ04)
A5: Due | B5: 16-Jul-2027 – Values for UAT
A6: How it is loaded | B6: Upload on the configuration screen Client & Policy › Product Maintenance › Incentive Criteria, approved by a second user
A7: Source | B7: Upload template of the configuration screen (the same columns, headers, mandatory flags and allowed values)
A8: Depends on | B8: PM-09 Lists of values and parameters → | C8: PM-01 Product catalogue →
A9: Progress | B9: Rows entered | C9: =SUMPRODUCT(((ROW($B$17:$B$517)>17)+($B$17<>"CPC2; CPC2 campaign 2028")>0)*(LEN($B$17:$B$517&$C$17:$C$517&$D$17:$D$517&$E$17:$E$517&$F$17:$F$517&$G$17:$G$517)>0)) | D9: Mandatory cells missing | E9: =SUMPRODUCT(((ROW($B$17:$B$517)>17)+($B$17<>"CPC2; CPC2 campaign 2028")>0)*(LEN($B$17:$B$517&$C$17:$C$517&$D$17:$D$517&$E$17:$E$517&$F$17:$F$517&$G$17:$G$517)>0)*(($B$17:$B$517="")+($C$17:$C$517="")+($D$17:$D$517="")+($F$17:$F$517="")+($G$17:$G$517="")))
A10: Confirmed by (BDOI owner) | D10: Date
A12: Mandatory | B12: Yes | C12: Yes | D12: Yes | E12: No | F12: Yes | G12: Yes
A13: Format | B13: A-Z, 0-9, _ and -; text | C13: Code from the drop-down | D13: Text | E13: Text | F13: One product per line | G13: dd-MMM-yyyy; dd-MMM-yyyy
A14: Allowed values | B14: Free entry | C14: OTHERS, MIGRATED (list Incentive type) | D14: Free entry | E14: Free entry | F14: Codes of PM-01 Product catalogue, column Risk code (one or more) | G14: Free entry
A15: What to enter | B15: Code; name | C15: Incentive type | D15: Rate (%), Fixed amount or Rule; value | E15: Parameter and value pairs separated by semicolons | F15: Risk code; market segment (blank = every segment) | G15: First day; last day after a semicolon, blank = open
A16: Row | B16: Code / Name * | C16: Incentive type * | D16: Value basis / Value * | E16: Rule parameters | F16: Products matrix: risk code / segment * | G16: Effective from / to *
A17: Example – overwrite or delete | B17: CPC2; CPC2 campaign 2028 | C17: OTHERS | D17: Rate (%); 1.00 | E17: Minimum Gross Premium 5000 | F17: MTR30; COMBANK | G17: 01-Jan-2028

Sheet TX-01 Party tax profiles
A1: TX-01 Party tax profiles (clients, insurers, payees) | S1: Step 47 of 52
A2: ← Back to Start here | B2: Step 47 of 52. Fill in one row per record below the column headers; the guide above each column says what to enter. | S2: Ask a question →
A3: Purpose | B3: One row per client, insurer, intermediary or payee whose tax details BIBS uses on the BIR forms, the 2307 certificates, the alphalists and the VAT classification of sales: the registered TIN and branch code, the payee class, the registered name and address, the VAT treatment and the default ATC withheld. The party code is the code of the client (C01 or the client upload), insurer (R04), business partner (MD-01) or payee (UP-02).
A4: Provided by | B4: Head, Comptrollership (Tax)
A5: Due | B5: 16-Jul-2027 – Values for UAT
A6: How it is loaded | B6: Configuration screen: Finance › Tax & Statutory › Party Tax Profiles, authorised by a second user
A7: Source | B7: BIR registrations (COR) of the parties; client KYC files
A8: Depends on | B8: D0-10 Tax codes → | D8: R04 Insurers → | F8: C01 Client master → | G8: MD-01 Business partners (reinsurers, intermediaries, suppliers) → | I8: UP-02 Payees →
A9: Tax status | B9: Withholding agent, top withholding agent, government payor and the tax exemption certificate with its validity are kept in the profile; a top withholding agent or a government payor is always a withholding agent
A10: Progress | B10: Rows entered | C10: =SUMPRODUCT(((ROW($B$18:$B$318)>18)+($B$18<>"C-000101")>0)*(LEN($B$18:$B$318&$C$18:$C$318&$D$18:$D$318&$E$18:$E$318&$F$18:$F$318&$G$18:$G$318&$H$18:$H$318&$I$18:$I$318&$J$18:$J$318&$K$18:$K$318&$L$18:$L$318&$M$18:$M$318&$N$18:$N$318&$O$18:$O$318&$P$18:$P$318&$Q$18:$Q$318&$R$18:$R$318&$S$18:$S$318)>0)) | D10: Mandatory cells missing | E10: =SUMPRODUCT(((ROW($B$18:$B$318)>18)+($B$18<>"C-000101")>0)*(LEN($B$18:$B$318&$C$18:$C$318&$D$18:$D$318&$E$18:$E$318&$F$18:$F$318&$G$18:$G$318&$H$18:$H$318&$I$18:$I$318&$J$18:$J$318&$K$18:$K$318&$L$18:$L$318&$M$18:$M$318&$N$18:$N$318&$O$18:$O$318&$P$18:$P$318&$Q$18:$Q$318&$R$18:$R$318&$S$18:$S$318)>0)*(($B$18:$B$318="")+($C$18:$C$318="")+($E$18:$E$318="")+($F$18:$F$318="")))
A11: Confirmed by (BDOI owner) | D11: Date
A13: Mandatory | B13: Yes | C13: Yes | D13: No | E13: Yes | F13: Yes | G13: Conditional: individuals | H13: Conditional: individuals | I13: No | J13: No | K13: No | L13: No | M13: No | N13: No | O13: No | P13: No | Q13: No | R13: Conditional: certificate number given | S13: Conditional: certificate number given
A14: Format | B14: Text, up to 30 | C14: Digits and dashes, up to 20 | D14: Up to 5 digits | E14: Code of the list | F14: Text, up to 200 | G14: Text, up to 60 | H14: Text, up to 60 | I14: Text, up to 60 | J14: Text, up to 300 | K14: Up to 10 characters | L14: Code of the list | M14: Tax code of D0-10 | N14: Y or N (blank = N) | O14: Y or N (blank = N) | P14: Y or N (blank = N) | Q14: Text, up to 40 | R14: dd-mmm-yyyy | S14: dd-mmm-yyyy
A15: Allowed values | B15: Free entry, up to 30 characters | C15: Free entry, up to 20 characters | D15: Free entry, up to 5 characters | E15: INDIVIDUAL, CORPORATE (list Payee class (BIR)) | F15: Free entry, up to 200 characters | G15: Free entry, up to 60 characters | H15: Free entry, up to 60 characters | I15: Free entry, up to 60 characters | J15: Free entry, up to 300 characters | K15: Free entry, up to 10 characters | L15: REGULAR, ZERO_RATED, EXEMPT (list VAT treatment) | M15: Free entry, up to 20 characters | N15: Y or N | O15: Y or N | P15: Y or N | Q15: Free entry, up to 40 characters | R15: A date, for example 15-Jan-2028 | S15: A date, for example 15-Jan-2028
A16: What to enter | B16: Code of the client, insurer, partner or payee | C16: Taxpayer identification number as registered | D16: TIN branch code (000 or 00000 for the head office) | E16: Individual or corporate (decides the WI or WC ATC and the alphalist name) | F16: Name as registered with the BIR | G16: Last name of an individual | H16: First name of an individual | I16: Middle name of an individual | J16: Address as registered with the BIR | K16: ZIP code of the registered address | L16: How a premium without VAT is classified on the VAT return | M16: Withholding tax code applied by default to payments to or from the party | N16: Y when the party withholds tax on its payments to BDOI (2307 expected); set by BIBS when Top withholding agent or Government payor is Y | O16: Y when the BIR classifies the party as a top withholding agent | P16: Y for a government office or company that withholds the final VAT and the final tax on its payments to BDOI | Q16: Number of the party's tax exemption certificate, when it has one | R16: First day of the certificate | S16: Last day of the certificate (not before the first day); a zero-rated or exempt invoice outside this period is flagged on the VAT worksheet
