Workbook

Sheet Cover
B6: BDOI INPUTS WORKBOOK
B7: BDOI Requirements and Inputs by BRD
B8: What the project needs from the BDOI business users, BRD by BRD
B9: BIBS – BDOI Broker System
B11: Client | C11: BDO Insurance and Reinsurance Brokers, Inc.
B12: BRD | C12: BRD-00 (all BRDs)
B13: Version | C13: 1.0
B14: Date | C14: 8 October 2026
B15: Classification | C15: Confidential
B16: Prepared by | C16: iorta TechNXT
B18: Sheets
B19: Sheet | C19: Content | D19: Rows
B20: README | C20: What each column of each sheet means, with the allowed values
B21: Instructions | C21: How to read and answer this workbook | D21: 0
B22: Summary | C22: Counts per BRD and type, status, owners and due dates | D22: 0
B23: BRD-00 Cross-cutting | C23: BRD-00 Core Replacement and cross-cutting points: what BDOI provides; owner BIBS Product Owner with the Program Manager, Business Project Services | D23: 144
B24: BRD-01 New Business | C24: BRD-01 New Business: what BDOI provides; owner Product Owner, New Business | D24: 76
B25: BRD-02 Operations | C25: BRD-02 Operations: what BDOI provides; owner Head, Operations Services | D25: 89
B26: BRD-03 Product Maintenance | C26: BRD-03 Product Maintenance: what BDOI provides; owner Product Owner, Marketing Business System (MBS) | D26: 79
B27: BRD-04 Collections | C27: BRD-04 Collections: what BDOI provides; owner VP and Head, BDOI Operations (Collections) | D27: 58
B28: BRD-05 Accounting and ACSL | C28: BRD-05 Accounting, Disbursement and ACSL: what BDOI provides; owner Head, Comptrollership | D28: 85
B29: BRD-06 Renewal | C29: BRD-06 Renewal: what BDOI provides; owner Product Owner, Renewal | D29: 64
B30: BRD-07 Claims | C30: BRD-07 Claims: what BDOI provides; owner Product Owner, Claims | D30: 38
B31: BRD-08 Employee Benefits | C31: BRD-08 Employee Benefits: what BDOI provides; owner Product Owner, Employee Benefits | D31: 34
B32: BRD-09 Customer Servicing | C32: BRD-09 Customer Servicing Facility: what BDOI provides; owner Product Owner, Customer Servicing Facility | D32: 26
... B37: RI Reinsurance (phase 2) | C37: Phase 2 ReInsurance (phase 2): what BDOI provides; owner BIBS Product Owner with the Head, Operations (Remittance) | D37: 5
B39: Legend
B40: Open | C40: Waiting for the BDOI answer
B41: Partly answered | C41: BDOI has answered in part; the rest of the point is open
B42: Answered | C42: BDOI has answered; the answer is applied and BDOI confirms it
B45: Prepared by iorta TechNXT for BDOI. Confidential – BDOI.

Sheet Instructions
A1: Instructions
A2: BDOI Requirements and Inputs by BRD, version 1.0, 8 October 2026
A4: Purpose | B4: This workbook lists, BRD by BRD, everything the project needs from the BDOI business users to complete the requirements, set BIBS up and test it: decisions, clarifications, confirmations of the proposed rules, configuration values, master data, sample documents, report layouts, integration details, test data and sign-offs. It answers the request of the BDOI product owner of 8 October 2026 for the BRD-specific requirements from the BDOI users.
A5: Where the rows come from | B5: The rows bring together the proposed business rules and clarifications (CLR) and the open questions of every FRS and of the Data Migration set, the discrepancy and clarification register, the earlier Drop 0 requirements list, the Drop 0 configuration register, the NFR targets and the dependencies, sign-offs and test windows of the project plan. A point raised in several documents is listed once; the Source column gives every ID under which it was raised, so an answer given against any of them is found here.
A6: One tab per BRD | B6: BRD-00 holds the cross-cutting points (several BRDs, programme, NFR targets, infrastructure and integrations). BRD-01 to BRD-13 hold the points of each BRD. The last tab holds the few points of ReInsurance, which is phase 2.
A7: How to answer | B7: Write the answer in BDOI response, set Status to Answered (or Partly answered) and send the workbook back to the iorta TechNXT project team. Where a proposal is given, an answer of 'Agree' is enough; otherwise give the decision, the value or attach the document and name it in the response. Do not change the Ref, so that the answer is traced back to the FRS, the register and the templates.
A8: Needed by and priority | B8: Needed by is the date of the project plan of 8 October 2026 by which the input is needed: the sign-off of the FRS or sign-off set of the BRD for decisions and clarifications, the configuration milestones (D1 to D7) for values and master data, the integration specifications for interface details and the UAT preparation for test data. High blocks a sign-off, the set-up or a test window; Medium is needed before UAT; Low can follow.
A9: Status | B9: The status is taken from the latest sources: Answered where BDOI has answered (the answer is in Remarks and BDOI confirms it), Partly answered where part of the point is answered, Open otherwise. Answered points stay in the list so that every answer is visible.
A10: Master data and configuration | B10: The rows of type Master data and Configuration value name the template to fill in. The templates are in the companion workbook BIBS_Templates_BRD-00_Master_Data_and_Configuration_Upload_Templates_v1.0, with its guide; fill the data there, not in this workbook.
A11: Proposals | B11: Until BDOI answers, the proposal of a row is the working assumption of the project team; the screens, tests and set-up follow it, and a different answer is applied by the change control of the programme.
A13: Types of input
A14: Type | B14: What BDOI provides
A15: Decision | B15: BDOI chooses between options or sets the scope; the choice changes what is delivered.
A16: Clarification | B16: The BRD text is unclear, incomplete or contradictory; BDOI explains what is meant.
A17: Business rule confirmation | B17: The project team proposes a rule; BDOI confirms it or gives its own.
A18: Configuration value | B18: A value BIBS is set up with: limits, days, rates, lists, numbering, parameters.
A19: Master data | B19: Records BIBS needs before go-live: organisation, users, products, insurers, accounts, clients.
A20: Sample document or template | B20: A letter, form, advice, slip or e-mail in the BDOI layout and wording.
A21: Report layout | B21: The columns, totals and filters of a report or an extract.
A22: Integration detail | B22: A file layout, interface, transport or contact of another system.
A23: Test data | B23: Testers, cases and business data for SIT and UAT.
A24: Sign-off | B24: A document or test result BDOI signs.

Sheet Summary
A1: Summary
A2: Counts per BRD, type and status follow the tabs as they are answered (formulas); owners and dates as issued.
A4: Items per BRD and type
A5: BRD | B5: Name | C5: Drop | D5: BDOI owner (role) | E5: Items | F5: Decision | G5: Clarification | H5: Business rule confirmation | I5: Configuration value | J5: Master data | K5: Sample document or template | L5: Report layout | M5: Integration detail | N5: Test data | O5: Sign-off | P5: Open | Q5: Partly answered | R5: Answered | S5: First needed by | T5: Last needed by
A6: BRD-00 | B6: Core Replacement and cross-cutting points | C6: Programme | D6: BIBS Product Owner with the Program Manager, Business Project Services | E6: =COUNTA('BRD-00 Cross-cutting'!A5:A649) | F6: =COUNTIF('BRD-00 Cross-cutting'!C5:C649,"Decision") | G6: =COUNTIF('BRD-00 Cross-cutting'!C5:C649,"Clarification") | H6: =COUNTIF('BRD-00 Cross-cutting'!C5:C649,"Business rule confirmation") | I6: =COUNTIF('BRD-00 Cross-cutting'!C5:C649,"Configuration value") | J6: =COUNTIF('BRD-00 Cross-cutting'!C5:C649,"Master data") | K6: =COUNTIF('BRD-00 Cross-cutting'!C5:C649,"Sample document or template") | L6: =COUNTIF('BRD-00 Cross-cutting'!C5:C649,"Report layout") | M6: =COUNTIF('BRD-00 Cross-cutting'!C5:C649,"Integration detail") | N6: =COUNTIF('BRD-00 Cross-cutting'!C5:C649,"Test data") | O6: =COUNTIF('BRD-00 Cross-cutting'!C5:C649,"Sign-off") | P6: =COUNTIF('BRD-00 Cross-cutting'!K5:K649,"Open") | Q6: =COUNTIF('BRD-00 Cross-cutting'!K5:K649,"Partly answered") | R6: =COUNTIF('BRD-00 Cross-cutting'!K5:K649,"Answered") | S6: =MIN('BRD-00 Cross-cutting'!I5:I649) | T6: =MAX('BRD-00 Cross-cutting'!I5:I649)
A7: BRD-01 | B7: New Business | C7: Drop 1 | D7: Product Owner, New Business | E7: =COUNTA('BRD-01 New Business'!A5:A581) | F7: =COUNTIF('BRD-01 New Business'!C5:C581,"Decision") | G7: =COUNTIF('BRD-01 New Business'!C5:C581,"Clarification") | H7: =COUNTIF('BRD-01 New Business'!C5:C581,"Business rule confirmation") | I7: =COUNTIF('BRD-01 New Business'!C5:C581,"Configuration value") | J7: =COUNTIF('BRD-01 New Business'!C5:C581,"Master data") | K7: =COUNTIF('BRD-01 New Business'!C5:C581,"Sample document or template") | L7: =COUNTIF('BRD-01 New Business'!C5:C581,"Report layout") | M7: =COUNTIF('BRD-01 New Business'!C5:C581,"Integration detail") | N7: =COUNTIF('BRD-01 New Business'!C5:C581,"Test data") | O7: =COUNTIF('BRD-01 New Business'!C5:C581,"Sign-off") | P7: =COUNTIF('BRD-01 New Business'!K5:K581,"Open") | Q7: =COUNTIF('BRD-01 New Business'!K5:K581,"Partly answered") | R7: =COUNTIF('BRD-01 New Business'!K5:K581,"Answered") | S7: =MIN('BRD-01 New Business'!I5:I581) | T7: =MAX('BRD-01 New Business'!I5:I581)
A8: BRD-02 | B8: Operations | C8: Drop 1 | D8: Head, Operations Services | E8: =COUNTA('BRD-02 Operations'!A5:A594) | F8: =COUNTIF('BRD-02 Operations'!C5:C594,"Decision") | G8: =COUNTIF('BRD-02 Operations'!C5:C594,"Clarification") | H8: =COUNTIF('BRD-02 Operations'!C5:C594,"Business rule confirmation") | I8: =COUNTIF('BRD-02 Operations'!C5:C594,"Configuration value") | J8: =COUNTIF('BRD-02 Operations'!C5:C594,"Master data") | K8: =COUNTIF('BRD-02 Operations'!C5:C594,"Sample document or template") | L8: =COUNTIF('BRD-02 Operations'!C5:C594,"Report layout") | M8: =COUNTIF('BRD-02 Operations'!C5:C594,"Integration detail") | N8: =COUNTIF('BRD-02 Operations'!C5:C594,"Test data") | O8: =COUNTIF('BRD-02 Operations'!C5:C594,"Sign-off") | P8: =COUNTIF('BRD-02 Operations'!K5:K594,"Open") | Q8: =COUNTIF('BRD-02 Operations'!K5:K594,"Partly answered") | R8: =COUNTIF('BRD-02 Operations'!K5:K594,"Answered") | S8: =MIN('BRD-02 Operations'!I5:I594) | T8: =MAX('BRD-02 Operations'!I5:I594)
A9: BRD-03 | B9: Product Maintenance | C9: Drop 0 | D9: Product Owner, Marketing Business System (MBS) | E9: =COUNTA('BRD-03 Product Maintenance'!A5:A584) | F9: =COUNTIF('BRD-03 Product Maintenance'!C5:C584,"Decision") | G9: =COUNTIF('BRD-03 Product Maintenance'!C5:C584,"Clarification") | H9: =COUNTIF('BRD-03 Product Maintenance'!C5:C584,"Business rule confirmation") | I9: =COUNTIF('BRD-03 Product Maintenance'!C5:C584,"Configuration value") | J9: =COUNTIF('BRD-03 Product Maintenance'!C5:C584,"Master data") | K9: =COUNTIF('BRD-03 Product Maintenance'!C5:C584,"Sample document or template") | L9: =COUNTIF('BRD-03 Product Maintenance'!C5:C584,"Report layout") | M9: =COUNTIF('BRD-03 Product Maintenance'!C5:C584,"Integration detail") | N9: =COUNTIF('BRD-03 Product Maintenance'!C5:C584,"Test data") | O9: =COUNTIF('BRD-03 Product Maintenance'!C5:C584,"Sign-off") | P9: =COUNTIF('BRD-03 Product Maintenance'!K5:K584,"Open") | Q9: =COUNTIF('BRD-03 Product Maintenance'!K5:K584,"Partly answered") | R9: =COUNTIF('BRD-03 Product Maintenance'!K5:K584,"Answered") | S9: =MIN('BRD-03 Product Maintenance'!I5:I584) | T9: =MAX('BRD-03 Product Maintenance'!I5:I584)
A10: BRD-04 | B10: Collections | C10: Drop 1 | D10: VP and Head, BDOI Operations (Collections) | E10: =COUNTA('BRD-04 Collections'!A5:A563) | F10: =COUNTIF('BRD-04 Collections'!C5:C563,"Decision") | G10: =COUNTIF('BRD-04 Collections'!C5:C563,"Clarification") | H10: =COUNTIF('BRD-04 Collections'!C5:C563,"Business rule confirmation") | I10: =COUNTIF('BRD-04 Collections'!C5:C563,"Configuration value") | J10: =COUNTIF('BRD-04 Collections'!C5:C563,"Master data") | K10: =COUNTIF('BRD-04 Collections'!C5:C563,"Sample document or template") | L10: =COUNTIF('BRD-04 Collections'!C5:C563,"Report layout") | M10: =COUNTIF('BRD-04 Collections'!C5:C563,"Integration detail") | N10: =COUNTIF('BRD-04 Collections'!C5:C563,"Test data") | O10: =COUNTIF('BRD-04 Collections'!C5:C563,"Sign-off") | P10: =COUNTIF('BRD-04 Collections'!K5:K563,"Open") | Q10: =COUNTIF('BRD-04 Collections'!K5:K563,"Partly answered") | R10: =COUNTIF('BRD-04 Collections'!K5:K563,"Answered") | S10: =MIN('BRD-04 Collections'!I5:I563) | T10: =MAX('BRD-04 Collections'!I5:I563)
A11: BRD-05 | B11: Accounting, Disbursement and ACSL | C11: Drop 1 | D11: Head, Comptrollership | E11: =COUNTA('BRD-05 Accounting and ACSL'!A5:A590) | F11: =COUNTIF('BRD-05 Accounting and ACSL'!C5:C590,"Decision") | G11: =COUNTIF('BRD-05 Accounting and ACSL'!C5:C590,"Clarification") | H11: =COUNTIF('BRD-05 Accounting and ACSL'!C5:C590,"Business rule confirmation") | I11: =COUNTIF('BRD-05 Accounting and ACSL'!C5:C590,"Configuration value") | J11: =COUNTIF('BRD-05 Accounting and ACSL'!C5:C590,"Master data") | K11: =COUNTIF('BRD-05 Accounting and ACSL'!C5:C590,"Sample document or template") | L11: =COUNTIF('BRD-05 Accounting and ACSL'!C5:C590,"Report layout") | M11: =COUNTIF('BRD-05 Accounting and ACSL'!C5:C590,"Integration detail") | N11: =COUNTIF('BRD-05 Accounting and ACSL'!C5:C590,"Test data") | O11: =COUNTIF('BRD-05 Accounting and ACSL'!C5:C590,"Sign-off") | P11: =COUNTIF('BRD-05 Accounting and ACSL'!K5:K590,"Open") | Q11: =COUNTIF('BRD-05 Accounting and ACSL'!K5:K590,"Partly answered") | R11: =COUNTIF('BRD-05 Accounting and ACSL'!K5:K590,"Answered") | S11: =MIN('BRD-05 Accounting and ACSL'!I5:I590) | T11: =MAX('BRD-05 Accounting and ACSL'!I5:I590)
A12: BRD-06 | B12: Renewal | C12: Drop 1 | D12: Product Owner, Renewal | E12: =COUNTA('BRD-06 Renewal'!A5:A569) | F12: =COUNTIF('BRD-06 Renewal'!C5:C569,"Decision") | G12: =COUNTIF('BRD-06 Renewal'!C5:C569,"Clarification") | H12: =COUNTIF('BRD-06 Renewal'!C5:C569,"Business rule confirmation") | I12: =COUNTIF('BRD-06 Renewal'!C5:C569,"Configuration value") | J12: =COUNTIF('BRD-06 Renewal'!C5:C569,"Master data") | K12: =COUNTIF('BRD-06 Renewal'!C5:C569,"Sample document or template") | L12: =COUNTIF('BRD-06 Renewal'!C5:C569,"Report layout") | M12: =COUNTIF('BRD-06 Renewal'!C5:C569,"Integration detail") | N12: =COUNTIF('BRD-06 Renewal'!C5:C569,"Test data") | O12: =COUNTIF('BRD-06 Renewal'!C5:C569,"Sign-off") | P12: =COUNTIF('BRD-06 Renewal'!K5:K569,"Open") | Q12: =COUNTIF('BRD-06 Renewal'!K5:K569,"Partly answered") | R12: =COUNTIF('BRD-06 Renewal'!K5:K569,"Answered") | S12: =MIN('BRD-06 Renewal'!I5:I569) | T12: =MAX('BRD-06 Renewal'!I5:I569)
A13: BRD-07 | B13: Claims | C13: Drop 2 | D13: Product Owner, Claims | E13: =COUNTA('BRD-07 Claims'!A5:A543) | F13: =COUNTIF('BRD-07 Claims'!C5:C543,"Decision") | G13: =COUNTIF('BRD-07 Claims'!C5:C543,"Clarification") | H13: =COUNTIF('BRD-07 Claims'!C5:C543,"Business rule confirmation") | I13: =COUNTIF('BRD-07 Claims'!C5:C543,"Configuration value") | J13: =COUNTIF('BRD-07 Claims'!C5:C543,"Master data") | K13: =COUNTIF('BRD-07 Claims'!C5:C543,"Sample document or template") | L13: =COUNTIF('BRD-07 Claims'!C5:C543,"Report layout") | M13: =COUNTIF('BRD-07 Claims'!C5:C543,"Integration detail") | N13: =COUNTIF('BRD-07 Claims'!C5:C543,"Test data") | O13: =COUNTIF('BRD-07 Claims'!C5:C543,"Sign-off") | P13: =COUNTIF('BRD-07 Claims'!K5:K543,"Open") | Q13: =COUNTIF('BRD-07 Claims'!K5:K543,"Partly answered") | R13: =COUNTIF('BRD-07 Claims'!K5:K543,"Answered") | S13: =MIN('BRD-07 Claims'!I5:I543) | T13: =MAX('BRD-07 Claims'!I5:I543)
A14: BRD-08 | B14: Employee Benefits | C14: Drop 2 | D14: Product Owner, Employee Benefits | E14: =COUNTA('BRD-08 Employee Benefits'!A5:A539) | F14: =COUNTIF('BRD-08 Employee Benefits'!C5:C539,"Decision") | G14: =COUNTIF('BRD-08 Employee Benefits'!C5:C539,"Clarification") | H14: =COUNTIF('BRD-08 Employee Benefits'!C5:C539,"Business rule confirmation") | I14: =COUNTIF('BRD-08 Employee Benefits'!C5:C539,"Configuration value") | J14: =COUNTIF('BRD-08 Employee Benefits'!C5:C539,"Master data") | K14: =COUNTIF('BRD-08 Employee Benefits'!C5:C539,"Sample document or template") | L14: =COUNTIF('BRD-08 Employee Benefits'!C5:C539,"Report layout") | M14: =COUNTIF('BRD-08 Employee Benefits'!C5:C539,"Integration detail") | N14: =COUNTIF('BRD-08 Employee Benefits'!C5:C539,"Test data") | O14: =COUNTIF('BRD-08 Employee Benefits'!C5:C539,"Sign-off") | P14: =COUNTIF('BRD-08 Employee Benefits'!K5:K539,"Open") | Q14: =COUNTIF('BRD-08 Employee Benefits'!K5:K539,"Partly answered") | R14: =COUNTIF('BRD-08 Employee Benefits'!K5:K539,"Answered") | S14: =MIN('BRD-08 Employee Benefits'!I5:I539) | T14: =MAX('BRD-08 Employee Benefits'!I5:I539)
A15: BRD-09 | B15: Customer Servicing Facility | C15: Drop 1 | D15: Product Owner, Customer Servicing Facility | E15: =COUNTA('BRD-09 Customer Servicing'!A5:A531) | F15: =COUNTIF('BRD-09 Customer Servicing'!C5:C531,"Decision") | G15: =COUNTIF('BRD-09 Customer Servicing'!C5:C531,"Clarification") | H15: =COUNTIF('BRD-09 Customer Servicing'!C5:C531,"Business rule confirmation") | I15: =COUNTIF('BRD-09 Customer Servicing'!C5:C531,"Configuration value") | J15: =COUNTIF('BRD-09 Customer Servicing'!C5:C531,"Master data") | K15: =COUNTIF('BRD-09 Customer Servicing'!C5:C531,"Sample document or template") | L15: =COUNTIF('BRD-09 Customer Servicing'!C5:C531,"Report layout") | M15: =COUNTIF('BRD-09 Customer Servicing'!C5:C531,"Integration detail") | N15: =COUNTIF('BRD-09 Customer Servicing'!C5:C531,"Test data") | O15: =COUNTIF('BRD-09 Customer Servicing'!C5:C531,"Sign-off") | P15: =COUNTIF('BRD-09 Customer Servicing'!K5:K531,"Open") | Q15: =COUNTIF('BRD-09 Customer Servicing'!K5:K531,"Partly answered") | R15: =COUNTIF('BRD-09 Customer Servicing'!K5:K531,"Answered") | S15: =MIN('BRD-09 Customer Servicing'!I5:I531) | T15: =MAX('BRD-09 Customer Servicing'!I5:I531)
A16: BRD-10 | B16: Sanction Screening and Risk Profiling | C16: Drop 1 | D16: Chief Compliance Officer (Compliance) | E16: =COUNTA('BRD-10 Sanction Screening'!A5:A530) | F16: =COUNTIF('BRD-10 Sanction Screening'!C5:C530,"Decision") | G16: =COUNTIF('BRD-10 Sanction Screening'!C5:C530,"Clarification") | H16: =COUNTIF('BRD-10 Sanction Screening'!C5:C530,"Business rule confirmation") | I16: =COUNTIF('BRD-10 Sanction Screening'!C5:C530,"Configuration value") | J16: =COUNTIF('BRD-10 Sanction Screening'!C5:C530,"Master data") | K16: =COUNTIF('BRD-10 Sanction Screening'!C5:C530,"Sample document or template") | L16: =COUNTIF('BRD-10 Sanction Screening'!C5:C530,"Report layout") | M16: =COUNTIF('BRD-10 Sanction Screening'!C5:C530,"Integration detail") | N16: =COUNTIF('BRD-10 Sanction Screening'!C5:C530,"Test data") | O16: =COUNTIF('BRD-10 Sanction Screening'!C5:C530,"Sign-off") | P16: =COUNTIF('BRD-10 Sanction Screening'!K5:K530,"Open") | Q16: =COUNTIF('BRD-10 Sanction Screening'!K5:K530,"Partly answered") | R16: =COUNTIF('BRD-10 Sanction Screening'!K5:K530,"Answered") | S16: =MIN('BRD-10 Sanction Screening'!I5:I530) | T16: =MAX('BRD-10 Sanction Screening'!I5:I530)
A17: BRD-11 | B17: User Access Maintenance | C17: Drop 0 | D17: Product Owner, MBS, with Business Administration (User Access) | E17: =COUNTA('BRD-11 User Access'!A5:A581) | F17: =COUNTIF('BRD-11 User Access'!C5:C581,"Decision") | G17: =COUNTIF('BRD-11 User Access'!C5:C581,"Clarification") | H17: =COUNTIF('BRD-11 User Access'!C5:C581,"Business rule confirmation") | I17: =COUNTIF('BRD-11 User Access'!C5:C581,"Configuration value") | J17: =COUNTIF('BRD-11 User Access'!C5:C581,"Master data") | K17: =COUNTIF('BRD-11 User Access'!C5:C581,"Sample document or template") | L17: =COUNTIF('BRD-11 User Access'!C5:C581,"Report layout") | M17: =COUNTIF('BRD-11 User Access'!C5:C581,"Integration detail") | N17: =COUNTIF('BRD-11 User Access'!C5:C581,"Test data") | O17: =COUNTIF('BRD-11 User Access'!C5:C581,"Sign-off") | P17: =COUNTIF('BRD-11 User Access'!K5:K581,"Open") | Q17: =COUNTIF('BRD-11 User Access'!K5:K581,"Partly answered") | R17: =COUNTIF('BRD-11 User Access'!K5:K581,"Answered") | S17: =MIN('BRD-11 User Access'!I5:I581) | T17: =MAX('BRD-11 User Access'!I5:I581)
A18: BRD-12 | B18: Submitted Policies | C18: Drop 1 | D18: Product Owner, Submitted Policies | E18: =COUNTA('BRD-12 Submitted Policies'!A5:A542) | F18: =COUNTIF('BRD-12 Submitted Policies'!C5:C542,"Decision") | G18: =COUNTIF('BRD-12 Submitted Policies'!C5:C542,"Clarification") | H18: =COUNTIF('BRD-12 Submitted Policies'!C5:C542,"Business rule confirmation") | I18: =COUNTIF('BRD-12 Submitted Policies'!C5:C542,"Configuration value") | J18: =COUNTIF('BRD-12 Submitted Policies'!C5:C542,"Master data") | K18: =COUNTIF('BRD-12 Submitted Policies'!C5:C542,"Sample document or template") | L18: =COUNTIF('BRD-12 Submitted Policies'!C5:C542,"Report layout") | M18: =COUNTIF('BRD-12 Submitted Policies'!C5:C542,"Integration detail") | N18: =COUNTIF('BRD-12 Submitted Policies'!C5:C542,"Test data") | O18: =COUNTIF('BRD-12 Submitted Policies'!C5:C542,"Sign-off") | P18: =COUNTIF('BRD-12 Submitted Policies'!K5:K542,"Open") | Q18: =COUNTIF('BRD-12 Submitted Policies'!K5:K542,"Partly answered") | R18: =COUNTIF('BRD-12 Submitted Policies'!K5:K542,"Answered") | S18: =MIN('BRD-12 Submitted Policies'!I5:I542) | T18: =MAX('BRD-12 Submitted Policies'!I5:I542)
A19: BRD-13 | B19: Data Migration | C19: Drop 0 | D19: Program Manager, Business Project Services (Data Migration) | E19: =COUNTA('BRD-13 Data Migration'!A5:A578) | F19: =COUNTIF('BRD-13 Data Migration'!C5:C578,"Decision") | G19: =COUNTIF('BRD-13 Data Migration'!C5:C578,"Clarification") | H19: =COUNTIF('BRD-13 Data Migration'!C5:C578,"Business rule confirmation") | I19: =COUNTIF('BRD-13 Data Migration'!C5:C578,"Configuration value") | J19: =COUNTIF('BRD-13 Data Migration'!C5:C578,"Master data") | K19: =COUNTIF('BRD-13 Data Migration'!C5:C578,"Sample document or template") | L19: =COUNTIF('BRD-13 Data Migration'!C5:C578,"Report layout") | M19: =COUNTIF('BRD-13 Data Migration'!C5:C578,"Integration detail") | N19: =COUNTIF('BRD-13 Data Migration'!C5:C578,"Test data") | O19: =COUNTIF('BRD-13 Data Migration'!C5:C578,"Sign-off") | P19: =COUNTIF('BRD-13 Data Migration'!K5:K578,"Open") | Q19: =COUNTIF('BRD-13 Data Migration'!K5:K578,"Partly answered") | R19: =COUNTIF('BRD-13 Data Migration'!K5:K578,"Answered") | S19: =MIN('BRD-13 Data Migration'!I5:I578) | T19: =MAX('BRD-13 Data Migration'!I5:I578)
A20: Phase 2 | B20: ReInsurance (phase 2) | C20: Phase 2 | D20: BIBS Product Owner with the Head, Operations (Remittance) | E20: =COUNTA('RI Reinsurance (phase 2)'!A5:A510) | F20: =COUNTIF('RI Reinsurance (phase 2)'!C5:C510,"Decision") | G20: =COUNTIF('RI Reinsurance (phase 2)'!C5:C510,"Clarification") | H20: =COUNTIF('RI Reinsurance (phase 2)'!C5:C510,"Business rule confirmation") | I20: =COUNTIF('RI Reinsurance (phase 2)'!C5:C510,"Configuration value") | J20: =COUNTIF('RI Reinsurance (phase 2)'!C5:C510,"Master data") | K20: =COUNTIF('RI Reinsurance (phase 2)'!C5:C510,"Sample document or template") | L20: =COUNTIF('RI Reinsurance (phase 2)'!C5:C510,"Report layout") | M20: =COUNTIF('RI Reinsurance (phase 2)'!C5:C510,"Integration detail") | N20: =COUNTIF('RI Reinsurance (phase 2)'!C5:C510,"Test data") | O20: =COUNTIF('RI Reinsurance (phase 2)'!C5:C510,"Sign-off") | P20: =COUNTIF('RI Reinsurance (phase 2)'!K5:K510,"Open") | Q20: =COUNTIF('RI Reinsurance (phase 2)'!K5:K510,"Partly answered") | R20: =COUNTIF('RI Reinsurance (phase 2)'!K5:K510,"Answered") | S20: =MIN('RI Reinsurance (phase 2)'!I5:I510) | T20: =MAX('RI Reinsurance (phase 2)'!I5:I510)
A21: Total | E21: =SUM(E6:E20) | F21: =SUM(F6:F20) | G21: =SUM(G6:G20) | H21: =SUM(H6:H20) | I21: =SUM(I6:I20) | J21: =SUM(J6:J20) | K21: =SUM(K6:K20) | L21: =SUM(L6:L20) | ... R21: =SUM(R6:R20) | S21: =MIN(S6:S20) | T21: =MAX(T6:T20)
A23: Items per BDOI owner (role), as issued (owners with five items or more)
A24: Owner (role) | E24: Items | F24: Open | G24: Partly answered | H24: Answered | I24: First needed by | J24: BRDs
A25: Head, Comptrollership | E25: 69 | F25: 67 | G25: 2 | H25: 0 | I25: 46311 | J25: BRD-00, BRD-05, BRD-11, BRD-13
A26: Head, Operations Services | E26: 69 | F26: 58 | G26: 9 | H26: 2 | I26: 46356 | J26: BRD-02
A27: Product Owner, New Business | E27: 50 | F27: 39 | G27: 11 | H27: 0 | I27: 46356 | J27: BRD-01
A28: Product Owner, Renewal | E28: 45 | F28: 39 | G28: 5 | H28: 1 | I28: 46356 | J28: BRD-06
A29: VP and Head, BDOI Operations (Collections) | E29: 43 | F29: 36 | G29: 6 | H29: 1 | I29: 46356 | J29: BRD-04
A30: Product Owner, Claims | E30: 29 | F30: 24 | G30: 4 | H30: 1 | I30: 46444 | J30: BRD-07
A31: Program Manager, Business Project Services (Data Migration) | E31: 26 | F31: 25 | G31: 1 | H31: 0 | I31: 46311 | J31: BRD-13
A32: Product Owner, Submitted Policies | E32: 24 | F32: 23 | G32: 0 | H32: 1 | I32: 46356 | J32: BRD-12
A33: BDOI IT | E33: 20 | F33: 20 | G33: 0 | H33: 0 | I33: 46311 | J33: BRD-00, BRD-03, BRD-13
A34: Marketing and Processing - Renewal (RMEL) | E34: 20 | F34: 16 | G34: 3 | H34: 1 | I34: 46356 | J34: BRD-00, BRD-04, BRD-06
A35: Head, BDOI Information Security | E35: 17 | F35: 16 | G35: 1 | H35: 0 | I35: 46357 | J35: BRD-11
A36: Process Owner, User Access Maintenance (Business Administration) | E36: 17 | F36: 17 | G36: 0 | H36: 0 | I36: 46357 | J36: BRD-11
... A68: Other owners (138 roles with fewer than 5 items each) | E68: 167 | F68: 150 | G68: 15 | H68: 2 | I68: 46311 | J68: BRD-00, BRD-01, BRD-02, BRD-03, BRD-04, BRD-05, BRD-06, BRD-07, BRD-08, BRD-09, BRD-10, BRD-11, BRD-12, BRD-13, RI
A70: Items by month needed, as issued
A71: Month | C71: Items | D71: High | E71: Medium | F71: Low
A72: Oct 2026 | C72: 59 | D72: 25 | E72: 33 | F72: 1
A73: Nov 2026 | C73: 523 | D73: 84 | E73: 410 | F73: 29
A74: Dec 2026 | C74: 62 | D74: 30 | E74: 26 | F74: 6
A75: Jan 2027 | C75: 52 | D75: 22 | E75: 30 | F75: 0
A76: Feb 2027 | C76: 63 | D76: 6 | E76: 55 | F76: 2
A77: Mar 2027 | C77: 2 | D77: 2 | E77: 0 | F77: 0
A78: Apr 2027 | C78: 15 | D78: 13 | E78: 2 | F78: 0
A79: May 2027 | C79: 2 | D79: 2 | E79: 0 | F79: 0
A80: Jun 2027 | C80: 8 | D80: 3 | E80: 5 | F80: 0
A81: Jul 2027 | C81: 90 | D81: 20 | E81: 70 | F81: 0
A82: Oct 2027 | C82: 5 | D82: 3 | E82: 2 | F82: 0
A83: Nov 2027 | C83: 12 | D83: 6 | E83: 6 | F83: 0
... A86: Feb 2028 | C86: 1 | D86: 1 | E86: 0 | F86: 0

Sheet BRD-00 Cross-cutting
A1: BRD-00 Cross-cutting
A2: BRD-00 Core Replacement and cross-cutting points: what BDOI provides; owner BIBS Product Owner with the Program Manager, Business Project Services
A4: Ref | B4: BRD / module | C4: Type | D4: What we need from BDOI | E4: Why / impact if not provided | F4: Our proposal (if any) | G4: Source (FRS section / CLR / BRD page) | H4: BDOI owner (role) | I4: Needed by | J4: Priority | K4: Status | L4: BDOI response | M4: Remarks
A5: CLR-CR-02 | B5: BRD-00 Core Replacement and cross-cutting points | C5: Clarification | D5: Claims cheque safekeeping: Answer CRQ03. | E5: Whether BDOI holds claim cheques is open (CRQ03, CLQ10). | F5: No cheque custody in phase 1; if BDOI holds claim settlement cheques, a cheque custody register is added in Claims with hand-over to and from Cashiering. | G5: FRS BRD-00 v1.1, Proposed business rules and clarifications; CORE-14.08-14.10; also raised as CRQ03 (open question), DCR-164 (register item) | H5: Claims and Risk Management | I5: 46356 | J5: High | K5: Open | M5: Also affects BRD-07.
A6: CLR-CR-03 | B6: BRD-00 Core Replacement and cross-cutting points | C6: Decision | D6: CSF case resolution: Decide the delivery drop of the Case Management module (CLR-CSF-07); close DCR-163 and CR-0005 against it. | E6: The addendum answers CRQ04 and the cross-BRD conflict XQ12 (DCR-163); change request CR-0005 kept case resolution out of phase 1. | F6: Case resolution is BDOI scope: the signed CSF Addendum - Case Management (BRCSFCM.001-012) is specified in FRS BRD-9 (FR-CSF-050 to 061). Its delivery drop and plan follow the decision of BDOI and the Change Control Board (FRS BRD-9 CLR-CSF-07). | G6: FRS BRD-00 v1.1, Proposed business rules and clarifications; CORE-16.06; also raised as CRQ04 (open question), XQ12 (open question), CSQ09 (open question), DCR-163 (register item) | H6: Contact Center Management / Alternative Distribution | I6: 46356 | J6: High | K6: Partly answered | M6: Answer so far: in scope by the Case Management Addendum; drop open, CLR-CSF-07; Case Management Addendum; drop open, CLR-CSF-07. Also affects BRD-09.
A7: NFR-PRF-01 | B7: BRD-00 Core Replacement and cross-cutting points | C7: Decision | D7: Screen response time: decide the target; the BRDs give different values | E7: Every screen opens, and every single-record action (save, submit, approve) completes, within the target at the design load. | F7: p95 at most 2.0 seconds and p99 at most 4.0 seconds | G7: Non-functional requirements register v1.0, NFR-PRF-01; BRD-00 p.42 (under 5 s for every role); BRD-12 p.13 (2 s); BRD-9 p.13 (3 s); BRD-1 p.210 and BRD-6 p.186 (10 s); register DCR-137, DCR-165; CRQ21; also raised as CRQ21 (open question), XQ08 (open question), CQ25 (open question), AQ27 (open question), RQ28 (open question), EBQ25 (open question), SANC-SQ18 (open question), DCR-057 (register item), DCR-071 (register item), DCR-137 (register item), DCR-139 (register item), DCR-165 (register item), DCR-193 (register item) | H7: BIBS Product Owner | I7: 46356 | J7: High | K7: Partly answered | M7: Answer so far: Umbrella: retention 5 / 15, backup every 4 hours kept 5 years, response under 5 s, users per role (1,344 / 429). Availability, hours and maintenance still per BRD. BRD-13 refers to a consolidated NFR document not in the pack (DMQ29). (BRD-00 p.42-45; BRD-13 p. Also affects BRD-01, BRD-02, BRD-03, BRD-04, BRD-05, BRD-06, BRD-07, BRD-08, BRD-09, BRD-10, BRD-11, BRD-12, BRD-13.
A8: NFR-PRF-02 | B8: BRD-00 Core Replacement and cross-cutting points | C8: Configuration value | D8: Search and work-list response time: confirm the proposed target or give the BDOI value | E8: The first page of any search result or work list is shown within the target; lists are paged on the server. | F8: First page (up to 50 rows) p95 at most 3.0 seconds; each further page p95 at most 2.0 seconds | G8: Non-functional requirements register v1.0, NFR-PRF-02; BRD-9 p.13 (retrieval and search under 3 s); BRD-4 NFR 15 (5 s); BRD-10 p.22-24 (3 to 5 s) | H8: BIBS Product Owner | I8: 46356 | J8: High | K8: Open
A9: NFR-PRF-03 | B9: BRD-00 Core Replacement and cross-cutting points | C9: Decision | D9: Interactive reports: decide the target; the BRDs give different values | E9: An on-screen report or its export is produced within the target; larger reports run as background jobs (NFR-PRF-04). | F9: At most 20 seconds (p95) for a report of up to 30,000 rows | G9: Non-functional requirements register v1.0, NFR-PRF-03; BRD-6 p.186 and BRD-11 p.11 (20 s); BRD-5 p.133-137 (10 to 20 s first load); register DCR-137 | H9: BIBS Product Owner | I9: 46356 | J9: High | K9: Open
A10: NFR-PRF-07 | B10: BRD-00 Core Replacement and cross-cutting points | C10: Configuration value | D10: Night batch window: confirm the proposed target or give the BDOI value | E10: The scheduled jobs of the night (booking batch, remittance extraction, GL-SL reconciliation, Collections files, renewal extraction, screening, application file) finish before the service window opens. | F10: The chain from 20:00 to 05:30 PHT completes before 06:00 PHT at year-5 volumes; a failed job can be re-run within the window | G10: Non-functional requirements register v1.0, NFR-PRF-07; Register DCR-133 (service window from 06:00); programme alignment pack, section 6.5 (job times); also raised as DCR-133 (register item) | H10: Head, BDOI IT | I10: 46356 | J10: High | K10: Open | M10: Also affects BRD-01, BRD-02, BRD-03, BRD-04, BRD-05, BRD-06, BRD-07, BRD-08, BRD-09, BRD-10, BRD-12.
A11: NFR-CAP-01 | B11: BRD-00 Core Replacement and cross-cutting points | C11: Decision | D11: Users: decide the target; the BRDs give different values | E11: BIBS serves every named user of BDOI and the concurrent sessions of the peak. | F11: 1,344 named users; design load 150 concurrent users in year 1, growing 20% a year (311 in year 5); peak test at 429 concurrent sessions | G11: Non-functional requirements register v1.0, NFR-CAP-01; BRD-00 p.42 (1,344 named, 429 concurrent); BRD-1 p.210 (485 / 145, growth 20%); IER architecture sheet (about 1,200 internal users); register DCR-166, DCR-232; CRQ21, CRQ24; also raised as CRQ24 (open question), DCR-166 (register item), DCR-232 (register item) | H11: BIBS Product Owner | I11: 46356 | J11: High | K11: Open | M11: Also affects BRD-03, BRD-07, BRD-08.
A12: NFR-CAP-03 | B12: BRD-00 Core Replacement and cross-cutting points | C12: Configuration value | D12: Data and document volume: confirm the proposed target or give the BDOI value | E12: Storage is sized for five years of data and documents with headroom. | F12: Five years (60 months) at 20% growth a year with at least 30% free capacity at the end of year 5; migrated base up to 1,000,000 client rows and 500,000 open items | G12: Non-functional requirements register v1.0, NFR-CAP-03; IER HW & SW Requirements (60 months; 15% growth a year); Data Migration Handbook (1,000,000 clients, 500,000 open items); programme alignment pack 6.3 (data store re-sized without documents) | H12: Cloud and Digital Operations Engineering (IER owner) | I12: 46356 | J12: High | K12: Open
A13: NFR-CAP-05 | B13: BRD-00 Core Replacement and cross-cutting points | C13: Configuration value | D13: Peak periods: confirm the proposed target or give the BDOI value | E13: The month-end, mid-month and year-end peaks are carried without missing the response targets. | F13: 1.5 times the average daily volume on the 15th, the 30th, month-end and year-end, within NFR-PRF-01 and NFR-PRF-02 | G13: Non-functional requirements register v1.0, NFR-CAP-05; BRD-2 (15th and 30th); BRD-5 (month-end and year-end); BRD-9 (first quarter); BRD-1 and BRD-6 (08:00-10:00 and 15:00-17:00) | H13: Head, Comptrollership | I13: 46356 | J13: High | K13: Open
A14: NFR-AVL-01 | B14: BRD-00 Core Replacement and cross-cutting points | C14: Decision | D14: Availability in the service window: decide the target; the BRDs give different values | E14: BIBS is available to users throughout the service window. | F14: 99.9% of the service window each month (about 25 minutes of unplanned unavailability in a month of 26 service days) | G14: Non-functional requirements register v1.0, NFR-AVL-01; Register DCR-134 (99.9% in service hours); BRD-2, 3, 9, 10, 12 (99.9%); BRD-8 (99.99%); BRD-5 Add.1 (100%); also raised as DCR-134 (register item) | H14: Head, BDOI IT | I14: 46356 | J14: High | K14: Open | M14: Also affects BRD-01, BRD-02, BRD-03, BRD-05, BRD-06, BRD-08, BRD-09, BRD-10, BRD-11, BRD-12.
A15: NFR-AVL-02 | B15: BRD-00 Core Replacement and cross-cutting points | C15: Decision | D15: Service window: decide the target; the BRDs give different values | E15: One service window serves every module; production runs 24 x 7 so jobs and interfaces run outside it. | F15: 06:00 to 22:00 PHT Monday to Saturday, plus month-end weekends; production infrastructure 24 x 7 | G15: Non-functional requirements register v1.0, NFR-AVL-02; Register DCR-133; IER Assumptions 3 and 4 (non-production 12 x 5, production 24 x 7); BRD service hours from 06:00 (BRD-4, 7, 9) to 22:00 (BRD-1, 4, 6, 9) | H15: BIBS Product Owner | I15: 46356 | J15: High | K15: Open
A16: NFR-AVL-03 | B16: BRD-00 Core Replacement and cross-cutting points | C16: Decision | D16: Planned maintenance: decide the target; the BRDs give different values | E16: Planned work happens in one window outside every module's service hours. | F16: 00:00 to 04:00 PHT; at most 45 minutes of planned downtime a month; announced 5 business days ahead; releases without downtime where the change allows | G16: Non-functional requirements register v1.0, NFR-AVL-03; Register DCR-138 and DCR-134; BRD-10 p.25 and BRD-12 p.14 (00:00-04:00, 45 minutes a month); also raised as CSQ12 (open question), DCR-103 (register item), DCR-138 (register item) | H16: Head, BDOI IT | I16: 46356 | J16: High | K16: Open | M16: Also affects BRD-01, BRD-04, BRD-05, BRD-09, BRD-10, BRD-12.
A17: NFR-REC-03 | B17: BRD-00 Core Replacement and cross-cutting points | C17: Decision | D17: Backup: decide the target; the BRDs give different values | E17: Data and documents are backed up continuously and kept for the retention period. | F17: Continuous transaction-log archiving plus a base backup every 4 hours; backups encrypted and kept 7 years; document store versioned with cross-region replication | G17: Non-functional requirements register v1.0, NFR-REC-03; Register DCR-102, DCR-135, DCR-136; BRD-00 p.45 (every 4 hours, kept 5 years); BRD-2 and BRD-8 (kept 7 years); also raised as DCR-135 (register item), DCR-136 (register item) | H17: Cloud and Digital Operations Engineering (IER owner) | I17: 46356 | J17: High | K17: Partly answered | M17: Answer so far: The IER workbook v20 (BDOI IT, received 26-Sep-2026) states RPO 15 minutes and RTO 4 hours, the values proposed here. To be confirmed by the BRD owners. Also affects BRD-01, BRD-02, BRD-03, BRD-04, BRD-05, BRD-06, BRD-07, BRD-08, BRD-09, BRD-10, BRD-11, BRD-12.
A18: NFR-REC-04 | B18: BRD-00 Core Replacement and cross-cutting points | C18: Configuration value | D18: Restore and DR drills: confirm the proposed target or give the BDOI value | E18: Recovery is proven before go-live and kept proven afterwards. | F18: Point-in-time restore tested every quarter; DR failover drill before go-live (Dec 2027) and twice a year after; each with a written result | G18: Non-functional requirements register v1.0, NFR-REC-04; Operations runbook (quarterly restore test); IER DR environment | H18: Head, BDOI IT | I18: 46356 | J18: High | K18: Open
A19: NFR-REC-05 | B19: BRD-00 Core Replacement and cross-cutting points | C19: Decision | D19: DR region: decide the target; the BRDs give different values | E19: A second AWS region hosts the DR copy of BIBS once BDOI confirms data residency. | F19: Data store cross-region replica, document store cross-region replication, standby Kubernetes cluster scaled from 0 to 6 backend pods at failover | G19: Non-functional requirements register v1.0, NFR-REC-05; IER PROD DR (cross-region read replica) and diagram (warm standby); register DCR-225; programme alignment pack 6.4; IQ26; also raised as IQ26 (open question), DCR-225 (register item) | H19: Cloud and Digital Operations Engineering (IER owner) | I19: 46356 | J19: High | K19: Open
A20: NFR-SEC-02 | B20: BRD-00 Core Replacement and cross-cutting points | C20: Configuration value | D20: Second factor: confirm the proposed target or give the BDOI value | E20: Privileged users prove a second factor. | F20: TOTP second factor for every privileged role and every break-glass administrator; EIAM conditional access for single sign-on users | G20: Non-functional requirements register v1.0, NFR-SEC-02; Security controls (TOTP, policy PRIVILEGED as delivered); drop plan EIAM | H20: BDOI Information Security | I20: 46356 | J20: High | K20: Open
A21: NFR-SEC-03 | B21: BRD-00 Core Replacement and cross-cutting points | C21: Decision | D21: User provisioning and leavers: decide the target; the BRDs give different values | E21: Joiners, movers and leavers reach BIBS from UIDM-ISC; dormant accounts are disabled. | F21: SCIM 2.0 provisioning from UIDM-ISC (planned); a leaver disabled in BIBS within 1 hour of the UIDM-ISC change; accounts dormant for 90 days disabled by the daily job | G21: Non-functional requirements register v1.0, NFR-SEC-03; Drop plan integration UIDM-ISC (INT-02); BRD-11 UAM-NFR-09 (dormant users disabled); IQ05, DCR-229; also raised as IQ05 (open question), DCR-229 (register item) | H21: BDOI Information Security | I21: 46356 | J21: High | K21: Open | M21: Also affects BRD-11.
A22: NFR-SEC-05 | B22: BRD-00 Core Replacement and cross-cutting points | C22: Decision | D22: Session and lock-out: decide the target; the BRDs give different values | E22: Idle sessions end and repeated failures lock the account. | F22: Inactivity warning at 15 minutes and sign-out at 30 minutes; absolute session end 8 hours; lock-out after 3 consecutive failed attempts | G22: Non-functional requirements register v1.0, NFR-SEC-05; BRD-11 UAM-NFR-19, 34; BRD-1 p.93 and BRD-6 p.44 (warning 15, log-out 30); BRD-4 p.53 and BRD-7 p.35 (15 minutes); register DCR-140, DCR-142; also raised as DCR-140 (register item), DCR-142 (register item) | H22: BDOI Information Security | I22: 46356 | J22: High | K22: Partly answered | M22: Answer so far: BRD-11 p.14: "Users should be locked out to the system after 3 invalid attempts.". Also affects BRD-01, BRD-04, BRD-07, BRD-11.
A23: NFR-SEC-06 | B23: BRD-00 Core Replacement and cross-cutting points | C23: Configuration value | D23: Encryption in transit and at rest: confirm the proposed target or give the BDOI value | E23: Data is encrypted on every connection and in every store. | F23: TLS 1.2 or higher on every connection (browser, Gateway Interface, between workloads, to the managed services); data store, document store and backups encrypted with customer-managed keys per environment | G23: Non-functional requirements register v1.0, NFR-SEC-06; Security controls (TLS at the edge and to the pods); programme alignment pack 6.3 (KMS keys per environment); BRD-8 derived privacy requirement (encryption in transit and at rest) | H23: BDOI Information Security | I23: 46356 | J23: High | K23: Open
A24: NFR-SEC-08 | B24: BRD-00 Core Replacement and cross-cutting points | C24: Configuration value | D24: DAST and penetration test: confirm the proposed target or give the BDOI value | E24: The running application is tested from outside before go-live. | F24: DAST scan of each release candidate in SIT and Pre-Prod with no open high or critical finding; early scan in SIT in June 2027; independent penetration test 1 Nov to 15 Dec 2027; critical and high findings closed before go-live | G24: Non-functional requirements register v1.0, NFR-SEC-08; BDOI programme timeline (performance and penetration test Nov to Dec 2027); programme alignment pack (early security scan, IQ35); project plan DEP-19; also raised as IQ35 (open question) | H24: BDOI Information Security | I24: 46356 | J24: High | K24: Open
A25: NFR-SEC-12 | B25: BRD-00 Core Replacement and cross-cutting points | C25: Configuration value | D25: Vulnerability remediation: confirm the proposed target or give the BDOI value | E25: Security findings in production are fixed within set times. | F25: Critical within 7 days, high within 30 days, medium within 90 days; an accepted finding expires after at most 6 months | G25: Non-functional requirements register v1.0, NFR-SEC-12; Quality gates (accepted findings expire after at most six months) | H25: BDOI Information Security | I25: 46356 | J25: High | K25: Open
A26: NFR-PRV-02 | B26: BRD-00 Core Replacement and cross-cutting points | C26: Decision | D26: Data residency and support access: decide the target; the BRDs give different values | E26: Production data stays in the agreed region and is reached only by authorised personnel in the Philippines. | F26: Production in AWS ap-southeast-1; DR region confirmed by BDOI after the data-residency check; production access only by named personnel in the Philippines, each session logged | G26: Non-functional requirements register v1.0, NFR-PRV-02; FRS BRD-00 NFR table (hosting appendix: AWS ap-southeast-1, access from the Philippines); register DCR-225; IQ26 | H26: Data Protection Officer, BDOI | I26: 46356 | J26: High | K26: Open
A27: NFR-ACC-01 | B27: BRD-00 Core Replacement and cross-cutting points | C27: Configuration value | D27: WCAG 2.2 level AA: confirm the proposed target or give the BDOI value | E27: Every screen meets the success criteria of WCAG 2.2 at levels A and AA. | F27: 0 open level A or AA failures on the screens of each sign-off set; 0 serious or critical issues in the scan of every screen | G27: Non-functional requirements register v1.0, NFR-ACC-01; BRD-11 UAM-NFR-05 (options for impaired vision or colour blindness); BDO UX guidelines (AA contrast, keyboard use) | H27: BIBS Product Owner | I27: 46356 | J27: High | K27: Open
A28: NFR-USE-01 | B28: BRD-00 Core Replacement and cross-cutting points | C28: Configuration value | D28: Low-click navigation: confirm the proposed target or give the BDOI value | E28: Daily work starts from the role home page with few clicks. | F28: Any daily task reached in at most 2 clicks from the role home page or the menu; a record opened from a search result in 1 click; the main action of a record (submit, approve) at most 1 click away | G28: Non-functional requirements register v1.0, NFR-USE-01; BRD-00 p.5 (role-based self-service, centralised dashboards); FRS BRD-00 FR-CR-001 and FR-CR-010 (persona menus, role home) | H28: BIBS Product Owner | I28: 46356 | J28: High | K28: Open
A29: NFR-RSP-03 | B29: BRD-00 Core Replacement and cross-cutting points | C29: Configuration value | D29: Supported browsers: confirm the proposed target or give the BDOI value | E29: Users need only a browser. | F29: Current and previous major versions of Microsoft Edge and Google Chrome on Windows, Safari on iOS and Chrome on Android; no plug-in or local install | G29: Non-functional requirements register v1.0, NFR-RSP-03; BRD-11 UAM-NFR-28 (browser only on workstations) | H29: Head, BDOI IT | I29: 46356 | J29: High | K29: Open
A30: NFR-MNT-02 | B30: BRD-00 Core Replacement and cross-cutting points | C30: Configuration value | D30: Code coverage: confirm the proposed target or give the BDOI value | E30: New and changed code is covered by unit testing. | F30: Line coverage above 90% on new and changed code (new-code gate of SonarQube); overall line coverage at least 80% and branch coverage at least 65% | G30: Non-functional requirements register v1.0, NFR-MNT-02; Quality gates (overall gate 80% lines, 65% branches); programme target for new code | H30: Head, BDOI IT | I30: 46356 | J30: High | K30: Open
A31: NFR-MNT-05 | B31: BRD-00 Core Replacement and cross-cutting points | C31: Configuration value | D31: Releases and rollback: confirm the proposed target or give the BDOI value | E31: Releases do not stop users and can be rolled back. | F31: Rolling deployment with no pod unavailable; data changes compatible with the previous release; rollback by redeploying the previous release within 30 minutes | G31: Non-functional requirements register v1.0, NFR-MNT-05; Operations runbook (rolling update, expand-migrate-contract, rollback by previous image) | H31: Head, BDOI IT | I31: 46356 | J31: High | K31: Open
A32: NFR-OBS-01 | B32: BRD-00 Core Replacement and cross-cutting points | C32: Decision | D32: Metrics and dashboards: decide the target; the BRDs give different values | E32: Operations sees the health and load of every workload. | F32: Application, JVM, request, connection-pool and business metrics sent to the BDO monitoring platform; dashboards per workload (web, jobs, integration, web tier) and for the managed services | G32: Non-functional requirements register v1.0, NFR-OBS-01; Operations runbook (metrics on the management port); IER VDI and K8S sheets (Dynatrace); IQ30; also raised as IQ30 (open question), DCR-224 (register item) | H32: Head, BDOI IT | I32: 46356 | J32: High | K32: Open
A33: NFR-OBS-02 | B33: BRD-00 Core Replacement and cross-cutting points | C33: Configuration value | D33: Logs: confirm the proposed target or give the BDOI value | E33: Logs let support trace every event without exposing personal data. | F33: One line per event with time stamp, correlation ID, user and module; shipped to the BDO log platform within 1 minute; no passwords or full personal identifiers in logs | G33: Non-functional requirements register v1.0, NFR-OBS-02; Operations runbook (logs, correlation ID); security controls (no passwords in logs); BRD-11 UAM-NFR-21 (error log sent to a remote log server) | H33: BDOI Information Security | I33: 46356 | J33: High | K33: Open
A34: NFR-OBS-03 | B34: BRD-00 Core Replacement and cross-cutting points | C34: Configuration value | D34: Alerts: confirm the proposed target or give the BDOI value | E34: Faults raise alerts before users report them. | F34: Alerts for an error rate above 1% over 5 minutes, p95 above its NFR-PRF target for 10 minutes, a failed job, a new dead letter, a security-store failure and a certificate expiring within 30 days; the on-call person notified within 5 minutes | G34: Non-functional requirements register v1.0, NFR-OBS-03; Operations runbook (security-store alert, dead letters); BRD-11 UAM-NFR-25 (failed batch e-mail) | H34: Head, BDOI IT | I34: 46356 | J34: High | K34: Open
A35: NFR-SUP-02 | B35: BRD-00 Core Replacement and cross-cutting points | C35: Configuration value | D35: Incident handling within the agreed service levels: confirm the proposed target or give the BDOI value | E35: Production incidents are answered and resolved within the response and resolution times of their priority (P1 to P4) in the support service levels. | F35: At least 95% of incidents each month within the response and resolution times of their priority | G35: Non-functional requirements register v1.0, NFR-SUP-02; Production support approach and service levels (priorities P1 to P4) | H35: Head, BDOI IT | I35: 46356 | J35: High | K35: Open
A36: NFR-RET-01 | B36: BRD-00 Core Replacement and cross-cutting points | C36: Decision | D36: Retention per record type: decide the target; the BRDs give different values | E36: Each record type has its retention rule. | F36: Default 5 years online and 15 years archive; Claims 10 years online and 15 archive; Accounting vouchers and reports, Sanction Screening and Submitted Policies 5 years online and 5 archive | G36: Non-functional requirements register v1.0, NFR-RET-01; BRD-00 p.45 (5 / 15 years); BRD-7 p.41 (10 / 15); BRD-5 Add.1, BRD-10 p.25, BRD-12 p.14 (5 / 5); register DCR-136; CRQ22; also raised as CRQ22 (open question), DCR-167 (register item), DCR-209 (register item) | H36: BIBS Product Owner | I36: 46356 | J36: High | K36: Open | M36: Also affects BRD-05, BRD-07, BRD-09, BRD-10, BRD-12, BRD-13.
A37: NFR-RET-03 | B37: BRD-00 Core Replacement and cross-cutting points | C37: Decision | D37: Audit log retention: decide the target; the BRDs give different values | E37: Audit records outlive the records they describe. | F37: Audit records 5 years online and archived to 16 years | G37: Non-functional requirements register v1.0, NFR-RET-03; BRD-7 p.41 (audit logs archive 16 years); BRD-00 p.45 (5 / 15 years) | H37: Internal Audit, BDOI | I37: 46356 | J37: High | K37: Open
A38: NFR-INT-04 | B38: BRD-00 Core Replacement and cross-cutting points | C38: Configuration value | D38: File interfaces: confirm the proposed target or give the BDOI value | E38: Inbound files are validated, reconciled and reported. | F38: Every inbound file (PDC list, bills payment, bank and insurer files) validated against its layout; each run reconciled to its control totals; errors reported per row; a failed transfer retried up to 3 times | G38: Non-functional requirements register v1.0, NFR-INT-04; Programme alignment pack 5 (PMS, OBPCS, Old BOB, CMS / New BOB, insurer systems); FRS BRD-02 (payment files) | H38: Head, Operations | I38: 46356 | J38: High | K38: Open
A39: NFR-INT-05 | B39: BRD-00 Core Replacement and cross-cutting points | C39: Decision | D39: E-mail through CCM: decide the target; the BRDs give different values | E39: All outbound e-mail goes through the BDO communications service. | F39: 100% of outbound e-mail sent through CCM with its delivery status recorded | G39: Non-functional requirements register v1.0, NFR-INT-05; Drop plan integration CCM (INT-13); IQ11; also raised as IQ11 (open question) | H39: Head, BDOI IT | I39: 46356 | J39: High | K39: Open
A40: XQ04 | B40: BRD-00 Core Replacement and cross-cutting points | C40: Report layout | D40: Access classes of shared documents: Final confidentiality matrix per document type, including CSF (CSQ07, EBQ15) Background: The EB spec gives renewal advice the classes MARKETING and PROCESSING; CSF agents must view and resend RAs and claims reports; claims documents may be confidential | E40: Open point of the FRS (FR-CSF-033): the requirement cannot be finalised or tested as BDOI intends until it is answered. | F40: Treat master lists and utilization as sensitive personal information: need-to-know access classes, download logging, encryption. | G40: FRS BRD-09 v1.1, Open questions XQ04 (affects FR-CSF-033); Discrepancy and clarification register v1.2, open question XQ04; baseline Cross-BRD decisions section 5; also raised as EBQ15 (open question), CSQ07 (open question), DCR-094 (register item), DCR-148 (register item) | H40: Employee Benefits - Marketing, Processing and Collection | I40: 46356 | J40: High | K40: Open | M40: Also affects BRD-07, BRD-08, BRD-09.
A41: IQ01 | B41: BRD-00 Core Replacement and cross-cutting points | C41: Clarification | D41: Go-live date: (Priority 1) Which date in January 2028 is T? We propose Monday 3 January 2028, with the legacy freeze after the EOD of Wednesday 29 December 2027 and the legacy December / year-end close completed in legacy before the final extracts. If T is later in January, the migration rule "first business day of a month after a legacy month-end close" (DMQ25) no longer holds and the GL opening needs a short January period. | E41: Open point of the FRS: the requirement cannot be finalised or tested as BDOI intends until it is answered. | F41: T = Monday 3 January 2028; absolute trial-migration calendar Trial migration 1 Apr-May, Trial migration 2 Jun-Jul, Trial migration 3 Aug, re-load Oct, dress rehearsal Nov-Dec 2027. | G41: Discrepancy and clarification register v1.2, open question IQ01; baseline Timeline slide; answer A1; DMQ25, DMQ18; also raised as DCR-217 (register item) | H41: Enterprise Services Group - Business Project Services (Program Manager) with BDOI Comptrollership and Operations | I41: 46356 | J41: High | K41: Open | M41: Also affects BRD-13.
A42: IQ33 | B42: BRD-00 Core Replacement and cross-cutting points | C42: Sample document or template | D42: IER completeness: (Priority 2) Will BDOI IT add the Pre-Prod and DR cluster sheets, retitle the Pre-Prod sheet (it reads "UAT ENVIRONMENT") and replace the template rows of the environment cost sheets with the sizing of this document? | E42: Open point of the FRS: the requirement cannot be finalised or tested as BDOI intends until it is answered. | F42: Proposed: BIBS modular monolith with IER enterprise elements (edge security, managed AWS services, separate web, jobs and integration workloads), per the architecture option decision, awaiting BDOI confirmation. BDOI IT corrects the formula (or removes EFS), adds Pre-Prod and DR cluster sheets, fills the environment sheets from the alignment sizing and re-costs. | G42: Discrepancy and clarification register v1.2, open question IQ33; baseline IER Pre-Prod, K8s sheets; also raised as DCR-223 (register item) | H42: BDO Cloud and Digital Operations Engineering | I42: 46356 | J42: High | K42: Open
A43: XQ01 | B43: BRD-00 Core Replacement and cross-cutting points | C43: Report layout | D43: Two LAMD intakes: Is it one LAMD report (one file, one owner) or two different reports? Who uploads it? (RQ20, SP SQ06) Background: Renewal uploads LAMD paid-off / RMU reports (role LAMD); Submitted Policies uploads a LAMD loan snapshot. Both match on the PN | E43: Open point of the FRS: the requirement cannot be finalised or tested as BDOI intends until it is answered. | F43: One LAMD intake owned by one module and read by the other. | G43: Discrepancy and clarification register v1.2, open question XQ01; baseline Cross-BRD decisions section 5; also raised as RQ20 (open question), SP-SQ06 (open question), DCR-146 (register item) | H43: BIBS Product Owner, with the owners of the BRDs involved | I43: 46356 | J43: High | K43: Open | M43: Also affects BRD-06, BRD-12.
A44: XQ11 | B44: BRD-00 Core Replacement and cross-cutting points | C44: Decision | D44: Single session per device: Does it apply to all users? Background: (UQ09, rest of CQ23) | E44: Open point of the FRS: the requirement cannot be finalised or tested as BDOI intends until it is answered. | F44: Several roles per user allowed (BRD-11 governs access BIBS-wide); incompatible role pairs can be blocked as a segregation rule. | G44: Discrepancy and clarification register v1.2, open question XQ11; baseline Cross-BRD decisions section 5; also raised as CQ23 (open question), DCR-045 (register item), DCR-141 (register item) | H44: UAM process owner (Product Owner) with ITIO | I44: 46356 | J44: High | K44: Partly answered | M44: Answer so far: Lock-out at 3 for all users; several roles per user allowed. Single session per device open (UQ09). (BRD-11 p.13-14). Also affects BRD-04, BRD-07, BRD-11.
A45: DCR-010 | B45: BRD-00 Core Replacement and cross-cutting points | C45: Configuration value | D45: Confirm the two values (New Business, Renewal) and that a renewal with changed terms stays a Renewal (BRRN.033). | E45: Four BRDs require New Business / Renewal classification from creation to the invoice and as a report filter. BIBS booking sets every invoice to new business (booking InvoiceBuilder, line 129). Business: renewal production cannot be reported apart from new business. System: shared change BT0 (account business type, invoice, report filters). Test: every booking and production report test. | F45: One business type on the account (BT0) for all three BRDs, carried to the invoice and used as a report filter. | G45: Discrepancy and clarification register v1.2, DCR-010 (BRD vs platform); BRNB.097 (BRD-1); BRRN.033 (BRD-6, p.4-15); BRID-022.01 (BRD-8 Add. p.10); BRIDSP-26 / 27 (BRD-12 p.11) | H45: BIBS Product Owner, with the owners of the BRDs involved | I45: 46356 | J45: High | K45: Answered | M45: Answer so far: BRRN.033 (BRD-6), BRID-022.01 (BRD-8) and BRIDSP-26 / 27 (BRD-12) require the classification at creation and as a report filter. Also affects BRD-01, BRD-06, BRD-08, BRD-12.
A46: CLR-CR-01 | B46: BRD-00 Core Replacement and cross-cutting points | C46: Business rule confirmation | D46: Reinsurance: Confirm reinsurance in phase 2. | E46: The insurer-side reinsurance module does not fit the broker model. | F46: Phase 2: the ReInsurance BRD is received; phase 1 keeps party types, templates, subscriptions, open-item matching and event types open for the phase 2 module (section 6). | G46: FRS BRD-00 v1.1, Proposed business rules and clarifications; CORE-15.01-15.10 | H46: BIBS Product Owner with the Program Manager, Business Project Services | I46: 46356 | J46: Medium | K46: Open
A47: CLR-CR-04 | B47: BRD-00 Core Replacement and cross-cutting points | C47: Business rule confirmation | D47: Master data change log: Confirm the master data in the log (CRQ07). | E47: No function BRD owns the log. | F47: A field-level log of registered master data. | G47: FRS BRD-00 v1.1, Proposed business rules and clarifications; CORE-17.01; FR-CR-031; also raised as CRQ07 (open question), DCR-174 (register item) | H47: BIBS Product Owner, with the owners of the BRDs involved | I47: 46356 | J47: Medium | K47: Open
A48: CLR-CR-05 | B48: BRD-00 Core Replacement and cross-cutting points | C48: Business rule confirmation | D48: Insurer management: Confirm the insurer attributes (CRQ08). | E48: No function BRD owns the insurer record. | F48: An insurer page with the attributes the function BRDs do not hold. | G48: FRS BRD-00 v1.1, Proposed business rules and clarifications; CORE-17.02; FR-CR-061; also raised as CRQ08 (open question), DCR-176 (register item) | H48: Comptrollership - FRBS, Disbursement and ACSL | I48: 46356 | J48: Medium | K48: Open
A49: CLR-CR-06 | B49: BRD-00 Core Replacement and cross-cutting points | C49: Business rule confirmation | D49: MIS field definition: Confirm the catalogue (CRQ09). | E49: No function BRD owns MIS fields. | F49: A catalogue names the MIS fields of the existing data; users do not add data fields. | G49: FRS BRD-00 v1.1, Proposed business rules and clarifications; CORE-17.04; FR-CR-062; also raised as CRQ09 (open question), DCR-175 (register item), DCR-214 (register item) | H49: BIBS Product Owner, with the owners of the BRDs involved | I49: 46356 | J49: Medium | K49: Open | M49: Also affects BRD-05, BRD-11.
A50: CLR-CR-07 | B50: BRD-00 Core Replacement and cross-cutting points | C50: Report layout | D50: Report customisation: Confirm the variants. | E50: No function BRD owns report customisation. | F50: The user saves the layout of a report in a variant. | G50: FRS BRD-00 v1.1, Proposed business rules and clarifications; CORE-21.04; FR-CR-042 | H50: BIBS Product Owner with the Program Manager, Business Project Services | I50: 46356 | J50: Medium | K50: Open
A51: CLR-CR-08 | B51: BRD-00 Core Replacement and cross-cutting points | C51: Report layout | D51: Scheduled reports: Confirm the subscriptions. | E51: No function BRD owns report scheduling. | F51: The user subscribes to a report with a schedule and recipients (at most 20 active subscriptions per user by default). | G51: FRS BRD-00 v1.1, Proposed business rules and clarifications; CORE-21.05; FR-CR-043 | H51: BIBS Product Owner with the Program Manager, Business Project Services | I51: 46356 | J51: Medium | K51: Open
A52: CLR-CR-09 | B52: BRD-00 Core Replacement and cross-cutting points | C52: Clarification | D52: Emerging capabilities: List the capabilities (CRQ10). | E52: The capability is not defined (CRQ10). | F52: Not in scope until BDOI lists them. | G52: FRS BRD-00 v1.1, Proposed business rules and clarifications; CORE-18.01; also raised as CRQ10 (open question), DCR-180 (register item) | H52: Business Project Services (BRD owner) with the BIBS Product Owner | I52: 46356 | J52: Medium | K52: Open
A53: CLR-CR-10 | B53: BRD-00 Core Replacement and cross-cutting points | C53: Clarification | D53: ALeA e-mail address encoding: Define the requirement (CRQ20). | E53: The requirement is not defined (CRQ20). | F53: Not in scope until the requirement is defined. | G53: FRS BRD-00 v1.1, Proposed business rules and clarifications; XC-21; also raised as CRQ20 (open question), DCR-185 (register item) | H53: Business Project Services (BRD owner) with the BIBS Product Owner | I53: 46356 | J53: Medium | K53: Open
A54: CLR-CR-11 | B54: BRD-00 Core Replacement and cross-cutting points | C54: Report layout | D54: Role dashboards: Define the dashboard contents per role (CRQ06). | E54: The umbrella asks for centralised dashboards for all roles; the contents per role are open (CRQ06). | F54: Each role has a home page with its counts and queues, refreshed every 5 minutes by default. | G54: FRS BRD-00 v1.1, Proposed business rules and clarifications; XC-02; FR-CR-010, 011; also raised as CRQ06 (open question), DCR-178 (register item) | H54: BIBS Product Owner, with the owners of the BRDs involved | I54: 46356 | J54: Medium | K54: Open
A55: CLR-CR-12 | B55: BRD-00 Core Replacement and cross-cutting points | C55: Report layout | D55: Invoice Master List: Confirm the columns. | E55: No function BRD owns the list. | F55: The Invoice Master List columns are added to the invoice ledger view. | G55: FRS BRD-00 v1.1, Proposed business rules and clarifications; XC-13; FR-CR-090 | H55: BIBS Product Owner with the Program Manager, Business Project Services | I55: 46356 | J55: Medium | K55: Open
A56: CLR-CR-13 | B56: BRD-00 Core Replacement and cross-cutting points | C56: Clarification | D56: Insurer invoice batch: Answer CRQ18. | E56: The file format and whether the batch replaces the e-mail are open (CRQ18). | F56: A daily batch per insurer of the day's service invoices, stored and delivered through the insurer's channel; the file transfer channel is added when BDOI supplies the addresses. | G56: FRS BRD-00 v1.1, Proposed business rules and clarifications; XC-19; FR-CR-081; also raised as CRQ18 (open question), DCR-184 (register item) | H56: Marketing and Processing - New Business (Product Owner) | I56: 46356 | J56: Medium | K56: Open | M56: Also affects BRD-01.
A57: CLR-CR-14 | B57: BRD-00 Core Replacement and cross-cutting points | C57: Business rule confirmation | D57: Client migration and daily client batches: Confirm (CRQ19). | E57: The migration scope and coexistence are decided by the Data Migration BRD (CRQ19). | F57: Clients are loaded and fed through the Data Migration programme with the duplicate check. | G57: FRS BRD-00 v1.1, Proposed business rules and clarifications; XC-20; FR-CR-082; also raised as CRQ19 (open question) | H57: BIBS Product Owner with the Program Manager, Business Project Services | I57: 46356 | J57: Medium | K57: Open
A58: CLR-CR-15 | B58: BRD-00 Core Replacement and cross-cutting points | C58: Clarification | D58: SOA at booking: Answer CRQ12. | E58: The SOA of the placement report and booking is open (CRQ12). | F58: Booking issues the service invoice; the SOA is issued at booking once BDOI says which SOA is meant. | G58: FRS BRD-00 v1.1, Proposed business rules and clarifications; XC-10; FR-CR-093; also raised as CRQ12 (open question), DCR-171 (register item) | H58: Marketing and Processing - New Business (Product Owner) | I58: 46356 | J58: Medium | K58: Open | M58: Also affects BRD-01, BRD-04.
A59: CLR-CR-17 | B59: BRD-00 Core Replacement and cross-cutting points | C59: Business rule confirmation | D59: Design hand-over: Confirm that the UX documents meet BR-183, or name the Figma deliverables expected. | E59: BR-183 asks the vendor to use Figma for design execution; BIBS screens follow the platform design system. | F59: The design hand-over to the BDOI UX Design team is the 07 UX Screen Deck, the 08 UX screen register and the 09 image package of each business sign-off pack, which the team imports into its design tool; the project team does not keep the screens in Figma. | G59: FRS BRD-00 v1.1, Proposed business rules and clarifications; BR-183; XC-16; FR-CR-092 | H59: BIBS Product Owner with the Program Manager, Business Project Services | I59: 46356 | J59: Medium | K59: Open
A60: NFR-PRF-05 | B60: BRD-00 Core Replacement and cross-cutting points | C60: Configuration value | D60: Bulk uploads: confirm the proposed target or give the BDOI value | E60: An upload file is acknowledged at once and processed in the background with a result per row. | F60: Acknowledgement within 3 seconds; a 5,000-row file validated and committed within 10 minutes | G60: Non-functional requirements register v1.0, NFR-PRF-05; BRD-5 p.133-137 (upload or download 3 s per file); FRS BRD-01 (bulk uploads up to 5,000 rows per file) | H60: BIBS Product Owner | I60: 46356 | J60: Medium | K60: Open
A61: NFR-PRF-08 | B61: BRD-00 Core Replacement and cross-cutting points | C61: Configuration value | D61: Notifications and e-mail: confirm the proposed target or give the BDOI value | E61: Users are told of status changes, approvals and pending work without delay. | F61: In-app notification within 1 minute of the event; e-mail handed to CCM within 5 minutes | G61: Non-functional requirements register v1.0, NFR-PRF-08; FRS BRD-00 FR-CR-020; integration INT-13 (CCM) | H61: BIBS Product Owner | I61: 46356 | J61: Medium | K61: Open
A62: NFR-PRF-09 | B62: BRD-00 Core Replacement and cross-cutting points | C62: Configuration value | D62: Sign-in time: confirm the proposed target or give the BDOI value | E62: Single sign-on through EIAM completes quickly once the identity provider answers. | F62: p95 at most 3 seconds from the identity provider's answer to the role home page, excluding the user's own MFA entry | G62: Non-functional requirements register v1.0, NFR-PRF-09; Integration INT-01 (EIAM); BRD-1 p.210 peak hours 08:00-10:00 | H62: Head, BDOI IT | I62: 46356 | J62: Medium | K62: Open
A63: NFR-CAP-04 | B63: BRD-00 Core Replacement and cross-cutting points | C63: Configuration value | D63: File sizes: confirm the proposed target or give the BDOI value | E63: Users attach and upload files up to the limits; larger bulk files go straight to the document store. | F63: Attachments up to 10 MB a file; uploads through the screens up to 25 MB; bulk files up to 5 GB by direct transfer; limits are parameters | G63: Non-functional requirements register v1.0, NFR-CAP-04; Platform configuration (attachment and upload limits); BDO UX guidelines (format hint on upload fields) | H63: Head, BDOI IT | I63: 46356 | J63: Medium | K63: Open
A64: NFR-SCL-04 | B64: BRD-00 Core Replacement and cross-cutting points | C64: Configuration value | D64: Growth headroom: confirm the proposed target or give the BDOI value | E64: The production cluster carries the year-5 load with headroom. | F64: At the year-5 peak, CPU and memory use of the cluster below 70% | G64: Non-functional requirements register v1.0, NFR-SCL-04; IER K8S sheets (threshold 0.79 on worker nodes); programme alignment pack 6.4 | H64: Cloud and Digital Operations Engineering (IER owner) | I64: 46356 | J64: Medium | K64: Open
A65: NFR-PRV-04 | B65: BRD-00 Core Replacement and cross-cutting points | C65: Configuration value | D65: Data-subject requests: confirm the proposed target or give the BDOI value | E65: BDOI can answer a client's request to access or correct personal data. | F65: The personal data held on one client found and exported within 1 business day; corrections recorded with the audit trail | G65: Non-functional requirements register v1.0, NFR-PRV-04; Data Privacy Act 2012 (rights of the data subject); FRS BRD-09 (contact update with audit trail) | H65: Data Protection Officer, BDOI | I65: 46356 | J65: Medium | K65: Open
A66: NFR-PRV-06 | B66: BRD-00 Core Replacement and cross-cutting points | C66: Configuration value | D66: Security event alerts: confirm the proposed target or give the BDOI value | E66: Events that may indicate a personal-data breach reach BDO Information Security quickly. | F66: Alerts within 15 minutes for repeated failed sign-ins, privilege changes, refused data-scope access and exports above 10,000 rows | G66: Non-functional requirements register v1.0, NFR-PRV-06; Data Privacy Act 2012 (security incident management by the personal information controller); BRD-4 NFR 4 (audit exportable); BRD-11 UAM-NFR-40 (escalation of privilege changes) | H66: BDOI Information Security | I66: 46356 | J66: Medium | K66: Open
A67: NFR-ACC-04 | B67: BRD-00 Core Replacement and cross-cutting points | C67: Configuration value | D67: Zoom and reflow: confirm the proposed target or give the BDOI value | E67: Screens stay usable when users enlarge the text. | F67: Usable at 200% browser zoom and at a 320-pixel reflow width without loss of content or function | G67: Non-functional requirements register v1.0, NFR-ACC-04; WCAG 2.2 success criteria 1.4.4 and 1.4.10 | H67: BIBS Product Owner | I67: 46356 | J67: Medium | K67: Open
A68: NFR-USE-05 | B68: BRD-00 Core Replacement and cross-cutting points | C68: Configuration value | D68: Learnability: confirm the proposed target or give the BDOI value | E68: Trained users complete their main tasks without help. | F68: 90% of first attempts at the top task of each persona completed without help in UAT; System Usability Scale score of at least 75 in the UAT survey | G68: Non-functional requirements register v1.0, NFR-USE-05; BRD-9 p.13 (user-friendly, intuitive); BRD-00 BR-178 to BR-181 (design system and user journeys) | H68: BIBS Product Owner | I68: 46356 | J68: Medium | K68: Open
A69: NFR-LOC-04 | B69: BRD-00 Core Replacement and cross-cutting points | C69: Configuration value | D69: Philippine formats and calendar: confirm the proposed target or give the BDOI value | E69: Philippine identifiers, addresses and working days are handled correctly. | F69: TIN, mobile numbers and addresses (region, province, city or municipality, barangay) validated to Philippine formats; business-day rules follow the holiday calendar kept by the Business Administrator | G69: Non-functional requirements register v1.0, NFR-LOC-04; FRS BRD-01 (client record, EOPT details: TIN and registered address); programme alignment pack 4.2 (non-working days of the go-live calendar) | H69: BIBS Product Owner | I69: 46356 | J69: Medium | K69: Open
A70: NFR-MNT-06 | B70: BRD-00 Core Replacement and cross-cutting points | C70: Configuration value | D70: Documentation kept current: confirm the proposed target or give the BDOI value | E70: The technical and support documents match each release. | F70: Technical specification, configuration guide, runbook and data dictionary updated with each release; release notes list every changed function | G70: Non-functional requirements register v1.0, NFR-MNT-06; BRD-11 UAM-NFR-29 (system documentation); deliverables plan items 23 to 25 | H70: Head, BDOI IT | I70: 46356 | J70: Medium | K70: Open
... A72: NFR-INT-06 | B72: BRD-00 Core Replacement and cross-cutting points | C72: Configuration value | D72: Unavailable partner systems: confirm the proposed target or give the BDOI value | E72: An unavailable external system does not block users. | F72: Outbound messages queued and retried for 24 hours; an alert after 3 failed attempts; users keep working | G72: Non-functional requirements register v1.0, NFR-INT-06; Programme alignment pack 5 (integration inventory) | H72: Head, BDOI IT | I72: 46356 | J72: Medium | K72: Open
A73: CRQ01 | B73: BRD-00 Core Replacement and cross-cutting points | C73: Clarification | D73: BRD set and ownership: The umbrella lists ten BRDs (p.3) and cites a "User & Data Management" BRD (pp.38-41). Is it the umbrella over all twelve BRDs, the Data Migration BRD and the ReInsurance BRD? Who owns Data Management (capability 17)? | E73: Open point of the FRS (Scope): the requirement cannot be finalised or tested as BDOI intends until it is answered. | F73: Umbrella over all BRDs; capability 17 owned by the BIBS Product Owner. | G73: FRS BRD-00 v1.1, Open questions CRQ01 (affects Scope); Discrepancy and clarification register v1.2, open question CRQ01; baseline CF-07, CORE-17; also raised as DCR-169 (register item), DCR-201 (register item) | H73: Business Project Services (BRD owner) with the BIBS Product Owner | I73: 46356 | J73: Medium | K73: Open | M73: Also affects BRD-13.
A74: CRQ05 | B74: BRD-00 Core Replacement and cross-cutting points | C74: Decision | D74: Delete of prospect: Is deactivation with a reason, followed by the retention purge, acceptable for "delete of prospect / record" (BR-008), or must a prospect be erased on request (for example under the Data Privacy Act)? | E74: Open point of the FRS (A-CR-03): the requirement cannot be finalised or tested as BDOI intends until it is answered. | F74: Deactivation plus retention purge. | G74: FRS BRD-00 v1.1, Open questions CRQ05 (affects A-CR-03); Discrepancy and clarification register v1.2, open question CRQ05; baseline CORE-01.04; also raised as DCR-182 (register item) | H74: Marketing and Processing - New Business (Product Owner) | I74: 46356 | J74: Medium | K74: Open | M74: Also affects BRD-01.
A75: CRQ13 | B75: BRD-00 Core Replacement and cross-cutting points | C75: Report layout | D75: Invoice Master List: Is the Invoice Master List (BR-175) the Operations invoice ledger? Please confirm the columns (cover number, version number, assignees, placement status, approval dates) and the owner. | E75: Open point of the FRS (FR-CR-090): the requirement cannot be finalised or tested as BDOI intends until it is answered. | F75: Extend the invoice ledger view (FR-CR-090). | G75: FRS BRD-00 v1.1, Open questions CRQ13 (affects FR-CR-090); Discrepancy and clarification register v1.2, open question CRQ13; baseline XC-13; also raised as DCR-179 (register item) | H75: Operations - Financial Transactions and Processing | I75: 46356 | J75: Medium | K75: Open | M75: Also affects BRD-02.
A76: CRQ14 | B76: BRD-00 Core Replacement and cross-cutting points | C76: Sample document or template | D76: Letter names: The umbrella writes "Non-Renewal Letter (NRL)", BRD-6 "Not for Renewal Letter (NFR)". Which name is printed on the letter? | E76: Open point of the FRS (CORE-06.07): the requirement cannot be finalised or tested as BDOI intends until it is answered. | F76: Use the BRD-6 name until answered. | G76: FRS BRD-00 v1.1, Open questions CRQ14 (affects CORE-06.07); Discrepancy and clarification register v1.2, open question CRQ14; baseline CORE-06.07; also raised as DCR-168 (register item) | H76: Marketing and Processing - Renewal (RMEL) | I76: 46356 | J76: Medium | K76: Open | M76: Also affects BRD-06.
A77: CRQ15 | B77: BRD-00 Core Replacement and cross-cutting points | C77: Clarification | D77: Bank account operations: What does "Bank Account Operations" (p.9) cover beyond the account funding and bank instruments of BRD-5? | E77: Open point of the FRS (CORE-08.21): the requirement cannot be finalised or tested as BDOI intends until it is answered. | G77: FRS BRD-00 v1.1, Open questions CRQ15 (affects CORE-08.21); Discrepancy and clarification register v1.2, open question CRQ15; baseline CORE-08.21 | H77: BIBS Product Owner with the Program Manager, Business Project Services | I77: 46356 | J77: Medium | K77: Open
A78: CRQ16 | B78: BRD-00 Core Replacement and cross-cutting points | C78: Clarification | D78: CSF resend: Must CSF agents also resend e-policies (BR-164), or only RAs (BRCSF-006)? | E78: Open point of the FRS (CORE-16.04): the requirement cannot be finalised or tested as BDOI intends until it is answered. | F78: RA only until answered. | G78: FRS BRD-00 v1.1, Open questions CRQ16 (affects CORE-16.04); Discrepancy and clarification register v1.2, open question CRQ16; baseline CORE-16.04; also raised as DCR-172 (register item) | H78: Contact Center Management / Alternative Distribution | I78: 46356 | J78: Medium | K78: Partly answered | M78: Answer so far: BRD-9 e-mail item 9; FR-CSF-031. Also affects BRD-09.
A79: CRQ17 | B79: BRD-00 Core Replacement and cross-cutting points | C79: Clarification | D79: BDO design assets: Please supply the BDO icon and illustration set and the design system or Figma files (BR-179, 180, 183). | E79: Open point of the FRS (FR-CR-092): the requirement cannot be finalised or tested as BDOI intends until it is answered. | F79: Treat as design-system items (FR-CR-092). | G79: FRS BRD-00 v1.1, Open questions CRQ17 (affects FR-CR-092); Discrepancy and clarification register v1.2, open question CRQ17; baseline XC-14; also raised as DCR-187 (register item) | H79: Business Project Services (BRD owner) with the BIBS Product Owner | I79: 46356 | J79: Medium | K79: Open
A80: CRQ23 | B80: BRD-00 Core Replacement and cross-cutting points | C80: Business rule confirmation | D80: Traceability workbook: Please send "E2E BDOI Mapping.xlsx" (p.30) and confirm that the final IDs of each BRD (BRPM, BRRN, BRCLXN, BRCLM, BRCSF) govern where the umbrella cites earlier ones. | E80: Open point of the FRS (Section 10): the requirement cannot be finalised or tested as BDOI intends until it is answered. | F80: Final IDs of each BRD govern. | G80: FRS BRD-00 v1.1, Open questions CRQ23 (affects Section 10); Discrepancy and clarification register v1.2, open question CRQ23; baseline CF-08, §10; also raised as DCR-170 (register item) | H80: Business Project Services (BRD owner) with the BIBS Product Owner | I80: 46356 | J80: Medium | K80: Open | M80: Also affects BRD-03.
A81: CRQ25 | B81: BRD-00 Core Replacement and cross-cutting points | C81: Clarification | D81: Approval of the umbrella: The Product Owner for FRBS and ACSL is marked "On Mandatory Leave" without a signature; the Analytics and Risk Management head marks "sign-off not applicable"; four approvals are by e-mail only (pp.46-48). Is the document approved? | E81: Open point of the FRS (Sign-off): the requirement cannot be finalised or tested as BDOI intends until it is answered. | F81: Confirm approval. | G81: FRS BRD-00 v1.1, Open questions CRQ25 (affects Sign-off); Discrepancy and clarification register v1.2, open question CRQ25; baseline §14; also raised as DCR-186 (register item) | H81: Business Project Services (BRD owner) with the BIBS Product Owner | I81: 46356 | J81: Medium | K81: Open
A82: XQ02 | B82: BRD-00 Core Replacement and cross-cutting points | C82: Report layout | D82: Two Contact Center roles: Are they the same people (BDO Contact Center vs BDOI staff)? One role or two? (RQ21, CSQ10) Background: Renewal's contact center (follow-ups, remarks, documents on candidates, BRRN.026) and CSF's csf agent / csf supervisor (servicing). Renewal restricts Contact Center to a read-only projection without premium columns; CSF agents see all accounts | E82: Open point of the FRS (Section 3.1): the requirement cannot be finalised or tested as BDOI intends until it is answered. | F82: Two roles; one user may hold both. | G82: FRS BRD-09 v1.1, Open questions XQ02 (affects Section 3.1); Discrepancy and clarification register v1.2, open question XQ02; baseline Cross-BRD decisions section 5; also raised as RQ21 (open question), CSQ10 (open question), DCR-147 (register item) | H82: BIBS Product Owner, with the owners of the BRDs involved | I82: 46356 | J82: Medium | K82: Open | M82: Also affects BRD-06, BRD-09.
A83: XQ05 | B83: BRD-00 Core Replacement and cross-cutting points | C83: Report layout | D83: What is a "claims report" (BRCSF-009): Which claim documents does the contact centre retrieve, and should claim documents use the platform document type list or bcl document type? (CLQ26, CSQ07) Background: Claims keeps its own document-type LOV (bcl document type: PLA, CRF, estimate, offer, LOA, release papers...); CSF expects claim report | E83: Open point of the FRS (FR-CSF-033): the requirement cannot be finalised or tested as BDOI intends until it is answered. | G83: FRS BRD-09 v1.1, Open questions XQ05 (affects FR-CSF-033); Discrepancy and clarification register v1.2, open question XQ05; baseline Cross-BRD decisions section 5; also raised as CLQ26 (open question) | H83: BIBS Product Owner with the Program Manager, Business Project Services | I83: 46356 | J83: Medium | K83: Open
A84: IQ02 | B84: BRD-00 Core Replacement and cross-cutting points | C84: Configuration value | D84: Renewals around cut-over: (Priority 2) With the early renewal release withdrawn, please confirm that (a) legacy extracts, disposes, places and books all renewals up to T, (b) the RMEL cohorts expiring from T to T+140 days are carried forward into BIBS with their disposition (object P03), and (c) renewals expiring between the freeze and T are placed in legacy before the freeze or covered by hold covers. | E84: Open point of the FRS: the requirement cannot be finalised or tested as BDOI intends until it is answered. | F84: The paper is recorded as superseded as an operating model; its capabilities stay in scope for January 2028. | G84: Discrepancy and clarification register v1.2, open question IQ02; baseline Concept paper (superseded); answer A1; DMQ26; also raised as DCR-218 (register item), DCR-220 (register item) | H84: Marketing and Processing - Renewal (RMEL) | I84: 46356 | J84: Medium | K84: Answered | M84: Answer so far: January-May 2028 expiries are processed in BIBS after go-live (go-live extraction to 31-May-2028, January expiries urgent); no carry-forward of legacy cohorts. (BDOI answer 26-Sep-2026 (DMQ37)); BDOI answer of 26-Sep-2026: every module goes live together in January 2028; there is no early go-live.; BDOI answer of 26-Sep-2026 (DMQ37): renewals expiring January to May 2028 are processed in BIBS after go-live; no renewal candidates are carried from legacy. At go-live BIBS extracts every expiry from go-live to 31-May-2028 into the renewal pipeline, prioritis. Also affects BRD-06, BRD-13.
A85: IQ21 | B85: BRD-00 Core Replacement and cross-cutting points | C85: Clarification | D85: Marketing Collection (extraction): (Priority 2) What is "Marketing Collection (extraction)" in Drop 2? BRD-4 Collections is a BIBS module fed by the Operations ledger; is a separate Collection Management System kept, with an extraction from BIBS? | E85: Open point of the FRS: the requirement cannot be finalised or tested as BDOI intends until it is answered. | F85: BRD-4 in BIBS replaces the Collection Management System; the item means the Collections daily files; BRD-4 tested in Drop 2 except the DP rows (Drop 1). | G85: Discrepancy and clarification register v1.2, open question IQ21; baseline Drop plan 2.1; BRD-4; also raised as DCR-212 (register item) | H85: Operations - Collections (Head of BDOI Operations) | I85: 46356 | J85: Medium | K85: Open | M85: Also affects BRD-02, BRD-04.
A86: IQ23 | B86: BRD-00 Core Replacement and cross-cutting points | C86: Clarification | D86: Unplaced BRDs: (Priority 2) In which drop are BRD-10 Sanction Screening (we propose Drop 1 with Client Onboarding) and the CSF service-request functions (we propose Drop 2)? | E86: Open point of the FRS: the requirement cannot be finalised or tested as BDOI intends until it is answered. | F86: BRD-10 in Drop 1 with Client Onboarding (screening at onboarding); CSF service requests in Drop 2. | G86: Discrepancy and clarification register v1.2, open question IQ23; baseline Drop plan; also raised as DCR-213 (register item) | H86: BIBS Product Owner, with the owners of the BRDs involved | I86: 46356 | J86: Medium | K86: Open | M86: Also affects BRD-09, BRD-10.
A87: IQ28 | B87: BRD-00 Core Replacement and cross-cutting points | C87: Clarification | D87: VDI and access: (Priority 2) Does "access restricted to personnel in the Philippines" apply to DEV and SIT with masked data? Which vendor staff need VDI? Software list: Temurin 21, Maven 3.9, Node 22 (not JDK 17, Node 20, Angular). | E87: Open point of the FRS: the requirement cannot be finalised or tested as BDOI intends until it is answered. | F87: Production and UAT only from the Philippines; DEV and SIT with masked data reachable by named vendor staff through VDI. | G87: Discrepancy and clarification register v1.2, open question IQ28; baseline IER VDI Requirements; hosting appendix; also raised as DCR-231 (register item) | H87: BDO Cloud and Digital Operations Engineering with Compliance | I87: 46356 | J87: Medium | K87: Open
A88: IQ29 | B88: BRD-00 Core Replacement and cross-cutting points | C88: Clarification | D88: CI / CD toolchain: (Priority 2) Which toolchain applies: GitLab (HW sheet), a second CI toolchain named in the IER (infra diagram) or ArgoCD + Helm (diagram)? Container registry, image base (RHEL UBI or Alpine), SonarQube instance. | E88: Open point of the FRS: the requirement cannot be finalised or tested as BDOI intends until it is answered. | G88: Discrepancy and clarification register v1.2, open question IQ29; baseline IER sheets | H88: BIBS Product Owner with the Program Manager, Business Project Services | I88: 46356 | J88: Medium | K88: Open
A89: IQ32 | B89: BRD-00 Core Replacement and cross-cutting points | C89: Clarification | D89: Sizing basis: (Priority 2) Which user figures size the platform: 1,200 internal users (IER diagram) or 1,344 named / 429 concurrent (umbrella BRD p.42)? Transactions per second per year (IER K8s guideline 3). | E89: Open point of the FRS: the requirement cannot be finalised or tested as BDOI intends until it is answered. | G89: Discrepancy and clarification register v1.2, open question IQ32; baseline IER; DCR-166 | H89: BIBS Product Owner with the Program Manager, Business Project Services | I89: 46356 | J89: Medium | K89: Open
A90: IQ34 | B90: BRD-00 Core Replacement and cross-cutting points | C90: Business rule confirmation | D90: ElastiCache mode: (Priority 3) Please confirm cluster mode disabled (one shard, Multi-AZ replica) for Pre-Prod and PROD; "cluster" in the HW sheet would need a code change. | E90: Open point of the FRS: the requirement cannot be finalised or tested as BDOI intends until it is answered. | F90: ElastiCache for Valkey 8 (in place of Redis 7, client decision of 08-Oct-2026), cluster mode disabled, Multi-AZ replica. | G90: Discrepancy and clarification register v1.2, open question IQ34; baseline IER HW & SW Requirements; also raised as DCR-228 (register item) | H90: BDO Cloud and Digital Operations Engineering | I90: 46356 | J90: Medium | K90: Open
A91: DSQ01 | B91: BRD-00 Core Replacement and cross-cutting points | C91: Decision | D91: Document storage (S3): Which DR region is approved for the cross-border basis (the IER workbook plans a cross-region replica)? | E91: Open point of the FRS: the requirement cannot be finalised or tested as BDOI intends until it is answered. | G91: Discrepancy and clarification register v1.2, open question DSQ01; baseline Document storage proposal Open points for BDOI IT | H91: BIBS Product Owner with the Program Manager, Business Project Services | I91: 46356 | J91: Medium | K91: Open
A92: DSQ03 | B92: BRD-00 Core Replacement and cross-cutting points | C92: Clarification | D92: Document storage (S3): The DOA roles allowed to place and release legal holds and to authorise a governance bypass | E92: Open point of the FRS: the requirement cannot be finalised or tested as BDOI intends until it is answered. | G92: Discrepancy and clarification register v1.2, open question DSQ03; baseline Document storage proposal Open points for BDOI IT | H92: BIBS Product Owner with the Program Manager, Business Project Services | I92: 46356 | J92: Medium | K92: Open
A93: DSQ04 | B93: BRD-00 Core Replacement and cross-cutting points | C93: Clarification | D93: Document storage (S3): Key policy details: key administrators, rotation period, and whether imported key material is required | E93: Open point of the FRS: the requirement cannot be finalised or tested as BDOI intends until it is answered. | G93: Discrepancy and clarification register v1.2, open question DSQ04; baseline Document storage proposal Open points for BDOI IT | H93: BIBS Product Owner with the Program Manager, Business Project Services | I93: 46356 | J93: Medium | K93: Open
A94: XQ06 | B94: BRD-00 Core Replacement and cross-cutting points | C94: Report layout | D94: Renewal persistency report: Layout and definition of the general Renewal Persistency Report Background: Report List #135: SP proposes SBM-PERSISTENCY for submitted accounts and says the general report belongs to Renewal; the Renewal FRS has no persistency report | E94: Open point of the FRS: the requirement cannot be finalised or tested as BDOI intends until it is answered. | F94: General persistency report in Renewal over closed renewal candidates. | G94: Discrepancy and clarification register v1.2, open question XQ06; baseline Cross-BRD decisions section 5; also raised as DCR-149 (register item) | H94: Marketing and Processing - Renewal (RMEL) | I94: 46356 | J94: Medium | K94: Open | M94: Also affects BRD-06, BRD-12.
A95: XQ07 | B95: BRD-00 Core Replacement and cross-cutting points | C95: Configuration value | D95: Question-ID collision: Rename one series (e.g. SANC to SNQ) or always cite with the BRD prefix? Background: SP SQ01-SQ25 and SANC SQ01-SQ20 share the prefix | E95: Open point of the FRS: the requirement cannot be finalised or tested as BDOI intends until it is answered. | G95: Discrepancy and clarification register v1.2, open question XQ07; baseline Cross-BRD decisions section 5 | H95: BIBS Product Owner with the Program Manager, Business Project Services | I95: 46356 | J95: Medium | K95: Open
A96: XQ09 | B96: BRD-00 Core Replacement and cross-cutting points | C96: Report layout | D96: Late renewal requests report: Is it still needed, and is it a Renewal listing variant? (RQ29) Background: (BRNB.018, Q09). Neither the RN BRD nor the Report List (#182 is a package report) defines it | E96: Open point of the FRS: the requirement cannot be finalised or tested as BDOI intends until it is answered. | F96: Provide it in Renewal as a variant of the renewal listing (renewals booked after expiry). | G96: Discrepancy and clarification register v1.2, open question XQ09; baseline Cross-BRD decisions section 5; also raised as DCR-009 (register item) | H96: Marketing and Processing - Renewal (RMEL) | I96: 46356 | J96: Medium | K96: Open | M96: Also affects BRD-01, BRD-06, BRD-12.
A97: XQ10 | B97: BRD-00 Core Replacement and cross-cutting points | C97: Decision | D97: Total-loss indicator: Should Claims record a total-loss indicator (settlement type, loss nature or flag)? Background: (CLQ28, RQ13) | E97: Open point of the FRS: the requirement cannot be finalised or tested as BDOI intends until it is answered. | F97: Renewal reads claim experience from Claims; "Total Loss Claim" stays a manual reason until Claims records an indicator. | G97: Discrepancy and clarification register v1.2, open question XQ10; baseline Cross-BRD decisions section 5; also raised as DCR-150 (register item) | H97: BIBS Product Owner, with the owners of the BRDs involved | I97: 46356 | J97: Medium | K97: Open | M97: Also affects BRD-06, BRD-07.
A98: XQ13 | B98: BRD-00 Core Replacement and cross-cutting points | C98: Decision | D98: Claims cheque custody: Does BDOI hold settlement cheques, which unit keeps them, and what is recorded at hand-over and release? (CRQ03, CLQ10) Background: (Core CF-02). The umbrella asks for safekeeping of unclaimed cheques and hand-over to and retrieval from Cashiering (BR-146 to BR-148, p.21); BRD-7 has no claim money through BDOI | E98: Open point of the FRS: the requirement cannot be finalised or tested as BDOI intends until it is answered. | G98: Discrepancy and clarification register v1.2, open question XQ13; baseline Cross-BRD decisions section 5 | H98: BIBS Product Owner with the Program Manager, Business Project Services | I98: 46356 | J98: Medium | K98: Open
A99: DCR-130 | B99: BRD-00 Core Replacement and cross-cutting points | C99: Decision | D99: Note the proposed handling (no answer needed unless BDOI disagrees): Rows marked DROPPED; not in scope. | E99: #73 and #168 carry "DELETE - Same as Policy Transmittal Report / Report on... e-Policies"; #69 "BU confirmed that they do not need this report anymore". System: three reports dropped. | F99: Rows marked DROPPED; not in scope. | G99: Discrepancy and clarification register v1.2, DCR-130 (Document quality); Report List #69 (p.24), #73 (p.25), #168 (p.54) | H99: Report SMEs named in the Report List | I99: 46356 | J99: Low | K99: Answered | M99: Answer so far: Report List remarks on #69, #73 and #168.
A100: DCR-159 | B100: BRD-00 Core Replacement and cross-cutting points | C100: Business rule confirmation | D100: Confirm the registered name and the short name (BDOI or BDOIR) for outputs. | E100: The company name varies: "BDO Insurance Brokers, Inc." (BRD-2 Annex I, BRD-5 Appendix D, BRD-6 approval), "BDO Insurance and Brokerage, Inc." (BRD-5 Appendix C, BRD-11 p.5), "BDO Insurance and Brokers Inc." (BRD-11 p.19), BDOIR (BRD-10), against "BDO Insurance and Reinsurance Brokers, Inc.". Templates and report headers must use the registered name. | F100: Use "BDO Insurance and Reinsurance Brokers, Inc." on every output. | G100: Discrepancy and clarification register v1.2, DCR-159 (Document quality); BRD-2 Annex I (p.124); BRD-5 Appendix C (p.149), Appendix D; BRD-11 p.5, p.19; BRD-10 (BDOIR); BRD-6 approval (p.188-189) | H100: BIBS Product Owner, with the owners of the BRDs involved | I100: 46356 | J100: Low | K100: Open | M100: Also affects BRD-02, BRD-05, BRD-06, BRD-08, BRD-10, BRD-11.
A101: DCR-183 | B101: BRD-00 Core Replacement and cross-cutting points | C101: Business rule confirmation | D101: BR-196, 197, 198 repeat BR-184, 185, 186; BR-004 has no priority. Confirm the duplicates can be removed. | E101: BR-196, 197, 198 repeat BR-184, 185, 186; BR-004 has no priority. None on the system. | F101: Correct in the next revision. | G101: Discrepancy and clarification register v1.2, DCR-183 (Data / numbering issue); BR-184-198 (p.23-24); BR-004 (p.13) | H101: Business Project Services (BRD owner) with the BIBS Product Owner | I101: 46356 | J101: Low | K101: Open
A102: DCR-188 | B102: BRD-00 Core Replacement and cross-cutting points | C102: Clarification | D102: Both FRS number requirements FR-CL-nnn; 28 IDs exist in both documents. None (project correction). | E102: Both FRS number requirements FR-CL-nnn; 28 IDs exist in both documents. Test plans and RTM cannot key on the FR ID alone. | F102: Renumber Claims to FR-CM-nnn. Applied on 26 September 2026 to the Claims FRS, the Claims test plan (case IDs TC-CM, SC-CM, TD-CM) and the Core Replacement spec and FRS; Collections keeps FR-CL-nnn. | G102: Discrepancy and clarification register v1.2, DCR-188 (Document quality); FRS BRD-04 and FRS BRD-07 sources | H102: BIBS Product Owner, with the owners of the BRDs involved | I102: 46356 | J102: Low | K102: Open | M102: Also affects BRD-04, BRD-07.
...

Sheet BRD-01 New Business
A1: BRD-01 New Business
A2: BRD-01 New Business: what BDOI provides; owner Product Owner, New Business
A4: Ref | B4: BRD / module | C4: Type | D4: What we need from BDOI | E4: Why / impact if not provided | F4: Our proposal (if any) | G4: Source (FRS section / CLR / BRD page) | H4: BDOI owner (role) | I4: Needed by | J4: Priority | K4: Status | L4: BDOI response | M4: Remarks
A5: CLR-NB-17 | B5: BRD-01 New Business | C5: Business rule confirmation | D5: Placement file to insurers: Specify the insurer channels or confirm e-mail only (Q06). | E5: The electronic channels to insurers (file transfer or system-to-system) are not specified (Q06). | F5: Slips are sent by e-mail when Processing clicks Send. An insurer set up for another channel is refused with a message until the electronic channels are specified. | G5: FRS BRD-01 v2.1, Proposed business rules and clarifications; BRNB.071; FR-NB-081; also raised as Q06 (open question), DCR-211 (register item) | H5: Employee Benefits - Marketing, Processing and Collection | I5: 46356 | J5: High | K5: Partly answered | M5: Answer so far: For EB, insurers use a secure portal or Interface. Other lines: still e-mail. (BRD-8 BRID-005, 005.01-005.02, 009). Also affects BRD-00, BRD-08.
A6: CLR-NB-23 | B6: BRD-01 New Business | C6: Clarification | D6: Tags and instructions: Name the tags that block and the final list of tags and instructions (Q18). | E6: Which tags block a process, and the final list, are not given (Q18). | F6: Tags and instructions show as a banner that warns; they do not block a process. BRD-10 sets PEP and watchlist review by rule. | G6: FRS BRD-01 v2.1, Proposed business rules and clarifications; BRNB.091; FR-NB-036; also raised as Q18 (open question), DCR-112 (register item) | H6: Compliance (Chief Compliance Officer) | I6: 46356 | J6: High | K6: Partly answered | M6: Answer so far: PEP and high-risk tags are set by rules and trigger reviews. Block vs warn still open (SANC-SQ07). (BRD-10 SNSRP-302 / 303). Also affects BRD-06, BRD-10.
A7: CLR-NB-31 | B7: BRD-01 New Business | C7: Clarification | D7: Multi-year policies: Give the multi-year basis (Q35). | E7: The basis (upfront or yearly) is not given (Q35). | F7: The premium and commission basis of a multi-year policy follows BDOI's answer; each year is invoiced separately until then. | G7: FRS BRD-01 v2.1, Proposed business rules and clarifications; FR-NB-114; also raised as Q35 (open question), DCR-006 (register item) | H7: Marketing and Processing - New Business (Product Owner) | I7: 46356 | J7: High | K7: Partly answered | M7: Answer so far: Multi-year policies are billed per billing cycle. Accounting per cycle open. (BRD-4 BRCLXN.058).
A8: CLR-NB-32 | B8: BRD-01 New Business | C8: Business rule confirmation | D8: Premium tax and Motor bases: Confirm the premium tax basis (Q43) and the multi-year basis (Q35). | E8: The premium tax basis is to be confirmed (Q43). | F8: The Fire premium tax of 12% of net premium and the Motor OD / Theft bases of 90% and 81% of TSI are applied as written, as rates in the catalogue. | G8: FRS BRD-01 v2.1, Proposed business rules and clarifications; Appendix A; also raised as Q43 (open question), DCR-005 (register item) | H8: Marketing and Processing - New Business (Product Owner) | I8: 46356 | J8: High | K8: Open
A9: Q13 | B9: BRD-01 New Business | C9: Business rule confirmation | D9: Client code: BRNB.029 requires a client code for every quotation; BRNB.063 allows quotation without client code. Confirm: auto-create prospect code at quotation? | E9: Open point of the FRS (FR-NB-041, 046): the requirement cannot be finalised or tested as BDOI intends until it is answered. | F9: Allow a quotation without a confirmed client, and create a prospect client code automatically at quotation (BRNB.029 then holds for the prospect code). | G9: FRS BRD-01 v2.1, Open questions Q13 (affects FR-NB-041, 046); Discrepancy and clarification register v1.2, open question Q13; baseline BRNB.029, 063; also raised as DCR-001 (register item) | H9: Marketing and Processing - New Business (Product Owner) | I9: 46356 | J9: High | K9: Open
A10: SO-01-1 | B10: BRD-01 New Business | C10: Sign-off | D10: Sign the FRS and sign-off set of BRD-01 New Business. | E10: The signed document fixes the scope for the next step of the plan; a late sign-off moves the dates that follow it. | G10: Project plan v1.0 (8-Oct-2026), sign-offs and milestones | H10: Product Owner, New Business; Business Project Services (traceability) | I10: 46356 | J10: High | K10: Open
A11: CLR-NB-01 | B11: BRD-01 New Business | C11: Master data | D11: Approval levels: Give the approval chain by amount, product or segment, or confirm one approval stage (Q05). | E11: The BRD asks for TL, then TH, then UH; the chain by amount, product or segment is not given (Q05). | F11: One approval stage per quotation and per PRF: any holder of the approval permission other than the maker approves. | G11: FRS BRD-01 v2.1, Proposed business rules and clarifications; BRNB.005, 014; FR-NB-014, 043, 051; also raised as Q05 (open question) | H11: Product Owner, New Business | I11: 46356 | J11: Medium | K11: Partly answered | M11: Answer so far: Package requests: approved by the Marketing TL, TH or UH; TSU TL recommends, TH approves; ManCom sign-off. No amount limits. (BRD-3 BRPM.008 / 009 / 012 / 015, PMADD06).
A12: CLR-NB-03 | B12: BRD-01 New Business | C12: Report layout | D12: Late Renewal Requests Report: Confirm the Renewal listing variant (Q09, RQ29). | E12: The report concerns renewals; Report List #182 is a package report. | F12: A variant of the Renewal listing (RNW-LISTING) of BRD-6, restricted by role, in place of a New Business report. | G12: FRS BRD-01 v2.1, Proposed business rules and clarifications; BRNB.018; FR-NB-126; also raised as Q09 (open question), RQ29 (open question) | H12: Product Owner, New Business | I12: 46356 | J12: Medium | K12: Open
A13: CLR-NB-04 | B13: BRD-01 New Business | C13: Business rule confirmation | D13: Delete in-process records: Confirm void in place of delete. | E13: Every record is kept for the audit trail. | F13: A record is voided with a reason, hidden from the standard lists and found with the filter Include voided; it is never deleted. | G13: FRS BRD-01 v2.1, Proposed business rules and clarifications; BRNB.019; FR-NB-012 | H13: Product Owner, New Business | I13: 46356 | J13: Medium | K13: Open
A14: CLR-NB-05 | B14: BRD-01 New Business | C14: Business rule confirmation | D14: Status list: Confirm the stage list and its service levels (Q10). | E14: Endorsements are transactions on a booked account, not a stage of the account. | F14: The statuses are the stages of the four workflows (client, quotation, PRF, account). "Endorsed" shows as the endorsement invoices of a booked account. | G14: FRS BRD-01 v2.1, Proposed business rules and clarifications; BRNB.022; FR-NB-010; also raised as Q10 (open question) | H14: Product Owner, New Business | I14: 46356 | J14: Medium | K14: Partly answered | M14: Answer so far: Renewal stages and statuses, and package negotiation outcomes. Counter mapping still to confirm. (BRD-6 personas, tabs, counters, BRRN.040; BRD-3 PMADD04).
A15: CLR-NB-07 | B15: BRD-01 New Business | C15: Business rule confirmation | D15: Client code of a quotation: Confirm the automatic prospect and the confirmed client at account creation. | E15: The BRD requires a client code and also allows a quotation without one. | F15: A quotation without a client code creates a prospect automatically; a confirmed client is required from account creation. | G15: FRS BRD-01 v2.1, Proposed business rules and clarifications; BRNB.029, 063; FR-NB-041, 046 | H15: Product Owner, New Business | I15: 46356 | J15: Medium | K15: Open
A16: CLR-NB-08 | B16: BRD-01 New Business | C16: Report layout | D16: Print options: Confirm A4 only and separate summary and detail reports. | E16: BDOI stationery is A4; a summary / detail switch per report is replaced by separate reports. | F16: Reports print on A4 only. Summary reports and detail reports with group subtotals are separate reports. | G16: FRS BRD-01 v2.1, Proposed business rules and clarifications; BRNB.031; FR-NB-124 | H16: Product Owner, New Business | I16: 46356 | J16: Medium | K16: Open
A17: CLR-NB-09 | B17: BRD-01 New Business | C17: Business rule confirmation | D17: Duplicate checks: Confirm the client and account duplicate keys. | E17: BRNB.051 and 066 define account duplicates by risk; the BRD's example keys belong to the client. | F17: Clients are checked on their identity keys (e-mail, phone, ID number); accounts are compared on their risks (vehicle identifiers, location and insured items). | G17: FRS BRD-01 v2.1, Proposed business rules and clarifications; BRNB.032, 051, 066; FR-NB-033, 063 | H17: Product Owner, New Business | I17: 46356 | J17: Medium | K17: Open
A18: CLR-NB-10 | B18: BRD-01 New Business | C18: Business rule confirmation | D18: Changes before batch booking: Confirm the changes allowed in the booking queue. | E18: Account details are owned by the account workflow. | F18: Before a batch is booked, Processing changes the booking date and the cost center, removes an account from the queue or cancels the batch. Other account details are changed on the account. | G18: FRS BRD-01 v2.1, Proposed business rules and clarifications; BRNB.036; FR-NB-111 | H18: Product Owner, New Business | I18: 46356 | J18: Medium | K18: Open
A19: CLR-NB-12 | B19: BRD-01 New Business | C19: Business rule confirmation | D19: Requests received by e-mail: Confirm manual capture, or specify the mailbox reading (Q12). | E19: Automatic reading of a shared mailbox is not specified (Q12). | F19: Requests received in a shared mailbox are captured in the request inbox with the e-mail attached. | G19: FRS BRD-01 v2.1, Proposed business rules and clarifications; BRNB.041; FR-NB-040; also raised as Q12 (open question) | H19: Product Owner, New Business | I19: 46356 | J19: Medium | K19: Partly answered
A20: CLR-NB-13 | B20: BRD-01 New Business | C20: Business rule confirmation | D20: Draft and cancel in bulk updates: Confirm the review before commit in place of save-draft and cancel. | E20: The review before commit gives the same control as a draft. | F20: The upload is reviewed before commit; valid rows are then saved directly, without a separate draft state. | G20: FRS BRD-01 v2.1, Proposed business rules and clarifications; BRNB.047, 065; FR-NB-035 | H20: Product Owner, New Business | I20: 46356 | J20: Medium | K20: Open
A21: CLR-NB-14 | B21: BRD-01 New Business | C21: Report layout | D21: Dynamic reports: Confirm saved variants (Q40). | E21: BRD-8 and BRD-12 answer Q40 that saved variants are enough. | F21: Users save report variants with their own column filters; there is no ad-hoc report designer. | G21: FRS BRD-01 v2.1, Proposed business rules and clarifications; BRNB.057; FR-NB-123; also raised as Q40 (open question), CRQ11 (open question), DCR-177 (register item) | H21: Report SMEs named in the Report List | I21: 46356 | J21: Medium | K21: Partly answered | M21: Answer so far: User-defined filters and exports; the umbrella adds customised reports with fields, charts and summaries, scheduled or on demand (CRQ11). (BRD-8 BRID-022 AC9; Report List #74; BRD-00 BR-053, BR-054). Also affects BRD-00.
A22: CLR-NB-15 | B22: BRD-01 New Business | C22: Business rule confirmation | D22: Cancelled placement: Confirm the stage Placement cancelled and the reactivation. | E22: The account keeps its history and can be reactivated (BRD 2.1.16). | F22: A cancelled placement stays in the stage Placement cancelled, visible and reportable, until it is reactivated to Ready for placement. | G22: FRS BRD-01 v2.1, Proposed business rules and clarifications; BRNB.062; FR-NB-085, 086 | H22: Product Owner, New Business | I22: 46356 | J22: Medium | K22: Open
A23: CLR-NB-16 | B23: BRD-01 New Business | C23: Business rule confirmation | D23: CLPC billing file: Specify the CLPC transfer or confirm the manual forwarding (Q28). | E23: The CLPC transfer is not specified (Q28); QPS references end with the migration (OOS-2). | F23: The billing file is downloaded and forwarded to CLPC by the user, and the ARN replaces the QPS reference number. An automatic transfer is added when BDOI specifies it. | G23: FRS BRD-01 v2.1, Proposed business rules and clarifications; BRNB.067; FR-NB-090; also raised as Q28 (open question) | H23: Product Owner, New Business | I23: 46356 | J23: Medium | K23: Partly answered | M23: Answer so far: Three CLPC billing variants with sample files. Transport and schedule open. (Report List #65-67).
A24: CLR-NB-18 | B24: BRD-01 New Business | C24: Clarification | D24: Hold cover request: Name the accounts that need an automatic request and the outcome at expiry (Q27). | E24: Which accounts need an automatic request, and the outcome at expiry, are not given (Q27). | F24: The request is sent when Processing clicks Request Hold Cover. At expiry without a policy BIBS raises an alert. | G24: FRS BRD-01 v2.1, Proposed business rules and clarifications; BRNB.072; FR-NB-082, 083; also raised as Q27 (open question), SP-SQ12 (open question), DCR-155 (register item) | H24: BIBS Product Owner, with the owners of the BRDs involved | I24: 46356 | J24: Medium | K24: Partly answered | M24: Answer so far: Hold covers apply to renewals; 30-day hold cover for submitted renewals, accepted within 3-5 days. Expiry handling open. (BRD-6 1.009.3.1.33-34; BRD-12 p.5, BRIDSP-24 / 32). Also affects BRD-06, BRD-12.
A25: CLR-NB-19 | B25: BRD-01 New Business | C25: Business rule confirmation | D25: E-policy receipt: Specify the e-policy channels or confirm the upload (Q31). | E25: The insurer channels for e-policies are not specified (Q31, Q12). | F25: E-policies are uploaded by Processing. Automatic reading of an insurer mailbox or file transfer folder is added when specified. | G25: FRS BRD-01 v2.1, Proposed business rules and clarifications; BRNB.073; FR-NB-100; also raised as Q31 (open question) | H25: Product Owner, New Business | I25: 46356 | J25: Medium | K25: Partly answered | M25: Answer so far: EB insurers upload policy forms and billing through the portal. Other lines open. (BRD-8 BRID-005.01).
A26: CLR-NB-20 | B26: BRD-01 New Business | C26: Report layout | D26: Production reports: Confirm the grouping and provide the sales hierarchy and targets (Q41). | E26: "Per system" is read as per officer; QPS reports end with the migration (OOS-2); the sales hierarchy and targets are not given (Q41). | F26: Production is shown per region, department, team and officer; the Placement Summary replaces the QPS Placement Report. | G26: FRS BRD-01 v2.1, Proposed business rules and clarifications; BRNB.075; FR-NB-122; also raised as Q41 (open question) | H26: Product Owner, New Business | I26: 46356 | J26: Medium | K26: Open
A27: CLR-NB-21 | B27: BRD-01 New Business | C27: Business rule confirmation | D27: Workload allocation: Confirm manual claim and assignment. | E27: The BRD does not define an allocation rule. | F27: Work is claimed by a user or assigned by a team lead; there is no automatic allocation. | G27: FRS BRD-01 v2.1, Proposed business rules and clarifications; BRNB.080; FR-NB-011 | H27: Product Owner, New Business | I27: 46356 | J27: Medium | K27: Open
A28: CLR-NB-22 | B28: BRD-01 New Business | C28: Configuration value | D28: Delete lists of values: Confirm deactivation in place of delete. | E28: Records keep their meaning over time. | F28: A list value is deactivated, never deleted, so older records keep their labels. | G28: FRS BRD-01 v2.1, Proposed business rules and clarifications; BRNB.083; FR-NB-132 | H28: Product Owner, New Business | I28: 46356 | J28: Medium | K28: Open
A29: CLR-NB-24 | B29: BRD-01 New Business | C29: Clarification | D29: Authoritative source per data element: Give the list of data elements and their sources (Q37). | E29: BDOI's list of sources is not yet given (Q37). | F29: BIBS is the source of the clients, accounts and invoices it creates; the policy number is set only from the e-policy. The register of sources of the other elements is completed with BDOI's list. | G29: FRS BRD-01 v2.1, Proposed business rules and clarifications; BRNB.092; FR-NB-020; also raised as Q37 (open question) | H29: Product Owner, New Business | I29: 46356 | J29: Medium | K29: Partly answered | M29: Answer so far: Policy number flows from the policy system to Claims; QPS / EBIX are systems of record for contacts during coexistence; from cutover the new Core holds the trusted client master and reference data (BRD-13 draft). (BRD-7 BRCLM.007 / 039; BRD-9 p.3, BRCSF-002; B.
A30: CLR-NB-25 | B30: BRD-01 New Business | C30: Business rule confirmation | D30: Leads: Confirm that leads are out of scope, or describe the lead process (Q19). | E30: The lead process is not described in the BRD (Q19). | F30: Business starts at the prospect; lead management before the prospect (for example bank referrals) is not part of this FRS. | G30: FRS BRD-01 v2.1, Proposed business rules and clarifications; BRNB.099; FR-NB-037; also raised as Q19 (open question) | H30: Product Owner, New Business | I30: 46356 | J30: Medium | K30: Open
A31: CLR-NB-26 | B31: BRD-01 New Business | C31: Decision | D31: Extraction from uploaded documents: Decide whether scanned e-policies need OCR (Q24). | E31: OCR of scanned documents is not decided (Q24). | F31: BIBS reads the e-policy data from text PDFs; scanned documents are keyed in. | G31: FRS BRD-01 v2.1, Proposed business rules and clarifications; BRNB.104; FR-NB-101; also raised as Q24 (open question) | H31: Product Owner, New Business | I31: 46356 | J31: Medium | K31: Partly answered | M31: Answer so far: Submitted policy documents are extracted and confirmed by a user; scanned input implies OCR. (BRD-12 BRIDSP-02).
A32: CLR-NB-27 | B32: BRD-01 New Business | C32: Decision | D32: Retention, archive and purge: Decide the archive and purge approach (Q39). | E32: The storage and backup decision is open (Q39). | F32: Retention rules and review counts are kept in BIBS; nothing is deleted. The physical archive and purge follow the storage and backup decision. | G32: FRS BRD-01 v2.1, Proposed business rules and clarifications; BRNB.106; FR-NB-137; also raised as Q39 (open question), DCR-007 (register item) | H32: Marketing and Processing - New Business (Product Owner) | I32: 46356 | J32: Medium | K32: Partly answered | M32: Answer so far: Umbrella: 5 years online / 15 years offline for application, data store, audit logs and historical data. Claims 10 / 15; EB 5 / 15; CSF 5 / 15; screening 5 / 5. Exceptions per record type and purge vs archive open (CRQ22). (BRD-7 p.41; BRD-8 p.54; BRD-9 p.14;.
A33: CLR-NB-28 | B33: BRD-01 New Business | C33: Clarification | D33: Incentive criteria: Provide the criteria content (Q33). | E33: BRD-3 PMADD07 and 08 give Product Maintenance the criteria; their content is not given (Q33). | F33: The incentive criteria are maintained in Product Maintenance (BRD-3) and stamped on the invoice when it is evaluated (CLR-NB-46); computation and payout are out of scope. | G33: FRS BRD-01 v2.1, Proposed business rules and clarifications; BRNB.107; FR-NB-118; also raised as Q33 (open question) | H33: Product Owner, New Business | I33: 46356 | J33: Medium | K33: Partly answered | M33: Answer so far: Incentive criteria kept on the products matrix; CPC2 = package Fire / Motor incentive computed per remittance. Rates not given. (BRD-3 PMADD07 / 08; BRD-5 DIS 3.29.2).
A34: CLR-NB-29 | B34: BRD-01 New Business | C34: Business rule confirmation | D34: Shared path: Confirm the in-system list. | E34: A shared network path is replaced by the in-system list. | F34: The list is kept in BIBS with its report and a notification; the user downloads it to any folder. | G34: FRS BRD-01 v2.1, Proposed business rules and clarifications; BRNB.110; FR-NB-038 | H34: Product Owner, New Business | I34: 46356 | J34: Medium | K34: Open
A35: CLR-NB-30 | B35: BRD-01 New Business | C35: Business rule confirmation | D35: Direct payment accounting: Confirm the direct payment accounting (Q29). | E35: The accounting variant is not given in the BRD (Q29). | F35: For a direct payment account, booking records the commission receivable only. | G35: FRS BRD-01 v2.1, Proposed business rules and clarifications; FR-NB-069; also raised as Q29 (open question) | H35: Product Owner, New Business | I35: 46356 | J35: Medium | K35: Open
A36: CLR-NB-33 | B36: BRD-01 New Business | C36: Business rule confirmation | D36: BIR CAS / e-invoicing: Confirm that BIR transmission is out of this phase. | E36: The BIR transmission is not in the BRD. | F36: Service invoices are numbered, produced and dispatched in BIBS; transmission to BIR CAS / e-invoicing is not part of this phase. | G36: FRS BRD-01 v2.1, Proposed business rules and clarifications; FR-NB-117 | H36: Product Owner, New Business | I36: 46356 | J36: Medium | K36: Open
A37: CLR-NB-34 | B37: BRD-01 New Business | C37: Configuration value | D37: TSU rule thresholds: Confirm maker-checker on TSU rule changes. | E37: The BRD does not say whether a threshold change needs authorisation. | F37: A change of a TSU rule threshold applies to the next evaluation and is authorised by a second user, like the other catalogue masters. | G37: FRS BRD-01 v2.1, Proposed business rules and clarifications; FR-NB-005 | H37: Product Owner, New Business | I37: 46356 | J37: Medium | K37: Open
A38: CLR-NB-35 | B38: BRD-01 New Business | C38: Clarification | D38: BDOI number format: Give the number format (Q15). | E38: The format is not given (Q15). | F38: The account reference is ARN-yyyy-nnnnnn until BDOI states the format of its number. | G38: FRS BRD-01 v2.1, Proposed business rules and clarifications; FR-NB-047; also raised as Q15 (open question), RQ03 (open question), DCR-156 (register item) | H38: BIBS Product Owner, with the owners of the BRDs involved | I38: 46356 | J38: Medium | K38: Partly answered | M38: Answer so far: A mandatory unique renewal reference is the matching key; no format given. (BRD-6 BRRN.022). Also affects BRD-06, BRD-12.
A39: CLR-NB-36 | B39: BRD-01 New Business | C39: Business rule confirmation | D39: Escalation beyond the stage owners: Confirm that no escalation to the unit head is needed. | E39: The BRD does not ask for escalation beyond the stage owners. | F39: Overdue work alerts the owners of the stage and shows on the NB Dashboard; it is not escalated to a higher level. | G39: FRS BRD-01 v2.1, Proposed business rules and clarifications; FR-NB-010, 011 | H39: Product Owner, New Business | I39: 46356 | J39: Medium | K39: Open
A40: CLR-NB-37 | B40: BRD-01 New Business | C40: Sample document or template | D40: Document layouts: Provide the document layouts (Q03). | E40: BDOI's layouts are not yet provided (Q03). | F40: Documents are produced from versioned templates in proposed draft layouts; BDOI's layouts are loaded as new template versions. | G40: FRS BRD-01 v2.1, Proposed business rules and clarifications; FR-NB-004; also raised as Q03 (open question), RQ26 (open question), EBQ08 (open question) | H40: Product Owner, New Business | I40: 46356 | J40: Medium | K40: Open
A41: CLR-NB-38 | B41: BRD-01 New Business | C41: Business rule confirmation | D41: Main path of the stepper: Confirm the main path and the endings of each stepper. | E41: Two good endings on one line would make the path read as two steps. | F41: The stepper of a quotation, proposal request and account shows the main path to its first good ending (for example the quotation ends at Account Created). Where a workflow has a second good ending (a quotation Accepted by Client without an account yet, an account Booked or issued without booking), that ending is shown only when the record reaches it. | G41: FRS BRD-01 v2.1, Proposed business rules and clarifications; screen standards | H41: Product Owner, New Business | I41: 46356 | J41: Medium | K41: Open
A42: CLR-NB-39 | B42: BRD-01 New Business | C42: Configuration value | D42: Scheme rate in the Rate Exceptions table: Confirm the rate the requested rate is compared with. | E42: The exception is approved against the package scheme (BRD-3). | F42: The Scheme Rate column shows the package rate of the version that priced the quotation; the panel insurer's own rate is not shown in the table. | G42: FRS BRD-01 v2.1, Proposed business rules and clarifications; BRD-3 FR-PM-051 | H42: Product Owner, New Business | I42: 46356 | J42: Medium | K42: Open
A43: CLR-NB-40 | B43: BRD-01 New Business | C43: Configuration value | D43: Difference column of the Rate Exceptions table: Confirm percentage points with the sign. | E43: A percentage of the rate would read as a second rate. | F43: The difference is shown in percentage points with its sign and two decimals (requested 1.10 against scheme 1.20 reads -0.10). | G43: FRS BRD-01 v2.1, Proposed business rules and clarifications | H43: Product Owner, New Business | I43: 46356 | J43: Medium | K43: Open
A44: CLR-NB-41 | B44: BRD-01 New Business | C44: Business rule confirmation | D44: Special instructions on records: Confirm the notice and the tags. | E44: The instructions warn and do not block. | F44: The special instructions of the client in force show as one short information notice under the record header of the client, quotation, proposal request and account; client tags such as BDO employee are tags in the header. | G44: FRS BRD-01 v2.1, Proposed business rules and clarifications; FR-NB-036 | H44: Product Owner, New Business | I44: 46356 | J44: Medium | K44: Open
A45: CLR-NB-42 | B45: BRD-01 New Business | C45: Business rule confirmation | D45: Endorsement type labels: Confirm the labels or give BDOI's wording. | E45: Users read labels, not codes. | F45: Endorsement types show their business labels: Additional premium, Refund (return premium), Renewal, Cancellation (pro-rata 1/365) and NIL (non-financial); endorsement requests show the list label of their type. | G45: FRS BRD-01 v2.1, Proposed business rules and clarifications | H45: Product Owner, New Business | I45: 46356 | J45: Medium | K45: Open
A46: CLR-NB-43 | B46: BRD-01 New Business | C46: Business rule confirmation | D46: Full status labels: Confirm full labels and the short forms of the longer ones. | E46: The client asked for full labels where they fit (27-Sep-2026). | F46: Statuses show their full label (for example Returned to Marketing, Ready for Placement, Pending Authorization); a short form with the full label in the tooltip is used only above 21 characters. | G46: FRS BRD-01 v2.1, Proposed business rules and clarifications | H46: Product Owner, New Business | I46: 46356 | J46: Medium | K46: Open
A47: CLR-NB-44 | B47: BRD-01 New Business | C47: Business rule confirmation | D47: BRNB.100 restated: Confirm that the addendum adds the EOPT requirement to BRNB.100 and that the service invoice production of the Workshop wording remains required. | E47: The IT Walkthrough Addendum gives BRNB.100 a new requirement (EOPT) and does not repeat the service invoice text, while BRNB.100.1 still sends the generated service invoice. | F47: BRNB.100 is met by the EOPT details on the placement (FR-NB-087). The service invoice production of the Workshop wording of BRNB.100 (template, triggers, owner) stays in scope with FR-NB-117, which also meets BRNB.100.1. | G47: FRS BRD-01 v2.1, Proposed business rules and clarifications; FR-NB-087, FR-NB-117 | H47: Product Owner, New Business | I47: 46356 | J47: Medium | K47: Open
A48: CLR-NB-45 | B48: BRD-01 New Business | C48: Master data | D48: EOPT details on the placement: Give the full list of EOPT fields, confirm the client's address as the registered address or name another source, and say whether missing EOPT details should stop the sending for some insurers or segments. | E48: The BRD lists "taxpayer name, TIN number, registered address, etc." and asks for them "when EOPT information is available". | F48: The slip carries the taxpayer name, TIN and registered address from the client record (the client's address serves as the registered address). A change before the final sending regenerates the slip. When details are missing the slip is sent with the details shown as not available; it is not blocked. | G48: FRS BRD-01 v2.1, Proposed business rules and clarifications; BRNB.100; FR-NB-087 | H48: Product Owner, New Business | I48: 46356 | J48: Medium | K48: Open
A49: CLR-NB-46 | B49: BRD-01 New Business | C49: Business rule confirmation | D49: Incentive indicator at full payment: Confirm the reading of fully paid (all instalments; an endorsement with an unpaid premium), the endorsements that count, and whether an authorised override is needed (if so, by which role, with a reason and a second user). | E49: The addendum moves the evaluation from booking to full payment and adds the endorsements; BRRN.041 of the Renewal addendum states the same rule. "Fully paid" is read as the invoice balance at zero, all instalments included. The BRD allows an override "unless authorized" without saying by whom. | F49: One rule for New Business and Renewal: evaluation only when the transaction is booked and fully paid, after the applicable endorsements are considered; re-evaluation on every posted financial endorsement and on cancellation; each decision logged with the rules applied. Pending until fully paid. No manual change of the indicator. | G49: FRS BRD-01 v2.1, Proposed business rules and clarifications; BRNB.107; FR-NB-118; BRD-6 BRRN.041 | H49: Product Owner, New Business | I49: 46356 | J49: Medium | K49: Open
A50: CLR-NB-47 | B50: BRD-01 New Business | C50: Master data | D50: Bulk quotations and their documents: Give the supporting documents that are mandatory for sending per product, and the IDF and FFYMI layouts (Q03). | E50: The addendum asks for partial success, supporting documents and blocking when mandatory documents are missing; it does not list the mandatory documents or the IDF and FFYMI layouts. | F50: A batch is sent quotation by quotation: valid quotations are sent, the others are listed with their reason. Supporting documents are ticked from the Documents tab and sent with the quotation or on their own. The documents mandatory for sending are set per product. The IDF and FFYMI are quotation document templates of their products. | G50: FRS BRD-01 v2.1, Proposed business rules and clarifications; BRNB.042; FR-NB-044, 046 | H50: Product Owner, New Business | I50: 46356 | J50: Medium | K50: Open
... A54: Q04 | B54: BRD-01 New Business | C54: Configuration value | D54: TSU routing: Exact TSU involvement criteria: package vs non-package list, fleet threshold (no. of units), multi-location threshold, TSI threshold, endorsement types. | E54: Open point of the FRS (FR-NB-005): the requirement cannot be finalised or tested as BDOI intends until it is answered. | F54: Keep TSU functions in the existing modules, with a TSU menu section. | G54: FRS BRD-01 v2.1, Open questions Q04 (affects FR-NB-005); Discrepancy and clarification register v1.2, open question Q04; baseline BRNB.098; also raised as DCR-131 (register item) | H54: Report SMEs named in the Report List | I54: 46356 | J54: Medium | K54: Open
A55: Q14 | B55: BRD-01 New Business | C55: Clarification | D55: Sanitation: Defined sanitisation criteria for bulk lists. | E55: Open point of the FRS (FR-NB-019, 065): the requirement cannot be finalised or tested as BDOI intends until it is answered. | G55: FRS BRD-01 v2.1, Open questions Q14 (affects FR-NB-019, 065); Discrepancy and clarification register v1.2, open question Q14; baseline BRNB.064 | H55: Product Owner, New Business | I55: 46356 | J55: Medium | K55: Partly answered | M55: Answer so far: Renewal sanitation is rule-based (criteria not listed); submitted-policy criteria listed. (BRD-6 BRRN.020; BRD-12, Report List #151).
A56: Q16 | B56: BRD-01 New Business | C56: Clarification | D56: Client / KYC: BDO 'bank standard' client data and KYC fields; is there a BDO CIF to integrate with (source of truth for bank clients)? | E56: Open point of the FRS (FR-NB-031, 033): the requirement cannot be finalised or tested as BDOI intends until it is answered. | G56: FRS BRD-01 v2.1, Open questions Q16 (affects FR-NB-031, 033); Discrepancy and clarification register v1.2, open question Q16; baseline BRNB.030, 065, 090, 092; also raised as RQ22 (open question) | H56: Product Owner, New Business | I56: 46356 | J56: Medium | K56: Open
A57: Q17 | B57: BRD-01 New Business | C57: Clarification | D57: Dedupe: Duplicate-client keys and match precedence (name + DOB, ID number, e-mail, mobile, TIN). | E57: Open point of the FRS (FR-NB-031, 033): the requirement cannot be finalised or tested as BDOI intends until it is answered. | G57: FRS BRD-01 v2.1, Open questions Q17 (affects FR-NB-031, 033); Discrepancy and clarification register v1.2, open question Q17; baseline BRNB.032 | H57: Product Owner, New Business | I57: 46356 | J57: Medium | K57: Open
A58: Q20 | B58: BRD-01 New Business | C58: Business rule confirmation | D58: Prospect: Prospect vs confirmed client: which event confirms (KYC complete, first booking)? | E58: Open point of the FRS (FR-NB-034, 037): the requirement cannot be finalised or tested as BDOI intends until it is answered. | G58: FRS BRD-01 v2.1, Open questions Q20 (affects FR-NB-034, 037); Discrepancy and clarification register v1.2, open question Q20; baseline BRNB.101 | H58: Product Owner, New Business | I58: 46356 | J58: Medium | K58: Open
A59: Q21 | B59: BRD-01 New Business | C59: Report layout | D59: KYC review: KYC review frequency by risk rating for non-bank clients; 'shared path' - is an in-system report acceptable? | E59: Open point of the FRS (FR-NB-038): the requirement cannot be finalised or tested as BDOI intends until it is answered. | G59: FRS BRD-01 v2.1, Open questions Q21 (affects FR-NB-038); Discrepancy and clarification register v1.2, open question Q21; baseline BRNB.110; also raised as SANC-SQ03 (open question) | H59: Product Owner, New Business | I59: 46356 | J59: Medium | K59: Partly answered | M59: Answer so far: KYC due is visibility only in renewal; high-risk / PEP clients with an active policy get a review case. Frequency per rating not given. (BRD-6 BRRN.028; BRD-10 SNSRP-102 / 303).
A60: Q22 | B60: BRD-01 New Business | C60: Clarification | D60: Duplicates: Fire duplicate rule 'same client ID + location + items' - exact or normalised address match? Motor: CTPL vs MTR exception confirmed. | E60: Open point of the FRS (FR-NB-063): the requirement cannot be finalised or tested as BDOI intends until it is answered. | G60: FRS BRD-01 v2.1, Open questions Q22 (affects FR-NB-063); Discrepancy and clarification register v1.2, open question Q22; baseline BRNB.051, 066 | H60: Product Owner, New Business | I60: 46356 | J60: Medium | K60: Open
A61: Q23 | B61: BRD-01 New Business | C61: Clarification | D61: Files: Maximum file size and full list of allowed file types; file-naming syntax. | E61: Open point of the FRS (FR-NB-017): the requirement cannot be finalised or tested as BDOI intends until it is answered. | F61: One allowed-type list and size limit as configuration; the screening naming pattern for screening documents only. | G61: FRS BRD-01 v2.1, Open questions Q23 (affects FR-NB-017); Discrepancy and clarification register v1.2, open question Q23; baseline BRNB.026; also raised as CSQ08 (open question), DCR-154 (register item) | H61: BIBS Product Owner, with the owners of the BRDs involved | I61: 46356 | J61: Medium | K61: Partly answered | M61: Answer so far: File types listed for EB and CSF; naming syntax for screening documents only. Maximum size open. (BRD-8 BRID-002, 005.01, 014; BRD-9 BRCSF-007; BRD-10 SNSRP-601). Also affects BRD-08, BRD-09, BRD-10.
A62: Q25 | B62: BRD-01 New Business | C62: Decision | D62: Reactivation: Reactivate cancelled placement (BRD 2.1.16) has no BRNB ID - confirm in scope. | E62: Open point of the FRS (FR-NB-086): the requirement cannot be finalised or tested as BDOI intends until it is answered. | F62: Add a BRNB ID for reactivation of cancelled placements, or confirm it is dropped. | G62: FRS BRD-01 v2.1, Open questions Q25 (affects FR-NB-086); Discrepancy and clarification register v1.2, open question Q25; baseline BRD 2.1.16; also raised as DCR-002 (register item) | H62: Marketing and Processing - New Business (Product Owner) | I62: 46356 | J62: Medium | K62: Open
A63: Q26 | B63: BRD-01 New Business | C63: Clarification | D63: Placement: Prerequisites before placement per segment (payment received, client confirmation, docs complete, TSU clearance). | E63: Open point of the FRS (FR-NB-080): the requirement cannot be finalised or tested as BDOI intends until it is answered. | G63: FRS BRD-01 v2.1, Open questions Q26 (affects FR-NB-080); Discrepancy and clarification register v1.2, open question Q26; baseline BRNB.069 | H63: Product Owner, New Business | I63: 46356 | J63: Medium | K63: Open
A64: Q32 | B64: BRD-01 New Business | C64: Clarification | D64: Accounting: Booking accounting entries (premium receivable/payable to insurer, commission income, VAT, EWT) and service invoice rules - is commission invoiced per booking or monthly per insurer? | E64: Open point of the FRS (FR-NB-110, 117): the requirement cannot be finalised or tested as BDOI intends until it is answered. | F64: Assign an ID in the next addendum revision; BRNB.100b is used until then. | G64: FRS BRD-01 v2.1, Open questions Q32 (affects FR-NB-110, 117); Discrepancy and clarification register v1.2, open question Q32; baseline BRNB.027, 100; also raised as DCR-003 (register item) | H64: Marketing and Processing - New Business (Product Owner) | I64: 46356 | J64: Medium | K64: Partly answered | M64: Answer so far: Related transactions must link to a single invoice number. No entries given. (BRD-5 ACSL 2.16.0, DIS 3.27.2).
A65: Q34 | B65: BRD-01 New Business | C65: Clarification | D65: Cost center: Cost center master data source and default rule (by AO, branch, segment). | E65: Open point of the FRS (FR-NB-119): the requirement cannot be finalised or tested as BDOI intends until it is answered. | G65: FRS BRD-01 v2.1, Open questions Q34 (affects FR-NB-119); Discrepancy and clarification register v1.2, open question Q34; baseline BRNB.108 | H65: Product Owner, New Business | I65: 46356 | J65: Medium | K65: Open
A66: Q36 | B66: BRD-01 New Business | C66: Clarification | D66: FFY: Free First-Year: who pays the first-year premium (dealer / bank), FFY period length and renewal hand-off. | E66: Open point of the FRS (FR-NB-068): the requirement cannot be finalised or tested as BDOI intends until it is answered. | G66: FRS BRD-01 v2.1, Open questions Q36 (affects FR-NB-068); Discrepancy and clarification register v1.2, open question Q36; baseline BRNB.113 | H66: Product Owner, New Business | I66: 46356 | J66: Medium | K66: Partly answered | M66: Answer so far: FFY accounts get an FFY RA template; FFY is both a renewal and a non-renewal bucket. Payer not stated. (BRD-12 BRIDSP-13 / 14).
A67: Q38 | B67: BRD-01 New Business | C67: Clarification | D67: GRF/ARF: Describe the existing GRF and ARF request forms to replicate their behaviour. | E67: Open point of the FRS (FR-NB-011): the requirement cannot be finalised or tested as BDOI intends until it is answered. | G67: FRS BRD-01 v2.1, Open questions Q38 (affects FR-NB-011); Discrepancy and clarification register v1.2, open question Q38; baseline BRNB.096 | H67: Product Owner, New Business | I67: 46356 | J67: Medium | K67: Open
A68: DCR-004 | B68: BRD-01 New Business | C68: Report layout | D68: Please confirm criterion 1 of BRNB.089 is "generate the audit log report". | E68: Under "a. Generate audit log report", criterion 1 reads "User should be able to assign cancel placement function", copied from the row above. Test: the criterion does not describe the audit log report. | F68: Read criterion 1 as "generate the audit log report". | G68: Discrepancy and clarification register v1.2, DCR-004 (Document quality); BRNB.089 / BRD 3.4.3.1 (p.127) | H68: Marketing and Processing - New Business (Product Owner) | I68: 46356 | J68: Low | K68: Open
A69: SO-01-2 | B69: BRD-01 New Business | C69: Sign-off | D69: Approve the test plan of BRD-01 New Business. | E69: The signed document fixes the scope for the next step of the plan; a late sign-off moves the dates that follow it. | G69: Project plan v1.0 (8-Oct-2026), sign-offs and milestones | H69: Product Owner, New Business | I69: 46374 | J69: High | K69: Open
A70: CLR-NB-02 | B70: BRD-01 New Business | C70: Integration detail | D70: Data synchronisation: Confirm that no other BDOI system needs a New Business feed (Q08). | E70: Q08 names QPS and EBIX for client contact updates only (BRD-9). | F70: BIBS passes each event to its own modules (Operations, Collections, Renewal). A feed to other BDOI systems is added when BDOI names them. | G70: FRS BRD-01 v2.1, Proposed business rules and clarifications; BRNB.015; FR-NB-015; also raised as Q08 (open question) | H70: BDOI IT with the Product Owner, New Business | I70: 46418 | J70: Medium | K70: Partly answered | M70: Answer so far: QPS and EBIX receive client contact updates during coexistence (BRD-9); BRD-13 makes legacy read-only after cutover with no feed required (conflict DCR-202). Accounting is internal to BIBS. Other targets open. (BRD-9 p.3 footnote 3; BRD-5 FRBS 2.5.0; BRD-13 p.
A71: CLR-NB-06 | B71: BRD-01 New Business | C71: Integration detail | D71: HLS requests: Specify the HLS interface (Q11). | E71: The HLS interface is not specified (Q11). | F71: HLS requests are loaded by upload of the HLS extract and kept in the request inbox. The direct HLS interface with its source check is added when BDOI specifies it. | G71: FRS BRD-01 v2.1, Proposed business rules and clarifications; BRNB.023; FR-NB-040; also raised as Q11 (open question) | H71: BDOI IT with the Product Owner, New Business | I71: 46418 | J71: Medium | K71: Partly answered | M71: Answer so far: Sources named (LFS, HLS, CIU, SPI, LAMD, Loan Booking Report, IA masterlist), all Excel. Layouts and transport open. (BRD-12 p.4-5; Report List #138, #151).
A72: CLR-NB-11 | B72: BRD-01 New Business | C72: Integration detail | D72: Directory sign-in: Supply the directory interface and the date it is available. | E72: The directory interface is not yet specified (decision D6; BRD-11 UQ04). | F72: Sign-in is local to BIBS until BDO supplies the directory interface (BDO EUA / Windows ID, LDAP / AD or SSO). | G72: FRS BRD-01 v2.1, Proposed business rules and clarifications; BRNB.040, 087; FR-NB-130 | H72: BDOI IT with the Product Owner, New Business | I72: 46418 | J72: Medium | K72: Open
A73: CFG-007 | B73: BRD-01 New Business | C73: Master data | D73: Sales organisation (regions, departments, teams, unit heads, account officers): The sales units and account officers in force, and the inactive officers of open items; after go-live maintained on Sales Organisation | E73: Needed for: Reference data for Trial migration 1 (M4) (Extracts for Trial migration 1; reference data and clients first). | F73: Fill in the template R03 of the Master Data and Configuration Upload Templates workbook. | G73: Drop 0 configuration register CFG-007 (Drop 0 Configuration Inputs v2.0, area Organisation) | H73: Product Owner, BDOI (New Business) | I73: 46486 | J73: High | K73: Open
A74: CFG-045 | B74: BRD-01 New Business | C74: Master data | D74: Bank list (mortgagee banks): The banks named as mortgagee or payout bank; the legacy bank codes are mapped to this list by code map BANK | E74: Needed for: Reference data for Trial migration 1 (M4) (Extracts for Trial migration 1; reference data and clients first). | F74: Give the values wanted on the sheet Lists of values of the Master Data and Configuration Upload Templates workbook. | G74: Drop 0 configuration register CFG-045 (Drop 0 Configuration Inputs v2.0, area Banks and bank accounts) | H74: Product Owner, BDOI (New Business) | I74: 46486 | J74: High | K74: Open
A75: TD-01 | B75: BRD-01 New Business | C75: Test data | D75: Name the UAT testers of BRD-01 New Business (at least two per business unit, with their user IDs and group profiles) and provide the business data of the UAT scenarios: the clients, policies, insurers and amounts each scenario of the test plan uses, from the migrated data of Trial migration 3 or as additional cases. | E75: UAT of Drop 1 runs on migrated data and the production values; testers without access or scenarios without data stop the UAT. | F75: The test plan (04 workbook of the set) names the scenarios; the BDOI testers choose the cases from the migrated data and add the cases the legacy data does not hold. | G75: Project plan: dependency DEP-20 (UAT testers), milestone MS-20 (UAT plans, values for UAT and testers, 16-Jul-2027) | H75: Product Owner, New Business (UAT testers of the business units) | I75: 46584 | J75: High | K75: Open
A76: CFG-008 | B76: BRD-01 New Business | C76: Configuration value | D76: Production targets: The 2028 production targets per sales unit and officer for the New Business reports | E76: Needed for: Values for UAT (UAT plans and sign-off forms due 16-Jul-2027; UAT Aug - Dec 2027 runs on the production values). | F76: Configured on the screen Reports › New Business Reports › Production Targets (sheet Configured on screens of the Master Data and Configuration Upload Templates workbook). | G76: Drop 0 configuration register CFG-008 (Drop 0 Configuration Inputs v2.0, area Organisation) | H76: Product Owner, BDOI (New Business) | I76: 46584 | J76: Medium | K76: Open
A77: CFG-120 | B77: BRD-01 New Business | C77: Configuration value | D77: Booking rules and incentive rules: The automatic booking rules and the booking incentive rules | E77: Needed for: Values for UAT (UAT plans and sign-off forms due 16-Jul-2027; UAT Aug - Dec 2027 runs on the production values). | F77: Configured on the screen Client & Policy › Booking › Booking Setup (sheet Configured on screens of the Master Data and Configuration Upload Templates workbook). | G77: Drop 0 configuration register CFG-120 (Drop 0 Configuration Inputs v2.0, area Module rules and set-up) | H77: Product Owner, BDOI (New Business) | I77: 46584 | J77: Medium | K77: Open
A78: CFG-131 | B78: BRD-01 New Business | C78: Configuration value | D78: New Business report variants: The report variants the units use | E78: Needed for: Values for UAT (UAT plans and sign-off forms due 16-Jul-2027; UAT Aug - Dec 2027 runs on the production values). | F78: Configured on the screen Reports › New Business Reports › New Business Reports (sheet Configured on screens of the Master Data and Configuration Upload Templates workbook). | G78: Drop 0 configuration register CFG-131 (Drop 0 Configuration Inputs v2.0, area Module rules and set-up) | H78: Product Owner, BDOI (New Business) | I78: 46584 | J78: Medium | K78: Open
A79: DOC-05 | B79: BRD-01 New Business | C79: Sample document or template | D79: Documents of New Business: give the BDOI layout, logo placement and wording of the 10 documents BIBS generates (Your e-policy; Request for hold cover; Insurance advice; Placement slip; Proposal slip; Insurance quotation; Quotation slip; Terms and conditions; Service invoice; Validation slip), as a filled-in sample of each. | E79: BIBS generates each document from its template; without the BDOI layout the documents keep the proposed layout in SIT and UAT. | F79: The proposed layouts are reviewed on the Document Templates screen; BDOI marks the changes on a printout or sends its current form. | G79: Document templates of the platform (Drop 0 Configuration Inputs, Ref Document templates); configuration register CFG-082 | H79: Product Owner, BDOI (New Business) | I79: 46584 | J79: Medium | K79: Open | M79: Review sheet Document templates of the Master Data and Configuration Upload Templates workbook.
A80: SO-01-3 | B80: BRD-01 New Business | C80: Sign-off | D80: Sign the UAT sign-off certificate of BRD-01 New Business. | E80: The signed document fixes the scope for the next step of the plan; a late sign-off moves the dates that follow it. | G80: Project plan v1.0 (8-Oct-2026), sign-offs and milestones | H80: Product Owner, New Business; BIBS Product Owner | I80: 46738 | J80: High | K80: Open

Sheet BRD-02 Operations
A1: BRD-02 Operations
A2: BRD-02 Operations: what BDOI provides; owner Head, Operations Services
A4: Ref | B4: BRD / module | C4: Type | D4: What we need from BDOI | E4: Why / impact if not provided | F4: Our proposal (if any) | G4: Source (FRS section / CLR / BRD page) | H4: BDOI owner (role) | I4: Needed by | J4: Priority | K4: Status | L4: BDOI response | M4: Remarks
A5: CLR-OP-09 | B5: BRD-02 Operations | C5: Business rule confirmation | D5: Minimal balances: Confirm the boundary of 10.00 (OQ11). | E5: The BRD reverses up to 10.00 and writes off 10.00-100.00 from a file, with 10.00 in both (OQ11). | F5: Minimal balances are cleared when the payment is processed (CLR-OP-39); the safety-net run skips an invoice already written off by the minimal balance file, so a balance is never reversed twice. | G5: FRS BRD-02 v2.1, Proposed business rules and clarifications; CSHID.016, ADJID.026; FR-OP-023, 059; also raised as OQ11 (open question), CQ03 (open question), DCR-014 (register item) | H5: Operations - Financial Transactions and Processing | I5: 46356 | J5: High | K5: Open
A6: CLR-OP-11 | B6: BRD-02 Operations | C6: Decision | D6: DTIP balance: Choose Exclude or Cap (OQ19). | E6: The BRD's expected result and acceptance criteria differ (OQ19). | F6: A paid AR above the DTIP balance is excluded from the remittance by default (option Exclude); the option Cap remits the DTIP balance only. | G6: FRS BRD-02 v2.1, Proposed business rules and clarifications; RMTID.014; FR-OP-031; also raised as OQ19 (open question), DCR-015 (register item) | H6: Operations - Financial Transactions and Processing | I6: 46356 | J6: High | K6: Open
A7: CLR-OP-21 | B7: BRD-02 Operations | C7: Business rule confirmation | D7: Non-financial endorsement: Confirm (OQ32). | E7: The account data belong to New Business (OQ32). | F7: Booking records the non-financial endorsement with its description; the account data are not changed. | G7: FRS BRD-02 v2.1, Proposed business rules and clarifications; ADJID.003; FR-OP-050; also raised as OQ32 (open question), DCR-012 (register item), DCR-027 (register item) | H7: Operations - Financial Transactions and Processing | I7: 46356 | J7: High | K7: Partly answered | M7: Answer so far: Endorsements must be on the mother policy before renewal approval. Ownership of the request open. (BRD-6 BRRN.032). Also affects BRD-01.
A8: CLR-OP-41 | B8: BRD-02 Operations | C8: Business rule confirmation | D8: PR 2307 accounting entries: Comptrollership confirms the entry, together with the owners of BRD-4 and BRD-5. | E8: Comptrollership (R. dela Cruz) recommended this entry in the gap discussion recorded by ITG (p.69-70, p.188-189); BRD v1.01 only says the PR is zeroed out and refers the entries to the Collections BRD (OQ16). | F8: One entry when Marketing Collection posts the reversal: Dr DTIP / Cr PR by component; no entry when Disbursement releases the certificates. The v2.0 two-step entries (Dr PR2307 / Cr PR, then Dr DTIP / Cr PR2307) are withdrawn. | G8: FRS BRD-02 v2.1, Proposed business rules and clarifications; MKTID.013; DBMID.001; FR-OP-113, 121; section 5.3; also raised as OQ16 (open question), DCR-028 (register item) | H8: Operations - Financial Transactions and Processing | I8: 46356 | J8: High | K8: Partly answered | M8: Answer so far: 2307 tagging stays in BIBS; client 2307s are remitted to insurers in batches. Posting moment open. (BRD-4 p.41, p.59; BRD-5 Appendix C, DIS 2.11).
A9: CLR-OP-47 | B9: BRD-02 Operations | C9: Business rule confirmation | D9: Early remittance incentive and estimated items moved: Confirm the start of the window, whether the reconciliation check of FR-OP-078 stays, and the definition of estimated items. | E9: The annexes move PRCID.028 to Remittance as RMTID.041 and RMTID.037 to Production Reconciliation; the start of the window and the definition of estimated items are open (OQ23, OQ27). | F9: Remittance validates and computes the incentive for CLG / CBG motor and fire accounts (2%, window of 30 days from inception by default) as a separate line; Production Reconciliation keeps a read-only check of the incentive the insurer applied (FR-OP-078). Estimated items are flagged by the Production Reconciliation Handler. | G9: FRS BRD-02 v2.1, Proposed business rules and clarifications; RMTID.041, RMTID.037; FR-OP-038, 078, 097; also raised as OQ23 (open question), OQ27 (open question), DCR-013 (register item) | H9: Operations - Financial Transactions and Processing | I9: 46356 | J9: High | K9: Partly answered | M9: Answer so far: Early incentive: service invoice with 2% withholding; Other Income. Rates not given. (BRD-5 DIS 3.29.1, FRBS 3.1.2; BRD-4 draft 062).
A10: SO-02-1 | B10: BRD-02 Operations | C10: Sign-off | D10: Sign the FRS and sign-off set of BRD-02 Operations. | E10: The signed document fixes the scope for the next step of the plan; a late sign-off moves the dates that follow it. | G10: Project plan v1.0 (8-Oct-2026), sign-offs and milestones | H10: Head, Operations Services; Business Project Services (traceability) | I10: 46356 | J10: High | K10: Open
A11: CLR-OP-01 | B11: BRD-02 Operations | C11: Business rule confirmation | D11: Operations sections: Confirm the role filter, or ask for personal pin and hide. | E11: The role filter shows each user only the sections of the user's work. | F11: The Operations sections are filtered by role; a personal pin or hide of sections is not proposed. | G11: FRS BRD-02 v2.1, Proposed business rules and clarifications; BRQID.003; FR-OP-003 | H11: Head, Operations Services | I11: 46356 | J11: Medium | K11: Open
A12: CLR-OP-02 | B12: BRD-02 Operations | C12: Clarification | D12: Lock while with Comptrollership: Name the Comptrollership activity (OQ28). | E12: The Comptrollership activity that should lock the invoice is not named (OQ28). | F12: Remittance and Adjustment lock the invoice while they work on it; a Comptrollership lock is added when BDOI names the activity. | G12: FRS BRD-02 v2.1, Proposed business rules and clarifications; RMTID.040; FR-OP-006; also raised as OQ28 (open question) | H12: Head, Operations Services | I12: 46356 | J12: Medium | K12: Open
A13: CLR-OP-03 | B13: BRD-02 Operations | C13: Report layout | D13: Insurer production report: Specify the insurer channels (OQ29), or confirm the upload. | E13: The insurer channels are not specified (OQ29). | F13: The handler uploads the insurer file; a mailbox or file transfer pick-up is added when the insurer channels are specified. | G13: FRS BRD-02 v2.1, Proposed business rules and clarifications; PRCID.009; FR-OP-074; also raised as OQ29 (open question), DCR-019 (register item) | H13: Operations - Financial Transactions and Processing | I13: 46356 | J13: Medium | K13: Partly answered | M13: Answer so far: A secure insurer portal will exist. Frequencies, templates and naming open. (BRD-8 BRID-005).
A14: CLR-OP-04 | B14: BRD-02 Operations | C14: Configuration value | D14: Schedule to Marketing: Confirm that the processor sends the schedule. | E14: The BRD has Marketing initiate the request (OQ22). | F14: The Remittance processor sends the approved schedule from the batch, once. | G14: FRS BRD-02 v2.1, Proposed business rules and clarifications; MKTID.001; FR-OP-110; also raised as OQ22 (open question) | H14: Head, Operations Services | I14: 46356 | J14: Medium | K14: Open
A15: CLR-OP-05 | B15: BRD-02 Operations | C15: Business rule confirmation | D15: Edit of the extracted file: Confirm exclusion in place of edits. | E15: The December 2025 addendum, merged into BRD v1.01 (p.113), governs over the original BRD, which allowed online edits. | F15: Rows of the extract are excluded and restored with a reason; financial fields cannot be edited. | G15: FRS BRD-02 v2.1, Proposed business rules and clarifications; RMTID.002; FR-OP-032 | H15: Head, Operations Services | I15: 46356 | J15: Medium | K15: Open
A16: CLR-OP-06 | B16: BRD-02 Operations | C16: Business rule confirmation | D16: Receipt cancellation and reinstatement: Confirm the Cashiering TL / TH approval (OQ06). | E16: The BRD does not name an approver (OQ06). | F16: A cancellation or reinstatement is a request approved by a Cashiering TL / TH (four eyes) before it posts. | G16: FRS BRD-02 v2.1, Proposed business rules and clarifications; CSHID.001-005; FR-OP-014; also raised as OQ06 (open question) | H16: Head, Operations Services | I16: 46356 | J16: Medium | K16: Open
A17: CLR-OP-07 | B17: BRD-02 Operations | C17: Business rule confirmation | D17: Commission OR per batch: Confirm the OR per batch and per payment (OQ49). | E17: The BRD allows one OR per batch or per payment (OQ49). | F17: Remittance approval issues one commission OR per batch; the Collection upload issues one OR per insurer, certificate and payment. | G17: FRS BRD-02 v2.1, Proposed business rules and clarifications; CSHID.007; FR-OP-021; also raised as OQ49 (open question), DCR-017 (register item) | H17: Operations - Financial Transactions and Processing | I17: 46356 | J17: Medium | K17: Open
A18: CLR-OP-08 | B18: BRD-02 Operations | C18: Business rule confirmation | D18: Payment files: Confirm the upload by Operations users (OQ03, OQ04). | E18: The BRD has IT run the Trade, CLPC and Direct Credit files on FS04 (OQ03, OQ04). | F18: Operations users upload the bank files; each file is stored read-only with its fingerprint, a duplicate file is refused, and the layouts are configurable. | G18: FRS BRD-02 v2.1, Proposed business rules and clarifications; CSHID.008; FR-OP-015; also raised as OQ03 (open question), OQ04 (open question), DCR-020 (register item) | H18: Operations - Financial Transactions and Processing | I18: 46356 | J18: Medium | K18: Open
A19: CLR-OP-10 | B19: BRD-02 Operations | C19: Business rule confirmation | D19: End-of-day extraction: Confirm the queue for the evening run (OQ18). | E19: The BRD text "if payment application is searched" is open to reading (OQ18). | F19: A user queues the searched invoice for the evening extraction run. | G19: FRS BRD-02 v2.1, Proposed business rules and clarifications; RMTID.005; FR-OP-030; also raised as OQ18 (open question) | H19: Head, Operations Services | I19: 46356 | J19: Medium | K19: Open
A20: CLR-OP-12 | B20: BRD-02 Operations | C20: Configuration value | D20: Insurer OR comparison: Give the tolerance, or confirm the exact comparison (OQ22). | E20: No tolerance is given (OQ22). | F20: The insurer OR amount is compared exactly with the paid PR per invoice. | G20: FRS BRD-02 v2.1, Proposed business rules and clarifications; RMTID.016; FR-OP-037 | H20: Head, Operations Services | I20: 46356 | J20: Medium | K20: Open
A21: CLR-OP-13 | B21: BRD-02 Operations | C21: Business rule confirmation | D21: Cleared checks: Confirm the counting (OQ20). | E21: The BRD asks for checks at least 3 banking days old and cleared (OQ20). | F21: Checks are counted in banking days from the last applied value date on the branch calendar; the cleared status comes from the payment application. | G21: FRS BRD-02 v2.1, Proposed business rules and clarifications; RMTID.017; FR-OP-031; also raised as OQ20 (open question) | H21: Head, Operations Services | I21: 46356 | J21: Medium | K21: Open
A22: CLR-OP-14 | B22: BRD-02 Operations | C22: Business rule confirmation | D22: Invoice statuses: Confirm the two statuses (OQ21). | E22: The BRD's eight statuses mix payment and remittance states (OQ21). | F22: The invoice keeps a payment status and a remittance status; the batch has its own workflow stages. | G22: FRS BRD-02 v2.1, Proposed business rules and clarifications; RMTID.019; FR-OP-033, 035; also raised as OQ21 (open question), DCR-016 (register item) | H22: Operations - Financial Transactions and Processing | I22: 46356 | J22: Medium | K22: Open
A23: CLR-OP-16 | B23: BRD-02 Operations | C23: Report layout | D23: Insurer register columns: Confirm the editable columns. | E23: PRCID.022 asks the insurer to report unbooked production in the same file. | F23: The Remarks and Incentive columns and 200 blank rows are editable, so the insurer can add unbooked production. | G23: FRS BRD-02 v2.1, Proposed business rules and clarifications; PRCID.002; FR-OP-072 | H23: Head, Operations Services | I23: 46356 | J23: Medium | K23: Open
A24: CLR-OP-17 | B24: BRD-02 Operations | C24: Business rule confirmation | D24: Location filter: Confirm the filters. | E24: The invoice ledger groups items by sales organisation. | F24: Reconciliation items filter by AO, sales unit, segment and product line; the location filter is on the reports. | G24: FRS BRD-02 v2.1, Proposed business rules and clarifications; PRCID.014, 021; FR-OP-077 | H24: Head, Operations Services | I24: 46356 | J24: Medium | K24: Open
A25: CLR-OP-18 | B25: BRD-02 Operations | C25: Business rule confirmation | D25: Reconciliation statuses: Confirm the fifth status. | E25: The BRD's four statuses do not cover accounts missing from the insurer's file. | F25: A fifth status, BDOI Only, marks booked accounts that the insurer did not return (see also CLR-OP-50 for the three statuses of the annex). | G25: FRS BRD-02 v2.1, Proposed business rules and clarifications; PRCID.030; FR-OP-075 | H25: Head, Operations Services | I25: 46356 | J25: Medium | K25: Open
... A28: CLR-OP-22 | B28: BRD-02 Operations | C28: Business rule confirmation | D28: Quotation for a TSI increase: Confirm the hand-off to Marketing. | E28: The quotation is prepared in New Business. | F28: A hand-off to Marketing; the quotation number is linked on the request by reference. | G28: FRS BRD-02 v2.1, Proposed business rules and clarifications; ADJID.008; FR-OP-055 | H28: Head, Operations Services | I28: 46356 | J28: Medium | K28: Open
A29: CLR-OP-23 | B29: BRD-02 Operations | C29: Business rule confirmation | D29: DP premium receivable reversal: Confirm the ledger-only reversal (OQ07). | E29: Booking of a DP invoice has no premium receivable to reverse (OQ07). | F29: The ledger reversal is always recorded; its GL entry is switched off by a parameter because booking posts no PR for DP invoices. | G29: FRS BRD-02 v2.1, Proposed business rules and clarifications; MKTID.012; FR-OP-094; also raised as OQ07 (open question), AQ02 (open question) | H29: Head, Operations Services | I29: 46356 | J29: Medium | K29: Partly answered | M29: Answer so far: Account names given through the reports; no chart and no entries. (BRD-5 FRBS 2.3.x, reports; BRD-4 draft 061 / 063).
A30: CLR-OP-24 | B30: BRD-02 Operations | C30: Clarification | D30: Incentive schemes: See CLR-OP-58. | E30: The annex of May 2026 replaces the target-based schemes (OQ39). | F30: Superseded by CLR-OP-58: the incentives follow each insurer's SLA per invoice; the programmes stay inactive until BDOI gives the SLA parameters. | G30: FRS BRD-02 v2.1, Proposed business rules and clarifications; CMRID.005, 006; FR-OP-095; also raised as OQ39 (open question), SP-SQ14 (open question) | H30: Head, Operations Services | I30: 46356 | J30: Medium | K30: Partly answered | M30: Answer so far: No Touch = submitted CBG Motor accounts billed a service fee; criteria on the products matrix; CPC2 defined. Targets and tiers open. (Report List #164; BRD-3 PMADD07 / 08; BRD-5 DIS 3.29.2).
A31: CLR-OP-25 | B31: BRD-02 Operations | C31: Business rule confirmation | D31: Collection and Disbursement systems: Confirm the uploads and the queue until then. | E31: The Collection and Disbursement systems are replaced by BIBS modules (OQ01, OQ02, OQ45). | F31: Uploads for the Collection data and an in-app Disbursement queue, until BRD-4 Collections and BRD-5 Disbursement replace them. | G31: FRS BRD-02 v2.1, Proposed business rules and clarifications; BRQID.004, MKTID.010, 013, CMRID.001, DBMID.001, RMTID.034; FR-OP-130, 120; also raised as OQ01 (open question), OQ02 (open question), OQ45 (open question), DCR-023 (register item) | H31: Operations - Financial Transactions and Processing | I31: 46356 | J31: Medium | K31: Partly answered | M31: Answer so far: Collection, Accounting, Disbursement and Claims are BIBS modules. Marketing (ISYS) open. (BRD-4 p.37-39; BRD-5 FRBS 2.5.0, DIS 3.25.0; BRD-7 p.23; BRD-8 BRID-021); Disbursement is a Comptrollership unit working in BIBS; it creates DVs from system-triggered requests and returns instrument statuses. (BRD-5 DIS 2.7.5-2.7.12, 2.20.0, 3.25.0); Tagging dispositions and the handling-fee disposition are Marketing activities in BIBS. Holds and special remittance open. (BRD-4; BRD-12 BRIDSP-31). Also affects BRD-04.
A32: CLR-OP-26 | B32: BRD-02 Operations | C32: Configuration value | D32: Match keys and automatch frequency: Give the match keys and the automatch frequency (OQ30). | E32: The keys and the frequency are not given (OQ30). | F32: Lines are matched on the match keys of the reconciliation parameters in order (by default the invoice number, then the policy number); the automatch runs on every upload and when the handler clicks Match Again. | G32: FRS BRD-02 v2.1, Proposed business rules and clarifications; PRCID.024-027; FR-OP-075; also raised as OQ30 (open question) | H32: Head, Operations Services | I32: 46356 | J32: Medium | K32: Open
A33: CLR-OP-28 | B33: BRD-02 Operations | C33: Business rule confirmation | D33: Insurer in the references: Confirm the short code in the references and record titles, or ask for the name there. | E33: The code in the reference tells the insurer at a glance in lists and file names. | F33: Remittance batches, reconciliation cycles and their titles carry the insurer's short code in the reference (for example RMB-INS-MGIC-2026-000001, PRC-INS-MGIC-202609-000001); the insurer's name shows in the record facts and the documents. | G33: FRS BRD-02 v2.1, Proposed business rules and clarifications; screen standards | H33: Head, Operations Services | I33: 46356 | J33: Medium | K33: Open
A34: CLR-OP-32 | B34: BRD-02 Operations | C34: Configuration value | D34: Insurer's decision in the DP billing: Confirm the values, or give the insurers' wording. | E34: Fixed values let the answer be read without interpretation. | F34: The insurer answers each account in the Decision column with Approved or Rejected (Yes or No is read the same way) and gives the reason of a rejection; DP Responses reads these values. | G34: FRS BRD-02 v2.1, Proposed business rules and clarifications; DO-08 | H34: Head, Operations Services | I34: 46356 | J34: Medium | K34: Open
A35: CLR-OP-33 | B35: BRD-02 Operations | C35: Clarification | D35: Hold reasons: Give the list of hold reasons (OQ24). | E35: The list is to be supplied by BDOI (OQ24). | F35: The hold reason list has one value, Others, with the comment, until BDOI gives its list. | G35: FRS BRD-02 v2.1, Proposed business rules and clarifications; MKTID.003; FR-OP-111; also raised as OQ24 (open question) | H35: Head, Operations Services | I35: 46356 | J35: Medium | K35: Open
A36: CLR-OP-34 | B36: BRD-02 Operations | C36: Business rule confirmation | D36: Insurer references in the generated workbooks: Confirm the layout for the insurers, or give the layout each insurer needs. | E36: The files are read back by the insurers and by BIBS. | F36: The production register and the DP billing show the insurer's short code, the dates as yyyy-mm-dd and the remittance status as a code, for the insurer's own systems to read. | G36: FRS BRD-02 v2.1, Proposed business rules and clarifications; DO-07, DO-08 | H36: Head, Operations Services | I36: 46356 | J36: Medium | K36: Open
A37: CLR-OP-35 | B37: BRD-02 Operations | C37: Business rule confirmation | D37: Basis of the recompute: Confirm the premium in force of the policy year as the basis. | E37: The cancellation takes back the whole policy year, so a Before of the booking invoice alone would show negative After amounts. | F37: Before, Change and After of a request are all taken on the premium in force of the policy year: the invoice with the endorsements and returns of the same policy year, as booking computes a cancellation. A flat cancellation of a policy with later endorsements therefore shows the whole policy year going to zero; a write-off or a non-financial request stays on the invoice alone. | G37: FRS BRD-02 v2.1, Proposed business rules and clarifications; ADJID.014; FR-OP-054 | H37: Head, Operations Services | I37: 46356 | J37: Medium | K37: Open
A38: CLR-OP-36 | B38: BRD-02 Operations | C38: Business rule confirmation | D38: Approval status of the May 2026 annexes: Confirm that the annexes are approved as issued, or have the two signatures added. | E38: On the overall approval page of the annexes (p.66) Jose Melvin Jarin is marked on leave and Roderick Lim has neither signed nor dated. | F38: The set treats the five annexes as approved by their signatories (p.8, 18, 27, 39, 65) and BRD v1.01 as approved on its sheet (p.184-185). | G38: FRS BRD-02 v2.1, Proposed business rules and clarifications; R2; references | H38: Head, Operations Services | I38: 46356 | J38: Medium | K38: Open
A39: CLR-OP-37 | B39: BRD-02 Operations | C39: Business rule confirmation | D39: Audit trail standard: Confirm that the seven items and the recording of refused actions meet the IT audit standard; BDOI IT confirms the origin detail it needs. | E39: BDOI Operations made its sign-off of BRD v1.01 conditional on this standard. | F39: Every Operations audit record holds the seven items of the IT standard: user, event type, module, from and to values, origin of the event (IP address, MAC address, terminal ID or equivalent), date and time, success or failure indicator; refused actions are recorded with Failure. | G39: FRS BRD-02 v2.1, Proposed business rules and clarifications; BRD v1.01 sign-off, p.67, p.186; NFR; FR-OP-024 | H39: Head, Operations Services | I39: 46356 | J39: Medium | K39: Open
A40: CLR-OP-38 | B40: BRD-02 Operations | C40: Business rule confirmation | D40: Check pick-up removed: Confirm the withdrawal in both sets, and whether the cancellation reason "Check not picked up" stays in the receipt cancellation reasons. | E40: The Cashiering annex (p.4-6, MOM 05052026) removes CSHID.009 because the process is no longer part of BDOI's target process. | F40: The Check Pick-up screen, the pick-up requests from Collections, the Check Pick-ups Due tile and the pick-up report are withdrawn; checks picked up by Marketing Collection are received like any other check. The same removal applies to the hand-off of FRS BRD-4 Collections (FR-CL-032 and its walkthrough WT-A), which the Collections set handles. | G40: FRS BRD-02 v2.1, Proposed business rules and clarifications; CSHID.009; FR-OP-017; cross-reference BRD-4 Collections | H40: Head, Operations Services | I40: 46356 | J40: Medium | K40: Open
A41: CLR-OP-39 | B41: BRD-02 Operations | C41: Configuration value | D41: Minimal balances at processing: Confirm the threshold values and that a balance of exactly 10.00 is cleared at processing, not written off by the file. | E41: The annex requires clearing when the transaction is processed, a configurable threshold and no duplicate reversal; the BRD has a second rule of 10.00 to 100.00 in Adjustment (OQ11). | F41: Minimal balances and minimal excess payments are cleared in the posting of the payment, never routed to Unapplied Payments; the daily run stays as a safety net for balances left by later events. Threshold 10.00 for premium and excess until BDOI confirms; the Adjustment file keeps 10.00 to 100.00. | G41: FRS BRD-02 v2.1, Proposed business rules and clarifications; CSHID.016; FR-OP-023, 059 | H41: Head, Operations Services | I41: 46356 | J41: Medium | K41: Open
A42: CLR-OP-40 | B42: BRD-02 Operations | C42: Business rule confirmation | D42: Owner of the PR 2307 reversal: Confirm Marketing Collection as owner of every step and the handling of a 2% paid in cash. | E42: BRD v1.01 deletes the Cashiering steps and the e-mail record confirms "the removal of cashiering from certificate handling". | F42: Marketing Collection tags, validates against the certificates, generates and posts the BIR 2307 transaction report and routes it to Disbursement; the Cashier's 2307 right moves to Marketing Collection. The cash payment of the 2% by a client is received by Cashiering as an ordinary payment applied to the withheld portion, without a 2307 tag (the Settle in Cash step of v2.0 is withdrawn). The screens of chapter 13 show the v2.0 layout and are updated with this change. | G42: FRS BRD-02 v2.1, Proposed business rules and clarifications; MKTID.013; CSHID.026, 027 deleted; FR-OP-026, 113, 121 | H42: Head, Operations Services | I42: 46356 | J42: Medium | K42: Open
A43: CLR-OP-42 | B43: BRD-02 Operations | C43: Business rule confirmation | D43: Outstanding commission receivable (CRU) in the PR 2307 reversal: Confirm the definition of the CRU and the follow-up by Commission Receivables. | E43: The BRD names the CRU check but does not define the CRU or what the Commission Receivables team does with the flag. | F43: CRU means a commission receivable of BDOI still unpaid on the same invoice or account (a DP commission billed or not yet collected). When one exists, the reversal and release continue, the tag is flagged For Commission Receivable and listed for the Commission Receivables team. | G43: FRS BRD-02 v2.1, Proposed business rules and clarifications; MKTID.010, 013; FR-OP-113, 094 | H43: Head, Operations Services | I43: 46356 | J43: Medium | K43: Open
... A48: CLR-OP-48 | B48: BRD-02 Operations | C48: Sample document or template | D48: Cover letter: Confirm whether PRCID.003 is removed from scope or only unchanged. | E48: The Production Reconciliation annex says cover letter generation "is no longer included in this addendum" but prints PRCID.003 unchanged; BRD v1.01 keeps it. | F48: The register is sent with the cover letter as in v2.0 until BDOI confirms. | G48: FRS BRD-02 v2.1, Proposed business rules and clarifications; PRCID.003; FR-OP-073 | H48: Head, Operations Services | I48: 46356 | J48: Medium | K48: Open
A49: CLR-OP-49 | B49: BRD-02 Operations | C49: Configuration value | D49: Peso-equivalent tolerance: Confirm the rate and the date of the conversion. | E49: The annex asks for the conversion without naming the rate or its date (OQ08). | F49: The difference of a foreign currency account is converted to pesos at the BOOK rate of the booking date of the invoice before the 1.00 tolerance is applied. | G49: FRS BRD-02 v2.1, Proposed business rules and clarifications; PRCID.026; FR-OP-075; also raised as OQ08 (open question) | H49: Head, Operations Services | I49: 46356 | J49: Medium | K49: Partly answered | M49: Answer so far: A monthly revaluation rate is entered in BIBS. Its use for receipts is not stated. (BRD-5 FRBS 2.2.0, 3.5.0, 3.6.0).
A50: CLR-OP-50 | B50: BRD-02 Operations | C50: Business rule confirmation | D50: Reconciliation statuses: Confirm the mapping of the five statuses to the three of the annex. | E50: The annex names three statuses; the three kinds of Unmatched let each be followed (CLR-OP-18). | F50: Matched and Matched with Discrepancy as in the annex; the annex status Unmatched is shown as three kinds: BDOI Only, Unmatched - Pre-booked and Unmatched - No Booking. A record with a variance reported by the insurer is never Matched. | G50: FRS BRD-02 v2.1, Proposed business rules and clarifications; PRCID.022, 030; FR-OP-074, 075 | H50: Head, Operations Services | I50: 46356 | J50: Medium | K50: Open
A51: CLR-OP-51 | B51: BRD-02 Operations | C51: Business rule confirmation | D51: Renumbered Marketing activities: Confirm whether ADJID.003 moved to Marketing and which MKTID was deleted. | E51: The revision log of the Adjustment annex names ADJID.003 and "deleted duplicate MKTID", which its table does not show (OQ32). | F51: The FRs are traced to MKTID.014-019; ADJID.003 stays an Adjustment requirement and MKTID.008 stays next to MKTID.018 until BDOI confirms which one was deleted as the duplicate. | G51: FRS BRD-02 v2.1, Proposed business rules and clarifications; MKTID.008, 014-019; ADJID.003; FR-OP-050, 053, 060, 114 | H51: Head, Operations Services | I51: 46356 | J51: Medium | K51: Open
A52: CLR-OP-52 | B52: BRD-02 Operations | C52: Business rule confirmation | D52: Return of endorsement requests: Confirm the mandatory reason. | E52: ADJID.005 says the reason is optional in its expected result and "mandatory or configurable" in its criteria; MKTID.016 makes it mandatory. | F52: A reason from the list is mandatory for every return; the request goes to the Marketing owner of the account, who corrects and resubmits; the request page shows each return and resubmission. | G52: FRS BRD-02 v2.1, Proposed business rules and clarifications; ADJID.005, MKTID.016; FR-OP-053 | H52: Head, Operations Services | I52: 46356 | J52: Medium | K52: Open
A53: CLR-OP-53 | B53: BRD-02 Operations | C53: Configuration value | D53: Justification and over-adjustment limits: Give the limit per adjustment and the warning level. | E53: The annex sets the rules but not the values of the limit per adjustment and of "approaching" (OQ37). | F53: Justification is required when a single adjustment exceeds the limit per adjustment, the balance becomes negative, the cumulative adjustments approach or exceed the original premium or DTIP, or a duplicate is overridden; warning at 90% of the original premium; cumulative limit 100%. | G53: FRS BRD-02 v2.1, Proposed business rules and clarifications; ADJID.023 annex; FR-OP-058; also raised as OQ37 (open question) | H53: Head, Operations Services | I53: 46356 | J53: Medium | K53: Open
A54: CLR-OP-54 | B54: BRD-02 Operations | C54: Business rule confirmation | D54: Source of the DP entries: Confirm the withdrawal of the DP list upload. | E54: The annex introduction eliminates manual file uploads, while CMRID.001 is reprinted with the Head Office and branch DP lists (OQ38). | F54: The DP tagging of the booking confirmed by Marketing Collection is the source of the DP entries; the DP list upload stays as a fallback until BDOI withdraws it. | G54: FRS BRD-02 v2.1, Proposed business rules and clarifications; CMRID.001; FR-OP-090; also raised as OQ38 (open question), EBQ17 (open question) | H54: Head, Operations Services | I54: 46356 | J54: Medium | K54: Partly answered | M54: Answer so far: DP list is the Collections disposition "DP PR for reversal"; EB direct billing uploaded by the AO. (BRD-4 FRID-024 / 025 / 028; BRD-8 BRID-025).
A55: CLR-OP-55 | B55: BRD-02 Operations | C55: Business rule confirmation | D55: Read-only review of DP entries: Confirm the flags shown (missing data, duplicate, status discrepancy). | E55: CMRID.002 forbids validation, reconciliation, matching and computation in the review but allows highlighting inconsistencies. | F55: The review shows the production record, commission history, remittance and commission status read-only and highlights visible inconsistencies as flags; the v2.0 ledger checks become such flags and no longer set a sanitation result. | G55: FRS BRD-02 v2.1, Proposed business rules and clarifications; CMRID.002; FR-OP-091 | H55: Head, Operations Services | I55: 46356 | J55: Medium | K55: Open
A56: CLR-OP-56 | B56: BRD-02 Operations | C56: Business rule confirmation | D56: Exclusion rules: Provide the annex of exclusion criteria; confirm the withdrawal of the manual exclusion. | E56: CMRID.003 refers to an annex of exclusion criteria that is not in the document and forbids undefined terms and user-driven exclusion. | F56: Rules Negative amount and Fully cancelled (the v2.0 rule "erroneous booking" is renamed); the handler's manual exclusion with a reason is withdrawn; other rules are added from BDOI's annex of criteria. | G56: FRS BRD-02 v2.1, Proposed business rules and clarifications; CMRID.003; FR-OP-091, 095 | H56: Head, Operations Services | I56: 46356 | J56: Medium | K56: Open
A57: CLR-OP-57 | B57: BRD-02 Operations | C57: Business rule confirmation | D57: Classification of commission entries: Confirm the categories and who sets the Priority tag. | E57: The requirement text names Priority / Direct Payment / Direct Bill against Regular Commission, while the expected result names Direct Billed (Regular) and Direct Billed (Priority); the source of the Priority tag is not given. | F57: Direct Billed (Regular) and Direct Billed (Priority) for direct payment / direct bill entries, Regular Commission for non-direct bill accounts; the Priority tag is proposed as a flag on the DP tagging at quotation or policy. | G57: FRS BRD-02 v2.1, Proposed business rules and clarifications; CMRID.004; FR-OP-098 | H57: Head, Operations Services | I57: 46356 | J57: Medium | K57: Open
A58: CLR-OP-58 | B58: BRD-02 Operations | C58: Master data | D58: SLA incentive programmes: Give the SLA parameters per insurer; confirm whether incentives are passed on to branches. | E58: The annex replaces the production-target incentives and the Motor Mania plan; the SLA parameters are not given and the pass-on to branches is no longer stated (OQ39). | F58: Programmes are configured from each insurer's SLA (criteria, rate or fixed amount, multiplier, credit term, product, period, branch, marketing unit); No Touch, Top Up and Motor Mania become entries of the programme type list; the branch pass-on is kept only if BDOI confirms it. | G58: FRS BRD-02 v2.1, Proposed business rules and clarifications; CMRID.005, 006; FR-OP-095 | H58: Head, Operations Services | I58: 46356 | J58: Medium | K58: Open
A59: CLR-OP-59 | B59: BRD-02 Operations | C59: Configuration value | D59: Statement of Account: Give the SOA layout and the schedule. | E59: The annex asks for outputs usable for SOA preparation without a layout (OQ38). | F59: A Statement of Account per insurer (proposed layout in FR-OP-092) besides the billing; billings and statements on demand or on a schedule. | G59: FRS BRD-02 v2.1, Proposed business rules and clarifications; CMRID.007; FR-OP-092 | H59: Head, Operations Services | I59: 46356 | J59: Medium | K59: Open
A60: CLR-OP-60 | B60: BRD-02 Operations | C60: Business rule confirmation | D60: DP account statuses: Confirm the statuses and give the feedback reasons. | E60: The annex replaces the tags DP for billing and DP for confirmation by Valid / Invalid / Returned (OQ40). | F60: Valid (eligible, not excluded, approved), Invalid (excluded or rejected) and Returned (sent back for correction or review), with a predefined reason before Invalid or Returned is final; the v2.0 tags map to them. | G60: FRS BRD-02 v2.1, Proposed business rules and clarifications; CMRID.008; FR-OP-091, 093; also raised as OQ40 (open question) | H60: Head, Operations Services | I60: 46356 | J60: Medium | K60: Open
A61: CLR-OP-61 | B61: BRD-02 Operations | C61: Configuration value | D61: Ageing of commission receivables: Confirm the buckets and the reference date, and whether the reminder stays. | E61: The annex replaces the 10-working-day feedback timeline by ageing and rejects "timeline tracking instead of ageing logic"; CMRID.009 still asks for billing within the SLA (OQ43). | F61: Ageing per invoice from the billing date or the SOA date with buckets 0-30, 31-60, 61-90, 91-180 and over 180 days; the 10-working-day follow-up date is kept as a reminder that the handler can switch off. | G61: FRS BRD-02 v2.1, Proposed business rules and clarifications; CMRID.011; FR-OP-092, 093, 099; also raised as OQ43 (open question), DCR-084 (register item), DCR-158 (register item) | H61: Claims and Risk Management | I61: 46356 | J61: Medium | K61: Partly answered | M61: Answer so far: ACSL ageing buckets given; Collections and Cashiering buckets not given. (BRD-5 Appendix C). Also affects BRD-04, BRD-05, BRD-07.
A62: CLR-OP-62 | B62: BRD-02 Operations | C62: Business rule confirmation | D62: Fully paid status for billing: Confirm the payment status as the source, with the BRD-4 Collections owners. | E62: The annex requires system-driven eligibility from the PR tagging upstream and no manual inference. | F62: An account is eligible for billing when the payment status of the invoice ledger is Paid (fed by Cashiering and the Collections dispositions of BRD-4); the handler no longer confirms the payment and no manual override is offered. | G62: FRS BRD-02 v2.1, Proposed business rules and clarifications; CMRID.013; FR-OP-091 | H62: Head, Operations Services | I62: 46356 | J62: Medium | K62: Open
A63: OQ05 | B63: BRD-02 Operations | C63: Configuration value | D63: Receipt series: AR / OR numbering: BIR ATP series per branch? Format and length; pre-printed vs system-generated receipts (CAS registration); low-series warning threshold; are AR numbers BIR-controlled like ORs? | E63: Open point of the FRS (FR-OP-010): the requirement cannot be finalised or tested as BDOI intends until it is answered. | G63: FRS BRD-02 v2.1, Open questions OQ05 (affects FR-OP-010); Discrepancy and clarification register v1.2, open question OQ05; baseline CSHID.001/002/006/015/019 | H63: Head, Operations Services | I63: 46356 | J63: Medium | K63: Open
A64: OQ09 | B64: BRD-02 Operations | C64: Clarification | D64: Application hierarchy: Component hierarchy DST -> VAT -> LGT -> Other -> Basic confirmed; meaning of mode-of-payment hierarchy 'Check, Cash'; order across several invoices of one payer (oldest first?); hierarchy for commission receipts. | E64: Open point of the FRS (FR-OP-019): the requirement cannot be finalised or tested as BDOI intends until it is answered. | G64: FRS BRD-02 v2.1, Open questions OQ09 (affects FR-OP-019); Discrepancy and clarification register v1.2, open question OQ09; baseline CSHID.022, CSHID.020 | H64: Head, Operations Services | I64: 46356 | J64: Medium | K64: Open
A65: OQ10 | B65: BRD-02 Operations | C65: Sample document or template | D65: 2% CWT: Which clients / invoices are 2% CWT (flag source)? Apply 98% and keep 2% as PR2307 until certificate - confirm. CSHID.026 cash path says 'premium is reversed, remittance processed': which entries? | E65: Open point of the FRS (FR-OP-018): the requirement cannot be finalised or tested as BDOI intends until it is answered. | G65: FRS BRD-02 v2.1, Open questions OQ10 (affects FR-OP-018); Discrepancy and clarification register v1.2, open question OQ10; baseline CSHID.020/026/016, MKTID.010 | H65: Head, Operations Services | I65: 46356 | J65: Medium | K65: Partly answered | M65: Answer so far: Net-of-CWT payments keep the tag with Marketing until the BIR 2307 is collected. (BRD-4 p.41, p.59).
A66: OQ12 | B66: BRD-02 Operations | C66: Configuration value | D66: Pre-booked matching: Key used to match a payment to a pre-booked account (ARN, invoice no., PN no.?), re-run schedule, retention in the pre-booked table. BRD-1 placement also matches CLPC payments before placement (BRNB.067/068): confirm Cashiering is the single payment intake and the placement gate consumes its result. | E66: Open point of the FRS (FR-OP-018): the requirement cannot be finalised or tested as BDOI intends until it is answered. | G66: FRS BRD-02 v2.1, Open questions OQ12 (affects FR-OP-018); Discrepancy and clarification register v1.2, open question OQ12; baseline CSHID.020, CSHID.008 | H66: Head, Operations Services | I66: 46356 | J66: Medium | K66: Partly answered | M66: Answer so far: Handling fee: PN for CLPC, Location Reference for OTC; PN is the LAMD matching key. General pre-booked key open. (BRD-12 BRIDSP-31; BRD-6 BRRN.029 / 039).
A67: OQ13 | B67: BRD-02 Operations | C67: Clarification | D67: Check pick-up: How does the Collection 'for check pick' status reach Operations? Is the AR printed and handed over at pick-up? | E67: Open point of the FRS (FR-OP-017 (removed from scope, CSHID.009): the requirement cannot be finalised or tested as BDOI intends until it is answered. | G67: FRS BRD-02 v2.1, Open questions OQ13 (affects FR-OP-017 (removed from scope, CSHID.009)); Discrepancy and clarification register v1.2, open question OQ13; baseline CSHID.009 | H67: Head, Operations Services | I67: 46356 | J67: Medium | K67: Answered | M67: Answer so far: Check pick-up is a Collection Handler task in BIBS. Printing of the AR at pick-up open. (BRD-4 p.40).
A68: OQ14 | B68: BRD-02 Operations | C68: Clarification | D68: AR Insurance: Definition and identification of non-premium insurer payments (refunds of remitted premium, others) and the AR Insurance accounting. | E68: Open point of the FRS (FR-OP-021): the requirement cannot be finalised or tested as BDOI intends until it is answered. | G68: FRS BRD-02 v2.1, Open questions OQ14 (affects FR-OP-021); Discrepancy and clarification register v1.2, open question OQ14; baseline CSHID.021, ADJID.012 | H68: Head, Operations Services | I68: 46356 | J68: Medium | K68: Partly answered | M68: Answer so far: AR insurer's refund and A/P refund from insurer are separate schedules. (BRD-5 Appendix C).
A69: OQ25 | B69: BRD-02 Operations | C69: Configuration value | D69: Special remittance: Approvers and SLA; exact eligibility for claims / renewal / installment / immediate OR. | E69: Open point of the FRS (FR-OP-112): the requirement cannot be finalised or tested as BDOI intends until it is answered. | G69: FRS BRD-02 v2.1, Open questions OQ25 (affects FR-OP-112); Discrepancy and clarification register v1.2, open question OQ25; baseline MKTID.009, RMTID.030 | H69: Head, Operations Services | I69: 46356 | J69: Medium | K69: Partly answered | M69: Answer so far: Claims condition: invoice of the cover of an open claim in status "With BDOI - For Premium Remittance". Approvers and SLA open. (BRD-7 BRCLM.010).
A70: OQ26 | B70: BRD-02 Operations | C70: Clarification | D70: Write-off: Who writes off accounts and through which transaction (adjustment request type 'Write-off', minimal balance file)? | E70: Open point of the FRS (FR-OP-059): the requirement cannot be finalised or tested as BDOI intends until it is answered. | G70: FRS BRD-02 v2.1, Open questions OQ26 (affects FR-OP-059); Discrepancy and clarification register v1.2, open question OQ26; baseline RMTID.022, ADJID.026 | H70: Head, Operations Services | I70: 46356 | J70: Medium | K70: Open
A71: OQ31 | B71: BRD-02 Operations | C71: Clarification | D71: Recon lists: Company-concerned list (to be provided), disposition list for unmatched items, 'For Closure' handling. | E71: Open point of the FRS (FR-OP-077): the requirement cannot be finalised or tested as BDOI intends until it is answered. | G71: FRS BRD-02 v2.1, Open questions OQ31 (affects FR-OP-077); Discrepancy and clarification register v1.2, open question OQ31; baseline PRCID.016/033/038/039 | H71: Head, Operations Services | I71: 46356 | J71: Medium | K71: Open
A72: OQ34 | B72: BRD-02 Operations | C72: Configuration value | D72: Service invoice on adjustments: Addendum ADJID.014: for a decrease in commission / income, is a credit memo or a negative service invoice issued? Numbering and recipient. | E72: Open point of the FRS (FR-OP-054): the requirement cannot be finalised or tested as BDOI intends until it is answered. | G72: FRS BRD-02 v2.1, Open questions OQ34 (affects FR-OP-054); Discrepancy and clarification register v1.2, open question OQ34; baseline ADJID.014, BRNB.100 | H72: Head, Operations Services | I72: 46356 | J72: Medium | K72: Open
A73: OQ35 | B73: BRD-02 Operations | C73: Business rule confirmation | D73: Endorsement type names: 'Extension of cover' is both financial (ADJID.002e / 010, additional premium, approval) and non-financial (ADJID.004 items 2-4). Confirm the list and who approves additional premium. | E73: Open point of the FRS (FR-OP-050, 053): the requirement cannot be finalised or tested as BDOI intends until it is answered. | F73: Two types: "Extension of cover (period, with premium)" and "Additional clause / warranty (no premium)". | G73: FRS BRD-02 v2.1, Open questions OQ35 (affects FR-OP-050, 053); Discrepancy and clarification register v1.2, open question OQ35; baseline ADJID.002/004/010; also raised as DCR-018 (register item) | H73: Operations - Financial Transactions and Processing | I73: 46356 | J73: Medium | K73: Open
A74: OQ36 | B74: BRD-02 Operations | C74: Configuration value | D74: Refund computation: Partial cancellation and decrease of TSI: pro-rata or short-period rate; 'Canceled flat retain DST'; commission recovery. | E74: Open point of the FRS (FR-OP-054): the requirement cannot be finalised or tested as BDOI intends until it is answered. | G74: FRS BRD-02 v2.1, Open questions OQ36 (affects FR-OP-054); Discrepancy and clarification register v1.2, open question OQ36; baseline ADJID.009/014 | H74: Head, Operations Services | I74: 46356 | J74: Medium | K74: Open
A75: OQ41 | B75: BRD-02 Operations | C75: Sample document or template | D75: BIR certificates: CMRID.015 certificates are insurers' EWT certificates on commissions paid to BDOI: confirm, and the Comptrollership acknowledgment roles. | E75: Open point of the FRS (FR-OP-096): the requirement cannot be finalised or tested as BDOI intends until it is answered. | G75: FRS BRD-02 v2.1, Open questions OQ41 (affects FR-OP-096); Discrepancy and clarification register v1.2, open question OQ41; baseline CMRID.010/015 | H75: Head, Operations Services | I75: 46356 | J75: Medium | K75: Answered | M75: Answer so far: Disbursement receives the insurers' CWT certificates on commission and incentives and tags them. (BRD-5 DIS 2.11, Appendix B).
A76: OQ42 | B76: BRD-02 Operations | C76: Report layout | D76: Report layouts: Fields / formats for reports without detail in the Annex (Cashiering 9-18, 20-21; Remittance 8) and for CMRID.004 / 014. | E76: Open point of the FRS (Section 6; FR-OP-099 (CLR-OP-61): the requirement cannot be finalised or tested as BDOI intends until it is answered. | G76: FRS BRD-02 v2.1, Open questions OQ42 (affects Section 6; FR-OP-099 (CLR-OP-61)); Discrepancy and clarification register v1.2, open question OQ42; baseline CSHID.023, RMTID.039, CMRID.004/014; also raised as CLQ21 (open question), SANC-SQ17 (open question) | H76: Head, Operations Services | I76: 46356 | J76: Medium | K76: Partly answered | M76: Answer so far: Key fields of Cashiering 9-18, 20-21 and Remittance 8 listed. (Report List #85-96, #103; BRD-5 Appendices B-C); Report List of 13-May-2026.
A77: OQ47 | B77: BRD-02 Operations | C77: Clarification | D77: Search logs: Purpose and retention of search logs (CSHID.010 AC 7). | E77: Open point of the FRS (FR-OP-024): the requirement cannot be finalised or tested as BDOI intends until it is answered. | G77: FRS BRD-02 v2.1, Open questions OQ47 (affects FR-OP-024); Discrepancy and clarification register v1.2, open question OQ47; baseline CSHID.010 | H77: Head, Operations Services | I77: 46356 | J77: Medium | K77: Open
A78: OQ50 | B78: BRD-02 Operations | C78: Clarification | D78: Co-insured remittance: For co-insured invoices, is remittance extracted and scheduled per insurer share? | E78: Open point of the FRS (FR-OP-007): the requirement cannot be finalised or tested as BDOI intends until it is answered. | G78: FRS BRD-02 v2.1, Open questions OQ50 (affects FR-OP-007); Discrepancy and clarification register v1.2, open question OQ50; baseline ADJID.027, RMTID.001 | H78: Head, Operations Services | I78: 46356 | J78: Medium | K78: Open
A79: DCR-011 | B79: BRD-02 Operations | C79: Business rule confirmation | D79: None; recorded for traceability. BDOI to confirm the main-BRD wording is superseded. | E79: Main BRD: "Facility to allow User to edit the extracted file" and push it "with or without edit". Addendum 1: users "mark specific record or row for exclusion"; only non-excluded data is pushed; no editing of financial data. System: remittance extraction screen. The addendum governs. | F79: Exclusion only (no edit of financial fields), per Addendum 1. | G79: Discrepancy and clarification register v1.2, DCR-011 (Contradiction within BRD); RMTID.002: main BRD (p.50) and Addendum 1 (p.3-4) | H79: Operations - Financial Transactions and Processing | I79: 46356 | J79: Medium | K79: Answered | M79: Answer so far: Operations Addendum 1 (p.3-4): exclusion instead of edit; "When the file is pushed to Disbursement, only non-excluded data" is sent.
A80: DCR-021 | B80: BRD-02 Operations | C80: Configuration value | D80: Several IDs have no key-capability number. MKTID numbering does not follow document order (MKTID.013 is in Cashiering, MKTID.008 comes last, in Adjustment). None; correct in the next revision. | E80: Several IDs have no key-capability number. MKTID numbering does not follow document order (MKTID.013 is in Cashiering, MKTID.008 comes last, in Adjustment). Traceability only. | F80: Trace by ID; key capability inferred from the section. | G80: Discrepancy and clarification register v1.2, DCR-021 (Data / numbering issue); CSHID.026 / 027, RMTID.038 / 040, ADJID.026-028, CMRID.015, MKTID.010-013 | H80: Operations - Financial Transactions and Processing | I80: 46356 | J80: Low | K80: Open
A81: DCR-024 | B81: BRD-02 Operations | C81: Business rule confirmation | D81: The acronym table gives "DTIP - Due To Insurer Provider" and "BDOI - BDO Insurance Brokers, Inc." Please confirm the expansion of DTIP. | E81: The acronym table gives "DTIP - Due To Insurer Provider" and "BDOI - BDO Insurance Brokers, Inc." Glossary only. | F81: Glossary uses "Due to Insurance Provider" and the registered company name. | G81: Discrepancy and clarification register v1.2, DCR-024 (Document quality); Annex I acronyms (p.124) | H81: Operations - Financial Transactions and Processing | I81: 46356 | J81: Low | K81: Open
A82: DCR-026 | B82: BRD-02 Operations | C82: Business rule confirmation | D82: A reviewer date on the addendum approval page is written "1/6/2025"; the addendum is dated 18-Dec-2025, so it is probably 1/6/2026. Please confirm the date. | E82: A reviewer date on the addendum approval page is written "1/6/2025"; the addendum is dated 18-Dec-2025, so it is probably 1/6/2026. Approval record only. | F82: None. | G82: Discrepancy and clarification register v1.2, DCR-026 (Document quality); Addendum 1 approval (p.6) | H82: Operations - Financial Transactions and Processing | I82: 46356 | J82: Low | K82: Open
A83: SO-02-2 | B83: BRD-02 Operations | C83: Sign-off | D83: Approve the test plan of BRD-02 Operations. | E83: The signed document fixes the scope for the next step of the plan; a late sign-off moves the dates that follow it. | G83: Project plan v1.0 (8-Oct-2026), sign-offs and milestones | H83: Head, Operations Services | I83: 46374 | J83: High | K83: Open
A84: CLR-OP-15 | B84: BRD-02 Operations | C84: Integration detail | D84: Claims condition of a special remittance: Specify the Claims feed (OQ46). | E84: The Claims feed is not yet specified (OQ46). | F84: The claims condition is confirmed through the Claims feed when it is connected; until then the request carries a note. | G84: FRS BRD-02 v2.1, Proposed business rules and clarifications; MKTID.009; FR-OP-112; also raised as OQ46 (open question), DCR-022 (register item), DCR-086 (register item) | H84: BDOI IT with the BIBS Product Owner, with the owners of the BRDs involved | I84: 46418 | J84: High | K84: Partly answered | M84: Answer so far: Claims blocks on unpaid premium and feeds the special remittance; Renewal needs claims per expiring policy. (BRD-7 BRCLM.001 / 010; BRD-6 BRRN.027 / 031 / 034). Also affects BRD-04, BRD-05, BRD-07.
A85: CFG-100 | B85: BRD-02 Operations | C85: Master data | D85: Insurers and insurer branches: The insurer panel with accreditation, placement e-mails and credit days, and the insurer branches with their LGT rate (BRD-03 template CI-05) | E85: Needed for: Reference data for Trial migration 1 (M4) (Extracts for Trial migration 1; reference data and clients first). | F85: Fill in the templates R04, R04B, R07 of the Master Data and Configuration Upload Templates workbook. | G85: Drop 0 configuration register CFG-100 (Drop 0 Configuration Inputs v2.0, area Insurers and partners) | H85: Head, Operations Services | I85: 46486 | J85: High | K85: Open
A86: CFG-101 | B86: BRD-02 Operations | C86: Master data | D86: Commission rates by insurer and product: The commission rates in force at cut-over and later (commission rows of BRD-03 template CI-05) | E86: Needed for: Reference data for Trial migration 1 (M4) (Extracts for Trial migration 1; reference data and clients first). | F86: Fill in the templates R04, R04B, R07 of the Master Data and Configuration Upload Templates workbook. | G86: Drop 0 configuration register CFG-101 (Drop 0 Configuration Inputs v2.0, area Insurers and partners) | H86: Head, Operations Services | I86: 46486 | J86: High | K86: Open
A87: TD-02 | B87: BRD-02 Operations | C87: Test data | D87: Name the UAT testers of BRD-02 Operations (at least two per business unit, with their user IDs and group profiles) and provide the business data of the UAT scenarios: the clients, policies, insurers and amounts each scenario of the test plan uses, from the migrated data of Trial migration 3 or as additional cases. | E87: UAT of Drop 1 runs on migrated data and the production values; testers without access or scenarios without data stop the UAT. | F87: The test plan (04 workbook of the set) names the scenarios; the BDOI testers choose the cases from the migrated data and add the cases the legacy data does not hold. | G87: Project plan: dependency DEP-20 (UAT testers), milestone MS-20 (UAT plans, values for UAT and testers, 16-Jul-2027) | H87: Head, Operations Services (UAT testers of the business units) | I87: 46584 | J87: High | K87: Open
A88: CFG-044 | B88: BRD-02 Operations | C88: Configuration value | D88: Payment file layouts of the collection channels: Confirmation of the payment files received from Bills Payment, Trade, Direct Credit, CLPC and PMS and their field names | E88: Needed for: Values for UAT (UAT plans and sign-off forms due 16-Jul-2027; UAT Aug - Dec 2027 runs on the production values). | F88: Configured on the screen Finance › Cashiering › Cashiering Setup (sheet Configured on screens of the Master Data and Configuration Upload Templates workbook). | G88: Drop 0 configuration register CFG-044 (Drop 0 Configuration Inputs v2.0, area Banks and bank accounts) | H88: Head, Operations Services | I88: 46584 | J88: Medium | K88: Open
