Workbook
Name CODES_D0_02_BRANCH_CODE: 'D0-02 Branches'!$B$17:$B$517
Name CODES_D0_04_CODE: 'D0-04 Dimensions'!$C$17:$C$517
Name CODES_D0_06_ACCOUNT_CODE: 'D0-06 Chart of accounts'!$C$17:$C$517
Name CODES_D0_07_CATEGORY_CODE: 'D0-07 Categories and numbering'!$C$17:$C$517
Name CODES_PM_01_COVER_TYPE_CODE: 'PM-01 Product catalogue'!$E$17:$E$517
Name CODES_PM_01_LINE_CODE: 'PM-01 Product catalogue'!$B$17:$B$517
Name CODES_UA_02_GROUP_PROFILE_CODE: 'UA-02 Role matrix'!$B$17:$B$517
Name CODES_UA_01_USER_ID: 'UA-01 Users and roles'!$C$17:$C$517
Name CODES_PM_01_RISK_CODE: 'PM-01 Product catalogue'!$H$17:$H$517
Name CODES_D0_11_BANK_ACCOUNT_CODE: 'D0-11 Bank accounts'!$B$17:$B$517
Name CODES_D0_05_EMPLOYEE_NUMBER: 'D0-05 Employees'!$B$17:$B$517
Name CODES_PM_05_PARTNER_CODE: 'PM-05 Insurers'!$B$17:$B$517
Name LIST_YES_NO: 'Reference lists'!$C$5:$C$6
Name LIST_MARKET_SEGMENT: 'Reference lists'!$C$7:$C$11
Name LIST_PLACEMENT_GATE: 'Reference lists'!$C$12:$C$13
Name LIST_TSU_REVIEW: 'Reference lists'!$C$14:$C$16
Name LIST_CI02_RECORD: 'Reference lists'!$C$17:$C$19
Name LIST_DOCUMENT_TYPE: 'Reference lists'!$C$20:$C$82
Name LIST_CLAUSE_KIND: 'Reference lists'!$C$83:$C$86
Name LIST_RATE_TABLE: 'Reference lists'!$C$87:$C$89
Name LIST_MAP_ACTION: 'Reference lists'!$C$90:$C$91
Name LIST_PKG_DOCUMENT: 'Reference lists'!$C$92:$C$97
Name LIST_PM_LIST_OR_PARAMETER: 'Reference lists'!$C$98:$C$137
Name LIST_INCENTIVE_TYPE: 'Reference lists'!$C$138:$C$139
Name LIST_UA_ACTION: 'Reference lists'!$C$140:$C$143
Name LIST_PRIVILEGE_LEVEL: 'Reference lists'!$C$144:$C$147
Name LIST_KEEP_ADD_REMOVE: 'Reference lists'!$C$148:$C$150
Name LIST_UA_ROLE: 'Reference lists'!$C$151:$C$155
Name LIST_SOD_STATUS: 'Reference lists'!$C$156:$C$158
Name LIST_SOD_CONTROL: 'Reference lists'!$C$159:$C$161
Name LIST_REVIEW_FREQUENCY: 'Reference lists'!$C$162:$C$163
Name LIST_UA_PARAMETER: 'Reference lists'!$C$164:$C$180
Name LIST_UA_LIST: 'Reference lists'!$C$181:$C$183
Name LIST_DIMENSION: 'Reference lists'!$C$184:$C$185
Name LIST_ACCOUNT_CLASS: 'Reference lists'!$C$186:$C$190
Name LIST_ACCOUNT_CLASS_CHART: 'Reference lists'!$C$191:$C$196
Name LIST_ACCOUNT_LEVEL: 'Reference lists'!$C$197:$C$200
Name LIST_NEGATIVE_BALANCE: 'Reference lists'!$C$201:$C$203
Name LIST_CATEGORY_ROW: 'Reference lists'!$C$204:$C$205
Name LIST_ACCOUNTING_EVENT: 'Reference lists'!$C$206:$C$295
Name LIST_DEBIT_CREDIT: 'Reference lists'!$C$296:$C$297
Name LIST_LEGACY_ACCOUNT: 'Reference lists'!$C$298:$C$305
Name LIST_TAX_TYPE: 'Reference lists'!$C$306:$C$309
Name LIST_PAYEE_CLASS: 'Reference lists'!$C$310:$C$315
Name LIST_APPROVAL_MODULE: 'Reference lists'!$C$316:$C$319
Name LIST_ROUTE: 'Reference lists'!$C$320:$C$322
Name LIST_STATUS: 'Reference lists'!$C$323:$C$327
Name LIST_TEMPLATES: 'Reference lists'!$C$328:$C$359
Name LIST_QUESTION_STATUS: 'Reference lists'!$C$360:$C$362

Sheet Start here
A3: Drop 0 Configuration Inputs
A4: Every configuration input BDOI provides before go-live for Drop 0 and the platform set-up Drop 1 depends on
A6: Client | C6: BDO Insurance and Reinsurance Brokers, Inc.
A7: Scope | C7: Drop 0 (BRD-03, BRD-11, BRD-13) and the platform set-up Drop 1 depends on
A8: Version and date | C8: Version 2.1, 8 October 2026
A9: Go-live | C9: Go-live is proposed for Monday 3 January 2028 (T), at the year-end boundary (option A of the Data Migration set, for Comptrollership to confirm).
A10: Owner | C10: Program Manager, Business Project Services, with the BDOI owner of each item
A11: Prepared by | C11: iorta TechNXT
A12: Classification | C12: Confidential
A14: How to fill in this workbook
A15: 1 | B15: The index below lists every configuration input of Drop 0 and of the platform set-up that Drop 1 depends on, one row per item, by due date; within a due date the templates come in the order they are filled in, a template whose codes others use first.
A16: 2 | B16: Each item has one route. Template: fill in the template sheet (Open →); its rows are then entered or uploaded on the named screen and authorised by a second user. Screen: enter the item on the named BIBS screen and record the decision in BDOI comments. Migration object: the item comes from the legacy systems through the named object of the Migration Workbook (BRD-13); it is not typed here.
A17: 3 | B17: On a template sheet, read the header block and the guide above each column (Mandatory, Format, Allowed values, What to enter; * marks a mandatory column), overwrite or delete the grey example row and enter one row per record. Drop-downs offer the allowed values (sheet Reference lists) and the codes of the templates filled in before; a mandatory cell left empty turns red.
A18: 4 | B18: The sheets starting with Ref list every list of values, system parameter, numbering prefix, notification event, document template and accounting event of BIBS, and the migration cross-reference; set the value wanted, the decision or the comment on each row you own.
A19: 5 | B19: Set the Status of each item, follow Rows entered and Mandatory cells missing, raise questions on the sheet Questions and comments, and return the workbook to the iorta TechNXT project team by each due date. The status is reviewed at the weekly programme meeting. Codes must be the codes of the other sheets: branch codes of D0-02, accounts of D0-06, cost centres of D0-04, bank accounts of D0-11, group profiles of UA-02 and users of UA-01.
A21: Configuration inputs by due date, templates in the order they are filled in
A22: Step | B22: ID | C22: Configuration item | D22: What BDOI provides | E22: Owner (BDOI unit) | F22: Due | G22: Route | H22: Entered or loaded on | I22: Prepared in | J22: Depends on | K22: Rows entered | L22: Mandatory cells missing | M22: Status | N22: BDOI comments | O22: Provided on | P22: Open
A23: 1 | B23: CFG-023 | C23: Legacy control accounts and Migration Clearing | D23: The account codes of the legacy control accounts and of Migration Clearing in the production chart (proposed rule PR-DM-02) | E23: Head, Comptrollership | F23: 1-Dec-2026 – Drafts with the Drop 0 sign-off | G23: Template | H23: Finance › General Ledger › Chart of Accounts | I23: Drop 0 template D0-09, sheet D0-09 Legacy accounts | J23: D0-06 | K23: ='D0-09 Legacy accounts'!$C$9 | L23: ='D0-09 Legacy accounts'!$E$9 | M23: Not started | P23: D0-09 →
A24: 2 | B24: CFG-075 | C24: Directory sign-in and provisioning (EIAM, UIDM-ISC) | D24: The sign-in mode, the EIAM tenant and claims, and the UIDM-ISC option (clarifications CLR-UA-01 and CLR-UA-03) | E24: BDOI IT | F24: 1-Dec-2026 – Drafts with the Drop 0 sign-off | G24: Screen | H24: Setup & Administration › Administration › System Parameters | I24: This index row (decision and values in BDOI comments) | J24: - | M24: Not started
A25: 3 | B25: CFG-002 | C25: Branches and invoicing branches | D25: Every BDOI branch with its region, address, opening date, head-office flag, contact and weekly rest days; the legacy branch codes are mapped to them by the migration (R02, check only) | E25: Head, Comptrollership | F25: 4-Jan-2027 – Platform set-up for Drop 1 SIT | G25: Template | H25: Setup & Administration › Setup › Branches | I25: Drop 0 template D0-02, sheet D0-02 Branches | J25: - | K25: ='D0-02 Branches'!$C$9 | L25: ='D0-02 Branches'!$E$9 | M25: Not started | P25: D0-02 →
A26: 4 | B26: CFG-004 | C26: Cost centres and business lines | D26: The cost centres and business lines used on journal lines and in the cost-centre rules; the legacy cost centres are mapped by code map COST_CENTER | E26: Head, Comptrollership | F26: 4-Jan-2027 – Platform set-up for Drop 1 SIT | G26: Template | H26: Setup & Administration › Setup › Dimensions | I26: Drop 0 template D0-04, sheet D0-04 Dimensions | J26: - | K26: ='D0-04 Dimensions'!$C$9 | L26: ='D0-04 Dimensions'!$E$9 | M26: Not started | P26: D0-04 →
A27: 5 | B27: CFG-021 | C27: Account categories and numbering scheme | D27: The GL categories (with the bank categories) and the numbering scheme under each parent (separator and width) | E27: Head, Comptrollership | F27: 4-Jan-2027 – Platform set-up for Drop 1 SIT | G27: Template | H27: Finance › General Ledger › Chart of Accounts | I27: Drop 0 template D0-07, sheet D0-07 Categories and numbering | J27: - | K27: ='D0-07 Categories and numbering'!$C$9 | L27: ='D0-07 Categories and numbering'!$E$9 | M27: Not started | P27: D0-07 →
A28: 6 | B28: CFG-052 | C28: Account numbering scheme | D28: Covered by CFG-021: the separator and width of the account codes under each parent | E28: Head, Comptrollership | F28: 4-Jan-2027 – Platform set-up for Drop 1 SIT | G28: Template | I28: Drop 0 template D0-07, sheet D0-07 Categories and numbering | J28: - | K28: ='D0-07 Categories and numbering'!$C$9 | L28: ='D0-07 Categories and numbering'!$E$9 | M28: Not started | P28: D0-07 →
A29: 7 | B29: CFG-020 | C29: Chart of accounts | D29: The production chart of accounts of BDOI in the chart upload template: every account with its parent, class, level, control and sub-ledger flags, currencies and report group | E29: Head, Comptrollership | F29: 4-Jan-2027 – Platform set-up for Drop 1 SIT | G29: Template | H29: Finance › General Ledger › Chart Upload | I29: Drop 0 template D0-06, sheet D0-06 Chart of accounts | J29: D0-07 | K29: ='D0-06 Chart of accounts'!$C$9 | L29: ='D0-06 Chart of accounts'!$E$9 | M29: Not started | P29: D0-06 →
A30: 8 | B30: CFG-003 | C30: Holiday calendar | D30: Public and company holidays of 2027 and 2028, company-wide or per branch; they drive the working days of service levels, value dates and jobs | E30: Head, Comptrollership; Human Resources | F30: 4-Jan-2027 – Platform set-up for Drop 1 SIT | G30: Template | H30: Setup & Administration › Setup › Holiday Calendar | I30: Drop 0 template D0-03, sheet D0-03 Holiday calendar | J30: D0-02 | K30: ='D0-03 Holiday calendar'!$C$9 | L30: ='D0-03 Holiday calendar'!$E$9 | M30: Not started | P30: D0-03 →
A31: 9 | B31: CFG-040 | C31: Company bank accounts | D31: Every BDOI bank account used for collections and disbursements: bank, account number, currency, branch, GL account and PDC clearing account | E31: Head, Comptrollership; Treasury | F31: 4-Jan-2027 – Platform set-up for Drop 1 SIT | G31: Template | H31: Finance › Disbursement › Bank Accounts and Checks | I31: Drop 0 template D0-11, sheet D0-11 Bank accounts | J31: D0-06, D0-02 | K31: ='D0-11 Bank accounts'!$C$9 | L31: ='D0-11 Bank accounts'!$E$9 | M31: Not started | P31: D0-11 →
A32: 10 | B32: CFG-001 | C32: Company | D32: The BDOI company record: code, registered name, TIN, address, base currency, fiscal year start and the value-date window of postings | E32: Head, Comptrollership | F32: 4-Jan-2027 – Platform set-up for Drop 1 SIT | G32: Template | H32: Setup & Administration › Setup › Companies | I32: Drop 0 template D0-01, sheet D0-01 Company | J32: D0-06 | K32: ='D0-01 Company'!$C$9 | L32: ='D0-01 Company'!$E$9 | M32: Not started | P32: D0-01 →
A33: 11 | B33: CFG-022 | C33: Accounting rules per event | D33: For each accounting event of the platform, the debit and credit accounts per amount component, business line and currency | E33: Head, Comptrollership | F33: 4-Jan-2027 – Platform set-up for Drop 1 SIT | G33: Template | H33: Finance › Accounting Engine › Accounting Rules | I33: Drop 0 template D0-08, sheet D0-08 Accounting rules | J33: D0-04, D0-06 | K33: ='D0-08 Accounting rules'!$C$9 | L33: ='D0-08 Accounting rules'!$E$9 | M33: Not started | P33: D0-08 →
A34: 12 | B34: CFG-111 | C34: Role-to-permission matrix | D34: BRD-11 template CI-02 | E34: Business Administration with the unit heads; reviewed and signed by BDOI Information Security | F34: 9-Apr-2027 – Reference data for Trial migration 1 (M4) | G34: Template | H34: Setup & Administration › User Access › Group Profile Requests | I34: BRD-11 template CI-02, sheet UA-02 Role matrix | J34: - | K34: ='UA-02 Role matrix'!$C$9 | L34: ='UA-02 Role matrix'!$E$9 | M34: Not started | P34: UA-02 →
A35: 13 | B35: CFG-045 | C35: Bank list (mortgagee banks) | D35: The banks named as mortgagee or payout bank; the legacy bank codes are mapped to this list by code map BANK | E35: Product Owner, BDOI (New Business) | F35: 9-Apr-2027 – Reference data for Trial migration 1 (M4) | G35: Template | H35: Setup & Administration › Broking Setup › Lists of Values | I35: This workbook, sheet Ref Lists of values | J35: - | M35: Not started | P35: Open →
A36: 14 | B36: CFG-060 | C36: Lists of values (every list of the platform) | D36: For every list: its owner, and the values BDOI keeps, adds or retires. The lists whose values come from the legacy systems are loaded by R01; the others are entered on Lists of Values under maker-checker (see the sheet Ref Lists of values for the route of each list) | E36: BDOI IT | F36: 9-Apr-2027 – Reference data for Trial migration 1 (M4) | G36: Template | H36: Setup & Administration › Broking Setup › Lists of Values | I36: This workbook, sheet Ref Lists of values | J36: - | M36: Not started | P36: Open →
A37: 15 | B37: CFG-090 | C37: Product catalogue | D37: Product lines, cover types and products (risk codes) with their features, prepared in BRD-03 template CI-01 | E37: Product Owner, Marketing Business System (MBS) | F37: 9-Apr-2027 – Reference data for Trial migration 1 (M4) | G37: Migration object | H37: Data migration object R05 Product lines, cover types, products and risk codes; after go-live: Client & Policy › Product Maintenance › Products | I37: BRD-03 template CI-01, sheet PM-01 Product catalogue; delivered in the layout of R05 | J37: PM-09 | K37: ='PM-01 Product catalogue'!$C$9 | L37: ='PM-01 Product catalogue'!$E$9 | M37: Not started | P37: PM-01 →
A38: 16 | B38: CFG-100 | C38: Insurers and insurer branches | D38: The insurer panel with accreditation, placement e-mails and credit days, and the insurer branches with their LGT rate (BRD-03 template CI-05) | E38: Head, Operations Services | F38: 9-Apr-2027 – Reference data for Trial migration 1 (M4) | G38: Migration object | H38: Data migration object R04 Insurers and insurer branches; after go-live: Client & Policy › Product Maintenance › Insurers | I38: BRD-03 template CI-05, sheet PM-05 Insurers; delivered in the layout of R04 | J38: PM-01 | K38: ='PM-05 Insurers'!$C$9 | L38: ='PM-05 Insurers'!$E$9 | M38: Not started | P38: PM-05 →
A39: 17 | B39: CFG-101 | C39: Commission rates by insurer and product | D39: The commission rates in force at cut-over and later (commission rows of BRD-03 template CI-05) | E39: Head, Operations Services | F39: 9-Apr-2027 – Reference data for Trial migration 1 (M4) | G39: Migration object | H39: Data migration object R07 Commission rates by insurer and product; after go-live: Client & Policy › Product Maintenance › Insurers | I39: BRD-03 template CI-05, sheet PM-05 Insurers; delivered in the layout of R07 | J39: PM-01 | K39: ='PM-05 Insurers'!$C$9 | L39: ='PM-05 Insurers'!$E$9 | M39: Not started | P39: PM-05 →
A40: 18 | B40: CFG-007 | C40: Sales organisation (regions, departments, teams, unit heads, account officers) | D40: The sales units and account officers in force, and the inactive officers of open items; after go-live maintained on Sales Organisation | E40: Product Owner, BDOI (New Business) | F40: 9-Apr-2027 – Reference data for Trial migration 1 (M4) | G40: Migration object | H40: Data migration object R03 Sales organisation (regions, departments, teams, unit heads, account officers); after go-live: Client & Policy › Product Maintenance › Sales Organisation | I40: Migration Workbook, layout R03 | J40: - | M40: Not started | P40: R03 →
A41: 19 | B41: CFG-103 | C41: Payees | D41: Active payees of EBIX, loaded by the payee registration of Disbursement if BDOI brings R09 into scope (conditional object, DMQ30); otherwise registered on Payees | E41: Head, Comptrollership | F41: 9-Apr-2027 – Reference data for Trial migration 1 (M4) | G41: Migration object | H41: Data migration object R09 Payees; after go-live: Finance › Disbursement › Payees | I41: Migration Workbook, layout R09 | J41: - | M41: Not started | P41: R09 →
A42: 20 | B42: CFG-095 | C42: Package map (legacy package to BIBS package version) | D42: BRD-03 template CI-07, loaded as reference data for the package check of the Renewal sanitation | E42: Product Owner, Marketing Business System (MBS) | F42: 18-Jun-2027 – Code maps approved (M5) | G42: Migration object | H42: Data migration object R06 Package code map (legacy package and version to BIBS package version); after go-live: Data Migration › Data Migration › Code Maps | I42: BRD-03 template CI-07, sheet PM-07 Package map; delivered in the layout of R06 | J42: PM-01, PM-05, PM-06 | K42: ='PM-07 Package map'!$C$9 | L42: ='PM-07 Package map'!$E$9 | M42: Not started | P42: PM-07 →
A43: 21 | B43: CFG-024 | C43: Chart of accounts mapping (legacy GL account to BIBS account) | D43: The map of every legacy GL account of EBIX and ISYS to a BIBS account; control accounts to Migration Clearing | E43: Program Manager, Business Project Services (Data Migration) | F43: 18-Jun-2027 – Code maps approved (M5) | G43: Migration object | H43: Data migration object R08 Chart of accounts mapping (legacy GL account to BIBS account); after go-live: Data Migration › Data Migration › Code Maps | I43: Migration Workbook, layout R08 | J43: - | M43: Not started | P43: R08 →
A44: 22 | B44: CFG-061 | C44: Values of the lists used by migrated records | D44: The legacy values of the lists mapped by the code maps LOV and MIS, and the BIBS value of each | E44: Program Manager, Business Project Services (Data Migration) | F44: 18-Jun-2027 – Code maps approved (M5) | G44: Migration object | H44: Data migration object R01 Lists of values and MIS values; after go-live: Data Migration › Data Migration › Code Maps | I44: Migration Workbook, layout R01 | J44: - | M44: Not started | P44: R01 →
A45: 23 | B45: CFG-140 | C45: Code maps of the reference data | D45: The approved versions of the code maps (branches, sales units, officers, users, cost centres, banks, currencies, dispositions, statuses) that turn legacy codes into BIBS codes | E45: Program Manager, Business Project Services (Data Migration) | F45: 18-Jun-2027 – Code maps approved (M5) | G45: Migration object | H45: Data migration object R01 Lists of values and MIS values; after go-live: Data Migration › Data Migration › Code Maps | I45: Migration Workbook, layout R01 | J45: - | M45: Not started | P45: R01 →
A46: 24 | B46: CFG-141 | C46: Branch code map | D46: The map of every legacy branch and invoicing branch to a BIBS branch of CFG-002 | E46: Program Manager, Business Project Services (Data Migration) | F46: 18-Jun-2027 – Code maps approved (M5) | G46: Migration object | H46: Data migration object R02 Branches and invoicing branches; after go-live: Data Migration › Data Migration › Code Maps | I46: Migration Workbook, layout R02 | J46: - | M46: Not started | P46: R02 →
A47: 25 | B47: CFG-097 | C47: Lists and parameters of Product Maintenance | D47: BRD-03 template CI-09 (the lists and parameters it names are listed with this route on the sheets Ref Lists of values and Ref System parameters) | E47: Product Owner, MBS; System Administrator (entry) | F47: 16-Jul-2027 – Values for UAT | G47: Template | H47: Setup & Administration › Broking Setup › Lists of Values | I47: BRD-03 template CI-09, sheet PM-09 Lists and parameters | J47: - | K47: ='PM-09 Lists and parameters'!$C$9 | L47: ='PM-09 Lists and parameters'!$E$9 | M47: Not started | P47: PM-09 →
A48: 26 | B48: CFG-005 | C48: Employees | D48: Employees with their branch and cost centre, for the cost-centre rules, petty cash custodians and staff advances | E48: Human Resources; Head, Comptrollership | F48: 16-Jul-2027 – Values for UAT | G48: Template | H48: Setup & Administration › Setup › Employees | I48: Drop 0 template D0-05, sheet D0-05 Employees | J48: D0-02, D0-04 | K48: ='D0-05 Employees'!$C$9 | L48: ='D0-05 Employees'!$E$9 | M48: Not started | P48: D0-05 →
A49: 27 | B49: CFG-113 | C49: Separation-of-duties rules | D49: BRD-11 template CI-04 | E49: BDOI Information Security | F49: 16-Jul-2027 – Values for UAT | G49: Template | H49: Setup & Administration › User Access › Separation of Duties | I49: BRD-11 template CI-04, sheet UA-04 SoD rules | J49: UA-02 | K49: ='UA-04 SoD rules'!$C$9 | L49: ='UA-04 SoD rules'!$E$9 | M49: Not started | P49: UA-04 →
A50: 28 | B50: CFG-091 | C50: Coverages, perils and field rules | D50: BRD-03 template CI-02 | E50: MBS | F50: 16-Jul-2027 – Values for UAT | G50: Template | H50: Client & Policy › Product Maintenance › Coverages & Clauses | I50: BRD-03 template CI-02, sheet PM-02 Coverages and rules | J50: PM-09, PM-01 | K50: ='PM-02 Coverages and rules'!$C$9 | L50: ='PM-02 Coverages and rules'!$E$9 | M50: Not started | P50: PM-02 →
A51: 29 | B51: CFG-092 | C51: Clause library | D51: BRD-03 template CI-03 | E51: TSU (wordings); MBS (maintenance) | F51: 16-Jul-2027 – Values for UAT | G51: Template | H51: Client & Policy › Product Maintenance › Coverages & Clauses | I51: BRD-03 template CI-03, sheet PM-03 Clause library | J51: PM-09, PM-01 | K51: ='PM-03 Clause library'!$C$9 | L51: ='PM-03 Clause library'!$E$9 | M51: Not started | P51: PM-03 →
A52: 30 | B52: CFG-025 | C52: Tax codes and forms | D52: The withholding, VAT and percentage tax codes with their ATC, rate, GL account and effective dates; the RDO code | E52: Head, Comptrollership (Tax) | F52: 16-Jul-2027 – Values for UAT | G52: Template | H52: Finance › Tax & Statutory › Tax Codes & Forms | I52: Drop 0 template D0-10, sheet D0-10 Tax codes | J52: D0-06 | K52: ='D0-10 Tax codes'!$C$9 | L52: ='D0-10 Tax codes'!$E$9 | M52: Not started | P52: D0-10 →
A53: 31 | B53: CFG-114 | C53: Approval limits and matrices of the modules | D53: The approval levels by amount, sum insured or segment of Submitted Policies, Employee Benefits, Sanction Screening and Disbursement, with the approver role and the signatory | E53: Owners of the modules; Head, Comptrollership for the amounts | F53: 16-Jul-2027 – Values for UAT | G53: Template | I53: Drop 0 template D0-15, sheet D0-15 Approval limits | J53: UA-02, UA-01 | K53: ='D0-15 Approval limits'!$C$9 | L53: ='D0-15 Approval limits'!$E$9 | M53: Not started | P53: D0-15 →
A54: 32 | B54: CFG-093 | C54: Rate tables | D54: BRD-03 template CI-04 | E54: Product Owner, MBS; Comptrollership (taxes) | F54: 16-Jul-2027 – Values for UAT | G54: Template | H54: Client & Policy › Product Maintenance › Rates & Taxes | I54: BRD-03 template CI-04, sheet PM-04 Rate tables | J54: PM-01 | K54: ='PM-04 Rate tables'!$C$9 | L54: ='PM-04 Rate tables'!$E$9 | M54: Not started | P54: PM-04 →
A55: 33 | B55: CFG-096 | C55: Incentive criteria | D55: BRD-03 template CI-10 | E55: Incentive Maintenance user (MBS); Comptrollership (CPC2 definition, PQ04) | F55: 16-Jul-2027 – Values for UAT | G55: Template | H55: Client & Policy › Product Maintenance › Incentive Criteria | I55: BRD-03 template CI-10, sheet PM-10 Incentive criteria | J55: PM-09, PM-01 | K55: ='PM-10 Incentive criteria'!$C$9 | L55: ='PM-10 Incentive criteria'!$E$9 | M55: Not started | P55: PM-10 →
A56: 34 | B56: CFG-112 | C56: Approvers, approval rules and authorisation limits | D56: BRD-11 template CI-03: the access approvers and the authorisation limit of each user who approves by amount | E56: Business Administration; BDOI Information Security for the second approval; Comptrollership for the authorisation limits | F56: 16-Jul-2027 – Values for UAT | G56: Template | H56: Setup & Administration › User Access › New Request | I56: BRD-11 template CI-03, sheet UA-03 Approval rules | J56: UA-01 | K56: ='UA-03 Approval rules'!$C$9 | L56: ='UA-03 Approval rules'!$E$9 | M56: Not started | P56: UA-03 →
A57: 35 | B57: CFG-043 | C57: Bank statement layouts | D57: The column layout of the statement file of each bank account for the bank reconciliation | E57: Head, Comptrollership; Treasury | F57: 16-Jul-2027 – Values for UAT | G57: Template | H57: Setup & Administration › Setup › Bank Statement Layouts | I57: Drop 0 template D0-14, sheet D0-14 Statement layouts | J57: D0-11 | K57: ='D0-14 Statement layouts'!$C$9 | L57: ='D0-14 Statement layouts'!$E$9 | M57: Not started | P57: D0-14 →
A58: 36 | B58: CFG-098 | C58: Package document templates | D58: BRD-03 template CI-08: the texts of the package documents | E58: TSU and MBS (texts); Business Administrator (maintenance) | F58: 16-Jul-2027 – Values for UAT | G58: Template | H58: Setup & Administration › Broking Setup › Document Templates | I58: BRD-03 template CI-08, sheet PM-08 Document templates | J58: - | K58: ='PM-08 Document templates'!$C$9 | L58: ='PM-08 Document templates'!$E$9 | M58: Not started | P58: PM-08 →
A59: 37 | B59: CFG-071 | C59: Sign-in, password, session and access-request parameters | D59: The security values agreed with BDOI Information Security (BRD-11 template CI-05) | E59: BDOI Information Security; BDOI IT for the sign-in mode | F59: 16-Jul-2027 – Values for UAT | G59: Template | H59: Setup & Administration › Administration › System Parameters | I59: BRD-11 template CI-05, sheet UA-05 Parameters | J59: - | K59: ='UA-05 Parameters'!$C$9 | L59: ='UA-05 Parameters'!$E$9 | M59: Not started | P59: UA-05 →
A60: 38 | B60: CFG-051 | C60: Document number prefixes | D60: The prefix of every numbered document (quotations, proposals, slips, package requests, renewals, submitted policies, screening cases); the year and the running number follow the prefix | E60: BDOI IT | F60: 16-Jul-2027 – Values for UAT | G60: Template | I60: This workbook, sheet Ref Document numbering | J60: - | M60: Not started | P60: Open →
A61: 39 | B61: CFG-070 | C61: System parameters (every parameter of the platform) | D61: For every parameter: the value BDOI wants against the value proposed, with the reason and the approver (see the sheet Ref System parameters) | E61: BDOI IT | F61: 16-Jul-2027 – Values for UAT | G61: Template | H61: Setup & Administration › Administration › System Parameters | I61: This workbook, sheet Ref System parameters | J61: - | M61: Not started | P61: Open →
A62: 40 | B62: CFG-080 | C62: Notification events and recipients | D62: For every notification event: in-app and e-mail by default, and any unit mailbox that must receive it besides the users of the step (see the sheet Ref Notifications) | E62: BDOI IT | F62: 16-Jul-2027 – Values for UAT | G62: Template | H62: Operations › Operations › Notification Settings | I62: This workbook, sheet Ref Notifications | J62: - | M62: Not started | P62: Open →
A63: 41 | B63: CFG-081 | C63: Fixed recipients and sender address | D63: The sender address of BIBS e-mails and the recipients of job failures and watchlist loads (parameters MAIL_FROM_ADDRESS, JOB_FAILURE_RECIPIENTS, SCR_INGEST_ALERT_RECIPIENTS) | E63: BDOI IT | F63: 16-Jul-2027 – Values for UAT | G63: Template | H63: Setup & Administration › Administration › System Parameters | I63: This workbook, sheet Ref System parameters | J63: - | M63: Not started | P63: Open →
A64: 42 | B64: CFG-082 | C64: Document templates (letters, slips, advices, e-mails) | D64: The BDOI wording and layout of every generated document (see the sheet Ref Document templates) | E64: BDOI IT | F64: 16-Jul-2027 – Values for UAT | G64: Template | H64: Setup & Administration › Broking Setup › Document Templates | I64: This workbook, sheet Ref Document templates | J64: - | M64: Not started | P64: Open →
A65: 43 | B65: CFG-006 | C65: Cost-centre rules | D65: Which cost centre an automatic posting takes by module, event, branch, party or account | E65: Head, Comptrollership | F65: 16-Jul-2027 – Values for UAT | G65: Screen | H65: Setup & Administration › Setup › Cost-Centre Rules | I65: This index row (decision and values in BDOI comments) | J65: - | M65: Not started
A66: 44 | B66: CFG-008 | C66: Production targets | D66: The 2028 production targets per sales unit and officer for the New Business reports | E66: Product Owner, BDOI (New Business) | F66: 16-Jul-2027 – Values for UAT | G66: Screen | H66: Reports › New Business Reports › Production Targets | I66: This index row (decision and values in BDOI comments) | J66: - | M66: Not started
A67: 45 | B67: CFG-010 | C67: Currencies and exchange rates | D67: The currencies in use and the source and owner of the daily BOOK rate; the legacy currency codes are mapped by code map CURRENCY | E67: Head, Comptrollership | F67: 16-Jul-2027 – Values for UAT | G67: Screen | H67: Setup & Administration › Setup › Currencies & Rates | I67: This index row (decision and values in BDOI comments) | J67: - | M67: Not started
A68: 46 | B68: CFG-026 | C68: Financial statement formats and account schedules | D68: The lines of the financial statements and MIS formats and the accounts in each, as Comptrollership reports them | E68: Head, Comptrollership | F68: 16-Jul-2027 – Values for UAT | G68: Screen | H68: Finance › Accounting Reports › Account Schedules | I68: This index row (decision and values in BDOI comments) | J68: - | M68: Not started
A69: 47 | B69: CFG-028 | C69: Asset categories | D69: Fixed-asset categories with their useful life, method and accounts | E69: Head, Comptrollership | F69: 16-Jul-2027 – Values for UAT | G69: Screen | H69: Finance › Assets & Investments › Asset Categories | I69: This index row (decision and values in BDOI comments) | J69: - | M69: Not started
A70: 48 | B70: CFG-029 | C70: Investment portfolios | D70: The investment portfolios and their accounts, when BDOI keeps investments in BIBS | E70: Head, Comptrollership | F70: 16-Jul-2027 – Values for UAT | G70: Screen | H70: Finance › Assets & Investments › Investment Portfolios | I70: This index row (decision and values in BDOI comments) | J70: - | M70: Not started
A71: 49 | B71: CFG-030 | C71: GL-SL reconciliation controls (ACSL) | D71: The control accounts reconciled against their sub-ledgers and the tolerance of each | E71: Head, Comptrollership | F71: 16-Jul-2027 – Values for UAT | G71: Screen | H71: Finance › ACSL › GL-SL Reconciliation | I71: This index row (decision and values in BDOI comments) | J71: - | M71: Not started
A72: 50 | B72: CFG-031 | C72: Service fee rates | D72: The service fee rates per segment and their recipients | E72: Head, Comptrollership | F72: 16-Jul-2027 – Values for UAT | G72: Screen | H72: Finance › Accounting Reports › Service Fee Rates | I72: This index row (decision and values in BDOI comments) | J72: - | M72: Not started
A73: 51 | B73: CFG-044 | C73: Payment file layouts of the collection channels | D73: Confirmation of the payment files received from Bills Payment, Trade, Direct Credit, CLPC and PMS and their field names | E73: Head, Operations Services | F73: 16-Jul-2027 – Values for UAT | G73: Screen | H73: Finance › Cashiering › Cashiering Setup | I73: This index row (decision and values in BDOI comments) | J73: - | M73: Not started
A74: 52 | B74: CFG-072 | C74: Exception codes and alert thresholds | D74: Which exceptions raise an alert, with their severity and the amount or day threshold of each | E74: BDOI IT | F74: 16-Jul-2027 – Values for UAT | G74: Screen | H74: Setup & Administration › Administration › Exception Codes | I74: This index row (decision and values in BDOI comments) | J74: - | M74: Not started
A75: 53 | B75: CFG-073 | C75: Scheduled job times | D75: The run time of each daily and monthly job in Philippine time, and the blackout windows | E75: BDOI IT | F75: 16-Jul-2027 – Values for UAT | G75: Screen | H75: Setup & Administration › Administration › Scheduled Jobs | I75: This index row (decision and values in BDOI comments) | J75: - | M75: Not started
A76: 54 | B76: CFG-074 | C76: Data retention rules | D76: Years online and in the archive per record type, and the action at the end, as Compliance sets them | E76: Compliance | F76: 16-Jul-2027 – Values for UAT | G76: Screen | H76: Setup & Administration › Broking Setup › Data Retention | I76: This index row (decision and values in BDOI comments) | J76: - | M76: Not started
... A92: 70 | B92: CFG-131 | C92: New Business report variants | D92: The report variants the units use | E92: Product Owner, BDOI (New Business) | F92: 16-Jul-2027 – Values for UAT | G92: Screen | H92: Reports › New Business Reports › New Business Reports | I92: This index row (decision and values in BDOI comments) | J92: - | M92: Not started
A93: 71 | B93: CFG-110 | C93: Users at go-live | D93: BRD-11 template CI-01, uploaded as a bulk request and approved; users are not migrated (R10 excluded, legacy user IDs only mapped) | E93: Business Administration, with the unit heads who name their users | F93: 1-Nov-2027 – Production values before the dress rehearsal | G93: Template | H93: Setup & Administration › User Access › Bulk Request | I93: BRD-11 template CI-01, sheet UA-01 Users and roles | J93: UA-06, UA-02 | K93: ='UA-01 Users and roles'!$C$9 | L93: ='UA-01 Users and roles'!$E$9 | M93: Not started | P93: UA-01 →
A94: 72 | B94: CFG-094 | C94: Packages in force at go-live | D94: BRD-03 template CI-06: one package request per package, set up and validated before the map freeze | E94: TSU (prepares); Product Owner, MBS (approves) | F94: 1-Nov-2027 – Production values before the dress rehearsal | G94: Template | H94: Client & Policy › Product Maintenance › New Package Request | I94: BRD-03 template CI-06, sheet PM-06 Packages | J94: PM-01, PM-02, PM-05, PM-03 | K94: ='PM-06 Packages'!$C$9 | L94: ='PM-06 Packages'!$E$9 | M94: Not started | P94: PM-06 →
A95: 73 | B95: CFG-041 | C95: Check books | D95: The check books in stock per bank account at go-live: first, last and next check number | E95: Treasury; Product Owner, Comptrollership - Disbursement | F95: 1-Nov-2027 – Production values before the dress rehearsal | G95: Template | H95: Finance › Disbursement › Bank Accounts and Checks | I95: Drop 0 template D0-12, sheet D0-12 Check books | J95: D0-11 | K95: ='D0-12 Check books'!$C$9 | L95: ='D0-12 Check books'!$E$9 | M95: Not started | P95: D0-12 →
A96: 74 | B96: CFG-042 | C96: Petty cash funds | D96: Each petty cash fund: branch, custodian, imprest amount, GL account and replenishment bank account | E96: Head, Comptrollership | F96: 1-Nov-2027 – Production values before the dress rehearsal | G96: Template | H96: Finance › Payables & Cash › Petty Cash | I96: Drop 0 template D0-13, sheet D0-13 Petty cash funds | J96: D0-02, D0-05, D0-06, D0-11 | K96: ='D0-13 Petty cash funds'!$C$9 | L96: ='D0-13 Petty cash funds'!$E$9 | M96: Not started | P96: D0-13 →
A97: 75 | B97: CFG-009 | C97: Financial year and periods | D97: Financial year 2028 and its periods, opened by Comptrollership; FY2027 stays in legacy (year-end option A) | E97: Head, Comptrollership | F97: 1-Nov-2027 – Production values before the dress rehearsal | G97: Screen | H97: Finance › General Ledger › Financial Periods | I97: This index row (decision and values in BDOI comments) | J97: - | M97: Not started
A98: 76 | B98: CFG-027 | C98: Recurring journals | D98: The monthly accruals and allocations Comptrollership posts as recurring journals from January 2028 | E98: Head, Comptrollership | F98: 1-Nov-2027 – Production values before the dress rehearsal | G98: Screen | H98: Finance › General Ledger › Recurring Journals | I98: This index row (decision and values in BDOI comments) | J98: - | M98: Not started
A99: 77 | B99: CFG-050 | C99: Receipt series in use (AR and OR) | D99: The BIR-authorised AR and OR series of each branch in use at the freeze (ATP, range and next number), so BIBS continues them without gap or overlap | E99: Head, Operations Services | F99: 27-Dec-2027 – Map freeze (T-7) | G99: Migration object | H99: Data migration object R11 Receipt series in use (AR and OR, ATP and next number); after go-live: Finance › Cashiering › Receipt Series | I99: Migration Workbook, layout R11 | J99: - | M99: Not started | P99: R11 →
A101: Due milestones
A102: Due | B102: Milestone | E102: Due date | F102: Before go-live | G102: Items | H102: Why this date
A103: D1 | B103: Drafts with the Drop 0 sign-off | E103: 1-Dec-2026 | F103: T-56 weeks | G103: 2 | H103: Sign-off of BRD-11 on 1-Dec-2026, the last of the three Drop 0 sets
A104: D2 | B104: Platform set-up for Drop 1 SIT | E104: 4-Jan-2027 | F104: T-52 weeks | G104: 9 | H104: Drop 1 SIT runs Jan - Jul 2027 on the BDOI organisation, chart of accounts and banks
A105: D3 | B105: Reference data for Trial migration 1 (M4) | E105: 9-Apr-2027 | F105: T-38 weeks | G105: 8 | H105: Extracts for Trial migration 1; reference data and clients first
A106: D4 | B106: Code maps approved (M5) | E106: 18-Jun-2027 | F106: T-28 weeks | G106: 5 | H106: Code maps approved for Trial migration 2, including the package code map
A107: D5 | B107: Values for UAT | E107: 16-Jul-2027 | F107: T-24 weeks | G107: 46 | H107: UAT plans and sign-off forms due 16-Jul-2027; UAT Aug - Dec 2027 runs on the production values
A108: D6 | B108: Production values before the dress rehearsal | E108: 1-Nov-2027 | F108: T-9 weeks | G108: 6 | H108: Dress rehearsal in November 2027; the values loaded for it are the go-live values
A109: D7 | B109: Map freeze (T-7) | E109: 27-Dec-2027 | F109: T-1 weeks | G109: 1 | H109: No change of a code map or reference value after the freeze except by change request
A111: Reference sheets and other sheets
A112: Sheet | D112: What it holds
A113: Ref Lists of values | D113: Every list of values of BIBS with its owner and its one route
A114: Ref System parameters | D114: Every system parameter with the value proposed and the value BDOI wants
A115: Ref Document numbering | D115: Prefixes of the numbered documents; receipt series come from object R11, check numbers from D0-12
A116: Ref Notifications | D116: Every notification event with its default channels; users choose their own channels in Notification Settings
A117: Ref Document templates | D117: Every generated document with the unit that gives its BDOI wording and layout
A118: Ref Accounting events | D118: The accounting events that need a rule of template D0-08; owner Head, Comptrollership
A119: Ref Migration cross-reference | D119: Reference data loaded by the migration and the register items it carries
A120: Reference lists | D120: Every list of allowed values of the drop-downs, with code and label
A121: Questions and comments | D121: Questions and comments per template and column, with the answer
A123: Prepared by iorta TechNXT for BDOI. Confidential – BDOI.

Sheet D0-02 Branches
A1: D0-02 Branches | M1: Step 1 of 31
A2: ← Back to Start here | B2: Step 1 of 31. Fill in one row per record below the column headers; the guide above each column says what to enter. | M2: Ask a question →
A3: Purpose | B3: Every BDOI branch and invoicing branch
A4: Provided by | B4: Head, Comptrollership
A5: Due | B5: 4-Jan-2027 – Platform set-up for Drop 1 SIT
A6: How it is loaded | B6: Branches (Setup & Administration), before the first migration mock; the legacy branches are mapped to them by the code map BRANCH (object R02)
A7: Source | B7: BDOI branch list; EBIX branch codes for the code map BRANCH
A8: Depends on | B8: Nothing: this template can be filled in first
A9: Progress | B9: Rows entered | C9: =SUMPRODUCT(((ROW($B$17:$B$517)>17)+($B$17<>"HO")>0)*(LEN($B$17:$B$517&$C$17:$C$517&$D$17:$D$517&$E$17:$E$517&$F$17:$F$517&$G$17:$G$517&$H$17:$H$517&$I$17:$I$517&$J$17:$J$517&$K$17:$K$517&$L$17:$L$517&$M$17:$M$517)>0)) | D9: Mandatory cells missing | E9: =SUMPRODUCT(((ROW($B$17:$B$517)>17)+($B$17<>"HO")>0)*(LEN($B$17:$B$517&$C$17:$C$517&$D$17:$D$517&$E$17:$E$517&$F$17:$F$517&$G$17:$G$517&$H$17:$H$517&$I$17:$I$517&$J$17:$J$517&$K$17:$K$517&$L$17:$L$517&$M$17:$M$517)>0)*(($B$17:$B$517="")+($C$17:$C$517="")+($F$17:$F$517="")+($G$17:$G$517="")+($H$17:$H$517="")))
A10: Confirmed by (BDOI owner) | D10: Date
A12: Mandatory | B12: Yes | C12: Yes | D12: No | E12: No | F12: Yes | G12: Yes | H12: Yes | I12: No | J12: No | K12: No | L12: No | M12: No
A13: Format | B13: Up to 10 capitals | C13: Up to 120 characters | D13: Text | E13: Text | F13: dd-MMM-yyyy | G13: Y or N | H13: Y or N | I13: Text | J13: E-mail address | K13: Name | L13: SAT, SUN | M13: EBIX codes separated by commas
A14: Allowed values | B14: Free entry, up to 10 characters | C14: Free entry, up to 120 characters | D14: Free entry | E14: Free entry | F14: A date, for example 15-Jan-2028 | G14: Y or N | H14: Y or N | I14: Free entry | J14: Free entry | K14: Free entry | L14: Free entry | M14: Free entry
A15: What to enter | B15: Code of the branch; unique | C15: Name shown on screens and documents | D15: Region of the branch | E15: Address printed on documents | F15: Date the branch opened | G15: Y for one branch only | H15: May receive and pay in foreign currency | I15: Branch telephone | J15: Branch mailbox | K15: Head of the branch | L15: Days the branch is closed each week | M15: For the code map BRANCH (R02)
A16: Row | B16: Branch code * | C16: Branch name * | D16: Region | E16: Address | F16: Opening date * | G16: Head office * | H16: Foreign currency authorised * | I16: Contact phone | J16: Contact e-mail | K16: Branch manager | L16: Weekly rest days | M16: Legacy branch codes
A17: Example – overwrite or delete | B17: HO | C17: Head Office | D17: NCR | E17: 7899 Makati Avenue, Makati City | F17: 40179 | G17: Y | H17: Y | I17: (02) 8888-0000 | J17: ho@bdoi.example.ph | L17: SAT,SUN | M17: 001

Sheet D0-04 Dimensions
A1: D0-04 Cost centres and business lines | G1: Step 2 of 31
A2: ← Back to Start here | B2: Step 2 of 31. Fill in one row per record below the column headers; the guide above each column says what to enter. | G2: Ask a question →
A3: Purpose | B3: The values of the dimensions of journal lines
A4: Provided by | B4: Head, Comptrollership
A5: Due | B5: 4-Jan-2027 – Platform set-up for Drop 1 SIT
A6: How it is loaded | B6: Dimensions (Setup & Administration); the legacy cost centres are mapped by the code map COST_CENTER
A7: Source | B7: Current cost centre list of Comptrollership; the product lines for the business lines
A8: Depends on | B8: Nothing: this template can be filled in first
A9: Progress | B9: Rows entered | C9: =SUMPRODUCT(((ROW($B$17:$B$517)>17)+($B$17<>"COST_CENTER")>0)*(LEN($B$17:$B$517&$C$17:$C$517&$D$17:$D$517&$E$17:$E$517)>0)) | D9: Mandatory cells missing | E9: =SUMPRODUCT(((ROW($B$17:$B$517)>17)+($B$17<>"COST_CENTER")>0)*(LEN($B$17:$B$517&$C$17:$C$517&$D$17:$D$517&$E$17:$E$517)>0)*(($B$17:$B$517="")+($C$17:$C$517="")+($D$17:$D$517="")+($E$17:$E$517="")))
A10: Confirmed by (BDOI owner) | D10: Date
A12: Mandatory | B12: Yes | C12: Yes | D12: Yes | E12: Yes
A13: Format | B13: COST_CENTER or BUSINESS_LINE | C13: Up to 20 capitals or digits | D13: Up to 120 characters | E13: Y or N
A14: Allowed values | B14: COST_CENTER, BUSINESS_LINE (list Dimension) | C14: Free entry, up to 20 characters | D14: Free entry, up to 120 characters | E14: Y or N
A15: What to enter | B15: Dimension of the value | C15: Code of the value | D15: Name shown on screens and reports | E15: N keeps the value for history only
A16: Row | B16: Dimension * | C16: Code * | D16: Name * | E16: Active *
A17: Example – overwrite or delete | B17: COST_CENTER | C17: FIN | D17: Finance and Accounting | E17: Y

Sheet D0-07 Categories and numbering
A1: D0-07 Account categories and numbering | I1: Step 3 of 31
A2: ← Back to Start here | B2: Step 3 of 31. Fill in one row per record below the column headers; the guide above each column says what to enter. | I2: Ask a question →
A3: Purpose | B3: The GL categories and the numbering scheme under each parent account
A4: Provided by | B4: Head, Comptrollership
A5: Due | B5: 4-Jan-2027 – Platform set-up for Drop 1 SIT
A6: How it is loaded | B6: Chart of Accounts (General Ledger)
A7: Source | B7: The BDOI chart of accounts
A8: Depends on | B8: Nothing: this template can be filled in first
A9: Progress | B9: Rows entered | C9: =SUMPRODUCT(((ROW($B$17:$B$517)>17)+($B$17<>"CATEGORY")>0)*(LEN($B$17:$B$517&$C$17:$C$517&$D$17:$D$517&$E$17:$E$517&$F$17:$F$517&$G$17:$G$517&$H$17:$H$517&$I$17:$I$517)>0)) | D9: Mandatory cells missing | E9: =SUMPRODUCT(((ROW($B$17:$B$517)>17)+($B$17<>"CATEGORY")>0)*(LEN($B$17:$B$517&$C$17:$C$517&$D$17:$D$517&$E$17:$E$517&$F$17:$F$517&$G$17:$G$517&$H$17:$H$517&$I$17:$I$517)>0)*(($B$17:$B$517="")))
A10: Confirmed by (BDOI owner) | D10: Date
A12: Mandatory | B12: Yes | C12: Conditional: CATEGORY | D12: Conditional: CATEGORY | E12: Conditional: CATEGORY | F12: Conditional: CATEGORY | G12: Conditional: NUMBERING | H12: Conditional: NUMBERING | I12: Conditional: NUMBERING
A13: Format | B13: CATEGORY or NUMBERING | C13: Up to 20 capitals | D13: Text | E13: ASSET, LIABILITY, EQUITY, INCOME, EXPENSE | F13: Y or N | G13: Account code of D0-06 | H13: . or - or none | I13: 1 to 6
A14: Allowed values | B14: CATEGORY, NUMBERING (list Category or numbering row) | C14: Free entry, up to 20 characters | D14: Free entry | E14: ASSET, LIABILITY, EQUITY, INCOME, EXPENSE (list Account class) | F14: Y or N | G14: Free entry | H14: Free entry | I14: A whole number from 1 to 6
A15: What to enter | B15: What the row defines | C15: GL category | D15: Name of the category | E15: Class of the accounts of the category | F15: Y for the accounts of bank accounts (D0-11) | G15: Parent whose children are numbered | H15: Between the parent code and the running number | I15: Digits of the running number
A16: Row | B16: Row * | C16: Category code | D16: Category name | E16: Account class | F16: Bank category | G16: Parent account | H16: Separator | I16: Width
A17: Example – overwrite or delete | B17: CATEGORY | C17: CASH_IN_BANK | D17: Cash in bank | E17: ASSET | F17: Y | G17: 1110 | H17: . | I17: 2

Sheet PM-09 Lists and parameters
A1: PM-09 Lists of values and parameters | G1: Step 4 of 31
A2: ← Back to Start here | B2: Step 4 of 31. Fill in one row per record below the column headers; the guide above each column says what to enter. | G2: Ask a question →
A3: Purpose | B3: The values of the Product Maintenance lists (request reasons, response outcomes, advisory groups, not-proceeded reasons, incentive types, coverage kinds, clause kinds, document types, market segments) and the parameters (numbering, reply days, expiry notice, advisory groups, service levels)
A4: Provided by | B4: Product Owner, MBS; System Administrator (entry)
A5: Due | B5: 16-Jul-2027 – Values for UAT
A6: How it is loaded | B6: Data migration object R01 for the values used by migrated records; the other values on Lists of Values and System Parameters
A7: Source | B7: Delivered values (FRS chapter 9) confirmed or changed by BDOI
A8: Depends on | B8: Nothing: this template can be filled in first
A9: Progress | B9: Rows entered | C9: =SUMPRODUCT(((ROW($B$17:$B$517)>17)+($B$17<>"PKG_REQUEST_REASON")>0)*(LEN($B$17:$B$517&$C$17:$C$517&$D$17:$D$517&$E$17:$E$517&$F$17:$F$517)>0)) | D9: Mandatory cells missing | E9: =SUMPRODUCT(((ROW($B$17:$B$517)>17)+($B$17<>"PKG_REQUEST_REASON")>0)*(LEN($B$17:$B$517&$C$17:$C$517&$D$17:$D$517&$E$17:$E$517&$F$17:$F$517)>0)*(($B$17:$B$517="")+($D$17:$D$517="")))
A10: Confirmed by (BDOI owner) | D10: Date
A12: Mandatory | B12: Yes | C12: Conditional: list | D12: Yes | E12: No | F12: No
A13: Format | B13: Code of the list or parameter | C13: Up to 40 capitals | D13: Text; number for a parameter | E13: Number; Y or N | F13: dd-MMM-yyyy
A14: Allowed values | B14: List Product Maintenance list or parameter: 40 values, see Reference lists | C14: Free entry, up to 40 characters | D14: Free entry | E14: Free entry | F14: A date, for example 15-Jan-2028
A15: What to enter | B15: For example PKG_REQUEST_REASON, PKG_SLA_NEGOTIATION | C15: Code of the value | D15: Label shown to users, or the parameter value | E15: Display order and status | F15: From when the value applies
A16: Row | B16: List or parameter * | C16: Value code | D16: Label or value * | E16: Order / Active | F16: Effective from
A17: Example – overwrite or delete | B17: PKG_REQUEST_REASON | C17: LOSS_EXPERIENCE | D17: Loss experience | E17: 50; Y | F17: 46327

Sheet UA-02 Role matrix
A1: UA-02 Role-to-permission matrix | I1: Step 5 of 31
A2: ← Back to Start here | B2: Step 5 of 31. Fill in one row per record below the column headers; the guide above each column says what to enter. | I2: Ask a question →
A3: Purpose | B3: The group profiles BDOI keeps, their privilege level and the permissions of each, starting from the User Access Matrix as delivered
A4: Provided by | B4: Business Administration with the unit heads; reviewed and signed by BDOI Information Security
A5: Due | B5: 9-Apr-2027 – Reference data for Trial migration 1 (M4)
A6: How it is loaded | B6: Group-profile requests (SCR-UA-12): one request per new or changed profile, approved in order and implemented by the System Administrator; checked with the User Group Profile Report
A7: Source | B7: The User Access Matrix export of this set (DO-06) and the menus by persona of FRS chapter 12
A8: Depends on | B8: Nothing: this template can be filled in first
A9: Progress | B9: Rows entered | C9: =SUMPRODUCT(((ROW($B$17:$B$517)>17)+($B$17<>"MKT_AO")>0)*(LEN($B$17:$B$517&$C$17:$C$517&$D$17:$D$517&$E$17:$E$517&$F$17:$F$517&$G$17:$G$517&$H$17:$H$517&$I$17:$I$517)>0)) | D9: Mandatory cells missing | E9: =SUMPRODUCT(((ROW($B$17:$B$517)>17)+($B$17<>"MKT_AO")>0)*(LEN($B$17:$B$517&$C$17:$C$517&$D$17:$D$517&$E$17:$E$517&$F$17:$F$517&$G$17:$G$517&$H$17:$H$517&$I$17:$I$517)>0)*(($B$17:$B$517="")+($C$17:$C$517="")+($E$17:$E$517="")+($F$17:$F$517="")+($H$17:$H$517="")+($I$17:$I$517="")))
A10: Confirmed by (BDOI owner) | D10: Date
A12: Mandatory | B12: Yes | C12: Yes | D12: No | E12: Yes | F12: Yes | G12: No | H12: Yes | I12: Yes
A13: Format | B13: Up to 40 capital letters, digits or _ | C13: Up to 120 characters | D13: Up to 500 characters | E13: Low, Standard, High or Admin | F13: Permission code of the User Access Matrix | G13: View only, Create, Amend, Approve / Validate | H13: KEEP, ADD or REMOVE | I13: Name
A14: Allowed values | B14: Free entry, up to 40 characters | C14: Free entry, up to 120 characters | D14: Free entry, up to 500 characters | E14: Low, Standard, High, Admin (list Privilege level) | F14: Free entry | G14: Free entry | H14: KEEP, ADD, REMOVE (list Change against the matrix) | I14: Free entry
A15: What to enter | B15: Code of the profile; an existing code changes the profile | C15: Name shown on screens | D15: What the profile is for | E15: High and Admin need a second approval when given or raised | F15: One row per permission of the profile | G15: As shown by the matrix, for the review | H15: Change against the matrix as delivered | I15: Unit head who confirms the row
A16: Row | B16: Group profile code * | C16: Name * | D16: Description | E16: Privilege level * | F16: Permission * | G16: Action class | H16: Keep / Add / Remove * | I16: Approved by unit head *
A17: Example – overwrite or delete | B17: MKT_AO | C17: Marketing Account Officer | D17: Marketing account officers of the Combank and Corbank units | E17: Standard | F17: QUOTE_MAINTAIN | G17: Create, Amend | H17: KEEP | I17: Carla Reyes

Sheet UA-06 Lists of values
A1: UA-06 Lists of values | G1: Step 6 of 31
A2: ← Back to Start here | B2: Step 6 of 31. Fill in one row per record below the column headers; the guide above each column says what to enter. | G2: Ask a question →
A3: Purpose | B3: The values of the lists of user access (business unit groups and user levels, empty as delivered; deactivation reasons, to confirm with BDOI; the reason No sign-in for the dormancy period is used by the dormant-user job and stays)
A4: Provided by | B4: Business Administration
A5: Due | B5: 1-Nov-2027 – before the templates that use its codes
A6: How it is loaded | B6: Lists of Values (New Business set) under maker-checker; before the users of CI-01 are loaded
A7: Source | B7: BDOI organisation (UQ05)
A8: Depends on | B8: Nothing: this template can be filled in first
A9: Progress | B9: Rows entered | C9: =SUMPRODUCT(((ROW($B$17:$B$517)>17)+($B$17<>"UAM_BUSINESS_UNIT")>0)*(LEN($B$17:$B$517&$C$17:$C$517&$D$17:$D$517&$E$17:$E$517&$F$17:$F$517)>0)) | D9: Mandatory cells missing | E9: =SUMPRODUCT(((ROW($B$17:$B$517)>17)+($B$17<>"UAM_BUSINESS_UNIT")>0)*(LEN($B$17:$B$517&$C$17:$C$517&$D$17:$D$517&$E$17:$E$517&$F$17:$F$517)>0)*(($B$17:$B$517="")+($C$17:$C$517="")+($D$17:$D$517="")+($F$17:$F$517="")))
A10: Confirmed by (BDOI owner) | D10: Date
A12: Mandatory | B12: Yes | C12: Yes | D12: Yes | E12: No | F12: Yes
A13: Format | B13: UAM_BUSINESS_UNIT, UAM_USER_LEVEL or UAM_DEACTIVATION_REASON | C13: Up to 30 capitals, digits or _ | D13: Up to 120 characters | E13: Whole number | F13: dd-MMM-yyyy
A14: Allowed values | B14: UAM_BUSINESS_UNIT, UAM_USER_LEVEL, UAM_DEACTIVATION_REASON (list User access list) | C14: Free entry, up to 30 characters | D14: Free entry, up to 120 characters | E14: A whole number | F14: A date, for example 15-Jan-2028
A15: What to enter | B15: The list | C15: Code of the value | D15: Label shown on screens | E15: Order in the drop-down | F15: Date the value may be used
A16: Row | B16: List * | C16: Code * | D16: Label * | E16: Sort order | F16: Effective from *
A17: Example – overwrite or delete | B17: UAM_BUSINESS_UNIT | C17: COMBANK_MKT | D17: Combank Marketing | E17: 10 | F17: 46391

Sheet D0-05 Employees
A1: D0-05 Employees | H1: Step 7 of 31
A2: ← Back to Start here | B2: Step 7 of 31. Fill in one row per record below the column headers; the guide above each column says what to enter. | H2: Ask a question →
A3: Purpose | B3: Employees used by the cost-centre rules, petty cash and staff advances
A4: Provided by | B4: Human Resources; Head, Comptrollership
A5: Due | B5: 16-Jul-2027 – Values for UAT
A6: How it is loaded | B6: Employees (Setup & Administration)
A7: Source | B7: HR employee list
A8: Depends on | B8: D0-02 Branches → | D8: D0-04 Cost centres and business lines →
A9: Progress | B9: Rows entered | C9: =SUMPRODUCT(((ROW($B$17:$B$517)>17)+($B$17<>"1203344")>0)*(LEN($B$17:$B$517&$C$17:$C$517&$D$17:$D$517&$E$17:$E$517&$F$17:$F$517&$G$17:$G$517&$H$17:$H$517)>0)) | D9: Mandatory cells missing | E9: =SUMPRODUCT(((ROW($B$17:$B$517)>17)+($B$17<>"1203344")>0)*(LEN($B$17:$B$517&$C$17:$C$517&$D$17:$D$517&$E$17:$E$517&$F$17:$F$517&$G$17:$G$517&$H$17:$H$517)>0)*(($B$17:$B$517="")+($C$17:$C$517="")+($D$17:$D$517="")+($E$17:$E$517="")))
A10: Confirmed by (BDOI owner) | D10: Date
A12: Mandatory | B12: Yes | C12: Yes | D12: Yes | E12: Yes | F12: No | G12: No | H12: No
A13: Format | B13: HR number | C13: Up to 120 characters | D13: Code of D0-02 | E13: Cost centre of D0-04 | F13: Text | G13: Company e-mail | H13: dd-MMM-yyyy
A14: Allowed values | B14: Free entry | C14: Free entry, up to 120 characters | D14: A code of D0-02 Branches, column Branch code | E14: A code of D0-04 Cost centres and business lines, column Code | F14: Free entry | G14: Free entry | H14: A date, for example 15-Jan-2028
A15: What to enter | B15: Unique | C15: Name of the employee | D15: Home branch | E15: Cost centre of the employee | F15: Position title | G15: For advices and statements | H15: Date of hire
A16: Row | B16: Employee number * | C16: Full name * | D16: Branch code * | E16: Cost centre * | F16: Position | G16: E-mail | H16: Hired on
A17: Example – overwrite or delete | B17: 1203344 | C17: Andrea Mercado | D17: HO | E17: FIN | F17: Accounting Officer | G17: andrea.mercado@bdoi.example.ph | H17: 43527

Sheet D0-06 Chart of accounts
A1: D0-06 Chart of accounts | Q1: Step 8 of 31
A2: ← Back to Start here | B2: Step 8 of 31. Fill in one row per record below the column headers; the guide above each column says what to enter. | Q2: Ask a question →
A3: Purpose | B3: The production chart of accounts, in the columns of the chart upload. List every parent before its children. Accounts are created pending authorization.
A4: Provided by | B4: Head, Comptrollership
A5: Due | B5: 4-Jan-2027 – Platform set-up for Drop 1 SIT
A6: How it is loaded | B6: Chart Upload (General Ledger): the file is checked row by row and every account is created pending authorisation by Comptrollership
A7: Source | B7: The BDOI chart of accounts in use, completed with the legacy control accounts (D0-09)
A8: Depends on | B8: D0-07 Account categories and numbering →
A9: Progress | B9: Rows entered | C9: =SUMPRODUCT(((ROW($C$17:$C$517)>17)+($C$17<>"1210.07")>0)*(LEN($B$17:$B$517&$C$17:$C$517&$D$17:$D$517&$E$17:$E$517&$F$17:$F$517&$G$17:$G$517&$H$17:$H$517&$I$17:$I$517&$J$17:$J$517&$K$17:$K$517&$L$17:$L$517&$M$17:$M$517&$N$17:$N$517&$O$17:$O$517&$P$17:$P$517&$Q$17:$Q$517)>0)) | D9: Mandatory cells missing | E9: =SUMPRODUCT(((ROW($C$17:$C$517)>17)+($C$17<>"1210.07")>0)*(LEN($B$17:$B$517&$C$17:$C$517&$D$17:$D$517&$E$17:$E$517&$F$17:$F$517&$G$17:$G$517&$H$17:$H$517&$I$17:$I$517&$J$17:$J$517&$K$17:$K$517&$L$17:$L$517&$M$17:$M$517&$N$17:$N$517&$O$17:$O$517&$P$17:$P$517&$Q$17:$Q$517)>0)*(($D$17:$D$517="")+($F$17:$F$517="")+($G$17:$G$517="")))
A10: Confirmed by (BDOI owner) | D10: Date
A12: Mandatory | B12: No | C12: No | D12: Yes | E12: No | F12: Yes | G12: Yes | H12: No | I12: No | J12: No | K12: No | L12: No | M12: No | N12: No | O12: No | P12: No | Q12: No
A13: Format | B13: Text | C13: Text | D13: Text | E13: Text | F13: Text | G13: Text | H13: Text | I13: Y or N | J13: Text | K13: Text | L13: Y or N | M13: Y or N | N13: Y or N | O13: Text | P13: yyyy-MM-dd | Q13: Text
A14: Allowed values | B14: A code of D0-06 Chart of accounts, column Account Code | C14: Free entry | D14: Free entry | E14: Free entry | F14: ASSET, LIABILITY, EQUITY, INCOME, EXPENSE, MEMORANDUM (list Account class of the chart) | G14: GROUP, MAIN, SUB, MICRO (list Account level) | H14: A code of D0-07 Account categories and numbering, column Category code | I14: Y or N | J14: Free entry | K14: Free entry | L14: Y or N | M14: Y or N | N14: Y or N | O14: Free entry | P14: Free entry | Q14: ALLOW, WARN, BLOCK (list Negative balance)
A15: What to enter | B15: Code of the parent account; blank for a top-level group | C15: Account code; blank for the next number of the parent's scheme | D15: Account name | E15: Unique short code used on journal lines | F15: Class of the account | G15: Level of the account, one tier below the parent | H15: GL category | I15: Control account | J15: Sub-ledger the account controls; blank for none | K15: Currencies allowed on the account; blank for all | L15: Manual journals allowed; blank for Y | M15: Cost centre mandatory on journal lines | N15: Revalued at month end | O15: Financial statement line | P15: Opening date; blank for today | Q15: What a negative balance does; blank for ALLOW
A16: Row | B16: Parent Code | C16: Account Code | D16: Account Name * | E16: Short Code | F16: Class * | G16: Level * | H16: Category | I16: Control Account | J16: Sub-ledger Type | K16: Currencies | L16: Manual Posting | M16: Cost Centre Required | N16: Revaluation Required | O16: Report Group | P16: Opened On | Q16: Negative Balance
A17: Example – overwrite or delete | C17: 1210.07 | D17: Premium Receivable - Motor | E17: PRMOTOR | F17: ASSET | G17: SUB | I17: N | J17: POLICYHOLDER | K17: {baseCurrency} | L17: Y | M17: N | N17: N | O17: Premium Receivable | P17: 2026-01-01 | Q17: WARN

Sheet PM-01 Product catalogue
A1: PM-01 Product catalogue | W1: Step 9 of 31
A2: ← Back to Start here | B2: Step 9 of 31. Fill in one row per record below the column headers; the guide above each column says what to enter. | W2: Ask a question →
A3: Purpose | B3: Product lines, cover types and subtypes, and every product (risk code) with its features
A4: Provided by | B4: Product Owner, Marketing Business System (MBS)
A5: Due | B5: 9-Apr-2027 – Reference data for Trial migration 1 (M4)
A6: How it is loaded | B6: Data migration object R05 (product lines, cover types, products) through the catalogue services, pending authorisation; after go-live on Products (SCR-PM-11)
A7: Source | B7: Legacy QPS and EBIX product lists, completed by MBS
A8: Depends on | B8: PM-09 Lists of values and parameters →
A9: Progress | B9: Rows entered | C9: =SUMPRODUCT(((ROW($B$17:$B$517)>17)+($B$17<>"MOTOR")>0)*(LEN($B$17:$B$517&$C$17:$C$517&$D$17:$D$517&$E$17:$E$517&$F$17:$F$517&$G$17:$G$517&$H$17:$H$517&$I$17:$I$517&$J$17:$J$517&$K$17:$K$517&$L$17:$L$517&$M$17:$M$517&$N$17:$N$517&$O$17:$O$517&$P$17:$P$517&$Q$17:$Q$517&$R$17:$R$517&$S$17:$S$517&$T$17:$T$517&$U$17:$U$517&$V$17:$V$517&$W$17:$W$517)>0)) | D9: Mandatory cells missing | E9: =SUMPRODUCT(((ROW($B$17:$B$517)>17)+($B$17<>"MOTOR")>0)*(LEN($B$17:$B$517&$C$17:$C$517&$D$17:$D$517&$E$17:$E$517&$F$17:$F$517&$G$17:$G$517&$H$17:$H$517&$I$17:$I$517&$J$17:$J$517&$K$17:$K$517&$L$17:$L$517&$M$17:$M$517&$N$17:$N$517&$O$17:$O$517&$P$17:$P$517&$Q$17:$Q$517&$R$17:$R$517&$S$17:$S$517&$T$17:$T$517&$U$17:$U$517&$V$17:$V$517&$W$17:$W$517)>0)*(($B$17:$B$517="")+($C$17:$C$517="")+($H$17:$H$517="")+($I$17:$I$517="")+($K$17:$K$517="")+($M$17:$M$517="")+($P$17:$P$517="")+($Q$17:$Q$517="")))
A10: Confirmed by (BDOI owner) | D10: Date
A12: Mandatory | B12: Yes | C12: Yes | D12: No | E12: Conditional: package products | F12: Conditional: with the code | G12: No | H12: Yes | I12: Yes | J12: No | K12: Yes | L12: No | M12: Yes | N12: No | O12: No | P12: Yes | Q12: Yes | R12: No | S12: No | T12: No | U12: No | V12: No | W12: No
A13: Format | B13: Up to 30 capitals | C13: Text | D13: Regular expression | E13: Up to 30 capitals | F13: Text | G13: Cover type code | H13: 1 to 20 capitals or digits | I13: Up to 200 characters | J13: Text | K13: Y or N | L13: Codes separated by commas; blank = all | M13: PAID or CLIENT_CONFIRMATION | N13: BY_RULES, ALWAYS or NEVER | O13: Up to four decimals | P13: Percentage | Q13: Amount in PHP | R13: Amount in PHP | S13: Y or N | T13: Y or N | U13: Y or N | V13: Y or N; 2 to 10 years | W13: Y or N
A14: Allowed values | B14: Free entry, up to 30 characters | C14: Free entry | D14: Free entry | E14: Free entry, up to 30 characters | F14: Free entry | G14: A code of PM-01 Product catalogue, column Cover type code | H14: Free entry, up to 20 characters | I14: Free entry, up to 200 characters | J14: Free entry | K14: Y or N | L14: One or more codes of the list Market segment (Reference lists), separated by commas | M14: PAID, CLIENT_CONFIRMATION (list Placement after) | N14: BY_RULES, ALWAYS, NEVER (list TSU review) | O14: A number from 0 to 100 | P14: A number from 0 to 100 | Q14: A number | R14: A number | S14: Y or N | T14: Y or N | U14: Y or N | V14: Free entry | W14: Y or N
A15: What to enter | B15: Product line (level 1), for example MOTOR, PROPERTY | C15: Name shown in the drop-downs | D15: Naming convention of the risk codes of the line, when BDOI states one | E15: Cover type (level 2) of the line | F15: Name of the cover type | G15: Only for a subtype (one level below a cover type) | H15: Product code (level 3); unique | I15: Name shown to users | J15: Code of the product in QPS or EBIX, for the migration map | K15: Y for a package product (terms change through versions) | L15: Segments the product is offered to (list MARKET_SEGMENT) | M15: Payment gate before placement | N15: When TSU reviews an account of the product | O15: Rate of a non-package product; for a package, of version 1 | P15: Commission when no insurer rate applies | Q15: Minimum premium of the product | R15: Above it the account goes to TSU | S15: Several vehicles on one account | T15: Mortgage or loan related | U15: Premium may be paid directly to the insurer | V15: Multi-year term and its maximum | W15: Free First Year eligible
A16: Row | B16: Line code * | C16: Line name * | D16: Risk-code pattern | E16: Cover type code | F16: Cover type name | G16: Parent cover type | H16: Risk code * | I16: Product name * | J16: Legacy code | K16: Package * | L16: Market segments | M16: Placement after * | N16: TSU review | O16: Default rate % | P16: Default commission % * | Q16: Minimum premium * | R16: Package TSI limit | S16: Fleet | T16: Mortgage related | U16: Direct payment allowed | V16: Multi-year / Maximum term | W16: Free First Year
A17: Example – overwrite or delete | B17: MOTOR | C17: Motor | D17: MTR[0-9]{2} | E17: COMPREHENSIVE | F17: Comprehensive | H17: MTR30 | I17: Motor Fleet Plus | J17: QPS-MFP | K17: Y | L17: COMBANK | M17: PAID | N17: BY_RULES | O17: 1.2 | P17: 15 | Q17: 5000 | R17: 5000000 | S17: Y | T17: N | U17: N | V17: N | W17: N

Sheet UA-01 Users and roles
A1: UA-01 Users and roles load | L1: Step 10 of 31
A2: ← Back to Start here | B2: Step 10 of 31. Fill in one row per record below the column headers; the guide above each column says what to enter. | L2: Ask a question →
A3: Purpose | B3: Every BIBS user at go-live with the user data and the group profiles, in the columns of the Bulk Request template
A4: Provided by | B4: Business Administration, with the unit heads who name their users
A5: Due | B5: 1-Nov-2027 – Production values before the dress rehearsal
A6: How it is loaded | B6: Bulk Request (SCR-UA-09): the file of this template is uploaded as a bulk batch, checked row by row and approved by an approver like single requests; users are out of the data migration scope (DMQ30)
A7: Source | B7: The users of the legacy systems and the unit rosters; the HR list of employees for the full names and e-mails
A8: Depends on | B8: UA-06 Lists of values → | D8: UA-02 Role-to-permission matrix →
A9: Progress | B9: Rows entered | C9: =SUMPRODUCT(((ROW($B$17:$B$517)>17)+($B$17<>"ENROL")>0)*(LEN($B$17:$B$517&$C$17:$C$517&$D$17:$D$517&$E$17:$E$517&$F$17:$F$517&$G$17:$G$517&$H$17:$H$517&$I$17:$I$517&$J$17:$J$517&$K$17:$K$517&$L$17:$L$517)>0)) | D9: Mandatory cells missing | E9: =SUMPRODUCT(((ROW($B$17:$B$517)>17)+($B$17<>"ENROL")>0)*(LEN($B$17:$B$517&$C$17:$C$517&$D$17:$D$517&$E$17:$E$517&$F$17:$F$517&$G$17:$G$517&$H$17:$H$517&$I$17:$I$517&$J$17:$J$517&$K$17:$K$517&$L$17:$L$517)>0)*(($B$17:$B$517="")+($C$17:$C$517="")+($L$17:$L$517="")))
A10: Confirmed by (BDOI owner) | D10: Date
A12: Mandatory | B12: Yes | C12: Yes | D12: Conditional: ENROL | E12: No | F12: No | G12: No | H12: No | I12: No | J12: Conditional: ENROL | K12: No | L12: Yes
A13: Format | B13: ENROL, MODIFY, DEACTIVATE or REACTIVATE | C13: A letter and nine digits (BDOI format a999999999) | D13: Up to 120 characters | E13: Company e-mail address | F13: Windows log-on name; unique | G13: Branch code | H13: Code of the list Business unit group (CI-06) | I13: Code of the list User level (CI-06) | J13: Profile codes of CI-02 separated by ';' | K13: yyyy-MM-dd; blank = on approval | L13: Up to 1,000 characters
A14: Allowed values | B14: ENROL, MODIFY, DEACTIVATE, REACTIVATE (list Bulk request action) | C14: Free entry, up to 10 characters | D14: Free entry, up to 120 characters | E14: Free entry | F14: Free entry | G14: Free entry | H14: Codes of UA-06 Lists of values, column Code (one or more) | I14: Codes of UA-06 Lists of values, column Code (one or more) | J14: Codes of UA-02 Role-to-permission matrix, column Group profile code (one or more) | K14: Free entry | L14: Free entry, up to 1000 characters
A15: What to enter | B15: ENROL for the go-live load | C15: The BIBS user ID; unique | D15: Name shown on screens and reports | E15: Receives the access-changed notices and the reset links | F15: Used for the BDO directory sign-in when it is enabled | G15: Home branch of the user | H15: Business unit group | I15: User level | J15: The group profiles of the user | K15: Date the change applies | L15: Justification of the line
A16: Row | B16: Action * | C16: User ID * | D16: Full Name | E16: E-mail | F16: Windows ID | G16: Home Branch Code | H16: Business Unit | I16: User Level | J16: Group Profiles | K16: Effective Date | L16: Remarks *
A17: Example – overwrite or delete | B17: ENROL | C17: a013000201 | D17: Andrea Mercado | E17: andrea.mercado@brokerverse-seed.ph | F17: AMERCADO | G17: HO | J17: MKT_AO | L17: Joined Marketing

Sheet D0-03 Holiday calendar
A1: D0-03 Holiday calendar | G1: Step 11 of 31
A2: ← Back to Start here | B2: Step 11 of 31. Fill in one row per record below the column headers; the guide above each column says what to enter. | G2: Ask a question →
A3: Purpose | B3: Public and company holidays of 2027 and 2028
A4: Provided by | B4: Head, Comptrollership; Human Resources
A5: Due | B5: 4-Jan-2027 – Platform set-up for Drop 1 SIT
A6: How it is loaded | B6: Holiday Calendar (Setup & Administration); 2028 before the dress rehearsal, later years each December
A7: Source | B7: Proclamations of the national holidays; BDOI company holidays
A8: Depends on | B8: D0-02 Branches →
A9: Progress | B9: Rows entered | C9: =SUMPRODUCT(((ROW($D$17:$D$517)>17)+($D$17<>"New Year's Day")>0)*(LEN($B$17:$B$517&$C$17:$C$517&$D$17:$D$517)>0)) | D9: Mandatory cells missing | E9: =SUMPRODUCT(((ROW($D$17:$D$517)>17)+($D$17<>"New Year's Day")>0)*(LEN($B$17:$B$517&$C$17:$C$517&$D$17:$D$517)>0)*(($C$17:$C$517="")+($D$17:$D$517="")))
A10: Confirmed by (BDOI owner) | D10: Date
A12: Mandatory | B12: No | C12: Yes | D12: Yes
A13: Format | B13: Code of D0-02; blank = every branch | C13: dd-MMM-yyyy | D13: Up to 120 characters
A14: Allowed values | B14: A code of D0-02 Branches, column Branch code | C14: A date, for example 15-Jan-2028 | D14: Free entry, up to 120 characters
A15: What to enter | B15: Branch the holiday applies to | C15: Date of the holiday | D15: Name of the holiday
A16: Row | B16: Branch code | C16: Date * | D16: Description *
A17: Example – overwrite or delete | C17: 46753 | D17: New Year's Day

Sheet UA-04 SoD rules
A1: UA-04 Separation-of-duties rules | H1: Step 12 of 31
A2: ← Back to Start here | B2: Step 12 of 31. Fill in one row per record below the column headers; the guide above each column says what to enter. | H2: Ask a question →
A3: Purpose | B3: The rules BIBS enforces, for confirmation, and the combinations of profiles or permissions that BDOI Information Security does not allow one user to hold
A4: Provided by | B4: BDOI Information Security
A5: Due | B5: 16-Jul-2027 – Values for UAT
A6: How it is loaded | B6: The rules marked Enforced are fixed in BIBS; the privileged profiles are set by the privilege level of CI-02. Each combination of two profiles is entered on Separation of Duties (SCR-UA-19) by the Business Administrator and authorised by Information Security; BIBS then refuses every request and bulk line that breaks it. A combination of permissions is reviewed with the reports
A7: Source | B7: BDOI information security policy; the separation-of-duties rules of FRS chapter 13
A8: Depends on | B8: UA-02 Role-to-permission matrix →
A9: Progress | B9: Rows entered | C9: =SUMPRODUCT(((ROW($B$17:$B$517)>17)+($B$17<>"SOD-01")>0)*(LEN($B$17:$B$517&$C$17:$C$517&$D$17:$D$517&$E$17:$E$517&$F$17:$F$517&$G$17:$G$517&$H$17:$H$517)>0)) | D9: Mandatory cells missing | E9: =SUMPRODUCT(((ROW($B$17:$B$517)>17)+($B$17<>"SOD-01")>0)*(LEN($B$17:$B$517&$C$17:$C$517&$D$17:$D$517&$E$17:$E$517&$F$17:$F$517&$G$17:$G$517&$H$17:$H$517)>0)*(($B$17:$B$517="")+($C$17:$C$517="")+($D$17:$D$517="")+($G$17:$G$517="")))
A10: Confirmed by (BDOI owner) | D10: Date
A12: Mandatory | B12: Yes | C12: Yes | D12: Yes | E12: Conditional: combination rule | F12: Conditional: combination rule | G12: Yes | H12: Conditional: Detect by review
A13: Format | B13: SOD-nn | C13: Text | D13: Enforced, To confirm, New | E13: Profile or permission of CI-02 | F13: Profile or permission of CI-02 | G13: Prevent (a rule of Separation of Duties, for two profiles), Detect by review, Second approval | H13: Monthly, Quarterly
A14: Allowed values | B14: Free entry | C14: Free entry | D14: Enforced, To confirm, New (list Separation-of-duties rule status) | E14: Codes of UA-02 Role-to-permission matrix, column Group profile code (one or more) | F14: Codes of UA-02 Role-to-permission matrix, column Group profile code (one or more) | G14: Prevent, Detect by review, Second approval (list Separation-of-duties control) | H14: Monthly, Quarterly (list Review frequency)
A15: What to enter | B15: Identifier of the rule | C15: The rule | D15: Enforced = a fixed rule of BIBS | E15: First profile or permission of a combination | F15: Profile or permission that may not be held with A | G15: How the rule is controlled | H15: How often the reports are reviewed
A16: Row | B16: Rule ID * | C16: Rule * | D16: Status * | E16: Profile or permission A | F16: Profile or permission B | G16: Control * | H16: Review frequency
A17: Example – overwrite or delete | B17: SOD-01 | C17: The requester never decides his own request | D17: Enforced | E17: User Access Requestor | F17: User Access Approver | G17: Prevent | H17: Quarterly

Sheet D0-11 Bank accounts
A1: D0-11 Company bank accounts | J1: Step 13 of 31
A2: ← Back to Start here | B2: Step 13 of 31. Fill in one row per record below the column headers; the guide above each column says what to enter. | J2: Ask a question →
A3: Purpose | B3: The bank accounts of BDOI used for collections and disbursements
A4: Provided by | B4: Head, Comptrollership; Treasury
A5: Due | B5: 4-Jan-2027 – Platform set-up for Drop 1 SIT
A6: How it is loaded | B6: Bank Accounts and Checks (Disbursement), authorised by Comptrollership
A7: Source | B7: BDOI bank account list
A8: Depends on | B8: D0-06 Chart of accounts → | D8: D0-02 Branches →
A9: Progress | B9: Rows entered | C9: =SUMPRODUCT(((ROW($B$17:$B$517)>17)+($B$17<>"BDO-CA-001")>0)*(LEN($B$17:$B$517&$C$17:$C$517&$D$17:$D$517&$E$17:$E$517&$F$17:$F$517&$G$17:$G$517&$H$17:$H$517&$I$17:$I$517&$J$17:$J$517)>0)) | D9: Mandatory cells missing | E9: =SUMPRODUCT(((ROW($B$17:$B$517)>17)+($B$17<>"BDO-CA-001")>0)*(LEN($B$17:$B$517&$C$17:$C$517&$D$17:$D$517&$E$17:$E$517&$F$17:$F$517&$G$17:$G$517&$H$17:$H$517&$I$17:$I$517&$J$17:$J$517)>0)*(($B$17:$B$517="")+($C$17:$C$517="")+($D$17:$D$517="")+($E$17:$E$517="")+($F$17:$F$517="")+($G$17:$G$517="")+($J$17:$J$517="")))
A10: Confirmed by (BDOI owner) | D10: Date
A12: Mandatory | B12: Yes | C12: Yes | D12: Yes | E12: Yes | F12: Yes | G12: Yes | H12: No | I12: No | J12: Yes
A13: Format | B13: Up to 20 capitals | C13: Text | D13: Bank name | E13: As printed by the bank | F13: ISO 4217 | G13: Account of D0-06 with a bank category | H13: Account of D0-06 | I13: Code of D0-02 | J13: Format of the bank advice
A14: Allowed values | B14: Free entry, up to 20 characters | C14: Free entry | D14: Free entry | E14: Free entry | F14: Free entry, up to 3 characters | G14: A code of D0-06 Chart of accounts, column Account Code | H14: A code of D0-06 Chart of accounts, column Account Code | I14: A code of D0-02 Branches, column Branch code | J14: Free entry
A15: What to enter | B15: Code of the account in BIBS | C15: Name shown on screens | D15: Bank of the account | E15: Account number | F15: Currency of the account | G15: Cash-in-bank account | H15: Account of issued post-dated checks | I15: Branch that uses the account | J15: Format of the notification to the payee
A16: Row | B16: Bank account code * | C16: Name * | D16: Bank * | E16: Account number * | F16: Currency * | G16: GL account * | H16: PDC clearing account | I16: Branch code | J16: Payment notification format *
A17: Example – overwrite or delete | B17: BDO-CA-001 | C17: BDO Makati current account | D17: BDO Unibank, Inc. | E17: 000123456789 | F17: PHP | G17: 1110.01 | H17: 2241 | I17: HO | J17: EMAIL

Sheet PM-02 Coverages and rules
A1: PM-02 Coverages, perils and field rules | J1: Step 14 of 31
A2: ← Back to Start here | B2: Step 14 of 31. Fill in one row per record below the column headers; the guide above each column says what to enter. | J2: Ask a question →
A3: Purpose | B3: The coverage and peril level of each line, and the fields and documents each product needs on an account
A4: Provided by | B4: MBS
A5: Due | B5: 16-Jul-2027 – Values for UAT
A6: How it is loaded | B6: Entered on Coverages & Clauses (SCR-PM-15) and on the rule tabs of Products (SCR-PM-11, SCR-PM-12) before UAT; not migrated
A7: Source | B7: MBS and TSU (product matrix, PQ02)
A8: Depends on | B8: PM-09 Lists of values and parameters → | D8: PM-01 Product catalogue →
A9: Progress | B9: Rows entered | C9: =SUMPRODUCT(((ROW($B$17:$B$517)>17)+($B$17<>"COVERAGE")>0)*(LEN($B$17:$B$517&$C$17:$C$517&$D$17:$D$517&$E$17:$E$517&$F$17:$F$517&$G$17:$G$517&$H$17:$H$517&$I$17:$I$517&$J$17:$J$517)>0)) | D9: Mandatory cells missing | E9: =SUMPRODUCT(((ROW($B$17:$B$517)>17)+($B$17<>"COVERAGE")>0)*(LEN($B$17:$B$517&$C$17:$C$517&$D$17:$D$517&$E$17:$E$517&$F$17:$F$517&$G$17:$G$517&$H$17:$H$517&$I$17:$I$517&$J$17:$J$517)>0)*(($B$17:$B$517="")+($C$17:$C$517="")+($D$17:$D$517="")+($E$17:$E$517="")+($F$17:$F$517="")+($J$17:$J$517="")))
A10: Confirmed by (BDOI owner) | D10: Date
A12: Mandatory | B12: Yes | C12: Yes | D12: Yes | E12: Yes | F12: Yes | G12: Conditional: coverage | H12: Conditional: list, range or format rules | I12: Conditional: document rule | J12: Yes
A13: Format | B13: COVERAGE, FIELD_RULE or DOCUMENT_RULE | C13: Line or product the row applies to; * = every product | D13: A-Z, 0-9 and _ (coverage); field key (rule) | E13: Text | F13: Coverage kind (Section, Coverage, Peril, Extension); check (Presence, List of values, Number range, Format) | G13: Y or N | H13: List code; minimum and maximum; pattern | I13: List DOCUMENT_TYPE | J13: Y or N
A14: Allowed values | B14: COVERAGE, FIELD_RULE, DOCUMENT_RULE (list Coverage and rule record) | C14: Codes of PM-01 Product catalogue, column Risk code (one or more) | D14: Free entry | E14: Free entry | F14: Free entry | G14: Y or N | H14: Free entry | I14: List Document type: 63 values, see Reference lists | J14: Y or N
A15: What to enter | B15: What the row defines | C15: Scope of the row | D15: Coverage code or the account field checked | E15: Coverage name or field label | F15: Coverage kind or rule check | G15: A package needs at least one basic coverage | H15: Parameters of the check | I15: Document an account needs before submission | J15: Required or optional
A16: Row | B16: Record * | C16: Line code / Risk code * | D16: Code or field key * | E16: Name or label * | F16: Kind or check * | G16: Basic | H16: Parameters | I16: Document type | J16: Mandatory *
A17: Example – overwrite or delete | B17: COVERAGE | C17: MOTOR | D17: OD_THEFT | E17: Own damage and theft | F17: Coverage | G17: Y | J17: Y

Sheet PM-03 Clause library
A1: PM-03 Clause library | G1: Step 15 of 31
A2: ← Back to Start here | B2: Step 15 of 31. Fill in one row per record below the column headers; the guide above each column says what to enter. | G2: Ask a question →
A3: Purpose | B3: Warranties, clauses, exclusions and deductible wordings used in the insurer terms of package versions
A4: Provided by | B4: TSU (wordings); MBS (maintenance)
A5: Due | B5: 16-Jul-2027 – Values for UAT
A6: How it is loaded | B6: Entered on Coverages & Clauses › Clause Library (SCR-PM-15); not migrated
A7: Source | B7: Current package slips and insurer wordings
A8: Depends on | B8: PM-09 Lists of values and parameters → | D8: PM-01 Product catalogue →
A9: Progress | B9: Rows entered | C9: =SUMPRODUCT(((ROW($B$17:$B$517)>17)+($B$17<>"FLEET_REPAIR")>0)*(LEN($B$17:$B$517&$C$17:$C$517&$D$17:$D$517&$E$17:$E$517&$F$17:$F$517&$G$17:$G$517)>0)) | D9: Mandatory cells missing | E9: =SUMPRODUCT(((ROW($B$17:$B$517)>17)+($B$17<>"FLEET_REPAIR")>0)*(LEN($B$17:$B$517&$C$17:$C$517&$D$17:$D$517&$E$17:$E$517&$F$17:$F$517&$G$17:$G$517)>0)*(($B$17:$B$517="")+($C$17:$C$517="")+($E$17:$E$517="")+($F$17:$F$517="")+($G$17:$G$517="")))
A10: Confirmed by (BDOI owner) | D10: Date
A12: Mandatory | B12: Yes | C12: Yes | D12: No | E12: Yes | F12: Yes | G12: Yes (from)
A13: Format | B13: A-Z, 0-9 and _ | C13: WARRANTY, CLAUSE, EXCLUSION or DEDUCTIBLE_WORDING | D13: Line code; blank = every line | E13: Text | F13: Full text | G13: dd-MMM-yyyy
A14: Allowed values | B14: Free entry | C14: WARRANTY, CLAUSE, EXCLUSION, DEDUCTIBLE_WORDING (list Clause kind) | D14: A code of PM-01 Product catalogue, column Line code | E14: Free entry | F14: Free entry | G14: Free entry
A15: What to enter | B15: Unique code | C15: Code of the list CLAUSE_KIND | D15: Lines the clause is offered for | E15: Title shown in the pickers | F15: Wording printed on the package documents | G15: Validity of the wording
A16: Row | B16: Clause code * | C16: Kind * | D16: Line code | E16: Title * | F16: Wording * | G16: Effective from / to *
A17: Example – overwrite or delete | B17: FLEET_REPAIR | C17: CLAUSE | D17: MOTOR | E17: Accredited repair shops for fleets | F17: Repairs are made at the accredited shops of the insurer... | G17: 01-Jan-2027

Sheet PM-05 Insurers
A1: PM-05 Insurers, branches and commission rates | J1: Step 16 of 31
A2: ← Back to Start here | B2: Step 16 of 31. Fill in one row per record below the column headers; the guide above each column says what to enter. | J2: Ask a question →
A3: Purpose | B3: The insurer panel with accreditation and placement e-mails, the branches with their LGT rate, and the commission rates per product
A4: Provided by | B4: Head of Operations; MBS (commission per package)
A5: Due | B5: 9-Apr-2027 – Reference data for Trial migration 1 (M4)
A6: How it is loaded | B6: Data migration objects R04 (insurers, branches, business partners) and R07 (commission rates); after go-live on Insurers (SCR-PM-17, SCR-PM-18)
A7: Source | B7: Legacy QPS and EBIX insurer masters
A8: Depends on | B8: PM-01 Product catalogue →
A9: Progress | B9: Rows entered | C9: =SUMPRODUCT(((ROW($B$17:$B$517)>17)+($B$17<>"INS-MGIC")>0)*(LEN($B$17:$B$517&$C$17:$C$517&$D$17:$D$517&$E$17:$E$517&$F$17:$F$517&$G$17:$G$517&$H$17:$H$517&$I$17:$I$517&$J$17:$J$517)>0)) | D9: Mandatory cells missing | E9: =SUMPRODUCT(((ROW($B$17:$B$517)>17)+($B$17<>"INS-MGIC")>0)*(LEN($B$17:$B$517&$C$17:$C$517&$D$17:$D$517&$E$17:$E$517&$F$17:$F$517&$G$17:$G$517&$H$17:$H$517&$I$17:$I$517&$J$17:$J$517)>0)*(($B$17:$B$517="")+($C$17:$C$517="")))
A10: Confirmed by (BDOI owner) | D10: Date
A12: Mandatory | B12: Yes | C12: Yes (name) | D12: No | E12: No | F12: Conditional: for package insurers | G12: No | H12: Conditional: branch rows | I12: Conditional: branch rows | J12: Conditional: commission rows
A13: Format | B13: INS- followed by capitals | C13: Text | D13: 000-000-000-000; text | E13: Text; dd-MMM-yyyy | F13: Addresses separated by commas | G13: 0 to 365 | H13: Text | I13: 0 to 100 | J13: Risk code or blank for all; percentage; dd-MMM-yyyy
A14: Allowed values | B14: Free entry | C14: Free entry | D14: Free entry | E14: Free entry | F14: Free entry | G14: A whole number from 0 to 365 | H14: Free entry | I14: A number from 0 to 100 | J14: Codes of PM-01 Product catalogue, column Risk code (one or more)
A15: What to enter | B15: Insurer code; unique | C15: Registered and short name | D15: Business partner details | E15: Insurance Commission accreditation | F15: Where quotation and placement slips are sent | G15: Default credit days | H15: Branch of the insurer | I15: Local government tax on premium | J15: Commission rate of the insurer
A16: Row | B16: Partner code * | C16: Name / Short name * | D16: TIN / Address | E16: IC accreditation no. / Accredited until | F16: Placement e-mails | G16: Credit days | H16: Branch code / Branch name / City | I16: LGT % | J16: Commission product / Commission % / From / To
A17: Example – overwrite or delete | B17: INS-MGIC | C17: Mabuhay General Insurance Corp. | D17: 123-456-789-000 | E17: IC-2026-001; 31-Dec-2027 | F17: placement@insurer.example | G17: 30 | H17: MKT; Makati; Makati City | I17: 0.5 | J17: MTR30; 15; 01-Jan-2028; -

Sheet D0-01 Company
A1: D0-01 Company | J1: Step 17 of 31
A2: ← Back to Start here | B2: Step 17 of 31. Fill in one row per record below the column headers; the guide above each column says what to enter. | J2: Ask a question →
A3: Purpose | B3: The company record of BDOI
A4: Provided by | B4: Head, Comptrollership
A5: Due | B5: 4-Jan-2027 – Platform set-up for Drop 1 SIT
A6: How it is loaded | B6: Companies (Setup & Administration), entered by the System Administrator and authorised by Comptrollership
A7: Source | B7: BDOI registration documents and the current chart of accounts
A8: Depends on | B8: D0-06 Chart of accounts →
A9: Progress | B9: Rows entered | C9: =SUMPRODUCT(((ROW($B$17:$B$517)>17)+($B$17<>"BDOI")>0)*(LEN($B$17:$B$517&$C$17:$C$517&$D$17:$D$517&$E$17:$E$517&$F$17:$F$517&$G$17:$G$517&$H$17:$H$517&$I$17:$I$517&$J$17:$J$517)>0)) | D9: Mandatory cells missing | E9: =SUMPRODUCT(((ROW($B$17:$B$517)>17)+($B$17<>"BDOI")>0)*(LEN($B$17:$B$517&$C$17:$C$517&$D$17:$D$517&$E$17:$E$517&$F$17:$F$517&$G$17:$G$517&$H$17:$H$517&$I$17:$I$517&$J$17:$J$517)>0)*(($B$17:$B$517="")+($C$17:$C$517="")+($D$17:$D$517="")+($E$17:$E$517="")+($F$17:$F$517="")+($G$17:$G$517="")+($H$17:$H$517="")+($I$17:$I$517="")+($J$17:$J$517="")))
A10: Confirmed by (BDOI owner) | D10: Date
A12: Mandatory | B12: Yes | C12: Yes | D12: Yes | E12: Yes | F12: Yes | G12: Yes | H12: Yes | I12: Yes | J12: Yes
A13: Format | B13: Up to 10 capitals | C13: Up to 200 characters | D13: 000-000-000-00000 | E13: Text | F13: ISO 4217 | G13: 1 to 12 | H13: Whole number | I13: Whole number | J13: Account code of D0-06
A14: Allowed values | B14: Free entry, up to 10 characters | C14: Free entry, up to 200 characters | D14: Free entry | E14: Free entry | F14: Free entry, up to 3 characters | G14: A whole number from 1 to 12 | H14: A whole number from 0 to 365 | I14: A whole number from 0 to 365 | J14: A code of D0-06 Chart of accounts, column Account Code
A15: What to enter | B15: Code of the company on every record | C15: Name as registered with the SEC | D15: Tax identification number with branch code | E15: Address printed on receipts and BIR forms | F15: Currency of the books | G15: First month of the financial year | H15: How many days before today a posting may be dated | I15: How many days after today a posting may be dated | J15: Account that receives the year-end result
A16: Row | B16: Company code * | C16: Registered name * | D16: TIN * | E16: Registered address * | F16: Base currency * | G16: Fiscal year start month * | H16: Back-value days * | I16: Forward-value days * | J16: Retained earnings account *
A17: Example – overwrite or delete | B17: BDOI | C17: BDO Insurance and Reinsurance Brokers, Inc. | D17: 000-000-000-00000 | E17: 7899 Makati Avenue, Makati City | F17: PHP | G17: 1 | H17: 5 | I17: 0 | J17: 3200

Sheet D0-08 Accounting rules
A1: D0-08 Accounting rules | K1: Step 18 of 31
A2: ← Back to Start here | B2: Step 18 of 31. Fill in one row per record below the column headers; the guide above each column says what to enter. | K2: Ask a question →
A3: Purpose | B3: The debit and credit accounts of each accounting event of the platform
A4: Provided by | B4: Head, Comptrollership
A5: Due | B5: 4-Jan-2027 – Platform set-up for Drop 1 SIT
A6: How it is loaded | B6: Accounting Rules (Accounting Engine), checked with the Rule Simulator and authorised by Comptrollership
A7: Source | B7: The posting rules of EBIX and ISYS; the accounting events listed on the sheet Ref Accounting events
A8: Depends on | B8: D0-04 Cost centres and business lines → | D8: D0-06 Chart of accounts →
A9: Progress | B9: Rows entered | C9: =SUMPRODUCT(((ROW($B$17:$B$517)>17)+($B$17<>"PREMIUM_BOOKED")>0)*(LEN($B$17:$B$517&$C$17:$C$517&$D$17:$D$517&$E$17:$E$517&$F$17:$F$517&$G$17:$G$517&$H$17:$H$517&$I$17:$I$517&$J$17:$J$517&$K$17:$K$517)>0)) | D9: Mandatory cells missing | E9: =SUMPRODUCT(((ROW($B$17:$B$517)>17)+($B$17<>"PREMIUM_BOOKED")>0)*(LEN($B$17:$B$517&$C$17:$C$517&$D$17:$D$517&$E$17:$E$517&$F$17:$F$517&$G$17:$G$517&$H$17:$H$517&$I$17:$I$517&$J$17:$J$517&$K$17:$K$517)>0)*(($B$17:$B$517="")+($C$17:$C$517="")+($F$17:$F$517="")+($G$17:$G$517="")+($H$17:$H$517="")+($I$17:$I$517="")+($J$17:$J$517="")))
A10: Confirmed by (BDOI owner) | D10: Date
A12: Mandatory | B12: Yes | C12: Yes | D12: No | E12: No | F12: Yes | G12: Yes | H12: Yes | I12: Yes | J12: Yes | K12: No
A13: Format | B13: Code of the sheet Ref Accounting events | C13: Text | D13: Code of D0-04; blank = every line | E13: ISO 4217; blank = every currency | F13: dd-MMM-yyyy | G13: 1, 2, 3 | H13: DEBIT or CREDIT | I13: Account of D0-06 | J13: Component of the event | K13: Text
A14: Allowed values | B14: List Accounting event: 90 values, see Reference lists | C14: Free entry | D14: A code of D0-04 Cost centres and business lines, column Code | E14: Free entry | F14: A date, for example 15-Jan-2028 | G14: A whole number from 1 to 99 | H14: DEBIT, CREDIT (list Debit or credit) | I14: A code of D0-06 Chart of accounts, column Account Code | J14: Free entry | K14: Free entry
A15: What to enter | B15: Event that the rule posts | C15: Name of the rule | D15: Line the rule applies to | E15: Currency the rule applies to | F15: First posting date of the rule | G15: Order of the line in the entry | H15: Side of the line | I15: Account posted | J15: Amount the line posts | K15: Text of the journal line
A16: Row | B16: Event type * | C16: Rule name * | D16: Business line | E16: Currency | F16: Effective from * | G16: Line * | H16: Debit or credit * | I16: Account code * | J16: Amount component * | K16: Narration
A17: Example – overwrite or delete | B17: PREMIUM_BOOKED | C17: Premium booked - non-life | F17: 46753 | G17: 1 | H17: DEBIT | I17: 1210.07 | J17: GROSS_PREMIUM | K17: Premium receivable

Sheet D0-09 Legacy accounts
A1: D0-09 Legacy control accounts | G1: Step 19 of 31
A2: ← Back to Start here | B2: Step 19 of 31. Fill in one row per record below the column headers; the guide above each column says what to enter. | G2: Ask a question →
A3: Purpose | B3: The accounts that carry the migrated invoices and unapplied payments until they run off, and Migration Clearing
A4: Provided by | B4: Head, Comptrollership
A5: Due | B5: 1-Dec-2026 – Drafts with the Drop 0 sign-off
A6: How it is loaded | B6: Created with the chart of accounts (D0-06); named in the accounting rules of the legacy items
A7: Source | B7: Proposed rule PR-DM-02 of the Data Migration set
A8: Depends on | B8: D0-06 Chart of accounts →
A9: Progress | B9: Rows entered | C9: =SUMPRODUCT(((ROW($B$17:$B$517)>17)+($B$17<>"Migration Clearing")>0)*(LEN($B$17:$B$517&$C$17:$C$517&$D$17:$D$517&$E$17:$E$517&$F$17:$F$517)>0)) | D9: Mandatory cells missing | E9: =SUMPRODUCT(((ROW($B$17:$B$517)>17)+($B$17<>"Migration Clearing")>0)*(LEN($B$17:$B$517&$C$17:$C$517&$D$17:$D$517&$E$17:$E$517&$F$17:$F$517)>0)*(($B$17:$B$517="")+($D$17:$D$517="")))
A10: Confirmed by (BDOI owner) | D10: Date
A12: Mandatory | B12: Yes | C12: Conditional: Premium Receivable - Legacy | D12: Yes | E12: No | F12: No
A13: Format | B13: Premium Receivable - Legacy (per component), PR 2307 - Legacy, Due to Insurers - Legacy, Commission Receivable - Legacy, Unrealised Commission - Legacy, Deferred Output VAT - Legacy, Unapplied Collections - Legacy, Migration Clearing | C13: Basic premium, DST, premium tax or VAT, LGT, FST, other charges | D13: Account of D0-06 | E13: EBIX and ISYS account codes separated by commas | F13: Text
A14: Allowed values | B14: List Legacy control account: 8 values, see Reference lists | C14: Free entry | D14: A code of D0-06 Chart of accounts, column Account Code | E14: Free entry | F14: Free entry
A15: What to enter | B15: One row per account | C15: Component the account holds | D15: Account in the production chart | E15: The legacy accounts it replaces (for the code map GL_ACCOUNT, R08) | F15: End state after the run-off
A16: Row | B16: Legacy account * | C16: Component | D16: BIBS account code * | E16: Legacy GL accounts | F16: Remarks
A17: Example – overwrite or delete | B17: Migration Clearing | D17: 1990.01 | E17: 1210-01 | F17: Nets to 0.00 after the opening

Sheet D0-10 Tax codes
A1: D0-10 Tax codes | K1: Step 20 of 31
A2: ← Back to Start here | B2: Step 20 of 31. Fill in one row per record below the column headers; the guide above each column says what to enter. | K2: Ask a question →
A3: Purpose | B3: The tax codes with their ATC, rate and GL account
A4: Provided by | B4: Head, Comptrollership (Tax)
A5: Due | B5: 16-Jul-2027 – Values for UAT
A6: How it is loaded | B6: Tax Codes & Forms (Tax & Statutory), authorised by Comptrollership
A7: Source | B7: BIR ATC list; current tax set-up
A8: Depends on | B8: D0-06 Chart of accounts →
A9: Progress | B9: Rows entered | C9: =SUMPRODUCT(((ROW($B$17:$B$517)>17)+($B$17<>"EWT_WC158")>0)*(LEN($B$17:$B$517&$C$17:$C$517&$D$17:$D$517&$E$17:$E$517&$F$17:$F$517&$G$17:$G$517&$H$17:$H$517&$I$17:$I$517&$J$17:$J$517&$K$17:$K$517)>0)) | D9: Mandatory cells missing | E9: =SUMPRODUCT(((ROW($B$17:$B$517)>17)+($B$17<>"EWT_WC158")>0)*(LEN($B$17:$B$517&$C$17:$C$517&$D$17:$D$517&$E$17:$E$517&$F$17:$F$517&$G$17:$G$517&$H$17:$H$517&$I$17:$I$517&$J$17:$J$517&$K$17:$K$517)>0)*(($B$17:$B$517="")+($C$17:$C$517="")+($D$17:$D$517="")+($G$17:$G$517="")+($H$17:$H$517="")+($J$17:$J$517="")))
A10: Confirmed by (BDOI owner) | D10: Date
A12: Mandatory | B12: Yes | C12: Yes | D12: Yes | E12: Conditional: withholding | F12: No | G12: Yes | H12: Yes | I12: No | J12: Yes | K12: No
A13: Format | B13: Up to 20 capitals | C13: Text | D13: EWT, FWT, VAT, PT | E13: BIR ATC | F13: List PAYEE_CLASS | G13: 0 to 100 | H13: Account of D0-06 | I13: Text | J13: dd-MMM-yyyy | K13: dd-MMM-yyyy
A14: Allowed values | B14: Free entry, up to 20 characters | C14: Free entry | D14: EWT, FWT, VAT, PT (list Tax type) | E14: Free entry | F14: SUPPLIER, INSURER, EMPLOYEE, CLIENT, GOVERNMENT, OTHER (list Payee class) | G14: A number from 0 to 100 | H14: A code of D0-06 Chart of accounts, column Account Code | I14: Free entry | J14: A date, for example 15-Jan-2028 | K14: A date, for example 15-Jan-2028
A15: What to enter | B15: Code of the tax | C15: Name shown on screens | D15: Kind of tax | E15: Alphanumeric tax code | F15: Payees it applies to | G15: Rate of the tax | H15: Account of the tax | I15: Nature of the income payment | J15: First date of the rate | K15: Last date of the rate
A16: Row | B16: Tax code * | C16: Name * | D16: Tax type * | E16: ATC | F16: Payee class | G16: Rate % * | H16: GL account * | I16: Income nature | J16: Effective from * | K16: Effective to
A17: Example – overwrite or delete | B17: EWT_WC158 | C17: EWT 1% - goods | D17: EWT | E17: WC158 | F17: CORPORATE | G17: 1 | H17: 2150.02 | I17: Purchase of goods | J17: 46753

Sheet D0-15 Approval limits
A1: D0-15 Approval limits and matrices | J1: Step 21 of 31
A2: ← Back to Start here | B2: Step 21 of 31. Fill in one row per record below the column headers; the guide above each column says what to enter. | J2: Ask a question →
A3: Purpose | B3: The approval levels by amount, sum insured or segment of the modules that approve by level
A4: Provided by | B4: Owners of the modules; Head, Comptrollership for the amounts
A5: Due | B5: 16-Jul-2027 – Values for UAT
A6: How it is loaded | B6: Submitted Policies Setup, EB Setup, Compliance Setup (Configuration Versions) and Disbursement approver routing; the authorisation limit of a user is in UA-03
A7: Source | B7: BDOI approval matrix and signing authorities
A8: Depends on | B8: UA-02 Role-to-permission matrix → | C8: UA-01 Users and roles load →
A9: Progress | B9: Rows entered | C9: =SUMPRODUCT(((ROW($B$17:$B$517)>17)+($B$17<>"Submitted Policies")>0)*(LEN($B$17:$B$517&$C$17:$C$517&$D$17:$D$517&$E$17:$E$517&$F$17:$F$517&$G$17:$G$517&$H$17:$H$517&$I$17:$I$517&$J$17:$J$517)>0)) | D9: Mandatory cells missing | E9: =SUMPRODUCT(((ROW($B$17:$B$517)>17)+($B$17<>"Submitted Policies")>0)*(LEN($B$17:$B$517&$C$17:$C$517&$D$17:$D$517&$E$17:$E$517&$F$17:$F$517&$G$17:$G$517&$H$17:$H$517&$I$17:$I$517&$J$17:$J$517)>0)*(($B$17:$B$517="")+($C$17:$C$517="")+($G$17:$G$517="")+($H$17:$H$517="")))
A10: Confirmed by (BDOI owner) | D10: Date
A12: Mandatory | B12: Yes | C12: Yes | D12: No | E12: No | F12: No | G12: Yes | H12: Yes | I12: No | J12: No
A13: Format | B13: Submitted Policies, Employee Benefits, Sanction Screening, Disbursement | C13: Text | D13: Segment, benefit line or case type | E13: PHP | F13: PHP; blank = no limit | G13: 1, 2, 3 | H13: Group profile of UA-02 | I13: User ID of UA-01 | J13: Text
A14: Allowed values | B14: Submitted Policies, Employee Benefits, Sanction Screening, Disbursement (list Module of an approval matrix) | C14: Free entry | D14: Free entry | E14: A number | F14: A number | G14: A whole number from 1 to 9 | H14: A code of UA-02 Role-to-permission matrix, column Group profile code | I14: A code of UA-01 Users and roles load, column User ID | J14: Free entry
A15: What to enter | B15: Module of the approval | C15: What is approved | D15: Scope of the row | E15: Lower bound (sum insured, premium or amount) | F15: Upper bound | G15: Order of the approval | H15: Profile that approves | I15: Only when one person approves | J15: Title printed on the document
A16: Row | B16: Module * | C16: Document or transaction * | D16: Segment or case type | E16: From amount | F16: To amount | G16: Approval level * | H16: Approver role * | I16: Named approver | J16: Signatory title
A17: Example – overwrite or delete | B17: Submitted Policies | C17: Terms of reference | D17: CBG | E17: 0 | F17: 10000000 | G17: 1 | H17: SBM_APPROVER | J17: Unit Head, Combank

Sheet PM-04 Rate tables
A1: PM-04 Rate tables | H1: Step 22 of 31
A2: ← Back to Start here | B2: Step 22 of 31. Fill in one row per record below the column headers; the guide above each column says what to enter. | H2: Ask a question →
A3: Purpose | B3: Statutory charges and rating factors, the short-period table and the motor BI / PD limit premiums
A4: Provided by | B4: Product Owner, MBS; Comptrollership (taxes)
A5: Due | B5: 16-Jul-2027 – Values for UAT
A6: How it is loaded | B6: Entered on Rates & Taxes (SCR-PM-19), pending authorisation; not migrated (effective-dated from go-live)
A7: Source | B7: BIR and LGU rates; current rating tables
A8: Depends on | B8: PM-01 Product catalogue →
A9: Progress | B9: Rows entered | C9: =SUMPRODUCT(((ROW($B$17:$B$517)>17)+($B$17<>"TAX")>0)*(LEN($B$17:$B$517&$C$17:$C$517&$D$17:$D$517&$E$17:$E$517&$F$17:$F$517&$G$17:$G$517&$H$17:$H$517)>0)) | D9: Mandatory cells missing | E9: =SUMPRODUCT(((ROW($B$17:$B$517)>17)+($B$17<>"TAX")>0)*(LEN($B$17:$B$517&$C$17:$C$517&$D$17:$D$517&$E$17:$E$517&$F$17:$F$517&$G$17:$G$517&$H$17:$H$517)>0)*(($B$17:$B$517="")+($H$17:$H$517="")))
A10: Confirmed by (BDOI owner) | D10: Date
A12: Mandatory | B12: Yes | C12: Conditional: TAX | D12: No | E12: Conditional: TAX, SHORT_PERIOD | F12: Conditional: SHORT_PERIOD | G12: Conditional: MOTOR_LIMIT | H12: Yes (from)
A13: Format | B13: TAX, SHORT_PERIOD or MOTOR_LIMIT | C13: DST, premium tax, VAT, fire service tax, motor factors | D13: Line; blank = every line | E13: Up to four decimals, 0 to 100 | F13: 1 to 12 | G13: BI or PD; amounts in PHP | H13: dd-MMM-yyyy
A14: Allowed values | B14: TAX, SHORT_PERIOD, MOTOR_LIMIT (list Rate table) | C14: Free entry | D14: A code of PM-01 Product catalogue, column Line code | E14: A number from 0 to 100 | F14: A whole number from 1 to 12 | G14: Free entry | H14: Free entry
A15: What to enter | B15: Table of the row | C15: Charge or factor | D15: Line the rate applies to | E15: Rate, or % of the annual premium | F15: Months covered, up to | G15: Limit and its premium | H15: Validity of the row
A16: Row | B16: Table * | C16: Rate | D16: Line code | E16: Rate % | F16: Months covered | G16: Coverage / Limit / Premium | H16: Effective from / to *
A17: Example – overwrite or delete | B17: TAX | C17: DST | E17: 12.5 | F17: 6 | G17: BI; 100000.00; 350.00 | H17: 01-Jan-2028

Sheet PM-10 Incentive criteria
A1: PM-10 Incentive criteria | G1: Step 23 of 31
A2: ← Back to Start here | B2: Step 23 of 31. Fill in one row per record below the column headers; the guide above each column says what to enter. | G2: Ask a question →
A3: Purpose | B3: The incentive criteria (for example CPC2) with their value, the products matrix and the effective dates
A4: Provided by | B4: Incentive Maintenance user (MBS); Comptrollership (CPC2 definition, PQ04)
A5: Due | B5: 16-Jul-2027 – Values for UAT
A6: How it is loaded | B6: Entered on Incentive Criteria (SCR-PM-16), pending authorisation; the copied booking rules are reviewed there
A7: Source | B7: Current incentive programmes; the booking incentive rules copied into the catalogue
A8: Depends on | B8: PM-09 Lists of values and parameters → | C8: PM-01 Product catalogue →
A9: Progress | B9: Rows entered | C9: =SUMPRODUCT(((ROW($B$17:$B$517)>17)+($B$17<>"CPC2; CPC2 campaign 2028")>0)*(LEN($B$17:$B$517&$C$17:$C$517&$D$17:$D$517&$E$17:$E$517&$F$17:$F$517&$G$17:$G$517)>0)) | D9: Mandatory cells missing | E9: =SUMPRODUCT(((ROW($B$17:$B$517)>17)+($B$17<>"CPC2; CPC2 campaign 2028")>0)*(LEN($B$17:$B$517&$C$17:$C$517&$D$17:$D$517&$E$17:$E$517&$F$17:$F$517&$G$17:$G$517)>0)*(($B$17:$B$517="")+($C$17:$C$517="")+($D$17:$D$517="")+($F$17:$F$517="")+($G$17:$G$517="")))
A10: Confirmed by (BDOI owner) | D10: Date
A12: Mandatory | B12: Yes | C12: Yes | D12: Yes (basis) | E12: No | F12: Yes (one product) | G12: Yes (from)
A13: Format | B13: A-Z, 0-9, _ and -; text | C13: List INCENTIVE_TYPE | D13: Rate (%), Fixed amount or Rule; number | E13: Parameter and value pairs separated by semicolons | F13: Active risk codes; segment or blank | G13: dd-MMM-yyyy
A14: Allowed values | B14: Free entry | C14: OTHERS, MIGRATED (list Incentive type) | D14: Free entry | E14: Free entry | F14: Codes of PM-01 Product catalogue, column Risk code (one or more) | G14: Free entry
A15: What to enter | B15: Criterion | C15: Type of criterion | D15: Value of the criterion | E15: Parameters of a rule criterion, as agreed with Comptrollership | F15: Products and segments the criterion applies to | G15: Validity; no overlap with another row of the code
A16: Row | B16: Code / Name * | C16: Incentive type * | D16: Value basis / Value * | E16: Rule parameters | F16: Products matrix: risk code / segment * | G16: Effective from / to *
A17: Example – overwrite or delete | B17: CPC2; CPC2 campaign 2028 | C17: CAMPAIGN | D17: Rate (%); 1.00 | E17: Minimum premium 5000 | F17: MTR30; COMBANK | G17: 01-Jan-2028

Sheet UA-03 Approval rules
A1: UA-03 Approvers, approval rules and limits | G1: Step 24 of 31
A2: ← Back to Start here | B2: Step 24 of 31. Fill in one row per record below the column headers; the guide above each column says what to enter. | G2: Ask a question →
A3: Purpose | B3: Who requests and who approves user access, the order of the approvers of group-profile requests, the second approvers, the implementers, and the authorisation limits of the users whose work other modules approve by amount
A4: Provided by | B4: Business Administration; BDOI Information Security for the second approval; Comptrollership for the authorisation limits
A5: Due | B5: 16-Jul-2027 – Values for UAT
A6: How it is loaded | B6: The users are given the Requestor, Approver, Second Approver and System Administrator profiles by requests (CI-01); the approvers are chosen on each request; UAM_ANY_APPROVER is set on System Parameters. The authorisation limit is set by an Enrol new user or Modify user request (field Authorisation Limit) decided by an approver; the bulk file has no limit column, so the limits are requested after the users are loaded
A7: Source | B7: BDOI's approval matrix (UQ01, UQ02)
A8: Depends on | B8: UA-01 Users and roles load →
A9: Progress | B9: Rows entered | C9: =SUMPRODUCT(((ROW($B$17:$B$517)>17)+($B$17<>"Approver")>0)*(LEN($B$17:$B$517&$C$17:$C$517&$D$17:$D$517&$E$17:$E$517&$F$17:$F$517&$G$17:$G$517)>0)) | D9: Mandatory cells missing | E9: =SUMPRODUCT(((ROW($B$17:$B$517)>17)+($B$17<>"Approver")>0)*(LEN($B$17:$B$517&$C$17:$C$517&$D$17:$D$517&$E$17:$E$517&$F$17:$F$517&$G$17:$G$517)>0)*(($B$17:$B$517="")+($C$17:$C$517="")+($D$17:$D$517="")))
A10: Confirmed by (BDOI owner) | D10: Date
A12: Mandatory | B12: Yes | C12: Yes | D12: Yes | E12: Conditional: Approver | F12: No | G12: No
A13: Format | B13: Requestor, Approver, Second Approver, Group-profile requester, Implementer | C13: User ID of CI-01 | D13: Business unit | E13: 1, 2, 3 | F13: Y or N | G13: Amount in PHP; blank = unlimited
A14: Allowed values | B14: Requestor, Approver, Second Approver, Group-profile requester, Implementer (list Role in user access) | C14: A code of UA-01 Users and roles load, column User ID | D14: Free entry | E14: A whole number from 1 to 9 | F14: Y or N | G14: A number
A15: What to enter | B15: The user access role of the user | C15: The user who holds the role | D15: Unit the user requests or approves for | E15: Usual order of the approvers of a group-profile request | F15: Y sets UAM_ANY_APPROVER: any approver decides any request, not only the chosen one | G15: Limit of the user's approvals by amount in the modules that use it (journals, payables)
A16: Row | B16: Role in user access * | C16: User ID * | D16: Unit * | E16: Approver order for group profiles | F16: Any approver may decide | G16: Authorisation limit
A17: Example – overwrite or delete | B17: Approver | C17: a013000205 | D17: Combank Marketing | E17: 1 | F17: N | G17: 500000

Sheet PM-06 Packages
A1: PM-06 Packages in force at go-live | J1: Step 25 of 31
A2: ← Back to Start here | B2: Step 25 of 31. Fill in one row per record below the column headers; the guide above each column says what to enter. | J2: Ask a question →
A3: Purpose | B3: For every package sold at go-live: its terms as they will be set up in BIBS through a package request (TSU) and a package version (MBS): rate scheme, dates, coverages, panel insurers and their terms
A4: Provided by | B4: TSU (prepares); Product Owner, MBS (approves)
A5: Due | B5: 1-Nov-2027 – Production values before the dress rehearsal
A6: How it is loaded | B6: Not migrated: TSU raises a package request per package (type New package, or Update for an existing risk code) and MBS sets up and validates the version before the map freeze; the Package Request Form accepts the same fields
A7: Source | B7: Signed package slips and ManCom sign-offs in force
A8: Depends on | B8: PM-01 Product catalogue → | D8: PM-02 Coverages, perils and field rules → | E8: PM-05 Insurers, branches and commission rates → | F8: PM-03 Clause library →
A9: Progress | B9: Rows entered | C9: =SUMPRODUCT(((ROW($B$17:$B$517)>17)+($B$17<>"MTR30")>0)*(LEN($B$17:$B$517&$C$17:$C$517&$D$17:$D$517&$E$17:$E$517&$F$17:$F$517&$G$17:$G$517&$H$17:$H$517&$I$17:$I$517&$J$17:$J$517)>0)) | D9: Mandatory cells missing | E9: =SUMPRODUCT(((ROW($B$17:$B$517)>17)+($B$17<>"MTR30")>0)*(LEN($B$17:$B$517&$C$17:$C$517&$D$17:$D$517&$E$17:$E$517&$F$17:$F$517&$G$17:$G$517&$H$17:$H$517&$I$17:$I$517&$J$17:$J$517)>0)*(($B$17:$B$517="")+($C$17:$C$517="")+($D$17:$D$517="")+($E$17:$E$517="")+($F$17:$F$517="")+($G$17:$G$517="")+($H$17:$H$517="")+($I$17:$I$517="")+($J$17:$J$517="")))
A10: Confirmed by (BDOI owner) | D10: Date
A12: Mandatory | B12: Yes | C12: Yes (name, scope) | D12: Yes (effective from, package end) | E12: Yes (minimum, commission; rate or insurer rates) | F12: Yes | G12: Yes (one basic coverage) | H12: Yes (the panel) | I12: Yes (every insurer and included coverage) | J12: Yes
A13: Format | B13: Code of CI-01 | C13: Text; Generic or Client-specific; client code | D13: dd-MMM-yyyy | E13: Percentages and PHP amounts | F13: Text | G13: Codes of CI-02; Y or N; PHP | H13: Codes of CI-05; Panel, Lead or Participant; shares total 100 | I13: Codes of CI-03 separated by commas | J13: Reference; the signed slip file
A14: Allowed values | B14: A code of PM-01 Product catalogue, column Risk code | C14: Free entry | D14: Free entry | E14: Free entry | F14: Free entry | G14: Codes of PM-02 Coverages, perils and field rules, column Code or field key (one or more) | H14: Codes of PM-05 Insurers, branches and commission rates, column Partner code (one or more) | I14: Codes of PM-03 Clause library, column Clause code (one or more) | J14: Free entry
A15: What to enter | B15: Package product | C15: As on the Package Request Form | D15: Dates of the version | E15: Rate scheme of the version | F15: How the premium is computed | G15: Coverages of the version | H15: Panel insurers | I15: Terms per insurer and coverage | J15: Evidence kept on the request
A16: Row | B16: Risk code * | C16: Package name / Scope / Client code * | D16: Effective from / Package start / Package end / Anniversary * | E16: Package rate % / Minimum premium / Commission % / Package TSI limit * | F16: Computation basis * | G16: Coverage code / Included / Optional / Limit / Deductible * | H16: Insurer code / Role / Share % / Rate % / Minimum premium * | I16: Insurer terms: insurer / coverage / limit / deductible / clauses * | J16: ManCom sign-off reference / Signed package slip *
A17: Example – overwrite or delete | B17: MTR30 | C17: Motor Fleet Plus; Generic | D17: 01-Jan-2028; 01-Jan-2028; 31-Dec-2028; - | E17: 1.2000; 5000.00; 15; 5000000.00 | F17: Comprehensive rate on the vehicle value | G17: OD_THEFT; Y; N; -; 2000.00 | H17: INS-MGIC; Panel; -; 1.2000; - | I17: INS-MGIC; OD_THEFT; -; 2000.00; FLEET_REPAIR | J17: MC-2026-017

Sheet D0-12 Check books
A1: D0-12 Check books | G1: Step 26 of 31
A2: ← Back to Start here | B2: Step 26 of 31. Fill in one row per record below the column headers; the guide above each column says what to enter. | G2: Ask a question →
A3: Purpose | B3: The check books in stock per bank account at go-live
A4: Provided by | B4: Treasury; Product Owner, Comptrollership - Disbursement
A5: Due | B5: 1-Nov-2027 – Production values before the dress rehearsal
A6: How it is loaded | B6: Bank Accounts and Checks (Disbursement)
A7: Source | B7: Check book register of Treasury
A8: Depends on | B8: D0-11 Company bank accounts →
A9: Progress | B9: Rows entered | C9: =SUMPRODUCT(((ROW($B$17:$B$517)>17)+($B$17<>"BDO-CA-001")>0)*(LEN($B$17:$B$517&$C$17:$C$517&$D$17:$D$517&$E$17:$E$517&$F$17:$F$517)>0)) | D9: Mandatory cells missing | E9: =SUMPRODUCT(((ROW($B$17:$B$517)>17)+($B$17<>"BDO-CA-001")>0)*(LEN($B$17:$B$517&$C$17:$C$517&$D$17:$D$517&$E$17:$E$517&$F$17:$F$517)>0)*(($B$17:$B$517="")+($C$17:$C$517="")+($D$17:$D$517="")+($E$17:$E$517="")+($F$17:$F$517="")))
A10: Confirmed by (BDOI owner) | D10: Date
A12: Mandatory | B12: Yes | C12: Yes | D12: Yes | E12: Yes | F12: Yes
A13: Format | B13: Code of D0-11 | C13: Digits | D13: Digits | E13: Digits | F13: dd-MMM-yyyy
A14: Allowed values | B14: A code of D0-11 Company bank accounts, column Bank account code | C14: Free entry | D14: Free entry | E14: Free entry | F14: A date, for example 15-Jan-2028
A15: What to enter | B15: Account of the check book | C15: First number of the book | D15: Last number of the book | E15: Next number to issue at go-live | F15: Date the book was received
A16: Row | B16: Bank account code * | C16: First check number * | D16: Last check number * | E16: Next check number * | F16: Received on *
A17: Example – overwrite or delete | B17: BDO-CA-001 | C17: 0001001 | D17: 0001100 | E17: 0001001 | F17: 46722

Sheet D0-13 Petty cash funds
A1: D0-13 Petty cash funds | I1: Step 27 of 31
A2: ← Back to Start here | B2: Step 27 of 31. Fill in one row per record below the column headers; the guide above each column says what to enter. | I2: Ask a question →
A3: Purpose | B3: The petty cash funds of the branches
A4: Provided by | B4: Head, Comptrollership
A5: Due | B5: 1-Nov-2027 – Production values before the dress rehearsal
A6: How it is loaded | B6: Petty Cash (Payables & Cash)
A7: Source | B7: Petty cash register
A8: Depends on | B8: D0-02 Branches → | D8: D0-05 Employees → | E8: D0-06 Chart of accounts → | G8: D0-11 Company bank accounts →
A9: Progress | B9: Rows entered | C9: =SUMPRODUCT(((ROW($B$17:$B$517)>17)+($B$17<>"HO")>0)*(LEN($B$17:$B$517&$C$17:$C$517&$D$17:$D$517&$E$17:$E$517&$F$17:$F$517&$G$17:$G$517&$H$17:$H$517&$I$17:$I$517)>0)) | D9: Mandatory cells missing | E9: =SUMPRODUCT(((ROW($B$17:$B$517)>17)+($B$17<>"HO")>0)*(LEN($B$17:$B$517&$C$17:$C$517&$D$17:$D$517&$E$17:$E$517&$F$17:$F$517&$G$17:$G$517&$H$17:$H$517&$I$17:$I$517)>0)*(($B$17:$B$517="")+($C$17:$C$517="")+($D$17:$D$517="")+($E$17:$E$517="")+($F$17:$F$517="")+($G$17:$G$517="")+($H$17:$H$517="")+($I$17:$I$517="")))
A10: Confirmed by (BDOI owner) | D10: Date
A12: Mandatory | B12: Yes | C12: Yes | D12: Yes | E12: Yes | F12: Yes | G12: Yes | H12: Yes | I12: Yes
A13: Format | B13: Code of D0-02 | C13: Up to 20 capitals | D13: Text | E13: Employee of D0-05 | F13: Account of D0-06 | G13: Code of D0-11 | H13: ISO 4217 | I13: Amount
A14: Allowed values | B14: A code of D0-02 Branches, column Branch code | C14: Free entry, up to 20 characters | D14: Free entry | E14: A code of D0-05 Employees, column Employee number | F14: A code of D0-06 Chart of accounts, column Account Code | G14: A code of D0-11 Company bank accounts, column Bank account code | H14: Free entry, up to 3 characters | I14: A number
A15: What to enter | B15: Branch of the fund | C15: Code of the fund | D15: Name of the fund | E15: Custodian of the fund | F15: Petty cash account | G15: Account that replenishes the fund | H15: Currency of the fund | I15: Amount of the fund
A16: Row | B16: Branch code * | C16: Fund code * | D16: Name * | E16: Custodian * | F16: GL account * | G16: Replenishment bank account * | H16: Currency * | I16: Imprest amount *
A17: Example – overwrite or delete | B17: HO | C17: PCF-HO | D17: Head Office petty cash | E17: 1203344 | F17: 1101.01 | G17: BDO-CA-001 | H17: PHP | I17: 20000

Sheet D0-14 Statement layouts
A1: D0-14 Bank statement layouts | K1: Step 28 of 31
A2: ← Back to Start here | B2: Step 28 of 31. Fill in one row per record below the column headers; the guide above each column says what to enter. | K2: Ask a question →
A3: Purpose | B3: The columns of the statement file of each bank account
A4: Provided by | B4: Head, Comptrollership; Treasury
A5: Due | B5: 16-Jul-2027 – Values for UAT
A6: How it is loaded | B6: Bank Statement Layouts (Setup & Administration)
A7: Source | B7: Statement files of the banks
A8: Depends on | B8: D0-11 Company bank accounts →
A9: Progress | B9: Rows entered | C9: =SUMPRODUCT(((ROW($B$17:$B$517)>17)+($B$17<>"BDO-CA-001")>0)*(LEN($B$17:$B$517&$C$17:$C$517&$D$17:$D$517&$E$17:$E$517&$F$17:$F$517&$G$17:$G$517&$H$17:$H$517&$I$17:$I$517&$J$17:$J$517&$K$17:$K$517)>0)) | D9: Mandatory cells missing | E9: =SUMPRODUCT(((ROW($B$17:$B$517)>17)+($B$17<>"BDO-CA-001")>0)*(LEN($B$17:$B$517&$C$17:$C$517&$D$17:$D$517&$E$17:$E$517&$F$17:$F$517&$G$17:$G$517&$H$17:$H$517&$I$17:$I$517&$J$17:$J$517&$K$17:$K$517)>0)*(($B$17:$B$517="")+($C$17:$C$517="")+($D$17:$D$517="")+($E$17:$E$517="")+($K$17:$K$517="")))
A10: Confirmed by (BDOI owner) | D10: Date
A12: Mandatory | B12: Yes | C12: Yes | D12: Yes | E12: Yes | F12: No | G12: Conditional: separate columns | H12: Conditional: separate columns | I12: Conditional: one signed column | J12: No | K12: Yes
A13: Format | B13: Code of D0-11 | C13: Text | D13: Column header or number | E13: Column header or number | F13: Column header or number | G13: Column header or number | H13: Column header or number | I13: Column header or number | J13: Column header or number | K13: For example dd/MM/yyyy
A14: Allowed values | B14: A code of D0-11 Company bank accounts, column Bank account code | C14: Free entry | D14: Free entry | E14: Free entry | F14: Free entry | G14: Free entry | H14: Free entry | I14: Free entry | J14: Free entry | K14: Free entry
A15: What to enter | B15: Account of the statement | C15: Name of the layout | D15: Column of the transaction date | E15: Column of the description | F15: Column of the reference | G15: Column of the debits | H15: Column of the credits | I15: Column of a signed amount | J15: Column of the running balance | K15: Format of the dates in the file
A16: Row | B16: Bank account code * | C16: Layout name * | D16: Date column * | E16: Description column * | F16: Reference column | G16: Debit column | H16: Credit column | I16: Amount column | J16: Balance column | K16: Date format *
A17: Example – overwrite or delete | B17: BDO-CA-001 | C17: BDO CSV statement | D17: Posting Date | E17: Description | F17: Reference No. | G17: Debit | H17: Credit | J17: Balance | K17: MM/dd/yyyy

Sheet PM-07 Package map
A1: PM-07 Package map (legacy package to BIBS package version) | I1: Step 29 of 31
A2: ← Back to Start here | B2: Step 29 of 31. Fill in one row per record below the column headers; the guide above each column says what to enter. | I2: Ask a question →
A3: Purpose | B3: Entries from each legacy package and version to the BIBS package version that renews it, with qualifiers where one legacy package splits; read at Renewal sanitation (check PACKAGE_REMAP)
A4: Provided by | B4: TSU (prepares); Product Owner, MBS (approves each map version)
A5: Due | B5: 18-Jun-2027 – Code maps approved (M5)
A6: How it is loaded | B6: Data migration object R06 (loaded as reference data and handed to the Renewal package map); new map versions until the map freeze (T-7), then maintained in Renewal
A7: Source | B7: QPS package list of the in-force policies expiring from go-live
A8: Depends on | B8: PM-01 Product catalogue → | C8: PM-05 Insurers, branches and commission rates → | D8: PM-06 Packages in force at go-live →
A9: Progress | B9: Rows entered | C9: =SUMPRODUCT(((ROW($B$17:$B$517)>17)+($B$17<>"PKG-MOTOR-FLEET; 3")>0)*(LEN($B$17:$B$517&$C$17:$C$517&$D$17:$D$517&$E$17:$E$517&$F$17:$F$517&$G$17:$G$517&$H$17:$H$517&$I$17:$I$517)>0)) | D9: Mandatory cells missing | E9: =SUMPRODUCT(((ROW($B$17:$B$517)>17)+($B$17<>"PKG-MOTOR-FLEET; 3")>0)*(LEN($B$17:$B$517&$C$17:$C$517&$D$17:$D$517&$E$17:$E$517&$F$17:$F$517&$G$17:$G$517&$H$17:$H$517&$I$17:$I$517)>0)*(($B$17:$B$517="")+($H$17:$H$517="")))
A10: Confirmed by (BDOI owner) | D10: Date
A12: Mandatory | B12: Yes | C12: No | D12: No | E12: No | F12: No | G12: Conditional: action MAP | H12: Yes | I12: No
A13: Format | B13: As stored in QPS | C13: Text | D13: Risk code of CI-01 | E13: Partner code of CI-05 | F13: PHP amounts | G13: A package version active in Product Maintenance | H13: MAP or REJECT | I13: Text
A14: Allowed values | B14: Free entry | C14: Free entry | D14: A code of PM-01 Product catalogue, column Risk code | E14: A code of PM-05 Insurers, branches and commission rates, column Partner code | F14: Free entry | G14: Codes of PM-06 Packages in force at go-live, column Risk code (one or more) | H14: MAP, REJECT (list Package map action) | I14: Free entry
A15: What to enter | B15: Package of the legacy policy headers | C15: For reading only | D15: When one legacy package maps to several BIBS packages by product | E15: When the split is by insurer | F15: When the split is by sum-insured band | G15: Target of the entry | H15: REJECT sends the candidate to the Renewal Exception bucket | I15: Reason of a REJECT or a split
A16: Row | B16: Legacy package code / Legacy version * | C16: Legacy package name | D16: Qualifier: risk code | E16: Qualifier: insurer | F16: Qualifier: sum insured from / to | G16: BIBS risk code / BIBS version | H16: Action * | I16: Remarks
A17: Example – overwrite or delete | B17: PKG-MOTOR-FLEET; 3 | C17: Motor fleet package 2025 | D17: MTR30 | G17: MTR30; 1 | H17: MAP

Sheet PM-08 Document templates
A1: PM-08 Document templates | G1: Step 30 of 31
A2: ← Back to Start here | B2: Step 30 of 31. Fill in one row per record below the column headers; the guide above each column says what to enter. | G2: Ask a question →
A3: Purpose | B3: The texts of the package documents: Package Request Form, quotation slip, comparative table, package slip, package advisory and package renewal advisory, with the merge fields each may use
A4: Provided by | B4: TSU and MBS (texts); Business Administrator (maintenance)
A5: Due | B5: 16-Jul-2027 – Values for UAT
A6: How it is loaded | B6: Entered on Document Templates (New Business set, SCR-NB-44) as a new template version effective from a date; not migrated
A7: Source | B7: BDOI layouts of the current documents (Q03)
A8: Depends on | B8: Nothing: this template can be filled in first
A9: Progress | B9: Rows entered | C9: =SUMPRODUCT(((ROW($B$17:$B$517)>17)+($B$17<>"PKG_ADVISORY")>0)*(LEN($B$17:$B$517&$C$17:$C$517&$D$17:$D$517&$E$17:$E$517&$F$17:$F$517)>0)) | D9: Mandatory cells missing | E9: =SUMPRODUCT(((ROW($B$17:$B$517)>17)+($B$17<>"PKG_ADVISORY")>0)*(LEN($B$17:$B$517&$C$17:$C$517&$D$17:$D$517&$E$17:$E$517&$F$17:$F$517)>0)*(($B$17:$B$517="")+($C$17:$C$517="")+($D$17:$D$517="")+($F$17:$F$517="")))
A10: Confirmed by (BDOI owner) | D10: Date
A12: Mandatory | B12: Yes | C12: Yes | D12: Yes | E12: No | F12: Yes
A13: Format | B13: PKG_REQUEST_FORM, PKG_QUOTATION_SLIP, PKG_COMPARATIVE, PKG_SLIP, PKG_ADVISORY, PKG_RENEWAL_ADVISORY | C13: Text | D13: Text with merge fields in double braces | E13: PKG_REQUEST_FORM: reference, requestType, title; PKG_QUOTATION_SLIP: reference, roundNo, replyBy; PKG_COMPARATIVE: reference, roundNo, variant; PKG_SLIP: reference, title; advisories: productCode, productName, versionNo, effectiveFrom, reference | F13: dd-MMM-yyyy
A14: Allowed values | B14: List Package document template: 6 values, see Reference lists | C14: Free entry | D14: Free entry | E14: Free entry | F14: A date, for example 15-Jan-2028
A15: What to enter | B15: Template code | C15: Title of the template version | D15: Opening text of the document | E15: Fields filled in by BIBS | F15: Date from which the version is used
A16: Row | B16: Template * | C16: Title * | D16: Text * | E16: Merge fields used | F16: Effective from *
A17: Example – overwrite or delete | B17: PKG_ADVISORY | C17: Package advisory | D17: This is to advise that the package {{productCode}} - {{productName}} ... | E17: productCode, productName, versionNo, effectiveFrom, reference | F17: 46327

Sheet UA-05 Parameters
A1: UA-05 Password, session and sign-in parameters | G1: Step 31 of 31
A2: ← Back to Start here | B2: Step 31 of 31. Fill in one row per record below the column headers; the guide above each column says what to enter. | G2: Ask a question →
A3: Purpose | B3: The values of the sign-in, password, session and access-request parameters, as delivered and as BDOI Information Security wants them
A4: Provided by | B4: BDOI Information Security; BDOI IT for the sign-in mode
A5: Due | B5: 16-Jul-2027 – Values for UAT
A6: How it is loaded | B6: System Parameters (SCR-UA-18): entered by the System Administrator and approved by the Information Security Officer, audited; checked in SIT with the test plan
A7: Source | B7: BDOI security policy (UQ07, UQ08); the values delivered (FRS section 9.1)
A8: Depends on | B8: Nothing: this template can be filled in first
A9: Progress | B9: Rows entered | C9: =SUMPRODUCT(((ROW($B$17:$B$517)>17)+($B$17<>"PASSWORD_MAX_AGE_DAYS")>0)*(LEN($B$17:$B$517&$C$17:$C$517&$D$17:$D$517&$E$17:$E$517&$F$17:$F$517)>0)) | D9: Mandatory cells missing | E9: =SUMPRODUCT(((ROW($B$17:$B$517)>17)+($B$17<>"PASSWORD_MAX_AGE_DAYS")>0)*(LEN($B$17:$B$517&$C$17:$C$517&$D$17:$D$517&$E$17:$E$517&$F$17:$F$517)>0)*(($B$17:$B$517="")+($C$17:$C$517="")+($D$17:$D$517="")+($F$17:$F$517="")))
A10: Confirmed by (BDOI owner) | D10: Date
A12: Mandatory | B12: Yes | C12: Yes | D12: Yes | E12: Conditional: value changed | F12: Yes
A13: Format | B13: LOGIN_MAX_FAILED_ATTEMPTS, SESSION_IDLE_WARNING_MINUTES, SESSION_TIMEOUT_MINUTES, SESSION_EXPIRY_WARNING_MINUTES, AUTH_MODE, USER_ID_PATTERN, USER_ID_FORMAT_TEXT, PASSWORD_HISTORY_COUNT, PASSWORD_MAX_AGE_DAYS, PASSWORD_MIN_AGE_DAYS, UAM_WORKING_HOURS, UAM_ANY_APPROVER, UAM_ROLE_APPLY_ON_APPROVAL, UAM_EXTERNAL_USERS, UAM_DORMANT_DAYS, UAM_DORMANT_NOTICE_DAYS, JOB_FAILURE_RECIPIENTS | C13: As on System Parameters | D13: Same type and range | E13: Text | F13: Name
A14: Allowed values | B14: List Sign-in: 17 values, see Reference lists | C14: Free entry | D14: Free entry | E14: Free entry | F14: Free entry
A15: What to enter | B15: One row per parameter | C15: The value proposed with the system | D15: The value BDOI wants | E15: Policy reference or reason | F15: Information Security or BDOI IT approver of the value
A16: Row | B16: Parameter * | C16: Value as delivered * | D16: Value wanted * | E16: Reason | F16: Approved by *
A17: Example – overwrite or delete | B17: PASSWORD_MAX_AGE_DAYS | C17: 90 | D17: 90 | E17: BDO password policy | F17: Ramon Dizon

Sheet Ref Lists of values
A1: Reference: Lists of values
A2: ← Back to Start here | B2: Every list of values of BIBS with its owner and its one route
A4: List | B4: Name | C4: Module | D4: Drop | E4: Owner (BDOI unit) | F4: Values proposed | G4: Route | H4: Prepared in | I4: Due | J4: Values to keep, add or retire | K4: Status | L4: BDOI comments
A5: ACSL_CASE_TYPE | B5: ACSL case type | C5: Accounting, Disbursement and ACSL | D5: Drop 1 | E5: Head, Comptrollership | F5: 5 | G5: Template | H5: This workbook, sheet Ref Lists of values | I5: 9-Apr-2027 (T-38 weeks) | K5: Not started
A6: ACSL_CORRECTION_KIND | B6: ACSL correction kind | C6: Accounting, Disbursement and ACSL | D6: Drop 1 | E6: Head, Comptrollership | F6: 4 | G6: Template | H6: This workbook, sheet Ref Lists of values | I6: 9-Apr-2027 (T-38 weeks) | K6: Not started
A7: ADJ_RETURN_REASON | B7: Endorsement return reason | C7: Operations | D7: Drop 1 | E7: Head, Operations Services | F7: 6 | G7: Template | H7: This workbook, sheet Ref Lists of values | I7: 9-Apr-2027 (T-38 weeks) | K7: Not started
A8: AR_CLASS | B8: Acknowledgement receipt class | C8: Operations | D8: Drop 1 | E8: Head, Operations Services | F8: 11 | G8: Template | H8: This workbook, sheet Ref Lists of values | I8: 9-Apr-2027 (T-38 weeks) | K8: Not started
A9: BCL_ADJUSTER | B9: Adjuster / appraiser | C9: Claims | D9: Drop 2 | E9: Product Owner, Claims | F9: 25 | G9: Template | H9: This workbook, sheet Ref Lists of values | I9: 9-Apr-2027 (T-38 weeks) | K9: Not started
A10: BCL_CATASTROPHE | B10: Catastrophe code | C10: Claims | D10: Drop 2 | E10: Product Owner, Claims | F10: 7 | G10: Template | H10: This workbook, sheet Ref Lists of values | I10: 9-Apr-2027 (T-38 weeks) | K10: Not started
A11: BCL_CLAIM_STATUS | B11: Claim status | C11: Claims | D11: Drop 2 | E11: Product Owner, Claims | F11: 18 | G11: Template | H11: This workbook, sheet Ref Lists of values | I11: 9-Apr-2027 (T-38 weeks) | K11: Not started
A12: BCL_CLAIM_TYPE | B12: Claim type | C12: Claims | D12: Drop 2 | E12: Product Owner, Claims | F12: 10 | G12: Template | H12: This workbook, sheet Ref Lists of values | I12: 9-Apr-2027 (T-38 weeks) | K12: Not started
A13: BCL_DIARY_TYPE | B13: Claim diary entry type | C13: Claims | D13: Drop 2 | E13: Product Owner, Claims | F13: 5 | G13: Template | H13: This workbook, sheet Ref Lists of values | I13: 9-Apr-2027 (T-38 weeks) | K13: Not started
A14: BCL_DOCUMENT_TYPE | B14: Claim document type | C14: Claims | D14: Drop 2 | E14: Product Owner, Claims | F14: 9 | G14: Template | H14: This workbook, sheet Ref Lists of values | I14: 9-Apr-2027 (T-38 weeks) | K14: Not started
A15: BCL_LOSS_NATURE | B15: Nature of loss | C15: Claims | D15: Drop 2 | E15: Product Owner, Claims | F15: 10 | G15: Template | H15: This workbook, sheet Ref Lists of values | I15: 9-Apr-2027 (T-38 weeks) | K15: Not started
A16: BCL_OVERRIDE_REASON | B16: Claim override reason | C16: Claims | D16: Drop 2 | E16: Product Owner, Claims | F16: 4 | G16: Template | H16: This workbook, sheet Ref Lists of values | I16: 9-Apr-2027 (T-38 weeks) | K16: Not started
... A145: VOID_REASON | B145: Void reason | C145: Operations | D145: Drop 1 | E145: Head, Operations Services | F145: 4 | G145: Template | H145: This workbook, sheet Ref Lists of values | I145: 9-Apr-2027 (T-38 weeks) | K145: Not started

Sheet Ref System parameters
A1: Reference: System parameters
A2: ← Back to Start here | B2: Every system parameter with the value proposed and the value BDOI wants
A4: Parameter | B4: Group | C4: Module | D4: Drop | E4: Owner (BDOI unit) | F4: What it controls | G4: Type | H4: Value proposed | I4: Allowed range | J4: Route | K4: Prepared in | L4: Due | M4: Value wanted | N4: Reason | O4: Approved by | P4: Status | Q4: BDOI comments
A5: BROKING_CLOSE_TIME | B5: Accounting | C5: Accounting, Disbursement and ACSL | D5: Drop 1 | E5: Head, Comptrollership | F5: Time (PHT, HH:MM) at which the broking books are closed on the last day of the month | G5: string | H5: 23:00 | J5: Template | K5: This workbook, sheet Ref System parameters | L5: 16-Jul-2027 (T-24 weeks) | P5: Not started
A6: BROKING_SOURCE_MODULES | B6: Accounting | C6: Accounting, Disbursement and ACSL | D6: Drop 1 | E6: Head, Comptrollership | F6: Source modules of the broking books: their postings are refused once the BROKING books of the period are closed | G6: code list | H6: BOOKING,OPSLEDGER,CASHIERING,REMITTANCE,ADJUSTMENT,COMMISSION,PRODRECON,DISBURSEMENT | J6: Template | K6: This workbook, sheet Ref System parameters | L6: 16-Jul-2027 (T-24 weeks) | P6: Not started
A7: CLOSE_ONLY_PREVIOUS_MONTH | B7: Accounting | C7: Accounting, Disbursement and ACSL | D7: Drop 1 | E7: Head, Comptrollership | F7: Month-end close only for the previous month and year | G7: boolean | H7: true | J7: Template | K7: This workbook, sheet Ref System parameters | L7: 16-Jul-2027 (T-24 weeks) | P7: Not started
A8: EWT_RATE_TOLERANCE | B8: Accounting | C8: Accounting, Disbursement and ACSL | D8: Drop 1 | E8: Head, Comptrollership | F8: Largest difference in percentage points between the withholding rate of a document and the rate of the ATC before the EWT worksheet flags it | G8: decimal | H8: 0.05 | J8: Template | K8: This workbook, sheet Ref System parameters | L8: 16-Jul-2027 (T-24 weeks) | P8: Not started
A9: OPS_BOOK_RATE_SOURCE | B9: Accounting | C9: Accounting, Disbursement and ACSL | D9: Drop 1 | E9: Head, Comptrollership | F9: Source of the Operations BOOK rate: CLOSING_PREV_MONTH copies the revaluation rate of the previous month end, MANUAL keeps it by hand | G9: string | H9: CLOSING_PREV_MONTH | J9: Template | K9: This workbook, sheet Ref System parameters | L9: 16-Jul-2027 (T-24 weeks) | P9: Not started
A10: YEAR_END_CLOSE_DEADLINE | B10: Accounting | C10: Accounting, Disbursement and ACSL | D10: Drop 1 | E10: Head, Comptrollership | F10: Month and day (MM-DD) by which the previous year must be closed; YEAR_END_CLOSE_DUE is raised before | G10: string | H10: 04-15 | J10: Template | K10: This workbook, sheet Ref System parameters | L10: 16-Jul-2027 (T-24 weeks) | P10: Not started
A11: ACSL_SOA_MAX_ROWS | B11: Acsl | C11: Accounting, Disbursement and ACSL | D11: Drop 1 | E11: Head, Comptrollership | F11: Largest number of rows of one insurer statement of account upload | G11: integer | H11: 20000 | I11: 1 to 200000 | J11: Template | K11: This workbook, sheet Ref System parameters | L11: 16-Jul-2027 (T-24 weeks) | P11: Not started
A12: BOOKING_BILLING_NO_LINES | B12: Booking | C12: New Business | D12: Drop 1 | E12: Product Owner, BDOI (New Business) | F12: Product lines whose bookings need the insurer billing number, unique per insurer | G12: code list | H12: HMO,GLI,GPA | J12: Template | K12: This workbook, sheet Ref System parameters | L12: 16-Jul-2027 (T-24 weeks) | P12: Not started
A13: BOOKING_CWT2_SEGMENTS | B13: Booking | C13: New Business | D13: Drop 1 | E13: Product Owner, BDOI (New Business) | F13: Market segments whose corporate clients withhold 2% creditable tax on premium | G13: code list | H13: (blank) | J13: Template | K13: This workbook, sheet Ref System parameters | L13: 16-Jul-2027 (T-24 weeks) | P13: Not started
A14: BOOKING_WTAX_RATE | B14: Booking | C14: New Business | D14: Drop 1 | E14: Product Owner, BDOI (New Business) | F14: Withholding tax rate (percent) the insurer withholds on the broker commission, printed on the booked invoice and service invoice | G14: decimal | H14: 10 | I14: 0 to 100 | J14: Template | K14: This workbook, sheet Ref System parameters | L14: 16-Jul-2027 (T-24 weeks) | P14: Not started
A15: OPS_COMMISSION_REALIZATION | B15: Booking | C15: New Business | D15: Drop 1 | E15: Product Owner, BDOI (New Business) | F15: When broker commission is realized: ON_COLLECTION (unrealized at booking, realized when premium is applied) or ON_BOOKING (commission income and output VAT at booking) | G15: string | H15: ON_COLLECTION | J15: Template | K15: This workbook, sheet Ref System parameters | L15: 16-Jul-2027 (T-24 weeks) | P15: Not started
A16: SERVICE_INVOICE_CREDIT_DAYS | B16: Booking | C16: New Business | D16: Drop 1 | E16: Product Owner, BDOI (New Business) | F16: Credit days printed on a service invoice (payment terms merged into its template) | G16: integer | H16: 30 | I16: 0 to 365 | J16: Template | K16: This workbook, sheet Ref System parameters | L16: 16-Jul-2027 (T-24 weeks) | P16: Not started
A17: CLIENT_CREDIT_DAYS | B17: Broking | C17: New Business | D17: Drop 1 | E17: Product Owner, BDOI (New Business) | F17: Credit days of the accounting party created for a client | G17: integer | H17: 30 | I17: 0 to 365 | J17: Template | K17: This workbook, sheet Ref System parameters | L17: 16-Jul-2027 (T-24 weeks) | P17: Not started
A18: PROPOSAL_NUMBER_PREFIX | B18: Broking | C18: New Business | D18: Drop 1 | E18: Product Owner, BDOI (New Business) | F18: Prefix of the PRF marketing reference (<prefix>-<yyyy>-nnnnnn) | G18: string | H18: PRF | J18: Template | K18: This workbook, sheet Ref Document numbering | L18: 16-Jul-2027 (T-24 weeks) | P18: Not started
A19: PROPOSAL_SLIP_PREFIX | B19: Broking | C19: New Business | D19: Drop 1 | E19: Product Owner, BDOI (New Business) | F19: Prefix of proposal slip numbers (<prefix>-<yyyy>-nnnnnn) | G19: string | H19: PS | J19: Template | K19: This workbook, sheet Ref Document numbering | L19: 16-Jul-2027 (T-24 weeks) | P19: Not started
A20: QUOTATION_EXPIRING_DAYS | B20: Broking | C20: New Business | D20: Drop 1 | E20: Product Owner, BDOI (New Business) | F20: Quotations whose validity ends within this many days are listed as expiring | G20: integer | H20: 7 | I20: 1 to 90 | J20: Template | K20: This workbook, sheet Ref System parameters | L20: 16-Jul-2027 (T-24 weeks) | P20: Not started
A21: QUOTATION_NUMBER_PREFIX | B21: Broking | C21: New Business | D21: Drop 1 | E21: Product Owner, BDOI (New Business) | F21: Prefix of package quotation numbers (<prefix>-<yyyy>-nnnnnn), shown as Proposal No. | G21: string | H21: QT | J21: Template | K21: This workbook, sheet Ref Document numbering | L21: 16-Jul-2027 (T-24 weeks) | P21: Not started
A22: QUOTATION_REQUEST_PREFIX | B22: Broking | C22: New Business | D22: Drop 1 | E22: Product Owner, BDOI (New Business) | F22: Prefix of quotation request numbers (<prefix>-<yyyy>-nnnnnn) | G22: string | H22: REQ | J22: Template | K22: This workbook, sheet Ref Document numbering | L22: 16-Jul-2027 (T-24 weeks) | P22: Not started
A23: QUOTATION_SLIP_PREFIX | B23: Broking | C23: New Business | D23: Drop 1 | E23: Product Owner, BDOI (New Business) | F23: Prefix of quotation slip numbers (<prefix>-<yyyy>-nnnnnn) | G23: string | H23: QS | J23: Template | K23: This workbook, sheet Ref Document numbering | L23: 16-Jul-2027 (T-24 weeks) | P23: Not started
A24: QUOTATION_SLIP_REPLY_DAYS | B24: Broking | C24: New Business | D24: Drop 1 | E24: Product Owner, BDOI (New Business) | F24: Days given to insurers to reply to a quotation slip | G24: integer | H24: 5 | I24: 1 to 60 | J24: Template | K24: This workbook, sheet Ref System parameters | L24: 16-Jul-2027 (T-24 weeks) | P24: Not started
A25: QUOTATION_VALIDITY_DAYS | B25: Broking | C25: New Business | D25: Drop 1 | E25: Product Owner, BDOI (New Business) | F25: Default validity of a quotation in days from its creation | G25: integer | H25: 30 | I25: 1 to 365 | J25: Template | K25: This workbook, sheet Ref System parameters | L25: 16-Jul-2027 (T-24 weeks) | P25: Not started
A26: RATE_EXCEPTION_VALIDITY_DAYS | B26: Broking | C26: New Business | D26: Drop 1 | E26: Product Owner, BDOI (New Business) | F26: Days a rate-scheme exception stays valid when the request gives no end date | G26: integer | H26: 30 | I26: 1 to 3650 | J26: Template | K26: This workbook, sheet Ref System parameters | L26: 16-Jul-2027 (T-24 weeks) | P26: Not started
A27: BULK_MAX_ROWS | B27: Bulk | C27: Platform set-up | D27: Drop 0 | E27: BDOI IT | F27: Maximum number of data rows in one bulk upload file | G27: integer | H27: 5000 | I27: 10 to 50000 | J27: Template | K27: This workbook, sheet Ref System parameters | L27: 16-Jul-2027 (T-24 weeks) | P27: Not started
A28: BCL_AGEING_BUCKETS | B28: Claims Handling | C28: Claims | D28: Drop 2 | E28: Product Owner, Claims | F28: Upper bounds in days of the claims ageing buckets: 0-30, 31-60, 61-90, 91-180, 181+ | G28: integer list | H28: 30,60,90,180 | I28: 1 to 3650 | J28: Template | K28: This workbook, sheet Ref System parameters | L28: 16-Jul-2027 (T-24 weeks) | P28: Not started
A29: BCL_AUTH_DP_POLICY | B29: Claims Handling | C29: Claims | D29: Drop 2 | E29: Product Owner, Claims | F29: Claims authorization code on a direct-payment cover: ALLOW, CONFIRM (insurer payment evidence attached) or BLOCK | G29: string | H29: CONFIRM | J29: Template | K29: This workbook, sheet Ref System parameters | L29: 16-Jul-2027 (T-24 weeks) | P29: Not started
A30: BCL_DEFAULT_CURRENCY | B30: Claims Handling | C30: Claims | D30: Drop 2 | E30: Product Owner, Claims | F30: Currency of a claim whose cover has none | G30: string | H30: PHP | J30: Template | K30: This workbook, sheet Ref System parameters | L30: 16-Jul-2027 (T-24 weeks) | P30: Not started
A31: BCL_FOLLOW_UP_DAYS | B31: Claims Handling | C31: Claims | D31: Drop 2 | E31: Product Owner, Claims | F31: Days from a status change to the next follow-up date when the status has no follow up days attribute | G31: integer | H31: 7 | I31: 1 to 365 | J31: Template | K31: This workbook, sheet Ref System parameters | L31: 16-Jul-2027 (T-24 weeks) | P31: Not started
A32: BCL_PAST_DUE_DAYS | B32: Claims Handling | C32: Claims | D32: Drop 2 | E32: Product Owner, Claims | F32: Age in days above which an outstanding claim is past due: report and alert BCL_CLAIM_PAST_DUE | G32: integer | H32: 90 | I32: 1 to 3650 | J32: Template | K32: This workbook, sheet Ref System parameters | L32: 16-Jul-2027 (T-24 weeks) | P32: Not started
A33: BCL_PRONE_MIN_CLAIMS | B33: Claims Handling | C33: Claims | D33: Drop 2 | E33: Product Owner, Claims | F33: Claims at one location that make it claims-prone | G33: integer | H33: 3 | I33: 1 to 100 | J33: Template | K33: This workbook, sheet Ref System parameters | L33: 16-Jul-2027 (T-24 weeks) | P33: Not started
A34: BCL_PRONE_YEARS | B34: Claims Handling | C34: Claims | D34: Drop 2 | E34: Product Owner, Claims | F34: Look-back years of the claims-prone location analysis | G34: integer | H34: 3 | I34: 1 to 20 | J34: Template | K34: This workbook, sheet Ref System parameters | L34: 16-Jul-2027 (T-24 weeks) | P34: Not started
A35: CLX_AGING_BASIS | B35: Collections | C35: Collections | D35: Drop 1 | E35: VP and Head, BDOI Operations (Collections) | F35: Date the aging of a collection item counts from: BOOKING or INCEPTION | G35: string | H35: BOOKING | J35: Template | K35: This workbook, sheet Ref System parameters | L35: 16-Jul-2027 (T-24 weeks) | P35: Not started
A36: CLX_AGING_BRACKETS | B36: Collections | C36: Collections | D36: Drop 1 | E36: VP and Head, BDOI Operations (Collections) | F36: Aging brackets of the worklist, the home chart and the reports, in days | G36: code list | H36: 0-30,31-45,46-60,61-90,91-120,121+ | J36: Template | K36: This workbook, sheet Ref System parameters | L36: 16-Jul-2027 (T-24 weeks) | P36: Not started
A37: CLX_EDIT_LOCK_MINUTES | B37: Collections | C37: Collections | D37: Drop 1 | E37: VP and Head, BDOI Operations (Collections) | F37: Minutes after which the "<user> is editing" lock of a collection account expires | G37: integer | H37: 15 | I37: 1 to 240 | J37: Template | K37: This workbook, sheet Ref System parameters | L37: 16-Jul-2027 (T-24 weeks) | P37: Not started
A38: CLX_EXPORT_MAX_ROWS | B38: Collections | C38: Collections | D38: Drop 1 | E38: VP and Head, BDOI Operations (Collections) | F38: Maximum rows of an asynchronous Collections export | G38: integer | H38: 50000 | I38: 100 to 1000000 | J38: Template | K38: This workbook, sheet Ref System parameters | L38: 16-Jul-2027 (T-24 weeks) | P38: Not started
A39: CLX_INVOICE_NO_PATTERN | B39: Collections | C39: Collections | D39: Drop 1 | E39: VP and Head, BDOI Operations (Collections) | F39: Regular expression of the invoice number of "For application to invoice": EBIX I######## or BI-... of this system | G39: string | H39: ^(I\d{8}|BI-.+)$ | J39: Template | K39: This workbook, sheet Ref System parameters | L39: 16-Jul-2027 (T-24 weeks) | P39: Not started
A40: CLX_MIN_BALANCE_THRESHOLD | B40: Collections | C40: Collections | D40: Drop 1 | E40: VP and Head, BDOI Operations (Collections) | F40: Net outstanding PR above which an invoice enters the collection worklist | G40: decimal | H40: 10.00 | I40: 0 to 100000 | J40: Template | K40: This workbook, sheet Ref System parameters | L40: 16-Jul-2027 (T-24 weeks) | P40: Not started
A41: CLX_PROMISE_GRACE_DAYS | B41: Collections | C41: Collections | D41: Drop 1 | E41: VP and Head, BDOI Operations (Collections) | F41: Days after the promised date before an unpaid promise to pay is broken | G41: integer | H41: 0 | I41: 0 to 30 | J41: Template | K41: This workbook, sheet Ref System parameters | L41: 16-Jul-2027 (T-24 weeks) | P41: Not started
A42: CONFIG_PROMOTION_MAX_PACKAGE_MB | B42: Config Promotion | C42: Platform set-up | D42: Drop 0 | E42: BDOI IT | F42: Largest configuration package accepted, in megabytes once unpacked | G42: integer | H42: 50 | I42: 1 to 500 | J42: Template | K42: This workbook, sheet Ref System parameters | L42: 16-Jul-2027 (T-24 weeks) | P42: Not started
A43: CONFIG_PROMOTION_NOTIFY | B43: Config Promotion | C43: Platform set-up | D43: Drop 0 | E43: BDOI IT | F43: Permissions whose holders are told when a configuration import waits for approval, is applied, rejected or fails | G43: code list | H43: CONFIG_IMPORT_APPROVE,CONFIG_BASELINE_MANAGE | J43: Template | K43: This workbook, sheet Ref System parameters | L43: 16-Jul-2027 (T-24 weeks) | P43: Not started
A44: CONFIG_PROMOTION_PIPELINE_APPLY | B44: Config Promotion | C44: Platform set-up | D44: Drop 0 | E44: BDOI IT | F44: Outside production only: when true, the deployment pipeline may apply its own dry-run import without a second user; production always needs the approval of a second user | G44: boolean | H44: false | J44: Template | K44: This workbook, sheet Ref System parameters | L44: 16-Jul-2027 (T-24 weeks) | P44: Not started
A45: CONFIG_PROMOTION_PRODUCTION_WINDOW | B45: Config Promotion | C45: Platform set-up | D45: Drop 0 | E45: BDOI IT | F45: Change window in which a configuration package may be applied in production, for example SAT-SUN 20:00-06:00 (days, then the hours; an end before the start runs into the next day); empty = no window, production imports are refused | G45: string | H45: (blank) | J45: Template | K45: This workbook, sheet Ref System parameters | L45: 16-Jul-2027 (T-24 weeks) | P45: Not started
A46: SUSPENSE_ACCOUNT_CODES | B46: Controls | C46: Accounting, Disbursement and ACSL | D46: Drop 1 | E46: Head, Comptrollership | F46: GL account codes monitored by the SUSPENSE_BALANCE exception (blank = accounts named Suspense) | G46: code list | H46: (blank) | J46: Template | K46: This workbook, sheet Ref System parameters | L46: 16-Jul-2027 (T-24 weeks) | P46: Not started
A47: CLIENT_MIN_AGE | B47: Crm | C47: New Business | D47: Drop 1 | E47: Product Owner, BDOI (New Business) | F47: Minimum age in years of an individual policyholder | G47: integer | H47: 18 | I47: 0 to 100 | J47: Template | K47: This workbook, sheet Ref System parameters | L47: 16-Jul-2027 (T-24 weeks) | P47: Not started
A48: CLIENT_MIN_FIELDS_CORPORATE | B48: Crm | C48: New Business | D48: Drop 1 | E48: Product Owner, BDOI (New Business) | F48: Fields a corporate client needs to be complete. Codes: TIN, ID, CONTACT, ADDRESS, MARKET_SEGMENT, SOURCE_OF_FUNDS | G48: code list | H48: TIN,CONTACT,ADDRESS,MARKET_SEGMENT | J48: Template | K48: This workbook, sheet Ref System parameters | L48: 16-Jul-2027 (T-24 weeks) | P48: Not started
A49: CLIENT_MIN_FIELDS_INDIVIDUAL | B49: Crm | C49: New Business | D49: Drop 1 | E49: Product Owner, BDOI (New Business) | F49: Fields an individual client needs to be complete. Codes: BIRTH_DATE, TIN, ID, CONTACT, ADDRESS, MARKET_SEGMENT, NATIONALITY, SOURCE_OF_FUNDS, OCCUPATION | G49: code list | H49: BIRTH_DATE,TIN,ID,CONTACT,ADDRESS,MARKET_SEGMENT | J49: Template | K49: This workbook, sheet Ref System parameters | L49: 16-Jul-2027 (T-24 weeks) | P49: Not started
A50: KYC_DUE_WINDOW_DAYS | B50: Crm | C50: New Business | D50: Drop 1 | E50: Product Owner, BDOI (New Business) | F50: Days ahead in which a KYC review is listed as coming due | G50: integer | H50: 30 | I50: 0 to 365 | J50: Template | K50: This workbook, sheet Ref System parameters | L50: 16-Jul-2027 (T-24 weeks) | P50: Not started
A51: KYC_REVIEW_MONTHS | B51: Crm | C51: New Business | D51: Drop 1 | E51: Product Owner, BDOI (New Business) | F51: Months between periodic KYC reviews of standard and low risk clients | G51: integer | H51: 36 | I51: 1 to 120 | J51: Template | K51: This workbook, sheet Ref System parameters | L51: 16-Jul-2027 (T-24 weeks) | P51: Not started
A52: KYC_REVIEW_MONTHS_HIGH_RISK | B52: Crm | C52: New Business | D52: Drop 1 | E52: Product Owner, BDOI (New Business) | F52: Months between periodic KYC reviews of high risk clients | G52: integer | H52: 12 | I52: 1 to 120 | J52: Template | K52: This workbook, sheet Ref System parameters | L52: 16-Jul-2027 (T-24 weeks) | P52: Not started
A53: CSF_LEGACY_SYNC_ENABLED | B53: Customer Service | C53: Customer Servicing Facility | D53: Drop 1 | E53: Product Owner, Customer Servicing Facility | F53: Send contact changes to the legacy policy systems while they are still in use | G53: boolean | H53: false | J53: Template | K53: This workbook, sheet Ref System parameters | L53: 16-Jul-2027 (T-24 weeks) | P53: Not started
A54: CSF_PAYMENT_HISTORY_MONTHS | B54: Customer Service | C54: Customer Servicing Facility | D54: Drop 1 | E54: Product Owner, Customer Servicing Facility | F54: Months of payment history the contact centre sees before Show Older | G54: integer | H54: 12 | I54: 1 to 120 | J54: Template | K54: This workbook, sheet Ref System parameters | L54: 16-Jul-2027 (T-24 weeks) | P54: Not started
A55: CSF_SEARCH_MAX_RESULTS | B55: Customer Service | C55: Customer Servicing Facility | D55: Drop 1 | E55: Product Owner, Customer Servicing Facility | F55: Maximum clients a customer search returns before the contact centre officer must refine it | G55: integer | H55: 50 | I55: 5 to 500 | J55: Template | K55: This workbook, sheet Ref System parameters | L55: 16-Jul-2027 (T-24 weeks) | P55: Not started
A56: CSF_SEARCH_MIN_CHARS | B56: Customer Service | C56: Customer Servicing Facility | D56: Drop 1 | E56: Product Owner, Customer Servicing Facility | F56: Minimum characters of a client name search | G56: integer | H56: 3 | I56: 1 to 20 | J56: Template | K56: This workbook, sheet Ref System parameters | L56: 16-Jul-2027 (T-24 weeks) | P56: Not started
A57: CSF_VERIFICATION_VALID_MINUTES | B57: Customer Service | C57: Customer Servicing Facility | D57: Drop 1 | E57: Product Owner, Customer Servicing Facility | F57: Minutes a passed verification of a caller stays valid for a change | G57: integer | H57: 30 | I57: 1 to 480 | J57: Template | K57: This workbook, sheet Ref System parameters | L57: 16-Jul-2027 (T-24 weeks) | P57: Not started
A58: CSF_VERIFY_MAX_FAILS | B58: Customer Service | C58: Customer Servicing Facility | D58: Drop 1 | E58: Product Owner, Customer Servicing Facility | F58: Failed verifications of one client in a day that raise an alert to the supervisors | G58: integer | H58: 3 | I58: 1 to 20 | J58: Template | K58: This workbook, sheet Ref System parameters | L58: 16-Jul-2027 (T-24 weeks) | P58: Not started
A59: CSF_VERIFY_MIN_MATCHES | B59: Customer Service | C59: Customer Servicing Facility | D59: Drop 1 | E59: Product Owner, Customer Servicing Facility | F59: Verification checks that must match before the contact details of a client can be changed | G59: integer | H59: 2 | I59: 1 to 10 | J59: Template | K59: This workbook, sheet Ref System parameters | L59: 16-Jul-2027 (T-24 weeks) | P59: Not started
A60: INSURER_DEFAULT_CREDIT_DAYS | B60: Data Migration | C60: Data Migration | D60: Drop 0 | E60: Program Manager, Business Project Services (Data Migration) | F60: Credit days of an insurer loaded by data migration without credit days | G60: integer | H60: 30 | I60: 0 to 365 | J60: Template | K60: This workbook, sheet Ref System parameters | L60: 16-Jul-2027 (T-24 weeks) | P60: Not started
A61: MIG_ACCESS_EXPORT_ALERT_ROWS | B61: Data Migration | C61: Data Migration | D61: Drop 0 | E61: Program Manager, Business Project Services (Data Migration) | F61: Archive records exported by one user in a day above which the unusual-access alert is raised | G61: integer | H61: 5000 | I61: 1 to 1000000 | J61: Template | K61: This workbook, sheet Ref System parameters | L61: 16-Jul-2027 (T-24 weeks) | P61: Not started
A62: MIG_AMOUNT_TOLERANCE | B62: Data Migration | C62: Data Migration | D62: Drop 0 | E62: Program Manager, Business Project Services (Data Migration) | F62: Largest amount difference accepted by the amount reconciliation | G62: decimal | H62: 0.00 | J62: Template | K62: This workbook, sheet Ref System parameters | L62: 16-Jul-2027 (T-24 weeks) | P62: Not started
A63: MIG_ARCHIVE_EXPORT_MAX_ROWS | B63: Data Migration | C63: Data Migration | D63: Drop 0 | E63: Program Manager, Business Project Services (Data Migration) | F63: Largest number of archive records exported to Excel at a time | G63: integer | H63: 1000 | I63: 1 to 100000 | J63: Template | K63: This workbook, sheet Ref System parameters | L63: 16-Jul-2027 (T-24 weeks) | P63: Not started
A64: MIG_CHUNK_SIZE | B64: Data Migration | C64: Data Migration | D64: Drop 0 | E64: Program Manager, Business Project Services (Data Migration) | F64: Rows loaded per transaction | G64: integer | H64: 500 | I64: 10 to 5000 | J64: Template | K64: This workbook, sheet Ref System parameters | L64: 16-Jul-2027 (T-24 weeks) | P64: Not started
A65: MIG_CLIENT_MATCH_AUTO | B65: Data Migration | C65: Data Migration | D65: Drop 0 | E65: Program Manager, Business Project Services (Data Migration) | F65: Client match score from which two legacy clients are merged automatically | G65: integer | H65: 90 | I65: 60 to 100 | J65: Template | K65: This workbook, sheet Ref System parameters | L65: 16-Jul-2027 (T-24 weeks) | P65: Not started
A66: MIG_CLIENT_MATCH_REVIEW | B66: Data Migration | C66: Data Migration | D66: Drop 0 | E66: Program Manager, Business Project Services (Data Migration) | F66: Client match score from which a pair goes to the Data Steward review queue | G66: integer | H66: 60 | I66: 1 to 100 | J66: Template | K66: This workbook, sheet Ref System parameters | L66: 16-Jul-2027 (T-24 weeks) | P66: Not started
A67: MIG_CUTOVER_DATE | B67: Data Migration | C67: Data Migration | D67: Drop 0 | E67: Program Manager, Business Project Services (Data Migration) | F67: Go-live date (yyyy-MM-dd); the first business day on BIBS | G67: string | H67: 2028-01-03 | J67: Template | K67: This workbook, sheet Ref System parameters | L67: 16-Jul-2027 (T-24 weeks) | P67: Not started
A68: MIG_ENVIRONMENT_CLASS | B68: Data Migration | C68: Data Migration | D68: Drop 0 | E68: Program Manager, Business Project Services (Data Migration) | F68: PRODUCTION or NON_PRODUCTION; outside production personal data of the extracts is masked before staging | G68: string | H68: NON_PRODUCTION | J68: Template | K68: This workbook, sheet Ref System parameters | L68: 16-Jul-2027 (T-24 weeks) | P68: Not started
A69: MIG_FREEZE_AT | B69: Data Migration | C69: Data Migration | D69: Drop 0 | E69: Program Manager, Business Project Services (Data Migration) | F69: Start of the legacy business freeze (yyyy-MM-dd HH:mm, Philippine time) | G69: string | H69: 2027-12-31 22:00 | J69: Template | K69: This workbook, sheet Ref System parameters | L69: 16-Jul-2027 (T-24 weeks) | P69: Not started
A70: MIG_GOLIVE_RENEWAL_TO | B70: Data Migration | C70: Data Migration | D70: Drop 0 | E70: Program Manager, Business Project Services (Data Migration) | F70: Last expiry date of the migrated policies taken over by Renewal at go-live (yyyy-MM-dd) | G70: string | H70: 2028-05-31 | J70: Template | K70: This workbook, sheet Ref System parameters | L70: 16-Jul-2027 (T-24 weeks) | P70: Not started
A71: MIG_INVOICE_NO_COLLISION_PREFIX | B71: Data Migration | C71: Data Migration | D71: Drop 0 | E71: Program Manager, Business Project Services (Data Migration) | F71: Prefix the source system to a legacy invoice number found in two source systems | G71: boolean | H71: true | J71: Template | K71: This workbook, sheet Ref Document numbering | L71: 16-Jul-2027 (T-24 weeks) | P71: Not started
A72: MIG_LAST_LEGACY_BUSINESS_DAY | B72: Data Migration | C72: Data Migration | D72: Drop 0 | E72: Program Manager, Business Project Services (Data Migration) | F72: Last business day processed in the legacy systems (yyyy-MM-dd) | G72: string | H72: 2027-12-29 | J72: Template | K72: This workbook, sheet Ref System parameters | L72: 16-Jul-2027 (T-24 weeks) | P72: Not started
A73: MIG_LEGACY_ACCESS_REASON_REQUIRED | B73: Data Migration | C73: Data Migration | D73: Drop 0 | E73: Program Manager, Business Project Services (Data Migration) | F73: A reason is required before the legacy archive is searched | G73: boolean | H73: true | J73: Template | K73: This workbook, sheet Ref System parameters | L73: 16-Jul-2027 (T-24 weeks) | P73: Not started
A74: MIG_LEGACY_INVOICE_NO_PATTERN | B74: Data Migration | C74: Data Migration | D74: Drop 0 | E74: Program Manager, Business Project Services (Data Migration) | F74: Patterns of legacy invoice numbers recognised by the payment matcher (comma separated regular expressions) | G74: string | H74: ^I\d{8}$ | J74: Template | K74: This workbook, sheet Ref System parameters | L74: 16-Jul-2027 (T-24 weeks) | P74: Not started
A75: MIG_LEGACY_LINK_EBIX | B75: Data Migration | C75: Data Migration | D75: Drop 0 | E75: Program Manager, Business Project Services (Data Migration) | F75: Address of the read-only EBIX application for users who still need it | G75: string | H75: (blank) | J75: Template | K75: This workbook, sheet Ref System parameters | L75: 16-Jul-2027 (T-24 weeks) | P75: Not started
A76: MIG_LEGACY_LINK_QPS | B76: Data Migration | C76: Data Migration | D76: Drop 0 | E76: Program Manager, Business Project Services (Data Migration) | F76: Address of the read-only QPS application for users who still need it | G76: string | H76: (blank) | J76: Template | K76: This workbook, sheet Ref System parameters | L76: 16-Jul-2027 (T-24 weeks) | P76: Not started
A77: MIG_MAX_ERROR_RATE_FINANCIAL | B77: Data Migration | C77: Data Migration | D77: Drop 0 | E77: Program Manager, Business Project Services (Data Migration) | F77: Largest percentage of failing or waived rows with which open items, unapplied payments and the trial balance may be loaded | G77: decimal | H77: 0 | J77: Template | K77: This workbook, sheet Ref System parameters | L77: 16-Jul-2027 (T-24 weeks) | P77: Not started
A78: MIG_MAX_ERROR_RATE_MASTER | B78: Data Migration | C78: Data Migration | D78: Drop 0 | E78: Program Manager, Business Project Services (Data Migration) | F78: Largest percentage of failing or waived rows with which master data may be loaded | G78: decimal | H78: 0.5 | J78: Template | K78: This workbook, sheet Ref System parameters | L78: 16-Jul-2027 (T-24 weeks) | P78: Not started
A79: MIG_OPENING_VALUE_DATE | B79: Data Migration | C79: Data Migration | D79: Drop 0 | E79: Program Manager, Business Project Services (Data Migration) | F79: Value date of the opening entries and of the opening-balance adjustments (yyyy-MM-dd) | G79: string | H79: 2028-01-01 | J79: Template | K79: This workbook, sheet Ref System parameters | L79: 16-Jul-2027 (T-24 weeks) | P79: Not started
A80: MIG_PARTITIONS | B80: Data Migration | C80: Data Migration | D80: Drop 0 | E80: Program Manager, Business Project Services (Data Migration) | F80: Partitions loaded in parallel | G80: integer | H80: 4 | I80: 1 to 16 | J80: Template | K80: This workbook, sheet Ref System parameters | L80: 16-Jul-2027 (T-24 weeks) | P80: Not started
A81: MIG_RA_MAX_LEAD_DAYS | B81: Data Migration | C81: Data Migration | D81: Drop 0 | E81: Program Manager, Business Project Services (Data Migration) | F81: An advice already sent more than this number of days before expiry is loaded with a warning | G81: integer | H81: 140 | I81: 1 to 365 | J81: Template | K81: This workbook, sheet Ref System parameters | L81: 16-Jul-2027 (T-24 weeks) | P81: Not started
A82: MIG_RENEWAL_URGENT_TO | B82: Data Migration | C82: Data Migration | D82: Drop 0 | E82: Program Manager, Business Project Services (Data Migration) | F82: Migrated policies expiring up to this date are flagged urgent in the go-live renewal queue (yyyy-MM-dd) | G82: string | H82: 2028-01-31 | J82: Template | K82: This workbook, sheet Ref System parameters | L82: 16-Jul-2027 (T-24 weeks) | P82: Not started
A83: MIG_RESUBMIT_DEADLINE | B83: Data Migration | C83: Data Migration | D83: Drop 0 | E83: Program Manager, Business Project Services (Data Migration) | F83: Last time a corrected resubmission of the advices already sent may be approved (yyyy-MM-dd HH:mm, Philippine time) | G83: string | H83: 2028-01-02 12:00 | J83: Template | K83: This workbook, sheet Ref System parameters | L83: 16-Jul-2027 (T-24 weeks) | P83: Not started
A84: MIG_STAGING_RETENTION_DAYS | B84: Data Migration | C84: Data Migration | D84: Drop 0 | E84: Program Manager, Business Project Services (Data Migration) | F84: Days staging data and extract files are kept after the batch is signed off or rolled back | G84: integer | H84: 5 | I84: 1 to 5 | J84: Template | K84: This workbook, sheet Ref System parameters | L84: 16-Jul-2027 (T-24 weeks) | P84: Not started
A85: MIG_UPP_ISSUE_AR | B85: Data Migration | C85: Data Migration | D85: Drop 0 | E85: Program Manager, Business Project Services (Data Migration) | F85: Issue a BIBS acknowledgement receipt for each migrated unapplied payment (no cash posting) | G85: boolean | H85: false | J85: Template | K85: This workbook, sheet Ref System parameters | L85: 16-Jul-2027 (T-24 weeks) | P85: Not started
A86: MIG_YEAR_END_OPTION | B86: Data Migration | C86: Data Migration | D86: Drop 0 | E86: Program Manager, Business Project Services (Data Migration) | F86: Year-end cut-over option: A = provisional opening trial balance at the year-end boundary with controlled true-ups | G86: string | H86: A | J86: Template | K86: This workbook, sheet Ref System parameters | L86: 16-Jul-2027 (T-24 weeks) | P86: Not started
A87: DISB_AUTO_APPROVER_ROUTING | B87: Disbursement | C87: Accounting, Disbursement and ACSL | D87: Drop 1 | E87: Head, Comptrollership | F87: Request types whose disbursement voucher is prepared automatically and routed straight to the approver | G87: code list | H87: REFUND,REMITTANCE | J87: Template | K87: This workbook, sheet Ref System parameters | L87: 16-Jul-2027 (T-24 weeks) | P87: Not started
A88: DISB_CHECK_CLEARING | B88: Disbursement | C88: Accounting, Disbursement and ACSL | D88: Drop 1 | E88: Head, Comptrollership | F88: ON: issued checks are credited to checks outstanding until negotiated; OFF: to the bank at approval | G88: string | H88: ON | J88: Template | K88: This workbook, sheet Ref System parameters | L88: 16-Jul-2027 (T-24 weeks) | P88: Not started
A89: DISB_CHECK_CLEARING_ACCOUNT | B89: Disbursement | C89: Accounting, Disbursement and ACSL | D89: Drop 1 | E89: Head, Comptrollership | F89: Checks outstanding clearing account credited for issued checks while DISB_CHECK_CLEARING = ON | G89: string | H89: 2241 | J89: Template | K89: This workbook, sheet Ref System parameters | L89: 16-Jul-2027 (T-24 weeks) | P89: Not started
A90: DISB_CHECK_SERIES_WARNING | B90: Disbursement | C90: Accounting, Disbursement and ACSL | D90: Drop 1 | E90: Head, Comptrollership | F90: Remaining check leaves of a paying account at which CHECK_SERIES_LOW is raised | G90: integer | H90: 20 | I90: 1 to 1000 | J90: Template | K90: This workbook, sheet Ref System parameters | L90: 16-Jul-2027 (T-24 weeks) | P90: Not started
A91: DISB_NO_PAYEE_ACTION | B91: Disbursement | C91: Accounting, Disbursement and ACSL | D91: Drop 1 | E91: Head, Comptrollership | F91: Gateway request whose payee is not maintained: HOLD keeps it as NO_PAYEE, raises DISB_PAYEE_NO_MATCH and a payee request and resumes it once the payee is authorised; RETURN returns it at once to its source | G91: string | H91: HOLD | J91: Template | K91: This workbook, sheet Ref System parameters | L91: 16-Jul-2027 (T-24 weeks) | P91: Not started
A92: DISB_STALE_DAYS | B92: Disbursement | C92: Accounting, Disbursement and ACSL | D92: Drop 1 | E92: Head, Comptrollership | F92: Days after the print date at which a printed or released check becomes stale | G92: integer | H92: 180 | I92: 30 to 720 | J92: Template | K92: This workbook, sheet Ref System parameters | L92: 16-Jul-2027 (T-24 weeks) | P92: Not started
A93: EARLY_INCENTIVE_WTAX_RATE | B93: Disbursement | C93: Accounting, Disbursement and ACSL | D93: Drop 1 | E93: Head, Comptrollership | F93: Withholding tax rate (percent) of the early-incentive service invoice | G93: decimal | H93: 2 | I93: 0 to 100 | J93: Template | K93: This workbook, sheet Ref System parameters | L93: 16-Jul-2027 (T-24 weeks) | P93: Not started
A94: EB_ADJ_BOOKING_REQUIRES_PAYMENT | B94: Employee Benefits | C94: Employee Benefits | D94: Drop 2 | E94: Product Owner, Employee Benefits | F94: Raise the endorsement request of a member change only after its billing is paid | G94: boolean | H94: false | J94: Template | K94: This workbook, sheet Ref System parameters | L94: 16-Jul-2027 (T-24 weeks) | P94: Not started
A95: EB_COMPARATIVE_DAYS | B95: Employee Benefits | C95: Employee Benefits | D95: Drop 2 | E95: Product Owner, Employee Benefits | F95: Working days from the last proposal to the comparative sent to the client | G95: integer | H95: 3 | I95: 1 to 30 | J95: Template | K95: This workbook, sheet Ref System parameters | L95: 16-Jul-2027 (T-24 weeks) | P95: Not started
A96: EB_FOLLOWUP_DAYS | B96: Employee Benefits | C96: Employee Benefits | D96: Drop 2 | E96: Product Owner, Employee Benefits | F96: Working days between follow-ups of a pending tracked item | G96: integer | H96: 5 | I96: 1 to 60 | J96: Template | K96: This workbook, sheet Ref System parameters | L96: 16-Jul-2027 (T-24 weeks) | P96: Not started
A97: EB_FOLLOWUP_MAX | B97: Employee Benefits | C97: Employee Benefits | D97: Drop 2 | E97: Product Owner, Employee Benefits | F97: Follow-ups sent before a tracked item is escalated | G97: integer | H97: 3 | I97: 1 to 20 | J97: Template | K97: This workbook, sheet Ref System parameters | L97: 16-Jul-2027 (T-24 weeks) | P97: Not started
A98: EB_FRANCHISE_ADVICE_DAYS | B98: Employee Benefits | C98: Employee Benefits | D98: Drop 2 | E98: Product Owner, Employee Benefits | F98: Working days to advise the client of the franchise outcome | G98: integer | H98: 2 | I98: 1 to 30 | J98: Template | K98: This workbook, sheet Ref System parameters | L98: 16-Jul-2027 (T-24 weeks) | P98: Not started
A99: EB_FRANCHISE_GRACE_DAYS | B99: Employee Benefits | C99: Employee Benefits | D99: Drop 2 | E99: Product Owner, Employee Benefits | F99: Working days after the franchise decision date before an undecided franchise request expires | G99: integer | H99: 2 | I99: 0 to 30 | J99: Template | K99: This workbook, sheet Ref System parameters | L99: 16-Jul-2027 (T-24 weeks) | P99: Not started
A100: EB_FRANCHISE_TAT_DAYS | B100: Employee Benefits | C100: Employee Benefits | D100: Drop 2 | E100: Product Owner, Employee Benefits | F100: Working days for the insurer franchise decision | G100: integer | H100: 5 | I100: 1 to 60 | J100: Template | K100: This workbook, sheet Ref System parameters | L100: 16-Jul-2027 (T-24 weeks) | P100: Not started
A101: EB_PROPOSAL_REPLY_DAYS | B101: Employee Benefits | C101: Employee Benefits | D101: Drop 2 | E101: Product Owner, Employee Benefits | F101: Working days an insurer has to answer a request for proposal | G101: integer | H101: 5 | I101: 1 to 60 | J101: Template | K101: This workbook, sheet Ref System parameters | L101: 16-Jul-2027 (T-24 weeks) | P101: Not started
...

Sheet Ref Document numbering
A1: Reference: Document numbering
A2: ← Back to Start here | B2: Prefixes of the numbered documents; receipt series come from object R11, check numbers from D0-12
A4: Parameter | B4: Module | C4: Numbered document | D4: Prefix proposed | E4: Prepared in | F4: Owner (BDOI unit) | G4: Prefix wanted | H4: Status | I4: BDOI comments
A5: PROPOSAL_NUMBER_PREFIX | B5: New Business | C5: Prefix of the PRF marketing reference (<prefix>-<yyyy>-nnnnnn) | D5: PRF | E5: This workbook, sheet Ref Document numbering | F5: Product Owner, BDOI (New Business) | H5: Not started
A6: PROPOSAL_SLIP_PREFIX | B6: New Business | C6: Prefix of proposal slip numbers (<prefix>-<yyyy>-nnnnnn) | D6: PS | E6: This workbook, sheet Ref Document numbering | F6: Product Owner, BDOI (New Business) | H6: Not started
A7: QUOTATION_NUMBER_PREFIX | B7: New Business | C7: Prefix of package quotation numbers (<prefix>-<yyyy>-nnnnnn), shown as Proposal No. | D7: QT | E7: This workbook, sheet Ref Document numbering | F7: Product Owner, BDOI (New Business) | H7: Not started
A8: QUOTATION_REQUEST_PREFIX | B8: New Business | C8: Prefix of quotation request numbers (<prefix>-<yyyy>-nnnnnn) | D8: REQ | E8: This workbook, sheet Ref Document numbering | F8: Product Owner, BDOI (New Business) | H8: Not started
A9: QUOTATION_SLIP_PREFIX | B9: New Business | C9: Prefix of quotation slip numbers (<prefix>-<yyyy>-nnnnnn) | D9: QS | E9: This workbook, sheet Ref Document numbering | F9: Product Owner, BDOI (New Business) | H9: Not started
A10: MIG_INVOICE_NO_COLLISION_PREFIX | B10: Data Migration | C10: Prefix the source system to a legacy invoice number found in two source systems | D10: true | E10: This workbook, sheet Ref Document numbering | F10: Program Manager, Business Project Services (Data Migration) | H10: Not started
A11: PKG_DEACTIVATION_PREFIX | B11: Product Maintenance | C11: Prefix of package deactivation request numbers; the year is appended | D11: PKD- | E11: BRD-03 template CI-09, sheet PM-09 Lists and parameters | F11: Product Owner, Marketing Business System (MBS) | H11: Not started
A12: PKG_DEPLOYMENT_PREFIX | B12: Product Maintenance | C12: Prefix of package deployment request numbers; the year is appended | D12: PDR- | E12: BRD-03 template CI-09, sheet PM-09 Lists and parameters | F12: Product Owner, Marketing Business System (MBS) | H12: Not started
A13: PKG_QS_PREFIX | B13: Product Maintenance | C13: Prefix of package quotation slip numbers; the year is appended | D13: PQS- | E13: BRD-03 template CI-09, sheet PM-09 Lists and parameters | F13: Product Owner, Marketing Business System (MBS) | H13: Not started
A14: PKG_REQUEST_PREFIX | B14: Product Maintenance | C14: Prefix of package request numbers; the year is appended | D14: PKR- | E14: BRD-03 template CI-09, sheet PM-09 Lists and parameters | F14: Product Owner, Marketing Business System (MBS) | H14: Not started
A15: RNW_REFERENCE_PREFIX | B15: Renewal | C15: Prefix of the renewal reference (prefix-yyyy-nnnnnn) | D15: RNW | E15: This workbook, sheet Ref Document numbering | F15: Product Owner, Renewal | H15: Not started
A16: SCR_CASE_SEQUENCE_PREFIX | B16: Sanction Screening | C16: Prefix of the screening case number <prefix>-yyyy-nnnnnn | D16: SCR | E16: This workbook, sheet Ref Document numbering | F16: Compliance | H16: Not started
A17: SBM_NUMBER_PREFIX | B17: Submitted Policies | C17: Prefix of the masterlist number (prefix-yyyy-nnnnnn) | D17: SBM | E17: This workbook, sheet Ref Document numbering | F17: Product Owner, Submitted Policies | H17: Not started

Sheet Ref Notifications
A1: Reference: Notifications
A2: ← Back to Start here | B2: Every notification event with its default channels; users choose their own channels in Notification Settings
A4: Event | B4: Name | C4: Module | D4: Drop | E4: Owner (BDOI unit) | F4: Who is told and when | G4: In-app proposed | H4: E-mail proposed | I4: In-app wanted | J4: E-mail wanted | K4: Unit mailbox | L4: Status | M4: BDOI comments
A5: ACSL_CASE_STATUS | B5: ACSL case or correction status | C5: Accounting, Disbursement and ACSL | D5: Drop 1 | E5: Head, Comptrollership | F5: An ACSL case you requested has a result, or a correction entry you prepared was returned, approved or posted | G5: Y | H5: N | L5: Not started
A6: ACSL_GLSL_DIFFERENCE | B6: GL-SL difference found | C6: Accounting, Disbursement and ACSL | D6: Drop 1 | E6: Head, Comptrollership | F6: The GL-SL reconciliation found a control account whose sub-ledger differs from the general ledger | G6: Y | H6: Y | L6: Not started
A7: ADJ_REQUEST_STATUS | B7: Endorsement request status | C7: Operations | D7: Drop 1 | E7: Head, Operations Services | F7: An endorsement request you raised was returned, approved or posted | G7: Y | H7: N | L7: Not started
A8: BOOKING_BILLING_BOOKED | B8: Booked with billing number | C8: New Business | D8: Drop 1 | E8: Product Owner, BDOI (New Business) | F8: An account was booked with its insurer billing number | G8: Y | H8: N | L8: Not started
A9: BOOKING_BILLING_DUPLICATE | B9: Duplicate billing number | C9: New Business | D9: Drop 1 | E9: Product Owner, BDOI (New Business) | F9: A booking was refused because the insurer billing number is already on an invoice | G9: Y | H9: Y | L9: Not started
A10: CASH_APPROVAL_REQUEST | B10: Cashiering approval request | C10: Operations | D10: Drop 1 | E10: Head, Operations Services | F10: A receipt cancellation, reinstatement or disposition waits for approval | G10: Y | H10: N | L10: Not started
A11: CASH_RECORD_FOR_POSTING | B11: Cashiering record for posting | C11: Operations | D11: Drop 1 | E11: Head, Operations Services | F11: An AR / OR creation, cancellation or reinstatement record was submitted for posting | G11: Y | H11: N | L11: Not started
A12: CASH_RECORD_DECIDED | B12: Cashiering record returned or posted | C12: Operations | D12: Drop 1 | E12: Head, Operations Services | F12: An AR / OR record you created was returned with a reason or posted | G12: Y | H12: N | L12: Not started
A13: CASH_FORM_FOR_APPROVAL | B13: Receipt form for approval | C13: Operations | D13: Drop 1 | E13: Head, Operations Services | F13: A change of the AR or OR form waits for the approval of another authorised user | G13: Y | H13: N | L13: Not started
A14: BCL_FOLLOW_UP_DUE | B14: Claim follow-up due | C14: Claims | D14: Drop 2 | E14: Product Owner, Claims | F14: A claim of yours has its next follow-up or a diary entry due today | G14: Y | H14: N | L14: Not started
A15: BCL_CLAIM_ASSIGNED | B15: Claim assigned | C15: Claims | D15: Drop 2 | E15: Product Owner, Claims | F15: A claim was assigned or re-assigned to you | G15: Y | H15: Y | L15: Not started
A16: BCL_STATUS_CHANGED | B16: Claim status changed | C16: Claims | D16: Drop 2 | E16: Product Owner, Claims | F16: The status of a claim of one of your accounts changed | G16: Y | H16: N | L16: Not started
... A118: MFA_RESET_DONE | B118: Second factor reset | C118: User Access Maintenance | D118: Drop 0 | E118: Business Administration (User Access) | F118: Your authenticator app was reset by the administrators; enrol it again at your next sign-in | G118: Y | H118: Y | L118: Not started

Sheet Ref Document templates
A1: Reference: Document templates
A2: ← Back to Start here | B2: Every generated document with the unit that gives its BDOI wording and layout
A4: Template | B4: Title | C4: Module | D4: Drop | E4: Owner (BDOI unit) | F4: Merge fields available | G4: Prepared in | H4: Due | I4: BDOI layout attached | J4: Status | K4: BDOI comments
A5: BCL_LOSS_ADVICE | B5: Loss advice {{claimNo}} - {{assuredName}} | C5: Claims | D5: Drop 2 | E5: Product Owner, Claims | F5: adjusterName, arn, assuredName, claimNo, currency, handlerName, initialReserve, insurerClaimNos, insurerName, lossDate, lossDescription, lossNature, lossPlace, policyNo, policyYear | G5: This workbook, sheet Ref Document templates | H5: 16-Jul-2027 (T-24 weeks) | J5: Not started
A6: CLX_SOA | B6: Statement of account | C6: Collections | D6: Drop 1 | E6: VP and Head, BDOI Operations (Collections) | F6: arn, balance, currency, cycleFrom, cycleTo, dueDate, frequency | G6: This workbook, sheet Ref Document templates | H6: 16-Jul-2027 (T-24 weeks) | J6: Not started
A7: DSB_ATD | B7: Authority to debit | C7: Accounting, Disbursement and ACSL | D7: Drop 1 | E7: Head, Comptrollership | F7: bankAccountNo, bankName, currency, dvNo, netAmount, payeeAccountNo, payeeName, valueDate | G7: This workbook, sheet Ref Document templates | H7: 16-Jul-2027 (T-24 weeks) | J7: Not started
A8: DSB_ATD_EMAIL | B8: Authority to debit {{dvNo}} | C8: Accounting, Disbursement and ACSL | D8: Drop 1 | E8: Head, Comptrollership | F8: currency, dvNo, instrumentNo, netAmount, payeeName | G8: This workbook, sheet Ref Document templates | H8: 16-Jul-2027 (T-24 weeks) | J8: Not started
A9: DSB_CHECK | B9: Check | C9: Accounting, Disbursement and ACSL | D9: Drop 1 | E9: Head, Comptrollership | F9: bankAccountNo, bankName, currency, dvNo, instrumentNo, netAmount, payeeName, printDate | G9: This workbook, sheet Ref Document templates | H9: 16-Jul-2027 (T-24 weeks) | J9: Not started
A10: DSB_CREDIT_TICKET | B10: Credit ticket | C10: Accounting, Disbursement and ACSL | D10: Drop 1 | E10: Head, Comptrollership | F10: bankAccountNo, bankName, currency, dvNo, netAmount, payeeAccountNo, payeeName | G10: This workbook, sheet Ref Document templates | H10: 16-Jul-2027 (T-24 weeks) | J10: Not started
A11: DSB_MC_DD | B11: Manager's check / demand draft request | C11: Accounting, Disbursement and ACSL | D11: Drop 1 | E11: Head, Comptrollership | F11: bankAccountNo, bankName, currency, dvNo, netAmount, payeeName | G11: This workbook, sheet Ref Document templates | H11: 16-Jul-2027 (T-24 weeks) | J11: Not started
A12: DSB_PAYMENT_ADVICE | B12: Payment advice {{dvNo}} | C12: Accounting, Disbursement and ACSL | D12: Drop 1 | E12: Head, Comptrollership | F12: currency, dvNo, instrumentText, mode, netAmount, payeeName, valueDate | G12: This workbook, sheet Ref Document templates | H12: 16-Jul-2027 (T-24 weeks) | J12: Not started
A13: DSB_TT | B13: Telegraphic transfer | C13: Accounting, Disbursement and ACSL | D13: Drop 1 | E13: Head, Comptrollership | F13: bankAccountNo, bankName, currency, dvNo, netAmount, payeeAccountNo, payeeBank, payeeName | G13: This workbook, sheet Ref Document templates | H13: 16-Jul-2027 (T-24 weeks) | J13: Not started
A14: DSB_VOUCHER | B14: Disbursement voucher | C14: Accounting, Disbursement and ACSL | D14: Drop 1 | E14: Head, Comptrollership | F14: currency, dvNo, mode, netAmount, payeeName, purpose, requestNo | G14: This workbook, sheet Ref Document templates | H14: 16-Jul-2027 (T-24 weeks) | J14: Not started
A15: EB_COMPARATIVE | B15: Comparative analysis - {{programmeName}} ({{policyYear}}) | C15: Employee Benefits | D15: Drop 2 | E15: Product Owner, Employee Benefits | F15: aoName, comparativeNo, contactName, programmeName | G15: This workbook, sheet Ref Document templates | H15: 16-Jul-2027 (T-24 weeks) | J15: Not started
A16: EB_FRANCHISE_ADVICE | B16: Franchise outcome - {{programmeName}} | C16: Employee Benefits | D16: Drop 2 | E16: Product Owner, Employee Benefits | F16: aoName, contactName, insurerName, outcome, programmeName, reasonText | G16: This workbook, sheet Ref Document templates | H16: 16-Jul-2027 (T-24 weeks) | J16: Not started
... A45: QUOTATION_SLIP | B45: Quotation slip | C45: New Business | D45: Drop 1 | E45: Product Owner, BDOI (New Business) | F45: reference, replyBy | G45: This workbook, sheet Ref Document templates | H45: 16-Jul-2027 (T-24 weeks) | J45: Not started
A46: QUOTATION_TERMS | B46: Terms and conditions | C46: New Business | D46: Drop 1 | E46: Product Owner, BDOI (New Business) | G46: This workbook, sheet Ref Document templates | H46: 16-Jul-2027 (T-24 weeks) | J46: Not started
A47: REMITTANCE_PAYMENT_REQUEST | B47: Payment request | C47: Operations | D47: Drop 1 | E47: Head, Operations Services | F47: amount, approvedBy, currency, insurerName, reference | G47: This workbook, sheet Ref Document templates | H47: 16-Jul-2027 (T-24 weeks) | J47: Not started
A48: REMITTANCE_SCHEDULE | B48: Remittance schedule | C48: Operations | D48: Drop 1 | E48: Head, Operations Services | F48: incentiveNote, insurerName, reference, remittanceType | G48: This workbook, sheet Ref Document templates | H48: 16-Jul-2027 (T-24 weeks) | J48: Not started
A49: RNW_ACCOUNT_DETAILS | B49: Renewal account details - {{renewalRef}} | C49: Renewal | D49: Drop 1 | E49: Product Owner, Renewal | F49: asOf, clientName, expiringArn | G49: This workbook, sheet Ref Document templates | H49: 16-Jul-2027 (T-24 weeks) | J49: Not started
A50: RNW_INSURER_COVER | B50: Renewals for your decision - batch {{batchNo}} | C50: Renewal | D50: Drop 1 | E50: Product Owner, Renewal | F50: count, expiryFrom, expiryTo, insurerName, replyDue | G50: This workbook, sheet Ref Document templates | H50: 16-Jul-2027 (T-24 weeks) | J50: Not started
A51: RNW_NAL | B51: Notice on your policy {{policyNo}} | C51: Renewal | D51: Drop 1 | E51: Product Owner, Renewal | F51: aoName, clientName, expiryDate, insurerName, policyNo, renewalRef | G51: This workbook, sheet Ref Document templates | H51: 16-Jul-2027 (T-24 weeks) | J51: Not started
A52: RNW_NFR | B52: Your policy {{policyNo}} will not be renewed | C52: Renewal | D52: Drop 1 | E52: Product Owner, Renewal | F52: aoName, clientName, expiryDate, insurerName, policyNo, reason, renewalRef | G52: This workbook, sheet Ref Document templates | H52: 16-Jul-2027 (T-24 weeks) | J52: Not started
A53: RNW_NON_ACCEPTANCE | B53: Your policy {{policyNo}} has expired | C53: Renewal | D53: Drop 1 | E53: Product Owner, Renewal | F53: aoName, clientName, expiryDate, insurerName, policyNo, renewalRef | G53: This workbook, sheet Ref Document templates | H53: 16-Jul-2027 (T-24 weeks) | J53: Not started
A54: RNW_NRNS_REMINDER | B54: Reminder: renewal of your policy {{policyNo}} | C54: Renewal | D54: Drop 1 | E54: Product Owner, Renewal | F54: aoName, clientName, expiryDate, insurerName, policyNo, renewalRef | G54: This workbook, sheet Ref Document templates | H54: 16-Jul-2027 (T-24 weeks) | J54: Not started
A55: RNW_RA_FFY | B55: Renewal Advice (first year free) - {{assuredName}} - policy {{policyNo}} | C55: Renewal | D55: Drop 1 | E55: Product Owner, Renewal | F55: aoName, clientName, currency, expiryDate, grossPremium, insurerName, policyNo, renewalFrom, renewalRef, renewalTo, sumInsured | G55: This workbook, sheet Ref Document templates | H55: 16-Jul-2027 (T-24 weeks) | J55: Not started
A56: RNW_RA_FIRST | B56: Renewal Advice - {{assuredName}} - policy {{policyNo}} | C56: Renewal | D56: Drop 1 | E56: Product Owner, Renewal | F56: aoName, clientName, currency, expiryDate, grossPremium, insurerName, policyNo, productName, renewalFrom, renewalRef, renewalTo, sumInsured | G56: This workbook, sheet Ref Document templates | H56: 16-Jul-2027 (T-24 weeks) | J56: Not started
A57: RNW_RA_SECOND | B57: Second notice: Renewal Advice - {{assuredName}} - policy {{policyNo}} | C57: Renewal | D57: Drop 1 | E57: Product Owner, Renewal | F57: aoName, clientName, currency, expiryDate, grossPremium, insurerName, policyNo, renewalRef, sumInsured | G57: This workbook, sheet Ref Document templates | H57: 16-Jul-2027 (T-24 weeks) | J57: Not started
A58: RNW_SFU | B58: Follow-up on the renewal of your mortgaged property - policy {{policyNo}} | C58: Renewal | D58: Drop 1 | E58: Product Owner, Renewal | F58: aoName, clientName, expiryDate, policyNo, renewalRef | G58: This workbook, sheet Ref Document templates | H58: 16-Jul-2027 (T-24 weeks) | J58: Not started
... A66: VALIDATION_SLIP | B66: Validation slip | C66: New Business | D66: Drop 1 | E66: Product Owner, BDOI (New Business) | F66: invoiceNo, requestNo, status, validatedOn | G66: This workbook, sheet Ref Document templates | H66: 16-Jul-2027 (T-24 weeks) | J66: Not started

Sheet Ref Accounting events
A1: Reference: Accounting events
A2: ← Back to Start here | B2: The accounting events that need a rule of template D0-08; owner Head, Comptrollership
A4: Event type | B4: Name | C4: Category | D4: Journal type | E4: Amount components | F4: Prepared in | G4: Status | H4: BDOI comments
A5: CLAIM_RECOVERY | B5: Salvage / subrogation recovery | C5: Claims | D5: Receipt | E5: AMOUNT | F5: Drop 0 template D0-08, sheet D0-08 Accounting rules | G5: Not started
A6: CLAIM_RESERVE | B6: Claim reserve change | C6: Claims | D6: Claims | E6: RESERVE_CHANGE | F6: Drop 0 template D0-08, sheet D0-08 Accounting rules | G6: Not started
A7: CLAIM_SETTLEMENT | B7: Claim settlement approved | C7: Claims | D7: Claims | E7: PAID_AMOUNT, RESERVE_RELEASE | F7: Drop 0 template D0-08, sheet D0-08 Accounting rules | G7: Not started
A8: CLAIM_COINSURANCE | B8: Coinsurer share of a claim | C8: Coinsurance | D8: Claims | E8: COINSURER_SHARE, COINSURER_RECOVERY | F8: Drop 0 template D0-08, sheet D0-08 Accounting rules | G8: Not started
A9: COINSURANCE_SHARE | B9: Coinsurer share of premium | C9: Coinsurance | D9: Premium | E9: COINSURER_PREMIUM | F9: Drop 0 template D0-08, sheet D0-08 Accounting rules | G9: Not started
A10: COMMISSION_ACCRUAL | B10: Commission accrued | C10: Commission | D10: Commission | E10: COMMISSION, WITHHOLDING_TAX, NET_COMMISSION | F10: Drop 0 template D0-08, sheet D0-08 Accounting rules | G10: Not started
A11: OPS_ADJ_COMMISSION | B11: Commission adjustment without premium change | C11: Commission | D11: Commission | E11: COMMISSION_RECEIVABLE, UNREALIZED_COMMISSION, DEFERRED_OUTPUT_VAT | F11: Drop 0 template D0-08, sheet D0-08 Accounting rules | G11: Not started
A12: OPS_INCENTIVE_ACCRUE | B12: Incentive earned from insurer | C12: Commission | D12: Commission | E12: INCENTIVE | F12: Drop 0 template D0-08, sheet D0-08 Accounting rules | G12: Not started
A13: OPS_INCENTIVE_PASS_ON | B13: Incentive pass-on to branches | C13: Commission | D13: Commission | E13: PASS_ON | F13: Drop 0 template D0-08, sheet D0-08 Accounting rules | G13: Not started
A14: OPS_REMIT_CPC2 | B14: CPC2 incentive per remittance batch | C14: Commission | D14: Commission | E14: GROSS, CPC2_INCOME, OUTPUT_VAT | F14: Drop 0 template D0-08, sheet D0-08 Accounting rules | G14: Not started
A15: OPS_REMIT_INCENTIVE | B15: Early remittance incentive | C15: Commission | D15: Commission | E15: DUE_FOR_DISBURSEMENT, INCENTIVE_INCOME, OUTPUT_VAT | F15: Drop 0 template D0-08, sheet D0-08 Accounting rules | G15: Not started
A16: ASSET_ACQUISITION | B16: Fixed asset capitalized | C16: Payment | D16: Payment | E16: COST | F16: Drop 0 template D0-08, sheet D0-08 Accounting rules | G16: Not started
... A94: INVESTMENT_TAKE_ON | B94: Investment opening balance | C94: Treasury | D94: Opening | E94: CARRYING_AMOUNT, ACCRUED_INTEREST, TOTAL | F94: Drop 0 template D0-08, sheet D0-08 Accounting rules | G94: Not started

Sheet Ref Migration cross-reference
A1: Reference: migration cross-reference
A2: ← Back to Start here | B2: Reference data loaded through the migration and items entered on screens: one route per item
A4: Object | B4: Name | C4: Category | D4: Proposed decision | E4: Business owner | F4: Extracts due | G4: Configuration route | H4: Duplication rule
A5: R01 | B5: Lists of values and MIS values | C5: Reference | D5: Migrate | E5: Product Owner, Marketing Business System (MBS) | F5: M3 | G5: Loaded by the migration: CFG-061 Values of the lists used by migrated records; CFG-140 Code maps of the reference data | H5: One route: not typed in this workbook
A6: R02 | B6: Branches and invoicing branches | C6: Reference | D6: Migrate | E6: Head, Comptrollership | F6: M3 | G6: Loaded by the migration: CFG-141 Branch code map | H6: One route: not typed in this workbook
A7: R03 | B7: Sales organisation (regions, departments, teams, unit heads, account officers) | C7: Reference | D7: Migrate | E7: Heads, Retail and Corporate Marketing | F7: M3 | G7: Loaded by the migration: CFG-007 Sales organisation (regions, departments, teams, unit heads, account officers) | H7: One route: not typed in this workbook
A8: R04 | B8: Insurers and insurer branches | C8: Reference | D8: Migrate | E8: Head, Operations | F8: M3 | G8: Loaded by the migration: CFG-100 Insurers and insurer branches | H8: One route: not typed in this workbook
A9: R05 | B9: Product lines, cover types, products and risk codes | C9: Reference | D9: Migrate | E9: Product Owner, MBS | F9: M3 | G9: Loaded by the migration: CFG-090 Product catalogue | H9: One route: not typed in this workbook
A10: R06 | B10: Package code map (legacy package and version to BIBS package version) | C10: Reference | D10: Migrate | E10: Product Owner, MBS (approves); TSU (prepares) | F10: M5; final at T-7 | G10: Loaded by the migration: CFG-095 Package map (legacy package to BIBS package version) | H10: One route: not typed in this workbook
A11: R07 | B11: Commission rates by insurer and product | C11: Reference | D11: Migrate | E11: Head, Operations | F11: M3 | G11: Loaded by the migration: CFG-101 Commission rates by insurer and product | H11: One route: not typed in this workbook
A12: R08 | B12: Chart of accounts mapping (legacy GL account to BIBS account) | C12: Reference | D12: Migrate | E12: Head, Comptrollership; Product Owner FRBS and ACSL | F12: M3 | G12: Loaded by the migration: CFG-024 Chart of accounts mapping (legacy GL account to BIBS account) | H12: One route: not typed in this workbook
A13: R09 | B13: Payees | C13: Reference | D13: Conditional | E13: Product Owner, Comptrollership - Disbursement | F13: M3 | G13: Loaded by the migration: CFG-103 Payees | H13: One route: not typed in this workbook
A14: R10 | B14: Users and roles | C14: Reference | D14: Excluded | E14: Unit Head, Analytics and Risk Management (User Access) | F14: M5 (USER map) | G14: Not migrated (excluded): users are created by access requests from BRD-11 template CI-01 (CFG-110); legacy user IDs are only mapped (code map USER) so the officer, handler and collector fields of migrated records resolve | H14: -
A15: R11 | B15: Receipt series in use (AR and OR, ATP and next number) | C15: Reference | D15: Carry Forward | E15: Operations - Financial Transactions | F15: M3; final at T-3 | G15: Loaded by the migration: CFG-050 Receipt series in use (AR and OR) | H15: One route: not typed in this workbook
... A36: H02 | B36: Legacy documents (policies, SOAs, ORs, certificates, letters) | C36: History | D36: Archive | E36: Audit / Compliance | F36: Before decommissioning | G36: Business data, not configuration: prepared and signed in the Migration Workbook only | H36: -

Sheet Reference lists
A1: Reference lists
A2: ← Back to Start here | B2: Every list of allowed values used by the drop-downs, with its code and label. A drop-down accepts the codes of its list.
A4: List | B4: Used in | C4: Code | D4: Label | E4: Note
A5: Yes or no (YES_NO) | B5: D0-02 Branches: Head office D0-02 Branches: Foreign currency authorised D0-04 Dimensions: Active D0-07 Categories and numbering: Bank category D0-06 Chart of accounts: Control Account D0-06 Chart of accounts: Manual Posting D0-06 Chart of accounts: Cost Centre Required D0-06 Chart of accounts: Revaluation Required PM-01 Product catalogue: Package PM-01 Product catalogue: Fleet PM-01 Product catalogue: Mortgage related PM-01 Product catalogue: Direct payment allowed PM-01 Product catalogue: Free First Year PM-02 Coverages and rules: Basic PM-02 Coverages and rules: Mandatory UA-03 Approval rules: Any approver may decide Ref Notifications: In-app wanted Ref Notifications: E-mail wanted Ref Document templates: BDOI layout attached | C5: Y | D5: Yes
C6: N | D6: No
A7: Market segment (MARKET_SEGMENT) | B7: PM-01 Product catalogue: Market segments | C7: CBG | D7: Consumer Banking Group (CBG) | E7: The values of the list MARKET_SEGMENT as delivered with BIBS; a new value is added with its template and may then be used here.
C8: COMBANK | D8: Commercial Banking
C9: CORBANK | D9: Corporate Banking
C10: RETAIL | D10: Retail Marketing
C11: INSTITUTIONAL | D11: Institutional Banking / SM / BDO accounts
A12: Placement after (PLACEMENT_GATE) | B12: PM-01 Product catalogue: Placement after | C12: PAID | D12: Premium paid
C13: CLIENT_CONFIRMATION | D13: Client confirmation
A14: TSU review (TSU_REVIEW) | B14: PM-01 Product catalogue: TSU review | C14: BY_RULES | D14: By the review rules
C15: ALWAYS | D15: Always
C16: NEVER | D16: Never
A17: Coverage and rule record (CI02_RECORD) | B17: PM-02 Coverages and rules: Record | C17: COVERAGE | D17: Coverage or peril of a line
C18: FIELD_RULE | D18: Field an account of the product needs
C19: DOCUMENT_RULE | D19: Document an account of the product needs
A20: Document type (DOCUMENT_TYPE) | B20: PM-02 Coverages and rules: Document type | C20: IDF | D20: Insurance Declaration Form (IDF) | E20: The values of the list DOCUMENT_TYPE as delivered with BIBS; a new value is added with its template and may then be used here.
C21: VALID_ID | D21: Valid ID
C22: BIRTH_CERTIFICATE | D22: Birth certificate
C23: ACCOUNT_LIST | D23: List of account details (Excel)
C24: QUOTATION | D24: Quotation / proposal
C25: CLIENT_ACCEPTANCE | D25: Client acceptance e-mail
C26: EPOLICY | D26: E-policy
C27: OFFICIAL_RECEIPT | D27: Official receipt
C28: POLICY_COPY | D28: Issued policy copy
C29: OTHERS | D29: Others
C30: KYC_FORM | D30: Client information sheet / KYC form
C31: PROOF_OF_ADDRESS | D31: Proof of address
C32: SEC_CERTIFICATE | D32: SEC / DTI certificate of registration
... C82: PLACEMENT_FILE | D82: Placement file
A83: Clause kind (CLAUSE_KIND) | B83: PM-03 Clause library: Kind | C83: WARRANTY | D83: Warranty | E83: The values of the list CLAUSE_KIND as delivered with BIBS; a new value is added with its template and may then be used here.
C84: CLAUSE | D84: Clause
C85: EXCLUSION | D85: Exclusion
C86: DEDUCTIBLE_WORDING | D86: Deductible wording
A87: Rate table (RATE_TABLE) | B87: PM-04 Rate tables: Table | C87: TAX | D87: Statutory charge or rating factor
C88: SHORT_PERIOD | D88: Short-period table
C89: MOTOR_LIMIT | D89: Motor BI / PD limit premium
A90: Package map action (MAP_ACTION) | B90: PM-07 Package map: Action | C90: MAP | D90: Renew with the BIBS package version
C91: REJECT | D91: Send the candidate to the Renewal Exception bucket
A92: Package document template (PKG_DOCUMENT) | B92: PM-08 Document templates: Template | C92: PKG_REQUEST_FORM | D92: Package Request Form
C93: PKG_QUOTATION_SLIP | D93: Package quotation slip
C94: PKG_COMPARATIVE | D94: Package comparative table
C95: PKG_SLIP | D95: Package slip
C96: PKG_ADVISORY | D96: Package advisory
C97: PKG_RENEWAL_ADVISORY | D97: Package renewal advisory
A98: Product Maintenance list or parameter (PM_LIST_OR_PARAMETER) | B98: PM-09 Lists and parameters: List or parameter | C98: PKG_REQUEST_REASON | D98: List: Package request reason
C99: PKG_RESPONSE_OUTCOME | D99: List: Insurer response outcome
C100: PKG_ADVISORY_GROUP | D100: List: Advisory recipient group
C101: PKG_NOT_PROCEEDED_REASON | D101: List: Package not proceeded reason
C102: PKG_REQUEST_TYPE | D102: List: Package request type
C103: INCENTIVE_TYPE | D103: List: Incentive type
C104: COVERAGE_KIND | D104: List: Coverage kind
C105: CLAUSE_KIND | D105: List: Clause kind
C106: DOCUMENT_TYPE | D106: List: Document type
C107: MARKET_SEGMENT | D107: List: Market segment
C108: PKG_REQUEST_PREFIX | D108: Parameter: Prefix of package request numbers; the year is appended
C109: PKG_QS_PREFIX | D109: Parameter: Prefix of package quotation slip numbers; the year is appended
C110: PKG_QS_REPLY_DAYS | D110: Parameter: Days insurers have to reply to a package quotation slip
... C137: PLACEMENT_UPDATE_SCOPE | D137: Parameter: QUOTATION: the report lists the quotation requests (the bank's process); QUOTATION_AND_PACKAGE: the package requests follow
A138: Incentive type (INCENTIVE_TYPE) | B138: PM-10 Incentive criteria: Incentive type | C138: OTHERS | D138: Others (see description) | E138: The values of the list INCENTIVE_TYPE as delivered with BIBS; a new value is added with its template and may then be used here.
C139: MIGRATED | D139: Migrated booking incentive rule
A140: Bulk request action (UA_ACTION) | B140: UA-01 Users and roles: Action | C140: ENROL | D140: Enrol a new user
C141: MODIFY | D141: Modify a user
C142: DEACTIVATE | D142: Deactivate a user
C143: REACTIVATE | D143: Reactivate a user
A144: Privilege level (PRIVILEGE_LEVEL) | B144: UA-02 Role matrix: Privilege level | C144: Low | D144: Low
C145: Standard | D145: Standard
C146: High | D146: High: a second approval when given or raised
C147: Admin | D147: Admin: a second approval when given or raised
A148: Change against the matrix (KEEP_ADD_REMOVE) | B148: UA-02 Role matrix: Keep / Add / Remove | C148: KEEP | D148: Keep the permission
C149: ADD | D149: Add the permission
C150: REMOVE | D150: Remove the permission
A151: Role in user access (UA_ROLE) | B151: UA-03 Approval rules: Role in user access | C151: Requestor | D151: Raises access requests for the unit
C152: Approver | D152: Approves access requests
C153: Second Approver | D153: Second approval of High and Admin privileges
C154: Group-profile requester | D154: Raises group-profile requests
C155: Implementer | D155: System Administrator who implements approved requests
A156: Separation-of-duties rule status (SOD_STATUS) | B156: UA-04 SoD rules: Status | C156: Enforced | D156: A fixed rule of BIBS
C157: To confirm | D157: Proposed; BDOI confirms
C158: New | D158: Added by BDOI
A159: Separation-of-duties control (SOD_CONTROL) | B159: UA-04 SoD rules: Control | C159: Prevent | D159: A rule of Separation of Duties: BIBS refuses the request
C160: Detect by review | D160: Reviewed with the reports
C161: Second approval | D161: A second approver decides
A162: Review frequency (REVIEW_FREQUENCY) | B162: UA-04 SoD rules: Review frequency | C162: Monthly | D162: Monthly
C163: Quarterly | D163: Quarterly
A164: Sign-in (UA_PARAMETER) | B164: UA-05 Parameters: Parameter | C164: LOGIN_MAX_FAILED_ATTEMPTS | D164: Consecutive failed logins that lock a user account; applies to all users
C165: SESSION_IDLE_WARNING_MINUTES | D165: Minutes of inactivity after which the web client warns that the session will sign out
C166: SESSION_TIMEOUT_MINUTES | D166: Minutes of inactivity after which the web session signs out automatically
C167: SESSION_EXPIRY_WARNING_MINUTES | D167: Minutes before the system-triggered (absolute) sign-out at which the web client warns the user
C168: AUTH_MODE | D168: Sign-in mode: LOCAL (BIBS passwords) or DIRECTORY (BDO directory sign-in by Windows ID, when the EIAM sign-in is specified)
C169: USER_ID_PATTERN | D169: Regular expression of a new user ID on enrolment requests
C170: USER_ID_FORMAT_TEXT | D170: The user ID format in words, shown to the requester with the format check of USER_ID_PATTERN
C171: PASSWORD_HISTORY_COUNT | D171: Previous passwords a local account may not reuse (at least the last ten)
C172: PASSWORD_MAX_AGE_DAYS | D172: Days after which a password must be changed, LOCAL mode; 0 = never
C173: PASSWORD_MIN_AGE_DAYS | D173: Days before a changed password may be changed again, LOCAL mode
C174: UAM_WORKING_HOURS | D174: Working hours; an access request submitted outside them needs a second approval
C175: UAM_ANY_APPROVER | D175: When true, any holder of ACCESS_APPROVE may decide a request, not only the approver chosen by the requester
C176: UAM_ROLE_APPLY_ON_APPROVAL | D176: When true, an approved group-profile or role-permission request applies at its last approval; when false it waits for the System Administrator to implement it
...

Sheet Questions and comments
A1: Questions and comments
A2: ← Back to Start here | B2: Raise a question or a comment on a template or a column; the iorta TechNXT project team answers here.
A4: No. | B4: Template | C4: Column | D4: Question / comment | E4: Raised by | F4: Date | G4: Answer | H4: Answered by | I4: Status
A5: 1
A6: 2
A7: 3
A8: 4
A9: 5
A10: 6
A11: 7
A12: 8
A13: 9
A14: 10
A15: 11
A16: 12
... A104: 100
