Workbook

Sheet Read Me
B2: iNXT BrokerVerse - BDOI New Business (BRD-1) Fit / Gap
B3: BDO Insurance and Reinsurance Brokers, Inc. (Philippines) - requirements baseline and platform fit/gap for concurrence before build
B5: Purpose | C5: Trace every requirement in the New Business BRD pack to the iNXT BrokerVerse platform, classify the fit, propose the solution and list the questions BDOI must answer before the build starts.
B6: Source documents | C6: 1) NB Workshop Addendum, 10-Apr-2026 (BRNB.090-115 and updates to BRNB.004/022/069) - pp.1-44 (two identical signed copies) 2) NB Addendum - Other Lines & Non-Package, 16-Dec-2025 (BRNB.001-039 + Annex risk codes / product lines) - pp.45-90 3) NB Fire & Motor - BRD ID consolidation, 18-Dec-2025 (BRNB.040-089, maps legacy BRD 1.x-3.x IDs) - pp.91-129 4) NB Fire & Motor BRD V06162025 (legacy BRD 1.1.1-3.4.3, NFRs, Appendix A calculations, Appendix B product matrix) - pp.130-218
B7: Business context | C7: BDOI is an insurance broker. Insurers issue the policies; BDOI prepares quotations, onboards clients, places risks with insurers, collects premium (e.g. via CLPC loan billing), receives and distributes e-policies, and books the account (commission income, service invoice). BrokerVerse today is built around an insurer core; this workbook shows what is re-used, extended and newly built.
B8: Fit classes | C8: FIT: Works today in BrokerVerse; no change beyond set-up CONFIGURE: Existing capability; parameters / master data only CHANGE: Existing capability extended or re-purposed for the broker model NEW: New build OUT: Out of scope per BRD
B9: Effort | C9: S = up to 5 person-days, M = 5-15, L = 15-40, XL = more than 40 (build + unit tests; excludes UAT). Indicative only.
B10: How to review | C10: Sheet "Fit-Gap": review each row, choose BDOI concurrence (yellow column) and add comments. Sheet "Open Questions": answer each question (yellow columns) - answers drive the detailed design. Sheets "Target Workflow", "Product Catalogue", "Calculations", "NFR" are proposals / transcriptions for confirmation. Sheet "Sign-off": BDOI and iORTA TechNXT signatories.
B11: Status | C11: No build has started. Implementation begins after concurrence on this workbook and answers to the must-answer questions.

Sheet Summary
B2: Summary
B3: Counts are formulas over the Fit-Gap sheet and update as BDOI records concurrence
B5: Area | C5: FIT | D5: CONFIGURE | E5: CHANGE | F5: NEW | G5: OUT | H5: Total | I5: Agreed | J5: Pending review
B6: Product lines & product rules | C6: =COUNTIFS('Fit-Gap'!$B$2:$B$400,$B6,'Fit-Gap'!$H$2:$H$400,"FIT") -> 0 | D6: =COUNTIFS('Fit-Gap'!$B$2:$B$400,$B6,'Fit-Gap'!$H$2:$H$400,"CONFIGURE") -> 0 | E6: =COUNTIFS('Fit-Gap'!$B$2:$B$400,$B6,'Fit-Gap'!$H$2:$H$400,"CHANGE") -> 4 | F6: =COUNTIFS('Fit-Gap'!$B$2:$B$400,$B6,'Fit-Gap'!$H$2:$H$400,"NEW") -> 2 | G6: =COUNTIFS('Fit-Gap'!$B$2:$B$400,$B6,'Fit-Gap'!$H$2:$H$400,"OUT") -> 0 | H6: =SUM(C6:G6) -> 6 | I6: =COUNTIFS('Fit-Gap'!$B$2:$B$400,$B6,'Fit-Gap'!$N$2:$N$400,"Agreed")+COUNTIFS('Fit-Gap'!$B$2:$B$400,$B6,'Fit-Gap'!$N$2:$N$400,"Agreed with changes") -> 0 | J6: =H6-I6 -> 6
B7: Non-package placement (PRF / QS / TSU) | C7: =COUNTIFS('Fit-Gap'!$B$2:$B$400,$B7,'Fit-Gap'!$H$2:$H$400,"FIT") -> 1 | D7: =COUNTIFS('Fit-Gap'!$B$2:$B$400,$B7,'Fit-Gap'!$H$2:$H$400,"CONFIGURE") -> 0 | E7: =COUNTIFS('Fit-Gap'!$B$2:$B$400,$B7,'Fit-Gap'!$H$2:$H$400,"CHANGE") -> 5 | F7: =COUNTIFS('Fit-Gap'!$B$2:$B$400,$B7,'Fit-Gap'!$H$2:$H$400,"NEW") -> 8 | G7: =COUNTIFS('Fit-Gap'!$B$2:$B$400,$B7,'Fit-Gap'!$H$2:$H$400,"OUT") -> 0 | H7: =SUM(C7:G7) -> 14 | I7: =COUNTIFS('Fit-Gap'!$B$2:$B$400,$B7,'Fit-Gap'!$N$2:$N$400,"Agreed")+COUNTIFS('Fit-Gap'!$B$2:$B$400,$B7,'Fit-Gap'!$N$2:$N$400,"Agreed with changes") -> 0 | J7: =H7-I7 -> 14
B8: Quotation / proposal | C8: =COUNTIFS('Fit-Gap'!$B$2:$B$400,$B8,'Fit-Gap'!$H$2:$H$400,"FIT") -> 1 | D8: =COUNTIFS('Fit-Gap'!$B$2:$B$400,$B8,'Fit-Gap'!$H$2:$H$400,"CONFIGURE") -> 0 | E8: =COUNTIFS('Fit-Gap'!$B$2:$B$400,$B8,'Fit-Gap'!$H$2:$H$400,"CHANGE") -> 4 | F8: =COUNTIFS('Fit-Gap'!$B$2:$B$400,$B8,'Fit-Gap'!$H$2:$H$400,"NEW") -> 3 | G8: =COUNTIFS('Fit-Gap'!$B$2:$B$400,$B8,'Fit-Gap'!$H$2:$H$400,"OUT") -> 0 | H8: =SUM(C8:G8) -> 8 | I8: =COUNTIFS('Fit-Gap'!$B$2:$B$400,$B8,'Fit-Gap'!$N$2:$N$400,"Agreed")+COUNTIFS('Fit-Gap'!$B$2:$B$400,$B8,'Fit-Gap'!$N$2:$N$400,"Agreed with changes") -> 0 | J8: =H8-I8 -> 8
B9: Client (CRM, onboarding, KYC) | C9: =COUNTIFS('Fit-Gap'!$B$2:$B$400,$B9,'Fit-Gap'!$H$2:$H$400,"FIT") -> 1 | D9: =COUNTIFS('Fit-Gap'!$B$2:$B$400,$B9,'Fit-Gap'!$H$2:$H$400,"CONFIGURE") -> 0 | E9: =COUNTIFS('Fit-Gap'!$B$2:$B$400,$B9,'Fit-Gap'!$H$2:$H$400,"CHANGE") -> 5 | F9: =COUNTIFS('Fit-Gap'!$B$2:$B$400,$B9,'Fit-Gap'!$H$2:$H$400,"NEW") -> 6 | G9: =COUNTIFS('Fit-Gap'!$B$2:$B$400,$B9,'Fit-Gap'!$H$2:$H$400,"OUT") -> 0 | H9: =SUM(C9:G9) -> 12 | I9: =COUNTIFS('Fit-Gap'!$B$2:$B$400,$B9,'Fit-Gap'!$N$2:$N$400,"Agreed")+COUNTIFS('Fit-Gap'!$B$2:$B$400,$B9,'Fit-Gap'!$N$2:$N$400,"Agreed with changes") -> 0 | J9: =H9-I9 -> 12
B10: Account (risk record) | C10: =COUNTIFS('Fit-Gap'!$B$2:$B$400,$B10,'Fit-Gap'!$H$2:$H$400,"FIT") -> 0 | D10: =COUNTIFS('Fit-Gap'!$B$2:$B$400,$B10,'Fit-Gap'!$H$2:$H$400,"CONFIGURE") -> 0 | E10: =COUNTIFS('Fit-Gap'!$B$2:$B$400,$B10,'Fit-Gap'!$H$2:$H$400,"CHANGE") -> 4 | F10: =COUNTIFS('Fit-Gap'!$B$2:$B$400,$B10,'Fit-Gap'!$H$2:$H$400,"NEW") -> 4 | G10: =COUNTIFS('Fit-Gap'!$B$2:$B$400,$B10,'Fit-Gap'!$H$2:$H$400,"OUT") -> 0 | H10: =SUM(C10:G10) -> 8 | I10: =COUNTIFS('Fit-Gap'!$B$2:$B$400,$B10,'Fit-Gap'!$N$2:$N$400,"Agreed")+COUNTIFS('Fit-Gap'!$B$2:$B$400,$B10,'Fit-Gap'!$N$2:$N$400,"Agreed with changes") -> 0 | J10: =H10-I10 -> 8
B11: Bulk intake & source systems | C11: =COUNTIFS('Fit-Gap'!$B$2:$B$400,$B11,'Fit-Gap'!$H$2:$H$400,"FIT") -> 0 | D11: =COUNTIFS('Fit-Gap'!$B$2:$B$400,$B11,'Fit-Gap'!$H$2:$H$400,"CONFIGURE") -> 0 | E11: =COUNTIFS('Fit-Gap'!$B$2:$B$400,$B11,'Fit-Gap'!$H$2:$H$400,"CHANGE") -> 0 | F11: =COUNTIFS('Fit-Gap'!$B$2:$B$400,$B11,'Fit-Gap'!$H$2:$H$400,"NEW") -> 7 | G11: =COUNTIFS('Fit-Gap'!$B$2:$B$400,$B11,'Fit-Gap'!$H$2:$H$400,"OUT") -> 0 | H11: =SUM(C11:G11) -> 7 | I11: =COUNTIFS('Fit-Gap'!$B$2:$B$400,$B11,'Fit-Gap'!$N$2:$N$400,"Agreed")+COUNTIFS('Fit-Gap'!$B$2:$B$400,$B11,'Fit-Gap'!$N$2:$N$400,"Agreed with changes") -> 0 | J11: =H11-I11 -> 7
B12: Documents | C12: =COUNTIFS('Fit-Gap'!$B$2:$B$400,$B12,'Fit-Gap'!$H$2:$H$400,"FIT") -> 0 | D12: =COUNTIFS('Fit-Gap'!$B$2:$B$400,$B12,'Fit-Gap'!$H$2:$H$400,"CONFIGURE") -> 0 | E12: =COUNTIFS('Fit-Gap'!$B$2:$B$400,$B12,'Fit-Gap'!$H$2:$H$400,"CHANGE") -> 3 | F12: =COUNTIFS('Fit-Gap'!$B$2:$B$400,$B12,'Fit-Gap'!$H$2:$H$400,"NEW") -> 2 | G12: =COUNTIFS('Fit-Gap'!$B$2:$B$400,$B12,'Fit-Gap'!$H$2:$H$400,"OUT") -> 0 | H12: =SUM(C12:G12) -> 5 | I12: =COUNTIFS('Fit-Gap'!$B$2:$B$400,$B12,'Fit-Gap'!$N$2:$N$400,"Agreed")+COUNTIFS('Fit-Gap'!$B$2:$B$400,$B12,'Fit-Gap'!$N$2:$N$400,"Agreed with changes") -> 0 | J12: =H12-I12 -> 5
B13: Placement with insurers | C13: =COUNTIFS('Fit-Gap'!$B$2:$B$400,$B13,'Fit-Gap'!$H$2:$H$400,"FIT") -> 0 | D13: =COUNTIFS('Fit-Gap'!$B$2:$B$400,$B13,'Fit-Gap'!$H$2:$H$400,"CONFIGURE") -> 0 | E13: =COUNTIFS('Fit-Gap'!$B$2:$B$400,$B13,'Fit-Gap'!$H$2:$H$400,"CHANGE") -> 0 | F13: =COUNTIFS('Fit-Gap'!$B$2:$B$400,$B13,'Fit-Gap'!$H$2:$H$400,"NEW") -> 10 | G13: =COUNTIFS('Fit-Gap'!$B$2:$B$400,$B13,'Fit-Gap'!$H$2:$H$400,"OUT") -> 0 | H13: =SUM(C13:G13) -> 10 | I13: =COUNTIFS('Fit-Gap'!$B$2:$B$400,$B13,'Fit-Gap'!$N$2:$N$400,"Agreed")+COUNTIFS('Fit-Gap'!$B$2:$B$400,$B13,'Fit-Gap'!$N$2:$N$400,"Agreed with changes") -> 0 | J13: =H13-I13 -> 10
B14: Billing & payment confirmation | C14: =COUNTIFS('Fit-Gap'!$B$2:$B$400,$B14,'Fit-Gap'!$H$2:$H$400,"FIT") -> 0 | D14: =COUNTIFS('Fit-Gap'!$B$2:$B$400,$B14,'Fit-Gap'!$H$2:$H$400,"CONFIGURE") -> 0 | E14: =COUNTIFS('Fit-Gap'!$B$2:$B$400,$B14,'Fit-Gap'!$H$2:$H$400,"CHANGE") -> 1 | F14: =COUNTIFS('Fit-Gap'!$B$2:$B$400,$B14,'Fit-Gap'!$H$2:$H$400,"NEW") -> 2 | G14: =COUNTIFS('Fit-Gap'!$B$2:$B$400,$B14,'Fit-Gap'!$H$2:$H$400,"OUT") -> 0 | H14: =SUM(C14:G14) -> 3 | I14: =COUNTIFS('Fit-Gap'!$B$2:$B$400,$B14,'Fit-Gap'!$N$2:$N$400,"Agreed")+COUNTIFS('Fit-Gap'!$B$2:$B$400,$B14,'Fit-Gap'!$N$2:$N$400,"Agreed with changes") -> 0 | J14: =H14-I14 -> 3
B15: E-policy & insurance advice | C15: =COUNTIFS('Fit-Gap'!$B$2:$B$400,$B15,'Fit-Gap'!$H$2:$H$400,"FIT") -> 0 | D15: =COUNTIFS('Fit-Gap'!$B$2:$B$400,$B15,'Fit-Gap'!$H$2:$H$400,"CONFIGURE") -> 0 | E15: =COUNTIFS('Fit-Gap'!$B$2:$B$400,$B15,'Fit-Gap'!$H$2:$H$400,"CHANGE") -> 0 | F15: =COUNTIFS('Fit-Gap'!$B$2:$B$400,$B15,'Fit-Gap'!$H$2:$H$400,"NEW") -> 8 | G15: =COUNTIFS('Fit-Gap'!$B$2:$B$400,$B15,'Fit-Gap'!$H$2:$H$400,"OUT") -> 0 | H15: =SUM(C15:G15) -> 8 | I15: =COUNTIFS('Fit-Gap'!$B$2:$B$400,$B15,'Fit-Gap'!$N$2:$N$400,"Agreed")+COUNTIFS('Fit-Gap'!$B$2:$B$400,$B15,'Fit-Gap'!$N$2:$N$400,"Agreed with changes") -> 0 | J15: =H15-I15 -> 8
B16: Booking, endorsements & cancellation | C16: =COUNTIFS('Fit-Gap'!$B$2:$B$400,$B16,'Fit-Gap'!$H$2:$H$400,"FIT") -> 0 | D16: =COUNTIFS('Fit-Gap'!$B$2:$B$400,$B16,'Fit-Gap'!$H$2:$H$400,"CONFIGURE") -> 1 | E16: =COUNTIFS('Fit-Gap'!$B$2:$B$400,$B16,'Fit-Gap'!$H$2:$H$400,"CHANGE") -> 8 | F16: =COUNTIFS('Fit-Gap'!$B$2:$B$400,$B16,'Fit-Gap'!$H$2:$H$400,"NEW") -> 5 | G16: =COUNTIFS('Fit-Gap'!$B$2:$B$400,$B16,'Fit-Gap'!$H$2:$H$400,"OUT") -> 0 | H16: =SUM(C16:G16) -> 14 | I16: =COUNTIFS('Fit-Gap'!$B$2:$B$400,$B16,'Fit-Gap'!$N$2:$N$400,"Agreed")+COUNTIFS('Fit-Gap'!$B$2:$B$400,$B16,'Fit-Gap'!$N$2:$N$400,"Agreed with changes") -> 0 | J16: =H16-I16 -> 14
B17: Workflow, status & governance | C17: =COUNTIFS('Fit-Gap'!$B$2:$B$400,$B17,'Fit-Gap'!$H$2:$H$400,"FIT") -> 1 | D17: =COUNTIFS('Fit-Gap'!$B$2:$B$400,$B17,'Fit-Gap'!$H$2:$H$400,"CONFIGURE") -> 0 | E17: =COUNTIFS('Fit-Gap'!$B$2:$B$400,$B17,'Fit-Gap'!$H$2:$H$400,"CHANGE") -> 2 | F17: =COUNTIFS('Fit-Gap'!$B$2:$B$400,$B17,'Fit-Gap'!$H$2:$H$400,"NEW") -> 6 | G17: =COUNTIFS('Fit-Gap'!$B$2:$B$400,$B17,'Fit-Gap'!$H$2:$H$400,"OUT") -> 1 | H17: =SUM(C17:G17) -> 10 | I17: =COUNTIFS('Fit-Gap'!$B$2:$B$400,$B17,'Fit-Gap'!$N$2:$N$400,"Agreed")+COUNTIFS('Fit-Gap'!$B$2:$B$400,$B17,'Fit-Gap'!$N$2:$N$400,"Agreed with changes") -> 0 | J17: =H17-I17 -> 10
... B19: Access, security & administration | C19: =COUNTIFS('Fit-Gap'!$B$2:$B$400,$B19,'Fit-Gap'!$H$2:$H$400,"FIT") -> 4 | D19: =COUNTIFS('Fit-Gap'!$B$2:$B$400,$B19,'Fit-Gap'!$H$2:$H$400,"CONFIGURE") -> 1 | E19: =COUNTIFS('Fit-Gap'!$B$2:$B$400,$B19,'Fit-Gap'!$H$2:$H$400,"CHANGE") -> 3 | F19: =COUNTIFS('Fit-Gap'!$B$2:$B$400,$B19,'Fit-Gap'!$H$2:$H$400,"NEW") -> 1 | G19: =COUNTIFS('Fit-Gap'!$B$2:$B$400,$B19,'Fit-Gap'!$H$2:$H$400,"OUT") -> 0 | H19: =SUM(C19:G19) -> 9 | I19: =COUNTIFS('Fit-Gap'!$B$2:$B$400,$B19,'Fit-Gap'!$N$2:$N$400,"Agreed")+COUNTIFS('Fit-Gap'!$B$2:$B$400,$B19,'Fit-Gap'!$N$2:$N$400,"Agreed with changes") -> 0 | J19: =H19-I19 -> 9
B20: Total | C20: =SUM(C6:C19) -> 8 | D20: =SUM(D6:D19) -> 2 | E20: =SUM(E6:E19) -> 42 | F20: =SUM(F6:F19) -> 65 | G20: =SUM(G6:G19) -> 2 | H20: =SUM(H6:H19) -> 119 | I20: =SUM(I6:I19) -> 0 | J20: =SUM(J6:J19) -> 119
B22: Effort by target module (count of rows)
B23: Target module | C23: S | D23: M | E23: L | F23: XL | G23: Rows
B24: Account | C24: =COUNTIFS('Fit-Gap'!$K$2:$K$400,$B24,'Fit-Gap'!$L$2:$L$400,"S") -> 5 | D24: =COUNTIFS('Fit-Gap'!$K$2:$K$400,$B24,'Fit-Gap'!$L$2:$L$400,"M") -> 3 | E24: =COUNTIFS('Fit-Gap'!$K$2:$K$400,$B24,'Fit-Gap'!$L$2:$L$400,"L") -> 1 | F24: =COUNTIFS('Fit-Gap'!$K$2:$K$400,$B24,'Fit-Gap'!$L$2:$L$400,"XL") -> 0 | G24: =SUM(C24:F24) -> 9
B25: Administration | C25: =COUNTIFS('Fit-Gap'!$K$2:$K$400,$B25,'Fit-Gap'!$L$2:$L$400,"S") -> 4 | D25: =COUNTIFS('Fit-Gap'!$K$2:$K$400,$B25,'Fit-Gap'!$L$2:$L$400,"M") -> 1 | E25: =COUNTIFS('Fit-Gap'!$K$2:$K$400,$B25,'Fit-Gap'!$L$2:$L$400,"L") -> 0 | F25: =COUNTIFS('Fit-Gap'!$K$2:$K$400,$B25,'Fit-Gap'!$L$2:$L$400,"XL") -> 0 | G25: =SUM(C25:F25) -> 5
B26: Billing & Collection | C26: =COUNTIFS('Fit-Gap'!$K$2:$K$400,$B26,'Fit-Gap'!$L$2:$L$400,"S") -> 0 | D26: =COUNTIFS('Fit-Gap'!$K$2:$K$400,$B26,'Fit-Gap'!$L$2:$L$400,"M") -> 2 | E26: =COUNTIFS('Fit-Gap'!$K$2:$K$400,$B26,'Fit-Gap'!$L$2:$L$400,"L") -> 1 | F26: =COUNTIFS('Fit-Gap'!$K$2:$K$400,$B26,'Fit-Gap'!$L$2:$L$400,"XL") -> 0 | G26: =SUM(C26:F26) -> 3
B27: Booking & Accounting | C27: =COUNTIFS('Fit-Gap'!$K$2:$K$400,$B27,'Fit-Gap'!$L$2:$L$400,"S") -> 4 | D27: =COUNTIFS('Fit-Gap'!$K$2:$K$400,$B27,'Fit-Gap'!$L$2:$L$400,"M") -> 7 | E27: =COUNTIFS('Fit-Gap'!$K$2:$K$400,$B27,'Fit-Gap'!$L$2:$L$400,"L") -> 1 | F27: =COUNTIFS('Fit-Gap'!$K$2:$K$400,$B27,'Fit-Gap'!$L$2:$L$400,"XL") -> 0 | G27: =SUM(C27:F27) -> 12
B28: Bulk Processing | C28: =COUNTIFS('Fit-Gap'!$K$2:$K$400,$B28,'Fit-Gap'!$L$2:$L$400,"S") -> 1 | D28: =COUNTIFS('Fit-Gap'!$K$2:$K$400,$B28,'Fit-Gap'!$L$2:$L$400,"M") -> 7 | E28: =COUNTIFS('Fit-Gap'!$K$2:$K$400,$B28,'Fit-Gap'!$L$2:$L$400,"L") -> 1 | F28: =COUNTIFS('Fit-Gap'!$K$2:$K$400,$B28,'Fit-Gap'!$L$2:$L$400,"XL") -> 0 | G28: =SUM(C28:F28) -> 9
B29: Client | C29: =COUNTIFS('Fit-Gap'!$K$2:$K$400,$B29,'Fit-Gap'!$L$2:$L$400,"S") -> 7 | D29: =COUNTIFS('Fit-Gap'!$K$2:$K$400,$B29,'Fit-Gap'!$L$2:$L$400,"M") -> 5 | E29: =COUNTIFS('Fit-Gap'!$K$2:$K$400,$B29,'Fit-Gap'!$L$2:$L$400,"L") -> 0 | F29: =COUNTIFS('Fit-Gap'!$K$2:$K$400,$B29,'Fit-Gap'!$L$2:$L$400,"XL") -> 0 | G29: =SUM(C29:F29) -> 12
B30: Documents | C30: =COUNTIFS('Fit-Gap'!$K$2:$K$400,$B30,'Fit-Gap'!$L$2:$L$400,"S") -> 3 | D30: =COUNTIFS('Fit-Gap'!$K$2:$K$400,$B30,'Fit-Gap'!$L$2:$L$400,"M") -> 2 | E30: =COUNTIFS('Fit-Gap'!$K$2:$K$400,$B30,'Fit-Gap'!$L$2:$L$400,"L") -> 1 | F30: =COUNTIFS('Fit-Gap'!$K$2:$K$400,$B30,'Fit-Gap'!$L$2:$L$400,"XL") -> 1 | G30: =SUM(C30:F30) -> 7
B31: Intake | C31: =COUNTIFS('Fit-Gap'!$K$2:$K$400,$B31,'Fit-Gap'!$L$2:$L$400,"S") -> 0 | D31: =COUNTIFS('Fit-Gap'!$K$2:$K$400,$B31,'Fit-Gap'!$L$2:$L$400,"M") -> 1 | E31: =COUNTIFS('Fit-Gap'!$K$2:$K$400,$B31,'Fit-Gap'!$L$2:$L$400,"L") -> 0 | F31: =COUNTIFS('Fit-Gap'!$K$2:$K$400,$B31,'Fit-Gap'!$L$2:$L$400,"XL") -> 0 | G31: =SUM(C31:F31) -> 1
B32: Integration | C32: =COUNTIFS('Fit-Gap'!$K$2:$K$400,$B32,'Fit-Gap'!$L$2:$L$400,"S") -> 0 | D32: =COUNTIFS('Fit-Gap'!$K$2:$K$400,$B32,'Fit-Gap'!$L$2:$L$400,"M") -> 0 | E32: =COUNTIFS('Fit-Gap'!$K$2:$K$400,$B32,'Fit-Gap'!$L$2:$L$400,"L") -> 1 | F32: =COUNTIFS('Fit-Gap'!$K$2:$K$400,$B32,'Fit-Gap'!$L$2:$L$400,"XL") -> 0 | G32: =SUM(C32:F32) -> 1
B33: Non-Package Placement | C33: =COUNTIFS('Fit-Gap'!$K$2:$K$400,$B33,'Fit-Gap'!$L$2:$L$400,"S") -> 1 | D33: =COUNTIFS('Fit-Gap'!$K$2:$K$400,$B33,'Fit-Gap'!$L$2:$L$400,"M") -> 4 | E33: =COUNTIFS('Fit-Gap'!$K$2:$K$400,$B33,'Fit-Gap'!$L$2:$L$400,"L") -> 2 | F33: =COUNTIFS('Fit-Gap'!$K$2:$K$400,$B33,'Fit-Gap'!$L$2:$L$400,"XL") -> 0 | G33: =SUM(C33:F33) -> 7
B34: Placement | C34: =COUNTIFS('Fit-Gap'!$K$2:$K$400,$B34,'Fit-Gap'!$L$2:$L$400,"S") -> 5 | D34: =COUNTIFS('Fit-Gap'!$K$2:$K$400,$B34,'Fit-Gap'!$L$2:$L$400,"M") -> 3 | E34: =COUNTIFS('Fit-Gap'!$K$2:$K$400,$B34,'Fit-Gap'!$L$2:$L$400,"L") -> 0 | F34: =COUNTIFS('Fit-Gap'!$K$2:$K$400,$B34,'Fit-Gap'!$L$2:$L$400,"XL") -> 0 | G34: =SUM(C34:F34) -> 8
B35: Platform | C35: =COUNTIFS('Fit-Gap'!$K$2:$K$400,$B35,'Fit-Gap'!$L$2:$L$400,"S") -> 2 | D35: =COUNTIFS('Fit-Gap'!$K$2:$K$400,$B35,'Fit-Gap'!$L$2:$L$400,"M") -> 2 | E35: =COUNTIFS('Fit-Gap'!$K$2:$K$400,$B35,'Fit-Gap'!$L$2:$L$400,"L") -> 0 | F35: =COUNTIFS('Fit-Gap'!$K$2:$K$400,$B35,'Fit-Gap'!$L$2:$L$400,"XL") -> 0 | G35: =SUM(C35:F35) -> 4
... B41: Workflow | C41: =COUNTIFS('Fit-Gap'!$K$2:$K$400,$B41,'Fit-Gap'!$L$2:$L$400,"S") -> 6 | D41: =COUNTIFS('Fit-Gap'!$K$2:$K$400,$B41,'Fit-Gap'!$L$2:$L$400,"M") -> 6 | E41: =COUNTIFS('Fit-Gap'!$K$2:$K$400,$B41,'Fit-Gap'!$L$2:$L$400,"L") -> 1 | F41: =COUNTIFS('Fit-Gap'!$K$2:$K$400,$B41,'Fit-Gap'!$L$2:$L$400,"XL") -> 0 | G41: =SUM(C41:F41) -> 13
B42: Total | C42: =SUM(C24:C41) -> 51 | D42: =SUM(D24:D41) -> 54 | E42: =SUM(E24:E41) -> 11 | F42: =SUM(F24:F41) -> 1 | G42: =SUM(G24:G41) -> 117
B44: Open questions answered | C44: =COUNTA('Open Questions'!$E$2:$E$200)&" of "&COUNTA('Open Questions'!$A$2:$A$200) -> 0 of 44

Sheet Fit-Gap
A1: BR ID | B1: Area | C1: Persona | D1: Requirement | E1: Key acceptance criteria | F1: Legacy BRD IDs | G1: Source | H1: Fit | I1: Current BrokerVerse capability | J1: Proposed solution | K1: Target module | L1: Effort | M1: Questions | N1: BDOI concurrence | O1: BDOI comments
A2: BRNB.001 | B2: Product lines & product rules | C2: System | D2: Other Lines follow the same workflow as Fire and Motor (quotation -> client/account -> placement -> billing -> issuance -> reporting) | E2: Product codes mapped/validated at creation; workflow steps mirror Fire & Motor; mis-mapping logged | G2: NB Addendum - Other Lines & Non-Package (Dec-2025) pp.45-90 | H2: CHANGE | I2: Product master with line of business; one underwriting workflow for all products | J2: Product master keyed by BDOI risk code (CAR00..TRP03, MTRxx, PARxx) and product line / cover type; single NB workflow engine shared by all lines | K2: Product & Rules | L2: M | M2: Q01
A3: BRNB.002 | B3: Product lines & product rules | C3: System | D3: Capture critical (product-specific) fields | E3: All product-specific fields stored; no missing/incorrect entries | G3: NB Addendum - Other Lines & Non-Package (Dec-2025) pp.45-90 | H3: CHANGE | I3: Risk details per policy (generic + marine details) | J3: Product-driven risk schema: field definitions per product line (motor vehicle, property location, engineering project, liability, marine, PA insured persons ...) | K3: Product & Rules | L3: L | M3: Q02
A4: BRNB.003 | B4: Product lines & product rules | C4: System | D4: Apply validation rules by product type | E4: Rules applied dynamically by product; invalid data prevented | G4: NB Addendum - Other Lines & Non-Package (Dec-2025) pp.45-90 | H4: CHANGE | I4: Bean validation + underwriting rules (fixed in code) | J4: Configurable rule set per product (mandatory, LOV, range, cross-field) evaluated server-side and mirrored in UI | K4: Product & Rules | L4: M | M4: Q02
A5: BRNB.004 | B5: Product lines & product rules | C5: Marketing | D5: Shared templates with dynamic fields; standard intake template for quotation/proposal (updated in workshop: package + non-package, versioned) | E5: Templates auto-populate product data; completeness validated before creation; template versioning maintained | G5: NB Workshop Addendum (Apr-2026) pp.1-44 / NB Addendum - Other Lines & Non-Package (Dec-2025) pp.45-90 | H5: NEW | I5: Report/PDF rendering exists; no document template engine | J5: Versioned document & intake template library (HTML->PDF / XLSX) with merge fields per product; intake template version stamped on each quotation | K5: Documents | L5: L | M5: Q03
A6: BRNB.093 | B6: Product lines & product rules | C6: Marketing | D6: Data standards for risk information (vehicle, property, address) | E6: Product matrix defines minimum fields per line; incomplete data fails validation; required fields configurable per LOB | G6: NB Workshop Addendum (Apr-2026) pp.1-44 | H6: CHANGE | I6: Fixed mandatory fields | J6: Minimum-field matrix per product line held in product master (loaded from BDOI product matrix MTR/PAR files) | K6: Product & Rules | L6: M | M6: Q02
A7: BRNB.098 | B7: Product lines & product rules | C7: TSU | D7: Rule-based TSU involvement (package vs non-package, fleet thresholds, single vs multiple locations, endorsements) | E7: Criteria defined; system routes/flags TSU cases; TSU actions logged | G7: NB Workshop Addendum (Apr-2026) pp.1-44 | H7: NEW | I7: Approval limits by amount only | J7: Routing rules table (product class, fleet count, location count, TSI threshold, endorsement type) -> TSU queue | K7: Workflow | L7: M | M7: Q04
A8: BRNB.005 | B8: Non-package placement (PRF / QS / TSU) | C8: Marketing AO | D8: Create Proposal Request Form (PRF) with complete risk details and attachments for quotation to insurers | E8: Create/edit/track PRF; TL/TH/UH approval before TSU; blocked if details/attachments missing; unique sequential ref; notifications; insurers have no system access | G8: NB Addendum - Other Lines & Non-Package (Dec-2025) pp.45-90 | H8: NEW | I8: Quotation with approval exists (insurer-side) | J8: PRF entity + screen; approval chain Marketing TL -> TH -> UH; mandatory-document checklist per product; submit to TSU queue | K8: Non-Package Placement | L8: L | M8: Q05
A9: BRNB.006 | B9: Non-package placement (PRF / QS / TSU) | C9: System | D9: Automatic unique sequential marketing reference number for each PRF | E9: Unique, gap-free, not editable, displayed everywhere, logged | G9: NB Addendum - Other Lines & Non-Package (Dec-2025) pp.45-90 | H9: CHANGE | I9: Document numbering series exist (quotation/policy numbers) | J9: New numbering series MKT-YYYY-nnnnnn; gap-free DB sequence per year; immutable | K9: Non-Package Placement | L9: S
A10: BRNB.007 | B10: Non-package placement (PRF / QS / TSU) | C10: TSU | D10: Receive / view PRF requests; amend, update, return (with reason) or delete | E10: Filter by type/status; view returns with reasons; edit & resubmit; notifications | G10: NB Addendum - Other Lines & Non-Package (Dec-2025) pp.45-90 | H10: NEW | I10: Approval inbox (approve/reject only) | J10: TSU work queue with actions Accept / Return (reason LOV) / Update / Delete (in-process only) | K10: Non-Package Placement | L10: M
A11: BRNB.008 | B11: Non-package placement (PRF / QS / TSU) | C11: TSU | D11: Prepare and send Quotation Slip (QS) to selected insurers with terms and conditions | E11: QS generated from validated PRF; TSU edits; internal approval before send; system e-mail to selected insurers; full communication log; resend | G11: NB Addendum - Other Lines & Non-Package (Dec-2025) pp.45-90 | H11: NEW | I11: No outbound e-mail | J11: QS document from template; insurer panel selection; approval; outbound e-mail service with delivery log (recipient, time, body, attachment hash) | K11: Non-Package Placement | L11: L | M11: Q06
A12: BRNB.009 | B12: Non-package placement (PRF / QS / TSU) | C12: TSU | D12: Key-in insurer feedback / terms, editable by authorised users | E12: Entry & edit of insurer responses; changes tracked | G12: NB Addendum - Other Lines & Non-Package (Dec-2025) pp.45-90 | H12: NEW | I12: Quotation iterations (single insurer view) | J12: Insurer response grid per QS (premium, rate, deductibles, conditions, validity) with version history | K12: Non-Package Placement | L12: M
A13: BRNB.010 | B13: Non-package placement (PRF / QS / TSU) | C13: System | D13: Automatically compile insurer feedback into an exportable comparative table | E13: Always current; export Excel/PDF | G13: NB Addendum - Other Lines & Non-Package (Dec-2025) pp.45-90 | H13: NEW | I13: - | J13: Comparative table view generated from insurer responses; XLSX/PDF export; recommended insurer flag | K13: Non-Package Placement | L13: M
A14: BRNB.011 | B14: Non-package placement (PRF / QS / TSU) | C14: Marketing / TSU | D14: Placement Update Reports (individual and collective) | E14: Complete, timely, role-restricted | G14: NB Addendum - Other Lines & Non-Package (Dec-2025) pp.45-90 | H14: NEW | I14: Report framework (role-based, XLSX/CSV/PDF) | J14: New report on report framework | K14: Reports | L14: S
A15: BRNB.012 | B15: Non-package placement (PRF / QS / TSU) | C15: Marketing / TSU | D15: Dashboard for real-time tracking of requests, reports and comparative tables | E15: Filter, customise, export by access level | G15: NB Addendum - Other Lines & Non-Package (Dec-2025) pp.45-90 | H15: CHANGE | I15: Dashboard module (finance KPIs) | J15: NB operations dashboard: requests by status/age/unit, SLA breaches, drill-down | K15: Reports | L15: M
A16: BRNB.013 | B16: Non-package placement (PRF / QS / TSU) | C16: System | D16: Password protection / encryption of all outbound documents (QS, PS, advisories, comparative tables, placement update, renewal request reports) | E16: Only authorised recipients open documents | G16: NB Addendum - Other Lines & Non-Package (Dec-2025) pp.45-90 | H16: NEW | I16: - | J16: PDF AES-256 password protection (and password-protected XLSX); password per convention; password sent in separate e-mail | K16: Documents | L16: M | M16: Q07
A17: BRNB.014 | B17: Non-package placement (PRF / QS / TSU) | C17: System | D17: Validation and multi-level approval enforced before documents are sent | E17: Nothing sent without passing validation and approvals | G17: NB Addendum - Other Lines & Non-Package (Dec-2025) pp.45-90 | H17: CHANGE | I17: Maker-checker with authorization limits | J17: Configurable multi-level approval chains per document type; send action disabled until approved | K17: Workflow | L17: M | M17: Q05
A18: BRNB.015 | B18: Non-package placement (PRF / QS / TSU) | C18: System | D18: Notifications on status changes and integration with BDOI tracking/reporting | E18: Timely notifications; data synchronised with BDOI systems | G18: NB Addendum - Other Lines & Non-Package (Dec-2025) pp.45-90 | H18: CHANGE | I18: In-app alerts | J18: Notification service: in-app + e-mail per event/role; integration via file/API outbox | K18: Workflow | L18: M | M18: Q08
A19: BRNB.016 | B19: Non-package placement (PRF / QS / TSU) | C19: System | D19: Audit trail for all actions and changes | E19: Complete audit trail per request/document | G19: NB Addendum - Other Lines & Non-Package (Dec-2025) pp.45-90 | H19: FIT | I19: Immutable audit trail (DB-enforced) with before/after values | J19: Extend audit coverage to new entities; audit viewer per record | K19: Platform | L19: S
A20: BRNB.017 | B20: Non-package placement (PRF / QS / TSU) | C20: TSU | D20: Generate Proposal Slip for non-package placement after approvals; archive and retrieve | E20: PS keeps QS terms; sent to Marketing only after approvals; archived & searchable | G20: NB Addendum - Other Lines & Non-Package (Dec-2025) pp.45-90 | H20: NEW | I20: - | J20: Proposal Slip document from accepted insurer terms; approval; stored as versioned document | K20: Non-Package Placement | L20: M
A21: BRNB.018 | B21: Non-package placement (PRF / QS / TSU) | C21: TSU | D21: Late Renewal Requests Report (renewals received after expiry) | E21: Scheduled, role-restricted, flags documentation needed | G21: NB Addendum - Other Lines & Non-Package (Dec-2025) pp.45-90 | H21: CHANGE | I21: Renewal due report exists | J21: Scheduled late-renewal report (renewal request date > expiry) | K21: Reports | L21: S | M21: Q09
A22: BRNB.019 | B22: Workflow, status & governance | C22: Authorised user | D22: Delete prospect/account records that are still in-process (not finalised/posted/in active workflow) | E22: Role-restricted; confirmation + reason; logged; excluded from searches/reports but kept in audit; finalised records blocked | G22: NB Addendum - Other Lines & Non-Package (Dec-2025) pp.45-90 | H22: CHANGE | I22: Draft delete for some entities; no soft delete | J22: Soft-delete (VOIDED) with reason for in-process records; audit retained | K22: Platform | L22: S
A23: BRNB.020 | B23: Quotation / proposal | C23: Authorised user | D23: Edit quotation/proposal before approval/finalisation with version history | E23: Only Draft / For Review editable; validation on save; edit logged; status returns to For Review | G23: NB Addendum - Other Lines & Non-Package (Dec-2025) pp.45-90 | H23: CHANGE | I23: Quotation iterations + draft edit | J23: Quotation versioning (v1..vn) with diff view | K23: Quotation | L23: S
A24: BRNB.021 | B24: Quotation / proposal | C24: Approver | D24: Approve/reject quotation/proposal before sending to client or account creation | E24: Full details + history; comments; approved locked and routed | G24: NB Addendum - Other Lines & Non-Package (Dec-2025) pp.45-90 | H24: FIT | I24: Quotation approval with authorization limit and comments | J24: Re-use; add lock + routing to next stage | K24: Quotation | L24: S
A25: BRNB.022 | B25: Workflow, status & governance | C25: System | D25: Automatic status tracking (Received, In Process, Sent to Client, Accepted, Rejected, Account Created, Submitted for Placement, Booked, Cancelled, Endorsed); workshop update: defined stages and allowed transitions | E25: Status history with user/time; auto updates; downloadable status reports; stage list and allowed transitions enforced | F25: BRD 1.3.13.1.2 | G25: NB Workshop Addendum (Apr-2026) pp.1-44 / NB Addendum - Other Lines & Non-Package (Dec-2025) pp.45-90 | H25: NEW | I25: Per-entity status enums (Draft/Pending/Approved/...) | J25: Workflow engine: configurable stage & status model per transaction type, transition table, status history table, SLA timers | K25: Workflow | L25: L | M25: Q10
A26: BRNB.023 | B26: Bulk intake & source systems | C26: Marketing | D26: Receive quotation requests for home insurance directly from HLS (Home Loan System) | E26: Auto-create quotation per valid HLS request; source logged; format validated; bulk & individual; non-HLS files rejected/flagged | F26: BRD 1.1.2.1, 2.1.2.1 | G26: NB Addendum - Other Lines & Non-Package (Dec-2025) pp.45-90 | H26: NEW | I26: - | J26: HLS inbound interface (SFTP file or REST) with source signature check, staging table, validation and auto quotation creation | K26: Integration | L26: L | M26: Q11
A27: BRNB.041 | B27: Quotation / proposal | C27: Marketing | D27: Receive quotation/proposal request via e-mail or system-triggered request | E27: Both channels supported | F27: BRD 1.1.2.1, 2.1.2.1 | G27: NB Fire & Motor - BRD ID consolidation (Dec-2025) pp.91-129 | H27: NEW | I27: - | J27: Request intake: manual capture of e-mailed requests (attach e-mail) + system channel (HLS/API) | K27: Intake | L27: M | M27: Q12
A28: BRNB.024 | B28: Quotation / proposal | C28: Marketing | D28: Receive single/multiple accepted quotations; update them via file upload or manually | E28: XLSX upload matched by reference; invalid rows rejected with reasons; summary report | F28: BRD 1.1.4.1 | G28: NB Addendum - Other Lines & Non-Package (Dec-2025) pp.45-90 | H28: NEW | I28: No bulk update upload | J28: Generic bulk-upload framework (template download, validate, partial commit, error report) - used by all bulk features | K28: Bulk Processing | L28: L
A29: BRNB.028 | B29: Bulk intake & source systems | C29: System | D29: Create bulk quotations from source-system request details (integration or manual upload) | E29: Mapping, doc linking, validation, per-row feedback, duplicate prevention, integration log, authorised only | F29: BRD 1.3.1.1.2 | G29: NB Addendum - Other Lines & Non-Package (Dec-2025) pp.45-90 | H29: NEW | I29: - | J29: Bulk quotation job on bulk-upload framework | K29: Bulk Processing | L29: M | M29: Q11
A30: BRNB.029 | B30: Quotation / proposal | C30: System | D30: Quotation requires a client code (minimum prospect data); incomplete client info flagged; downstream blocked until complete | E30: Save with client code only; flag incomplete; booking/issuance blocked until complete | F30: BRD 1.3.1.1.3 | G30: NB Addendum - Other Lines & Non-Package (Dec-2025) pp.45-90 | H30: CHANGE | I30: Quotation requires a full party | J30: Prospect-level party with minimum fields + completeness flag; gate at placement/booking | K30: Client | L30: S | M30: Q13
A31: BRNB.063 | B31: Bulk intake & source systems | C31: System | D31: Create bulk quotation/proposal from received requests / uploaded list / source system; allow creation without client code; generate reference | E31: As listed | F31: BRD 1.3.1.1-1.3.1.2 | G31: NB Fire & Motor - BRD ID consolidation (Dec-2025) pp.91-129 | H31: NEW | I31: - | J31: Bulk quotation job; note conflict with BRNB.029 (client code required) - see Q13 | K31: Bulk Processing | L31: M | M31: Q13
A32: BRNB.064 | B32: Bulk intake & source systems | C32: System | D32: Generate accounts for bulk processing from source system or manual upload (.xlsx/.ods); sanitise list by defined criteria; push to next stage | E32: As listed | F32: BRD 1.3.2.1-1.3.2.3 | G32: NB Fire & Motor - BRD ID consolidation (Dec-2025) pp.91-129 | H32: NEW | I32: - | J32: Bulk account job with sanitisation rules (trim, case, format, dedupe, LOV mapping) | K32: Bulk Processing | L32: M | M32: Q14
A33: BRNB.039 | B33: Bulk intake & source systems | C33: User | D33: Accept manually uploaded accounts for bulk processing using the standard template | E33: Template enforced & downloadable; .xlsx/.csv; valid rows processed, error report for failed rows; summary | F33: BRD 1.3.2.2 | G33: NB Addendum - Other Lines & Non-Package (Dec-2025) pp.45-90 | H33: NEW | I33: - | J33: Bulk-upload framework | K33: Bulk Processing | L33: S
A34: BRNB.042 | B34: Bulk intake & source systems | C34: Marketing | D34: Create quotation/proposal for bulk processing (IDF, FFYMI ...), generate reference, send single/multiple | E34: As listed | F34: BRD 1.1.3.1-1.1.3.3 | G34: NB Fire & Motor - BRD ID consolidation (Dec-2025) pp.91-129 | H34: NEW | I34: - | J34: Bulk quotation + batch send | K34: Bulk Processing | L34: M
A35: BRNB.044 | B35: Bulk intake & source systems | C35: Marketing | D35: Manually build accounts for bulk processing (receive accepted quotes, download PDF/XLSX, create client/account upload list, upload docs, search client) | E35: As listed | F35: BRD 1.1.4.1-1.1.4.5 | G35: NB Fire & Motor - BRD ID consolidation (Dec-2025) pp.91-129 | H35: NEW | I35: - | J35: Bulk-upload framework + account list builder | K35: Bulk Processing | L35: M
A36: BRNB.043 | B36: Quotation / proposal | C36: Marketing | D36: Create individual quotation/proposal (IDF, FFYMI), reference number, send via e-mail, receive acceptance, download PDF/XLSX, save | E36: As listed | F36: BRD 2.1.3.1-2.1.3.6 | G36: NB Fire & Motor - BRD ID consolidation (Dec-2025) pp.91-129 | H36: CHANGE | I36: Quotation create/approve/print | J36: Broker quotation per product with premium calc (Appendix A), PDF/XLSX output, e-mail to client, acceptance capture | K36: Quotation | L36: M
A37: BRNB.045 | B37: Quotation / proposal | C37: Marketing | D37: Receive client's e-mail acceptance and create list of accounts (individual) | E37: As listed | F37: BRD 2.1.4.1-2.1.4.2 | G37: NB Fire & Motor - BRD ID consolidation (Dec-2025) pp.91-129 | H37: NEW | I37: Convert quotation to policy | J37: Acceptance capture (upload acceptance e-mail) -> create account(s) from quotation | K37: Quotation | L37: S
A38: BRNB.102 | B38: Quotation / proposal | C38: Marketing / Ops | D38: One unique reference number per account from quotation, reused through processing, booking, issuance, invoicing | E38: Generated at quotation; unchanged downstream; shown on all screens/reports/interfaces | G38: NB Workshop Addendum (Apr-2026) pp.1-44 | H38: CHANGE | I38: Separate quotation and policy numbers | J38: Account Reference Number (ARN) as golden key carried on every child record, report and interface | K38: Account | L38: M | M38: Q15
A39: BRNB.030 | B39: Client (CRM, onboarding, KYC) | C39: User / System | D39: Create client or update existing (bank standards); dedupe; flag invalid; upload KYC docs (internal & external sources); drafts; unique client code; push to next stage | E39: As listed | F39: BRD 1.3.3.x, 2.1.5.x | G39: NB Addendum - Other Lines & Non-Package (Dec-2025) pp.45-90 | H39: CHANGE | I39: Party master with approval, TIN, addresses | J39: Client master: individual/corporate KYC fields per BDO standard, dedupe keys, draft state, client code series, document checklist | K39: Client | L39: M | M39: Q16
A40: BRNB.032 | B40: Client (CRM, onboarding, KYC) | C40: User | D40: Prevent duplicate clients/accounts for Fire, Motor, Other Lines; allow flagged duplicates for endorsements | E40: Keys: name+DOB, e-mail, phone, ID; block before save; endorsement duplicates flagged; attempts logged | F40: BRD 1.3.4.1.3, 2.1.8.1.5, 2.3.10.2 | G40: NB Addendum - Other Lines & Non-Package (Dec-2025) pp.45-90 | H40: CHANGE | I40: Party TIN uniqueness | J40: Duplicate-detection service (exact + fuzzy name) returning matches with reference numbers | K40: Client | L40: M | M40: Q17
A41: BRNB.046 | B41: Client (CRM, onboarding, KYC) | C41: Marketing / Processing | D41: Search clients by single/multiple criteria and view full details | E41: As listed | F41: BRD 1.1.5.1, 1.2.2.1, 2.1.6.1, 2.2.1.2.1 | G41: NB Fire & Motor - BRD ID consolidation (Dec-2025) pp.91-129 | H41: FIT | I41: Party search with filters | J41: Add criteria (ID no., mobile, e-mail, client code, status) | K41: Client | L41: S
A42: BRNB.047 | B42: Client (CRM, onboarding, KYC) | C42: Marketing | D42: Update client details in bulk with validation, draft, cancel, push | E42: As listed | F42: BRD 1.1.6.1-1.1.6.4 | G42: NB Fire & Motor - BRD ID consolidation (Dec-2025) pp.91-129 | H42: NEW | I42: - | J42: Bulk client update upload | K42: Client | L42: S
A43: BRNB.048 | B43: Client (CRM, onboarding, KYC) | C43: Marketing | D43: Create client (individual) with validation, documents, draft, cancel, client code, push | E43: As listed | F43: BRD 2.1.5.1-2.1.5.6 | G43: NB Fire & Motor - BRD ID consolidation (Dec-2025) pp.91-129 | H43: CHANGE | I43: Party create + approval | J43: See BRNB.030 | K43: Client | L43: S
A44: BRNB.049 | B44: Client (CRM, onboarding, KYC) | C44: Marketing | D44: Update client (individual) with documents, draft, cancel, push | E44: As listed | F44: BRD 2.1.7.1-2.1.7.5 | G44: NB Fire & Motor - BRD ID consolidation (Dec-2025) pp.91-129 | H44: CHANGE | I44: Party edit + approval | J44: Draft + document upload on client | K44: Client | L44: S
A45: BRNB.065 | B45: Client (CRM, onboarding, KYC) | C45: System | D45: Auto-create clients not yet existing / auto-update existing (bank standard) during bulk; flag invalid; drafts; client codes | E45: As listed | F45: BRD 1.3.3.1-1.3.3.6 | G45: NB Fire & Motor - BRD ID consolidation (Dec-2025) pp.91-129 | H45: NEW | I45: - | J45: Client upsert step in bulk job using dedupe keys | K45: Bulk Processing | L45: M | M45: Q16
A46: BRNB.090 | B46: Client (CRM, onboarding, KYC) | C46: Marketing / Ops | D46: Standard client onboarding step before any new business | E46: Onboarding is a prerequisite; outcome = verified client; audit | G46: NB Workshop Addendum (Apr-2026) pp.1-44 | H46: CHANGE | I46: Party approval (maker-checker) | J46: Onboarding workflow: Prospect -> KYC verified -> Confirmed client; quotation/booking gates | K46: Client | L46: M | M46: Q16
A47: BRNB.091 | B47: Client (CRM, onboarding, KYC) | C47: All users | D47: Client-level and account-level tags and special instructions applied across servicing, collections, processing | E47: Controlled values; captured/viewed by role; enforced/shown in processes; change log; history | G47: NB Workshop Addendum (Apr-2026) pp.1-44 | H47: NEW | I47: - | J47: Tag LOV + special-instruction notes on client/account; banner on every related screen; history | K47: Client | L47: M | M47: Q18
A48: BRNB.099 | B48: Client (CRM, onboarding, KYC) | C48: Processing | D48: CRM-like view: leads, prospects, special instructions; linkage client-account-policy visible; missing linkage flagged | E48: Linked identifiers shown; changes logged; missing linkage flagged | G48: NB Workshop Addendum (Apr-2026) pp.1-44 | H48: NEW | I48: - | J48: Client 360 page (accounts, policies, documents, instructions, activity timeline) | K48: Client | L48: M | M48: Q19
A49: BRNB.101 | B49: Client (CRM, onboarding, KYC) | C49: Marketing | D49: Distinct identifier for prospect vs confirmed clients; traceable conversion | E49: Distinct IDs; explicit status; conversion keeps history; logged | G49: NB Workshop Addendum (Apr-2026) pp.1-44 | H49: NEW | I49: - | J49: Client status PROSPECT/CONFIRMED; prospect code P-nnnn converted to client code C-nnnn (both retained) | K49: Client | L49: S | M49: Q20
A50: BRNB.110 | B50: Client (CRM, onboarding, KYC) | C50: Marketing | D50: Monthly list of non-bank clients due for KYC review | E50: Notification when list ready; view in shared path; download/print; filter | G50: NB Workshop Addendum (Apr-2026) pp.1-44 | H50: NEW | I50: Monitored job framework | J50: KYC review-date per client + monthly job producing report + notification | K50: Client | L50: S | M50: Q21
A51: BRNB.025 | B51: Account (risk record) | C51: User | D51: Update account(s) - bulk and individual upload/entry, validate mandatory fields, draft, submit | E51: Bulk: match by ID, error report, summary; individual: immediate confirmation | F51: BRD 1.1.8.x, 1.2.4.1, 2.1.10.x, 2.2.1.4.1.1 | G51: NB Addendum - Other Lines & Non-Package (Dec-2025) pp.45-90 | H51: NEW | I51: - | J51: Account entity + bulk update | K51: Account | L51: M
A52: BRNB.050 | B52: Account (risk record) | C52: Marketing / Processing | D52: Search accounts by single/multiple criteria and view full details | E52: As listed | F52: BRD 1.1.7.1, 1.2.3.1, 2.1.9.1, 2.2.1.3.1 | G52: NB Fire & Motor - BRD ID consolidation (Dec-2025) pp.91-129 | H52: CHANGE | I52: Policy search | J52: Account search (ARN, PN no., plate, engine, chassis, location, client, status, insurer) | K52: Account | L52: S
A53: BRNB.051 | B53: Account (risk record) | C53: Marketing | D53: Create account (individual): multi-value fields, currency, auto calculations (pro-rata, short-term, period), duplicate fall-out (motor vehicle IDs / fire client+location+items), link client, docs, auto status, reference, draft, cancel, push | E53: As listed incl. CTPL vs MTR exception and fall-out report with existing reference | F53: BRD 2.1.8.1-2.1.8.8 | G53: NB Fire & Motor - BRD ID consolidation (Dec-2025) pp.91-129 | H53: CHANGE | I53: Policy with risks, currency, premium calculator, cover period | J53: Account (placement record) with multi-risk items, FX, calculator per Appendix A, duplicate rules per line | K53: Account | L53: L | M53: Q22
A54: BRNB.052 | B54: Account (risk record) | C54: Marketing / Processing | D54: Update account (bulk) with validation, multi-values, auto calculation, draft, cancel, push | E54: As listed | F54: BRD 1.1.8.1-1.1.8.4, 1.2.4.x | G54: NB Fire & Motor - BRD ID consolidation (Dec-2025) pp.91-129 | H54: NEW | I54: - | J54: Bulk update | K54: Account | L54: S
A55: BRNB.053 | B55: Account (risk record) | C55: Marketing | D55: Update account (individual) incl. document upload | E55: As listed | F55: BRD 2.1.10.1-2.1.10.5 | G55: NB Fire & Motor - BRD ID consolidation (Dec-2025) pp.91-129 | H55: CHANGE | I55: Policy draft edit | J55: Account edit | K55: Account | L55: S
A56: BRNB.054 | B56: Account (risk record) | C56: Processing | D56: Update account (individual) - processing | E56: As listed | F56: BRD 2.2.1.4.1-2.2.1.4.4 | G56: NB Fire & Motor - BRD ID consolidation (Dec-2025) pp.91-129 | H56: CHANGE | I56: Policy draft edit | J56: Account edit with role-specific fields | K56: Account | L56: S
A57: BRNB.066 | B57: Account (risk record) | C57: System | D57: Auto-create accounts in bulk: validation, multi-values, currency, dedupe fall-out, link client, receive docs with naming, auto status, auto-save draft, reference, associate quotation ref, push | E57: As listed | F57: BRD 1.3.4.1-1.3.4.7 | G57: NB Fire & Motor - BRD ID consolidation (Dec-2025) pp.91-129 | H57: NEW | I57: - | J57: Bulk account creation job | K57: Bulk Processing | L57: M | M57: Q22
A58: BRNB.109 | B58: Account (risk record) | C58: Marketing | D58: Account-level contact details used for communication; default from client level | E58: Account contacts used in e-mails/letters; editable; logged | G58: NB Workshop Addendum (Apr-2026) pp.1-44 | H58: NEW | I58: Party addresses/contacts | J58: Account contact block defaulted from client | K58: Account | L58: S
A59: BRNB.026 | B59: Documents | C59: User | D59: Upload single/multiple files (.jpg .xlsx .ods .pdf ...), inherit or nominate file name (syntax), size limits, link to account(s), remove | E59: Type/size validated; linked; view/download/remove; no performance degradation; .exe blocked | F59: BRD 1.1.9.x, 2.1.11.x, 2.2.1.7.x, 2.3.3.x | G59: NB Addendum - Other Lines & Non-Package (Dec-2025) pp.45-90 | H59: CHANGE | I59: Attachments: PDF/PNG/JPEG/XLSX/DOCX/CSV with signature check & virus-scan hook | J59: Add ODS/others, multi-file upload, naming syntax, link one file to many accounts, document type LOV | K59: Documents | L59: S | M59: Q23
A60: BRNB.055 | B60: Documents | C60: Marketing / Processing / System | D60: Upload files/documents (same as BRNB.026) | E60: As listed | F60: BRD 1.1.9.1, 1.2.7.1, 2.1.11.1, 2.2.1.7.1, 2.3.3.1 | G60: NB Fire & Motor - BRD ID consolidation (Dec-2025) pp.91-129 | H60: CHANGE | I60: Attachments | J60: See BRNB.026 | K60: Documents | L60: S
A61: BRNB.056 | B61: Documents | C61: Marketing / Processing | D61: View client-level and account-level documents; download single/multiple; save | E61: As listed | F61: BRD 1.1.10.x, 1.2.8.x, 2.1.12.x, 2.2.1.8.x | G61: NB Fire & Motor - BRD ID consolidation (Dec-2025) pp.91-129 | H61: CHANGE | I61: Attachment list/download per record | J61: Multi-select ZIP download; client + account document tabs | K61: Documents | L61: S
A62: BRNB.104 | B62: Documents | C62: System | D62: Auto-extract details from uploaded documents (e.g. e-policy) and update account after user confirmation | E62: Key fields extracted and mapped; user confirms; update logged with source doc | G62: NB Workshop Addendum (Apr-2026) pp.1-44 | H62: NEW | I62: - | J62: Document extraction service (PDF text + OCR, insurer-specific templates) with review screen | K62: Documents | L62: XL | M62: Q24
A63: BRNB.105 | B63: Documents | C63: System | D63: Uploaded documents trigger defined business processes | E63: Trigger rules; correct workflow started; linked; logged | G63: NB Workshop Addendum (Apr-2026) pp.1-44 | H63: NEW | I63: - | J63: Document-type trigger rules (e.g. e-policy uploaded -> policy number update -> booking) | K63: Workflow | L63: M | M63: Q24
A64: BRNB.033 | B64: Placement with insurers | C64: Marketing | D64: Handle accounts returned by Processing: view, update, comment, push | E64: Returned list; edit; comments; push; notifications; logged | F64: BRD 1.1.13.1 | G64: NB Addendum - Other Lines & Non-Package (Dec-2025) pp.45-90 | H64: NEW | I64: Reject with comment only | J64: Return-to-sender action with reason LOV and return queue | K64: Workflow | L64: S
A65: BRNB.034 | B65: Placement with insurers | C65: Processing | D65: Handle placement requests returned by insurer: update, remarks, return to Marketing AO/TL, receive updates, push | E65: As listed | F65: BRD 1.2.6.1 | G65: NB Addendum - Other Lines & Non-Package (Dec-2025) pp.45-90 | H65: NEW | I65: - | J65: Insurer return capture + return loop Processing <-> Marketing | K65: Placement | L65: M
A66: BRNB.058 | B66: Placement with insurers | C66: Marketing | D66: Handle returned placement request (same as BRNB.033) | E66: As listed | F66: BRD 1.1.13.1-1.1.13.3, 2.1.14.x | G66: NB Fire & Motor - BRD ID consolidation (Dec-2025) pp.91-129 | H66: NEW | I66: - | J66: See BRNB.033 | K66: Workflow | L66: S
A67: BRNB.059 | B67: Placement with insurers | C67: Processing | D67: Handle returned placement request from insurer (same as BRNB.034) | E67: As listed | F67: BRD 1.2.6.2-1.2.6.5, 2.2.1.6.x | G67: NB Fire & Motor - BRD ID consolidation (Dec-2025) pp.91-129 | H67: NEW | I67: - | J67: See BRNB.034 | K67: Placement | L67: S
A68: BRNB.062 | B68: Placement with insurers | C68: Processing | D68: Cancel placement (single/multiple) with comments; auto-tag Cancelled Placement and return to previous stage | E68: As listed | F68: BRD 2.2.1.11.1-2.2.1.11.3 | G68: NB Fire & Motor - BRD ID consolidation (Dec-2025) pp.91-129 | H68: NEW | I68: - | J68: Cancel-placement action (pre-issuance reversal, see BRNB.094) | K68: Placement | L68: S
A69: BRD 2.1.16 | B69: Placement with insurers | C69: Marketing | D69: Reactivate cancelled placed accounts (single/multiple) and move to next stage (listed in role matrix, no BRNB ID) | E69: As listed | F69: BRD 2.1.16, 3.4.2.2.35 | G69: NB Fire & Motor BRD V06162025 pp.130-218 | H69: NEW | I69: - | J69: Reactivate action | K69: Placement | L69: S | M69: Q25
A70: BRNB.069 | B70: Placement with insurers | C70: Processing / System | D70: Generate placement file/slip automatically, individually or in batch; regenerate for returns; only when prerequisites met (workshop update) | E70: Prerequisites defined; blocked when unmet; auditable | F70: BRD 1.3.7.1-1.3.7.2, 2.3.2.1 | G70: NB Workshop Addendum (Apr-2026) pp.1-44 / NB Fire & Motor - BRD ID consolidation (Dec-2025) pp.91-129 | H70: NEW | I70: - | J70: Placement slip per insurer format (XLSX/PDF) with prerequisite checks (paid/confirmed, docs complete, TSU cleared) | K70: Placement | L70: M | M70: Q26
A71: BRNB.071 | B71: Placement with insurers | C71: System | D71: Automatically send placement file/slip to insurer(s); resend for returns | E71: As listed | F71: BRD 1.3.9.1, 2.3.5 | G71: NB Fire & Motor - BRD ID consolidation (Dec-2025) pp.91-129 | H71: NEW | I71: - | J71: Insurer channel config (e-mail / SFTP / API) + send log | K71: Placement | L71: M | M71: Q06
A72: BRNB.072 | B72: Placement with insurers | C72: System | D72: Automatically send 30-day hold-cover request to insurer(s) | E72: As listed | F72: BRD 1.3.10.1, 2.3.6 | G72: NB Fire & Motor - BRD ID consolidation (Dec-2025) pp.91-129 | H72: NEW | I72: - | J72: Hold-cover request document + send | K72: Placement | L72: S | M72: Q27
A73: BRNB.103 | B73: Placement with insurers | C73: Marketing | D73: Record insurer hold-cover confirmation (insurer, reference, date); status visible | E73: Entry; explicit status; logged | G73: NB Workshop Addendum (Apr-2026) pp.1-44 | H73: NEW | I73: - | J73: Hold-cover confirmation capture + expiry monitor | K73: Placement | L73: S | M73: Q27
A74: BRNB.067 | B74: Billing & payment confirmation | C74: System | D74: CBG Fire billing file to CLPC (PN no., loan application no., booking date, borrower, originating unit, premium, reference, BDOI location, amortised Y/N); save .xlsx/.ods; forward to CLPC; receive payment report; match paid/unpaid by PN or loan application no.; push paid | E74: As listed | F74: BRD 1.3.5.1-1.3.5.6 | G74: NB Fire & Motor - BRD ID consolidation (Dec-2025) pp.91-129 | H74: NEW | I74: Receivables module (open items, receipts) | J74: CLPC outbound billing file + inbound payment report matcher; creates premium receivable/receipt entries | K74: Billing & Collection | L74: L | M74: Q28
A75: BRNB.068 | B75: Billing & payment confirmation | C75: System | D75: Validate payment for other market segments by matching payment reports on reference number | E75: As listed | F75: BRD 1.3.6, 2.3.1 | G75: NB Fire & Motor - BRD ID consolidation (Dec-2025) pp.91-129 | H75: CHANGE | I75: Receipt matching to open items | J75: Payment-report import + auto-match on ARN; payment gate per segment (CBG Fire & Motor paid; Other Lines client confirmation) | K75: Billing & Collection | L75: M | M75: Q28
A76: BRNB.114 | B76: Billing & payment confirmation | C76: Marketing | D76: Identify and tag accounts paid directly to insurers (Direct Payment) | E76: Configurable criteria; auto/manual tag; role-based edit; list; logged; visible in billing/accounting; downstream use | G76: NB Workshop Addendum (Apr-2026) pp.1-44 | H76: NEW | I76: - | J76: Payment-arrangement attribute (via BDOI / direct to insurer) driving billing and commission receivable | K76: Billing & Collection | L76: M | M76: Q29
A77: BRNB.035 | B77: E-policy & insurance advice | C77: System / User | D77: Encrypt and password-protect Insurance Advice and e-policies before sending; password standard or generated; password in separate e-mail; single & bulk | E77: As listed | F77: BRD 1.1.14.4.1, 1.4.1.2.1.1.1, 2.1.15.4.1, 2.4.1.2.1.1.1 | G77: NB Addendum - Other Lines & Non-Package (Dec-2025) pp.45-90 | H77: NEW | I77: - | J77: See BRNB.013 + outbound e-mail | K77: Documents | L77: M | M77: Q07
A78: BRNB.060 | B78: E-policy & insurance advice | C78: Marketing | D78: Access system-generated Insurance Advice: search, list, view, download, save, send single/multiple, encrypt | E78: As listed | F78: BRD 1.1.14.x, 2.1.15.x | G78: NB Fire & Motor - BRD ID consolidation (Dec-2025) pp.91-129 | H78: NEW | I78: - | J78: Insurance Advice register screen | K78: Policy Issuance | L78: M
A79: BRNB.070 | B79: E-policy & insurance advice | C79: System | D79: Generate Insurance Advice (mortgaged accounts only), single or multiple | E79: As listed | F79: BRD 1.3.8.1, 2.3.4 | G79: NB Fire & Motor - BRD ID consolidation (Dec-2025) pp.91-129 | H79: NEW | I79: - | J79: IA document (template) for mortgagee-bank accounts | K79: Policy Issuance | L79: M | M79: Q30
A80: BRNB.095 | B80: E-policy & insurance advice | C80: System | D80: Explicit IA generation trigger rules aligned to lifecycle | E80: Trigger points defined; only when criteria met; logged | G80: NB Workshop Addendum (Apr-2026) pp.1-44 | H80: NEW | I80: - | J80: IA trigger rule (e.g. on placement confirmation / booking) | K80: Policy Issuance | L80: S | M80: Q30
A81: BRNB.073 | B81: E-policy & insurance advice | C81: System | D81: Receive e-policy (PDF) from insurers and save to designated folder | E81: As listed | F81: BRD 1.3.11.1, 2.3.7 | G81: NB Fire & Motor - BRD ID consolidation (Dec-2025) pp.91-129 | H81: NEW | I81: - | J81: E-policy inbox (monitored mailbox / SFTP / upload) matched to account | K81: Policy Issuance | L81: M | M81: Q31
A82: BRNB.074 | B82: E-policy & insurance advice | C82: System | D82: Automatically update policy number and link e-policy artifacts to the account | E82: As listed | F82: BRD 1.3.12.1-1.3.12.2, 2.3.8 | G82: NB Fire & Motor - BRD ID consolidation (Dec-2025) pp.91-129 | H82: NEW | I82: - | J82: Policy number capture (from extraction or insurer file) -> account | K82: Policy Issuance | L82: M | M82: Q24
A83: BRNB.077 | B83: E-policy & insurance advice | C83: E-policy Sender | D83: E-mail e-policy to client, single/multiple, encrypted, attach, advise password syntax | E83: As listed | F83: BRD 1.4.1.2.1, 2.4.1.2 | G83: NB Fire & Motor - BRD ID consolidation (Dec-2025) pp.91-129 | H83: NEW | I83: - | J83: E-policy dispatch screen + batch job | K83: Policy Issuance | L83: M | M83: Q07
A84: BRNB.078 | B84: E-policy & insurance advice | C84: E-policy Sender | D84: Report on successfully/unsuccessfully sent e-policies with reasons, by date range | E84: As listed | F84: BRD 1.4.1.3.1-1.4.1.3.2, 2.4.1.3 | G84: NB Fire & Motor - BRD ID consolidation (Dec-2025) pp.91-129 | H84: NEW | I84: - | J84: E-policy dispatch report from send log | K84: Reports | L84: S
A85: BRNB.027 | B85: Booking, endorsements & cancellation | C85: System | D85: Book accounts (individual/bulk) and positive financial endorsements; on approval auto-post GL entry and generate service invoice on booking date; all linked in audit; failures roll back booking | E85: As listed | F85: BRD 1.2.10.1-1.2.10.4, 2.2.1.10.x | G85: NB Addendum - Other Lines & Non-Package (Dec-2025) pp.45-90 | H85: CHANGE | I85: Accounting engine (event -> rule -> journal), immutable ledger, receivables invoices, VAT | J85: Broker booking event: commission income + VAT on commission, premium receivable from client / payable to insurer (or direct-payment variant); service (commission) invoice to insurer; atomic | K85: Booking & Accounting | L85: L | M85: Q32
A86: BRNB.036 | B86: Booking, endorsements & cancellation | C86: System / User | D86: Individual vs batch booking (manual & bulk upload), scheduled batch trigger (e.g. end-of-day), edit/delete before booking, confirm/cancel | E86: As listed | F86: BRD 1.2.10.x, 1.3.14.x, 2.2.1.10.x, 2.3.10.x | G86: NB Addendum - Other Lines & Non-Package (Dec-2025) pp.45-90 | H86: CHANGE | I86: Monitored job scheduler; single policy approval | J86: Booking batch (select many, scheduled EOD job) with pre-booking confirmation | K86: Booking & Accounting | L86: M
A87: BRNB.038 | B87: Booking, endorsements & cancellation | C87: User | D87: Direct booking without placement (individual/bulk) with documents, validation, confirmation and reports | E87: As listed | G87: NB Addendum - Other Lines & Non-Package (Dec-2025) pp.45-90 | H87: NEW | I87: - | J87: Direct-booking path (see BRNB.111) | K87: Booking & Accounting | L87: M
A88: BRNB.061 | B88: Booking, endorsements & cancellation | C88: Processing | D88: Book accounts manually / bulk; process positive financial endorsements | E88: As listed | F88: BRD 1.2.10.1-1.2.10.4, 2.2.1.10.x | G88: NB Fire & Motor - BRD ID consolidation (Dec-2025) pp.91-129 | H88: CHANGE | I88: Policy approval posting | J88: See BRNB.027 | K88: Booking & Accounting | L88: S
A89: BRNB.076 | B89: Booking, endorsements & cancellation | C89: System | D89: Auto-book on defined criteria (e.g. after e-policy receipt); prevent duplicate booking; financial & non-financial endorsements | E89: As listed | F89: BRD 1.3.14.1-1.3.14.3, 2.3.10.x | G89: NB Fire & Motor - BRD ID consolidation (Dec-2025) pp.91-129 | H89: CHANGE | I89: Endorsements (additional/refund/renewal/cancellation/nil) | J89: Auto-booking rule + idempotent booking key (ARN + transaction no.) | K89: Booking & Accounting | L89: M
A90: BRNB.081 | B90: Booking, endorsements & cancellation | C90: Adjustment | D90: Cancel booking (single/multiple); negative financial and non-financial endorsements | E90: As listed | F90: BRD 3.2.2.1-3.2.2.3 | G90: NB Fire & Motor - BRD ID consolidation (Dec-2025) pp.91-129 | H90: CHANGE | I90: Cancellation & refund endorsements with reversal journals | J90: Booking cancellation reverses commission/receivable entries; credit note to insurer | K90: Booking & Accounting | L90: M
A91: BRNB.094 | B91: Booking, endorsements & cancellation | C91: System | D91: Distinguish true policy cancellation (post-issuance) from internal reversal (pre-issuance / correction) | E91: Defined statuses & conditions; transitions enforced; reason + user/time logged | G91: NB Workshop Addendum (Apr-2026) pp.1-44 | H91: CHANGE | I91: Cancellation endorsement only | J91: Two lifecycle actions: REVERSED (pre-issuance, no insurer impact) vs CANCELLED (post-issuance endorsement) | K91: Workflow | L91: S
A92: BRNB.100 | B92: Booking, endorsements & cancellation | C92: Processing | D92: Service invoice generated from defined template and triggers; owner assigned; per invoice type (insurer / internal) | E92: Only on approved triggers; visible owner; consistent; details per type; traceable | G92: NB Workshop Addendum (Apr-2026) pp.1-44 | H92: CHANGE | I92: Receivables invoice with BIR fields | J92: Service-invoice types (Insurer commission invoice, internal) with trigger rules and owner; BIR-compliant numbering | K92: Booking & Accounting | L92: M | M92: Q32
A93: BRNB.100b | B93: Booking, endorsements & cancellation | C93: Processing | D93: Send generated service invoice to recipients; notify success/failure with reason (unnumbered row in addendum) | E93: Notification of sent/failed; reason; traceable | G93: NB Workshop Addendum (Apr-2026) pp.1-44 | H93: NEW | I93: - | J93: Invoice dispatch via e-mail service + log | K93: Booking & Accounting | L93: S
A94: BRNB.107 | B94: Booking, endorsements & cancellation | C94: System | D94: Incentive eligibility indicator on booked transactions (rule-based) | E94: Evaluated vs rules; stored at booking; visible; override only when authorised; logged | G94: NB Workshop Addendum (Apr-2026) pp.1-44 | H94: NEW | I94: - | J94: Incentive rule table (product, segment, channel, period) -> indicator on booking | K94: Booking & Accounting | L94: M | M94: Q33
A95: BRNB.108 | B95: Booking, endorsements & cancellation | C95: System | D95: Cost center captured for every booked transaction (MIS) | E95: Mandatory; from master data; blocks booking if missing; in reports & interfaces; logged | G95: NB Workshop Addendum (Apr-2026) pp.1-44 | H95: CONFIGURE | I95: Dimensions module (COST_CENTER, PROFIT_CENTER, DEPARTMENT) posted on journals | J95: Make cost center mandatory on booking; default from AO / unit | K95: Booking & Accounting | L95: S | M95: Q34
A96: BRNB.111 | B96: Booking, endorsements & cancellation | C96: Marketing / Processing | D96: Bypass placement and book directly when insurer already issued the policy; issued-policy upload mandatory | E96: Bypass allowed; placement fields optional; at least one policy document mandatory; error if none; stored & linked | G96: NB Workshop Addendum (Apr-2026) pp.1-44 | H96: NEW | I96: - | J96: Direct-booking path with document gate | K96: Booking & Accounting | L96: S
A97: BRNB.112 | B97: Booking, endorsements & cancellation | C97: Marketing / Processing | D97: Book multi-year policies (e.g. 5-year term = 5 policy numbers linked to one booking reference) | E97: Supported; flagged multi-year; all policy numbers linked; audit | G97: NB Workshop Addendum (Apr-2026) pp.1-44 | H97: CHANGE | I97: Single-period policies; renewal creates new period | J97: Multi-year booking with yearly policy-number schedule and per-year commission recognition (Appendix A multi-year formula) | K97: Booking & Accounting | L97: M | M97: Q35
A98: BRNB.113 | B98: Booking, endorsements & cancellation | C98: Marketing | D98: Maintain Free First-Year (FFY) accounts list: upload, tag, edit dates, cancel, auto end date, list, audit | E98: 12 criteria incl. dedupe by serial/motor number, only active accounts, persists, used for renewals | G98: NB Workshop Addendum (Apr-2026) pp.1-44 | H98: NEW | I98: - | J98: FFY attribute + bulk tagging + FFY register | K98: Account | L98: M | M98: Q36
A99: BRNB.092 | B99: Workflow, status & governance | C99: Business unit | D99: Defined authoritative source of truth per data element (client, vehicle, property, address, policy, invoice) | E99: List of sources incl. fallback; read-only vs editable enforced; conflicts flagged | G99: NB Workshop Addendum (Apr-2026) pp.1-44 | H99: NEW | I99: - | J99: Data-ownership register + field-level source/lock metadata | K99: Platform | L99: M | M99: Q37
A100: BRNB.096 | B100: Workflow, status & governance | C100: System | D100: Marketing submissions are the official trigger for Processing (like GRF/ARF requests) | E100: Single Processing inbox with status, date, originating unit; tracked; logged | G100: NB Workshop Addendum (Apr-2026) pp.1-44 | H100: NEW | I100: Approval inbox | J100: Processing request queue | K100: Workflow | L100: M | M100: Q38
...

Sheet Target Workflow
A1: Stage | B1: Stage name | C1: Owner | D1: Meaning | E1: Allowed next | F1: BDOI concurrence | G1: BDOI comments
A2: S01 | B2: Request received | C2: Marketing AO | D2: Quotation / PRF request logged (e-mail, HLS, upload) | E2: S02, S99
A3: S02 | B3: Quotation in progress | C3: Marketing AO / TSU | D3: Quotation or QS being prepared; insurer terms collected for non-package | E3: S03, S99
A4: S03 | B4: Quotation approved | C4: Approver | D4: Quotation / QS / PS approved and locked | E4: S04
A5: S04 | B5: Sent to client | C5: Marketing AO | D5: Quotation / proposal e-mailed (encrypted) | E5: S05, S06
A6: S05 | B6: Accepted by client | C6: Marketing AO | D6: Acceptance recorded; client onboarding checked | E6: S07
A7: S06 | B7: Declined / not proceeded | C7: Marketing AO | D7: Closed; retention policy applies | E7: -
A8: S07 | B8: Account created | C8: Marketing / System | D8: Client confirmed; account(s) with ARN created; documents complete | E8: S08, S20
A9: S08 | B9: Awaiting payment / confirmation | C9: System | D9: CLPC billing / payment matching / client confirmation per segment | E9: S09, S98
A10: S09 | B10: Submitted for placement | C10: Processing | D10: Placement slip generated (prerequisites met) | E10: S10
A11: S10 | B11: Placed with insurer | C11: System | D11: Placement slip sent; hold-cover requested / confirmed | E11: S11, S12
A12: S11 | B12: Returned by insurer | C12: Processing | D12: Returned with remarks; may go back to Marketing | E12: S09, S98
A13: S12 | B13: Policy issued (e-policy received) | C13: System | D13: Policy number updated; e-policy linked; IA generated if mortgaged | E13: S13
... A19: S99 | B19: Voided | C19: Authorised user | D19: In-process record deleted (soft) with reason | E19: -
B21: Proposal answering BRNB.022 / 094 / 115 and question Q10. Every change of stage is time-stamped with user or system action.

Sheet Platform Impact
A1: Platform area | B1: Treatment | C1: Broker-model impact
A2: Underwriting (insurer) | B2: Re-purpose | C2: Quotations/policies/endorsements become broker quotation -> account -> placement -> booking; premium calculator re-used with Appendix A formulas
A3: Parties | B3: Extend | C3: Client master: prospect/confirmed, KYC, tags, special instructions, dedupe; insurers become panel parties with channels and branches
A4: Attachments | B4: Extend | C4: Document types, ODS, naming syntax, multi-link, extraction, triggers
A5: Approvals / maker-checker | B5: Extend | C5: Multi-level chains (PRF, QS, LOV, user access)
A6: Accounting engine / GL | B6: Re-use | C6: New broker events: booking, cancellation, commission, VAT on commission, premium receivable/payable
A7: Receivables / Payables | B7: Re-use | C7: Premium collected from clients and remitted to insurers; commission receivable from insurers
A8: Tax (PH BIR) | B8: Re-use | C8: VAT on commission, EWT on commission, BIR service invoice
A9: Dimensions | B9: Re-use | C9: Cost center / region / department / team on every booking
A10: Reports & dashboard | B10: Extend | C10: ODS/XML output, print metadata, dynamic reports, NB operational reports
A11: Jobs & alerts | B11: Re-use | C11: Batch booking, KYC monthly list, retention, hold-cover monitor, e-policy dispatch
A12: Security & audit | B12: Re-use | C12: Roles/permissions for 39 NB functions; immutable audit trail
... A14: New modules | B14: Build | C14: Workflow engine & queues, Non-package placement (PRF/QS/PS), Bulk processing framework, Placement, E-policy & IA, Outbound e-mail & encryption, Integrations (HLS, CLPC, insurers), LOV service, Document extraction

Sheet Open Questions
A1: Q# | B1: Topic | C1: Question | D1: Related requirements | E1: BDOI answer | F1: Answered by | G1: Date
A2: Q01 | B2: Product master | C2: Please share the product matrix files (MTR08..MTR38, PAR01..PAR25, other risk codes) referenced in Appendix B; the SharePoint link is internal to BDO. | D2: BRNB.001-003, 093
A3: Q02 | B3: Product master | C3: Minimum mandatory fields per product line / cover type (Annex II: Property, Motor, Engineering, Liability, Crime, Floater, Marine, Hull, Aviation, PA, EEI, Misc.). | D3: BRNB.002, 003, 093
A4: Q03 | B4: Templates | C4: Sample layouts for IDF, FFYMI quotation, Quotation Slip, Proposal Slip, Comparative Table, Placement Slip, Hold Cover request, Insurance Advice, Service Invoice. | D4: BRNB.004, 008, 017, 069, 070, 100
A5: Q04 | B5: TSU routing | C5: Exact TSU involvement criteria: package vs non-package list, fleet threshold (no. of units), multi-location threshold, TSI threshold, endorsement types. | D5: BRNB.098
A6: Q05 | B6: Approvals | C6: Approval chain and limits for PRF (Marketing TL / TH / UH) and QS (TSU) - by amount, product or segment? | D6: BRNB.005, 014
A7: Q06 | B7: Insurer channel | C7: How are insurers reached per insurer: e-mail only, SFTP, or insurer API? List of panel insurers and branch codes (LGT depends on insurer branch). | D7: BRNB.008, 071
A8: Q07 | B8: Encryption | C8: Password convention for outbound documents (standard vs generated syntax, e.g. surname + birth date); which documents to clients vs insurers. | D8: BRNB.013, 035, 077
A9: Q08 | B9: Integration | C9: Which 'BDOI systems' must receive NB data (core/accounting, CRM, GRF/ARF, data warehouse) and preferred interface (file vs API). | D9: BRNB.015, 096
A10: Q09 | B10: Renewals | C10: Late Renewal Requests Report is renewal-related - confirm it stays in NB scope or moves to the Renewal BRD. | D10: BRNB.018
A11: Q10 | B11: Workflow | C11: Confirm the master list of stages and statuses and allowed transitions per transaction type (NB individual, NB bulk, non-package, direct booking, endorsement). | D11: BRNB.022, 115
A12: Q11 | B12: HLS | C12: HLS interface specification (format, fields, frequency, transport, source authentication) and other source systems for bulk (e.g. auto loans for FFYMI). | D12: BRNB.023, 028
A13: Q12 | B13: E-mail intake | C13: Should the system read a shared mailbox for quotation requests automatically, or is manual capture with the e-mail attached sufficient? | D13: BRNB.041
... A45: Q44 | B45: Scope boundary | C45: Broker model: confirm insurer-only platform functions (reinsurance, technical reserves, IBNR, claims reserving) are not required for BDOI. | D45: Platform

Sheet Product Catalogue
A1: Risk code | B1: Risk name | C1: Source | D1: Product line (BDOI to map) | E1: In scope (Y/N)
A2: CAR00 | B2: BDOI Contractor's All Risk | C2: Annex I - Other Lines risk codes as of 22-Oct-2025
A3: CAR01 | B3: BDO/SM Employees | C3: Annex I - Other Lines risk codes as of 22-Oct-2025
A4: CAR02 | B4: BDOI Commercial Banking Insurance Program - CAR/EAR (Group A) | C4: Annex I - Other Lines risk codes as of 22-Oct-2025
A5: CAR03 | B5: BDOI Mall Tenants and Consignors Contractor's All | C5: Annex I - Other Lines risk codes as of 22-Oct-2025
A6: CAR04 | B6: Non-SM, Non-BDO, Non-SM Tenants, Non-SM Consignors | C6: Annex I - Other Lines risk codes as of 22-Oct-2025
A7: CAR05 | B7: SM and BDO Owned Construction Projects | C7: Annex I - Other Lines risk codes as of 22-Oct-2025
A8: CAR06 | B8: Various Non-SM, Non-BDO, Non-SM Tenants and Non-SM Consignors | C8: Annex I - Other Lines risk codes as of 22-Oct-2025
A9: CAR07 | B9: Next Asialand Inc | C9: Annex I - Other Lines risk codes as of 22-Oct-2025
A10: CAR09 | B10: SM Owned Projects - CARI Open Cover - Php100M and below | C10: Annex I - Other Lines risk codes as of 22-Oct-2025
A11: CAR10 | B11: Mall Tenants and/or Consignors - CARI Open Cover - Php100M and below | C11: Annex I - Other Lines risk codes as of 22-Oct-2025
A12: CAR11 | B12: 2021 BDOI CAR Program - Group A (Php500M and below) | C12: Annex I - Other Lines risk codes as of 22-Oct-2025
A13: CAR12 | B13: 2021 Goldilocks Bakeshop Open CARI Program | C13: Annex I - Other Lines risk codes as of 22-Oct-2025
... A68: TRP03 | B68: Combank Leasing BBG Branches - Trust Receipt Program | C68: Annex I - Other Lines risk codes as of 22-Oct-2025
A69: MTR08 | B69: Motor package - product matrix file (content not in BRD) | C69: Appendix B - Fire & Motor product matrix | D69: Motor
A70: MTR10 | B70: Motor package - product matrix file (content not in BRD) | C70: Appendix B - Fire & Motor product matrix | D70: Motor
A71: MTR12 | B71: Motor package - product matrix file (content not in BRD) | C71: Appendix B - Fire & Motor product matrix | D71: Motor
A72: MTR15 | B72: Motor package - product matrix file (content not in BRD) | C72: Appendix B - Fire & Motor product matrix | D72: Motor
A73: MTR22 | B73: Motor package - product matrix file (content not in BRD) | C73: Appendix B - Fire & Motor product matrix | D73: Motor
A74: MTR23 | B74: Motor package - product matrix file (content not in BRD) | C74: Appendix B - Fire & Motor product matrix | D74: Motor
A75: MTR24 | B75: Motor package - product matrix file (content not in BRD) | C75: Appendix B - Fire & Motor product matrix | D75: Motor
A76: MTR25 | B76: Motor package - product matrix file (content not in BRD) | C76: Appendix B - Fire & Motor product matrix | D76: Motor
A77: MTR26 | B77: Motor package - product matrix file (content not in BRD) | C77: Appendix B - Fire & Motor product matrix | D77: Motor
A78: MTR27 | B78: Motor package - product matrix file (content not in BRD) | C78: Appendix B - Fire & Motor product matrix | D78: Motor
A79: MTR28 | B79: Motor package - product matrix file (content not in BRD) | C79: Appendix B - Fire & Motor product matrix | D79: Motor
A80: MTR29 | B80: Motor package - product matrix file (content not in BRD) | C80: Appendix B - Fire & Motor product matrix | D80: Motor
... A91: PAR25 | B91: Property package - product matrix file (content not in BRD) | C91: Appendix B - Fire & Motor product matrix | D91: Property
A93: # | B93: Product line | C93: Types of cover (Annex II)
A94: 1 | B94: Property | C94: Fire and Lightning only; All-Risk; Broad-Named Perils
A95: 2 | B95: Motor | C95: TPL only (no L/D cover); Comprehensive
A96: 3 | B96: Engineering | C96: CAR; EAR
A97: 4 | B97: Liability | C97: CGL; CPL; Employers; Products; Professional; D&O; E&O; Cyber; Contaminated Products; Pollution Legal; Contractor's Pollution
A98: 5 | B98: Crime | C98: MSP; FG; MSP + FG; DDD; BBB
A99: 6 | B99: Property / Equipment Floater | C99: -
A100: 7 | B100: Marine | C100: Inland; Inter-Island; Import; Export; combinations; Project Cargo; Charterer's Liability; Terminal Operators Liability; Freight Forwarder's Liability; Stock Throughput; Trust Receipt
A101: 8 | B101: Marine Hull | C101: Hull and Machinery; Ship Repairer's Liability; Builder's Risk; Protection & Indemnity
A102: 9 | B102: Aviation | C102: General Aviation; Drone; Airport Contractor's Liability; Airport Owner's & Operator's Liability; Aviation Products Liability; Aviation Refuellers Liability; Hangar Keepers Liability; Pilot Loss of License
A103: 10 | B103: Personal Accident | C103: Individual PA; Group PA; Marine PA; Travel PA
A104: 11 | B104: Electronic Equipment | C104: -
A105: 12 | B105: Others / Miscellaneous | C105: S&T; PV; Trade Credit; Parametric; Golfer's / Hole-in-One; Fine Arts; Jewelers Block

Sheet Calculations
A1: Line | B1: Field | C1: Formula (Appendix A, as written) | D1: BDOI confirmation | E1: Comments
A2: All lines | B2: Pro-rata | C2: Premium components x days covered / 365 (or 366)
A3: All lines | B3: Short-term period rate | C3: Premium x short-period % by months/days covered (cancellation before expiry) - table needed
A4: All lines | B4: Minimum premium | C4: Applied when TSI below package threshold; not for endorsements or pro-rata (per product matrix)
A5: Fire | B5: Net premium | C5: TSI x premium rate
A6: Fire | B6: DST | C6: 12.5% of net premium; rounding: .01-.49 -> .50, .51-.99 -> next 1.00
A7: Fire | B7: PTX (premium tax) | C7: 12% of net premium [note: statutory PH premium tax for non-life is generally 2% / VAT 12% - to confirm]
A8: Fire | B8: FST (fire service tax) | C8: 2% of net premium
A9: Fire | B9: LGT | C9: Rate depends on insurer branch
A10: Fire | B10: Total charges / Gross premium | C10: DST + PTX + FST + LGT (+OTH); gross = net + charges
A11: Fire | B11: Commission | C11: Commission rate x net premium
A12: Fire | B12: VAT on commission | C12: 12% of commission
A13: Motor | B13: OD/Theft coverage | C13: Annual: 90% of TSI; multi-year: 81% of TSI [to confirm which column applies]
... A21: Motor | B21: Total premium | C21: Basic premium + DST + VAT + LGT

Sheet NFR
A1: Topic | B1: BRD requirement | C1: BrokerVerse approach | D1: Fit
A2: Users | B2: 485 named users (392 Marketing AO/TL, 82 Processing, 3 System Admin); max concurrent 145 | C2: Platform is stateless; horizontal scaling (k8s HPA). Size for 150 concurrent + 20%/yr growth | D2: CONFIGURE
A3: Volume | B3: 21,200 transactions/month across quotation, client, account, upload, booking; endorsements 1,300/month; +20%/yr | C3: ~1,000/day; bulk jobs chunked (500 rows/commit) | D3: FIT
A4: Response time | B4: 10 seconds for all listed functions | C4: Target p95 < 3 s online; bulk jobs asynchronous with progress | D4: FIT
A5: Peak hours | B5: 08:00-10:00 and 15:00-17:00 | C5: Run batch booking / e-mail dispatch outside peaks | D5: CONFIGURE
A6: Availability | B6: 07:00-22:00 Mon-Sat; other items 'follow existing QPS set-up' | C6: Maintenance window outside service hours; HA deployment | D6: CONFIGURE
A7: Retention | B7: Application, DB, audit logs and historical data: 5 years online, 15 years archive, backup every 4 hours, backup retention 5 years | C7: Archive tablespace/object storage + retention job (BRNB.106); DB backups every 4h | D7: NEW
A8: Security | B8: All outbound documents encrypted / password protected; insurers have no system access | C8: PDF/XLSX encryption; no external user roles | D8: NEW
A9: Devices | B9: Any BDO-issued device / workstation | C9: Browser-based; optional IP allow-list / SSO | D9: FIT

Sheet Legacy BRD Map
A1: Legacy BRD ID | B1: BR ID | C1: Requirement
A2: BRD 1.1.1.1 | B2: BRNB.040 | C2: Log in from any BDO-issued device with role profile; inactivity warning after 15 min; warning 30 min before system-triggered logout
A3: BRD 1.1.2.1 | B3: BRNB.023 | C3: Receive quotation requests for home insurance directly from HLS (Home Loan System)
A4: BRD 1.1.2.1 | B4: BRNB.041 | C4: Receive quotation/proposal request via e-mail or system-triggered request
A5: BRD 1.1.3.1-1.1.3.3 | B5: BRNB.042 | C5: Create quotation/proposal for bulk processing (IDF, FFYMI ...), generate reference, send single/multiple
A6: BRD 1.1.4.1 | B6: BRNB.024 | C6: Receive single/multiple accepted quotations; update them via file upload or manually
A7: BRD 1.1.4.1-1.1.4.5 | B7: BRNB.044 | C7: Manually build accounts for bulk processing (receive accepted quotes, download PDF/XLSX, create client/account upload list, upload docs, search client)
A8: BRD 1.1.5.1 | B8: BRNB.046 | C8: Search clients by single/multiple criteria and view full details
A9: BRD 1.1.6.1-1.1.6.4 | B9: BRNB.047 | C9: Update client details in bulk with validation, draft, cancel, push
A10: BRD 1.1.7.1 | B10: BRNB.050 | C10: Search accounts by single/multiple criteria and view full details
A11: BRD 1.1.8 | B11: BRNB.025 | C11: Update account(s) - bulk and individual upload/entry, validate mandatory fields, draft, submit
A12: BRD 1.1.8.1-1.1.8.4 | B12: BRNB.052 | C12: Update account (bulk) with validation, multi-values, auto calculation, draft, cancel, push
... A144: BRD 3.4.3.1 | B144: BRNB.089 | C144: Generate and export audit log reports

Sheet Sign-off
B2: Sign-off
B3: Concurrence on the BRD-1 New Business fit/gap before build
B5: Organisation | C5: Name | D5: Designation | E5: Signature | F5: Date
B6: BDOI - Product Owner
B7: BDOI - Marketing Business Services
B8: BDOI - Processing
B9: BDOI - TSU
B10: BDOI - Comptrollership
B11: BDO ESG - Business Project Services
B12: iORTA TechNXT - Delivery
