Workbook

Sheet Cover
B6: READINESS CHECKLIST
B7: Production Readiness Checklist
B8: Operational, security, performance, data, support, compliance and business readiness of BIBS for the January 2028 go-live
B9: BIBS – BDOI Broker System
B11: Client | C11: BDO Insurance and Reinsurance Brokers, Inc.
B12: BRD | C12: BRD-00
B13: Version | C13: 1.0
B14: Date | C14: 8 October 2026
B15: Classification | C15: Confidential
B16: Prepared by | C16: iorta TechNXT
B18: Sheets
B19: Sheet | C19: Content | D19: Rows
B20: README | C20: What each column of each sheet means, with the allowed values
B21: Checklist | C21: Production readiness criteria of BIBS with owner, evidence, gate and status | D21: 73
B22: Summary | C22: Counts by area and status, recalculated from the Checklist | D22: 8
B23: Gates | C23: Readiness reviews and go / no-go gates | D23: 5
B25: Legend
B26: OPEN | C26: Not started or not yet evidenced
B27: IN PROGRESS | C27: Work under way, evidence partial
B28: DONE | C28: Met; evidence filed
B29: BLOCKED | C29: Cannot be met without a decision or a dependency
B30: N/A | C30: Not applicable, with the reason in Remarks
B32: One row per readiness criterion. The owner updates the status and files the evidence reference; the BIBS Service Owner reviews the sheet weekly from 1 October 2027 and before each gate.
B33: A criterion is met only with its evidence. A criterion that is not met at its gate is either waived by the gate (recorded in Remarks with the approver) or blocks the gate.
B34: Gates: ORR 15-Dec-2027, PRR 17-Dec-2027, GNG-1 19-Dec-2027, GNG-2 29-Dec-2027, GNG-3 2-Jan-2028 18:00.
B36: Prepared by iorta TechNXT for BDOI. Confidential – BDOI.

Sheet README
A1: README – columns of each sheet
A2: Production Readiness Checklist, version 1.0. Drop-down columns accept only the listed values.
A4: Sheet | B4: Column | C4: Meaning | D4: Allowed values
A5: Checklist | B5: ID | C5: Criterion identifier: area prefix and number
A6: Checklist | B6: Area | C6: Readiness area | D6: Operational, Security, Performance, Data, Support, Compliance, Business
A7: Checklist | B7: Criterion | C7: What must be true before go-live
A8: Checklist | B8: Measure / threshold | C8: How the criterion is judged met
A9: Checklist | B9: Evidence required | C9: The record that proves it
A10: Checklist | B10: Owner | C10: Accountable role
A11: Checklist | B11: Due | C11: Date by which the evidence is filed
A12: Checklist | B12: Gate | C12: Review or go / no-go gate that checks it | D12: ORR, PRR, GNG-1, GNG-2, GNG-3
A13: Checklist | B13: Status | C13: Status of the criterion | D13: OPEN, IN PROGRESS, DONE, BLOCKED, N/A
A14: Checklist | B14: Evidence reference | C14: Document, record or link of the evidence (filled in by the owner)
A15: Checklist | B15: Date met | C15: Date the evidence was accepted (filled in by the owner)
A16: Checklist | B16: Remarks | C16: Waiver with approver, dependency or comment
A17: Summary | B17: Area | C17: Readiness area
A18: Summary | B18: Criteria | C18: Number of criteria
A19: Summary | B19: Open | C19: Criteria with status OPEN
A20: Summary | B20: In Progress | C20: Criteria with status IN PROGRESS
A21: Summary | B21: Done | C21: Criteria with status DONE
A22: Summary | B22: Blocked | C22: Criteria with status BLOCKED
A23: Summary | B23: N/A | C23: Criteria with status N/A
A24: Summary | B24: Met (%) | C24: Criteria met as a share of the applicable criteria
A25: Gates | B25: Gate | C25: Gate code
... A29: Gates | B29: Passes when | C29: Rule of the gate

Sheet Checklist
A1: Checklist
A2: Production readiness criteria of BIBS with owner, evidence, gate and status
A4: ID | B4: Area | C4: Criterion | D4: Measure / threshold | E4: Evidence required | F4: Owner | G4: Due | H4: Gate | I4: Status | J4: Evidence reference | K4: Date met | L4: Remarks
A5: OPS-01 | B5: Operational | C5: Production environment provisioned to the agreed sizing: EKS with the four workloads, RDS PostgreSQL 16 Multi-AZ, ElastiCache for Valkey 8 with replica, MSK Kafka 3.9 with three brokers, S3 buckets | D5: Sizing of the Programme Alignment, section Kubernetes sizing; spread over three availability zones | E5: Environment acceptance checklist; infrastructure inventory | F5: BDO Cloud Operations | G5: 46721 | H5: ORR | I5: OPEN
A6: OPS-02 | B6: Operational | C6: DR region environment provisioned as warm standby with the RDS cross-region replica, S3 cross-region replication with replication time control, image and secrets replication | D6: Replica lag below 5 minutes for 7 days; S3 replication within 15 minutes | E6: DR environment acceptance record; replication metrics | F6: BDO Cloud Operations | G6: 46721 | H6: ORR | I6: OPEN
A7: OPS-03 | B7: Operational | C7: Pre-Prod environment production-sized and used for the performance test and the dress rehearsals | D7: Same sizing and versions as production | E7: Environment comparison report | F7: BDO Cloud Operations | G7: 46661 | H7: ORR | I7: OPEN
A8: OPS-04 | B8: Operational | C8: Network paths in place: users through the BDO network to the internal load balancer with WAF; BDO systems through Apigee X on the private route; no internet path | D8: Connectivity test from each client network range and each Apigee source range; refused from any other range | E8: Network test record | F8: BDO Cloud Operations | G8: 46721 | H8: ORR | I8: OPEN
A9: OPS-05 | B9: Operational | C9: Certificates: browser certificate on the BDO domain under the BDO corporate PKI; in-cluster certificates from the private CA with automatic renewal | D9: Valid for at least 90 days at go-live; renewal alarm at 30 days | E9: Certificate inventory | F9: BDO Cloud Operations | G9: 46721 | H9: ORR | I9: OPEN
A10: OPS-06 | B10: Operational | C10: Gateway API controller in place of ingress-nginx; routes for users and for the integration path tested | D10: Routes answer through the Gateway only; health checks green | E10: Route test record | F10: BDO Cloud Operations | G10: 46721 | H10: ORR | I10: OPEN
A11: OPS-07 | B11: Operational | C11: Monitoring live: synthetic sign-in check, service dashboards, alert catalogue of the Operations Runbook with routing to L1, L2, L3 and Cloud Operations | D11: Every alert rule of the catalogue fired once in Pre-Prod and reached its responder | E11: Alert test record; dashboard links | F11: iorta TechNXT infrastructure team | G11: 46729 | H11: ORR | I11: OPEN
A12: OPS-08 | B12: Operational | C12: Logs shipped to the BDO log platform and SIEM with the correlation id; retention 5 years online | D12: A request found by its error reference within 5 minutes | E12: Log search demonstration record | F12: BDO Cloud Operations | G12: 46729 | H12: ORR | I12: OPEN
A13: OPS-09 | B13: Operational | C13: Backups: automated backups with point-in-time recovery, base backup every 4 hours, retention 7 years for the monthly copies; S3 versioning | D13: Latest restorable time within 15 minutes; restore test passed | E13: Backup configuration export; restore test record | F13: BDO Cloud Operations | G13: 46729 | H13: ORR | I13: OPEN
A14: OPS-10 | B14: Operational | C14: Restore test: production-sized snapshot restored into an isolated instance and BIBS started against it | D14: Restore within 2 hours; row counts of key records equal | E14: Restore test record | F14: BDO Cloud Operations | G14: 46729 | H14: ORR | I14: OPEN
A15: OPS-11 | B15: Operational | C15: DR drill before go-live: regional failover of Pre-Prod to the DR region and failback | D15: RTO 4 hours and RPO 15 minutes met | E15: DR drill report (DR plan, chapter 8) | F15: BDO Cloud Operations | G15: 46724 | H15: ORR | I15: OPEN
A16: OPS-12 | B16: Operational | C16: Scheduled jobs set for production as in the jobs catalogue; non-production schedule overrides removed | D16: Job list equals the catalogue | E16: Scheduled Jobs printout signed by L2 lead | F16: iorta TechNXT infrastructure team | G16: 46740 | H16: GNG-1 | I16: OPEN
... A77: BUS-11 | B77: Business | C77: Legacy systems can be set read-only with access logging; freeze tested | D77: Freeze test refused a posting in each business module | E77: Freeze test record (CT-036) | F77: BDOI IT | G77: 46752 | H77: GNG-3 | I77: OPEN

Sheet Summary
A1: Summary
A2: Counts by area and status, recalculated from the Checklist
A4: Area | B4: Criteria | C4: Open | D4: In Progress | E4: Done | F4: Blocked | G4: N/A | H4: Met (%)
A5: Operational | B5: =COUNTIF(Checklist!$B$5:$B$600,"Operational") | C5: =COUNTIFS(Checklist!$B$5:$B$600,"Operational",Checklist!$I$5:$I$600,"OPEN") | D5: =COUNTIFS(Checklist!$B$5:$B$600,"Operational",Checklist!$I$5:$I$600,"IN PROGRESS") | E5: =COUNTIFS(Checklist!$B$5:$B$600,"Operational",Checklist!$I$5:$I$600,"DONE") | F5: =COUNTIFS(Checklist!$B$5:$B$600,"Operational",Checklist!$I$5:$I$600,"BLOCKED") | G5: =COUNTIFS(Checklist!$B$5:$B$600,"Operational",Checklist!$I$5:$I$600,"N/A") | H5: =IF(B5-G5=0,0,ROUND(100*E5/(B5-G5),1))
A6: Security | B6: =COUNTIF(Checklist!$B$5:$B$600,"Security") | C6: =COUNTIFS(Checklist!$B$5:$B$600,"Security",Checklist!$I$5:$I$600,"OPEN") | D6: =COUNTIFS(Checklist!$B$5:$B$600,"Security",Checklist!$I$5:$I$600,"IN PROGRESS") | E6: =COUNTIFS(Checklist!$B$5:$B$600,"Security",Checklist!$I$5:$I$600,"DONE") | F6: =COUNTIFS(Checklist!$B$5:$B$600,"Security",Checklist!$I$5:$I$600,"BLOCKED") | G6: =COUNTIFS(Checklist!$B$5:$B$600,"Security",Checklist!$I$5:$I$600,"N/A") | H6: =IF(B6-G6=0,0,ROUND(100*E6/(B6-G6),1))
A7: Performance | B7: =COUNTIF(Checklist!$B$5:$B$600,"Performance") | C7: =COUNTIFS(Checklist!$B$5:$B$600,"Performance",Checklist!$I$5:$I$600,"OPEN") | D7: =COUNTIFS(Checklist!$B$5:$B$600,"Performance",Checklist!$I$5:$I$600,"IN PROGRESS") | E7: =COUNTIFS(Checklist!$B$5:$B$600,"Performance",Checklist!$I$5:$I$600,"DONE") | F7: =COUNTIFS(Checklist!$B$5:$B$600,"Performance",Checklist!$I$5:$I$600,"BLOCKED") | G7: =COUNTIFS(Checklist!$B$5:$B$600,"Performance",Checklist!$I$5:$I$600,"N/A") | H7: =IF(B7-G7=0,0,ROUND(100*E7/(B7-G7),1))
A8: Data | B8: =COUNTIF(Checklist!$B$5:$B$600,"Data") | C8: =COUNTIFS(Checklist!$B$5:$B$600,"Data",Checklist!$I$5:$I$600,"OPEN") | D8: =COUNTIFS(Checklist!$B$5:$B$600,"Data",Checklist!$I$5:$I$600,"IN PROGRESS") | E8: =COUNTIFS(Checklist!$B$5:$B$600,"Data",Checklist!$I$5:$I$600,"DONE") | F8: =COUNTIFS(Checklist!$B$5:$B$600,"Data",Checklist!$I$5:$I$600,"BLOCKED") | G8: =COUNTIFS(Checklist!$B$5:$B$600,"Data",Checklist!$I$5:$I$600,"N/A") | H8: =IF(B8-G8=0,0,ROUND(100*E8/(B8-G8),1))
A9: Support | B9: =COUNTIF(Checklist!$B$5:$B$600,"Support") | C9: =COUNTIFS(Checklist!$B$5:$B$600,"Support",Checklist!$I$5:$I$600,"OPEN") | D9: =COUNTIFS(Checklist!$B$5:$B$600,"Support",Checklist!$I$5:$I$600,"IN PROGRESS") | E9: =COUNTIFS(Checklist!$B$5:$B$600,"Support",Checklist!$I$5:$I$600,"DONE") | F9: =COUNTIFS(Checklist!$B$5:$B$600,"Support",Checklist!$I$5:$I$600,"BLOCKED") | G9: =COUNTIFS(Checklist!$B$5:$B$600,"Support",Checklist!$I$5:$I$600,"N/A") | H9: =IF(B9-G9=0,0,ROUND(100*E9/(B9-G9),1))
A10: Compliance | B10: =COUNTIF(Checklist!$B$5:$B$600,"Compliance") | C10: =COUNTIFS(Checklist!$B$5:$B$600,"Compliance",Checklist!$I$5:$I$600,"OPEN") | D10: =COUNTIFS(Checklist!$B$5:$B$600,"Compliance",Checklist!$I$5:$I$600,"IN PROGRESS") | E10: =COUNTIFS(Checklist!$B$5:$B$600,"Compliance",Checklist!$I$5:$I$600,"DONE") | F10: =COUNTIFS(Checklist!$B$5:$B$600,"Compliance",Checklist!$I$5:$I$600,"BLOCKED") | G10: =COUNTIFS(Checklist!$B$5:$B$600,"Compliance",Checklist!$I$5:$I$600,"N/A") | H10: =IF(B10-G10=0,0,ROUND(100*E10/(B10-G10),1))
A11: Business | B11: =COUNTIF(Checklist!$B$5:$B$600,"Business") | C11: =COUNTIFS(Checklist!$B$5:$B$600,"Business",Checklist!$I$5:$I$600,"OPEN") | D11: =COUNTIFS(Checklist!$B$5:$B$600,"Business",Checklist!$I$5:$I$600,"IN PROGRESS") | E11: =COUNTIFS(Checklist!$B$5:$B$600,"Business",Checklist!$I$5:$I$600,"DONE") | F11: =COUNTIFS(Checklist!$B$5:$B$600,"Business",Checklist!$I$5:$I$600,"BLOCKED") | G11: =COUNTIFS(Checklist!$B$5:$B$600,"Business",Checklist!$I$5:$I$600,"N/A") | H11: =IF(B11-G11=0,0,ROUND(100*E11/(B11-G11),1))
A12: Total | B12: =COUNTA(Checklist!$A$5:$A$600) | C12: =COUNTIF(Checklist!$I$5:$I$600,"OPEN") | D12: =COUNTIF(Checklist!$I$5:$I$600,"IN PROGRESS") | E12: =COUNTIF(Checklist!$I$5:$I$600,"DONE") | F12: =COUNTIF(Checklist!$I$5:$I$600,"BLOCKED") | G12: =COUNTIF(Checklist!$I$5:$I$600,"N/A") | H12: =IF(B12-G12=0,0,ROUND(100*E12/(B12-G12),1))

Sheet Gates
A1: Gates
A2: Readiness reviews and go / no-go gates
A4: Gate | B4: Name | C4: When | D4: Decided by | E4: Passes when
A5: ORR | B5: Operational readiness review | C5: 15-Dec-2027 | D5: BIBS Service Owner (chair), BDO Cloud Operations, Information Security Officer, iorta TechNXT Project Manager | E5: Operations, security, performance and support criteria met; evidence pack accepted
A6: PRR | B6: Production readiness review | C6: 17-Dec-2027 | D6: Head, BDOI IT (chair), BIBS Product Owner, Program Manager, iorta TechNXT Project Manager | E6: Every ORR criterion met or waived; production and DR accepted; data and business criteria on track
A7: GNG-1 | B7: Go / no-go 1: start the pre-load | C7: 19-Dec-2027 (T-15) | D7: Go / no-go board | E7: Criteria of the Data Migration Handbook, Part D, and the PRR result
A8: GNG-2 | B8: Go / no-go 2: enter the legacy freeze | C8: 29-Dec-2027 (T-5) | D8: Go / no-go board | E8: Reference data and clients accepted; communications sent; business readiness confirmed
A9: GNG-3 | B9: Go / no-go 3: go live | C9: 2-Jan-2028 18:00 (T-1) | D9: Go / no-go board | E9: Every Day-1 object accepted; reconciliation 0.00; smoke test passed; support in place

Sheet _lists
A1: Operational | B1: ORR | C1: OPEN
A2: Security | B2: PRR | C2: IN PROGRESS
A3: Performance | B3: GNG-1 | C3: DONE
A4: Data | B4: GNG-2 | C4: BLOCKED
A5: Support | B5: GNG-3 | C5: N/A
A6: Compliance
A7: Business
