Workbook

Sheet Cover
B6: CHANGE REGISTER
B7: Change Management Register
B8: For documentation and change control; does not change the platform or the FRS baseline.
B9: BIBS – BDOI Broker System
B11: Client | C11: BDO Insurance and Reinsurance Brokers, Inc.
B12: BRD | C12: BRD-00
B13: Version | C13: 1.0
B14: Date | C14: 26 September 2026
B15: Classification | C15: Confidential
B16: Prepared by | C16: iorta TechNXT
B18: Sheets
B19: Sheet | C19: Content | D19: Rows
B20: How to read | C20: Reading guide, deviation types, statuses, priorities, size classes and column definitions
B21: Document control | C21: Version history, review and approval, distribution; the statement that the register does not change the platform or the FRS
B22: Register | C22: 178 deviations from the BRDs for change control. For documentation and change control; does not change the platform or the FRS baseline. | D22: 178
B23: Summary | C23: Counts and man-days by drop, BRD, deviation type, status and priority. Formulas read the Register sheet, so the figures follow any change to it.
B24: Effort basis | C24: How the man-days are estimated: team roles, the man-day, what is included and excluded, and the size classes.
B25: Change control | C25: Change-control process for deviations and new change requests, with the roles and the proposed Change Control Board (CCB).
B26: CR form | C26: Change request form: one per CR; the Project Manager files the signed form with the register.
B28: Legend
B29: Draft | C29: Raised by the project team. Impact analysis done; the BDOI answer or decision it needs is still open.
B30: For CCB review | C30: Impact analysis complete; ready for the Change Control Board to approve, reject or defer.
B31: Approved | C31: Approved by the CCB; scheduled into a drop or release.
B32: Rejected | C32: Rejected by the CCB; the BRD text stands, or the item is closed without change.
B33: For acceptance | C33: The proposed behaviour is decided and documented and differs from the BRD text; the CCB records the acceptance. No work remains.
B35: Status as of 26 September 2026. Baseline: FRS v1.0 of every BRD (BRD-2, BRD-6, BRD-11 and BRD-13 at v1.1 or later), discrepancy register v1.2, BDOI answers of 26 September 2026.
B37: Prepared by iorta TechNXT for BDOI. Confidential – BDOI.

Sheet Document control
A1: Document control
A3: For documentation and change control; does not change the platform or the FRS baseline.
A5: Document | B5: Change Management Register (BIBS-CMR-BRD-00)
A6: Version | B6: 1.0
A7: Date | B7: 26 September 2026
A8: Status | B8: Issued for BDOI review
A9: Status as of | B9: 26 September 2026
A10: Baseline | B10: FRS v1.0 of every BRD (BRD-2, BRD-6, BRD-11 and BRD-13 at v1.1 or later), discrepancy register v1.2, BDOI answers of 26 September 2026
A11: Word summary | B11: BIBS_Change_Register_BRD-00_Change_Management_Summary_v1.0.docx
A12: Owner of the register | B12: Project Manager (iorta TechNXT) on behalf of the Change Control Board
A14: Version history
A15: Version | B15: Date | C15: Author | D15: Reviewer | E15: Approver | F15: Change
A16: 1.0 | B16: 26 Sep 2026 | C16: iorta TechNXT Business Analyst lead | D16: iorta TechNXT Solution Architect | E16: BIBS Product Owner (pending) | F16: First issue: 178 deviations from BRD-00 to BRD-13 with effort in man-days
A18: Review and approval
A19: Role | B19: Organisation | C19: Name | D19: Signature | E19: Date | F19: Purpose
A20: BIBS Product Owner | B20: BDOI | F20: Chair of the CCB; approves the register
A21: Program Manager, Business Project Services | B21: BDO Unibank ESG | F21: Plan, drops and effort
A22: Head, Comptrollership | B22: BDOI | F22: Posting, GL, tax and BIR items
A23: Chief Compliance Officer | B23: BDOI | F23: Screening, access and retention items
A24: Project Manager | B24: iorta TechNXT | F24: Register owner; CCB secretary
A26: Distribution
A27: Recipient | B27: Organisation | C27: Purpose
A28: Owners of BRD-1 to BRD-13 (department heads and product owners) | B28: BDOI | C28: Review the CRs of their BRD; decision owners
A29: BDOI IT (integration owners) | B29: BDOI | C29: Interface and infrastructure CRs
A30: Project team | B30: iorta TechNXT | C30: Impact analysis, scheduling, FRS revisions

Sheet How to read
A1: How to read this register
A2: For documentation and change control; does not change the platform or the FRS baseline.
A4: Reading guide
A5: • | B5: One row per deviation from a BRD requirement, merged across sources (the clarifications chapters of the FRS, the requirements baselines, the discrepancy register v1.2, the alignment pack, the cross-BRD decisions and the BDOI answers of 26 September 2026). The Source column says where each deviation is recorded.
A6: • | B6: Filter the Register sheet by Drop, BRD, Deviation type, Priority or CR status. The Summary sheet recounts from the Register, so it stays correct when rows are added or a status changes.
A7: • | B7: Effort is in man-days for the work still needed to close the deviation as proposed (Effort basis sheet). It is 0 when no work remains and the behaviour only needs acceptance. 'BRD as written' gives the indicative effort to deliver the BRD text instead, where the CCB may want to compare.
A8: • | B8: A CR moves Draft -> For CCB review -> Approved or Rejected. Rows marked 'For acceptance' describe decided behaviour that differs from the BRD: the CCB records the acceptance; no work remains.
A9: • | B9: The register does not change the FRS. An approved CR reaches the FRS only through the next FRS revision, which cites the CR ID.
A11: Deviation types
A12: Type | B12: Meaning
A13: Scope addition — beyond BRD | B13: BIBS does more than the BRD asks, or the umbrella FRS proposes a requirement that no function BRD owns. BDOI accepts the addition or removes it.
A14: Scope reduction / descoped | B14: A BRD requirement is not delivered, or is delivered with less than the BRD asks, by a BDOI instruction or a proposal. BDOI confirms the descoping.
A15: Behaviour differs from BRD | B15: The requirement is met in a different way from the BRD text. BDOI accepts the proposed behaviour or asks for the BRD text.
A16: Deferred pending BDOI answer | B16: The element runs with a documented default and waits for a BDOI answer (values, layouts, rules, a yes / no on scope).
A17: Deferred to Phase 2 | B17: Out of phase 1 by BDOI decision; kept for phase 2.
A18: BRD conflict resolved by decision | B18: Two BRDs, or two parts of one BRD, conflict. A binding decision (D1-D10) or a proposed resolution settles the conflict; BDOI confirms it.
A19: Integration dependency | B19: The requirement depends on an interface with a BDO or insurer system that is not yet specified. BIBS runs on an upload or a manual step until the interface exists.
A20: NFR / infrastructure change | B20: A non-functional value (hours, availability, recovery, retention, sizing) or an infrastructure choice differs from one or more BRDs, or from the IER workbook.
A21: Data migration | B21: The migration or cut-over treatment differs from what a BRD assumes, or adds work that a BRD does not state.
A23: CR status
A24: Status | B24: Meaning
A25: Draft | B25: Raised by the project team. Impact analysis done; the BDOI answer or decision it needs is still open.
A26: For CCB review | B26: Impact analysis complete; ready for the Change Control Board to approve, reject or defer.
A27: Approved | B27: Approved by the CCB; scheduled into a drop or release.
A28: Rejected | B28: Rejected by the CCB; the BRD text stands, or the item is closed without change.
A29: For acceptance | B29: The proposed behaviour is decided and documented and differs from the BRD text; the CCB records the acceptance. No work remains.
A31: Priority
A32: Priority | B32: Meaning
A33: High | B33: Affects money (premium, commission, GL, remittance), regulatory compliance, security or access, or blocks a drop. Decide before the FRS of the area is signed off.
A34: Medium | B34: Changes a rule, screen, report or interface; a documented default runs until BDOI decides.
A35: Low | B35: Wording, labels or presentation; no effect on money, control or data.
A37: Size classes (effort basis)
A38: Class | B38: Man-days
A39: 0 | B39: Acceptance only
A40: S | B40: 1 to 3
A41: M | B41: 4 to 10
A42: L | B42: 11 to 25
A43: XL | B43: more than 25
A45: Columns of the data sheets
A46: Sheet | B46: Column | C46: Meaning | D46: Allowed values
A47: Register | B47: CR ID | C47: Change request identifier, CR-nnnn
A48: Register | B48: Drop | C48: BDOI drop of the item (Drop 0 set-up and migration, Drop 1 transactional, Drop 2 independent), Programme (cross-drop) or Phase 2 | D48: Drop 0, Drop 1, Drop 2, Programme, Phase 2
A49: Register | B49: BRD | C49: Primary BRD; other BRDs involved are named in the BRD requirement column | D49: BRD-00, BRD-01, BRD-02, BRD-03, BRD-04, BRD-05, BRD-06, BRD-07, BRD-08, BRD-09, BRD-10, BRD-11, BRD-12, BRD-13
A50: Register | B50: BRD requirement ID(s) and page | C50: BRD requirement IDs with the PDF page of the source BRD
A51: Register | B51: FRS FR ID(s) | C51: Functional requirement IDs of the FRS, or the FRS section that records the item
A52: Register | B52: Deviation type | C52: Kind of deviation (How to read) | D52: Scope addition — beyond BRD, Scope reduction / descoped, Behaviour differs from BRD, Deferred pending BDOI answer, Deferred to Phase 2, BRD conflict resolved by decision, Integration dependency, NFR / infrastructure change, Data migration
A53: Register | B53: BRD requirement | C53: What the BRD asks, in short
A54: Register | B54: Proposed behaviour | C54: The proposed behaviour of BIBS
A55: Register | B55: Reason | C55: BDOI decision, open question or technical constraint behind the deviation
A56: Register | B56: Business impact | C56: Effect on the business process, money, control or users
A57: Register | B57: Affected departments | C57: BDOI departments affected
A58: Register | B58: Analysis (md) | C58: Man-days of analysis still needed
A59: Register | B59: Dev. (md) | C59: Man-days of development and configuration
A60: Register | B60: Test (md) | C60: Man-days of SIT test preparation, execution and regression
A61: Register | B61: Doc. (md) | C61: Man-days of documentation (FRS, test plan, guides)
A62: Register | B62: Total (md) | C62: Sum of the four effort columns (formula)
A63: Register | B63: Size basis | C63: Size class and chosen number: S 1-3, M 4-10, L 11-25, XL over 25; 0 = acceptance only (formula)
A64: Register | B64: BRD as written (md) | C64: Indicative man-days to deliver the BRD text instead of the proposed behaviour (blank where not applicable)
A65: Register | B65: Priority | C65: High, Medium or Low (How to read) | D65: High, Medium, Low
A66: Register | B66: CR status | C66: Status in the change-control process | D66: Draft, For CCB review, Approved, Rejected, For acceptance
A67: Register | B67: Decision owner (BDOI) | C67: BDOI role that decides the CR
A68: Register | B68: Register / question refs | C68: Discrepancy register items (DCR-), question IDs and decisions (D1-D10)
A69: Register | B69: Target drop / release | C69: Drop or release in which the CR is closed | D69: FRS sign-off (Nov 2026), Drop 1, first release (Nov - Dec 2026), Drop 1, second release (Jan - Feb 2027), Migration functions (Nov 2026 - Mar 2027), Infrastructure before SIT (by Jan 2027), Drop 2 (Mar - Apr 2027), Before go-live (Oct - Dec 2027), Phase 2, After BDOI answer (slot set by the CCB)
A70: Register | B70: Source of the record | C70: Where the deviation is recorded (FRS section, requirements baseline, register, alignment pack)

Sheet Register
A1: Register
A2: 178 deviations from the BRDs for change control. For documentation and change control; does not change the platform or the FRS baseline.
A4: CR ID | B4: Drop | C4: BRD | D4: BRD requirement ID(s) and page | E4: FRS FR ID(s) | F4: Deviation type | G4: BRD requirement | H4: Proposed behaviour | I4: Reason | J4: Business impact | K4: Affected departments | L4: Analysis (md) | M4: Dev. (md) | N4: Test (md) | O4: Doc. (md) | P4: Total (md) | Q4: Size basis | R4: BRD as written (md) | S4: Priority | T4: CR status | U4: Decision owner (BDOI) | V4: Register / question refs | W4: Target drop / release | X4: Source of the record
A5: CR-0001 | B5: Phase 2 | C5: BRD-00 | D5: CORE-15.01-15.10; BR-153 to BR-160 (p.10-11); capability matrix (p.28); ReInsurance BRD | E5: FRS BRD-00 section 6 (Reinsurance, phase 2); CLR-CR-01 | F5: Deferred to Phase 2 | G5: Reinsurance placement, slips, SOA, claims reporting and payment, net settlement (capability 15). | H5: Out of phase 1: the ReInsurance BRD is received and is phase 2. Phase 1 keeps open reinsurer party types, template-driven slips and SOAs, report subscriptions, open-item matching and the claim party model. The insurer-side reinsurance module of the platform stays hidden from BDOI roles. | I5: BDOI answer A3 of 26-Sep-2026: the reinsurance module is phase 2. | J5: Reinsurance placement stays outside BIBS until phase 2; only the transactions routed through Remittance (CR-0002) are in phase 1. | K5: Reinsurance; Comptrollership; Operations | L5: 0 | M5: 0 | N5: 0 | O5: 1 | P5: =SUM(L5:O5) | Q5: =IF(P5=0,"0 - acceptance only",IF(P5<=3,"S",IF(P5<=10,"M",IF(P5<=25,"L","XL")))&" ("&P5&")") | S5: Medium | T5: For CCB review | U5: BIBS Product Owner with the Program Manager, Business Project Services | V5: A3; CLR-CR-01; A-CR-04 | W5: Phase 2 | X5: FRS BRD-00 sections 1.2, 5, 6; Programme alignment 1.2
A6: CR-0002 | B6: Drop 1 | C6: BRD-02 | D6: Drop plan item 1.D3 (Operations BRD, Remittance Addendum; Reinsurance BRD); RMTID.001-040 (p.49-70) | E6: FR-OP-030 to FR-OP-041 (Remittance); FRS BRD-2 v1.1 introduction | F6: Scope addition — beyond BRD | G6: The Operations BRD specifies remittance to insurers only. The drop plan names the Reinsurance BRD for Remittance in Drop 1. | H6: Proposed: the named reinsurance transactions run in Remittance as remittance types with reinsurer counterparties and their own accounting rules; treaty and facultative processing stays phase 2. | I6: BDOI answer A3 of 26-Sep-2026: Remittance handles the reinsurance transactions in Drop 1. Which transactions and their accounting are open (IQ20). | J6: Reinsurance premium and recoveries settled through BIBS from go-live; new posting rules for Comptrollership. | K6: Operations (Remittance); Comptrollership; Reinsurance | L6: 4 | M6: 12 | N6: 6 | O6: 2 | P6: =SUM(L6:O6) | Q6: =IF(P6=0,"0 - acceptance only",IF(P6<=3,"S",IF(P6<=10,"M",IF(P6<=25,"L","XL")))&" ("&P6&")") | S6: High | T6: Draft | U6: Head of Operations (Financial Transactions and Processing) | V6: DCR-210; IQ20; A3 | W6: Drop 1, second release (Jan - Feb 2027) | X6: Register DCR-210; Programme alignment 2.2 item 1
A7: CR-0003 | B7: Drop 1 | C7: BRD-02 | D7: Drop plan items 1.D2 and 1.D3: Operations BRD (Cashiering Addendum), (Remittance Addendum) | E7: FRS BRD-2 (Cashiering, Remittance chapters) | F7: Deferred pending BDOI answer | G7: The drop plan names a Cashiering Addendum and a Remittance Addendum to the Operations BRD. | H7: The Operations pack received has only Addendum 1 (RMTID.002, ADJID.014). FRS BRD-2 is written without the two addenda; they are taken into FRS BRD-2 v1.2 when received and their impact is estimated then. | I7: Documents not received (DCR-215, IQ20). | J7: Cashiering and Remittance requirements may change after FRS sign-off. | K7: Operations (Cashiering, Remittance) | L7: 3 | M7: 0 | N7: 0 | O7: 2 | P7: =SUM(L7:O7) | Q7: =IF(P7=0,"0 - acceptance only",IF(P7<=3,"S",IF(P7<=10,"M",IF(P7<=25,"L","XL")))&" ("&P7&")") | S7: Medium | T7: Draft | U7: Head of Operations (Financial Transactions and Processing) | V7: DCR-215; IQ20 | W7: After BDOI answer (slot set by the CCB) | X7: Register DCR-215; Programme alignment 2.2
A8: CR-0004 | B8: Drop 2 | C8: BRD-00 | D8: CORE-14.08-14.10; BR-146 to BR-148 (p.10); BRD-7 (no claim money through BDOI) | E8: FRS BRD-00 CLR-CR-02; FR-CM (none) | F8: Deferred pending BDOI answer | G8: Safekeeping of unclaimed settlement cheques, hand-over to and retrieval from Cashiering. | H8: BRD-7 has no claim money through BDOI (CLQ10) and Claims posts no accounting entry. If BDOI holds cheques: a cheque custody register in Claims using the Cashiering cheque hand-over. | I8: Conflict between the umbrella BRD and BRD-7; CRQ03, CLQ10, XQ13. | J8: Without a register, cheque custody stays manual outside BIBS. | K8: Claims; Operations (Cashiering) | L8: 2 | M8: 5 | N8: 3 | O8: 1 | P8: =SUM(L8:O8) | Q8: =IF(P8=0,"0 - acceptance only",IF(P8<=3,"S",IF(P8<=10,"M",IF(P8<=25,"L","XL")))&" ("&P8&")") | R8: 11 | S8: Medium | T8: For CCB review | U8: BIBS Product Owner with the Program Manager, Business Project Services | V8: DCR-164; CRQ03; CLQ10; XQ13 | W8: Drop 2 (Mar - Apr 2027) | X8: FRS BRD-00 chapter 5 (CLR-CR-02); Cross-BRD decisions XQ13
A9: CR-0005 | B9: Drop 1 | C9: BRD-00 | D9: CORE-16.06; BR-165 (p.11); BRD-9 CSF-EM10 (e-mail of 13-Feb-2026) | E9: FRS BRD-00 CLR-CR-03; FRS BRD-9 chapter 12 | F9: Scope reduction / descoped | G9: CSF case resolution: add and edit case details and status. | H9: Out of phase 1. BRD-9 puts case management out of scope and keeps case logging in SharePoint. If BDOI brings it in: a CSF case record in the CSF module. | I9: BRD-9 e-mail of 13-Feb-2026; CRQ04 open; XQ12. | J9: Contact Center cases stay in SharePoint; no case history in BIBS. | K9: Contact Center Management; Alternative Distribution | L9: 0 | M9: 0 | N9: 0 | O9: 1 | P9: =SUM(L9:O9) | Q9: =IF(P9=0,"0 - acceptance only",IF(P9<=3,"S",IF(P9<=10,"M",IF(P9<=25,"L","XL")))&" ("&P9&")") | R9: 18 | S9: Medium | T9: For CCB review | U9: Product Owner, CSF (Contact Center Management) | V9: DCR-163; CRQ04; XQ12 | W9: FRS sign-off (Nov 2026) | X9: FRS BRD-00 chapter 5 (CLR-CR-03); FRS BRD-9 chapter 12
A10: CR-0006 | B10: Programme | C10: BRD-00 | D10: CORE-18.01; BR-176 (p.11) | E10: FRS BRD-00 CLR-CR-09 | F10: Scope reduction / descoped | G10: Include any other or additional system capabilities (emerging capabilities). | H10: No work until the capabilities are listed: the requirement has no content to deliver or test. BDOI lists the capabilities or withdraws BR-176. | I10: CRQ10 open. | J10: None until BDOI names a capability; a named capability becomes its own CR. | K10: Business Project Services | L10: 0 | M10: 0 | N10: 0 | O10: 0 | P10: =SUM(L10:O10) | Q10: =IF(P10=0,"0 - acceptance only",IF(P10<=3,"S",IF(P10<=10,"M",IF(P10<=25,"L","XL")))&" ("&P10&")") | S10: Low | T10: For CCB review | U10: BIBS Product Owner with the Program Manager, Business Project Services | V10: CRQ10; CLR-CR-09 | W10: FRS sign-off (Nov 2026) | X10: FRS BRD-00 section 5
A11: CR-0007 | B11: Programme | C11: BRD-00 | D11: XC-21 ALeA e-mail address encoding (p.43) | E11: FRS BRD-00 CLR-CR-10 | F11: Deferred pending BDOI answer | G11: ALeA e-mail address encoding, as needed. | H11: Not in scope; the term is not defined in the BRD pack. | I11: CRQ20 open. | J11: None known until BDOI explains ALeA. | K11: BDOI IT | L11: 1 | M11: 0 | N11: 0 | O11: 0 | P11: =SUM(L11:O11) | Q11: =IF(P11=0,"0 - acceptance only",IF(P11<=3,"S",IF(P11<=10,"M",IF(P11<=25,"L","XL")))&" ("&P11&")") | S11: Low | T11: Draft | U11: BIBS Product Owner with the Program Manager, Business Project Services | V11: CRQ20; CLR-CR-10 | W11: After BDOI answer (slot set by the CCB) | X11: FRS BRD-00 section 5
A12: CR-0008 | B12: Programme | C12: BRD-00 | D12: XC-16; BR-183 (p.23) | E12: FRS BRD-00 traceability (OUT); A-CR-05 | F12: Behaviour differs from BRD | G12: The vendor uses Figma for design execution. | H12: Screens follow the BDO UX guidelines and the BIBS design system in code; the vendor-qualification items are met by the alignment pass and persona walkthroughs. BDOI supplies the icon set and design files (CRQ17). | I12: A-CR-05: BR-178 to BR-183 are vendor-qualification items. | J12: None on the business process. | K12: Business Project Services | L12: 0 | M12: 0 | N12: 0 | O12: 0 | P12: =SUM(L12:O12) | Q12: =IF(P12=0,"0 - acceptance only",IF(P12<=3,"S",IF(P12<=10,"M",IF(P12<=25,"L","XL")))&" ("&P12&")") | S12: Low | T12: For acceptance | U12: BIBS Product Owner with the Program Manager, Business Project Services | V12: CRQ17; A-CR-05 | W12: FRS sign-off (Nov 2026) | X12: FRS BRD-00 traceability XC-16
A13: CR-0009 | B13: Drop 0 | C13: BRD-00 | D13: CORE-17.01; BR-170 (p.11) | E13: FR-CR-031 | F13: Scope addition — beyond BRD | G13: Master data change logging for users, products, insurers and LOVs. No function BRD owns it. | H13: BIBS audits each action with a summary. Proposed: a field-level log (old and new values) for the registered master types. | I13: Umbrella requirement without an owning BRD (Drop 0 item 0.4); CRQ07 open on the master types, approver and viewers. | J13: Auditors can see what changed on a master record, field by field. | K13: Business Project Services; Compliance; MBS; Comptrollership | L13: 2 | M13: 6 | N13: 4 | O13: 1 | P13: =SUM(L13:O13) | Q13: =IF(P13=0,"0 - acceptance only",IF(P13<=3,"S",IF(P13<=10,"M",IF(P13<=25,"L","XL")))&" ("&P13&")") | S13: Medium | T13: Draft | U13: BIBS Product Owner with the Program Manager, Business Project Services | V13: DCR-174; CRQ07; CLR-CR-04 | W13: Drop 1, second release (Jan - Feb 2027) | X13: FRS BRD-00 chapter 5 (CLR-CR-04); register DCR-174
A14: CR-0010 | B14: Drop 0 | C14: BRD-00 | D14: CORE-17.02; BR-171 (p.11) | E14: FR-CR-061 | F14: Scope addition — beyond BRD | G14: Insurer management: risk participation, payment terms, remittance schedules on the insurer. | H14: The insurer page has no such attributes. Proposed: add the attributes and LOV INSURER_CONTACT_FUNCTION. | I14: Umbrella requirement without an owning BRD; CRQ08 open on meaning, owners and approval. | J14: One place for insurer terms used by Remittance and Collections. | K14: MBS; Operations (Remittance) | L14: 2 | M14: 4 | N14: 2 | O14: 1 | P14: =SUM(L14:O14) | Q14: =IF(P14=0,"0 - acceptance only",IF(P14<=3,"S",IF(P14<=10,"M",IF(P14<=25,"L","XL")))&" ("&P14&")") | S14: Medium | T14: Draft | U14: BIBS Product Owner with the Program Manager, Business Project Services | V14: CRQ08; CLR-CR-05 | W14: Drop 1, second release (Jan - Feb 2027) | X14: FRS BRD-00 chapter 5 (CLR-CR-05)
A15: CR-0011 | B15: Drop 0 | C15: BRD-00 | D15: CORE-17.04; BR-173, BR-174 (p.11) | E15: FR-CR-062 | F15: Scope addition — beyond BRD | G15: MIS field definition. | H15: Proposed: an MIS field catalogue that names existing data per entity; users do not add database fields (A-CR-06). | I15: Umbrella requirement without an owning BRD; CRQ09 (fixed list or user-defined fields). | J15: Consistent MIS reporting fields across modules and migration. | K15: Business Project Services; MIS; Marketing | L15: 2 | M15: 6 | N15: 3 | O15: 1 | P15: =SUM(L15:O15) | Q15: =IF(P15=0,"0 - acceptance only",IF(P15<=3,"S",IF(P15<=10,"M",IF(P15<=25,"L","XL")))&" ("&P15&")") | R15: 30 | S15: Medium | T15: Draft | U15: BIBS Product Owner with the Program Manager, Business Project Services | V15: CRQ09; CLR-CR-06 | W15: Drop 1, second release (Jan - Feb 2027) | X15: FRS BRD-00 chapter 5 (CLR-CR-06)
A16: CR-0012 | B16: Programme | C16: BRD-00 | D16: CORE-21.04; BR-053 (p.12) | E16: FR-CR-042 | F16: Scope addition — beyond BRD | G16: Dynamic report customisation: data fields, charts and summaries. | H16: BIBS has fixed report columns and saved parameter variants. Proposed: column layout stored in the variant. | I16: Umbrella requirement without an owning BRD; CRQ11 open. | J16: Users choose and order report columns without a change request. | K16: All report users | L16: 2 | M16: 8 | N16: 4 | O16: 1 | P16: =SUM(L16:O16) | Q16: =IF(P16=0,"0 - acceptance only",IF(P16<=3,"S",IF(P16<=10,"M",IF(P16<=25,"L","XL")))&" ("&P16&")") | S16: Medium | T16: Draft | U16: BIBS Product Owner with the Program Manager, Business Project Services | V16: DCR-177; CRQ11; CLR-CR-07 | W16: Drop 1, second release (Jan - Feb 2027) | X16: FRS BRD-00 chapter 5 (CLR-CR-07)
A17: CR-0013 | B17: Programme | C17: BRD-00 | D17: CORE-21.05; BR-054, BR-103 (p.12) | E17: FR-CR-043 | F17: Scope addition — beyond BRD | G17: Scheduled or on-demand report generation for any report. | H17: Only system-scheduled files exist. Proposed: report subscriptions per user (REPORT_SUBSCRIPTIONS_MAX 20; external domains limited). | I17: Umbrella requirement without an owning BRD; CRQ11 open. | J17: Users receive recurring reports by e-mail without manual runs. | K17: All report users | L17: 1 | M17: 6 | N17: 3 | O17: 1 | P17: =SUM(L17:O17) | Q17: =IF(P17=0,"0 - acceptance only",IF(P17<=3,"S",IF(P17<=10,"M",IF(P17<=25,"L","XL")))&" ("&P17&")") | S17: Medium | T17: Draft | U17: BIBS Product Owner with the Program Manager, Business Project Services | V17: DCR-177; CRQ11; CLR-CR-08 | W17: Drop 1, second release (Jan - Feb 2027) | X17: FRS BRD-00 chapter 5 (CLR-CR-08)
A18: CR-0014 | B18: Programme | C18: BRD-00 | D18: XC-02; BR-125, BR-152, BR-160, BR-203 (p.5, p.20-21) | E18: FR-CR-010, FR-CR-011 | F18: Scope addition — beyond BRD | G18: Centralised, real-time dashboards for all roles, with drill-down. | H18: Each module has its home page. Proposed: a role home with configurable widgets per role family (DASHBOARD_REFRESH_MINUTES 5). | I18: Umbrella requirement without an owning BRD; CRQ06 open (figures per role). | J18: Each role sees its work and figures on one page. | K18: All departments | L18: 3 | M18: 8 | N18: 4 | O18: 1 | P18: =SUM(L18:O18) | Q18: =IF(P18=0,"0 - acceptance only",IF(P18<=3,"S",IF(P18<=10,"M",IF(P18<=25,"L","XL")))&" ("&P18&")") | S18: Medium | T18: Draft | U18: BIBS Product Owner with the Program Manager, Business Project Services | V18: CRQ06; CLR-CR-11 | W18: Drop 1, second release (Jan - Feb 2027) | X18: FRS BRD-00 chapter 5 (CLR-CR-11)
A19: CR-0015 | B19: Drop 1 | C19: BRD-00 | D19: XC-13; BR-175 (p.23) | E19: FR-CR-090 | F19: Scope addition — beyond BRD | G19: Invoice Master List across workflows. | H19: Proposed: columns added to the Operations invoice ledger view. | I19: Umbrella requirement without an owning BRD; CRQ13 open. | J19: One list of invoices with their status across NB, Operations and Collections. | K19: Operations; Collections; Comptrollership | L19: 1 | M19: 3 | N19: 2 | O19: 1 | P19: =SUM(L19:O19) | Q19: =IF(P19=0,"0 - acceptance only",IF(P19<=3,"S",IF(P19<=10,"M",IF(P19<=25,"L","XL")))&" ("&P19&")") | S19: Low | T19: Draft | U19: BIBS Product Owner with the Program Manager, Business Project Services | V19: CRQ13; CLR-CR-12 | W19: Drop 1, second release (Jan - Feb 2027) | X19: FRS BRD-00 chapter 5 (CLR-CR-12)
A20: CR-0016 | B20: Drop 1 | C20: BRD-00 | D20: XC-19 (p.43); BRNB.100 related | E20: FR-CR-081; FR-NB-117 | F20: Integration dependency | G20: Invoice batch printing, delivery to insurers by SFTP and a delivery report, daily per insurer. | H20: Service invoices are issued and e-mailed. Proposed: daily batch per insurer at 20:00 PHT with SFTP delivery once the insurer SFTP addresses are given. | I20: CRQ18 open (format, SFTP addresses, replaces e-mail?). | J20: Insurers receive invoices in one daily file instead of single e-mails. | K20: Processing; Operations; BDOI IT | L20: 2 | M20: 6 | N20: 4 | O20: 1 | P20: =SUM(L20:O20) | Q20: =IF(P20=0,"0 - acceptance only",IF(P20<=3,"S",IF(P20<=10,"M",IF(P20<=25,"L","XL")))&" ("&P20&")") | S20: Medium | T20: Draft | U20: BDOI IT (integration owner) with the BIBS Product Owner | V20: CRQ18; CLR-CR-13 | W20: Drop 1, second release (Jan - Feb 2027) | X20: FRS BRD-00 chapter 5 (CLR-CR-13)
A21: CR-0017 | B21: Drop 0 | C21: BRD-00 | D21: XC-20 client migration and daily client batches (p.43); BRD-13 BRID 2.1 (p.7) | E21: FR-CR-082; FR-DM-031, FR-DM-032 | F21: Data migration | G21: Umbrella BRD: one-time client migration 2020 to present plus daily midday and EOD client batches with a modification report. | H21: Selective migration of clean client master data by the Data Migration programme; legacy read-only after cut-over; no daily client batches after go-live. | I21: Conflict between the umbrella and BRD-13, decided in the Data Migration design; CRQ19, DMQ05 open on the client scope. | J21: Legacy client changes stop at the freeze; BIBS is the client master from go-live. | K21: Business Project Services; Marketing; Processing | L21: 0 | M21: 0 | N21: 0 | O21: 1 | P21: =SUM(L21:O21) | Q21: =IF(P21=0,"0 - acceptance only",IF(P21<=3,"S",IF(P21<=10,"M",IF(P21<=25,"L","XL")))&" ("&P21&")") | S21: Medium | T21: For CCB review | U21: Program Manager, Business Project Services, with Comptrollership and Operations | V21: DCR-173; CRQ19; DMQ05; CLR-CR-14 | W21: Migration functions (Nov 2026 - Mar 2027) | X21: FRS BRD-00 chapter 5 (CLR-CR-14); register DCR-173
A22: CR-0018 | B22: Drop 1 | C22: BRD-00 | D22: XC-10; BR-039, BR-043 (p.14-15) | E22: FR-CR-093 | F22: Deferred pending BDOI answer | G22: SOA generated with the placement report and the Insurance Advice; service invoice issued to the insurer with the SOA at booking. | H22: Proposed after BDOI states which SOA is meant. | I22: CRQ12 open. | J22: Insurers and clients receive the SOA from BIBS instead of a manual document. | K22: Processing; Operations | L22: 1 | M22: 3 | N22: 2 | O22: 1 | P22: =SUM(L22:O22) | Q22: =IF(P22=0,"0 - acceptance only",IF(P22<=3,"S",IF(P22<=10,"M",IF(P22<=25,"L","XL")))&" ("&P22&")") | S22: Medium | T22: Draft | U22: BIBS Product Owner with the Program Manager, Business Project Services | V22: CRQ12; CLR-CR-15 | W22: After BDOI answer (slot set by the CCB) | X22: FRS BRD-00 chapter 5 (CLR-CR-15)
A23: CR-0019 | B23: Programme | C23: BRD-00 | D23: NFR sections of every BRD: service hours, availability, maintenance window, BCP (umbrella p.42-46) | E23: FRS BRD-00 section 7 | F23: NFR / infrastructure change | G23: Service hours differ by BRD (07:00-22:00 Mon-Sat NB and RN; 06:00-20:00 Mon-Fri Claims; 08:00-18:00 Mon-Fri SANC; others); availability 99.9% to 100%; maintenance windows 19:00-07:00 (ACCT) to 00:00-04:00 (SANC, SP). | H23: Proposed one BIBS-wide set: service 06:00-22:00 Mon-Sat plus month-end weekends; 99.9% within service hours; maintenance 00:00-04:00; batch after 22:00. | I23: XQ08; OQ44, CQ25, AQ27, PQ18, CLQ24, EBQ25, CSQ11, SP SQ21 / SQ22, RQ28. | J23: One service level for all departments; month-end work covered. | K23: All departments; BDOI IT | L23: 2 | M23: 0 | N23: 0 | O23: 2 | P23: =SUM(L23:O23) | Q23: =IF(P23=0,"0 - acceptance only",IF(P23<=3,"S",IF(P23<=10,"M",IF(P23<=25,"L","XL")))&" ("&P23&")") | S23: High | T23: For CCB review | U23: BIBS Product Owner with the Program Manager, Business Project Services | V23: DCR-133; DCR-134; DCR-138; DCR-057; XQ08 | W23: FRS sign-off (Nov 2026) | X23: Register DCR-133, 134, 138; FRS BRD-00 section 7
A24: CR-0020 | B24: Programme | C24: BRD-00 | D24: NFR recovery objectives: RPO 24 h (OPS, PM, EB), 4 h (CLXN, CLM, CSF); CSF backup every 15 minutes (BRCSF-011.001, p.11) | E24: FRS BRD-00 section 7; FR-CSF-043 | F24: NFR / infrastructure change | G24: Recovery objectives and backup frequency differ by BRD; the DR location is not stated. | H24: RPO 15 minutes (continuous WAL archiving) and RTO 4 hours for the whole platform, as in the IER. Proposed DR: RDS cross-region replica, S3 cross-region replication, EKS standby scaled at failover, DR runbook and a failover test. DR region to be named after the data-residency check. | I24: IER workbook v20 (BDO IT) states RPO 15 minutes, RTO 4 hours; IQ26 open on the DR region. | J24: One recovery target; CSF 15-minute backup met by continuous archiving. | K24: BDOI IT; all departments | L24: 2 | M24: 3 | N24: 4 | O24: 2 | P24: =SUM(L24:O24) | Q24: =IF(P24=0,"0 - acceptance only",IF(P24<=3,"S",IF(P24<=10,"M",IF(P24<=25,"L","XL")))&" ("&P24&")") | S24: High | T24: For CCB review | U24: BDO Cloud and Digital Operations Engineering (IER owner) with BDOI IT | V24: DCR-135; DCR-225; CSQ11; IQ26 | W24: Before go-live (Oct - Dec 2027) | X24: Register DCR-135, DCR-225; Programme alignment 6.2, 6.5
A25: CR-0021 | B25: Programme | C25: BRD-00 | D25: Retention: umbrella 5 years online / 15 offline (p.42-46); BRD-7 10 / 15; BRD-5, 10, 12 5 / 5; BRNB.106 (p.12) | E25: FR-NB-137; FRS BRD-00 section 7 | F25: NFR / infrastructure change | G25: Retain, archive and purge per the BRD values, which differ by BRD. | H25: Retention rules per record type with review counts (default 5 years online, 15 years archive; backup kept 7 years). Archive and purge wait until BDOI gives the retention per record type. | I25: Q39, CRQ22 open. | J25: Legal record keeping; database size and cost over time. | K25: Compliance; Comptrollership; BDOI IT; all record owners | L25: 2 | M25: 8 | N25: 4 | O25: 2 | P25: =SUM(L25:O25) | Q25: =IF(P25=0,"0 - acceptance only",IF(P25<=3,"S",IF(P25<=10,"M",IF(P25<=25,"L","XL")))&" ("&P25&")") | S25: High | T25: Draft | U25: BIBS Product Owner with the Program Manager, Business Project Services | V25: DCR-136; DCR-167; DCR-209; Q39; CRQ22 | W25: After BDOI answer (slot set by the CCB) | X25: FRS BRD-1 chapter 21 (BRNB.106); register DCR-136
A26: CR-0022 | B26: Programme | C26: BRD-00 | D26: Response times: 2 s (SP) to 10 s (NB, RN, UAM); umbrella under 5 s for every role (p.42) | E26: FRS BRD-00 section 7 | F26: NFR / infrastructure change | G26: Response-time targets differ by BRD. | H26: Proposed: screens and single-record actions p95 under 2 seconds; reports and batches run as jobs with progress. Proved in the performance test (deliverable 28). | I26: CRQ21 open. | J26: One testable target for every screen. | K26: All departments | L26: 1 | M26: 0 | N26: 0 | O26: 1 | P26: =SUM(L26:O26) | Q26: =IF(P26=0,"0 - acceptance only",IF(P26<=3,"S",IF(P26<=10,"M",IF(P26<=25,"L","XL")))&" ("&P26&")") | S26: Medium | T26: For CCB review | U26: BIBS Product Owner with the Program Manager, Business Project Services | V26: DCR-137; DCR-165; CRQ21 | W26: FRS sign-off (Nov 2026) | X26: Register DCR-137, DCR-165
A27: CR-0023 | B27: Programme | C27: BRD-00 | D27: Umbrella p.42: 1,344 named / 429 concurrent users; IER: about 1,200 internal users | E27: FRS BRD-00 section 7 | F27: NFR / infrastructure change | G27: User counts differ between the umbrella, BRD-3, BRD-7, BRD-8 and the IER. | H27: Sized and tested for 429 concurrent sessions as the peak case; no external users. | I27: CRQ21, CRQ24, IQ32 open. | J27: Infrastructure cost and the performance test depend on the figure. | K27: BDOI IT | L27: 1 | M27: 0 | N27: 0 | O27: 1 | P27: =SUM(L27:O27) | Q27: =IF(P27=0,"0 - acceptance only",IF(P27<=3,"S",IF(P27<=10,"M",IF(P27<=25,"L","XL")))&" ("&P27&")") | S27: Medium | T27: For CCB review | U27: BDO Cloud and Digital Operations Engineering (IER owner) with BDOI IT | V27: DCR-166; DCR-232; IQ32; CRQ24 | W27: FRS sign-off (Nov 2026) | X27: Register DCR-166, DCR-232
... A32: CR-0028 | B32: Programme | C32: BRD-00 | D32: BDOI answer A4 of 26-Sep-2026 (documents in S3 only); every BRD that stores files | E32: FRS BRD-00 section 4 (document generation, data management) | F32: NFR / infrastructure change | G32: Documents and attachments are stored in an S3 bucket only. | H32: Proposed: every file in S3 with its metadata in PostgreSQL; signed links after the permission check and audit; quarantine until the malware scan passes; retention and legal hold; every module moved to the S3 store and the existing files copied with a checksum check. | I32: Decision D9 (option C of DOCUMENT_STORAGE_DECISION, approved 26-Sep-2026); five design points still to confirm (IQ31). | J32: Smaller database and backups; encryption with BDOI keys; Object Lock for records under legal hold. | K32: BDOI IT; Compliance; all departments that upload or print documents | L32: 3 | M32: 22 | N32: 8 | O32: 3 | P32: =SUM(L32:O32) | Q32: =IF(P32=0,"0 - acceptance only",IF(P32<=3,"S",IF(P32<=10,"M",IF(P32<=25,"L","XL")))&" ("&P32&")") | S32: High | T32: For CCB review | U32: BDOI IT (integration owner) with the BIBS Product Owner | V32: DCR-227; D9; A4; IQ31; DSQ01-DSQ04 | W32: Drop 1, first release (Nov - Dec 2026) | X32: Document storage proposal section 4; Programme alignment 6.3
A33: CR-0029 | B33: Programme | C33: BRD-00 | D33: IER HW and SW sheet: ElastiCache Redis 7 "(cluster)" in Pre-Prod and PROD | E33: FRS BRD-00 section 7 | F33: NFR / infrastructure change | G33: The IER asks for ElastiCache in cluster mode. | H33: BIBS runs Redis 7 with cluster mode disabled (one shard, Multi-AZ replica); the cache clear and the job lock assume one shard. | I33: Technical constraint; IQ34 open. | J33: None if accepted; cluster mode enabled needs a code change. | K33: BDOI IT | L33: 0 | M33: 0 | N33: 0 | O33: 1 | P33: =SUM(L33:O33) | Q33: =IF(P33=0,"0 - acceptance only",IF(P33<=3,"S",IF(P33<=10,"M",IF(P33<=25,"L","XL")))&" ("&P33&")") | R33: 10 | S33: Low | T33: For CCB review | U33: BDO Cloud and Digital Operations Engineering (IER owner) with BDOI IT | V33: DCR-228; IQ34 | W33: Infrastructure before SIT (by Jan 2027) | X33: Register DCR-228; Programme alignment 6.2
A34: CR-0030 | B34: Programme | C34: BRD-00 | D34: IER VDI sheet: OpenJDK 17, Node 20, Angular SPA; RDS rows "RHEL 9.x" | E34: FRS BRD-00 section 7 | F34: NFR / infrastructure change | G34: The IER names JDK 17, Node 20 and an Angular front end. | H34: BIBS runs on Java 21, Spring Boot 3.5, Node 22 and React 19. Proposed IER correction: Temurin 21, Maven 3.9, Node 22, no Angular; RDS rows without an operating system. | I34: Technology baseline of BIBS; IQ28, IQ29. | J34: VDI images and base images follow the real stack. | K34: BDOI IT | L34: 0 | M34: 0 | N34: 0 | O34: 1 | P34: =SUM(L34:O34) | Q34: =IF(P34=0,"0 - acceptance only",IF(P34<=3,"S",IF(P34<=10,"M",IF(P34<=25,"L","XL")))&" ("&P34&")") | S34: Low | T34: For CCB review | U34: BDO Cloud and Digital Operations Engineering (IER owner) with BDOI IT | V34: DCR-224; IQ28; IQ29 | W34: Infrastructure before SIT (by Jan 2027) | X34: Register DCR-224; Programme alignment 6.2
A35: CR-0031 | B35: Programme | C35: BRD-00 | D35: IER assumptions: non-production 12 x 5 hours | E35: FRS BRD-00 section 7 | F35: NFR / infrastructure change | G35: Non-production environments run 12 hours a day, 5 days a week. | H35: Night jobs run from 20:00 to 06:00 PHT and would never fire. Proposed: non-production crons moved into the window by environment variables; extended hours booked for batch, month-end and migration rehearsal cycles. | I35: Technical constraint; IQ27 open. | J35: SIT and UAT can test the batch cycle and month-end. | K35: BDOI IT; QA | L35: 1 | M35: 1 | N35: 1 | O35: 1 | P35: =SUM(L35:O35) | Q35: =IF(P35=0,"0 - acceptance only",IF(P35<=3,"S",IF(P35<=10,"M",IF(P35<=25,"L","XL")))&" ("&P35&")") | S35: Medium | T35: For CCB review | U35: BDO Cloud and Digital Operations Engineering (IER owner) with BDOI IT | V35: DCR-226; IQ27 | W35: Infrastructure before SIT (by Jan 2027) | X35: Register DCR-226; Programme alignment 6.5
A36: CR-0032 | B36: Programme | C36: BRD-00 | D36: IER workbook v20 (HW and SW sheet, infrastructure diagram, architecture diagram): GitLab runner, Jenkins, ArgoCD and Helm | E36: FRS BRD-00 section 7 | F36: NFR / infrastructure change | G36: Three CI / CD toolchains appear in the IER; the BDO standard is not named. | H36: Proposed: a Helm chart or Kustomize overlays per environment and a pipeline on the toolchain BDO IT names (container registry, image base, code-quality server). | I36: IQ29 open. | J36: Releases follow BDO change management and tooling. | K36: BDOI IT | L36: 1 | M36: 5 | N36: 2 | O36: 1 | P36: =SUM(L36:O36) | Q36: =IF(P36=0,"0 - acceptance only",IF(P36<=3,"S",IF(P36<=10,"M",IF(P36<=25,"L","XL")))&" ("&P36&")") | S36: Medium | T36: Draft | U36: BDO Cloud and Digital Operations Engineering (IER owner) with BDOI IT | V36: DCR-224; IQ29 | W36: Infrastructure before SIT (by Jan 2027) | X36: Programme alignment 6.2, 6.6
A37: CR-0033 | B37: Programme | C37: BRD-00 | D37: IER: Dynatrace (VDI, K8s sheets) against CloudWatch, X-Ray, Prometheus, Loki, Grafana (diagram); BRD-11 NFR remote log server (p.14) | E37: FRS BRD-11 interfaces (remote log server, on hold) | F37: NFR / infrastructure change | G37: Two observability stacks named; BRD-11 asks for logs on a remote log server. | H37: Health checks, metrics for Prometheus and structured logs. Proposed: monitoring collectors and log shipping for the stack BDO IT chooses; alert routing per the alert catalogue (deliverable 38). | I37: IQ30 open. | J37: Production support sees BIBS in the BDO monitoring tools. | K37: BDOI IT; production support | L37: 1 | M37: 4 | N37: 2 | O37: 1 | P37: =SUM(L37:O37) | Q37: =IF(P37=0,"0 - acceptance only",IF(P37<=3,"S",IF(P37<=10,"M",IF(P37<=25,"L","XL")))&" ("&P37&")") | S37: Medium | T37: Draft | U37: BDO Cloud and Digital Operations Engineering (IER owner) with BDOI IT | V37: IQ30 | W37: Infrastructure before SIT (by Jan 2027) | X37: Programme alignment 6.2; FRS BRD-11 interfaces
A38: CR-0034 | B38: Programme | C38: BRD-00 | D38: Hosting appendix (access restricted to personnel in the Philippines); IER VDI sheet (15 users) | E38: FRS BRD-00 section 7 | F38: NFR / infrastructure change | G38: Access is restricted to personnel in the Philippines; the IER plans 15 VDI users without saying where they sit. | H38: Proposed: production and UAT reachable only from the Philippines; DEV and SIT with masked data reachable by named vendor staff through VDI. | I38: IQ28 open. | J38: Defines who can support the platform from where. | K38: BDOI IT; Compliance | L38: 1 | M38: 0 | N38: 0 | O38: 1 | P38: =SUM(L38:O38) | Q38: =IF(P38=0,"0 - acceptance only",IF(P38<=3,"S",IF(P38<=10,"M",IF(P38<=25,"L","XL")))&" ("&P38&")") | S38: Medium | T38: For CCB review | U38: BDO Cloud and Digital Operations Engineering (IER owner) with BDOI IT | V38: DCR-231; IQ28 | W38: Infrastructure before SIT (by Jan 2027) | X38: Register DCR-231
A39: CR-0035 | B39: Programme | C39: BRD-00 | D39: Concept paper "Advance Implementation of Renewal Processing" V1.0 (MANCOM, 06-Sep-2026); timeline slide | E39: FRS BRD-6 v1.1 introduction; FRS BRD-13 (FR-DM-120) | F39: BRD conflict resolved by decision | G39: The signed concept paper proposes an early renewal release by 15-Aug-2027 for January to May 2028 expiries, with early migration of client and reference data. | H39: Superseded: every module goes live together in January 2028; no early release and no early migration. Its capabilities stay in scope for January 2028. | I39: BDOI answer A1 of 26-Sep-2026. | J39: One cut-over; renewals of January to May 2028 run in BIBS after go-live (CR-0139). | K39: Marketing; Processing; Business Project Services | L39: 0 | M39: 0 | N39: 0 | O39: 1 | P39: =SUM(L39:O39) | Q39: =IF(P39=0,"0 - acceptance only",IF(P39<=3,"S",IF(P39<=10,"M",IF(P39<=25,"L","XL")))&" ("&P39&")") | S39: High | T39: For CCB review | U39: BIBS Product Owner with the Program Manager, Business Project Services | V39: DCR-218; DCR-240; A1 | W39: FRS sign-off (Nov 2026) | X39: Programme alignment 3; register DCR-218, DCR-240
A40: CR-0036 | B40: Programme | C40: BRD-00 | D40: Drop plan: BRD-10 Sanction Screening and CSF service requests not placed; Drop 0 items 0.1, 0.4, 0.5 without a BRD | E40: FRS BRD-00 section 3; FRS BRD-10; FRS BRD-9 | F40: BRD conflict resolved by decision | G40: The drop plan does not place BRD-10 or the CSF service-request functions, and names Drop 0 items without a governing BRD. | H40: Proposed: BRD-10 in Drop 1 with Client Onboarding; CSF service requests in Drop 2; Drop 0 acceptance on BRD-11 plus EIAM (item 0.1), CORE-17 of the umbrella (item 0.4) and the workflows of each BRD (item 0.5). Documents are filed by this map. | I40: IQ23, IQ24 open. | J40: Test and sign-off windows for the two BRDs. | K40: Compliance; Contact Center Management; Business Project Services | L40: 0 | M40: 0 | N40: 0 | O40: 1 | P40: =SUM(L40:O40) | Q40: =IF(P40=0,"0 - acceptance only",IF(P40<=3,"S",IF(P40<=10,"M",IF(P40<=25,"L","XL")))&" ("&P40&")") | S40: Medium | T40: For CCB review | U40: BIBS Product Owner with the Program Manager, Business Project Services | V40: DCR-213; DCR-214; IQ23; IQ24 | W40: FRS sign-off (Nov 2026) | X40: Programme alignment 2.2 items 5-6
A41: CR-0037 | B41: Programme | C41: BRD-00 | D41: BRD-8 BRID-022.01 (PDF/XLSX/CSV/WORD); other BRDs Excel and PDF; FRBS 3.2.0 (p.63) board schedules in Word | E41: FRS BRD-00 (report generation); FRS BRD-5 Vol.1 chapter 12 | F41: Scope addition — beyond BRD | G41: BRD-8 asks for Word export of reports; BRD-5 asks for board schedules in Word; the other BRDs ask for Excel and PDF. | H41: Word export for every report, Word on documents and schedules (GL-SCHEDULE, GL-BVA, FRBS-MANCOM-MARKET, RI-SOA, FIN-AP-VOUCHER), and a Word copy of each composed business document. | I41: Work item P2; FRS BRD-5 Vol.1 clarification CLR-AC-10. | J41: All departments can export to Word, beyond what their BRD asks. | K41: All report users; Comptrollership | L41: 0 | M41: 0 | N41: 0 | O41: 0 | P41: =SUM(L41:O41) | Q41: =IF(P41=0,"0 - acceptance only",IF(P41<=3,"S",IF(P41<=10,"M",IF(P41<=25,"L","XL")))&" ("&P41&")") | S41: Low | T41: For acceptance | U41: BIBS Product Owner with the Program Manager, Business Project Services | V41: DCR-161; P2; EBQ21 | W41: FRS sign-off (Nov 2026) | X41: Deliverables plan item 17; register DCR-161
A42: CR-0038 | B42: Programme | C42: BRD-00 | D42: BRD-7, BRD-4, BRD-10, BRD-2, BRD-1 shared-drive and FS04 targets; BRNB.110 (p.14); SNSRP-706 (p.19-20) | E42: FR-NB-038; FR-SS-071; FR-CM-064; FR-OP (extracts) | F42: Behaviour differs from BRD | G42: Several BRDs send files or lists to a shared drive or a designated folder. | H42: Files are kept in BIBS with download and notification; a shared-drive or SFTP drop is added only where a downstream system reads the file (for example FS04, CR-0104). | I42: BRD-12 asks for one master database instead of shared-drive files; OQ17, CLQ21. | J42: No uncontrolled copies on shared drives; users download from BIBS. | K42: Claims; Compliance; Operations; Marketing | L42: 0 | M42: 0 | N42: 0 | O42: 0 | P42: =SUM(L42:O42) | Q42: =IF(P42=0,"0 - acceptance only",IF(P42<=3,"S",IF(P42<=10,"M",IF(P42<=25,"L","XL")))&" ("&P42&")") | S42: Low | T42: For acceptance | U42: BIBS Product Owner with the Program Manager, Business Project Services | V42: DCR-152; OQ17; CLQ21 | W42: FRS sign-off (Nov 2026) | X42: Register DCR-152; FRS BRD-1 chapter 21
A43: CR-0039 | B43: Programme | C43: BRD-00 | D43: Ageing buckets: ACSL 2.14.x (p.124); Claims report list; BRCLXN reports; Cashiering reports | E43: FR-CM-060; FR-CL (reports); FR-AS (ACSL reports) | F43: BRD conflict resolved by decision | G43: Ageing buckets differ: ACSL 0-30 to over 730 days; Claims 0-30 to 181+; Collections and Cashiering without buckets. | H43: Proposed: ageing buckets configurable per report family, ACSL buckets as the default, as a shared setting. | I43: Conflict between BRDs; OQ43. | J43: Ageing reports agree across departments. | K43: Comptrollership; Claims; Collections; Operations | L43: 1 | M43: 3 | N43: 2 | O43: 0 | P43: =SUM(L43:O43) | Q43: =IF(P43=0,"0 - acceptance only",IF(P43<=3,"S",IF(P43<=10,"M",IF(P43<=25,"L","XL")))&" ("&P43&")") | S43: Low | T43: Draft | U43: BIBS Product Owner with the Program Manager, Business Project Services | V43: DCR-158; OQ43 | W43: Drop 1, second release (Jan - Feb 2027) | X43: Register DCR-158
A44: CR-0040 | B44: Programme | C44: BRD-00 | D44: BRD-8 (documents restricted by process), BRD-9 BRCSF-006, 009 (p.9-10), BRD-7 claim document types | E44: FR-CSF-030, FR-CSF-033; FR-EB-002 | F44: BRD conflict resolved by decision | G44: Contact Center users view and resend renewal advices and claims reports; EB restricts documents by process; claim documents may be confidential. | H44: Access class per document type; CSF users may view RENEWAL_ADVICE and CLAIM_REPORT; the loss advice and insurer claim reports are stored as CLAIM_REPORT. Final confidentiality matrix to confirm. | I44: XQ04, XQ05; CSQ07, EBQ15, CLQ26. | J44: Contact Center sees only the document types it is cleared for. | K44: Contact Center Management; Claims; Employee Benefits | L44: 0 | M44: 0 | N44: 0 | O44: 0 | P44: =SUM(L44:O44) | Q44: =IF(P44=0,"0 - acceptance only",IF(P44<=3,"S",IF(P44<=10,"M",IF(P44<=25,"L","XL")))&" ("&P44&")") | S44: Medium | T44: For acceptance | U44: BIBS Product Owner with the Program Manager, Business Project Services | V44: DCR-148; XQ04; XQ05; P3 | W44: FRS sign-off (Nov 2026) | X44: Cross-BRD decisions 5, 6.1
A45: CR-0041 | B45: Programme | C45: BRD-00 | D45: Report List as of 27-Apr-2026: #69, #73, #168 (BDOI remarks "DELETE" / "no longer needed") | E45: FRS BRD-00 report generation | F45: Scope reduction / descoped | G45: The Report List carries #69, #73 and #168. | H45: Marked DROPPED and not in scope, per the BDOI remarks in the Report List. | I45: Report List remarks (DCR-130, answered). | J45: None; the data is in the Policy Transmittal and e-policy reports. | K45: Report SMEs named in the Report List | L45: 0 | M45: 0 | N45: 0 | O45: 0 | P45: =SUM(L45:O45) | Q45: =IF(P45=0,"0 - acceptance only",IF(P45<=3,"S",IF(P45<=10,"M",IF(P45<=25,"L","XL")))&" ("&P45&")") | S45: Low | T45: For acceptance | U45: BIBS Product Owner with the Program Manager, Business Project Services | V45: DCR-130 | W45: FRS sign-off (Nov 2026) | X45: Register DCR-130
... A51: CR-0047 | B51: Drop 0 | C51: BRD-00 | D51: Drop plan INT-13 CCM (e-mail sending); every BRD that sends e-mail or protected documents | E51: FR-NB-013; FR-RN (letters); messaging | F51: Integration dependency | G51: All outbound e-mail goes through CCM. | H51: BIBS sends e-mail through SMTP with an outbox. Proposed: SMTP relay to CCM (configuration); an API interface with delivery status only if CCM requires it. | I51: IQ11 open (SMTP or API, attachment limit, bounces). | J51: Renewal advices and protected PDFs leave through the BDO mail platform. | K51: BDOI IT; Marketing; Processing | L51: 1 | M51: 2 | N51: 2 | O51: 0 | P51: =SUM(L51:O51) | Q51: =IF(P51=0,"0 - acceptance only",IF(P51<=3,"S",IF(P51<=10,"M",IF(P51<=25,"L","XL")))&" ("&P51&")") | S51: Medium | T51: Draft | U51: BDOI IT (integration owner) with the BIBS Product Owner | V51: IQ11 | W51: Drop 1, second release (Jan - Feb 2027) | X51: Programme alignment 5 (INT-13)
A52: CR-0048 | B52: Drop 1 | C52: BRD-01 | D52: BRNB.005 (p.50-51); BRNB.014 (p.56) | E52: FR-NB-014, FR-NB-051 | F52: Behaviour differs from BRD | G52: Multi-level approval TL, TH, UH. | H52: One approval stage per document; the approver permission decides who approves. | I52: Q05 open (approval chain). | J52: Fewer approval hops; a chain needs a CR if BDOI requires it. | K52: Marketing; TSU | L52: 0 | M52: 0 | N52: 0 | O52: 0 | P52: =SUM(L52:O52) | Q52: =IF(P52=0,"0 - acceptance only",IF(P52<=3,"S",IF(P52<=10,"M",IF(P52<=25,"L","XL")))&" ("&P52&")") | R52: 13 | S52: Medium | T52: For acceptance | U52: Product Owner, New Business (Marketing and Processing) | V52: Q05 | W52: FRS sign-off (Nov 2026) | X52: FRS BRD-1 chapter 21
A53: CR-0049 | B53: Drop 1 | C53: BRD-01 | D53: BRNB.015 (p.56) | E53: FR-NB-015 | F53: Integration dependency | G53: Data synchronised with the BDOI tracking systems. | H53: Internal events only; the external feed is on hold until BDOI names the systems. | I53: Q08 open. | J53: Other BDOI systems do not receive NB data automatically. | K53: Marketing; BDOI IT | L53: 2 | M53: 5 | N53: 3 | O53: 1 | P53: =SUM(L53:O53) | Q53: =IF(P53=0,"0 - acceptance only",IF(P53<=3,"S",IF(P53<=10,"M",IF(P53<=25,"L","XL")))&" ("&P53&")") | S53: Low | T53: Draft | U53: BDOI IT (integration owner) with the BIBS Product Owner | V53: Q08 | W53: After BDOI answer (slot set by the CCB) | X53: FRS BRD-1 chapter 21
A54: CR-0050 | B54: Drop 1 | C54: BRD-01 | D54: BRNB.018 (p.57); Report List #182 | E54: FR-NB-126; FR-RN-112 | F54: Deferred pending BDOI answer | G54: Late Renewal Requests Report in New Business. | H54: Neither the RN BRD nor the Report List defines it (#182 is a package report). Proposed: a variant of the renewal listing (renewals booked after expiry). | I54: Q09, RQ29, XQ09 open. | J54: Late renewals are visible in the Renewal status report until then. | K54: Marketing; Processing | L54: 1 | M54: 2 | N54: 2 | O54: 1 | P54: =SUM(L54:O54) | Q54: =IF(P54=0,"0 - acceptance only",IF(P54<=3,"S",IF(P54<=10,"M",IF(P54<=25,"L","XL")))&" ("&P54&")") | S54: Low | T54: Draft | U54: Product Owner, New Business (Marketing and Processing) | V54: DCR-009; Q09; RQ29; XQ09 | W54: Drop 1, second release (Jan - Feb 2027) | X54: FRS BRD-1 chapter 21; register DCR-009
A55: CR-0051 | B55: Drop 1 | C55: BRD-01 | D55: BRNB.019 (p.58); BRNB.094 (p.5-6) | E55: FR-NB-012 | F55: Behaviour differs from BRD | G55: Delete in-process records. | H55: Void with a reason; records are kept and hidden from standard lists. | I55: Audit trail and record retention. | J55: Voided records remain available to audit. | K55: Marketing; Processing | L55: 0 | M55: 0 | N55: 0 | O55: 0 | P55: =SUM(L55:O55) | Q55: =IF(P55=0,"0 - acceptance only",IF(P55<=3,"S",IF(P55<=10,"M",IF(P55<=25,"L","XL")))&" ("&P55&")") | S55: Low | T55: For acceptance | U55: Product Owner, New Business (Marketing and Processing) | V55: CRQ05 | W55: FRS sign-off (Nov 2026) | X55: FRS BRD-1 chapter 21
A56: CR-0052 | B56: Drop 1 | C56: BRD-01 | D56: BRNB.022 (p.60-61) | E56: FR-NB-010 | F56: Behaviour differs from BRD | G56: One status list including "Endorsed". | H56: Stages of four workflows (client, quotation, proposal, account); endorsements are invoices on a booked account. | I56: Q10 (master list of stages). | J56: Status reporting reads the workflow stages. | K56: Marketing; Processing | L56: 0 | M56: 0 | N56: 0 | O56: 0 | P56: =SUM(L56:O56) | Q56: =IF(P56=0,"0 - acceptance only",IF(P56<=3,"S",IF(P56<=10,"M",IF(P56<=25,"L","XL")))&" ("&P56&")") | S56: Low | T56: For acceptance | U56: Product Owner, New Business (Marketing and Processing) | V56: Q10 | W56: FRS sign-off (Nov 2026) | X56: FRS BRD-1 chapter 21
A57: CR-0053 | B57: Drop 0 | C57: BRD-01 | D57: BRNB.023 (p.61); Submitted Policies HLS report; CLPC HLS billing | E57: FR-NB-040 | F57: Integration dependency | G57: Quotation requests come directly from HLS with a source check. | H57: The user uploads the HLS extract; the direct interface is on hold. HLS (Drop 0) and LOAS (Drop 2) are one system, HL-LOAS; proposed one interface specification delivered in Drop 0. | I57: Q11, IQ07 open. | J57: Home-loan quotation requests are uploaded by hand until the interface exists. | K57: Marketing (CBG); BDOI IT | L57: 2 | M57: 6 | N57: 4 | O57: 1 | P57: =SUM(L57:O57) | Q57: =IF(P57=0,"0 - acceptance only",IF(P57<=3,"S",IF(P57<=10,"M",IF(P57<=25,"L","XL")))&" ("&P57&")") | S57: Medium | T57: Draft | U57: BDOI IT (integration owner) with the BIBS Product Owner | V57: DCR-216; Q11; IQ07 | W57: Drop 1, second release (Jan - Feb 2027) | X57: FRS BRD-1 chapter 21; Programme alignment 5 (INT-04)
A58: CR-0054 | B58: Drop 1 | C58: BRD-01 | D58: BRNB.029 (p.68-69); BRNB.063 (p.109-110) | E58: FR-NB-041, FR-NB-046 | F58: BRD conflict resolved by decision | G58: BRNB.029 requires a client code for a quotation; BRNB.063 allows a quotation without a client code. | H58: A prospect client code is created automatically at quotation; a confirmed client is required from account creation. | I58: Contradiction within BRD-1 resolved by proposal. | J58: Walk-in and bank-referred prospects can be quoted. | K58: Marketing | L58: 0 | M58: 0 | N58: 0 | O58: 0 | P58: =SUM(L58:O58) | Q58: =IF(P58=0,"0 - acceptance only",IF(P58<=3,"S",IF(P58<=10,"M",IF(P58<=25,"L","XL")))&" ("&P58&")") | S58: Medium | T58: For acceptance | U58: Product Owner, New Business (Marketing and Processing) | V58: DCR-001; Q13; Q20 | W58: FRS sign-off (Nov 2026) | X58: FRS BRD-1 chapter 21; register DCR-001
A59: CR-0055 | B59: Drop 1 | C59: BRD-01 | D59: BRNB.031 (p.71-72) | E59: FR-NB-124 | F59: Behaviour differs from BRD | G59: Print on A4 or Letter; summary or detail. | H59: A4 only; summary and detail are separate reports. | I59: BDO document template is A4. | J59: Letter-size printing not offered. | K59: Marketing; Processing | L59: 0 | M59: 0 | N59: 0 | O59: 0 | P59: =SUM(L59:O59) | Q59: =IF(P59=0,"0 - acceptance only",IF(P59<=3,"S",IF(P59<=10,"M",IF(P59<=25,"L","XL")))&" ("&P59&")") | R59: 2 | S59: Low | T59: For acceptance | U59: Product Owner, New Business (Marketing and Processing) | V59: - | W59: FRS sign-off (Nov 2026) | X59: FRS BRD-1 chapter 21
A60: CR-0056 | B60: Drop 1 | C60: BRD-01 | D60: BRNB.032 (p.72-73) | E60: FR-NB-033, FR-NB-063 | F60: Behaviour differs from BRD | G60: Account duplicates checked by e-mail, phone and ID. | H60: Clients are checked on identity keys (TIN, ID, name with birth date; e-mail and mobile warn); accounts on vehicle and location keys. | I60: Duplicate rules per record type. | J60: Fewer false duplicates on accounts of the same client. | K60: Marketing | L60: 0 | M60: 0 | N60: 0 | O60: 0 | P60: =SUM(L60:O60) | Q60: =IF(P60=0,"0 - acceptance only",IF(P60<=3,"S",IF(P60<=10,"M",IF(P60<=25,"L","XL")))&" ("&P60&")") | S60: Low | T60: For acceptance | U60: Product Owner, New Business (Marketing and Processing) | V60: DMQ04 | W60: FRS sign-off (Nov 2026) | X60: FRS BRD-1 chapter 21
A61: CR-0057 | B61: Drop 1 | C61: BRD-01 | D61: BRNB.036 (p.77-78) | E61: FR-NB-111 | F61: Behaviour differs from BRD | G61: Edit or delete accounts before batch booking. | H61: Edit the booking date and cost center, remove from the queue, cancel the batch. | I61: Account data is fixed once approved for booking. | J61: Corrections go back through the account workflow. | K61: Processing | L61: 0 | M61: 0 | N61: 0 | O61: 0 | P61: =SUM(L61:O61) | Q61: =IF(P61=0,"0 - acceptance only",IF(P61<=3,"S",IF(P61<=10,"M",IF(P61<=25,"L","XL")))&" ("&P61&")") | S61: Low | T61: For acceptance | U61: Product Owner, New Business (Marketing and Processing) | V61: - | W61: FRS sign-off (Nov 2026) | X61: FRS BRD-1 chapter 21
A62: CR-0058 | B62: Drop 1 | C62: BRD-01 | D62: BRNB.041 (p.94); BRNB.073 (p.116-117) | E62: FR-NB-040, FR-NB-100 | F62: Integration dependency | G62: Requests received by e-mail and e-policies received from insurers are read automatically. | H62: Requests are captured manually with the e-mail attached; e-policies are uploaded by Processing. Proposed: a mailbox reader through Microsoft Graph (M365 Exchange) if BDOI confirms its role against CCM. | I62: Q12, Q31, IQ12 open. | J62: Manual capture of e-mailed requests and e-policies. | K62: Marketing; Processing; BDOI IT | L62: 2 | M62: 8 | N62: 4 | O62: 1 | P62: =SUM(L62:O62) | Q62: =IF(P62=0,"0 - acceptance only",IF(P62<=3,"S",IF(P62<=10,"M",IF(P62<=25,"L","XL")))&" ("&P62&")") | S62: Medium | T62: Draft | U62: BDOI IT (integration owner) with the BIBS Product Owner | V62: Q12; Q31; IQ12 | W62: After BDOI answer (slot set by the CCB) | X62: FRS BRD-1 chapter 21; Programme alignment 5 (INT-14)
A63: CR-0059 | B63: Drop 1 | C63: BRD-01 | D63: BRNB.047, BRNB.065 (p.97-98, p.110-111) | E63: FR-NB-035 | F63: Behaviour differs from BRD | G63: Save draft and cancel in bulk updates. | H63: Review before commit; valid rows are saved directly. | I63: Bulk framework design. | J63: No draft bulk batches. | K63: Marketing | L63: 0 | M63: 0 | N63: 0 | O63: 0 | P63: =SUM(L63:O63) | Q63: =IF(P63=0,"0 - acceptance only",IF(P63<=3,"S",IF(P63<=10,"M",IF(P63<=25,"L","XL")))&" ("&P63&")") | S63: Low | T63: For acceptance | U63: Product Owner, New Business (Marketing and Processing) | V63: Q14 | W63: FRS sign-off (Nov 2026) | X63: FRS BRD-1 chapter 21
A64: CR-0060 | B64: Programme | C64: BRD-01 | D64: BRNB.057 (p.106); Claims dynamic reports (Q40) | E64: FR-NB-123; FR-CM-064 | F64: Scope reduction / descoped | G64: Users create dynamic reports. | H64: Saved report variants; no ad-hoc report builder. | I64: Q40 open (scope of dynamic reports). | J64: New report layouts need a change request (see also CR-0012). | K64: Marketing; Claims; all report users | L64: 0 | M64: 0 | N64: 0 | O64: 0 | P64: =SUM(L64:O64) | Q64: =IF(P64=0,"0 - acceptance only",IF(P64<=3,"S",IF(P64<=10,"M",IF(P64<=25,"L","XL")))&" ("&P64&")") | R64: 33 | S64: Medium | T64: For CCB review | U64: Product Owner, New Business (Marketing and Processing) | V64: Q40 | W64: FRS sign-off (Nov 2026) | X64: FRS BRD-1 chapter 21; BRD-7 requirements baseline (Q40)
A65: CR-0061 | B65: Drop 1 | C65: BRD-01 | D65: BRNB.062 (p.109); BRD 2.1.16 reactivate cancelled placements (p.180) | E65: FR-NB-085, FR-NB-086 | F65: Behaviour differs from BRD | G65: A cancelled placement returns to the previous workflow; reactivation is in the role matrix without a BRNB ID. | H65: Stage "Placement cancelled" until reactivated to "Ready for placement"; reactivation as in BRD 2.1.16. | I65: DCR-002 (no BRNB ID); Q25. | J65: Cancelled placements are visible until reactivated. | K65: Processing | L65: 0 | M65: 0 | N65: 0 | O65: 0 | P65: =SUM(L65:O65) | Q65: =IF(P65=0,"0 - acceptance only",IF(P65<=3,"S",IF(P65<=10,"M",IF(P65<=25,"L","XL")))&" ("&P65&")") | S65: Low | T65: For acceptance | U65: Product Owner, New Business (Marketing and Processing) | V65: DCR-002; Q25 | W65: FRS sign-off (Nov 2026) | X65: FRS BRD-1 chapter 21 and traceability
A66: CR-0062 | B66: Drop 1 | C66: BRD-01 | D66: BRNB.067 (p.114-115); BRNB.068 (p.115) | E66: FR-NB-090, FR-NB-091 | F66: Integration dependency | G66: The billing file is forwarded to CLPC automatically; QPS reference used. | H66: The user downloads the billing file and uploads the payment report; the ARN replaces the QPS reference. Proposed: automated transfer once LMS / HL-LOAS layouts and transport are given. | I66: Q28, IQ06 open. | J66: Manual file hand-over with CLPC. | K66: Processing; Operations (Cashiering); BDOI IT | L66: 2 | M66: 5 | N66: 3 | O66: 1 | P66: =SUM(L66:O66) | Q66: =IF(P66=0,"0 - acceptance only",IF(P66<=3,"S",IF(P66<=10,"M",IF(P66<=25,"L","XL")))&" ("&P66&")") | S66: Medium | T66: Draft | U66: BDOI IT (integration owner) with the BIBS Product Owner | V66: Q28; IQ06; DCR-027 | W66: Drop 1, second release (Jan - Feb 2027) | X66: FRS BRD-1 chapter 21; Programme alignment 5 (INT-03)
A67: CR-0063 | B67: Drop 1 | C67: BRD-01 | D67: BRNB.072 (p.116); BRNB.103 (p.10-11) | E67: FR-NB-082, FR-NB-083 | F67: Behaviour differs from BRD | G67: The hold cover request is sent automatically. | H67: Sent when Processing clicks Request Hold Cover. | I67: Q27 open (accounts needing an automatic hold cover). | J67: One click per hold cover. | K67: Processing | L67: 0 | M67: 0 | N67: 0 | O67: 0 | P67: =SUM(L67:O67) | Q67: =IF(P67=0,"0 - acceptance only",IF(P67<=3,"S",IF(P67<=10,"M",IF(P67<=25,"L","XL")))&" ("&P67&")") | R67: 7 | S67: Low | T67: For acceptance | U67: Product Owner, New Business (Marketing and Processing) | V67: Q27 | W67: FRS sign-off (Nov 2026) | X67: FRS BRD-1 chapter 21
A68: CR-0064 | B68: Drop 1 | C68: BRD-01 | D68: BRNB.075 (p.117-118) | E68: FR-NB-122 | F68: Behaviour differs from BRD | G68: Production per system; QPS placement report. | H68: Production per region, department, team and officer; Placement Summary. | I68: QPS is replaced by BIBS. | J68: None. | K68: Marketing | L68: 0 | M68: 0 | N68: 0 | O68: 0 | P68: =SUM(L68:O68) | Q68: =IF(P68=0,"0 - acceptance only",IF(P68<=3,"S",IF(P68<=10,"M",IF(P68<=25,"L","XL")))&" ("&P68&")") | S68: Low | T68: For acceptance | U68: Product Owner, New Business (Marketing and Processing) | V68: - | W68: FRS sign-off (Nov 2026) | X68: FRS BRD-1 chapter 21
A69: CR-0065 | B69: Drop 1 | C69: BRD-01 | D69: BRNB.080 (p.120) | E69: FR-NB-011 | F69: Behaviour differs from BRD | G69: Assign and re-assign workload. | H69: Manual claim and assignment; no automatic allocation. | I69: No allocation rule given in the BRD. | J69: Team leads assign work by hand. | K69: Marketing; Processing | L69: 0 | M69: 0 | N69: 0 | O69: 0 | P69: =SUM(L69:O69) | Q69: =IF(P69=0,"0 - acceptance only",IF(P69<=3,"S",IF(P69<=10,"M",IF(P69<=25,"L","XL")))&" ("&P69&")") | R69: 12 | S69: Low | T69: For acceptance | U69: Product Owner, New Business (Marketing and Processing) | V69: - | W69: FRS sign-off (Nov 2026) | X69: FRS BRD-1 chapter 21
A70: CR-0066 | B70: Drop 1 | C70: BRD-01 | D70: BRNB.083 (p.121) | E70: FR-NB-132 | F70: Behaviour differs from BRD | G70: Delete LOVs. | H70: Values are deactivated, never deleted. | I70: Historical records keep their values. | J70: None. | K70: MBS; System Administrator | L70: 0 | M70: 0 | N70: 0 | O70: 0 | P70: =SUM(L70:O70) | Q70: =IF(P70=0,"0 - acceptance only",IF(P70<=3,"S",IF(P70<=10,"M",IF(P70<=25,"L","XL")))&" ("&P70&")") | S70: Low | T70: For acceptance | U70: Product Owner, New Business (Marketing and Processing) | V70: - | W70: FRS sign-off (Nov 2026) | X70: FRS BRD-1 chapter 21
A71: CR-0067 | B71: Drop 1 | C71: BRD-01 | D71: BRNB.091 (p.4) | E71: FR-NB-036 | F71: Deferred pending BDOI answer | G71: Tags and instructions are enforced. | H71: Banner only (warn); blocking is on hold until BDOI lists the tags that block. | I71: Q18 open. | J71: Users can proceed past a tag after the warning. | K71: Marketing; Compliance | L71: 1 | M71: 3 | N71: 2 | O71: 1 | P71: =SUM(L71:O71) | Q71: =IF(P71=0,"0 - acceptance only",IF(P71<=3,"S",IF(P71<=10,"M",IF(P71<=25,"L","XL")))&" ("&P71&")") | S71: Medium | T71: Draft | U71: Product Owner, New Business (Marketing and Processing) | V71: Q18 | W71: After BDOI answer (slot set by the CCB) | X71: FRS BRD-1 chapter 21
A72: CR-0068 | B72: Drop 1 | C72: BRD-01 | D72: BRNB.092 (p.5) | E72: FR-NB-020 | F72: Deferred pending BDOI answer | G72: Authoritative source per data element. | H72: Proposed: a data governance register naming the authoritative source per data element, once BDOI answers Q37. | I72: Q37 open. | J72: Source of truth per data element is documented outside BIBS. | K72: Business Project Services; MIS | L72: 2 | M72: 4 | N72: 2 | O72: 1 | P72: =SUM(L72:O72) | Q72: =IF(P72=0,"0 - acceptance only",IF(P72<=3,"S",IF(P72<=10,"M",IF(P72<=25,"L","XL")))&" ("&P72&")") | S72: Low | T72: Draft | U72: Product Owner, New Business (Marketing and Processing) | V72: Q37 | W72: After BDOI answer (slot set by the CCB) | X72: FRS BRD-1 chapter 21 and traceability
A73: CR-0069 | B73: Drop 1 | C73: BRD-01 | D73: BRNB.097 (p.6-7); BRRN.033 (p.10); BRID-022.01; BRIDSP-26, 27 | E73: FR-NB-119; FR-RN; FR-EB-061; FR-SP | F73: BRD conflict resolved by decision | G73: NB and Renewal classification per transaction, from creation to the invoice and as a report filter (four BRDs). | H73: Business type on the account (BT0), carried to the invoice and used as a report filter; NB booking stamps New Business. | I73: Decision D1. | J73: Production reports split NB and Renewal consistently. | K73: Marketing; Processing; Comptrollership | L73: 0 | M73: 0 | N73: 0 | O73: 0 | P73: =SUM(L73:O73) | Q73: =IF(P73=0,"0 - acceptance only",IF(P73<=3,"S",IF(P73<=10,"M",IF(P73<=25,"L","XL")))&" ("&P73&")") | S73: Medium | T73: For acceptance | U73: Product Owner, New Business (Marketing and Processing) | V73: DCR-010; D1; BT0 | W73: FRS sign-off (Nov 2026) | X73: FRS BRD-1 chapter 21; Cross-BRD decisions D1, 6.1
A74: CR-0070 | B74: Drop 1 | C74: BRD-01 | D74: BRNB.099 (p.8) | E74: FR-NB-037 | F74: Deferred pending BDOI answer | G74: Leads management. | H74: Prospects only; leads management is on hold. | I74: Q19 open. | J74: Leads are tracked outside BIBS. | K74: Marketing | L74: 2 | M74: 8 | N74: 4 | O74: 1 | P74: =SUM(L74:O74) | Q74: =IF(P74=0,"0 - acceptance only",IF(P74<=3,"S",IF(P74<=10,"M",IF(P74<=25,"L","XL")))&" ("&P74&")") | S74: Low | T74: Draft | U74: Product Owner, New Business (Marketing and Processing) | V74: Q19 | W74: After BDOI answer (slot set by the CCB) | X74: FRS BRD-1 chapter 21
A75: CR-0071 | B75: Drop 1 | C75: BRD-01 | D75: BRNB.104 (p.11); BRIDSP-02 (p.8) | E75: FR-NB-101; FR-SP-002 | F75: Deferred pending BDOI answer | G75: Extraction from uploaded documents, including scanned submitted policies. | H75: Text PDFs are extracted; OCR of scanned documents waits for BDOI (SP SQ03). | I75: Q24 open (documents to extract; OCR). | J75: Scanned documents are keyed by the user. | K75: Processing; Submitted Policies | L75: 2 | M75: 8 | N75: 5 | O75: 1 | P75: =SUM(L75:O75) | Q75: =IF(P75=0,"0 - acceptance only",IF(P75<=3,"S",IF(P75<=10,"M",IF(P75<=25,"L","XL")))&" ("&P75&")") | S75: Medium | T75: Draft | U75: Product Owner, New Business (Marketing and Processing) | V75: Q24 | W75: After BDOI answer (slot set by the CCB) | X75: FRS BRD-1 chapter 21; FRS BRD-12 scope
A76: CR-0072 | B76: Drop 1 | C76: BRD-01 | D76: BRNB.107 (p.12-13); PMADD07, PMADD08 (p.5-6) | E76: FR-NB-118; FR-PM-080 | F76: Behaviour differs from BRD | G76: Incentive indicator on booking. | H76: The indicator comes from the BRD-3 incentive criteria on the products matrix; the booking incentive rules are frozen. | I76: One incentive master (DCR-037). | J76: Incentive criteria maintained once by MBS. | K76: Processing; MBS | L76: 0 | M76: 0 | N76: 0 | O76: 0 | P76: =SUM(L76:O76) | Q76: =IF(P76=0,"0 - acceptance only",IF(P76<=3,"S",IF(P76<=10,"M",IF(P76<=25,"L","XL")))&" ("&P76&")") | S76: Low | T76: For acceptance | U76: Product Owner, New Business (Marketing and Processing) | V76: DCR-037 | W76: FRS sign-off (Nov 2026) | X76: FRS BRD-1 chapter 21; BRD-3 requirements baseline
A77: CR-0073 | B77: Drop 1 | C77: BRD-01 | D77: BRNB.040, BRNB.087 (p.93-94, p.122); BRD-11 NFR (p.13-14, 17); BRD-4, BRD-7 NFR (Windows credentials); BRCSF-001 (p.6) | E77: FR-UA-003; FR-NB-130; FR-CM-001; FR-CSF-001 | F77: Integration dependency | G77: Sign-in with the BDO profile: Windows ID through BDO EUA, LDAP / AD or SSO. | H77: BIBS sign-in with user ID and password. BDOI named EIAM on Microsoft Entra ID: proposed OpenID Connect sign-in (authorisation code with PKCE), identity mapped to the BIBS user, roles kept in BIBS, BIBS sign-in kept for a break-glass administrator. | I77: Decision D6; drop plan Drop 0 (EIAM); IQ04 open. | J77: Single sign-on for all internal users; password, MFA and lock-out move to Entra ID. | K77: All departments; ITIO; BDOI IT | L77: 3 | M77: 12 | N77: 6 | O77: 2 | P77: =SUM(L77:O77) | Q77: =IF(P77=0,"0 - acceptance only",IF(P77<=3,"S",IF(P77<=10,"M",IF(P77<=25,"L","XL")))&" ("&P77&")") | S77: High | T77: Draft | U77: UAM Product Owner with ITIO | V77: DCR-143; DCR-230; D6; IQ04; Q42; UQ04 | W77: Drop 1, first release (Nov - Dec 2026) | X77: FRS BRD-11 v1.1 (FR-UA-003); FRS BRD-1 chapter 21; Programme alignment 5 (INT-01)
A78: CR-0074 | B78: Drop 1 | C78: BRD-01 | D78: Drop plan item 1.U6 (EB placement in Drop 1); BRD-8 in Drop 2 | E78: FR-EB-046, FR-EB-051; FR-NB (placement) | F78: BRD conflict resolved by decision | G78: EB placement and EB upstream reports are in Drop 1 while the EB module is in Drop 2. | H78: Proposed: EB programmes are placed through the NB placement screens in Drop 1; each Report List item goes with the drop of its owning module. | I78: IQ22 open. | J78: EB placement is tested with NB in Drop 1. | K78: Employee Benefits; Processing | L78: 1 | M78: 0 | N78: 1 | O78: 1 | P78: =SUM(L78:O78) | Q78: =IF(P78=0,"0 - acceptance only",IF(P78<=3,"S",IF(P78<=10,"M",IF(P78<=25,"L","XL")))&" ("&P78&")") | S78: Low | T78: For CCB review | U78: Product Owner, Employee Benefits | V78: DCR-235; IQ22 | W78: FRS sign-off (Nov 2026) | X78: Programme alignment 2.2 item 8
A79: CR-0075 | B79: Drop 1 | C79: BRD-02 | D79: BRQID.003 (p.17) | E79: FR-OP-003 | F79: Behaviour differs from BRD | G79: Users customise or filter the Operations sections. | H79: Sections are filtered by role; a personal pin or hide of sections is not proposed. | I79: Role menus meet the access need. | J79: Users cannot hide sections they do not use. | K79: Operations | L79: 0 | M79: 0 | N79: 0 | O79: 0 | P79: =SUM(L79:O79) | Q79: =IF(P79=0,"0 - acceptance only",IF(P79<=3,"S",IF(P79<=10,"M",IF(P79<=25,"L","XL")))&" ("&P79&")") | R79: 3 | S79: Low | T79: For acceptance | U79: Head of Operations (Financial Transactions and Processing) | V79: - | W79: FRS sign-off (Nov 2026) | X79: FRS BRD-2 chapter 12
A80: CR-0076 | B80: Drop 1 | C80: BRD-02 | D80: RMTID.040 (p.69-70) | E80: FR-OP (remittance locks) | F80: Deferred pending BDOI answer | G80: Lock the invoice while it is "still with Comptrollership". | H80: Remittance and Adjustment lock the invoice while they work on it; no Comptrollership lock until BDOI names the activity. | I80: OQ28 open. | J80: An invoice under Comptrollership review can still be adjusted. | K80: Operations; Comptrollership | L80: 1 | M80: 2 | N80: 1 | O80: 0 | P80: =SUM(L80:O80) | Q80: =IF(P80=0,"0 - acceptance only",IF(P80<=3,"S",IF(P80<=10,"M",IF(P80<=25,"L","XL")))&" ("&P80&")") | S80: Medium | T80: Draft | U80: Head of Operations (Financial Transactions and Processing) | V80: OQ28 | W80: After BDOI answer (slot set by the CCB) | X80: FRS BRD-2 chapter 12
A81: CR-0077 | B81: Drop 1 | C81: BRD-02 | D81: MKTID.001 (p.70-71); RMTID.016 (p.57-58) | E81: FR-OP (remittance schedule) | F81: Behaviour differs from BRD | G81: Marketing initiates the request to send the schedule. | H81: The Remittance processor sends the approved schedule from the batch, once. | I81: OQ22. | J81: Marketing no longer triggers the schedule. | K81: Operations (Remittance); Marketing | L81: 0 | M81: 0 | N81: 0 | O81: 0 | P81: =SUM(L81:O81) | Q81: =IF(P81=0,"0 - acceptance only",IF(P81<=3,"S",IF(P81<=10,"M",IF(P81<=25,"L","XL")))&" ("&P81&")") | S81: Low | T81: For acceptance | U81: Head of Operations (Financial Transactions and Processing) | V81: OQ22 | W81: FRS sign-off (Nov 2026) | X81: FRS BRD-2 chapter 12
A82: CR-0078 | B82: Drop 1 | C82: BRD-02 | D82: RMTID.002 (p.50); Addendum 1 (p.4-5) | E82: FR-OP (remittance extraction) | F82: BRD conflict resolved by decision | G82: Main BRD: edit the extracted file online and push it with or without edits. | H82: Addendum 1 governs: rows are excluded and restored with a reason; financial fields cannot be edited. | I82: Operations Addendum 1 (DCR-011 answered). | J82: No editing of financial data in the remittance file. | K82: Operations (Remittance) | L82: 0 | M82: 0 | N82: 0 | O82: 0 | P82: =SUM(L82:O82) | Q82: =IF(P82=0,"0 - acceptance only",IF(P82<=3,"S",IF(P82<=10,"M",IF(P82<=25,"L","XL")))&" ("&P82&")") | S82: Medium | T82: For acceptance | U82: Head of Operations (Financial Transactions and Processing) | V82: DCR-011 | W82: FRS sign-off (Nov 2026) | X82: FRS BRD-2 chapter 12; register DCR-011
A83: CR-0079 | B83: Drop 1 | C83: BRD-02 | D83: CSHID.001-005 (p.23-28) | E83: FR-OP (receipt cancellation and reinstatement) | F83: Scope addition — beyond BRD | G83: Cancellation and reinstatement of receipts without a stated approver. | H83: A cancellation or reinstatement is a request approved by a Cashiering TL / TH (four eyes) before it posts. | I83: OQ06; control over receipts. | J83: One more approval step per cancellation. | K83: Operations (Cashiering) | L83: 0 | M83: 0 | N83: 0 | O83: 0 | P83: =SUM(L83:O83) | Q83: =IF(P83=0,"0 - acceptance only",IF(P83<=3,"S",IF(P83<=10,"M",IF(P83<=25,"L","XL")))&" ("&P83&")") | S83: Medium | T83: For acceptance | U83: Head of Operations (Financial Transactions and Processing) | V83: OQ06 | W83: FRS sign-off (Nov 2026) | X83: FRS BRD-2 chapter 12
A84: CR-0080 | B84: Drop 1 | C84: BRD-02 | D84: CSHID.007 (p.29) | E84: FR-OP (OR issue) | F84: Behaviour differs from BRD | G84: One OR per remittance batch, or per payment unless consolidated. | H84: Remittance approval issues one commission OR per batch; the Collection upload issues one OR per insurer, certificate and payment. | I84: OQ49. | J84: OR count follows batch and insurer. | K84: Operations (Cashiering); Comptrollership | L84: 0 | M84: 0 | N84: 0 | O84: 0 | P84: =SUM(L84:O84) | Q84: =IF(P84=0,"0 - acceptance only",IF(P84<=3,"S",IF(P84<=10,"M",IF(P84<=25,"L","XL")))&" ("&P84&")") | S84: Medium | T84: For acceptance | U84: Head of Operations (Financial Transactions and Processing) | V84: OQ49 | W84: FRS sign-off (Nov 2026) | X84: FRS BRD-2 chapter 12
A85: CR-0081 | B85: Drop 0 | C85: BRD-02 | D85: CSHID.008 (p.29-32); DIS 2.22.0 (p.93); DIS 2.16.1 (p.88) | E85: FR-OP-015; FR-DS (bank uploads, DCTF) | F85: Integration dependency | G85: Payment files are encrypted and cannot be edited; Trade, CLPC and Direct Credit run by IT. Drop plan: OBPCS, Old BOB, PMS, TFS, AFTS and CMS / New BOB channels. | H85: Operations users upload the files; each file is stored read-only with its SHA-256 and a duplicate is refused; layouts are configurable. Disbursement uses a minimal CSV for bank uploads and a DCTF without trailer. Proposed: layouts per channel in the layout table, the CMS / New BOB outward file in Disbursement, automated transfer where BDO IT offers it; AFTS purpose to confirm. | I85: OQ03, OQ04, AQ09, IQ09, IQ10, IQ14 open. | J85: Bank files handled by upload until the layouts and transport are given. | K85: Operations (Cashiering); Comptrollership (Disbursement); BDOI IT | L85: 3 | M85: 10 | N85: 6 | O85: 1 | P85: =SUM(L85:O85) | Q85: =IF(P85=0,"0 - acceptance only",IF(P85<=3,"S",IF(P85<=10,"M",IF(P85<=25,"L","XL")))&" ("&P85&")") | S85: High | T85: Draft | U85: BDOI IT (integration owner) with the BIBS Product Owner | V85: DCR-234; OQ03; OQ04; AQ09; IQ09; IQ10; IQ14 | W85: Drop 1, second release (Jan - Feb 2027) | X85: FRS BRD-2 chapter 12; FRS BRD-5 Vol.2 chapter 12; Programme alignment 5 (INT-06 to INT-10)
A86: CR-0082 | B86: Drop 1 | C86: BRD-02 | D86: CSHID.016 (p.37-38); ADJID.026 | E86: FR-OP (minimal balance sweep) | F86: Behaviour differs from BRD | G86: PR up to 10.00 reversed; file 10.00-100.00 written off (10.00 in both ranges). | H86: The sweep skips an invoice already written off by the file, so a balance is never reversed twice. | I86: OQ11. | J86: No double reversal at 10.00. | K86: Operations; Comptrollership | L86: 0 | M86: 0 | N86: 0 | O86: 0 | P86: =SUM(L86:O86) | Q86: =IF(P86=0,"0 - acceptance only",IF(P86<=3,"S",IF(P86<=10,"M",IF(P86<=25,"L","XL")))&" ("&P86&")") | S86: Low | T86: For acceptance | U86: Head of Operations (Financial Transactions and Processing) | V86: OQ11 | W86: FRS sign-off (Nov 2026) | X86: FRS BRD-2 chapter 12
A87: CR-0083 | B87: Drop 1 | C87: BRD-02 | D87: RMTID.005 (p.52) | E87: FR-OP (extraction queue) | F87: Behaviour differs from BRD | G87: Trigger extraction at end of day "if payment application is searched". | H87: A user queues the searched invoice for the evening extraction run. | I87: OQ18. | J87: None. | K87: Operations (Remittance) | L87: 0 | M87: 0 | N87: 0 | O87: 0 | P87: =SUM(L87:O87) | Q87: =IF(P87=0,"0 - acceptance only",IF(P87<=3,"S",IF(P87<=10,"M",IF(P87<=25,"L","XL")))&" ("&P87&")") | S87: Low | T87: For acceptance | U87: Head of Operations (Financial Transactions and Processing) | V87: OQ18 | W87: FRS sign-off (Nov 2026) | X87: FRS BRD-2 chapter 12
A88: CR-0084 | B88: Drop 1 | C88: BRD-02 | D88: RMTID.014 (p.56-57) | E88: FR-OP (remittance extraction rules) | F88: Deferred pending BDOI answer | G88: Expected result: remit the DTIP balance; acceptance criteria: flag and exclude. | H88: Excluded by default (EXCLUDE); CAP remits the DTIP balance only. BDOI chooses the setting. | I88: OQ19 open; register priority item DCR-015. | J88: Remittance to insurers withheld or capped when the paid AR exceeds the DTIP balance. | K88: Operations (Remittance); Comptrollership | L88: 0 | M88: 0 | N88: 1 | O88: 0 | P88: =SUM(L88:O88) | Q88: =IF(P88=0,"0 - acceptance only",IF(P88<=3,"S",IF(P88<=10,"M",IF(P88<=25,"L","XL")))&" ("&P88&")") | S88: High | T88: For CCB review | U88: Head of Operations (Financial Transactions and Processing) | V88: DCR-015; OQ19 | W88: FRS sign-off (Nov 2026) | X88: FRS BRD-2 chapter 12; register priority list
A89: CR-0085 | B89: Drop 1 | C89: BRD-02 | D89: RMTID.016 (p.57-58) | E89: FR-OP (OR comparison) | F89: Deferred pending BDOI answer | G89: Compare the insurer OR amount with the paid PR. | H89: Exact comparison per invoice; no tolerance until BDOI gives one. | I89: OQ22 open. | J89: Small differences are flagged for manual review. | K89: Operations (Remittance) | L89: 0 | M89: 1 | N89: 1 | O89: 0 | P89: =SUM(L89:O89) | Q89: =IF(P89=0,"0 - acceptance only",IF(P89<=3,"S",IF(P89<=10,"M",IF(P89<=25,"L","XL")))&" ("&P89&")") | S89: Low | T89: Draft | U89: Head of Operations (Financial Transactions and Processing) | V89: OQ22 | W89: After BDOI answer (slot set by the CCB) | X89: FRS BRD-2 chapter 12
A90: CR-0086 | B90: Drop 1 | C90: BRD-02 | D90: RMTID.017 (p.58-59); RMTID.019 (p.59-60) | E90: FR-OP (remittance eligibility, statuses) | F90: Behaviour differs from BRD | G90: Checks at least 3 banking days old and cleared; eight statuses that mix payment and remittance states. | H90: Banking days counted from the last applied value date on the BDOI banking-day calendar, cleared status from the payment application; the invoice keeps a payment status and a remittance status, and the batch has its own stages. | I90: OQ20, OQ21. | J90: Status reports show two statuses per invoice. | K90: Operations | L90: 0 | M90: 0 | N90: 0 | O90: 0 | P90: =SUM(L90:O90) | Q90: =IF(P90=0,"0 - acceptance only",IF(P90<=3,"S",IF(P90<=10,"M",IF(P90<=25,"L","XL")))&" ("&P90&")") | S90: Low | T90: For acceptance | U90: Head of Operations (Financial Transactions and Processing) | V90: OQ20; OQ21 | W90: FRS sign-off (Nov 2026) | X90: FRS BRD-2 chapter 12
A91: CR-0087 | B91: Drop 1 | C91: BRD-02 | D91: PRCID.002 (p.79); PRCID.030 (p.85) | E91: FR-OP-070 to FR-OP-074 | F91: Scope addition — beyond BRD | G91: Only the Remarks column is editable; four reconciliation statuses. | H91: Remarks and Incentive columns and 200 blank rows are editable so the insurer can add unbooked production; a fifth status BDOI_ONLY marks booked accounts the insurer did not return. | I91: PRCID.022; analysis R6 5.1. | J91: Unbooked production is captured in the same file. | K91: Operations (Production Reconciliation) | L91: 0 | M91: 0 | N91: 0 | O91: 0 | P91: =SUM(L91:O91) | Q91: =IF(P91=0,"0 - acceptance only",IF(P91<=3,"S",IF(P91<=10,"M",IF(P91<=25,"L","XL")))&" ("&P91&")") | S91: Low | T91: For acceptance | U91: Head of Operations (Financial Transactions and Processing) | V91: PRCID.022 | W91: FRS sign-off (Nov 2026) | X91: FRS BRD-2 chapter 12
A92: CR-0088 | B92: Drop 2 | C92: BRD-02 | D92: PRCID.014, PRCID.021 (p.82); Annex IV #5 | E92: FR-OP-070 to FR-OP-074 | F92: Scope reduction / descoped | G92: Filter by BDOI location; Sum Insured on the production register. | H92: Items filter by AO, sales unit, segment and product line; the location filter is on the reports only. Sum Insured is left out: the invoice ledger does not hold it. | I92: Data not held in the invoice ledger. | J92: Sum Insured read from the account when needed. | K92: Operations (Production Reconciliation) | L92: 0 | M92: 0 | N92: 0 | O92: 0 | P92: =SUM(L92:O92) | Q92: =IF(P92=0,"0 - acceptance only",IF(P92<=3,"S",IF(P92<=10,"M",IF(P92<=25,"L","XL")))&" ("&P92&")") | R92: 4 | S92: Low | T92: For acceptance | U92: Head of Operations (Financial Transactions and Processing) | V92: - | W92: FRS sign-off (Nov 2026) | X92: FRS BRD-2 chapter 12
A93: CR-0089 | B93: Drop 1 | C93: BRD-02 | D93: ADJID.001 (p.89); ADJID.008 (p.92-93) | E93: FR-OP-050 to FR-OP-055 | F93: Behaviour differs from BRD | G93: Multiple accounts in one transaction; prompt the AO to prepare a quotation. | H93: One request per invoice; the wizard and the upload raise several requests at once. A hand-off to Marketing; the quotation number is linked on the request by reference. | I93: Analysis R6 4.1. | J93: Approvals are per invoice. | K93: Operations (Adjustment); Marketing | L93: 0 | M93: 0 | N93: 0 | O93: 0 | P93: =SUM(L93:O93) | Q93: =IF(P93=0,"0 - acceptance only",IF(P93<=3,"S",IF(P93<=10,"M",IF(P93<=25,"L","XL")))&" ("&P93&")") | S93: Low | T93: For acceptance | U93: Head of Operations (Financial Transactions and Processing) | V93: - | W93: FRS sign-off (Nov 2026) | X93: FRS BRD-2 chapter 12
A94: CR-0090 | B94: Drop 1 | C94: BRD-02 | D94: ADJID.003 (p.90) | E94: FR-OP-052 | F94: Behaviour differs from BRD | G94: Marketing updates the account through a non-financial endorsement. | H94: Booking records the non-financial endorsement with its description; the account data are not changed. | I94: OQ32 open (endorsement ownership). | J94: Account fields are corrected through the account workflow. | K94: Marketing; Operations | L94: 0 | M94: 0 | N94: 0 | O94: 0 | P94: =SUM(L94:O94) | Q94: =IF(P94=0,"0 - acceptance only",IF(P94<=3,"S",IF(P94<=10,"M",IF(P94<=25,"L","XL")))&" ("&P94&")") | R94: 8 | S94: Medium | T94: For acceptance | U94: Head of Operations (Financial Transactions and Processing) | V94: OQ32 | W94: FRS sign-off (Nov 2026) | X94: FRS BRD-2 chapter 12
A95: CR-0091 | B95: Drop 1 | C95: BRD-02 | D95: MKTID.012 (p.75-76) | E95: FR-OP (DP PR reversal) | F95: Behaviour differs from BRD | G95: Auto-reverse the DP premium receivable. | H95: The ledger reversal is always recorded; its GL entry is off because booking posts no PR for DP invoices. | I95: OQ07 (chart and default entries). | J95: No GL entry for a PR that was never posted. | K95: Operations (Commission); Comptrollership | L95: 0 | M95: 0 | N95: 0 | O95: 0 | P95: =SUM(L95:O95) | Q95: =IF(P95=0,"0 - acceptance only",IF(P95<=3,"S",IF(P95<=10,"M",IF(P95<=25,"L","XL")))&" ("&P95&")") | S95: Medium | T95: For acceptance | U95: Head of Operations (Financial Transactions and Processing) | V95: OQ07 | W95: FRS sign-off (Nov 2026) | X95: FRS BRD-2 chapter 12
A96: CR-0092 | B96: Drop 1 | C96: BRD-03 | D96: PMADD07, PMADD08 (p.5-6); DIS 3.29.1, 3.29.2 (Add. p.7-9); CMRID.005, 006 (p.108-109); BRCLXN.061-064 | E96: FR-PM-080; FR-OP-095; FR-DS (CPC2); FR-CL (incentives) | F96: BRD conflict resolved by decision | G96: Incentives are specified in four BRDs: criteria on the products matrix (BRD-3), CPC2 and early incentive (BRD-5), No Touch, Top Up and Motor Mania (BRD-2), incentive receivables (BRD-4 draft). | H96: Criteria kept once in Product Maintenance; CPC2 and early incentive computed in Remittance; schemes in Commission reference the criteria. Schemes stay inactive until BDOI gives targets, amounts and the CPC2 base and VAT treatment. | I96: DCR-037 proposal; OQ39, AQ24, PQ04, Q33 open. | J96: Incentive income not computed until the schemes are set up. | K96: MBS; Operations (Remittance, Commission); Comptrollership | L96: 2 | M96: 2 | N96: 3 | O96: 1 | P96: =SUM(L96:O96) | Q96: =IF(P96=0,"0 - acceptance only",IF(P96<=3,"S",IF(P96<=10,"M",IF(P96<=25,"L","XL")))&" ("&P96&")") | S96: High | T96: For CCB review | U96: Head, Marketing Business Services (MBS) with the TSU Head | V96: DCR-037; OQ39; AQ24; PQ04; Q33 | W96: After BDOI answer (slot set by the CCB) | X96: Register DCR-037; FRS BRD-2 chapter 12; FRS BRD-5 Vol.2 chapter 12
A97: CR-0093 | B97: Drop 1 | C97: BRD-02 | D97: BRQID.004 (p.18); CSHID.009; MKTID.010, 013; CMRID.001; DBMID.001 (p.46); RMTID.034; MKTID.009 (p.74) | E97: FR-OP-130 to FR-OP-132 | F97: BRD conflict resolved by decision | G97: Operations integrates with Collection, Accounting, Disbursement, Marketing and Claims as other systems. | H97: Collections, Disbursement, FRBS and Claims are BIBS modules; Operations uses in-app ports. The claims condition of a special remittance is confirmed through the Claims feed. | I97: DCR-022 answered by BRD-4, BRD-5 and BRD-7. | J97: No file interfaces between these functions. | K97: Operations; Collections; Comptrollership; Claims | L97: 0 | M97: 0 | N97: 0 | O97: 0 | P97: =SUM(L97:O97) | Q97: =IF(P97=0,"0 - acceptance only",IF(P97<=3,"S",IF(P97<=10,"M",IF(P97<=25,"L","XL")))&" ("&P97&")") | S97: Medium | T97: For acceptance | U97: Head of Operations (Financial Transactions and Processing) | V97: DCR-022; OQ01; OQ02; OQ45; OQ46 | W97: FRS sign-off (Nov 2026) | X97: FRS BRD-2 chapter 12; register DCR-022
A98: CR-0094 | B98: Drop 1 | C98: BRD-02 | D98: BRNB.067 (p.114-115), 068 (p.115), 076 (p.118), 081 (p.120), 094 (p.5-6), 114 (p.17); CSHID.008 (p.29-32); ADJID.001 (p.89), 003 (p.90), 011 (p.94) | E98: FR-NB-090, FR-NB-116; FR-OP-015; FR-OP-050 | F98: BRD conflict resolved by decision | G98: The same functions are specified in BRD-1 and BRD-2: CLPC payment matching, endorsements and cancellation, DP tagging. | H98: Cashiering is the single payment intake and placement reads its result; Adjustment owns endorsements and cancellations after booking; Marketing raises the request. | I98: Conflict between BRDs resolved by proposal. | J98: One place for each function. | K98: Marketing; Processing; Operations | L98: 0 | M98: 0 | N98: 0 | O98: 0 | P98: =SUM(L98:O98) | Q98: =IF(P98=0,"0 - acceptance only",IF(P98<=3,"S",IF(P98<=10,"M",IF(P98<=25,"L","XL")))&" ("&P98&")") | S98: High | T98: For acceptance | U98: Head of Operations (Financial Transactions and Processing) | V98: DCR-027 | W98: FRS sign-off (Nov 2026) | X98: Register DCR-027
A99: CR-0095 | B99: Drop 0 | C99: BRD-03 | D99: BRD revision log of 27-Oct-2025 (p.11); April 2026 addendum | E99: FRS BRD-3 section 1.2 (out of scope) | F99: Scope reduction / descoped | G99: Maintenance of non-package products. | H99: Out of this phase: the revision log moved it to an addendum and the April 2026 addendum does not add it. | I99: PQ19 open. | J99: Non-package products keep today's set-up in the catalog without the package request workflow. | K99: MBS; TSU | L99: 0 | M99: 0 | N99: 0 | O99: 1 | P99: =SUM(L99:O99) | Q99: =IF(P99=0,"0 - acceptance only",IF(P99<=3,"S",IF(P99<=10,"M",IF(P99<=25,"L","XL")))&" ("&P99&")") | R99: 15 | S99: Medium | T99: For CCB review | U99: Head, Marketing Business Services (MBS) with the TSU Head | V99: PQ19 | W99: FRS sign-off (Nov 2026) | X99: FRS BRD-3 section 1.2
A100: CR-0096 | B100: Drop 0 | C100: BRD-03 | D100: BRPM.022 (p.31) | E100: FR-PM-081; FR-CR-063 | F100: Integration dependency | G100: Product master changes synchronised with BDOI tracking systems and repositories. | H100: Each change of the product master is logged; transfer to other BDOI systems waits for PQ16. | I100: PQ16 open. | J100: Other systems do not receive product changes automatically. | K100: MBS; BDOI IT | L100: 1 | M100: 3 | N100: 2 | O100: 1 | P100: =SUM(L100:O100) | Q100: =IF(P100=0,"0 - acceptance only",IF(P100<=3,"S",IF(P100<=10,"M",IF(P100<=25,"L","XL")))&" ("&P100&")") | S100: Low | T100: Draft | U100: BDOI IT (integration owner) with the BIBS Product Owner | V100: PQ16 | W100: After BDOI answer (slot set by the CCB) | X100: FRS BRD-3 section 1.2 and interfaces
A101: CR-0097 | B101: Drop 0 | C101: BRD-03 | D101: PMADD07, PMADD08 (p.5-6) | E101: FR-PM-080 | F101: Scope reduction / descoped | G101: Incentive criteria on the products matrix, "i.e. CPC2". | H101: Criteria only; computation and payout of incentives are out of BRD-3 (they run in Remittance and Commission, CR-0092). | I101: Q33. | J101: None beyond CR-0092. | K101: MBS | L101: 0 | M101: 0 | N101: 0 | O101: 0 | P101: =SUM(L101:O101) | Q101: =IF(P101=0,"0 - acceptance only",IF(P101<=3,"S",IF(P101<=10,"M",IF(P101<=25,"L","XL")))&" ("&P101&")") | S101: Low | T101: For acceptance | U101: Head, Marketing Business Services (MBS) with the TSU Head | V101: Q33; DCR-037 | W101: FRS sign-off (Nov 2026) | X101: FRS BRD-3 section 1.2
A102: CR-0098 | B102: Drop 1 | C102: BRD-04 | D102: BRCLXN.013-015 (p.27 / p.47) | E102: FR-CL (daily refresh) | F102: Behaviour differs from BRD | G102: Daily batch extracts all data from EBIX after the 22:00 EOD. | H102: EBIX is replaced by BIBS booking: the job reads the BIBS invoice ledger at 22:15 and the balance of a listed account is also refreshed after each payment. | I102: EBIX replaced by BIBS. | J102: Collectors see balances updated during the day. | K102: Collections | L102: 0 | M102: 0 | N102: 0 | O102: 0 | P102: =SUM(L102:O102) | Q102: =IF(P102=0,"0 - acceptance only",IF(P102<=3,"S",IF(P102<=10,"M",IF(P102<=25,"L","XL")))&" ("&P102&")") | S102: Low | T102: For acceptance | U102: Head of BDOI Operations (Collections) | V102: CQ07 | W102: FRS sign-off (Nov 2026) | X102: FRS BRD-4 chapter 12
A103: CR-0099 | B103: Drop 1 | C103: BRD-04 | D103: BRCLXN.010 (p.27 / p.47); BRCLXN.011 (p.27) | E103: FR-CL (worklist rules) | F103: Behaviour differs from BRD | G103: Exclude negative balances of transaction type C; filter by Unit Head. | H103: Negatives of cancellations and return invoices are never listed; other negatives are kept on a Credit Balances tab. The Unit Head is the head of the invoice's sales unit, maintained on Collections Setup. | I103: CQ04, CQ05. | J103: Credit balances are visible for follow-up. | K103: Collections | L103: 0 | M103: 0 | N103: 0 | O103: 0 | P103: =SUM(L103:O103) | Q103: =IF(P103=0,"0 - acceptance only",IF(P103<=3,"S",IF(P103<=10,"M",IF(P103<=25,"L","XL")))&" ("&P103&")") | S103: Low | T103: For acceptance | U103: Head of BDOI Operations (Collections) | V103: CQ04; CQ05 | W103: FRS sign-off (Nov 2026) | X103: FRS BRD-4 chapter 12
A104: CR-0100 | B104: Drop 1 | C104: BRD-04 | D104: BRCLXN.012 (p.27 / p.47) | E104: FR-CL (data scope) | F104: Deferred pending BDOI answer | G104: Show only the accounts of the selected segment and Unit Head. | H104: Server-side filters; no default data scope per user: every CLX_VIEW user sees every account and filters. | I104: CQ06 open (CSF users see all accounts; other roles open). | J104: Collectors see accounts outside their segment. | K104: Collections; Compliance | L104: 1 | M104: 3 | N104: 2 | O104: 1 | P104: =SUM(L104:O104) | Q104: =IF(P104=0,"0 - acceptance only",IF(P104<=3,"S",IF(P104<=10,"M",IF(P104<=25,"L","XL")))&" ("&P104&")") | S104: Medium | T104: Draft | U104: Head of BDOI Operations (Collections) | V104: CQ06 | W104: After BDOI answer (slot set by the CCB) | X104: FRS BRD-4 chapter 12
A105: CR-0101 | B105: Drop 1 | C105: BRD-04 | D105: BRCLXN.024, 026 (p.28-29 / p.48); BRCLXN.030, 032 (p.29) | E105: FR-CL (hand-offs) | F105: Scope addition — beyond BRD | G105: A monthly batch "generates the file"; request application of payment. | H105: The file is also a hand-off: a DP PR disposition goes at once to the Commission DP list, a PR 2307 disposition to Cashiering's 2307 intake; the monthly file is the audit copy. Application requests go to Cashiering's Incoming Requests and the Operations disposition workflow. | I105: OQ15, OQ16, OQ38. | J105: Faster reversal and application. | K105: Collections; Operations | L105: 0 | M105: 0 | N105: 0 | O105: 0 | P105: =SUM(L105:O105) | Q105: =IF(P105=0,"0 - acceptance only",IF(P105<=3,"S",IF(P105<=10,"M",IF(P105<=25,"L","XL")))&" ("&P105&")") | S105: Low | T105: For acceptance | U105: Head of BDOI Operations (Collections) | V105: OQ15; OQ16; OQ38 | W105: FRS sign-off (Nov 2026) | X105: FRS BRD-4 chapter 12
A106: CR-0102 | B106: Drop 1 | C106: BRD-04 | D106: BRCLXN.026 (p.29 / p.48) | E106: FR-CL (COLLECTION_CWT2307 hand-off) | F106: Behaviour differs from BRD | G106: 2307 accounts reach Operations for reversal. | H106: Proposed: Cashiering takes the COLLECTION_CWT2307 hand-offs in its 2307 intake; a hand-off not taken within one day raises the alert CLX_OUTBOX_STALE. | I106: The BRD does not name the Cashiering step for the 2307 accounts. | J106: Double handling of 2307 accounts until closed. | K106: Collections; Operations (Cashiering) | L106: 1 | M106: 3 | N106: 2 | O106: 0 | P106: =SUM(L106:O106) | Q106: =IF(P106=0,"0 - acceptance only",IF(P106<=3,"S",IF(P106<=10,"M",IF(P106<=25,"L","XL")))&" ("&P106&")") | S106: Medium | T106: Draft | U106: Head of BDOI Operations (Collections) | V106: FRS BRD-4 CLR-CL-06 | W106: Drop 1, first release (Nov - Dec 2026) | X106: FRS BRD-4 chapter 12
A107: CR-0103 | B107: Drop 1 | C107: BRD-04 | D107: BRCLXN.036 (p.31 / p.49) | E107: FR-CL (account view columns) | F107: Deferred pending BDOI answer | G107: UH, AO and bank officer shown as names; booker name; Processing Stage, Business Origin, Client Code Match, System Remarks. | H107: User names shown for UH and AO; booker and bank officer names, Business Origin and System Remarks are not shown; "Processing Stage" is the Cashiering tab. | I107: CQ11 open. | J107: Collectors look up the missing fields on the account. | K107: Collections | L107: 1 | M107: 2 | N107: 1 | O107: 0 | P107: =SUM(L107:O107) | Q107: =IF(P107=0,"0 - acceptance only",IF(P107<=3,"S",IF(P107<=10,"M",IF(P107<=25,"L","XL")))&" ("&P107&")") | S107: Low | T107: Draft | U107: Head of BDOI Operations (Collections) | V107: CQ11 | W107: After BDOI answer (slot set by the CCB) | X107: FRS BRD-4 chapter 12
A108: CR-0104 | B108: Drop 2 | C108: BRD-04 | D108: BRCLXN.041-042 (p.32 / p.49); BRCLXN.047 (p.33) | E108: FR-CL (CLX-APPLICATION-TO-INVOICE) | F108: Integration dependency | G108: Text file loaded to FS04 before 06:00; EBIX invoice number format I########. | H108: The pipe-delimited file is written at 05:00 to the in-system folder FS04/CLX_APPLICATION_TO_INVOICE; the transport to FS04 is on hold. Invoice pattern accepts EBIX and BIBS numbers. | I108: OQ17, CQ12, CQ13; keep FS04 only if a downstream system reads it. | J108: Downstream readers of FS04 need the transport. | K108: Collections; BDOI IT | L108: 1 | M108: 2 | N108: 2 | O108: 0 | P108: =SUM(L108:O108) | Q108: =IF(P108=0,"0 - acceptance only",IF(P108<=3,"S",IF(P108<=10,"M",IF(P108<=25,"L","XL")))&" ("&P108&")") | S108: Low | T108: Draft | U108: BDOI IT (integration owner) with the BIBS Product Owner | V108: DCR-046; OQ17; CQ12; CQ13 | W108: Drop 2 (Mar - Apr 2027) | X108: FRS BRD-4 chapter 12; register DCR-046
A109: CR-0105 | B109: Drop 1 | C109: BRD-04 | D109: BRCLXN.051 (Add. p.5 / p.17) | E109: FR-CL (bulk update) | F109: Behaviour differs from BRD | G109: Bulk update of several invoices. | H109: The worklist updates several accounts with a disposition or effort and reassigns them; promises and escalations are recorded in bulk on their screens. The upload records promises and escalations only; its disposition, effort and remarks columns are refused. Proposed: accept those columns in the upload. | I109: FRS BRD-4 Gap G1. | J109: Dispositions are bulk-updated on screen, not by file. | K109: Collections | L109: 1 | M109: 3 | N109: 2 | O109: 1 | P109: =SUM(L109:O109) | Q109: =IF(P109=0,"0 - acceptance only",IF(P109<=3,"S",IF(P109<=10,"M",IF(P109<=25,"L","XL")))&" ("&P109&")") | S109: Low | T109: Draft | U109: Head of BDOI Operations (Collections) | V109: CLR-CR-01 (FRS BRD-4) | W109: Drop 1, second release (Jan - Feb 2027) | X109: FRS BRD-4 chapter 12
A110: CR-0106 | B110: Drop 1 | C110: BRD-04 | D110: BRCLXN.053 (Add. p.5-6); BRCLXN.055 (Add. p.6); BRCLXN.059 (Add. p.7-8) | E110: FR-CL (installments, promises, CR billing) | F110: Behaviour differs from BRD | G110: Installment schedule per account; broken promises per installment; CR billing needs Premium Receivable confirmation. | H110: Plans made in Collections (policy years, generated or manual); a promise is KEPT, PARTIALLY_KEPT or BROKEN by the payments in the promise window (grace 0 days); Commission bills a DP account after the CRU reviewer confirms it fully paid to the insurer. | I110: CQ15, CQ16, OQ38. | J110: Installment terms are not taken from the quotation. | K110: Collections; Operations (Commission) | L110: 0 | M110: 0 | N110: 0 | O110: 0 | P110: =SUM(L110:O110) | Q110: =IF(P110=0,"0 - acceptance only",IF(P110<=3,"S",IF(P110<=10,"M",IF(P110<=25,"L","XL")))&" ("&P110&")") | S110: Low | T110: For acceptance | U110: Head of BDOI Operations (Collections) | V110: CQ15; CQ16; OQ38 | W110: FRS sign-off (Nov 2026) | X110: FRS BRD-4 chapter 12
...

Sheet Summary
A1: Summary
A2: Counts and man-days by drop, BRD, deviation type, status and priority. Formulas read the Register sheet, so the figures follow any change to it.
A4: By drop
A5: Value | B5: Description | C5: CRs | D5: High | E5: Draft | F5: For CCB review | G5: For acceptance | H5: Analysis (md) | I5: Dev. (md) | J5: Test (md) | K5: Doc. (md) | L5: Total (md)
A6: Drop 0 | B6: Drop 0 - Setup and Data Migration | C6: =COUNTIFS(Register!$B$5:$B$682,"Drop 0") | D6: =COUNTIFS(Register!$B$5:$B$682,"Drop 0",Register!$S$5:$S$682,"High") | E6: =COUNTIFS(Register!$B$5:$B$682,"Drop 0",Register!$T$5:$T$682,"Draft") | F6: =COUNTIFS(Register!$B$5:$B$682,"Drop 0",Register!$T$5:$T$682,"For CCB review") | G6: =COUNTIFS(Register!$B$5:$B$682,"Drop 0",Register!$T$5:$T$682,"For acceptance") | H6: =SUMIFS(Register!$L$5:$L$682,Register!$B$5:$B$682,"Drop 0") | I6: =SUMIFS(Register!$M$5:$M$682,Register!$B$5:$B$682,"Drop 0") | J6: =SUMIFS(Register!$N$5:$N$682,Register!$B$5:$B$682,"Drop 0") | K6: =SUMIFS(Register!$O$5:$O$682,Register!$B$5:$B$682,"Drop 0") | L6: =SUMIFS(Register!$P$5:$P$682,Register!$B$5:$B$682,"Drop 0")
A7: Drop 1 | B7: Drop 1 - Transactional (upstream and downstream) | C7: =COUNTIFS(Register!$B$5:$B$682,"Drop 1") | D7: =COUNTIFS(Register!$B$5:$B$682,"Drop 1",Register!$S$5:$S$682,"High") | E7: =COUNTIFS(Register!$B$5:$B$682,"Drop 1",Register!$T$5:$T$682,"Draft") | F7: =COUNTIFS(Register!$B$5:$B$682,"Drop 1",Register!$T$5:$T$682,"For CCB review") | G7: =COUNTIFS(Register!$B$5:$B$682,"Drop 1",Register!$T$5:$T$682,"For acceptance") | H7: =SUMIFS(Register!$L$5:$L$682,Register!$B$5:$B$682,"Drop 1") | I7: =SUMIFS(Register!$M$5:$M$682,Register!$B$5:$B$682,"Drop 1") | J7: =SUMIFS(Register!$N$5:$N$682,Register!$B$5:$B$682,"Drop 1") | K7: =SUMIFS(Register!$O$5:$O$682,Register!$B$5:$B$682,"Drop 1") | L7: =SUMIFS(Register!$P$5:$P$682,Register!$B$5:$B$682,"Drop 1")
A8: Drop 2 | B8: Drop 2 - Independent | C8: =COUNTIFS(Register!$B$5:$B$682,"Drop 2") | D8: =COUNTIFS(Register!$B$5:$B$682,"Drop 2",Register!$S$5:$S$682,"High") | E8: =COUNTIFS(Register!$B$5:$B$682,"Drop 2",Register!$T$5:$T$682,"Draft") | F8: =COUNTIFS(Register!$B$5:$B$682,"Drop 2",Register!$T$5:$T$682,"For CCB review") | G8: =COUNTIFS(Register!$B$5:$B$682,"Drop 2",Register!$T$5:$T$682,"For acceptance") | H8: =SUMIFS(Register!$L$5:$L$682,Register!$B$5:$B$682,"Drop 2") | I8: =SUMIFS(Register!$M$5:$M$682,Register!$B$5:$B$682,"Drop 2") | J8: =SUMIFS(Register!$N$5:$N$682,Register!$B$5:$B$682,"Drop 2") | K8: =SUMIFS(Register!$O$5:$O$682,Register!$B$5:$B$682,"Drop 2") | L8: =SUMIFS(Register!$P$5:$P$682,Register!$B$5:$B$682,"Drop 2")
A9: Programme | B9: Programme (cross-drop) | C9: =COUNTIFS(Register!$B$5:$B$682,"Programme") | D9: =COUNTIFS(Register!$B$5:$B$682,"Programme",Register!$S$5:$S$682,"High") | E9: =COUNTIFS(Register!$B$5:$B$682,"Programme",Register!$T$5:$T$682,"Draft") | F9: =COUNTIFS(Register!$B$5:$B$682,"Programme",Register!$T$5:$T$682,"For CCB review") | G9: =COUNTIFS(Register!$B$5:$B$682,"Programme",Register!$T$5:$T$682,"For acceptance") | H9: =SUMIFS(Register!$L$5:$L$682,Register!$B$5:$B$682,"Programme") | I9: =SUMIFS(Register!$M$5:$M$682,Register!$B$5:$B$682,"Programme") | J9: =SUMIFS(Register!$N$5:$N$682,Register!$B$5:$B$682,"Programme") | K9: =SUMIFS(Register!$O$5:$O$682,Register!$B$5:$B$682,"Programme") | L9: =SUMIFS(Register!$P$5:$P$682,Register!$B$5:$B$682,"Programme")
A10: Phase 2 | B10: Reinsurance module (BDOI answer A3) | C10: =COUNTIFS(Register!$B$5:$B$682,"Phase 2") | D10: =COUNTIFS(Register!$B$5:$B$682,"Phase 2",Register!$S$5:$S$682,"High") | E10: =COUNTIFS(Register!$B$5:$B$682,"Phase 2",Register!$T$5:$T$682,"Draft") | F10: =COUNTIFS(Register!$B$5:$B$682,"Phase 2",Register!$T$5:$T$682,"For CCB review") | G10: =COUNTIFS(Register!$B$5:$B$682,"Phase 2",Register!$T$5:$T$682,"For acceptance") | H10: =SUMIFS(Register!$L$5:$L$682,Register!$B$5:$B$682,"Phase 2") | I10: =SUMIFS(Register!$M$5:$M$682,Register!$B$5:$B$682,"Phase 2") | J10: =SUMIFS(Register!$N$5:$N$682,Register!$B$5:$B$682,"Phase 2") | K10: =SUMIFS(Register!$O$5:$O$682,Register!$B$5:$B$682,"Phase 2") | L10: =SUMIFS(Register!$P$5:$P$682,Register!$B$5:$B$682,"Phase 2")
A11: Total | C11: =SUM(C6:C10) | D11: =SUM(D6:D10) | E11: =SUM(E6:E10) | F11: =SUM(F6:F10) | G11: =SUM(G6:G10) | H11: =SUM(H6:H10) | I11: =SUM(I6:I10) | J11: =SUM(J6:J10) | ... L11: =SUM(L6:L10)
A13: By BRD
A14: Value | B14: Description | C14: CRs | D14: High | E14: Draft | F14: For CCB review | G14: For acceptance | H14: Analysis (md) | I14: Dev. (md) | J14: Test (md) | K14: Doc. (md) | L14: Total (md)
A15: BRD-00 | B15: Core Replacement (umbrella) and programme | C15: =COUNTIFS(Register!$C$5:$C$682,"BRD-00") | D15: =COUNTIFS(Register!$C$5:$C$682,"BRD-00",Register!$S$5:$S$682,"High") | E15: =COUNTIFS(Register!$C$5:$C$682,"BRD-00",Register!$T$5:$T$682,"Draft") | F15: =COUNTIFS(Register!$C$5:$C$682,"BRD-00",Register!$T$5:$T$682,"For CCB review") | G15: =COUNTIFS(Register!$C$5:$C$682,"BRD-00",Register!$T$5:$T$682,"For acceptance") | H15: =SUMIFS(Register!$L$5:$L$682,Register!$C$5:$C$682,"BRD-00") | I15: =SUMIFS(Register!$M$5:$M$682,Register!$C$5:$C$682,"BRD-00") | J15: =SUMIFS(Register!$N$5:$N$682,Register!$C$5:$C$682,"BRD-00") | K15: =SUMIFS(Register!$O$5:$O$682,Register!$C$5:$C$682,"BRD-00") | L15: =SUMIFS(Register!$P$5:$P$682,Register!$C$5:$C$682,"BRD-00")
A16: BRD-01 | B16: New Business | C16: =COUNTIFS(Register!$C$5:$C$682,"BRD-01") | D16: =COUNTIFS(Register!$C$5:$C$682,"BRD-01",Register!$S$5:$S$682,"High") | E16: =COUNTIFS(Register!$C$5:$C$682,"BRD-01",Register!$T$5:$T$682,"Draft") | F16: =COUNTIFS(Register!$C$5:$C$682,"BRD-01",Register!$T$5:$T$682,"For CCB review") | G16: =COUNTIFS(Register!$C$5:$C$682,"BRD-01",Register!$T$5:$T$682,"For acceptance") | H16: =SUMIFS(Register!$L$5:$L$682,Register!$C$5:$C$682,"BRD-01") | I16: =SUMIFS(Register!$M$5:$M$682,Register!$C$5:$C$682,"BRD-01") | J16: =SUMIFS(Register!$N$5:$N$682,Register!$C$5:$C$682,"BRD-01") | K16: =SUMIFS(Register!$O$5:$O$682,Register!$C$5:$C$682,"BRD-01") | L16: =SUMIFS(Register!$P$5:$P$682,Register!$C$5:$C$682,"BRD-01")
A17: BRD-02 | B17: Operations | C17: =COUNTIFS(Register!$C$5:$C$682,"BRD-02") | D17: =COUNTIFS(Register!$C$5:$C$682,"BRD-02",Register!$S$5:$S$682,"High") | E17: =COUNTIFS(Register!$C$5:$C$682,"BRD-02",Register!$T$5:$T$682,"Draft") | F17: =COUNTIFS(Register!$C$5:$C$682,"BRD-02",Register!$T$5:$T$682,"For CCB review") | G17: =COUNTIFS(Register!$C$5:$C$682,"BRD-02",Register!$T$5:$T$682,"For acceptance") | H17: =SUMIFS(Register!$L$5:$L$682,Register!$C$5:$C$682,"BRD-02") | I17: =SUMIFS(Register!$M$5:$M$682,Register!$C$5:$C$682,"BRD-02") | J17: =SUMIFS(Register!$N$5:$N$682,Register!$C$5:$C$682,"BRD-02") | K17: =SUMIFS(Register!$O$5:$O$682,Register!$C$5:$C$682,"BRD-02") | L17: =SUMIFS(Register!$P$5:$P$682,Register!$C$5:$C$682,"BRD-02")
A18: BRD-03 | B18: Product Maintenance | C18: =COUNTIFS(Register!$C$5:$C$682,"BRD-03") | D18: =COUNTIFS(Register!$C$5:$C$682,"BRD-03",Register!$S$5:$S$682,"High") | E18: =COUNTIFS(Register!$C$5:$C$682,"BRD-03",Register!$T$5:$T$682,"Draft") | F18: =COUNTIFS(Register!$C$5:$C$682,"BRD-03",Register!$T$5:$T$682,"For CCB review") | G18: =COUNTIFS(Register!$C$5:$C$682,"BRD-03",Register!$T$5:$T$682,"For acceptance") | H18: =SUMIFS(Register!$L$5:$L$682,Register!$C$5:$C$682,"BRD-03") | I18: =SUMIFS(Register!$M$5:$M$682,Register!$C$5:$C$682,"BRD-03") | J18: =SUMIFS(Register!$N$5:$N$682,Register!$C$5:$C$682,"BRD-03") | K18: =SUMIFS(Register!$O$5:$O$682,Register!$C$5:$C$682,"BRD-03") | L18: =SUMIFS(Register!$P$5:$P$682,Register!$C$5:$C$682,"BRD-03")
A19: BRD-04 | B19: Collections | C19: =COUNTIFS(Register!$C$5:$C$682,"BRD-04") | D19: =COUNTIFS(Register!$C$5:$C$682,"BRD-04",Register!$S$5:$S$682,"High") | E19: =COUNTIFS(Register!$C$5:$C$682,"BRD-04",Register!$T$5:$T$682,"Draft") | F19: =COUNTIFS(Register!$C$5:$C$682,"BRD-04",Register!$T$5:$T$682,"For CCB review") | G19: =COUNTIFS(Register!$C$5:$C$682,"BRD-04",Register!$T$5:$T$682,"For acceptance") | H19: =SUMIFS(Register!$L$5:$L$682,Register!$C$5:$C$682,"BRD-04") | I19: =SUMIFS(Register!$M$5:$M$682,Register!$C$5:$C$682,"BRD-04") | J19: =SUMIFS(Register!$N$5:$N$682,Register!$C$5:$C$682,"BRD-04") | K19: =SUMIFS(Register!$O$5:$O$682,Register!$C$5:$C$682,"BRD-04") | L19: =SUMIFS(Register!$P$5:$P$682,Register!$C$5:$C$682,"BRD-04")
A20: BRD-05 | B20: Accounting, Disbursement and ACSL | C20: =COUNTIFS(Register!$C$5:$C$682,"BRD-05") | D20: =COUNTIFS(Register!$C$5:$C$682,"BRD-05",Register!$S$5:$S$682,"High") | E20: =COUNTIFS(Register!$C$5:$C$682,"BRD-05",Register!$T$5:$T$682,"Draft") | F20: =COUNTIFS(Register!$C$5:$C$682,"BRD-05",Register!$T$5:$T$682,"For CCB review") | G20: =COUNTIFS(Register!$C$5:$C$682,"BRD-05",Register!$T$5:$T$682,"For acceptance") | H20: =SUMIFS(Register!$L$5:$L$682,Register!$C$5:$C$682,"BRD-05") | I20: =SUMIFS(Register!$M$5:$M$682,Register!$C$5:$C$682,"BRD-05") | J20: =SUMIFS(Register!$N$5:$N$682,Register!$C$5:$C$682,"BRD-05") | K20: =SUMIFS(Register!$O$5:$O$682,Register!$C$5:$C$682,"BRD-05") | L20: =SUMIFS(Register!$P$5:$P$682,Register!$C$5:$C$682,"BRD-05")
A21: BRD-06 | B21: Renewal | C21: =COUNTIFS(Register!$C$5:$C$682,"BRD-06") | D21: =COUNTIFS(Register!$C$5:$C$682,"BRD-06",Register!$S$5:$S$682,"High") | E21: =COUNTIFS(Register!$C$5:$C$682,"BRD-06",Register!$T$5:$T$682,"Draft") | F21: =COUNTIFS(Register!$C$5:$C$682,"BRD-06",Register!$T$5:$T$682,"For CCB review") | G21: =COUNTIFS(Register!$C$5:$C$682,"BRD-06",Register!$T$5:$T$682,"For acceptance") | H21: =SUMIFS(Register!$L$5:$L$682,Register!$C$5:$C$682,"BRD-06") | I21: =SUMIFS(Register!$M$5:$M$682,Register!$C$5:$C$682,"BRD-06") | J21: =SUMIFS(Register!$N$5:$N$682,Register!$C$5:$C$682,"BRD-06") | K21: =SUMIFS(Register!$O$5:$O$682,Register!$C$5:$C$682,"BRD-06") | L21: =SUMIFS(Register!$P$5:$P$682,Register!$C$5:$C$682,"BRD-06")
A22: BRD-07 | B22: Claims | C22: =COUNTIFS(Register!$C$5:$C$682,"BRD-07") | D22: =COUNTIFS(Register!$C$5:$C$682,"BRD-07",Register!$S$5:$S$682,"High") | E22: =COUNTIFS(Register!$C$5:$C$682,"BRD-07",Register!$T$5:$T$682,"Draft") | F22: =COUNTIFS(Register!$C$5:$C$682,"BRD-07",Register!$T$5:$T$682,"For CCB review") | G22: =COUNTIFS(Register!$C$5:$C$682,"BRD-07",Register!$T$5:$T$682,"For acceptance") | H22: =SUMIFS(Register!$L$5:$L$682,Register!$C$5:$C$682,"BRD-07") | I22: =SUMIFS(Register!$M$5:$M$682,Register!$C$5:$C$682,"BRD-07") | J22: =SUMIFS(Register!$N$5:$N$682,Register!$C$5:$C$682,"BRD-07") | K22: =SUMIFS(Register!$O$5:$O$682,Register!$C$5:$C$682,"BRD-07") | L22: =SUMIFS(Register!$P$5:$P$682,Register!$C$5:$C$682,"BRD-07")
A23: BRD-08 | B23: Employee Benefits | C23: =COUNTIFS(Register!$C$5:$C$682,"BRD-08") | D23: =COUNTIFS(Register!$C$5:$C$682,"BRD-08",Register!$S$5:$S$682,"High") | E23: =COUNTIFS(Register!$C$5:$C$682,"BRD-08",Register!$T$5:$T$682,"Draft") | F23: =COUNTIFS(Register!$C$5:$C$682,"BRD-08",Register!$T$5:$T$682,"For CCB review") | G23: =COUNTIFS(Register!$C$5:$C$682,"BRD-08",Register!$T$5:$T$682,"For acceptance") | H23: =SUMIFS(Register!$L$5:$L$682,Register!$C$5:$C$682,"BRD-08") | I23: =SUMIFS(Register!$M$5:$M$682,Register!$C$5:$C$682,"BRD-08") | J23: =SUMIFS(Register!$N$5:$N$682,Register!$C$5:$C$682,"BRD-08") | K23: =SUMIFS(Register!$O$5:$O$682,Register!$C$5:$C$682,"BRD-08") | L23: =SUMIFS(Register!$P$5:$P$682,Register!$C$5:$C$682,"BRD-08")
A24: BRD-09 | B24: Customer Servicing Facility | C24: =COUNTIFS(Register!$C$5:$C$682,"BRD-09") | D24: =COUNTIFS(Register!$C$5:$C$682,"BRD-09",Register!$S$5:$S$682,"High") | E24: =COUNTIFS(Register!$C$5:$C$682,"BRD-09",Register!$T$5:$T$682,"Draft") | F24: =COUNTIFS(Register!$C$5:$C$682,"BRD-09",Register!$T$5:$T$682,"For CCB review") | G24: =COUNTIFS(Register!$C$5:$C$682,"BRD-09",Register!$T$5:$T$682,"For acceptance") | H24: =SUMIFS(Register!$L$5:$L$682,Register!$C$5:$C$682,"BRD-09") | I24: =SUMIFS(Register!$M$5:$M$682,Register!$C$5:$C$682,"BRD-09") | J24: =SUMIFS(Register!$N$5:$N$682,Register!$C$5:$C$682,"BRD-09") | K24: =SUMIFS(Register!$O$5:$O$682,Register!$C$5:$C$682,"BRD-09") | L24: =SUMIFS(Register!$P$5:$P$682,Register!$C$5:$C$682,"BRD-09")
A25: BRD-10 | B25: Sanction Screening | C25: =COUNTIFS(Register!$C$5:$C$682,"BRD-10") | D25: =COUNTIFS(Register!$C$5:$C$682,"BRD-10",Register!$S$5:$S$682,"High") | E25: =COUNTIFS(Register!$C$5:$C$682,"BRD-10",Register!$T$5:$T$682,"Draft") | F25: =COUNTIFS(Register!$C$5:$C$682,"BRD-10",Register!$T$5:$T$682,"For CCB review") | G25: =COUNTIFS(Register!$C$5:$C$682,"BRD-10",Register!$T$5:$T$682,"For acceptance") | H25: =SUMIFS(Register!$L$5:$L$682,Register!$C$5:$C$682,"BRD-10") | I25: =SUMIFS(Register!$M$5:$M$682,Register!$C$5:$C$682,"BRD-10") | J25: =SUMIFS(Register!$N$5:$N$682,Register!$C$5:$C$682,"BRD-10") | K25: =SUMIFS(Register!$O$5:$O$682,Register!$C$5:$C$682,"BRD-10") | L25: =SUMIFS(Register!$P$5:$P$682,Register!$C$5:$C$682,"BRD-10")
A26: BRD-11 | B26: User Access Maintenance | C26: =COUNTIFS(Register!$C$5:$C$682,"BRD-11") | D26: =COUNTIFS(Register!$C$5:$C$682,"BRD-11",Register!$S$5:$S$682,"High") | E26: =COUNTIFS(Register!$C$5:$C$682,"BRD-11",Register!$T$5:$T$682,"Draft") | F26: =COUNTIFS(Register!$C$5:$C$682,"BRD-11",Register!$T$5:$T$682,"For CCB review") | G26: =COUNTIFS(Register!$C$5:$C$682,"BRD-11",Register!$T$5:$T$682,"For acceptance") | H26: =SUMIFS(Register!$L$5:$L$682,Register!$C$5:$C$682,"BRD-11") | I26: =SUMIFS(Register!$M$5:$M$682,Register!$C$5:$C$682,"BRD-11") | J26: =SUMIFS(Register!$N$5:$N$682,Register!$C$5:$C$682,"BRD-11") | K26: =SUMIFS(Register!$O$5:$O$682,Register!$C$5:$C$682,"BRD-11") | L26: =SUMIFS(Register!$P$5:$P$682,Register!$C$5:$C$682,"BRD-11")
A27: BRD-12 | B27: Submitted Policies | C27: =COUNTIFS(Register!$C$5:$C$682,"BRD-12") | D27: =COUNTIFS(Register!$C$5:$C$682,"BRD-12",Register!$S$5:$S$682,"High") | E27: =COUNTIFS(Register!$C$5:$C$682,"BRD-12",Register!$T$5:$T$682,"Draft") | F27: =COUNTIFS(Register!$C$5:$C$682,"BRD-12",Register!$T$5:$T$682,"For CCB review") | G27: =COUNTIFS(Register!$C$5:$C$682,"BRD-12",Register!$T$5:$T$682,"For acceptance") | H27: =SUMIFS(Register!$L$5:$L$682,Register!$C$5:$C$682,"BRD-12") | I27: =SUMIFS(Register!$M$5:$M$682,Register!$C$5:$C$682,"BRD-12") | J27: =SUMIFS(Register!$N$5:$N$682,Register!$C$5:$C$682,"BRD-12") | K27: =SUMIFS(Register!$O$5:$O$682,Register!$C$5:$C$682,"BRD-12") | L27: =SUMIFS(Register!$P$5:$P$682,Register!$C$5:$C$682,"BRD-12")
A28: BRD-13 | B28: Data Migration | C28: =COUNTIFS(Register!$C$5:$C$682,"BRD-13") | D28: =COUNTIFS(Register!$C$5:$C$682,"BRD-13",Register!$S$5:$S$682,"High") | E28: =COUNTIFS(Register!$C$5:$C$682,"BRD-13",Register!$T$5:$T$682,"Draft") | F28: =COUNTIFS(Register!$C$5:$C$682,"BRD-13",Register!$T$5:$T$682,"For CCB review") | G28: =COUNTIFS(Register!$C$5:$C$682,"BRD-13",Register!$T$5:$T$682,"For acceptance") | H28: =SUMIFS(Register!$L$5:$L$682,Register!$C$5:$C$682,"BRD-13") | I28: =SUMIFS(Register!$M$5:$M$682,Register!$C$5:$C$682,"BRD-13") | J28: =SUMIFS(Register!$N$5:$N$682,Register!$C$5:$C$682,"BRD-13") | K28: =SUMIFS(Register!$O$5:$O$682,Register!$C$5:$C$682,"BRD-13") | L28: =SUMIFS(Register!$P$5:$P$682,Register!$C$5:$C$682,"BRD-13")
A29: Total | C29: =SUM(C15:C28) | D29: =SUM(D15:D28) | E29: =SUM(E15:E28) | F29: =SUM(F15:F28) | G29: =SUM(G15:G28) | H29: =SUM(H15:H28) | I29: =SUM(I15:I28) | J29: =SUM(J15:J28) | ... L29: =SUM(L15:L28)
A31: By deviation type
A32: Value | B32: Description | C32: CRs | D32: High | E32: Draft | F32: For CCB review | G32: For acceptance | H32: Analysis (md) | I32: Dev. (md) | J32: Test (md) | K32: Doc. (md) | L32: Total (md)
A33: Scope addition — beyond BRD | B33: BIBS does more than the BRD asks, or the umbrella FRS proposes a requirement that no function BRD owns | C33: =COUNTIFS(Register!$F$5:$F$682,"Scope addition — beyond BRD") | D33: =COUNTIFS(Register!$F$5:$F$682,"Scope addition — beyond BRD",Register!$S$5:$S$682,"High") | E33: =COUNTIFS(Register!$F$5:$F$682,"Scope addition — beyond BRD",Register!$T$5:$T$682,"Draft") | F33: =COUNTIFS(Register!$F$5:$F$682,"Scope addition — beyond BRD",Register!$T$5:$T$682,"For CCB review") | G33: =COUNTIFS(Register!$F$5:$F$682,"Scope addition — beyond BRD",Register!$T$5:$T$682,"For acceptance") | H33: =SUMIFS(Register!$L$5:$L$682,Register!$F$5:$F$682,"Scope addition — beyond BRD") | I33: =SUMIFS(Register!$M$5:$M$682,Register!$F$5:$F$682,"Scope addition — beyond BRD") | J33: =SUMIFS(Register!$N$5:$N$682,Register!$F$5:$F$682,"Scope addition — beyond BRD") | K33: =SUMIFS(Register!$O$5:$O$682,Register!$F$5:$F$682,"Scope addition — beyond BRD") | L33: =SUMIFS(Register!$P$5:$P$682,Register!$F$5:$F$682,"Scope addition — beyond BRD")
A34: Scope reduction / descoped | B34: A BRD requirement is not delivered, or is delivered with less than the BRD asks, by a BDOI instruction or a proposal | C34: =COUNTIFS(Register!$F$5:$F$682,"Scope reduction / descoped") | D34: =COUNTIFS(Register!$F$5:$F$682,"Scope reduction / descoped",Register!$S$5:$S$682,"High") | E34: =COUNTIFS(Register!$F$5:$F$682,"Scope reduction / descoped",Register!$T$5:$T$682,"Draft") | F34: =COUNTIFS(Register!$F$5:$F$682,"Scope reduction / descoped",Register!$T$5:$T$682,"For CCB review") | G34: =COUNTIFS(Register!$F$5:$F$682,"Scope reduction / descoped",Register!$T$5:$T$682,"For acceptance") | H34: =SUMIFS(Register!$L$5:$L$682,Register!$F$5:$F$682,"Scope reduction / descoped") | I34: =SUMIFS(Register!$M$5:$M$682,Register!$F$5:$F$682,"Scope reduction / descoped") | J34: =SUMIFS(Register!$N$5:$N$682,Register!$F$5:$F$682,"Scope reduction / descoped") | K34: =SUMIFS(Register!$O$5:$O$682,Register!$F$5:$F$682,"Scope reduction / descoped") | L34: =SUMIFS(Register!$P$5:$P$682,Register!$F$5:$F$682,"Scope reduction / descoped")
A35: Behaviour differs from BRD | B35: The requirement is met in a different way from the BRD text | C35: =COUNTIFS(Register!$F$5:$F$682,"Behaviour differs from BRD") | D35: =COUNTIFS(Register!$F$5:$F$682,"Behaviour differs from BRD",Register!$S$5:$S$682,"High") | E35: =COUNTIFS(Register!$F$5:$F$682,"Behaviour differs from BRD",Register!$T$5:$T$682,"Draft") | F35: =COUNTIFS(Register!$F$5:$F$682,"Behaviour differs from BRD",Register!$T$5:$T$682,"For CCB review") | G35: =COUNTIFS(Register!$F$5:$F$682,"Behaviour differs from BRD",Register!$T$5:$T$682,"For acceptance") | H35: =SUMIFS(Register!$L$5:$L$682,Register!$F$5:$F$682,"Behaviour differs from BRD") | I35: =SUMIFS(Register!$M$5:$M$682,Register!$F$5:$F$682,"Behaviour differs from BRD") | J35: =SUMIFS(Register!$N$5:$N$682,Register!$F$5:$F$682,"Behaviour differs from BRD") | K35: =SUMIFS(Register!$O$5:$O$682,Register!$F$5:$F$682,"Behaviour differs from BRD") | L35: =SUMIFS(Register!$P$5:$P$682,Register!$F$5:$F$682,"Behaviour differs from BRD")
A36: Deferred pending BDOI answer | B36: The element runs with a documented default and waits for a BDOI answer (values, layouts, rules, a yes / no on scope) | C36: =COUNTIFS(Register!$F$5:$F$682,"Deferred pending BDOI answer") | D36: =COUNTIFS(Register!$F$5:$F$682,"Deferred pending BDOI answer",Register!$S$5:$S$682,"High") | E36: =COUNTIFS(Register!$F$5:$F$682,"Deferred pending BDOI answer",Register!$T$5:$T$682,"Draft") | F36: =COUNTIFS(Register!$F$5:$F$682,"Deferred pending BDOI answer",Register!$T$5:$T$682,"For CCB review") | G36: =COUNTIFS(Register!$F$5:$F$682,"Deferred pending BDOI answer",Register!$T$5:$T$682,"For acceptance") | H36: =SUMIFS(Register!$L$5:$L$682,Register!$F$5:$F$682,"Deferred pending BDOI answer") | I36: =SUMIFS(Register!$M$5:$M$682,Register!$F$5:$F$682,"Deferred pending BDOI answer") | J36: =SUMIFS(Register!$N$5:$N$682,Register!$F$5:$F$682,"Deferred pending BDOI answer") | K36: =SUMIFS(Register!$O$5:$O$682,Register!$F$5:$F$682,"Deferred pending BDOI answer") | L36: =SUMIFS(Register!$P$5:$P$682,Register!$F$5:$F$682,"Deferred pending BDOI answer")
A37: Deferred to Phase 2 | B37: Out of phase 1 by BDOI decision; kept for phase 2 | C37: =COUNTIFS(Register!$F$5:$F$682,"Deferred to Phase 2") | D37: =COUNTIFS(Register!$F$5:$F$682,"Deferred to Phase 2",Register!$S$5:$S$682,"High") | E37: =COUNTIFS(Register!$F$5:$F$682,"Deferred to Phase 2",Register!$T$5:$T$682,"Draft") | F37: =COUNTIFS(Register!$F$5:$F$682,"Deferred to Phase 2",Register!$T$5:$T$682,"For CCB review") | G37: =COUNTIFS(Register!$F$5:$F$682,"Deferred to Phase 2",Register!$T$5:$T$682,"For acceptance") | H37: =SUMIFS(Register!$L$5:$L$682,Register!$F$5:$F$682,"Deferred to Phase 2") | I37: =SUMIFS(Register!$M$5:$M$682,Register!$F$5:$F$682,"Deferred to Phase 2") | J37: =SUMIFS(Register!$N$5:$N$682,Register!$F$5:$F$682,"Deferred to Phase 2") | K37: =SUMIFS(Register!$O$5:$O$682,Register!$F$5:$F$682,"Deferred to Phase 2") | L37: =SUMIFS(Register!$P$5:$P$682,Register!$F$5:$F$682,"Deferred to Phase 2")
A38: BRD conflict resolved by decision | B38: Two BRDs, or two parts of one BRD, conflict | C38: =COUNTIFS(Register!$F$5:$F$682,"BRD conflict resolved by decision") | D38: =COUNTIFS(Register!$F$5:$F$682,"BRD conflict resolved by decision",Register!$S$5:$S$682,"High") | E38: =COUNTIFS(Register!$F$5:$F$682,"BRD conflict resolved by decision",Register!$T$5:$T$682,"Draft") | F38: =COUNTIFS(Register!$F$5:$F$682,"BRD conflict resolved by decision",Register!$T$5:$T$682,"For CCB review") | G38: =COUNTIFS(Register!$F$5:$F$682,"BRD conflict resolved by decision",Register!$T$5:$T$682,"For acceptance") | H38: =SUMIFS(Register!$L$5:$L$682,Register!$F$5:$F$682,"BRD conflict resolved by decision") | I38: =SUMIFS(Register!$M$5:$M$682,Register!$F$5:$F$682,"BRD conflict resolved by decision") | J38: =SUMIFS(Register!$N$5:$N$682,Register!$F$5:$F$682,"BRD conflict resolved by decision") | K38: =SUMIFS(Register!$O$5:$O$682,Register!$F$5:$F$682,"BRD conflict resolved by decision") | L38: =SUMIFS(Register!$P$5:$P$682,Register!$F$5:$F$682,"BRD conflict resolved by decision")
A39: Integration dependency | B39: The requirement depends on an interface with a BDO or insurer system that is not yet specified | C39: =COUNTIFS(Register!$F$5:$F$682,"Integration dependency") | D39: =COUNTIFS(Register!$F$5:$F$682,"Integration dependency",Register!$S$5:$S$682,"High") | E39: =COUNTIFS(Register!$F$5:$F$682,"Integration dependency",Register!$T$5:$T$682,"Draft") | F39: =COUNTIFS(Register!$F$5:$F$682,"Integration dependency",Register!$T$5:$T$682,"For CCB review") | G39: =COUNTIFS(Register!$F$5:$F$682,"Integration dependency",Register!$T$5:$T$682,"For acceptance") | H39: =SUMIFS(Register!$L$5:$L$682,Register!$F$5:$F$682,"Integration dependency") | I39: =SUMIFS(Register!$M$5:$M$682,Register!$F$5:$F$682,"Integration dependency") | J39: =SUMIFS(Register!$N$5:$N$682,Register!$F$5:$F$682,"Integration dependency") | K39: =SUMIFS(Register!$O$5:$O$682,Register!$F$5:$F$682,"Integration dependency") | L39: =SUMIFS(Register!$P$5:$P$682,Register!$F$5:$F$682,"Integration dependency")
A40: NFR / infrastructure change | B40: A non-functional value (hours, availability, recovery, retention, sizing) or an infrastructure choice differs from one or more BRDs, or from the IER workbook | C40: =COUNTIFS(Register!$F$5:$F$682,"NFR / infrastructure change") | D40: =COUNTIFS(Register!$F$5:$F$682,"NFR / infrastructure change",Register!$S$5:$S$682,"High") | E40: =COUNTIFS(Register!$F$5:$F$682,"NFR / infrastructure change",Register!$T$5:$T$682,"Draft") | F40: =COUNTIFS(Register!$F$5:$F$682,"NFR / infrastructure change",Register!$T$5:$T$682,"For CCB review") | G40: =COUNTIFS(Register!$F$5:$F$682,"NFR / infrastructure change",Register!$T$5:$T$682,"For acceptance") | H40: =SUMIFS(Register!$L$5:$L$682,Register!$F$5:$F$682,"NFR / infrastructure change") | I40: =SUMIFS(Register!$M$5:$M$682,Register!$F$5:$F$682,"NFR / infrastructure change") | J40: =SUMIFS(Register!$N$5:$N$682,Register!$F$5:$F$682,"NFR / infrastructure change") | K40: =SUMIFS(Register!$O$5:$O$682,Register!$F$5:$F$682,"NFR / infrastructure change") | L40: =SUMIFS(Register!$P$5:$P$682,Register!$F$5:$F$682,"NFR / infrastructure change")
A41: Data migration | B41: The migration or cut-over treatment differs from what a BRD assumes, or adds work that a BRD does not state | C41: =COUNTIFS(Register!$F$5:$F$682,"Data migration") | D41: =COUNTIFS(Register!$F$5:$F$682,"Data migration",Register!$S$5:$S$682,"High") | E41: =COUNTIFS(Register!$F$5:$F$682,"Data migration",Register!$T$5:$T$682,"Draft") | F41: =COUNTIFS(Register!$F$5:$F$682,"Data migration",Register!$T$5:$T$682,"For CCB review") | G41: =COUNTIFS(Register!$F$5:$F$682,"Data migration",Register!$T$5:$T$682,"For acceptance") | H41: =SUMIFS(Register!$L$5:$L$682,Register!$F$5:$F$682,"Data migration") | I41: =SUMIFS(Register!$M$5:$M$682,Register!$F$5:$F$682,"Data migration") | J41: =SUMIFS(Register!$N$5:$N$682,Register!$F$5:$F$682,"Data migration") | K41: =SUMIFS(Register!$O$5:$O$682,Register!$F$5:$F$682,"Data migration") | L41: =SUMIFS(Register!$P$5:$P$682,Register!$F$5:$F$682,"Data migration")
A42: Total | C42: =SUM(C33:C41) | D42: =SUM(D33:D41) | E42: =SUM(E33:E41) | F42: =SUM(F33:F41) | G42: =SUM(G33:G41) | H42: =SUM(H33:H41) | I42: =SUM(I33:I41) | J42: =SUM(J33:J41) | ... L42: =SUM(L33:L41)
A44: By CR status
A45: Value | B45: Description | C45: CRs | D45: High | E45: Draft | F45: For CCB review | G45: For acceptance | H45: Analysis (md) | I45: Dev. (md) | J45: Test (md) | K45: Doc. (md) | L45: Total (md)
A46: Draft | B46: Raised by the project team | C46: =COUNTIFS(Register!$T$5:$T$682,"Draft") | D46: =COUNTIFS(Register!$T$5:$T$682,"Draft",Register!$S$5:$S$682,"High") | E46: =COUNTIFS(Register!$T$5:$T$682,"Draft",Register!$T$5:$T$682,"Draft") | F46: =COUNTIFS(Register!$T$5:$T$682,"Draft",Register!$T$5:$T$682,"For CCB review") | G46: =COUNTIFS(Register!$T$5:$T$682,"Draft",Register!$T$5:$T$682,"For acceptance") | H46: =SUMIFS(Register!$L$5:$L$682,Register!$T$5:$T$682,"Draft") | I46: =SUMIFS(Register!$M$5:$M$682,Register!$T$5:$T$682,"Draft") | J46: =SUMIFS(Register!$N$5:$N$682,Register!$T$5:$T$682,"Draft") | K46: =SUMIFS(Register!$O$5:$O$682,Register!$T$5:$T$682,"Draft") | L46: =SUMIFS(Register!$P$5:$P$682,Register!$T$5:$T$682,"Draft")
A47: For CCB review | B47: Impact analysis complete; ready for the Change Control Board to approve, reject or defer | C47: =COUNTIFS(Register!$T$5:$T$682,"For CCB review") | D47: =COUNTIFS(Register!$T$5:$T$682,"For CCB review",Register!$S$5:$S$682,"High") | E47: =COUNTIFS(Register!$T$5:$T$682,"For CCB review",Register!$T$5:$T$682,"Draft") | F47: =COUNTIFS(Register!$T$5:$T$682,"For CCB review",Register!$T$5:$T$682,"For CCB review") | G47: =COUNTIFS(Register!$T$5:$T$682,"For CCB review",Register!$T$5:$T$682,"For acceptance") | H47: =SUMIFS(Register!$L$5:$L$682,Register!$T$5:$T$682,"For CCB review") | I47: =SUMIFS(Register!$M$5:$M$682,Register!$T$5:$T$682,"For CCB review") | J47: =SUMIFS(Register!$N$5:$N$682,Register!$T$5:$T$682,"For CCB review") | K47: =SUMIFS(Register!$O$5:$O$682,Register!$T$5:$T$682,"For CCB review") | L47: =SUMIFS(Register!$P$5:$P$682,Register!$T$5:$T$682,"For CCB review")
A48: Approved | B48: Approved by the CCB; scheduled into a drop or release | C48: =COUNTIFS(Register!$T$5:$T$682,"Approved") | D48: =COUNTIFS(Register!$T$5:$T$682,"Approved",Register!$S$5:$S$682,"High") | E48: =COUNTIFS(Register!$T$5:$T$682,"Approved",Register!$T$5:$T$682,"Draft") | F48: =COUNTIFS(Register!$T$5:$T$682,"Approved",Register!$T$5:$T$682,"For CCB review") | G48: =COUNTIFS(Register!$T$5:$T$682,"Approved",Register!$T$5:$T$682,"For acceptance") | H48: =SUMIFS(Register!$L$5:$L$682,Register!$T$5:$T$682,"Approved") | I48: =SUMIFS(Register!$M$5:$M$682,Register!$T$5:$T$682,"Approved") | J48: =SUMIFS(Register!$N$5:$N$682,Register!$T$5:$T$682,"Approved") | K48: =SUMIFS(Register!$O$5:$O$682,Register!$T$5:$T$682,"Approved") | L48: =SUMIFS(Register!$P$5:$P$682,Register!$T$5:$T$682,"Approved")
A49: Rejected | B49: Rejected by the CCB; the BRD text stands, or the item is closed without change | C49: =COUNTIFS(Register!$T$5:$T$682,"Rejected") | D49: =COUNTIFS(Register!$T$5:$T$682,"Rejected",Register!$S$5:$S$682,"High") | E49: =COUNTIFS(Register!$T$5:$T$682,"Rejected",Register!$T$5:$T$682,"Draft") | F49: =COUNTIFS(Register!$T$5:$T$682,"Rejected",Register!$T$5:$T$682,"For CCB review") | G49: =COUNTIFS(Register!$T$5:$T$682,"Rejected",Register!$T$5:$T$682,"For acceptance") | H49: =SUMIFS(Register!$L$5:$L$682,Register!$T$5:$T$682,"Rejected") | I49: =SUMIFS(Register!$M$5:$M$682,Register!$T$5:$T$682,"Rejected") | J49: =SUMIFS(Register!$N$5:$N$682,Register!$T$5:$T$682,"Rejected") | K49: =SUMIFS(Register!$O$5:$O$682,Register!$T$5:$T$682,"Rejected") | L49: =SUMIFS(Register!$P$5:$P$682,Register!$T$5:$T$682,"Rejected")
A50: For acceptance | B50: The proposed behaviour is decided and documented and differs from the BRD text; the CCB records the acceptance | C50: =COUNTIFS(Register!$T$5:$T$682,"For acceptance") | D50: =COUNTIFS(Register!$T$5:$T$682,"For acceptance",Register!$S$5:$S$682,"High") | E50: =COUNTIFS(Register!$T$5:$T$682,"For acceptance",Register!$T$5:$T$682,"Draft") | F50: =COUNTIFS(Register!$T$5:$T$682,"For acceptance",Register!$T$5:$T$682,"For CCB review") | G50: =COUNTIFS(Register!$T$5:$T$682,"For acceptance",Register!$T$5:$T$682,"For acceptance") | H50: =SUMIFS(Register!$L$5:$L$682,Register!$T$5:$T$682,"For acceptance") | I50: =SUMIFS(Register!$M$5:$M$682,Register!$T$5:$T$682,"For acceptance") | J50: =SUMIFS(Register!$N$5:$N$682,Register!$T$5:$T$682,"For acceptance") | K50: =SUMIFS(Register!$O$5:$O$682,Register!$T$5:$T$682,"For acceptance") | L50: =SUMIFS(Register!$P$5:$P$682,Register!$T$5:$T$682,"For acceptance")
A51: Total | C51: =SUM(C46:C50) | D51: =SUM(D46:D50) | E51: =SUM(E46:E50) | F51: =SUM(F46:F50) | G51: =SUM(G46:G50) | H51: =SUM(H46:H50) | I51: =SUM(I46:I50) | J51: =SUM(J46:J50) | ... L51: =SUM(L46:L50)
A53: By priority
A54: Value | B54: Description | C54: CRs | D54: High | E54: Draft | F54: For CCB review | G54: For acceptance | H54: Analysis (md) | I54: Dev. (md) | J54: Test (md) | K54: Doc. (md) | L54: Total (md)
A55: High | B55: Affects money (premium, commission, GL, remittance), regulatory compliance, security or access, or blocks a drop | C55: =COUNTIFS(Register!$S$5:$S$682,"High") | D55: =COUNTIFS(Register!$S$5:$S$682,"High",Register!$S$5:$S$682,"High") | E55: =COUNTIFS(Register!$S$5:$S$682,"High",Register!$T$5:$T$682,"Draft") | F55: =COUNTIFS(Register!$S$5:$S$682,"High",Register!$T$5:$T$682,"For CCB review") | G55: =COUNTIFS(Register!$S$5:$S$682,"High",Register!$T$5:$T$682,"For acceptance") | H55: =SUMIFS(Register!$L$5:$L$682,Register!$S$5:$S$682,"High") | I55: =SUMIFS(Register!$M$5:$M$682,Register!$S$5:$S$682,"High") | J55: =SUMIFS(Register!$N$5:$N$682,Register!$S$5:$S$682,"High") | K55: =SUMIFS(Register!$O$5:$O$682,Register!$S$5:$S$682,"High") | L55: =SUMIFS(Register!$P$5:$P$682,Register!$S$5:$S$682,"High")
A56: Medium | B56: Changes a rule, screen, report or interface; a documented default runs until BDOI decides | C56: =COUNTIFS(Register!$S$5:$S$682,"Medium") | D56: =COUNTIFS(Register!$S$5:$S$682,"Medium",Register!$S$5:$S$682,"High") | E56: =COUNTIFS(Register!$S$5:$S$682,"Medium",Register!$T$5:$T$682,"Draft") | F56: =COUNTIFS(Register!$S$5:$S$682,"Medium",Register!$T$5:$T$682,"For CCB review") | G56: =COUNTIFS(Register!$S$5:$S$682,"Medium",Register!$T$5:$T$682,"For acceptance") | H56: =SUMIFS(Register!$L$5:$L$682,Register!$S$5:$S$682,"Medium") | I56: =SUMIFS(Register!$M$5:$M$682,Register!$S$5:$S$682,"Medium") | J56: =SUMIFS(Register!$N$5:$N$682,Register!$S$5:$S$682,"Medium") | K56: =SUMIFS(Register!$O$5:$O$682,Register!$S$5:$S$682,"Medium") | L56: =SUMIFS(Register!$P$5:$P$682,Register!$S$5:$S$682,"Medium")
A57: Low | B57: Wording, labels or presentation; no effect on money, control or data | C57: =COUNTIFS(Register!$S$5:$S$682,"Low") | D57: =COUNTIFS(Register!$S$5:$S$682,"Low",Register!$S$5:$S$682,"High") | E57: =COUNTIFS(Register!$S$5:$S$682,"Low",Register!$T$5:$T$682,"Draft") | F57: =COUNTIFS(Register!$S$5:$S$682,"Low",Register!$T$5:$T$682,"For CCB review") | G57: =COUNTIFS(Register!$S$5:$S$682,"Low",Register!$T$5:$T$682,"For acceptance") | H57: =SUMIFS(Register!$L$5:$L$682,Register!$S$5:$S$682,"Low") | I57: =SUMIFS(Register!$M$5:$M$682,Register!$S$5:$S$682,"Low") | J57: =SUMIFS(Register!$N$5:$N$682,Register!$S$5:$S$682,"Low") | K57: =SUMIFS(Register!$O$5:$O$682,Register!$S$5:$S$682,"Low") | L57: =SUMIFS(Register!$P$5:$P$682,Register!$S$5:$S$682,"Low")
A58: Total | C58: =SUM(C55:C57) | D58: =SUM(D55:D57) | E58: =SUM(E55:E57) | F58: =SUM(F55:F57) | G58: =SUM(G55:G57) | H58: =SUM(H55:H57) | I58: =SUM(I55:I57) | J58: =SUM(J55:J57) | ... L58: =SUM(L55:L57)

Sheet Effort basis
A1: Effort basis
A2: How the man-days are estimated: team roles, the man-day, what is included and excluded, and the size classes.
A4: Assumptions
A5: 1 | B5: A man-day is 8 working hours of one team member. Figures are rounded to whole days.
A6: 2 | B6: Effort is the work still needed to close the deviation as proposed in the "Proposed behaviour" column. It is 0 when the behaviour is decided and documented and only needs acceptance.
A7: 3 | B7: For an item deferred pending a BDOI answer, the effort is the work to complete it once BDOI answers as proposed (interface, values, layouts, screens). A different answer is re-estimated at impact analysis.
A8: 4 | B8: The optional column "BRD as written" gives the indicative effort to deliver the BRD text instead of the proposed behaviour, for the CCB to compare.
A9: 5 | B9: Development includes configuration. Test covers SIT test cases (writing and running) and regression. Documentation covers the FRS, test plan and guides.
A10: 6 | B10: Excluded: UAT support, BDOI staff time, infrastructure provisioning by BDO IT (buckets, keys, network routes, certificates), licences and third-party services, and the Phase 2 Reinsurance module.
A11: 7 | B11: Excluded: the delivery of what the FRS specify (BRD-6, BRD-8, BRD-9, BRD-12, BRD-13, BRD-7). Only the delta caused by the deviation is estimated.
A12: 8 | B12: Estimates are at the accuracy of an impact analysis (about plus or minus 30 percent). The CCB re-estimates an item when BDOI's answer differs from the proposal.
A13: 9 | B13: Status and counts are as of the date on the cover and are refreshed with each issue of the register.
A15: Team roles
B16: Role | C16: Work counted in the estimate
B17: Business analyst | C17: Analysis: impact analysis, BDOI workshops, rules and layouts, FRS and test plan updates (with the technical writer)
B18: Solution architect | C18: Analysis of interfaces, data and infrastructure items
B19: Backend developer | C19: Development: services, data changes, jobs, interfaces, reports
B20: Frontend developer | C20: Development: screens, forms and lists
B21: QA engineer | C21: Test: SIT test cases written and run, regression
B22: Technical writer | C22: Documentation: FRS, test plan, user and configuration guides, release notes
A24: Size classes
B25: Class | C25: Man-days | D25: CRs
B26: 0 | C26: Acceptance only | D26: =COUNTIFS(Register!$P$5:$P$682,0)
B27: S | C27: 1 to 3 | D27: =COUNTIFS(Register!$P$5:$P$682,">=1",Register!$P$5:$P$682,"<=3")
B28: M | C28: 4 to 10 | D28: =COUNTIFS(Register!$P$5:$P$682,">=4",Register!$P$5:$P$682,"<=10")
B29: L | C29: 11 to 25 | D29: =COUNTIFS(Register!$P$5:$P$682,">=11",Register!$P$5:$P$682,"<=25")
B30: XL | C30: more than 25 | D30: =COUNTIFS(Register!$P$5:$P$682,">=26",Register!$P$5:$P$682,"<=9999")
A32: Man-days by activity (all CRs)
B33: Activity | C33: Meaning | D33: Man-days
B34: Analysis | C34: Impact analysis, workshops, rules and layouts | D34: =SUM(Register!$L$5:$L$682)
B35: Development | C35: Development and configuration | D35: =SUM(Register!$M$5:$M$682)
B36: Test | C36: SIT cases written and run, regression | D36: =SUM(Register!$N$5:$N$682)
B37: Documentation | C37: FRS, test plan, guides | D37: =SUM(Register!$O$5:$O$682)
B38: Total | D38: =SUM(Register!$P$5:$P$682)

Sheet Change control
A1: Change control
A2: Change-control process for deviations and new change requests, with the roles and the proposed Change Control Board (CCB).
A4: Process: request, impact analysis, CCB, approval, schedule, implement, verify, close
A5: Step | B5: What happens | C5: Who | D5: Output | E5: Time
A6: 1. Request | B6: Anyone in BDOI or the project team raises a change request on the CR form, or the project team raises a CR from a recorded deviation (FRS clarifications, register, alignment pack). | C6: Requester; Project Manager (iorta TechNXT) logs it | D6: CR row in this register, status Draft | E6: Same day
A7: 2. Impact analysis | B7: The business analyst and solution architect assess scope, BRD and FRS references, affected modules, data, interfaces, tests, documents and drop; estimate effort in man-days (Analysis, Development, Test, Documentation). | C7: Business analyst, Solution architect; BDOI owner of the BRD for business impact | D7: Impact analysis on the CR form; status For CCB review | E7: 5 working days (10 for L / XL)
A8: 3. CCB review | B8: The Change Control Board reviews the CR at its fortnightly meeting (or ad hoc for High priority items): accept, reject, defer, or ask for more analysis. | C8: Change Control Board | D8: Minutes with the decision per CR | E8: Fortnightly
A9: 4. Approval | B9: Approved CRs are signed on the CR form by the BDOI decision owner and the BIBS Product Owner. A CR above 25 man-days, or one that moves a drop date, also needs the Program Manager. | C9: Decision owner; BIBS Product Owner; Program Manager (L / XL, date change) | D9: Status Approved or Rejected; signed CR form | E9: Within 5 working days of the CCB
A10: 5. Schedule | B10: The Project Manager places the CR in a drop or release and updates the plan, the FRS change list and the test plan scope. | C10: Project Manager (iorta TechNXT); BDOI Program Manager | D10: Target drop / release set; plan updated | E10: Next planning cycle
A11: 6. Implement | B11: The team delivers and documents the change: configuration, FRS revision, test cases, user and configuration guides. | C11: Delivery team | D11: Delivered change, FRS revision, test cases | E11: As scheduled
A12: 7. Verify | B12: QA runs the SIT cases and regression; the BDOI owner checks the behaviour in SIT or UAT against the CR. | C12: QA engineer; BDOI owner of the BRD | D12: Test evidence; acceptance by the owner | E12: Within the drop SIT / UAT window
A13: 8. Close | B13: The Project Manager records the result, the FRS version that carries it and the closing date; the CR is reported in the release notes. | C13: Project Manager; BIBS Product Owner | D13: Status Implemented; release note entry | E13: At release
A15: Change Control Board (proposed membership)
B16: Member | C16: Organisation | D16: Role on the board
B17: BIBS Product Owner | C17: BDOI | D17: Chair; casting vote on scope and priority
B18: Program Manager, Business Project Services | C18: BDO Unibank ESG | D18: Plan, drops and budget; approves L / XL items and date changes
B19: Owner of the BRD concerned (department head or product owner) | C19: BDOI | D19: Decision owner of the CR; attends for the CRs of the BRD
B20: Head, Comptrollership | C20: BDOI | D20: Member for any CR that touches posting, GL, tax or BIR reports
B21: Chief Compliance Officer (or delegate) | C21: BDOI | D21: Member for any CR that touches screening, KYC, access control or retention
B22: BDOI IT (integration owner) | C22: BDOI | D22: Member for interfaces and infrastructure items
B23: Project Manager | C23: iorta TechNXT | D23: Secretary: agenda, register, minutes, schedule
B24: Solution Architect | C24: iorta TechNXT | D24: Presents impact analysis and effort
B25: Business Analyst lead | C25: iorta TechNXT | D25: Presents BRD / FRS references and test impact
A27: Rules of the board
A28: • | B28: Quorum: the chair (or a named delegate), the Program Manager and the decision owner of each CR on the agenda.
A29: • | B29: The CCB meets every two weeks from October 2026 to go-live, and ad hoc for High priority items that block a drop.
A30: • | B30: A CR above 25 man-days, or one that moves a drop or the go-live date, needs the Program Manager's approval.
A31: • | B31: Approved CRs reach the FRS only through an FRS revision that cites the CR ID; the FRS baseline is not changed by this register.
A32: • | B32: Rejected CRs keep their row with the reason; the BRD text stands.

Sheet CR form
A1: CR form
A2: Change request form: one per CR; the Project Manager files the signed form with the register.
A4: Request
A5: CR ID | B5: CR-nnnn, given by the Project Manager when the CR is logged
A6: Title | B6: Short name of the change
A7: Requested by / date | B7: Name, department, date
A8: BRD and requirement ID(s), page | B8: For example BRNB.071 (p.116)
A9: FRS FR ID(s) | B9: For example FR-NB-081
A10: Drop | B10: Drop 0 / Drop 1 / Drop 2 / Programme / Phase 2
A11: Deviation type | B11: One of the nine types (How to read)
A12: What the BRD asks | B12: Quote or summarise the BRD text
A13: Change requested or proposed behaviour | B13: What BIBS does or should do instead
A14: Reason | B14: BDOI decision, question reference or technical constraint
A16: Impact analysis
A17: Business impact | B17: Effect on the process, money, control and customers
A18: Affected departments and modules | B18: BDOI departments; BIBS modules and screens
A19: Interfaces and data | B19: Systems, files, migration objects affected
A20: Documents affected | B20: FRS, design, test plan, guides, register
A21: Effort (man-days) | B21: Analysis / Development / Test / Documentation / Total; size S, M, L, XL
A22: Effect on the plan | B22: Drop, release, dependency on other CRs
A23: Priority | B23: High / Medium / Low
A25: Decision
A26: CCB decision and date | B26: Approved / Rejected / Deferred, with the meeting date
A27: Conditions | B27: Any condition set by the CCB
A28: Decision owner (BDOI) | B28: Name and signature
A29: BIBS Product Owner | B29: Name and signature
A30: Program Manager (L / XL or date change) | B30: Name and signature
A32: Implementation
A33: Target drop / release | B33: Drop or release
A34: FRS version carrying the change | B34: For example FRS BRD-1 v1.2
A35: Verified by / date | B35: QA and BDOI owner
A36: Closed on | B36: Date

Sheet _lists
A1: Drop 0 | B1: BRD-00 | C1: Scope addition — beyond BRD | D1: High | E1: Draft | F1: FRS sign-off (Nov 2026)
A2: Drop 1 | B2: BRD-01 | C2: Scope reduction / descoped | D2: Medium | E2: For CCB review | F2: Drop 1, first release (Nov - Dec 2026)
A3: Drop 2 | B3: BRD-02 | C3: Behaviour differs from BRD | D3: Low | E3: Approved | F3: Drop 1, second release (Jan - Feb 2027)
A4: Programme | B4: BRD-03 | C4: Deferred pending BDOI answer | E4: Rejected | F4: Migration functions (Nov 2026 - Mar 2027)
A5: Phase 2 | B5: BRD-04 | C5: Deferred to Phase 2 | E5: For acceptance | F5: Infrastructure before SIT (by Jan 2027)
B6: BRD-05 | C6: BRD conflict resolved by decision | F6: Drop 2 (Mar - Apr 2027)
B7: BRD-06 | C7: Integration dependency | F7: Before go-live (Oct - Dec 2027)
B8: BRD-07 | C8: NFR / infrastructure change | F8: Phase 2
B9: BRD-08 | C9: Data migration | F9: After BDOI answer (slot set by the CCB)
B10: BRD-09
B11: BRD-10
B12: BRD-11
B13: BRD-12
B14: BRD-13
