Workbook
Name cur_ex: #REF!
Name curex: #REF!
Name ESHardwareDiscount: #REF!
Name ESHardwareDiscount: #REF!
Name ESSoftwareDiscount: #REF!
Name ESSoftwareDiscount: #REF!
Name OnPremDiscount: #REF!
Name OnPremDiscount: #REF!
Name sw_inflation: #REF!

Sheet Document Control
B1: Information Technology Cloud & Digital Operations Engineering | D1: Infrastructure Estimation and Recommendation Workbook | G1: Doc. Ref. No.: | H1: FR-ITC-ENG007
G2: Effective Date: | H2: 44643
G3: Ver. and Rev. No.: | H3: 5
B7: Document Version History
B8: Ver. and Rev. No. | C8: Date | D8: Prepared By | E8: Reviewed By | F8: Approved By | G8: Description
B9: 1 | C9: 43648 | D9: Edlin Resurreccion | E9: Ronna May Dimapilis | F9: Joel Eric Tesoro | G9: Initial Creation
B10: 2 | C10: 43901 | D10: Josephus Carl Gallo | E10: Ronna May Dimapilis | F10: Joel Eric Tesoro | G10: - Updated General Assumptions list with common assumptions, and added "Suggestions to minimize cost" section - General assumptions for Dollar-to-Php, Cost Buffer, and TCO % increase per year conversion has been linked to Summary page - Modified Licenses and One-Time Cost computations from US Dollars to Philippine Peso (PhP) - Modified Environment sheets by adding Monthly EBS Snapshot costs for all environments - Removed 5-year TCO in Environment sheets, adjusted currency fields to 2 decimal digits - Modified Summary page with the costing buffer and TCO values for easier estimations - Modified the Additional Cost % on Summay Page and Grand Total visuals only
B11: 2.1 | C11: 43921 | D11: Ryan Kerwin Macrohon | E11: Ronna May Dimapilis | F11: Joel Eric Tesoro | G11: Added note in HW & SW Requirements regarding technical refresh
B12: 2.2 | C12: 43937 | D12: Ronna May Dimapilis | E12: Ryan Kerwin Macrohon | F12: Joel Eric Tesoro | G12: - Color coded tabs and cells to be filled out by requesting unit (green) and servicing unit (blue) - Updated utilization to 36% in all non-productions environments based on the assumption 12x5 availability per month - Removed Instance Count column - Updated reference to the new AWS calculator - Updated document ownership to Engineering - Renamed from Cost Estimation Workbook to Infrastructure Estimation and Recommendation Workbook - Other formatting updates
B13: 3 | C13: 44046 | D13: Hanna Raissa Sarmiento Ronna May Dimapilis | E13: Ryan Kerwin Macrohon | F13: Joel Eric Tesoro | G13: - Added RTO, RPO requirements, expected % YoY growth, tabs for IT Infrastructure outputs (Architecture Diagram, HW&SW Specifications) - Updated computation for growth rate - Added dropdown for cost buffer
B14: 4 | C14: 44228 | D14: Ronna May Dimapilis | E14: Joel Eric Tesoro | F14: Joel Eric Tesoro | G14: - Added VDI-related requirements, specifications, and costing - Renamed Licenses and One-Time Cost to Software Licenses - Updated variables, computations, and Summary tab
B15: 5 | C15: 44643 | D15: Gian Carlo Adivncula | E15: Ryan Kerwin Macrohon / Augustus Anthony Lim | F15: Augustus Anthony Lim | G15: - Added IER Change Log to keep track of cost changes - Added Max Concurrent Users field in VDI Requirements tab
B16: 6 | C16: 44860 | D16: Joseph Bartolome | E16: Ryan Kerwin Macrohon / Augustus Anthony Lim | F16: Augustus Anthony Lim | G16: Modified formula for IER Change Log sheet to reference the previous change instead of the 1st year total cost
B17: 7 | C17: 44902 | D17: Joseph Bartolome | E17: Ryan Kerwin Macrohon / Augustus Anthony Lim | F17: Augustus Anthony Lim | G17: - Modified utilization from percentage to number of hours - Added Prod Support to VDI User drop down menu
B18: 8 | C18: 44993 | D18: Joy Coronado | E18: Augustus Anthony Lim | F18: Augustus Anthony Lim | G18: - Modified utilization to hours - Automatic compute of number of hours
B19: 9 | C19: 45051 | D19: Alan Villanobles II | E19: Catherine Joy Coronado | F19: Augustus Anthony Lim | G19: - Modified context in the Assumption to automatically get the dollar conversion rate from the Summary worksheet. - Updated drop-down list in the VDI Requirements worksheet to include "Prod Support" to the 2nd and 3rd tables. - added "Estimated Duration of Use" on each profile in the "VDI Requirements" and "HW & SW Requirements" worksheets - added "Prod Support" description to align with the profile added on v7
B20: 10 | C20: 45294 | D20: Benbol Del Pilar | E20: Rhett Lee Martinez | F20: Augustus Anthony Lim | G20: - Modified the cost for VDI - Add additional pre-prod environment
... B32: 19 | C32: 46176 | D32: Catherine Joy Coronado | E32: Rhett Lee Martinez | F32: Augustus Anthony Lim | G32: 1. Update the following: a. K8s Min/Max column b. K8s Ephemeral Storage c. K8s Kube-System and additional pods for autoscaling d. K8s PDB column e. Horizontal Scaling (separating sheets for k8s yearly increase) 2. Added Assumptions and notes for EKS/AKS form applicability

Sheet Assumptions
A1: GENERAL ASSUMPTIONS
A2: No. | B2: Assumption
A3: 1 | B3: Costing found in this workbook represents only the infrastructure costing for the given project. This should not be mistaken to represent costing for the entire project.
A4: 2 | B4: Costing found in this workbook represents the infrastructure costing only for the project components that are declared in this workbook. Any additional components not initially declared may have an impact on costing.
A5: 3 | B5: The Non-Production instances (DEV, SIT, UAT, Pre-Prod) are going to run for 12 hours a day, 5 days a week (12 x 5).
A6: 4 | B6: The Production instances are going to run for 24 hours a day, 7 days a week (24 x 7).
A7: 5 | B7: Snapshot costs are included for all environments (10% change for monthly snapshots).
A8: 6 | B8: VAT is only applicable to our Public Cloud components
A9: 7 | B9: Enterprise discount for Azure component is already part of the monthly cost in their calculator. For AWS the enterprise discount is 10.5%
A10: 8 | B10: Micrsoft Licenses has a minimum of 4 Licenses
A11: 9 | B11: Use K8S sheets to identify container technology requirements. Remove Kube-system namespace if the hosting environment will be on AKS and add the system pool worker nodes group instead
A12: 10 | B12: =CONCATENATE("USD to PHP exchange rate is 1 USD : ", SUMMARY!C22, " Philippine Pesos. This is based on the prevailing exchange rate on the week of this workbook's review and approval.") -> USD to PHP exchange rate is 1 USD : 60 Philippine Pesos. This is based on the prevailing exchange rate on the week of this workbook's review and approval.
A13: 11
A14: 12
A15: 13
A16: 14
A17: 15
A18: 16
A19: 17
A20: 18
A21: 19
A22: 20
A23: 21
A24: No. | B24: Suggestions to minimize cost
A25: 1
A26: 2
A27: 3
A28: 4
A29: 5
A30: 6
A31: 7
A32: 8

Sheet IER Change Log
E2: Initial Cost Estimate / Technical Recommendation Summary
F3: 1st-yr TCO (manual input) | G3: 5-yr TCO (manual input)
F4: 0 | G4: 0
A7: Cost Estimate / Technical Recommendation - Revision History (fill-out as necessary)
A8: Change # | B8: High Level Description of Change | C8: Details/Rationale for the change | D8: Change Driver | E8: Date of Change (MM/DD/YYYY) | F8: Cost Impact 1st yr TCO (manual input) | G8: Cost Impact 5-yr TCO (manual input) | H8: Calculated Compared to Initial 1st yr (auto-fill) | I8: Calculated Compared to Initial 5-yr (auto-fill) | J8: Calculated Compared to Previous Change 1st yr (auto-fill) | K8: Calculated Compared to Previous Change 5-yr (auto-fill)
A9: 1 | F9: 0 | G9: 0 | H9: =IF(F9=0,"₱0",F9-$F$4) -> ₱0 | I9: =IF(G9=0,"₱0",G9-$G$4) -> ₱0 | J9: N/A | K9: N/A
A10: 2 | F10: 0 | G10: 0 | H10: =IF(F10=0,"₱0",F10-$F$4) -> ₱0 | I10: =IF(G10=0,"₱0",G10-$G$4) -> ₱0 | J10: =IF(F10=0,"₱0",F10-$F9) -> ₱0 | K10: =IF(G10=0,"₱0",G10-$G9) -> ₱0
A11: 3 | F11: 0 | G11: 0 | H11: =IF(F11=0,"₱0",F11-$F$4) -> ₱0 | I11: =IF(G11=0,"₱0",G11-$G$4) -> ₱0 | J11: =IF(F11=0,"₱0",F11-$F10) -> ₱0 | K11: =IF(G11=0,"₱0",G11-$G10) -> ₱0
A12: 4 | F12: 0 | G12: 0 | H12: =IF(F12=0,"₱0",F12-$F$4) -> ₱0 | I12: =IF(G12=0,"₱0",G12-$G$4) -> ₱0 | J12: =IF(F12=0,"₱0",F12-$F11) -> ₱0 | K12: =IF(G12=0,"₱0",G12-$G11) -> ₱0
A13: 5 | F13: 0 | G13: 0 | H13: =IF(F13=0,"₱0",F13-$F$4) -> ₱0 | I13: =IF(G13=0,"₱0",G13-$G$4) -> ₱0 | J13: =IF(F13=0,"₱0",F13-$F12) -> ₱0 | K13: =IF(G13=0,"₱0",G13-$G12) -> ₱0
A14: 6 | F14: 0 | G14: 0 | H14: =IF(F14=0,"₱0",F14-$F$4) -> ₱0 | I14: =IF(G14=0,"₱0",G14-$G$4) -> ₱0 | J14: =IF(F14=0,"₱0",F14-$F13) -> ₱0 | K14: =IF(G14=0,"₱0",G14-$G13) -> ₱0
A15: 7 | F15: 0 | G15: 0 | H15: =IF(F15=0,"₱0",F15-$F$4) -> ₱0 | I15: =IF(G15=0,"₱0",G15-$G$4) -> ₱0 | J15: =IF(F15=0,"₱0",F15-$F14) -> ₱0 | K15: =IF(G15=0,"₱0",G15-$G14) -> ₱0
A16: 8 | F16: 0 | G16: 0 | H16: =IF(F16=0,"₱0",F16-$F$4) -> ₱0 | I16: =IF(G16=0,"₱0",G16-$G$4) -> ₱0 | J16: =IF(F16=0,"₱0",F16-$F15) -> ₱0 | K16: =IF(G16=0,"₱0",G16-$G15) -> ₱0
A17: 9 | F17: 0 | G17: 0 | H17: =IF(F17=0,"₱0",F17-$F$4) -> ₱0 | I17: =IF(G17=0,"₱0",G17-$G$4) -> ₱0 | J17: =IF(F17=0,"₱0",F17-$F16) -> ₱0 | K17: =IF(G17=0,"₱0",G17-$G16) -> ₱0
A18: 10 | F18: 0 | G18: 0 | H18: =IF(F18=0,"₱0",F18-$F$4) -> ₱0 | I18: =IF(G18=0,"₱0",G18-$G$4) -> ₱0 | J18: =IF(F18=0,"₱0",F18-$F17) -> ₱0 | K18: =IF(G18=0,"₱0",G18-$G17) -> ₱0

Sheet Architecture Diagram
A2: iNXT BrokerVerse — High-Level Architecture (BDOI Core Modernization)
A4: Recovery Point Objective | B4: 15 minutes | C4: may be in seconds, minutes, hours, days | G4: Recovery Time Objective | H4: 4 hours | I4: may be in seconds, minutes, hours, days
A5: Place high-level architecture diagram below:

Sheet HW & SW Requirements
A1: Hardware and Software Requirements (to be filled out by requesting unit)
A2: Kindly fill in the necessary details below with the requested specs for each environment as discussed and recommended by the vendor or solution developer.
A3: Expected % YoY Growth | B3: 15 | D3: Estimated Duration of Use | E3: 60 | F3: months
A5: Environment | B5: Description | C5: CPU | D5: Memory (GB) | E5: Storage (GB) | F5: Operating System and Software Requirement | G5: Remarks
A6: DEV | B6: Application Database (PostgreSQL) | C6: 4 | D6: 16 | E6: 200 | F6: RHEL 9.x + PostgreSQL 16 (Amazon RDS, Single-AZ) | G6: Primary OLTP DB for iNXT BrokerVerse
A7: DEV | B7: Cache & Event Streaming (Redis + Kafka) | C7: 4 | D7: 16 | E7: 200 | F7: Amazon ElastiCache for Redis 7.x + Amazon MSK (Apache Kafka 3.6) | G7: Session/cache + async eventing
A8: SIT | B8: Application Database (PostgreSQL) | C8: 4 | D8: 16 | E8: 200 | F8: RHEL 9.x + PostgreSQL 16 (Amazon RDS, Single-AZ) | G8: Integration test OLTP DB
A9: SIT | B9: Cache & Event Streaming (Redis + Kafka) | C9: 4 | D9: 16 | E9: 200 | F9: Amazon ElastiCache for Redis 7.x + Amazon MSK (Kafka 3.6) | G9: Cache + eventing
A10: UAT | B10: Application Database (PostgreSQL) | C10: 8 | D10: 32 | E10: 500 | F10: RHEL 9.x + PostgreSQL 16 (Amazon RDS, Single-AZ) | G10: UAT OLTP DB, prod-like data volume
A11: UAT | B11: Cache & Event Streaming (Redis + Kafka) | C11: 4 | D11: 16 | E11: 300 | F11: Amazon ElastiCache for Redis 7.x + Amazon MSK (Kafka 3.6) | G11: Cache + eventing
A12: PRE-PROD | B12: Application Database (PostgreSQL) | C12: 8 | D12: 64 | E12: 1000 | F12: RHEL 9.x + PostgreSQL 16 (Amazon RDS, Multi-AZ) | G12: Prod-mirror DB for performance & cutover rehearsal
A13: PRE-PROD | B13: Cache & Event Streaming (Redis + Kafka) | C13: 8 | D13: 32 | E13: 1000 | F13: ElastiCache for Redis 7.x (cluster) + Amazon MSK (3 brokers) | G13: Cache + eventing
A14: PROD | B14: Application Database (PostgreSQL) | C14: 16 | D14: 128 | E14: 2000 | F14: RHEL 9.x + PostgreSQL 16 (Amazon RDS, Multi-AZ) | G14: Primary OLTP, HA Multi-AZ, automated backups
A15: PROD | B15: Cache & Event Streaming (Redis + Kafka) | C15: 8 | D15: 32 | E15: 1000 | F15: ElastiCache for Redis 7.x (cluster) + Amazon MSK (3 brokers) | G15: Cache + durable eventing
A16: PROD | B16: Bastion / CI-CD Runner | C16: 4 | D16: 16 | E16: 200 | F16: RHEL 9.x + GitLab Runner, AWS SSM, kubectl/helm | G16: Shared deploy & jump host
A17: PROD DR | B17: Application Database (PostgreSQL standby) | C17: 16 | D17: 128 | E17: 2000 | F17: RHEL 9.x + PostgreSQL 16 (cross-region read replica) | G17: DR standby, async replication, RPO target ≤15 min
A18: PROD DR | B18: Cache & Event Streaming (Redis + Kafka) | C18: 8 | D18: 32 | E18: 1000 | F18: ElastiCache for Redis 7.x + Amazon MSK (3 brokers) | G18: DR cache + eventing
A19: PROD | B19: Object & File Storage | F19: Amazon S3 (document store) + Amazon EFS (shared K8s PV) | G19: Managed, consumption-based; lifecycle to S3-IA/Glacier

Sheet VDI Requirements
A1: VDI Requirements (to be filled out by requesting unit)
G3: Total Number of VDI Users | H3: =SUM(B7,B33,B59) -> 15
J5: User Profiles
A6: User Profile | B6: Developer | J6: Basic User : no runtime requirements; only requires productivity tools such
A7: =CONCATENATE("No. of ", $B$6, "s") -> No. of Developers | B7: 8 | J7: as office tools and access to documents, applications/sytems
A8: =CONCATENATE("Max Concurrent No. of ", $B$6, "s") -> Max Concurrent No. of Developers | B8: 6
A9: Estimated Duration of Use | B9: 24 | C9: months | J9: Developer : has runtime requirements; requires developer tools and
A10: Uptime Schedule | B10: 12 | C10: hours | D10: Multi-Session Aware : software/application allows multiple concurrent interactive sessions | J10: productivity tools and access to environments
B11: 5 | C11: days | D11: Information is required as it impacts specification and cost. | J11: Tester : has runtime requirements; requires QA and productivity tools
A12: Total Hours | B12: =((B10*B11*4)/(24*7*4))*730 -> 260.71429 | J12: and access to environments.
A13: Software Name indicate (1) standard software not included in the default list* and (2) other required software/tools | B13: Software Version | C13: Description | D13: Purpose | E13: Multi-Session Aware? (Y/N) | F13: Memory Requirement (GB) if known | G13: Storage Requirement (GB) if known | H13: Remarks | J13: Prod Support : may need runtime requirements and access to production environment (User Role/Profile only) (needs a separate request and approval for accessing the prod system/environment)
A14: Visual Studio Code | B14: 1.9x | C14: Primary IDE | D14: development | E14: N | F14: 2 | G14: 5 | H14: Angular/Java microservice dev
A15: OpenJDK (Temurin) | B15: 17 LTS | C15: Java SDK & runtime | D15: development | E15: N | F15: 1 | G15: 2 | H15: BrokerVerse services build on JDK 17
A16: Node.js + npm | B16: 20 LTS | C16: Front-end build toolchain | D16: development | E16: N | F16: 1 | G16: 3 | H16: Angular SPA build | J16: *List of Standard Software Installed by default
A17: Git client | B17: 2.4x | C17: Source control | D17: development | E17: N | F17: 1 | G17: 1 | H17: Connects to GitLab | J17: Software | K17: Version
A18: DBeaver | B18: 24.x | C18: PostgreSQL DB client | D18: development | E18: N | F18: 1 | G18: 1 | J18: Libre Office tools | K18: 5.4.5
A19: Postman | B19: 11.x | C19: API testing | D19: development | E19: N | F19: 1 | G19: 1 | J19: OpenOffice | K19: 4.1.6
A20: Docker CLI / kubectl / Helm | B20: latest | C20: Container & K8s tooling | D20: development | E20: N | F20: 1 | G20: 2 | H20: EKS deploy from runner | J20: WinSCP | K20: 5.17
J21: 7-Zip | K21: 19
J22: Putty | K22: 0.73
J23: Notepad++ | K23: 7.8.6
J24: Microsoft Edge / Firefox | K24: 83.0 / 68.8.0esr
J25: Adobe Acrobat Reader | K25: 2017 17.011.30113
J26: For the complete list, please refer to:
J27: https://www.ito.bdo.com.ph/references/memoranda/bdo-system-image
F29: =SUM(F14:F28) -> 8 | G29: =SUM(G14:G28) -> 15 | J29: List of Standard Software that can be requested for installation
J30: http://fs01.software.bdo.com.ph/workstation/free-software-and-tools/ITD%20Tools/
A32: User Profile | B32: Tester
A33: =CONCATENATE("No. of ", $B$32, "s") -> No. of Testers | B33: 4
A34: =CONCATENATE("Max Concurrent No. of ", $B$32, "s") -> Max Concurrent No. of Testers | B34: 3
A35: Estimated Duration of Use | B35: 18 | C35: months
A36: Uptime Schedule | B36: 12 | C36: hours | D36: Multi-Session Aware : software/application allows multiple concurrent interactive sessions
B37: 5 | C37: days | D37: Information is required as it impacts specification and cost.
A38: Total Hours | B38: =((B36*B37*4)/(24*7*4))*730 -> 260.71429
A39: Software Name indicate (1) standard software not included in the default list* and (2) other required software/tools | B39: Software Version | C39: Description | D39: Purpose | E39: Multi-Session Aware? (Y/N) | F39: Memory Requirement (GB) if known | G39: Storage Requirement (GB) if known | H39: Remarks
A40: Katalon Studio / Selenium | B40: latest | C40: UI test automation | D40: testing | E40: N | F40: 2 | G40: 4 | H40: Regression automation
A41: Apache JMeter | B41: 5.6 | C41: Performance & load testing | D41: testing | E41: N | F41: 2 | G41: 2 | H41: NFR/TPS validation
A42: Postman / Newman | B42: 11.x | C42: API test execution | D42: testing | E42: N | F42: 1 | G42: 1
A43: DBeaver | B43: 24.x | C43: Test data validation | D43: testing | E43: N | F43: 1 | G43: 1
A44: Xray / TestRail (browser) | B44: SaaS | C44: Test management | D44: testing | E44: N | F44: 1 | G44: 1 | H44: Web client
F55: =SUM(F40:F54) -> 7 | G55: =SUM(G40:G54) -> 9
A58: User Profile | B58: Prod Support
A59: =CONCATENATE("No. of ", $B$58, "s") -> No. of Prod Supports | B59: 3
A60: =CONCATENATE("Max Concurrent No. of ", $B$58, "s") -> Max Concurrent No. of Prod Supports | B60: 2
A61: Estimated Duration of Use | B61: 60 | C61: months
A62: Uptime Schedule | B62: 12 | C62: hours | D62: Multi-Session Aware : software/application allows multiple concurrent interactive sessions
B63: 5 | C63: days | D63: Information is required as it impacts specification and cost.
A64: Total Hours | B64: =((B62*B63*4)/(24*7*4))*730 -> 260.71429
A65: Software Name indicate (1) standard software not included in the default list* and (2) other required software/tools | B65: Software Version | C65: Description | D65: Purpose | E65: Multi-Session Aware? (Y/N) | F65: Memory Requirement (GB) if known | G65: Storage Requirement (GB) if known | H65: Remarks
A66: DBeaver (read-only) | B66: 24.x | C66: Prod DB diagnostics | D66: part of system design | E66: N | F66: 1 | G66: 1 | H66: Least-privilege role
A67: Dynatrace (browser) | B67: SaaS | C67: APM / observability | D67: part of system design | E67: N | F67: 1 | G67: 1 | H67: Web client
A68: Lens / kubectl (read-only) | B68: latest | C68: K8s diagnostics | D68: part of system design | E68: N | F68: 1 | G68: 2 | H68: EKS read access
A69: WinSCP / PuTTY | B69: std | C69: Secure console & file transfer | D69: part of system design | E69: N | F69: 1 | G69: 1
F81: =SUM(F66:F80) -> 4 | G81: =SUM(G66:G80) -> 5

Sheet Architecture Diagram (Infra)
A2: High-Level Architecture ( to be filled out by servicing unit)
A4: Recovery Point Objective | C4: 15 min | G4: Recovery Time Objective | I4: 4 h
A5: Place recommended high-level architecture diagram below:
A142: DB1
A146: DB2
A290: DB1
A294: DB2

Sheet HW & SW Specifications (Infra)
A1: Hardware and Software Specifications (to be filled out by servicing unit)
B2: Estimated Duration of Use | C2: =IF(ISBLANK('HW & SW Requirements'!E3),"",'HW & SW Requirements'!E3) -> 60 | D2: months
A3: Environment | B3: Description | C3: CPU | D3: Memory (GB) | E3: Storage (GB) | F3: Operating System and Software Requirement | G3: Remarks

Sheet VDI Specifications (Infra)
A1: VDI Specifications (to be filled out by servicing unit)
A3: Description | B3: Estimated Duration of Use (months) | C3: Hours | D3: CPU | E3: Memory (GB) | F3: Storage (GB) | G3: Monthly Subscription Cost ($) | H3: Monthly Storage Cost ($) | I3: Total Monthly Cost (VAT Inc $) | J3: Total Annual Cost ($)
A4: =CONCATENATE('VDI Requirements'!$B$6, " VM(s)") -> Developer VM(s)
B5: ='VDI Requirements'!B9 -> 24 | C5: ='VDI Requirements'!B12 -> 260.71429 | F5: Managed disks (128GB) Profile (30GB) | H5: 0 | I5: =SUM(G5:H5) * 1.12 -> 0 | J5: =I5*12 -> 0
C6: ='VDI Requirements'!B12 -> 260.71429 | F6: Managed disks (128GB) Profile (30GB) | I6: =SUM(G6:H6) * 1.12 -> 0 | J6: =I6*12 -> 0
C7: ='VDI Requirements'!B12 -> 260.71429 | F7: Managed disks (128GB) Profile (30GB) | I7: =SUM(G7:H7) * 1.12 -> 0 | J7: =I7*12 -> 0
A8: =CONCATENATE('VDI Requirements'!$B$32, " VM(s)") -> Tester VM(s)
B9: ='VDI Requirements'!B35 -> 18 | C9: ='VDI Requirements'!B38 -> 260.71429 | F9: Managed disks (128GB) Profile (30GB) | I9: =SUM(G9:H9) * 1.12 -> 0 | J9: =I9*12 -> 0
C10: ='VDI Requirements'!B38 -> 260.71429 | F10: Managed disks (128GB) Profile (30GB) | I10: =SUM(G10:H10) * 1.12 -> 0 | J10: =I10*12 -> 0
C11: ='VDI Requirements'!B38 -> 260.71429 | F11: Managed disks (128GB) Profile (30GB) | I11: =SUM(G11:H11) * 1.12 -> 0 | J11: =I11*12 -> 0
A12: =CONCATENATE('VDI Requirements'!$B$58, " VM(s)") -> Prod Support VM(s)
B13: ='VDI Requirements'!B61 -> 60 | C13: ='VDI Requirements'!B64 -> 260.71429 | F13: Managed disks (128GB) Profile (30GB) | I13: =SUM(G13:H13) * 1.12 -> 0 | J13: =I13*12 -> 0
C14: ='VDI Requirements'!B64 -> 260.71429 | F14: Managed disks (128GB) Profile (30GB) | I14: =SUM(G14:H14) * 1.12 -> 0 | J14: =I14*12 -> 0
C15: ='VDI Requirements'!B64 -> 260.71429 | F15: Managed disks (128GB) Profile (30GB) | I15: =SUM(G15:H15) * 1.12 -> 0 | J15: =I15*12 -> 0
A16: TOTAL | I16: =SUM(I5:I15) -> 0 | J16: =SUM(J5:J15) -> 0

Sheet Software Licenses
A1: SOFTWARE / LICENSE COST
A2: Environment | B2: Software/License Name and Version | C2: No. of Cores/CPU/vCPU | D2: License Unit Cost | E2: No. of License Needed | F2: Amount | G2: Recurring Cost
G3: Year 1 | H3: Year 2 | I3: Year 3 | J3: Year 4 | K3: Year 5 | L3: Total
F4: =ROUNDUP(E4*D4,0) -> 0 | G4: =F4 -> 0 | H4: =G4 -> 0 | I4: =H4 -> 0 | J4: =I4 -> 0 | K4: =J4 -> 0 | L4: =SUM(G4:K4) -> 0
F5: =ROUNDUP(E5*D5,0) -> 0 | G5: =F5 -> 0 | H5: =G5 -> 0 | I5: =H5 -> 0 | J5: =I5 -> 0 | K5: =J5 -> 0 | L5: =SUM(G5:K5) -> 0
F6: =ROUNDUP(E6*D6,0) -> 0 | G6: =F6 -> 0 | H6: =G6 -> 0 | I6: =H6 -> 0 | J6: =I6 -> 0 | K6: =J6 -> 0 | L6: =SUM(G6:K6) -> 0
F7: =ROUNDUP(E7*D7,0) -> 0 | G7: =F7 -> 0 | H7: =G7 -> 0 | I7: =H7 -> 0 | J7: =I7 -> 0 | K7: =J7 -> 0 | L7: =SUM(G7:K7) -> 0
F8: =ROUNDUP(E8*D8,0) -> 0 | G8: =F8 -> 0 | H8: =G8 -> 0 | I8: =H8 -> 0 | J8: =I8 -> 0 | K8: =J8 -> 0 | L8: =SUM(G8:K8) -> 0
F9: =ROUNDUP(E9*D9,0) -> 0 | G9: =F9 -> 0 | H9: =G9 -> 0 | I9: =H9 -> 0 | J9: =I9 -> 0 | K9: =J9 -> 0 | L9: =SUM(G9:K9) -> 0
F10: =ROUNDUP(E10*D10,0) -> 0 | G10: =F10 -> 0 | H10: =G10 -> 0 | I10: =H10 -> 0 | J10: =I10 -> 0 | K10: =J10 -> 0 | L10: =SUM(G10:K10) -> 0
F11: =ROUNDUP(E11*D11,0) -> 0 | G11: =F11 -> 0 | H11: =G11 -> 0 | I11: =H11 -> 0 | J11: =I11 -> 0 | K11: =J11 -> 0 | L11: =SUM(G11:K11) -> 0
F12: =ROUNDUP(E12*D12,0) -> 0 | G12: =F12 -> 0 | H12: =G12 -> 0 | I12: =H12 -> 0 | J12: =I12 -> 0 | K12: =J12 -> 0 | L12: =SUM(G12:K12) -> 0
F13: =ROUNDUP(E13*D13,0) -> 0 | G13: =F13 -> 0 | H13: =G13 -> 0 | I13: =H13 -> 0 | J13: =I13 -> 0 | K13: =J13 -> 0 | L13: =SUM(G13:K13) -> 0
F14: =ROUNDUP(E14*D14,0) -> 0 | G14: =F14 -> 0 | H14: =G14 -> 0 | I14: =H14 -> 0 | J14: =I14 -> 0 | K14: =J14 -> 0 | L14: =SUM(G14:K14) -> 0
F15: =ROUNDUP(E15*D15,0) -> 0 | G15: =F15 -> 0 | H15: =G15 -> 0 | I15: =H15 -> 0 | J15: =I15 -> 0 | K15: =J15 -> 0 | L15: =SUM(G15:K15) -> 0
... F18: =ROUNDUP(E18*D18,0) -> 0 | G18: =F18 -> 0 | H18: =G18 -> 0 | I18: =H18 -> 0 | J18: =I18 -> 0 | K18: =J18 -> 0 | L18: =SUM(G18:K18) -> 0
A19: TOTAL COST | F19: =SUM(F4:F18) -> 0 | G19: =SUM(G4:G18) -> 0 | H19: =SUM(H4:H18) -> 0 | I19: =SUM(I4:I18) -> 0 | J19: =SUM(J4:J18) -> 0 | K19: =SUM(K4:K18) -> 0 | L19: =SUM(L4:L18) -> 0
A23: VDI License Cost
A24: Total Number of Users | C24: Monthy License Cost per User | E24: Total Monthly License Cost | G24: Year 1 | H24: Year 2 | I24: Year 3 | J24: Year 4 | K24: Year 5 | L24: Total
A25: ='VDI Requirements'!H3 -> 15 | C25: 13 | E25: =$A$25*$C$25 -> 195 | G25: =($A$25*$C$25)*12 -> 2340 | H25: =($A$25*$C$25)*12 -> 2340 | I25: =($A$25*$C$25)*12 -> 2340 | J25: =($A$25*$C$25)*12 -> 2340 | K25: =($A$25*$C$25)*12 -> 2340 | L25: =SUM(G25:K26) -> 11700

Sheet DEV
A1: DEVELOPMENT ENVIRONMENT (to be filled out by servicing unit)
A2: YEAR 1
A3: Description | B3: Hours | C3: Cloud Platform | D3: Instance Type, Specs | E3: CPU | F3: Memory (GB) | G3: Operating System | H3: Disk Space Description (Size in GB) | J3: Disk Space (GB) | K3: Monthly EBS Volume Cost ($) | L3: Monthly Subscription Cost ($) | M3: VAT | N3: Enterprise Discount | O3: Total Monthly Cost ($) | P3: Total Annual Cost ($)
B4: =((12*5*4)/(24*7*4))*730 -> 260.71429 | C4: AWS | G4: Windows Server | H4: =IF(G4="Windows Server", "C:\", "/") -> C:\ | I4: =IF(G4="Windows Server", 150, 20) -> 150 | J4: =SUM(I4:I7) -> 300 | K4: =J4 *(IF(C4="AZURE", SUMMARY!C$20, SUMMARY!C$21)) -> 28.8 | M4: =IF(C4="ON PREM", 0, SUMMARY!C$25%) -> 0.12 | N4: =IF(C4="AWS",SUMMARY!C$26%, 0) -> 0.13 | O4: =((SUM(K4:L4))-((SUM(K4:L4))*N4))*(1 + M4) -> 28.06272 | P4: =O4*12 -> 336.75264
H5: =IF(G4="Windows Server", "F:\appdir", "/appdir") -> F:\appdir
H6: =IF(G4="Windows Server", "G:\Log", "/var/log") -> G:\Log | I6: =IF(G4="Windows Server", 50, 20) -> 50
H7: =IF(G4="Windows Server", "H:\Backup", "/backup") -> H:\Backup | I7: =IF(G4="Windows Server", 100, 10) -> 100
B8: =((12*5*4)/(24*7*4))*730 -> 260.71429 | C8: AWS | G8: Windows Server | H8: =IF(G8="Windows Server", "C:\", "/") -> C:\ | I8: =IF(G8="Windows Server", 150, 20) -> 150 | J8: =SUM(I8:I11) -> 300 | K8: =J8 *(IF(C8="AZURE", SUMMARY!C$20, SUMMARY!C$21)) -> 28.8 | M8: =IF(C8="ON PREM", 0, SUMMARY!C$25%) -> 0.12 | N8: =IF(C8="AWS",SUMMARY!C$26%, 0) -> 0.13 | O8: =((SUM(K8:L8))-((SUM(K8:L8))*N8))*(1 + M8) -> 28.06272 | P8: =O8*12 -> 336.75264
H9: =IF(G8="Windows Server", "F:\appdir", "/appdir") -> F:\appdir
H10: =IF(G8="Windows Server", "G:\Log", "/var/log") -> G:\Log | I10: =IF(G8="Windows Server", 50, 20) -> 50
H11: =IF(G8="Windows Server", "H:\Backup", "/backup") -> H:\Backup | I11: =IF(G8="Windows Server", 100, 10) -> 100
E12: =SUM(E4:E11) -> 0 | F12: =SUM(F4:F11) -> 0 | J12: =SUM(J4:J11) -> 600 | K12: =SUM(K4:K11) -> 57.6 | L12: =SUM(L4:L11) -> 0 | O12: =SUM(O4:O11) -> 56.12544 | P12: =SUM(P4:P11) -> 673.50528
A13: YEAR 2
B14: =((12*5*4)/(24*7*4))*730 -> 260.71429 | C14: AWS | E14: =$E$4 -> 0 | F14: =$F$4 -> 0 | G14: Windows Server | H14: =IF(G14="Windows Server", "C:\", "/") -> C:\ | I14: =IF(G14="Windows Server", 150, 20) -> 150 | J14: =SUM(I14:I17) -> 300 | K14: =J14 *(IF(C14="AZURE", SUMMARY!C$20, SUMMARY!C$21)) -> 28.8 | M14: =IF(C14="ON PREM", 0, SUMMARY!C$25%) -> 0.12 | N14: =IF(C14="AWS",SUMMARY!C$26%, 0) -> 0.13 | O14: =((SUM(K14:L14))-((SUM(K14:L14))*N14))*(1 + M14) -> 28.06272 | P14: =O14*12 -> 336.75264
H15: =IF(G14="Windows Server", "F:\appdir", "/appdir'") -> F:\appdir | I15: =$I$5 -> 0
H16: =IF(G14="Windows Server", "G:\Log", "/var/log") -> G:\Log | I16: =IF(G14="Windows Server", 50, 20) -> 50
H17: =IF(G14="Windows Server", "H:\Backup", "/backup") -> H:\Backup | I17: =IF(G14="Windows Server", 100, 10) -> 100
B18: =((12*5*4)/(24*7*4))*730 -> 260.71429 | C18: AWS | E18: =$E$8 -> 0 | F18: =$F$8 -> 0 | G18: Windows Server | H18: =IF(G18="Windows Server", "C:\", "/") -> C:\ | I18: =IF(G18="Windows Server", 150, 20) -> 150 | J18: =SUM(I18:I21) -> 300 | K18: =J18 *(IF(C18="AZURE", SUMMARY!C$20, SUMMARY!C$21)) -> 28.8 | M18: =IF(C18="ON PREM", 0, SUMMARY!C$25%) -> 0.12 | N18: =IF(C18="AWS",SUMMARY!C$26%, 0) -> 0.13 | O18: =((SUM(K18:L18))-((SUM(K18:L18))*N18))*(1 + M18) -> 28.06272 | P18: =O18*12 -> 336.75264
H19: =IF(G18="Windows Server", "F:\appdir", "/appdir") -> F:\appdir | I19: =$I$9 -> 0
H20: =IF(G18="Windows Server", "G:\Log", "/var/log") -> G:\Log | I20: =IF(G18="Windows Server", 50, 20) -> 50
H21: =IF(G18="Windows Server", "H:\Backup", "/backup") -> H:\Backup | I21: =IF(G18="Windows Server", 100, 10) -> 100
E22: =SUM(E14:E21) -> 0 | F22: =SUM(F14:F21) -> 0 | J22: =SUM(J14:J21) -> 600 | K22: =SUM(K14:K21) -> 57.6 | L22: =SUM(L14:L21) -> 0 | O22: =SUM(O14:O21) -> 56.12544 | P22: =SUM(P14:P21) -> 673.50528
A23: YEAR 3
B24: =((12*5*4)/(24*7*4))*730 -> 260.71429 | C24: EXACC | E24: =$E$4 -> 0 | F24: =$F$4 -> 0 | G24: RHEL | H24: =IF(G24="Windows Server", "C:\", "/") -> / | I24: =IF(G24="Windows Server", 150, 20) -> 20 | J24: =SUM(I24:I27) -> 50 | K24: =J24 *(IF(C24="AZURE", SUMMARY!C$20, SUMMARY!C$21)) -> 4.8 | M24: =IF(C24="ON PREM", 0, SUMMARY!C$25%) -> 0.12 | N24: =IF(C24="AWS",SUMMARY!C$26%, 0) -> 0 | O24: =((SUM(K24:L24))-((SUM(K24:L24))*N24))*(1 + M24) -> 5.376 | P24: =O24*12 -> 64.512
H25: =IF(G24="Windows Server", "F:\appdir", "/appdir") -> /appdir
H26: =IF(G24="Windows Server", "G:\Log", "/var/log") -> /var/log | I26: =IF(G24="Windows Server", 50, 20) -> 20
H27: =IF(G24="Windows Server", "H:\Backup", "/backup") -> /backup | I27: =IF(G24="Windows Server", 100, 10) -> 10
B28: =((12*5*4)/(24*7*4))*730 -> 260.71429 | C28: ON PREM | E28: =$E$8 -> 0 | F28: =$F$8 -> 0 | G28: RHEL | H28: =IF(G28="Windows Server", "C:\", "/") -> / | I28: =IF(G28="Windows Server", 150, 20) -> 20 | J28: =SUM(I28:I31) -> 50 | K28: =J28 *(IF(C28="AZURE", SUMMARY!C$20, SUMMARY!C$21)) -> 4.8 | M28: =IF(C28="ON PREM", 0, SUMMARY!C$25%) -> 0 | N28: =IF(C28="AWS",SUMMARY!C$26%, 0) -> 0 | O28: =((SUM(K28:L28))-((SUM(K28:L28))*N28))*(1 + M28) -> 4.8 | P28: =O28*12 -> 57.6
H29: =IF(G28="Windows Server", "F:\appdir", "/appdir") -> /appdir
H30: =IF(G28="Windows Server", "G:\Log", "/var/log") -> /var/log | I30: =IF(G28="Windows Server", 50, 20) -> 20
H31: =IF(G28="Windows Server", "H:\Backup", "/backup") -> /backup | I31: =IF(G28="Windows Server", 100, 10) -> 10
E32: =SUM(E24:E31) -> 0 | F32: =SUM(F24:F31) -> 0 | J32: =SUM(J24:J31) -> 100 | K32: =SUM(K24:K31) -> 9.6 | L32: =SUM(L24:L31) -> 0 | O32: =SUM(O24:O31) -> 10.176 | P32: =SUM(P24:P31) -> 122.112
A33: YEAR 4
B34: =((12*5*4)/(24*7*4))*730 -> 260.71429 | C34: AWS | E34: =$E$4 -> 0 | F34: =$F$4 -> 0 | G34: Windows Server | H34: =IF(G34="Windows Server", "C:\", "/") -> C:\ | I34: =IF(G34="Windows Server", 150, 20) -> 150 | J34: =SUM(I34:I37) -> 300 | K34: =J34 *(IF(C34="AZURE", SUMMARY!C$20, SUMMARY!C$21)) -> 28.8 | M34: =IF(C34="ON PREM", 0, SUMMARY!C$25%) -> 0.12 | N34: =IF(C34="AWS",SUMMARY!C$26%, 0) -> 0.13 | O34: =((SUM(K34:L34))-((SUM(K34:L34))*N34))*(1 + M34) -> 28.06272 | P34: =O34*12 -> 336.75264
H35: =IF(G34="Windows Server", "F:\appdir", "/appdir") -> F:\appdir | I35: =$I$5 -> 0
H36: =IF(G34="Windows Server", "G:\Log", "/var/log") -> G:\Log | I36: =IF(G34="Windows Server", 50, 20) -> 50
H37: =IF(G34="Windows Server", "H:\Backup", "/backup") -> H:\Backup | I37: =IF(G34="Windows Server", 100, 10) -> 100
B38: =((12*5*4)/(24*7*4))*730 -> 260.71429 | C38: AWS | E38: =$E$8 -> 0 | F38: =$F$8 -> 0 | G38: RHEL | H38: =IF(G38="Windows Server", "C:\", "/") -> / | I38: =IF(G38="Windows Server", 150, 20) -> 20 | J38: =SUM(I38:I41) -> 50 | K38: =J38 *(IF(C38="AZURE", SUMMARY!C$20, SUMMARY!C$21)) -> 4.8 | M38: =IF(C38="ON PREM", 0, SUMMARY!C$25%) -> 0.12 | N38: =IF(C38="AWS",SUMMARY!C$26%, 0) -> 0.13 | O38: =((SUM(K38:L38))-((SUM(K38:L38))*N38))*(1 + M38) -> 4.67712 | P38: =O38*12 -> 56.12544
H39: =IF(G38="Windows Server", "F:\appdir", "/appdir") -> /appdir | I39: =$I$9 -> 0
H40: =IF(G38="Windows Server", "G:\Log", "/var/log") -> /var/log | I40: =IF(G38="Windows Server", 50, 20) -> 20
H41: =IF(G38="Windows Server", "H:\Backup", "/backup") -> /backup | I41: =IF(G38="Windows Server", 100, 10) -> 10
E42: =SUM(E34:E41) -> 0 | F42: =SUM(F34:F41) -> 0 | J42: =SUM(J34:J41) -> 350 | K42: =SUM(K34:K41) -> 33.6 | L42: =SUM(L34:L41) -> 0 | O42: =SUM(O34:O41) -> 32.73984 | P42: =SUM(P34:P41) -> 392.87808
A43: YEAR 5
B44: =((12*5*4)/(24*7*4))*730 -> 260.71429 | C44: EXACC | E44: =$E$4 -> 0 | F44: =$F$4 -> 0 | G44: RHEL | H44: =IF(G44="Windows Server", "C:\", "/") -> / | I44: =IF(G44="Windows Server", 150, 20) -> 20 | J44: =SUM(I44:I47) -> 50 | K44: =J44 *(IF(C44="AZURE", SUMMARY!C$20, SUMMARY!C$21)) -> 4.8 | M44: =IF(C44="ON PREM", 0, 12%) -> 0.12 | N44: =IF(C44="AWS",SUMMARY!C$26%, 0) -> 0 | O44: =((SUM(K44:L44))-((SUM(K44:L44))*N44))*(1 + M44) -> 5.376 | P44: =O44*12 -> 64.512
H45: =IF(G44="Windows Server", "F:\appdir", "/appdir") -> /appdir
H46: =IF(G44="Windows Server", "G:\Log", "/var/log") -> /var/log | I46: =IF(G44="Windows Server", 50, 20) -> 20
H47: =IF(G44="Windows Server", "H:\Backup", "/backup") -> /backup | I47: =IF(G44="Windows Server", 100, 10) -> 10
B48: =((12*5*4)/(24*7*4))*730 -> 260.71429 | C48: EXACC | E48: =$E$8 -> 0 | F48: =$F$8 -> 0 | G48: RHEL | H48: =IF(G48="Windows Server", "C:\", "/") -> / | I48: =IF(G48="Windows Server", 150, 20) -> 20 | J48: =SUM(I48:I51) -> 50 | K48: =J48 *(IF(C48="AZURE", SUMMARY!C$20, SUMMARY!C$21)) -> 4.8 | M48: =IF(C48="ON PREM", 0, 12%) -> 0.12 | N48: =IF(C48="AWS",SUMMARY!C$26%, 0) -> 0 | O48: =((SUM(K48:L48))-((SUM(K48:L48))*N48))*(1 + M48) -> 5.376 | P48: =O48*12 -> 64.512
H49: =IF(G48="Windows Server", "F:\appdir", "/appdir") -> /appdir
H50: =IF(G48="Windows Server", "G:\Log", "/var/log") -> /var/log | I50: =IF(G48="Windows Server", 50, 20) -> 20
H51: =IF(G48="Windows Server", "H:\Backup", "/backup") -> /backup | I51: =IF(G48="Windows Server", 100, 10) -> 10
E52: =SUM(E44:E51) -> 0 | F52: =SUM(F44:F51) -> 0 | J52: =SUM(J44:J51) -> 100 | K52: =SUM(K44:K51) -> 9.6 | L52: =SUM(L44:L51) -> 0 | O52: =SUM(O44:O51) -> 10.752 | P52: =SUM(P44:P51) -> 129.024

Sheet SIT
A1: SIT ENVIRONMENT (to be filled out by servicing unit)
A2: YEAR 1
A3: Description | B3: Hours | C3: Cloud Platform | D3: Instance Type, Specs | E3: CPU | F3: Memory (GB) | G3: Operating System | H3: Disk Space Description (Size in GB) | J3: Disk Space (GB) | K3: Monthly EBS Volume Cost ($) | L3: Monthly Subscription Cost ($) | M3: VAT | N3: Enterprise Discount | O3: Total Monthly Cost ($) | P3: Total Annual Cost ($)
B4: =((12*5*4)/(24*7*4))*730 -> 260.71429 | C4: EXACC | G4: Windows Server | H4: =IF(G4="Windows Server", "C:\", "/") -> C:\ | I4: =IF(G4="Windows Server", 150, 20) -> 150 | J4: =SUM(I4:I7) -> 300 | K4: =J4 *(IF(C4="AZURE", SUMMARY!C$20, SUMMARY!C$21)) -> 28.8 | L4: 2 | M4: =IF(C4="ON PREM", 0, SUMMARY!C$25%) -> 0.12 | N4: =IF(C4="AWS",SUMMARY!C$26%, 0) -> 0 | O4: =((SUM(K4:L4))-((SUM(K4:L4))*N4))*(1 + M4) -> 34.496 | P4: =O4*12 -> 413.952
H5: =IF(G4="Windows Server", "F:\appdir", "/appdir") -> F:\appdir
H6: =IF(G4="Windows Server", "G:\Log", "/var/log") -> G:\Log | I6: =IF(G4="Windows Server", 50, 20) -> 50
H7: =IF(G4="Windows Server", "H:\Backup", "/backup") -> H:\Backup | I7: =IF(G4="Windows Server", 100, 10) -> 100
B8: =((12*5*4)/(24*7*4))*730 -> 260.71429 | C8: ON PREM | G8: Windows Server | H8: =IF(G8="Windows Server", "C:\", "/") -> C:\ | I8: =IF(G8="Windows Server", 150, 20) -> 150 | J8: =SUM(I8:I11) -> 300 | K8: =J8 *(IF(C8="AZURE", SUMMARY!C$20, SUMMARY!C$21)) -> 28.8 | L8: 2 | M8: =IF(C8="ON PREM", 0, SUMMARY!C$25%) -> 0 | N8: =IF(C8="AWS",SUMMARY!C$26%, 0) -> 0 | O8: =((SUM(K8:L8))-((SUM(K8:L8))*N8))*(1 + M8) -> 30.8 | P8: =O8*12 -> 369.6
H9: =IF(G8="Windows Server", "F:\appdir", "/appdir") -> F:\appdir
H10: =IF(G8="Windows Server", "G:\Log", "/var/log") -> G:\Log | I10: =IF(G8="Windows Server", 50, 20) -> 50
H11: =IF(G8="Windows Server", "H:\Backup", "/backup") -> H:\Backup | I11: =IF(G8="Windows Server", 100, 10) -> 100
E12: =SUM(E4:E11) -> 0 | F12: =SUM(F4:F11) -> 0 | J12: =SUM(J4:J11) -> 600 | K12: =SUM(K4:K11) -> 57.6 | L12: =SUM(L4:L11) -> 4 | O12: =SUM(O4:O11) -> 65.296 | P12: =SUM(P4:P11) -> 783.552
A13: YEAR 2
B14: =((12*5*4)/(24*7*4))*730 -> 260.71429 | C14: AWS | E14: =$E$4 -> 0 | F14: =$F$4 -> 0 | G14: Windows Server | H14: =IF(G14="Windows Server", "C:\", "/") -> C:\ | I14: =IF(G14="Windows Server", 150, 20) -> 150 | J14: =SUM(I14:I17) -> 300 | K14: =J14 *(IF(C14="AZURE", SUMMARY!C$20, SUMMARY!C$21)) -> 28.8 | M14: =IF(C14="ON PREM", 0, SUMMARY!C$25%) -> 0.12 | N14: =IF(C14="AWS",SUMMARY!C$26%, 0) -> 0.13 | O14: =((SUM(K14:L14))-((SUM(K14:L14))*N14))*(1 + M14) -> 28.06272 | P14: =O14*12 -> 336.75264
H15: =IF(G14="Windows Server", "F:\appdir", "/appdir'") -> F:\appdir | I15: =$I$5 -> 0
H16: =IF(G14="Windows Server", "G:\Log", "/var/log") -> G:\Log | I16: =IF(G14="Windows Server", 50, 20) -> 50
H17: =IF(G14="Windows Server", "H:\Backup", "/backup") -> H:\Backup | I17: =IF(G14="Windows Server", 100, 10) -> 100
B18: =((12*5*4)/(24*7*4))*730 -> 260.71429 | C18: AWS | E18: =$E$8 -> 0 | F18: =$F$8 -> 0 | G18: Windows Server | H18: =IF(G18="Windows Server", "C:\", "/") -> C:\ | I18: =IF(G18="Windows Server", 150, 20) -> 150 | J18: =SUM(I18:I21) -> 300 | K18: =J18 *(IF(C18="AZURE", SUMMARY!C$20, SUMMARY!C$21)) -> 28.8 | M18: =IF(C18="ON PREM", 0, SUMMARY!C$25%) -> 0.12 | N18: =IF(C18="AWS",SUMMARY!C$26%, 0) -> 0.13 | O18: =((SUM(K18:L18))-((SUM(K18:L18))*N18))*(1 + M18) -> 28.06272 | P18: =O18*12 -> 336.75264
H19: =IF(G18="Windows Server", "F:\appdir", "/appdir") -> F:\appdir | I19: =$I$9 -> 0
H20: =IF(G18="Windows Server", "G:\Log", "/var/log") -> G:\Log | I20: =IF(G18="Windows Server", 50, 20) -> 50
H21: =IF(G18="Windows Server", "H:\Backup", "/backup") -> H:\Backup | I21: =IF(G18="Windows Server", 100, 10) -> 100
E22: =SUM(E14:E21) -> 0 | F22: =SUM(F14:F21) -> 0 | J22: =SUM(J14:J21) -> 600 | K22: =SUM(K14:K21) -> 57.6 | L22: =SUM(L14:L21) -> 0 | O22: =SUM(O14:O21) -> 56.12544 | P22: =SUM(P14:P21) -> 673.50528
A23: YEAR 3
B24: =((12*5*4)/(24*7*4))*730 -> 260.71429 | C24: EXACC | E24: =$E$4 -> 0 | F24: =$F$4 -> 0 | G24: RHEL | H24: =IF(G24="Windows Server", "C:\", "/") -> / | I24: =IF(G24="Windows Server", 150, 20) -> 20 | J24: =SUM(I24:I27) -> 50 | K24: =J24 *(IF(C24="AZURE", SUMMARY!C$20, SUMMARY!C$21)) -> 4.8 | M24: =IF(C24="ON PREM", 0, SUMMARY!C$25%) -> 0.12 | N24: =IF(C24="AWS",SUMMARY!C$26%, 0) -> 0 | O24: =((SUM(K24:L24))-((SUM(K24:L24))*N24))*(1 + M24) -> 5.376 | P24: =O24*12 -> 64.512
H25: =IF(G24="Windows Server", "F:\appdir", "/appdir") -> /appdir
H26: =IF(G24="Windows Server", "G:\Log", "/var/log") -> /var/log | I26: =IF(G24="Windows Server", 50, 20) -> 20
H27: =IF(G24="Windows Server", "H:\Backup", "/backup") -> /backup | I27: =IF(G24="Windows Server", 100, 10) -> 10
B28: =((12*5*4)/(24*7*4))*730 -> 260.71429 | C28: ON PREM | E28: =$E$8 -> 0 | F28: =$F$8 -> 0 | G28: RHEL | H28: =IF(G28="Windows Server", "C:\", "/") -> / | I28: =IF(G28="Windows Server", 150, 20) -> 20 | J28: =SUM(I28:I31) -> 50 | K28: =J28 *(IF(C28="AZURE", SUMMARY!C$20, SUMMARY!C$21)) -> 4.8 | M28: =IF(C28="ON PREM", 0, SUMMARY!C$25%) -> 0 | N28: =IF(C28="AWS",SUMMARY!C$26%, 0) -> 0 | O28: =((SUM(K28:L28))-((SUM(K28:L28))*N28))*(1 + M28) -> 4.8 | P28: =O28*12 -> 57.6
H29: =IF(G28="Windows Server", "F:\appdir", "/appdir") -> /appdir
H30: =IF(G28="Windows Server", "G:\Log", "/var/log") -> /var/log | I30: =IF(G28="Windows Server", 50, 20) -> 20
H31: =IF(G28="Windows Server", "H:\Backup", "/backup") -> /backup | I31: =IF(G28="Windows Server", 100, 10) -> 10
E32: =SUM(E24:E31) -> 0 | F32: =SUM(F24:F31) -> 0 | J32: =SUM(J24:J31) -> 100 | K32: =SUM(K24:K31) -> 9.6 | L32: =SUM(L24:L31) -> 0 | O32: =SUM(O24:O31) -> 10.176 | P32: =SUM(P24:P31) -> 122.112
A33: YEAR 4
B34: =((12*5*4)/(24*7*4))*730 -> 260.71429 | C34: AWS | E34: =$E$4 -> 0 | F34: =$F$4 -> 0 | G34: Windows Server | H34: =IF(G34="Windows Server", "C:\", "/") -> C:\ | I34: =IF(G34="Windows Server", 150, 20) -> 150 | J34: =SUM(I34:I37) -> 300 | K34: =J34 *(IF(C34="AZURE", SUMMARY!C$20, SUMMARY!C$21)) -> 28.8 | M34: =IF(C34="ON PREM", 0, SUMMARY!C$25%) -> 0.12 | N34: =IF(C34="AWS",SUMMARY!C$26%, 0) -> 0.13 | O34: =((SUM(K34:L34))-((SUM(K34:L34))*N34))*(1 + M34) -> 28.06272 | P34: =O34*12 -> 336.75264
H35: =IF(G34="Windows Server", "F:\appdir", "/appdir") -> F:\appdir | I35: =$I$5 -> 0
H36: =IF(G34="Windows Server", "G:\Log", "/var/log") -> G:\Log | I36: =IF(G34="Windows Server", 50, 20) -> 50
H37: =IF(G34="Windows Server", "H:\Backup", "/backup") -> H:\Backup | I37: =IF(G34="Windows Server", 100, 10) -> 100
B38: =((12*5*4)/(24*7*4))*730 -> 260.71429 | C38: AWS | E38: =$E$8 -> 0 | F38: =$F$8 -> 0 | G38: RHEL | H38: =IF(G38="Windows Server", "C:\", "/") -> / | I38: =IF(G38="Windows Server", 150, 20) -> 20 | J38: =SUM(I38:I41) -> 50 | K38: =J38 *(IF(C38="AZURE", SUMMARY!C$20, SUMMARY!C$21)) -> 4.8 | M38: =IF(C38="ON PREM", 0, SUMMARY!C$25%) -> 0.12 | N38: =IF(C38="AWS",SUMMARY!C$26%, 0) -> 0.13 | O38: =((SUM(K38:L38))-((SUM(K38:L38))*N38))*(1 + M38) -> 4.67712 | P38: =O38*12 -> 56.12544
H39: =IF(G38="Windows Server", "F:\appdir", "/appdir") -> /appdir | I39: =$I$9 -> 0
H40: =IF(G38="Windows Server", "G:\Log", "/var/log") -> /var/log | I40: =IF(G38="Windows Server", 50, 20) -> 20
H41: =IF(G38="Windows Server", "H:\Backup", "/backup") -> /backup | I41: =IF(G38="Windows Server", 100, 10) -> 10
E42: =SUM(E34:E41) -> 0 | F42: =SUM(F34:F41) -> 0 | J42: =SUM(J34:J41) -> 350 | K42: =SUM(K34:K41) -> 33.6 | L42: =SUM(L34:L41) -> 0 | O42: =SUM(O34:O41) -> 32.73984 | P42: =SUM(P34:P41) -> 392.87808
A43: YEAR 5
B44: =((12*5*4)/(24*7*4))*730 -> 260.71429 | C44: EXACC | E44: =$E$4 -> 0 | F44: =$F$4 -> 0 | G44: RHEL | H44: =IF(G44="Windows Server", "C:\", "/") -> / | I44: =IF(G44="Windows Server", 150, 20) -> 20 | J44: =SUM(I44:I47) -> 50 | K44: =J44 *(IF(C44="AZURE", SUMMARY!C$20, SUMMARY!C$21)) -> 4.8 | M44: =IF(C44="ON PREM", 0, 12%) -> 0.12 | N44: =IF(C44="AWS",SUMMARY!C$26%, 0) -> 0 | O44: =((SUM(K44:L44))-((SUM(K44:L44))*N44))*(1 + M44) -> 5.376 | P44: =O44*12 -> 64.512
H45: =IF(G44="Windows Server", "F:\appdir", "/appdir") -> /appdir
H46: =IF(G44="Windows Server", "G:\Log", "/var/log") -> /var/log | I46: =IF(G44="Windows Server", 50, 20) -> 20
H47: =IF(G44="Windows Server", "H:\Backup", "/backup") -> /backup | I47: =IF(G44="Windows Server", 100, 10) -> 10
B48: =((12*5*4)/(24*7*4))*730 -> 260.71429 | C48: EXACC | E48: =$E$8 -> 0 | F48: =$F$8 -> 0 | G48: RHEL | H48: =IF(G48="Windows Server", "C:\", "/") -> / | I48: =IF(G48="Windows Server", 150, 20) -> 20 | J48: =SUM(I48:I51) -> 50 | K48: =J48 *(IF(C48="AZURE", SUMMARY!C$20, SUMMARY!C$21)) -> 4.8 | M48: =IF(C48="ON PREM", 0, 12%) -> 0.12 | N48: =IF(C48="AWS",SUMMARY!C$26%, 0) -> 0 | O48: =((SUM(K48:L48))-((SUM(K48:L48))*N48))*(1 + M48) -> 5.376 | P48: =O48*12 -> 64.512
H49: =IF(G48="Windows Server", "F:\appdir", "/appdir") -> /appdir
H50: =IF(G48="Windows Server", "G:\Log", "/var/log") -> /var/log | I50: =IF(G48="Windows Server", 50, 20) -> 20
H51: =IF(G48="Windows Server", "H:\Backup", "/backup") -> /backup | I51: =IF(G48="Windows Server", 100, 10) -> 10
E52: =SUM(E44:E51) -> 0 | F52: =SUM(F44:F51) -> 0 | J52: =SUM(J44:J51) -> 100 | K52: =SUM(K44:K51) -> 9.6 | L52: =SUM(L44:L51) -> 0 | O52: =SUM(O44:O51) -> 10.752 | P52: =SUM(P44:P51) -> 129.024

Sheet UAT
A1: UAT ENVIRONMENT (to be filled out by servicing unit)
A2: YEAR 1
A3: Description | B3: Hours | C3: Cloud Platform | D3: Instance Type, Specs | E3: CPU | F3: Memory (GB) | G3: Operating System | H3: Disk Space Description (Size in GB) | J3: Disk Space (GB) | K3: Monthly EBS Volume Cost ($) | L3: Monthly Subscription Cost ($) | M3: VAT | N3: Enterprise Discount | O3: Total Monthly Cost ($) | P3: Total Annual Cost ($)
B4: =((12*5*4)/(24*7*4))*730 -> 260.71429 | C4: EXACC | G4: Ubuntu | H4: =IF(G4="Windows Server", "C:\", "/") -> / | I4: =IF(G4="Windows Server", 150, 20) -> 20 | J4: =SUM(I4:I7) -> 50 | K4: =J4 *(IF(C4="AZURE", SUMMARY!C$20, SUMMARY!C$21)) -> 4.8 | M4: =IF(C4="ON PREM", 0, SUMMARY!C$25%) -> 0.12 | N4: =IF(C4="AWS",SUMMARY!C$26%, 0) -> 0 | O4: =((SUM(K4:L4))-((SUM(K4:L4))*N4))*(1 + M4) -> 5.376 | P4: =O4*12 -> 64.512
H5: =IF(G4="Windows Server", "F:\appdir", "/appdir") -> /appdir
H6: =IF(G4="Windows Server", "G:\Log", "/var/log") -> /var/log | I6: =IF(G4="Windows Server", 50, 20) -> 20
H7: =IF(G4="Windows Server", "H:\Backup", "/backup") -> /backup | I7: =IF(G4="Windows Server", 100, 10) -> 10
B8: =((12*5*4)/(24*7*4))*730 -> 260.71429 | C8: ON PREM | G8: Ubuntu | H8: =IF(G8="Windows Server", "C:\", "/") -> / | I8: =IF(G8="Windows Server", 150, 20) -> 20 | J8: =SUM(I8:I11) -> 50 | K8: =J8 *(IF(C8="AZURE", SUMMARY!C$20, SUMMARY!C$21)) -> 4.8 | M8: =IF(C8="ON PREM", 0, SUMMARY!C$25%) -> 0 | N8: =IF(C8="AWS",SUMMARY!C$26%, 0) -> 0 | O8: =((SUM(K8:L8))-((SUM(K8:L8))*N8))*(1 + M8) -> 4.8 | P8: =O8*12 -> 57.6
H9: =IF(G8="Windows Server", "F:\appdir", "/appdir") -> /appdir
H10: =IF(G8="Windows Server", "G:\Log", "/var/log") -> /var/log | I10: =IF(G8="Windows Server", 50, 20) -> 20
H11: =IF(G8="Windows Server", "H:\Backup", "/backup") -> /backup | I11: =IF(G8="Windows Server", 100, 10) -> 10
B12: =((12*5*4)/(24*7*4))*730 -> 260.71429 | C12: EXACC | G12: Oracle Linux | H12: =IF(G12="Windows Server", "C:\", "/") -> / | I12: =IF(G12="Windows Server", 150, 20) -> 20 | J12: =SUM(I12:I15) -> 50 | K12: =J12 *(IF(C12="AZURE", SUMMARY!C$20, SUMMARY!C$21)) -> 4.8 | M12: =IF(C12="ON PREM", 0, SUMMARY!C$25%) -> 0.12 | N12: =IF(C12="AWS",SUMMARY!C$26%, 0) -> 0 | O12: =((SUM(K12:L12))-((SUM(K12:L12))*N12))*(1 + M12) -> 5.376 | P12: =O12*12 -> 64.512
H13: =IF(G12="Windows Server", "F:\appdir", "/appdir") -> /appdir
H14: =IF(G12="Windows Server", "G:\Log", "/var/log") -> /var/log | I14: =IF(G12="Windows Server", 50, 20) -> 20
H15: =IF(G12="Windows Server", "H:\Backup", "/backup") -> /backup | I15: =IF(G12="Windows Server", 100, 10) -> 10
B16: =((12*5*4)/(24*7*4))*730 -> 260.71429 | C16: ON PREM | G16: Oracle Linux | H16: =IF(G16="Windows Server", "C:\", "/") -> / | I16: =IF(G16="Windows Server", 150, 20) -> 20 | J16: =SUM(I16:I19) -> 50 | K16: =J16 *(IF(C16="AZURE", SUMMARY!C$20, SUMMARY!C$21)) -> 4.8 | M16: =IF(C16="ON PREM", 0, SUMMARY!C$25%) -> 0 | N16: =IF(C16="AWS",SUMMARY!C$26%, 0) -> 0 | O16: =((SUM(K16:L16))-((SUM(K16:L16))*N16))*(1 + M16) -> 4.8 | P16: =O16*12 -> 57.6
H17: =IF(G16="Windows Server", "F:\appdir", "/appdir") -> /appdir
H18: =IF(G16="Windows Server", "G:\Log", "/var/log") -> /var/log | I18: =IF(G16="Windows Server", 50, 20) -> 20
H19: =IF(G16="Windows Server", "H:\Backup", "/backup") -> /backup | I19: =IF(G16="Windows Server", 100, 10) -> 10
B20: =((12*5*4)/(24*7*4))*730 -> 260.71429 | C20: EXACC | G20: Ubuntu | H20: =IF(G20="Windows Server", "C:\", "/") -> / | I20: =IF(G20="Windows Server", 150, 20) -> 20 | J20: =SUM(I20:I23) -> 50 | K20: =J20 *(IF(C20="AZURE", SUMMARY!C$20, SUMMARY!C$21)) -> 4.8 | M20: =IF(C20="ON PREM", 0, SUMMARY!C$25%) -> 0.12 | N20: =IF(C20="AWS",SUMMARY!C$26%, 0) -> 0 | O20: =((SUM(K20:L20))-((SUM(K20:L20))*N20))*(1 + M20) -> 5.376 | P20: =O20*12 -> 64.512
H21: =IF(G20="Windows Server", "F:\appdir", "/appdir") -> /appdir
H22: =IF(G20="Windows Server", "G:\Log", "/var/log") -> /var/log | I22: =IF(G20="Windows Server", 50, 20) -> 20
H23: =IF(G20="Windows Server", "H:\Backup", "/backup") -> /backup | I23: =IF(G20="Windows Server", 100, 10) -> 10
B24: =((12*5*4)/(24*7*4))*730 -> 260.71429 | C24: EXACC | G24: Oracle Linux | H24: =IF(G24="Windows Server", "C:\", "/") -> / | I24: =IF(G24="Windows Server", 150, 20) -> 20 | J24: =SUM(I24:I27) -> 50 | K24: =J24 *(IF(C24="AZURE", SUMMARY!C$20, SUMMARY!C$21)) -> 4.8 | M24: =IF(C24="ON PREM", 0, SUMMARY!C$25%) -> 0.12 | N24: =IF(C24="AWS",SUMMARY!C$26%, 0) -> 0 | O24: =((SUM(K24:L24))-((SUM(K24:L24))*N24))*(1 + M24) -> 5.376 | P24: =O24*12 -> 64.512
H25: =IF(G24="Windows Server", "F:\appdir", "/appdir") -> /appdir
H26: =IF(G24="Windows Server", "G:\Log", "/var/log") -> /var/log | I26: =IF(G24="Windows Server", 50, 20) -> 20
H27: =IF(G24="Windows Server", "H:\Backup", "/backup") -> /backup | I27: =IF(G24="Windows Server", 100, 10) -> 10
E28: =SUM(E4:E27) -> 0 | F28: =SUM(F4:F27) -> 0 | J28: =SUM(J4:J27) -> 300 | K28: =SUM(K4:K27) -> 28.8 | L28: =SUM(L4:L27) -> 0 | O28: =SUM(O4:O27) -> 31.104 | P28: =SUM(P4:P27) -> 373.248
A29: YEAR 2
B30: =((12*5*4)/(24*7*4))*730 -> 260.71429 | C30: AWS | E30: =CEILING(E4*(100+SUMMARY!$C$24)%,1) -> 0 | F30: =CEILING(F4*(100+SUMMARY!$C$24)%,1) -> 0 | G30: Windows Server | H30: =IF(G30="Windows Server", "C:\", "/") -> C:\ | I30: =IF(G30="Windows Server", 150, 20) -> 150 | J30: =SUM(I30:I33) -> 300 | K30: =J30 *(IF(C30="AZURE", SUMMARY!C$20, SUMMARY!C$21)) -> 28.8 | M30: =IF(C30="ON PREM", 0, SUMMARY!C$25%) -> 0.12 | N30: =IF(C30="AWS",SUMMARY!C$26%, 0) -> 0.13 | O30: =((SUM(K30:L30))-((SUM(K30:L30))*N30))*(1 + M30) -> 28.06272 | P30: =O30*12 -> 336.75264
H31: =IF(G30="Windows Server", "F:\appdir", "/appdir") -> F:\appdir | I31: =CEILING(I5*(100+SUMMARY!$C$24)%,1) -> 0
H32: =IF(G30="Windows Server", "G:\Log", "/var/log") -> G:\Log | I32: =IF(G30="Windows Server", 50, 20) -> 50
H33: =IF(G30="Windows Server", "H:\Backup", "/backup") -> H:\Backup | I33: =IF(G30="Windows Server", 100, 10) -> 100
B34: =((12*5*4)/(24*7*4))*730 -> 260.71429 | C34: AWS | E34: =CEILING(E8*(100+SUMMARY!$C$24)%,1) -> 0 | F34: =CEILING(F8*(100+SUMMARY!$C$24)%,1) -> 0 | G34: RHEL | H34: =IF(G34="Windows Server", "C:\", "/") -> / | I34: =IF(G34="Windows Server", 150, 20) -> 20 | J34: =SUM(I34:I37) -> 50 | K34: =J34 *(IF(C34="AZURE", SUMMARY!C$20, SUMMARY!C$21)) -> 4.8 | M34: =IF(C34="ON PREM", 0, SUMMARY!C$25%) -> 0.12 | N34: =IF(C34="AWS",SUMMARY!C$26%, 0) -> 0.13 | O34: =((SUM(K34:L34))-((SUM(K34:L34))*N34))*(1 + M34) -> 4.67712 | P34: =O34*12 -> 56.12544
H35: =IF(G34="Windows Server", "F:\appdir", "/appdir") -> /appdir | I35: =CEILING(I9*(100+SUMMARY!$C$24)%,1) -> 0
H36: =IF(G34="Windows Server", "G:\Log", "/var/log") -> /var/log | I36: =IF(G34="Windows Server", 50, 20) -> 20
H37: =IF(G34="Windows Server", "H:\Backup", "/backup") -> /backup | I37: =IF(G34="Windows Server", 100, 10) -> 10
B38: =((12*5*4)/(24*7*4))*730 -> 260.71429 | C38: AWS | E38: =CEILING(E12*(100+SUMMARY!$C$24)%,1) -> 0 | F38: =CEILING(F12*(100+SUMMARY!$C$24)%,1) -> 0 | G38: Windows Server | H38: =IF(G38="Windows Server", "C:\", "/") -> C:\ | I38: =IF(G38="Windows Server", 150, 20) -> 150 | J38: =SUM(I38:I41) -> 300 | K38: =J38 *(IF(C38="AZURE", SUMMARY!C$20, SUMMARY!C$21)) -> 28.8 | M38: =IF(C38="ON PREM", 0, SUMMARY!C$25%) -> 0.12 | N38: =IF(C38="AWS",SUMMARY!C$26%, 0) -> 0.13 | O38: =((SUM(K38:L38))-((SUM(K38:L38))*N38))*(1 + M38) -> 28.06272 | P38: =O38*12 -> 336.75264
H39: =IF(G38="Windows Server", "F:\appdir", "/appdir") -> F:\appdir | I39: =CEILING(I13*(100+SUMMARY!$C$24)%,1) -> 0
H40: =IF(G38="Windows Server", "G:\Log", "/var/log") -> G:\Log | I40: =IF(G38="Windows Server", 50, 20) -> 50
H41: =IF(G38="Windows Server", "H:\Backup", "/backup") -> H:\Backup | I41: =IF(G38="Windows Server", 100, 10) -> 100
B42: =((12*5*4)/(24*7*4))*730 -> 260.71429 | C42: AWS | E42: =CEILING(E16*(100+SUMMARY!$C$24)%,1) -> 0 | F42: =CEILING(F16*(100+SUMMARY!$C$24)%,1) -> 0 | G42: Windows Server | H42: =IF(G42="Windows Server", "C:\", "/") -> C:\ | I42: =IF(G42="Windows Server", 150, 20) -> 150 | J42: =SUM(I42:I45) -> 300 | K42: =J42 *(IF(C42="AZURE", SUMMARY!C$20, SUMMARY!C$21)) -> 28.8 | M42: =IF(C42="ON PREM", 0, SUMMARY!C$25%) -> 0.12 | N42: =IF(C42="AWS",SUMMARY!C$26%, 0) -> 0.13 | O42: =((SUM(K42:L42))-((SUM(K42:L42))*N42))*(1 + M42) -> 28.06272 | P42: =O42*12 -> 336.75264
H43: =IF(G42="Windows Server", "F:\appdir", "/appdir") -> F:\appdir | I43: =CEILING(I17*(100+SUMMARY!$C$24)%,1) -> 0
H44: =IF(G42="Windows Server", "G:\Log", "/var/log") -> G:\Log | I44: =IF(G42="Windows Server", 50, 20) -> 50
H45: =IF(G42="Windows Server", "H:\Backup", "/backup") -> H:\Backup | I45: =IF(G42="Windows Server", 100, 10) -> 100
B46: =((12*5*4)/(24*7*4))*730 -> 260.71429 | C46: AWS | E46: =CEILING(E20*(100+SUMMARY!$C$24)%,1) -> 0 | F46: =CEILING(F20*(100+SUMMARY!$C$24)%,1) -> 0 | G46: Windows Server | H46: =IF(G46="Windows Server", "C:\", "/") -> C:\ | I46: =IF(G46="Windows Server", 150, 20) -> 150 | J46: =SUM(I46:I49) -> 300 | K46: =J46 *(IF(C46="AZURE", SUMMARY!C$20, SUMMARY!C$21)) -> 28.8 | M46: =IF(C46="ON PREM", 0, SUMMARY!C$25%) -> 0.12 | N46: =IF(C46="AWS",SUMMARY!C$26%, 0) -> 0.13 | O46: =((SUM(K46:L46))-((SUM(K46:L46))*N46))*(1 + M46) -> 28.06272 | P46: =O46*12 -> 336.75264
H47: =IF(G46="Windows Server", "F:\appdir", "/appdir") -> F:\appdir | I47: =CEILING(I21*(100+SUMMARY!$C$24)%,1) -> 0
H48: =IF(G46="Windows Server", "G:\Log", "/var/log") -> G:\Log | I48: =IF(G46="Windows Server", 50, 20) -> 50
H49: =IF(G46="Windows Server", "H:\Backup", "/backup") -> H:\Backup | I49: =IF(G46="Windows Server", 100, 10) -> 100
B50: =((12*5*4)/(24*7*4))*730 -> 260.71429 | C50: AWS | E50: =CEILING(E24*(100+SUMMARY!$C$24)%,1) -> 0 | F50: =CEILING(F24*(100+SUMMARY!$C$24)%,1) -> 0 | G50: Windows Server | H50: =IF(G50="Windows Server", "C:\", "/") -> C:\ | I50: =IF(G50="Windows Server", 150, 20) -> 150 | J50: =SUM(I50:I53) -> 300 | K50: =J50 *(IF(C50="AZURE", SUMMARY!C$20, SUMMARY!C$21)) -> 28.8 | M50: =IF(C50="ON PREM", 0, SUMMARY!C$25%) -> 0.12 | N50: =IF(C50="AWS",SUMMARY!C$26%, 0) -> 0.13 | O50: =((SUM(K50:L50))-((SUM(K50:L50))*N50))*(1 + M50) -> 28.06272 | P50: =O50*12 -> 336.75264
H51: =IF(G50="Windows Server", "F:\appdir", "/appdir") -> F:\appdir | I51: =CEILING(I25*(100+SUMMARY!$C$24)%,1) -> 0
H52: =IF(G50="Windows Server", "G:\Log", "/var/log") -> G:\Log | I52: =IF(G50="Windows Server", 50, 20) -> 50
H53: =IF(G50="Windows Server", "H:\Backup", "/backup") -> H:\Backup | I53: =IF(G50="Windows Server", 100, 10) -> 100
E54: =SUM(E30:E53) -> 0 | F54: =SUM(F30:F53) -> 0 | J54: =SUM(J30:J53) -> 1550 | K54: =SUM(K30:K53) -> 148.8 | L54: =SUM(L30:L53) -> 0 | O54: =SUM(O30:O53) -> 144.99072 | P54: =SUM(P30:P53) -> 1739.8886
A55: YEAR 3
B56: =((12*5*4)/(24*7*4))*730 -> 260.71429 | C56: EXACC | E56: =CEILING(E30*(100+SUMMARY!$C$24)%,1) -> 0 | F56: =CEILING(F30*(100+SUMMARY!$C$24)%,1) -> 0 | G56: Windows Server | H56: =IF(G56="Windows Server", "C:\", "/") -> C:\ | I56: =IF(G56="Windows Server", 150, 20) -> 150 | J56: =SUM(I56:I59) -> 300 | K56: =J56 *(IF(C56="AZURE", SUMMARY!C$20, SUMMARY!C$21)) -> 28.8 | M56: =IF(C56="ON PREM", 0, SUMMARY!C$25%) -> 0.12 | N56: =IF(C56="AWS",SUMMARY!C$26%, 0) -> 0 | O56: =((SUM(K56:L56))-((SUM(K56:L56))*N56))*(1 + M56) -> 32.256 | P56: =O56*12 -> 387.072
H57: =IF(G56="Windows Server", "F:\appdir", "/appdir") -> F:\appdir | I57: =CEILING(I31*(100+SUMMARY!$C$24)%,1) -> 0
H58: =IF(G56="Windows Server", "G:\Log", "/var/log") -> G:\Log | I58: =IF(G56="Windows Server", 50, 20) -> 50
H59: =IF(G56="Windows Server", "H:\Backup", "/backup") -> H:\Backup | I59: =IF(G56="Windows Server", 100, 10) -> 100
B60: =((12*5*4)/(24*7*4))*730 -> 260.71429 | C60: ON PREM | E60: =CEILING(E34*(100+SUMMARY!$C$24)%,1) -> 0 | F60: =CEILING(F34*(100+SUMMARY!$C$24)%,1) -> 0 | G60: Ubuntu | H60: =IF(G60="Windows Server", "C:\", "/") -> / | I60: =IF(G60="Windows Server", 150, 20) -> 20 | J60: =SUM(I60:I63) -> 50 | K60: =J60 *(IF(C60="AZURE", SUMMARY!C$20, SUMMARY!C$21)) -> 4.8 | M60: =IF(C60="ON PREM", 0, SUMMARY!C$25%) -> 0 | N60: =IF(C60="AWS",SUMMARY!C$26%, 0) -> 0 | O60: =((SUM(K60:L60))-((SUM(K60:L60))*N60))*(1 + M60) -> 4.8 | P60: =O60*12 -> 57.6
H61: =IF(G60="Windows Server", "F:\appdir", "/appdir") -> /appdir | I61: =CEILING(I35*(100+SUMMARY!$C$24)%,1) -> 0
H62: =IF(G60="Windows Server", "G:\Log", "/var/log") -> /var/log | I62: =IF(G60="Windows Server", 50, 20) -> 20
H63: =IF(G60="Windows Server", "H:\Backup", "/backup") -> /backup | I63: =IF(G60="Windows Server", 100, 10) -> 10
B64: =((12*5*4)/(24*7*4))*730 -> 260.71429 | C64: EXACC | E64: =CEILING(E38*(100+SUMMARY!$C$24)%,1) -> 0 | F64: =CEILING(F38*(100+SUMMARY!$C$24)%,1) -> 0 | G64: Windows Server | H64: =IF(G64="Windows Server", "C:\", "/") -> C:\ | I64: =IF(G64="Windows Server", 150, 20) -> 150 | J64: =SUM(I64:I67) -> 300 | K64: =J64 *(IF(C64="AZURE", SUMMARY!C$20, SUMMARY!C$21)) -> 28.8 | M64: =IF(C64="ON PREM", 0, SUMMARY!C$25%) -> 0.12 | N64: =IF(C64="AWS",SUMMARY!C$26%, 0) -> 0 | O64: =((SUM(K64:L64))-((SUM(K64:L64))*N64))*(1 + M64) -> 32.256 | P64: =O64*12 -> 387.072
H65: =IF(G64="Windows Server", "F:\appdir", "/appdir") -> F:\appdir | I65: =CEILING(I39*(100+SUMMARY!$C$24)%,1) -> 0
H66: =IF(G64="Windows Server", "G:\Log", "/var/log") -> G:\Log | I66: =IF(G64="Windows Server", 50, 20) -> 50
H67: =IF(G64="Windows Server", "H:\Backup", "/backup") -> H:\Backup | I67: =IF(G64="Windows Server", 100, 10) -> 100
B68: =((12*5*4)/(24*7*4))*730 -> 260.71429 | C68: EXACC | E68: =CEILING(E42*(100+SUMMARY!$C$24)%,1) -> 0 | F68: =CEILING(F42*(100+SUMMARY!$C$24)%,1) -> 0 | G68: Oracle Linux | H68: =IF(G68="Windows Server", "C:\", "/") -> / | I68: =IF(G68="Windows Server", 150, 20) -> 20 | J68: =SUM(I68:I71) -> 50 | K68: =J68 *(IF(C68="AZURE", SUMMARY!C$20, SUMMARY!C$21)) -> 4.8 | M68: =IF(C68="ON PREM", 0, SUMMARY!C$25%) -> 0.12 | N68: =IF(C68="AWS",SUMMARY!C$26%, 0) -> 0 | O68: =((SUM(K68:L68))-((SUM(K68:L68))*N68))*(1 + M68) -> 5.376 | P68: =O68*12 -> 64.512
H69: =IF(G68="Windows Server", "F:\appdir", "/appdir") -> /appdir | I69: =CEILING(I43*(100+SUMMARY!$C$24)%,1) -> 0
H70: =IF(G68="Windows Server", "G:\Log", "/var/log") -> /var/log | I70: =IF(G68="Windows Server", 50, 20) -> 20
H71: =IF(G68="Windows Server", "H:\Backup", "/backup") -> /backup | I71: =IF(G68="Windows Server", 100, 10) -> 10
B72: =((12*5*4)/(24*7*4))*730 -> 260.71429 | C72: EXACC | E72: =CEILING(E46*(100+SUMMARY!$C$24)%,1) -> 0 | F72: =CEILING(F46*(100+SUMMARY!$C$24)%,1) -> 0 | G72: Ubuntu | H72: =IF(G72="Windows Server", "C:\", "/") -> / | I72: =IF(G72="Windows Server", 150, 20) -> 20 | J72: =SUM(I72:I75) -> 50 | K72: =J72 *(IF(C72="AZURE", SUMMARY!C$20, SUMMARY!C$21)) -> 4.8 | M72: =IF(C72="ON PREM", 0, SUMMARY!C$25%) -> 0.12 | N72: =IF(C72="AWS",SUMMARY!C$26%, 0) -> 0 | O72: =((SUM(K72:L72))-((SUM(K72:L72))*N72))*(1 + M72) -> 5.376 | P72: =O72*12 -> 64.512
H73: =IF(G72="Windows Server", "F:\appdir", "/appdir") -> /appdir | I73: =CEILING(I47*(100+SUMMARY!$C$24)%,1) -> 0
H74: =IF(G72="Windows Server", "G:\Log", "/var/log") -> /var/log | I74: =IF(G72="Windows Server", 50, 20) -> 20
H75: =IF(G72="Windows Server", "H:\Backup", "/backup") -> /backup | I75: =IF(G72="Windows Server", 100, 10) -> 10
B76: =((12*5*4)/(24*7*4))*730 -> 260.71429 | C76: EXACC | E76: =CEILING(E50*(100+SUMMARY!$C$24)%,1) -> 0 | F76: =CEILING(F50*(100+SUMMARY!$C$24)%,1) -> 0 | G76: Windows Server | H76: =IF(G76="Windows Server", "C:\", "/") -> C:\ | I76: =IF(G76="Windows Server", 150, 20) -> 150 | J76: =SUM(I76:I79) -> 300 | K76: =J76 *(IF(C76="AZURE", SUMMARY!C$20, SUMMARY!C$21)) -> 28.8 | M76: =IF(C76="ON PREM", 0, SUMMARY!C$25%) -> 0.12 | N76: =IF(C76="AWS",SUMMARY!C$26%, 0) -> 0 | O76: =((SUM(K76:L76))-((SUM(K76:L76))*N76))*(1 + M76) -> 32.256 | P76: =O76*12 -> 387.072
H77: =IF(G76="Windows Server", "F:\appdir", "/appdir") -> F:\appdir | I77: =CEILING(I51*(100+SUMMARY!$C$24)%,1) -> 0
H78: =IF(G76="Windows Server", "G:\Log", "/var/log") -> G:\Log | I78: =IF(G76="Windows Server", 50, 20) -> 50
H79: =IF(G76="Windows Server", "H:\Backup", "/backup") -> H:\Backup | I79: =IF(G76="Windows Server", 100, 10) -> 100
E80: =SUM(E56:E79) -> 0 | F80: =SUM(F56:F79) -> 0 | J80: =SUM(J56:J79) -> 1050 | K80: =SUM(K56:K79) -> 100.8 | L80: =SUM(L56:L79) -> 0 | O80: =SUM(O56:O79) -> 112.32 | P80: =SUM(P56:P79) -> 1347.84
A81: YEAR 4
B82: =((12*5*4)/(24*7*4))*730 -> 260.71429 | C82: AWS | E82: =CEILING(E56*(100+SUMMARY!$C$24)%,1) -> 0 | F82: =CEILING(F56*(100+SUMMARY!$C$24)%,1) -> 0 | G82: Windows Server | H82: =IF(G82="Windows Server", "C:\", "/") -> C:\ | I82: =IF(G82="Windows Server", 150, 20) -> 150 | J82: =SUM(I82:I85) -> 300 | K82: =J82 *(IF(C82="AZURE", SUMMARY!C$20, SUMMARY!C$21)) -> 28.8 | M82: =IF(C82="ON PREM", 0, SUMMARY!C$25%) -> 0.12 | N82: =IF(C82="AWS",SUMMARY!C$26%, 0) -> 0.13 | O82: =((SUM(K82:L82))-((SUM(K82:L82))*N82))*(1 + M82) -> 28.06272 | P82: =O82*12 -> 336.75264
H83: =IF(G82="Windows Server", "F:\appdir", "/appdir") -> F:\appdir | I83: =CEILING(I57*(100+SUMMARY!$C$24)%,1) -> 0
H84: =IF(G82="Windows Server", "G:\Log", "/var/log") -> G:\Log | I84: =IF(G82="Windows Server", 50, 20) -> 50
H85: =IF(G82="Windows Server", "H:\Backup", "/backup") -> H:\Backup | I85: =IF(G82="Windows Server", 100, 10) -> 100
B86: =((12*5*4)/(24*7*4))*730 -> 260.71429 | C86: AWS | E86: =CEILING(E60*(100+SUMMARY!$C$24)%,1) -> 0 | F86: =CEILING(F60*(100+SUMMARY!$C$24)%,1) -> 0 | G86: RHEL | H86: =IF(G86="Windows Server", "C:\", "/") -> / | I86: =IF(G86="Windows Server", 150, 20) -> 20 | J86: =SUM(I86:I89) -> 50 | K86: =J86 *(IF(C86="AZURE", SUMMARY!C$20, SUMMARY!C$21)) -> 4.8 | M86: =IF(C86="ON PREM", 0, SUMMARY!C$25%) -> 0.12 | N86: =IF(C86="AWS",SUMMARY!C$26%, 0) -> 0.13 | O86: =((SUM(K86:L86))-((SUM(K86:L86))*N86))*(1 + M86) -> 4.67712 | P86: =O86*12 -> 56.12544
H87: =IF(G86="Windows Server", "F:\appdir", "/appdir") -> /appdir | I87: =CEILING(I61*(100+SUMMARY!$C$24)%,1) -> 0
H88: =IF(G86="Windows Server", "G:\Log", "/var/log") -> /var/log | I88: =IF(G86="Windows Server", 50, 20) -> 20
H89: =IF(G86="Windows Server", "H:\Backup", "/backup") -> /backup | I89: =IF(G86="Windows Server", 100, 10) -> 10
B90: =((12*5*4)/(24*7*4))*730 -> 260.71429 | C90: AWS | E90: =CEILING(E64*(100+SUMMARY!$C$24)%,1) -> 0 | F90: =CEILING(F64*(100+SUMMARY!$C$24)%,1) -> 0 | G90: Windows Server | H90: =IF(G90="Windows Server", "C:\", "/") -> C:\ | I90: =IF(G90="Windows Server", 150, 20) -> 150 | J90: =SUM(I90:I93) -> 300 | K90: =J90 *(IF(C90="AZURE", SUMMARY!C$20, SUMMARY!C$21)) -> 28.8 | M90: =IF(C90="ON PREM", 0, SUMMARY!C$25%) -> 0.12 | N90: =IF(C90="AWS",SUMMARY!C$26%, 0) -> 0.13 | O90: =((SUM(K90:L90))-((SUM(K90:L90))*N90))*(1 + M90) -> 28.06272 | P90: =O90*12 -> 336.75264
H91: =IF(G90="Windows Server", "F:\appdir", "/appdir") -> F:\appdir | I91: =CEILING(I65*(100+SUMMARY!$C$24)%,1) -> 0
H92: =IF(G90="Windows Server", "G:\Log", "/var/log") -> G:\Log | I92: =IF(G90="Windows Server", 50, 20) -> 50
H93: =IF(G90="Windows Server", "H:\Backup", "/backup") -> H:\Backup | I93: =IF(G90="Windows Server", 100, 10) -> 100
B94: =((12*5*4)/(24*7*4))*730 -> 260.71429 | C94: AWS | E94: =CEILING(E68*(100+SUMMARY!$C$24)%,1) -> 0 | F94: =CEILING(F68*(100+SUMMARY!$C$24)%,1) -> 0 | G94: Windows Server | H94: =IF(G94="Windows Server", "C:\", "/") -> C:\ | I94: =IF(G94="Windows Server", 150, 20) -> 150 | J94: =SUM(I94:I97) -> 300 | K94: =J94 *(IF(C94="AZURE", SUMMARY!C$20, SUMMARY!C$21)) -> 28.8 | M94: =IF(C94="ON PREM", 0, SUMMARY!C$25%) -> 0.12 | N94: =IF(C94="AWS",SUMMARY!C$26%, 0) -> 0.13 | O94: =((SUM(K94:L94))-((SUM(K94:L94))*N94))*(1 + M94) -> 28.06272 | P94: =O94*12 -> 336.75264
H95: =IF(G94="Windows Server", "F:\appdir", "/appdir") -> F:\appdir | I95: =CEILING(I69*(100+SUMMARY!$C$24)%,1) -> 0
H96: =IF(G94="Windows Server", "G:\Log", "/var/log") -> G:\Log | I96: =IF(G94="Windows Server", 50, 20) -> 50
H97: =IF(G94="Windows Server", "H:\Backup", "/backup") -> H:\Backup | I97: =IF(G94="Windows Server", 100, 10) -> 100
B98: =((12*5*4)/(24*7*4))*730 -> 260.71429 | C98: AWS | E98: =CEILING(E72*(100+SUMMARY!$C$24)%,1) -> 0 | F98: =CEILING(F72*(100+SUMMARY!$C$24)%,1) -> 0 | G98: Windows Server | H98: =IF(G98="Windows Server", "C:\", "/") -> C:\ | I98: =IF(G98="Windows Server", 150, 20) -> 150 | J98: =SUM(I98:I101) -> 300 | K98: =J98 *(IF(C98="AZURE", SUMMARY!C$20, SUMMARY!C$21)) -> 28.8 | M98: =IF(C98="ON PREM", 0, SUMMARY!C$25%) -> 0.12 | N98: =IF(C98="AWS",SUMMARY!C$26%, 0) -> 0.13 | O98: =((SUM(K98:L98))-((SUM(K98:L98))*N98))*(1 + M98) -> 28.06272 | P98: =O98*12 -> 336.75264
H99: =IF(G98="Windows Server", "F:\appdir", "/appdir") -> F:\appdir | I99: =CEILING(I73*(100+SUMMARY!$C$24)%,1) -> 0
H100: =IF(G98="Windows Server", "G:\Log", "/var/log") -> G:\Log | I100: =IF(G98="Windows Server", 50, 20) -> 50
...

Sheet Pre-Prod
A1: UAT ENVIRONMENT (to be filled out by servicing unit)
A2: YEAR 1
A3: Description | B3: Hours | C3: Cloud Platform | D3: Instance Type, Specs | E3: CPU | F3: Memory (GB) | G3: Operating System | H3: Disk Space Description (Size in GB) | J3: Disk Space (GB) | K3: Monthly EBS Volume Cost ($) | L3: Monthly Subscription Cost ($) | M3: VAT | N3: Enterprise Discount | O3: Total Monthly Cost ($) | P3: Total Annual Cost ($)
B4: =((12*5*4)/(24*7*4))*730 -> 260.71429 | C4: EXACC | G4: Ubuntu | H4: =IF(G4="Windows Server", "C:\", "/") -> / | I4: =IF(G4="Windows Server", 150, 20) -> 20 | J4: =SUM(I4:I7) -> 50 | K4: =J4 *(IF(C4="AZURE", SUMMARY!C$20, SUMMARY!C$21)) -> 4.8 | M4: =IF(C4="ON PREM", 0, SUMMARY!C$25%) -> 0.12 | N4: =IF(C4="AWS",SUMMARY!C$26%, 0) -> 0 | O4: =((SUM(K4:L4))-((SUM(K4:L4))*N4))*(1 + M4) -> 5.376 | P4: =O4*12 -> 64.512
H5: =IF(G4="Windows Server", "F:\appdir", "/appdir") -> /appdir
H6: =IF(G4="Windows Server", "G:\Log", "/var/log") -> /var/log | I6: =IF(G4="Windows Server", 50, 20) -> 20
H7: =IF(G4="Windows Server", "H:\Backup", "/backup") -> /backup | I7: =IF(G4="Windows Server", 100, 10) -> 10
B8: =((12*5*4)/(24*7*4))*730 -> 260.71429 | C8: ON PREM | G8: RHEL | H8: =IF(G8="Windows Server", "C:\", "/") -> / | I8: =IF(G8="Windows Server", 150, 20) -> 20 | J8: =SUM(I8:I11) -> 50 | K8: =J8 *(IF(C8="AZURE", SUMMARY!C$20, SUMMARY!C$21)) -> 4.8 | M8: =IF(C8="ON PREM", 0, SUMMARY!C$25%) -> 0 | N8: =IF(C8="AWS",SUMMARY!C$26%, 0) -> 0 | O8: =((SUM(K8:L8))-((SUM(K8:L8))*N8))*(1 + M8) -> 4.8 | P8: =O8*12 -> 57.6
H9: =IF(G8="Windows Server", "F:\appdir", "/appdir") -> /appdir
H10: =IF(G8="Windows Server", "G:\Log", "/var/log") -> /var/log | I10: =IF(G8="Windows Server", 50, 20) -> 20
H11: =IF(G8="Windows Server", "H:\Backup", "/backup") -> /backup | I11: =IF(G8="Windows Server", 100, 10) -> 10
B12: =((12*5*4)/(24*7*4))*730 -> 260.71429 | C12: EXACC | G12: Oracle Linux | H12: =IF(G12="Windows Server", "C:\", "/") -> / | I12: =IF(G12="Windows Server", 150, 20) -> 20 | J12: =SUM(I12:I15) -> 50 | K12: =J12 *(IF(C12="AZURE", SUMMARY!C$20, SUMMARY!C$21)) -> 4.8 | M12: =IF(C12="ON PREM", 0, SUMMARY!C$25%) -> 0.12 | N12: =IF(C12="AWS",SUMMARY!C$26%, 0) -> 0 | O12: =((SUM(K12:L12))-((SUM(K12:L12))*N12))*(1 + M12) -> 5.376 | P12: =O12*12 -> 64.512
H13: =IF(G12="Windows Server", "F:\appdir", "/appdir") -> /appdir
H14: =IF(G12="Windows Server", "G:\Log", "/var/log") -> /var/log | I14: =IF(G12="Windows Server", 50, 20) -> 20
H15: =IF(G12="Windows Server", "H:\Backup", "/backup") -> /backup | I15: =IF(G12="Windows Server", 100, 10) -> 10
B16: =((12*5*4)/(24*7*4))*730 -> 260.71429 | C16: EXACC | G16: Oracle Linux | H16: =IF(G16="Windows Server", "C:\", "/") -> / | I16: =IF(G16="Windows Server", 150, 20) -> 20 | J16: =SUM(I16:I19) -> 50 | K16: =J16 *(IF(C16="AZURE", SUMMARY!C$20, SUMMARY!C$21)) -> 4.8 | M16: =IF(C16="ON PREM", 0, SUMMARY!C$25%) -> 0.12 | N16: =IF(C16="AWS",SUMMARY!C$26%, 0) -> 0 | O16: =((SUM(K16:L16))-((SUM(K16:L16))*N16))*(1 + M16) -> 5.376 | P16: =O16*12 -> 64.512
H17: =IF(G16="Windows Server", "F:\appdir", "/appdir") -> /appdir
H18: =IF(G16="Windows Server", "G:\Log", "/var/log") -> /var/log | I18: =IF(G16="Windows Server", 50, 20) -> 20
H19: =IF(G16="Windows Server", "H:\Backup", "/backup") -> /backup | I19: =IF(G16="Windows Server", 100, 10) -> 10
B20: =((12*5*4)/(24*7*4))*730 -> 260.71429 | C20: EXACC | G20: Ubuntu | H20: =IF(G20="Windows Server", "C:\", "/") -> / | I20: =IF(G20="Windows Server", 150, 20) -> 20 | J20: =SUM(I20:I23) -> 50 | K20: =J20 *(IF(C20="AZURE", SUMMARY!C$20, SUMMARY!C$21)) -> 4.8 | M20: =IF(C20="ON PREM", 0, SUMMARY!C$25%) -> 0.12 | N20: =IF(C20="AWS",SUMMARY!C$26%, 0) -> 0 | O20: =((SUM(K20:L20))-((SUM(K20:L20))*N20))*(1 + M20) -> 5.376 | P20: =O20*12 -> 64.512
H21: =IF(G20="Windows Server", "F:\appdir", "/appdir") -> /appdir
H22: =IF(G20="Windows Server", "G:\Log", "/var/log") -> /var/log | I22: =IF(G20="Windows Server", 50, 20) -> 20
H23: =IF(G20="Windows Server", "H:\Backup", "/backup") -> /backup | I23: =IF(G20="Windows Server", 100, 10) -> 10
B24: =((12*5*4)/(24*7*4))*730 -> 260.71429 | C24: EXACC | G24: RHEL | H24: =IF(G24="Windows Server", "C:\", "/") -> / | I24: =IF(G24="Windows Server", 150, 20) -> 20 | J24: =SUM(I24:I27) -> 50 | K24: =J24 *(IF(C24="AZURE", SUMMARY!C$20, SUMMARY!C$21)) -> 4.8 | M24: =IF(C24="ON PREM", 0, SUMMARY!C$25%) -> 0.12 | N24: =IF(C24="AWS",SUMMARY!C$26%, 0) -> 0 | O24: =((SUM(K24:L24))-((SUM(K24:L24))*N24))*(1 + M24) -> 5.376 | P24: =O24*12 -> 64.512
H25: =IF(G24="Windows Server", "F:\appdir", "/appdir") -> /appdir
H26: =IF(G24="Windows Server", "G:\Log", "/var/log") -> /var/log | I26: =IF(G24="Windows Server", 50, 20) -> 20
H27: =IF(G24="Windows Server", "H:\Backup", "/backup") -> /backup | I27: =IF(G24="Windows Server", 100, 10) -> 10
E28: =SUM(E4:E27) -> 0 | F28: =SUM(F4:F27) -> 0 | J28: =SUM(J4:J27) -> 300 | K28: =SUM(K4:K27) -> 28.8 | L28: =SUM(L4:L27) -> 0 | O28: =SUM(O4:O27) -> 31.68 | P28: =SUM(P4:P27) -> 380.16
A29: YEAR 2
B30: =((12*5*4)/(24*7*4))*730 -> 260.71429 | C30: AWS | E30: =CEILING(E4*(100+SUMMARY!$C$24)%,1) -> 0 | F30: =CEILING(F4*(100+SUMMARY!$C$24)%,1) -> 0 | G30: Windows Server | H30: =IF(G30="Windows Server", "C:\", "/") -> C:\ | I30: =IF(G30="Windows Server", 150, 20) -> 150 | J30: =SUM(I30:I33) -> 300 | K30: =J30 *(IF(C30="AZURE", SUMMARY!C$20, SUMMARY!C$21)) -> 28.8 | M30: =IF(C30="ON PREM", 0, SUMMARY!C$25%) -> 0.12 | N30: =IF(C30="AWS",SUMMARY!C$26%, 0) -> 0.13 | O30: =((SUM(K30:L30))-((SUM(K30:L30))*N30))*(1 + M30) -> 28.06272 | P30: =O30*12 -> 336.75264
H31: =IF(G30="Windows Server", "F:\appdir", "/appdir") -> F:\appdir | I31: =CEILING(I5*(100+SUMMARY!$C$24)%,1) -> 0
H32: =IF(G30="Windows Server", "G:\Log", "/var/log") -> G:\Log | I32: =IF(G30="Windows Server", 50, 20) -> 50
H33: =IF(G30="Windows Server", "H:\Backup", "/backup") -> H:\Backup | I33: =IF(G30="Windows Server", 100, 10) -> 100
B34: =((12*5*4)/(24*7*4))*730 -> 260.71429 | C34: AWS | E34: =CEILING(E8*(100+SUMMARY!$C$24)%,1) -> 0 | F34: =CEILING(F8*(100+SUMMARY!$C$24)%,1) -> 0 | G34: RHEL | H34: =IF(G34="Windows Server", "C:\", "/") -> / | I34: =IF(G34="Windows Server", 150, 20) -> 20 | J34: =SUM(I34:I37) -> 50 | K34: =J34 *(IF(C34="AZURE", SUMMARY!C$20, SUMMARY!C$21)) -> 4.8 | M34: =IF(C34="ON PREM", 0, SUMMARY!C$25%) -> 0.12 | N34: =IF(C34="AWS",SUMMARY!C$26%, 0) -> 0.13 | O34: =((SUM(K34:L34))-((SUM(K34:L34))*N34))*(1 + M34) -> 4.67712 | P34: =O34*12 -> 56.12544
H35: =IF(G34="Windows Server", "F:\appdir", "/appdir") -> /appdir | I35: =CEILING(I9*(100+SUMMARY!$C$24)%,1) -> 0
H36: =IF(G34="Windows Server", "G:\Log", "/var/log") -> /var/log | I36: =IF(G34="Windows Server", 50, 20) -> 20
H37: =IF(G34="Windows Server", "H:\Backup", "/backup") -> /backup | I37: =IF(G34="Windows Server", 100, 10) -> 10
B38: =((12*5*4)/(24*7*4))*730 -> 260.71429 | C38: AWS | E38: =CEILING(E12*(100+SUMMARY!$C$24)%,1) -> 0 | F38: =CEILING(F12*(100+SUMMARY!$C$24)%,1) -> 0 | G38: Windows Server | H38: =IF(G38="Windows Server", "C:\", "/") -> C:\ | I38: =IF(G38="Windows Server", 150, 20) -> 150 | J38: =SUM(I38:I41) -> 300 | K38: =J38 *(IF(C38="AZURE", SUMMARY!C$20, SUMMARY!C$21)) -> 28.8 | M38: =IF(C38="ON PREM", 0, SUMMARY!C$25%) -> 0.12 | N38: =IF(C38="AWS",SUMMARY!C$26%, 0) -> 0.13 | O38: =((SUM(K38:L38))-((SUM(K38:L38))*N38))*(1 + M38) -> 28.06272 | P38: =O38*12 -> 336.75264
H39: =IF(G38="Windows Server", "F:\appdir", "/appdir") -> F:\appdir | I39: =CEILING(I13*(100+SUMMARY!$C$24)%,1) -> 0
H40: =IF(G38="Windows Server", "G:\Log", "/var/log") -> G:\Log | I40: =IF(G38="Windows Server", 50, 20) -> 50
H41: =IF(G38="Windows Server", "H:\Backup", "/backup") -> H:\Backup | I41: =IF(G38="Windows Server", 100, 10) -> 100
B42: =((12*5*4)/(24*7*4))*730 -> 260.71429 | C42: AWS | E42: =CEILING(E16*(100+SUMMARY!$C$24)%,1) -> 0 | F42: =CEILING(F16*(100+SUMMARY!$C$24)%,1) -> 0 | G42: Windows Server | H42: =IF(G42="Windows Server", "C:\", "/") -> C:\ | I42: =IF(G42="Windows Server", 150, 20) -> 150 | J42: =SUM(I42:I45) -> 300 | K42: =J42 *(IF(C42="AZURE", SUMMARY!C$20, SUMMARY!C$21)) -> 28.8 | M42: =IF(C42="ON PREM", 0, SUMMARY!C$25%) -> 0.12 | N42: =IF(C42="AWS",SUMMARY!C$26%, 0) -> 0.13 | O42: =((SUM(K42:L42))-((SUM(K42:L42))*N42))*(1 + M42) -> 28.06272 | P42: =O42*12 -> 336.75264
H43: =IF(G42="Windows Server", "F:\appdir", "/appdir") -> F:\appdir | I43: =CEILING(I17*(100+SUMMARY!$C$24)%,1) -> 0
H44: =IF(G42="Windows Server", "G:\Log", "/var/log") -> G:\Log | I44: =IF(G42="Windows Server", 50, 20) -> 50
H45: =IF(G42="Windows Server", "H:\Backup", "/backup") -> H:\Backup | I45: =IF(G42="Windows Server", 100, 10) -> 100
B46: =((12*5*4)/(24*7*4))*730 -> 260.71429 | C46: AWS | E46: =CEILING(E20*(100+SUMMARY!$C$24)%,1) -> 0 | F46: =CEILING(F20*(100+SUMMARY!$C$24)%,1) -> 0 | G46: Windows Server | H46: =IF(G46="Windows Server", "C:\", "/") -> C:\ | I46: =IF(G46="Windows Server", 150, 20) -> 150 | J46: =SUM(I46:I49) -> 300 | K46: =J46 *(IF(C46="AZURE", SUMMARY!C$20, SUMMARY!C$21)) -> 28.8 | M46: =IF(C46="ON PREM", 0, SUMMARY!C$25%) -> 0.12 | N46: =IF(C46="AWS",SUMMARY!C$26%, 0) -> 0.13 | O46: =((SUM(K46:L46))-((SUM(K46:L46))*N46))*(1 + M46) -> 28.06272 | P46: =O46*12 -> 336.75264
H47: =IF(G46="Windows Server", "F:\appdir", "/appdir") -> F:\appdir | I47: =CEILING(I21*(100+SUMMARY!$C$24)%,1) -> 0
H48: =IF(G46="Windows Server", "G:\Log", "/var/log") -> G:\Log | I48: =IF(G46="Windows Server", 50, 20) -> 50
H49: =IF(G46="Windows Server", "H:\Backup", "/backup") -> H:\Backup | I49: =IF(G46="Windows Server", 100, 10) -> 100
B50: =((12*5*4)/(24*7*4))*730 -> 260.71429 | C50: AWS | E50: =CEILING(E24*(100+SUMMARY!$C$24)%,1) -> 0 | F50: =CEILING(F24*(100+SUMMARY!$C$24)%,1) -> 0 | G50: Windows Server | H50: =IF(G50="Windows Server", "C:\", "/") -> C:\ | I50: =IF(G50="Windows Server", 150, 20) -> 150 | J50: =SUM(I50:I53) -> 300 | K50: =J50 *(IF(C50="AZURE", SUMMARY!C$20, SUMMARY!C$21)) -> 28.8 | M50: =IF(C50="ON PREM", 0, SUMMARY!C$25%) -> 0.12 | N50: =IF(C50="AWS",SUMMARY!C$26%, 0) -> 0.13 | O50: =((SUM(K50:L50))-((SUM(K50:L50))*N50))*(1 + M50) -> 28.06272 | P50: =O50*12 -> 336.75264
H51: =IF(G50="Windows Server", "F:\appdir", "/appdir") -> F:\appdir | I51: =CEILING(I25*(100+SUMMARY!$C$24)%,1) -> 0
H52: =IF(G50="Windows Server", "G:\Log", "/var/log") -> G:\Log | I52: =IF(G50="Windows Server", 50, 20) -> 50
H53: =IF(G50="Windows Server", "H:\Backup", "/backup") -> H:\Backup | I53: =IF(G50="Windows Server", 100, 10) -> 100
E54: =SUM(E30:E53) -> 0 | F54: =SUM(F30:F53) -> 0 | J54: =SUM(J30:J53) -> 1550 | K54: =SUM(K30:K53) -> 148.8 | L54: =SUM(L30:L53) -> 0 | O54: =SUM(O30:O53) -> 144.99072 | P54: =SUM(P30:P53) -> 1739.8886
A55: YEAR 3
B56: =((12*5*4)/(24*7*4))*730 -> 260.71429 | C56: EXACC | E56: =CEILING(E30*(100+SUMMARY!$C$24)%,1) -> 0 | F56: =CEILING(F30*(100+SUMMARY!$C$24)%,1) -> 0 | G56: Windows Server | H56: =IF(G56="Windows Server", "C:\", "/") -> C:\ | I56: =IF(G56="Windows Server", 150, 20) -> 150 | J56: =SUM(I56:I59) -> 300 | K56: =J56 *(IF(C56="AZURE", SUMMARY!C$20, SUMMARY!C$21)) -> 28.8 | M56: =IF(C56="ON PREM", 0, SUMMARY!C$25%) -> 0.12 | N56: =IF(C56="AWS",SUMMARY!C$26%, 0) -> 0 | O56: =((SUM(K56:L56))-((SUM(K56:L56))*N56))*(1 + M56) -> 32.256 | P56: =O56*12 -> 387.072
H57: =IF(G56="Windows Server", "F:\appdir", "/appdir") -> F:\appdir | I57: =CEILING(I31*(100+SUMMARY!$C$24)%,1) -> 0
H58: =IF(G56="Windows Server", "G:\Log", "/var/log") -> G:\Log | I58: =IF(G56="Windows Server", 50, 20) -> 50
H59: =IF(G56="Windows Server", "H:\Backup", "/backup") -> H:\Backup | I59: =IF(G56="Windows Server", 100, 10) -> 100
B60: =((12*5*4)/(24*7*4))*730 -> 260.71429 | C60: ON PREM | E60: =CEILING(E34*(100+SUMMARY!$C$24)%,1) -> 0 | F60: =CEILING(F34*(100+SUMMARY!$C$24)%,1) -> 0 | G60: Ubuntu | H60: =IF(G60="Windows Server", "C:\", "/") -> / | I60: =IF(G60="Windows Server", 150, 20) -> 20 | J60: =SUM(I60:I63) -> 50 | K60: =J60 *(IF(C60="AZURE", SUMMARY!C$20, SUMMARY!C$21)) -> 4.8 | M60: =IF(C60="ON PREM", 0, SUMMARY!C$25%) -> 0 | N60: =IF(C60="AWS",SUMMARY!C$26%, 0) -> 0 | O60: =((SUM(K60:L60))-((SUM(K60:L60))*N60))*(1 + M60) -> 4.8 | P60: =O60*12 -> 57.6
H61: =IF(G60="Windows Server", "F:\appdir", "/appdir") -> /appdir | I61: =CEILING(I35*(100+SUMMARY!$C$24)%,1) -> 0
H62: =IF(G60="Windows Server", "G:\Log", "/var/log") -> /var/log | I62: =IF(G60="Windows Server", 50, 20) -> 20
H63: =IF(G60="Windows Server", "H:\Backup", "/backup") -> /backup | I63: =IF(G60="Windows Server", 100, 10) -> 10
B64: =((12*5*4)/(24*7*4))*730 -> 260.71429 | C64: EXACC | E64: =CEILING(E38*(100+SUMMARY!$C$24)%,1) -> 0 | F64: =CEILING(F38*(100+SUMMARY!$C$24)%,1) -> 0 | G64: Windows Server | H64: =IF(G64="Windows Server", "C:\", "/") -> C:\ | I64: =IF(G64="Windows Server", 150, 20) -> 150 | J64: =SUM(I64:I67) -> 300 | K64: =J64 *(IF(C64="AZURE", SUMMARY!C$20, SUMMARY!C$21)) -> 28.8 | M64: =IF(C64="ON PREM", 0, SUMMARY!C$25%) -> 0.12 | N64: =IF(C64="AWS",SUMMARY!C$26%, 0) -> 0 | O64: =((SUM(K64:L64))-((SUM(K64:L64))*N64))*(1 + M64) -> 32.256 | P64: =O64*12 -> 387.072
H65: =IF(G64="Windows Server", "F:\appdir", "/appdir") -> F:\appdir | I65: =CEILING(I39*(100+SUMMARY!$C$24)%,1) -> 0
H66: =IF(G64="Windows Server", "G:\Log", "/var/log") -> G:\Log | I66: =IF(G64="Windows Server", 50, 20) -> 50
H67: =IF(G64="Windows Server", "H:\Backup", "/backup") -> H:\Backup | I67: =IF(G64="Windows Server", 100, 10) -> 100
B68: =((12*5*4)/(24*7*4))*730 -> 260.71429 | C68: EXACC | E68: =CEILING(E42*(100+SUMMARY!$C$24)%,1) -> 0 | F68: =CEILING(F42*(100+SUMMARY!$C$24)%,1) -> 0 | G68: Oracle Linux | H68: =IF(G68="Windows Server", "C:\", "/") -> / | I68: =IF(G68="Windows Server", 150, 20) -> 20 | J68: =SUM(I68:I71) -> 50 | K68: =J68 *(IF(C68="AZURE", SUMMARY!C$20, SUMMARY!C$21)) -> 4.8 | M68: =IF(C68="ON PREM", 0, SUMMARY!C$25%) -> 0.12 | N68: =IF(C68="AWS",SUMMARY!C$26%, 0) -> 0 | O68: =((SUM(K68:L68))-((SUM(K68:L68))*N68))*(1 + M68) -> 5.376 | P68: =O68*12 -> 64.512
H69: =IF(G68="Windows Server", "F:\appdir", "/appdir") -> /appdir | I69: =CEILING(I43*(100+SUMMARY!$C$24)%,1) -> 0
H70: =IF(G68="Windows Server", "G:\Log", "/var/log") -> /var/log | I70: =IF(G68="Windows Server", 50, 20) -> 20
H71: =IF(G68="Windows Server", "H:\Backup", "/backup") -> /backup | I71: =IF(G68="Windows Server", 100, 10) -> 10
B72: =((12*5*4)/(24*7*4))*730 -> 260.71429 | C72: EXACC | E72: =CEILING(E46*(100+SUMMARY!$C$24)%,1) -> 0 | F72: =CEILING(F46*(100+SUMMARY!$C$24)%,1) -> 0 | G72: Ubuntu | H72: =IF(G72="Windows Server", "C:\", "/") -> / | I72: =IF(G72="Windows Server", 150, 20) -> 20 | J72: =SUM(I72:I75) -> 50 | K72: =J72 *(IF(C72="AZURE", SUMMARY!C$20, SUMMARY!C$21)) -> 4.8 | M72: =IF(C72="ON PREM", 0, SUMMARY!C$25%) -> 0.12 | N72: =IF(C72="AWS",SUMMARY!C$26%, 0) -> 0 | O72: =((SUM(K72:L72))-((SUM(K72:L72))*N72))*(1 + M72) -> 5.376 | P72: =O72*12 -> 64.512
H73: =IF(G72="Windows Server", "F:\appdir", "/appdir") -> /appdir | I73: =CEILING(I47*(100+SUMMARY!$C$24)%,1) -> 0
H74: =IF(G72="Windows Server", "G:\Log", "/var/log") -> /var/log | I74: =IF(G72="Windows Server", 50, 20) -> 20
H75: =IF(G72="Windows Server", "H:\Backup", "/backup") -> /backup | I75: =IF(G72="Windows Server", 100, 10) -> 10
B76: =((12*5*4)/(24*7*4))*730 -> 260.71429 | C76: EXACC | E76: =CEILING(E50*(100+SUMMARY!$C$24)%,1) -> 0 | F76: =CEILING(F50*(100+SUMMARY!$C$24)%,1) -> 0 | G76: Windows Server | H76: =IF(G76="Windows Server", "C:\", "/") -> C:\ | I76: =IF(G76="Windows Server", 150, 20) -> 150 | J76: =SUM(I76:I79) -> 300 | K76: =J76 *(IF(C76="AZURE", SUMMARY!C$20, SUMMARY!C$21)) -> 28.8 | M76: =IF(C76="ON PREM", 0, SUMMARY!C$25%) -> 0.12 | N76: =IF(C76="AWS",SUMMARY!C$26%, 0) -> 0 | O76: =((SUM(K76:L76))-((SUM(K76:L76))*N76))*(1 + M76) -> 32.256 | P76: =O76*12 -> 387.072
H77: =IF(G76="Windows Server", "F:\appdir", "/appdir") -> F:\appdir | I77: =CEILING(I51*(100+SUMMARY!$C$24)%,1) -> 0
H78: =IF(G76="Windows Server", "G:\Log", "/var/log") -> G:\Log | I78: =IF(G76="Windows Server", 50, 20) -> 50
H79: =IF(G76="Windows Server", "H:\Backup", "/backup") -> H:\Backup | I79: =IF(G76="Windows Server", 100, 10) -> 100
E80: =SUM(E56:E79) -> 0 | F80: =SUM(F56:F79) -> 0 | J80: =SUM(J56:J79) -> 1050 | K80: =SUM(K56:K79) -> 100.8 | L80: =SUM(L56:L79) -> 0 | O80: =SUM(O56:O79) -> 112.32 | P80: =SUM(P56:P79) -> 1347.84
A81: YEAR 4
B82: =((12*5*4)/(24*7*4))*730 -> 260.71429 | C82: AWS | E82: =CEILING(E56*(100+SUMMARY!$C$24)%,1) -> 0 | F82: =CEILING(F56*(100+SUMMARY!$C$24)%,1) -> 0 | G82: Windows Server | H82: =IF(G82="Windows Server", "C:\", "/") -> C:\ | I82: =IF(G82="Windows Server", 150, 20) -> 150 | J82: =SUM(I82:I85) -> 300 | K82: =J82 *(IF(C82="AZURE", SUMMARY!C$20, SUMMARY!C$21)) -> 28.8 | M82: =IF(C82="ON PREM", 0, SUMMARY!C$25%) -> 0.12 | N82: =IF(C82="AWS",SUMMARY!C$26%, 0) -> 0.13 | O82: =((SUM(K82:L82))-((SUM(K82:L82))*N82))*(1 + M82) -> 28.06272 | P82: =O82*12 -> 336.75264
H83: =IF(G82="Windows Server", "F:\appdir", "/appdir") -> F:\appdir | I83: =CEILING(I57*(100+SUMMARY!$C$24)%,1) -> 0
H84: =IF(G82="Windows Server", "G:\Log", "/var/log") -> G:\Log | I84: =IF(G82="Windows Server", 50, 20) -> 50
H85: =IF(G82="Windows Server", "H:\Backup", "/backup") -> H:\Backup | I85: =IF(G82="Windows Server", 100, 10) -> 100
B86: =((12*5*4)/(24*7*4))*730 -> 260.71429 | C86: AWS | E86: =CEILING(E60*(100+SUMMARY!$C$24)%,1) -> 0 | F86: =CEILING(F60*(100+SUMMARY!$C$24)%,1) -> 0 | G86: RHEL | H86: =IF(G86="Windows Server", "C:\", "/") -> / | I86: =IF(G86="Windows Server", 150, 20) -> 20 | J86: =SUM(I86:I89) -> 50 | K86: =J86 *(IF(C86="AZURE", SUMMARY!C$20, SUMMARY!C$21)) -> 4.8 | M86: =IF(C86="ON PREM", 0, SUMMARY!C$25%) -> 0.12 | N86: =IF(C86="AWS",SUMMARY!C$26%, 0) -> 0.13 | O86: =((SUM(K86:L86))-((SUM(K86:L86))*N86))*(1 + M86) -> 4.67712 | P86: =O86*12 -> 56.12544
H87: =IF(G86="Windows Server", "F:\appdir", "/appdir") -> /appdir | I87: =CEILING(I61*(100+SUMMARY!$C$24)%,1) -> 0
H88: =IF(G86="Windows Server", "G:\Log", "/var/log") -> /var/log | I88: =IF(G86="Windows Server", 50, 20) -> 20
H89: =IF(G86="Windows Server", "H:\Backup", "/backup") -> /backup | I89: =IF(G86="Windows Server", 100, 10) -> 10
B90: =((12*5*4)/(24*7*4))*730 -> 260.71429 | C90: AWS | E90: =CEILING(E64*(100+SUMMARY!$C$24)%,1) -> 0 | F90: =CEILING(F64*(100+SUMMARY!$C$24)%,1) -> 0 | G90: Windows Server | H90: =IF(G90="Windows Server", "C:\", "/") -> C:\ | I90: =IF(G90="Windows Server", 150, 20) -> 150 | J90: =SUM(I90:I93) -> 300 | K90: =J90 *(IF(C90="AZURE", SUMMARY!C$20, SUMMARY!C$21)) -> 28.8 | M90: =IF(C90="ON PREM", 0, SUMMARY!C$25%) -> 0.12 | N90: =IF(C90="AWS",SUMMARY!C$26%, 0) -> 0.13 | O90: =((SUM(K90:L90))-((SUM(K90:L90))*N90))*(1 + M90) -> 28.06272 | P90: =O90*12 -> 336.75264
H91: =IF(G90="Windows Server", "F:\appdir", "/appdir") -> F:\appdir | I91: =CEILING(I65*(100+SUMMARY!$C$24)%,1) -> 0
H92: =IF(G90="Windows Server", "G:\Log", "/var/log") -> G:\Log | I92: =IF(G90="Windows Server", 50, 20) -> 50
H93: =IF(G90="Windows Server", "H:\Backup", "/backup") -> H:\Backup | I93: =IF(G90="Windows Server", 100, 10) -> 100
B94: =((12*5*4)/(24*7*4))*730 -> 260.71429 | C94: AWS | E94: =CEILING(E68*(100+SUMMARY!$C$24)%,1) -> 0 | F94: =CEILING(F68*(100+SUMMARY!$C$24)%,1) -> 0 | G94: Windows Server | H94: =IF(G94="Windows Server", "C:\", "/") -> C:\ | I94: =IF(G94="Windows Server", 150, 20) -> 150 | J94: =SUM(I94:I97) -> 300 | K94: =J94 *(IF(C94="AZURE", SUMMARY!C$20, SUMMARY!C$21)) -> 28.8 | M94: =IF(C94="ON PREM", 0, SUMMARY!C$25%) -> 0.12 | N94: =IF(C94="AWS",SUMMARY!C$26%, 0) -> 0.13 | O94: =((SUM(K94:L94))-((SUM(K94:L94))*N94))*(1 + M94) -> 28.06272 | P94: =O94*12 -> 336.75264
H95: =IF(G94="Windows Server", "F:\appdir", "/appdir") -> F:\appdir | I95: =CEILING(I69*(100+SUMMARY!$C$24)%,1) -> 0
H96: =IF(G94="Windows Server", "G:\Log", "/var/log") -> G:\Log | I96: =IF(G94="Windows Server", 50, 20) -> 50
H97: =IF(G94="Windows Server", "H:\Backup", "/backup") -> H:\Backup | I97: =IF(G94="Windows Server", 100, 10) -> 100
B98: =((12*5*4)/(24*7*4))*730 -> 260.71429 | C98: AWS | E98: =CEILING(E72*(100+SUMMARY!$C$24)%,1) -> 0 | F98: =CEILING(F72*(100+SUMMARY!$C$24)%,1) -> 0 | G98: Windows Server | H98: =IF(G98="Windows Server", "C:\", "/") -> C:\ | I98: =IF(G98="Windows Server", 150, 20) -> 150 | J98: =SUM(I98:I101) -> 300 | K98: =J98 *(IF(C98="AZURE", SUMMARY!C$20, SUMMARY!C$21)) -> 28.8 | M98: =IF(C98="ON PREM", 0, SUMMARY!C$25%) -> 0.12 | N98: =IF(C98="AWS",SUMMARY!C$26%, 0) -> 0.13 | O98: =((SUM(K98:L98))-((SUM(K98:L98))*N98))*(1 + M98) -> 28.06272 | P98: =O98*12 -> 336.75264
H99: =IF(G98="Windows Server", "F:\appdir", "/appdir") -> F:\appdir | I99: =CEILING(I73*(100+SUMMARY!$C$24)%,1) -> 0
H100: =IF(G98="Windows Server", "G:\Log", "/var/log") -> G:\Log | I100: =IF(G98="Windows Server", 50, 20) -> 50
...

Sheet PROD
A1: PROD ENVIRONMENT (to be filled out by servicing unit)
A2: YEAR 1
A3: Description | B3: Hours | C3: Cloud Platform | D3: Instance Type, Specs | E3: CPU | F3: Memory (GB) | G3: Operating System | H3: Disk Space Description (Size in GB) | J3: Disk Space (GB) | K3: Monthly EBS Volume Cost ($) | L3: Monthly Subscription Cost ($) | M3: VAT | N3: Enterprise Discount | O3: Total Monthly Cost ($) | P3: Total Annual Cost ($)
A4: App Server | B4: =((24*7*4)/(24*7*4))*730 -> 730 | C4: AWS | E4: 4 | F4: 16 | G4: Windows Server | H4: =IF(G4="Windows Server", "C:\", "/") -> C:\ | I4: =IF(G4="Windows Server", 150, 20) -> 150 | J4: =SUM(I4:I7) -> 300 | K4: =J4 *(IF(C4="AZURE", SUMMARY!C$20, SUMMARY!C$21)) -> 28.8 | M4: =IF(C4="ON PREM", 0, SUMMARY!C$25%) -> 0.12 | N4: =IF(C4="AWS",SUMMARY!C$26%, 0) -> 0.13 | O4: =((SUM(K4:L4))-((SUM(K4:L4))*N4))*(1 + M4) -> 28.06272 | P4: =O4*12 -> 336.75264
H5: =IF(G4="Windows Server", "F:\appdir", "/appdir") -> F:\appdir
H6: =IF(G4="Windows Server", "G:\Log", "/var/log") -> G:\Log | I6: =IF(G4="Windows Server", 50, 20) -> 50
H7: =IF(G4="Windows Server", "H:\Backup", "/backup") -> H:\Backup | I7: =IF(G4="Windows Server", 100, 10) -> 100
B8: =((24*7*4)/(24*7*4))*730 -> 730 | C8: ON PREM | G8: Windows Server | H8: =IF(G8="Windows Server", "C:\", "/") -> C:\ | I8: =IF(G8="Windows Server", 150, 20) -> 150 | J8: =SUM(I8:I11) -> 300 | K8: =J8 *(IF(C8="AZURE", SUMMARY!C$20, SUMMARY!C$21)) -> 28.8 | M8: =IF(C8="ON PREM", 0, SUMMARY!C$25%) -> 0 | N8: =IF(C8="AWS",SUMMARY!C$26%, 0) -> 0 | O8: =((SUM(K8:L8))-((SUM(K8:L8))*N8))*(1 + M8) -> 28.8 | P8: =O8*12 -> 345.6
H9: =IF(G8="Windows Server", "F:\appdir", "/appdir") -> F:\appdir
H10: =IF(G8="Windows Server", "G:\Log", "/var/log") -> G:\Log | I10: =IF(G8="Windows Server", 50, 20) -> 50
H11: =IF(G8="Windows Server", "H:\Backup", "/backup") -> H:\Backup | I11: =IF(G8="Windows Server", 100, 10) -> 100
B12: =((24*7*4)/(24*7*4))*730 -> 730 | C12: EXACC | G12: RHEL | H12: =IF(G12="Windows Server", "C:\", "/") -> / | I12: =IF(G12="Windows Server", 150, 20) -> 20 | J12: =SUM(I12:I15) -> 50 | K12: =J12 *(IF(C12="AZURE", SUMMARY!C$20, SUMMARY!C$21)) -> 4.8 | M12: =IF(C12="ON PREM", 0, SUMMARY!C$25%) -> 0.12 | N12: =IF(C12="AWS",SUMMARY!C$26%, 0) -> 0 | O12: =((SUM(K12:L12))-((SUM(K12:L12))*N12))*(1 + M12) -> 5.376 | P12: =O12*12 -> 64.512
H13: =IF(G12="Windows Server", "F:\appdir", "/appdir") -> /appdir
H14: =IF(G12="Windows Server", "G:\Log", "/var/log") -> /var/log | I14: =IF(G12="Windows Server", 50, 20) -> 20
H15: =IF(G12="Windows Server", "H:\Backup", "/backup") -> /backup | I15: =IF(G12="Windows Server", 100, 10) -> 10
B16: =((24*7*4)/(24*7*4))*730 -> 730 | C16: EXACC | G16: Oracle Linux | H16: =IF(G16="Windows Server", "C:\", "/") -> / | I16: =IF(G16="Windows Server", 150, 20) -> 20 | J16: =SUM(I16:I19) -> 50 | K16: =J16 *(IF(C16="AZURE", SUMMARY!C$20, SUMMARY!C$21)) -> 4.8 | M16: =IF(C16="ON PREM", 0, SUMMARY!C$25%) -> 0.12 | N16: =IF(C16="AWS",SUMMARY!C$26%, 0) -> 0 | O16: =((SUM(K16:L16))-((SUM(K16:L16))*N16))*(1 + M16) -> 5.376 | P16: =O16*12 -> 64.512
H17: =IF(G16="Windows Server", "F:\appdir", "/appdir") -> /appdir
H18: =IF(G16="Windows Server", "G:\Log", "/var/log") -> /var/log | I18: =IF(G16="Windows Server", 50, 20) -> 20
H19: =IF(G16="Windows Server", "H:\Backup", "/backup") -> /backup | I19: =IF(G16="Windows Server", 100, 10) -> 10
B20: =((24*7*4)/(24*7*4))*730 -> 730 | C20: EXACC | G20: Ubuntu | H20: =IF(G20="Windows Server", "C:\", "/") -> / | I20: =IF(G20="Windows Server", 150, 20) -> 20 | J20: =SUM(I20:I23) -> 50 | K20: =J20 *(IF(C20="AZURE", SUMMARY!C$20, SUMMARY!C$21)) -> 4.8 | M20: =IF(C20="ON PREM", 0, SUMMARY!C$25%) -> 0.12 | N20: =IF(C20="AWS",SUMMARY!C$26%, 0) -> 0 | O20: =((SUM(K20:L20))-((SUM(K20:L20))*N20))*(1 + M20) -> 5.376 | P20: =O20*12 -> 64.512
H21: =IF(G20="Windows Server", "F:\appdir", "/appdir") -> /appdir
H22: =IF(G20="Windows Server", "G:\Log", "/var/log") -> /var/log | I22: =IF(G20="Windows Server", 50, 20) -> 20
H23: =IF(G20="Windows Server", "H:\Backup", "/backup") -> /backup | I23: =IF(G20="Windows Server", 100, 10) -> 10
B24: =((24*7*4)/(24*7*4))*730 -> 730 | C24: EXACC | G24: Windows Server | H24: =IF(G24="Windows Server", "C:\", "/") -> C:\ | I24: =IF(G24="Windows Server", 150, 20) -> 150 | J24: =SUM(I24:I27) -> 300 | K24: =J24 *(IF(C24="AZURE", SUMMARY!C$20, SUMMARY!C$21)) -> 28.8 | M24: =IF(C24="ON PREM", 0, SUMMARY!C$25%) -> 0.12 | N24: =IF(C24="AWS",SUMMARY!C$26%, 0) -> 0 | O24: =((SUM(K24:L24))-((SUM(K24:L24))*N24))*(1 + M24) -> 32.256 | P24: =O24*12 -> 387.072
H25: =IF(G24="Windows Server", "F:\appdir", "/appdir") -> F:\appdir
H26: =IF(G24="Windows Server", "G:\Log", "/var/log") -> G:\Log | I26: =IF(G24="Windows Server", 50, 20) -> 50
H27: =IF(G24="Windows Server", "H:\Backup", "/backup") -> H:\Backup | I27: =IF(G24="Windows Server", 100, 10) -> 100
E28: =SUM(E4:E27) -> 4 | F28: =SUM(F4:F27) -> 16 | J28: =SUM(J4:J27) -> 1050 | K28: =SUM(K4:K27) -> 100.8 | L28: =SUM(L4:L27) -> 0 | O28: =SUM(O4:O27) -> 105.24672 | P28: =SUM(P4:P27) -> 1262.9606
A29: YEAR 2
B30: =((24*7*4)/(24*7*4))*730 -> 730 | C30: AWS | E30: =CEILING(E4*(100+SUMMARY!$C$24)%,1) -> 5 | F30: =CEILING(F4*(100+SUMMARY!$C$24)%,1) -> 19 | G30: Windows Server | H30: =IF(G30="Windows Server", "C:\", "/") -> C:\ | I30: =IF(G30="Windows Server", 150, 20) -> 150 | J30: =SUM(I30:I33) -> 300 | K30: =J30 *(IF(C30="AZURE", SUMMARY!C$20, SUMMARY!C$21)) -> 28.8 | M30: =IF(C30="ON PREM", 0, SUMMARY!C$25%) -> 0.12 | N30: =IF(C30="AWS",SUMMARY!C$26%, 0) -> 0.13 | O30: =((SUM(K30:L30))-((SUM(K30:L30))*N30))*(1 + M30) -> 28.06272 | P30: =O30*12 -> 336.75264
H31: =IF(G30="Windows Server", "F:\appdir", "/appdir") -> F:\appdir | I31: =CEILING(I5*(100+SUMMARY!$C$24)%,1) -> 0
H32: =IF(G30="Windows Server", "G:\Log", "/var/log") -> G:\Log | I32: =IF(G30="Windows Server", 50, 20) -> 50
H33: =IF(G30="Windows Server", "H:\Backup", "/backup") -> H:\Backup | I33: =IF(G30="Windows Server", 100, 10) -> 100
B34: =((24*7*4)/(24*7*4))*730 -> 730 | C34: AWS | E34: =CEILING(E8*(100+SUMMARY!$C$24)%,1) -> 0 | F34: =CEILING(F8*(100+SUMMARY!$C$24)%,1) -> 0 | G34: Windows Server | H34: =IF(G34="Windows Server", "C:\", "/") -> C:\ | I34: =IF(G34="Windows Server", 150, 20) -> 150 | J34: =SUM(I34:I37) -> 300 | K34: =J34 *(IF(C34="AZURE", SUMMARY!C$20, SUMMARY!C$21)) -> 28.8 | M34: =IF(C34="ON PREM", 0, SUMMARY!C$25%) -> 0.12 | N34: =IF(C34="AWS",SUMMARY!C$26%, 0) -> 0.13 | O34: =((SUM(K34:L34))-((SUM(K34:L34))*N34))*(1 + M34) -> 28.06272 | P34: =O34*12 -> 336.75264
H35: =IF(G34="Windows Server", "F:\appdir", "/appdir") -> F:\appdir | I35: =CEILING(I9*(100+SUMMARY!$C$24)%,1) -> 0
H36: =IF(G34="Windows Server", "G:\Log", "/var/log") -> G:\Log | I36: =IF(G34="Windows Server", 50, 20) -> 50
H37: =IF(G34="Windows Server", "H:\Backup", "/backup") -> H:\Backup | I37: =IF(G34="Windows Server", 100, 10) -> 100
B38: =((24*7*4)/(24*7*4))*730 -> 730 | C38: AWS | E38: =CEILING(E12*(100+SUMMARY!$C$24)%,1) -> 0 | F38: =CEILING(F12*(100+SUMMARY!$C$24)%,1) -> 0 | G38: Windows Server | H38: =IF(G38="Windows Server", "C:\", "/") -> C:\ | I38: =IF(G38="Windows Server", 150, 20) -> 150 | J38: =SUM(I38:I41) -> 300 | K38: =J38 *(IF(C38="AZURE", SUMMARY!C$20, SUMMARY!C$21)) -> 28.8 | M38: =IF(C38="ON PREM", 0, SUMMARY!C$25%) -> 0.12 | N38: =IF(C38="AWS",SUMMARY!C$26%, 0) -> 0.13 | O38: =((SUM(K38:L38))-((SUM(K38:L38))*N38))*(1 + M38) -> 28.06272 | P38: =O38*12 -> 336.75264
H39: =IF(G38="Windows Server", "F:\appdir", "/appdir") -> F:\appdir | I39: =CEILING(I13*(100+SUMMARY!$C$24)%,1) -> 0
H40: =IF(G38="Windows Server", "G:\Log", "/var/log") -> G:\Log | I40: =IF(G38="Windows Server", 50, 20) -> 50
H41: =IF(G38="Windows Server", "H:\Backup", "/backup") -> H:\Backup | I41: =IF(G38="Windows Server", 100, 10) -> 100
B42: =((24*7*4)/(24*7*4))*730 -> 730 | C42: AWS | E42: =CEILING(E16*(100+SUMMARY!$C$24)%,1) -> 0 | F42: =CEILING(F16*(100+SUMMARY!$C$24)%,1) -> 0 | G42: Windows Server | H42: =IF(G42="Windows Server", "C:\", "/") -> C:\ | I42: =IF(G42="Windows Server", 150, 20) -> 150 | J42: =SUM(I42:I45) -> 300 | K42: =J42 *(IF(C42="AZURE", SUMMARY!C$20, SUMMARY!C$21)) -> 28.8 | M42: =IF(C42="ON PREM", 0, SUMMARY!C$25%) -> 0.12 | N42: =IF(C42="AWS",SUMMARY!C$26%, 0) -> 0.13 | O42: =((SUM(K42:L42))-((SUM(K42:L42))*N42))*(1 + M42) -> 28.06272 | P42: =O42*12 -> 336.75264
H43: =IF(G42="Windows Server", "F:\appdir", "/appdir") -> F:\appdir | I43: =CEILING(I17*(100+SUMMARY!$C$24)%,1) -> 0
H44: =IF(G42="Windows Server", "G:\Log", "/var/log") -> G:\Log | I44: =IF(G42="Windows Server", 50, 20) -> 50
H45: =IF(G42="Windows Server", "H:\Backup", "/backup") -> H:\Backup | I45: =IF(G42="Windows Server", 100, 10) -> 100
B46: =((24*7*4)/(24*7*4))*730 -> 730 | C46: AWS | E46: =CEILING(E20*(100+SUMMARY!$C$24)%,1) -> 0 | F46: =CEILING(F20*(100+SUMMARY!$C$24)%,1) -> 0 | G46: Windows Server | H46: =IF(G46="Windows Server", "C:\", "/") -> C:\ | I46: =IF(G46="Windows Server", 150, 20) -> 150 | J46: =SUM(I46:I49) -> 300 | K46: =J46 *(IF(C46="AZURE", SUMMARY!C$20, SUMMARY!C$21)) -> 28.8 | M46: =IF(C46="ON PREM", 0, SUMMARY!C$25%) -> 0.12 | N46: =IF(C46="AWS",SUMMARY!C$26%, 0) -> 0.13 | O46: =((SUM(K46:L46))-((SUM(K46:L46))*N46))*(1 + M46) -> 28.06272 | P46: =O46*12 -> 336.75264
H47: =IF(G46="Windows Server", "F:\appdir", "/appdir") -> F:\appdir | I47: =CEILING(I21*(100+SUMMARY!$C$24)%,1) -> 0
H48: =IF(G46="Windows Server", "G:\Log", "/var/log") -> G:\Log | I48: =IF(G46="Windows Server", 50, 20) -> 50
H49: =IF(G46="Windows Server", "H:\Backup", "/backup") -> H:\Backup | I49: =IF(G46="Windows Server", 100, 10) -> 100
B50: =((24*7*4)/(24*7*4))*730 -> 730 | C50: AWS | E50: =CEILING(E24*(100+SUMMARY!$C$24)%,1) -> 0 | F50: =CEILING(F24*(100+SUMMARY!$C$24)%,1) -> 0 | G50: Windows Server | H50: =IF(G50="Windows Server", "C:\", "/") -> C:\ | I50: =IF(G50="Windows Server", 150, 20) -> 150 | J50: =SUM(I50:I53) -> 300 | K50: =J50 *(IF(C50="AZURE", SUMMARY!C$20, SUMMARY!C$21)) -> 28.8 | M50: =IF(C50="ON PREM", 0, SUMMARY!C$25%) -> 0.12 | N50: =IF(C50="AWS",SUMMARY!C$26%, 0) -> 0.13 | O50: =((SUM(K50:L50))-((SUM(K50:L50))*N50))*(1 + M50) -> 28.06272 | P50: =O50*12 -> 336.75264
H51: =IF(G50="Windows Server", "F:\appdir", "/appdir") -> F:\appdir | I51: =CEILING(I25*(100+SUMMARY!$C$24)%,1) -> 0
H52: =IF(G50="Windows Server", "G:\Log", "/var/log") -> G:\Log | I52: =IF(G50="Windows Server", 50, 20) -> 50
H53: =IF(G50="Windows Server", "H:\Backup", "/backup") -> H:\Backup | I53: =IF(G50="Windows Server", 100, 10) -> 100
E54: =SUM(E30:E53) -> 5 | F54: =SUM(F30:F53) -> 19 | J54: =SUM(J30:J53) -> 1800 | K54: =SUM(K30:K53) -> 172.8 | L54: =SUM(L30:L53) -> 0 | O54: =SUM(O30:O53) -> 168.37632 | P54: =SUM(P30:P53) -> 2020.5158
B56: =((24*7*4)/(24*7*4))*730 -> 730 | C56: EXACC | E56: =CEILING(E30*(100+SUMMARY!$C$24)%,1) -> 6 | F56: =CEILING(F30*(100+SUMMARY!$C$24)%,1) -> 22 | G56: Windows Server | H56: =IF(G56="Windows Server", "C:\", "/") -> C:\ | I56: =IF(G56="Windows Server", 150, 20) -> 150 | J56: =SUM(I56:I59) -> 300 | K56: =J56 *(IF(C56="AZURE", SUMMARY!C$20, SUMMARY!C$21)) -> 28.8 | M56: =IF(C56="ON PREM", 0, SUMMARY!C$25%) -> 0.12 | N56: =IF(C56="AWS",SUMMARY!C$26%, 0) -> 0 | O56: =((SUM(K56:L56))-((SUM(K56:L56))*N56))*(1 + M56) -> 32.256 | P56: =O56*12 -> 387.072
H57: =IF(G56="Windows Server", "F:\appdir", "/appdir") -> F:\appdir | I57: =CEILING(I31*(100+SUMMARY!$C$24)%,1) -> 0
H58: =IF(G56="Windows Server", "G:\Log", "/var/log") -> G:\Log | I58: =IF(G56="Windows Server", 50, 20) -> 50
H59: =IF(G56="Windows Server", "H:\Backup", "/backup") -> H:\Backup | I59: =IF(G56="Windows Server", 100, 10) -> 100
B60: =((24*7*4)/(24*7*4))*730 -> 730 | C60: ON PREM | E60: =CEILING(E34*(100+SUMMARY!$C$24)%,1) -> 0 | F60: =CEILING(F34*(100+SUMMARY!$C$24)%,1) -> 0 | G60: Windows Server | H60: =IF(G60="Windows Server", "C:\", "/") -> C:\ | I60: =IF(G60="Windows Server", 150, 20) -> 150 | J60: =SUM(I60:I63) -> 300 | K60: =J60 *(IF(C60="AZURE", SUMMARY!C$20, SUMMARY!C$21)) -> 28.8 | M60: =IF(C60="ON PREM", 0, SUMMARY!C$25%) -> 0 | N60: =IF(C60="AWS",SUMMARY!C$26%, 0) -> 0 | O60: =((SUM(K60:L60))-((SUM(K60:L60))*N60))*(1 + M60) -> 28.8 | P60: =O60*12 -> 345.6
H61: =IF(G60="Windows Server", "F:\appdir", "/appdir") -> F:\appdir | I61: =CEILING(I35*(100+SUMMARY!$C$24)%,1) -> 0
H62: =IF(G60="Windows Server", "G:\Log", "/var/log") -> G:\Log | I62: =IF(G60="Windows Server", 50, 20) -> 50
H63: =IF(G60="Windows Server", "H:\Backup", "/backup") -> H:\Backup | I63: =IF(G60="Windows Server", 100, 10) -> 100
B64: =((24*7*4)/(24*7*4))*730 -> 730 | C64: EXACC | E64: =CEILING(E38*(100+SUMMARY!$C$24)%,1) -> 0 | F64: =CEILING(F38*(100+SUMMARY!$C$24)%,1) -> 0 | G64: Windows Server | H64: =IF(G64="Windows Server", "C:\", "/") -> C:\ | I64: =IF(G64="Windows Server", 150, 20) -> 150 | J64: =SUM(I64:I67) -> 300 | K64: =J64 *(IF(C64="AZURE", SUMMARY!C$20, SUMMARY!C$21)) -> 28.8 | M64: =IF(C64="ON PREM", 0, SUMMARY!C$25%) -> 0.12 | N64: =IF(C64="AWS",SUMMARY!C$26%, 0) -> 0 | O64: =((SUM(K64:L64))-((SUM(K64:L64))*N64))*(1 + M64) -> 32.256 | P64: =O64*12 -> 387.072
H65: =IF(G64="Windows Server", "F:\appdir", "/appdir") -> F:\appdir | I65: =CEILING(I39*(100+SUMMARY!$C$24)%,1) -> 0
H66: =IF(G64="Windows Server", "G:\Log", "/var/log") -> G:\Log | I66: =IF(G64="Windows Server", 50, 20) -> 50
H67: =IF(G64="Windows Server", "H:\Backup", "/backup") -> H:\Backup | I67: =IF(G64="Windows Server", 100, 10) -> 100
B68: =((24*7*4)/(24*7*4))*730 -> 730 | C68: EXACC | E68: =CEILING(E42*(100+SUMMARY!$C$24)%,1) -> 0 | F68: =CEILING(F42*(100+SUMMARY!$C$24)%,1) -> 0 | G68: Windows Server | H68: =IF(G68="Windows Server", "C:\", "/") -> C:\ | I68: =IF(G68="Windows Server", 150, 20) -> 150 | J68: =SUM(I68:I71) -> 300 | K68: =J68 *(IF(C68="AZURE", SUMMARY!C$20, SUMMARY!C$21)) -> 28.8 | M68: =IF(C68="ON PREM", 0, SUMMARY!C$25%) -> 0.12 | N68: =IF(C68="AWS",SUMMARY!C$26%, 0) -> 0 | O68: =((SUM(K68:L68))-((SUM(K68:L68))*N68))*(1 + M68) -> 32.256 | P68: =O68*12 -> 387.072
H69: =IF(G68="Windows Server", "F:\appdir", "/appdir") -> F:\appdir | I69: =CEILING(I43*(100+SUMMARY!$C$24)%,1) -> 0
H70: =IF(G68="Windows Server", "G:\Log", "/var/log") -> G:\Log | I70: =IF(G68="Windows Server", 50, 20) -> 50
H71: =IF(G68="Windows Server", "H:\Backup", "/backup") -> H:\Backup | I71: =IF(G68="Windows Server", 100, 10) -> 100
B72: =((24*7*4)/(24*7*4))*730 -> 730 | C72: EXACC | E72: =CEILING(E46*(100+SUMMARY!$C$24)%,1) -> 0 | F72: =CEILING(F46*(100+SUMMARY!$C$24)%,1) -> 0 | G72: Windows Server | H72: =IF(G72="Windows Server", "C:\", "/") -> C:\ | I72: =IF(G72="Windows Server", 150, 20) -> 150 | J72: =SUM(I72:I75) -> 300 | K72: =J72 *(IF(C72="AZURE", SUMMARY!C$20, SUMMARY!C$21)) -> 28.8 | M72: =IF(C72="ON PREM", 0, SUMMARY!C$25%) -> 0.12 | N72: =IF(C72="AWS",SUMMARY!C$26%, 0) -> 0 | O72: =((SUM(K72:L72))-((SUM(K72:L72))*N72))*(1 + M72) -> 32.256 | P72: =O72*12 -> 387.072
H73: =IF(G72="Windows Server", "F:\appdir", "/appdir") -> F:\appdir | I73: =CEILING(I47*(100+SUMMARY!$C$24)%,1) -> 0
H74: =IF(G72="Windows Server", "G:\Log", "/var/log") -> G:\Log | I74: =IF(G72="Windows Server", 50, 20) -> 50
H75: =IF(G72="Windows Server", "H:\Backup", "/backup") -> H:\Backup | I75: =IF(G72="Windows Server", 100, 10) -> 100
B76: =((24*7*4)/(24*7*4))*730 -> 730 | C76: EXACC | E76: =CEILING(E50*(100+SUMMARY!$C$24)%,1) -> 0 | F76: =CEILING(F50*(100+SUMMARY!$C$24)%,1) -> 0 | G76: Windows Server | H76: =IF(G76="Windows Server", "C:\", "/") -> C:\ | I76: =IF(G76="Windows Server", 150, 20) -> 150 | J76: =SUM(I76:I79) -> 300 | K76: =J76 *(IF(C76="AZURE", SUMMARY!C$20, SUMMARY!C$21)) -> 28.8 | M76: =IF(C76="ON PREM", 0, SUMMARY!C$25%) -> 0.12 | N76: =IF(C76="AWS",SUMMARY!C$26%, 0) -> 0 | O76: =((SUM(K76:L76))-((SUM(K76:L76))*N76))*(1 + M76) -> 32.256 | P76: =O76*12 -> 387.072
H77: =IF(G76="Windows Server", "F:\appdir", "/appdir") -> F:\appdir | I77: =CEILING(I51*(100+SUMMARY!$C$24)%,1) -> 0
H78: =IF(G76="Windows Server", "G:\Log", "/var/log") -> G:\Log | I78: =IF(G76="Windows Server", 50, 20) -> 50
H79: =IF(G76="Windows Server", "H:\Backup", "/backup") -> H:\Backup | I79: =IF(G76="Windows Server", 100, 10) -> 100
E80: =SUM(E56:E79) -> 6 | F80: =SUM(F56:F79) -> 22 | J80: =SUM(J56:J79) -> 1800 | K80: =SUM(K56:K79) -> 172.8 | L80: =SUM(L56:L79) -> 0 | O80: =SUM(O56:O79) -> 190.08 | P80: =SUM(P56:P79) -> 2280.96
B82: =((24*7*4)/(24*7*4))*730 -> 730 | C82: AWS | E82: =CEILING(E56*(100+SUMMARY!$C$24)%,1) -> 7 | F82: =CEILING(F56*(100+SUMMARY!$C$24)%,1) -> 26 | G82: Windows Server | H82: =IF(G82="Windows Server", "C:\", "/") -> C:\ | I82: =IF(G82="Windows Server", 150, 20) -> 150 | J82: =SUM(I82:I85) -> 300 | K82: =J82 *(IF(C82="AZURE", SUMMARY!C$20, SUMMARY!C$21)) -> 28.8 | M82: =IF(C82="ON PREM", 0, SUMMARY!C$25%) -> 0.12 | N82: =IF(C82="AWS",SUMMARY!C$26%, 0) -> 0.13 | O82: =((SUM(K82:L82))-((SUM(K82:L82))*N82))*(1 + M82) -> 28.06272 | P82: =O82*12 -> 336.75264
H83: =IF(G82="Windows Server", "F:\appdir", "/appdir") -> F:\appdir | I83: =CEILING(I57*(100+SUMMARY!$C$24)%,1) -> 0
H84: =IF(G82="Windows Server", "G:\Log", "/var/log") -> G:\Log | I84: =IF(G82="Windows Server", 50, 20) -> 50
H85: =IF(G82="Windows Server", "H:\Backup", "/backup") -> H:\Backup | I85: =IF(G82="Windows Server", 100, 10) -> 100
B86: =((24*7*4)/(24*7*4))*730 -> 730 | C86: AWS | E86: =CEILING(E60*(100+SUMMARY!$C$24)%,1) -> 0 | F86: =CEILING(F60*(100+SUMMARY!$C$24)%,1) -> 0 | G86: Windows Server | H86: =IF(G86="Windows Server", "C:\", "/") -> C:\ | I86: =IF(G86="Windows Server", 150, 20) -> 150 | J86: =SUM(I86:I89) -> 300 | K86: =J86 *(IF(C86="AZURE", SUMMARY!C$20, SUMMARY!C$21)) -> 28.8 | M86: =IF(C86="ON PREM", 0, SUMMARY!C$25%) -> 0.12 | N86: =IF(C86="AWS",SUMMARY!C$26%, 0) -> 0.13 | O86: =((SUM(K86:L86))-((SUM(K86:L86))*N86))*(1 + M86) -> 28.06272 | P86: =O86*12 -> 336.75264
H87: =IF(G86="Windows Server", "F:\appdir", "/appdir") -> F:\appdir | I87: =CEILING(I61*(100+SUMMARY!$C$24)%,1) -> 0
H88: =IF(G86="Windows Server", "G:\Log", "/var/log") -> G:\Log | I88: =IF(G86="Windows Server", 50, 20) -> 50
H89: =IF(G86="Windows Server", "H:\Backup", "/backup") -> H:\Backup | I89: =IF(G86="Windows Server", 100, 10) -> 100
B90: =((24*7*4)/(24*7*4))*730 -> 730 | C90: AWS | E90: =CEILING(E64*(100+SUMMARY!$C$24)%,1) -> 0 | F90: =CEILING(F64*(100+SUMMARY!$C$24)%,1) -> 0 | G90: Windows Server | H90: =IF(G90="Windows Server", "C:\", "/") -> C:\ | I90: =IF(G90="Windows Server", 150, 20) -> 150 | J90: =SUM(I90:I93) -> 300 | K90: =J90 *(IF(C90="AZURE", SUMMARY!C$20, SUMMARY!C$21)) -> 28.8 | M90: =IF(C90="ON PREM", 0, SUMMARY!C$25%) -> 0.12 | N90: =IF(C90="AWS",SUMMARY!C$26%, 0) -> 0.13 | O90: =((SUM(K90:L90))-((SUM(K90:L90))*N90))*(1 + M90) -> 28.06272 | P90: =O90*12 -> 336.75264
H91: =IF(G90="Windows Server", "F:\appdir", "/appdir") -> F:\appdir | I91: =CEILING(I65*(100+SUMMARY!$C$24)%,1) -> 0
H92: =IF(G90="Windows Server", "G:\Log", "/var/log") -> G:\Log | I92: =IF(G90="Windows Server", 50, 20) -> 50
H93: =IF(G90="Windows Server", "H:\Backup", "/backup") -> H:\Backup | I93: =IF(G90="Windows Server", 100, 10) -> 100
B94: =((24*7*4)/(24*7*4))*730 -> 730 | C94: AWS | E94: =CEILING(E68*(100+SUMMARY!$C$24)%,1) -> 0 | F94: =CEILING(F68*(100+SUMMARY!$C$24)%,1) -> 0 | G94: Windows Server | H94: =IF(G94="Windows Server", "C:\", "/") -> C:\ | I94: =IF(G94="Windows Server", 150, 20) -> 150 | J94: =SUM(I94:I97) -> 300 | K94: =J94 *(IF(C94="AZURE", SUMMARY!C$20, SUMMARY!C$21)) -> 28.8 | M94: =IF(C94="ON PREM", 0, SUMMARY!C$25%) -> 0.12 | N94: =IF(C94="AWS",SUMMARY!C$26%, 0) -> 0.13 | O94: =((SUM(K94:L94))-((SUM(K94:L94))*N94))*(1 + M94) -> 28.06272 | P94: =O94*12 -> 336.75264
H95: =IF(G94="Windows Server", "F:\appdir", "/appdir") -> F:\appdir | I95: =CEILING(I69*(100+SUMMARY!$C$24)%,1) -> 0
H96: =IF(G94="Windows Server", "G:\Log", "/var/log") -> G:\Log | I96: =IF(G94="Windows Server", 50, 20) -> 50
H97: =IF(G94="Windows Server", "H:\Backup", "/backup") -> H:\Backup | I97: =IF(G94="Windows Server", 100, 10) -> 100
B98: =((24*7*4)/(24*7*4))*730 -> 730 | C98: AWS | E98: =CEILING(E72*(100+SUMMARY!$C$24)%,1) -> 0 | F98: =CEILING(F72*(100+SUMMARY!$C$24)%,1) -> 0 | G98: Windows Server | H98: =IF(G98="Windows Server", "C:\", "/") -> C:\ | I98: =IF(G98="Windows Server", 150, 20) -> 150 | J98: =SUM(I98:I101) -> 300 | K98: =J98 *(IF(C98="AZURE", SUMMARY!C$20, SUMMARY!C$21)) -> 28.8 | M98: =IF(C98="ON PREM", 0, SUMMARY!C$25%) -> 0.12 | N98: =IF(C98="AWS",SUMMARY!C$26%, 0) -> 0.13 | O98: =((SUM(K98:L98))-((SUM(K98:L98))*N98))*(1 + M98) -> 28.06272 | P98: =O98*12 -> 336.75264
H99: =IF(G98="Windows Server", "F:\appdir", "/appdir") -> F:\appdir | I99: =CEILING(I73*(100+SUMMARY!$C$24)%,1) -> 0
H100: =IF(G98="Windows Server", "G:\Log", "/var/log") -> G:\Log | I100: =IF(G98="Windows Server", 50, 20) -> 50
H101: =IF(G98="Windows Server", "H:\Backup", "/backup") -> H:\Backup | I101: =IF(G98="Windows Server", 100, 10) -> 100
B102: =((24*7*4)/(24*7*4))*730 -> 730 | C102: AWS | E102: =CEILING(E76*(100+SUMMARY!$C$24)%,1) -> 0 | F102: =CEILING(F76*(100+SUMMARY!$C$24)%,1) -> 0 | G102: Windows Server | H102: =IF(G102="Windows Server", "C:\", "/") -> C:\ | I102: =IF(G102="Windows Server", 150, 20) -> 150 | J102: =SUM(I102:I105) -> 300 | K102: =J102 *(IF(C102="AZURE", SUMMARY!C$20, SUMMARY!C$21)) -> 28.8 | M102: =IF(C102="ON PREM", 0, SUMMARY!C$25%) -> 0.12 | N102: =IF(C102="AWS",SUMMARY!C$26%, 0) -> 0.13 | O102: =((SUM(K102:L102))-((SUM(K102:L102))*N102))*(1 + M102) -> 28.06272 | P102: =O102*12 -> 336.75264
...

Sheet DR
A1: DR ENVIRONMENT (to be filled out by servicing unit)
A2: YEAR 1
A3: Description | B3: Hours | C3: Cloud Platform | D3: Instance Type, Specs | E3: CPU | F3: Memory (GB) | G3: Operating System | H3: Disk Space Description (Size in GB) | J3: Disk Space (GB) | K3: Monthly EBS Volume Cost ($) | L3: Monthly Subscription Cost ($) | M3: VAT | N3: Enterprise Discount | O3: Total Monthly Cost ($) | P3: Total Annual Cost ($)
B4: =((12*7*4)/(24*7*4))*730 -> 365 | C4: AWS | G4: Windows Server | H4: =IF(G4="Windows Server", "C:\", "/") -> C:\ | I4: =IF(G4="Windows Server", 150, 20) -> 150 | J4: =SUM(I4:I7) -> 300 | K4: =J4 *(IF(C4="AZURE", SUMMARY!C$20, SUMMARY!C$21)) -> 28.8 | L4: 2 | M4: =IF(C4="ON PREM", 0, SUMMARY!C$25%) -> 0.12 | N4: =IF(C4="AWS",SUMMARY!C$26%, 0) -> 0.13 | O4: =((SUM(K4:L4))-((SUM(K4:L4))*N4))*(1 + M4) -> 30.01152 | P4: =O4*12 -> 360.13824
H5: =IF(G4="Windows Server", "F:\appdir", "/appdir") -> F:\appdir
H6: =IF(G4="Windows Server", "G:\Log", "/var/log") -> G:\Log | I6: =IF(G4="Windows Server", 50, 20) -> 50
H7: =IF(G4="Windows Server", "H:\Backup", "/backup") -> H:\Backup | I7: =IF(G4="Windows Server", 100, 10) -> 100
B8: =((12*7*4)/(24*7*4))*730 -> 365 | C8: AWS | G8: Windows Server | H8: =IF(G8="Windows Server", "C:\", "/") -> C:\ | I8: =IF(G8="Windows Server", 150, 20) -> 150 | J8: =SUM(I8:I11) -> 300 | K8: =J8 *(IF(C8="AZURE", SUMMARY!C$20, SUMMARY!C$21)) -> 28.8 | M8: =IF(C8="ON PREM", 0, SUMMARY!C$25%) -> 0.12 | N8: =IF(C8="AWS",SUMMARY!C$26%, 0) -> 0.13 | O8: =((SUM(K8:L8))-((SUM(K8:L8))*N8))*(1 + M8) -> 28.06272 | P8: =O8*12 -> 336.75264
H9: =IF(G8="Windows Server", "F:\appdir", "/appdir") -> F:\appdir
H10: =IF(G8="Windows Server", "G:\Log", "/var/log") -> G:\Log | I10: =IF(G8="Windows Server", 50, 20) -> 50
H11: =IF(G8="Windows Server", "H:\Backup", "/backup") -> H:\Backup | I11: =IF(G8="Windows Server", 100, 10) -> 100
B12: =((12*7*4)/(24*7*4))*730 -> 365 | C12: EXACC | G12: Windows Server | H12: =IF(G12="Windows Server", "C:\", "/") -> C:\ | I12: =IF(G12="Windows Server", 150, 20) -> 150 | J12: =SUM(I12:I15) -> 300 | K12: =J12 *(IF(C12="AZURE", SUMMARY!C$20, SUMMARY!C$21)) -> 28.8 | M12: =IF(C12="ON PREM", 0, SUMMARY!C$25%) -> 0.12 | N12: =IF(C12="AWS",SUMMARY!C$26%, 0) -> 0 | O12: =((SUM(K12:L12))-((SUM(K12:L12))*N12))*(1 + M12) -> 32.256 | P12: =O12*12 -> 387.072
H13: =IF(G12="Windows Server", "F:\appdir", "/appdir") -> F:\appdir
H14: =IF(G12="Windows Server", "G:\Log", "/var/log") -> G:\Log | I14: =IF(G12="Windows Server", 50, 20) -> 50
H15: =IF(G12="Windows Server", "H:\Backup", "/backup") -> H:\Backup | I15: =IF(G12="Windows Server", 100, 10) -> 100
B16: =((12*7*4)/(24*7*4))*730 -> 365 | C16: EXACC | G16: Windows Server | H16: =IF(G16="Windows Server", "C:\", "/") -> C:\ | I16: =IF(G16="Windows Server", 150, 20) -> 150 | J16: =SUM(I16:I19) -> 300 | K16: =J16 *(IF(C16="AZURE", SUMMARY!C$20, SUMMARY!C$21)) -> 28.8 | M16: =IF(C16="ON PREM", 0, SUMMARY!C$25%) -> 0.12 | N16: =IF(C16="AWS",SUMMARY!C$26%, 0) -> 0 | O16: =((SUM(K16:L16))-((SUM(K16:L16))*N16))*(1 + M16) -> 32.256 | P16: =O16*12 -> 387.072
H17: =IF(G16="Windows Server", "F:\appdir", "/appdir") -> F:\appdir
H18: =IF(G16="Windows Server", "G:\Log", "/var/log") -> G:\Log | I18: =IF(G16="Windows Server", 50, 20) -> 50
H19: =IF(G16="Windows Server", "H:\Backup", "/backup") -> H:\Backup | I19: =IF(G16="Windows Server", 100, 10) -> 100
B20: =((12*7*4)/(24*7*4))*730 -> 365 | C20: EXACC | G20: Windows Server | H20: =IF(G20="Windows Server", "C:\", "/") -> C:\ | I20: =IF(G20="Windows Server", 150, 20) -> 150 | J20: =SUM(I20:I23) -> 300 | K20: =J20 *(IF(C20="AZURE", SUMMARY!C$20, SUMMARY!C$21)) -> 28.8 | M20: =IF(C20="ON PREM", 0, SUMMARY!C$25%) -> 0.12 | N20: =IF(C20="AWS",SUMMARY!C$26%, 0) -> 0 | O20: =((SUM(K20:L20))-((SUM(K20:L20))*N20))*(1 + M20) -> 32.256 | P20: =O20*12 -> 387.072
H21: =IF(G20="Windows Server", "F:\appdir", "/appdir") -> F:\appdir
H22: =IF(G20="Windows Server", "G:\Log", "/var/log") -> G:\Log | I22: =IF(G20="Windows Server", 50, 20) -> 50
H23: =IF(G20="Windows Server", "H:\Backup", "/backup") -> H:\Backup | I23: =IF(G20="Windows Server", 100, 10) -> 100
B24: =((12*7*4)/(24*7*4))*730 -> 365 | C24: EXACC | G24: Windows Server | H24: =IF(G24="Windows Server", "C:\", "/") -> C:\ | I24: =IF(G24="Windows Server", 150, 20) -> 150 | J24: =SUM(I24:I27) -> 300 | K24: =J24 *(IF(C24="AZURE", SUMMARY!C$20, SUMMARY!C$21)) -> 28.8 | M24: =IF(C24="ON PREM", 0, SUMMARY!C$25%) -> 0.12 | N24: =IF(C24="AWS",SUMMARY!C$26%, 0) -> 0 | O24: =((SUM(K24:L24))-((SUM(K24:L24))*N24))*(1 + M24) -> 32.256 | P24: =O24*12 -> 387.072
H25: =IF(G24="Windows Server", "F:\appdir", "/appdir") -> F:\appdir
H26: =IF(G24="Windows Server", "G:\Log", "/var/log") -> G:\Log | I26: =IF(G24="Windows Server", 50, 20) -> 50
H27: =IF(G24="Windows Server", "H:\Backup", "/backup") -> H:\Backup | I27: =IF(G24="Windows Server", 100, 10) -> 100
E28: =SUM(E4:E27) -> 0 | F28: =SUM(F4:F27) -> 0 | J28: =SUM(J4:J27) -> 1800 | K28: =SUM(K4:K27) -> 172.8 | L28: =SUM(L4:L27) -> 2 | O28: =SUM(O4:O27) -> 187.09824 | P28: =SUM(P4:P27) -> 2245.1789
A29: YEAR 2
B30: =((12*7*4)/(24*7*4))*730 -> 365 | C30: AWS | E30: =CEILING(E4*(100+SUMMARY!$C$24)%,1) -> 0 | F30: =CEILING(F4*(100+SUMMARY!$C$24)%,1) -> 0 | G30: Windows Server | H30: =IF(G30="Windows Server", "C:\", "/") -> C:\ | I30: =IF(G30="Windows Server", 150, 20) -> 150 | J30: =SUM(I30:I33) -> 300 | K30: =J30 *(IF(C30="AZURE", SUMMARY!C$20, SUMMARY!C$21)) -> 28.8 | M30: =IF(C30="ON PREM", 0, SUMMARY!C$25%) -> 0.12 | N30: =IF(C30="AWS",SUMMARY!C$26%, 0) -> 0.13 | O30: =((SUM(K30:L30))-((SUM(K30:L30))*N30))*(1 + M30) -> 28.06272 | P30: =O30*12 -> 336.75264
H31: =IF(G30="Windows Server", "F:\appdir", "/appdir") -> F:\appdir | I31: =CEILING(I5*(100+SUMMARY!$C$24)%,1) -> 0
H32: =IF(G30="Windows Server", "G:\Log", "/var/log") -> G:\Log | I32: =IF(G30="Windows Server", 50, 20) -> 50
H33: =IF(G30="Windows Server", "H:\Backup", "/backup") -> H:\Backup | I33: =IF(G30="Windows Server", 100, 10) -> 100
B34: =((12*7*4)/(24*7*4))*730 -> 365 | C34: AWS | E34: =CEILING(E8*(100+SUMMARY!$C$24)%,1) -> 0 | F34: =CEILING(F8*(100+SUMMARY!$C$24)%,1) -> 0 | G34: Windows Server | H34: =IF(G34="Windows Server", "C:\", "/") -> C:\ | I34: =IF(G34="Windows Server", 150, 20) -> 150 | J34: =SUM(I34:I37) -> 300 | K34: =J34 *(IF(C34="AZURE", SUMMARY!C$20, SUMMARY!C$21)) -> 28.8 | M34: =IF(C34="ON PREM", 0, SUMMARY!C$25%) -> 0.12 | N34: =IF(C34="AWS",SUMMARY!C$26%, 0) -> 0.13 | O34: =((SUM(K34:L34))-((SUM(K34:L34))*N34))*(1 + M34) -> 28.06272 | P34: =O34*12 -> 336.75264
H35: =IF(G34="Windows Server", "F:\appdir", "/appdir") -> F:\appdir | I35: =CEILING(I9*(100+SUMMARY!$C$24)%,1) -> 0
H36: =IF(G34="Windows Server", "G:\Log", "/var/log") -> G:\Log | I36: =IF(G34="Windows Server", 50, 20) -> 50
H37: =IF(G34="Windows Server", "H:\Backup", "/backup") -> H:\Backup | I37: =IF(G34="Windows Server", 100, 10) -> 100
B38: =((12*7*4)/(24*7*4))*730 -> 365 | C38: AWS | E38: =CEILING(E12*(100+SUMMARY!$C$24)%,1) -> 0 | F38: =CEILING(F12*(100+SUMMARY!$C$24)%,1) -> 0 | G38: Windows Server | H38: =IF(G38="Windows Server", "C:\", "/") -> C:\ | I38: =IF(G38="Windows Server", 150, 20) -> 150 | J38: =SUM(I38:I41) -> 300 | K38: =J38 *(IF(C38="AZURE", SUMMARY!C$20, SUMMARY!C$21)) -> 28.8 | M38: =IF(C38="ON PREM", 0, SUMMARY!C$25%) -> 0.12 | N38: =IF(C38="AWS",SUMMARY!C$26%, 0) -> 0.13 | O38: =((SUM(K38:L38))-((SUM(K38:L38))*N38))*(1 + M38) -> 28.06272 | P38: =O38*12 -> 336.75264
H39: =IF(G38="Windows Server", "F:\appdir", "/appdir") -> F:\appdir | I39: =CEILING(I13*(100+SUMMARY!$C$24)%,1) -> 0
H40: =IF(G38="Windows Server", "G:\Log", "/var/log") -> G:\Log | I40: =IF(G38="Windows Server", 50, 20) -> 50
H41: =IF(G38="Windows Server", "H:\Backup", "/backup") -> H:\Backup | I41: =IF(G38="Windows Server", 100, 10) -> 100
B42: =((12*7*4)/(24*7*4))*730 -> 365 | C42: AWS | E42: =CEILING(E16*(100+SUMMARY!$C$24)%,1) -> 0 | F42: =CEILING(F16*(100+SUMMARY!$C$24)%,1) -> 0 | G42: Windows Server | H42: =IF(G42="Windows Server", "C:\", "/") -> C:\ | I42: =IF(G42="Windows Server", 150, 20) -> 150 | J42: =SUM(I42:I45) -> 300 | K42: =J42 *(IF(C42="AZURE", SUMMARY!C$20, SUMMARY!C$21)) -> 28.8 | M42: =IF(C42="ON PREM", 0, SUMMARY!C$25%) -> 0.12 | N42: =IF(C42="AWS",SUMMARY!C$26%, 0) -> 0.13 | O42: =((SUM(K42:L42))-((SUM(K42:L42))*N42))*(1 + M42) -> 28.06272 | P42: =O42*12 -> 336.75264
H43: =IF(G42="Windows Server", "F:\appdir", "/appdir") -> F:\appdir | I43: =CEILING(I17*(100+SUMMARY!$C$24)%,1) -> 0
H44: =IF(G42="Windows Server", "G:\Log", "/var/log") -> G:\Log | I44: =IF(G42="Windows Server", 50, 20) -> 50
H45: =IF(G42="Windows Server", "H:\Backup", "/backup") -> H:\Backup | I45: =IF(G42="Windows Server", 100, 10) -> 100
B46: =((12*7*4)/(24*7*4))*730 -> 365 | C46: AWS | E46: =CEILING(E20*(100+SUMMARY!$C$24)%,1) -> 0 | F46: =CEILING(F20*(100+SUMMARY!$C$24)%,1) -> 0 | G46: Windows Server | H46: =IF(G46="Windows Server", "C:\", "/") -> C:\ | I46: =IF(G46="Windows Server", 150, 20) -> 150 | J46: =SUM(I46:I49) -> 300 | K46: =J46 *(IF(C46="AZURE", SUMMARY!C$20, SUMMARY!C$21)) -> 28.8 | M46: =IF(C46="ON PREM", 0, SUMMARY!C$25%) -> 0.12 | N46: =IF(C46="AWS",SUMMARY!C$26%, 0) -> 0.13 | O46: =((SUM(K46:L46))-((SUM(K46:L46))*N46))*(1 + M46) -> 28.06272 | P46: =O46*12 -> 336.75264
H47: =IF(G46="Windows Server", "F:\appdir", "/appdir") -> F:\appdir | I47: =CEILING(I21*(100+SUMMARY!$C$24)%,1) -> 0
H48: =IF(G46="Windows Server", "G:\Log", "/var/log") -> G:\Log | I48: =IF(G46="Windows Server", 50, 20) -> 50
H49: =IF(G46="Windows Server", "H:\Backup", "/backup") -> H:\Backup | I49: =IF(G46="Windows Server", 100, 10) -> 100
B50: =((12*7*4)/(24*7*4))*730 -> 365 | C50: AWS | E50: =CEILING(E24*(100+SUMMARY!$C$24)%,1) -> 0 | F50: =CEILING(F24*(100+SUMMARY!$C$24)%,1) -> 0 | G50: Windows Server | H50: =IF(G50="Windows Server", "C:\", "/") -> C:\ | I50: =IF(G50="Windows Server", 150, 20) -> 150 | J50: =SUM(I50:I53) -> 300 | K50: =J50 *(IF(C50="AZURE", SUMMARY!C$20, SUMMARY!C$21)) -> 28.8 | M50: =IF(C50="ON PREM", 0, SUMMARY!C$25%) -> 0.12 | N50: =IF(C50="AWS",SUMMARY!C$26%, 0) -> 0.13 | O50: =((SUM(K50:L50))-((SUM(K50:L50))*N50))*(1 + M50) -> 28.06272 | P50: =O50*12 -> 336.75264
H51: =IF(G50="Windows Server", "F:\appdir", "/appdir") -> F:\appdir | I51: =CEILING(I25*(100+SUMMARY!$C$24)%,1) -> 0
H52: =IF(G50="Windows Server", "G:\Log", "/var/log") -> G:\Log | I52: =IF(G50="Windows Server", 50, 20) -> 50
H53: =IF(G50="Windows Server", "H:\Backup", "/backup") -> H:\Backup | I53: =IF(G50="Windows Server", 100, 10) -> 100
E54: =SUM(E30:E53) -> 0 | F54: =SUM(F30:F53) -> 0 | J54: =SUM(J30:J53) -> 1800 | K54: =SUM(K30:K53) -> 172.8 | L54: =SUM(L30:L53) -> 0 | O54: =SUM(O30:O53) -> 168.37632 | P54: =SUM(P30:P53) -> 2020.5158
A55: YEAR 3
B56: =((12*7*4)/(24*7*4))*730 -> 365 | C56: EXACC | E56: =CEILING(E30*(100+SUMMARY!$C$24)%,1) -> 0 | F56: =CEILING(F30*(100+SUMMARY!$C$24)%,1) -> 0 | G56: Windows Server | H56: =IF(G56="Windows Server", "C:\", "/") -> C:\ | I56: =IF(G56="Windows Server", 150, 20) -> 150 | J56: =SUM(I56:I59) -> 300 | K56: =J56 *(IF(C56="AZURE", SUMMARY!C$20, SUMMARY!C$21)) -> 28.8 | M56: =IF(C56="ON PREM", 0, SUMMARY!C$25%) -> 0.12 | N56: =IF(C56="AWS",SUMMARY!C$26%, 0) -> 0 | O56: =((SUM(K56:L56))-((SUM(K56:L56))*N56))*(1 + M56) -> 32.256 | P56: =O56*12 -> 387.072
H57: =IF(G56="Windows Server", "F:\appdir", "/appdir") -> F:\appdir | I57: =CEILING(I31*(100+SUMMARY!$C$24)%,1) -> 0
H58: =IF(G56="Windows Server", "G:\Log", "/var/log") -> G:\Log | I58: =IF(G56="Windows Server", 50, 20) -> 50
H59: =IF(G56="Windows Server", "H:\Backup", "/backup") -> H:\Backup | I59: =IF(G56="Windows Server", 100, 10) -> 100
B60: =((12*7*4)/(24*7*4))*730 -> 365 | C60: ON PREM | E60: =CEILING(E34*(100+SUMMARY!$C$24)%,1) -> 0 | F60: =CEILING(F34*(100+SUMMARY!$C$24)%,1) -> 0 | G60: Windows Server | H60: =IF(G60="Windows Server", "C:\", "/") -> C:\ | I60: =IF(G60="Windows Server", 150, 20) -> 150 | J60: =SUM(I60:I63) -> 300 | K60: =J60 *(IF(C60="AZURE", SUMMARY!C$20, SUMMARY!C$21)) -> 28.8 | M60: =IF(C60="ON PREM", 0, SUMMARY!C$25%) -> 0 | N60: =IF(C60="AWS",SUMMARY!C$26%, 0) -> 0 | O60: =((SUM(K60:L60))-((SUM(K60:L60))*N60))*(1 + M60) -> 28.8 | P60: =O60*12 -> 345.6
H61: =IF(G60="Windows Server", "F:\appdir", "/appdir") -> F:\appdir | I61: =CEILING(I35*(100+SUMMARY!$C$24)%,1) -> 0
H62: =IF(G60="Windows Server", "G:\Log", "/var/log") -> G:\Log | I62: =IF(G60="Windows Server", 50, 20) -> 50
H63: =IF(G60="Windows Server", "H:\Backup", "/backup") -> H:\Backup | I63: =IF(G60="Windows Server", 100, 10) -> 100
B64: =((12*7*4)/(24*7*4))*730 -> 365 | C64: EXACC | E64: =CEILING(E38*(100+SUMMARY!$C$24)%,1) -> 0 | F64: =CEILING(F38*(100+SUMMARY!$C$24)%,1) -> 0 | G64: Windows Server | H64: =IF(G64="Windows Server", "C:\", "/") -> C:\ | I64: =IF(G64="Windows Server", 150, 20) -> 150 | J64: =SUM(I64:I67) -> 300 | K64: =J64 *(IF(C64="AZURE", SUMMARY!C$20, SUMMARY!C$21)) -> 28.8 | M64: =IF(C64="ON PREM", 0, SUMMARY!C$25%) -> 0.12 | N64: =IF(C64="AWS",SUMMARY!C$26%, 0) -> 0 | O64: =((SUM(K64:L64))-((SUM(K64:L64))*N64))*(1 + M64) -> 32.256 | P64: =O64*12 -> 387.072
H65: =IF(G64="Windows Server", "F:\appdir", "/appdir") -> F:\appdir | I65: =CEILING(I39*(100+SUMMARY!$C$24)%,1) -> 0
H66: =IF(G64="Windows Server", "G:\Log", "/var/log") -> G:\Log | I66: =IF(G64="Windows Server", 50, 20) -> 50
H67: =IF(G64="Windows Server", "H:\Backup", "/backup") -> H:\Backup | I67: =IF(G64="Windows Server", 100, 10) -> 100
B68: =((12*7*4)/(24*7*4))*730 -> 365 | C68: EXACC | E68: =CEILING(E42*(100+SUMMARY!$C$24)%,1) -> 0 | F68: =CEILING(F42*(100+SUMMARY!$C$24)%,1) -> 0 | G68: Windows Server | H68: =IF(G68="Windows Server", "C:\", "/") -> C:\ | I68: =IF(G68="Windows Server", 150, 20) -> 150 | J68: =SUM(I68:I71) -> 300 | K68: =J68 *(IF(C68="AZURE", SUMMARY!C$20, SUMMARY!C$21)) -> 28.8 | M68: =IF(C68="ON PREM", 0, SUMMARY!C$25%) -> 0.12 | N68: =IF(C68="AWS",SUMMARY!C$26%, 0) -> 0 | O68: =((SUM(K68:L68))-((SUM(K68:L68))*N68))*(1 + M68) -> 32.256 | P68: =O68*12 -> 387.072
H69: =IF(G68="Windows Server", "F:\appdir", "/appdir") -> F:\appdir | I69: =CEILING(I43*(100+SUMMARY!$C$24)%,1) -> 0
H70: =IF(G68="Windows Server", "G:\Log", "/var/log") -> G:\Log | I70: =IF(G68="Windows Server", 50, 20) -> 50
H71: =IF(G68="Windows Server", "H:\Backup", "/backup") -> H:\Backup | I71: =IF(G68="Windows Server", 100, 10) -> 100
B72: =((12*7*4)/(24*7*4))*730 -> 365 | C72: EXACC | E72: =CEILING(E46*(100+SUMMARY!$C$24)%,1) -> 0 | F72: =CEILING(F46*(100+SUMMARY!$C$24)%,1) -> 0 | G72: Windows Server | H72: =IF(G72="Windows Server", "C:\", "/") -> C:\ | I72: =IF(G72="Windows Server", 150, 20) -> 150 | J72: =SUM(I72:I75) -> 300 | K72: =J72 *(IF(C72="AZURE", SUMMARY!C$20, SUMMARY!C$21)) -> 28.8 | M72: =IF(C72="ON PREM", 0, SUMMARY!C$25%) -> 0.12 | N72: =IF(C72="AWS",SUMMARY!C$26%, 0) -> 0 | O72: =((SUM(K72:L72))-((SUM(K72:L72))*N72))*(1 + M72) -> 32.256 | P72: =O72*12 -> 387.072
H73: =IF(G72="Windows Server", "F:\appdir", "/appdir") -> F:\appdir | I73: =CEILING(I47*(100+SUMMARY!$C$24)%,1) -> 0
H74: =IF(G72="Windows Server", "G:\Log", "/var/log") -> G:\Log | I74: =IF(G72="Windows Server", 50, 20) -> 50
H75: =IF(G72="Windows Server", "H:\Backup", "/backup") -> H:\Backup | I75: =IF(G72="Windows Server", 100, 10) -> 100
B76: =((12*7*4)/(24*7*4))*730 -> 365 | C76: EXACC | E76: =CEILING(E50*(100+SUMMARY!$C$24)%,1) -> 0 | F76: =CEILING(F50*(100+SUMMARY!$C$24)%,1) -> 0 | G76: Windows Server | H76: =IF(G76="Windows Server", "C:\", "/") -> C:\ | I76: =IF(G76="Windows Server", 150, 20) -> 150 | J76: =SUM(I76:I79) -> 300 | K76: =J76 *(IF(C76="AZURE", SUMMARY!C$20, SUMMARY!C$21)) -> 28.8 | M76: =IF(C76="ON PREM", 0, SUMMARY!C$25%) -> 0.12 | N76: =IF(C76="AWS",SUMMARY!C$26%, 0) -> 0 | O76: =((SUM(K76:L76))-((SUM(K76:L76))*N76))*(1 + M76) -> 32.256 | P76: =O76*12 -> 387.072
H77: =IF(G76="Windows Server", "F:\appdir", "/appdir") -> F:\appdir | I77: =CEILING(I51*(100+SUMMARY!$C$24)%,1) -> 0
H78: =IF(G76="Windows Server", "G:\Log", "/var/log") -> G:\Log | I78: =IF(G76="Windows Server", 50, 20) -> 50
H79: =IF(G76="Windows Server", "H:\Backup", "/backup") -> H:\Backup | I79: =IF(G76="Windows Server", 100, 10) -> 100
E80: =SUM(E56:E79) -> 0 | F80: =SUM(F56:F79) -> 0 | J80: =SUM(J56:J79) -> 1800 | K80: =SUM(K56:K79) -> 172.8 | L80: =SUM(L56:L79) -> 0 | O80: =SUM(O56:O79) -> 190.08 | P80: =SUM(P56:P79) -> 2280.96
A81: YEAR 4
B82: =((12*7*4)/(24*7*4))*730 -> 365 | C82: AWS | E82: =CEILING(E56*(100+SUMMARY!$C$24)%,1) -> 0 | F82: =CEILING(F56*(100+SUMMARY!$C$24)%,1) -> 0 | G82: RHEL | H82: =IF(G82="Windows Server", "C:\", "/") -> / | I82: =IF(G82="Windows Server", 150, 20) -> 20 | J82: =SUM(I82:I85) -> 50 | K82: =J82 *(IF(C82="AZURE", SUMMARY!C$20, SUMMARY!C$21)) -> 4.8 | M82: =IF(C82="ON PREM", 0, SUMMARY!C$25%) -> 0.12 | N82: =IF(C82="AWS",SUMMARY!C$26%, 0) -> 0.13 | O82: =((SUM(K82:L82))-((SUM(K82:L82))*N82))*(1 + M82) -> 4.67712 | P82: =O82*12 -> 56.12544
H83: =IF(G82="Windows Server", "F:\appdir", "/appdir") -> /appdir | I83: =CEILING(I57*(100+SUMMARY!$C$24)%,1) -> 0
H84: =IF(G82="Windows Server", "G:\Log", "/var/log") -> /var/log | I84: =IF(G82="Windows Server", 50, 20) -> 20
H85: =IF(G82="Windows Server", "H:\Backup", "/backup") -> /backup | I85: =IF(G82="Windows Server", 100, 10) -> 10
B86: =((12*7*4)/(24*7*4))*730 -> 365 | C86: AWS | E86: =CEILING(E60*(100+SUMMARY!$C$24)%,1) -> 0 | F86: =CEILING(F60*(100+SUMMARY!$C$24)%,1) -> 0 | G86: Windows Server | H86: =IF(G86="Windows Server", "C:\", "/") -> C:\ | I86: =IF(G86="Windows Server", 150, 20) -> 150 | J86: =SUM(I86:I89) -> 300 | K86: =J86 *(IF(C86="AZURE", SUMMARY!C$20, SUMMARY!C$21)) -> 28.8 | M86: =IF(C86="ON PREM", 0, SUMMARY!C$25%) -> 0.12 | N86: =IF(C86="AWS",SUMMARY!C$26%, 0) -> 0.13 | O86: =((SUM(K86:L86))-((SUM(K86:L86))*N86))*(1 + M86) -> 28.06272 | P86: =O86*12 -> 336.75264
H87: =IF(G86="Windows Server", "F:\appdir", "/appdir") -> F:\appdir | I87: =CEILING(I61*(100+SUMMARY!$C$24)%,1) -> 0
H88: =IF(G86="Windows Server", "G:\Log", "/var/log") -> G:\Log | I88: =IF(G86="Windows Server", 50, 20) -> 50
H89: =IF(G86="Windows Server", "H:\Backup", "/backup") -> H:\Backup | I89: =IF(G86="Windows Server", 100, 10) -> 100
B90: =((12*7*4)/(24*7*4))*730 -> 365 | C90: AWS | E90: =CEILING(E64*(100+SUMMARY!$C$24)%,1) -> 0 | F90: =CEILING(F64*(100+SUMMARY!$C$24)%,1) -> 0 | G90: Windows Server | H90: =IF(G90="Windows Server", "C:\", "/") -> C:\ | I90: =IF(G90="Windows Server", 150, 20) -> 150 | J90: =SUM(I90:I93) -> 300 | K90: =J90 *(IF(C90="AZURE", SUMMARY!C$20, SUMMARY!C$21)) -> 28.8 | M90: =IF(C90="ON PREM", 0, SUMMARY!C$25%) -> 0.12 | N90: =IF(C90="AWS",SUMMARY!C$26%, 0) -> 0.13 | O90: =((SUM(K90:L90))-((SUM(K90:L90))*N90))*(1 + M90) -> 28.06272 | P90: =O90*12 -> 336.75264
H91: =IF(G90="Windows Server", "F:\appdir", "/appdir") -> F:\appdir | I91: =CEILING(I65*(100+SUMMARY!$C$24)%,1) -> 0
H92: =IF(G90="Windows Server", "G:\Log", "/var/log") -> G:\Log | I92: =IF(G90="Windows Server", 50, 20) -> 50
H93: =IF(G90="Windows Server", "H:\Backup", "/backup") -> H:\Backup | I93: =IF(G90="Windows Server", 100, 10) -> 100
B94: =((12*7*4)/(24*7*4))*730 -> 365 | C94: AWS | E94: =CEILING(E68*(100+SUMMARY!$C$24)%,1) -> 0 | F94: =CEILING(F68*(100+SUMMARY!$C$24)%,1) -> 0 | G94: Windows Server | H94: =IF(G94="Windows Server", "C:\", "/") -> C:\ | I94: =IF(G94="Windows Server", 150, 20) -> 150 | J94: =SUM(I94:I97) -> 300 | K94: =J94 *(IF(C94="AZURE", SUMMARY!C$20, SUMMARY!C$21)) -> 28.8 | M94: =IF(C94="ON PREM", 0, SUMMARY!C$25%) -> 0.12 | N94: =IF(C94="AWS",SUMMARY!C$26%, 0) -> 0.13 | O94: =((SUM(K94:L94))-((SUM(K94:L94))*N94))*(1 + M94) -> 28.06272 | P94: =O94*12 -> 336.75264
H95: =IF(G94="Windows Server", "F:\appdir", "/appdir") -> F:\appdir | I95: =CEILING(I69*(100+SUMMARY!$C$24)%,1) -> 0
H96: =IF(G94="Windows Server", "G:\Log", "/var/log") -> G:\Log | I96: =IF(G94="Windows Server", 50, 20) -> 50
H97: =IF(G94="Windows Server", "H:\Backup", "/backup") -> H:\Backup | I97: =IF(G94="Windows Server", 100, 10) -> 100
B98: =((12*7*4)/(24*7*4))*730 -> 365 | C98: AWS | E98: =CEILING(E72*(100+SUMMARY!$C$24)%,1) -> 0 | F98: =CEILING(F72*(100+SUMMARY!$C$24)%,1) -> 0 | G98: Windows Server | H98: =IF(G98="Windows Server", "C:\", "/") -> C:\ | I98: =IF(G98="Windows Server", 150, 20) -> 150 | J98: =SUM(I98:I101) -> 300 | K98: =J98 *(IF(C98="AZURE", SUMMARY!C$20, SUMMARY!C$21)) -> 28.8 | M98: =IF(C98="ON PREM", 0, SUMMARY!C$25%) -> 0.12 | N98: =IF(C98="AWS",SUMMARY!C$26%, 0) -> 0.13 | O98: =((SUM(K98:L98))-((SUM(K98:L98))*N98))*(1 + M98) -> 28.06272 | P98: =O98*12 -> 336.75264
H99: =IF(G98="Windows Server", "F:\appdir", "/appdir") -> F:\appdir | I99: =CEILING(I73*(100+SUMMARY!$C$24)%,1) -> 0
H100: =IF(G98="Windows Server", "G:\Log", "/var/log") -> G:\Log | I100: =IF(G98="Windows Server", 50, 20) -> 50
...

Sheet SUMMARY
B1: SUMMARY (auto-fill)
B2: Cost Item | C2: Philippine Peso
C3: 1-year TCO | D3: 2-year TCO | E3: 3-year TCO | F3: 4-year TCO | G3: 5-year TCO | H3: Total Amount
B4: DEV | C4: =DEV!$P$12*$C$22 -> 40410.317 | D4: =DEV!$P$22*$C$22 -> 40410.317 | E4: =DEV!$P$32*$C$22 -> 7326.72 | F4: =DEV!$P$42*$C$22 -> 23572.685 | G4: =DEV!$P$52*$C$22 -> 7741.44 | H4: =SUM(C4:G4) -> 119461.48
B5: SIT | C5: =SIT!$P$12*$C$22 -> 47013.12 | D5: =SIT!$P$22*$C$22 -> 40410.317 | E5: =SIT!$P$32*$C$22 -> 7326.72 | F5: =SIT!$P$42*$C$22 -> 23572.685 | G5: =SIT!$P$52*$C$22 -> 7741.44 | H5: =SUM(C5:G5) -> 126064.28
B6: UAT | C6: =UAT!$P$28*$C$22 -> 22394.88 | D6: =UAT!$P$54*$C$22 -> 104393.32 | E6: =UAT!$P$80*$C$22 -> 80870.4 | F6: =UAT!$P$106*$C$22 -> 104393.32 | G6: =UAT!$P$132*$C$22 -> 58497.638 | H6: =SUM(C6:G6) -> 370549.56
B7: Pre-Prod | C7: ='Pre-Prod'!$P$28*$C$22 -> 22809.6 | D7: ='Pre-Prod'!$P$54*$C$22 -> 104393.32 | E7: ='Pre-Prod'!$P$80*$C$22 -> 80870.4 | F7: ='Pre-Prod'!$P$106*$C$22 -> 104393.32 | G7: ='Pre-Prod'!$P$132*$C$22 -> 61516.8 | H7: =SUM(C7:G7) -> 373983.44
B8: PROD | C8: =PROD!$P$28*$C$22 -> 75777.638 | D8: =PROD!$P$54*$C$22 -> 121230.95 | E8: =PROD!$P$80*$C$22 -> 136857.6 | F8: =PROD!$P$106*$C$22 -> 121230.95 | G8: =PROD!$P$132*$C$22 -> 136857.6 | H8: =SUM(C8:G8) -> 591954.74
B9: PROD DR | C9: =DR!$P$28*$C$22 -> 134710.73 | D9: =DR!$P$54*$C$22 -> 121230.95 | E9: =DR!$P$80*$C$22 -> 136857.6 | F9: =DR!$P$106*$C$22 -> 104393.32 | G9: =DR!$P$132*$C$22 -> 61516.8 | H9: =SUM(C9:G9) -> 558709.4
B10: Software Licenses | C10: ='Software Licenses'!G19 -> 0 | D10: ='Software Licenses'!H19 -> 0 | E10: ='Software Licenses'!I19 -> 0 | F10: ='Software Licenses'!J19 -> 0 | G10: ='Software Licenses'!K19 -> 0 | H10: =SUM(C10:G10) -> 0
B11: VDI (including licenses) | C11: =('VDI Specifications (Infra)'!$J$16+'Software Licenses'!G25)*$C$22 -> 140400 | D11: =('VDI Specifications (Infra)'!$J$16+'Software Licenses'!H25)*$C$22 -> 140400 | E11: =('VDI Specifications (Infra)'!$J$16+'Software Licenses'!I25)*$C$22 -> 140400 | F11: =('VDI Specifications (Infra)'!$J$16+'Software Licenses'!J25)*$C$22 -> 140400 | G11: =('VDI Specifications (Infra)'!$J$16+'Software Licenses'!K25)*$C$22 -> 140400 | H11: =SUM(C11:G11) -> 702000
B12: TOTAL(VAT Inclusive) | C12: =SUM(C4:C11) -> 483516.29 | D12: =SUM(D4:D11) -> 672469.17 | E12: =SUM(E4:E11) -> 590509.44 | F12: =SUM(F4:F11) -> 621956.28 | G12: =SUM(G4:G11) -> 474271.72 | H12: =SUM(C12:G12) -> 2842722.9
B13: =CONCATENATE(SUMMARY!C23, "% Cost Buffer") -> 25% Cost Buffer | C13: =(C12*($C$23)%) -> 120879.07 | D13: =(D12*($C$23)%) -> 168117.29 | E13: =(E12*($C$23)%) -> 147627.36 | F13: =(F12*($C$23)%) -> 155489.07 | G13: =(G12*($C$23)%) -> 118567.93 | H13: =(H12*($C$23)%) -> 710680.72
B15: GRAND TOTAL(VAT Inclusive) | C15: =SUM(C12:C13) -> 604395.36 | D15: =SUM(D12:D13) -> 840586.46 | E15: =SUM(E12:E13) -> 738136.8 | F15: =SUM(F12:F13) -> 777445.34 | G15: =SUM(G12:G13) -> 592839.65 | H15: =SUM(H12:H13) -> 3553403.6
B17: Reference | C17: https://calculator.aws/#/
C18: https://azure.Microsoft.com/en-us/pricing/calculator
B19: SCTASK Number
B20: Azure Storage Cost Multiplier | C20: 0.097 | D20: https://azure.microsoft.com/en-us/pricing/details/managed-disks/?msockid=07c55edcd9076a5a3d524a7dd8c76ba8#:~:text=only%2020%20GB.-,Pricing,true%20availability%20of%20this%20service%20can%20be%20found%20in%20documentation.,-Standard%20SSD
B21: AWS/On-Prem Storage Cost Multiplier | C21: 0.096 | D21: https://aws.amazon.com/ebs/pricing/
B22: USD to PHP exchange rate | C22: 60 | D22: As of Week of <<Current Monday DATE>>
B23: Cost Buffer (%) | C23: 25
B24: TCO increase per year (%) | C24: ='HW & SW Requirements'!$B$3 -> 15
B25: VAT(%) | C25: 12
B26: AWS Enterprise Discount(%) | C26: 13
C27: Change these values accordingly.
C28: *All cost is VAT inc for applicable components
C29: *Azure Enterprise discount is already part of the monthly cost

Sheet K8S (DEV Cluster)
A1: Kindly Fill Up for Cluster Sizing Request
A2: Worker Node Group
L3: MINIMUM | N3: MAXIMUM
A4: Kube-system Namespace | B4: PDB Requirements | C4: Desired Replica | D4: Min Replicas | E4: Max Replicas | F4: Requests CPU (millicores) | G4: Requests Memory (M) | H4: Limits CPU (millicores) | I4: Limits Memory (M) | J4: Ephemeral Storage (MB) | K4: PV (GB) | L4: CPU | M4: Memory | N4: CPU | O4: Memory | P4: Ephemeral Storage per node | Q4: Total PV (GB) EFS | R4: Remarks
A5: aws-node | B5: 1 | C5: 1 | D5: 1 | E5: 2 | F5: 25 | G5: 70 | H5: 50 | I5: 100 | J5: 80 | K5: 0 | L5: =D5*F5 -> 25 | M5: =D5*G5 -> 70 | N5: =E5*H5 -> 100 | O5: =E5*I5 -> 200 | P5: =J5*3 -> 240 | Q5: =E5*K5 -> 0
A6: kube-proxy | B6: 1 | C6: 1 | D6: 1 | E6: 2 | F6: 100 | G6: 50 | H6: 100 | I6: 50 | J6: 60 | K6: 0 | L6: =D6*F6 -> 100 | M6: =D6*G6 -> 50 | N6: =E6*H6 -> 200 | O6: =E6*I6 -> 100 | P6: =J6*3 -> 180 | Q6: =E6*K6 -> 0
A7: coredns | B7: 1 | C7: 1 | D7: 1 | E7: 2 | F7: 100 | G7: 70 | H7: 100 | I7: 170 | J7: 40 | K7: 0 | L7: =D7*F7 -> 100 | M7: =D7*G7 -> 70 | N7: =E7*H7 -> 200 | O7: =E7*I7 -> 340 | P7: =J7*3 -> 120 | Q7: =E7*K7 -> 0
A8: efs-csi-controller | B8: 1 | C8: 1 | D8: 1 | E8: 2 | F8: 100 | G8: 128 | H8: 100 | I8: 128 | J8: 50 | K8: 0 | L8: =D8*F8 -> 100 | M8: =D8*G8 -> 128 | N8: =E8*H8 -> 200 | O8: =E8*I8 -> 256 | P8: =J8*3 -> 150 | Q8: =E8*K8 -> 0
A9: Metric Server | B9: 1 | C9: 1 | D9: 1 | E9: 2 | F9: 100 | G9: 200 | H9: 100 | I9: 200 | J9: 50 | K9: 0 | L9: =D9*F9 -> 100 | M9: =D9*G9 -> 200 | N9: =E9*H9 -> 200 | O9: =E9*I9 -> 400 | P9: =J9*3 -> 150 | Q9: =E9*K9 -> 0
A10: Cluster Autoscaler | B10: 1 | C10: 1 | D10: 1 | E10: 2 | F10: 100 | G10: 600 | H10: 100 | I10: 600 | J10: 50 | K10: 0 | L10: =D10*F10 -> 100 | M10: =D10*G10 -> 600 | N10: =E10*H10 -> 200 | O10: =E10*I10 -> 1200 | P10: =J10*3 -> 150 | Q10: =E10*K10 -> 0
A11: Ingress Namespace
A12: ingress-nginx-controller | B12: 1 | C12: 1 | D12: 1 | E12: 2 | F12: 25 | G12: 100 | H12: 100 | I12: 100 | J12: 50 | K12: 0 | L12: =D12*F12 -> 25 | M12: =D12*G12 -> 100 | N12: =E12*H12 -> 200 | O12: =E12*I12 -> 200 | P12: =J12*3 -> 150 | Q12: =E12*K12 -> 0
A13: brokerverse-core Namespace
A14: bv-policy-admin-svc | B14: 1 | C14: 1 | D14: 1 | E14: 2 | F14: 500 | G14: 1024 | H14: 1500 | I14: 2048 | J14: 2048 | K14: 0 | L14: =D14*F14 -> 500 | M14: =D14*G14 -> 1024 | N14: =E14*H14 -> 3000 | O14: =E14*I14 -> 4096 | P14: =J14*3 -> 6144 | Q14: =E14*H14 -> 3000
A15: bv-claims-svc | B15: 1 | C15: 1 | D15: 1 | E15: 2 | F15: 500 | G15: 1024 | H15: 1500 | I15: 2048 | J15: 2048 | K15: 0 | L15: =D15*F15 -> 500 | M15: =D15*G15 -> 1024 | N15: =E15*H15 -> 3000 | O15: =E15*I15 -> 4096 | P15: =J15*3 -> 6144 | Q15: =E15*H15 -> 3000
A16: bv-billing-collections-svc | B16: 1 | C16: 1 | D16: 1 | E16: 2 | F16: 500 | G16: 1024 | H16: 1500 | I16: 2048 | J16: 2048 | K16: 0 | L16: =D16*F16 -> 500 | M16: =D16*G16 -> 1024 | N16: =E16*H16 -> 3000 | O16: =E16*I16 -> 4096 | P16: =J16*3 -> 6144 | Q16: =E16*H16 -> 3000
A17: bv-distribution-svc | B17: 1 | C17: 1 | D17: 1 | E17: 2 | F17: 400 | G17: 768 | H17: 1200 | I17: 1536 | J17: 2048 | K17: 0 | L17: =D17*F17 -> 400 | M17: =D17*G17 -> 768 | N17: =E17*H17 -> 2400 | O17: =E17*I17 -> 3072 | P17: =J17*3 -> 6144 | Q17: =E17*H17 -> 2400
A18: bv-web-portal | B18: 1 | C18: 1 | D18: 1 | E18: 2 | F18: 200 | G18: 256 | H18: 500 | I18: 512 | J18: 1024 | K18: 0 | L18: =D18*F18 -> 200 | M18: =D18*G18 -> 256 | N18: =E18*H18 -> 1000 | O18: =E18*I18 -> 1024 | P18: =J18*3 -> 3072 | Q18: =E18*H18 -> 1000
A19: brokerverse-platform Namespace
A20: bv-api-gateway | B20: 1 | C20: 1 | D20: 1 | E20: 2 | F20: 500 | G20: 512 | H20: 1000 | I20: 1024 | J20: 1024 | K20: 0 | L20: =D20*F20 -> 500 | M20: =D20*G20 -> 512 | N20: =E20*H20 -> 2000 | O20: =E20*I20 -> 2048 | P20: =J20*3 -> 3072 | Q20: =E20*H20 -> 2000
A21: bv-iam-svc | B21: 1 | C21: 1 | D21: 1 | E21: 2 | F21: 400 | G21: 768 | H21: 1000 | I21: 1536 | J21: 1024 | K21: 0 | L21: =D21*F21 -> 400 | M21: =D21*G21 -> 768 | N21: =E21*H21 -> 2000 | O21: =E21*I21 -> 3072 | P21: =J21*3 -> 3072 | Q21: =E21*H21 -> 2000
A22: bv-integration-svc | B22: 1 | C22: 1 | D22: 1 | E22: 2 | F22: 500 | G22: 1024 | H22: 1500 | I22: 2048 | J22: 2048 | K22: 0 | L22: =D22*F22 -> 500 | M22: =D22*G22 -> 1024 | N22: =E22*H22 -> 3000 | O22: =E22*I22 -> 4096 | P22: =J22*3 -> 6144 | Q22: =E22*H22 -> 3000
A23: bv-document-svc | B23: 1 | C23: 1 | D23: 1 | E23: 2 | F23: 400 | G23: 768 | H23: 1200 | I23: 1536 | J23: 2048 | K23: 20 | L23: =D23*F23 -> 400 | M23: =D23*G23 -> 768 | N23: =E23*H23 -> 2400 | O23: =E23*I23 -> 3072 | P23: =J23*3 -> 6144 | Q23: =E23*H23 -> 2400
A24: bv-batch-notification-svc | B24: 1 | C24: 1 | D24: 1 | E24: 2 | F24: 400 | G24: 768 | H24: 1200 | I24: 1536 | J24: 2048 | K24: 0 | L24: =D24*F24 -> 400 | M24: =D24*G24 -> 768 | N24: =E24*H24 -> 2400 | O24: =E24*I24 -> 3072 | P24: =J24*3 -> 6144
A25: Total Applications | E25: =SUM(E5:E24) -> 34 | L25: =SUM(L5:L24) -> 4850 | M25: =SUM(M5:M24) -> 9154 | N25: =SUM(N5:N24) -> 25500 | O25: =SUM(O5:O24) -> 34440 | P25: =SUM(P5:P24) -> 53364 | Q25: =SUM(Q5:Q24) -> 21800
L26: =CEILING(L25/1024,1) -> 5 | M26: =CEILING(M25/1024,1) -> 9 | N26: =CEILING(N25/1024,1) -> 25 | O26: =CEILING(O25/1024,1) -> 34 | P26: =CEILING(P25/1024,1) -> 53 | Q26: =Q25 -> 21800
K27: with Threshold | L27: =CEILING(L26/E32,1) -> 7 | M27: =CEILING(M26/E32,1) -> 12 | N27: =CEILING(N26/E32,1) -> 32 | O27: =CEILING(O26/E32,1) -> 44 | P27: =CEILING(P26/E32,1) -> 68 | Q27: =CEILING(Q26/E32,1) -> 27595
K28: Worker Nodes | L28: CPUs | M28: GB of RAM | N28: CPUs | O28: GB of RAM | P28: EBS Disk Space (GB)per node | Q28: Disk Space (GB)
P29: Note: This was multiplied by 3 for caching, replica updates and retention updates use. | Q29: Note: PV should be stored on a separate storage preferrably EFS
A30: Worker Nodes - Recommended Sizing
A32: # of Worker nodes requested | B32: 2 | D32: Threshold | E32: 0.79
B33: Worker Node Size | C33: Instance Type | D33: Total Persistent Volume | E33: Needed ENI | F33: Total ENI Available
A34: CPU | B34: 16 | C34: m5.4xlarge (16x64) | D34: =Q26 -> 21800 | E34: =E25 -> 34 | F34: =B36*F45 -> 468
A35: RAM | B35: 64
A36: ENI per worker node | B36: 234
A39: Cluster Sizing Recommendation (for IA)
A40: Calculated # of Nodes
A41: TOTAL WORKER NODES BDOI | B41: Y1 | E41: TOTAL WORKER NODES BDOI | F41: Y1
B42: #of Nodes computed | C42: Y1 Requirement | F42: #of Nodes computed | G42: Y1 Requirement
A43: CPU | B43: =ROUNDUP(C43/B34,0) -> 1 | C43: =L27 -> 7 | E43: CPU | F43: =ROUNDUP(G43/B34,0) -> 2 | G43: =N27 -> 32
A44: RAM | B44: =ROUNDUP(C44/B35,0) -> 1 | C44: =M27 -> 12 | E44: RAM | F44: =ROUNDUP(G44/B35,0) -> 1 | G44: =O27 -> 44
A45: Minimum # of Nodes Needed | B45: =MAX(B43:B44) -> 1 | E45: Maximum # of Nodes Needed | F45: =MAX(F43:F44) -> 2
A48: Cost Analysis base on instance type
A49: Instance Type | B49: Required instance | C49: Amount per instance | D49: Total
A50: c5.2xlarge 8x16 | B50: 12 | C50: 286.16 | D50: =C50*B50 -> 3433.92
A51: c5.4xlarge 16x32 | B51: 7 | C51: 572.32 | D51: =C51*B51 -> 4006.24
A52: m5.2xlarge 8x32 | B52: 12 | C52: 350.4 | D52: =C52*B52 -> 4204.8
A53: r5.2xlarge 8x64 | B53: 12 | C53: 443.84 | D53: =C53*B53 -> 5326.08
A54: m5.4xlarge 16x64 | B54: 7 | C54: 700.8 | D54: =C54*B54 -> 4905.6
A55: r5.4xlarge 16x128 | B55: 7 | C55: 887.68 | D55: =C55*B55 -> 6213.76

Sheet K8S (SIT Cluster)
A1: Kindly Fill Up for Cluster Sizing Request
A2: Worker Node Group
L3: MINIMUM | N3: MAXIMUM
A4: Kube-system Namespace | B4: PDB Requirements | C4: Desired Replica | D4: Min Replicas | E4: Max Replicas | F4: Requests CPU (millicores) | G4: Requests Memory (M) | H4: Limits CPU (millicores) | I4: Limits Memory (M) | J4: Ephemeral Storage (MB) | K4: PV (GB) | L4: CPU | M4: Memory | N4: CPU | O4: Memory | P4: Ephemeral Storage per node | Q4: Total PV (GB) EFS | R4: Remarks
A5: aws-node | B5: 1 | C5: 1 | D5: 1 | E5: 2 | F5: 25 | G5: 70 | H5: 50 | I5: 100 | J5: 80 | K5: 0 | L5: =D5*F5 -> 25 | M5: =D5*G5 -> 70 | N5: =E5*H5 -> 100 | O5: =E5*I5 -> 200 | P5: =J5*3 -> 240 | Q5: =E5*K5 -> 0
A6: kube-proxy | B6: 1 | C6: 1 | D6: 1 | E6: 2 | F6: 100 | G6: 50 | H6: 100 | I6: 50 | J6: 60 | K6: 0 | L6: =D6*F6 -> 100 | M6: =D6*G6 -> 50 | N6: =E6*H6 -> 200 | O6: =E6*I6 -> 100 | P6: =J6*3 -> 180 | Q6: =E6*K6 -> 0
A7: coredns | B7: 1 | C7: 1 | D7: 1 | E7: 2 | F7: 100 | G7: 70 | H7: 100 | I7: 170 | J7: 40 | K7: 0 | L7: =D7*F7 -> 100 | M7: =D7*G7 -> 70 | N7: =E7*H7 -> 200 | O7: =E7*I7 -> 340 | P7: =J7*3 -> 120 | Q7: =E7*K7 -> 0
A8: efs-csi-controller | B8: 1 | C8: 1 | D8: 1 | E8: 2 | F8: 100 | G8: 128 | H8: 100 | I8: 128 | J8: 50 | K8: 0 | L8: =D8*F8 -> 100 | M8: =D8*G8 -> 128 | N8: =E8*H8 -> 200 | O8: =E8*I8 -> 256 | P8: =J8*3 -> 150 | Q8: =E8*K8 -> 0
A9: Metric Server | B9: 1 | C9: 1 | D9: 1 | E9: 2 | F9: 100 | G9: 200 | H9: 100 | I9: 200 | J9: 50 | K9: 0 | L9: =D9*F9 -> 100 | M9: =D9*G9 -> 200 | N9: =E9*H9 -> 200 | O9: =E9*I9 -> 400 | P9: =J9*3 -> 150 | Q9: =E9*K9 -> 0
A10: Cluster Autoscaler | B10: 1 | C10: 1 | D10: 1 | E10: 2 | F10: 100 | G10: 600 | H10: 100 | I10: 600 | J10: 50 | K10: 0 | L10: =D10*F10 -> 100 | M10: =D10*G10 -> 600 | N10: =E10*H10 -> 200 | O10: =E10*I10 -> 1200 | P10: =J10*3 -> 150 | Q10: =E10*K10 -> 0
A11: Ingress Namespace
A12: ingress-nginx-controller | B12: 1 | C12: 1 | D12: 1 | E12: 2 | F12: 25 | G12: 100 | H12: 100 | I12: 100 | J12: 50 | K12: 0 | L12: =D12*F12 -> 25 | M12: =D12*G12 -> 100 | N12: =E12*H12 -> 200 | O12: =E12*I12 -> 200 | P12: =J12*3 -> 150 | Q12: =E12*K12 -> 0
A13: brokerverse-core Namespace
A14: bv-policy-admin-svc | B14: 1 | C14: 1 | D14: 1 | E14: 2 | F14: 500 | G14: 1024 | H14: 1500 | I14: 2048 | J14: 2048 | K14: 0 | L14: =D14*F14 -> 500 | M14: =D14*G14 -> 1024 | N14: =E14*H14 -> 3000 | O14: =E14*I14 -> 4096 | P14: =J14*3 -> 6144 | Q14: =E14*H14 -> 3000
A15: bv-claims-svc | B15: 1 | C15: 1 | D15: 1 | E15: 2 | F15: 500 | G15: 1024 | H15: 1500 | I15: 2048 | J15: 2048 | K15: 0 | L15: =D15*F15 -> 500 | M15: =D15*G15 -> 1024 | N15: =E15*H15 -> 3000 | O15: =E15*I15 -> 4096 | P15: =J15*3 -> 6144 | Q15: =E15*H15 -> 3000
A16: bv-billing-collections-svc | B16: 1 | C16: 1 | D16: 1 | E16: 2 | F16: 500 | G16: 1024 | H16: 1500 | I16: 2048 | J16: 2048 | K16: 0 | L16: =D16*F16 -> 500 | M16: =D16*G16 -> 1024 | N16: =E16*H16 -> 3000 | O16: =E16*I16 -> 4096 | P16: =J16*3 -> 6144 | Q16: =E16*H16 -> 3000
A17: bv-distribution-svc | B17: 1 | C17: 1 | D17: 1 | E17: 2 | F17: 400 | G17: 768 | H17: 1200 | I17: 1536 | J17: 2048 | K17: 0 | L17: =D17*F17 -> 400 | M17: =D17*G17 -> 768 | N17: =E17*H17 -> 2400 | O17: =E17*I17 -> 3072 | P17: =J17*3 -> 6144 | Q17: =E17*H17 -> 2400
A18: bv-web-portal | B18: 1 | C18: 1 | D18: 1 | E18: 2 | F18: 200 | G18: 256 | H18: 500 | I18: 512 | J18: 1024 | K18: 0 | L18: =D18*F18 -> 200 | M18: =D18*G18 -> 256 | N18: =E18*H18 -> 1000 | O18: =E18*I18 -> 1024 | P18: =J18*3 -> 3072 | Q18: =E18*H18 -> 1000
A19: brokerverse-platform Namespace
A20: bv-api-gateway | B20: 1 | C20: 1 | D20: 1 | E20: 2 | F20: 500 | G20: 512 | H20: 1000 | I20: 1024 | J20: 1024 | K20: 0 | L20: =D20*F20 -> 500 | M20: =D20*G20 -> 512 | N20: =E20*H20 -> 2000 | O20: =E20*I20 -> 2048 | P20: =J20*3 -> 3072 | Q20: =E20*H20 -> 2000
A21: bv-iam-svc | B21: 1 | C21: 1 | D21: 1 | E21: 2 | F21: 400 | G21: 768 | H21: 1000 | I21: 1536 | J21: 1024 | K21: 0 | L21: =D21*F21 -> 400 | M21: =D21*G21 -> 768 | N21: =E21*H21 -> 2000 | O21: =E21*I21 -> 3072 | P21: =J21*3 -> 3072 | Q21: =E21*H21 -> 2000
A22: bv-integration-svc | B22: 1 | C22: 1 | D22: 1 | E22: 2 | F22: 500 | G22: 1024 | H22: 1500 | I22: 2048 | J22: 2048 | K22: 0 | L22: =D22*F22 -> 500 | M22: =D22*G22 -> 1024 | N22: =E22*H22 -> 3000 | O22: =E22*I22 -> 4096 | P22: =J22*3 -> 6144 | Q22: =E22*H22 -> 3000
A23: bv-document-svc | B23: 1 | C23: 1 | D23: 1 | E23: 2 | F23: 400 | G23: 768 | H23: 1200 | I23: 1536 | J23: 2048 | K23: 20 | L23: =D23*F23 -> 400 | M23: =D23*G23 -> 768 | N23: =E23*H23 -> 2400 | O23: =E23*I23 -> 3072 | P23: =J23*3 -> 6144 | Q23: =E23*H23 -> 2400
A24: bv-batch-notification-svc | B24: 1 | C24: 1 | D24: 1 | E24: 2 | F24: 400 | G24: 768 | H24: 1200 | I24: 1536 | J24: 2048 | K24: 0 | L24: =D24*F24 -> 400 | M24: =D24*G24 -> 768 | N24: =E24*H24 -> 2400 | O24: =E24*I24 -> 3072 | P24: =J24*3 -> 6144
A25: Total Applications | E25: =SUM(E5:E24) -> 34 | L25: =SUM(L5:L24) -> 4850 | M25: =SUM(M5:M24) -> 9154 | N25: =SUM(N5:N24) -> 25500 | O25: =SUM(O5:O24) -> 34440 | P25: =SUM(P5:P24) -> 53364 | Q25: =SUM(Q5:Q24) -> 21800
L26: =CEILING(L25/1024,1) -> 5 | M26: =CEILING(M25/1024,1) -> 9 | N26: =CEILING(N25/1024,1) -> 25 | O26: =CEILING(O25/1024,1) -> 34 | P26: =CEILING(P25/1024,1) -> 53 | Q26: =Q25 -> 21800
K27: with Threshold | L27: =CEILING(L26/E32,1) -> 7 | M27: =CEILING(M26/E32,1) -> 12 | N27: =CEILING(N26/E32,1) -> 32 | O27: =CEILING(O26/E32,1) -> 44 | P27: =CEILING(P26/E32,1) -> 68 | Q27: =CEILING(Q26/E32,1) -> 27595
K28: Worker Nodes | L28: CPUs | M28: GB of RAM | N28: CPUs | O28: GB of RAM | P28: EBS Disk Space (GB)per node | Q28: Disk Space (GB)
P29: Note: This was multiplied by 3 for caching, replica updates and retention updates use. | Q29: Note: PV should be stored on a separate storage preferrably EFS
A30: Worker Nodes - Recommended Sizing
A32: # of Worker nodes requested | B32: 2 | D32: Threshold | E32: 0.79
B33: Worker Node Size | C33: Instance Type | D33: Total Persistent Volume | E33: Needed ENI | F33: Total ENI Available
A34: CPU | B34: 16 | C34: m5.4xlarge (16x64) | D34: =Q26 -> 21800 | E34: =E25 -> 34 | F34: =B36*F45 -> 468
A35: RAM | B35: 64
A36: ENI per worker node | B36: 234
A39: Cluster Sizing Recommendation (for IA)
A40: Calculated # of Nodes
A41: TOTAL WORKER NODES BDOI | B41: Y1 | E41: TOTAL WORKER NODES BDOI | F41: Y1
B42: #of Nodes computed | C42: Y1 Requirement | F42: #of Nodes computed | G42: Y1 Requirement
A43: CPU | B43: =ROUNDUP(C43/B34,0) -> 1 | C43: =L27 -> 7 | E43: CPU | F43: =ROUNDUP(G43/B34,0) -> 2 | G43: =N27 -> 32
A44: RAM | B44: =ROUNDUP(C44/B35,0) -> 1 | C44: =M27 -> 12 | E44: RAM | F44: =ROUNDUP(G44/B35,0) -> 1 | G44: =O27 -> 44
A45: Minimum # of Nodes Needed | B45: =MAX(B43:B44) -> 1 | E45: Maximum # of Nodes Needed | F45: =MAX(F43:F44) -> 2
A48: Cost Analysis base on instance type
A49: Instance Type | B49: Required instance | C49: Amount per instance | D49: Total
A50: c5.2xlarge 8x16 | B50: 12 | C50: 286.16 | D50: =C50*B50 -> 3433.92
A51: c5.4xlarge 16x32 | B51: 7 | C51: 572.32 | D51: =C51*B51 -> 4006.24
A52: m5.2xlarge 8x32 | B52: 12 | C52: 350.4 | D52: =C52*B52 -> 4204.8
A53: r5.2xlarge 8x64 | B53: 12 | C53: 443.84 | D53: =C53*B53 -> 5326.08
A54: m5.4xlarge 16x64 | B54: 7 | C54: 700.8 | D54: =C54*B54 -> 4905.6
A55: r5.4xlarge 16x128 | B55: 7 | C55: 887.68 | D55: =C55*B55 -> 6213.76

Sheet K8S (UAT Cluster)
A1: Kindly Fill Up for Cluster Sizing Request
A2: Worker Node Group
L3: MINIMUM | N3: MAXIMUM
A4: Dynatrace Namespace | B4: PDB Requirements | C4: Desired Replica | D4: Min Replicas | E4: Max Replicas | F4: Requests CPU (millicores) | G4: Requests Memory (M) | H4: Limits CPU (millicores) | I4: Limits Memory (M) | J4: Ephemeral Storage (MB) | K4: PV (GB) | L4: CPU | M4: Memory | N4: CPU | O4: Memory | P4: Ephemeral Storage per node | Q4: Total PV (GB) EFS | R4: Remarks
A5: Dynakube-Activegate | B5: 1 | C5: 1 | D5: 1 | E5: 2 | F5: 500 | G5: 512 | H5: 1000 | I5: 1536 | J5: =6*1024 -> 6144 | K5: 0 | L5: =D5*F5 -> 500 | M5: =D5*G5 -> 512 | N5: =E5*H5 -> 2000 | O5: =E5*I5 -> 3072 | P5: =J5*3 -> 18432 | Q5: =E5*K5 -> 0
A6: Dynakube-OneAgent | B6: 1 | C6: 1 | D6: 1 | E6: 2 | F6: 100 | G6: 512 | H6: 300 | I6: 1536 | J6: =1024*8 -> 8192 | K6: 30 | L6: =D6*F6 -> 100 | M6: =D6*G6 -> 512 | N6: =E6*H6 -> 600 | O6: =E6*I6 -> 3072 | P6: =J6*3 -> 24576 | Q6: =E6*K6 -> 60
A7: Dynakube-Webhook | B7: 1 | C7: 1 | D7: 1 | E7: 2 | F7: 300 | G7: 128 | H7: 300 | I7: 128 | J7: =1024 -> 1024 | K7: 0 | L7: =D7*F7 -> 300 | M7: =D7*G7 -> 128 | N7: =E7*H7 -> 600 | O7: =E7*I7 -> 256 | P7: =J7*3 -> 3072 | Q7: =E7*K7 -> 0
A8: Dynakube-Operator | B8: 1 | C8: 1 | D8: 1 | E8: 2 | F8: 100 | G8: 128 | H8: 100 | I8: 128 | J8: 1024 | K8: 0 | L8: =D8*F8 -> 100 | M8: =D8*G8 -> 128 | N8: =E8*H8 -> 200 | O8: =E8*I8 -> 256 | P8: =J8*3 -> 3072 | Q8: =E8*K8 -> 0
A9: Kube-system Namespace
A10: aws-node | B10: 1 | C10: 1 | D10: 1 | E10: 2 | F10: 25 | G10: 70 | H10: 50 | I10: 100 | J10: 80 | K10: 0 | L10: =D10*F10 -> 25 | M10: =D10*G10 -> 70 | N10: =E10*H10 -> 100 | O10: =E10*I10 -> 200 | P10: =J10*3 -> 240 | Q10: =E10*K10 -> 0
A11: kube-proxy | B11: 1 | C11: 1 | D11: 1 | E11: 2 | F11: 100 | G11: 50 | H11: 100 | I11: 50 | J11: 60 | K11: 0 | L11: =D11*F11 -> 100 | M11: =D11*G11 -> 50 | N11: =E11*H11 -> 200 | O11: =E11*I11 -> 100 | P11: =J11*3 -> 180 | Q11: =E11*K11 -> 0
A12: coredns | B12: 1 | C12: 1 | D12: 1 | E12: 2 | F12: 100 | G12: 70 | H12: 100 | I12: 170 | J12: 40 | K12: 0 | L12: =D12*F12 -> 100 | M12: =D12*G12 -> 70 | N12: =E12*H12 -> 200 | O12: =E12*I12 -> 340 | P12: =J12*3 -> 120 | Q12: =E12*K12 -> 0
A13: efs-csi-controller | B13: 1 | C13: 1 | D13: 1 | E13: 2 | F13: 100 | G13: 128 | H13: 100 | I13: 128 | J13: 50 | K13: 0 | L13: =D13*F13 -> 100 | M13: =D13*G13 -> 128 | N13: =E13*H13 -> 200 | O13: =E13*I13 -> 256 | P13: =J13*3 -> 150 | Q13: =E13*K13 -> 0
A14: Metric Server | B14: 1 | C14: 1 | D14: 1 | E14: 2 | F14: 100 | G14: 200 | H14: 100 | I14: 200 | J14: 50 | K14: 0 | L14: =D14*F14 -> 100 | M14: =D14*G14 -> 200 | N14: =E14*H14 -> 200 | O14: =E14*I14 -> 400 | P14: =J14*3 -> 150 | Q14: =E14*K14 -> 0
A15: Cluster Autoscaler | B15: 1 | C15: 1 | D15: 1 | E15: 2 | F15: 100 | G15: 600 | H15: 100 | I15: 600 | J15: 50 | K15: 0 | L15: =D15*F15 -> 100 | M15: =D15*G15 -> 600 | N15: =E15*H15 -> 200 | O15: =E15*I15 -> 1200 | P15: =J15*3 -> 150 | Q15: =E15*K15 -> 0
A16: Crowdstrike Falcon
A17: Crowdstrike Falcon | B17: 1 | C17: 0 | D17: 0 | E17: 0 | F17: 250 | G17: 512 | H17: 1000 | I17: 2048 | J17: 1024 | K17: 0 | L17: =D17*F17 -> 0 | M17: =D17*G17 -> 0 | N17: =E17*H17 -> 0 | O17: =E17*I17 -> 0 | P17: =J17*3 -> 3072 | Q17: =E17*K17 -> 0
A18: Ingress Namespace
A19: ingress-nginx-controller | B19: 1 | C19: 1 | D19: 1 | E19: 2 | F19: 25 | G19: 100 | H19: 100 | I19: 100 | J19: 50 | K19: 0 | L19: =D19*F19 -> 25 | M19: =D19*G19 -> 100 | N19: =E19*H19 -> 200 | O19: =E19*I19 -> 200 | P19: =J19*3 -> 150 | Q19: =E19*K19 -> 0
A20: brokerverse-core Namespace
A21: bv-policy-admin-svc | B21: 1 | C21: 2 | D21: 2 | E21: 3 | F21: 500 | G21: 1024 | H21: 1500 | I21: 2048 | J21: 2048 | K21: 0 | L21: =D21*F21 -> 1000 | M21: =D21*G21 -> 2048 | N21: =E21*H21 -> 4500 | O21: =E21*I21 -> 6144 | P21: =J21*3 -> 6144 | Q21: =E21*H21 -> 4500
A22: bv-claims-svc | B22: 1 | C22: 2 | D22: 2 | E22: 3 | F22: 500 | G22: 1024 | H22: 1500 | I22: 2048 | J22: 2048 | K22: 0 | L22: =D22*F22 -> 1000 | M22: =D22*G22 -> 2048 | N22: =E22*H22 -> 4500 | O22: =E22*I22 -> 6144 | P22: =J22*3 -> 6144 | Q22: =E22*H22 -> 4500
A23: bv-billing-collections-svc | B23: 1 | C23: 2 | D23: 2 | E23: 3 | F23: 500 | G23: 1024 | H23: 1500 | I23: 2048 | J23: 2048 | K23: 0 | L23: =D23*F23 -> 1000 | M23: =D23*G23 -> 2048 | N23: =E23*H23 -> 4500 | O23: =E23*I23 -> 6144 | P23: =J23*3 -> 6144 | Q23: =E23*H23 -> 4500
A24: bv-distribution-svc | B24: 1 | C24: 2 | D24: 2 | E24: 3 | F24: 400 | G24: 768 | H24: 1200 | I24: 1536 | J24: 2048 | K24: 0 | L24: =D24*F24 -> 800 | M24: =D24*G24 -> 1536 | N24: =E24*H24 -> 3600 | O24: =E24*I24 -> 4608 | P24: =J24*3 -> 6144 | Q24: =E24*H24 -> 3600
A25: bv-web-portal | B25: 1 | C25: 2 | D25: 2 | E25: 3 | F25: 200 | G25: 256 | H25: 500 | I25: 512 | J25: 1024 | K25: 0 | L25: =D25*F25 -> 400 | M25: =D25*G25 -> 512 | N25: =E25*H25 -> 1500 | O25: =E25*I25 -> 1536 | P25: =J25*3 -> 3072 | Q25: =E25*H25 -> 1500
A26: brokerverse-platform Namespace
A27: bv-api-gateway | B27: 1 | C27: 2 | D27: 2 | E27: 3 | F27: 500 | G27: 512 | H27: 1000 | I27: 1024 | J27: 1024 | K27: 0 | L27: =D27*F27 -> 1000 | M27: =D27*G27 -> 1024 | N27: =E27*H27 -> 3000 | O27: =E27*I27 -> 3072 | P27: =J27*3 -> 3072 | Q27: =E27*H27 -> 3000
A28: bv-iam-svc | B28: 1 | C28: 2 | D28: 2 | E28: 3 | F28: 400 | G28: 768 | H28: 1000 | I28: 1536 | J28: 1024 | K28: 0 | L28: =D28*F28 -> 800 | M28: =D28*G28 -> 1536 | N28: =E28*H28 -> 3000 | O28: =E28*I28 -> 4608 | P28: =J28*3 -> 3072 | Q28: =E28*H28 -> 3000
A29: bv-integration-svc | B29: 1 | C29: 2 | D29: 2 | E29: 3 | F29: 500 | G29: 1024 | H29: 1500 | I29: 2048 | J29: 2048 | K29: 0 | L29: =D29*F29 -> 1000 | M29: =D29*G29 -> 2048 | N29: =E29*H29 -> 4500 | O29: =E29*I29 -> 6144 | P29: =J29*3 -> 6144 | Q29: =E29*H29 -> 4500
A30: bv-document-svc | B30: 1 | C30: 2 | D30: 2 | E30: 3 | F30: 400 | G30: 768 | H30: 1200 | I30: 1536 | J30: 2048 | K30: 20 | L30: =D30*F30 -> 800 | M30: =D30*G30 -> 1536 | N30: =E30*H30 -> 3600 | O30: =E30*I30 -> 4608 | P30: =J30*3 -> 6144 | Q30: =E30*H30 -> 3600
A31: bv-batch-notification-svc | B31: 1 | C31: 1 | D31: 1 | E31: 2 | F31: 400 | G31: 768 | H31: 1200 | I31: 1536 | J31: 2048 | K31: 0 | L31: =D31*F31 -> 400 | M31: =D31*G31 -> 768 | N31: =E31*H31 -> 2400 | O31: =E31*I31 -> 3072 | P31: =J31*3 -> 6144
A32: Total Applications | E32: =SUM(E5:E31) -> 51 | L32: =SUM(L5:L31) -> 9750 | M32: =SUM(M5:M31) -> 17602 | N32: =SUM(N5:N31) -> 39800 | O32: =SUM(O5:O31) -> 55432 | P32: =SUM(P5:P31) -> 105588 | Q32: =SUM(Q5:Q31) -> 32760
L33: =CEILING(L32/1024,1) -> 10 | M33: =CEILING(M32/1024,1) -> 18 | N33: =CEILING(N32/1024,1) -> 39 | O33: =CEILING(O32/1024,1) -> 55 | P33: =CEILING(P32/1024,1) -> 104 | Q33: =Q32 -> 32760
K34: with Threshold | L34: =CEILING(L33/E39,1) -> 13 | M34: =CEILING(M33/E39,1) -> 23 | N34: =CEILING(N33/E39,1) -> 50 | O34: =CEILING(O33/E39,1) -> 70 | P34: =CEILING(P33/E39,1) -> 132 | Q34: =CEILING(Q33/E39,1) -> 41469
K35: Worker Nodes | L35: CPUs | M35: GB of RAM | N35: CPUs | O35: GB of RAM | P35: EBS Disk Space (GB)per node | Q35: Disk Space (GB)
P36: Note: This was multiplied by 3 for caching, replica updates and retention updates use. | Q36: Note: PV should be stored on a separate storage preferrably EFS
A37: Worker Nodes - Recommended Sizing
A39: # of Worker nodes requested | B39: 2 | D39: Threshold | E39: 0.79
B40: Worker Node Size | C40: Instance Type | D40: Total Persistent Volume | E40: Needed ENI | F40: Total ENI Available
A41: CPU | B41: 16 | C41: m5.4xlarge (16x64) | D41: =Q33 -> 32760 | E41: =E32 -> 51 | F41: =B43*F52 -> 936
A42: RAM | B42: 64
A43: ENI per worker node | B43: 234
A46: Cluster Sizing Recommendation (for IA)
A47: Calculated # of Nodes
A48: TOTAL WORKER NODES BDOI | B48: Y1 | E48: TOTAL WORKER NODES BDOI | F48: Y1
B49: #of Nodes computed | C49: Y1 Requirement | F49: #of Nodes computed | G49: Y1 Requirement
A50: CPU | B50: =ROUNDUP(C50/B41,0) -> 1 | C50: =L34 -> 13 | E50: CPU | F50: =ROUNDUP(G50/B41,0) -> 4 | G50: =N34 -> 50
A51: RAM | B51: =ROUNDUP(C51/B42,0) -> 1 | C51: =M34 -> 23 | E51: RAM | F51: =ROUNDUP(G51/B42,0) -> 2 | G51: =O34 -> 70
A52: Minimum # of Nodes Needed | B52: =MAX(B50:B51) -> 1 | E52: Maximum # of Nodes Needed | F52: =MAX(F50:F51) -> 4
A55: Cost Analysis base on instance type
A56: Instance Type | B56: Required instance | C56: Amount per instance | D56: Total
A57: c5.2xlarge 8x16 | B57: 12 | C57: 286.16 | D57: =C57*B57 -> 3433.92
A58: c5.4xlarge 16x32 | B58: 7 | C58: 572.32 | D58: =C58*B58 -> 4006.24
A59: m5.2xlarge 8x32 | B59: 12 | C59: 350.4 | D59: =C59*B59 -> 4204.8
A60: r5.2xlarge 8x64 | B60: 12 | C60: 443.84 | D60: =C60*B60 -> 5326.08
A61: m5.4xlarge 16x64 | B61: 7 | C61: 700.8 | D61: =C61*B61 -> 4905.6
A62: r5.4xlarge 16x128 | B62: 7 | C62: 887.68 | D62: =C62*B62 -> 6213.76

Sheet K8S (PROD Cluster) Y1
A1: Kubernetes General Guidelines
A2: 1. The requestor must fill out the pod requirements.
A3: 2. The requestor should consider defining a Pod Disruption Budget (PDB).
A4: 3. The requestor must provide Y1–Y5 pod requirements based on the NFR/TPS for each year, corresponding to the required number of replicas.
A5: 4. Persistent Volumes (PV) should be hosted on separate storage, preferably on EFS.
A6: 5. Allocate container runtime storage based on each microservice’s image size and its runtime storage requirements.
A7: 6. When determining the appropriate instance type, the “Cost Analysis Based on Instance Type” table below may be used as a reference to compare costs.
A8: 7. Remove the kube-system namespace if the hosting environment is on AKS, and add another worker node group for the system pool instead.
A9: 8. Change the number of min and max replicas for Dyntrace and Crowdstrike based on the outcome of the total number worker nodes.
A10: 9. The requestor should provide autoscaling requirements, including the preferred autoscaling approach (e.g., HPA-Metric Server,Cluster Autoscale, KEDA (K8S Event-Driven Autoscaling and other)
A12: Kindly Fill Up for Cluster Sizing Request
A13: Worker Node Group
L14: MINIMUM | N14: MAXIMUM
A15: Dynatrace Namespace | B15: PDB Requirements | C15: Desired Replica | D15: Min Replicas | E15: Max Replicas | F15: Requests CPU (millicores) | G15: Requests Memory (M) | H15: Limits CPU (millicores) | I15: Limits Memory (M) | J15: Ephemeral Storage (MB) | K15: PV (GB) | L15: CPU | M15: Memory | N15: CPU | O15: Memory | P15: Ephemeral Storage per node | Q15: Total PV (GB) EFS | R15: Remarks
A16: Dynakube-Activegate | B16: 1 | C16: 1 | D16: 1 | E16: 2 | F16: 500 | G16: 512 | H16: 1000 | I16: 1536 | J16: =6*1024 -> 6144 | K16: 0 | L16: =D16*F16 -> 500 | M16: =D16*G16 -> 512 | N16: =E16*H16 -> 2000 | O16: =E16*I16 -> 3072 | P16: =J16*3 -> 18432 | Q16: =E16*K16 -> 0
A17: Dynakube-OneAgent | B17: 1 | C17: 0 | D17: 0 | E17: 0 | F17: 100 | G17: 512 | H17: 300 | I17: 1536 | J17: =1024*8 -> 8192 | K17: 30 | L17: =D17*F17 -> 0 | M17: =D17*G17 -> 0 | N17: =E17*H17 -> 0 | O17: =E17*I17 -> 0 | P17: =J17*3 -> 24576 | Q17: =E17*K17 -> 0
A18: Dynakube-Webhook | B18: 1 | C18: 1 | D18: 1 | E18: 2 | F18: 300 | G18: 128 | H18: 300 | I18: 128 | J18: =1024 -> 1024 | K18: 0 | L18: =D18*F18 -> 300 | M18: =D18*G18 -> 128 | N18: =E18*H18 -> 600 | O18: =E18*I18 -> 256 | P18: =J18*3 -> 3072 | Q18: =E18*K18 -> 0
A19: Dynakube-Operator | B19: 1 | C19: 1 | D19: 1 | E19: 2 | F19: 100 | G19: 128 | H19: 100 | I19: 128 | J19: 1024 | K19: 0 | L19: =D19*F19 -> 100 | M19: =D19*G19 -> 128 | N19: =E19*H19 -> 200 | O19: =E19*I19 -> 256 | P19: =J19*3 -> 3072 | Q19: =E19*K19 -> 0
A20: Kube-system Namespace
A21: aws-node | B21: 1 | C21: 1 | D21: 1 | E21: 2 | F21: 25 | G21: 70 | H21: 50 | I21: 100 | J21: 80 | K21: 0 | L21: =D21*F21 -> 25 | M21: =D21*G21 -> 70 | N21: =E21*H21 -> 100 | O21: =E21*I21 -> 200 | P21: =J21*3 -> 240 | Q21: =E21*K21 -> 0
A22: kube-proxy | B22: 1 | C22: 1 | D22: 1 | E22: 2 | F22: 100 | G22: 50 | H22: 100 | I22: 50 | J22: 60 | K22: 0 | L22: =D22*F22 -> 100 | M22: =D22*G22 -> 50 | N22: =E22*H22 -> 200 | O22: =E22*I22 -> 100 | P22: =J22*3 -> 180 | Q22: =E22*K22 -> 0
A23: coredns | B23: 1 | C23: 1 | D23: 1 | E23: 2 | F23: 100 | G23: 70 | H23: 100 | I23: 170 | J23: 40 | K23: 0 | L23: =D23*F23 -> 100 | M23: =D23*G23 -> 70 | N23: =E23*H23 -> 200 | O23: =E23*I23 -> 340 | P23: =J23*3 -> 120 | Q23: =E23*K23 -> 0
A24: efs-csi-controller | B24: 1 | C24: 1 | D24: 1 | E24: 2 | F24: 100 | G24: 128 | H24: 100 | I24: 128 | J24: 50 | K24: 0 | L24: =D24*F24 -> 100 | M24: =D24*G24 -> 128 | N24: =E24*H24 -> 200 | O24: =E24*I24 -> 256 | P24: =J24*3 -> 150 | Q24: =E24*K24 -> 0
A25: Metric Server | B25: 1 | C25: 1 | D25: 1 | E25: 2 | F25: 100 | G25: 200 | H25: 100 | I25: 200 | J25: 50 | K25: 0 | L25: =D25*F25 -> 100 | M25: =D25*G25 -> 200 | N25: =E25*H25 -> 200 | O25: =E25*I25 -> 400 | P25: =J25*3 -> 150 | Q25: =E25*K25 -> 0
A26: Cluster Autoscaler | B26: 1 | C26: 1 | D26: 1 | E26: 2 | F26: 100 | G26: 600 | H26: 100 | I26: 600 | J26: 50 | K26: 0 | L26: =D26*F26 -> 100 | M26: =D26*G26 -> 600 | N26: =E26*H26 -> 200 | O26: =E26*I26 -> 1200 | P26: =J26*3 -> 150 | Q26: =E26*K26 -> 0
A27: Crowdstrike Falcon
A28: Crowdstrike Falcon | B28: 1 | C28: 0 | D28: 0 | E28: 0 | F28: 250 | G28: 512 | H28: 1000 | I28: 2048 | J28: 1024 | K28: 0 | L28: =D28*F28 -> 0 | M28: =D28*G28 -> 0 | N28: =E28*H28 -> 0 | O28: =E28*I28 -> 0 | P28: =J28*3 -> 3072 | Q28: =E28*K28 -> 0
A29: Ingress Namespace
A30: ingress-nginx-controller | B30: 1 | C30: 1 | D30: 1 | E30: 2 | F30: 25 | G30: 100 | H30: 100 | I30: 100 | J30: 50 | K30: 0 | L30: =D30*F30 -> 25 | M30: =D30*G30 -> 100 | N30: =E30*H30 -> 200 | O30: =E30*I30 -> 200 | P30: =J30*3 -> 150 | Q30: =E30*K30 -> 0
A31: brokerverse-core Namespace
A32: bv-policy-admin-svc | B32: 1 | C32: 2 | D32: 2 | E32: 4 | F32: 500 | G32: 1024 | H32: 1500 | I32: 2048 | J32: 2048 | K32: 0 | L32: =D32*F32 -> 1000 | M32: =D32*G32 -> 2048 | N32: =E32*H32 -> 6000 | O32: =E32*I32 -> 8192 | P32: =J32*3 -> 6144 | Q32: =E32*H32 -> 6000
A33: bv-claims-svc | B33: 1 | C33: 2 | D33: 2 | E33: 4 | F33: 500 | G33: 1024 | H33: 1500 | I33: 2048 | J33: 2048 | K33: 0 | L33: =D33*F33 -> 1000 | M33: =D33*G33 -> 2048 | N33: =E33*H33 -> 6000 | O33: =E33*I33 -> 8192 | P33: =J33*3 -> 6144 | Q33: =E33*H33 -> 6000
A34: bv-billing-collections-svc | B34: 1 | C34: 2 | D34: 2 | E34: 4 | F34: 500 | G34: 1024 | H34: 1500 | I34: 2048 | J34: 2048 | K34: 0 | L34: =D34*F34 -> 1000 | M34: =D34*G34 -> 2048 | N34: =E34*H34 -> 6000 | O34: =E34*I34 -> 8192 | P34: =J34*3 -> 6144 | Q34: =E34*H34 -> 6000
A35: bv-distribution-svc | B35: 1 | C35: 2 | D35: 2 | E35: 4 | F35: 400 | G35: 768 | H35: 1200 | I35: 1536 | J35: 2048 | K35: 0 | L35: =D35*F35 -> 800 | M35: =D35*G35 -> 1536 | N35: =E35*H35 -> 4800 | O35: =E35*I35 -> 6144 | P35: =J35*3 -> 6144 | Q35: =E35*H35 -> 4800
A36: bv-web-portal | B36: 1 | C36: 2 | D36: 2 | E36: 4 | F36: 200 | G36: 256 | H36: 500 | I36: 512 | J36: 1024 | K36: 0 | L36: =D36*F36 -> 400 | M36: =D36*G36 -> 512 | N36: =E36*H36 -> 2000 | O36: =E36*I36 -> 2048 | P36: =J36*3 -> 3072 | Q36: =E36*H36 -> 2000
A37: brokerverse-platform Namespace
A38: bv-api-gateway | B38: 1 | C38: 2 | D38: 2 | E38: 4 | F38: 500 | G38: 512 | H38: 1000 | I38: 1024 | J38: 1024 | K38: 0 | L38: =D38*F38 -> 1000 | M38: =D38*G38 -> 1024 | N38: =E38*H38 -> 4000 | O38: =E38*I38 -> 4096 | P38: =J38*3 -> 3072 | Q38: =E38*H38 -> 4000
A39: bv-iam-svc | B39: 1 | C39: 2 | D39: 2 | E39: 4 | F39: 400 | G39: 768 | H39: 1000 | I39: 1536 | J39: 1024 | K39: 0 | L39: =D39*F39 -> 800 | M39: =D39*G39 -> 1536 | N39: =E39*H39 -> 4000 | O39: =E39*I39 -> 6144 | P39: =J39*3 -> 3072 | Q39: =E39*H39 -> 4000
A40: bv-integration-svc | B40: 1 | C40: 2 | D40: 2 | E40: 4 | F40: 500 | G40: 1024 | H40: 1500 | I40: 2048 | J40: 2048 | K40: 0 | L40: =D40*F40 -> 1000 | M40: =D40*G40 -> 2048 | N40: =E40*H40 -> 6000 | O40: =E40*I40 -> 8192 | P40: =J40*3 -> 6144 | Q40: =E40*H40 -> 6000
A41: bv-document-svc | B41: 1 | C41: 2 | D41: 2 | E41: 4 | F41: 400 | G41: 768 | H41: 1200 | I41: 1536 | J41: 2048 | K41: 20 | L41: =D41*F41 -> 800 | M41: =D41*G41 -> 1536 | N41: =E41*H41 -> 4800 | O41: =E41*I41 -> 6144 | P41: =J41*3 -> 6144 | Q41: =E41*H41 -> 4800
A42: bv-batch-notification-svc | B42: 1 | C42: 1 | D42: 1 | E42: 2 | F42: 400 | G42: 768 | H42: 1200 | I42: 1536 | J42: 2048 | K42: 0 | L42: =D42*F42 -> 400 | M42: =D42*G42 -> 768 | N42: =E42*H42 -> 2400 | O42: =E42*I42 -> 3072 | P42: =J42*3 -> 6144
A43: Total Applications | E43: =SUM(E16:E42) -> 58 | L43: =SUM(L16:L42) -> 9650 | M43: =SUM(M16:M42) -> 17090 | N43: =SUM(N16:N42) -> 50100 | O43: =SUM(O16:O42) -> 66696 | P43: =SUM(P16:P42) -> 105588 | Q43: =SUM(Q16:Q42) -> 43600
L44: =CEILING(L43/1024,1) -> 10 | M44: =CEILING(M43/1024,1) -> 17 | N44: =CEILING(N43/1024,1) -> 49 | O44: =CEILING(O43/1024,1) -> 66 | P44: =CEILING(P43/1024,1) -> 104 | Q44: =Q43 -> 43600
K45: with Threshold | L45: =CEILING(L44/E50,1) -> 13 | M45: =CEILING(M44/E50,1) -> 22 | N45: =CEILING(N44/E50,1) -> 63 | O45: =CEILING(O44/E50,1) -> 84 | P45: =CEILING(P44/E50,1) -> 132 | Q45: =CEILING(Q44/E50,1) -> 55190
K46: Worker Nodes | L46: CPUs | M46: GB of RAM | N46: CPUs | O46: GB of RAM | P46: EBS Disk Space (GB)per node | Q46: Disk Space (GB)
P47: Note: This was multiplied by 3 for caching, replica updates and retention updates use. | Q47: Note: PV should be stored on a separate storage preferrably EFS
A48: Worker Nodes - Recommended Sizing
A50: # of Worker nodes requested | B50: 3 | D50: Threshold | E50: 0.79
B51: Worker Node Size | C51: Instance Type | D51: Total Persistent Volume | E51: Needed ENI | F51: Total ENI Available
A52: CPU | B52: =VLOOKUP(C52,'Ref - ENI Max Pods'!A1:D24,2,FALSE()) -> 16 | C52: m5.4xlarge (16x64) | D52: =Q44 -> 43600 | E52: =E43 -> 58 | F52: =B54*F63 -> 936
A53: RAM | B53: =VLOOKUP(C52,'Ref - ENI Max Pods'!A2:D25,3,FALSE()) -> 64
A54: ENI per worker node | B54: =VLOOKUP(C52,'Ref - ENI Max Pods'!A3:D26,4,FALSE()) -> 234
A57: Cluster Sizing Recommendation (for IA)
A58: Calculated # of Nodes | I58: Cost Analysis base on instance type
A59: TOTAL WORKER NODES BDOI | B59: Y1 | E59: TOTAL WORKER NODES BDOI | F59: Y1 | I59: Instance Type | J59: Required instance | K59: Amount per instance | L59: Total
B60: #of Nodes computed | C60: Y1 Requirement | F60: #of Nodes computed | G60: Y1 Requirement | I60: c5.2xlarge 8x16 | J60: 12 | K60: 286.16 | L60: =K60*J60 -> 3433.92
A61: CPU | B61: =ROUNDUP(C61/B52,0) -> 1 | C61: =L45 -> 13 | E61: CPU | F61: =ROUNDUP(G61/B52,0) -> 4 | G61: =N45 -> 63 | I61: c5.4xlarge 16x32 | J61: 7 | K61: 572.32 | L61: =K61*J61 -> 4006.24
A62: RAM | B62: =ROUNDUP(C62/B53,0) -> 1 | C62: =M45 -> 22 | E62: RAM | F62: =ROUNDUP(G62/B53,0) -> 2 | G62: =O45 -> 84 | I62: m5.2xlarge 8x32 | J62: 12 | K62: 350.4 | L62: =K62*J62 -> 4204.8
A63: Minimum # of Nodes Needed | B63: =MAX(B61:B62) -> 1 | E63: Maximum # of Nodes Needed | F63: =MAX(F61:F62) -> 4 | I63: r5.2xlarge 8x64 | J63: 12 | K63: 443.84 | L63: =K63*J63 -> 5326.08
I64: m5.4xlarge 16x64 | J64: 7 | K64: 700.8 | L64: =K64*J64 -> 4905.6
I65: r5.4xlarge 16x128 | J65: 7 | K65: 887.68 | L65: =K65*J65 -> 6213.76

Sheet K8S (PROD Cluster) Y2
A1: Kubernetes General Guidelines
A2: 1. The requestor must fill out the pod requirements.
A3: 2. The requestor should consider defining a Pod Disruption Budget (PDB).
A4: 3. The requestor must provide Y1–Y5 pod requirements based on the NFR/TPS for each year, corresponding to the required number of replicas.
A5: 4. Persistent Volumes (PV) should be hosted on separate storage, preferably on EFS.
A6: 5. Allocate container runtime storage based on each microservice’s image size and its runtime storage requirements.
A7: 6. When determining the appropriate instance type, the “Cost Analysis Based on Instance Type” table below may be used as a reference to compare costs.
A8: 7. Remove the kube-system namespace if the hosting environment is on AKS, and add another worker node group for the system pool instead.
A9: 8. Change the number of min and max replicas for Dyntrace and Crowdstrike based on the outcome of the total number worker nodes.
A10: 9. The requestor should provide autoscaling requirements, including the preferred autoscaling approach (e.g., HPA-Metric Server,Cluster Autoscale, KEDA (K8S Event-Driven Autoscaling and other)
A12: Kindly Fill Up for Cluster Sizing Request
A13: Worker Node Group
L14: MINIMUM | N14: MAXIMUM
A15: Dynatrace Namespace | B15: PDB Requirements | C15: Desired Replica | D15: Min Replicas | E15: Max Replicas | F15: Requests CPU (millicores) | G15: Requests Memory (M) | H15: Limits CPU (millicores) | I15: Limits Memory (M) | J15: Ephemeral Storage (MB) | K15: PV (GB) | L15: CPU | M15: Memory | N15: CPU | O15: Memory | P15: Ephemeral Storage per node | Q15: Total PV (GB) EFS | R15: Remarks
A16: Dynakube-Activegate | B16: 1 | C16: 1 | D16: 1 | E16: 2 | F16: 500 | G16: 512 | H16: 1000 | I16: 1536 | J16: =6*1024 -> 6144 | K16: 0 | L16: =D16*F16 -> 500 | M16: =D16*G16 -> 512 | N16: =E16*H16 -> 2000 | O16: =E16*I16 -> 3072 | P16: =J16*3 -> 18432 | Q16: =E16*K16 -> 0
A17: Dynakube-OneAgent | B17: 1 | C17: 0 | D17: 0 | E17: 0 | F17: 100 | G17: 512 | H17: 300 | I17: 1536 | J17: =1024*8 -> 8192 | K17: 30 | L17: =D17*F17 -> 0 | M17: =D17*G17 -> 0 | N17: =E17*H17 -> 0 | O17: =E17*I17 -> 0 | P17: =J17*3 -> 24576 | Q17: =E17*K17 -> 0
A18: Dynakube-Webhook | B18: 1 | C18: 1 | D18: 1 | E18: 2 | F18: 300 | G18: 128 | H18: 300 | I18: 128 | J18: =1024 -> 1024 | K18: 0 | L18: =D18*F18 -> 300 | M18: =D18*G18 -> 128 | N18: =E18*H18 -> 600 | O18: =E18*I18 -> 256 | P18: =J18*3 -> 3072 | Q18: =E18*K18 -> 0
A19: Dynakube-Operator | B19: 1 | C19: 1 | D19: 1 | E19: 2 | F19: 100 | G19: 128 | H19: 100 | I19: 128 | J19: 1024 | K19: 0 | L19: =D19*F19 -> 100 | M19: =D19*G19 -> 128 | N19: =E19*H19 -> 200 | O19: =E19*I19 -> 256 | P19: =J19*3 -> 3072 | Q19: =E19*K19 -> 0
A20: Kube-system Namespace
A21: aws-node | B21: 1 | C21: 1 | D21: 1 | E21: 2 | F21: 25 | G21: 70 | H21: 50 | I21: 100 | J21: 80 | K21: 0 | L21: =D21*F21 -> 25 | M21: =D21*G21 -> 70 | N21: =E21*H21 -> 100 | O21: =E21*I21 -> 200 | P21: =J21*3 -> 240 | Q21: =E21*K21 -> 0
A22: kube-proxy | B22: 1 | C22: 1 | D22: 1 | E22: 2 | F22: 100 | G22: 50 | H22: 100 | I22: 50 | J22: 60 | K22: 0 | L22: =D22*F22 -> 100 | M22: =D22*G22 -> 50 | N22: =E22*H22 -> 200 | O22: =E22*I22 -> 100 | P22: =J22*3 -> 180 | Q22: =E22*K22 -> 0
A23: coredns | B23: 1 | C23: 1 | D23: 1 | E23: 2 | F23: 100 | G23: 70 | H23: 100 | I23: 170 | J23: 40 | K23: 0 | L23: =D23*F23 -> 100 | M23: =D23*G23 -> 70 | N23: =E23*H23 -> 200 | O23: =E23*I23 -> 340 | P23: =J23*3 -> 120 | Q23: =E23*K23 -> 0
A24: efs-csi-controller | B24: 1 | C24: 1 | D24: 1 | E24: 2 | F24: 100 | G24: 128 | H24: 100 | I24: 128 | J24: 50 | K24: 0 | L24: =D24*F24 -> 100 | M24: =D24*G24 -> 128 | N24: =E24*H24 -> 200 | O24: =E24*I24 -> 256 | P24: =J24*3 -> 150 | Q24: =E24*K24 -> 0
A25: Metric Server | B25: 1 | C25: 1 | D25: 1 | E25: 2 | F25: 100 | G25: 200 | H25: 100 | I25: 200 | J25: 50 | K25: 0 | L25: =D25*F25 -> 100 | M25: =D25*G25 -> 200 | N25: =E25*H25 -> 200 | O25: =E25*I25 -> 400 | P25: =J25*3 -> 150 | Q25: =E25*K25 -> 0
A26: Cluster Autoscaler | B26: 1 | C26: 1 | D26: 1 | E26: 2 | F26: 100 | G26: 600 | H26: 100 | I26: 600 | J26: 50 | K26: 0 | L26: =D26*F26 -> 100 | M26: =D26*G26 -> 600 | N26: =E26*H26 -> 200 | O26: =E26*I26 -> 1200 | P26: =J26*3 -> 150 | Q26: =E26*K26 -> 0
A27: Crowdstrike Falcon
A28: Crowdstrike Falcon | B28: 1 | C28: 0 | D28: 0 | E28: 0 | F28: 250 | G28: 512 | H28: 1000 | I28: 2048 | J28: 1024 | K28: 0 | L28: =D28*F28 -> 0 | M28: =D28*G28 -> 0 | N28: =E28*H28 -> 0 | O28: =E28*I28 -> 0 | P28: =J28*3 -> 3072 | Q28: =E28*K28 -> 0
A29: Ingress Namespace
A30: ingress-nginx-controller | B30: 1 | C30: 1 | D30: 1 | E30: 2 | F30: 25 | G30: 100 | H30: 100 | I30: 100 | J30: 50 | K30: 0 | L30: =D30*F30 -> 25 | M30: =D30*G30 -> 100 | N30: =E30*H30 -> 200 | O30: =E30*I30 -> 200 | P30: =J30*3 -> 150 | Q30: =E30*K30 -> 0
A31: brokerverse-core Namespace
A32: bv-policy-admin-svc | B32: 1 | C32: 2 | D32: 2 | E32: 5 | F32: 500 | G32: 1024 | H32: 1500 | I32: 2048 | J32: 2048 | K32: 0 | L32: =D32*F32 -> 1000 | M32: =D32*G32 -> 2048 | N32: =E32*H32 -> 7500 | O32: =E32*I32 -> 10240 | P32: =J32*3 -> 6144 | Q32: =E32*H32 -> 7500
A33: bv-claims-svc | B33: 1 | C33: 2 | D33: 2 | E33: 5 | F33: 500 | G33: 1024 | H33: 1500 | I33: 2048 | J33: 2048 | K33: 0 | L33: =D33*F33 -> 1000 | M33: =D33*G33 -> 2048 | N33: =E33*H33 -> 7500 | O33: =E33*I33 -> 10240 | P33: =J33*3 -> 6144 | Q33: =E33*H33 -> 7500
A34: bv-billing-collections-svc | B34: 1 | C34: 2 | D34: 2 | E34: 5 | F34: 500 | G34: 1024 | H34: 1500 | I34: 2048 | J34: 2048 | K34: 0 | L34: =D34*F34 -> 1000 | M34: =D34*G34 -> 2048 | N34: =E34*H34 -> 7500 | O34: =E34*I34 -> 10240 | P34: =J34*3 -> 6144 | Q34: =E34*H34 -> 7500
A35: bv-distribution-svc | B35: 1 | C35: 2 | D35: 2 | E35: 5 | F35: 400 | G35: 768 | H35: 1200 | I35: 1536 | J35: 2048 | K35: 0 | L35: =D35*F35 -> 800 | M35: =D35*G35 -> 1536 | N35: =E35*H35 -> 6000 | O35: =E35*I35 -> 7680 | P35: =J35*3 -> 6144 | Q35: =E35*H35 -> 6000
A36: bv-web-portal | B36: 1 | C36: 2 | D36: 2 | E36: 5 | F36: 200 | G36: 256 | H36: 500 | I36: 512 | J36: 1024 | K36: 0 | L36: =D36*F36 -> 400 | M36: =D36*G36 -> 512 | N36: =E36*H36 -> 2500 | O36: =E36*I36 -> 2560 | P36: =J36*3 -> 3072 | Q36: =E36*H36 -> 2500
A37: brokerverse-platform Namespace
A38: bv-api-gateway | B38: 1 | C38: 2 | D38: 2 | E38: 5 | F38: 500 | G38: 512 | H38: 1000 | I38: 1024 | J38: 1024 | K38: 0 | L38: =D38*F38 -> 1000 | M38: =D38*G38 -> 1024 | N38: =E38*H38 -> 5000 | O38: =E38*I38 -> 5120 | P38: =J38*3 -> 3072 | Q38: =E38*H38 -> 5000
A39: bv-iam-svc | B39: 1 | C39: 2 | D39: 2 | E39: 5 | F39: 400 | G39: 768 | H39: 1000 | I39: 1536 | J39: 1024 | K39: 0 | L39: =D39*F39 -> 800 | M39: =D39*G39 -> 1536 | N39: =E39*H39 -> 5000 | O39: =E39*I39 -> 7680 | P39: =J39*3 -> 3072 | Q39: =E39*H39 -> 5000
A40: bv-integration-svc | B40: 1 | C40: 2 | D40: 2 | E40: 5 | F40: 500 | G40: 1024 | H40: 1500 | I40: 2048 | J40: 2048 | K40: 0 | L40: =D40*F40 -> 1000 | M40: =D40*G40 -> 2048 | N40: =E40*H40 -> 7500 | O40: =E40*I40 -> 10240 | P40: =J40*3 -> 6144 | Q40: =E40*H40 -> 7500
A41: bv-document-svc | B41: 1 | C41: 2 | D41: 2 | E41: 5 | F41: 400 | G41: 768 | H41: 1200 | I41: 1536 | J41: 2048 | K41: 20 | L41: =D41*F41 -> 800 | M41: =D41*G41 -> 1536 | N41: =E41*H41 -> 6000 | O41: =E41*I41 -> 7680 | P41: =J41*3 -> 6144 | Q41: =E41*H41 -> 6000
A42: bv-batch-notification-svc | B42: 1 | C42: 1 | D42: 1 | E42: 2 | F42: 400 | G42: 768 | H42: 1200 | I42: 1536 | J42: 2048 | K42: 0 | L42: =D42*F42 -> 400 | M42: =D42*G42 -> 768 | N42: =E42*H42 -> 2400 | O42: =E42*I42 -> 3072 | P42: =J42*3 -> 6144
A43: Total Applications | E43: =SUM(E16:E42) -> 67 | L43: =SUM(L16:L42) -> 9650 | M43: =SUM(M16:M42) -> 17090 | N43: =SUM(N16:N42) -> 61000 | O43: =SUM(O16:O42) -> 81032 | P43: =SUM(P16:P42) -> 105588 | Q43: =SUM(Q16:Q42) -> 54500
L44: =CEILING(L43/1024,1) -> 10 | M44: =CEILING(M43/1024,1) -> 17 | N44: =CEILING(N43/1024,1) -> 60 | O44: =CEILING(O43/1024,1) -> 80 | P44: =CEILING(P43/1024,1) -> 104 | Q44: =Q43 -> 54500
K45: with Threshold | L45: =CEILING(L44/E50,1) -> 13 | M45: =CEILING(M44/E50,1) -> 22 | N45: =CEILING(N44/E50,1) -> 76 | O45: =CEILING(O44/E50,1) -> 102 | P45: =CEILING(P44/E50,1) -> 132 | Q45: =CEILING(Q44/E50,1) -> 68988
K46: Worker Nodes | L46: CPUs | M46: GB of RAM | N46: CPUs | O46: GB of RAM | P46: EBS Disk Space (GB)per node | Q46: Disk Space (GB)
P47: Note: This was multiplied by 3 for caching, replica updates and retention updates use. | Q47: Note: PV should be stored on a separate storage preferrably EFS
A48: Worker Nodes - Recommended Sizing
A50: # of Worker nodes requested | B50: 3 | D50: Threshold | E50: 0.79
B51: Worker Node Size | C51: Instance Type | D51: Total Persistent Volume | E51: Needed ENI | F51: Total ENI Available
A52: CPU | B52: =VLOOKUP(C52,'Ref - ENI Max Pods'!A1:D24,2,FALSE()) -> 16 | C52: m5.4xlarge (16x64) | D52: =Q44 -> 54500 | E52: =E43 -> 67 | F52: =B54*F63 -> 1170
A53: RAM | B53: =VLOOKUP(C52,'Ref - ENI Max Pods'!A2:D25,3,FALSE()) -> 64
A54: ENI per worker node | B54: =VLOOKUP(C52,'Ref - ENI Max Pods'!A3:D26,4,FALSE()) -> 234
A57: Cluster Sizing Recommendation (for IA)
A58: Calculated # of Nodes | I58: Cost Analysis base on instance type
A59: TOTAL WORKER NODES BDOI | B59: Y2 | E59: TOTAL WORKER NODES BDOI | F59: Y2 | I59: Instance Type | J59: Required instance | K59: Amount per instance | L59: Total
B60: #of Nodes computed | C60: Y1 Requirement | F60: #of Nodes computed | G60: Y1 Requirement | I60: c5.2xlarge 8x16 | J60: 12 | K60: 286.16 | L60: =K60*J60 -> 3433.92
A61: CPU | B61: =ROUNDUP(C61/B52,0) -> 1 | C61: =L45 -> 13 | E61: CPU | F61: =ROUNDUP(G61/B52,0) -> 5 | G61: =N45 -> 76 | I61: c5.4xlarge 16x32 | J61: 7 | K61: 572.32 | L61: =K61*J61 -> 4006.24
A62: RAM | B62: =ROUNDUP(C62/B53,0) -> 1 | C62: =M45 -> 22 | E62: RAM | F62: =ROUNDUP(G62/B53,0) -> 2 | G62: =O45 -> 102 | I62: m5.2xlarge 8x32 | J62: 12 | K62: 350.4 | L62: =K62*J62 -> 4204.8
A63: Minimum # of Nodes Needed | B63: =MAX(B61:B62) -> 1 | E63: Maximum # of Nodes Needed | F63: =MAX(F61:F62) -> 5 | I63: r5.2xlarge 8x64 | J63: 12 | K63: 443.84 | L63: =K63*J63 -> 5326.08
I64: m5.4xlarge 16x64 | J64: 7 | K64: 700.8 | L64: =K64*J64 -> 4905.6
I65: r5.4xlarge 16x128 | J65: 7 | K65: 887.68 | L65: =K65*J65 -> 6213.76

Sheet K8S (PROD Cluster) Y3
A1: Kubernetes General Guidelines
A2: 1. The requestor must fill out the pod requirements.
A3: 2. The requestor should consider defining a Pod Disruption Budget (PDB).
A4: 3. The requestor must provide Y1–Y5 pod requirements based on the NFR/TPS for each year, corresponding to the required number of replicas.
A5: 4. Persistent Volumes (PV) should be hosted on separate storage, preferably on EFS.
A6: 5. Allocate container runtime storage based on each microservice’s image size and its runtime storage requirements.
A7: 6. When determining the appropriate instance type, the “Cost Analysis Based on Instance Type” table below may be used as a reference to compare costs.
A8: 7. Remove the kube-system namespace if the hosting environment is on AKS, and add another worker node group for the system pool instead.
A9: 8. Change the number of min and max replicas for Dyntrace and Crowdstrike based on the outcome of the total number worker nodes.
A10: 9. The requestor should provide autoscaling requirements, including the preferred autoscaling approach (e.g., HPA-Metric Server,Cluster Autoscale, KEDA (K8S Event-Driven Autoscaling and other)
A12: Kindly Fill Up for Cluster Sizing Request
A13: Worker Node Group
L14: MINIMUM | N14: MAXIMUM
A15: Dynatrace Namespace | B15: PDB Requirements | C15: Desired Replica | D15: Min Replicas | E15: Max Replicas | F15: Requests CPU (millicores) | G15: Requests Memory (M) | H15: Limits CPU (millicores) | I15: Limits Memory (M) | J15: Ephemeral Storage (MB) | K15: PV (GB) | L15: CPU | M15: Memory | N15: CPU | O15: Memory | P15: Ephemeral Storage per node | Q15: Total PV (GB) EFS | R15: Remarks
A16: Dynakube-Activegate | B16: 1 | C16: 1 | D16: 1 | E16: 2 | F16: 500 | G16: 512 | H16: 1000 | I16: 1536 | J16: =6*1024 -> 6144 | K16: 0 | L16: =D16*F16 -> 500 | M16: =D16*G16 -> 512 | N16: =E16*H16 -> 2000 | O16: =E16*I16 -> 3072 | P16: =J16*3 -> 18432 | Q16: =E16*K16 -> 0
A17: Dynakube-OneAgent | B17: 1 | C17: 0 | D17: 0 | E17: 0 | F17: 100 | G17: 512 | H17: 300 | I17: 1536 | J17: =1024*8 -> 8192 | K17: 30 | L17: =D17*F17 -> 0 | M17: =D17*G17 -> 0 | N17: =E17*H17 -> 0 | O17: =E17*I17 -> 0 | P17: =J17*3 -> 24576 | Q17: =E17*K17 -> 0
A18: Dynakube-Webhook | B18: 1 | C18: 1 | D18: 1 | E18: 2 | F18: 300 | G18: 128 | H18: 300 | I18: 128 | J18: =1024 -> 1024 | K18: 0 | L18: =D18*F18 -> 300 | M18: =D18*G18 -> 128 | N18: =E18*H18 -> 600 | O18: =E18*I18 -> 256 | P18: =J18*3 -> 3072 | Q18: =E18*K18 -> 0
A19: Dynakube-Operator | B19: 1 | C19: 1 | D19: 1 | E19: 2 | F19: 100 | G19: 128 | H19: 100 | I19: 128 | J19: 1024 | K19: 0 | L19: =D19*F19 -> 100 | M19: =D19*G19 -> 128 | N19: =E19*H19 -> 200 | O19: =E19*I19 -> 256 | P19: =J19*3 -> 3072 | Q19: =E19*K19 -> 0
A20: Kube-system Namespace
A21: aws-node | B21: 1 | C21: 1 | D21: 1 | E21: 2 | F21: 25 | G21: 70 | H21: 50 | I21: 100 | J21: 80 | K21: 0 | L21: =D21*F21 -> 25 | M21: =D21*G21 -> 70 | N21: =E21*H21 -> 100 | O21: =E21*I21 -> 200 | P21: =J21*3 -> 240 | Q21: =E21*K21 -> 0
A22: kube-proxy | B22: 1 | C22: 1 | D22: 1 | E22: 2 | F22: 100 | G22: 50 | H22: 100 | I22: 50 | J22: 60 | K22: 0 | L22: =D22*F22 -> 100 | M22: =D22*G22 -> 50 | N22: =E22*H22 -> 200 | O22: =E22*I22 -> 100 | P22: =J22*3 -> 180 | Q22: =E22*K22 -> 0
A23: coredns | B23: 1 | C23: 1 | D23: 1 | E23: 2 | F23: 100 | G23: 70 | H23: 100 | I23: 170 | J23: 40 | K23: 0 | L23: =D23*F23 -> 100 | M23: =D23*G23 -> 70 | N23: =E23*H23 -> 200 | O23: =E23*I23 -> 340 | P23: =J23*3 -> 120 | Q23: =E23*K23 -> 0
A24: efs-csi-controller | B24: 1 | C24: 1 | D24: 1 | E24: 2 | F24: 100 | G24: 128 | H24: 100 | I24: 128 | J24: 50 | K24: 0 | L24: =D24*F24 -> 100 | M24: =D24*G24 -> 128 | N24: =E24*H24 -> 200 | O24: =E24*I24 -> 256 | P24: =J24*3 -> 150 | Q24: =E24*K24 -> 0
A25: Metric Server | B25: 1 | C25: 1 | D25: 1 | E25: 2 | F25: 100 | G25: 200 | H25: 100 | I25: 200 | J25: 50 | K25: 0 | L25: =D25*F25 -> 100 | M25: =D25*G25 -> 200 | N25: =E25*H25 -> 200 | O25: =E25*I25 -> 400 | P25: =J25*3 -> 150 | Q25: =E25*K25 -> 0
A26: Cluster Autoscaler | B26: 1 | C26: 1 | D26: 1 | E26: 2 | F26: 100 | G26: 600 | H26: 100 | I26: 600 | J26: 50 | K26: 0 | L26: =D26*F26 -> 100 | M26: =D26*G26 -> 600 | N26: =E26*H26 -> 200 | O26: =E26*I26 -> 1200 | P26: =J26*3 -> 150 | Q26: =E26*K26 -> 0
A27: Crowdstrike Falcon
A28: Crowdstrike Falcon | B28: 1 | C28: 0 | D28: 0 | E28: 0 | F28: 250 | G28: 512 | H28: 1000 | I28: 2048 | J28: 1024 | K28: 0 | L28: =D28*F28 -> 0 | M28: =D28*G28 -> 0 | N28: =E28*H28 -> 0 | O28: =E28*I28 -> 0 | P28: =J28*3 -> 3072 | Q28: =E28*K28 -> 0
A29: Ingress Namespace
A30: ingress-nginx-controller | B30: 1 | C30: 1 | D30: 1 | E30: 2 | F30: 25 | G30: 100 | H30: 100 | I30: 100 | J30: 50 | K30: 0 | L30: =D30*F30 -> 25 | M30: =D30*G30 -> 100 | N30: =E30*H30 -> 200 | O30: =E30*I30 -> 200 | P30: =J30*3 -> 150 | Q30: =E30*K30 -> 0
A31: brokerverse-core Namespace
A32: bv-policy-admin-svc | B32: 1 | C32: 3 | D32: 3 | E32: 6 | F32: 500 | G32: 1024 | H32: 1500 | I32: 2048 | J32: 2048 | K32: 0 | L32: =D32*F32 -> 1500 | M32: =D32*G32 -> 3072 | N32: =E32*H32 -> 9000 | O32: =E32*I32 -> 12288 | P32: =J32*3 -> 6144 | Q32: =E32*H32 -> 9000
A33: bv-claims-svc | B33: 1 | C33: 3 | D33: 3 | E33: 6 | F33: 500 | G33: 1024 | H33: 1500 | I33: 2048 | J33: 2048 | K33: 0 | L33: =D33*F33 -> 1500 | M33: =D33*G33 -> 3072 | N33: =E33*H33 -> 9000 | O33: =E33*I33 -> 12288 | P33: =J33*3 -> 6144 | Q33: =E33*H33 -> 9000
A34: bv-billing-collections-svc | B34: 1 | C34: 3 | D34: 3 | E34: 6 | F34: 500 | G34: 1024 | H34: 1500 | I34: 2048 | J34: 2048 | K34: 0 | L34: =D34*F34 -> 1500 | M34: =D34*G34 -> 3072 | N34: =E34*H34 -> 9000 | O34: =E34*I34 -> 12288 | P34: =J34*3 -> 6144 | Q34: =E34*H34 -> 9000
A35: bv-distribution-svc | B35: 1 | C35: 3 | D35: 3 | E35: 6 | F35: 400 | G35: 768 | H35: 1200 | I35: 1536 | J35: 2048 | K35: 0 | L35: =D35*F35 -> 1200 | M35: =D35*G35 -> 2304 | N35: =E35*H35 -> 7200 | O35: =E35*I35 -> 9216 | P35: =J35*3 -> 6144 | Q35: =E35*H35 -> 7200
A36: bv-web-portal | B36: 1 | C36: 3 | D36: 3 | E36: 6 | F36: 200 | G36: 256 | H36: 500 | I36: 512 | J36: 1024 | K36: 0 | L36: =D36*F36 -> 600 | M36: =D36*G36 -> 768 | N36: =E36*H36 -> 3000 | O36: =E36*I36 -> 3072 | P36: =J36*3 -> 3072 | Q36: =E36*H36 -> 3000
A37: brokerverse-platform Namespace
A38: bv-api-gateway | B38: 1 | C38: 3 | D38: 3 | E38: 6 | F38: 500 | G38: 512 | H38: 1000 | I38: 1024 | J38: 1024 | K38: 0 | L38: =D38*F38 -> 1500 | M38: =D38*G38 -> 1536 | N38: =E38*H38 -> 6000 | O38: =E38*I38 -> 6144 | P38: =J38*3 -> 3072 | Q38: =E38*H38 -> 6000
A39: bv-iam-svc | B39: 1 | C39: 3 | D39: 3 | E39: 6 | F39: 400 | G39: 768 | H39: 1000 | I39: 1536 | J39: 1024 | K39: 0 | L39: =D39*F39 -> 1200 | M39: =D39*G39 -> 2304 | N39: =E39*H39 -> 6000 | O39: =E39*I39 -> 9216 | P39: =J39*3 -> 3072 | Q39: =E39*H39 -> 6000
A40: bv-integration-svc | B40: 1 | C40: 3 | D40: 3 | E40: 6 | F40: 500 | G40: 1024 | H40: 1500 | I40: 2048 | J40: 2048 | K40: 0 | L40: =D40*F40 -> 1500 | M40: =D40*G40 -> 3072 | N40: =E40*H40 -> 9000 | O40: =E40*I40 -> 12288 | P40: =J40*3 -> 6144 | Q40: =E40*H40 -> 9000
A41: bv-document-svc | B41: 1 | C41: 3 | D41: 3 | E41: 6 | F41: 400 | G41: 768 | H41: 1200 | I41: 1536 | J41: 2048 | K41: 20 | L41: =D41*F41 -> 1200 | M41: =D41*G41 -> 2304 | N41: =E41*H41 -> 7200 | O41: =E41*I41 -> 9216 | P41: =J41*3 -> 6144 | Q41: =E41*H41 -> 7200
A42: bv-batch-notification-svc | B42: 1 | C42: 2 | D42: 2 | E42: 3 | F42: 400 | G42: 768 | H42: 1200 | I42: 1536 | J42: 2048 | K42: 0 | L42: =D42*F42 -> 800 | M42: =D42*G42 -> 1536 | N42: =E42*H42 -> 3600 | O42: =E42*I42 -> 4608 | P42: =J42*3 -> 6144
A43: Total Applications | E43: =SUM(E16:E42) -> 77 | L43: =SUM(L16:L42) -> 13950 | M43: =SUM(M16:M42) -> 25026 | N43: =SUM(N16:N42) -> 73100 | O43: =SUM(O16:O42) -> 96904 | P43: =SUM(P16:P42) -> 105588 | Q43: =SUM(Q16:Q42) -> 65400
L44: =CEILING(L43/1024,1) -> 14 | M44: =CEILING(M43/1024,1) -> 25 | N44: =CEILING(N43/1024,1) -> 72 | O44: =CEILING(O43/1024,1) -> 95 | P44: =CEILING(P43/1024,1) -> 104 | Q44: =Q43 -> 65400
K45: with Threshold | L45: =CEILING(L44/E50,1) -> 18 | M45: =CEILING(M44/E50,1) -> 32 | N45: =CEILING(N44/E50,1) -> 92 | O45: =CEILING(O44/E50,1) -> 121 | P45: =CEILING(P44/E50,1) -> 132 | Q45: =CEILING(Q44/E50,1) -> 82785
K46: Worker Nodes | L46: CPUs | M46: GB of RAM | N46: CPUs | O46: GB of RAM | P46: EBS Disk Space (GB)per node | Q46: Disk Space (GB)
P47: Note: This was multiplied by 3 for caching, replica updates and retention updates use. | Q47: Note: PV should be stored on a separate storage preferrably EFS
A48: Worker Nodes - Recommended Sizing
A50: # of Worker nodes requested | B50: 4 | D50: Threshold | E50: 0.79
B51: Worker Node Size | C51: Instance Type | D51: Total Persistent Volume | E51: Needed ENI | F51: Total ENI Available
A52: CPU | B52: =VLOOKUP(C52,'Ref - ENI Max Pods'!A1:D24,2,FALSE()) -> 16 | C52: m5.4xlarge (16x64) | D52: =Q44 -> 65400 | E52: =E43 -> 77 | F52: =B54*F63 -> 1404
A53: RAM | B53: =VLOOKUP(C52,'Ref - ENI Max Pods'!A2:D25,3,FALSE()) -> 64
A54: ENI per worker node | B54: =VLOOKUP(C52,'Ref - ENI Max Pods'!A3:D26,4,FALSE()) -> 234
A57: Cluster Sizing Recommendation (for IA)
A58: Calculated # of Nodes | I58: Cost Analysis base on instance type
A59: TOTAL WORKER NODES BDOI | B59: Y3 | E59: TOTAL WORKER NODES BDOI | F59: Y3 | I59: Instance Type | J59: Required instance | K59: Amount per instance | L59: Total
B60: #of Nodes computed | C60: Y1 Requirement | F60: #of Nodes computed | G60: Y1 Requirement | I60: c5.2xlarge 8x16 | J60: 12 | K60: 286.16 | L60: =K60*J60 -> 3433.92
A61: CPU | B61: =ROUNDUP(C61/B52,0) -> 2 | C61: =L45 -> 18 | E61: CPU | F61: =ROUNDUP(G61/B52,0) -> 6 | G61: =N45 -> 92 | I61: c5.4xlarge 16x32 | J61: 7 | K61: 572.32 | L61: =K61*J61 -> 4006.24
A62: RAM | B62: =ROUNDUP(C62/B53,0) -> 1 | C62: =M45 -> 32 | E62: RAM | F62: =ROUNDUP(G62/B53,0) -> 2 | G62: =O45 -> 121 | I62: m5.2xlarge 8x32 | J62: 12 | K62: 350.4 | L62: =K62*J62 -> 4204.8
A63: Minimum # of Nodes Needed | B63: =MAX(B61:B62) -> 2 | E63: Maximum # of Nodes Needed | F63: =MAX(F61:F62) -> 6 | I63: r5.2xlarge 8x64 | J63: 12 | K63: 443.84 | L63: =K63*J63 -> 5326.08
I64: m5.4xlarge 16x64 | J64: 7 | K64: 700.8 | L64: =K64*J64 -> 4905.6
I65: r5.4xlarge 16x128 | J65: 7 | K65: 887.68 | L65: =K65*J65 -> 6213.76

Sheet K8S (PROD Cluster) Y4
A1: Kubernetes General Guidelines
A2: 1. The requestor must fill out the pod requirements.
A3: 2. The requestor should consider defining a Pod Disruption Budget (PDB).
A4: 3. The requestor must provide Y1–Y5 pod requirements based on the NFR/TPS for each year, corresponding to the required number of replicas.
A5: 4. Persistent Volumes (PV) should be hosted on separate storage, preferably on EFS.
A6: 5. Allocate container runtime storage based on each microservice’s image size and its runtime storage requirements.
A7: 6. When determining the appropriate instance type, the “Cost Analysis Based on Instance Type” table below may be used as a reference to compare costs.
A8: 7. Remove the kube-system namespace if the hosting environment is on AKS, and add another worker node group for the system pool instead.
A9: 8. Change the number of min and max replicas for Dyntrace and Crowdstrike based on the outcome of the total number worker nodes.
A10: 9. The requestor should provide autoscaling requirements, including the preferred autoscaling approach (e.g., HPA-Metric Server,Cluster Autoscale, KEDA (K8S Event-Driven Autoscaling and other)
A12: Kindly Fill Up for Cluster Sizing Request
A13: Worker Node Group
L14: MINIMUM | N14: MAXIMUM
A15: Dynatrace Namespace | B15: PDB Requirements | C15: Desired Replica | D15: Min Replicas | E15: Max Replicas | F15: Requests CPU (millicores) | G15: Requests Memory (M) | H15: Limits CPU (millicores) | I15: Limits Memory (M) | J15: Ephemeral Storage (MB) | K15: PV (GB) | L15: CPU | M15: Memory | N15: CPU | O15: Memory | P15: Ephemeral Storage per node | Q15: Total PV (GB) EFS | R15: Remarks
A16: Dynakube-Activegate | B16: 1 | C16: 1 | D16: 1 | E16: 2 | F16: 500 | G16: 512 | H16: 1000 | I16: 1536 | J16: =6*1024 -> 6144 | K16: 0 | L16: =D16*F16 -> 500 | M16: =D16*G16 -> 512 | N16: =E16*H16 -> 2000 | O16: =E16*I16 -> 3072 | P16: =J16*3 -> 18432 | Q16: =E16*K16 -> 0
A17: Dynakube-OneAgent | B17: 1 | C17: 0 | D17: 0 | E17: 0 | F17: 100 | G17: 512 | H17: 300 | I17: 1536 | J17: =1024*8 -> 8192 | K17: 30 | L17: =D17*F17 -> 0 | M17: =D17*G17 -> 0 | N17: =E17*H17 -> 0 | O17: =E17*I17 -> 0 | P17: =J17*3 -> 24576 | Q17: =E17*K17 -> 0
A18: Dynakube-Webhook | B18: 1 | C18: 1 | D18: 1 | E18: 2 | F18: 300 | G18: 128 | H18: 300 | I18: 128 | J18: =1024 -> 1024 | K18: 0 | L18: =D18*F18 -> 300 | M18: =D18*G18 -> 128 | N18: =E18*H18 -> 600 | O18: =E18*I18 -> 256 | P18: =J18*3 -> 3072 | Q18: =E18*K18 -> 0
A19: Dynakube-Operator | B19: 1 | C19: 1 | D19: 1 | E19: 2 | F19: 100 | G19: 128 | H19: 100 | I19: 128 | J19: 1024 | K19: 0 | L19: =D19*F19 -> 100 | M19: =D19*G19 -> 128 | N19: =E19*H19 -> 200 | O19: =E19*I19 -> 256 | P19: =J19*3 -> 3072 | Q19: =E19*K19 -> 0
A20: Kube-system Namespace
A21: aws-node | B21: 1 | C21: 1 | D21: 1 | E21: 2 | F21: 25 | G21: 70 | H21: 50 | I21: 100 | J21: 80 | K21: 0 | L21: =D21*F21 -> 25 | M21: =D21*G21 -> 70 | N21: =E21*H21 -> 100 | O21: =E21*I21 -> 200 | P21: =J21*3 -> 240 | Q21: =E21*K21 -> 0
A22: kube-proxy | B22: 1 | C22: 1 | D22: 1 | E22: 2 | F22: 100 | G22: 50 | H22: 100 | I22: 50 | J22: 60 | K22: 0 | L22: =D22*F22 -> 100 | M22: =D22*G22 -> 50 | N22: =E22*H22 -> 200 | O22: =E22*I22 -> 100 | P22: =J22*3 -> 180 | Q22: =E22*K22 -> 0
A23: coredns | B23: 1 | C23: 1 | D23: 1 | E23: 2 | F23: 100 | G23: 70 | H23: 100 | I23: 170 | J23: 40 | K23: 0 | L23: =D23*F23 -> 100 | M23: =D23*G23 -> 70 | N23: =E23*H23 -> 200 | O23: =E23*I23 -> 340 | P23: =J23*3 -> 120 | Q23: =E23*K23 -> 0
A24: efs-csi-controller | B24: 1 | C24: 1 | D24: 1 | E24: 2 | F24: 100 | G24: 128 | H24: 100 | I24: 128 | J24: 50 | K24: 0 | L24: =D24*F24 -> 100 | M24: =D24*G24 -> 128 | N24: =E24*H24 -> 200 | O24: =E24*I24 -> 256 | P24: =J24*3 -> 150 | Q24: =E24*K24 -> 0
A25: Metric Server | B25: 1 | C25: 1 | D25: 1 | E25: 2 | F25: 100 | G25: 200 | H25: 100 | I25: 200 | J25: 50 | K25: 0 | L25: =D25*F25 -> 100 | M25: =D25*G25 -> 200 | N25: =E25*H25 -> 200 | O25: =E25*I25 -> 400 | P25: =J25*3 -> 150 | Q25: =E25*K25 -> 0
A26: Cluster Autoscaler | B26: 1 | C26: 1 | D26: 1 | E26: 2 | F26: 100 | G26: 600 | H26: 100 | I26: 600 | J26: 50 | K26: 0 | L26: =D26*F26 -> 100 | M26: =D26*G26 -> 600 | N26: =E26*H26 -> 200 | O26: =E26*I26 -> 1200 | P26: =J26*3 -> 150 | Q26: =E26*K26 -> 0
A27: Crowdstrike Falcon
A28: Crowdstrike Falcon | B28: 1 | C28: 0 | D28: 0 | E28: 0 | F28: 250 | G28: 512 | H28: 1000 | I28: 2048 | J28: 1024 | K28: 0 | L28: =D28*F28 -> 0 | M28: =D28*G28 -> 0 | N28: =E28*H28 -> 0 | O28: =E28*I28 -> 0 | P28: =J28*3 -> 3072 | Q28: =E28*K28 -> 0
A29: Ingress Namespace
A30: ingress-nginx-controller | B30: 1 | C30: 1 | D30: 1 | E30: 2 | F30: 25 | G30: 100 | H30: 100 | I30: 100 | J30: 50 | K30: 0 | L30: =D30*F30 -> 25 | M30: =D30*G30 -> 100 | N30: =E30*H30 -> 200 | O30: =E30*I30 -> 200 | P30: =J30*3 -> 150 | Q30: =E30*K30 -> 0
A31: brokerverse-core Namespace
A32: bv-policy-admin-svc | B32: 1 | C32: 3 | D32: 3 | E32: 7 | F32: 500 | G32: 1024 | H32: 1500 | I32: 2048 | J32: 2048 | K32: 0 | L32: =D32*F32 -> 1500 | M32: =D32*G32 -> 3072 | N32: =E32*H32 -> 10500 | O32: =E32*I32 -> 14336 | P32: =J32*3 -> 6144 | Q32: =E32*H32 -> 10500
A33: bv-claims-svc | B33: 1 | C33: 3 | D33: 3 | E33: 7 | F33: 500 | G33: 1024 | H33: 1500 | I33: 2048 | J33: 2048 | K33: 0 | L33: =D33*F33 -> 1500 | M33: =D33*G33 -> 3072 | N33: =E33*H33 -> 10500 | O33: =E33*I33 -> 14336 | P33: =J33*3 -> 6144 | Q33: =E33*H33 -> 10500
A34: bv-billing-collections-svc | B34: 1 | C34: 3 | D34: 3 | E34: 7 | F34: 500 | G34: 1024 | H34: 1500 | I34: 2048 | J34: 2048 | K34: 0 | L34: =D34*F34 -> 1500 | M34: =D34*G34 -> 3072 | N34: =E34*H34 -> 10500 | O34: =E34*I34 -> 14336 | P34: =J34*3 -> 6144 | Q34: =E34*H34 -> 10500
A35: bv-distribution-svc | B35: 1 | C35: 3 | D35: 3 | E35: 7 | F35: 400 | G35: 768 | H35: 1200 | I35: 1536 | J35: 2048 | K35: 0 | L35: =D35*F35 -> 1200 | M35: =D35*G35 -> 2304 | N35: =E35*H35 -> 8400 | O35: =E35*I35 -> 10752 | P35: =J35*3 -> 6144 | Q35: =E35*H35 -> 8400
A36: bv-web-portal | B36: 1 | C36: 3 | D36: 3 | E36: 7 | F36: 200 | G36: 256 | H36: 500 | I36: 512 | J36: 1024 | K36: 0 | L36: =D36*F36 -> 600 | M36: =D36*G36 -> 768 | N36: =E36*H36 -> 3500 | O36: =E36*I36 -> 3584 | P36: =J36*3 -> 3072 | Q36: =E36*H36 -> 3500
A37: brokerverse-platform Namespace
A38: bv-api-gateway | B38: 1 | C38: 3 | D38: 3 | E38: 7 | F38: 500 | G38: 512 | H38: 1000 | I38: 1024 | J38: 1024 | K38: 0 | L38: =D38*F38 -> 1500 | M38: =D38*G38 -> 1536 | N38: =E38*H38 -> 7000 | O38: =E38*I38 -> 7168 | P38: =J38*3 -> 3072 | Q38: =E38*H38 -> 7000
A39: bv-iam-svc | B39: 1 | C39: 3 | D39: 3 | E39: 7 | F39: 400 | G39: 768 | H39: 1000 | I39: 1536 | J39: 1024 | K39: 0 | L39: =D39*F39 -> 1200 | M39: =D39*G39 -> 2304 | N39: =E39*H39 -> 7000 | O39: =E39*I39 -> 10752 | P39: =J39*3 -> 3072 | Q39: =E39*H39 -> 7000
A40: bv-integration-svc | B40: 1 | C40: 3 | D40: 3 | E40: 7 | F40: 500 | G40: 1024 | H40: 1500 | I40: 2048 | J40: 2048 | K40: 0 | L40: =D40*F40 -> 1500 | M40: =D40*G40 -> 3072 | N40: =E40*H40 -> 10500 | O40: =E40*I40 -> 14336 | P40: =J40*3 -> 6144 | Q40: =E40*H40 -> 10500
A41: bv-document-svc | B41: 1 | C41: 3 | D41: 3 | E41: 7 | F41: 400 | G41: 768 | H41: 1200 | I41: 1536 | J41: 2048 | K41: 20 | L41: =D41*F41 -> 1200 | M41: =D41*G41 -> 2304 | N41: =E41*H41 -> 8400 | O41: =E41*I41 -> 10752 | P41: =J41*3 -> 6144 | Q41: =E41*H41 -> 8400
A42: bv-batch-notification-svc | B42: 1 | C42: 2 | D42: 2 | E42: 3 | F42: 400 | G42: 768 | H42: 1200 | I42: 1536 | J42: 2048 | K42: 0 | L42: =D42*F42 -> 800 | M42: =D42*G42 -> 1536 | N42: =E42*H42 -> 3600 | O42: =E42*I42 -> 4608 | P42: =J42*3 -> 6144
A43: Total Applications | E43: =SUM(E16:E42) -> 86 | L43: =SUM(L16:L42) -> 13950 | M43: =SUM(M16:M42) -> 25026 | N43: =SUM(N16:N42) -> 84000 | O43: =SUM(O16:O42) -> 111240 | P43: =SUM(P16:P42) -> 105588 | Q43: =SUM(Q16:Q42) -> 76300
L44: =CEILING(L43/1024,1) -> 14 | M44: =CEILING(M43/1024,1) -> 25 | N44: =CEILING(N43/1024,1) -> 83 | O44: =CEILING(O43/1024,1) -> 109 | P44: =CEILING(P43/1024,1) -> 104 | Q44: =Q43 -> 76300
K45: with Threshold | L45: =CEILING(L44/E50,1) -> 18 | M45: =CEILING(M44/E50,1) -> 32 | N45: =CEILING(N44/E50,1) -> 106 | O45: =CEILING(O44/E50,1) -> 138 | P45: =CEILING(P44/E50,1) -> 132 | Q45: =CEILING(Q44/E50,1) -> 96583
K46: Worker Nodes | L46: CPUs | M46: GB of RAM | N46: CPUs | O46: GB of RAM | P46: EBS Disk Space (GB)per node | Q46: Disk Space (GB)
P47: Note: This was multiplied by 3 for caching, replica updates and retention updates use. | Q47: Note: PV should be stored on a separate storage preferrably EFS
A48: Worker Nodes - Recommended Sizing
A50: # of Worker nodes requested | B50: 5 | D50: Threshold | E50: 0.79
B51: Worker Node Size | C51: Instance Type | D51: Total Persistent Volume | E51: Needed ENI | F51: Total ENI Available
A52: CPU | B52: =VLOOKUP(C52,'Ref - ENI Max Pods'!A1:D24,2,FALSE()) -> 16 | C52: m5.4xlarge (16x64) | D52: =Q44 -> 76300 | E52: =E43 -> 86 | F52: =B54*F63 -> 1638
A53: RAM | B53: =VLOOKUP(C52,'Ref - ENI Max Pods'!A2:D25,3,FALSE()) -> 64
A54: ENI per worker node | B54: =VLOOKUP(C52,'Ref - ENI Max Pods'!A3:D26,4,FALSE()) -> 234
A57: Cluster Sizing Recommendation (for IA)
A58: Calculated # of Nodes | I58: Cost Analysis base on instance type
A59: TOTAL WORKER NODES BDOI | B59: Y4 | E59: TOTAL WORKER NODES BDOI | F59: Y4 | I59: Instance Type | J59: Required instance | K59: Amount per instance | L59: Total
B60: #of Nodes computed | C60: Y1 Requirement | F60: #of Nodes computed | G60: Y1 Requirement | I60: c5.2xlarge 8x16 | J60: 12 | K60: 286.16 | L60: =K60*J60 -> 3433.92
A61: CPU | B61: =ROUNDUP(C61/B52,0) -> 2 | C61: =L45 -> 18 | E61: CPU | F61: =ROUNDUP(G61/B52,0) -> 7 | G61: =N45 -> 106 | I61: c5.4xlarge 16x32 | J61: 7 | K61: 572.32 | L61: =K61*J61 -> 4006.24
A62: RAM | B62: =ROUNDUP(C62/B53,0) -> 1 | C62: =M45 -> 32 | E62: RAM | F62: =ROUNDUP(G62/B53,0) -> 3 | G62: =O45 -> 138 | I62: m5.2xlarge 8x32 | J62: 12 | K62: 350.4 | L62: =K62*J62 -> 4204.8
A63: Minimum # of Nodes Needed | B63: =MAX(B61:B62) -> 2 | E63: Maximum # of Nodes Needed | F63: =MAX(F61:F62) -> 7 | I63: r5.2xlarge 8x64 | J63: 12 | K63: 443.84 | L63: =K63*J63 -> 5326.08
I64: m5.4xlarge 16x64 | J64: 7 | K64: 700.8 | L64: =K64*J64 -> 4905.6
I65: r5.4xlarge 16x128 | J65: 7 | K65: 887.68 | L65: =K65*J65 -> 6213.76

Sheet K8S (PROD Cluster) Y5
A1: Kubernetes General Guidelines
A2: 1. The requestor must fill out the pod requirements.
A3: 2. The requestor should consider defining a Pod Disruption Budget (PDB).
A4: 3. The requestor must provide Y1–Y5 pod requirements based on the NFR/TPS for each year, corresponding to the required number of replicas.
A5: 4. Persistent Volumes (PV) should be hosted on separate storage, preferably on EFS.
A6: 5. Allocate container runtime storage based on each microservice’s image size and its runtime storage requirements.
A7: 6. When determining the appropriate instance type, the “Cost Analysis Based on Instance Type” table below may be used as a reference to compare costs.
A8: 7. Remove the kube-system namespace if the hosting environment is on AKS, and add another worker node group for the system pool instead.
A9: 8. Change the number of min and max replicas for Dyntrace and Crowdstrike based on the outcome of the total number worker nodes.
A10: 9. The requestor should provide autoscaling requirements, including the preferred autoscaling approach (e.g., HPA-Metric Server,Cluster Autoscale, KEDA (K8S Event-Driven Autoscaling and other)
A12: Kindly Fill Up for Cluster Sizing Request
A13: Worker Node Group
L14: MINIMUM | N14: MAXIMUM
A15: Dynatrace Namespace | B15: PDB Requirements | C15: Desired Replica | D15: Min Replicas | E15: Max Replicas | F15: Requests CPU (millicores) | G15: Requests Memory (M) | H15: Limits CPU (millicores) | I15: Limits Memory (M) | J15: Ephemeral Storage (MB) | K15: PV (GB) | L15: CPU | M15: Memory | N15: CPU | O15: Memory | P15: Ephemeral Storage per node | Q15: Total PV (GB) EFS | R15: Remarks
A16: Dynakube-Activegate | B16: 1 | C16: 1 | D16: 1 | E16: 2 | F16: 500 | G16: 512 | H16: 1000 | I16: 1536 | J16: =6*1024 -> 6144 | K16: 0 | L16: =D16*F16 -> 500 | M16: =D16*G16 -> 512 | N16: =E16*H16 -> 2000 | O16: =E16*I16 -> 3072 | P16: =J16*3 -> 18432 | Q16: =E16*K16 -> 0
A17: Dynakube-OneAgent | B17: 1 | C17: 0 | D17: 0 | E17: 0 | F17: 100 | G17: 512 | H17: 300 | I17: 1536 | J17: =1024*8 -> 8192 | K17: 30 | L17: =D17*F17 -> 0 | M17: =D17*G17 -> 0 | N17: =E17*H17 -> 0 | O17: =E17*I17 -> 0 | P17: =J17*3 -> 24576 | Q17: =E17*K17 -> 0
A18: Dynakube-Webhook | B18: 1 | C18: 1 | D18: 1 | E18: 2 | F18: 300 | G18: 128 | H18: 300 | I18: 128 | J18: =1024 -> 1024 | K18: 0 | L18: =D18*F18 -> 300 | M18: =D18*G18 -> 128 | N18: =E18*H18 -> 600 | O18: =E18*I18 -> 256 | P18: =J18*3 -> 3072 | Q18: =E18*K18 -> 0
A19: Dynakube-Operator | B19: 1 | C19: 1 | D19: 1 | E19: 2 | F19: 100 | G19: 128 | H19: 100 | I19: 128 | J19: 1024 | K19: 0 | L19: =D19*F19 -> 100 | M19: =D19*G19 -> 128 | N19: =E19*H19 -> 200 | O19: =E19*I19 -> 256 | P19: =J19*3 -> 3072 | Q19: =E19*K19 -> 0
A20: Kube-system Namespace
A21: aws-node | B21: 1 | C21: 1 | D21: 1 | E21: 2 | F21: 25 | G21: 70 | H21: 50 | I21: 100 | J21: 80 | K21: 0 | L21: =D21*F21 -> 25 | M21: =D21*G21 -> 70 | N21: =E21*H21 -> 100 | O21: =E21*I21 -> 200 | P21: =J21*3 -> 240 | Q21: =E21*K21 -> 0
A22: kube-proxy | B22: 1 | C22: 1 | D22: 1 | E22: 2 | F22: 100 | G22: 50 | H22: 100 | I22: 50 | J22: 60 | K22: 0 | L22: =D22*F22 -> 100 | M22: =D22*G22 -> 50 | N22: =E22*H22 -> 200 | O22: =E22*I22 -> 100 | P22: =J22*3 -> 180 | Q22: =E22*K22 -> 0
A23: coredns | B23: 1 | C23: 1 | D23: 1 | E23: 2 | F23: 100 | G23: 70 | H23: 100 | I23: 170 | J23: 40 | K23: 0 | L23: =D23*F23 -> 100 | M23: =D23*G23 -> 70 | N23: =E23*H23 -> 200 | O23: =E23*I23 -> 340 | P23: =J23*3 -> 120 | Q23: =E23*K23 -> 0
A24: efs-csi-controller | B24: 1 | C24: 1 | D24: 1 | E24: 2 | F24: 100 | G24: 128 | H24: 100 | I24: 128 | J24: 50 | K24: 0 | L24: =D24*F24 -> 100 | M24: =D24*G24 -> 128 | N24: =E24*H24 -> 200 | O24: =E24*I24 -> 256 | P24: =J24*3 -> 150 | Q24: =E24*K24 -> 0
A25: Metric Server | B25: 1 | C25: 1 | D25: 1 | E25: 2 | F25: 100 | G25: 200 | H25: 100 | I25: 200 | J25: 50 | K25: 0 | L25: =D25*F25 -> 100 | M25: =D25*G25 -> 200 | N25: =E25*H25 -> 200 | O25: =E25*I25 -> 400 | P25: =J25*3 -> 150 | Q25: =E25*K25 -> 0
A26: Cluster Autoscaler | B26: 1 | C26: 1 | D26: 1 | E26: 2 | F26: 100 | G26: 600 | H26: 100 | I26: 600 | J26: 50 | K26: 0 | L26: =D26*F26 -> 100 | M26: =D26*G26 -> 600 | N26: =E26*H26 -> 200 | O26: =E26*I26 -> 1200 | P26: =J26*3 -> 150 | Q26: =E26*K26 -> 0
A27: Crowdstrike Falcon
A28: Crowdstrike Falcon | B28: 1 | C28: 0 | D28: 0 | E28: 0 | F28: 250 | G28: 512 | H28: 1000 | I28: 2048 | J28: 1024 | K28: 0 | L28: =D28*F28 -> 0 | M28: =D28*G28 -> 0 | N28: =E28*H28 -> 0 | O28: =E28*I28 -> 0 | P28: =J28*3 -> 3072 | Q28: =E28*K28 -> 0
A29: Ingress Namespace
A30: ingress-nginx-controller | B30: 1 | C30: 1 | D30: 1 | E30: 2 | F30: 25 | G30: 100 | H30: 100 | I30: 100 | J30: 50 | K30: 0 | L30: =D30*F30 -> 25 | M30: =D30*G30 -> 100 | N30: =E30*H30 -> 200 | O30: =E30*I30 -> 200 | P30: =J30*3 -> 150 | Q30: =E30*K30 -> 0
A31: brokerverse-core Namespace
A32: bv-policy-admin-svc | B32: 1 | C32: 4 | D32: 4 | E32: 8 | F32: 500 | G32: 1024 | H32: 1500 | I32: 2048 | J32: 2048 | K32: 0 | L32: =D32*F32 -> 2000 | M32: =D32*G32 -> 4096 | N32: =E32*H32 -> 12000 | O32: =E32*I32 -> 16384 | P32: =J32*3 -> 6144 | Q32: =E32*H32 -> 12000
A33: bv-claims-svc | B33: 1 | C33: 4 | D33: 4 | E33: 8 | F33: 500 | G33: 1024 | H33: 1500 | I33: 2048 | J33: 2048 | K33: 0 | L33: =D33*F33 -> 2000 | M33: =D33*G33 -> 4096 | N33: =E33*H33 -> 12000 | O33: =E33*I33 -> 16384 | P33: =J33*3 -> 6144 | Q33: =E33*H33 -> 12000
A34: bv-billing-collections-svc | B34: 1 | C34: 4 | D34: 4 | E34: 8 | F34: 500 | G34: 1024 | H34: 1500 | I34: 2048 | J34: 2048 | K34: 0 | L34: =D34*F34 -> 2000 | M34: =D34*G34 -> 4096 | N34: =E34*H34 -> 12000 | O34: =E34*I34 -> 16384 | P34: =J34*3 -> 6144 | Q34: =E34*H34 -> 12000
A35: bv-distribution-svc | B35: 1 | C35: 4 | D35: 4 | E35: 8 | F35: 400 | G35: 768 | H35: 1200 | I35: 1536 | J35: 2048 | K35: 0 | L35: =D35*F35 -> 1600 | M35: =D35*G35 -> 3072 | N35: =E35*H35 -> 9600 | O35: =E35*I35 -> 12288 | P35: =J35*3 -> 6144 | Q35: =E35*H35 -> 9600
